Workbook

Sheet About
A1: CECRCbI Cost Effective CCS Retrofit Capacity by Industry
A3: Source: | B3: Industry-specific CCS cost curves | D3: "Other" CCS Costs
B4: NREL | D4: indst/CC
B5: Carbon Capture Retrofit Database
B6: https://netl.doe.gov/node/12070
B7: 2022
B9: Iron & Steel Plant Data | D9: BAU Process Emissions
B10: Global Energy Monitor | D10: indst/BPE
B11: Global Iron & Steel Tracker
B12: https://globalenergymonitor.org/projects/global-iron-and-steel-tracker/
B13: 2025
B15: Refining CCS Cost Curves
B16: International Journal of Greenhouse Gas Control
B17: Quantifying carbon capture potential and cost of carbon capture technology application in the U.S. refining industry
B18: https://escholarship.org/content/qt3jt6n671/qt3jt6n671.pdf
B19: 2018
A21: Notes:

Sheet cpi
A1: Historical Consumer Price Index for All Urban Consumers (CPI-U): U.S. city average, all items, index
A2: averages — Continued
A3: [1982-84=100, unless otherwise noted]
A4: Year | B4: Semiannual averages | D4: Annual avg. | E4: Percent change from previous | G4: Multiply by to get 2012 Dollars
B5: 1st half | C5: 2nd half | E5: Dec. | F5: Annual avg.
A6: 1968............................................................................. . | B6: – | C6: – | D6: 34.8 | E6: 4.7 | F6: 4.2
A7: 1969............................................................................. . | B7: – | C7: – | D7: 36.7 | E7: 6.2 | F7: 5.5
A8: 1970............................................................................. . | B8: – | C8: – | D8: 38.8 | E8: 5.6 | F8: 5.7
A9: 1971............................................................................. . | B9: – | C9: – | D9: 40.5 | E9: 3.3 | F9: 4.4
A10: 1972............................................................................. . | B10: – | C10: – | D10: 41.8 | E10: 3.4 | F10: 3.2
A11: 1973............................................................................. . | B11: – | C11: – | D11: 44.4 | E11: 8.7 | F11: 6.2
A12: 1974............................................................................. . | B12: – | C12: – | D12: 49.3 | E12: 12.3 | F12: 11
A13: 1975............................................................................. . | B13: – | C13: – | D13: 53.8 | E13: 6.9 | F13: 9.1
A14: 1976............................................................................. . | B14: – | C14: – | D14: 56.9 | E14: 4.9 | F14: 5.8
A15: 1977............................................................................. . | B15: – | C15: – | D15: 60.6 | E15: 6.7 | F15: 6.5
A16: 1978............................................................................. . | B16: – | C16: – | D16: 65.2 | E16: 9 | F16: 7.6
A17: 1979............................................................................. . | B17: – | C17: – | D17: 72.6 | E17: 13.3 | F17: 11.3
... A21: 1983............................................................................. . | B21: – | C21: – | D21: 99.6 | E21: 3.8 | F21: 3.2
A22: 1984............................................................................. . | B22: 102.9 | C22: 104.9 | D22: 103.9 | E22: 3.9 | F22: 4.3
A23: 1985............................................................................. . | B23: 106.6 | C23: 108.5 | D23: 107.6 | E23: 3.8 | F23: 3.6
A24: 1986............................................................................. . | B24: 109.1 | C24: 110.1 | D24: 109.6 | E24: 1.1 | F24: 1.9
A25: 1987............................................................................. . | B25: 112.4 | C25: 114.9 | D25: 113.6 | E25: 4.4 | F25: 3.6
A26: 1988............................................................................. . | B26: 116.8 | C26: 119.7 | D26: 118.3 | E26: 4.4 | F26: 4.1
A27: 1989............................................................................. . | B27: 122.7 | C27: 125.3 | D27: 124 | E27: 4.6 | F27: 4.8
A28: 1990............................................................................. . | B28: 128.7 | C28: 132.6 | D28: 130.7 | E28: 6.1 | F28: 5.4 | G28: 1.7566488
A29: 1991............................................................................. . | B29: 135.2 | C29: 137.2 | D29: 136.2 | E29: 3.1 | F29: 4.2 | G29: 1.6857122
A30: 1992............................................................................. . | B30: 139.2 | C30: 141.4 | D30: 140.3 | E30: 2.9 | F30: 3 | G30: 1.6364505
A31: 1993............................................................................. . | B31: 143.7 | C31: 145.3 | D31: 144.5 | E31: 2.7 | F31: 3 | G31: 1.5888858
A32: 1994............................................................................. . | B32: 147.2 | C32: 149.3 | D32: 148.2 | E32: 2.7 | F32: 2.6 | G32: 1.5492173
A33: 1995............................................................................. . | B33: 151.5 | C33: 153.2 | D33: 152.4 | E33: 2.5 | F33: 2.8 | G33: 1.5065223
A34: 1996............................................................................. . | B34: 155.8 | C34: 157.9 | D34: 156.9 | E34: 3.3 | F34: 3 | G34: 1.4633142
A35: 1997............................................................................. . | B35: 159.9 | C35: 161.2 | D35: 160.5 | E35: 1.7 | F35: 2.3 | G35: 1.4304922
A36: 1998............................................................................. . | B36: 162.3 | C36: 163.7 | D36: 163 | E36: 1.6 | F36: 1.6 | G36: 1.4085521
A37: 1999............................................................................. . | B37: 165.4 | C37: 167.8 | D37: 166.6 | E37: 2.7 | F37: 2.2 | G37: 1.3781152
A38: 2000............................................................................. . | B38: 170.8 | C38: 173.6 | D38: 172.2 | E38: 3.4 | F38: 3.4 | G38: 1.3332985
A39: 2001............................................................................. . | B39: 176.6 | C39: 177.5 | D39: 177.1 | E39: 1.6 | F39: 2.8 | G39: 1.2964088
... A60: 2022............................................................................. . | B60: 288.347 | C60: 296.963 | D60: 292.655 | E60: 6.5 | F60: 8 | G60: 0.78452102
A61: 2023............................................................................. . | B61: 302.408 | C61: 306.996 | D61: 304.702 | G61: 0.75350342
A62: 2024............................................................................. . | B62: 312.145 | C62: 315.233 | D62: 313.689 | G62: 0.73191601

Sheet Retrofit Cost vs SOC Data
A1: *all costs in 2018 USD
B2: DO NOT FILTER OR SORT DATA HERE. IF NEEDED, USE "RESULTS" TABS TO FILTER AND/OR SORT DATA
B3: Ammonia | D3: Cement | F3: Ethanol | H3: Hydrogen | J3: Natural Gas with AGR
B4: Pre-retrofit total CO₂ emissions*, x1,000 TPY
B5: 37964.113 | C5: 1309.1073 | D5: 74664.849 | E5: 829.60944 | F5: 71351.376 | G5: 435.64292 | H5: 42242.863 | I5: 422.42863 | J5: 16316.935 | K5: 53.149625
B6: Cost of CO2 Avoided | C6: Cost of CO2 Captured | D6: Cost of CO2 Avoided | E6: Cost of CO2 Captured | F6: Cost of CO2 Avoided | G6: Cost of CO2 Captured | H6: Cost of CO2 Avoided | I6: Cost of CO2 Captured | J6: Cost of CO2 Avoided | K6: Cost of CO2 Captured
A7: T&S = $0/tonne | B7: 71.738249 | C7: 58.067922 | D7: 101.94958 | E7: 75.547457 | F7: 83.430431 | G7: 68.436788 | H7: 97.106488 | I7: 76.045227 | J7: 99.328025 | K7: 89.328025
A8: T&S = 10$/tonne | B8: 60.158203 | C8: 56.803171 | D8: 90.032265 | E8: 75.547457 | F8: 72.834266 | G8: 68.436788 | H8: 85.820971 | I8: 76.045227 | J8: 89.328025 | K8: 89.328025
A9: t&s cost assumption | B9: =B7-B8 -> 11.580046 | D9: =D7-D8 -> 11.917312 | F9: =F7-F8 -> 10.596165 | H9: =H7-H8 -> 11.285517 | J9: =J7-J8 -> 10
B10: Cost of CO₂ Avoided vs Cumulative Portion of Capacity | D10: Cost of CO₂ Avoided vs Cumulative Portion of Capacity | F10: Cost of CO₂ Avoided vs Cumulative Portion of Capacity | H10: Cost of CO₂ Avoided vs Cumulative Portion of Capacity | J10: Cost of CO₂ Avoided vs Cumulative Portion of Capacity
B11: Cost of CO₂ Avoided [$/tonne] | C11: Cumulative Portion of Capacity | D11: Cost of CO₂ Avoided [$/tonne] | E11: Cumulative Portion of Capacity | F11: Cost of CO₂ Avoided [$/tonne] | G11: Cumulative Portion of Capacity | H11: Cost of CO₂ Avoided [$/tonne] | I11: Cumulative Portion of Capacity | J11: Cost of CO₂ Avoided [$/tonne] | K11: Cumulative Portion of Capacity
B12: 33.410889 | C12: 0.27371651 | D12: 71.85449 | E12: 0.044531576 | F12: 39.733659 | G12: 0.0048640916 | H12: 54.99567 | I12: 0.047399647 | J12: 24.063621 | K12: 0.10295942
B13: 61.299601 | C13: 0.32345627 | D13: 78.02083 | E13: 0.072631908 | F13: 39.889084 | G13: 0.01037196 | H13: 56.512987 | I13: 0.077965842 | J13: 27.729504 | K13: 0.1436564
B14: 69.104743 | C14: 0.71271808 | D14: 79.271548 | E14: 0.094124553 | F14: 41.017282 | G14: 0.014449213 | H14: 57.342162 | I14: 0.11943986 | J14: 28.678436 | K14: 0.18050857
B15: 70.784247 | C15: 0.96831526 | D15: 80.819322 | E15: 0.11373608 | F15: 43.067224 | G15: 0.018383405 | H15: 57.441461 | I15: 0.14770529 | J15: 29.017078 | K15: 0.21496589
B16: 124.09176 | C16: 1 | D16: 80.952471 | E16: 0.13063396 | F16: 46.934473 | G16: 0.020886981 | H16: 57.449046 | I16: 0.19933207 | J16: 29.528675 | K16: 0.24996464
B17: #N/A | C17: #N/A | D17: 81.324551 | E17: 0.15662362 | F17: 47.102372 | G17: 0.026108727 | H17: 58.337848 | I17: 0.22559651 | J17: 30.250603 | K17: 0.28027082
B18: #N/A | C18: #N/A | D18: 81.862063 | E18: 0.17509357 | F18: 49.755709 | G18: 0.032403433 | H18: 58.349382 | I18: 0.25183649 | J18: 32.555733 | K18: 0.29899746
B19: #N/A | C19: #N/A | D19: 82.036775 | E19: 0.18834775 | F19: 50.218753 | G19: 0.034191702 | H19: 59.386041 | I19: 0.27600034 | J19: 32.656926 | K19: 0.31742775
B20: #N/A | C20: #N/A | D20: 82.506585 | E20: 0.20789705 | F20: 50.758939 | G20: 0.036194564 | H20: 59.873929 | I20: 0.29926495 | J20: 33.626154 | K20: 0.33147144
B21: #N/A | C21: #N/A | D21: 82.675298 | E21: 0.22506503 | F21: 53.918216 | G21: 0.037625179 | H21: 59.940422 | I21: 0.32857177 | J21: 33.838478 | K21: 0.34508341
B22: #N/A | C22: #N/A | D22: 83.454874 | E22: 0.24196096 | F22: 57.416132 | G22: 0.041917024 | H22: 60.648619 | I22: 0.35722978 | J22: 33.904647 | K22: 0.36033015
B23: #N/A | C23: #N/A | D23: 84.619375 | E23: 0.26301483 | F23: 62.522527 | G23: 0.071459227 | H23: 60.742704 | I23: 0.38567016 | J23: 34.038725 | K23: 0.37513117
B24: #N/A | C24: #N/A | D24: 85.222615 | E24: 0.27642288 | F24: 63.476319 | G24: 0.072174535 | H24: 62.047596 | I24: 0.41131323 | J24: 34.458134 | K24: 0.38758169
B25: #N/A | C25: #N/A | D25: 85.719295 | E25: 0.29138285 | F25: 64.151576 | G25: 0.096494993 | H25: 62.626899 | I25: 0.4358351 | J25: 34.841753 | K25: 0.39937977
B26: #N/A | C26: #N/A | D26: 85.837639 | E26: 0.30964086 | F26: 64.434547 | G26: 0.1351216 | H26: 63.015087 | I26: 0.45428305 | J26: 35.022004 | K26: 0.41103663
B27: #N/A | C27: #N/A | D27: 86.385221 | E27: 0.32309944 | F27: 64.447034 | G27: 0.13869814 | H27: 63.120619 | I27: 0.47790189 | J27: 35.029816 | K27: 0.42401964
B28: #N/A | C28: #N/A | D28: 86.615388 | E28: 0.33558657 | F28: 64.653953 | G28: 0.14763948 | H28: 66.591305 | I28: 0.49239138 | J28: 35.219857 | K28: 0.43916996
... B98: #N/A | C98: #N/A | D98: 137.83677 | E98: 0.99420303 | F98: 84.171241 | G98: 0.75400572 | H98: 193.91907 | I98: 1 | J98: 51.046965 | K98: 0.83502238
B99: #N/A | C99: #N/A | D99: 137.92407 | E99: 0.99702284 | F99: 84.200128 | G99: 0.75901288 | H99: #N/A | I99: #N/A | J99: 51.070452 | K99: 0.83728005
B100: #N/A | C100: #N/A | D100: 151.29458 | E100: 0.99867156 | F100: 84.500701 | G100: 0.76616595 | H100: #N/A | I100: #N/A | J100: 51.112868 | K100: 0.83953038
B101: #N/A | C101: #N/A | D101: 168.39645 | E101: 1 | F101: 84.735423 | G101: 0.77081545 | H101: #N/A | I101: #N/A | J101: 51.422292 | K101: 0.84172811
B102: #N/A | C102: #N/A | D102: #N/A | E102: #N/A | F102: 84.912512 | G102: 0.77653791 | H102: #N/A | I102: #N/A | J102: 51.849254 | K102: 0.84409986
B103: #N/A | C103: #N/A | D103: #N/A | E103: #N/A | F103: 84.914084 | G103: 0.78311874 | H103: #N/A | I103: #N/A | J103: 51.886875 | K103: 0.84646485
B104: #N/A | C104: #N/A | D104: #N/A | E104: #N/A | F104: 85.509463 | G104: 0.78848355 | H104: #N/A | I104: #N/A | J104: 51.902736 | K104: 0.84882701
B105: #N/A | C105: #N/A | D105: #N/A | E105: #N/A | F105: 85.638272 | G105: 0.79563662 | H105: #N/A | I105: #N/A | J105: 51.972944 | K105: 0.85117666
B106: #N/A | C106: #N/A | D106: #N/A | E106: #N/A | F106: 85.816539 | G106: 0.80207439 | H106: #N/A | I106: #N/A | J106: 52.096796 | K106: 0.85350447
B107: #N/A | C107: #N/A | D107: #N/A | E107: #N/A | F107: 85.951077 | G107: 0.80693848 | H107: #N/A | I107: #N/A | J107: 52.18696 | K107: 0.85581655
B108: #N/A | C108: #N/A | D108: #N/A | E108: #N/A | F108: 86.78987 | G108: 0.81087268 | H108: #N/A | I108: #N/A | J108: 52.388659 | K108: 0.85809397
B109: #N/A | C109: #N/A | D109: #N/A | E109: #N/A | F109: 87.039812 | G109: 0.81459227 | H109: #N/A | I109: #N/A | J109: 52.395071 | K109: 0.86013684
B110: #N/A | C110: #N/A | D110: #N/A | E110: #N/A | F110: 87.378017 | G110: 0.81924177 | H110: #N/A | I110: #N/A | J110: 52.501618 | K110: 0.86239515
B111: #N/A | C111: #N/A | D111: #N/A | E111: #N/A | F111: 87.40984 | G111: 0.82410587 | H111: #N/A | I111: #N/A | J111: 52.771563 | K111: 0.86460869
B112: #N/A | C112: #N/A | D112: #N/A | E112: #N/A | F112: 87.973317 | G112: 0.82896996 | H112: #N/A | I112: #N/A | J112: 53.035328 | K112: 0.86677962
B113: #N/A | C113: #N/A | D113: #N/A | E113: #N/A | F113: 88.053835 | G113: 0.8341917 | H113: #N/A | I113: #N/A | J113: 53.221026 | K113: 0.86891049
... B160: #N/A | C160: #N/A | D160: #N/A | E160: #N/A | F160: 262.99703 | G160: 1 | H160: #N/A | I160: #N/A | J160: 63.715335 | K160: 0.94173701
B161: #N/A | C161: #N/A | D161: #N/A | E161: #N/A | F161: #N/A | G161: #N/A | H161: #N/A | I161: #N/A | J161: 63.886429 | K161: 0.94281418
B162: #N/A | C162: #N/A | D162: #N/A | E162: #N/A | F162: #N/A | G162: #N/A | H162: #N/A | I162: #N/A | J162: 64.104894 | K162: 0.94384318
B163: #N/A | C163: #N/A | D163: #N/A | E163: #N/A | F163: #N/A | G163: #N/A | H163: #N/A | I163: #N/A | J163: 64.348055 | K163: 0.94489245
B164: #N/A | C164: #N/A | D164: #N/A | E164: #N/A | F164: #N/A | G164: #N/A | H164: #N/A | I164: #N/A | J164: 64.572063 | K164: 0.94589492
B165: #N/A | C165: #N/A | D165: #N/A | E165: #N/A | F165: #N/A | G165: #N/A | H165: #N/A | I165: #N/A | J165: 64.732091 | K165: 0.94692173
B166: #N/A | C166: #N/A | D166: #N/A | E166: #N/A | F166: #N/A | G166: #N/A | H166: #N/A | I166: #N/A | J166: 65.154562 | K166: 0.94792457
B167: #N/A | C167: #N/A | D167: #N/A | E167: #N/A | F167: #N/A | G167: #N/A | H167: #N/A | I167: #N/A | J167: 65.456452 | K167: 0.94891076
B168: #N/A | C168: #N/A | D168: #N/A | E168: #N/A | F168: #N/A | G168: #N/A | H168: #N/A | I168: #N/A | J168: 65.657278 | K168: 0.94985509
B169: #N/A | C169: #N/A | D169: #N/A | E169: #N/A | F169: #N/A | G169: #N/A | H169: #N/A | I169: #N/A | J169: 65.924917 | K169: 0.95081254
B170: #N/A | C170: #N/A | D170: #N/A | E170: #N/A | F170: #N/A | G170: #N/A | H170: #N/A | I170: #N/A | J170: 66.810438 | K170: 0.95172847
B171: #N/A | C171: #N/A | D171: #N/A | E171: #N/A | F171: #N/A | G171: #N/A | H171: #N/A | I171: #N/A | J171: 67.271714 | K171: 0.952622
B172: #N/A | C172: #N/A | D172: #N/A | E172: #N/A | F172: #N/A | G172: #N/A | H172: #N/A | I172: #N/A | J172: 67.314566 | K172: 0.95348607
... B318: #N/A | C318: #N/A | D318: #N/A | E318: #N/A | F318: #N/A | G318: #N/A | H318: #N/A | I318: #N/A | J318: 1401.9639 | K318: 1

Sheet BPE - Table 4-1_2021
A1: Table 4-1: Emissions from Industrial Processes and Product Use (MMT CO2 Eq.)
AJ2: EPS industry | AK2: EPS pollutant
A3: Gas/Source | B3: 1990 | C3: 1991 | D3: 1992 | E3: 1993 | F3: 1994 | G3: 1995 | H3: 1996 | I3: 1997 | J3: 1998 | K3: 1999 | L3: 2000 | M3: 2001 | N3: 2002 | O3: 2003 | P3: 2004 | Q3: 2005 | R3: 2006 | S3: 2007 | T3: 2008 | U3: 2009 | V3: 2010 | W3: 2011 | X3: 2012 | Y3: 2013 | Z3: 2014 | AA3: 2015 | AB3: 2016 | AC3: 2017 | AD3: 2018 | AE3: 2019 | AF3: 2020 | AG3: 2021 | AH3: 2022
A4: CO2 | B4: 214 | C4: 204.4 | D4: 207.6 | E4: 205.4 | F4: 213 | G4: 221.4 | H4: 222.5 | I4: 227.2 | J4: 223.7 | K4: 222.7 | L4: 219.7 | M4: 198.3 | N4: 197.9 | O4: 192.8 | P4: 200.6 | Q4: 195.4 | R4: 200.2 | S4: 202.5 | T4: 187.5 | U4: 145.1 | V4: 173 | W4: 176.9 | X4: 174.4 | Y4: 175.3 | Z4: 180.6 | AA4: 173.4 | AB4: 165.1 | AC4: 165.3 | AD4: 164.4 | AE4: 168.2 | AF4: 160.7 | AG4: 168.8 | AH4: 168.9
A5: Cement Production | B5: 104.7 | C5: 95.2 | D5: 96 | E5: 91.6 | F5: 94.5 | G5: 98.4 | H5: 96.4 | I5: 97.6 | J5: 91.1 | K5: 89 | L5: 90.5 | M5: 79.8 | N5: 75.8 | O5: 72.7 | P5: 72.2 | Q5: 70.1 | R5: 72.8 | S5: 74.5 | T5: 69.9 | U5: 45.1 | V5: 58.6 | W5: 63 | X5: 57.3 | Y5: 55.2 | Z5: 58.2 | AA5: 39.9 | AB5: 39.4 | AC5: 40.3 | AD5: 39 | AE5: 40.9 | AF5: 40.7 | AG5: 41.3 | AH5: 41.9 | AJ5: cement and other nonmetallic minerals 239 | AK5: CO2
A6: Iron and Steel Production & Metallurgical Coke Production | B6: 99.1 | C6: 90.1 | D6: 92 | E6: 88.7 | F6: 89.4 | G6: 93.2 | H6: 92 | I6: 93.8 | J6: 86.4 | K6: 84.3 | L6: 85.9 | M6: 76.8 | N6: 71.6 | O6: 68.3 | P6: 68.4 | Q6: 66.2 | R6: 69 | S6: 70.6 | T6: 65.8 | U6: 42.9 | V6: 54.8 | W6: 59.8 | X6: 55 | Y6: 51.6 | Z6: 54.5 | AA6: 47.9 | AB6: 43.6 | AC6: 40.8 | AD6: 42.9 | AE6: 43.1 | AF6: 37.7 | AG6: 41.9 | AH6: 40.7
A7: Iron and Steel Production | B7: 5.6 | C7: 5.1 | D7: 4 | E7: 3 | F7: 5.2 | G7: 5.2 | H7: 4.4 | I7: 3.8 | J7: 4.8 | K7: 4.7 | L7: 4.5 | M7: 3 | N7: 4.2 | O7: 4.4 | P7: 3.8 | Q7: 3.9 | R7: 3.8 | S7: 3.9 | T7: 4.1 | U7: 2.2 | V7: 3.8 | W7: 3.1 | X7: 2.2 | Y7: 3.5 | Z7: 3.7 | AA7: 43.5 | AB7: 41 | AC7: 38.8 | AD7: 41.6 | AE7: 40.1 | AF7: 35.4 | AG7: 38.6 | AH7: 37.7 | AJ7: iron and steel 241 | AK7: CO2
A8: Metallurgical Coke Production | B8: 33.5 | C8: 32.7 | D8: 33 | E8: 34.8 | F8: 36.3 | G8: 37.1 | H8: 37.3 | I8: 38.6 | J8: 39.5 | K8: 40.2 | L8: 41.4 | M8: 41.6 | N8: 43.2 | O8: 43.3 | P8: 45.9 | Q8: 46.2 | R8: 46.9 | S8: 45.5 | T8: 41.4 | U8: 29.6 | V8: 31.4 | W8: 32.2 | X8: 35.3 | Y8: 36.4 | Z8: 39.4 | AA8: 4.4 | AB8: 2.6 | AC8: 2 | AD8: 1.3 | AE8: 3 | AF8: 2.3 | AG8: 3.2 | AH8: 3 | AJ8: refined petroleum and coke 19 | AK8: CO2
A9: Petrochemical Production | B9: 21.6 | C9: 23.1 | D9: 23.7 | E9: 24.6 | F9: 26.6 | G9: 27.9 | H9: 29.1 | I9: 30.5 | J9: 30.9 | K9: 32.3 | L9: 31.6 | M9: 27.6 | N9: 28.7 | O9: 28.5 | P9: 30.7 | Q9: 27.4 | R9: 27.6 | S9: 28.1 | T9: 24.7 | U9: 23.8 | V9: 27.3 | W9: 26.3 | X9: 26.5 | Y9: 26.4 | Z9: 26.5 | AA9: 27.2 | AB9: 26.8 | AC9: 27.3 | AD9: 27.2 | AE9: 28.5 | AF9: 27.9 | AG9: 30.7 | AH9: 28.8 | AJ9: chemicals 20 | AK9: CO2
A10: Ammonia Production | B10: 14.4 | C10: 14.7 | D10: 15.1 | E10: 14.5 | F10: 15.6 | G10: 14.9 | H10: 15.2 | I10: 15.4 | J10: 15.6 | K10: 14.3 | L10: 13.4 | M10: 10.3 | N10: 11.7 | O10: 9.8 | P10: 10.6 | Q10: 10.2 | R10: 9.8 | S10: 10.3 | T10: 9.4 | U10: 9.3 | V10: 9.8 | W10: 9 | X10: 10 | Y10: 9.9 | Z10: 10.6 | AA10: 10.1 | AB10: 10.2 | AC10: 12.5 | AD10: 12.7 | AE10: 12.4 | AF10: 13 | AG10: 12.2 | AH10: 12.6 | AJ10: chemicals 20 | AK10: CO2
A11: Lime Production | B11: 11.7 | C11: 11.5 | D11: 11.9 | E11: 12.3 | F11: 12.7 | G11: 13.5 | H11: 14.2 | I11: 14.5 | J11: 14.8 | K11: 14.4 | L11: 14.3 | M11: 13.7 | N11: 13.2 | O11: 13.9 | P11: 14.6 | Q11: 14.6 | R11: 15.2 | S11: 14.7 | T11: 14.5 | U11: 11.4 | V11: 13.4 | W11: 14 | X11: 13.8 | Y11: 14 | Z11: 14.2 | AA11: 13.3 | AB11: 12.6 | AC11: 12.9 | AD11: 13.1 | AE11: 12.1 | AF11: 11.3 | AG11: 11.9 | AH11: 12.2 | AJ11: cement and other nonmetallic minerals 239 | AK11: CO2
A12: Other Process Uses of Carbonates | B12: 6.2 | C12: 5.6 | D12: 5.6 | E12: 5.2 | F12: 5.5 | G12: 7.3 | H12: 8 | I12: 7.7 | J12: 7.8 | K12: 8.6 | L12: 5.8 | M12: 6 | N12: 6.3 | O12: 4.9 | P12: 6.7 | Q12: 7.5 | R12: 8.6 | S12: 7.9 | T12: 6.7 | U12: 8.7 | V12: 10.6 | W12: 9.7 | X12: 8.9 | Y12: 10.9 | Z12: 12.6 | AA12: 12.7 | AB12: 11.4 | AC12: 10.4 | AD12: 7.9 | AE12: 9 | AF12: 9 | AG12: 8.6 | AH12: 10.4 | AJ12: cement and other nonmetallic minerals 239 | AK12: CO2
A13: Urea Consumption for Non-Agricultural Purposes | B13: 3.8 | C13: 3.5 | D13: 3.9 | E13: 4.6 | F13: 4.3 | G13: 4.3 | H13: 3.9 | I13: 3.9 | J13: 4.8 | K13: 4.7 | L13: 4.2 | M13: 4.1 | N13: 3.7 | O13: 3.6 | P13: 3.7 | Q13: 3.7 | R13: 3.5 | S13: 4.9 | T13: 4.1 | U13: 3.4 | V13: 4.7 | W13: 5.1 | X13: 4.8 | Y13: 4.6 | Z13: 1.8 | AA13: 4.6 | AB13: 5.3 | AC13: 5.2 | AD13: 6.1 | AE13: 6.2 | AF13: 5.8 | AG13: 6.6 | AH13: 7.1 | AJ13: chemicals 20 | AK13: CO2
A14: Carbon Dioxide Consumption | B14: 1.5 | C14: 1.5 | D14: 1.5 | E14: 1.5 | F14: 1.5 | G14: 1.5 | H14: 1.5 | I14: 1.5 | J14: 1.5 | K14: 1.5 | L14: 1.5 | M14: 0.9 | N14: 1 | O14: 1.4 | P14: 1.3 | Q14: 1.4 | R14: 1.8 | S14: 1.9 | T14: 1.8 | U14: 1.8 | V14: 4.4 | W14: 4.1 | X14: 4 | Y14: 4.2 | Z14: 4.5 | AA14: 4.9 | AB14: 4.6 | AC14: 4.6 | AD14: 4.1 | AE14: 4.9 | AF14: 5 | AG14: 5 | AH14: 5 | AJ14: food beverage and tobacco 10T12 | AK14: CO2 | AL14: *according to the GHG report, this represents CO2 used in food and beverage applications that is emitted to the atmosphere (does not include CO2 used in EOR)
A15: Glass Production | B15: 1.9 | C15: 2.1 | D15: 2.2 | E15: 2.3 | F15: 2.3 | G15: 2.3 | H15: 2.4 | I15: 2.5 | J15: 2.5 | K15: 2.6 | L15: 2.5 | M15: 2.4 | N15: 2.4 | O15: 2.4 | P15: 2.4 | Q15: 2.4 | R15: 2.4 | S15: 2.3 | T15: 2.2 | U15: 1.9 | V15: 2.1 | W15: 2.1 | X15: 2 | Y15: 2 | Z15: 2 | AA15: 2 | AB15: 2.1 | AC15: 2 | AD15: 2 | AE15: 1.9 | AF15: 1.9 | AG15: 2 | AH15: 2 | AJ15: cement and other nonmetallic minerals 239 | AK15: CO2
A16: Soda Ash Production | B16: 6.8 | C16: 6.9 | D16: 6.8 | E16: 6.2 | F16: 5.5 | G16: 5.7 | H16: 6 | I16: 6 | J16: 6.2 | K16: 6.3 | L16: 6.1 | M16: 4.4 | N16: 4.5 | O16: 4.5 | P16: 4.2 | Q16: 4.1 | R16: 3.8 | S16: 4.3 | T16: 4.5 | U16: 3 | V16: 2.7 | W16: 3.3 | X16: 3.4 | Y16: 3.3 | Z16: 2.8 | AA16: 1.7 | AB16: 1.7 | AC16: 1.8 | AD16: 1.7 | AE16: 1.8 | AF16: 1.5 | AG16: 1.7 | AH16: 1.7 | AJ16: cement and other nonmetallic minerals 239 | AK16: CO2
A17: Titanium Dioxide Production | B17: 1.4 | C17: 1.4 | D17: 1.5 | E17: 1.4 | F17: 1.4 | G17: 1.6 | H17: 1.6 | I17: 1.7 | J17: 1.6 | K17: 1.5 | L17: 1.5 | M17: 1.5 | N17: 1.5 | O17: 1.5 | P17: 1.6 | Q17: 1.7 | R17: 1.6 | S17: 1.7 | T17: 1.7 | U17: 1.5 | V17: 1.5 | W17: 1.6 | X17: 1.7 | Y17: 1.7 | Z17: 1.7 | AA17: 1.6 | AB17: 1.7 | AC17: 1.7 | AD17: 1.5 | AE17: 1.3 | AF17: 1.3 | AG17: 1.5 | AH17: 1.5 | AJ17: other metals 242 | AK17: CO2
A18: Aluminum Production | B18: 2.2 | C18: 1.9 | D18: 2 | E18: 1.9 | F18: 2 | G18: 2 | H18: 2.1 | I18: 2.2 | J18: 2.2 | K18: 2.2 | L18: 1.9 | M18: 1.5 | N18: 1.3 | O18: 1.3 | P18: 1.4 | Q18: 1.4 | R18: 1.5 | S18: 1.6 | T18: 1.6 | U18: 1.5 | V18: 1.7 | W18: 1.7 | X18: 1.9 | Y18: 1.8 | Z18: 2 | AA18: 2.8 | AB18: 1.3 | AC18: 1.2 | AD18: 1.5 | AE18: 1.9 | AF18: 1.7 | AG18: 1.5 | AH18: 1.4 | AJ18: other metals 242 | AK18: CO2
A19: Ferroalloy Production | B19: 1.2 | C19: 1.2 | D19: 1.4 | E19: 1.4 | F19: 1.5 | G19: 1.5 | H19: 1.5 | I19: 1.7 | J19: 1.7 | K19: 1.7 | L19: 1.8 | M19: 1.7 | N19: 1.8 | O19: 1.8 | P19: 2.1 | Q19: 1.8 | R19: 1.8 | S19: 1.9 | T19: 1.8 | U19: 1.6 | V19: 1.8 | W19: 1.7 | X19: 1.5 | Y19: 1.7 | Z19: 1.7 | AA19: 2 | AB19: 1.8 | AC19: 2 | AD19: 2.1 | AE19: 1.6 | AF19: 1.4 | AG19: 1.6 | AH19: 1.3 | AJ19: iron and steel 241 | AK19: CO2
A20: Zinc Production | B20: 0.6 | C20: 0.8 | D20: 0.8 | E20: 0.9 | F20: 0.9 | G20: 0.9 | H20: 0.9 | I20: 1 | J20: 0.9 | K20: 0.9 | L20: 0.9 | M20: 0.7 | N20: 0.7 | O20: 1.1 | P20: 1 | Q20: 1 | R20: 1 | S20: 1 | T20: 1.2 | U20: 0.9 | V20: 1.2 | W20: 1.3 | X20: 1.5 | Y20: 1.4 | Z20: 0.9 | AA20: 0.9 | AB20: 0.8 | AC20: 0.9 | AD20: 1 | AE20: 1 | AF20: 1 | AG20: 1 | AH20: 0.9 | AJ20: other metals 242 | AK20: CO2
A21: Phosphoric Acid Production | B21: 1.5 | C21: 1.4 | D21: 1.5 | E21: 1.3 | F21: 1.5 | G21: 1.5 | H21: 1.6 | I21: 1.5 | J21: 1.6 | K21: 1.5 | L21: 1.4 | M21: 1.3 | N21: 1.3 | O21: 1.4 | P21: 1.4 | Q21: 1.3 | R21: 1.2 | S21: 1.2 | T21: 1.1 | U21: 1 | V21: 1.1 | W21: 1.2 | X21: 1.1 | Y21: 1.1 | Z21: 1 | AA21: 1 | AB21: 1 | AC21: 1 | AD21: 0.9 | AE21: 0.9 | AF21: 0.9 | AG21: 0.9 | AH21: 0.8 | AJ21: chemicals 20 | AK21: CO2
A22: Lead Production | B22: 0.5 | C22: 0.5 | D22: 0.5 | E22: 0.5 | F22: 0.5 | G22: 0.6 | H22: 0.6 | I22: 0.6 | J22: 0.6 | K22: 0.6 | L22: 0.6 | M22: 0.6 | N22: 0.6 | O22: 0.6 | P22: 0.5 | Q22: 0.6 | R22: 0.6 | S22: 0.6 | T22: 0.5 | U22: 0.5 | V22: 0.5 | W22: 0.5 | X22: 0.5 | Y22: 0.5 | Z22: 0.5 | AA22: 0.5 | AB22: 0.5 | AC22: 0.5 | AD22: 0.5 | AE22: 0.5 | AF22: 0.5 | AG22: 0.4 | AH22: 0.4 | AJ22: other metals 242 | AK22: CO2
A23: Carbide Production and Consumption | B23: 0.2 | C23: 0.2 | D23: 0.2 | E23: 0.2 | F23: 0.2 | G23: 0.2 | H23: 0.2 | I23: 0.2 | J23: 0.3 | K23: 0.2 | L23: 0.2 | M23: 0.2 | N23: 0.2 | O23: 0.2 | P23: 0.2 | Q23: 0.2 | R23: 0.2 | S23: 0.2 | T23: 0.2 | U23: 0.1 | V23: 0.2 | W23: 0.2 | X23: 0.2 | Y23: 0.2 | Z23: 0.2 | AA23: 0.2 | AB23: 0.2 | AC23: 0.2 | AD23: 0.2 | AE23: 0.2 | AF23: 0.2 | AG23: 0.2 | AH23: 0.2 | AJ23: chemicals 20 | AK23: CO2 | AL23: *carbide production is classified under the "industrial inorganic chemicals" SIC code
A24: Substitution of Ozone Depleting Substances | AA24: + | AB24: + | AC24: + | AD24: + | AE24: + | AF24: + | AG24: + | AH24: +
A25: Magnesium Production and Processing | B25: 0.1 | C25: 0.1 | D25: 0.1 | E25: 0.1 | F25: 0.1 | G25: 0.1 | H25: 0.1 | I25: 0.1 | J25: 0.1 | K25: 0.1 | L25: 0.1 | M25: 0.1 | N25: 0 | O25: 0 | P25: 0 | Q25: 0 | R25: 0 | S25: 0 | T25: 0 | U25: 0 | V25: 0 | W25: 0 | X25: 0 | Y25: 0 | Z25: 0 | AA25: + | AB25: + | AC25: + | AD25: + | AE25: + | AF25: + | AG25: + | AH25: +
A26: CH4 | B26: 0.3 | C26: 0.3 | D26: 0.3 | E26: 0.4 | F26: 0.4 | G26: 0.4 | H26: 0.4 | I26: 0.4 | J26: 0.4 | K26: 0.4 | L26: 0.4 | M26: 0.3 | N26: 0.3 | O26: 0.3 | P26: 0.2 | Q26: 0.1 | R26: 0.1 | S26: 0.1 | T26: 0.1 | U26: 0.1 | V26: 0.1 | W26: 0.1 | X26: 0.1 | Y26: 0.1 | Z26: 0.2 | AA26: + | AB26: + | AC26: + | AD26: + | AE26: + | AF26: + | AG26: + | AH26: +
A27: Carbide Production and Consumption | B27: 0 | C27: 0 | D27: 0 | E27: 0 | F27: 0 | G27: 0 | H27: 0 | I27: 0 | J27: 0 | K27: 0 | L27: 0 | M27: 0 | N27: 0 | O27: 0 | P27: 0 | Q27: 0 | R27: 0 | S27: 0 | T27: 0 | U27: 0 | V27: 0 | W27: 0 | X27: 0 | Y27: 0 | Z27: 0 | AA27: + | AB27: + | AC27: + | AD27: + | AE27: + | AF27: + | AG27: + | AH27: +
A28: Ferroalloy Production | B28: 0 | C28: 0 | D28: 0 | E28: 0 | F28: 0 | G28: 0 | H28: 0 | I28: 0 | J28: 0 | K28: 0 | L28: 0 | M28: 0 | N28: 0 | O28: 0 | P28: 0 | Q28: 0 | R28: 0 | S28: 0 | T28: 0 | U28: 0 | V28: 0 | W28: 0 | X28: 0 | Y28: 0 | Z28: 0 | AA28: + | AB28: + | AC28: + | AD28: + | AE28: + | AF28: + | AG28: + | AH28: +
A29: Iron and Steel Production & Metallurgical Coke Production | B29: 0 | C29: 0 | D29: 0 | E29: 0 | F29: 0 | G29: 0 | H29: 0 | I29: 0 | J29: 0 | K29: 0 | L29: 0 | M29: 0 | N29: 0 | O29: 0 | P29: 0 | Q29: 0 | R29: 0 | S29: 0 | T29: 0 | U29: 0 | V29: 0 | W29: 0 | X29: 0 | Y29: 0 | Z29: 0 | AA29: + | AB29: + | AC29: + | AD29: + | AE29: + | AF29: + | AG29: + | AH29: +
A30: Petrochemical Production | B30: 0.2 | C30: 0.3 | D30: 0.2 | E30: 0.3 | F30: 0.3 | G30: 0.3 | H30: 0.4 | I30: 0.4 | J30: 0.4 | K30: 0.4 | L30: 0.3 | M30: 0.2 | N30: 0.2 | O30: 0.2 | P30: 0.2 | Q30: 0.1 | R30: 0.1 | S30: 0.1 | T30: 0.1 | U30: 0.1 | V30: 0.1 | W30: 0.1 | X30: 0.1 | Y30: 0.1 | Z30: 0.1 | AA30: + | AB30: + | AC30: + | AD30: + | AE30: + | AF30: + | AG30: + | AH30: +
A31: N2O | B31: 29.6 | C31: 29.1 | D31: 27.6 | E31: 29.1 | F31: 29.5 | G31: 32.7 | H31: 33.1 | I31: 27.2 | J31: 23.2 | K31: 22.4 | L31: 22.6 | M31: 19.5 | N31: 20.4 | O31: 20.2 | P31: 18.7 | Q31: 22.2 | R31: 23.2 | S31: 26.8 | T31: 18.1 | U31: 16.8 | V31: 19.9 | W31: 24.7 | X31: 20 | Y31: 18.8 | Z31: 20.3 | AA31: 19.7 | AB31: 20.8 | AC31: 20.2 | AD31: 23.1 | AE31: 18.7 | AF31: 20.8 | AG31: 19.7 | AH31: 16.1
A32: Nitric Acid Production | B32: 10.8 | C32: 10.8 | D32: 11.1 | E32: 11.2 | F32: 11.9 | G32: 12 | H32: 12.5 | I32: 12.8 | J32: 12.6 | K32: 12.2 | L32: 11.8 | M32: 9.6 | N32: 10.4 | O32: 9.8 | P32: 9.7 | Q32: 10.1 | R32: 9.9 | S32: 11.7 | T32: 10 | U32: 8.6 | V32: 10.3 | W32: 9.7 | X32: 9.3 | Y32: 9.5 | Z32: 9.7 | AA32: 10.3 | AB32: 9 | AC32: 8.3 | AD32: 8.5 | AE32: 8.9 | AF32: 8.3 | AG32: 7.9 | AH32: 8.6 | AJ32: chemicals 20 | AK32: N2O
A33: N2O from Product Uses | B33: 3.8 | C33: 3.7 | D33: 3.5 | E33: 3.9 | F33: 3.9 | G33: 3.9 | H33: 3.9 | I33: 4.2 | J33: 4.2 | K33: 4.2 | L33: 4.2 | M33: 4.2 | N33: 3.8 | O33: 3.8 | P33: 3.8 | Q33: 3.8 | R33: 3.8 | S33: 3.8 | T33: 3.8 | U33: 3.8 | V33: 3.8 | W33: 3.8 | X33: 3.8 | Y33: 3.8 | Z33: 3.8 | AA33: 3.8 | AB33: 3.8 | AC33: 3.8 | AD33: 3.8 | AE33: 3.8 | AF33: 3.8 | AG33: 3.8 | AH33: 3.8 | AJ33: chemicals 20 | AK33: N2O
A34: Adipic Acid Production | B34: 13.5 | C34: 13.2 | D34: 11.5 | E34: 12.4 | F34: 12 | G34: 15 | H34: 14.9 | I34: 8.4 | J34: 4.6 | K34: 4.2 | L34: 4.7 | M34: 4 | N34: 4.4 | O34: 4.8 | P34: 3.3 | Q34: 6.3 | R34: 7.6 | S34: 9.1 | T34: 2.2 | U34: 2.4 | V34: 3.8 | W34: 9.1 | X34: 4.9 | Y34: 3.5 | Z34: 4.8 | AA34: 3.8 | AB34: 6.3 | AC34: 6.6 | AD34: 9.3 | AE34: 4.7 | AF34: 7.4 | AG34: 6.6 | AH34: 2.1 | AJ34: chemicals 20 | AK34: N2O
A35: Caprolactam, Glyoxal, and Glyoxylic Acid Production | B35: 1.5 | C35: 1.4 | D35: 1.5 | E35: 1.6 | F35: 1.7 | G35: 1.7 | H35: 1.7 | I35: 1.7 | J35: 1.8 | K35: 1.8 | L35: 1.8 | M35: 1.6 | N35: 1.8 | O35: 1.7 | P35: 1.9 | Q35: 1.9 | R35: 1.8 | S35: 2 | T35: 1.9 | U35: 1.9 | V35: 2 | W35: 2 | X35: 1.8 | Y35: 1.9 | Z35: 1.8 | AA35: 1.7 | AB35: 1.5 | AC35: 1.3 | AD35: 1.3 | AE35: 1.2 | AF35: 1.1 | AG35: 1.2 | AH35: 1.3 | AJ35: chemicals 20 | AK35: N2O
A36: Electronics Industry | B36: 0 | C36: 0 | D36: 0 | E36: 0 | F36: 0 | G36: 0.1 | H36: 0.1 | I36: 0.1 | J36: 0.1 | K36: 0.1 | L36: 0.1 | M36: 0.1 | N36: 0.1 | O36: 0.1 | P36: 0.1 | Q36: 0.1 | R36: 0.2 | S36: 0.2 | T36: 0.2 | U36: 0.1 | V36: 0.1 | W36: 0.2 | X36: 0.2 | Y36: 0.2 | Z36: 0.2 | AA36: 0.2 | AB36: 0.2 | AC36: 0.2 | AD36: 0.2 | AE36: 0.2 | AF36: 0.3 | AG36: 0.3 | AH36: 0.3 | AJ36: computers and electronics 26 | AK36: N2O
A37: HFCs | B37: 39 | C37: 35.4 | D37: 40.4 | E37: 40.8 | F37: 47.1 | G37: 64.7 | H37: 74.5 | I37: 84.4 | J37: 102.3 | K37: 100.9 | L37: 105.8 | M37: 102.9 | N37: 109.2 | O37: 104.3 | P37: 113.3 | Q37: 116.4 | R37: 120.7 | S37: 131.2 | T37: 135.7 | U37: 136.2 | V37: 144.7 | W37: 148.4 | X37: 148.1 | Y37: 149.1 | Z37: 154.1 | AA37: 160.8 | AB37: 160.6 | AC37: 163 | AD37: 163.9 | AE37: 168.2 | AF37: 170.3 | AG37: 177 | AH37: 182.8
A38: Substitution of Ozone Depleting Substances a | B38: 0.3 | C38: 0.5 | D38: 1.6 | E38: 5.5 | F38: 13.5 | G38: 29.4 | H38: 41.1 | I38: 52.2 | J38: 60.1 | K38: 68.2 | L38: 75.2 | M38: 81.8 | N38: 86.6 | O38: 91.1 | P38: 94.9 | Q38: 99.4 | R38: 105.8 | S38: 113 | T38: 121 | U38: 130.3 | V38: 137.7 | W38: 140.8 | X38: 143.2 | Y38: 145.3 | Z38: 149.5 | AA38: 154.1 | AB38: 155.8 | AC38: 156.2 | AD38: 157.9 | AE38: 162.1 | AF38: 166.2 | AG38: 172.6 | AH38: 178.1 | AJ38: chemicals 20 | AK38: F-gases
A39: Fluorochemical Production | B39: 38.6 | C39: 34.7 | D39: 38.6 | E39: 35.1 | F39: 33.4 | G39: 34.9 | H39: 33 | I39: 31.9 | J39: 41.8 | K39: 32.2 | L39: 30.3 | M39: 20.9 | N39: 22.4 | O39: 13 | P39: 18.3 | Q39: 16.8 | R39: 14.7 | S39: 18 | T39: 14.4 | U39: 5.7 | V39: 6.7 | W39: 7.3 | X39: 4.6 | Y39: 3.4 | Z39: 4.2 | AA39: 6.4 | AB39: 4.4 | AC39: 6.4 | AD39: 5.7 | AE39: 5.7 | AF39: 3.8 | AG39: 4 | AH39: 4.3 | AJ39: chemicals 20 | AK39: F-gases
A40: Electronics Industry | B40: 0.2 | C40: 0.2 | D40: 0.2 | E40: 0.2 | F40: 0.2 | G40: 0.3 | H40: 0.3 | I40: 0.4 | J40: 0.5 | K40: 0.5 | L40: 0.3 | M40: 0.2 | N40: 0.2 | O40: 0.2 | P40: 0.2 | Q40: 0.2 | R40: 0.2 | S40: 0.2 | T40: 0.2 | U40: 0.2 | V40: 0.2 | W40: 0.2 | X40: 0.3 | Y40: 0.2 | Z40: 0.3 | AA40: 0.3 | AB40: 0.3 | AC40: 0.3 | AD40: 0.3 | AE40: 0.3 | AF40: 0.3 | AG40: 0.4 | AH40: 0.3 | AJ40: chemicals 20 | AK40: F-gases | AL40: <this is really the electrical equipment industry, but we group with chemicals here
A41: Magnesium Production and Processing | B41: 0 | C41: 0 | D41: 0 | E41: 0 | F41: 0 | G41: 0 | H41: 0 | I41: 0 | J41: 0 | K41: 0 | L41: 0 | M41: 0 | N41: 0 | O41: 0 | P41: 0 | Q41: 0 | R41: 0 | S41: 0 | T41: 0 | U41: 0 | V41: 0 | W41: 0 | X41: 0 | Y41: 0.1 | Z41: 0.1 | AA41: 0.1 | AB41: 0.1 | AC41: 0.1 | AD41: 0.1 | AE41: 0.1 | AF41: 0.1 | AG41: 0 | AH41: 0 | AJ41: other metals 242 | AK41: F-gases
A42: PFCs | B42: 21.8 | C42: 18.8 | D42: 17.5 | E42: 17.5 | F42: 16.2 | G42: 16.8 | H42: 17.9 | I42: 16.4 | J42: 15.3 | K42: 15.2 | L42: 14.4 | M42: 7.5 | N42: 9.3 | O42: 7.4 | P42: 6.2 | Q42: 6.1 | R42: 5.9 | S42: 7.2 | T42: 5.8 | U42: 3.9 | V42: 4.3 | W42: 6.7 | X42: 5.8 | Y42: 5.6 | Z42: 5.2 | AA42: 6.8 | AB42: 5.8 | AC42: 5.4 | AD42: 7.4 | AE42: 7.3 | AF42: 6.6 | AG42: 6.3 | AH42: 6.7
A43: Fluorochemical Production | AA43: 1.9 | AB43: 1.6 | AC43: 1.5 | AD43: 2.9 | AE43: 3 | AF43: 2.5 | AG43: 2.6 | AH43: 3 | AJ43: chemicals 20 | AK43: F-gases
A44: Electronics Industry | B44: 2.5 | C44: 2.5 | D44: 2.5 | E44: 3.2 | F44: 3.5 | G44: 4.4 | H44: 4.9 | I44: 5.2 | J44: 6.3 | K44: 6.4 | L44: 5.5 | M44: 3.9 | N44: 3.8 | O44: 3.5 | P44: 3.2 | Q44: 3 | R44: 3.2 | S44: 3 | T44: 2.7 | U44: 1.9 | V44: 2.5 | W44: 3.4 | X44: 3 | Y44: 2.7 | Z44: 2.8 | AA44: 2.8 | AB44: 2.7 | AC44: 2.7 | AD44: 2.9 | AE44: 2.6 | AF44: 2.5 | AG44: 2.6 | AH44: 2.7 | AJ44: chemicals 20 | AK44: F-gases | AL44: <this is really the electrical equipment industry, but we group with chemicals here
A45: Aluminum Production | B45: 19.3 | C45: 16.3 | D45: 15 | E45: 14.4 | F45: 12.7 | G45: 12.4 | H45: 13 | I45: 11.3 | J45: 9 | K45: 8.8 | L45: 8.9 | M45: 3.6 | N45: 5.5 | O45: 3.9 | P45: 3 | Q45: 3.1 | R45: 2.7 | S45: 4.2 | T45: 3 | U45: 1.9 | V45: 1.8 | W45: 3.2 | X45: 2.8 | Y45: 2.8 | Z45: 2.4 | AA45: 1.9 | AB45: 1.3 | AC45: 1 | AD45: 1.4 | AE45: 1.4 | AF45: 1.4 | AG45: 0.9 | AH45: 0.8 | AJ45: other metals 242 | AK45: F-gases
A46: SF6 and PFCs from Other Product Use | AA46: 0.2 | AB46: 0.1 | AC46: 0.2 | AD46: 0.2 | AE46: 0.2 | AF46: 0.2 | AG46: 0.1 | AH46: 0.2 | AJ46: chemicals 20 | AK46: F-gases
A47: Substitution of Ozone Depleting Substances a | B47: 0 | C47: 0 | D47: 0 | E47: 0 | F47: 0 | G47: 0 | H47: 0 | I47: 0 | J47: 0 | K47: 0 | L47: 0 | M47: 0 | N47: 0 | O47: 0 | P47: 0 | Q47: 0 | R47: 0 | S47: 0 | T47: 0 | U47: 0 | V47: 0 | W47: 0 | X47: 0 | Y47: 0 | Z47: 0 | AA47: + | AB47: + | AC47: + | AD47: + | AE47: + | AF47: + | AG47: + | AH47: +
A48: Electrical Equipment | B48: 0 | C48: 0 | D48: 0 | E48: 0 | F48: 0 | G48: 0 | H48: 0 | I48: 0 | J48: 0 | K48: 0 | L48: 0 | M48: 0 | N48: 0 | O48: 0 | P48: 0 | Q48: 0 | R48: 0 | S48: 0 | T48: 0 | U48: 0 | V48: 0 | W48: 0 | X48: 0 | Y48: 0 | Z48: 0 | AA48: + | AB48: + | AC48: + | AD48: + | AE48: + | AF48: + | AG48: + | AH48: +
A49: SF6 | B49: 30.5 | C49: 29.2 | D49: 29.4 | E49: 28.9 | F49: 27.6 | G49: 26.3 | H49: 25.6 | I49: 23.9 | J49: 21 | K49: 20.7 | L49: 18 | M49: 17.3 | N49: 16.5 | O49: 16.6 | P49: 15.7 | Q49: 15.5 | R49: 14.6 | S49: 13.4 | T49: 12.6 | U49: 10.5 | V49: 9.6 | W49: 9.6 | X49: 8.3 | Y49: 7.9 | Z49: 7.8 | AA49: 8.2 | AB49: 8.5 | AC49: 7.9 | AD49: 7.6 | AE49: 8.4 | AF49: 8.1 | AG49: 8.5 | AH49: 7.6
A50: Electrical Equipment | B50: 24.7 | C50: 23.6 | D50: 23.6 | E50: 22.8 | F50: 21.5 | G50: 19.8 | H50: 18.1 | I50: 16.6 | J50: 14.1 | K50: 14.5 | L50: 14 | M50: 13.7 | N50: 13 | O50: 12.5 | P50: 12.2 | Q50: 11.8 | R50: 11 | S50: 10.2 | T50: 10.2 | U50: 9 | V50: 7.8 | W50: 7.1 | X50: 6.1 | Y50: 5.9 | Z50: 6.1 | AA50: 5.3 | AB50: 5.4 | AC50: 5.3 | AD50: 5 | AE50: 6.1 | AF50: 5.9 | AG50: 6 | AH50: 5.1 | AJ50: chemicals 20 | AK50: F-gases | AL50: <this is really the electrical equipment industry, but we group with chemicals here
A51: Magnesium Production and Processing | B51: 5.4 | C51: 5.1 | D51: 5.4 | E51: 5.5 | F51: 5.3 | G51: 5.5 | H51: 6.5 | I51: 6.2 | J51: 5.6 | K51: 5 | L51: 3 | M51: 2.9 | N51: 2.9 | O51: 3.4 | P51: 2.8 | Q51: 2.9 | R51: 2.9 | S51: 2.6 | T51: 1.9 | U51: 1.1 | V51: 1.3 | W51: 1.8 | X51: 1.5 | Y51: 1.3 | Z51: 1 | AA51: 1 | AB51: 1.2 | AC51: 1 | AD51: 1.1 | AE51: 0.9 | AF51: 0.9 | AG51: 1.2 | AH51: 1.1 | AJ51: other metals 242 | AK51: F-gases
A52: Electronics Industry | B52: 0.5 | C52: 0.5 | D52: 0.5 | E52: 0.6 | F52: 0.7 | G52: 0.9 | H52: 1 | I52: 1 | J52: 1.3 | K52: 1.3 | L52: 1 | M52: 0.7 | N52: 0.6 | O52: 0.8 | P52: 0.7 | Q52: 0.8 | R52: 0.8 | S52: 0.6 | T52: 0.6 | U52: 0.4 | V52: 0.6 | W52: 0.7 | X52: 0.7 | Y52: 0.7 | Z52: 0.8 | AA52: 0.8 | AB52: 0.9 | AC52: 0.7 | AD52: 0.8 | AE52: 0.8 | AF52: 0.8 | AG52: 0.9 | AH52: 0.8 | AJ52: chemicals 20 | AK52: F-gases | AL52: <this is really the electrical equipment industry, but we group with chemicals here
A53: SF6 and PFCs from Other Product Use | AA53: 1.1 | AB53: 1.1 | AC53: 0.8 | AD53: 0.8 | AE53: 0.6 | AF53: 0.5 | AG53: 0.4 | AH53: 0.6 | AJ53: chemicals 20 | AK53: F-gases
A54: Fluorochemical Production | AA54: + | AB54: + | AC54: + | AD54: + | AE54: + | AF54: + | AG54: + | AH54: +
A55: NF3 | B55: 0 | C55: 0 | D55: 0 | E55: 0.1 | F55: 0.1 | G55: 0.1 | H55: 0.1 | I55: 0.1 | J55: 0.1 | K55: 0.1 | L55: 0.2 | M55: 0.2 | N55: 0.5 | O55: 0.5 | P55: 0.5 | Q55: 0.4 | R55: 0.6 | S55: 0.5 | T55: 0.5 | U55: 0.4 | V55: 0.4 | W55: 0.5 | X55: 0.5 | Y55: 0.5 | Z55: 0.5 | AA55: 0.8 | AB55: 0.7 | AC55: 0.9 | AD55: 0.7 | AE55: 1.1 | AF55: 1.3 | AG55: 1.1 | AH55: 1.1
A56: Electronics Industry | B56: 0 | C56: 0 | D56: 0 | E56: 0.1 | F56: 0.1 | G56: 0.1 | H56: 0.1 | I56: 0.1 | J56: 0.1 | K56: 0.1 | L56: 0.2 | M56: 0.2 | N56: 0.5 | O56: 0.5 | P56: 0.5 | Q56: 0.4 | R56: 0.6 | S56: 0.5 | T56: 0.5 | U56: 0.4 | V56: 0.4 | W56: 0.5 | X56: 0.5 | Y56: 0.5 | Z56: 0.5 | AA56: 0.5 | AB56: 0.5 | AC56: 0.5 | AD56: 0.5 | AE56: 0.5 | AF56: 0.6 | AG56: 0.6 | AH56: 0.6 | AJ56: chemicals 20 | AK56: F-gases | AL56: <this is really the electrical equipment industry, but we group with chemicals here
A57: Fluorochemical Production | AA57: 0.2 | AB57: 0.2 | AC57: 0.4 | AD57: 0.1 | AE57: 0.6 | AF57: 0.7 | AG57: 0.5 | AH57: 0.5 | AJ57: chemicals 20 | AK57: F-gases
A58: Total b | B58: 335.4 | C58: 317.3 | D58: 322.8 | E58: 322.2 | F58: 333.9 | G58: 362.3 | H58: 374.1 | I58: 379.7 | J58: 386.1 | K58: 382.4 | L58: 381 | M58: 345.9 | N58: 354 | O58: 342.1 | P58: 355.2 | Q58: 356.1 | R58: 365.3 | S58: 381.7 | T58: 360.2 | U58: 312.9 | V58: 352 | W58: 367 | X58: 357.2 | Y58: 357.2 | Z58: 368.7 | AA58: 369.7 | AB58: 361.6 | AC58: 362.7 | AD58: 367.2 | AE58: 371.9 | AF58: 367.9 | AG58: 381.6 | AH58: 383.2
A59: + Does not exceed 0.05 MMT CO2 Eq.
A60: NO (Not Occurring)
A61: a Small amounts of PFC emissions from this source are included under HFCs due to confidential business information.
A62: b Total does not include other fluorinated gases, such as HFEs and PFPEs, which are reported separately in Section 4.24.
A63: Note: Totals may not sum due to independent rounding. Emissions of F-HTFs that are not HFCs, PFCs or SF6 are not included in Inventory totals and are included for informational purposes only in Section 4.24. Emissions presented for informational purposes include HFEs, PFPMIEs, perfluoroalkylmorpholines, and perfluorotrialkylamines.

Sheet BPE - US specific multipliers
B1: Summary of Start Year EPA Data from Inventory
B3: EPA Summary (mmt CO2e AR5)
E4: 2021 | F4: 2022
C5: Industry | D5: Gas
B6: 5-1 | C6: agriculture and forestry 01T03 | D6: CO2 | E6: 7.6 | F6: 8.6
B7: 5-1 | C7: agriculture and forestry 01T03 | D7: CH4 | E7: 281.8 | F7: 276.8
B8: 5-1 | C8: agriculture and forestry 01T03 | D8: N2O | E8: 315.3 | F8: 308
B9: 3-1 | C9: coal mining 05 | D9: CO2 | E9: 2.5 | F9: 2.5
B10: 3-1 | C10: coal mining 05 | D10: CH4 | E10: 51 | F10: 49.9
B11: 3-68 | C11: oil and gas extraction 06 | D11: CO2 | E11: 34.8 | F11: 35.3
B12: 3-46 | C12: oil and gas extraction 06 | D12: CO2 | E12: 21.1 | F12: 19.1
B13: subtotal | C13: oil and gas extraction 06 | D13: CO2 | E13: 55.9 | F13: 54.4
B14: 3-44 | C14: oil and gas extraction 06 | D14: CH4 | E14: 47.7 | F14: 38.7
B15: 3-66 | C15: oil and gas extraction 06 | D15: CH4 | E15: 106.5 | F15: 105
B16: 3-1 | C16: oil and gas extraction 06 | D16: CH4 | E16: 8.6 | F16: 8.5
B17: subtotal | C17: oil and gas extraction 06 | D17: CH4 | E17: 162.8 | F17: 152.2
... B44: 7-1 | C44: water and waste 36T39 | D44: N2O | E44: 23.9 | F44: 23.7

Sheet Steel
A2: This graph is Figure 6-54 on pg. 138 of the NETL report.
A26: Plant ID | B26: Plant name (English) | C26: Plant name (other language) | D26: Country/Area | E26: Status | F26: Start date | G26: Nominal BOF steel capacity (ttpa) | H26: Nominal BF capacity (ttpa) | I26: Other/unspecified iron capacity (ttpa) | J26: CO2 available | K26: Steel Production Capacity | L26: COC, $/tonne | M26: COA, 2018 $/tonne | N26: COA, 2012 $/tonne | O26: Cumulative Capacity
A27: P100000120966 | B27: U.S. Steel Gary Works | D27: United States | E27: operating | F27: 1908 | G27: 7800 | H27: 6495 | I27: N/A | J27: 10.594409 | K27: 6.5041573 | L27: 54.647887 | M27: =L27+AVERAGE('Retrofit Cost vs SOC Data'!$B$9,'Retrofit Cost vs SOC Data'!$D$9,'Retrofit Cost vs SOC Data'!$F$9,'Retrofit Cost vs SOC Data'!$H$9,'Retrofit Cost vs SOC Data'!$J$9) -> 65.723695 | N27: =M27*cpi!$G$56 -> 60.092973 | O27: =SUM(H27:H$27)/SUM(H$27:H$33) -> 0.25150048
A28: P100000120923 | B28: Cleveland-Cliffs Burns Harbor steel plant | D28: United States | E28: operating | F28: 1964 | G28: 5001 | H28: 4960 | I28: N/A | J28: 8.0828734 | K28: 4.9455809 | L28: 57.042254 | M28: =L28+AVERAGE('Retrofit Cost vs SOC Data'!$B$9,'Retrofit Cost vs SOC Data'!$D$9,'Retrofit Cost vs SOC Data'!$F$9,'Retrofit Cost vs SOC Data'!$H$9,'Retrofit Cost vs SOC Data'!$J$9) -> 68.118062 | N28: =M28*cpi!$G$56 -> 62.282207 | O28: =SUM(H$27:H28)/SUM(H$27:H$33) -> 0.44356244
A29: P100000120926 | B29: Cleveland-Cliffs Indiana Harbor steel plant | D29: United States | E29: operating | F29: 1901 | G29: 6800 | H29: 4200 | I29: N/A | J29: 6.8402322 | K29: 4.2057503 | L29: 58.732394 | M29: =L29+AVERAGE('Retrofit Cost vs SOC Data'!$B$9,'Retrofit Cost vs SOC Data'!$D$9,'Retrofit Cost vs SOC Data'!$F$9,'Retrofit Cost vs SOC Data'!$H$9,'Retrofit Cost vs SOC Data'!$J$9) -> 69.808203 | N29: =M29*cpi!$G$56 -> 63.827549 | O29: =SUM(H$27:H29)/SUM(H$27:H$33) -> 0.60619555
A30: P100000120927 | B30: Cleveland-Cliffs Cleveland steel plant | D30: United States | E30: operating | F30: 1913 | G30: 4100 | H30: 2810 | I30: N/A | J30: 4.5649736 | K30: 2.8050044 | L30: 63.239437 | M30: =L30+AVERAGE('Retrofit Cost vs SOC Data'!$B$9,'Retrofit Cost vs SOC Data'!$D$9,'Retrofit Cost vs SOC Data'!$F$9,'Retrofit Cost vs SOC Data'!$H$9,'Retrofit Cost vs SOC Data'!$J$9) -> 74.315245 | N30: =M30*cpi!$G$56 -> 67.948461 | O30: =SUM(H$27:H30)/SUM(H$27:H$33) -> 0.71500484
A31: P100000120964 | B31: U.S. Steel Edgar Thomson Plant | D31: United States | E31: operating | F31: 1875 | G31: 2600 | H31: 2770 | I31: N/A | J31: 4.5212187 | K31: 2.7754111 | L31: 63.380282 | M31: =L31+AVERAGE('Retrofit Cost vs SOC Data'!$B$9,'Retrofit Cost vs SOC Data'!$D$9,'Retrofit Cost vs SOC Data'!$F$9,'Retrofit Cost vs SOC Data'!$H$9,'Retrofit Cost vs SOC Data'!$J$9) -> 74.45609 | N31: =M31*cpi!$G$56 -> 68.07724 | O31: =SUM(H$27:H31)/SUM(H$27:H$33) -> 0.82226525
A32: P100000120920 | B32: Cleveland-Cliffs Dearborn steel plant | D32: United States | E32: operating | F32: 1920 | G32: 3000 | H32: 2500 | I32: N/A | J32: 4.048665 | K32: 2.4992077 | L32: 64.71831 | M32: =L32+AVERAGE('Retrofit Cost vs SOC Data'!$B$9,'Retrofit Cost vs SOC Data'!$D$9,'Retrofit Cost vs SOC Data'!$F$9,'Retrofit Cost vs SOC Data'!$H$9,'Retrofit Cost vs SOC Data'!$J$9) -> 75.794118 | N32: =M32*cpi!$G$56 -> 69.300636 | O32: =SUM(H$27:H32)/SUM(H$27:H$33) -> 0.91907067
A33: P100000120921 | B33: Cleveland-Cliffs Middletown steel plant | D33: United States | E33: operating pre-retirement | F33: 1901 | G33: N/A | H33: 2090 | I33: N/A | J33: 3.4010914 | K33: 2.094767 | L33: 66.901408 | M33: =L33+AVERAGE('Retrofit Cost vs SOC Data'!$B$9,'Retrofit Cost vs SOC Data'!$D$9,'Retrofit Cost vs SOC Data'!$F$9,'Retrofit Cost vs SOC Data'!$H$9,'Retrofit Cost vs SOC Data'!$J$9) -> 77.977217 | N33: =M33*cpi!$G$56 -> 71.296702 | O33: =SUM(H$27:H33)/SUM(H$27:H$33) -> 1
B37: TABLE 2(I).A-H SECTORAL BACKGROUND DATA FOR INDUSTRIAL PROCESSES AND PRODUCT USE
B38: 1. Iron and steel production | H38: 41656.176
B39: a. Steel | C39: Steel Production | D39: 57306.86 | E39: 0.096273492 | F39: NA | H39: 5517.1315
B40: b. Pig iron | C40: Pig Iron Production | D40: 22246.358 | E40: 0.32078687 | F40: NA | H40: 7136.3397
B41: c. Direct reduced iron | C41: Production | D41: C | E41: C | F41: NE,NO | H41: 1984.2827
B42: d. Sinter | C42: Production | D42: 4181.708 | E42: 0.2 | F42: 7e-05 | H42: 836.3416
B43: e. Pellet | C43: Production | D43: 27949.069 | E43: 0.03 | F43: NA | H43: 838.47208
B44: f. Other (please specify) | H44: 25343.609
B45: Other Blast Furnace Gas Consumption | C45: Consumption | D45: 33176.627 | E45: 0.62333333 | F45: NO,IE | H45: 20680.098
B46: Coke | C46: Consumption | D46: 11380.824 | E46: 0.28331807 | F46: NO,IE | H46: 3224.3931
B47: Other Coke Oven Gas Consumption | C47: Consumption | D47: 835.07812 | E47: 1.7233333 | F47: NO,IE | H47: 1439.118
A51: Share of Steel emissions from these BF/BOFs
A52: =SUMIFS(Table2[GHG QUANTITY (METRIC TONS CO2e)],Table2[Column1],"Yes")/SUM(Table2[GHG QUANTITY (METRIC TONS CO2e)]) -> 0.59489255

Sheet FLIGHT Facilities and GHG Quant
A1: Data Extracted from EPA's FLIGHT Tool (http://ghgdata.epa.gov/ghgp)
A2: The data was reported to EPA by facilities as of 08/16/2024
A3: All emissions data is presented in units of metric tons of carbon dioxide equivalent using GWP's from IPCC's AR4
A4: Search Parameters: year=2023; GHGs=CO2; data type=All Direct Emitters;
A6: REPORTING YEAR | B6: FACILITY NAME | C6: GHGRP ID | D6: REPORTED ADDRESS | E6: LATITUDE | F6: LONGITUDE | G6: CITY NAME | H6: COUNTY NAME | I6: STATE | J6: ZIP CODE | K6: PARENT COMPANIES | L6: GHG QUANTITY (METRIC TONS CO2e) | M6: SUBPARTS | N6: Column1
A7: 2023 | B7: US Steel Corp - Gary Works | C7: 1000418 | D7: 1 NORTH BROADWAY | E7: 41.6133 | F7: -87.3281 | G7: GARY | H7: Lake | I7: IN | J7: 46402 | K7: US STEEL CORP (100%) | L7: 10812592 | M7: C,Q,TT | N7: Yes
A8: 2023 | B8: Cleveland-Cliffs Burns Harbor LLC | C8: 1003962 | D8: 250 W US 12 | E8: 41.634 | F8: -87.131 | G8: BURNS HARBOR | H8: PORTER COUNTY | I8: IN | J8: 46304 | K8: CLEVELAND-CLIFFS INC (100%) | L8: 7641790 | M8: C,Q | N8: Yes
A9: 2023 | B9: Cleveland-Cliffs Steel LLC | C9: 1000156 | D9: 3210 WATLING ST | E9: 41.68 | F9: -87.4264 | G9: EAST CHICAGO | H9: Lake | I9: IN | J9: 46312 | K9: CLEVELAND-CLIFFS INC (100%) | L9: 5640848 | M9: C,Q,S | N9: Yes
A10: 2023 | B10: Cleveland-Cliffs Cleveland Works LLC | C10: 1007177 | D10: 3060 EGGERS AVENUE | E10: 41.4739 | F10: -81.6728 | G10: CLEVELAND | H10: Cuyahoga | I10: OH | J10: 44105 | K10: CLEVELAND-CLIFFS INC (100%) | L10: 4268433 | M10: C,Q | N10: Yes
A11: 2023 | B11: US Steel (Edgar Thomson) | C11: 1000233 | D11: 13th Street and Braddock Avenue | E11: 40.3925 | F11: -79.8564 | G11: Braddock | H11: Allegheny | I11: PA | J11: 15104 | K11: US STEEL CORP (100%) | L11: 3575971 | M11: C,Q | N11: Yes
A12: 2023 | B12: Cleveland-Cliffs Steel Corporation - Middletown Works | C12: 1000274 | D12: 1801 CRAWFORD STREET | E12: 39.4968 | F12: -84.3901 | G12: MIDDLETOWN | H12: Butler | I12: OH | J12: 45043 | K12: CLEVELAND-CLIFFS INC (100%) | L12: 3510727 | M12: C,Q | N12: Yes
A13: 2023 | B13: US STEEL - GRANITE CITY | C13: 1006041 | D13: 1951 STATE ST | E13: 38.6954 | F13: -90.1367 | G13: GRANITE CITY | H13: MADISON COUNTY | I13: IL | J13: 62040 | K13: US STEEL CORP (100%) | L13: 1697023 | M13: C,Q,TT
A14: 2023 | B14: US STEEL - Minntac | C14: 1001621 | D14: 8819 OLD HIGHWAY 169 | E14: 47.565 | F14: -92.6328 | G14: MOUNTAIN IRON | H14: ST. LOUIS COUNTY | I14: MN | J14: 55768 | K14: US STEEL CORP (100%) | L14: 1305630 | M14: C,Q
A15: 2023 | B15: Nucor Steel Louisiana LLC | C15: 1010766 | D15: 9101 LA HWY 3125 | E15: 30.081306 | F15: -90.860528 | G15: Convent | H15: ST. JAMES PARISH | I15: LA | J15: 70723 | K15: NUCOR CORP (100%) | L15: 1086372 | M15: C,Q
A16: 2023 | B16: TILDEN MINING COMPANY L C | C16: 1004458 | E16: 46.439735 | F16: -87.649771 | G16: ISHPEMING | H16: MARQUETTE COUNTY | I16: MI | J16: 49849 | K16: CLEVELAND-CLIFFS INC (100%) | L16: 1065597 | M16: C,Q
A17: 2023 | B17: Indiana Harbor Coke Company | C17: 1007287 | D17: 3210 Watling St. | E17: 41.656321 | F17: -87.450142 | G17: East Chicago | H17: LAKE COUNTY | I17: IN | J17: 46312 | K17: SUNCOKE ENERGY INC (85%); DTE ENERGY CO (15%) | L17: 1065008 | M17: C,Q | N17: Yes
A18: 2023 | B18: CLEVELAND-CLIFFS STEEL CORPORATION DEARBORN WORKS | C18: 1003403 | D18: 4001 MILLER RD | E18: 42.301742 | F18: -83.162934 | G18: DEARBORN | H18: WAYNE COUNTY | I18: MI | J18: 48120 | K18: CLEVELAND-CLIFFS INC (100%) | L18: 1006617 | M18: C,Q | N18: Yes
A19: 2023 | B19: STEEL DYNAMICS INC | C19: 1005584 | D19: 4500 CR 59 | E19: 41.364278 | F19: -84.914083 | G19: BUTLER | H19: DEKALB COUNTY | I19: IN | J19: 46721 | K19: STEEL DYNAMICS INC (100%) | L19: 982345 | M19: C,Q
A20: 2023 | B20: HAVERHILL COKE COMPANY, LLC | C20: 1002777 | D20: 2446 GALLIA PIKE | E20: 38.5973 | F20: -82.8271 | G20: FRANKLIN FURNACE | H20: SCIOTO COUNTY | I20: OH | J20: 45629 | K20: SUNCOKE ENERGY INC (100%) | L20: 921306 | M20: C,Q
A21: 2023 | B21: IronUnits LLC | C21: 1014155 | D21: 300 Millard Avenue | E21: 41.675323 | F21: -83.477908 | G21: Toledo | H21: LUCAS COUNTY | I21: OH | J21: 43605 | K21: CLEVELAND-CLIFFS INC (100%) | L21: 802792 | M21: C,Q
A22: 2023 | B22: US Steel (Clairton Coke) | C22: 1000124 | D22: 400 STATE ST | E22: 40.3097 | F22: -79.8819 | G22: CLAIRTON | H22: Allegheny | I22: PA | J22: 15025 | K22: US STEEL CORP (100%) | L22: 768558 | M22: C,Q
A23: 2023 | B23: Cleveland-Cliffs Steel LLC | C23: 1000588 | D23: 3001 Dickey Road | E23: 41.651165 | F23: -87.459167 | G23: East Chicago | H23: LAKE COUNTY | I23: IN | J23: 46312 | K23: CLEVELAND-CLIFFS INC (100%) | L23: 703371 | M23: C,Q | N23: Yes
A24: 2023 | B24: NUCOR STEEL - BERKELEY | C24: 1002266 | D24: 1455 HAGAN AVENUE | E24: 33.004097 | F24: -79.8816 | G24: HUGER | H24: BERKELEY COUNTY | I24: SC | J24: 29450 | K24: NUCOR CORP (100%) | L24: 598742 | M24: C,Q
A25: 2023 | B25: ArcelorMittal Texas HBI | C25: 1012625 | D25: 2800 Kay Bailey Hutchison Road | E25: 27.888611 | F25: -97.277778 | G25: Portland | H25: SAN PATRICIO COUNTY | I25: TX | J25: 78374 | K25: ARCELORMITTAL HOLDINGS LLC (100%) | L25: 556898 | M25: C,Q
A26: 2023 | B26: Steel Dynamics Columbus, LLC | C26: 1004616 | D26: 1945 Airport Road | E26: 33.443611 | F26: -88.575556 | G26: Columbus | H26: LOWNDES COUNTY | I26: MS | J26: 39703 | K26: STEEL DYNAMICS INC (100%) | L26: 497936 | M26: C,Q
A27: 2023 | B27: GATEWAY ENERGY & COKE CO LLC | C27: 1003204 | D27: 2585 EDWARDSVILLE RD | E27: 38.695766 | F27: -90.132874 | G27: GRANITE CITY | H27: MADISON COUNTY | I27: IL | J27: 62040 | K27: SUNCOKE ENERGY INC (100%) | L27: 472572 | M27: C,Q
A28: 2023 | B28: NUCOR STEEL DECATUR | C28: 1005976 | D28: 4301 IVERSON BOULEVARD | E28: 34.638906 | F28: -87.089036 | G28: TRINITY | H28: MORGAN COUNTY | I28: AL | J28: 35673 | K28: NUCOR CORP (100%) | L28: 452004 | M28: C,Q
A29: 2023 | B29: NORTH STAR BLUESCOPE STEEL LLC * | C29: 1005163 | D29: 6767 COUNTY ROAD 9 | E29: 41.5684 | F29: -84.03759 | G29: DELTA | H29: FULTON COUNTY | I29: OH | J29: 43515 | K29: BLUESCOPE STEEL INVESTMENTS INC (50%); BLUESCOPE STEEL INVESTMENTS INC 3 (30%); BLUESCOPE STEEL INVESTMENTS INC 2 (20%) | L29: 442356 | M29: C,Q
A30: 2023 | B30: SunCoke Energy Middletown Operations | C30: 1006159 | D30: 3353 Yankee Road | E30: 39.47215 | F30: -84.39693 | G30: Middletown | H30: BUTLER COUNTY | I30: OH | J30: 45044 | K30: SUNCOKE ENERGY INC (100%) | L30: 429686 | M30: C,Q
A31: 2023 | B31: UNITED TACONITE LLC - FAIRLANE PLANT | C31: 1005294 | D31: 8470 Townline Road | E31: 47.3502 | F31: -92.5735 | G31: FORBES | H31: ST. LOUIS COUNTY | I31: MN | J31: 55738 | K31: CLEVELAND-CLIFFS INC (100%) | L31: 398411 | M31: C,Q
A32: 2023 | B32: Big River Steel LLC | C32: 1012997 | D32: 2027 E. State Hwy.198 | E32: 35.696993 | F32: -90.03732 | G32: Osceola | I32: AR | J32: 72370 | K32: US STEEL CORP (99.9%) | L32: 380122 | M32: C,Q
A33: 2023 | B33: Nucor Steel Gallatin LLC | C33: 1005700 | D33: 4831 US 42 W | E33: 38.766667 | F33: -85.004167 | G33: GHENT | H33: GALLATIN COUNTY | I33: KY | J33: 41045 | K33: NUCOR CORP (100%) | L33: 378072 | M33: C,Q
A34: 2023 | B34: JEWELL COAL & COKE | C34: 1005598 | D34: 1034 Dismal River Road | E34: 37.234374 | F34: -82.043024 | G34: Oakwood | H34: BUCHANAN COUNTY | I34: VA | J34: 24631 | K34: SUNCOKE ENERGY INC (100%) | L34: 376555 | M34: C,Q
A35: 2023 | B35: NUCOR-YAMATO STEEL CO | C35: 1007642 | D35: 5929 E. STATE HWY. 18 | E35: 35.8925 | F35: -89.784167 | G35: BLYTHEVILLE | H35: MISSISSIPPI COUNTY | I35: AR | J35: 72316 | K35: NUCOR CORP (51%); YAMATO KOGYO (USA) CORP (49%) | L35: 375181 | M35: C,Q
A36: 2023 | B36: NUCOR STEEL - ARKANSAS | C36: 1007921 | D36: 7301 EAST COUNTY ROAD 142 | E36: 35.944388 | F36: -89.723636 | G36: BLYTHEVILLE | H36: MISSISSIPPI COUNTY | I36: AR | J36: 72315 | K36: NUCOR CORP (100%) | L36: 372241 | M36: C,Q
A37: 2023 | B37: US STEEL - IRVIN WORKS | C37: 1000802 | E37: 40.3372 | F37: -79.9108 | G37: West Mifflin | H37: ALLEGHENY COUNTY | I37: PA | J37: 15122 | K37: US STEEL CORP (100%) | L37: 361981 | M37: C,Q
A38: 2023 | B38: SSAB ALABAMA INCORPORATED | C38: 1005283 | D38: 12400 HIGHWAY 43 NORTH | E38: 30.943048 | F38: -88.012823 | G38: AXIS | H38: MOBILE COUNTY | I38: AL | J38: 36505 | K38: SSAB US HOLDING INC (100%) | L38: 335572 | M38: C,Q
A39: 2023 | B39: EES COKE BATTERY | C39: 1007392 | D39: 1400 ZUG ISLAND | E39: 42.283105 | F39: -83.113962 | G39: RIVER ROUGE | H39: WAYNE COUNTY | I39: MI | J39: 48218 | K39: DTE ENERGY CO (100%) | L39: 331929 | M39: C,Q
A40: 2023 | B40: STEEL DYNAMICS. INC. (SDI), STRUCTUAL AND RAIL DIVISION | C40: 1005602 | D40: 2601 COUNTY ROAD 700 EAST | E40: 41.124348 | F40: -85.395659 | G40: COLUMBIA CITY | H40: WHITLEY COUNTY | I40: IN | J40: 46725 | K40: STEEL DYNAMICS INC (100%) | L40: 327943 | M40: C,Q
A41: 2023 | B41: TIMKENSTEEL CORP (1576000613) | C41: 1003860 | D41: 1835 DUEBER AVENUE, S.W. | E41: 40.780505 | F41: -81.397259 | G41: CANTON | H41: STARK COUNTY | I41: OH | J41: 44706 | K41: TIMKENSTEEL CORP (100%) | L41: 320101 | M41: C,Q
A42: 2023 | B42: Steel Dynamics Southwest, LLC | C42: 1014686 | D42: 8534 HWY 89 | E42: 28.057072 | F42: -97.464965 | G42: Sinton | I42: TX | J42: 78387 | K42: STEEL DYNAMICS INC (100%) | L42: 297285 | M42: C,Q
A43: 2023 | B43: SSAB Iowa Inc. | C43: 1002147 | D43: 1770 BILL SHARP BOULEVARD | E43: 41.48553 | F43: -90.82278 | G43: MUSCATINE | H43: MUSCATINE COUNTY | I43: IA | J43: 52761 | K43: SSAB US HOLDING INC (100%) | L43: 295289 | M43: C,Q
A44: 2023 | B44: Hibbing Taconite Company | C44: 1005116 | D44: 4950 County Highway 5 North | E44: 47.478 | F44: -92.9676 | G44: Hibbing | H44: ST. LOUIS COUNTY | I44: MN | J44: 55746 | K44: CLEVELAND-CLIFFS INC (85.3%); US STEEL CORP (14.7%) | L44: 286217 | M44: C,Q
A45: 2023 | B45: North American Stainless | C45: 1002977 | D45: 6870 Highway 42 East | E45: 38.734905 | F45: -85.002554 | G45: Ghent | H45: GALLATIN COUNTY | I45: KY | J45: 41045 | K45: NORTH AMERICAN STAINLESS (100%) | L45: 274881 | M45: C,Q
A46: 2023 | B46: CHAPARRAL STEEL MIDLOTHIAN PLANT | C46: 1005344 | D46: 300 WARD ROAD | E46: 32.458249 | F46: -97.036607 | G46: MIDLOTHIAN | H46: ELLIS COUNTY | I46: TX | J46: 76065 | K46: GERDAU USA INC (100%) | L46: 272782 | M46: C,Q
A47: 2023 | B47: NUCOR STEEL INDIANA | C47: 1004151 | D47: 4537 S NUCOR RD | E47: 39.9747 | F47: -86.8301 | G47: CRAWFORDSVILLE | H47: MONTGOMERY COUNTY | I47: IN | J47: 47933 | K47: NUCOR CORP (100%) | L47: 255254 | M47: C,Q
A48: 2023 | B48: Cleveland-Cliffs Steel Corporation /BUTLER WORKS | C48: 1002903 | D48: 1 ARMCO DR | E48: 40.82926 | F48: -79.94273 | G48: BUTLER | H48: BUTLER COUNTY | I48: PA | J48: 16003 | K48: CLEVELAND-CLIFFS INC (100%) | L48: 251082 | M48: C,Q,TT
A49: 2023 | B49: Cleveland-Cliffs Minorca Mine | C49: 1003669 | D49: 5950 Old Highway 53 | E49: 47.5607 | F49: -92.520349 | G49: Virginia | H49: ST. LOUIS COUNTY | I49: MN | J49: 55792 | K49: CLEVELAND-CLIFFS INC (100%) | L49: 238227 | M49: C,Q
A50: 2023 | B50: US Steel - Keetac | C50: 1001618 | D50: 1 MINE ROAD | E50: 47.413883 | F50: -93.062672 | G50: KEEWATIN | H50: ST. LOUIS COUNTY | I50: MN | J50: 55753 | K50: US STEEL CORP (100%) | L50: 231327 | M50: C,Q
A51: 2023 | B51: CF & I STEEL L P/ DBA ROCKY MOUNTAIN STEEL MILLS | C51: 1003902 | D51: 2100 SOUTH FREEWAY | E51: 38.232627 | F51: -104.60726 | G51: PUEBLO | H51: PUEBLO COUNTY | I51: CO | J51: 81004 | K51: EVRAZ INC NORTH AMERICA (100%) | L51: 229028 | M51: C,Q,TT
A52: 2023 | B52: NUCOR STEEL HERTFORD COUNTY | C52: 1002958 | D52: 1505 RIVER RD | E52: 36.355216 | F52: -76.81115 | G52: COFIELD | H52: HERTFORD COUNTY | I52: NC | J52: 27922 | K52: NUCOR CORP (100%) | L52: 216366 | M52: C,Q
A53: 2023 | B53: STRUCTURAL METALS INC | C53: 1004259 | D53: 1 STEEL MILL ROAD | E53: 29.57906 | F53: -98.02368 | G53: SEGUIN | H53: GUADALUPE COUNTY | I53: TX | J53: 78155 | K53: COMMERCIAL METALS CO (100%) | L53: 213696 | M53: C,Q
A54: 2023 | B54: NUCOR STEEL - UTAH | C54: 1005777 | D54: 7285 W 21200 N | E54: 41.8825 | F54: -112.1964 | G54: PLYMOUTH | H54: BOX ELDER COUNTY | I54: UT | J54: 84330 | K54: NUCOR CORP (100%) | L54: 203814 | M54: C,Q,TT
... A104: 2023 | B104: Carpenter Technology - Latrobe Operations | C104: 1004434 | D104: 2626 LIGONIER STREET | E104: 40.302598 | F104: -79.372804 | G104: LATROBE | H104: WESTMORELAND COUNTY | I104: PA | J104: 15650 | K104: CARPENTER TECHNOLOGY CORP (100%) | L104: 61279 | M104: C,Q
A105: 2023 | B105: Nucor Steel Longview | C105: 1012352 | D105: 5400 W Loop 281, Bldg 52 | E105: 32.381759 | F105: -94.707062 | G105: Longview | I105: TX | J105: 75603 | K105: NUCOR CORP (100%) | L105: 58945 | M105: C,Q
A106: 2023 | B106: CMC Steel Oklahoma, LLC | C106: 1013215 | D106: 2253 E. Main Street | E106: 33.997672 | F106: -96.404008 | G106: Durant | H106: BRYAN COUNTY | I106: OK | J106: 74701 | K106: COMMERCIAL METALS CO (100%) | L106: 55564 | M106: C,Q
A107: 2023 | B107: SWVA, INC. | C107: 1006972 | D107: 2ND AVE & 17TH STREET | E107: 38.4265 | F107: -82.42532 | G107: HUNTINGTON | H107: CABELL COUNTY | I107: WV | J107: 25726 | K107: STEEL DYNAMICS INC (100%) | L107: 55428 | M107: C,Q
A108: 2023 | B108: Gerdau Ameristeel US, Inc - Charlotte Mill | C108: 1003507 | D108: 6601 LAKEVIEW ROAD | E108: 35.33908 | F108: -80.83114 | G108: CHARLOTTE | H108: MECKLENBURG COUNTY | I108: NC | J108: 28269 | K108: GERDAU USA INC (100%) | L108: 50112 | M108: C,Q
A109: 2023 | B109: HUNTINGTON INGALLS INCORPORATED | C109: 1001958 | D109: 4101 WASHINGTON AVE | E109: 36.98767 | F109: -76.43943 | G109: NEWPORT NEWS | H109: NEWPORT NEWS CITY | I109: VA | J109: 23607 | K109: HUNTINGTON INGALLS INDUSTRIES INC (100%) | L109: 49648 | M109: C,Q
A110: 2023 | B110: ELLWOOD QUALITY STEELS | C110: 1001669 | D110: 700 MORAVIA STREET | E110: 40.99341 | F110: -80.34696 | G110: NEW CASTLE | H110: LAWRENCE COUNTY | I110: PA | J110: 16101 | K110: ELLWOOD GROUP INC (100%) | L110: 48279 | M110: C,Q
A111: 2023 | B111: VINTON STEEL LLC | C111: 1003580 | D111: INTERSTATE 10 AND VINTON ROAD | E111: 31.96534 | F111: -106.58505 | G111: VINTON | H111: EL PASO COUNTY | I111: TX | J111: 79821 | K111: VINTON STEEL LLC (100%) | L111: 42473 | M111: C,Q
A112: 2023 | B112: UNIVERSAL STAINLESS BRIDGEVILLE PLT | C112: 1005423 | D112: 600 MAYER STREET | E112: 40.36682 | F112: -80.09976 | G112: BRIDGEVILLE | H112: ALLEGHENY COUNTY | I112: PA | J112: 15017 | K112: UNIVERSAL STAINLESS & ALLOY PRODUCTS INC (100%) | L112: 42407 | M112: C,Q
A113: 2023 | B113: HOEGANAES CORPORATION | C113: 1005515 | D113: 1315 AIRPORT ROAD | E113: 36.371493 | F113: -86.423903 | G113: GALLATIN | H113: SUMNER COUNTY | I113: TN | J113: 37066 | K113: GKN Powdered Metallurgy Holdings INC (100%) | L113: 36522 | M113: C,Q
A114: 2023 | B114: Nucor Steel Florida Inc. | C114: 1013487 | D114: 22 Nucor Dr. | E114: 27.655245 | F114: -81.51858 | G114: Frostproof | H114: POLK COUNTY | I114: FL | J114: 33843 | K114: NUCOR CORP (100%) | L114: 35009 | M114: C,Q
A115: 2023 | B115: FINKL & SONS CO | C115: 1008735 | D115: 1355 E 93RD ST | E115: 41.728542 | F115: -87.591648 | G115: CHICAGO | H115: COOK COUNTY | I115: IL | J115: 60619 | K115: FINKL & SONS CO (100%) | L115: 34585 | M115: C,Q
A116: 2023 | B116: UNION ELEC HARMON CREEK PLT | C116: 1000399 | D116: 31 UNION ELECTRIC STEEL ROAD ROUTE 18 NORTH | E116: 40.411133 | F116: -80.40839 | G116: BURGETTSTOWN | H116: WASHINGTON COUNTY | I116: PA | J116: 15021 | K116: AMPCO-PITTSBURGH CORP (100%) | L116: 34351 | M116: C,Q
A117: 2023 | B117: Mid American Steel & Wire | C117: 1004453 | D117: 1327 Smiley Road | E117: 34.07091 | F117: -96.75503 | G117: Madill | H117: MARSHALL COUNTY | I117: OK | J117: 73446 | K117: MID AMERICAN STEEL & WIRE CO LLC (100%) | L117: 33815 | M117: C,Q
... A127: 2023 | B127: MOUNTAIN STATE CARBON | C127: 1001563 | D127: 1851 MAIN ST | E127: 40.34361 | F127: -80.60667 | G127: FOLLANSBEE | H127: BROOKE COUNTY | I127: WV | J127: 26037 | K127: CLEVELAND-CLIFFS INC (100%) | L127: 2323 | M127: C,Q

Sheet Refining
A1: assume 3 scenarios: low-cost post-combustion techs, average of low and high, and high-cost
K3: Plot digitizer
M5: x | N5: y | S5: 177 | T5: 2013 refining emissions (same source), Mt CO2
L6: CCU | M6: 31.267606 | N6: 53.646477 | O6: =M6 -> 31.267606
L7: steam | M7: 52.957746 | N7: 57.948084 | O7: =M7-M6 -> 21.690141 | Q7: scenario | R7: Column1 | S7: co2 potl | T7: cost | U7: avoidance cost | Y7: cost | Z7: share | AA7: cum
L8: SMR | M8: 77.323944 | N8: 59.728059 | O8: =M8-M7 -> 24.366197 | Q8: low | R8: =L6 -> CCU | S8: =O6/3 -> 10.422535 | T8: =N6 -> 53.646477 | U8: =T8*cpi!$G$52+AVERAGE('Retrofit Cost vs SOC Data'!$B$9,'Retrofit Cost vs SOC Data'!$D$9,'Retrofit Cost vs SOC Data'!$F$9,'Retrofit Cost vs SOC Data'!$H$9,'Retrofit Cost vs SOC Data'!$J$9)*cpi!$G$56 -> 62.154951 | V8: =RANK(U8,$U$8:$U$49,1) -> 1 | X8: 1 | Y8: =INDEX($U$8:$U$49,MATCH(X8,$V$8:$V$49,0)) -> 62.154951 | Z8: =INDEX($S$8:$S$49,MATCH(X8,$V$8:$V$49,0)) -> 10.422535 | AA8: =IFERROR(Z8+AA7,Z8) -> 10.422535
L9: ACU | M9: 90.422535 | N9: 64.400494 | O9: =M9-M8 -> 13.098592 | Q9: low | R9: =L7 -> steam | S9: =O7/3 -> 7.2300469 | T9: =N7 -> 57.948084 | U9: =T9*cpi!$G$52+AVERAGE('Retrofit Cost vs SOC Data'!$B$9,'Retrofit Cost vs SOC Data'!$D$9,'Retrofit Cost vs SOC Data'!$F$9,'Retrofit Cost vs SOC Data'!$H$9,'Retrofit Cost vs SOC Data'!$J$9)*cpi!$G$56 -> 66.326784 | V9: =RANK(U9,$U$8:$U$49,1) -> 2 | X9: 2 | Y9: =INDEX($U$8:$U$49,MATCH(X9,$V$8:$V$49,0)) -> 66.326784 | Z9: =INDEX($S$8:$S$49,MATCH(X9,$V$8:$V$49,0)) -> 7.2300469 | AA9: =IFERROR(Z9+AA8,Z9) -> 17.652582
L10: CRU | M10: 101.83099 | N10: 65.438813 | O10: =M10-M9 -> 11.408451 | Q10: low | R10: =L8 -> SMR | S10: =O8/3 -> 8.1220657 | T10: =N8 -> 59.728059 | U10: =T10*cpi!$G$52+AVERAGE('Retrofit Cost vs SOC Data'!$B$9,'Retrofit Cost vs SOC Data'!$D$9,'Retrofit Cost vs SOC Data'!$F$9,'Retrofit Cost vs SOC Data'!$H$9,'Retrofit Cost vs SOC Data'!$J$9)*cpi!$G$56 -> 68.05306 | V10: =RANK(U10,$U$8:$U$49,1) -> 3 | X10: 3 | Y10: =INDEX($U$8:$U$49,MATCH(X10,$V$8:$V$49,0)) -> 68.05306 | Z10: =INDEX($S$8:$S$49,MATCH(X10,$V$8:$V$49,0)) -> 8.1220657 | AA10: =IFERROR(Z10+AA9,Z10) -> 25.774648
L11: HCU | M11: 106.05634 | N11: 67.737948 | O11: =M11-M10 -> 4.2253521 | Q11: low | R11: =L9 -> ACU | S11: =O9/3 -> 4.3661972 | T11: =N9 -> 64.400494 | U11: =T11*cpi!$G$52+AVERAGE('Retrofit Cost vs SOC Data'!$B$9,'Retrofit Cost vs SOC Data'!$D$9,'Retrofit Cost vs SOC Data'!$F$9,'Retrofit Cost vs SOC Data'!$H$9,'Retrofit Cost vs SOC Data'!$J$9)*cpi!$G$56 -> 72.584534 | V11: =RANK(U11,$U$8:$U$49,1) -> 4 | X11: 4 | Y11: =INDEX($U$8:$U$49,MATCH(X11,$V$8:$V$49,0)) -> 72.584534 | Z11: =INDEX($S$8:$S$49,MATCH(X11,$V$8:$V$49,0)) -> 4.3661972 | AA11: =IFERROR(Z11+AA10,Z11) -> 30.140845
L12: CKU | M12: 110.28169 | N12: 70.556242 | O12: =M12-M11 -> 4.2253521 | Q12: low | R12: =L10 -> CRU | S12: =O10/3 -> 3.8028169 | T12: =N10 -> 65.438813 | U12: =T12*cpi!$G$52+AVERAGE('Retrofit Cost vs SOC Data'!$B$9,'Retrofit Cost vs SOC Data'!$D$9,'Retrofit Cost vs SOC Data'!$F$9,'Retrofit Cost vs SOC Data'!$H$9,'Retrofit Cost vs SOC Data'!$J$9)*cpi!$G$56 -> 73.591529 | V12: =RANK(U12,$U$8:$U$49,1) -> 5 | X12: 5 | Y12: =INDEX($U$8:$U$49,MATCH(X12,$V$8:$V$49,0)) -> 73.591529 | Z12: =INDEX($S$8:$S$49,MATCH(X12,$V$8:$V$49,0)) -> 3.8028169 | AA12: =IFERROR(Z12+AA11,Z12) -> 33.943662
L13: VCU | M13: 114.22535 | N13: 73.300371 | O13: =M13-M12 -> 3.943662 | Q13: low | R13: =L11 -> HCU | S13: =O11/3 -> 1.4084507 | T13: =N11 -> 67.737948 | U13: =T13*cpi!$G$52+AVERAGE('Retrofit Cost vs SOC Data'!$B$9,'Retrofit Cost vs SOC Data'!$D$9,'Retrofit Cost vs SOC Data'!$F$9,'Retrofit Cost vs SOC Data'!$H$9,'Retrofit Cost vs SOC Data'!$J$9)*cpi!$G$56 -> 75.821302 | V13: =RANK(U13,$U$8:$U$49,1) -> 6 | X13: 6 | Y13: =INDEX($U$8:$U$49,MATCH(X13,$V$8:$V$49,0)) -> 75.821302 | Z13: =INDEX($S$8:$S$49,MATCH(X13,$V$8:$V$49,0)) -> 1.4084507 | AA13: =IFERROR(Z13+AA12,Z13) -> 35.352113
L14: CTU | M14: 115.6338 | N14: 78.862794 | O14: =M14-M13 -> 1.4084507 | Q14: low | R14: =L12 -> CKU | S14: =O12/3 -> 1.4084507 | T14: =N12 -> 70.556242 | U14: =T14*cpi!$G$52+AVERAGE('Retrofit Cost vs SOC Data'!$B$9,'Retrofit Cost vs SOC Data'!$D$9,'Retrofit Cost vs SOC Data'!$F$9,'Retrofit Cost vs SOC Data'!$H$9,'Retrofit Cost vs SOC Data'!$J$9)*cpi!$G$56 -> 78.554572 | V14: =RANK(U14,$U$8:$U$49,1) -> 8 | X14: 7 | Y14: =INDEX($U$8:$U$49,MATCH(X14,$V$8:$V$49,0)) -> 78.454969 | Z14: =INDEX($S$8:$S$49,MATCH(X14,$V$8:$V$49,0)) -> 10.438806 | AA14: =IFERROR(Z14+AA13,Z14) -> 45.790918
L15: GTU | M15: 117.88732 | N15: 81.681088 | O15: =M15-M14 -> 2.2535211 | Q15: low | R15: =L13 -> VCU | S15: =O13/3 -> 1.314554 | T15: =N13 -> 73.300371 | U15: =T15*cpi!$G$52+AVERAGE('Retrofit Cost vs SOC Data'!$B$9,'Retrofit Cost vs SOC Data'!$D$9,'Retrofit Cost vs SOC Data'!$F$9,'Retrofit Cost vs SOC Data'!$H$9,'Retrofit Cost vs SOC Data'!$J$9)*cpi!$G$56 -> 81.215914 | V15: =RANK(U15,$U$8:$U$49,1) -> 9 | X15: 8 | Y15: =INDEX($U$8:$U$49,MATCH(X15,$V$8:$V$49,0)) -> 78.554572 | Z15: =INDEX($S$8:$S$49,MATCH(X15,$V$8:$V$49,0)) -> 1.4084507 | AA15: =IFERROR(Z15+AA14,Z15) -> 47.199369
L16: NTU | M16: 121.69014 | N16: 82.051916 | O16: =M16-M15 -> 3.8028169 | Q16: low | R16: =L14 -> CTU | S16: =O14/3 -> 0.46948357 | T16: =N14 -> 78.862794 | U16: =T16*cpi!$G$52+AVERAGE('Retrofit Cost vs SOC Data'!$B$9,'Retrofit Cost vs SOC Data'!$D$9,'Retrofit Cost vs SOC Data'!$F$9,'Retrofit Cost vs SOC Data'!$H$9,'Retrofit Cost vs SOC Data'!$J$9)*cpi!$G$56 -> 86.610526 | V16: =RANK(U16,$U$8:$U$49,1) -> 11 | X16: 9 | Y16: =INDEX($U$8:$U$49,MATCH(X16,$V$8:$V$49,0)) -> 81.215914 | Z16: =INDEX($S$8:$S$49,MATCH(X16,$V$8:$V$49,0)) -> 1.314554 | AA16: =IFERROR(Z16+AA15,Z16) -> 48.513923
L17: KTU | M17: 122.8169 | N17: 90.061805 | O17: =M17-M16 -> 1.1267606 | Q17: low | R17: =L15 -> GTU | S17: =O15/3 -> 0.75117371 | T17: =N15 -> 81.681088 | U17: =T17*cpi!$G$52+AVERAGE('Retrofit Cost vs SOC Data'!$B$9,'Retrofit Cost vs SOC Data'!$D$9,'Retrofit Cost vs SOC Data'!$F$9,'Retrofit Cost vs SOC Data'!$H$9,'Retrofit Cost vs SOC Data'!$J$9)*cpi!$G$56 -> 89.343796 | V17: =RANK(U17,$U$8:$U$49,1) -> 12 | X17: 10 | Y17: =INDEX($U$8:$U$49,MATCH(X17,$V$8:$V$49,0)) -> 84.507484 | Z17: =INDEX($S$8:$S$49,MATCH(X17,$V$8:$V$49,0)) -> 8.0983724 | AA17: =IFERROR(Z17+AA16,Z17) -> 56.612295
L18: DTU | M18: 125.35211 | N18: 90.210136 | O18: =M18-M17 -> 2.5352113 | Q18: low | R18: =L16 -> NTU | S18: =O16/3 -> 1.2676056 | T18: =N16 -> 82.051916 | U18: =T18*cpi!$G$52+AVERAGE('Retrofit Cost vs SOC Data'!$B$9,'Retrofit Cost vs SOC Data'!$D$9,'Retrofit Cost vs SOC Data'!$F$9,'Retrofit Cost vs SOC Data'!$H$9,'Retrofit Cost vs SOC Data'!$J$9)*cpi!$G$56 -> 89.703437 | V18: =RANK(U18,$U$8:$U$49,1) -> 13 | X18: 11 | Y18: =INDEX($U$8:$U$49,MATCH(X18,$V$8:$V$49,0)) -> 86.610526 | Z18: =INDEX($S$8:$S$49,MATCH(X18,$V$8:$V$49,0)) -> 0.46948357 | AA18: =IFERROR(Z18+AA17,Z18) -> 57.081779
L19: ISU | M19: 126.90141 | N19: 95.846724 | O19: =M19-M18 -> 1.5492958 | Q19: low | R19: =L17 -> KTU | S19: =O17/3 -> 0.37558685 | T19: =N17 -> 90.061805 | U19: =T19*cpi!$G$52+AVERAGE('Retrofit Cost vs SOC Data'!$B$9,'Retrofit Cost vs SOC Data'!$D$9,'Retrofit Cost vs SOC Data'!$F$9,'Retrofit Cost vs SOC Data'!$H$9,'Retrofit Cost vs SOC Data'!$J$9)*cpi!$G$56 -> 97.471678 | V19: =RANK(U19,$U$8:$U$49,1) -> 15 | X19: 12 | Y19: =INDEX($U$8:$U$49,MATCH(X19,$V$8:$V$49,0)) -> 89.343796 | Z19: =INDEX($S$8:$S$49,MATCH(X19,$V$8:$V$49,0)) -> 0.75117371 | AA19: =IFERROR(Z19+AA18,Z19) -> 57.832953
Q20: low | R20: =L18 -> DTU | S20: =O18/3 -> 0.84507042 | T20: =N18 -> 90.210136 | U20: =T20*cpi!$G$52+AVERAGE('Retrofit Cost vs SOC Data'!$B$9,'Retrofit Cost vs SOC Data'!$D$9,'Retrofit Cost vs SOC Data'!$F$9,'Retrofit Cost vs SOC Data'!$H$9,'Retrofit Cost vs SOC Data'!$J$9)*cpi!$G$56 -> 97.615534 | V20: =RANK(U20,$U$8:$U$49,1) -> 16 | X20: 13 | Y20: =INDEX($U$8:$U$49,MATCH(X20,$V$8:$V$49,0)) -> 89.703437 | Z20: =INDEX($S$8:$S$49,MATCH(X20,$V$8:$V$49,0)) -> 1.2676056 | AA20: =IFERROR(Z20+AA19,Z20) -> 59.100558
P21: =SUM(S36:S49) -> 42.287048 | Q21: low | R21: =L19 -> ISU | S21: =O19/3 -> 0.51643192 | T21: =N19 -> 95.846724 | U21: =T21*cpi!$G$52+AVERAGE('Retrofit Cost vs SOC Data'!$B$9,'Retrofit Cost vs SOC Data'!$D$9,'Retrofit Cost vs SOC Data'!$F$9,'Retrofit Cost vs SOC Data'!$H$9,'Retrofit Cost vs SOC Data'!$J$9)*cpi!$G$56 -> 103.08207 | V21: =RANK(U21,$U$8:$U$49,1) -> 18 | X21: 14 | Y21: =INDEX($U$8:$U$49,MATCH(X21,$V$8:$V$49,0)) -> 94.754988 | Z21: =INDEX($S$8:$S$49,MATCH(X21,$V$8:$V$49,0)) -> 10.455076 | AA21: =IFERROR(Z21+AA20,Z21) -> 69.555634
M22: x | N22: y | Q22: average | R22: =L6 -> CCU | S22: =AVERAGEIF($L$6:$L$36,R22,$O$6:$O$36)/3 -> 10.438806 | T22: =AVERAGEIF($L$6:$L$36,R22,$N$6:$N$36) -> 70.453542 | U22: =T22*cpi!$G$52+AVERAGE('Retrofit Cost vs SOC Data'!$B$9,'Retrofit Cost vs SOC Data'!$D$9,'Retrofit Cost vs SOC Data'!$F$9,'Retrofit Cost vs SOC Data'!$H$9,'Retrofit Cost vs SOC Data'!$J$9)*cpi!$G$56 -> 78.454969 | V22: =RANK(U22,$U$8:$U$49,1) -> 7 | X22: 15 | Y22: =INDEX($U$8:$U$49,MATCH(X22,$V$8:$V$49,0)) -> 97.471678 | Z22: =INDEX($S$8:$S$49,MATCH(X22,$V$8:$V$49,0)) -> 0.37558685 | AA22: =IFERROR(Z22+AA21,Z22) -> 69.931221
L23: CCU | M23: 31.365228 | N23: 87.260606 | O23: =M23 -> 31.365228 | Q23: average | R23: =L8 -> SMR | S23: =AVERAGEIF($L$6:$L$36,R23,$O$6:$O$36)/3 -> 8.0983724 | T23: =AVERAGEIF($L$6:$L$36,R23,$N$6:$N$36) -> 76.694333 | U23: =T23*cpi!$G$52+AVERAGE('Retrofit Cost vs SOC Data'!$B$9,'Retrofit Cost vs SOC Data'!$D$9,'Retrofit Cost vs SOC Data'!$F$9,'Retrofit Cost vs SOC Data'!$H$9,'Retrofit Cost vs SOC Data'!$J$9)*cpi!$G$56 -> 84.507484 | V23: =RANK(U23,$U$8:$U$49,1) -> 10 | X23: 16 | Y23: =INDEX($U$8:$U$49,MATCH(X23,$V$8:$V$49,0)) -> 97.615534 | Z23: =INDEX($S$8:$S$49,MATCH(X23,$V$8:$V$49,0)) -> 0.84507042 | AA23: =IFERROR(Z23+AA22,Z23) -> 70.776291
L24: SMR | M24: 55.589265 | N24: 93.660606 | O24: =M24-M23 -> 24.224037 | Q24: average | R24: =L7 -> steam | S24: =AVERAGEIF($L$6:$L$36,R24,$O$6:$O$36)/3 -> 7.232293 | T24: =AVERAGEIF($L$6:$L$36,R24,$N$6:$N$36) -> 96.55586 | U24: =T24*cpi!$G$52+AVERAGE('Retrofit Cost vs SOC Data'!$B$9,'Retrofit Cost vs SOC Data'!$D$9,'Retrofit Cost vs SOC Data'!$F$9,'Retrofit Cost vs SOC Data'!$H$9,'Retrofit Cost vs SOC Data'!$J$9)*cpi!$G$56 -> 103.76982 | V24: =RANK(U24,$U$8:$U$49,1) -> 19 | X24: 17 | Y24: =INDEX($U$8:$U$49,MATCH(X24,$V$8:$V$49,0)) -> 100.96191 | Z24: =INDEX($S$8:$S$49,MATCH(X24,$V$8:$V$49,0)) -> 8.0746791 | AA24: =IFERROR(Z24+AA23,Z24) -> 78.85097
L25: steam | M25: 77.292882 | N25: 135.16364 | O25: =M25-M24 -> 21.703617 | Q25: average | R25: =L9 -> ACU | S25: =AVERAGEIF($L$6:$L$36,R25,$O$6:$O$36)/3 -> 4.4001348 | T25: =AVERAGEIF($L$6:$L$36,R25,$N$6:$N$36) -> 107.15176 | U25: =T25*cpi!$G$52+AVERAGE('Retrofit Cost vs SOC Data'!$B$9,'Retrofit Cost vs SOC Data'!$D$9,'Retrofit Cost vs SOC Data'!$F$9,'Retrofit Cost vs SOC Data'!$H$9,'Retrofit Cost vs SOC Data'!$J$9)*cpi!$G$56 -> 114.04606 | V25: =RANK(U25,$U$8:$U$49,1) -> 20 | X25: 18 | Y25: =INDEX($U$8:$U$49,MATCH(X25,$V$8:$V$49,0)) -> 103.08207 | Z25: =INDEX($S$8:$S$49,MATCH(X25,$V$8:$V$49,0)) -> 0.51643192 | AA25: =IFERROR(Z25+AA24,Z25) -> 79.367402
L26: ACU | M26: 90.595099 | N26: 149.90303 | O26: =M26-M25 -> 13.302217 | Q26: average | R26: =L10 -> CRU | S26: =AVERAGEIF($L$6:$L$36,R26,$O$6:$O$36)/3 -> 3.8150607 | T26: =AVERAGEIF($L$6:$L$36,R26,$N$6:$N$36) -> 108.83456 | U26: =T26*cpi!$G$52+AVERAGE('Retrofit Cost vs SOC Data'!$B$9,'Retrofit Cost vs SOC Data'!$D$9,'Retrofit Cost vs SOC Data'!$F$9,'Retrofit Cost vs SOC Data'!$H$9,'Retrofit Cost vs SOC Data'!$J$9)*cpi!$G$56 -> 115.67808 | V26: =RANK(U26,$U$8:$U$49,1) -> 21 | X26: 19 | Y26: =INDEX($U$8:$U$49,MATCH(X26,$V$8:$V$49,0)) -> 103.76982 | Z26: =INDEX($S$8:$S$49,MATCH(X26,$V$8:$V$49,0)) -> 7.232293 | AA26: =IFERROR(Z26+AA25,Z26) -> 86.599695
L27: CRU | M27: 102.07701 | N27: 152.2303 | O27: =M27-M26 -> 11.481914 | Q27: average | R27: =L12 -> CKU | S27: =AVERAGEIF($L$6:$L$36,R27,$O$6:$O$36)/3 -> 1.3810048 | T27: =AVERAGEIF($L$6:$L$36,R27,$N$6:$N$36) -> 114.10842 | U27: =T27*cpi!$G$52+AVERAGE('Retrofit Cost vs SOC Data'!$B$9,'Retrofit Cost vs SOC Data'!$D$9,'Retrofit Cost vs SOC Data'!$F$9,'Retrofit Cost vs SOC Data'!$H$9,'Retrofit Cost vs SOC Data'!$J$9)*cpi!$G$56 -> 120.79284 | V27: =RANK(U27,$U$8:$U$49,1) -> 22 | X27: 20 | Y27: =INDEX($U$8:$U$49,MATCH(X27,$V$8:$V$49,0)) -> 114.04606 | Z27: =INDEX($S$8:$S$49,MATCH(X27,$V$8:$V$49,0)) -> 4.4001348 | AA27: =IFERROR(Z27+AA26,Z27) -> 90.99983
L28: CKU | M28: 106.13769 | N28: 157.66061 | O28: =M28-M27 -> 4.0606768 | Q28: average | R28: =L13 -> VCU | S28: =AVERAGEIF($L$6:$L$36,R28,$O$6:$O$36)/3 -> 1.3807309 | T28: =AVERAGEIF($L$6:$L$36,R28,$N$6:$N$36) -> 118.68049 | U28: =T28*cpi!$G$52+AVERAGE('Retrofit Cost vs SOC Data'!$B$9,'Retrofit Cost vs SOC Data'!$D$9,'Retrofit Cost vs SOC Data'!$F$9,'Retrofit Cost vs SOC Data'!$H$9,'Retrofit Cost vs SOC Data'!$J$9)*cpi!$G$56 -> 125.22698 | V28: =RANK(U28,$U$8:$U$49,1) -> 23 | X28: 21 | Y28: =INDEX($U$8:$U$49,MATCH(X28,$V$8:$V$49,0)) -> 115.67808 | Z28: =INDEX($S$8:$S$49,MATCH(X28,$V$8:$V$49,0)) -> 3.8150607 | AA28: =IFERROR(Z28+AA27,Z28) -> 94.814891
L29: VCU | M29: 110.47841 | N29: 164.06061 | O29: =M29-M28 -> 4.3407235 | Q29: average | R29: =L11 -> HCU | S29: =AVERAGEIF($L$6:$L$36,R29,$O$6:$O$36)/3 -> 1.3109931 | T29: =AVERAGEIF($L$6:$L$36,R29,$N$6:$N$36) -> 119.09928 | U29: =T29*cpi!$G$52+AVERAGE('Retrofit Cost vs SOC Data'!$B$9,'Retrofit Cost vs SOC Data'!$D$9,'Retrofit Cost vs SOC Data'!$F$9,'Retrofit Cost vs SOC Data'!$H$9,'Retrofit Cost vs SOC Data'!$J$9)*cpi!$G$56 -> 125.63313 | V29: =RANK(U29,$U$8:$U$49,1) -> 24 | X29: 22 | Y29: =INDEX($U$8:$U$49,MATCH(X29,$V$8:$V$49,0)) -> 120.79284 | Z29: =INDEX($S$8:$S$49,MATCH(X29,$V$8:$V$49,0)) -> 1.3810048 | AA29: =IFERROR(Z29+AA28,Z29) -> 96.195896
L30: HCU | M30: 114.11902 | N30: 170.46061 | O30: =M30-M29 -> 3.6406068 | Q30: average | R30: =L14 -> CTU | S30: =AVERAGEIF($L$6:$L$36,R30,$O$6:$O$36)/3 -> 0.46811401 | T30: =AVERAGEIF($L$6:$L$36,R30,$N$6:$N$36) -> 131.0617 | U30: =T30*cpi!$G$52+AVERAGE('Retrofit Cost vs SOC Data'!$B$9,'Retrofit Cost vs SOC Data'!$D$9,'Retrofit Cost vs SOC Data'!$F$9,'Retrofit Cost vs SOC Data'!$H$9,'Retrofit Cost vs SOC Data'!$J$9)*cpi!$G$56 -> 137.23466 | V30: =RANK(U30,$U$8:$U$49,1) -> 25 | X30: 23 | Y30: =INDEX($U$8:$U$49,MATCH(X30,$V$8:$V$49,0)) -> 125.22698 | Z30: =INDEX($S$8:$S$49,MATCH(X30,$V$8:$V$49,0)) -> 1.3807309 | AA30: =IFERROR(Z30+AA29,Z30) -> 97.576627
L31: CTU | M31: 115.51925 | N31: 183.26061 | O31: =M31-M30 -> 1.4002334 | Q31: average | R31: =L15 -> GTU | S31: =AVERAGEIF($L$6:$L$36,R31,$O$6:$O$36)/3 -> 0.79565687 | T31: =AVERAGEIF($L$6:$L$36,R31,$N$6:$N$36) -> 135.86479 | U31: =T31*cpi!$G$52+AVERAGE('Retrofit Cost vs SOC Data'!$B$9,'Retrofit Cost vs SOC Data'!$D$9,'Retrofit Cost vs SOC Data'!$F$9,'Retrofit Cost vs SOC Data'!$H$9,'Retrofit Cost vs SOC Data'!$J$9)*cpi!$G$56 -> 141.89285 | V31: =RANK(U31,$U$8:$U$49,1) -> 27 | X31: 24 | Y31: =INDEX($U$8:$U$49,MATCH(X31,$V$8:$V$49,0)) -> 125.63313 | Z31: =INDEX($S$8:$S$49,MATCH(X31,$V$8:$V$49,0)) -> 1.3109931 | AA31: =IFERROR(Z31+AA30,Z31) -> 98.88762
L32: GTU | M32: 118.03967 | N32: 190.04848 | O32: =M32-M31 -> 2.5204201 | Q32: average | R32: =L16 -> NTU | S32: =AVERAGEIF($L$6:$L$36,R32,$O$6:$O$36)/3 -> 1.2405706 | T32: =AVERAGEIF($L$6:$L$36,R32,$N$6:$N$36) -> 136.34111 | U32: =T32*cpi!$G$52+AVERAGE('Retrofit Cost vs SOC Data'!$B$9,'Retrofit Cost vs SOC Data'!$D$9,'Retrofit Cost vs SOC Data'!$F$9,'Retrofit Cost vs SOC Data'!$H$9,'Retrofit Cost vs SOC Data'!$J$9)*cpi!$G$56 -> 142.3548 | V32: =RANK(U32,$U$8:$U$49,1) -> 28 | X32: 25 | Y32: =INDEX($U$8:$U$49,MATCH(X32,$V$8:$V$49,0)) -> 137.23466 | Z32: =INDEX($S$8:$S$49,MATCH(X32,$V$8:$V$49,0)) -> 0.46811401 | AA32: =IFERROR(Z32+AA31,Z32) -> 99.355734
L33: NTU | M33: 121.68028 | N33: 190.6303 | O33: =M33-M32 -> 3.6406068 | Q33: average | R33: =L17 -> KTU | S33: =AVERAGEIF($L$6:$L$36,R33,$O$6:$O$36)/3 -> 0.39782843 | T33: =AVERAGEIF($L$6:$L$36,R33,$N$6:$N$36) -> 149.55818 | U33: =T33*cpi!$G$52+AVERAGE('Retrofit Cost vs SOC Data'!$B$9,'Retrofit Cost vs SOC Data'!$D$9,'Retrofit Cost vs SOC Data'!$F$9,'Retrofit Cost vs SOC Data'!$H$9,'Retrofit Cost vs SOC Data'!$J$9)*cpi!$G$56 -> 155.17312 | V33: =RANK(U33,$U$8:$U$49,1) -> 29 | X33: 26 | Y33: =INDEX($U$8:$U$49,MATCH(X33,$V$8:$V$49,0)) -> 141.21285 | Z33: =INDEX($S$8:$S$49,MATCH(X33,$V$8:$V$49,0)) -> 7.2345391 | AA33: =IFERROR(Z33+AA32,Z33) -> 106.59027
L34: KTU | M34: 122.94049 | N34: 209.05455 | O34: =M34-M33 -> 1.26021 | Q34: average | R34: =L18 -> DTU | S34: =AVERAGEIF($L$6:$L$36,R34,$O$6:$O$36)/3 -> 0.819268 | T34: =AVERAGEIF($L$6:$L$36,R34,$N$6:$N$36) -> 149.92325 | U34: =T34*cpi!$G$52+AVERAGE('Retrofit Cost vs SOC Data'!$B$9,'Retrofit Cost vs SOC Data'!$D$9,'Retrofit Cost vs SOC Data'!$F$9,'Retrofit Cost vs SOC Data'!$H$9,'Retrofit Cost vs SOC Data'!$J$9)*cpi!$G$56 -> 155.52719 | V34: =RANK(U34,$U$8:$U$49,1) -> 31 | X34: 27 | Y34: =INDEX($U$8:$U$49,MATCH(X34,$V$8:$V$49,0)) -> 141.89285 | Z34: =INDEX($S$8:$S$49,MATCH(X34,$V$8:$V$49,0)) -> 0.79565687 | AA34: =IFERROR(Z34+AA33,Z34) -> 107.38593
L35: DTU | M35: 125.32089 | N35: 209.63636 | O35: =M35-M34 -> 2.3803967 | Q35: average | R35: =L19 -> ISU | S35: =AVERAGEIF($L$6:$L$36,R35,$O$6:$O$36)/3 -> 0.51492541 | T35: =AVERAGEIF($L$6:$L$36,R35,$N$6:$N$36) -> 159.23851 | U35: =T35*cpi!$G$52+AVERAGE('Retrofit Cost vs SOC Data'!$B$9,'Retrofit Cost vs SOC Data'!$D$9,'Retrofit Cost vs SOC Data'!$F$9,'Retrofit Cost vs SOC Data'!$H$9,'Retrofit Cost vs SOC Data'!$J$9)*cpi!$G$56 -> 164.56142 | V35: =RANK(U35,$U$8:$U$49,1) -> 34 | X35: 28 | Y35: =INDEX($U$8:$U$49,MATCH(X35,$V$8:$V$49,0)) -> 142.3548 | Z35: =INDEX($S$8:$S$49,MATCH(X35,$V$8:$V$49,0)) -> 1.2405706 | AA35: =IFERROR(Z35+AA34,Z35) -> 108.6265
L36: ISU | M36: 126.86114 | N36: 222.6303 | O36: =M36-M35 -> 1.5402567 | Q36: high | R36: =L23 -> CCU | S36: =O23/3 -> 10.455076 | T36: =N23 -> 87.260606 | U36: =T36*cpi!$G$52+AVERAGE('Retrofit Cost vs SOC Data'!$B$9,'Retrofit Cost vs SOC Data'!$D$9,'Retrofit Cost vs SOC Data'!$F$9,'Retrofit Cost vs SOC Data'!$H$9,'Retrofit Cost vs SOC Data'!$J$9)*cpi!$G$56 -> 94.754988 | V36: =RANK(U36,$U$8:$U$49,1) -> 14 | X36: 29 | Y36: =INDEX($U$8:$U$49,MATCH(X36,$V$8:$V$49,0)) -> 155.17312 | Z36: =INDEX($S$8:$S$49,MATCH(X36,$V$8:$V$49,0)) -> 0.39782843 | AA36: =IFERROR(Z36+AA35,Z36) -> 109.02433
Q37: high | R37: =L24 -> SMR | S37: =O24/3 -> 8.0746791 | T37: =N24 -> 93.660606 | U37: =T37*cpi!$G$52+AVERAGE('Retrofit Cost vs SOC Data'!$B$9,'Retrofit Cost vs SOC Data'!$D$9,'Retrofit Cost vs SOC Data'!$F$9,'Retrofit Cost vs SOC Data'!$H$9,'Retrofit Cost vs SOC Data'!$J$9)*cpi!$G$56 -> 100.96191 | V37: =RANK(U37,$U$8:$U$49,1) -> 17 | X37: 30 | Y37: =INDEX($U$8:$U$49,MATCH(X37,$V$8:$V$49,0)) -> 155.50758 | Z37: =INDEX($S$8:$S$49,MATCH(X37,$V$8:$V$49,0)) -> 4.4340723 | AA37: =IFERROR(Z37+AA36,Z37) -> 113.4584
Q38: high | R38: =L25 -> steam | S38: =O25/3 -> 7.2345391 | T38: =N25 -> 135.16364 | U38: =T38*cpi!$G$52+AVERAGE('Retrofit Cost vs SOC Data'!$B$9,'Retrofit Cost vs SOC Data'!$D$9,'Retrofit Cost vs SOC Data'!$F$9,'Retrofit Cost vs SOC Data'!$H$9,'Retrofit Cost vs SOC Data'!$J$9)*cpi!$G$56 -> 141.21285 | V38: =RANK(U38,$U$8:$U$49,1) -> 26 | X38: 31 | Y38: =INDEX($U$8:$U$49,MATCH(X38,$V$8:$V$49,0)) -> 155.52719 | Z38: =INDEX($S$8:$S$49,MATCH(X38,$V$8:$V$49,0)) -> 0.819268 | AA38: =IFERROR(Z38+AA37,Z38) -> 114.27767
Q39: high | R39: =L26 -> ACU | S39: =O26/3 -> 4.4340723 | T39: =N26 -> 149.90303 | U39: =T39*cpi!$G$52+AVERAGE('Retrofit Cost vs SOC Data'!$B$9,'Retrofit Cost vs SOC Data'!$D$9,'Retrofit Cost vs SOC Data'!$F$9,'Retrofit Cost vs SOC Data'!$H$9,'Retrofit Cost vs SOC Data'!$J$9)*cpi!$G$56 -> 155.50758 | V39: =RANK(U39,$U$8:$U$49,1) -> 30 | X39: 32 | Y39: =INDEX($U$8:$U$49,MATCH(X39,$V$8:$V$49,0)) -> 157.76464 | Z39: =INDEX($S$8:$S$49,MATCH(X39,$V$8:$V$49,0)) -> 3.8273046 | AA39: =IFERROR(Z39+AA38,Z39) -> 118.10497
Q40: high | R40: =L27 -> CRU | S40: =O27/3 -> 3.8273046 | T40: =N27 -> 152.2303 | U40: =T40*cpi!$G$52+AVERAGE('Retrofit Cost vs SOC Data'!$B$9,'Retrofit Cost vs SOC Data'!$D$9,'Retrofit Cost vs SOC Data'!$F$9,'Retrofit Cost vs SOC Data'!$H$9,'Retrofit Cost vs SOC Data'!$J$9)*cpi!$G$56 -> 157.76464 | V40: =RANK(U40,$U$8:$U$49,1) -> 32 | X40: 33 | Y40: =INDEX($U$8:$U$49,MATCH(X40,$V$8:$V$49,0)) -> 163.03112 | Z40: =INDEX($S$8:$S$49,MATCH(X40,$V$8:$V$49,0)) -> 1.3535589 | AA40: =IFERROR(Z40+AA39,Z40) -> 119.45853
Q41: high | R41: =L28 -> CKU | S41: =O28/3 -> 1.3535589 | T41: =N28 -> 157.66061 | U41: =T41*cpi!$G$52+AVERAGE('Retrofit Cost vs SOC Data'!$B$9,'Retrofit Cost vs SOC Data'!$D$9,'Retrofit Cost vs SOC Data'!$F$9,'Retrofit Cost vs SOC Data'!$H$9,'Retrofit Cost vs SOC Data'!$J$9)*cpi!$G$56 -> 163.03112 | V41: =RANK(U41,$U$8:$U$49,1) -> 33 | X41: 34 | Y41: =INDEX($U$8:$U$49,MATCH(X41,$V$8:$V$49,0)) -> 164.56142 | Z41: =INDEX($S$8:$S$49,MATCH(X41,$V$8:$V$49,0)) -> 0.51492541 | AA41: =IFERROR(Z41+AA40,Z41) -> 119.97346
Q42: high | R42: =L29 -> VCU | S42: =O29/3 -> 1.4469078 | T42: =N29 -> 164.06061 | U42: =T42*cpi!$G$52+AVERAGE('Retrofit Cost vs SOC Data'!$B$9,'Retrofit Cost vs SOC Data'!$D$9,'Retrofit Cost vs SOC Data'!$F$9,'Retrofit Cost vs SOC Data'!$H$9,'Retrofit Cost vs SOC Data'!$J$9)*cpi!$G$56 -> 169.23804 | V42: =RANK(U42,$U$8:$U$49,1) -> 35 | X42: 35 | Y42: =INDEX($U$8:$U$49,MATCH(X42,$V$8:$V$49,0)) -> 169.23804 | Z42: =INDEX($S$8:$S$49,MATCH(X42,$V$8:$V$49,0)) -> 1.4469078 | AA42: =IFERROR(Z42+AA41,Z42) -> 121.42037
Q43: high | R43: =L30 -> HCU | S43: =O30/3 -> 1.2135356 | T43: =N30 -> 170.46061 | U43: =T43*cpi!$G$52+AVERAGE('Retrofit Cost vs SOC Data'!$B$9,'Retrofit Cost vs SOC Data'!$D$9,'Retrofit Cost vs SOC Data'!$F$9,'Retrofit Cost vs SOC Data'!$H$9,'Retrofit Cost vs SOC Data'!$J$9)*cpi!$G$56 -> 175.44496 | V43: =RANK(U43,$U$8:$U$49,1) -> 36 | X43: 36 | Y43: =INDEX($U$8:$U$49,MATCH(X43,$V$8:$V$49,0)) -> 175.44496 | Z43: =INDEX($S$8:$S$49,MATCH(X43,$V$8:$V$49,0)) -> 1.2135356 | AA43: =IFERROR(Z43+AA42,Z43) -> 122.6339
Q44: high | R44: =L31 -> CTU | S44: =O31/3 -> 0.46674446 | T44: =N31 -> 183.26061 | U44: =T44*cpi!$G$52+AVERAGE('Retrofit Cost vs SOC Data'!$B$9,'Retrofit Cost vs SOC Data'!$D$9,'Retrofit Cost vs SOC Data'!$F$9,'Retrofit Cost vs SOC Data'!$H$9,'Retrofit Cost vs SOC Data'!$J$9)*cpi!$G$56 -> 187.8588 | V44: =RANK(U44,$U$8:$U$49,1) -> 37 | X44: 37 | Y44: =INDEX($U$8:$U$49,MATCH(X44,$V$8:$V$49,0)) -> 187.8588 | Z44: =INDEX($S$8:$S$49,MATCH(X44,$V$8:$V$49,0)) -> 0.46674446 | AA44: =IFERROR(Z44+AA43,Z44) -> 123.10065
Q45: high | R45: =L32 -> GTU | S45: =O32/3 -> 0.84014002 | T45: =N32 -> 190.04848 | U45: =T45*cpi!$G$52+AVERAGE('Retrofit Cost vs SOC Data'!$B$9,'Retrofit Cost vs SOC Data'!$D$9,'Retrofit Cost vs SOC Data'!$F$9,'Retrofit Cost vs SOC Data'!$H$9,'Retrofit Cost vs SOC Data'!$J$9)*cpi!$G$56 -> 194.4419 | V45: =RANK(U45,$U$8:$U$49,1) -> 38 | X45: 38 | Y45: =INDEX($U$8:$U$49,MATCH(X45,$V$8:$V$49,0)) -> 194.4419 | Z45: =INDEX($S$8:$S$49,MATCH(X45,$V$8:$V$49,0)) -> 0.84014002 | AA45: =IFERROR(Z45+AA44,Z45) -> 123.94079
Q46: high | R46: =L33 -> NTU | S46: =O33/3 -> 1.2135356 | T46: =N33 -> 190.6303 | U46: =T46*cpi!$G$52+AVERAGE('Retrofit Cost vs SOC Data'!$B$9,'Retrofit Cost vs SOC Data'!$D$9,'Retrofit Cost vs SOC Data'!$F$9,'Retrofit Cost vs SOC Data'!$H$9,'Retrofit Cost vs SOC Data'!$J$9)*cpi!$G$56 -> 195.00616 | V46: =RANK(U46,$U$8:$U$49,1) -> 39 | X46: 39 | Y46: =INDEX($U$8:$U$49,MATCH(X46,$V$8:$V$49,0)) -> 195.00616 | Z46: =INDEX($S$8:$S$49,MATCH(X46,$V$8:$V$49,0)) -> 1.2135356 | AA46: =IFERROR(Z46+AA45,Z46) -> 125.15432
Q47: high | R47: =L34 -> KTU | S47: =O34/3 -> 0.42007001 | T47: =N34 -> 209.05455 | U47: =T47*cpi!$G$52+AVERAGE('Retrofit Cost vs SOC Data'!$B$9,'Retrofit Cost vs SOC Data'!$D$9,'Retrofit Cost vs SOC Data'!$F$9,'Retrofit Cost vs SOC Data'!$H$9,'Retrofit Cost vs SOC Data'!$J$9)*cpi!$G$56 -> 212.87457 | V47: =RANK(U47,$U$8:$U$49,1) -> 40 | X47: 40 | Y47: =INDEX($U$8:$U$49,MATCH(X47,$V$8:$V$49,0)) -> 212.87457 | Z47: =INDEX($S$8:$S$49,MATCH(X47,$V$8:$V$49,0)) -> 0.42007001 | AA47: =IFERROR(Z47+AA46,Z47) -> 125.57439
Q48: high | R48: =L35 -> DTU | S48: =O35/3 -> 0.79346558 | T48: =N35 -> 209.63636 | U48: =T48*cpi!$G$52+AVERAGE('Retrofit Cost vs SOC Data'!$B$9,'Retrofit Cost vs SOC Data'!$D$9,'Retrofit Cost vs SOC Data'!$F$9,'Retrofit Cost vs SOC Data'!$H$9,'Retrofit Cost vs SOC Data'!$J$9)*cpi!$G$56 -> 213.43884 | V48: =RANK(U48,$U$8:$U$49,1) -> 41 | X48: 41 | Y48: =INDEX($U$8:$U$49,MATCH(X48,$V$8:$V$49,0)) -> 213.43884 | Z48: =INDEX($S$8:$S$49,MATCH(X48,$V$8:$V$49,0)) -> 0.79346558 | AA48: =IFERROR(Z48+AA47,Z48) -> 126.36786
Q49: high | R49: =L36 -> ISU | S49: =O36/3 -> 0.5134189 | T49: =N36 -> 222.6303 | U49: =T49*cpi!$G$52+AVERAGE('Retrofit Cost vs SOC Data'!$B$9,'Retrofit Cost vs SOC Data'!$D$9,'Retrofit Cost vs SOC Data'!$F$9,'Retrofit Cost vs SOC Data'!$H$9,'Retrofit Cost vs SOC Data'!$J$9)*cpi!$G$56 -> 226.04077 | V49: =RANK(U49,$U$8:$U$49,1) -> 42 | X49: 42 | Y49: =INDEX($U$8:$U$49,MATCH(X49,$V$8:$V$49,0)) -> 226.04077 | Z49: =INDEX($S$8:$S$49,MATCH(X49,$V$8:$V$49,0)) -> 0.5134189 | AA49: =IFERROR(Z49+AA48,Z49) -> 126.88128

Sheet Other
A1: Costs from ccs/CC
A2: Low Estimates
A4: Facility Type | B4: Natural Gas Processing | C4: Ethanol Production | D4: Ammonia Production | E4: Hydrogen Production | F4: Cement Plant | G4: Refinery Fluidized Catalytic Converter | H4: Iron and Steel Plant | I4: Industrial Furnace
A5: Capacity (tonne / year) | B5: 276216 | C5: 401775 | D5: 458000 | E5: 400000 | F5: 990000 | G5: 440000 | H5: 3910384 | I5: 259016
A6: Total CapEx (US $ / annual tonne) | B6: 16.5 | C6: 21.48 | D6: 24.48 | E6: 58.91 | F6: 148.05 | G6: 135.91 | H6: 805.15 | I6: 91.77
A7: Electricity usage (MWh / tonne) | B7: 0.1 | C7: 0.12 | D7: 0.1 | E7: 0.18 | F7: 0.16 | G7: 0.14 | H7: 0.16 | I7: 0.16 | J7: 75 | K7: $/MWh (assumed industrial elec cost)
A8: Gas usage (MWh / tonne) | B8: 0 | C8: 0 | D8: 0 | E8: 2.55 | F8: 2.55 | G8: 2.55 | H8: 2.55 | I8: 2.6 | J8: =5*M8*M9 -> 16.440077 | K8: $/MWh | L8: tcf to therm | M8: =1/10.38 -> 0.096339114
A9: OpEx, Non-energy, annual (% CapEx) | B9: 0.06 | C9: 0.07 | D9: 0.05 | E9: 0.05 | F9: 0.07 | G9: 0.04 | H9: 0.05 | I9: 0.04 | L9: therm to MWh | M9: 34.1296
A10: Tax rate (%) | B10: 0.21 | C10: 0.21 | D10: 0.21 | E10: 0.21 | F10: 0.21 | G10: 0.21 | H10: 0.21 | I10: 0.21
A12: High Estimates
A14: Facility Type | B14: =B4 -> Natural Gas Processing | C14: =C4 -> Ethanol Production | D14: =D4 -> Ammonia Production | E14: =E4 -> Hydrogen Production | F14: =F4 -> Cement Plant | G14: =G4 -> Refinery Fluidized Catalytic Converter | H14: =H4 -> Iron and Steel Plant | I14: =I4 -> Industrial Furnace
A15: Capacity (tonne / year) | B15: =B5 -> 276216 | C15: =C5 -> 401775 | D15: =D5 -> 458000 | E15: =E5 -> 400000 | F15: =F5 -> 990000 | G15: =G5 -> 440000 | H15: =H5 -> 3910384 | I15: =I5 -> 259016
A16: Total CapEx (US $ / annual tonne) | B16: 27.5 | C16: 38.5 | D16: 40.81 | E16: 98.18 | F16: 246.75 | G16: 226.52 | H16: 343.17 | I16: 152.94
A17: Electricity usage (MWh / tonne) | B17: =B7 -> 0.1 | C17: =C7 -> 0.12 | D17: =D7 -> 0.1 | E17: =E7 -> 0.18 | F17: =F7 -> 0.16 | G17: =G7 -> 0.14 | H17: =H7 -> 0.16 | I17: =I7 -> 0.16
A18: Gas usage (MWh / tonne) | B18: =B8 -> 0 | C18: =C8 -> 0 | D18: =D8 -> 0 | E18: =E8 -> 2.55 | F18: =F8 -> 2.55 | G18: =G8 -> 2.55 | H18: =H8 -> 2.55 | I18: =I8 -> 2.6
A19: OpEx, Non-energy, annual (% CapEx) | B19: =B9 -> 0.06 | C19: =C9 -> 0.07 | D19: =D9 -> 0.05 | E19: =E9 -> 0.05 | F19: =F9 -> 0.07 | G19: =G9 -> 0.04 | H19: =H9 -> 0.05 | I19: =I9 -> 0.04
A20: Tax rate (%) | B20: =B10 -> 0.21 | C20: =C10 -> 0.21 | D20: =D10 -> 0.21 | E20: =E10 -> 0.21 | F20: =F10 -> 0.21 | G20: =G10 -> 0.21 | H20: =H10 -> 0.21 | I20: =I10 -> 0.21
A22: Averages
B23: energy pipelines and gas processing 352T353 | C23: chemicals 20 | F23: cement and other nonmetallic minerals 239 | G23: refined petroleum and coke 19 | H23: iron and steel 241
B24: =B4 -> Natural Gas Processing | C24: =C4 -> Ethanol Production | D24: =D4 -> Ammonia Production | E24: =E4 -> Hydrogen Production | F24: =F4 -> Cement Plant | G24: =G4 -> Refinery Fluidized Catalytic Converter | H24: =H4 -> Iron and Steel Plant | I24: =I4 -> Industrial Furnace | J24: add in t&s, energy costs
A25: CapEx ($ / annual tonne) | B25: =AVERAGE(B6,B16)*10^6/B15*(1+B20) -> 96.373852 | C25: =AVERAGE(C6,C16)*10^6/C15*(1+C20) -> 90.31896 | D25: =AVERAGE(D6,D16)*10^6/D15*(1+D20) -> 86.245524 | E25: =AVERAGE(E6,E16)*10^6/E15*(1+E20) -> 237.59862 | F25: =AVERAGE(F6,F16)*10^6/F15*(1+F20) -> 241.26667 | G25: =AVERAGE(G6,G16)*10^6/G15*(1+G20) -> 498.34125 | H25: =AVERAGE(H6,H16)*10^6/H15*(1+H20) -> 177.66378 | I25: =AVERAGE(I6,I16)*10^6/I15*(1+I20) -> 571.58457 | J25: =I25+AVERAGE('Retrofit Cost vs SOC Data'!B9,'Retrofit Cost vs SOC Data'!D9,'Retrofit Cost vs SOC Data'!F9,'Retrofit Cost vs SOC Data'!H9,'Retrofit Cost vs SOC Data'!J9) -> 582.66038
A26: Electricity usage (BTU / tonne) | B26: =AVERAGE(B7,B17)*$A$37 -> 341214.1 | C26: =AVERAGE(C7,C17)*$A$37 -> 409456.92 | D26: =AVERAGE(D7,D17)*$A$37 -> 341214.1 | E26: =AVERAGE(E7,E17)*$A$37 -> 614185.38 | F26: =AVERAGE(F7,F17)*$A$37 -> 545942.56 | G26: =AVERAGE(G7,G17)*$A$37 -> 477699.74 | H26: =AVERAGE(H7,H17)*$A$37 -> 545942.56 | I26: =AVERAGE(I7,I17)*$A$37 -> 545942.56
A27: Gas usage (BTU / tonne) | B27: =AVERAGE(B8,B18)*$A$37 -> 0 | C27: =AVERAGE(C8,C18)*$A$37 -> 0 | D27: =AVERAGE(D8,D18)*$A$37 -> 0 | E27: =AVERAGE(E8,E18)*$A$37 -> 8700959.5 | F27: =AVERAGE(F8,F18)*$A$37 -> 8700959.5 | G27: =AVERAGE(G8,G18)*$A$37 -> 8700959.5 | H27: =AVERAGE(H8,H18)*$A$37 -> 8700959.5 | I27: =AVERAGE(I8,I18)*$A$37 -> 8871566.6
A28: OpEx, Non-energy | B28: =AVERAGE(B9,B19)*B25 -> 5.7824311 | C28: =AVERAGE(C9,C19)*C25 -> 6.3223272 | D28: =AVERAGE(D9,D19)*D25 -> 4.3122762 | E28: =AVERAGE(E9,E19)*E25 -> 11.879931 | F28: =AVERAGE(F9,F19)*F25 -> 16.888667 | G28: =AVERAGE(G9,G19)*G25 -> 19.93365 | H28: =AVERAGE(H9,H19)*H25 -> 8.883189 | I28: =AVERAGE(I9,I19)*I25 -> 22.863383
I29: =(I16-I6)*10^6/I15*(1+I20)/2 -> 142.87863 | J29: stdev
A30: *We use ethanol production as a proxy for the chemicals industry, as we expect ammonia production to be decarbonized via | J30: assuming the "low" and "high" estimates are one standard deviations from the mean
A31: hydrogen electrolysis in our BAU case.
B33: 1 | C33: 2 | D33: 3 | E33: 4 | F33: 5 | G33: 6 | H33: 7 | I33: 8 | J33: 9 | K33: 10 | L33: 11 | M33: 12 | N33: 13 | O33: 14 | P33: 15 | Q33: 16 | R33: 17 | S33: 18 | T33: 19 | U33: 20 | V33: 21 | W33: 22 | X33: 23 | Y33: 24 | Z33: 25 | AA33: 26 | AB33: 27 | AC33: 28 | AD33: 29 | AE33: 30 | AF33: 31 | AG33: 32 | AH33: 33 | AI33: 34 | AJ33: 35 | AK33: 36 | AL33: 37 | AM33: 38 | AN33: 39 | AO33: 40 | AP33: 41 | AQ33: 42 | AR33: 43 | AS33: 44 | AT33: 45 | AU33: 46 | AV33: 47 | AW33: 48 | AX33: 49 | AY33: 50 | AZ33: 51 | BA33: 52 | BB33: 53 | BC33: 54 | BD33: 55 | BE33: 56 | BF33: 57 | BG33: 58 | BH33: 59 | BI33: 60 | BJ33: 61 | BK33: 62 | BL33: 63 | BM33: 64 | BN33: 65 | BO33: 66 | BP33: 67 | BQ33: 68 | BR33: 69 | BS33: 70 | BT33: 71 | BU33: 72 | BV33: 73 | BW33: 74 | BX33: 75 | BY33: 76 | BZ33: 77 | CA33: 78 | CB33: 79 | CC33: 80 | CD33: 81 | CE33: 82 | CF33: 83 | CG33: 84 | CH33: 85 | CI33: 86 | CJ33: 87 | CK33: 88 | CL33: 89 | CM33: 90 | CN33: 91 | CO33: 92 | CP33: 93 | CQ33: 94 | CR33: 95 | CS33: 96 | CT33: 97 | CU33: 98 | CV33: 99 | CW33: 100 | CX33: 101 | CY33: 102 | CZ33: 103 | DA33: 104 | DB33: 105 | DC33: 106 | DD33: 107 | DE33: 108 | DF33: 109 | DG33: 110 | DH33: 111 | DI33: 112 | DJ33: 113 | DK33: 114 | DL33: 115 | DM33: 116 | DN33: 117 | DO33: 118 | DP33: 119 | DQ33: 120 | DR33: 121 | DS33: 122 | DT33: 123 | DU33: 124 | DV33: 125 | DW33: 126 | DX33: 127 | DY33: 128 | DZ33: 129 | EA33: 130 | EB33: 131 | EC33: 132 | ED33: 133 | EE33: 134 | EF33: 135 | EG33: 136 | EH33: 137 | EI33: 138 | EJ33: 139 | EK33: 140 | EL33: 141 | EM33: 142 | EN33: 143 | EO33: 144 | EP33: 145 | EQ33: 146 | ER33: 147 | ES33: 148 | ET33: 149 | EU33: 150 | EV33: 151 | EW33: 152 | EX33: 153 | EY33: 154 | EZ33: 155 | FA33: 156 | FB33: 157 | FC33: 158 | FD33: 159 | FE33: 160 | FF33: 161 | FG33: 162 | FH33: 163 | FI33: 164 | FJ33: 165 | FK33: 166 | FL33: 167 | FM33: 168 | FN33: 169 | FO33: 170 | FP33: 171 | FQ33: 172 | FR33: 173 | FS33: 174 | FT33: 175 | FU33: 176 | FV33: 177 | FW33: 178 | FX33: 179 | FY33: 180 | FZ33: 181 | GA33: 182 | GB33: 183 | GC33: 184 | GD33: 185 | GE33: 186 | GF33: 187 | GG33: 188 | GH33: 189 | GI33: 190 | GJ33: 191 | GK33: 192 | GL33: 193 | GM33: 194 | GN33: 195 | GO33: 196 | GP33: 197 | GQ33: 198 | GR33: 199 | GS33: 200 | GT33: 201 | GU33: 202 | GV33: 203 | GW33: 204 | GX33: 205 | GY33: 206 | GZ33: 207 | HA33: 208 | HB33: 209 | HC33: 210 | HD33: 211 | HE33: 212 | HF33: 213 | HG33: 214 | HH33: 215 | HI33: 216 | HJ33: 217 | HK33: 218 | HL33: 219 | HM33: 220 | HN33: 221 | HO33: 222 | HP33: 223 | HQ33: 224 | HR33: 225 | HS33: 226 | HT33: 227 | HU33: 228 | HV33: 229 | HW33: 230 | HX33: 231 | HY33: 232 | HZ33: 233 | IA33: 234 | IB33: 235 | IC33: 236 | ID33: 237 | IE33: 238 | IF33: 239 | IG33: 240 | IH33: 241 | II33: 242 | IJ33: 243 | IK33: 244 | IL33: 245 | IM33: 246 | IN33: 247 | IO33: 248 | IP33: 249 | IQ33: 250 | IR33: 251 | IS33: 252 | IT33: 253 | IU33: 254 | IV33: 255 | IW33: 256 | IX33: 257 | IY33: 258 | IZ33: 259 | JA33: 260 | JB33: 261 | JC33: 262 | JD33: 263 | JE33: 264 | JF33: 265 | JG33: 266 | JH33: 267 | JI33: 268 | JJ33: 269 | JK33: 270 | JL33: 271 | JM33: 272 | JN33: 273 | JO33: 274 | JP33: 275 | JQ33: 276 | JR33: 277 | JS33: 278 | JT33: 279 | JU33: 280 | JV33: 281 | JW33: 282 | JX33: 283 | JY33: 284 | JZ33: 285 | KA33: 286 | KB33: 287 | KC33: 288 | KD33: 289 | KE33: 290 | KF33: 291 | KG33: 292 | KH33: 293 | KI33: 294 | KJ33: 295 | KK33: 296 | KL33: 297 | KM33: 298 | KN33: 299 | KO33: 300 | KP33: 301 | KQ33: 302 | KR33: 303 | KS33: 304 | KT33: 305 | KU33: 306 | KV33: 307 | KW33: 308 | KX33: 309 | KY33: 310 | KZ33: 311 | LA33: 312 | LB33: 313 | LC33: 314 | LD33: 315 | LE33: 316 | LF33: 317 | LG33: 318 | LH33: 319 | LI33: 320 | LJ33: 321 | LK33: 322 | LL33: 323 | LM33: 324 | LN33: 325 | LO33: 326 | LP33: 327 | LQ33: 328 | LR33: 329 | LS33: 330 | LT33: 331 | LU33: 332 | LV33: 333 | LW33: 334 | LX33: 335 | LY33: 336 | LZ33: 337 | MA33: 338 | MB33: 339 | MC33: 340 | MD33: 341 | ME33: 342 | MF33: 343 | MG33: 344 | MH33: 345 | MI33: 346 | MJ33: 347 | MK33: 348 | ML33: 349 | MM33: 350 | MN33: 351 | MO33: 352 | MP33: 353 | MQ33: 354 | MR33: 355 | MS33: 356 | MT33: 357 | MU33: 358 | MV33: 359 | MW33: 360 | MX33: 361 | MY33: 362 | MZ33: 363 | NA33: 364 | NB33: 365 | NC33: 366 | ND33: 367 | NE33: 368 | NF33: 369 | NG33: 370 | NH33: 371 | NI33: 372 | NJ33: 373 | NK33: 374 | NL33: 375 | NM33: 376 | NN33: 377 | NO33: 378 | NP33: 379 | NQ33: 380 | NR33: 381 | NS33: 382 | NT33: 383 | NU33: 384 | NV33: 385 | NW33: 386 | NX33: 387 | NY33: 388 | NZ33: 389 | OA33: 390 | OB33: 391 | OC33: 392 | OD33: 393 | OE33: 394 | OF33: 395 | OG33: 396 | OH33: 397 | OI33: 398 | OJ33: 399 | OK33: 400 | OL33: 401 | OM33: 402 | ON33: 403 | OO33: 404 | OP33: 405 | OQ33: 406 | OR33: 407 | OS33: 408 | OT33: 409 | OU33: 410 | OV33: 411 | OW33: 412 | OX33: 413 | OY33: 414 | OZ33: 415 | PA33: 416 | PB33: 417 | PC33: 418 | PD33: 419 | PE33: 420 | PF33: 421 | PG33: 422 | PH33: 423 | PI33: 424 | PJ33: 425 | PK33: 426 | PL33: 427 | PM33: 428 | PN33: 429 | PO33: 430 | PP33: 431 | PQ33: 432 | PR33: 433 | PS33: 434 | PT33: 435 | PU33: 436 | PV33: 437 | PW33: 438 | PX33: 439 | PY33: 440 | PZ33: 441 | QA33: 442 | QB33: 443 | QC33: 444 | QD33: 445 | QE33: 446 | QF33: 447 | QG33: 448 | QH33: 449 | QI33: 450 | QJ33: 451 | QK33: 452 | QL33: 453 | QM33: 454 | QN33: 455 | QO33: 456 | QP33: 457 | QQ33: 458 | QR33: 459 | QS33: 460 | QT33: 461 | QU33: 462 | QV33: 463 | QW33: 464 | QX33: 465 | QY33: 466 | QZ33: 467 | RA33: 468 | RB33: 469 | RC33: 470 | RD33: 471 | RE33: 472 | RF33: 473 | RG33: 474 | RH33: 475 | RI33: 476 | RJ33: 477 | RK33: 478 | RL33: 479 | RM33: 480 | RN33: 481 | RO33: 482 | RP33: 483 | RQ33: 484 | RR33: 485 | RS33: 486 | RT33: 487 | RU33: 488 | RV33: 489 | RW33: 490 | RX33: 491 | RY33: 492 | RZ33: 493 | SA33: 494 | SB33: 495 | SC33: 496 | SD33: 497 | SE33: 498 | SF33: 499 | SG33: 500 | SH33: 501 | SI33: 502 | SJ33: 503 | SK33: 504 | SL33: 505 | SM33: 506 | SN33: 507 | SO33: 508 | SP33: 509 | SQ33: 510 | SR33: 511 | SS33: 512 | ST33: 513 | SU33: 514 | SV33: 515 | SW33: 516 | SX33: 517 | SY33: 518 | SZ33: 519 | TA33: 520 | TB33: 521 | TC33: 522 | TD33: 523 | TE33: 524 | TF33: 525 | TG33: 526 | TH33: 527 | TI33: 528 | TJ33: 529 | TK33: 530 | TL33: 531 | TM33: 532 | TN33: 533 | TO33: 534 | TP33: 535 | TQ33: 536 | TR33: 537 | TS33: 538 | TT33: 539 | TU33: 540 | TV33: 541 | TW33: 542 | TX33: 543 | TY33: 544 | TZ33: 545 | UA33: 546 | UB33: 547 | UC33: 548 | UD33: 549 | UE33: 550 | UF33: 551 | UG33: 552 | UH33: 553 | UI33: 554 | UJ33: 555 | UK33: 556 | UL33: 557 | UM33: 558 | UN33: 559 | UO33: 560 | UP33: 561 | UQ33: 562 | UR33: 563 | US33: 564 | UT33: 565 | UU33: 566 | UV33: 567 | UW33: 568 | UX33: 569 | UY33: 570 | UZ33: 571 | VA33: 572 | VB33: 573 | VC33: 574 | VD33: 575 | VE33: 576 | VF33: 577 | VG33: 578 | VH33: 579 | VI33: 580 | VJ33: 581 | VK33: 582 | VL33: 583 | VM33: 584 | VN33: 585 | VO33: 586 | VP33: 587 | VQ33: 588 | VR33: 589 | VS33: 590 | VT33: 591 | VU33: 592 | VV33: 593 | VW33: 594 | VX33: 595 | VY33: 596 | VZ33: 597 | WA33: 598 | WB33: 599 | WC33: 600 | WD33: 601 | WE33: 602 | WF33: 603 | WG33: 604 | WH33: 605 | WI33: 606 | WJ33: 607 | WK33: 608 | WL33: 609 | WM33: 610 | WN33: 611 | WO33: 612 | WP33: 613 | WQ33: 614 | WR33: 615 | WS33: 616 | WT33: 617 | WU33: 618 | WV33: 619 | WW33: 620 | WX33: 621 | WY33: 622 | WZ33: 623 | XA33: 624 | XB33: 625 | XC33: 626 | XD33: 627 | XE33: 628 | XF33: 629 | XG33: 630 | XH33: 631 | XI33: 632 | XJ33: 633 | XK33: 634 | XL33: 635 | XM33: 636 | XN33: 637 | XO33: 638 | XP33: 639 | XQ33: 640 | XR33: 641 | XS33: 642 | XT33: 643 | XU33: 644 | XV33: 645 | XW33: 646 | XX33: 647 | XY33: 648 | XZ33: 649 | YA33: 650 | YB33: 651 | YC33: 652 | YD33: 653 | YE33: 654 | YF33: 655 | YG33: 656 | YH33: 657 | YI33: 658 | YJ33: 659 | YK33: 660 | YL33: 661 | YM33: 662 | YN33: 663 | YO33: 664 | YP33: 665 | YQ33: 666 | YR33: 667 | YS33: 668 | YT33: 669 | YU33: 670 | YV33: 671 | YW33: 672 | YX33: 673 | YY33: 674 | YZ33: 675 | ZA33: 676 | ZB33: 677 | ZC33: 678 | ZD33: 679 | ZE33: 680 | ZF33: 681 | ZG33: 682 | ZH33: 683 | ZI33: 684 | ZJ33: 685 | ZK33: 686 | ZL33: 687 | ZM33: 688 | ZN33: 689 | ZO33: 690 | ZP33: 691 | ZQ33: 692 | ZR33: 693 | ZS33: 694 | ZT33: 695 | ZU33: 696 | ZV33: 697 | ZW33: 698 | ZX33: 699 | ZY33: 700 | ZZ33: 701 | AAA33: 702 | AAB33: 703 | AAC33: 704 | AAD33: 705 | AAE33: 706 | AAF33: 707 | AAG33: 708 | AAH33: 709 | AAI33: 710 | AAJ33: 711 | AAK33: 712 | AAL33: 713 | AAM33: 714 | AAN33: 715 | AAO33: 716 | AAP33: 717 | AAQ33: 718 | AAR33: 719 | AAS33: 720 | AAT33: 721 | AAU33: 722 | AAV33: 723 | AAW33: 724 | AAX33: 725 | AAY33: 726 | AAZ33: 727 | ABA33: 728 | ABB33: 729 | ABC33: 730 | ABD33: 731 | ABE33: 732 | ABF33: 733 | ABG33: 734 | ABH33: 735 | ABI33: 736 | ABJ33: 737 | ABK33: 738 | ABL33: 739 | ABM33: 740 | ABN33: 741 | ABO33: 742 | ABP33: 743 | ABQ33: 744 | ABR33: 745 | ABS33: 746 | ABT33: 747 | ABU33: 748 | ABV33: 749 | ABW33: 750 | ABX33: 751 | ABY33: 752 | ABZ33: 753 | ACA33: 754 | ACB33: 755 | ACC33: 756 | ACD33: 757 | ACE33: 758 | ACF33: 759 | ACG33: 760 | ACH33: 761 | ACI33: 762 | ACJ33: 763 | ACK33: 764 | ACL33: 765 | ACM33: 766 | ACN33: 767 | ACO33: 768 | ACP33: 769 | ACQ33: 770 | ACR33: 771 | ACS33: 772 | ACT33: 773 | ACU33: 774 | ACV33: 775 | ACW33: 776 | ACX33: 777 | ACY33: 778 | ACZ33: 779 | ADA33: 780 | ADB33: 781 | ADC33: 782 | ADD33: 783 | ADE33: 784 | ADF33: 785 | ADG33: 786 | ADH33: 787 | ADI33: 788 | ADJ33: 789 | ADK33: 790 | ADL33: 791 | ADM33: 792 | ADN33: 793 | ADO33: 794 | ADP33: 795 | ADQ33: 796 | ADR33: 797 | ADS33: 798 | ADT33: 799 | ADU33: 800 | ADV33: 801 | ADW33: 802 | ADX33: 803 | ADY33: 804 | ADZ33: 805 | AEA33: 806 | AEB33: 807 | AEC33: 808 | AED33: 809 | AEE33: 810 | AEF33: 811 | AEG33: 812 | AEH33: 813 | AEI33: 814 | AEJ33: 815 | AEK33: 816 | AEL33: 817 | AEM33: 818 | AEN33: 819 | AEO33: 820 | AEP33: 821 | AEQ33: 822 | AER33: 823 | AES33: 824 | AET33: 825 | AEU33: 826 | AEV33: 827 | AEW33: 828 | AEX33: 829 | AEY33: 830 | AEZ33: 831 | AFA33: 832 | AFB33: 833 | AFC33: 834 | AFD33: 835 | AFE33: 836 | AFF33: 837 | AFG33: 838 | AFH33: 839 | AFI33: 840 | AFJ33: 841 | AFK33: 842 | AFL33: 843 | AFM33: 844 | AFN33: 845 | AFO33: 846 | AFP33: 847 | AFQ33: 848 | AFR33: 849 | AFS33: 850 | AFT33: 851 | AFU33: 852 | AFV33: 853 | AFW33: 854 | AFX33: 855 | AFY33: 856 | AFZ33: 857 | AGA33: 858 | AGB33: 859 | AGC33: 860 | AGD33: 861 | AGE33: 862 | AGF33: 863 | AGG33: 864 | AGH33: 865 | AGI33: 866 | AGJ33: 867 | AGK33: 868 | AGL33: 869 | AGM33: 870 | AGN33: 871 | AGO33: 872 | AGP33: 873 | AGQ33: 874 | AGR33: 875 | AGS33: 876 | AGT33: 877 | AGU33: 878 | AGV33: 879 | AGW33: 880 | AGX33: 881 | AGY33: 882 | AGZ33: 883 | AHA33: 884 | AHB33: 885 | AHC33: 886 | AHD33: 887 | AHE33: 888 | AHF33: 889 | AHG33: 890 | AHH33: 891 | AHI33: 892 | AHJ33: 893 | AHK33: 894 | AHL33: 895 | AHM33: 896 | AHN33: 897 | AHO33: 898 | AHP33: 899 | AHQ33: 900 | AHR33: 901 | AHS33: 902 | AHT33: 903 | AHU33: 904 | AHV33: 905 | AHW33: 906 | AHX33: 907 | AHY33: 908 | AHZ33: 909 | AIA33: 910 | AIB33: 911 | AIC33: 912 | AID33: 913 | AIE33: 914 | AIF33: 915 | AIG33: 916 | AIH33: 917 | AII33: 918 | AIJ33: 919 | AIK33: 920 | AIL33: 921 | AIM33: 922 | AIN33: 923 | AIO33: 924 | AIP33: 925 | AIQ33: 926 | AIR33: 927 | AIS33: 928 | AIT33: 929 | AIU33: 930 | AIV33: 931 | AIW33: 932 | AIX33: 933 | AIY33: 934 | AIZ33: 935 | AJA33: 936 | AJB33: 937 | AJC33: 938 | AJD33: 939 | AJE33: 940 | AJF33: 941 | AJG33: 942 | AJH33: 943 | AJI33: 944 | AJJ33: 945 | AJK33: 946 | AJL33: 947 | AJM33: 948 | AJN33: 949 | AJO33: 950 | AJP33: 951 | AJQ33: 952 | AJR33: 953 | AJS33: 954 | AJT33: 955 | AJU33: 956 | AJV33: 957 | AJW33: 958 | AJX33: 959 | AJY33: 960 | AJZ33: 961 | AKA33: 962 | AKB33: 963 | AKC33: 964 | AKD33: 965 | AKE33: 966 | AKF33: 967 | AKG33: 968 | AKH33: 969 | AKI33: 970 | AKJ33: 971 | AKK33: 972 | AKL33: 973 | AKM33: 974 | AKN33: 975 | AKO33: 976 | AKP33: 977 | AKQ33: 978 | AKR33: 979 | AKS33: 980 | AKT33: 981 | AKU33: 982 | AKV33: 983 | AKW33: 984 | AKX33: 985 | AKY33: 986 | AKZ33: 987 | ALA33: 988 | ALB33: 989 | ALC33: 990 | ALD33: 991 | ALE33: 992 | ALF33: 993 | ALG33: 994 | ALH33: 995 | ALI33: 996 | ALJ33: 997 | ALK33: 998 | ALL33: 999 | ALM33: 1000
B34: =_xlfn.NORM.DIST(B33,$J$25,$I$29,1) -> 2.3404821e-05 | C34: =_xlfn.NORM.DIST(C33,$I$25,$I$29,1) -> 3.3528617e-05 | D34: =_xlfn.NORM.DIST(D33,$I$25,$I$29,1) -> 3.453111e-05 | E34: =_xlfn.NORM.DIST(E33,$I$25,$I$29,1) -> 3.5561918e-05 | F34: =_xlfn.NORM.DIST(F33,$I$25,$I$29,1) -> 3.6621787e-05 | G34: =_xlfn.NORM.DIST(G33,$I$25,$I$29,1) -> 3.7711483e-05 | H34: =_xlfn.NORM.DIST(H33,$I$25,$I$29,1) -> 3.8831793e-05 | I34: =_xlfn.NORM.DIST(I33,$I$25,$I$29,1) -> 3.9983518e-05 | J34: =_xlfn.NORM.DIST(J33,$I$25,$I$29,1) -> 4.1167482e-05 | ... ALM34: =_xlfn.NORM.DIST(ALM33,$I$25,$I$29,1) -> 0.99864325
A37: 3412141 | B37: BTU per MWh

Sheet By Industry
C2: cement
B3: Share of Capacity | C3: 0 | D3: {=TRANSPOSE('Retrofit Cost vs SOC Data'!E12:E102)*MIN(1,'Retrofit Cost vs SOC Data'!D5/'BPE - US specific multipliers'!F34/1000)} -> 0.044531576 | E3: 0.072631908 | F3: 0.094124553 | G3: 0.11373608 | H3: 0.13063396 | I3: 0.15662362 | J3: 0.17509357 | K3: 0.18834775 | L3: 0.20789705 | M3: 0.22506503 | N3: 0.24196096 | O3: 0.26301483 | P3: 0.27642288 | Q3: 0.29138285 | R3: 0.30964086 | S3: 0.32309944 | T3: 0.33558657 | U3: 0.35132005 | V3: 0.37902189 | W3: 0.39115597 | X3: 0.40430496 | Y3: 0.41766725 | Z3: 0.42786322 | AA3: 0.44349093 | AB3: 0.4531661 | AC3: 0.46411341 | AD3: 0.47441527 | AE3: 0.4857275 | AF3: 0.49824933 | AG3: 0.50853538 | AH3: 0.52034384 | AI3: 0.5319317 | AJ3: 0.54502499 | AK3: 0.55665021 | AL3: 0.56838179 | AM3: 0.57731409 | AN3: 0.58724965 | AO3: 0.59592956 | AP3: 0.60593777 | AQ3: 0.61367443 | AR3: 0.62378337 | AS3: 0.63139617 | AT3: 0.63988094 | AU3: 0.6472025 | AV3: 0.65435061 | AW3: 0.68471541 | AX3: 0.69560335 | AY3: 0.70296414 | AZ3: 0.71014838 | BA3: 0.71682137 | BB3: 0.72712054 | BC3: 0.73720131 | BD3: 0.74722792 | BE3: 0.75501339 | BF3: 0.7618141 | BG3: 0.76936043 | BH3: 0.77704962 | BI3: 0.7844732 | BJ3: 0.79256781 | BK3: 0.8135841 | BL3: 0.82217938 | BM3: 0.82888668 | BN3: 0.83563098 | BO3: 0.84097175 | BP3: 0.84855377 | BQ3: 0.85610867 | BR3: 0.87273209 | BS3: 0.88125873 | BT3: 0.8867928 | BU3: 0.89155647 | BV3: 0.90732668 | BW3: 0.91248175 | BX3: 0.92518412 | BY3: 0.9306688 | BZ3: 0.93532415 | CA3: 0.94044419 | CB3: 0.94502493 | CC3: 0.9505385 | CD3: 0.9550445 | CE3: 0.96034263 | CF3: 0.97055212 | CG3: 0.97409615 | CH3: 0.97723708 | CI3: 0.98150142 | CJ3: 0.98494308 | CK3: 0.98924897 | CL3: 0.99420303 | CM3: 0.99702284 | CN3: 0.99867156 | CO3: 1 | CP3: #N/A
B4: Cost | C4: 0 | D4: {=TRANSPOSE('Retrofit Cost vs SOC Data'!D12:D102)*cpi!$G$56} -> 65.698526 | E4: 71.33658 | F4: 72.480145 | G4: 73.895318 | H4: 74.017059 | I4: 74.357261 | J4: 74.848723 | K4: 75.008467 | L4: 75.438028 | M4: 75.592287 | N4: 76.305074 | O4: 77.36981 | P4: 77.921368 | Q4: 78.375497 | R4: 78.483701 | S4: 78.984371 | T4: 79.194819 | U4: 80.888123 | V4: 80.943671 | W4: 82.167389 | X4: 82.169753 | Y4: 82.789656 | Z4: 83.097283 | AA4: 83.483747 | AB4: 84.054179 | AC4: 85.234941 | AD4: 85.348029 | AE4: 85.829135 | AF4: 85.833355 | AG4: 85.971778 | AH4: 86.20461 | AI4: 86.276607 | AJ4: 86.486335 | AK4: 86.925074 | AL4: 87.061838 | AM4: 87.512163 | AN4: 87.755394 | AO4: 88.105821 | AP4: 88.190112 | AQ4: 88.717584 | AR4: 88.891682 | AS4: 89.069772 | AT4: 90.47293 | AU4: 90.917429 | AV4: 91.038475 | AW4: 91.338956 | AX4: 92.226395 | AY4: 92.529942 | AZ4: 92.913673 | BA4: 93.014869 | BB4: 93.439013 | BC4: 93.760051 | BD4: 93.96509 | BE4: 94.287604 | BF4: 94.357625 | BG4: 95.247391 | BH4: 95.266805 | BI4: 95.330024 | BJ4: 96.250479 | BK4: 96.601801 | BL4: 97.092282 | BM4: 98.324663 | BN4: 98.808184 | BO4: 98.989825 | BP4: 99.041033 | BQ4: 99.856235 | BR4: 100.35611 | BS4: 100.86494 | BT4: 101.12656 | BU4: 101.1293 | BV4: 101.24632 | BW4: 104.68349 | BX4: 105.0925 | BY4: 106.59572 | BZ4: 106.65644 | CA4: 106.95006 | CB4: 107.13702 | CC4: 107.20217 | CD4: 107.52243 | CE4: 108.79343 | CF4: 109.30865 | CG4: 111.6864 | CH4: 113.23147 | CI4: 114.30039 | CJ4: 117.54731 | CK4: 120.12145 | CL4: 126.02793 | CM4: 126.10775 | CN4: 138.33278 | CO4: 153.96948 | CP4: #N/A
D6: NG processing
B7: Share of Capacity | C7: 0 | D7: {=TRANSPOSE('Retrofit Cost vs SOC Data'!K12:K336)*MIN(1,'Retrofit Cost vs SOC Data'!J5/'BPE - US specific multipliers'!F13/1000)} -> 0.030882023 | E7: 0.043088826 | F7: 0.054142401 | G7: 0.064477654 | H7: 0.074975307 | I7: 0.084065453 | J7: 0.089682391 | K7: 0.095210438 | L7: 0.099422755 | M7: 0.10350558 | N7: 0.10807874 | O7: 0.11251821 | P7: 0.11625267 | Q7: 0.11979143 | R7: 0.12328783 | S7: 0.127182 | T7: 0.13172624 | U7: 0.13619767 | V7: 0.13985791 | W7: 0.14322903 | X7: 0.14719681 | Y7: 0.15009952 | Z7: 0.15329613 | AA7: 0.15607037 | AB7: 0.15894547 | AC7: 0.16203129 | AD7: 0.16468255 | AE7: 0.16818409 | AF7: 0.17078711 | AG7: 0.17308704 | AH7: 0.17557246 | AI7: 0.17833672 | AJ7: 0.18063603 | AK7: 0.18277228 | AL7: 0.18490736 | AM7: 0.18736616 | AN7: 0.18948039 | AO7: 0.19133584 | AP7: 0.19320358 | AQ7: 0.19504565 | AR7: 0.19716875 | AS7: 0.19882094 | AT7: 0.20052647 | AU7: 0.20211798 | AV7: 0.20369503 | AW7: 0.20546251 | AX7: 0.20701328 | AY7: 0.20839681 | AZ7: 0.20986326 | BA7: 0.21124371 | BB7: 0.21274101 | BC7: 0.21404589 | BD7: 0.21520779 | BE7: 0.21650181 | BF7: 0.2177786 | BG7: 0.21905171 | BH7: 0.22029486 | BI7: 0.22169406 | BJ7: 0.22290773 | BK7: 0.22422947 | BL7: 0.22536816 | BM7: 0.22649824 | BN7: 0.22763126 | BO7: 0.22873888 | BP7: 0.23076418 | BQ7: 0.23194576 | BR7: 0.23299958 | BS7: 0.23416411 | BT7: 0.2352019 | BU7: 0.23621707 | BV7: 0.23712203 | BW7: 0.23809626 | BX7: 0.23905984 | BY7: 0.2400203 | BZ7: 0.24097615 | CA7: 0.24191883 | CB7: 0.24279174 | CC7: 0.24364229 | CD7: 0.24443605 | CE7: 0.2452586 | CF7: 0.24597375 | CG7: 0.24676254 | CH7: 0.24754634 | CI7: 0.24832917 | CJ7: 0.24901967 | CK7: 0.24970317 | CL7: 0.25045966 | CM7: 0.25113684 | CN7: 0.25181181 | CO7: 0.25247101 | CP7: 0.25318239 | CQ7: 0.25389176 | CR7: 0.25460027 | CS7: 0.25530504 | CT7: 0.25600325 | CU7: 0.25669674 | CV7: 0.25737984 | CW7: 0.25799259 | CX7: 0.25866995 | CY7: 0.25933389 | CZ7: 0.25998505 | DA7: 0.26062419 | DB7: 0.26122463 | DC7: 0.26184438 | DD7: 0.2624565 | DE7: 0.26305677 | DF7: 0.26365619 | DG7: 0.26425442 | DH7: 0.26485046 | DI7: 0.26542341 | DJ7: 0.26600934 | DK7: 0.26657831 | DL7: 0.2671464 | DM7: 0.26770827 | DN7: 0.26826988 | DO7: 0.26881513 | DP7: 0.26937326 | DQ7: 0.26987884 | DR7: 0.27034695 | DS7: 0.27083602 | DT7: 0.27132536 | DU7: 0.27180326 | DV7: 0.27223045 | DW7: 0.27274004 | DX7: 0.27315875 | DY7: 0.2736132 | DZ7: 0.27406514 | EA7: 0.27449807 | EB7: 0.27494353 | EC7: 0.27538328 | ED7: 0.27582153 | EE7: 0.2762402 | EF7: 0.27667108 | EG7: 0.27709588 | EH7: 0.27750788 | EI7: 0.27791919 | EJ7: 0.27827083 | EK7: 0.27866063 | EL7: 0.27905032 | EM7: 0.27942685 | EN7: 0.27980388 | EO7: 0.28015738 | EP7: 0.28051816 | EQ7: 0.28087572 | ER7: 0.28122728 | ES7: 0.28153671 | ET7: 0.28183938 | EU7: 0.28217214 | EV7: 0.28246804 | EW7: 0.28279113 | EX7: 0.28309977 | EY7: 0.28341449 | EZ7: 0.28371518 | FA7: 0.28402316 | FB7: 0.28432396 | FC7: 0.28461976 | FD7: 0.28490301 | FE7: 0.28519019 | FF7: 0.28546491 | FG7: 0.28573292 | FH7: 0.28599209 | FI7: 0.28625369 | FJ7: 0.28651301 | FK7: 0.28676839 | FL7: 0.28699502 | FM7: 0.28723966 | FN7: 0.28745287 | FO7: 0.28768699 | FP7: 0.28791504 | FQ7: 0.28814232 | FR7: 0.28835822 | FS7: 0.28857393 | FT7: 0.28878936 | FU7: 0.28900057 | FV7: 0.28920106 | FW7: 0.28939994 | FX7: 0.28960989 | FY7: 0.28980166 | FZ7: 0.2899802 | GA7: 0.29017462 | GB7: 0.29036739 | GC7: 0.2905722 | GD7: 0.29075795 | GE7: 0.29094605 | GF7: 0.29113409 | GG7: 0.29133364 | GH7: 0.29150316 | GI7: 0.29167083 | GJ7: 0.29185426 | GK7: 0.29203625 | GL7: 0.29221635 | GM7: 0.29239176 | GN7: 0.29256661 | GO7: 0.29274034 | GP7: 0.29291135 | GQ7: 0.29307751 | GR7: 0.29324635 | GS7: 0.29340887 | GT7: 0.29355894 | GU7: 0.29372001 | GV7: 0.29388465 | GW7: 0.29404206 | GX7: 0.29419514 | GY7: 0.29440787 | GZ7: 0.29456429 | HA7: 0.29471819 | HB7: 0.29487084 | HC7: 0.29502257 | HD7: 0.29516666 | HE7: 0.29530601 | HF7: 0.29544399 | HG7: 0.29557644 | HH7: 0.29571948 | HI7: 0.29584457 | HJ7: 0.29596804 | HK7: 0.29608898 | HL7: 0.29620824 | HM7: 0.29631506 | HN7: 0.29643225 | HO7: 0.29653205 | HP7: 0.29663404 | HQ7: 0.29674521 | HR7: 0.29684136 | HS7: 0.29692866 | HT7: 0.29702211 | HU7: 0.29711458 | HV7: 0.29720677 | HW7: 0.29729857 | HX7: 0.29738995 | HY7: 0.2974758 | HZ7: 0.29755426 | IA7: 0.29763269 | IB7: 0.29773929 | IC7: 0.29782245 | ID7: 0.29790408 | IE7: 0.29798448 | IF7: 0.29806426 | IG7: 0.29814052 | IH7: 0.29821643 | II7: 0.29829225 | IJ7: 0.29835995 | IK7: 0.29843288 | IL7: 0.29850299 | IM7: 0.29856416 | IN7: 0.29862427 | IO7: 0.29868421 | IP7: 0.29873146 | IQ7: 0.29878018 | IR7: 0.29882751 | IS7: 0.29887346 | IT7: 0.29891863 | IU7: 0.29896248 | IV7: 0.2990059 | IW7: 0.29904559 | IX7: 0.29908648 | IY7: 0.2991262 | IZ7: 0.29916041 | JA7: 0.29919491 | JB7: 0.29922742 | JC7: 0.29925723 | JD7: 0.29928871 | JE7: 0.29932016 | JF7: 0.29935114 | JG7: 0.29937924 | JH7: 0.29941032 | JI7: 0.29944032 | JJ7: 0.29947052 | JK7: 0.29950484 | JL7: 0.29953874 | JM7: 0.29956705 | JN7: 0.29959512 | JO7: 0.29962251 | JP7: 0.29964943 | JQ7: 0.29967403 | JR7: 0.29969787 | JS7: 0.29972087 | JT7: 0.29974295 | JU7: 0.29976431 | JV7: 0.29978255 | JW7: 0.29980095 | JX7: 0.29981883 | JY7: 0.29983421 | JZ7: 0.29984836 | KA7: 0.29985934 | KB7: 0.29986994 | KC7: 0.29988031 | KD7: 0.2998906 | KE7: 0.2999002 | KF7: 0.29990868 | KG7: 0.29991556 | KH7: 0.29992127 | KI7: 0.29992628 | KJ7: 0.29993059 | KK7: 0.29993463 | KL7: 0.29993683 | KM7: 0.29993863 | KN7: 0.29993986 | KO7: 0.29994074 | KP7: 0.29994147 | KQ7: 0.29994201 | KR7: 0.29994254 | KS7: 0.299943 | KT7: 0.29994331 | KU7: 0.29994345 | KV7: 0.29994359 | KW7: 0.29994362 | KX7: 0.29994365 | KY7: 0 | KZ7: 0 | LA7: 0 | LB7: 0 | LC7: 0 | LD7: 0 | LE7: 0 | LF7: 0 | LG7: 0 | LH7: 0 | LI7: 0 | LJ7: 0 | LK7: 0 | LL7: 0 | LM7: 0 | LN7: 0 | LO7: 0 | LP7: 0
B8: Cost | C8: 0 | D8: {=TRANSPOSE('Retrofit Cost vs SOC Data'!J12:J336)*cpi!$G$56} -> 22.002027 | E8: 25.353844 | F8: 26.221478 | G8: 26.531108 | H8: 26.998875 | I8: 27.658954 | J8: 29.766597 | K8: 29.859121 | L8: 30.745312 | M8: 30.939446 | N8: 30.999946 | O8: 31.122537 | P8: 31.506015 | Q8: 31.856768 | R8: 32.021577 | S8: 32.028719 | T8: 32.202479 | U8: 32.30347 | V8: 32.441187 | W8: 33.003227 | X8: 33.068851 | Y8: 33.207497 | Z8: 33.375114 | AA8: 33.529732 | AB8: 33.599335 | AC8: 33.625798 | AD8: 33.886855 | AE8: 33.904945 | AF8: 34.880112 | AG8: 34.921372 | AH8: 35.23424 | AI8: 35.591387 | AJ8: 35.843737 | AK8: 36.43544 | AL8: 36.439925 | AM8: 36.480588 | AN8: 36.520072 | AO8: 36.634211 | AP8: 37.556769 | AQ8: 37.612435 | AR8: 37.648857 | AS8: 38.089654 | AT8: 38.346211 | AU8: 38.901843 | AV8: 39.047471 | AW8: 39.196149 | AX8: 39.200567 | AY8: 39.283971 | AZ8: 39.716341 | BA8: 40.285623 | BB8: 40.686085 | BC8: 40.827082 | BD8: 40.856862 | BE8: 40.908399 | BF8: 41.039253 | BG8: 41.06757 | BH8: 41.301956 | BI8: 41.32051 | BJ8: 41.540138 | BK8: 41.865661 | BL8: 42.183129 | BM8: 42.197812 | BN8: 42.234097 | BO8: 42.466671 | BP8: 42.872696 | BQ8: 42.971628 | BR8: 42.984087 | BS8: 43.118255 | BT8: 43.145252 | BU8: 43.378497 | BV8: 43.419263 | BW8: 43.712947 | BX8: 43.937844 | BY8: 43.973 | BZ8: 44.025139 | CA8: 44.176071 | CB8: 45.026654 | CC8: 45.319055 | CD8: 45.590638 | CE8: 45.700223 | CF8: 46.05231 | CG8: 46.183778 | CH8: 46.257754 | CI8: 46.272198 | CJ8: 46.463956 | CK8: 46.670157 | CL8: 46.673636 | CM8: 46.695112 | CN8: 46.733894 | CO8: 47.016808 | CP8: 47.407191 | CQ8: 47.44159 | CR8: 47.456091 | CS8: 47.520284 | CT8: 47.633526 | CU8: 47.715965 | CV8: 47.900384 | CW8: 47.906247 | CX8: 48.003666 | CY8: 48.250483 | CZ8: 48.491651 | DA8: 48.66144 | DB8: 48.977434 | DC8: 49.112808 | DD8: 49.270203 | DE8: 49.519925 | DF8: 49.537947 | DG8: 49.563653 | DH8: 49.610686 | DI8: 49.818471 | DJ8: 49.831242 | DK8: 50.213171 | DL8: 50.233253 | DM8: 50.314681 | DN8: 50.383821 | DO8: 50.77384 | DP8: 50.90323 | DQ8: 51.251462 | DR8: 51.393066 | DS8: 51.706689 | DT8: 52.237886 | DU8: 52.565513 | DV8: 52.742458 | DW8: 52.845498 | DX8: 52.939527 | DY8: 53.271874 | DZ8: 53.350429 | EA8: 53.426534 | EB8: 53.556021 | EC8: 53.740193 | ED8: 53.789513 | EE8: 53.91235 | EF8: 54.033511 | EG8: 54.23954 | EH8: 54.622803 | EI8: 54.710519 | EJ8: 55.488324 | EK8: 55.506768 | EL8: 55.510814 | EM8: 55.965589 | EN8: 56.00799 | EO8: 56.457048 | EP8: 56.681197 | EQ8: 56.818769 | ER8: 57.081448 | ES8: 57.459919 | ET8: 57.895645 | EU8: 57.943147 | EV8: 58.256674 | EW8: 58.41311 | EX8: 58.612858 | EY8: 58.835187 | EZ8: 59.040004 | FA8: 59.186321 | FB8: 59.572599 | FC8: 59.848625 | FD8: 60.032245 | FE8: 60.276956 | FF8: 61.086611 | FG8: 61.508369 | FH8: 61.547549 | FI8: 61.924788 | FJ8: 62.07648 | FK8: 62.342317 | FL8: 62.841227 | FM8: 63.097144 | FN8: 63.749833 | FO8: 63.881171 | FP8: 64.355092 | FQ8: 64.416508 | FR8: 64.819484 | FS8: 65.375375 | FT8: 65.398702 | FU8: 65.76653 | FV8: 66.74776 | FW8: 66.900562 | FX8: 67.041518 | FY8: 67.061106 | FZ8: 67.239828 | GA8: 67.335307 | GB8: 67.499523 | GC8: 67.507455 | GD8: 67.680342 | GE8: 67.974721 | GF8: 67.979751 | GG8: 68.000799 | GH8: 68.066194 | GI8: 68.281848 | GJ8: 68.465171 | GK8: 68.620378 | GL8: 68.826313 | GM8: 69.350702 | GN8: 69.41305 | GO8: 69.542516 | GP8: 69.859673 | GQ8: 69.903058 | GR8: 70.116397 | GS8: 70.355568 | GT8: 70.509288 | GU8: 70.538951 | GV8: 70.628694 | GW8: 71.553392 | GX8: 71.594273 | GY8: 71.632077 | GZ8: 71.682634 | HA8: 72.022159 | HB8: 72.192969 | HC8: 72.320156 | HD8: 72.877402 | HE8: 74.073979 | HF8: 74.350116 | HG8: 74.709285 | HH8: 74.735569 | HI8: 76.522297 | HJ8: 76.815797 | HK8: 77.288325 | HL8: 77.607023 | HM8: 77.711426 | HN8: 78.010272 | HO8: 79.551377 | HP8: 79.932767 | HQ8: 80.402962 | HR8: 82.740065 | HS8: 83.228491 | HT8: 83.450264 | HU8: 83.71654 | HV8: 83.793252 | HW8: 83.89807 | HX8: 84.015796 | HY8: 85.06884 | HZ8: 85.496726 | IA8: 85.508117 | IB8: 86.231977 | IC8: 86.433759 | ID8: 86.922224 | IE8: 87.320498 | IF8: 87.528131 | IG8: 88.73418 | IH8: 88.853402 | II8: 88.890175 | IJ8: 89.459247 | IK8: 89.943821 | IL8: 91.034048 | IM8: 92.987269 | IN8: 95.432332 | IO8: 95.511695 | IP8: 100.39076 | IQ8: 101.84058 | IR8: 102.76147 | IS8: 103.71562 | IT8: 104.27463 | IU8: 105.24241 | IV8: 105.57023 | IW8: 106.38485 | IX8: 107.57344 | IY8: 108.56361 | IZ8: 113.25886 | JA8: 113.4962 | JB8: 115.64451 | JC8: 116.30269 | JD8: 116.84174 | JE8: 116.87763 | JF8: 117.42895 | JG8: 117.73543 | JH8: 118.47985 | JI8: 118.64246 | JJ8: 119.55139 | JK8: 119.67884 | JL8: 120.12671 | JM8: 120.86518 | JN8: 121.17638 | JO8: 122.14829 | JP8: 122.75804 | JQ8: 122.9661 | JR8: 127.70135 | JS8: 128.64407 | JT8: 130.36349 | JU8: 132.25537 | JV8: 135.38495 | JW8: 138.3185 | JX8: 140.14968 | JY8: 147.23683 | JZ8: 151.324 | KA8: 164.50997 | KB8: 166.45745 | KC8: 167.65746 | KD8: 169.22482 | KE8: 172.04834 | KF8: 179.26571 | KG8: 192.18279 | KH8: 204.84147 | KI8: 213.96893 | KJ8: 225.31601 | KK8: 227.00467 | KL8: 283.99167 | KM8: 303.40685 | KN8: 347.89359 | KO8: 390.30693 | KP8: 423.58524 | KQ8: 464.81797 | KR8: 467.32457 | KS8: 491.6532 | KT8: 556.90357 | KU8: 748.10594 | KV8: 765.78505 | KW8: 1281.854 | KX8: 1281.854 | KY8: 0 | KZ8: 0 | LA8: 0 | LB8: 0 | LC8: 0 | LD8: 0 | LE8: 0 | LF8: 0 | LG8: 0 | LH8: 0 | LI8: 0 | LJ8: 0 | LK8: 0 | LL8: 0 | LM8: 0 | LN8: 0 | LO8: 0 | LP8: 0
D10: refining
B11: Share of Capacity | C11: 0 | D11: {=TRANSPOSE('Retrofit Cost vs SOC Data'!G12:G183)*'BPE - US specific multipliers'!F22/'BPE - US specific multipliers'!F23} -> 0.0027824253 | E11: 0.0059331127 | F11: 0.0082654397 | G11: 0.010515931 | H11: 0.011948061 | I11: 0.014935077 | J11: 0.018535862 | K11: 0.019558813 | L11: 0.020704517 | M11: 0.021522878 | N11: 0.023977959 | O11: 0.0408771 | P11: 0.041286281 | Q11: 0.055198407 | R11: 0.077294137 | S11: 0.079340038 | T11: 0.08445479 | U11: 0.092474722 | V11: 0.097794064 | W11: 0.10454554 | X11: 0.11117426 | Y11: 0.11731196 | Z11: 0.11829399 | AA11: 0.12504546 | AB11: 0.13036481 | AC11: 0.13527497 | AD11: 0.14141267 | AE11: 0.14746854 | AF11: 0.15360624 | AG11: 0.15974394 | AH11: 0.16833673 | AI11: 0.17386066 | AJ11: 0.17897541 | AK11: 0.18470394 | AL11: 0.18981869 | AM11: 0.19595639 | AN11: 0.20168491 | AO11: 0.20598131 | AP11: 0.21170983 | AQ11: 0.21743835 | AR11: 0.21968884 | AS11: 0.22480359 | AT11: 0.23032753 | AU11: 0.23605605 | AV11: 0.24178457 | AW11: 0.24710391 | AX11: 0.25250509 | AY11: 0.26220266 | AZ11: 0.26760384 | BA11: 0.27312777 | BB11: 0.27836528 | BC11: 0.28376646 | BD11: 0.28900396 | BE11: 0.29432331 | BF11: 0.29915163 | BG11: 0.30414363 | BH11: 0.30966756 | BI11: 0.31531425 | BJ11: 0.31887412 | BK11: 0.3224749 | BL11: 0.32779425 | BM11: 0.33303175 | BN11: 0.33753273 | BO11: 0.3424429 | BP11: 0.34776224 | BQ11: 0.35234506 | BR11: 0.35684604 | BS11: 0.36216538 | BT11: 0.36605259 | BU11: 0.36981705 | BV11: 0.37431803 | BW11: 0.37840983 | BX11: 0.38209246 | BY11: 0.38577508 | BZ11: 0.3894577 | CA11: 0.39314032 | CB11: 0.39682294 | CC11: 0.40050556 | CD11: 0.40402451 | CE11: 0.40770714 | CF11: 0.41036681 | CG11: 0.41404943 | CH11: 0.41814123 | CI11: 0.42141467 | CJ11: 0.42509729 | CK11: 0.42804339 | CL11: 0.43131683 | CM11: 0.43418109 | CN11: 0.4382729 | CO11: 0.44093257 | CP11: 0.44420601 | CQ11: 0.44797047 | CR11: 0.45103932 | CS11: 0.45513112 | CT11: 0.45881374 | CU11: 0.46159617 | CV11: 0.46384666 | CW11: 0.46597439 | CX11: 0.46863407 | CY11: 0.47141649 | CZ11: 0.47419892 | DA11: 0.47718593 | DB11: 0.4798456 | DC11: 0.48205518 | DD11: 0.48455117 | DE11: 0.48680167 | DF11: 0.48958409 | DG11: 0.49216193 | DH11: 0.49486252 | DI11: 0.49784953 | DJ11: 0.50010002 | DK11: 0.5025551 | DL11: 0.504601 | DM11: 0.50717884 | DN11: 0.50983851 | DO11: 0.51229359 | DP11: 0.51442133 | DQ11: 0.51646723 | DR11: 0.51892231 | DS11: 0.52125464 | DT11: 0.5241189 | DU11: 0.52657398 | DV11: 0.52890631 | DW11: 0.53140231 | DX11: 0.53385739 | DY11: 0.53582145 | DZ11: 0.53794919 | EA11: 0.53991325 | EB11: 0.54195915 | EC11: 0.54400506 | ED11: 0.54605096 | EE11: 0.54809686 | EF11: 0.5504701 | EG11: 0.55272059 | EH11: 0.55562577 | EI11: 0.55754892 | EJ11: 0.55959482 | EK11: 0.56123154 | EL11: 0.56372754 | EM11: 0.56528243 | EN11: 0.56732833 | EO11: 0.5686377 | EP11: 0.56986524 | EQ11: 0.56990616 | ER11: 0.57076544 | ES11: 0.57146105 | ET11: 0.57170655 | EU11: 0.57191114 | EV11: 0.5720339 | EW11: #N/A | EX11: #N/A | EY11: #N/A | EZ11: #N/A | FA11: #N/A | FB11: #N/A | FC11: #N/A | FD11: #N/A | FE11: #N/A | FF11: #N/A | FG11: #N/A | FH11: #N/A | FI11: #N/A | FJ11: #N/A | FK11: #N/A | FL11: #N/A | FM11: #N/A | FN11: #N/A | FO11: #N/A | FP11: #N/A | FQ11: #N/A | FR11: #N/A | FS11: #N/A
B12: Cost | C12: 0 | D12: {=TRANSPOSE('Retrofit Cost vs SOC Data'!F12:F183)*cpi!$G$56} -> 36.329571 | E12: 36.47168 | F12: 37.503223 | G12: 39.377541 | H12: 42.913473 | I12: 43.066987 | J12: 45.493006 | K12: 45.91638 | L12: 46.410286 | M12: 49.2989 | N12: 52.49714 | O12: 57.166057 | P12: 58.038135 | Q12: 58.655541 | R12: 58.914269 | S12: 58.925687 | T12: 59.114878 | U12: 62.709891 | V12: 63.023901 | W12: 63.316676 | X12: 63.720146 | Y12: 63.855452 | Z12: 63.912826 | AA12: 64.400797 | AB12: 64.401236 | AC12: 65.262045 | AD12: 65.274135 | AE12: 65.730464 | AF12: 65.850525 | AG12: 66.152266 | AH12: 66.358497 | AI12: 66.518849 | AJ12: 66.564268 | AK12: 66.837352 | AL12: 67.027936 | AM12: 67.427888 | AN12: 67.556679 | AO12: 67.620591 | AP12: 67.644666 | AQ12: 67.650382 | AR12: 67.896827 | AS12: 67.937704 | AT12: 67.983329 | AU12: 68.0974 | AV12: 68.268447 | AW12: 68.269384 | AX12: 68.296296 | AY12: 68.384298 | AZ12: 68.508761 | BA12: 68.62207 | BB12: 68.950539 | BC12: 69.03284 | BD12: 69.234715 | BE12: 69.272544 | BF12: 69.310523 | BG12: 69.399624 | BH12: 69.613978 | BI12: 69.651132 | BJ12: 69.78068 | BK12: 70.035184 | BL12: 70.434998 | BM12: 70.544388 | BN12: 70.685143 | BO12: 70.844336 | BP12: 71.221654 | BQ12: 71.51219 | BR12: 71.557299 | BS12: 71.711605 | BT12: 71.714113 | BU12: 72.061456 | BV12: 72.359497 | BW12: 72.525753 | BX12: 72.813756 | BY12: 73.679709 | BZ12: 74.109861 | CA12: 74.162283 | CB12: 74.309802 | CC12: 74.546998 | CD12: 75.025395 | CE12: 75.458915 | CF12: 75.765683 | CG12: 75.787533 | CH12: 76.160122 | CI12: 76.202735 | CJ12: 76.525546 | CK12: 76.841881 | CL12: 76.960069 | CM12: 76.986481 | CN12: 77.261303 | CO12: 77.475915 | CP12: 77.637833 | CQ12: 77.63927 | CR12: 78.183642 | CS12: 78.301415 | CT12: 78.46441 | CU12: 78.587421 | CV12: 79.354352 | CW12: 79.582882 | CX12: 79.892111 | CY12: 79.921208 | CZ12: 80.436411 | DA12: 80.51003 | DB12: 80.647349 | DC12: 80.674702 | DD12: 80.758002 | DE12: 81.172248 | DF12: 81.461504 | DG12: 81.519641 | DH12: 81.785578 | DI12: 81.841454 | DJ12: 81.960658 | DK12: 82.869793 | DL12: 83.423635 | DM12: 83.470312 | DN12: 83.515443 | DO12: 83.638215 | DP12: 84.312759 | DQ12: 85.177943 | DR12: 85.224245 | DS12: 85.483539 | DT12: 85.658391 | DU12: 86.035479 | DV12: 86.089096 | DW12: 86.49242 | DX12: 86.902754 | DY12: 86.968019 | DZ12: 87.418099 | EA12: 87.455364 | EB12: 87.601898 | EC12: 88.155529 | ED12: 88.584067 | EE12: 88.977286 | EF12: 89.276614 | EG12: 89.363366 | EH12: 89.501741 | EI12: 90.704205 | EJ12: 91.913859 | EK12: 92.733571 | EL12: 94.86494 | EM12: 95.497007 | EN12: 96.414023 | EO12: 100.24117 | EP12: 101.9721 | EQ12: 102.24444 | ER12: 121.77084 | ES12: 126.45459 | ET12: 147.7939 | EU12: 182.42512 | EV12: 240.46538 | EW12: #N/A | EX12: #N/A | EY12: #N/A | EZ12: #N/A | FA12: #N/A | FB12: #N/A | FC12: #N/A | FD12: #N/A | FE12: #N/A | FF12: #N/A | FG12: #N/A | FH12: #N/A | FI12: #N/A | FJ12: #N/A | FK12: #N/A | FL12: #N/A | FM12: #N/A | FN12: #N/A | FO12: #N/A | FP12: #N/A | FQ12: #N/A | FR12: #N/A | FS12: #N/A
D14: chemicals
B15: Share of Capacity | C15: 0 | D15: {=TRANSPOSE('Retrofit Cost vs SOC Data'!C12:C19)*'BPE - Table 4-1_2021'!AH10/'BPE - US specific multipliers'!F30} -> 0.029351728 | E15: 0.034685523 | F15: 0.076427641 | G15: 0.10383636 | H15: 0.10723404 | I15: #N/A | J15: #N/A | K15: #N/A
B16: Cost | C16: 0 | D16: {=TRANSPOSE('Retrofit Cost vs SOC Data'!B12:B19)*cpi!$G$56} -> 30.54849 | E16: 56.047902 | F16: 63.184357 | G16: 64.719973 | H16: 113.4605 | I16: #N/A | J16: #N/A | K16: #N/A
D18: hydrogen
B19: Share of Capacity | C19: 0 | D19: {=TRANSPOSE('Retrofit Cost vs SOC Data'!I12:I104)} -> 0.047399647 | E19: 0.077965842 | F19: 0.11943986 | G19: 0.14770529 | H19: 0.19933207 | I19: 0.22559651 | J19: 0.25183649 | K19: 0.27600034 | L19: 0.29926495 | M19: 0.32857177 | N19: 0.35722978 | O19: 0.38567016 | P19: 0.41131323 | Q19: 0.4358351 | R19: 0.45428305 | S19: 0.47790189 | T19: 0.49239138 | U19: 0.51003331 | V19: 0.52482985 | W19: 0.5391515 | X19: 0.55044209 | Y19: 0.56379821 | Z19: 0.57694532 | AA19: 0.59008684 | AB19: 0.60832411 | AC19: 0.62347648 | AD19: 0.63546154 | AE19: 0.64709431 | AF19: 0.65888476 | AG19: 0.66773682 | AH19: 0.70560216 | AI19: 0.71582373 | AJ19: 0.72887708 | AK19: 0.73876265 | AL19: 0.74874804 | AM19: 0.75836524 | AN19: 0.78502862 | AO19: 0.80830063 | AP19: 0.83080895 | AQ19: 0.85254306 | AR19: 0.85875738 | AS19: 0.86524116 | AT19: 0.87227772 | AU19: 0.8896846 | AV19: 0.89513119 | AW19: 0.89990596 | AX19: 0.90456851 | AY19: 0.9095975 | AZ19: 0.91370379 | BA19: 0.91943203 | BB19: 0.92663506 | BC19: 0.93103626 | BD19: 0.9348074 | BE19: 0.93835198 | BF19: 0.94176897 | BG19: 0.94575153 | BH19: 0.94907614 | BI19: 0.95236225 | BJ19: 0.95560864 | BK19: 0.95793341 | BL19: 0.96094485 | BM19: 0.96332274 | BN19: 0.96556399 | BO19: 0.96789126 | BP19: 0.97066955 | BQ19: 0.97292245 | BR19: 0.97596405 | BS19: 0.97784565 | BT19: 0.97958969 | BU19: 0.98085923 | BV19: 0.98313673 | BW19: 0.98435474 | BX19: 0.98571395 | BY19: 0.98694839 | BZ19: 0.98799468 | CA19: 0.9895453 | CB19: 0.99035205 | CC19: 0.99129438 | CD19: 0.99212355 | CE19: 0.99307288 | CF19: 0.99368443 | CG19: 0.99671133 | CH19: 0.99773374 | CI19: 0.99847454 | CJ19: 0.99913855 | CK19: 0.99960397 | CL19: 1 | CM19: #N/A | CN19: #N/A | CO19: #N/A | CP19: #N/A | CQ19: #N/A | CR19: #N/A
B20: Cost | C20: 0 | D20: {=TRANSPOSE('Retrofit Cost vs SOC Data'!H12:H104)*cpi!$G$56} -> 50.284046 | E20: 51.67137 | F20: 52.429508 | G20: 52.520299 | H20: 52.527235 | I20: 53.33989 | J20: 53.350437 | K20: 54.298282 | L20: 54.744371 | M20: 54.805168 | N20: 55.452692 | O20: 55.538716 | P20: 56.731815 | Q20: 57.261487 | R20: 57.616418 | S20: 57.712909 | T20: 60.886252 | U20: 62.530287 | V20: 63.906317 | W20: 64.380274 | X20: 64.591618 | Y20: 65.414086 | Z20: 65.651476 | AA20: 65.657902 | AB20: 66.073942 | AC20: 66.52792 | AD20: 67.073043 | AE20: 67.542 | AF20: 68.411408 | AG20: 68.558741 | AH20: 69.522867 | AI20: 69.636726 | AJ20: 69.757799 | AK20: 69.970092 | AL20: 71.879282 | AM20: 72.496257 | AN20: 73.328416 | AO20: 74.944308 | AP20: 75.353372 | AQ20: 75.788032 | AR20: 76.548651 | AS20: 77.876463 | AT20: 78.178601 | AU20: 78.68202 | AV20: 82.13799 | AW20: 82.715698 | AX20: 83.044971 | AY20: 83.129162 | AZ20: 85.26526 | BA20: 85.937126 | BB20: 87.306791 | BC20: 87.542417 | BD20: 88.172159 | BE20: 93.093663 | BF20: 93.451875 | BG20: 96.56787 | BH20: 97.104717 | BI20: 97.393606 | BJ20: 97.696559 | BK20: 98.277743 | BL20: 98.654133 | BM20: 100.3204 | BN20: 100.85101 | BO20: 102.08704 | BP20: 102.83732 | BQ20: 108.97902 | BR20: 112.18628 | BS20: 114.45325 | BT20: 116.87524 | BU20: 117.56458 | BV20: 120.20162 | BW20: 123.81052 | BX20: 123.88861 | BY20: 125.93455 | BZ20: 131.5919 | CA20: 132.30633 | CB20: 135.23491 | CC20: 135.85136 | CD20: 140.34742 | CE20: 140.6279 | CF20: 147.05701 | CG20: 147.23878 | CH20: 147.57475 | CI20: 148.35868 | CJ20: 150.83235 | CK20: 161.21849 | CL20: 177.30551 | CM20: #N/A | CN20: #N/A | CO20: #N/A | CP20: #N/A | CQ20: #N/A | CR20: #N/A
D22: steel
B23: Share of Capacity | C23: 0 | D23: {=TRANSPOSE(Table1[Cumulative Capacity])*Steel!A52} -> 0.14961577 | E23: 0.26387199 | F23: 0.36062122 | G23: 0.42535105 | H23: 0.48915947 | I23: 0.5467483 | J23: 0.59489255
B24: Cost | C24: 0 | D24: {=TRANSPOSE(Table1[COA, 2012 $/tonne])*B53} -> 77.609732 | E24: 80.437116 | F24: 82.432917 | G24: 87.755051 | H24: 87.921368 | I24: 89.501376 | J24: 92.079285
D26: refining (petroleum -> energy)
B27: Share of Capacity | C27: 0 | D27: {=TRANSPOSE(Refining!AA8:AA49)/Refining!S5} -> 0.05888438 | E27: 0.099732103 | F27: 0.14561948 | G27: 0.17028726 | H27: 0.1917721 | I27: 0.19972945 | J27: 0.25870575 | K27: 0.2666631 | L27: 0.27408996 | M27: 0.31984348 | N27: 0.32249593 | O27: 0.32673985 | P27: 0.33390146 | Q27: 0.39296968 | R27: 0.39509164 | S27: 0.39986605 | T27: 0.44548571 | U27: 0.4484034 | V27: 0.48926382 | W27: 0.51412333 | X27: 0.53567735 | Y27: 0.54347964 | Z27: 0.55128038 | AA27: 0.55868712 | AB27: 0.56133183 | AC27: 0.60220493 | AD27: 0.60670017 | AE27: 0.61370904 | AF27: 0.61595666 | AG27: 0.64100792 | AH27: 0.64563655 | AI27: 0.66725974 | AJ27: 0.67490696 | AK27: 0.67781615 | AL27: 0.68599077 | AM27: 0.6928469 | AN27: 0.69548388 | AO27: 0.70023043 | AP27: 0.70708656 | AQ27: 0.70945984 | AR27: 0.7139427 | AS27: 0.71684337
B28: Cost | C28: 0 | D28: {=TRANSPOSE(Refining!Y8:Y49)} -> 62.154951 | E28: 66.326784 | F28: 68.05306 | G28: 72.584534 | H28: 73.591529 | I28: 75.821302 | J28: 78.454969 | K28: 78.554572 | L28: 81.215914 | M28: 84.507484 | N28: 86.610526 | O28: 89.343796 | P28: 89.703437 | Q28: 94.754988 | R28: 97.471678 | S28: 97.615534 | T28: 100.96191 | U28: 103.08207 | V28: 103.76982 | W28: 114.04606 | X28: 115.67808 | Y28: 120.79284 | Z28: 125.22698 | AA28: 125.63313 | AB28: 137.23466 | AC28: 141.21285 | AD28: 141.89285 | AE28: 142.3548 | AF28: 155.17312 | AG28: 155.50758 | AH28: 155.52719 | AI28: 157.76464 | AJ28: 163.03112 | AK28: 164.56142 | AL28: 169.23804 | AM28: 175.44496 | AN28: 187.8588 | AO28: 194.4419 | AP28: 195.00616 | AQ28: 212.87457 | AR28: 213.43884 | AS28: 226.04077
B50: 143 | C50: steel BF cost (EFI)
B51: =B50*cpi!G62 -> 104.66399 | C51: in 2012 USD
B52: =AVERAGE(Table1[COA, 2012 $/tonne]) -> 66.117967 | C52: average calculated
B53: =AVERAGE(B51:B52)/B52 -> 1.2914943 | C53: multiplier

Sheet CECRCbI-process
A1: CCS retrofitting percentage by cost (2012$/ton) | B1: 1 | C1: 2 | D1: 3 | E1: 4 | F1: 5 | G1: 6 | H1: 7 | I1: 8 | J1: 9 | K1: 10 | L1: 11 | M1: 12 | N1: 13 | O1: 14 | P1: 15 | Q1: 16 | R1: 17 | S1: 18 | T1: 19 | U1: 20 | V1: 21 | W1: 22 | X1: 23 | Y1: 24 | Z1: 25 | AA1: 26 | AB1: 27 | AC1: 28 | AD1: 29 | AE1: 30 | AF1: 31 | AG1: 32 | AH1: 33 | AI1: 34 | AJ1: 35 | AK1: 36 | AL1: 37 | AM1: 38 | AN1: 39 | AO1: 40 | AP1: 41 | AQ1: 42 | AR1: 43 | AS1: 44 | AT1: 45 | AU1: 46 | AV1: 47 | AW1: 48 | AX1: 49 | AY1: 50 | AZ1: 51 | BA1: 52 | BB1: 53 | BC1: 54 | BD1: 55 | BE1: 56 | BF1: 57 | BG1: 58 | BH1: 59 | BI1: 60 | BJ1: 61 | BK1: 62 | BL1: 63 | BM1: 64 | BN1: 65 | BO1: 66 | BP1: 67 | BQ1: 68 | BR1: 69 | BS1: 70 | BT1: 71 | BU1: 72 | BV1: 73 | BW1: 74 | BX1: 75 | BY1: 76 | BZ1: 77 | CA1: 78 | CB1: 79 | CC1: 80 | CD1: 81 | CE1: 82 | CF1: 83 | CG1: 84 | CH1: 85 | CI1: 86 | CJ1: 87 | CK1: 88 | CL1: 89 | CM1: 90 | CN1: 91 | CO1: 92 | CP1: 93 | CQ1: 94 | CR1: 95 | CS1: 96 | CT1: 97 | CU1: 98 | CV1: 99 | CW1: 100 | CX1: 101 | CY1: 102 | CZ1: 103 | DA1: 104 | DB1: 105 | DC1: 106 | DD1: 107 | DE1: 108 | DF1: 109 | DG1: 110 | DH1: 111 | DI1: 112 | DJ1: 113 | DK1: 114 | DL1: 115 | DM1: 116 | DN1: 117 | DO1: 118 | DP1: 119 | DQ1: 120 | DR1: 121 | DS1: 122 | DT1: 123 | DU1: 124 | DV1: 125 | DW1: 126 | DX1: 127 | DY1: 128 | DZ1: 129 | EA1: 130 | EB1: 131 | EC1: 132 | ED1: 133 | EE1: 134 | EF1: 135 | EG1: 136 | EH1: 137 | EI1: 138 | EJ1: 139 | EK1: 140 | EL1: 141 | EM1: 142 | EN1: 143 | EO1: 144 | EP1: 145 | EQ1: 146 | ER1: 147 | ES1: 148 | ET1: 149 | EU1: 150 | EV1: 151 | EW1: 152 | EX1: 153 | EY1: 154 | EZ1: 155 | FA1: 156 | FB1: 157 | FC1: 158 | FD1: 159 | FE1: 160 | FF1: 161 | FG1: 162 | FH1: 163 | FI1: 164 | FJ1: 165 | FK1: 166 | FL1: 167 | FM1: 168 | FN1: 169 | FO1: 170 | FP1: 171 | FQ1: 172 | FR1: 173 | FS1: 174 | FT1: 175 | FU1: 176 | FV1: 177 | FW1: 178 | FX1: 179 | FY1: 180 | FZ1: 181 | GA1: 182 | GB1: 183 | GC1: 184 | GD1: 185 | GE1: 186 | GF1: 187 | GG1: 188 | GH1: 189 | GI1: 190 | GJ1: 191 | GK1: 192 | GL1: 193 | GM1: 194 | GN1: 195 | GO1: 196 | GP1: 197 | GQ1: 198 | GR1: 199 | GS1: 200 | GT1: 201 | GU1: 202 | GV1: 203 | GW1: 204 | GX1: 205 | GY1: 206 | GZ1: 207 | HA1: 208 | HB1: 209 | HC1: 210 | HD1: 211 | HE1: 212 | HF1: 213 | HG1: 214 | HH1: 215 | HI1: 216 | HJ1: 217 | HK1: 218 | HL1: 219 | HM1: 220 | HN1: 221 | HO1: 222 | HP1: 223 | HQ1: 224 | HR1: 225 | HS1: 226 | HT1: 227 | HU1: 228 | HV1: 229 | HW1: 230 | HX1: 231 | HY1: 232 | HZ1: 233 | IA1: 234 | IB1: 235 | IC1: 236 | ID1: 237 | IE1: 238 | IF1: 239 | IG1: 240 | IH1: 241 | II1: 242 | IJ1: 243 | IK1: 244 | IL1: 245 | IM1: 246 | IN1: 247 | IO1: 248 | IP1: 249 | IQ1: 250 | IR1: 251 | IS1: 252 | IT1: 253 | IU1: 254 | IV1: 255 | IW1: 256 | IX1: 257 | IY1: 258 | IZ1: 259 | JA1: 260 | JB1: 261 | JC1: 262 | JD1: 263 | JE1: 264 | JF1: 265 | JG1: 266 | JH1: 267 | JI1: 268 | JJ1: 269 | JK1: 270 | JL1: 271 | JM1: 272 | JN1: 273 | JO1: 274 | JP1: 275 | JQ1: 276 | JR1: 277 | JS1: 278 | JT1: 279 | JU1: 280 | JV1: 281 | JW1: 282 | JX1: 283 | JY1: 284 | JZ1: 285 | KA1: 286 | KB1: 287 | KC1: 288 | KD1: 289 | KE1: 290 | KF1: 291 | KG1: 292 | KH1: 293 | KI1: 294 | KJ1: 295 | KK1: 296 | KL1: 297 | KM1: 298 | KN1: 299 | KO1: 300 | KP1: 301 | KQ1: 302 | KR1: 303 | KS1: 304 | KT1: 305 | KU1: 306 | KV1: 307 | KW1: 308 | KX1: 309 | KY1: 310 | KZ1: 311 | LA1: 312 | LB1: 313 | LC1: 314 | LD1: 315 | LE1: 316 | LF1: 317 | LG1: 318 | LH1: 319 | LI1: 320 | LJ1: 321 | LK1: 322 | LL1: 323 | LM1: 324 | LN1: 325 | LO1: 326 | LP1: 327 | LQ1: 328 | LR1: 329 | LS1: 330 | LT1: 331 | LU1: 332 | LV1: 333 | LW1: 334 | LX1: 335 | LY1: 336 | LZ1: 337 | MA1: 338 | MB1: 339 | MC1: 340 | MD1: 341 | ME1: 342 | MF1: 343 | MG1: 344 | MH1: 345 | MI1: 346 | MJ1: 347 | MK1: 348 | ML1: 349 | MM1: 350 | MN1: 351 | MO1: 352 | MP1: 353 | MQ1: 354 | MR1: 355 | MS1: 356 | MT1: 357 | MU1: 358 | MV1: 359 | MW1: 360 | MX1: 361 | MY1: 362 | MZ1: 363 | NA1: 364 | NB1: 365 | NC1: 366 | ND1: 367 | NE1: 368 | NF1: 369 | NG1: 370 | NH1: 371 | NI1: 372 | NJ1: 373 | NK1: 374 | NL1: 375 | NM1: 376 | NN1: 377 | NO1: 378 | NP1: 379 | NQ1: 380 | NR1: 381 | NS1: 382 | NT1: 383 | NU1: 384 | NV1: 385 | NW1: 386 | NX1: 387 | NY1: 388 | NZ1: 389 | OA1: 390 | OB1: 391 | OC1: 392 | OD1: 393 | OE1: 394 | OF1: 395 | OG1: 396 | OH1: 397 | OI1: 398 | OJ1: 399 | OK1: 400 | OL1: 401 | OM1: 402 | ON1: 403 | OO1: 404 | OP1: 405 | OQ1: 406 | OR1: 407 | OS1: 408 | OT1: 409 | OU1: 410 | OV1: 411 | OW1: 412 | OX1: 413 | OY1: 414 | OZ1: 415 | PA1: 416 | PB1: 417 | PC1: 418 | PD1: 419 | PE1: 420 | PF1: 421 | PG1: 422 | PH1: 423 | PI1: 424 | PJ1: 425 | PK1: 426 | PL1: 427 | PM1: 428 | PN1: 429 | PO1: 430 | PP1: 431 | PQ1: 432 | PR1: 433 | PS1: 434 | PT1: 435 | PU1: 436 | PV1: 437 | PW1: 438 | PX1: 439 | PY1: 440 | PZ1: 441 | QA1: 442 | QB1: 443 | QC1: 444 | QD1: 445 | QE1: 446 | QF1: 447 | QG1: 448 | QH1: 449 | QI1: 450 | QJ1: 451 | QK1: 452 | QL1: 453 | QM1: 454 | QN1: 455 | QO1: 456 | QP1: 457 | QQ1: 458 | QR1: 459 | QS1: 460 | QT1: 461 | QU1: 462 | QV1: 463 | QW1: 464 | QX1: 465 | QY1: 466 | QZ1: 467 | RA1: 468 | RB1: 469 | RC1: 470 | RD1: 471 | RE1: 472 | RF1: 473 | RG1: 474 | RH1: 475 | RI1: 476 | RJ1: 477 | RK1: 478 | RL1: 479 | RM1: 480 | RN1: 481 | RO1: 482 | RP1: 483 | RQ1: 484 | RR1: 485 | RS1: 486 | RT1: 487 | RU1: 488 | RV1: 489 | RW1: 490 | RX1: 491 | RY1: 492 | RZ1: 493 | SA1: 494 | SB1: 495 | SC1: 496 | SD1: 497 | SE1: 498 | SF1: 499 | SG1: 500 | SH1: 501 | SI1: 502 | SJ1: 503 | SK1: 504 | SL1: 505 | SM1: 506 | SN1: 507 | SO1: 508 | SP1: 509 | SQ1: 510 | SR1: 511 | SS1: 512 | ST1: 513 | SU1: 514 | SV1: 515 | SW1: 516 | SX1: 517 | SY1: 518 | SZ1: 519 | TA1: 520 | TB1: 521 | TC1: 522 | TD1: 523 | TE1: 524 | TF1: 525 | TG1: 526 | TH1: 527 | TI1: 528 | TJ1: 529 | TK1: 530 | TL1: 531 | TM1: 532 | TN1: 533 | TO1: 534 | TP1: 535 | TQ1: 536 | TR1: 537 | TS1: 538 | TT1: 539 | TU1: 540 | TV1: 541 | TW1: 542 | TX1: 543 | TY1: 544 | TZ1: 545 | UA1: 546 | UB1: 547 | UC1: 548 | UD1: 549 | UE1: 550 | UF1: 551 | UG1: 552 | UH1: 553 | UI1: 554 | UJ1: 555 | UK1: 556 | UL1: 557 | UM1: 558 | UN1: 559 | UO1: 560 | UP1: 561 | UQ1: 562 | UR1: 563 | US1: 564 | UT1: 565 | UU1: 566 | UV1: 567 | UW1: 568 | UX1: 569 | UY1: 570 | UZ1: 571 | VA1: 572 | VB1: 573 | VC1: 574 | VD1: 575 | VE1: 576 | VF1: 577 | VG1: 578 | VH1: 579 | VI1: 580 | VJ1: 581 | VK1: 582 | VL1: 583 | VM1: 584 | VN1: 585 | VO1: 586 | VP1: 587 | VQ1: 588 | VR1: 589 | VS1: 590 | VT1: 591 | VU1: 592 | VV1: 593 | VW1: 594 | VX1: 595 | VY1: 596 | VZ1: 597 | WA1: 598 | WB1: 599 | WC1: 600 | WD1: 601 | WE1: 602 | WF1: 603 | WG1: 604 | WH1: 605 | WI1: 606 | WJ1: 607 | WK1: 608 | WL1: 609 | WM1: 610 | WN1: 611 | WO1: 612 | WP1: 613 | WQ1: 614 | WR1: 615 | WS1: 616 | WT1: 617 | WU1: 618 | WV1: 619 | WW1: 620 | WX1: 621 | WY1: 622 | WZ1: 623 | XA1: 624 | XB1: 625 | XC1: 626 | XD1: 627 | XE1: 628 | XF1: 629 | XG1: 630 | XH1: 631 | XI1: 632 | XJ1: 633 | XK1: 634 | XL1: 635 | XM1: 636 | XN1: 637 | XO1: 638 | XP1: 639 | XQ1: 640 | XR1: 641 | XS1: 642 | XT1: 643 | XU1: 644 | XV1: 645 | XW1: 646 | XX1: 647 | XY1: 648 | XZ1: 649 | YA1: 650 | YB1: 651 | YC1: 652 | YD1: 653 | YE1: 654 | YF1: 655 | YG1: 656 | YH1: 657 | YI1: 658 | YJ1: 659 | YK1: 660 | YL1: 661 | YM1: 662 | YN1: 663 | YO1: 664 | YP1: 665 | YQ1: 666 | YR1: 667 | YS1: 668 | YT1: 669 | YU1: 670 | YV1: 671 | YW1: 672 | YX1: 673 | YY1: 674 | YZ1: 675 | ZA1: 676 | ZB1: 677 | ZC1: 678 | ZD1: 679 | ZE1: 680 | ZF1: 681 | ZG1: 682 | ZH1: 683 | ZI1: 684 | ZJ1: 685 | ZK1: 686 | ZL1: 687 | ZM1: 688 | ZN1: 689 | ZO1: 690 | ZP1: 691 | ZQ1: 692 | ZR1: 693 | ZS1: 694 | ZT1: 695 | ZU1: 696 | ZV1: 697 | ZW1: 698 | ZX1: 699 | ZY1: 700 | ZZ1: 701 | AAA1: 702 | AAB1: 703 | AAC1: 704 | AAD1: 705 | AAE1: 706 | AAF1: 707 | AAG1: 708 | AAH1: 709 | AAI1: 710 | AAJ1: 711 | AAK1: 712 | AAL1: 713 | AAM1: 714 | AAN1: 715 | AAO1: 716 | AAP1: 717 | AAQ1: 718 | AAR1: 719 | AAS1: 720 | AAT1: 721 | AAU1: 722 | AAV1: 723 | AAW1: 724 | AAX1: 725 | AAY1: 726 | AAZ1: 727 | ABA1: 728 | ABB1: 729 | ABC1: 730 | ABD1: 731 | ABE1: 732 | ABF1: 733 | ABG1: 734 | ABH1: 735 | ABI1: 736 | ABJ1: 737 | ABK1: 738 | ABL1: 739 | ABM1: 740 | ABN1: 741 | ABO1: 742 | ABP1: 743 | ABQ1: 744 | ABR1: 745 | ABS1: 746 | ABT1: 747 | ABU1: 748 | ABV1: 749 | ABW1: 750 | ABX1: 751 | ABY1: 752 | ABZ1: 753 | ACA1: 754 | ACB1: 755 | ACC1: 756 | ACD1: 757 | ACE1: 758 | ACF1: 759 | ACG1: 760 | ACH1: 761 | ACI1: 762 | ACJ1: 763 | ACK1: 764 | ACL1: 765 | ACM1: 766 | ACN1: 767 | ACO1: 768 | ACP1: 769 | ACQ1: 770 | ACR1: 771 | ACS1: 772 | ACT1: 773 | ACU1: 774 | ACV1: 775 | ACW1: 776 | ACX1: 777 | ACY1: 778 | ACZ1: 779 | ADA1: 780 | ADB1: 781 | ADC1: 782 | ADD1: 783 | ADE1: 784 | ADF1: 785 | ADG1: 786 | ADH1: 787 | ADI1: 788 | ADJ1: 789 | ADK1: 790 | ADL1: 791 | ADM1: 792 | ADN1: 793 | ADO1: 794 | ADP1: 795 | ADQ1: 796 | ADR1: 797 | ADS1: 798 | ADT1: 799 | ADU1: 800 | ADV1: 801 | ADW1: 802 | ADX1: 803 | ADY1: 804 | ADZ1: 805 | AEA1: 806 | AEB1: 807 | AEC1: 808 | AED1: 809 | AEE1: 810 | AEF1: 811 | AEG1: 812 | AEH1: 813 | AEI1: 814 | AEJ1: 815 | AEK1: 816 | AEL1: 817 | AEM1: 818 | AEN1: 819 | AEO1: 820 | AEP1: 821 | AEQ1: 822 | AER1: 823 | AES1: 824 | AET1: 825 | AEU1: 826 | AEV1: 827 | AEW1: 828 | AEX1: 829 | AEY1: 830 | AEZ1: 831 | AFA1: 832 | AFB1: 833 | AFC1: 834 | AFD1: 835 | AFE1: 836 | AFF1: 837 | AFG1: 838 | AFH1: 839 | AFI1: 840 | AFJ1: 841 | AFK1: 842 | AFL1: 843 | AFM1: 844 | AFN1: 845 | AFO1: 846 | AFP1: 847 | AFQ1: 848 | AFR1: 849 | AFS1: 850 | AFT1: 851 | AFU1: 852 | AFV1: 853 | AFW1: 854 | AFX1: 855 | AFY1: 856 | AFZ1: 857 | AGA1: 858 | AGB1: 859 | AGC1: 860 | AGD1: 861 | AGE1: 862 | AGF1: 863 | AGG1: 864 | AGH1: 865 | AGI1: 866 | AGJ1: 867 | AGK1: 868 | AGL1: 869 | AGM1: 870 | AGN1: 871 | AGO1: 872 | AGP1: 873 | AGQ1: 874 | AGR1: 875 | AGS1: 876 | AGT1: 877 | AGU1: 878 | AGV1: 879 | AGW1: 880 | AGX1: 881 | AGY1: 882 | AGZ1: 883 | AHA1: 884 | AHB1: 885 | AHC1: 886 | AHD1: 887 | AHE1: 888 | AHF1: 889 | AHG1: 890 | AHH1: 891 | AHI1: 892 | AHJ1: 893 | AHK1: 894 | AHL1: 895 | AHM1: 896 | AHN1: 897 | AHO1: 898 | AHP1: 899 | AHQ1: 900 | AHR1: 901 | AHS1: 902 | AHT1: 903 | AHU1: 904 | AHV1: 905 | AHW1: 906 | AHX1: 907 | AHY1: 908 | AHZ1: 909 | AIA1: 910 | AIB1: 911 | AIC1: 912 | AID1: 913 | AIE1: 914 | AIF1: 915 | AIG1: 916 | AIH1: 917 | AII1: 918 | AIJ1: 919 | AIK1: 920 | AIL1: 921 | AIM1: 922 | AIN1: 923 | AIO1: 924 | AIP1: 925 | AIQ1: 926 | AIR1: 927 | AIS1: 928 | AIT1: 929 | AIU1: 930 | AIV1: 931 | AIW1: 932 | AIX1: 933 | AIY1: 934 | AIZ1: 935 | AJA1: 936 | AJB1: 937 | AJC1: 938 | AJD1: 939 | AJE1: 940 | AJF1: 941 | AJG1: 942 | AJH1: 943 | AJI1: 944 | AJJ1: 945 | AJK1: 946 | AJL1: 947 | AJM1: 948 | AJN1: 949 | AJO1: 950 | AJP1: 951 | AJQ1: 952 | AJR1: 953 | AJS1: 954 | AJT1: 955 | AJU1: 956 | AJV1: 957 | AJW1: 958 | AJX1: 959 | AJY1: 960 | AJZ1: 961 | AKA1: 962 | AKB1: 963 | AKC1: 964 | AKD1: 965 | AKE1: 966 | AKF1: 967 | AKG1: 968 | AKH1: 969 | AKI1: 970 | AKJ1: 971 | AKK1: 972 | AKL1: 973 | AKM1: 974 | AKN1: 975 | AKO1: 976 | AKP1: 977 | AKQ1: 978 | AKR1: 979 | AKS1: 980 | AKT1: 981 | AKU1: 982 | AKV1: 983 | AKW1: 984 | AKX1: 985 | AKY1: 986 | AKZ1: 987 | ALA1: 988 | ALB1: 989 | ALC1: 990 | ALD1: 991 | ALE1: 992 | ALF1: 993 | ALG1: 994 | ALH1: 995 | ALI1: 996 | ALJ1: 997 | ALK1: 998 | ALL1: 999 | ALM1: 1000
A2: agriculture and forestry 01T03 | B2: =Other!B$34 -> 2.3404821e-05 | C2: =Other!C$34 -> 3.3528617e-05 | D2: =Other!D$34 -> 3.453111e-05 | E2: =Other!E$34 -> 3.5561918e-05 | F2: =Other!F$34 -> 3.6621787e-05 | G2: =Other!G$34 -> 3.7711483e-05 | H2: =Other!H$34 -> 3.8831793e-05 | I2: =Other!I$34 -> 3.9983518e-05 | ... ALM2: =Other!ALM$34 -> 0.99864325
A3: coal mining 05 | B3: =Other!B$34 -> 2.3404821e-05 | C3: =Other!C$34 -> 3.3528617e-05 | D3: =Other!D$34 -> 3.453111e-05 | E3: =Other!E$34 -> 3.5561918e-05 | F3: =Other!F$34 -> 3.6621787e-05 | G3: =Other!G$34 -> 3.7711483e-05 | H3: =Other!H$34 -> 3.8831793e-05 | I3: =Other!I$34 -> 3.9983518e-05 | ... ALM3: =Other!ALM$34 -> 0.99864325
A4: oil and gas extraction 06 | B4: =INDEX('By Industry'!$C$7:$KX$7,MATCH('CECRCbI-process'!B1,'By Industry'!$C$8:$KX$8,1)) -> 0 | C4: =INDEX('By Industry'!$C$7:$KX$7,MATCH('CECRCbI-process'!C1,'By Industry'!$C$8:$KX$8,1)) -> 0 | D4: =INDEX('By Industry'!$C$7:$KX$7,MATCH('CECRCbI-process'!D1,'By Industry'!$C$8:$KX$8,1)) -> 0 | E4: =INDEX('By Industry'!$C$7:$KX$7,MATCH('CECRCbI-process'!E1,'By Industry'!$C$8:$KX$8,1)) -> 0 | F4: =INDEX('By Industry'!$C$7:$KX$7,MATCH('CECRCbI-process'!F1,'By Industry'!$C$8:$KX$8,1)) -> 0 | G4: =INDEX('By Industry'!$C$7:$KX$7,MATCH('CECRCbI-process'!G1,'By Industry'!$C$8:$KX$8,1)) -> 0 | H4: =INDEX('By Industry'!$C$7:$KX$7,MATCH('CECRCbI-process'!H1,'By Industry'!$C$8:$KX$8,1)) -> 0 | I4: =INDEX('By Industry'!$C$7:$KX$7,MATCH('CECRCbI-process'!I1,'By Industry'!$C$8:$KX$8,1)) -> 0 | ... ALM4: =INDEX('By Industry'!$C$7:$KX$7,MATCH('CECRCbI-process'!ALM1,'By Industry'!$C$8:$KX$8,1)) -> 0.29994359
A5: other mining and quarrying 07T08 | B5: =Other!B$34 -> 2.3404821e-05 | C5: =Other!C$34 -> 3.3528617e-05 | D5: =Other!D$34 -> 3.453111e-05 | E5: =Other!E$34 -> 3.5561918e-05 | F5: =Other!F$34 -> 3.6621787e-05 | G5: =Other!G$34 -> 3.7711483e-05 | H5: =Other!H$34 -> 3.8831793e-05 | I5: =Other!I$34 -> 3.9983518e-05 | ... ALM5: =Other!ALM$34 -> 0.99864325
A6: food beverage and tobacco 10T12 | B6: =Other!B$34 -> 2.3404821e-05 | C6: =Other!C$34 -> 3.3528617e-05 | D6: =Other!D$34 -> 3.453111e-05 | E6: =Other!E$34 -> 3.5561918e-05 | F6: =Other!F$34 -> 3.6621787e-05 | G6: =Other!G$34 -> 3.7711483e-05 | H6: =Other!H$34 -> 3.8831793e-05 | I6: =Other!I$34 -> 3.9983518e-05 | ... ALM6: =Other!ALM$34 -> 0.99864325
A7: textiles apparel and leather 13T15 | B7: =Other!B$34 -> 2.3404821e-05 | C7: =Other!C$34 -> 3.3528617e-05 | D7: =Other!D$34 -> 3.453111e-05 | E7: =Other!E$34 -> 3.5561918e-05 | F7: =Other!F$34 -> 3.6621787e-05 | G7: =Other!G$34 -> 3.7711483e-05 | H7: =Other!H$34 -> 3.8831793e-05 | I7: =Other!I$34 -> 3.9983518e-05 | ... ALM7: =Other!ALM$34 -> 0.99864325
A8: wood products 16 | B8: =Other!B$34 -> 2.3404821e-05 | C8: =Other!C$34 -> 3.3528617e-05 | D8: =Other!D$34 -> 3.453111e-05 | E8: =Other!E$34 -> 3.5561918e-05 | F8: =Other!F$34 -> 3.6621787e-05 | G8: =Other!G$34 -> 3.7711483e-05 | H8: =Other!H$34 -> 3.8831793e-05 | I8: =Other!I$34 -> 3.9983518e-05 | ... ALM8: =Other!ALM$34 -> 0.99864325
A9: pulp paper and printing 17T18 | B9: =Other!B$34 -> 2.3404821e-05 | C9: =Other!C$34 -> 3.3528617e-05 | D9: =Other!D$34 -> 3.453111e-05 | E9: =Other!E$34 -> 3.5561918e-05 | F9: =Other!F$34 -> 3.6621787e-05 | G9: =Other!G$34 -> 3.7711483e-05 | H9: =Other!H$34 -> 3.8831793e-05 | I9: =Other!I$34 -> 3.9983518e-05 | ... ALM9: =Other!ALM$34 -> 0.99864325
A10: refined petroleum and coke 19 | B10: =INDEX('By Industry'!$C$11:$FS$11,MATCH('CECRCbI-process'!B1,'By Industry'!$C$12:$FS$12,1)) -> 0 | C10: =INDEX('By Industry'!$C$11:$FS$11,MATCH('CECRCbI-process'!C1,'By Industry'!$C$12:$FS$12,1)) -> 0 | D10: =INDEX('By Industry'!$C$11:$FS$11,MATCH('CECRCbI-process'!D1,'By Industry'!$C$12:$FS$12,1)) -> 0 | E10: =INDEX('By Industry'!$C$11:$FS$11,MATCH('CECRCbI-process'!E1,'By Industry'!$C$12:$FS$12,1)) -> 0 | F10: =INDEX('By Industry'!$C$11:$FS$11,MATCH('CECRCbI-process'!F1,'By Industry'!$C$12:$FS$12,1)) -> 0 | G10: =INDEX('By Industry'!$C$11:$FS$11,MATCH('CECRCbI-process'!G1,'By Industry'!$C$12:$FS$12,1)) -> 0 | H10: =INDEX('By Industry'!$C$11:$FS$11,MATCH('CECRCbI-process'!H1,'By Industry'!$C$12:$FS$12,1)) -> 0 | I10: =INDEX('By Industry'!$C$11:$FS$11,MATCH('CECRCbI-process'!I1,'By Industry'!$C$12:$FS$12,1)) -> 0 | ... ALM10: =INDEX('By Industry'!$C$11:$FS$11,MATCH('CECRCbI-process'!ALM1,'By Industry'!$C$12:$FS$12,1)) -> 0.5720339
A11: chemicals 20 | B11: =INDEX('By Industry'!$C$15:$K$15,MATCH('CECRCbI-process'!B1,'By Industry'!$C$16:$K$16,1)) -> 0 | C11: =INDEX('By Industry'!$C$15:$K$15,MATCH('CECRCbI-process'!C1,'By Industry'!$C$16:$K$16,1)) -> 0 | D11: =INDEX('By Industry'!$C$15:$K$15,MATCH('CECRCbI-process'!D1,'By Industry'!$C$16:$K$16,1)) -> 0 | E11: =INDEX('By Industry'!$C$15:$K$15,MATCH('CECRCbI-process'!E1,'By Industry'!$C$16:$K$16,1)) -> 0 | F11: =INDEX('By Industry'!$C$15:$K$15,MATCH('CECRCbI-process'!F1,'By Industry'!$C$16:$K$16,1)) -> 0 | G11: =INDEX('By Industry'!$C$15:$K$15,MATCH('CECRCbI-process'!G1,'By Industry'!$C$16:$K$16,1)) -> 0 | H11: =INDEX('By Industry'!$C$15:$K$15,MATCH('CECRCbI-process'!H1,'By Industry'!$C$16:$K$16,1)) -> 0 | I11: =INDEX('By Industry'!$C$15:$K$15,MATCH('CECRCbI-process'!I1,'By Industry'!$C$16:$K$16,1)) -> 0 | ... ALM11: =INDEX('By Industry'!$C$15:$K$15,MATCH('CECRCbI-process'!ALM1,'By Industry'!$C$16:$K$16,1)) -> 0.10723404
A12: rubber and plastic products 22 | B12: =Other!B$34 -> 2.3404821e-05 | C12: =Other!C$34 -> 3.3528617e-05 | D12: =Other!D$34 -> 3.453111e-05 | E12: =Other!E$34 -> 3.5561918e-05 | F12: =Other!F$34 -> 3.6621787e-05 | G12: =Other!G$34 -> 3.7711483e-05 | H12: =Other!H$34 -> 3.8831793e-05 | I12: =Other!I$34 -> 3.9983518e-05 | ... ALM12: =Other!ALM$34 -> 0.99864325
A13: glass and glass products 231 | B13: =Other!B$34 -> 2.3404821e-05 | C13: =Other!C$34 -> 3.3528617e-05 | D13: =Other!D$34 -> 3.453111e-05 | E13: =Other!E$34 -> 3.5561918e-05 | F13: =Other!F$34 -> 3.6621787e-05 | G13: =Other!G$34 -> 3.7711483e-05 | H13: =Other!H$34 -> 3.8831793e-05 | I13: =Other!I$34 -> 3.9983518e-05 | ... ALM13: =Other!ALM$34 -> 0.99864325
A14: cement and other nonmetallic minerals 239 | B14: =INDEX('By Industry'!$C$3:$CP$3,MATCH('CECRCbI-process'!B1,'By Industry'!$C$4:$CP$4,1)) -> 0 | C14: =INDEX('By Industry'!$C$3:$CP$3,MATCH('CECRCbI-process'!C1,'By Industry'!$C$4:$CP$4,1)) -> 0 | D14: =INDEX('By Industry'!$C$3:$CP$3,MATCH('CECRCbI-process'!D1,'By Industry'!$C$4:$CP$4,1)) -> 0 | E14: =INDEX('By Industry'!$C$3:$CP$3,MATCH('CECRCbI-process'!E1,'By Industry'!$C$4:$CP$4,1)) -> 0 | F14: =INDEX('By Industry'!$C$3:$CP$3,MATCH('CECRCbI-process'!F1,'By Industry'!$C$4:$CP$4,1)) -> 0 | G14: =INDEX('By Industry'!$C$3:$CP$3,MATCH('CECRCbI-process'!G1,'By Industry'!$C$4:$CP$4,1)) -> 0 | H14: =INDEX('By Industry'!$C$3:$CP$3,MATCH('CECRCbI-process'!H1,'By Industry'!$C$4:$CP$4,1)) -> 0 | I14: =INDEX('By Industry'!$C$3:$CP$3,MATCH('CECRCbI-process'!I1,'By Industry'!$C$4:$CP$4,1)) -> 0 | ... ALM14: =INDEX('By Industry'!$C$3:$CP$3,MATCH('CECRCbI-process'!ALM1,'By Industry'!$C$4:$CP$4,1)) -> 1
A15: iron and steel 241 | B15: =INDEX('By Industry'!$C$23:$CP$23,MATCH('CECRCbI-process'!B1,'By Industry'!$C$24:$CP$24,1)) -> 0 | C15: =INDEX('By Industry'!$C$23:$CP$23,MATCH('CECRCbI-process'!C1,'By Industry'!$C$24:$CP$24,1)) -> 0 | D15: =INDEX('By Industry'!$C$23:$CP$23,MATCH('CECRCbI-process'!D1,'By Industry'!$C$24:$CP$24,1)) -> 0 | E15: =INDEX('By Industry'!$C$23:$CP$23,MATCH('CECRCbI-process'!E1,'By Industry'!$C$24:$CP$24,1)) -> 0 | F15: =INDEX('By Industry'!$C$23:$CP$23,MATCH('CECRCbI-process'!F1,'By Industry'!$C$24:$CP$24,1)) -> 0 | G15: =INDEX('By Industry'!$C$23:$CP$23,MATCH('CECRCbI-process'!G1,'By Industry'!$C$24:$CP$24,1)) -> 0 | H15: =INDEX('By Industry'!$C$23:$CP$23,MATCH('CECRCbI-process'!H1,'By Industry'!$C$24:$CP$24,1)) -> 0 | I15: =INDEX('By Industry'!$C$23:$CP$23,MATCH('CECRCbI-process'!I1,'By Industry'!$C$24:$CP$24,1)) -> 0 | ... ALM15: =INDEX('By Industry'!$C$23:$CP$23,MATCH('CECRCbI-process'!ALM1,'By Industry'!$C$24:$CP$24,1)) -> 0.59489255
A16: other metals 242 | B16: =Other!B$34 -> 2.3404821e-05 | C16: =Other!C$34 -> 3.3528617e-05 | D16: =Other!D$34 -> 3.453111e-05 | E16: =Other!E$34 -> 3.5561918e-05 | F16: =Other!F$34 -> 3.6621787e-05 | G16: =Other!G$34 -> 3.7711483e-05 | H16: =Other!H$34 -> 3.8831793e-05 | I16: =Other!I$34 -> 3.9983518e-05 | ... ALM16: =Other!ALM$34 -> 0.99864325
A17: metal products except machinery and vehicles 25 | B17: =Other!B$34 -> 2.3404821e-05 | C17: =Other!C$34 -> 3.3528617e-05 | D17: =Other!D$34 -> 3.453111e-05 | E17: =Other!E$34 -> 3.5561918e-05 | F17: =Other!F$34 -> 3.6621787e-05 | G17: =Other!G$34 -> 3.7711483e-05 | H17: =Other!H$34 -> 3.8831793e-05 | I17: =Other!I$34 -> 3.9983518e-05 | ... ALM17: =Other!ALM$34 -> 0.99864325
A18: computers and electronics 26 | B18: =Other!B$34 -> 2.3404821e-05 | C18: =Other!C$34 -> 3.3528617e-05 | D18: =Other!D$34 -> 3.453111e-05 | E18: =Other!E$34 -> 3.5561918e-05 | F18: =Other!F$34 -> 3.6621787e-05 | G18: =Other!G$34 -> 3.7711483e-05 | H18: =Other!H$34 -> 3.8831793e-05 | I18: =Other!I$34 -> 3.9983518e-05 | ... ALM18: =Other!ALM$34 -> 0.99864325
A19: appliances and electrical equipment 27 | B19: =Other!B$34 -> 2.3404821e-05 | C19: =Other!C$34 -> 3.3528617e-05 | D19: =Other!D$34 -> 3.453111e-05 | E19: =Other!E$34 -> 3.5561918e-05 | F19: =Other!F$34 -> 3.6621787e-05 | G19: =Other!G$34 -> 3.7711483e-05 | H19: =Other!H$34 -> 3.8831793e-05 | I19: =Other!I$34 -> 3.9983518e-05 | ... ALM19: =Other!ALM$34 -> 0.99864325
A20: other machinery 28 | B20: =Other!B$34 -> 2.3404821e-05 | C20: =Other!C$34 -> 3.3528617e-05 | D20: =Other!D$34 -> 3.453111e-05 | E20: =Other!E$34 -> 3.5561918e-05 | F20: =Other!F$34 -> 3.6621787e-05 | G20: =Other!G$34 -> 3.7711483e-05 | H20: =Other!H$34 -> 3.8831793e-05 | I20: =Other!I$34 -> 3.9983518e-05 | ... ALM20: =Other!ALM$34 -> 0.99864325
A21: road vehicles 29 | B21: =Other!B$34 -> 2.3404821e-05 | C21: =Other!C$34 -> 3.3528617e-05 | D21: =Other!D$34 -> 3.453111e-05 | E21: =Other!E$34 -> 3.5561918e-05 | F21: =Other!F$34 -> 3.6621787e-05 | G21: =Other!G$34 -> 3.7711483e-05 | H21: =Other!H$34 -> 3.8831793e-05 | I21: =Other!I$34 -> 3.9983518e-05 | ... ALM21: =Other!ALM$34 -> 0.99864325
A22: nonroad vehicles 30 | B22: =Other!B$34 -> 2.3404821e-05 | C22: =Other!C$34 -> 3.3528617e-05 | D22: =Other!D$34 -> 3.453111e-05 | E22: =Other!E$34 -> 3.5561918e-05 | F22: =Other!F$34 -> 3.6621787e-05 | G22: =Other!G$34 -> 3.7711483e-05 | H22: =Other!H$34 -> 3.8831793e-05 | I22: =Other!I$34 -> 3.9983518e-05 | ... ALM22: =Other!ALM$34 -> 0.99864325
A23: other manufacturing 31T33 | B23: =Other!B$34 -> 2.3404821e-05 | C23: =Other!C$34 -> 3.3528617e-05 | D23: =Other!D$34 -> 3.453111e-05 | E23: =Other!E$34 -> 3.5561918e-05 | F23: =Other!F$34 -> 3.6621787e-05 | G23: =Other!G$34 -> 3.7711483e-05 | H23: =Other!H$34 -> 3.8831793e-05 | I23: =Other!I$34 -> 3.9983518e-05 | ... ALM23: =Other!ALM$34 -> 0.99864325
A24: energy pipelines and gas processing 352T353 | B24: =Other!B$34 -> 2.3404821e-05 | C24: =Other!C$34 -> 3.3528617e-05 | D24: =Other!D$34 -> 3.453111e-05 | E24: =Other!E$34 -> 3.5561918e-05 | F24: =Other!F$34 -> 3.6621787e-05 | G24: =Other!G$34 -> 3.7711483e-05 | H24: =Other!H$34 -> 3.8831793e-05 | I24: =Other!I$34 -> 3.9983518e-05 | ... ALM24: =Other!ALM$34 -> 0.99864325
A25: water and waste 36T39 | B25: =Other!B$34 -> 2.3404821e-05 | C25: =Other!C$34 -> 3.3528617e-05 | D25: =Other!D$34 -> 3.453111e-05 | E25: =Other!E$34 -> 3.5561918e-05 | F25: =Other!F$34 -> 3.6621787e-05 | G25: =Other!G$34 -> 3.7711483e-05 | H25: =Other!H$34 -> 3.8831793e-05 | I25: =Other!I$34 -> 3.9983518e-05 | ... ALM25: =Other!ALM$34 -> 0.99864325
A26: construction 41T43 | B26: =Other!B$34 -> 2.3404821e-05 | C26: =Other!C$34 -> 3.3528617e-05 | D26: =Other!D$34 -> 3.453111e-05 | E26: =Other!E$34 -> 3.5561918e-05 | F26: =Other!F$34 -> 3.6621787e-05 | G26: =Other!G$34 -> 3.7711483e-05 | H26: =Other!H$34 -> 3.8831793e-05 | I26: =Other!I$34 -> 3.9983518e-05 | ... ALM26: =Other!ALM$34 -> 0.99864325

Sheet CECRCbI-energy
A1: CCS retrofitting percentage by cost (2012$/ton) | B1: 1 | C1: 2 | D1: 3 | E1: 4 | F1: 5 | G1: 6 | H1: 7 | I1: 8 | J1: 9 | K1: 10 | L1: 11 | M1: 12 | N1: 13 | O1: 14 | P1: 15 | Q1: 16 | R1: 17 | S1: 18 | T1: 19 | U1: 20 | V1: 21 | W1: 22 | X1: 23 | Y1: 24 | Z1: 25 | AA1: 26 | AB1: 27 | AC1: 28 | AD1: 29 | AE1: 30 | AF1: 31 | AG1: 32 | AH1: 33 | AI1: 34 | AJ1: 35 | AK1: 36 | AL1: 37 | AM1: 38 | AN1: 39 | AO1: 40 | AP1: 41 | AQ1: 42 | AR1: 43 | AS1: 44 | AT1: 45 | AU1: 46 | AV1: 47 | AW1: 48 | AX1: 49 | AY1: 50 | AZ1: 51 | BA1: 52 | BB1: 53 | BC1: 54 | BD1: 55 | BE1: 56 | BF1: 57 | BG1: 58 | BH1: 59 | BI1: 60 | BJ1: 61 | BK1: 62 | BL1: 63 | BM1: 64 | BN1: 65 | BO1: 66 | BP1: 67 | BQ1: 68 | BR1: 69 | BS1: 70 | BT1: 71 | BU1: 72 | BV1: 73 | BW1: 74 | BX1: 75 | BY1: 76 | BZ1: 77 | CA1: 78 | CB1: 79 | CC1: 80 | CD1: 81 | CE1: 82 | CF1: 83 | CG1: 84 | CH1: 85 | CI1: 86 | CJ1: 87 | CK1: 88 | CL1: 89 | CM1: 90 | CN1: 91 | CO1: 92 | CP1: 93 | CQ1: 94 | CR1: 95 | CS1: 96 | CT1: 97 | CU1: 98 | CV1: 99 | CW1: 100 | CX1: 101 | CY1: 102 | CZ1: 103 | DA1: 104 | DB1: 105 | DC1: 106 | DD1: 107 | DE1: 108 | DF1: 109 | DG1: 110 | DH1: 111 | DI1: 112 | DJ1: 113 | DK1: 114 | DL1: 115 | DM1: 116 | DN1: 117 | DO1: 118 | DP1: 119 | DQ1: 120 | DR1: 121 | DS1: 122 | DT1: 123 | DU1: 124 | DV1: 125 | DW1: 126 | DX1: 127 | DY1: 128 | DZ1: 129 | EA1: 130 | EB1: 131 | EC1: 132 | ED1: 133 | EE1: 134 | EF1: 135 | EG1: 136 | EH1: 137 | EI1: 138 | EJ1: 139 | EK1: 140 | EL1: 141 | EM1: 142 | EN1: 143 | EO1: 144 | EP1: 145 | EQ1: 146 | ER1: 147 | ES1: 148 | ET1: 149 | EU1: 150 | EV1: 151 | EW1: 152 | EX1: 153 | EY1: 154 | EZ1: 155 | FA1: 156 | FB1: 157 | FC1: 158 | FD1: 159 | FE1: 160 | FF1: 161 | FG1: 162 | FH1: 163 | FI1: 164 | FJ1: 165 | FK1: 166 | FL1: 167 | FM1: 168 | FN1: 169 | FO1: 170 | FP1: 171 | FQ1: 172 | FR1: 173 | FS1: 174 | FT1: 175 | FU1: 176 | FV1: 177 | FW1: 178 | FX1: 179 | FY1: 180 | FZ1: 181 | GA1: 182 | GB1: 183 | GC1: 184 | GD1: 185 | GE1: 186 | GF1: 187 | GG1: 188 | GH1: 189 | GI1: 190 | GJ1: 191 | GK1: 192 | GL1: 193 | GM1: 194 | GN1: 195 | GO1: 196 | GP1: 197 | GQ1: 198 | GR1: 199 | GS1: 200 | GT1: 201 | GU1: 202 | GV1: 203 | GW1: 204 | GX1: 205 | GY1: 206 | GZ1: 207 | HA1: 208 | HB1: 209 | HC1: 210 | HD1: 211 | HE1: 212 | HF1: 213 | HG1: 214 | HH1: 215 | HI1: 216 | HJ1: 217 | HK1: 218 | HL1: 219 | HM1: 220 | HN1: 221 | HO1: 222 | HP1: 223 | HQ1: 224 | HR1: 225 | HS1: 226 | HT1: 227 | HU1: 228 | HV1: 229 | HW1: 230 | HX1: 231 | HY1: 232 | HZ1: 233 | IA1: 234 | IB1: 235 | IC1: 236 | ID1: 237 | IE1: 238 | IF1: 239 | IG1: 240 | IH1: 241 | II1: 242 | IJ1: 243 | IK1: 244 | IL1: 245 | IM1: 246 | IN1: 247 | IO1: 248 | IP1: 249 | IQ1: 250 | IR1: 251 | IS1: 252 | IT1: 253 | IU1: 254 | IV1: 255 | IW1: 256 | IX1: 257 | IY1: 258 | IZ1: 259 | JA1: 260 | JB1: 261 | JC1: 262 | JD1: 263 | JE1: 264 | JF1: 265 | JG1: 266 | JH1: 267 | JI1: 268 | JJ1: 269 | JK1: 270 | JL1: 271 | JM1: 272 | JN1: 273 | JO1: 274 | JP1: 275 | JQ1: 276 | JR1: 277 | JS1: 278 | JT1: 279 | JU1: 280 | JV1: 281 | JW1: 282 | JX1: 283 | JY1: 284 | JZ1: 285 | KA1: 286 | KB1: 287 | KC1: 288 | KD1: 289 | KE1: 290 | KF1: 291 | KG1: 292 | KH1: 293 | KI1: 294 | KJ1: 295 | KK1: 296 | KL1: 297 | KM1: 298 | KN1: 299 | KO1: 300 | KP1: 301 | KQ1: 302 | KR1: 303 | KS1: 304 | KT1: 305 | KU1: 306 | KV1: 307 | KW1: 308 | KX1: 309 | KY1: 310 | KZ1: 311 | LA1: 312 | LB1: 313 | LC1: 314 | LD1: 315 | LE1: 316 | LF1: 317 | LG1: 318 | LH1: 319 | LI1: 320 | LJ1: 321 | LK1: 322 | LL1: 323 | LM1: 324 | LN1: 325 | LO1: 326 | LP1: 327 | LQ1: 328 | LR1: 329 | LS1: 330 | LT1: 331 | LU1: 332 | LV1: 333 | LW1: 334 | LX1: 335 | LY1: 336 | LZ1: 337 | MA1: 338 | MB1: 339 | MC1: 340 | MD1: 341 | ME1: 342 | MF1: 343 | MG1: 344 | MH1: 345 | MI1: 346 | MJ1: 347 | MK1: 348 | ML1: 349 | MM1: 350 | MN1: 351 | MO1: 352 | MP1: 353 | MQ1: 354 | MR1: 355 | MS1: 356 | MT1: 357 | MU1: 358 | MV1: 359 | MW1: 360 | MX1: 361 | MY1: 362 | MZ1: 363 | NA1: 364 | NB1: 365 | NC1: 366 | ND1: 367 | NE1: 368 | NF1: 369 | NG1: 370 | NH1: 371 | NI1: 372 | NJ1: 373 | NK1: 374 | NL1: 375 | NM1: 376 | NN1: 377 | NO1: 378 | NP1: 379 | NQ1: 380 | NR1: 381 | NS1: 382 | NT1: 383 | NU1: 384 | NV1: 385 | NW1: 386 | NX1: 387 | NY1: 388 | NZ1: 389 | OA1: 390 | OB1: 391 | OC1: 392 | OD1: 393 | OE1: 394 | OF1: 395 | OG1: 396 | OH1: 397 | OI1: 398 | OJ1: 399 | OK1: 400 | OL1: 401 | OM1: 402 | ON1: 403 | OO1: 404 | OP1: 405 | OQ1: 406 | OR1: 407 | OS1: 408 | OT1: 409 | OU1: 410 | OV1: 411 | OW1: 412 | OX1: 413 | OY1: 414 | OZ1: 415 | PA1: 416 | PB1: 417 | PC1: 418 | PD1: 419 | PE1: 420 | PF1: 421 | PG1: 422 | PH1: 423 | PI1: 424 | PJ1: 425 | PK1: 426 | PL1: 427 | PM1: 428 | PN1: 429 | PO1: 430 | PP1: 431 | PQ1: 432 | PR1: 433 | PS1: 434 | PT1: 435 | PU1: 436 | PV1: 437 | PW1: 438 | PX1: 439 | PY1: 440 | PZ1: 441 | QA1: 442 | QB1: 443 | QC1: 444 | QD1: 445 | QE1: 446 | QF1: 447 | QG1: 448 | QH1: 449 | QI1: 450 | QJ1: 451 | QK1: 452 | QL1: 453 | QM1: 454 | QN1: 455 | QO1: 456 | QP1: 457 | QQ1: 458 | QR1: 459 | QS1: 460 | QT1: 461 | QU1: 462 | QV1: 463 | QW1: 464 | QX1: 465 | QY1: 466 | QZ1: 467 | RA1: 468 | RB1: 469 | RC1: 470 | RD1: 471 | RE1: 472 | RF1: 473 | RG1: 474 | RH1: 475 | RI1: 476 | RJ1: 477 | RK1: 478 | RL1: 479 | RM1: 480 | RN1: 481 | RO1: 482 | RP1: 483 | RQ1: 484 | RR1: 485 | RS1: 486 | RT1: 487 | RU1: 488 | RV1: 489 | RW1: 490 | RX1: 491 | RY1: 492 | RZ1: 493 | SA1: 494 | SB1: 495 | SC1: 496 | SD1: 497 | SE1: 498 | SF1: 499 | SG1: 500 | SH1: 501 | SI1: 502 | SJ1: 503 | SK1: 504 | SL1: 505 | SM1: 506 | SN1: 507 | SO1: 508 | SP1: 509 | SQ1: 510 | SR1: 511 | SS1: 512 | ST1: 513 | SU1: 514 | SV1: 515 | SW1: 516 | SX1: 517 | SY1: 518 | SZ1: 519 | TA1: 520 | TB1: 521 | TC1: 522 | TD1: 523 | TE1: 524 | TF1: 525 | TG1: 526 | TH1: 527 | TI1: 528 | TJ1: 529 | TK1: 530 | TL1: 531 | TM1: 532 | TN1: 533 | TO1: 534 | TP1: 535 | TQ1: 536 | TR1: 537 | TS1: 538 | TT1: 539 | TU1: 540 | TV1: 541 | TW1: 542 | TX1: 543 | TY1: 544 | TZ1: 545 | UA1: 546 | UB1: 547 | UC1: 548 | UD1: 549 | UE1: 550 | UF1: 551 | UG1: 552 | UH1: 553 | UI1: 554 | UJ1: 555 | UK1: 556 | UL1: 557 | UM1: 558 | UN1: 559 | UO1: 560 | UP1: 561 | UQ1: 562 | UR1: 563 | US1: 564 | UT1: 565 | UU1: 566 | UV1: 567 | UW1: 568 | UX1: 569 | UY1: 570 | UZ1: 571 | VA1: 572 | VB1: 573 | VC1: 574 | VD1: 575 | VE1: 576 | VF1: 577 | VG1: 578 | VH1: 579 | VI1: 580 | VJ1: 581 | VK1: 582 | VL1: 583 | VM1: 584 | VN1: 585 | VO1: 586 | VP1: 587 | VQ1: 588 | VR1: 589 | VS1: 590 | VT1: 591 | VU1: 592 | VV1: 593 | VW1: 594 | VX1: 595 | VY1: 596 | VZ1: 597 | WA1: 598 | WB1: 599 | WC1: 600 | WD1: 601 | WE1: 602 | WF1: 603 | WG1: 604 | WH1: 605 | WI1: 606 | WJ1: 607 | WK1: 608 | WL1: 609 | WM1: 610 | WN1: 611 | WO1: 612 | WP1: 613 | WQ1: 614 | WR1: 615 | WS1: 616 | WT1: 617 | WU1: 618 | WV1: 619 | WW1: 620 | WX1: 621 | WY1: 622 | WZ1: 623 | XA1: 624 | XB1: 625 | XC1: 626 | XD1: 627 | XE1: 628 | XF1: 629 | XG1: 630 | XH1: 631 | XI1: 632 | XJ1: 633 | XK1: 634 | XL1: 635 | XM1: 636 | XN1: 637 | XO1: 638 | XP1: 639 | XQ1: 640 | XR1: 641 | XS1: 642 | XT1: 643 | XU1: 644 | XV1: 645 | XW1: 646 | XX1: 647 | XY1: 648 | XZ1: 649 | YA1: 650 | YB1: 651 | YC1: 652 | YD1: 653 | YE1: 654 | YF1: 655 | YG1: 656 | YH1: 657 | YI1: 658 | YJ1: 659 | YK1: 660 | YL1: 661 | YM1: 662 | YN1: 663 | YO1: 664 | YP1: 665 | YQ1: 666 | YR1: 667 | YS1: 668 | YT1: 669 | YU1: 670 | YV1: 671 | YW1: 672 | YX1: 673 | YY1: 674 | YZ1: 675 | ZA1: 676 | ZB1: 677 | ZC1: 678 | ZD1: 679 | ZE1: 680 | ZF1: 681 | ZG1: 682 | ZH1: 683 | ZI1: 684 | ZJ1: 685 | ZK1: 686 | ZL1: 687 | ZM1: 688 | ZN1: 689 | ZO1: 690 | ZP1: 691 | ZQ1: 692 | ZR1: 693 | ZS1: 694 | ZT1: 695 | ZU1: 696 | ZV1: 697 | ZW1: 698 | ZX1: 699 | ZY1: 700 | ZZ1: 701 | AAA1: 702 | AAB1: 703 | AAC1: 704 | AAD1: 705 | AAE1: 706 | AAF1: 707 | AAG1: 708 | AAH1: 709 | AAI1: 710 | AAJ1: 711 | AAK1: 712 | AAL1: 713 | AAM1: 714 | AAN1: 715 | AAO1: 716 | AAP1: 717 | AAQ1: 718 | AAR1: 719 | AAS1: 720 | AAT1: 721 | AAU1: 722 | AAV1: 723 | AAW1: 724 | AAX1: 725 | AAY1: 726 | AAZ1: 727 | ABA1: 728 | ABB1: 729 | ABC1: 730 | ABD1: 731 | ABE1: 732 | ABF1: 733 | ABG1: 734 | ABH1: 735 | ABI1: 736 | ABJ1: 737 | ABK1: 738 | ABL1: 739 | ABM1: 740 | ABN1: 741 | ABO1: 742 | ABP1: 743 | ABQ1: 744 | ABR1: 745 | ABS1: 746 | ABT1: 747 | ABU1: 748 | ABV1: 749 | ABW1: 750 | ABX1: 751 | ABY1: 752 | ABZ1: 753 | ACA1: 754 | ACB1: 755 | ACC1: 756 | ACD1: 757 | ACE1: 758 | ACF1: 759 | ACG1: 760 | ACH1: 761 | ACI1: 762 | ACJ1: 763 | ACK1: 764 | ACL1: 765 | ACM1: 766 | ACN1: 767 | ACO1: 768 | ACP1: 769 | ACQ1: 770 | ACR1: 771 | ACS1: 772 | ACT1: 773 | ACU1: 774 | ACV1: 775 | ACW1: 776 | ACX1: 777 | ACY1: 778 | ACZ1: 779 | ADA1: 780 | ADB1: 781 | ADC1: 782 | ADD1: 783 | ADE1: 784 | ADF1: 785 | ADG1: 786 | ADH1: 787 | ADI1: 788 | ADJ1: 789 | ADK1: 790 | ADL1: 791 | ADM1: 792 | ADN1: 793 | ADO1: 794 | ADP1: 795 | ADQ1: 796 | ADR1: 797 | ADS1: 798 | ADT1: 799 | ADU1: 800 | ADV1: 801 | ADW1: 802 | ADX1: 803 | ADY1: 804 | ADZ1: 805 | AEA1: 806 | AEB1: 807 | AEC1: 808 | AED1: 809 | AEE1: 810 | AEF1: 811 | AEG1: 812 | AEH1: 813 | AEI1: 814 | AEJ1: 815 | AEK1: 816 | AEL1: 817 | AEM1: 818 | AEN1: 819 | AEO1: 820 | AEP1: 821 | AEQ1: 822 | AER1: 823 | AES1: 824 | AET1: 825 | AEU1: 826 | AEV1: 827 | AEW1: 828 | AEX1: 829 | AEY1: 830 | AEZ1: 831 | AFA1: 832 | AFB1: 833 | AFC1: 834 | AFD1: 835 | AFE1: 836 | AFF1: 837 | AFG1: 838 | AFH1: 839 | AFI1: 840 | AFJ1: 841 | AFK1: 842 | AFL1: 843 | AFM1: 844 | AFN1: 845 | AFO1: 846 | AFP1: 847 | AFQ1: 848 | AFR1: 849 | AFS1: 850 | AFT1: 851 | AFU1: 852 | AFV1: 853 | AFW1: 854 | AFX1: 855 | AFY1: 856 | AFZ1: 857 | AGA1: 858 | AGB1: 859 | AGC1: 860 | AGD1: 861 | AGE1: 862 | AGF1: 863 | AGG1: 864 | AGH1: 865 | AGI1: 866 | AGJ1: 867 | AGK1: 868 | AGL1: 869 | AGM1: 870 | AGN1: 871 | AGO1: 872 | AGP1: 873 | AGQ1: 874 | AGR1: 875 | AGS1: 876 | AGT1: 877 | AGU1: 878 | AGV1: 879 | AGW1: 880 | AGX1: 881 | AGY1: 882 | AGZ1: 883 | AHA1: 884 | AHB1: 885 | AHC1: 886 | AHD1: 887 | AHE1: 888 | AHF1: 889 | AHG1: 890 | AHH1: 891 | AHI1: 892 | AHJ1: 893 | AHK1: 894 | AHL1: 895 | AHM1: 896 | AHN1: 897 | AHO1: 898 | AHP1: 899 | AHQ1: 900 | AHR1: 901 | AHS1: 902 | AHT1: 903 | AHU1: 904 | AHV1: 905 | AHW1: 906 | AHX1: 907 | AHY1: 908 | AHZ1: 909 | AIA1: 910 | AIB1: 911 | AIC1: 912 | AID1: 913 | AIE1: 914 | AIF1: 915 | AIG1: 916 | AIH1: 917 | AII1: 918 | AIJ1: 919 | AIK1: 920 | AIL1: 921 | AIM1: 922 | AIN1: 923 | AIO1: 924 | AIP1: 925 | AIQ1: 926 | AIR1: 927 | AIS1: 928 | AIT1: 929 | AIU1: 930 | AIV1: 931 | AIW1: 932 | AIX1: 933 | AIY1: 934 | AIZ1: 935 | AJA1: 936 | AJB1: 937 | AJC1: 938 | AJD1: 939 | AJE1: 940 | AJF1: 941 | AJG1: 942 | AJH1: 943 | AJI1: 944 | AJJ1: 945 | AJK1: 946 | AJL1: 947 | AJM1: 948 | AJN1: 949 | AJO1: 950 | AJP1: 951 | AJQ1: 952 | AJR1: 953 | AJS1: 954 | AJT1: 955 | AJU1: 956 | AJV1: 957 | AJW1: 958 | AJX1: 959 | AJY1: 960 | AJZ1: 961 | AKA1: 962 | AKB1: 963 | AKC1: 964 | AKD1: 965 | AKE1: 966 | AKF1: 967 | AKG1: 968 | AKH1: 969 | AKI1: 970 | AKJ1: 971 | AKK1: 972 | AKL1: 973 | AKM1: 974 | AKN1: 975 | AKO1: 976 | AKP1: 977 | AKQ1: 978 | AKR1: 979 | AKS1: 980 | AKT1: 981 | AKU1: 982 | AKV1: 983 | AKW1: 984 | AKX1: 985 | AKY1: 986 | AKZ1: 987 | ALA1: 988 | ALB1: 989 | ALC1: 990 | ALD1: 991 | ALE1: 992 | ALF1: 993 | ALG1: 994 | ALH1: 995 | ALI1: 996 | ALJ1: 997 | ALK1: 998 | ALL1: 999 | ALM1: 1000
A2: agriculture and forestry 01T03 | B2: =Other!B$34 -> 2.3404821e-05 | C2: =Other!C$34 -> 3.3528617e-05 | D2: =Other!D$34 -> 3.453111e-05 | E2: =Other!E$34 -> 3.5561918e-05 | F2: =Other!F$34 -> 3.6621787e-05 | G2: =Other!G$34 -> 3.7711483e-05 | H2: =Other!H$34 -> 3.8831793e-05 | I2: =Other!I$34 -> 3.9983518e-05 | ... ALM2: =Other!ALM$34 -> 0.99864325
A3: coal mining 05 | B3: =Other!B$34 -> 2.3404821e-05 | C3: =Other!C$34 -> 3.3528617e-05 | D3: =Other!D$34 -> 3.453111e-05 | E3: =Other!E$34 -> 3.5561918e-05 | F3: =Other!F$34 -> 3.6621787e-05 | G3: =Other!G$34 -> 3.7711483e-05 | H3: =Other!H$34 -> 3.8831793e-05 | I3: =Other!I$34 -> 3.9983518e-05 | ... ALM3: =Other!ALM$34 -> 0.99864325
A4: oil and gas extraction 06 | B4: =Other!B$34 -> 2.3404821e-05 | C4: =Other!C$34 -> 3.3528617e-05 | D4: =Other!D$34 -> 3.453111e-05 | E4: =Other!E$34 -> 3.5561918e-05 | F4: =Other!F$34 -> 3.6621787e-05 | G4: =Other!G$34 -> 3.7711483e-05 | H4: =Other!H$34 -> 3.8831793e-05 | I4: =Other!I$34 -> 3.9983518e-05 | ... ALM4: =Other!ALM$34 -> 0.99864325
A5: other mining and quarrying 07T08 | B5: =Other!B$34 -> 2.3404821e-05 | C5: =Other!C$34 -> 3.3528617e-05 | D5: =Other!D$34 -> 3.453111e-05 | E5: =Other!E$34 -> 3.5561918e-05 | F5: =Other!F$34 -> 3.6621787e-05 | G5: =Other!G$34 -> 3.7711483e-05 | H5: =Other!H$34 -> 3.8831793e-05 | I5: =Other!I$34 -> 3.9983518e-05 | ... ALM5: =Other!ALM$34 -> 0.99864325
A6: food beverage and tobacco 10T12 | B6: =Other!B$34 -> 2.3404821e-05 | C6: =Other!C$34 -> 3.3528617e-05 | D6: =Other!D$34 -> 3.453111e-05 | E6: =Other!E$34 -> 3.5561918e-05 | F6: =Other!F$34 -> 3.6621787e-05 | G6: =Other!G$34 -> 3.7711483e-05 | H6: =Other!H$34 -> 3.8831793e-05 | I6: =Other!I$34 -> 3.9983518e-05 | ... ALM6: =Other!ALM$34 -> 0.99864325
A7: textiles apparel and leather 13T15 | B7: =Other!B$34 -> 2.3404821e-05 | C7: =Other!C$34 -> 3.3528617e-05 | D7: =Other!D$34 -> 3.453111e-05 | E7: =Other!E$34 -> 3.5561918e-05 | F7: =Other!F$34 -> 3.6621787e-05 | G7: =Other!G$34 -> 3.7711483e-05 | H7: =Other!H$34 -> 3.8831793e-05 | I7: =Other!I$34 -> 3.9983518e-05 | ... ALM7: =Other!ALM$34 -> 0.99864325
A8: wood products 16 | B8: =Other!B$34 -> 2.3404821e-05 | C8: =Other!C$34 -> 3.3528617e-05 | D8: =Other!D$34 -> 3.453111e-05 | E8: =Other!E$34 -> 3.5561918e-05 | F8: =Other!F$34 -> 3.6621787e-05 | G8: =Other!G$34 -> 3.7711483e-05 | H8: =Other!H$34 -> 3.8831793e-05 | I8: =Other!I$34 -> 3.9983518e-05 | ... ALM8: =Other!ALM$34 -> 0.99864325
A9: pulp paper and printing 17T18 | B9: =Other!B$34 -> 2.3404821e-05 | C9: =Other!C$34 -> 3.3528617e-05 | D9: =Other!D$34 -> 3.453111e-05 | E9: =Other!E$34 -> 3.5561918e-05 | F9: =Other!F$34 -> 3.6621787e-05 | G9: =Other!G$34 -> 3.7711483e-05 | H9: =Other!H$34 -> 3.8831793e-05 | I9: =Other!I$34 -> 3.9983518e-05 | ... ALM9: =Other!ALM$34 -> 0.99864325
A10: refined petroleum and coke 19 | B10: =INDEX('By Industry'!$C$27:$KX$27,MATCH('CECRCbI-process'!B1,'By Industry'!$C$28:$KX$28,1)) -> 0 | C10: =INDEX('By Industry'!$C$27:$KX$27,MATCH('CECRCbI-process'!C1,'By Industry'!$C$28:$KX$28,1)) -> 0 | D10: =INDEX('By Industry'!$C$27:$KX$27,MATCH('CECRCbI-process'!D1,'By Industry'!$C$28:$KX$28,1)) -> 0 | E10: =INDEX('By Industry'!$C$27:$KX$27,MATCH('CECRCbI-process'!E1,'By Industry'!$C$28:$KX$28,1)) -> 0 | F10: =INDEX('By Industry'!$C$27:$KX$27,MATCH('CECRCbI-process'!F1,'By Industry'!$C$28:$KX$28,1)) -> 0 | G10: =INDEX('By Industry'!$C$27:$KX$27,MATCH('CECRCbI-process'!G1,'By Industry'!$C$28:$KX$28,1)) -> 0 | H10: =INDEX('By Industry'!$C$27:$KX$27,MATCH('CECRCbI-process'!H1,'By Industry'!$C$28:$KX$28,1)) -> 0 | I10: =INDEX('By Industry'!$C$27:$KX$27,MATCH('CECRCbI-process'!I1,'By Industry'!$C$28:$KX$28,1)) -> 0 | ... ALM10: =INDEX('By Industry'!$C$27:$KX$27,MATCH('CECRCbI-process'!ALM1,'By Industry'!$C$28:$KX$28,1)) -> 0.71684337
A11: chemicals 20 | B11: =Other!B$34 -> 2.3404821e-05 | C11: =Other!C$34 -> 3.3528617e-05 | D11: =Other!D$34 -> 3.453111e-05 | E11: =Other!E$34 -> 3.5561918e-05 | F11: =Other!F$34 -> 3.6621787e-05 | G11: =Other!G$34 -> 3.7711483e-05 | H11: =Other!H$34 -> 3.8831793e-05 | I11: =Other!I$34 -> 3.9983518e-05 | ... ALM11: =Other!ALM$34 -> 0.99864325
A12: rubber and plastic products 22 | B12: =Other!B$34 -> 2.3404821e-05 | C12: =Other!C$34 -> 3.3528617e-05 | D12: =Other!D$34 -> 3.453111e-05 | E12: =Other!E$34 -> 3.5561918e-05 | F12: =Other!F$34 -> 3.6621787e-05 | G12: =Other!G$34 -> 3.7711483e-05 | H12: =Other!H$34 -> 3.8831793e-05 | I12: =Other!I$34 -> 3.9983518e-05 | ... ALM12: =Other!ALM$34 -> 0.99864325
A13: glass and glass products 231 | B13: =Other!B$34 -> 2.3404821e-05 | C13: =Other!C$34 -> 3.3528617e-05 | D13: =Other!D$34 -> 3.453111e-05 | E13: =Other!E$34 -> 3.5561918e-05 | F13: =Other!F$34 -> 3.6621787e-05 | G13: =Other!G$34 -> 3.7711483e-05 | H13: =Other!H$34 -> 3.8831793e-05 | I13: =Other!I$34 -> 3.9983518e-05 | ... ALM13: =Other!ALM$34 -> 0.99864325
A14: cement and other nonmetallic minerals 239 | B14: =Other!B$34 -> 2.3404821e-05 | C14: =Other!C$34 -> 3.3528617e-05 | D14: =Other!D$34 -> 3.453111e-05 | E14: =Other!E$34 -> 3.5561918e-05 | F14: =Other!F$34 -> 3.6621787e-05 | G14: =Other!G$34 -> 3.7711483e-05 | H14: =Other!H$34 -> 3.8831793e-05 | I14: =Other!I$34 -> 3.9983518e-05 | ... ALM14: =Other!ALM$34 -> 0.99864325
A15: iron and steel 241 | B15: =Other!B$34 -> 2.3404821e-05 | C15: =Other!C$34 -> 3.3528617e-05 | D15: =Other!D$34 -> 3.453111e-05 | E15: =Other!E$34 -> 3.5561918e-05 | F15: =Other!F$34 -> 3.6621787e-05 | G15: =Other!G$34 -> 3.7711483e-05 | H15: =Other!H$34 -> 3.8831793e-05 | I15: =Other!I$34 -> 3.9983518e-05 | ... ALM15: =Other!ALM$34 -> 0.99864325
A16: other metals 242 | B16: =Other!B$34 -> 2.3404821e-05 | C16: =Other!C$34 -> 3.3528617e-05 | D16: =Other!D$34 -> 3.453111e-05 | E16: =Other!E$34 -> 3.5561918e-05 | F16: =Other!F$34 -> 3.6621787e-05 | G16: =Other!G$34 -> 3.7711483e-05 | H16: =Other!H$34 -> 3.8831793e-05 | I16: =Other!I$34 -> 3.9983518e-05 | ... ALM16: =Other!ALM$34 -> 0.99864325
A17: metal products except machinery and vehicles 25 | B17: =Other!B$34 -> 2.3404821e-05 | C17: =Other!C$34 -> 3.3528617e-05 | D17: =Other!D$34 -> 3.453111e-05 | E17: =Other!E$34 -> 3.5561918e-05 | F17: =Other!F$34 -> 3.6621787e-05 | G17: =Other!G$34 -> 3.7711483e-05 | H17: =Other!H$34 -> 3.8831793e-05 | I17: =Other!I$34 -> 3.9983518e-05 | ... ALM17: =Other!ALM$34 -> 0.99864325
A18: computers and electronics 26 | B18: =Other!B$34 -> 2.3404821e-05 | C18: =Other!C$34 -> 3.3528617e-05 | D18: =Other!D$34 -> 3.453111e-05 | E18: =Other!E$34 -> 3.5561918e-05 | F18: =Other!F$34 -> 3.6621787e-05 | G18: =Other!G$34 -> 3.7711483e-05 | H18: =Other!H$34 -> 3.8831793e-05 | I18: =Other!I$34 -> 3.9983518e-05 | ... ALM18: =Other!ALM$34 -> 0.99864325
A19: appliances and electrical equipment 27 | B19: =Other!B$34 -> 2.3404821e-05 | C19: =Other!C$34 -> 3.3528617e-05 | D19: =Other!D$34 -> 3.453111e-05 | E19: =Other!E$34 -> 3.5561918e-05 | F19: =Other!F$34 -> 3.6621787e-05 | G19: =Other!G$34 -> 3.7711483e-05 | H19: =Other!H$34 -> 3.8831793e-05 | I19: =Other!I$34 -> 3.9983518e-05 | ... ALM19: =Other!ALM$34 -> 0.99864325
A20: other machinery 28 | B20: =Other!B$34 -> 2.3404821e-05 | C20: =Other!C$34 -> 3.3528617e-05 | D20: =Other!D$34 -> 3.453111e-05 | E20: =Other!E$34 -> 3.5561918e-05 | F20: =Other!F$34 -> 3.6621787e-05 | G20: =Other!G$34 -> 3.7711483e-05 | H20: =Other!H$34 -> 3.8831793e-05 | I20: =Other!I$34 -> 3.9983518e-05 | ... ALM20: =Other!ALM$34 -> 0.99864325
A21: road vehicles 29 | B21: =Other!B$34 -> 2.3404821e-05 | C21: =Other!C$34 -> 3.3528617e-05 | D21: =Other!D$34 -> 3.453111e-05 | E21: =Other!E$34 -> 3.5561918e-05 | F21: =Other!F$34 -> 3.6621787e-05 | G21: =Other!G$34 -> 3.7711483e-05 | H21: =Other!H$34 -> 3.8831793e-05 | I21: =Other!I$34 -> 3.9983518e-05 | ... ALM21: =Other!ALM$34 -> 0.99864325
A22: nonroad vehicles 30 | B22: =Other!B$34 -> 2.3404821e-05 | C22: =Other!C$34 -> 3.3528617e-05 | D22: =Other!D$34 -> 3.453111e-05 | E22: =Other!E$34 -> 3.5561918e-05 | F22: =Other!F$34 -> 3.6621787e-05 | G22: =Other!G$34 -> 3.7711483e-05 | H22: =Other!H$34 -> 3.8831793e-05 | I22: =Other!I$34 -> 3.9983518e-05 | ... ALM22: =Other!ALM$34 -> 0.99864325
... A26: construction 41T43 | B26: =Other!B$34 -> 2.3404821e-05 | C26: =Other!C$34 -> 3.3528617e-05 | D26: =Other!D$34 -> 3.453111e-05 | E26: =Other!E$34 -> 3.5561918e-05 | F26: =Other!F$34 -> 3.6621787e-05 | G26: =Other!G$34 -> 3.7711483e-05 | H26: =Other!H$34 -> 3.8831793e-05 | I26: =Other!I$34 -> 3.9983518e-05 | ... ALM26: =Other!ALM$34 -> 0.99864325
