Workbook
Name Fraction_coal: [1]About!$C$50
Name Percent_rural: [1]About!$A$77
Name Percent_urban: [1]About!$A$76
Name quadrillion: [1]About!$B$79
Name Table4: #REF!
Name Table5: #REF!

Sheet About
A1: ICpUEfEBE Incremental Cost per Unit Energy for Electrified Building Equipment
A3: Sources: | B3: Cost of technologies except commerial heat pumps | D3: Commercial heating and water heating heat pump costs
B4: EIA | D4: NREL
B5: 2018 | D5: 2018
B6: Updated Buildings Sector Appliance and Equipment Costs and Efficiencies | D6: Electrification Futures Study Technology Report Figure Data
B7: https://www.eia.gov/analysis/studies/buildings/equipcosts/pdf/full.pdf | D7: https://data.nrel.gov/system/files/93/EFS_70485_figure_data.xlsx
B8: p. 9, 12, 29, 46, 51, 54, 58, 90, 92, 120, 123 | D8: Tables 22 and 23
B10: Residential building equipment stock and average annual energy consumption | D10: Commercial building equipment load factors
B11: EIA | D11: NREL
B12: 20222023 | D12: 2018
B13: AEO 2022, AEO 2023 | D13: Electrification Futures Study: End-Use Electric Technology Cost and Performance Projections through 2050
B14: https://www.eia.gov/outlooks/aeo/tables_side.php | D14: https://www.nrel.gov/docs/fy18osti/70485.pdf
B15: Tables 4 and 21 | D15: P.90
A17: Notes:
A18: All policy-driven electrification in the EPS is assumed to rely on heat pumps,
A19: not electric resistance heating
A21: Methodology:
A22: For residential buildings, we calculate the average energy used by equipment
A23: of different types, which allows us to find a $/BTU value. We then estimate
A24: the cost of switching to heat pump equipment based on the data from EIA
A25: and annual energy consumption.
A27: For commercial buildings, we lack data on annual energy use, but the NREL
A28: report provides data on annual heating and water heating utilization rates
A29: and the costs are normalized to $/(kBTU/hr) input, so we standardize the costs
A30: from EIA and then estimate the cost per BTU shifted using the annual load factors.
... A52: 2017 to 2012 USD
A53: 0.9366596
A54: 2016 to 2012 USD
A55: 0.95661377

Sheet Source Data>

Sheet EIA Costs
A1: Residential Gas Fired Furnaces
A2: DATA | B2: 2009 | C2: 2015 | D2: 2017 | H2: 2020 | J2: 2030 | L2: 2040 | N2: 2050
B3: Installed Base | C3: Installed Base | D3: Current Standard | E3: Typical | F3: ENERGY STAR (South) | G3: High | H3: Typical | I3: High | J3: Typical | K3: High | L3: Typical | M3: High | N3: Typical | O3: High
A4: Typical Input Capacity (kBtu/h) | B4: 80 | C4: 80 | D4: 80 | E4: 80 | F4: 80 | G4: 80 | H4: 80 | I4: 80 | J4: 80 | K4: 80 | L4: 80 | M4: 80 | N4: 80 | O4: 80
A5: AFUE (%) | B5: 80 | C5: 80 | D5: 80 | E5: 80 | F5: 90 | G5: 99 | H5: 80 | I5: 99 | J5: 80 | K5: 99 | L5: 80 | M5: 99 | N5: 80 | O5: 99
A6: Electric Consumption (kWh/yr)* | B6: 548 | C6: 522 | D6: 470 | E6: 470 | F6: 408 | G6: 418 | H6: 329 | I6: 334 | J6: 329 | K6: 334 | L6: 329 | M6: 334 | N6: 329 | O6: 334
A7: Average Life (yrs)** | B7: 16 | C7: 16 | D7: 16 | E7: 16 | F7: 16 | G7: 16 | H7: 16 | I7: 16 | J7: 16 | K7: 16 | L7: 16 | M7: 16 | N7: 16 | O7: 16
B8: 27 | C8: 27 | D8: 27 | E8: 27 | F8: 27 | G8: 27 | H8: 27 | I8: 27 | J8: 27 | K8: 27 | L8: 27 | M8: 27 | N8: 27 | O8: 27
A9: Retail Equipment Cost (2017$) | B9: 840 | C9: 860 | D9: 890 | E9: 890 | F9: 1150 | G9: 1620 | H9: 1080 | I9: 1620 | J9: 1080 | K9: 1620 | L9: 1080 | M9: 1620 | N9: 1080 | O9: 1620
A10: Total Installed Cost (2017$) | B10: 2000 | C10: 2020 | D10: 2050 | E10: 2050 | F10: 2560 | G10: 3040 | H10: 2240 | I10: 3040 | J10: 2240 | K10: 3040 | L10: 2240 | M10: 3040 | N10: 2240 | O10: 3040
A11: Annual Maintenance Cost (2017$) | B11: 40 | C11: 40 | D11: 40 | E11: 40 | F11: 40 | G11: 40 | H11: 40 | I11: 40 | J11: 40 | K11: 40 | L11: 40 | M11: 40 | N11: 40 | O11: 40
A13: Residential Oil Fired Furnaces
A14: DATA | B14: 2009 | C14: 2015 | D14: 2017 | H14: 2020 | J14: 2030 | L14: 2040 | N14: 2050
B15: Installed Base | C15: Installed Base | D15: Current Standard | E15: Typical | F15: ENERGY STAR | G15: High | H15: Typical | I15: High Typical | K15: High | L15: Typical | M15: High | N15: Typical | O15: High
A16: Typical Input Capacity (kBtu/h) | B16: 105 | C16: 105 | D16: 105 | E16: 105 | F16: 105 | G16: 105 | H16: 105 | I16: 105 | J16: 105 | K16: 105 | L16: 105 | M16: 105 | N16: 105 | O16: 105
A17: AFUE (%) | B17: 80 | C17: 83 | D17: 83 | E17: 83 | F17: 85 | G17: 97 | H17: 83 | I17: 97 | J17: 84 | K17: 97 | L17: 84 | M17: 97 | N17: 84 | O17: 97
A18: Electric Consumption (kWh/yr)* | B18: 490 | C18: 477 | D18: 477 | E18: 477 | F18: 466 | G18: 410 | H18: 477 | I18: 410 | J18: 472 | K18: 410 | L18: 472 | M18: 410 | N18: 472 | O18: 410
A19: Average Life (yrs)** | B19: 20 | C19: 20 | D19: 20 | E19: 20 | F19: 20 | G19: 20 | H19: 20 | I19: 20 | J19: 20 | K19: 20 | L19: 20 | M19: 20 | N19: 20 | O19: 20
B20: 33 | C20: 33 | D20: 33 | E20: 33 | F20: 33 | G20: 33 | H20: 33 | I20: 33 | J20: 33 | K20: 33 | L20: 33 | M20: 33 | N20: 33 | O20: 33
A21: Retail Equipment Cost (2017$) | B21: 2150 | C21: 2200 | D21: 2200 | E21: 2200 | F21: 2250 | G21: 2700 | H21: 2200 | I21: 2700 | J21: 2250 | K21: 2700 | L21: 2250 | M21: 2700 | N21: 2250 | O21: 2700
B22: 2350 | C22: 2900 | D22: 2900 | E22: 2900 | F22: 2950 | G22: 3450 | H22: 2900 | I22: 3450 | J22: 2950 | K22: 3450 | L22: 2950 | M22: 3450 | N22: 2950 | O22: 3450
A23: Total Installed Cost (2017$) | B23: 2700 | C23: 2750 | D23: 2750 | E23: 2750 | F23: 2950 | G23: 4350 | H23: 2750 | I23: 4350 | J23: 2750 | K23: 4350 | L23: 2750 | M23: 4350 | N23: 2750 | O23: 4350
B24: 3400 | C24: 5500 | D24: 5500 | E24: 5500 | F24: 5750 | G24: 8550 | H24: 5500 | I24: 8550 | J24: 5700 | K24: 8550 | L24: 5700 | M24: 8550 | N24: 5700 | O24: 8550
A25: Annual Maintenance Cost (2017$) | B25: 70 | C25: 70 | D25: 70 | E25: 70 | F25: 70 | G25: 200 | H25: 70 | I25: 200 | J25: 70 | K25: 200 | L25: 70 | M25: 200 | N25: 70 | O25: 200
A27: Residential Wood Pellet Stoves
A28: DATA | B28: 2009 | C28: 2015 | D28: 2017 | F28: 2020 | H28: 2030 | J28: 2040 | L28: 2050
B29: Installed Base | C29: Installed Base | D29: Typical | E29: High | F29: Typical | G29: High | H29: Typical | I29: High | J29: Typical | K29: High | L29: Typical | M29: High
A30: Typical Capacity (kBtu/h) | B30: 50 | C30: 50 | D30: 50 | E30: 50 | F30: 50 | G30: 50 | H30: 50 | I30: 50 | J30: 50 | K30: 50 | L30: 50 | M30: 50
A31: Efficiency (HHV) | B31: 65 | C31: 70 | D31: 76 | E31: 87 | F31: 76 | G31: 87 | H31: 77 | I31: 87 | J31: 78 | K31: 88 | L31: 79 | M31: 89
A32: Annual Electricity Consumption (kWh) | B32: 600 | C32: 600 | D32: 600 | E32: 600 | F32: 600 | G32: 600 | H32: 600 | I32: 600 | J32: 600 | K32: 600 | L32: 600 | M32: 600
A33: Average Life (yrs) | B33: 12 | C33: 12 | D33: 12 | E33: 12 | F33: 12 | G33: 12 | H33: 12 | I33: 12 | J33: 12 | K33: 12 | L33: 12 | M33: 12
B34: 25 | C34: 25 | D34: 25 | E34: 25 | F34: 25 | G34: 25 | H34: 25 | I34: 25 | J34: 25 | K34: 25 | L34: 25 | M34: 25
A35: Retail Equipment Cost (2017$) | B35: 3300 | C35: 3300 | D35: 3300 | E35: 4000 | F35: 3300 | G35: 4000 | H35: 3400 | I35: 4000 | J35: 3500 | K35: 4100 | L35: 3600 | M35: 4200
A36: Total Installed Cost (2017$) | B36: 4700 | C36: 4700 | D36: 4700 | E36: 5400 | F36: 4700 | G36: 5400 | H36: 4800 | I36: 5400 | J36: 4900 | K36: 5500 | L36: 5000 | M36: 5600
A37: Annual Maintenance Cost (2017$) | B37: 260 | C37: 260 | D37: 260 | E37: 260 | F37: 260 | G37: 260 | H37: 260 | I37: 260 | J37: 260 | K37: 260 | L37: 260 | M37: 260
A39: Residential Air Source Heat Pumps
A40: DATA | B40: 2009 | C40: 2015 | D40: 2017 | H40: 2020 | J40: 2030** | L40: 2040 | N40: 2050
B41: Installed Base | C41: Installed Base | D41: Current Standard | E41: Typical | F41: ENERGY STAR | G41: High | H41: Typical | I41: High | J41: Typical | K41: High | L41: Typical | M41: High | N41: Typical | O41: High
A42: Typical Capacity (kBtu/h) | B42: 36 | C42: 36 | D42: 36 | E42: 36 | F42: 36 | G42: 36 | H42: 36 | I42: 36 | J42: 36 | K42: 36 | L42: 36 | M42: 36 | N42: 36 | O42: 36
A43: SEER (Cooling)* | B43: 12 | C43: 13.1 | D43: 14 | E43: 15.3 | F43: 15 | G43: 19 | H43: 15.3 | I43: 19 | J43: 15.8 | K43: 19 | L43: 15.8 | M43: 19 | N43: 15.8 | O43: 19
A44: HSPF (Heating)* | B44: 7 .0 | C44: 7.9 | D44: 8.2 | E44: 8.6 | F44: 8.5 | G44: 9 | H44: 8.6 | I44: 9 | J44: 8.8 | K44: 9 | L44: 8.8 | M44: 9 | N44: 8.8 | O44: 9
A45: Average Life (yrs) | B45: 9 | C45: 9 | D45: 9 | E45: 9 | F45: 9 | G45: 9 | H45: 9 | I45: 9 | J45: 9 | K45: 9 | L45: 9 | M45: 9 | N45: 9 | O45: 9
B46: 22 | C46: 22 | D46: 22 | E46: 22 | F46: 22 | G46: 22 | H46: 22 | I46: 22 | J46: 22 | K46: 22 | L46: 22 | M46: 22 | N46: 22 | O46: 22
A47: Retail Equipment Cost (2017$)* | B47: 2550 | C47: 2800 | D47: 3350 | E47: 3600 | F47: 3500 | G47: 4550 | H47: 3600 | I47: 4550 | J47: 3700 | K47: 4550 | L47: 3700 | M47: 4550 | N47: 3700 | O47: 4550
A48: Total Installed Cost (2017$)* | B48: 3000 | C48: 3250 | D48: 4850 | E48: 5100 | F48: 4950 | G48: 6100 | H48: 5100 | I48: 6100 | J48: 5150 | K48: 6100 | L48: 5150 | M48: 6100 | N48: 5150 | O48: 6100
A49: Annual Maintenance Cost (2017$) | B49: 20 | C49: 20 | D49: 20 | E49: 20 | F49: 20 | G49: 20 | H49: 20 | I49: 20 | J49: 20 | K49: 20 | L49: 20 | M49: 20 | N49: 20 | O49: 20
B50: 125 | C50: 125 | D50: 125 | E50: 125 | F50: 125 | G50: 125 | H50: 125 | I50: 125 | J50: 125 | K50: 125 | L50: 125 | M50: 125 | N50: 125 | O50: 125
A52: Residential Gas Water Heater
B53: 2009 | C53: 2015 | D53: 2017 | H53: 2020 | J53: 2030 | L53: 2040 | N53: 2050
B54: Installed Base | C54: Installed Base | D54: Current Standard | E54: Typical | F54: ENERGY STAR | G54: High | H54: Typical | I54: High | J54: Typical | K54: High | L54: Typical | M54: High | N54: Typical | O54: High
A55: Typical Capacity (gal) | B55: 40 | C55: 40 | D55: 40 | E55: 40 | F55: 40 | G55: 40 | H55: 40 | I55: 40 | J55: 40 | K55: 40 | L55: 40 | M55: 40 | N55: 40 | O55: 40
A56: Uniform Energy Factor (UEF)* | B56: 0.58 | C56: 0.58 | D56: 0.61 | E56: 0.63 | F56: 0.66 | G56: 0.81 | H56: 0.63 | I56: 0.81 | J56: 0.63 | K56: 0.81 | L56: 0.63 | M56: 0.81 | N56: 0.63 | O56: 0.81
A57: Average Life (yrs) | B57: 6 | C57: 6 | D57: 6 | E57: 6 | F57: 6 | G57: 6 | H57: 6 | I57: 6 | J57: 6 | K57: 6 | L57: 6 | M57: 6 | N57: 6 | O57: 6
B58: 20 | C58: 20 | D58: 20 | E58: 20 | F58: 20 | G58: 20 | H58: 20 | I58: 20 | J58: 20 | K58: 20 | L58: 20 | M58: 20 | N58: 20 | O58: 20
A59: Retail Equipment Cost (2017$) | B59: 500 | C59: 500 | D59: 700 | E59: 750 | F59: 800 | G59: 1850 | H59: 750 | I59: 1850 | J59: 750 | K59: 1850 | L59: 750 | M59: 1850 | N59: 750 | O59: 1850
B60: 550 | C60: 550 | D60: 1000 | E60: 1200 | F60: 1350 | G60: 2100 | H60: 1200 | I60: 2100 | J60: 1200 | K60: 2100 | L60: 1200 | M60: 2100 | N60: 1200 | O60: 2100
A61: Total Installed Cost (2017$)** | B61: 1050 | C61: 1050 | D61: 1350 | E61: 1400 | F61: 1500 | G61: 2450 | H61: 1400 | I61: 2450 | J61: 1400 | K61: 2450 | L61: 1400 | M61: 2450 | N61: 1400 | O61: 2450
B62: 1050 | C62: 1050 | D62: 2300 | E62: 2450 | F62: 2550 | G62: 3700 | H62: 2450 | I62: 3700 | J62: 2450 | K62: 3700 | L62: 2450 | M62: 3700 | N62: 2450 | O62: 3700
A63: Annual Maintenance Cost (2017$)*** | B63: - | C63: - | D63: - | E63: - | F63: - | G63: - | H63: - | I63: - | J63: - | K63: - | L63: - | M63: - | N63: - | O63: -
A66: Residential Oil Water Heater
A67: DATA | B67: 2009 | C67: 2015 | E67: 2017 | G67: 2020 | I67: 2030 | K67: 2040 | M67: 2050
B68: Installed Base | C68: =AVERAGE('EIA Costs'!D136:D137) -> 5225 | D68: Current Standard | E68: Typical | F68: High | G68: Typical | H68: High | I68: Typical | J68: High | K68: Typical | L68: High | M68: Typical | N68: High
A69: Typical Capacity (gal) | B69: 30 | C69: 32 | D69: 32 | E69: 32 | F69: 32 | G69: 32 | H69: 32 | I69: 32 | J69: 32 | K69: 32 | L69: 32 | M69: 32 | N69: 32
A70: Uniform Energy Factor (UEF)* | B70: 0.51 | C70: 0.51 | D70: 0.64 | E70: 0.67 | F70: 0.69 | G70: 0.67 | H70: 0.69 | I70: 0.67 | J70: 0.69 | K70: 0.67 | L70: 0.69 | M70: 0.67 | N70: 0.69
A71: Average Life (yrs) | B71: 6 | C71: 6 | D71: 6 | E71: 6 | F71: 6 | G71: 6 | H71: 6 | I71: 6 | J71: 6 | K71: 6 | L71: 6 | M71: 6 | N71: 6
B72: 20 | C72: 20 | D72: 20 | E72: 20 | F72: 20 | G72: 20 | H72: 20 | I72: 20 | J72: 20 | K72: 20 | L72: 20 | M72: 20 | N72: 20
A73: Retail Equipment Cost (2017$) | B73: 1350 | C73: 1350 | D73: 1500 | E73: 1600 | F73: 1600 | G73: 1600 | H73: 1600 | I73: 1600 | J73: 1600 | K73: 1600 | L73: 1600 | M73: 1600 | N73: 1600
B74: 1450 | C74: 1450 | D74: 1900 | E74: 2050 | F74: 2050 | G74: 2050 | H74: 2050 | I74: 2050 | J74: 2050 | K74: 2050 | L74: 2050 | M74: 2050 | N74: 2050
A75: Total Installed Cost (2017$) | B75: 2000 | C75: 2000 | D75: 2100 | E75: 2250 | F75: 2200 | G75: 2250 | H75: 2200 | I75: 2250 | J75: 2200 | K75: 2250 | L75: 2200 | M75: 2250 | N75: 2200
B76: 2100 | C76: 2100 | D76: 2700 | E76: 2850 | F76: 2850 | G76: 2850 | H76: 2850 | I76: 2850 | J76: 2850 | K76: 2850 | L76: 2850 | M76: 2850 | N76: 2850
A77: Annual Maintenance Cost (2017$) | B77: 180 | C77: 180 | D77: 180 | E77: 180 | F77: 180 | G77: 180 | H77: 180 | I77: 180 | J77: 180 | K77: 180 | L77: 180 | M77: 180 | N77: 180
A79: Residential Heat Pump Water Heater
A80: DATA | B80: 2009 | C80: 2015 | E80: 2017 | G80: 2020 | I80: 2030 | K80: 2040 | M80: 2050
B81: Installed Base | C81: Installed Base | D81: Typical | E81: ENERGY STAR | F81: High | G81: Typical | H81: High | I81: Typical | J81: High | K81: Typical | L81: High | M81: Typical | N81: High
A82: Typical Capacity (gal) | B82: 50 | C82: 50 | D82: 50 | E82: 50 | F82: 50 | G82: 50 | H82: 50 | I82: 50 | J82: 50 | K82: 50 | L82: 50 | M82: 50 | N82: 50
A83: Uniform Energy Factor (UEF)* | B83: 2.05 | C83: 2.05 | D83: 3.28 | E83: 2 | F83: 3.55 | G83: 3.28 | H83: 3.55 | I83: 3.28 | J83: 3.55 | K83: 3.28 | L83: 3.55 | M83: 3.28 | N83: 3.55
A84: Average Life (yrs) | B84: 6 | C84: 6 | D84: 6 | E84: 6 | F84: 6 | G84: 6 | H84: 6 | I84: 6 | J84: 6 | K84: 6 | L84: 6 | M84: 6 | N84: 6
B85: 20 | C85: 20 | D85: 20 | E85: 20 | F85: 20 | G85: 20 | H85: 20 | I85: 20 | J85: 20 | K85: 20 | L85: 20 | M85: 20 | N85: 20
A86: Retail Equipment Cost (2017$) | B86: 1550 | C86: 1100 | D86: 1200 | E86: 1050 | F86: 1200 | G86: 1200 | H86: 1200 | I86: 1200 | J86: 1200 | K86: 1200 | L86: 1200 | M86: 1200 | N86: 1200
B87: 1900 | C87: 1400 | D87: 1500 | E87: 1350 | F87: 2300 | G87: 1500 | H87: 2300 | I87: 1500 | J87: 2300 | K87: 1500 | L87: 2300 | M87: 1500 | N87: 2300
A88: Total Installed Cost (2017$) | B88: 1700 | C88: 1450 | D88: 1600 | E88: 1400 | F88: 1600 | G88: 1600 | H88: 1600 | I88: 1600 | J88: 1600 | K88: 1600 | L88: 1600 | M88: 1600 | N88: 1600
B89: 2450 | C89: 2500 | D89: 2550 | E89: 2400 | F89: 3350 | G89: 2550 | H89: 3350 | I89: 2550 | J89: 3350 | K89: 2550 | L89: 3350 | M89: 2550 | N89: 3350
A90: Annual Maintenance Cost (2017$) | B90: 20 | C90: 20 | D90: 20 | E90: 20 | F90: 20 | G90: 20 | H90: 20 | I90: 20 | J90: 20 | K90: 20 | L90: 20 | M90: 20 | N90: 20
A93: Commercial Gas Furnace
A94: DATA | B94: 2012 | D94: 2017 | F94: 2020 | H94: 2030 | J94: 2040 | L94: 2050
B95: Installed Base | C95: Current Standard | D95: Typical | E95: High | F95: Typical | G95: High | H95: Typical | I95: High | J95: Typical | K95: High | L95: Typical | M95: High
A96: Typical Input Capacity (kBtu/h) | B96: 400 | C96: 400 | D96: 400 | E96: 400 | F96: 400 | G96: 400 | H96: 400 | I96: 400 | J96: 400 | K96: 400 | L96: 400 | M96: 400
A97: Thermal Efficiency (%)* | B97: 80 | C97: 80 | D97: 80 | E97: 95 | F97: 80 | G97: 95 | H97: 81 | I97: 95 | J97: 81 | K97: 95 | L97: 81 | M97: 95
A98: Average Life (yrs) | B98: 23 | C98: 23 | D98: 23 | E98: 23 | F98: 23 | G98: 23 | H98: 23 | I98: 23 | J98: 23 | K98: 23 | L98: 23 | M98: 23
A99: Retail Equipment Cost (2017$) | B99: 1050 | C99: 1050 | D99: 1050 | E99: 2450 | F99: 1050 | G99: 2450 | H99: 1050 | I99: 2450 | J99: 1050 | K99: 2450 | L99: 1050 | M99: 2450
A100: Total Installed Cost (2017$) | B100: 2150 | C100: 2150 | D100: 2150 | E100: 3950 | F100: 2150 | G100: 3950 | H100: 2200 | I100: 3950 | J100: 2200 | K100: 3950 | L100: 2200 | M100: 3950
A101: Annual Maintenance Cost (2017$)** | B101: 170 | C101: 170 | D101: 170 | E101: 180 | F101: 170 | G101: 180 | H101: 170 | I101: 180 | J101: 170 | K101: 180 | L101: 170 | M101: 180
A104: Commercial Oil Furnace
A105: DATA | B105: 2012 | C105: 2017 | F105: 2020 | G105: 2030** | H105: 2040 | I105: 2050
B106: Installed Base | C106: Current Standard | D106: Typical | E106: High | F106: Typical | G106: Typical | H106: Typical | I106: Typical
A107: Typical Input Capacity (kBtu/h) | B107: 400 | C107: 400 | D107: 400 | E107: 400 | F107: 400 | G107: 400 | H107: 400 | I107: 400
A108: Thermal Efficiency (%)* | B108: 81 | C108: 81 | D108: 82 | E108: 85 | F108: 82 | G108: 82 | H108: 82 | I108: 82
A109: Average Life (yrs) | B109: 23 | C109: 23 | D109: 23 | E109: 23 | F109: 23 | G109: 23 | H109: 23 | I109: 23
A110: Retail Equipment Cost (2017$) | B110: 4650 | C110: 4650 | D110: 4700 | E110: 5050 | F110: 4700 | G110: 4700 | H110: 4700 | I110: 4700
A111: Total Installed Cost (2017$) | B111: 6550 | C111: 6550 | D111: 6600 | E111: 6750 | F111: 6600 | G111: 6600 | H111: 6600 | I111: 6600
...

Sheet Table_21._Residential_Sector_Eq
A1: Table 21. Residential Sector Equipment Stock and Efficiency, and Distributed Generation
A2: https://www.eia.gov/outlooks/aeo/data/browser/#/?id=30-AEO2025&cases=highZTC&sourcekey=0
A3: Tue Dec 02 2025 13:21:44 GMT-0800 (Pacific Standard Time)
A4: Source: U.S. Energy Information Administration
B5: full name | C5: api key | D5: units | E5: 2023 | F5: 2024 | G5: 2025 | H5: 2026 | I5: 2027 | J5: 2028 | K5: 2029 | L5: 2030 | M5: 2031 | N5: 2032 | O5: 2033 | P5: 2034 | Q5: 2035 | R5: 2036 | S5: 2037 | T5: 2038 | U5: 2039 | V5: 2040 | W5: 2041 | X5: 2042 | Y5: 2043 | Z5: 2044 | AA5: 2045 | AB5: 2046 | AC5: 2047 | AD5: 2048 | AE5: 2049 | AF5: 2050 | AG5: Growth (2024-2050)
A6: Equipment Stock (million units)
A7: Main Space Heaters
A8: Electric Heat Pumps | B8: Residential Equipment: Equipment Stock: Main Space Heaters: Electric Heat Pumps: High Zero-Carbon Technology Cost | C8: AEO.2025.HIGHZTC.EQNR_STK_RESD_MSHR_EHP_NA_NA_MILL.A | D8: millions | F8: 16.645529 | G8: 16.962238 | H8: 17.297937 | I8: 17.63735 | J8: 17.975958 | K8: 18.323191 | L8: 18.671122 | M8: 19.020292 | N8: 19.366976 | O8: 19.701832 | P8: 20.022341 | Q8: 20.338335 | R8: 20.648127 | S8: 20.94591 | T8: 21.232155 | U8: 21.506626 | V8: 21.772039 | W8: 22.026169 | X8: 22.27137 | Y8: 22.506741 | Z8: 22.737045 | AA8: 22.966516 | AB8: 23.194811 | AC8: 23.422667 | AD8: 23.650106 | AE8: 23.877323 | AF8: 24.103533 | AG8: 0.014
A9: Electric Other | B9: Residential Equipment: Equipment Stock: Main Space Heaters: Electric Other: High Zero-Carbon Technology Cost | C9: AEO.2025.HIGHZTC.EQNR_STK_RESD_MSHR_ELO_NA_NA_MILL.A | D9: millions | F9: 26.605318 | G9: 26.78159 | H9: 26.987282 | I9: 27.200581 | J9: 27.420454 | K9: 27.653374 | L9: 27.889208 | M9: 28.127293 | N9: 28.362696 | O9: 28.587048 | P9: 28.798485 | Q9: 29.005108 | R9: 29.206934 | S9: 29.397682 | T9: 29.579088 | U9: 29.751591 | V9: 29.918131 | W9: 30.076429 | X9: 30.228321 | Y9: 30.375742 | Z9: 30.522755 | AA9: 30.670509 | AB9: 30.818306 | AC9: 30.9662 | AD9: 31.114233 | AE9: 31.262747 | AF9: 31.41095 | AG9: 0.006
A10: Natural Gas Heat Pumps | B10: Residential Equipment: Equipment Stock: Main Space Heaters: Natural Gas Heat Pumps: High Zero-Carbon Technology Cost | C10: AEO.2025.HIGHZTC.EQNR_STK_RESD_MSHR_NHU_NA_NA_MILL.A | D10: millions | F10: 1.335856 | G10: 1.335485 | H10: 1.335121 | I10: 1.334763 | J10: 1.334411 | K10: 1.334067 | L10: 1.333728 | M10: 1.333394 | N10: 1.333067 | O10: 1.332746 | P10: 1.332431 | Q10: 1.33212 | R10: 1.331816 | S10: 1.331517 | T10: 1.331223 | U10: 1.330934 | V10: 1.330651 | W10: 1.330373 | X10: 1.330099 | Y10: 1.329831 | Z10: 1.329567 | AA10: 1.329308 | AB10: 1.329053 | AC10: 1.328804 | AD10: 1.328558 | AE10: 1.328316 | AF10: 1.328079 | AG10: 0
A11: Natural Gas Other | B11: Residential Equipment: Equipment Stock: Main Space Heaters: Natural Gas Other: High Zero-Carbon Technology Cost | C11: AEO.2025.HIGHZTC.EQNR_STK_RESD_MSHR_NGO_NA_NA_MILL.A | D11: millions | F11: 65.614693 | G11: 66.503311 | H11: 67.422646 | I11: 68.347206 | J11: 69.275345 | K11: 70.215851 | L11: 71.155624 | M11: 72.095222 | N11: 73.022018 | O11: 73.917961 | P11: 74.776138 | Q11: 75.619469 | R11: 76.443016 | S11: 77.232452 | T11: 77.991676 | U11: 78.71611 | V11: 79.412209 | W11: 80.076683 | X11: 80.717903 | Y11: 81.333214 | Z11: 81.934601 | AA11: 82.534103 | AB11: 83.129738 | AC11: 83.72612 | AD11: 84.322975 | AE11: 84.920403 | AF11: 85.516907 | AG11: 0.01
A12: Distillate Fuel Oil | B12: Residential Equipment: Equipment Stock: Main Space Heaters: Distillate Fuel Oil: High Zero-Carbon Technology Cost | C12: AEO.2025.HIGHZTC.EQNR_STK_RESD_MSHR_DFO_NA_NA_MILL.A | D12: millions | F12: 4.76794 | G12: 4.7259 | H12: 4.684821 | I12: 4.644579 | J12: 4.60502 | K12: 4.565969 | L12: 4.526826 | M12: 4.487612 | N12: 4.449521 | O12: 4.412687 | P12: 4.377314 | Q12: 4.343427 | R12: 4.310317 | S12: 4.277948 | T12: 4.246086 | U12: 4.214488 | V12: 4.183174 | W12: 4.152061 | X12: 4.122024 | Y12: 4.093054 | Z12: 4.065121 | AA12: 4.0385 | AB12: 4.012821 | AC12: 3.986746 | AD12: 3.960447 | AE12: 3.934162 | AF12: 3.908093 | AG12: -0.008
A13: Propane | B13: Residential Equipment: Equipment Stock: Main Space Heaters: Propane: High Zero-Carbon Technology Cost | C13: AEO.2025.HIGHZTC.EQNR_STK_RESD_MSHR_PROP_NA_NA_MILL.A | D13: millions | F13: 5.242597 | G13: 5.231007 | H13: 5.222726 | I13: 5.213856 | J13: 5.201762 | K13: 5.192317 | L13: 5.180441 | M13: 5.167188 | N13: 5.155312 | O13: 5.143894 | P13: 5.132373 | Q13: 5.121347 | R13: 5.111237 | S13: 5.101963 | T13: 5.09299 | U13: 5.084504 | V13: 5.077328 | W13: 5.070891 | X13: 5.064682 | Y13: 5.058537 | Z13: 5.052648 | AA13: 5.047476 | AB13: 5.043245 | AC13: 5.03766 | AD13: 5.030745 | AE13: 5.022702 | AF13: 5.01332 | AG13: -0.002
A14: Kerosene | B14: Residential Equipment: Equipment Stock: Main Space Heaters: Kerosene: High Zero-Carbon Technology Cost | C14: AEO.2025.HIGHZTC.EQNR_STK_RESD_MSHR_KRS_NA_NA_MILL.A | D14: millions | F14: 0.004925 | G14: 0.007897 | H14: 0.011523 | I14: 0.015072 | J14: 0.018269 | K14: 0.02133 | L14: 0.02419 | M14: 0.027018 | N14: 0.029863 | O14: 0.032679 | P14: 0.035394 | Q14: 0.038013 | R14: 0.040598 | S14: 0.043115 | T14: 0.045557 | U14: 0.047931 | V14: 0.050323 | W14: 0.052708 | X14: 0.055048 | Y14: 0.057337 | Z14: 0.059592 | AA14: 0.06182 | AB14: 0.063984 | AC14: 0.066125 | AD14: 0.068224 | AE14: 0.0703 | AF14: 0.072325 | AG14: 0.109
A15: Wood Stoves | B15: Residential Equipment: Equipment Stock: Main Space Heaters: Wood Stoves: High Zero-Carbon Technology Cost | C15: AEO.2025.HIGHZTC.EQNR_STK_RESD_MSHR_WDS_NA_NA_MILL.A | D15: millions | F15: 2.220637 | G15: 2.212639 | H15: 2.204829 | I15: 2.197059 | J15: 2.189375 | K15: 2.181753 | L15: 2.174187 | M15: 2.166692 | N15: 2.159028 | O15: 2.151248 | P15: 2.1434 | Q15: 2.135421 | R15: 2.127357 | S15: 2.119169 | T15: 2.11095 | U15: 2.102684 | V15: 2.094329 | W15: 2.085804 | X15: 2.077575 | Y15: 2.069646 | Z15: 2.062065 | AA15: 2.054862 | AB15: 2.048036 | AC15: 2.041663 | AD15: 2.035719 | AE15: 2.030173 | AF15: 2.025021 | AG15: -0.004
A16: Geothermal Heat Pumps | B16: Residential Equipment: Equipment Stock: Main Space Heaters: Geothermal Heat Pumps: High Zero-Carbon Technology Cost | C16: AEO.2025.HIGHZTC.EQNR_STK_RESD_MSHR_GEHP_NA_NA_MILL.A | D16: millions | F16: 1.360675 | G16: 1.408181 | H16: 1.455492 | I16: 1.50272 | J16: 1.549133 | K16: 1.595817 | L16: 1.642325 | M16: 1.688836 | N16: 1.73555 | O16: 1.781672 | P16: 1.826767 | Q16: 1.871948 | R16: 1.916753 | S16: 1.960757 | T16: 2.003791 | U16: 2.045475 | V16: 2.086105 | W16: 2.125625 | X16: 2.164013 | Y16: 2.200763 | Z16: 2.236357 | AA16: 2.271668 | AB16: 2.306613 | AC16: 2.34118 | AD16: 2.37536 | AE16: 2.409184 | AF16: 2.442582 | AG16: 0.023
A17: Total | B17: Residential Equipment: Equipment Stock: Main Space Heaters: Total: High Zero-Carbon Technology Cost | C17: AEO.2025.HIGHZTC.EQNR_STK_RESD_MSHR_TOT_NA_NA_MILL.A | D17: millions | F17: 123.79816 | G17: 125.16825 | H17: 126.62237 | I17: 128.09319 | J17: 129.56972 | K17: 131.08366 | L17: 132.59764 | M17: 134.11356 | N17: 135.61403 | O17: 137.06177 | P17: 138.44466 | Q17: 139.80519 | R17: 141.13614 | S17: 142.41052 | T17: 143.6335 | U17: 144.80035 | V17: 145.9243 | W17: 146.99674 | X17: 148.03105 | Y17: 149.02486 | Z17: 149.99976 | AA17: 150.97473 | AB17: 151.94659 | AC17: 152.91716 | AD17: 153.88637 | AE17: 154.8553 | AF17: 155.82082 | AG17: 0.009
A18: Space Cooling (million units)
A19: Electric Heat Pumps | B19: Residential Equipment: Equipment Stock: Space Cooling: Electric Heat Pumps: High Zero-Carbon Technology Cost | C19: AEO.2025.HIGHZTC.EQNR_STK_RESD_SPC_EHP_NA_NA_MILL.A | D19: millions | F19: 16.645529 | G19: 16.962236 | H19: 17.297932 | I19: 17.637352 | J19: 17.975958 | K19: 18.323191 | L19: 18.671116 | M19: 19.02029 | N19: 19.36697 | O19: 19.701841 | P19: 20.022339 | Q19: 20.338339 | R19: 20.648117 | S19: 20.945915 | T19: 21.232161 | U19: 21.506636 | V19: 21.772034 | W19: 22.026175 | X19: 22.271376 | Y19: 22.506746 | Z19: 22.737047 | AA19: 22.966528 | AB19: 23.194815 | AC19: 23.422672 | AD19: 23.650103 | AE19: 23.87734 | AF19: 24.103531 | AG19: 0.014
A20: Natural Gas Heat Pumps | B20: Residential Equipment: Equipment Stock: Space Cooling: Natural Gas Heat Pumps: High Zero-Carbon Technology Cost | C20: AEO.2025.HIGHZTC.EQNR_STK_RESD_SPC_NHU_NA_NA_MILL.A | D20: millions | F20: 1.335856 | G20: 1.335485 | H20: 1.335121 | I20: 1.334763 | J20: 1.334412 | K20: 1.334066 | L20: 1.333727 | M20: 1.333394 | N20: 1.333067 | O20: 1.332746 | P20: 1.33243 | Q20: 1.33212 | R20: 1.331816 | S20: 1.331517 | T20: 1.331223 | U20: 1.330934 | V20: 1.330651 | W20: 1.330372 | X20: 1.330099 | Y20: 1.329831 | Z20: 1.329567 | AA20: 1.329308 | AB20: 1.329053 | AC20: 1.328803 | AD20: 1.328558 | AE20: 1.328316 | AF20: 1.32808 | AG20: 0
A21: Geothermal Heat Pumps | B21: Residential Equipment: Equipment Stock: Space Cooling: Geothermal Heat Pumps: High Zero-Carbon Technology Cost | C21: AEO.2025.HIGHZTC.EQNR_STK_RESD_SPC_GEHP_NA_NA_MILL.A | D21: millions | F21: 1.360675 | G21: 1.40818 | H21: 1.455491 | I21: 1.50272 | J21: 1.549134 | K21: 1.595817 | L21: 1.642326 | M21: 1.688836 | N21: 1.73555 | O21: 1.781671 | P21: 1.826768 | Q21: 1.871948 | R21: 1.916753 | S21: 1.960756 | T21: 2.00379 | U21: 2.045475 | V21: 2.086105 | W21: 2.125626 | X21: 2.164013 | Y21: 2.200764 | Z21: 2.236356 | AA21: 2.271667 | AB21: 2.306613 | AC21: 2.341179 | AD21: 2.37536 | AE21: 2.409185 | AF21: 2.442581 | AG21: 0.023
A22: Central Air Conditioners | B22: Residential Equipment: Equipment Stock: Space Cooling: Central Air Conditioners: High Zero-Carbon Technology Cost | C22: AEO.2025.HIGHZTC.EQNR_STK_RESD_SPC_CAC_NA_NA_MILL.A | D22: millions | F22: 79.649452 | G22: 80.900047 | H22: 82.197365 | I22: 83.50415 | J22: 84.811256 | K22: 86.135658 | L22: 87.457458 | M22: 88.779007 | N22: 90.091568 | O22: 91.374115 | P22: 92.619194 | Q22: 93.851295 | R22: 95.065895 | S22: 96.248184 | T22: 97.400749 | U22: 98.520065 | V22: 99.614029 | W22: 100.67795 | X22: 101.7196 | Y22: 102.7365 | Z22: 103.74096 | AA22: 104.74514 | AB22: 105.74709 | AC22: 106.74812 | AD22: 107.74809 | AE22: 108.7477 | AF22: 109.74496 | AG22: 0.012
A23: Room Air Conditioners | B23: Residential Equipment: Equipment Stock: Space Cooling: Room Air Conditioners: High Zero-Carbon Technology Cost | C23: AEO.2025.HIGHZTC.EQNR_STK_RESD_SPC_RAC_NA_NA_MILL.A | D23: millions | F23: 43.140507 | G23: 43.232368 | H23: 43.345276 | I23: 43.46328 | J23: 43.586712 | K23: 43.719509 | L23: 43.854378 | M23: 43.990795 | N23: 44.124844 | O23: 44.250751 | P23: 44.367279 | Q23: 44.480221 | R23: 44.589432 | S23: 44.690407 | T23: 44.784588 | U23: 44.872437 | V23: 44.956017 | W23: 45.033756 | X23: 45.107018 | Y23: 45.177341 | Z23: 45.247604 | AA23: 45.318493 | AB23: 45.389637 | AC23: 45.461102 | AD23: 45.53299 | AE23: 45.605553 | AF23: 45.678272 | AG23: 0.002
A24: Total | B24: Residential Equipment: Equipment Stock: Space Cooling: Total: High Zero-Carbon Technology Cost | C24: AEO.2025.HIGHZTC.EQNR_STK_RESD_SPC_TOT_NA_NA_MILL.A | D24: millions | F24: 142.13202 | G24: 143.83832 | H24: 145.63118 | I24: 147.44226 | J24: 149.25748 | K24: 151.10825 | L24: 152.95901 | M24: 154.81233 | N24: 156.65199 | O24: 158.44113 | P24: 160.16801 | Q24: 161.87393 | R24: 163.55202 | S24: 165.17679 | T24: 166.75252 | U24: 168.27554 | V24: 169.75884 | W24: 171.19388 | X24: 172.5921 | Y24: 173.95119 | Z24: 175.29153 | AA24: 176.63113 | AB24: 177.96719 | AC24: 179.30188 | AD24: 180.6351 | AE24: 181.96808 | AF24: 183.29742 | AG24: 0.01
A25: Water Heaters (million units)
A26: Electric | B26: Residential Equipment: Equipment Stock: Water Heaters: Electric: High Zero-Carbon Technology Cost | C26: AEO.2025.HIGHZTC.EQNR_STK_RESD_WHT_ELE_NA_NA_MILL.A | D26: millions | F26: 62.064091 | G26: 62.296463 | H26: 62.600315 | I26: 62.92688 | J26: 63.228168 | K26: 64.053841 | L26: 64.829208 | M26: 65.567513 | N26: 66.280678 | O26: 66.984314 | P26: 67.653503 | Q26: 68.314453 | R26: 68.97834 | S26: 69.632027 | T26: 70.273941 | U26: 70.902107 | V26: 71.522514 | W26: 72.129929 | X26: 72.728317 | Y26: 73.317879 | Z26: 73.899185 | AA26: 74.478477 | AB26: 75.054726 | AC26: 75.626358 | AD26: 76.193161 | AE26: 76.757141 | AF26: 77.316254 | AG26: 0.008
A27: Natural Gas | B27: Residential Equipment: Equipment Stock: Water Heaters: Natural Gas: High Zero-Carbon Technology Cost | C27: AEO.2025.HIGHZTC.EQNR_STK_RESD_WHT_NG_NA_NA_MILL.A | D27: millions | F27: 64.896248 | G27: 65.896965 | H27: 66.916298 | I27: 67.939789 | J27: 68.981888 | K27: 69.718719 | L27: 70.479591 | M27: 71.256226 | N27: 72.025871 | O27: 72.786705 | P27: 73.528267 | Q27: 74.274551 | R27: 74.990112 | S27: 75.663231 | T27: 76.299583 | U27: 76.895554 | V27: 77.45697 | W27: 77.980125 | X27: 78.47403 | Y27: 78.935936 | Z27: 79.385979 | AA27: 79.836296 | AB27: 80.28476 | AC27: 80.734146 | AD27: 81.184738 | AE27: 81.635727 | AF27: 82.086113 | AG27: 0.009
A28: Distillate Fuel Oil | B28: Residential Equipment: Equipment Stock: Water Heaters: Distillate Fuel Oil: High Zero-Carbon Technology Cost | C28: AEO.2025.HIGHZTC.EQNR_STK_RESD_WHT_DFO_NA_NA_MILL.A | D28: millions | F28: 2.328812 | G28: 2.229761 | H28: 2.137233 | I28: 2.050461 | J28: 1.970477 | K28: 1.896038 | L28: 1.830604 | M28: 1.773455 | N28: 1.724959 | O28: 1.685178 | P28: 1.65441 | Q28: 1.632862 | R28: 1.610081 | S28: 1.586346 | T28: 1.561976 | U28: 1.537204 | V28: 1.512282 | W28: 1.487386 | X28: 1.462679 | Y28: 1.438287 | Z28: 1.414327 | AA28: 1.390946 | AB28: 1.368182 | AC28: 1.346109 | AD28: 1.32476 | AE28: 1.304158 | AF28: 1.284297 | AG28: -0.023
A29: Propane | B29: Residential Equipment: Equipment Stock: Water Heaters: Propane: High Zero-Carbon Technology Cost | C29: AEO.2025.HIGHZTC.EQNR_STK_RESD_WHT_PROP_NA_NA_MILL.A | D29: millions | F29: 3.994673 | G29: 3.890314 | H29: 3.796247 | I29: 3.708011 | J29: 3.626368 | K29: 3.531686 | L29: 3.447552 | M29: 3.374222 | N29: 3.31144 | O29: 3.259597 | P29: 3.218467 | Q29: 3.18944 | R29: 3.157171 | S29: 3.122084 | T29: 3.084893 | U29: 3.04617 | V29: 3.007124 | W29: 2.967928 | X29: 2.928841 | Y29: 2.889926 | Z29: 2.851814 | AA29: 2.814927 | AB29: 2.779243 | AC29: 2.745224 | AD29: 2.712765 | AE29: 2.681901 | AF29: 2.652292 | AG29: -0.016
A30: Solar Thermal | B30: Residential Equipment: Equipment Stock: Water Heaters: Solar Thermal: High Zero-Carbon Technology Cost | C30: AEO.2025.HIGHZTC.EQNR_STK_RESD_WHT_SLR_THERM_NA_MILL.A | D30: millions | F30: 1.564945 | G30: 1.899681 | H30: 2.211646 | I30: 2.501981 | J30: 2.791456 | K30: 2.906761 | L30: 3.028901 | M30: 3.155326 | N30: 3.279312 | O30: 3.349281 | P30: 3.38851 | Q30: 3.387712 | R30: 3.389602 | S30: 3.391462 | T30: 3.393306 | U30: 3.395105 | V30: 3.396857 | W30: 3.398571 | X30: 3.400233 | Y30: 3.401839 | Z30: 3.403495 | AA30: 3.405192 | AB30: 3.40693 | AC30: 3.408704 | AD30: 3.410507 | AE30: 3.412341 | AF30: 3.414205 | AG30: 0.03
A31: Total | B31: Residential Equipment: Equipment Stock: Water Heaters: Total: High Zero-Carbon Technology Cost | C31: AEO.2025.HIGHZTC.EQNR_STK_RESD_WHT_TOT_NA_NA_MILL.A | D31: millions | F31: 134.84877 | G31: 136.21318 | H31: 137.66174 | I31: 139.12712 | J31: 140.59836 | K31: 142.10706 | L31: 143.61586 | M31: 145.12672 | N31: 146.62227 | O31: 148.06508 | P31: 149.44313 | Q31: 150.79901 | R31: 152.12529 | S31: 153.39516 | T31: 154.61371 | U31: 155.77615 | V31: 156.89575 | W31: 157.96393 | X31: 158.99411 | Y31: 159.98387 | Z31: 160.95477 | AA31: 161.92584 | AB31: 162.89384 | AC31: 163.86055 | AD31: 164.82593 | AE31: 165.79126 | AF31: 166.75317 | AG31: 0.008
A32: Cooking Equipment (million units)
A33: Electric | B33: Residential Equipment: Equipment Stock: Cooking Equipment: Electric: High Zero-Carbon Technology Cost | C33: AEO.2025.HIGHZTC.EQNR_STK_RESD_CER_ELE_NA_NA_MILL.A | D33: millions | F33: 100.27812 | G33: 101.10259 | H33: 101.98053 | I33: 102.8632 | J33: 103.74537 | K33: 104.65044 | L33: 105.55076 | M33: 106.44516 | N33: 107.31894 | O33: 108.1434 | P33: 108.88472 | Q33: 109.57114 | R33: 110.1867 | S33: 110.70435 | T33: 111.20811 | U33: 111.71865 | V33: 112.24985 | W33: 112.80871 | X33: 113.41383 | Y33: 113.98341 | Z33: 114.53365 | AA33: 115.07655 | AB33: 115.60883 | AC33: 116.13017 | AD33: 116.6391 | AE33: 117.13462 | AF33: 117.61186 | AG33: 0.006
A34: Natural Gas | B34: Residential Equipment: Equipment Stock: Cooking Equipment: Natural Gas: High Zero-Carbon Technology Cost | C34: AEO.2025.HIGHZTC.EQNR_STK_RESD_CER_NG_NA_NA_MILL.A | D34: millions | F34: 53.97237 | G34: 54.503727 | H34: 55.061764 | I34: 55.632816 | J34: 56.213551 | K34: 56.80965 | L34: 57.412582 | M34: 58.02486 | N34: 58.644409 | O34: 59.262939 | P34: 59.903133 | Q34: 60.579704 | R34: 61.301079 | S34: 62.067856 | T34: 62.795506 | U34: 63.458031 | V34: 64.053505 | W34: 64.565849 | X34: 64.989624 | Y34: 65.410423 | Z34: 65.83329 | AA34: 66.264915 | AB34: 66.705818 | AC34: 67.157867 | AD34: 67.622643 | AE34: 68.102386 | AF34: 68.598465 | AG34: 0.009
A35: Propane | B35: Residential Equipment: Equipment Stock: Cooking Equipment: Propane: High Zero-Carbon Technology Cost | C35: AEO.2025.HIGHZTC.EQNR_STK_RESD_CER_PROP_NA_NA_MILL.A | D35: millions | F35: 6.249792 | G35: 6.24914 | H35: 6.252706 | I35: 6.255498 | J35: 6.255161 | K35: 6.254043 | L35: 6.251281 | M35: 6.247181 | N35: 6.241242 | O35: 6.233177 | P35: 6.221874 | Q35: 6.207108 | R35: 6.1889 | S35: 6.166887 | T35: 6.14676 | U35: 6.128918 | V35: 6.114851 | W35: 6.104977 | X35: 6.099405 | Y35: 6.092152 | Z35: 6.083468 | AA35: 6.07354 | AB35: 6.062016 | AC35: 6.049131 | AD35: 6.034698 | AE35: 6.018864 | AF35: 6.001561 | AG35: -0.002
A36: Total | B36: Residential Equipment: Equipment Stock: Cooking Equipment: Total: High Zero-Carbon Technology Cost | C36: AEO.2025.HIGHZTC.EQNR_STK_RESD_CER_TOT_NA_NA_MILL.A | D36: millions | F36: 160.50027 | G36: 161.85547 | H36: 163.295 | I36: 164.75151 | J36: 166.21408 | K36: 167.71414 | L36: 169.21463 | M36: 170.71719 | N36: 172.20459 | O36: 173.63953 | P36: 175.00974 | Q36: 176.35796 | R36: 177.67668 | S36: 178.93909 | T36: 180.15037 | U36: 181.3056 | V36: 182.41821 | W36: 183.47954 | X36: 184.50285 | Y36: 185.48598 | Z36: 186.45041 | AA36: 187.41501 | AB36: 188.37665 | AC36: 189.33717 | AD36: 190.29645 | AE36: 191.25586 | AF36: 192.21188 | AG36: 0.007
A37: Clothes Dryers (million units)
A38: Electric | B38: Residential Equipment: Equipment Stock: Clothes Dryers: Electric: High Zero-Carbon Technology Cost | C38: AEO.2025.HIGHZTC.EQNR_STK_RESD_CDR_ELE_NA_NA_MILL.A | D38: millions | F38: 92.221107 | G38: 94.908974 | H38: 97.661568 | I38: 100.4443 | J38: 103.24648 | K38: 106.05999 | L38: 108.87318 | M38: 111.66229 | N38: 114.41385 | O38: 117.12387 | P38: 119.78091 | Q38: 122.4272 | R38: 125.05272 | S38: 127.63446 | T38: 130.17616 | U38: 132.67476 | V38: 135.14604 | W38: 137.59196 | X38: 139.98711 | Y38: 142.33012 | Z38: 144.64094 | AA38: 146.94054 | AB38: 149.23036 | AC38: 151.51019 | AD38: 153.78226 | AE38: 156.04994 | AF38: 158.30891 | AG38: 0.021
A39: Natural Gas | B39: Residential Equipment: Equipment Stock: Clothes Dryers: Natural Gas: High Zero-Carbon Technology Cost | C39: AEO.2025.HIGHZTC.EQNR_STK_RESD_CDR_NG_NA_NA_MILL.A | D39: millions | F39: 20.353802 | G39: 20.727465 | H39: 21.108976 | I39: 21.498468 | J39: 21.905369 | K39: 22.331652 | L39: 22.776669 | M39: 23.24667 | N39: 23.740404 | O39: 24.225313 | P39: 24.699818 | Q39: 25.166246 | R39: 25.623446 | S39: 26.068548 | T39: 26.501984 | U39: 26.919897 | V39: 27.319826 | W39: 27.699757 | X39: 28.090372 | Y39: 28.489046 | Z39: 28.897078 | AA39: 29.31538 | AB39: 29.741957 | AC39: 30.175976 | AD39: 30.615866 | AE39: 31.060276 | AF39: 31.508205 | AG39: 0.017
A40: Total | B40: Residential Equipment: Equipment Stock: Clothes Dryers: Total: High Zero-Carbon Technology Cost | C40: AEO.2025.HIGHZTC.EQNR_STK_RESD_CDR_TOT_NA_NA_MILL.A | D40: millions | F40: 112.57491 | G40: 115.63644 | H40: 118.77055 | I40: 121.94276 | J40: 125.15185 | K40: 128.39165 | L40: 131.64984 | M40: 134.90897 | N40: 138.15425 | O40: 141.34918 | P40: 144.48073 | Q40: 147.59345 | R40: 150.67616 | S40: 153.703 | T40: 156.67815 | U40: 159.59465 | V40: 162.46587 | W40: 165.29172 | X40: 168.07748 | Y40: 170.81917 | Z40: 173.53803 | AA40: 176.25592 | AB40: 178.97232 | AC40: 181.68617 | AD40: 184.39812 | AE40: 187.11021 | AF40: 189.81712 | AG40: 0.02
A41: Other Appliances (million units)
A42: Refrigerators | B42: Residential Equipment: Equipment Stock: Other Appliances: Refrigerators: High Zero-Carbon Technology Cost | C42: AEO.2025.HIGHZTC.EQNR_STK_RESD_OTAR_RFG_NA_NA_MILL.A | D42: millions | F42: 185.51213 | G42: 187.57016 | H42: 189.72298 | I42: 191.89264 | J42: 194.05687 | K42: 196.26173 | L42: 198.46158 | M42: 200.66261 | N42: 202.84566 | O42: 204.9603 | P42: 206.98817 | Q42: 208.9885 | R42: 210.94859 | S42: 212.83372 | T42: 214.6485 | U42: 216.38301 | V42: 218.05542 | W42: 219.65475 | X42: 221.20091 | Y42: 222.68465 | Z42: 224.13631 | AA42: 225.58777 | AB42: 227.03429 | AC42: 228.47902 | AD42: 229.9216 | AE42: 231.36346 | AF42: 232.79994 | AG42: 0.009
A43: Freezers | B43: Residential Equipment: Equipment Stock: Other Appliances: Freezers: High Zero-Carbon Technology Cost | C43: AEO.2025.HIGHZTC.EQNR_STK_RESD_OTAR_FRZ_NA_NA_MILL.A | D43: millions | F43: 48.421524 | G43: 48.897556 | H43: 49.389957 | I43: 49.883247 | J43: 50.367458 | K43: 50.854794 | L43: 51.338001 | M43: 51.821068 | N43: 52.302494 | O43: 52.772449 | P43: 53.225803 | Q43: 53.674511 | R43: 54.115623 | S43: 54.542957 | T43: 54.956287 | U43: 55.352367 | V43: 55.735516 | W43: 56.103615 | X43: 56.460857 | Y43: 56.802979 | Z43: 57.136333 | AA43: 57.469646 | AB43: 57.801506 | AC43: 58.133106 | AD43: 58.464127 | AE43: 58.794895 | AF43: 59.124157 | AG43: 0.008
A44: Stock Average Equipment Efficiency
A45: Main Space Heaters
A46: Electric Heat Pumps (HSPF) | B46: Residential Equipment: Stock Average Efficiency: Main Space Heaters: Electric Heat Pumps: High Zero-Carbon Technology Cost | C46: AEO.2025.HIGHZTC.EFI_STK_RESD_SPHR_EHP_NA_NA_HSPF.A | D46: HSPF | F46: 8.301575 | G46: 8.411783 | H46: 8.524261 | I46: 8.639673 | J46: 8.759115 | K46: 8.870728 | L46: 8.974126 | M46: 9.069015 | N46: 9.155725 | O46: 9.226506 | P46: 9.289591 | Q46: 9.344809 | R46: 9.392457 | S46: 9.432801 | T46: 9.465774 | U46: 9.491529 | V46: 9.511662 | W46: 9.523355 | X46: 9.525758 | Y46: 9.528441 | Z46: 9.531271 | AA46: 9.534098 | AB46: 9.536915 | AC46: 9.539699 | AD46: 9.542423 | AE46: 9.545066 | AF46: 9.547633 | AG46: 0.005
A47: Natural Gas Heat Pumps (GCOP) | B47: Residential Equipment: Stock Average Efficiency: Main Space Heaters: Natural Gas Heat Pumps: High Zero-Carbon Technology Cost | C47: AEO.2025.HIGHZTC.EFI_STK_RESD_SPHR_NHU_NA_NA_GCOP.A | D47: GCOP | F47: 1.3 | G47: 1.3 | H47: 1.3 | I47: 1.3 | J47: 1.3 | K47: 1.3 | L47: 1.3 | M47: 1.3 | N47: 1.3 | O47: 1.3 | P47: 1.3 | Q47: 1.3 | R47: 1.3 | S47: 1.3 | T47: 1.3 | U47: 1.3 | V47: 1.3 | W47: 1.3 | X47: 1.3 | Y47: 1.3 | Z47: 1.3 | AA47: 1.3 | AB47: 1.3 | AC47: 1.3 | AD47: 1.3 | AE47: 1.3 | AF47: 1.3 | AG47: 0
A48: Geothermal Heat Pumps (COP) | B48: Residential Equipment: Stock Average Efficiency: Main Space Heaters: Geothermal Heat Pumps: High Zero-Carbon Technology Cost | C48: AEO.2025.HIGHZTC.EFI_STK_RESD_SPHR_GEHP_NA_NA_COP.A | D48: COP | F48: 3.198018 | G48: 3.229836 | H48: 3.260657 | I48: 3.290383 | J48: 3.318929 | K48: 3.346405 | L48: 3.372804 | M48: 3.398271 | N48: 3.421792 | O48: 3.4418 | P48: 3.459232 | Q48: 3.469077 | R48: 3.477528 | S48: 3.485055 | T48: 3.491715 | U48: 3.497602 | V48: 3.502827 | W48: 3.507296 | X48: 3.511081 | Y48: 3.514184 | Z48: 3.516665 | AA48: 3.51842 | AB48: 3.519624 | AC48: 3.520261 | AD48: 3.520312 | AE48: 3.519931 | AF48: 3.519072 | AG48: 0.004
A49: Natural Gas Furnace (AFUE) | B49: Residential Equipment: Stock Average Efficiency: Main Space Heaters: Natural Gas Furnace: High Zero-Carbon Technology Cost | C49: AEO.2025.HIGHZTC.EFI_STK_RESD_SPHR_NFR_NA_NA_AFUE.A | D49: AFUE | F49: 0.81869 | G49: 0.823765 | H49: 0.828838 | I49: 0.833879 | J49: 0.838906 | K49: 0.847897 | L49: 0.857558 | M49: 0.867226 | N49: 0.876317 | O49: 0.884643 | P49: 0.8924 | Q49: 0.899578 | R49: 0.906261 | S49: 0.912422 | T49: 0.918101 | U49: 0.923289 | V49: 0.928013 | W49: 0.932266 | X49: 0.936086 | Y49: 0.939438 | Z49: 0.942309 | AA49: 0.944658 | AB49: 0.946467 | AC49: 0.948268 | AD49: 0.950024 | AE49: 0.951704 | AF49: 0.953277 | AG49: 0.006
A50: Distillate Furnace (AFUE) | B50: Residential Equipment: Stock Average Efficiency: Main Space Heaters: Distillate Furnace: High Zero-Carbon Technology Cost | C50: AEO.2025.HIGHZTC.EFI_STK_RESD_SPHR_DFR_NA_NA_AFUE.A | D50: AFUE | F50: 0.835821 | G50: 0.83737 | H50: 0.838934 | I50: 0.840479 | J50: 0.841988 | K50: 0.843465 | L50: 0.844934 | M50: 0.846412 | N50: 0.847821 | O50: 0.849073 | P50: 0.850235 | Q50: 0.851286 | R50: 0.852252 | S50: 0.85311 | T50: 0.853878 | U50: 0.854555 | V50: 0.855138 | W50: 0.855625 | X50: 0.856018 | Y50: 0.856314 | Z50: 0.856506 | AA50: 0.856586 | AB50: 0.856572 | AC50: 0.856558 | AD50: 0.856545 | AE50: 0.856532 | AF50: 0.856519 | AG50: 0.001
A51: Space Cooling
A52: Electric Heat Pumps (SEER) | B52: Residential Equipment: Stock Average Efficiency: Space Cooling: Electric Heat Pumps: High Zero-Carbon Technology Cost | C52: AEO.2025.HIGHZTC.EFI_STK_RESD_SPC_EHP_NA_NA_SEER.A | D52: SEER | F52: 13.990335 | G52: 14.225822 | H52: 14.465521 | I52: 14.710986 | J52: 14.964726 | K52: 15.201395 | L52: 15.42023 | M52: 15.62071 | N52: 15.803606 | O52: 15.951933 | P52: 16.083612 | Q52: 16.198576 | R52: 16.297474 | S52: 16.380913 | T52: 16.448742 | U52: 16.501339 | V52: 16.546972 | W52: 16.574265 | X52: 16.58153 | Y52: 16.589703 | Z52: 16.598383 | AA52: 16.607206 | AB52: 16.616085 | AC52: 16.624941 | AD52: 16.633642 | AE52: 16.642115 | AF52: 16.650322 | AG52: 0.007
A53: Natural Gas Heat Pumps (GCOP) | B53: Residential Equipment: Stock Average Efficiency: Space Cooling: Natural Gas Heat Pumps: High Zero-Carbon Technology Cost | C53: AEO.2025.HIGHZTC.EFI_STK_RESD_SPC_NHU_NA_NA_GCOP.A | D53: GCOP | F53: 0.623339 | G53: 0.628984 | H53: 0.634922 | I53: 0.641268 | J53: 0.64812 | K53: 0.654681 | L53: 0.660912 | M53: 0.666764 | N53: 0.672238 | O53: 0.677284 | P53: 0.681912 | Q53: 0.686074 | R53: 0.689759 | S53: 0.692949 | T53: 0.695604 | U53: 0.697704 | V53: 0.699202 | W53: 0.7 | X53: 0.7 | Y53: 0.7 | Z53: 0.7 | AA53: 0.7 | AB53: 0.7 | AC53: 0.7 | AD53: 0.7 | AE53: 0.7 | AF53: 0.7 | AG53: 0.004
A54: Geothermal Heat Pumps (EER) | B54: Residential Equipment: Stock Average Efficiency: Space Cooling: Geothermal Heat Pumps: High Zero-Carbon Technology Cost | C54: AEO.2025.HIGHZTC.EFI_STK_RESD_SPC_GEHP_NA_NA_EER.A | D54: EER | F54: 13.993668 | G54: 14.221729 | H54: 14.442514 | I54: 14.655156 | J54: 14.858943 | K54: 15.054792 | L54: 15.24262 | M54: 15.423491 | N54: 15.590322 | O54: 15.732929 | P54: 15.857524 | Q54: 15.92991 | R54: 15.991646 | S54: 16.046743 | T54: 16.095617 | U54: 16.138885 | V54: 16.177298 | W54: 16.210196 | X54: 16.238113 | Y54: 16.261044 | Z54: 16.279423 | AA54: 16.292555 | AB54: 16.301682 | AC54: 16.306694 | AD54: 16.307491 | AE54: 16.305126 | AF54: 16.299299 | AG54: 0.006
A55: Central Air Conditioners (SEER) | B55: Residential Equipment: Stock Average Efficiency: Space Cooling: Central Air Conditioners: High Zero-Carbon Technology Cost | C55: AEO.2025.HIGHZTC.EFI_STK_RESD_SPC_CAC_NA_NA_SEER.A | D55: SEER | F55: 13.469368 | G55: 13.76048 | H55: 14.051945 | I55: 14.34586 | J55: 14.645688 | K55: 14.925357 | L55: 15.18473 | M55: 15.422161 | N55: 15.637525 | O55: 15.709616 | P55: 15.752591 | Q55: 15.78285 | R55: 15.799917 | S55: 15.80462 | T55: 15.79846 | U55: 15.781046 | V55: 15.75336 | W55: 15.715132 | X55: 15.665411 | Y55: 15.616528 | Z55: 15.568357 | AA55: 15.521166 | AB55: 15.475282 | AC55: 15.430945 | AD55: 15.388376 | AE55: 15.347758 | AF55: 15.309222 | AG55: 0.005
A56: Room Air Conditioners (EER) | B56: Residential Equipment: Stock Average Efficiency: Space Cooling: Room Air Conditioners: High Zero-Carbon Technology Cost | C56: AEO.2025.HIGHZTC.EFI_STK_RESD_SPC_RAC_NA_NA_EER.A | D56: EER | F56: 11.448732 | G56: 11.644737 | H56: 11.847325 | I56: 12.298437 | J56: 12.757018 | K56: 13.272966 | L56: 13.771557 | M56: 14.233994 | N56: 14.651569 | O56: 15.024332 | P56: 15.341799 | Q56: 15.580716 | R56: 15.738295 | S56: 15.813057 | T56: 15.872056 | U56: 15.916222 | V56: 15.947607 | W56: 15.968753 | X56: 15.982252 | Y56: 15.990417 | Z56: 15.995095 | AA56: 15.997622 | AB56: 15.998911 | AC56: 15.999532 | AD56: 15.999801 | AE56: 15.999924 | AF56: 15.999976 | AG56: 0.013
A57: Water Heaters
A58: Electric (EF) | B58: Residential Equipment: Stock Average Efficiency: Water Heaters: Electric: High Zero-Carbon Technology Cost | C58: AEO.2025.HIGHZTC.EFI_STK_RESD_WHT_ELE_NA_NA_EF.A | D58: EF | F58: 1.089594 | G58: 1.142516 | H58: 1.194647 | I58: 1.245785 | J58: 1.296718 | K58: 1.427567 | L58: 1.530845 | M58: 1.640694 | N58: 1.744714 | O58: 1.833205 | P58: 1.91778 | Q58: 1.995061 | R58: 2.064635 | S58: 2.126171 | T58: 2.179694 | U58: 2.225028 | V58: 2.262446 | W58: 2.291731 | X58: 2.312705 | Y58: 2.325641 | Z58: 2.33766 | AA58: 2.348729 | AB58: 2.358847 | AC58: 2.368028 | AD58: 2.376319 | AE58: 2.383758 | AF58: 2.390381 | AG58: 0.031
A59: Natural Gas (EF) | B59: Residential Equipment: Stock Average Efficiency: Water Heaters: Natural Gas: High Zero-Carbon Technology Cost | C59: AEO.2025.HIGHZTC.EFI_STK_RESD_WHT_NG_NA_NA_EF.A | D59: EF | F59: 0.605986 | G59: 0.613774 | H59: 0.620732 | I59: 0.626879 | J59: 0.632248 | K59: 0.640281 | L59: 0.647174 | M59: 0.653142 | N59: 0.658141 | O59: 0.660803 | P59: 0.662594 | Q59: 0.663523 | R59: 0.664392 | S59: 0.665197 | T59: 0.665936 | U59: 0.666609 | V59: 0.667216 | W59: 0.667758 | X59: 0.668238 | Y59: 0.66866 | Z59: 0.669028 | AA59: 0.669346 | AB59: 0.669618 | AC59: 0.669849 | AD59: 0.670043 | AE59: 0.670204 | AF59: 0.670337 | AG59: 0.004
A60: Distillate Fuel Oil (EF) | B60: Residential Equipment: Stock Average Efficiency: Water Heaters: Distillate Fuel Oil: High Zero-Carbon Technology Cost | C60: AEO.2025.HIGHZTC.EFI_STK_RESD_WHT_DFO_NA_NA_EF.A | D60: EF | F60: 0.547698 | G60: 0.559994 | H60: 0.572179 | I60: 0.583994 | J60: 0.59521 | K60: 0.60664 | L60: 0.616759 | M60: 0.625502 | N60: 0.632547 | O60: 0.637645 | P60: 0.640544 | Q60: 0.641082 | R60: 0.641634 | S60: 0.642193 | T60: 0.642754 | U60: 0.643312 | V60: 0.643862 | W60: 0.644401 | X60: 0.644925 | Y60: 0.64543 | Z60: 0.645913 | AA60: 0.646374 | AB60: 0.646809 | AC60: 0.647219 | AD60: 0.647602 | AE60: 0.647957 | AF60: 0.648285 | AG60: 0.007
A61: Propane (EF) | B61: Residential Equipment: Stock Average Efficiency: Water Heaters: Propane: High Zero-Carbon Technology Cost | C61: AEO.2025.HIGHZTC.EFI_STK_RESD_WHT_PROP_NA_NA_EF.A | D61: EF | F61: 0.609399 | G61: 0.618704 | H61: 0.627502 | I61: 0.635687 | J61: 0.643129 | K61: 0.650474 | L61: 0.656896 | M61: 0.662416 | N61: 0.666918 | O61: 0.669209 | P61: 0.670362 | Q61: 0.670312 | R61: 0.670217 | S61: 0.670084 | T61: 0.669917 | U61: 0.669723 | V61: 0.669505 | W61: 0.66927 | X61: 0.669022 | Y61: 0.668766 | Z61: 0.668508 | AA61: 0.668249 | AB61: 0.667995 | AC61: 0.667748 | AD61: 0.667511 | AE61: 0.667286 | AF61: 0.667075 | AG61: 0.003
A62: Other Appliances (kilowatthours per year)
A63: Refrigerators | B63: Residential Equipment: Stock Average Efficiency: Other Appliances: Refrigerators: High Zero-Carbon Technology Cost | C63: AEO.2025.HIGHZTC.EFI_STK_RESD_OTAR_RFG_NA_NA_KWH.A | D63: kWh | F63: 605.32141 | G63: 596.56372 | H63: 587.74408 | I63: 578.85461 | J63: 569.90594 | K63: 561.435 | L63: 548.93573 | M63: 536.88129 | N63: 525.27539 | O63: 514.09534 | P63: 503.3385 | Q63: 493.03497 | R63: 483.48178 | S63: 474.76013 | T63: 466.87344 | U63: 459.84949 | V63: 453.64551 | W63: 448.24676 | X63: 443.6087 | Y63: 439.75659 | Z63: 436.64328 | AA63: 434.2933 | AB63: 432.73151 | AC63: 431.93127 | AD63: 431.20816 | AE63: 430.55432 | AF63: 429.9595 | AG63: -0.013
A64: Freezers | B64: Residential Equipment: Stock Average Efficiency: Other Appliances: Freezers: High Zero-Carbon Technology Cost | C64: AEO.2025.HIGHZTC.EFI_STK_RESD_OTAR_FRZ_NA_NA_KWH.A | D64: kWh | F64: 463.55093 | G64: 458.8902 | H64: 454.28131 | I64: 449.72031 | J64: 445.12622 | K64: 440.45502 | L64: 433.68933 | M64: 426.78296 | N64: 419.79501 | O64: 413.10068 | P64: 406.70032 | Q64: 400.59753 | R64: 394.77927 | S64: 389.23379 | T64: 383.98914 | U64: 379.0647 | V64: 374.43823 | W64: 370.16132 | X64: 366.20215 | Y64: 362.57892 | Z64: 359.272 | AA64: 356.2627 | AB64: 353.61423 | AC64: 351.29883 | AD64: 349.36639 | AE64: 347.84357 | AF64: 346.73441 | AG64: -0.011
A65: Building Shell Efficiency Index
A66: Space Heating
A67: Pre-2020 Homes | B67: Residential Equipment: Building Shell Efficiency Index: Space Heating: Pre-2015 Homes: High Zero-Carbon Technology Cost | C67: AEO.2025.HIGHZTC.EFI_BSE_RESD_SPH_OLD_NA_NA_Y15EQ1.A | D67: 2015=1.00 | F67: 0.962499 | G67: 0.958293 | H67: 0.953861 | I67: 0.948976 | J67: 0.94338 | K67: 0.937139 | L67: 0.930514 | M67: 0.923414 | N67: 0.915817 | O67: 0.907954 | P67: 0.900289 | Q67: 0.89305 | R67: 0.886269 | S67: 0.879715 | T67: 0.873158 | U67: 0.86666 | V67: 0.860093 | W67: 0.853337 | X67: 0.846504 | Y67: 0.83967 | Z67: 0.83285 | AA67: 0.826026 | AB67: 0.819144 | AC67: 0.81229 | AD67: 0.805503 | AE67: 0.798702 | AF67: 0.791856 | AG67: -0.007
A68: New Construction | B68: Residential Equipment: Building Shell Efficiency Index: Space Heating: New Construction: High Zero-Carbon Technology Cost | C68: AEO.2025.HIGHZTC.EFI_BSE_RESD_SPH_NCO_NA_NA_Y15EQ1.A | D68: 2015=1.00 | F68: 0.777795 | G68: 0.777804 | H68: 0.788456 | I68: 0.791936 | J68: 0.797173 | K68: 0.796403 | L68: 0.797131 | M68: 0.795607 | N68: 0.791438 | O68: 0.90783 | P68: 0.903509 | Q68: 0.903332 | R68: 0.901356 | S68: 0.896882 | T68: 0.893279 | U68: 0.890833 | V68: 0.88829 | W68: 0.884528 | X68: 0.881262 | Y68: 0.880932 | Z68: 0.881812 | AA68: 0.880657 | AB68: 0.879689 | AC68: 0.87822 | AD68: 0.877219 | AE68: 0.876159 | AF68: 0.875121 | AG68: 0.005
A69: All Homes | B69: Residential Equipment: Building Shell Efficiency Index: Space Heating: All Homes: High Zero-Carbon Technology Cost | C69: AEO.2025.HIGHZTC.EFI_BSE_RESD_SPH_AHM_NA_NA_Y15EQ1.A | D69: 2015=1.00 | F69: 0.955143 | G69: 0.949095 | H69: 0.943004 | I69: 0.936667 | J69: 0.929901 | K69: 0.922678 | L69: 0.9153 | M69: 0.907667 | N69: 0.899751 | O69: 0.893162 | P69: 0.88683 | Q69: 0.880983 | R69: 0.87561 | S69: 0.870475 | T69: 0.865393 | U69: 0.860418 | V69: 0.855445 | W69: 0.850361 | X69: 0.845263 | Y69: 0.840229 | Z69: 0.83528 | AA69: 0.830391 | AB69: 0.82552 | AC69: 0.820726 | AD69: 0.816043 | AE69: 0.811407 | AF69: 0.806791 | AG69: -0.006
A70: Space Cooling
A71: Pre-2020 Homes | B71: Residential Equipment: Building Shell Efficiency Index: Space Cooling: Pre-2015 Homes: High Zero-Carbon Technology Cost | C71: AEO.2025.HIGHZTC.EFI_BSE_RESD_SPC_OLD_NA_NA_Y15EQ1.A | D71: 2015=1.00 | F71: 0.987064 | G71: 0.985772 | H71: 0.98427 | I71: 0.982508 | J71: 0.980458 | K71: 0.978187 | L71: 0.975783 | M71: 0.973246 | N71: 0.970565 | O71: 0.967795 | P71: 0.965096 | Q71: 0.962539 | R71: 0.960132 | S71: 0.957803 | T71: 0.955471 | U71: 0.953172 | V71: 0.950855 | W71: 0.948457 | X71: 0.946022 | Y71: 0.943575 | Z71: 0.941128 | AA71: 0.938696 | AB71: 0.936247 | AC71: 0.933813 | AD71: 0.931396 | AE71: 0.928972 | AF71: 0.92653 | AG71: -0.002
A72: New Construction | B72: Residential Equipment: Building Shell Efficiency Index: Space Cooling: New Construction: High Zero-Carbon Technology Cost | C72: AEO.2025.HIGHZTC.EFI_BSE_RESD_SPC_NCO_NA_NA_Y15EQ1.A | D72: 2015=1.00 | F72: 0.962238 | G72: 0.963735 | H72: 0.972506 | I72: 0.975369 | J72: 0.97906 | K72: 0.982037 | L72: 0.982878 | M72: 0.982742 | N72: 0.980868 | O72: 1.020371 | P72: 1.018169 | Q72: 1.017907 | R72: 1.016993 | S72: 1.014689 | T72: 1.012976 | U72: 1.012075 | V72: 1.01144 | W72: 1.010168 | X72: 1.008936 | Y72: 1.00961 | Z72: 1.010903 | AA72: 1.010773 | AB72: 1.010664 | AC72: 1.010374 | AD72: 1.010311 | AE72: 1.010293 | AF72: 1.0102 | AG72: 0.002
A73: All Homes | B73: Residential Equipment: Building Shell Efficiency Index: Space Cooling: All Homes: High Zero-Carbon Technology Cost | C73: AEO.2025.HIGHZTC.EFI_BSE_RESD_SPC_AHM_NA_NA_Y15EQ1.A | D73: 2015=1.00 | F73: 0.987118 | G73: 0.985658 | H73: 0.98411 | I73: 0.982377 | J73: 0.980453 | K73: 0.978394 | L73: 0.976264 | M73: 0.974055 | N73: 0.971739 | O73: 0.969759 | P73: 0.96783 | Q73: 0.966045 | R73: 0.964396 | S73: 0.9628 | T73: 0.961193 | U73: 0.959611 | V73: 0.958014 | W73: 0.956344 | X73: 0.954641 | Y73: 0.952937 | Z73: 0.951251 | AA73: 0.949591 | AB73: 0.947931 | AC73: 0.946295 | AD73: 0.944687 | AE73: 0.943085 | AF73: 0.941481 | AG73: -0.002
A74: Distributed Generation and
A75: Combined Heat and Power
A76: Generating Capacity (gigawatts)
A77: Natural Gas Fuel Cells | B77: Residential: Combined Heat and Power: Generating Capacity: Fuel Cells: High Zero-Carbon Technology Cost | C77: AEO.2025.HIGHZTC.CAP_NA_COMM_CHP_FCL_NA_NA_MW.A | D77: GW | F77: 0.001725 | G77: 0.003088 | H77: 0.003101 | I77: 0.003114 | J77: 0.003127 | K77: 0.00314 | L77: 0.003153 | M77: 0.003166 | N77: 0.003179 | O77: 0.003192 | P77: 0.003205 | Q77: 0.003218 | R77: 0.003231 | S77: 0.003244 | T77: 0.003257 | U77: 0.00327 | V77: 0.003285 | W77: 0.003301 | X77: 0.003322 | Y77: 0.003352 | Z77: 0.003399 | AA77: 0.003478 | AB77: 0.003618 | AC77: 0.003759 | AD77: 0.0039 | AE77: 0.004042 | AF77: 0.004185 | AG77: 0.035
A78: Solar Photovoltaic | B78: Residential: Combined Heat and Power: Generating Capacity: Solar Photovoltaic: High Zero-Carbon Technology Cost | C78: AEO.2025.HIGHZTC.CAP_NA_RESD_CHP_SLR_PHTVL_NA_MW.A | D78: GW | F78: 41.307827 | G78: 47.377987 | H78: 53.527718 | I78: 59.344631 | J78: 65.296082 | K78: 71.340698 | L78: 77.804955 | M78: 84.770462 | N78: 91.686966 | O78: 98.871689 | P78: 105.99403 | Q78: 111.56861 | R78: 117.32034 | S78: 123.13393 | T78: 129.23361 | U78: 135.37601 | V78: 141.64864 | W78: 147.97232 | X78: 154.48625 | Y78: 161.0881 | Z78: 167.79971 | AA78: 174.75017 | AB78: 181.85144 | AC78: 189.17082 | AD78: 196.66997 | AE78: 204.34807 | AF78: 212.12654 | AG78: 0.065
A79: Wind | B79: Residential: Combined Heat and Power: Generating Capacity: Wind: High Zero-Carbon Technology Cost | C79: AEO.2025.HIGHZTC.CAP_NA_RESD_CHP_WND_NA_NA_MW.A | D79: GW | F79: 0.308179 | G79: 0.560921 | H79: 0.806044 | I79: 0.908432 | J79: 1.022869 | K79: 1.146172 | L79: 1.390895 | M79: 1.690819 | N79: 1.994769 | O79: 2.108177 | P79: 2.161123 | Q79: 2.162338 | R79: 2.163817 | S79: 2.165545 | T79: 2.167536 | U79: 2.169726 | V79: 2.172139 | W79: 2.1748 | X79: 2.177634 | Y79: 2.18058 | Z79: 2.183634 | AA79: 2.186825 | AB79: 2.190188 | AC79: 2.193648 | AD79: 2.197246 | AE79: 2.200986 | AF79: 2.20487 | AG79: 0.079
A80: Total | B80: Residential: Combined Heat and Power: Generating Capacity: Total: High Zero-Carbon Technology Cost | C80: AEO.2025.HIGHZTC.CAP_NA_RESD_CHP_TOT_NA_NA_MW.A | D80: GW | F80: 41.617729 | G80: 47.941998 | H80: 54.336864 | I80: 60.256176 | J80: 66.322075 | K80: 72.490013 | L80: 79.198997 | M80: 86.464447 | N80: 93.684914 | O80: 100.98305 | P80: 108.15836 | Q80: 113.73417 | R80: 119.4874 | S80: 125.30272 | T80: 131.4044 | U80: 137.549 | V80: 143.82405 | W80: 150.15042 | X80: 156.66721 | Y80: 163.27203 | Z80: 169.98675 | AA80: 176.94047 | AB80: 184.04524 | AC80: 191.36822 | AD80: 198.87112 | AE80: 206.5531 | AF80: 214.33559 | AG80: 0.065
A81: Net Generation (billion kilowatthours)
A82: Natural Gas Fuel Cells | B82: Residential: Combined Heat and Power: Net Generation: Fuel Cells: High Zero-Carbon Technology Cost | C82: AEO.2025.HIGHZTC.GEN_NA_COMM_CHP_FCL_NA_NA_MILLKWH.A | D82: billion kWh | F82: 0.006833 | G82: 0.01223 | H82: 0.012281 | I82: 0.012333 | J82: 0.012384 | K82: 0.012436 | L82: 0.012487 | M82: 0.012539 | N82: 0.01259 | O82: 0.012642 | P82: 0.012693 | Q82: 0.012744 | R82: 0.012796 | S82: 0.012847 | T82: 0.012899 | U82: 0.012951 | V82: 0.013007 | W82: 0.013071 | X82: 0.013154 | Y82: 0.013272 | Z82: 0.013459 | AA82: 0.013774 | AB82: 0.014328 | AC82: 0.014885 | AD82: 0.015444 | AE82: 0.016007 | AF82: 0.016572 | AG82: 0.035
A83: Solar Photovoltaic | B83: Residential: Combined Heat and Power: Net Generation: Solar Photovoltaic: High Zero-Carbon Technology Cost | C83: AEO.2025.HIGHZTC.GEN_NA_COMM_CHP_SLR_PHTVL_NA_MILLKWH.A | D83: billion kWh | F83: 62.697704 | G83: 71.294235 | H83: 79.992973 | I83: 88.17804 | J83: 96.523483 | K83: 104.96889 | L83: 113.99036 | M83: 123.68132 | N83: 133.25902 | O83: 143.18649 | P83: 153.01392 | Q83: 160.67247 | R83: 168.56346 | S83: 176.51448 | T83: 184.85332 | U83: 193.22803 | V83: 201.7585 | W83: 210.33153 | X83: 219.14546 | Y83: 228.05829 | Z83: 237.09641 | AA83: 246.437 | AB83: 255.9633 | AC83: 265.76538 | AD83: 275.78906 | AE83: 286.03299 | AF83: 296.38397 | AG83: 0.062
A84: Wind | B84: Residential: Combined Heat and Power: Net Generation: Wind: High Zero-Carbon Technology Cost | C84: AEO.2025.HIGHZTC.GEN_NA_COMM_CHP_WND_NA_NA_MILLKWH.A | D84: billion kWh | F84: 0.36942 | G84: 0.627201 | H84: 0.879623 | I84: 0.996866 | J84: 1.127979 | K84: 1.269903 | L84: 1.541979 | M84: 1.900119 | N84: 2.263994 | O84: 2.387514 | P84: 2.444973 | Q84: 2.446357 | R84: 2.448035 | S84: 2.44999 | T84: 2.452236 | U84: 2.4547 | V84: 2.457409 | W84: 2.460389 | X84: 2.463559 | Y84: 2.466848 | Z84: 2.470254 | AA84: 2.473806 | AB84: 2.477537 | AC84: 2.481375 | AD84: 2.485367 | AE84: 2.489517 | AF84: 2.493827 | AG84: 0.076
A85: Total | B85: Residential: Combined Heat and Power: Net Generation: Total: High Zero-Carbon Technology Cost | C85: AEO.2025.HIGHZTC.GEN_NA_COMM_CHP_TOT_NA_NA_MILLKWH.A | D85: billion kWh | F85: 63.073956 | G85: 71.933662 | H85: 80.88488 | I85: 89.187233 | J85: 97.663849 | K85: 106.25123 | L85: 115.54483 | M85: 125.59397 | N85: 135.5356 | O85: 145.58664 | P85: 155.47159 | Q85: 163.13156 | R85: 171.02429 | S85: 178.97733 | T85: 187.31845 | U85: 195.69568 | V85: 204.22891 | W85: 212.80499 | X85: 221.62218 | Y85: 230.53841 | Z85: 239.58012 | AA85: 248.92458 | AB85: 258.45517 | AC85: 268.26166 | AD85: 278.28989 | AE85: 288.53851 | AF85: 298.89438 | AG85: 0.062
A86: Disposition
A87: Sales to the Grid | B87: Residential: Combined Heat and Power: Net Generation: Sales to the Grid: High Zero-Carbon Technology Cost | C87: AEO.2025.HIGHZTC.GEN_NA_COMM_CHP_STG_NA_NA_MILLKWH.A | D87: billion kWh | F87: 11.527926 | G87: 13.327675 | H87: 15.115705 | I87: 16.711512 | J87: 18.336744 | K87: 19.964907 | L87: 21.847279 | M87: 23.999292 | N87: 26.07505 | O87: 28.288122 | P87: 30.488134 | Q87: 32.147984 | R87: 33.877605 | S87: 35.58342 | T87: 37.42905 | U87: 39.226177 | V87: 41.04538 | W87: 42.813847 | X87: 44.644409 | Y87: 46.466736 | Z87: 48.275852 | AA87: 50.168255 | AB87: 52.062748 | AC87: 54.058846 | AD87: 56.059513 | AE87: 58.126335 | AF87: 60.175503 | AG87: 0.066
A88: Generation for Own Use | B88: Residential: Combined Heat and Power: Net Generation: Generation for Own Use: High Zero-Carbon Technology Cost | C88: AEO.2025.HIGHZTC.GEN_NA_COMM_CHP_GFO_NA_NA_MILLKWH.A | D88: billion kWh | F88: 51.546032 | G88: 58.605991 | H88: 65.769173 | I88: 72.475723 | J88: 79.32711 | K88: 86.286324 | L88: 93.697556 | M88: 101.59469 | N88: 109.46055 | O88: 117.29853 | P88: 124.98345 | Q88: 130.98358 | R88: 137.14668 | S88: 143.39391 | T88: 149.88939 | U88: 156.4695 | V88: 163.18352 | W88: 169.99115 | X88: 176.97777 | Y88: 184.07167 | Z88: 191.30428 | AA88: 198.75633 | AB88: 206.39241 | AC88: 214.20282 | AD88: 222.23038 | AE88: 230.41217 | AF88: 238.71884 | AG88: 0.061
A89: Energy Input (trillion Btu)
A90: Natural Gas Fuel Cells | B90: Residential: Combined Heat and Power: Energy Input: Fuel Cells: High Zero-Carbon Technology Cost | C90: AEO.2025.HIGHZTC.CNSM_NA_COMM_CHP_FCL_NA_NA_TRLBTU.A | D90: trillion Btu | F90: 0.052159 | G90: 0.093352 | H90: 0.093745 | I90: 0.094138 | J90: 0.094531 | K90: 0.094924 | L90: 0.095317 | M90: 0.09571 | N90: 0.096103 | O90: 0.096496 | P90: 0.096889 | Q90: 0.097282 | R90: 0.097675 | S90: 0.098068 | T90: 0.098461 | U90: 0.09886 | V90: 0.099284 | W90: 0.099774 | X90: 0.100407 | Y90: 0.101309 | Z90: 0.102735 | AA90: 0.105142 | AB90: 0.109371 | AC90: 0.113619 | AD90: 0.117891 | AE90: 0.122184 | AF90: 0.126495 | AG90: 0.035
A91: Solar Photovoltaic | B91: Residential: Combined Heat and Power: Energy Input: Solar Photovoltaic: High Zero-Carbon Technology Cost | C91: AEO.2025.HIGHZTC.CNSM_NA_COMM_CHP_SLR_PHTVL_NA_TRLBTU.A | D91: trillion Btu | F91: 213.92456 | G91: 243.25592 | H91: 272.93601 | I91: 300.86346 | J91: 329.3381 | K91: 358.15387 | L91: 388.93512 | M91: 422.00061 | N91: 454.67975 | O91: 488.55231 | P91: 522.08344 | Q91: 548.21448 | R91: 575.13855 | S91: 602.26739 | T91: 630.71948 | U91: 659.29395 | V91: 688.3999 | W91: 717.65118 | X91: 747.72437 | Y91: 778.13477 | Z91: 808.97296 | AA91: 840.84302 | AB91: 873.34674 | AC91: 906.7915 | AD91: 940.99225 | AE91: 975.94446 | AF91: 1011.262 | AG91: 0.062
A92: Wind | B92: Residential: Combined Heat and Power: Energy Input: Wind: High Zero-Carbon Technology Cost | C92: AEO.2025.HIGHZTC.CNSM_NA_COMM_CHP_WND_NA_NA_TRLBTU.A | D92: trillion Btu | F92: 1.26046 | G92: 2.140008 | H92: 3.001273 | I92: 3.401307 | J92: 3.848665 | K92: 4.332908 | L92: 5.261231 | M92: 6.483206 | N92: 7.724746 | O92: 8.146197 | P92: 8.342248 | Q92: 8.34697 | R92: 8.352695 | S92: 8.359365 | T92: 8.367029 | U92: 8.375438 | V92: 8.38468 | W92: 8.394847 | X92: 8.405662 | Y92: 8.416884 | Z92: 8.428505 | AA92: 8.440624 | AB92: 8.453354 | AC92: 8.46645 | AD92: 8.480072 | AE92: 8.494232 | AF92: 8.508938 | AG92: 0.076
A93: Total | B93: Residential: Combined Heat and Power: Energy Input: Total: High Zero-Carbon Technology Cost | C93: AEO.2025.HIGHZTC.CNSM_NA_COMM_CHP_TOT_NA_NA_TRLBTU.A | D93: trillion Btu | F93: 215.23717 | G93: 245.48929 | H93: 276.03104 | I93: 304.35892 | J93: 333.28131 | K93: 362.5817 | L93: 394.29166 | M93: 428.57953 | N93: 462.50058 | O93: 496.79501 | P93: 530.52252 | Q93: 556.65875 | R93: 583.58893 | S93: 610.72485 | T93: 639.18494 | U93: 667.76825 | V93: 696.88391 | W93: 726.14581 | X93: 756.23041 | Y93: 786.65295 | Z93: 817.50421 | AA93: 849.38879 | AB93: 881.90949 | AC93: 915.37158 | AD93: 949.59021 | AE93: 984.56091 | AF93: 1019.8973 | AG93: 0.062

Sheet Table_4._Residential_Sector_Key
A1: Table 4. Residential Sector Key Indicators and Consumption
A2: https://www.eia.gov/outlooks/aeo/data/browser/#/?id=4-AEO2025&cases=highZTC&sourcekey=0
A3: Tue Dec 02 2025 13:13:01 GMT-0800 (Pacific Standard Time)
A4: Source: U.S. Energy Information Administration
B5: full name | C5: api key | D5: units | E5: 2023 | F5: 2024 | G5: 2025 | H5: 2026 | I5: 2027 | J5: 2028 | K5: 2029 | L5: 2030 | M5: 2031 | N5: 2032 | O5: 2033 | P5: 2034 | Q5: 2035 | R5: 2036 | S5: 2037 | T5: 2038 | U5: 2039 | V5: 2040 | W5: 2041 | X5: 2042 | Y5: 2043 | Z5: 2044 | AA5: 2045 | AB5: 2046 | AC5: 2047 | AD5: 2048 | AE5: 2049 | AF5: 2050 | AG5: Growth (2024-2050)
A6: Key Indicators
A7: Households (millions)
A8: Single-Family | B8: Residential: Key Indicators: Households: Single-Family: High Zero-Carbon Technology Cost | C8: AEO.2025.HIGHZTC.KEI_HHD_RESD_SFR_NA_NA_USA_MILL.A | D8: millions | F8: 88.609744 | G8: 89.620168 | H8: 90.63056 | I8: 91.639144 | J8: 92.631344 | K8: 93.625568 | L8: 94.61288 | M8: 95.59792 | N8: 96.579056 | O8: 97.53976 | P8: 98.471496 | Q8: 99.397144 | R8: 100.30808 | S8: 101.19444 | T8: 102.05506 | U8: 102.88178 | V8: 103.68032 | W8: 104.44803 | X8: 105.19444 | Y8: 105.90901 | Z8: 106.60332 | AA8: 107.29699 | AB8: 107.98818 | AC8: 108.67842 | AD8: 109.36732 | AE8: 110.05501 | AF8: 110.7399 | AG8: 0.009
A9: Multifamily | B9: Residential: Key Indicators: Households: Multifamily: High Zero-Carbon Technology Cost | C9: AEO.2025.HIGHZTC.KEI_HHD_RESD_MFR_NA_NA_USA_MILL.A | D9: millions | F9: 34.017912 | G9: 34.38036 | H9: 34.797956 | I9: 35.233648 | J9: 35.702292 | K9: 36.208236 | L9: 36.726044 | M9: 37.24678 | N9: 37.753312 | O9: 38.226856 | P9: 38.666984 | Q9: 39.093076 | R9: 39.503836 | S9: 39.883568 | T9: 40.239072 | U9: 40.573248 | V9: 40.890328 | W9: 41.185544 | X9: 41.464128 | Y9: 41.734528 | Z9: 42.00598 | AA9: 42.277656 | AB9: 42.549808 | AC9: 42.820992 | AD9: 43.09248 | AE9: 43.364628 | AF9: 43.636816 | AG9: 0.01
A10: Mobile Homes | B10: Residential: Key Indicators: Households: Mobile Homes: High Zero-Carbon Technology Cost | C10: AEO.2025.HIGHZTC.KEI_HHD_RESD_MBH_NA_NA_USA_MILL.A | D10: millions | F10: 6.755902 | G10: 6.748634 | H10: 6.770403 | I10: 6.792666 | J10: 6.804218 | K10: 6.813859 | L10: 6.818653 | M10: 6.824849 | N10: 6.833779 | O10: 6.843395 | P10: 6.850643 | Q10: 6.855789 | R10: 6.86137 | S10: 6.866089 | T10: 6.869494 | U10: 6.871957 | V10: 6.87686 | W10: 6.883047 | X10: 6.889117 | Y10: 6.89479 | Z10: 6.900812 | AA10: 6.907353 | AB10: 6.912851 | AC10: 6.918932 | AD10: 6.924763 | AE10: 6.931044 | AF10: 6.936647 | AG10: 0.001
A11: Total | B11: Residential: Key Indicators: Households: Total: High Zero-Carbon Technology Cost | C11: AEO.2025.HIGHZTC.KEI_HHD_RESD_TEN_NA_NA_USA_MILL.A | D11: millions | F11: 129.38356 | G11: 130.74916 | H11: 132.19892 | I11: 133.66546 | J11: 135.13785 | K11: 136.64766 | L11: 138.15758 | M11: 139.66955 | N11: 141.16615 | O11: 142.61001 | P11: 143.98912 | Q11: 145.34601 | R11: 146.67328 | S11: 147.9441 | T11: 149.16362 | U11: 150.32698 | V11: 151.44751 | W11: 152.51662 | X11: 153.54769 | Y11: 154.53833 | Z11: 155.51011 | AA11: 156.482 | AB11: 157.45084 | AC11: 158.41834 | AD11: 159.38456 | AE11: 160.35068 | AF11: 161.31337 | AG11: 0.009
A12: Average House Square Footage | B12: Residential: Key Indicators: Average House Square Footage: High Zero-Carbon Technology Cost | C12: AEO.2025.HIGHZTC.KEI_HHD_RESD_NA_NA_NA_USA_SQFT.A | D12: sq ft | F12: 1643.9569 | G12: 1650.5161 | H12: 1656.462 | I12: 1662.1603 | J12: 1667.5287 | K12: 1672.5446 | L12: 1677.3794 | M12: 1682.076 | N12: 1686.7471 | O12: 1691.495 | P12: 1696.3218 | Q12: 1701.146 | R12: 1705.9552 | S12: 1710.8412 | T12: 1715.7644 | U12: 1720.6978 | V12: 1725.6134 | W12: 1730.5463 | X12: 1735.4882 | Y12: 1740.3724 | Z12: 1745.155 | AA12: 1749.8751 | AB12: 1754.5343 | AC12: 1759.1407 | AD12: 1763.6879 | AE12: 1768.1737 | AF12: 1772.6058 | AG12: 0.003
A13: Energy Intensity
A14: (MMBtu per household)
A15: Gross End-use Consumption | B15: Residential: Household Energy Intensity: Gross End-use Consumption: High Zero-Carbon Technology Cost | C15: AEO.2025.HIGHZTC.INY_HHD_RESD_DELE_NA_NA_USA_MILLBTUPHOSD.A | D15: MMBtu/household | F15: 85.992244 | G15: 87.9766 | H15: 87.58989 | I15: 87.167932 | J15: 86.534193 | K15: 85.477507 | L15: 84.242287 | M15: 82.878242 | N15: 81.472909 | O15: 80.23763 | P15: 79.124025 | Q15: 78.223224 | R15: 77.510909 | S15: 76.934631 | T15: 76.394609 | U15: 75.9338 | V15: 75.490184 | W15: 75.046198 | X15: 74.63335 | Y15: 74.262238 | Z15: 73.916539 | AA15: 73.581211 | AB15: 73.25364 | AC15: 72.937099 | AD15: 72.637647 | AE15: 72.361427 | AF15: 72.093053 | AG15: -0.007
A16: Delivered Energy Consumption | B16: Residential: Household Energy Intensity: Delivered Energy Consumption: High Zero-Carbon Technology Cost | C16: AEO.2025.HIGHZTC.INY_HHD_RESD_TEN_NA_NA_USA_MILLBTUPHOSD.A | D16: MMBtu/household | F16: 84.632913 | G16: 86.447232 | H16: 85.892414 | I16: 85.317887 | J16: 84.531319 | K16: 83.322996 | L16: 81.928291 | M16: 80.396377 | N16: 78.827237 | O16: 77.431217 | P16: 76.162388 | Q16: 75.148382 | R16: 74.320522 | S16: 73.627571 | T16: 72.966007 | U16: 72.382382 | V16: 71.813781 | W16: 71.24327 | X16: 70.700708 | Y16: 70.198181 | Z16: 69.719191 | AA16: 69.247444 | AB16: 68.781064 | AC16: 68.323618 | AD16: 67.880286 | AE16: 67.458633 | AF16: 67.043821 | AG16: -0.009
A17: (thousand Btu per square foot)
A18: Gross End-use Consumption | B18: Residential: Energy Intensity per Square Foot: Gross End-use Consumption: High Zero-Carbon Technology Cost | C18: AEO.2025.HIGHZTC.INY_HHD_RESD_DELE_NA_NA_USA_THBTUPSQFT.A | D18: thousand Btu/sq ft | F18: 52.308089 | G18: 53.302479 | H18: 52.877692 | I18: 52.442555 | J18: 51.893676 | K18: 51.106266 | L18: 50.22256 | M18: 49.2714 | N18: 48.301794 | O18: 47.435925 | P18: 46.644467 | Q18: 45.982663 | R18: 45.435489 | S18: 44.968891 | T18: 44.525116 | U18: 44.129656 | V18: 43.74687 | W18: 43.365612 | X18: 43.00424 | Y18: 42.670314 | Z18: 42.355285 | AA18: 42.049407 | AB18: 41.751045 | AC18: 41.461776 | AD18: 41.185092 | AE18: 40.924388 | AF18: 40.670662 | AG18: -0.01
A19: Delivered Energy Consumption | B19: Residential: Energy Intensity per Square Foot: Delivered Energy Consumption: High Zero-Carbon Technology Cost | C19: AEO.2025.HIGHZTC.INY_HHD_RESD_TEN_NA_NA_USA_THBTUPSQFT.A | D19: thousand Btu/sq ft | F19: 51.481224 | G19: 52.375879 | H19: 51.852933 | I19: 51.329518 | J19: 50.692573 | K19: 49.818103 | L19: 48.843029 | M19: 47.795923 | N19: 46.733288 | O19: 45.776794 | P19: 44.89855 | Q19: 44.175151 | R19: 43.565342 | S19: 43.035889 | T19: 42.526822 | U19: 42.065715 | V19: 41.616379 | W19: 41.168082 | X19: 40.738225 | Y19: 40.335149 | Z19: 39.950142 | AA19: 39.572792 | AB19: 39.201892 | AC19: 38.839199 | AD19: 38.487698 | AE19: 38.151587 | AF19: 37.822182 | AG19: -0.012
A20: Energy Consumption by Fuel
A21: Electricity
A22: Space Heating | B22: Residential: Electricity: Space Heating: High Zero-Carbon Technology Cost | C22: AEO.2025.HIGHZTC.CNSM_HHD_RESD_SPH_ELC_NA_USA_QBTU.A | D22: quads | F22: 0.528061 | G22: 0.582562 | H22: 0.585545 | I22: 0.589188 | J22: 0.589904 | K22: 0.586412 | L22: 0.580551 | M22: 0.573595 | N22: 0.566739 | O22: 0.560726 | P22: 0.554572 | Q22: 0.550309 | R22: 0.547657 | S22: 0.545295 | T22: 0.542041 | U22: 0.538591 | V22: 0.534952 | W22: 0.530828 | X22: 0.526828 | Y22: 0.522867 | Z22: 0.518328 | AA22: 0.513525 | AB22: 0.508348 | AC22: 0.502928 | AD22: 0.497403 | AE22: 0.492208 | AF22: 0.4868 | AG22: -0.003
A23: Space Cooling | B23: Residential: Electricity: Space Cooling: High Zero-Carbon Technology Cost | C23: AEO.2025.HIGHZTC.CNSM_NA_RESD_SPC_ELC_NA_USA_QBTU.A | D23: quads | F23: 0.997081 | G23: 0.952473 | H23: 0.971354 | I23: 0.98971 | J23: 1.002009 | K23: 1.00703 | L23: 1.009506 | M23: 1.010393 | N23: 1.012497 | O23: 1.019494 | P23: 1.028533 | Q23: 1.041697 | R23: 1.058786 | S23: 1.078113 | T23: 1.096537 | U23: 1.115933 | V23: 1.135576 | W23: 1.155665 | X23: 1.175584 | Y23: 1.195868 | Z23: 1.215889 | AA23: 1.235434 | AB23: 1.254577 | AC23: 1.273539 | AD23: 1.292448 | AE23: 1.311621 | AF23: 1.330636 | AG23: 0.011
A24: Water Heating | B24: Residential: Electricity: Water Heating: High Zero-Carbon Technology Cost | C24: AEO.2025.HIGHZTC.CNSM_NA_RESD_WTHT_ELC_NA_USA_QBTU.A | D24: quads | F24: 0.472693 | G24: 0.459259 | H24: 0.449699 | I24: 0.440442 | J24: 0.428544 | K24: 0.408148 | L24: 0.384946 | M24: 0.360722 | N24: 0.33842 | O24: 0.318282 | P24: 0.300561 | Q24: 0.285426 | R24: 0.272802 | S24: 0.262211 | T24: 0.253048 | U24: 0.245594 | V24: 0.239892 | W24: 0.23575 | X24: 0.233312 | Y24: 0.23256 | Z24: 0.231527 | AA24: 0.230325 | AB24: 0.228973 | AC24: 0.227549 | AD24: 0.226177 | AE24: 0.224938 | AF24: 0.223821 | AG24: -0.028
A25: Refrigeration | B25: Residential: Electricity: Refrigeration: High Zero-Carbon Technology Cost | C25: AEO.2025.HIGHZTC.CNSM_NA_RESD_REFR_ELC_NA_USA_QBTU.A | D25: quads | F25: 0.351479 | G25: 0.349737 | H25: 0.34897 | I25: 0.348118 | J25: 0.347168 | K25: 0.346545 | L25: 0.343717 | M25: 0.341147 | N25: 0.338816 | O25: 0.336635 | P25: 0.334581 | Q25: 0.332782 | R25: 0.331396 | S25: 0.330414 | T25: 0.32985 | U25: 0.329701 | V25: 0.329972 | W25: 0.33064 | X25: 0.331706 | Y25: 0.333167 | Z25: 0.335038 | AA25: 0.337389 | AB25: 0.340228 | AC25: 0.343544 | AD25: 0.346847 | AE25: 0.350126 | AF25: 0.353358 | AG25: 0
A26: Cooking | B26: Residential: Electricity: Cooking: High Zero-Carbon Technology Cost | C26: AEO.2025.HIGHZTC.CNSM_NA_RESD_CGR_ELC_NA_USA_QBTU.A | D26: quads | F26: 0.067364 | G26: 0.067851 | H26: 0.068571 | I26: 0.069303 | J26: 0.07004 | K26: 0.070797 | L26: 0.071554 | M26: 0.072311 | N26: 0.07306 | O26: 0.073778 | P26: 0.074459 | Q26: 0.075123 | R26: 0.075764 | S26: 0.076366 | T26: 0.076926 | U26: 0.077443 | V26: 0.077925 | W26: 0.078369 | X26: 0.078785 | Y26: 0.079176 | Z26: 0.079553 | AA26: 0.079923 | AB26: 0.080284 | AC26: 0.080637 | AD26: 0.080982 | AE26: 0.081316 | AF26: 0.081638 | AG26: 0.007
A27: Clothes Dryers | B27: Residential: Electricity: Clothes Dryers: High Zero-Carbon Technology Cost | C27: AEO.2025.HIGHZTC.CNSM_NA_RESD_CDR_ELC_NA_USA_QBTU.A | D27: quads | F27: 0.191812 | G27: 0.193075 | H27: 0.196545 | I27: 0.200855 | J27: 0.204061 | K27: 0.20567 | L27: 0.206345 | M27: 0.206255 | N27: 0.205808 | O27: 0.205284 | P27: 0.205276 | Q27: 0.206284 | R27: 0.208278 | S27: 0.210919 | T27: 0.213722 | U27: 0.216924 | V27: 0.220611 | W27: 0.224674 | X27: 0.228576 | Y27: 0.232386 | Z27: 0.235967 | AA27: 0.239332 | AB27: 0.242476 | AC27: 0.245414 | AD27: 0.248235 | AE27: 0.250977 | AF27: 0.253559 | AG27: 0.011
A28: Freezers | B28: Residential: Electricity: Freezers: High Zero-Carbon Technology Cost | C28: AEO.2025.HIGHZTC.CNSM_NA_RESD_FRZ_ELC_NA_USA_QBTU.A | D28: quads | F28: 0.079548 | G28: 0.079317 | H28: 0.079323 | I28: 0.079324 | J28: 0.079287 | K28: 0.079225 | L28: 0.07876 | M28: 0.078245 | N28: 0.07769 | O28: 0.077149 | P28: 0.076617 | Q28: 0.076115 | R28: 0.075638 | S28: 0.075175 | T28: 0.074736 | U28: 0.07432 | V28: 0.073932 | W28: 0.073581 | X28: 0.073268 | Y28: 0.072993 | Z28: 0.072761 | AA28: 0.072582 | AB28: 0.072468 | AC28: 0.072415 | AD28: 0.072435 | AE28: 0.072536 | AF28: 0.072717 | AG28: -0.003
A29: Lighting | B29: Residential: Electricity: Lighting: High Zero-Carbon Technology Cost | C29: AEO.2025.HIGHZTC.CNSM_NA_RESD_LGHTNG_ELC_NA_USA_QBTU.A | D29: quads | F29: 0.187371 | G29: 0.18539 | H29: 0.186964 | I29: 0.190632 | J29: 0.193727 | K29: 0.195604 | L29: 0.195166 | M29: 0.194531 | N29: 0.19432 | O29: 0.194149 | P29: 0.194404 | Q29: 0.195278 | R29: 0.196599 | S29: 0.198067 | T29: 0.199294 | U29: 0.200681 | V29: 0.198798 | W29: 0.197172 | X29: 0.195941 | Y29: 0.19514 | Z29: 0.194706 | AA29: 0.194468 | AB29: 0.194278 | AC29: 0.194106 | AD29: 0.194081 | AE29: 0.194207 | AF29: 0.194363 | AG29: 0.001
A30: Clothes Washers | B30: Residential: Electricity: Clothes Washers: High Zero-Carbon Technology Cost | C30: AEO.2025.HIGHZTC.CNSM_NA_RESD_CLW_ELC_NA_USA_QBTU.A | D30: quads | F30: 0.041807 | G30: 0.040731 | H30: 0.039766 | I30: 0.038787 | J30: 0.037633 | K30: 0.036454 | L30: 0.035086 | M30: 0.033659 | N30: 0.032143 | O30: 0.030826 | P30: 0.02971 | Q30: 0.028801 | R30: 0.028112 | S30: 0.027655 | T30: 0.027453 | U30: 0.027522 | V30: 0.02759 | W30: 0.027658 | X30: 0.027733 | Y30: 0.027815 | Z30: 0.027908 | AA30: 0.028016 | AB30: 0.028138 | AC30: 0.028273 | AD30: 0.02842 | AE30: 0.028576 | AF30: 0.028739 | AG30: -0.014
A31: Dishwashers | B31: Residential: Electricity: Dishwashers: High Zero-Carbon Technology Cost | C31: AEO.2025.HIGHZTC.CNSM_NA_RESD_DSW_ELC_NA_USA_QBTU.A | D31: quads | F31: 0.036367 | G31: 0.037219 | H31: 0.038216 | I31: 0.038546 | J31: 0.038751 | K31: 0.038915 | L31: 0.039032 | M31: 0.039101 | N31: 0.039118 | O31: 0.039202 | P31: 0.039359 | Q31: 0.039601 | R31: 0.039936 | S31: 0.040364 | T31: 0.040896 | U31: 0.041538 | V31: 0.042178 | W31: 0.042812 | X31: 0.043444 | Y31: 0.044074 | Z31: 0.044708 | AA31: 0.045349 | AB31: 0.045998 | AC31: 0.046655 | AD31: 0.047318 | AE31: 0.047988 | AF31: 0.048663 | AG31: 0.011
A32: Televisions and Related Equipment | B32: Residential: Electricity: Televisions: High Zero-Carbon Technology Cost | C32: AEO.2025.HIGHZTC.CNSM_NA_RESD_TVR_ELC_NA_USA_QBTU.A | D32: quads | F32: 0.129374 | G32: 0.126544 | H32: 0.125215 | I32: 0.124316 | J32: 0.122902 | K32: 0.120777 | L32: 0.118375 | M32: 0.115926 | N32: 0.113659 | O32: 0.11144 | P32: 0.1095 | Q32: 0.10799 | R32: 0.106861 | S32: 0.105954 | T32: 0.105066 | U32: 0.104306 | V32: 0.103691 | W32: 0.103142 | X32: 0.102677 | Y32: 0.102345 | Z32: 0.102119 | AA32: 0.102036 | AB32: 0.102082 | AC32: 0.102176 | AD32: 0.10236 | AE32: 0.102613 | AF32: 0.102926 | AG32: -0.009
A33: Computers and Related Equipment | B33: Residential: Electricity: Computers: High Zero-Carbon Technology Cost | C33: AEO.2025.HIGHZTC.CNSM_NA_RESD_CMPR_ELC_NA_USA_QBTU.A | D33: quads | F33: 0.100147 | G33: 0.098312 | H33: 0.097712 | I33: 0.097344 | J33: 0.096392 | K33: 0.094706 | L33: 0.092653 | M33: 0.090438 | N33: 0.088259 | O33: 0.086025 | P33: 0.083927 | Q33: 0.082077 | R33: 0.080451 | S33: 0.078944 | T33: 0.077403 | U33: 0.07593 | V33: 0.074545 | W33: 0.073196 | X33: 0.071926 | Y33: 0.070762 | Z33: 0.069712 | AA33: 0.068805 | AB33: 0.068054 | AC33: 0.067421 | AD33: 0.066941 | AE33: 0.066635 | AF33: 0.066465 | AG33: -0.016
... A39: Purchased Electricity at Residential Location | B39: Residential: Electricity: Purchased Electricity at Residential Location: High Zero-Carbon Technology Cost | C39: AEO.2025.HIGHZTC.CNSM_NA_RESD_PURCHELEC_ELC_NA_USA_QBTU.A | D39: quads | F39: 5.141959 | G39: 5.081856 | H39: 5.155061 | I39: 5.245214 | J39: 5.322819 | K39: 5.376949 | L39: 5.423333 | M39: 5.461133 | N39: 5.512463 | O39: 5.571132 | P39: 5.640814 | Q39: 5.72881 | R39: 5.829799 | S39: 5.937385 | T39: 6.039158 | U39: 6.141384 | V39: 6.238818 | W39: 6.331173 | X39: 6.419865 | Y39: 6.505672 | Z39: 6.584554 | AA39: 6.65771 | AB39: 6.726636 | AC39: 6.791243 | AD39: 6.851297 | AE39: 6.909533 | AF39: 6.964614 | AG39: 0.012
A40: Natural Gas
A41: Space Heating | B41: Residential: Natural Gas: Space Heating: High Zero-Carbon Technology Cost | C41: AEO.2025.HIGHZTC.CNSM_NA_RESD_SPH_NG_NA_USA_QBTU.A | D41: quads | F41: 2.777912 | G41: 3.12664 | H41: 3.141604 | I41: 3.146791 | J41: 3.143392 | K41: 3.126671 | L41: 3.103113 | M41: 3.069892 | N41: 3.026127 | O41: 2.987631 | P41: 2.946792 | Q41: 2.912199 | R41: 2.883551 | S41: 2.858295 | T41: 2.834296 | U41: 2.81154 | V41: 2.787776 | W41: 2.761015 | X41: 2.733698 | Y41: 2.706513 | Z41: 2.680865 | AA41: 2.657231 | AB41: 2.634207 | AC41: 2.611903 | AD41: 2.590528 | AE41: 2.569665 | AF41: 2.548368 | AG41: -0.003
A42: Space Cooling | B42: Residential: Natural Gas: Space Cooling: High Zero-Carbon Technology Cost | C42: AEO.2025.HIGHZTC.CNSM_NA_RESD_SPC_NG_NA_USA_QBTU.A | D42: quads | F42: 0.063499 | G42: 0.061038 | H42: 0.061464 | I42: 0.061531 | J42: 0.061383 | K42: 0.061147 | L42: 0.060918 | M42: 0.060665 | N42: 0.060395 | O42: 0.060147 | P42: 0.059927 | Q42: 0.059807 | R42: 0.059799 | S42: 0.059868 | T42: 0.059965 | U42: 0.060137 | V42: 0.060331 | W42: 0.060539 | X42: 0.060751 | Y42: 0.060975 | Z42: 0.061196 | AA42: 0.061401 | AB42: 0.061602 | AC42: 0.061793 | AD42: 0.061997 | AE42: 0.062199 | AF42: 0.062392 | AG42: -0.001
A43: Water Heating | B43: Residential: Natural Gas: Water Heating: High Zero-Carbon Technology Cost | C43: AEO.2025.HIGHZTC.CNSM_NA_RESD_WTHT_NG_NA_USA_QBTU.A | D43: quads | F43: 1.035874 | G43: 1.046498 | H43: 1.058767 | I43: 1.069351 | J43: 1.079818 | K43: 1.080751 | L43: 1.081037 | M43: 1.080496 | N43: 1.078113 | O43: 1.077774 | P43: 1.0797 | Q43: 1.084282 | R43: 1.088853 | S43: 1.093492 | T43: 1.09762 | U43: 1.101219 | V43: 1.10365 | W43: 1.104037 | X43: 1.102943 | Y43: 1.100647 | Z43: 1.097807 | AA43: 1.094437 | AB43: 1.09026 | AC43: 1.085951 | AD43: 1.081866 | AE43: 1.077826 | AF43: 1.074105 | AG43: 0.001
A44: Cooking | B44: Residential: Natural Gas: Cooking: High Zero-Carbon Technology Cost | C44: AEO.2025.HIGHZTC.CNSM_NA_RESD_CGR_NG_NA_USA_QBTU.A | D44: quads | F44: 0.077838 | G44: 0.077799 | H44: 0.077991 | I44: 0.078186 | J44: 0.078378 | K44: 0.078579 | L44: 0.078781 | M44: 0.078972 | N44: 0.079145 | O44: 0.079309 | P44: 0.079496 | Q44: 0.079723 | R44: 0.079999 | S44: 0.080326 | T44: 0.080726 | U44: 0.081166 | V44: 0.081648 | W44: 0.082162 | X44: 0.0827 | Y44: 0.083236 | Z44: 0.083776 | AA44: 0.084327 | AB44: 0.08489 | AC44: 0.085467 | AD44: 0.086059 | AE44: 0.08667 | AF44: 0.087302 | AG44: 0.004
A45: Clothes Dryers | B45: Residential: Natural Gas: Clothes Dryers: High Zero-Carbon Technology Cost | C45: AEO.2025.HIGHZTC.CNSM_NA_RESD_CDR_NG_NA_USA_QBTU.A | D45: quads | F45: 0.039583 | G45: 0.040486 | H45: 0.041405 | I45: 0.042257 | J45: 0.04311 | K45: 0.043956 | L45: 0.044797 | M45: 0.045565 | N45: 0.046229 | O45: 0.046833 | P45: 0.047464 | Q45: 0.048157 | R45: 0.04892 | S45: 0.049719 | T45: 0.050528 | U45: 0.051342 | V45: 0.052121 | W45: 0.052834 | X45: 0.053545 | Y45: 0.054265 | Z45: 0.055017 | AA45: 0.055794 | AB45: 0.056574 | AC45: 0.057377 | AD45: 0.058208 | AE45: 0.05904 | AF45: 0.059869 | AG45: 0.016
A46: Other Uses | B46: Residential: Natural Gas: Other Uses: High Zero-Carbon Technology Cost | C46: AEO.2025.HIGHZTC.CNSM_NA_RESD_OTHU_NG_NA_USA_QBTU.A | D46: quads | F46: 0.608734 | G46: 0.613747 | H46: 0.618291 | I46: 0.6214 | J46: 0.623526 | K46: 0.625004 | L46: 0.625873 | M46: 0.625361 | N46: 0.623064 | O46: 0.620104 | P46: 0.617586 | Q46: 0.615918 | R46: 0.615145 | S46: 0.61492 | T46: 0.614893 | U46: 0.615095 | V46: 0.615118 | W46: 0.614621 | X46: 0.613878 | Y46: 0.613063 | Z46: 0.612441 | AA46: 0.611882 | AB46: 0.611197 | AC46: 0.610648 | AD46: 0.610271 | AE46: 0.609813 | AF46: 0.609269 | AG46: 0
A47: Delivered Energy | B47: Residential: Natural Gas: Delivered Energy: High Zero-Carbon Technology Cost | C47: AEO.2025.HIGHZTC.CNSM_NA_RESD_DELE_NG_NA_USA_QBTU.A | D47: quads | F47: 4.60344 | G47: 4.966208 | H47: 4.999522 | I47: 5.019517 | J47: 5.029608 | K47: 5.016108 | L47: 4.994521 | M47: 4.960952 | N47: 4.913073 | O47: 4.871797 | P47: 4.830965 | Q47: 4.800086 | R47: 4.776269 | S47: 4.75662 | T47: 4.738029 | U47: 4.720499 | V47: 4.700645 | W47: 4.675209 | X47: 4.647515 | Y47: 4.6187 | Z47: 4.591101 | AA47: 4.565073 | AB47: 4.53873 | AC47: 4.513139 | AD47: 4.488929 | AE47: 4.465213 | AF47: 4.441305 | AG47: -0.001
A48: Distillate Fuel Oil
A49: Space Heating | B49: Residential: Distillate Fuel Oil: Space Heating: High Zero-Carbon Technology Cost | C49: AEO.2025.HIGHZTC.CNSM_NA_RESD_SPH_DFO_NA_USA_QBTU.A | D49: quads | F49: 0.379782 | G49: 0.410947 | H49: 0.40629 | I49: 0.399526 | J49: 0.391668 | K49: 0.383605 | L49: 0.375675 | M49: 0.368706 | N49: 0.36258 | O49: 0.357116 | P49: 0.351377 | Q49: 0.345757 | R49: 0.340382 | S49: 0.33508 | T49: 0.329944 | U49: 0.324954 | V49: 0.320003 | W49: 0.315094 | X49: 0.310324 | Y49: 0.305707 | Z49: 0.301 | AA49: 0.296803 | AB49: 0.292746 | AC49: 0.288855 | AD49: 0.285073 | AE49: 0.281366 | AF49: 0.277579 | AG49: -0.012
A50: Water Heating | B50: Residential: Distillate Fuel Oil: Water Heating: High Zero-Carbon Technology Cost | C50: AEO.2025.HIGHZTC.CNSM_NA_RESD_WTHT_DFO_NA_USA_QBTU.A | D50: quads | F50: 0.04028 | G50: 0.038163 | H50: 0.035939 | I50: 0.033678 | J50: 0.031549 | K50: 0.029547 | L50: 0.027811 | M50: 0.026394 | N50: 0.025277 | O50: 0.0244 | P50: 0.023768 | Q50: 0.023374 | R50: 0.022939 | S50: 0.022479 | T50: 0.022013 | U50: 0.02154 | V50: 0.021059 | W50: 0.020565 | X50: 0.020063 | Y50: 0.019557 | Z50: 0.019034 | AA50: 0.018539 | AB50: 0.018051 | AC50: 0.017579 | AD50: 0.017124 | AE50: 0.016686 | AF50: 0.016261 | AG50: -0.034
A51: Other Uses | B51: Residential: Distillate Fuel Oil: Other Uses: High Zero-Carbon Technology Cost | C51: AEO.2025.HIGHZTC.CNSM_NA_RESD_OTHU_DFO_NA_USA_QBTU.A | D51: quads | F51: 0.025815 | G51: 0.026125 | H51: 0.026247 | I51: 0.026216 | J51: 0.026099 | K51: 0.025952 | L51: 0.025805 | M51: 0.025722 | N51: 0.025691 | O51: 0.025659 | P51: 0.025626 | Q51: 0.025586 | R51: 0.025554 | S51: 0.025514 | T51: 0.025482 | U51: 0.025454 | V51: 0.025422 | W51: 0.025383 | X51: 0.025341 | Y51: 0.025298 | Z51: 0.025233 | AA51: 0.025202 | AB51: 0.025176 | AC51: 0.025159 | AD51: 0.025149 | AE51: 0.025135 | AF51: 0.025107 | AG51: -0.001
A52: Delivered Energy | B52: Residential: Distillate Fuel Oil: Delivered Energy: High Zero-Carbon Technology Cost | C52: AEO.2025.HIGHZTC.CNSM_NA_RESD_NA_DFO_NA_USA_QBTU.A | D52: quads | F52: 0.445877 | G52: 0.475235 | H52: 0.468476 | I52: 0.459419 | J52: 0.449316 | K52: 0.439104 | L52: 0.429291 | M52: 0.420822 | N52: 0.413547 | O52: 0.407175 | P52: 0.400771 | Q52: 0.394716 | R52: 0.388874 | S52: 0.383074 | T52: 0.377439 | U52: 0.371949 | V52: 0.366483 | W52: 0.361042 | X52: 0.355729 | Y52: 0.350562 | Z52: 0.345267 | AA52: 0.340544 | AB52: 0.335973 | AC52: 0.331592 | AD52: 0.327346 | AE52: 0.323188 | AF52: 0.318975 | AG52: -0.013
A53: Propane
A54: Space Heating | B54: Residential: Propane: Space Heating: High Zero-Carbon Technology Cost | C54: AEO.2025.HIGHZTC.CNSM_NA_RESD_SPH_PROP_NA_USA_QBTU.A | D54: quads | F54: 0.303247 | G54: 0.337638 | H54: 0.333916 | I54: 0.329423 | J54: 0.324515 | K54: 0.318994 | L54: 0.31282 | M54: 0.306422 | N54: 0.299933 | O54: 0.293791 | P54: 0.287481 | Q54: 0.281694 | R54: 0.27654 | S54: 0.271931 | T54: 0.267676 | U54: 0.263745 | V54: 0.260081 | W54: 0.256547 | X54: 0.253138 | Y54: 0.249816 | Z54: 0.246655 | AA54: 0.24367 | AB54: 0.240954 | AC54: 0.238307 | AD54: 0.235689 | AE54: 0.233024 | AF54: 0.230162 | AG54: -0.011
A55: Water Heating | B55: Residential: Propane: Water Heating: High Zero-Carbon Technology Cost | C55: AEO.2025.HIGHZTC.CNSM_NA_RESD_WTHT_PROP_NA_USA_QBTU.A | D55: quads | F55: 0.056642 | G55: 0.054625 | H55: 0.052684 | I55: 0.050775 | J55: 0.049031 | K55: 0.047143 | L55: 0.045398 | M55: 0.043868 | N55: 0.04252 | O55: 0.041422 | P55: 0.040549 | Q55: 0.039944 | R55: 0.039315 | S55: 0.038686 | T55: 0.038048 | U55: 0.037401 | V55: 0.03675 | W55: 0.036075 | X55: 0.035377 | Y55: 0.034657 | Z55: 0.033936 | AA55: 0.033213 | AB55: 0.032506 | AC55: 0.031829 | AD55: 0.031183 | AE55: 0.030557 | AF55: 0.029941 | AG55: -0.024
A56: Cooking | B56: Residential: Propane: Cooking: High Zero-Carbon Technology Cost | C56: AEO.2025.HIGHZTC.CNSM_NA_RESD_CGR_PROP_NA_USA_QBTU.A | D56: quads | F56: 0.010414 | G56: 0.010315 | H56: 0.010249 | I56: 0.010179 | J56: 0.010103 | K56: 0.010025 | L56: 0.009944 | M56: 0.009859 | N56: 0.009767 | O56: 0.009671 | P56: 0.009571 | Q56: 0.009465 | R56: 0.009354 | S56: 0.009237 | T56: 0.009139 | U56: 0.009061 | V56: 0.009006 | W56: 0.008974 | X56: 0.008966 | Y56: 0.008956 | Z56: 0.008943 | AA56: 0.008929 | AB56: 0.008912 | AC56: 0.008894 | AD56: 0.008872 | AE56: 0.008848 | AF56: 0.008823 | AG56: -0.006
A57: Other Uses | B57: Residential: Propane: Other Uses: High Zero-Carbon Technology Cost | C57: AEO.2025.HIGHZTC.CNSM_NA_RESD_OTHU_PROP_NA_USA_QBTU.A | D57: quads | F57: 0.075281 | G57: 0.078132 | H57: 0.080817 | I57: 0.083365 | J57: 0.085864 | K57: 0.088323 | L57: 0.090687 | M57: 0.093015 | N57: 0.095246 | O57: 0.097373 | P57: 0.099442 | Q57: 0.101583 | R57: 0.103856 | S57: 0.10623 | T57: 0.108665 | U57: 0.111141 | V57: 0.113638 | W57: 0.116105 | X57: 0.118547 | Y57: 0.120947 | Z57: 0.123361 | AA57: 0.125781 | AB57: 0.128248 | AC57: 0.130785 | AD57: 0.133369 | AE57: 0.13592 | AF57: 0.138362 | AG57: 0.024
A58: Delivered Energy | B58: Residential: Propane: Delivered Energy: High Zero-Carbon Technology Cost | C58: AEO.2025.HIGHZTC.CNSM_NA_RESD_DELE_PROP_NA_USA_QBTU.A | D58: quads | F58: 0.445585 | G58: 0.480711 | H58: 0.477666 | I58: 0.473743 | J58: 0.469514 | K58: 0.464486 | L58: 0.458849 | M58: 0.453163 | N58: 0.447466 | O58: 0.442258 | P58: 0.437043 | Q58: 0.432687 | R58: 0.429065 | S58: 0.426084 | T58: 0.423529 | U58: 0.421347 | V58: 0.419476 | W58: 0.417701 | X58: 0.416029 | Y58: 0.414376 | Z58: 0.412896 | AA58: 0.411593 | AB58: 0.41062 | AC58: 0.409815 | AD58: 0.409114 | AE58: 0.408349 | AF58: 0.407288 | AG58: -0.003
A59: Marketed Renewables (wood) | B59: Residential: Marketed Renewables (wood): High Zero-Carbon Technology Cost | C59: AEO.2025.HIGHZTC.CNSM_NA_RESD_NA_MRW_NA_USA_QBTU.A | D59: quads | F59: 0.357583 | G59: 0.365094 | H59: 0.352654 | I59: 0.347295 | J59: 0.345718 | K59: 0.345503 | L59: 0.34529 | M59: 0.342499 | N59: 0.337295 | O59: 0.332838 | P59: 0.328234 | Q59: 0.323965 | R59: 0.319381 | S59: 0.315221 | T59: 0.311018 | U59: 0.306564 | V59: 0.302182 | W59: 0.2981 | X59: 0.294377 | Y59: 0.29095 | Z59: 0.288536 | AA59: 0.284935 | AB59: 0.281377 | AC59: 0.277692 | AD59: 0.273872 | AE59: 0.270572 | AF59: 0.26805 | AG59: -0.011
A60: Energy Consumption by End Use
A61: Space Heating | B61: Residential: Delivered Energy Use by End Use: Space Heating: High Zero-Carbon Technology Cost | C61: AEO.2025.HIGHZTC.CNSM_NA_RESD_SPH_DEE_NA_USA_QBTU.A | D61: quads | F61: 4.346586 | G61: 4.82288 | H61: 4.820008 | I61: 4.812223 | J61: 4.795197 | K61: 4.761184 | L61: 4.717449 | M61: 4.661115 | N61: 4.592674 | O61: 4.532102 | P61: 4.468456 | Q61: 4.413923 | R61: 4.367511 | S61: 4.325822 | T61: 4.284976 | U61: 4.245395 | V61: 4.204994 | W61: 4.161585 | X61: 4.118366 | Y61: 4.075853 | Z61: 4.035384 | AA61: 3.996163 | AB61: 3.957632 | AC61: 3.919685 | AD61: 3.882566 | AE61: 3.846835 | AF61: 3.810959 | AG61: -0.005
A62: Space Cooling | B62: Residential: Delivered Energy Use by End Use: Space Cooling: High Zero-Carbon Technology Cost | C62: AEO.2025.HIGHZTC.CNSM_NA_RESD_SPC_DEE_NA_USA_QBTU.A | D62: quads | F62: 1.06058 | G62: 1.013512 | H62: 1.032818 | I62: 1.051242 | J62: 1.063392 | K62: 1.068177 | L62: 1.070424 | M62: 1.071058 | N62: 1.072892 | O62: 1.07964 | P62: 1.088461 | Q62: 1.101504 | R62: 1.118585 | S62: 1.137981 | T62: 1.156502 | U62: 1.17607 | V62: 1.195907 | W62: 1.216205 | X62: 1.236335 | Y62: 1.256843 | Z62: 1.277084 | AA62: 1.296835 | AB62: 1.316179 | AC62: 1.335333 | AD62: 1.354445 | AE62: 1.37382 | AF62: 1.393028 | AG62: 0.011
A63: Water Heating | B63: Residential: Delivered Energy Use by End Use: Water Heating: High Zero-Carbon Technology Cost | C63: AEO.2025.HIGHZTC.CNSM_NA_RESD_WTHT_DEE_NA_USA_QBTU.A | D63: quads | F63: 1.605489 | G63: 1.598546 | H63: 1.597089 | I63: 1.594245 | J63: 1.588942 | K63: 1.56559 | L63: 1.539192 | M63: 1.511479 | N63: 1.484329 | O63: 1.461879 | P63: 1.444578 | Q63: 1.433026 | R63: 1.423908 | S63: 1.416868 | T63: 1.410729 | U63: 1.405754 | V63: 1.401351 | W63: 1.396427 | X63: 1.391695 | Y63: 1.387422 | Z63: 1.382303 | AA63: 1.376514 | AB63: 1.36979 | AC63: 1.362908 | AD63: 1.356351 | AE63: 1.350008 | AF63: 1.344129 | AG63: -0.007
A64: Refrigeration | B64: Residential: Delivered Energy Use by End Use: Refrigeration: High Zero-Carbon Technology Cost | C64: AEO.2025.HIGHZTC.CNSM_NA_RESD_REFR_DEE_NA_USA_QBTU.A | D64: quads | F64: 0.351479 | G64: 0.349737 | H64: 0.34897 | I64: 0.348118 | J64: 0.347168 | K64: 0.346545 | L64: 0.343717 | M64: 0.341147 | N64: 0.338816 | O64: 0.336635 | P64: 0.334581 | Q64: 0.332782 | R64: 0.331396 | S64: 0.330414 | T64: 0.32985 | U64: 0.329701 | V64: 0.329972 | W64: 0.33064 | X64: 0.331706 | Y64: 0.333167 | Z64: 0.335038 | AA64: 0.337389 | AB64: 0.340228 | AC64: 0.343544 | AD64: 0.346847 | AE64: 0.350126 | AF64: 0.353358 | AG64: 0
A65: Cooking | B65: Residential: Delivered Energy Use by End Use: Cooking: High Zero-Carbon Technology Cost | C65: AEO.2025.HIGHZTC.CNSM_NA_RESD_CGR_DEE_NA_USA_QBTU.A | D65: quads | F65: 0.155616 | G65: 0.155966 | H65: 0.15681 | I65: 0.157668 | J65: 0.158521 | K65: 0.159401 | L65: 0.160279 | M65: 0.161142 | N65: 0.161972 | O65: 0.162759 | P65: 0.163526 | Q65: 0.164311 | R65: 0.165117 | S65: 0.165929 | T65: 0.166792 | U65: 0.16767 | V65: 0.168579 | W65: 0.169504 | X65: 0.170452 | Y65: 0.171368 | Z65: 0.172272 | AA65: 0.173179 | AB65: 0.174087 | AC65: 0.174998 | AD65: 0.175913 | AE65: 0.176835 | AF65: 0.177762 | AG65: 0.005
A66: Clothes Dryers | B66: Residential: Delivered Energy Use by End Use: Clothes Dryers: High Zero-Carbon Technology Cost | C66: AEO.2025.HIGHZTC.CNSM_NA_RESD_CDR_DEE_NA_USA_QBTU.A | D66: quads | F66: 0.231395 | G66: 0.233561 | H66: 0.237949 | I66: 0.243112 | J66: 0.247172 | K66: 0.249626 | L66: 0.251142 | M66: 0.251821 | N66: 0.252038 | O66: 0.252117 | P66: 0.25274 | Q66: 0.254441 | R66: 0.257198 | S66: 0.260638 | T66: 0.26425 | U66: 0.268266 | V66: 0.272733 | W66: 0.277508 | X66: 0.282121 | Y66: 0.28665 | Z66: 0.290984 | AA66: 0.295126 | AB66: 0.29905 | AC66: 0.302791 | AD66: 0.306443 | AE66: 0.310017 | AF66: 0.313427 | AG66: 0.012
A67: Freezers | B67: Residential: Delivered Energy Use by End Use: Freezers: High Zero-Carbon Technology Cost | C67: AEO.2025.HIGHZTC.CNSM_NA_RESD_FRZ_DEE_NA_USA_QBTU.A | D67: quads | F67: 0.079548 | G67: 0.079317 | H67: 0.079323 | I67: 0.079324 | J67: 0.079287 | K67: 0.079225 | L67: 0.07876 | M67: 0.078245 | N67: 0.07769 | O67: 0.077149 | P67: 0.076617 | Q67: 0.076115 | R67: 0.075638 | S67: 0.075175 | T67: 0.074736 | U67: 0.07432 | V67: 0.073932 | W67: 0.073581 | X67: 0.073268 | Y67: 0.072993 | Z67: 0.072761 | AA67: 0.072582 | AB67: 0.072468 | AC67: 0.072415 | AD67: 0.072435 | AE67: 0.072536 | AF67: 0.072717 | AG67: -0.003
A68: Lighting | B68: Residential: Delivered Energy Use by End Use: Lighting: High Zero-Carbon Technology Cost | C68: AEO.2025.HIGHZTC.CNSM_NA_RESD_LGHTNG_DEE_NA_USA_QBTU.A | D68: quads | F68: 0.187371 | G68: 0.18539 | H68: 0.186964 | I68: 0.190632 | J68: 0.193727 | K68: 0.195604 | L68: 0.195166 | M68: 0.194531 | N68: 0.19432 | O68: 0.194149 | P68: 0.194404 | Q68: 0.195278 | R68: 0.196599 | S68: 0.198067 | T68: 0.199294 | U68: 0.200681 | V68: 0.198798 | W68: 0.197172 | X68: 0.195941 | Y68: 0.19514 | Z68: 0.194706 | AA68: 0.194468 | AB68: 0.194278 | AC68: 0.194106 | AD68: 0.194081 | AE68: 0.194207 | AF68: 0.194363 | AG68: 0.001
A69: Clothes Washers | B69: Residential: Delivered Energy Use by End Use: Clothes Washers: High Zero-Carbon Technology Cost | C69: AEO.2025.HIGHZTC.CNSM_NA_RESD_CLW_DEE_NA_USA_QBTU.A | D69: quads | F69: 0.041807 | G69: 0.040731 | H69: 0.039766 | I69: 0.038787 | J69: 0.037633 | K69: 0.036454 | L69: 0.035086 | M69: 0.033659 | N69: 0.032143 | O69: 0.030826 | P69: 0.02971 | Q69: 0.028801 | R69: 0.028112 | S69: 0.027655 | T69: 0.027453 | U69: 0.027522 | V69: 0.02759 | W69: 0.027658 | X69: 0.027733 | Y69: 0.027815 | Z69: 0.027908 | AA69: 0.028016 | AB69: 0.028138 | AC69: 0.028273 | AD69: 0.02842 | AE69: 0.028576 | AF69: 0.028739 | AG69: -0.014
A70: Dishwashers | B70: Residential: Delivered Energy Use by End Use: Dishwashers: High Zero-Carbon Technology Cost | C70: AEO.2025.HIGHZTC.CNSM_NA_RESD_DSW_DEE_NA_USA_QBTU.A | D70: quads | F70: 0.036367 | G70: 0.037219 | H70: 0.038216 | I70: 0.038546 | J70: 0.038751 | K70: 0.038915 | L70: 0.039032 | M70: 0.039101 | N70: 0.039118 | O70: 0.039202 | P70: 0.039359 | Q70: 0.039601 | R70: 0.039936 | S70: 0.040364 | T70: 0.040896 | U70: 0.041538 | V70: 0.042178 | W70: 0.042812 | X70: 0.043444 | Y70: 0.044074 | Z70: 0.044708 | AA70: 0.045349 | AB70: 0.045998 | AC70: 0.046655 | AD70: 0.047318 | AE70: 0.047988 | AF70: 0.048663 | AG70: 0.011
A71: Televisions and Related Equipment | B71: Residential: Delivered Energy Use by End Use: Televisions: High Zero-Carbon Technology Cost | C71: AEO.2025.HIGHZTC.CNSM_NA_RESD_TVR_DEE_NA_USA_QBTU.A | D71: quads | F71: 0.129374 | G71: 0.126544 | H71: 0.125215 | I71: 0.124316 | J71: 0.122902 | K71: 0.120777 | L71: 0.118375 | M71: 0.115926 | N71: 0.113659 | O71: 0.11144 | P71: 0.1095 | Q71: 0.10799 | R71: 0.106861 | S71: 0.105954 | T71: 0.105066 | U71: 0.104306 | V71: 0.103691 | W71: 0.103142 | X71: 0.102677 | Y71: 0.102345 | Z71: 0.102119 | AA71: 0.102036 | AB71: 0.102082 | AC71: 0.102176 | AD71: 0.10236 | AE71: 0.102613 | AF71: 0.102926 | AG71: -0.009
A72: Computers and Related Equipment | B72: Residential: Delivered Energy Use by End Use: Computers: High Zero-Carbon Technology Cost | C72: AEO.2025.HIGHZTC.CNSM_NA_RESD_CMPR_DEE_NA_USA_QBTU.A | D72: quads | F72: 0.100147 | G72: 0.098312 | H72: 0.097712 | I72: 0.097344 | J72: 0.096392 | K72: 0.094706 | L72: 0.092653 | M72: 0.090438 | N72: 0.088259 | O72: 0.086025 | P72: 0.083927 | Q72: 0.082077 | R72: 0.080451 | S72: 0.078944 | T72: 0.077403 | U72: 0.07593 | V72: 0.074545 | W72: 0.073196 | X72: 0.071926 | Y72: 0.070762 | Z72: 0.069712 | AA72: 0.068805 | AB72: 0.068054 | AC72: 0.067421 | AD72: 0.066941 | AE72: 0.066635 | AF72: 0.066465 | AG72: -0.016
... A79: Electricity Related Losses | B79: Residential: Electricity Related Losses: High Zero-Carbon Technology Cost | C79: AEO.2025.HIGHZTC.CNSM_LOSSES_RESD_NA_ENRL_NA_USA_QBTU.A | D79: quads | F79: 7.308165 | G79: 7.003442 | H79: 6.681392 | I79: 6.538555 | J79: 6.488052 | K79: 6.438865 | L79: 6.233474 | M79: 6.076113 | N79: 5.736357 | O79: 5.608802 | P79: 5.473529 | Q79: 5.314852 | R79: 5.178302 | S79: 4.998352 | T79: 4.923231 | U79: 4.706847 | V79: 4.695487 | W79: 4.754326 | X79: 4.81075 | Y79: 4.841031 | Z79: 4.874164 | AA79: 4.873587 | AB79: 4.868451 | AC79: 4.876808 | AD79: 4.895246 | AE79: 4.921697 | AF79: 4.907921 | AG79: -0.015
A80: Total Energy Consumption by End Use
A81: Space Heating | B81: Residential: Total Energy Use by End Use: Space Heating: High Zero-Carbon Technology Cost | C81: AEO.2025.HIGHZTC.CNSM_NA_RESD_SPH_TEE_NA_USA_QBTU.A | D81: quads | F81: 5.072077 | G81: 5.594944 | H81: 5.546676 | I81: 5.512751 | J81: 5.478197 | K81: 5.42523 | L81: 5.345297 | M81: 5.258322 | N81: 5.141565 | O81: 5.054691 | P81: 4.964053 | Q81: 4.882354 | R81: 4.812238 | S81: 4.744048 | T81: 4.686104 | U81: 4.618788 | V81: 4.567894 | W81: 4.519598 | X81: 4.471659 | Y81: 4.422812 | Z81: 4.376312 | AA81: 4.328954 | AB81: 4.282132 | AC81: 4.23701 | AD81: 4.193624 | AE81: 4.152516 | AF81: 4.108894 | AG81: -0.008
A82: Space Cooling | B82: Residential: Total Energy Use by End Use: Space Cooling: High Zero-Carbon Technology Cost | C82: AEO.2025.HIGHZTC.CNSM_NA_RESD_SPC_TEE_NA_USA_QBTU.A | D82: quads | F82: 2.430449 | G82: 2.275815 | H82: 2.238277 | I82: 2.227978 | J82: 2.223534 | K82: 2.208526 | L82: 2.162174 | M82: 2.123043 | N82: 2.053504 | O82: 2.029796 | P82: 2.007618 | Q82: 1.988211 | R82: 1.978376 | S82: 1.964862 | T82: 1.967977 | U82: 1.949721 | V82: 1.966256 | W82: 1.995634 | X82: 2.024689 | Y82: 2.050387 | Z82: 2.07683 | AA82: 2.09746 | AB82: 2.117029 | AC82: 2.138878 | AD82: 2.162695 | AE82: 2.18839 | AF82: 2.207412 | AG82: -0.004
A83: Water Heating | B83: Residential: Total Energy Use by End Use: Water Heating: High Zero-Carbon Technology Cost | C83: AEO.2025.HIGHZTC.CNSM_NA_RESD_WTHT_TEE_NA_USA_QBTU.A | D83: quads | F83: 2.254912 | G83: 2.207198 | H83: 2.15517 | I83: 2.117918 | J83: 2.085118 | K83: 2.027772 | L83: 1.955499 | M83: 1.88705 | N83: 1.812092 | O83: 1.758513 | P83: 1.713177 | Q83: 1.675984 | R83: 1.645438 | S83: 1.617976 | T83: 1.597992 | U83: 1.576019 | V83: 1.564088 | W83: 1.555426 | X83: 1.548156 | Y83: 1.541742 | Z83: 1.534589 | AA83: 1.525777 | AB83: 1.515953 | AC83: 1.506481 | AD83: 1.497794 | AE83: 1.489704 | AF83: 1.481113 | AG83: -0.016
A84: Refrigeration | B84: Residential: Total Energy Use by End Use: Refrigeration: High Zero-Carbon Technology Cost | C84: AEO.2025.HIGHZTC.CNSM_NA_RESD_REFR_TEE_NA_USA_QBTU.A | D84: quads | F84: 0.834369 | G84: 0.81324 | H84: 0.782045 | I84: 0.76202 | J84: 0.749124 | K84: 0.738968 | L84: 0.715436 | M84: 0.696337 | N84: 0.666962 | O84: 0.650374 | P84: 0.633581 | Q84: 0.61605 | R84: 0.600507 | S84: 0.583832 | T84: 0.57395 | U84: 0.558276 | V84: 0.553818 | W84: 0.553637 | X84: 0.55415 | Y84: 0.554248 | Z84: 0.555408 | AA84: 0.556034 | AB84: 0.55741 | AC84: 0.560304 | AD84: 0.563752 | AE84: 0.567568 | AF84: 0.569623 | AG84: -0.015
A85: Cooking | B85: Residential: Total Energy Use by End Use: Cooking: High Zero-Carbon Technology Cost | C85: AEO.2025.HIGHZTC.CNSM_NA_RESD_CGR_TEE_NA_USA_QBTU.A | D85: quads | F85: 0.248167 | G85: 0.245888 | H85: 0.241907 | I85: 0.240067 | J85: 0.239614 | K85: 0.23957 | L85: 0.237662 | M85: 0.23643 | N85: 0.232731 | O85: 0.231519 | P85: 0.230068 | Q85: 0.228257 | R85: 0.226642 | S85: 0.224499 | T85: 0.22372 | U85: 0.22136 | V85: 0.221442 | W85: 0.22236 | X85: 0.223285 | Y85: 0.223908 | Z85: 0.224597 | AA85: 0.224973 | AB85: 0.225335 | AC85: 0.225876 | AD85: 0.226556 | AE85: 0.227335 | AF85: 0.227726 | AG85: -0.003
A86: Clothes Dryers | B86: Residential: Total Energy Use by End Use: Clothes Dryers: High Zero-Carbon Technology Cost | C86: AEO.2025.HIGHZTC.CNSM_NA_RESD_CDR_TEE_NA_USA_QBTU.A | D86: quads | F86: 0.494922 | G86: 0.489441 | H86: 0.481863 | I86: 0.481922 | J86: 0.483437 | K86: 0.482524 | L86: 0.474297 | M86: 0.466567 | N86: 0.451365 | O86: 0.443439 | P86: 0.436187 | Q86: 0.430033 | R86: 0.426331 | S86: 0.422407 | T86: 0.422411 | U86: 0.418654 | V86: 0.42239 | W86: 0.429038 | X86: 0.435405 | Y86: 0.440855 | Z86: 0.44619 | AA86: 0.450226 | AB86: 0.453832 | AC86: 0.457635 | AD86: 0.46168 | AE86: 0.465884 | AF86: 0.468612 | AG86: -0.002
A87: Freezers | B87: Residential: Total Energy Use by End Use: Freezers: High Zero-Carbon Technology Cost | C87: AEO.2025.HIGHZTC.CNSM_NA_RESD_FRZ_TEE_NA_USA_QBTU.A | D87: quads | F87: 0.188837 | G87: 0.184434 | H87: 0.177765 | I87: 0.173638 | J87: 0.171087 | K87: 0.168939 | L87: 0.163936 | M87: 0.159711 | N87: 0.152933 | O87: 0.149051 | P87: 0.145087 | Q87: 0.140906 | R87: 0.137059 | S87: 0.132833 | T87: 0.130043 | U87: 0.125845 | V87: 0.124086 | W87: 0.123207 | X87: 0.122402 | Y87: 0.121429 | Z87: 0.120619 | AA87: 0.119619 | AB87: 0.118727 | AC87: 0.118106 | AD87: 0.117734 | AE87: 0.117583 | AF87: 0.117221 | AG87: -0.018
A88: Lighting | B88: Residential: Total Energy Use by End Use: Lighting: High Zero-Carbon Technology Cost | C88: AEO.2025.HIGHZTC.CNSM_NA_RESD_LGHTNG_TEE_NA_USA_QBTU.A | D88: quads | F88: 0.444797 | G88: 0.431085 | H88: 0.418989 | I88: 0.417288 | J88: 0.418027 | K88: 0.417105 | L88: 0.406232 | M88: 0.39707 | N88: 0.382521 | O88: 0.375093 | P88: 0.368135 | Q88: 0.361501 | R88: 0.356248 | S88: 0.349978 | T88: 0.346777 | U88: 0.339808 | V88: 0.333658 | W88: 0.330153 | X88: 0.327341 | Y88: 0.32463 | Z88: 0.322772 | AA88: 0.320494 | AB88: 0.318293 | AC88: 0.316578 | AD88: 0.315452 | AE88: 0.314817 | AF88: 0.313318 | AG88: -0.013
A89: Clothes Washers | B89: Residential: Total Energy Use by End Use: Clothes Washers: High Zero-Carbon Technology Cost | C89: AEO.2025.HIGHZTC.CNSM_NA_RESD_CLW_TEE_NA_USA_QBTU.A | D89: quads | F89: 0.099244 | G89: 0.09471 | H89: 0.089117 | I89: 0.084904 | J89: 0.081205 | K89: 0.077735 | L89: 0.07303 | M89: 0.068704 | N89: 0.063274 | O89: 0.059556 | P89: 0.056261 | Q89: 0.053317 | R89: 0.050941 | S89: 0.048865 | T89: 0.047769 | U89: 0.046602 | V89: 0.046306 | W89: 0.046312 | X89: 0.046331 | Y89: 0.046272 | Z89: 0.046264 | AA89: 0.046172 | AB89: 0.0461 | AC89: 0.046112 | AD89: 0.046192 | AE89: 0.046323 | AF89: 0.046328 | AG89: -0.029
A90: Dishwashers | B90: Residential: Total Energy Use by End Use: Dishwashers: High Zero-Carbon Technology Cost | C90: AEO.2025.HIGHZTC.CNSM_NA_RESD_DSW_TEE_NA_USA_QBTU.A | D90: quads | F90: 0.086331 | G90: 0.086545 | H90: 0.085642 | I90: 0.084376 | J90: 0.083618 | K90: 0.082981 | L90: 0.081243 | M90: 0.079811 | N90: 0.077004 | O90: 0.075737 | P90: 0.074533 | Q90: 0.073311 | R90: 0.072366 | S90: 0.071323 | T90: 0.071161 | U90: 0.070336 | V90: 0.07079 | W90: 0.071685 | X90: 0.072578 | Y90: 0.073321 | Z90: 0.074114 | AA90: 0.074738 | AB90: 0.075361 | AC90: 0.076092 | AD90: 0.076909 | AE90: 0.07779 | AF90: 0.078446 | AG90: -0.004
A91: Televisions and Related Equipment | B91: Residential: Total Energy Use by End Use: Televisions: High Zero-Carbon Technology Cost | C91: AEO.2025.HIGHZTC.CNSM_NA_RESD_TVR_TEE_NA_USA_QBTU.A | D91: quads | F91: 0.307119 | G91: 0.294251 | H91: 0.280609 | I91: 0.272123 | J91: 0.265199 | K91: 0.257544 | L91: 0.246393 | M91: 0.236623 | N91: 0.223739 | O91: 0.2153 | P91: 0.207355 | Q91: 0.199913 | R91: 0.193637 | S91: 0.187217 | T91: 0.182818 | U91: 0.17662 | V91: 0.174033 | W91: 0.172705 | X91: 0.171532 | Y91: 0.170258 | Z91: 0.169288 | AA91: 0.168161 | AB91: 0.167245 | AC91: 0.166644 | AD91: 0.166372 | AE91: 0.16634 | AF91: 0.16592 | AG91: -0.023
A92: Computers and Related Equipment | B92: Residential: Total Energy Use by End Use: Computers: High Zero-Carbon Technology Cost | C92: AEO.2025.HIGHZTC.CNSM_NA_RESD_CMPR_TEE_NA_USA_QBTU.A | D92: quads | F92: 0.237738 | G92: 0.228604 | H92: 0.218973 | I92: 0.213083 | J92: 0.207996 | K92: 0.20195 | L92: 0.192855 | M92: 0.184598 | N92: 0.173739 | O92: 0.166199 | P92: 0.15893 | Q92: 0.151943 | R92: 0.145781 | S92: 0.139492 | T92: 0.134683 | U92: 0.12857 | V92: 0.125114 | W92: 0.122562 | X92: 0.12016 | Y92: 0.117718 | Z92: 0.115565 | AA92: 0.113394 | AB92: 0.111496 | AC92: 0.109961 | AD92: 0.108803 | AE92: 0.108018 | AF92: 0.107144 | AG92: -0.03
... A98: Total Energy | B98: Residential: Total Net Own-use Generation: Total Gross End-use Consumption: High Zero-Carbon Technology Cost | C98: AEO.2025.HIGHZTC.GEN_NA_RESD_TTG_TEE_NA_USA_QBTU.A | D98: quads | F98: 18.302611 | G98: 18.372553 | H98: 18.134776 | I98: 18.083752 | J98: 18.10504 | K98: 18.081033 | L98: 17.884776 | M98: 17.714714 | N98: 17.360242 | O98: 17.234044 | P98: 17.111412 | Q98: 16.995181 | R98: 16.921761 | S98: 16.816811 | T98: 16.812485 | U98: 16.668676 | V98: 16.723193 | W98: 16.83765 | X98: 16.944375 | Y98: 17.021435 | Z98: 17.096641 | AA98: 17.133556 | AB98: 17.16192 | AC98: 17.20043 | AD98: 17.245937 | AE98: 17.298698 | AF98: 17.308274 | AG98: -0.002
A99: Nonmarketed Renewables
A100: Solar Hot Water Heating | B100: Residential: Nonmarketed Renewables: Solar Hot Water Heating: High Zero-Carbon Technology Cost | C100: AEO.2025.HIGHZTC.CNSM_NA_RESD_SHW_NRW_NA_USA_QBTU.A | D100: quads | F100: 0.035525 | G100: 0.042155 | H100: 0.049198 | I100: 0.055102 | J100: 0.061131 | K100: 0.063327 | L100: 0.066036 | M100: 0.068474 | N100: 0.071069 | O100: 0.071029 | P100: 0.07183 | Q100: 0.071849 | R100: 0.071916 | S100: 0.071802 | T100: 0.071685 | U100: 0.071601 | V100: 0.070627 | W100: 0.070499 | X100: 0.070575 | Y100: 0.070644 | Z100: 0.070711 | AA100: 0.070803 | AB100: 0.071024 | AC100: 0.070883 | AD100: 0.070941 | AE100: 0.070838 | AF100: 0.07093 | AG100: 0.027
A101: Solar Photovoltaic | B101: Residential: Nonmarketed Renewables: Solar Photovoltaic: High Zero-Carbon Technology Cost | C101: AEO.2025.HIGHZTC.CNSM_NA_RESD_SOPH_NRW_NA_USA_QBTU.A | D101: quads | F101: 0.213925 | G101: 0.243256 | H101: 0.272936 | I101: 0.300863 | J101: 0.329338 | K101: 0.358154 | L101: 0.388935 | M101: 0.422001 | N101: 0.45468 | O101: 0.488552 | P101: 0.522083 | Q101: 0.548214 | R101: 0.575139 | S101: 0.602267 | T101: 0.630719 | U101: 0.659294 | V101: 0.6884 | W101: 0.717651 | X101: 0.747724 | Y101: 0.778135 | Z101: 0.808973 | AA101: 0.840843 | AB101: 0.873347 | AC101: 0.906792 | AD101: 0.940992 | AE101: 0.975945 | AF101: 1.011262 | AG101: 0.062
A102: Wind | B102: Residential: Nonmarketed Renewables: Wind: High Zero-Carbon Technology Cost | C102: AEO.2025.HIGHZTC.CNSM_NA_RESD_WND_NRW_NA_USA_QBTU.A | D102: quads | F102: 0.00126 | G102: 0.00214 | H102: 0.003001 | I102: 0.003401 | J102: 0.003849 | K102: 0.004333 | L102: 0.005261 | M102: 0.006483 | N102: 0.007725 | O102: 0.008146 | P102: 0.008342 | Q102: 0.008347 | R102: 0.008353 | S102: 0.008359 | T102: 0.008367 | U102: 0.008375 | V102: 0.008385 | W102: 0.008395 | X102: 0.008406 | Y102: 0.008417 | Z102: 0.008429 | AA102: 0.008441 | AB102: 0.008453 | AC102: 0.008466 | AD102: 0.00848 | AE102: 0.008494 | AF102: 0.008509 | AG102: 0.076
A103: Total | B103: Residential: Nonmarketed Renewables: Total: High Zero-Carbon Technology Cost | C103: AEO.2025.HIGHZTC.CNSM_NA_RESD_NA_NRW_NA_USA_QBTU.A | D103: quads | F103: 0.25071 | G103: 0.287551 | H103: 0.325135 | I103: 0.359367 | J103: 0.394318 | K103: 0.425814 | L103: 0.460232 | M103: 0.496958 | N103: 0.533473 | O103: 0.567727 | P103: 0.602256 | Q103: 0.628411 | R103: 0.655407 | S103: 0.682429 | T103: 0.710772 | U103: 0.73927 | V103: 0.767411 | W103: 0.796545 | X103: 0.826706 | Y103: 0.857196 | Z103: 0.888113 | AA103: 0.920087 | AB103: 0.952824 | AC103: 0.986141 | AD103: 1.020414 | AE103: 1.055277 | AF103: 1.090701 | AG103: 0.058
A104: Heating Degree Days
A105: New England | B105: Residential: Heating Degree Days: New England: High Zero-Carbon Technology Cost | C105: AEO.2025.HIGHZTC.KEI_HDD_RESD_NA_NA_NA_NENGL_HDD.A | D105: HDD | F105: 5643 | G105: 5924 | H105: 5901 | I105: 5879 | J105: 5856 | K105: 5833 | L105: 5810 | M105: 5787 | N105: 5764 | O105: 5741 | P105: 5718 | Q105: 5695 | R105: 5672 | S105: 5649 | T105: 5626 | U105: 5603 | V105: 5579 | W105: 5556 | X105: 5533 | Y105: 5510 | Z105: 5487 | AA105: 5464 | AB105: 5440 | AC105: 5417 | AD105: 5394 | AE105: 5371 | AF105: 5348 | AG105: -0.002
A106: Middle Atlantic | B106: Residential: Heating Degree Days: Middle Atlantic: High Zero-Carbon Technology Cost | C106: AEO.2025.HIGHZTC.KEI_HDD_RESD_NA_NA_NA_MATL_HDD.A | D106: HDD | F106: 4981 | G106: 5319 | H106: 5298 | I106: 5277 | J106: 5256 | K106: 5235 | L106: 5214 | M106: 5193 | N106: 5172 | O106: 5151 | P106: 5130 | Q106: 5109 | R106: 5088 | S106: 5068 | T106: 5047 | U106: 5026 | V106: 5005 | W106: 4984 | X106: 4963 | Y106: 4943 | Z106: 4922 | AA106: 4901 | AB106: 4880 | AC106: 4859 | AD106: 4838 | AE106: 4818 | AF106: 4797 | AG106: -0.001
A107: East North Central | B107: Residential: Heating Degree Days: East North Central: High Zero-Carbon Technology Cost | C107: AEO.2025.HIGHZTC.KEI_HDD_RESD_NA_NA_NA_ENC_HDD.A | D107: HDD | F107: 5306 | G107: 5952 | H107: 5937 | I107: 5923 | J107: 5908 | K107: 5894 | L107: 5879 | M107: 5864 | N107: 5850 | O107: 5835 | P107: 5820 | Q107: 5806 | R107: 5791 | S107: 5776 | T107: 5762 | U107: 5747 | V107: 5732 | W107: 5717 | X107: 5703 | Y107: 5688 | Z107: 5673 | AA107: 5658 | AB107: 5644 | AC107: 5629 | AD107: 5614 | AE107: 5599 | AF107: 5585 | AG107: 0.002
A108: West North Central | B108: Residential: Heating Degree Days: West North Central: High Zero-Carbon Technology Cost | C108: AEO.2025.HIGHZTC.KEI_HDD_RESD_NA_NA_NA_WNC_HDD.A | D108: HDD | F108: 5716 | G108: 6383 | H108: 6376 | I108: 6369 | J108: 6362 | K108: 6355 | L108: 6348 | M108: 6341 | N108: 6334 | O108: 6327 | P108: 6319 | Q108: 6312 | R108: 6304 | S108: 6297 | T108: 6289 | U108: 6282 | V108: 6274 | W108: 6267 | X108: 6259 | Y108: 6252 | Z108: 6244 | AA108: 6236 | AB108: 6229 | AC108: 6221 | AD108: 6213 | AE108: 6206 | AF108: 6198 | AG108: 0.003
A109: South Atlantic | B109: Residential: Heating Degree Days: South Atlantic: High Zero-Carbon Technology Cost | C109: AEO.2025.HIGHZTC.KEI_HDD_RESD_NA_NA_NA_SATL_HDD.A | D109: HDD | F109: 2271 | G109: 2344 | H109: 2329 | I109: 2313 | J109: 2298 | K109: 2283 | L109: 2267 | M109: 2251 | N109: 2235 | O109: 2220 | P109: 2204 | Q109: 2188 | R109: 2173 | S109: 2157 | T109: 2141 | U109: 2125 | V109: 2110 | W109: 2094 | X109: 2079 | Y109: 2063 | Z109: 2047 | AA109: 2032 | AB109: 2016 | AC109: 2001 | AD109: 1985 | AE109: 1970 | AF109: 1955 | AG109: -0.006
A110: East South Central | B110: Residential: Heating Degree Days: East South Central: High Zero-Carbon Technology Cost | C110: AEO.2025.HIGHZTC.KEI_HDD_RESD_NA_NA_NA_ESC_HDD.A | D110: HDD | F110: 3024 | G110: 3161 | H110: 3148 | I110: 3136 | J110: 3123 | K110: 3111 | L110: 3098 | M110: 3086 | N110: 3073 | O110: 3060 | P110: 3048 | Q110: 3035 | R110: 3022 | S110: 3009 | T110: 2996 | U110: 2984 | V110: 2971 | W110: 2958 | X110: 2945 | Y110: 2933 | Z110: 2920 | AA110: 2907 | AB110: 2894 | AC110: 2881 | AD110: 2869 | AE110: 2856 | AF110: 2843 | AG110: -0.002
A111: West South Central | B111: Residential: Heating Degree Days: West South Central: High Zero-Carbon Technology Cost | C111: AEO.2025.HIGHZTC.KEI_HDD_RESD_NA_NA_NA_WSC_HDD.A | D111: HDD | F111: 1844 | G111: 1949 | H111: 1942 | I111: 1935 | J111: 1928 | K111: 1921 | L111: 1914 | M111: 1907 | N111: 1900 | O111: 1893 | P111: 1886 | Q111: 1879 | R111: 1872 | S111: 1865 | T111: 1858 | U111: 1852 | V111: 1845 | W111: 1838 | X111: 1831 | Y111: 1825 | Z111: 1818 | AA111: 1811 | AB111: 1805 | AC111: 1798 | AD111: 1791 | AE111: 1785 | AF111: 1778 | AG111: -0.001
A112: Mountain | B112: Residential: Heating Degree Days: Mountain: High Zero-Carbon Technology Cost | C112: AEO.2025.HIGHZTC.KEI_HDD_RESD_NA_NA_NA_MTN_HDD.A | D112: HDD | F112: 4753 | G112: 4877 | H112: 4871 | I112: 4865 | J112: 4858 | K112: 4851 | L112: 4844 | M112: 4837 | N112: 4830 | O112: 4823 | P112: 4816 | Q112: 4809 | R112: 4802 | S112: 4796 | T112: 4789 | U112: 4782 | V112: 4776 | W112: 4769 | X112: 4763 | Y112: 4756 | Z112: 4750 | AA112: 4744 | AB112: 4737 | AC112: 4731 | AD112: 4725 | AE112: 4718 | AF112: 4712 | AG112: 0
A113: Pacific | B113: Residential: Heating Degree Days: Pacific: High Zero-Carbon Technology Cost | C113: AEO.2025.HIGHZTC.KEI_HDD_RESD_NA_NA_NA_PCF_HDD.A | D113: HDD | F113: 3352 | G113: 3290 | H113: 3283 | I113: 3277 | J113: 3270 | K113: 3263 | L113: 3256 | M113: 3249 | N113: 3242 | O113: 3234 | P113: 3227 | Q113: 3219 | R113: 3212 | S113: 3204 | T113: 3197 | U113: 3189 | V113: 3181 | W113: 3174 | X113: 3166 | Y113: 3158 | Z113: 3150 | AA113: 3143 | AB113: 3135 | AC113: 3127 | AD113: 3119 | AE113: 3112 | AF113: 3104 | AG113: -0.003
A114: United States | B114: Residential: Heating Degree Days: United States: High Zero-Carbon Technology Cost | C114: AEO.2025.HIGHZTC.KEI_HDD_RESD_NA_NA_NA_USA_HDD.A | D114: HDD | F114: 3753.9636 | G114: 3970.7402 | H114: 3953.677 | I114: 3936.8809 | J114: 3919.8694 | K114: 3903.1021 | L114: 3885.9797 | M114: 3868.9492 | N114: 3852.032 | O114: 3835.0635 | P114: 3818.0864 | Q114: 3801.1135 | R114: 3784.3435 | S114: 3767.4775 | T114: 3750.6677 | U114: 3733.8269 | V114: 3716.9988 | W114: 3700.1577 | X114: 3683.5239 | Y114: 3666.8364 | Z114: 3649.8879 | AA114: 3633.3447 | AB114: 3616.6768 | AC114: 3600.1343 | AD114: 3583.5701 | AE114: 3567.7378 | AF114: 3551.7458 | AG114: -0.002
A115: Cooling Degree Days
A116: New England | B116: Residential: Cooling Degree Days: New England: High Zero-Carbon Technology Cost | C116: AEO.2025.HIGHZTC.KEI_CDD_RESD_NA_NA_NA_NENGL_CDD.A | D116: CDD | F116: 620 | G116: 609 | H116: 615 | I116: 621 | J116: 627 | K116: 633 | L116: 640 | M116: 646 | N116: 652 | O116: 659 | P116: 665 | Q116: 671 | R116: 678 | S116: 684 | T116: 690 | U116: 697 | V116: 703 | W116: 710 | X116: 716 | Y116: 722 | Z116: 729 | AA116: 735 | AB116: 741 | AC116: 748 | AD116: 754 | AE116: 760 | AF116: 767 | AG116: 0.008
...

Sheet NREL EF Table 22
A1: Figure 22. Installed unit costs (left) and performance projections (right) for commercial air-source heat pumps
A2: Figure Notes: | B2: Installed costs include both capital and installation costs.
A4: Year | B4: Technology | C4: EFS Case | D4: Installed Cost ($/kBtu/hr) | E4: Efficiency (COP)
A5: 2015 | B5: Air Source Heat Pump | C5: Moderate Advancement | D5: 96 | E5: 3.3
A6: 2015 | B6: Air Source Heat Pump | C6: Rapid Advancement | D6: 96 | E6: 3.3
A7: 2015 | B7: Air Source Heat Pump | C7: Slow Advancement | D7: 96 | E7: 3.3
A8: 2015 | B8: Cold Climate Air Source Heat Pump | C8: Moderate Advancement | D8: 96 | E8: 1.5
A9: 2015 | B9: Cold Climate Air Source Heat Pump | C9: Rapid Advancement | D9: 96 | E9: 1.5
A10: 2015 | B10: Cold Climate Air Source Heat Pump | C10: Slow Advancement | D10: 96 | E10: 1.5
A11: 2020 | B11: Air Source Heat Pump | C11: Moderate Advancement | D11: 85 | E11: 3.75
A12: 2020 | B12: Air Source Heat Pump | C12: Rapid Advancement | D12: 80 | E12: 4
A13: 2020 | B13: Air Source Heat Pump | C13: Slow Advancement | D13: 92.873543 | E13: 3.4
A14: 2020 | B14: Cold Climate Air Source Heat Pump | C14: Moderate Advancement | D14: 85 | E14: 2
A15: 2020 | B15: Cold Climate Air Source Heat Pump | C15: Rapid Advancement | D15: 80 | E15: 2.5
A16: 2020 | B16: Cold Climate Air Source Heat Pump | C16: Slow Advancement | D16: 92.873543 | E16: 1.75
... A34: 2050 | B34: Cold Climate Air Source Heat Pump | C34: Slow Advancement | D34: 76.140668 | E34: 2.75

Sheet NREL EF Table 23
A1: Figure 23. Installed costs (left) and performance projections (right) for commercial HPWHs
A2: Figure Notes: | B2: Installed costs include both capital and installation costs.
A4: Year | B4: Technology | C4: EFS Case | D4: Installed Cost ($/kBtu/hr) | E4: Efficiency (COP)
A5: 2015 | B5: Heat Pump Water Heater | C5: Moderate Advancement | D5: 310 | E5: 2.45
A6: 2015 | B6: Heat Pump Water Heater | C6: Rapid Advancement | D6: 310 | E6: 2.45
A7: 2015 | B7: Heat Pump Water Heater | C7: Slow Advancement | D7: 310 | E7: 2.45
A8: 2020 | B8: Heat Pump Water Heater | C8: Moderate Advancement | D8: 287.51781 | E8: 3
A9: 2020 | B9: Heat Pump Water Heater | C9: Rapid Advancement | D9: 281.0389 | E9: 3
A10: 2020 | B10: Heat Pump Water Heater | C10: Slow Advancement | D10: 302.85283 | E10: 3
A11: 2030 | B11: Heat Pump Water Heater | C11: Moderate Advancement | D11: 247.32663 | E11: 3.25
A12: 2030 | B12: Heat Pump Water Heater | C12: Rapid Advancement | D12: 219.56945 | E12: 3.6
A13: 2030 | B13: Heat Pump Water Heater | C13: Slow Advancement | D13: 289.04903 | E13: 3
A14: 2040 | B14: Heat Pump Water Heater | C14: Moderate Advancement | D14: 212.75364 | E14: 3.35
A15: 2040 | B15: Heat Pump Water Heater | C15: Rapid Advancement | D15: 180 | E15: 3.85
A16: 2040 | B16: Heat Pump Water Heater | C16: Slow Advancement | D16: 275.8744 | E16: 3
... A19: 2050 | B19: Heat Pump Water Heater | C19: Slow Advancement | D19: 263.5 | E19: 3

Sheet Calcs>

Sheet Calculations
A1: Residential Equipment
A2: Heating
A3: Heating Energy Consumption per Unit per Year by Fuel (btu/unit) | B3: 2020 | C3: 2021 | D3: 2022 | E3: 2023 | F3: 2024 | G3: 2025 | H3: 2026 | I3: 2027 | J3: 2028 | K3: 2029 | L3: 2030 | M3: 2031 | N3: 2032 | O3: 2033 | P3: 2034 | Q3: 2035 | R3: 2036 | S3: 2037 | T3: 2038 | U3: 2039 | V3: 2040 | W3: 2041 | X3: 2042 | Y3: 2043 | Z3: 2044 | AA3: 2045 | AB3: 2046 | AC3: 2047 | AD3: 2048 | AE3: 2049 | AF3: 2050
A4: natural gas | C4: 0 | D4: 0 | E4: 0 | F4: =Table_4._Residential_Sector_Key!F41/SUM(Table_21._Residential_Sector_Eq!F10:F11)*10^15/10^6 -> 41491997 | G4: =Table_4._Residential_Sector_Key!G41/SUM(Table_21._Residential_Sector_Eq!G10:G11)*10^15/10^6 -> 46089261 | H4: =Table_4._Residential_Sector_Key!H41/SUM(Table_21._Residential_Sector_Eq!H10:H11)*10^15/10^6 -> 45690896 | I4: =Table_4._Residential_Sector_Key!I41/SUM(Table_21._Residential_Sector_Eq!I10:I11)*10^15/10^6 -> 45159330 | J4: =Table_4._Residential_Sector_Key!J41/SUM(Table_21._Residential_Sector_Eq!J10:J11)*10^15/10^6 -> 44517814 | K4: =Table_4._Residential_Sector_Key!K41/SUM(Table_21._Residential_Sector_Eq!K10:K11)*10^15/10^6 -> 43699156 | L4: =Table_4._Residential_Sector_Key!L41/SUM(Table_21._Residential_Sector_Eq!L10:L11)*10^15/10^6 -> 42807846 | M4: =Table_4._Residential_Sector_Key!M41/SUM(Table_21._Residential_Sector_Eq!M10:M11)*10^15/10^6 -> 41807842 | ... AF4: =Table_4._Residential_Sector_Key!AF41/SUM(Table_21._Residential_Sector_Eq!AF10:AF11)*10^15/10^6 -> 29343870
A5: oil | C5: 0 | D5: 0 | E5: 0 | F5: =Table_4._Residential_Sector_Key!F49/Table_21._Residential_Sector_Eq!F12*10^15/10^6 -> 79653267 | G5: =Table_4._Residential_Sector_Key!G49/Table_21._Residential_Sector_Eq!G12*10^15/10^6 -> 86956347 | H5: =Table_4._Residential_Sector_Key!H49/Table_21._Residential_Sector_Eq!H12*10^15/10^6 -> 86724765 | I5: =Table_4._Residential_Sector_Key!I49/Table_21._Residential_Sector_Eq!I12*10^15/10^6 -> 86019852 | J5: =Table_4._Residential_Sector_Key!J49/Table_21._Residential_Sector_Eq!J12*10^15/10^6 -> 85052399 | K5: =Table_4._Residential_Sector_Key!K49/Table_21._Residential_Sector_Eq!K12*10^15/10^6 -> 84013930 | L5: =Table_4._Residential_Sector_Key!L49/Table_21._Residential_Sector_Eq!L12*10^15/10^6 -> 82988611 | M5: =Table_4._Residential_Sector_Key!M49/Table_21._Residential_Sector_Eq!M12*10^15/10^6 -> 82160846 | ... AF5: =Table_4._Residential_Sector_Key!AF49/Table_21._Residential_Sector_Eq!AF12*10^15/10^6 -> 71026713
A6: biomass | C6: 0 | D6: 0 | E6: 0 | F6: =Table_4._Residential_Sector_Key!F59/Table_21._Residential_Sector_Eq!F15*10^15/10^6 -> 1.6102722e+08 | G6: =Table_4._Residential_Sector_Key!G59/Table_21._Residential_Sector_Eq!G15*10^15/10^6 -> 1.6500387e+08 | H6: =Table_4._Residential_Sector_Key!H59/Table_21._Residential_Sector_Eq!H15*10^15/10^6 -> 1.5994619e+08 | I6: =Table_4._Residential_Sector_Key!I59/Table_21._Residential_Sector_Eq!I15*10^15/10^6 -> 1.5807268e+08 | J6: =Table_4._Residential_Sector_Key!J59/Table_21._Residential_Sector_Eq!J15*10^15/10^6 -> 1.5790717e+08 | K6: =Table_4._Residential_Sector_Key!K59/Table_21._Residential_Sector_Eq!K15*10^15/10^6 -> 1.5836027e+08 | L6: =Table_4._Residential_Sector_Key!L59/Table_21._Residential_Sector_Eq!L15*10^15/10^6 -> 1.5881339e+08 | M6: =Table_4._Residential_Sector_Key!M59/Table_21._Residential_Sector_Eq!M15*10^15/10^6 -> 1.5807461e+08 | ... AF6: =Table_4._Residential_Sector_Key!AF59/Table_21._Residential_Sector_Eq!AF15*10^15/10^6 -> 1.32369e+08
A8: Incremental Equipment Cost | B8: 2017 | C8: 2020 | D8: 2030 | E8: 2040 | F8: 2050
A9: natural gas (2017 USD) | B9: ='EIA Costs'!E48-'EIA Costs'!E10 -> 3050 | C9: ='EIA Costs'!H48-'EIA Costs'!H10 -> 2860 | D9: ='EIA Costs'!J48-'EIA Costs'!J10 -> 2910 | E9: ='EIA Costs'!L48-'EIA Costs'!L10 -> 2910 | F9: ='EIA Costs'!N48-'EIA Costs'!N10 -> 2910
A10: oil (2017 USD) | B10: ='EIA Costs'!E48-AVERAGE('EIA Costs'!E23:E24) -> 975 | C10: ='EIA Costs'!H48-AVERAGE('EIA Costs'!H23:H24) -> 975 | D10: ='EIA Costs'!J48-AVERAGE('EIA Costs'!J23:J24) -> 925 | E10: ='EIA Costs'!L48-AVERAGE('EIA Costs'!L23:L24) -> 925 | F10: ='EIA Costs'!N48-AVERAGE('EIA Costs'!N23:N24) -> 925
A11: biomass (2017 USD) | B11: ='EIA Costs'!E48-'EIA Costs'!D36 -> 400 | C11: ='EIA Costs'!H48-'EIA Costs'!F36 -> 400 | D11: ='EIA Costs'!J48-'EIA Costs'!H36 -> 350 | E11: ='EIA Costs'!L48-'EIA Costs'!J36 -> 250 | F11: ='EIA Costs'!N48-'EIA Costs'!L36 -> 150
A13: Annualized Incremental Equipment Cost | B13: 2020 | C13: 2021 | D13: 2022 | E13: 2023 | F13: 2024 | G13: 2025 | H13: 2026 | I13: 2027 | J13: 2028 | K13: 2029 | L13: 2030 | M13: 2031 | N13: 2032 | O13: 2033 | P13: 2034 | Q13: 2035 | R13: 2036 | S13: 2037 | T13: 2038 | U13: 2039 | V13: 2040 | W13: 2041 | X13: 2042 | Y13: 2043 | Z13: 2044 | AA13: 2045 | AB13: 2046 | AC13: 2047 | AD13: 2048 | AE13: 2049 | AF13: 2050
A14: natural gas (2012 USD) | B14: =(TREND($B$9:$C$9,$B$8:$C$8,B$13))*(About!$A$53) -> 2678.8464 | C14: =(TREND($C$9:$D$9,$C$8:$D$8,C$13))*(About!$A$53) -> 2683.5297 | D14: =(TREND($C$9:$D$9,$C$8:$D$8,D$13))*(About!$A$53) -> 2688.213 | E14: =(TREND($C$9:$D$9,$C$8:$D$8,E$13))*(About!$A$53) -> 2692.8963 | F14: =(TREND($C$9:$D$9,$C$8:$D$8,F$13))*(About!$A$53) -> 2697.5796 | G14: =(TREND($C$9:$D$9,$C$8:$D$8,G$13))*(About!$A$53) -> 2702.2629 | H14: =(TREND($C$9:$D$9,$C$8:$D$8,H$13))*(About!$A$53) -> 2706.9462 | I14: =(TREND($C$9:$D$9,$C$8:$D$8,I$13))*(About!$A$53) -> 2711.6295 | J14: =(TREND($C$9:$D$9,$C$8:$D$8,J$13))*(About!$A$53) -> 2716.3128 | ... L14: =(TREND($C$9:$D$9,$C$8:$D$8,L$13))*(About!$A$53) -> 2725.6794 | M14: =(TREND($D$9:$F$9,$D$8:$F$8,M$13))*(About!$A$53) -> 2725.6794 | N14: =(TREND($D$9:$F$9,$D$8:$F$8,N$13))*(About!$A$53) -> 2725.6794 | O14: =(TREND($D$9:$F$9,$D$8:$F$8,O$13))*(About!$A$53) -> 2725.6794 | P14: =(TREND($D$9:$F$9,$D$8:$F$8,P$13))*(About!$A$53) -> 2725.6794 | Q14: =(TREND($D$9:$F$9,$D$8:$F$8,Q$13))*(About!$A$53) -> 2725.6794 | R14: =(TREND($D$9:$F$9,$D$8:$F$8,R$13))*(About!$A$53) -> 2725.6794 | S14: =(TREND($D$9:$F$9,$D$8:$F$8,S$13))*(About!$A$53) -> 2725.6794 | T14: =(TREND($D$9:$F$9,$D$8:$F$8,T$13))*(About!$A$53) -> 2725.6794 | ... AF14: =(TREND($D$9:$F$9,$D$8:$F$8,AF$13))*(About!$A$53) -> 2725.6794
A15: oil (2012 USD) | B15: =(TREND($B$10:$C$10,$B$8:$C$8,B$13))*(About!$A$53) -> 913.24311 | C15: =(TREND($C$10:$D$10,$C$8:$D$8,C$13))*(About!$A$53) -> 908.55981 | D15: =(TREND($C$10:$D$10,$C$8:$D$8,D$13))*(About!$A$53) -> 903.87651 | E15: =(TREND($C$10:$D$10,$C$8:$D$8,E$13))*(About!$A$53) -> 899.19321 | F15: =(TREND($C$10:$D$10,$C$8:$D$8,F$13))*(About!$A$53) -> 894.50991 | G15: =(TREND($C$10:$D$10,$C$8:$D$8,G$13))*(About!$A$53) -> 889.82662 | H15: =(TREND($C$10:$D$10,$C$8:$D$8,H$13))*(About!$A$53) -> 885.14332 | I15: =(TREND($C$10:$D$10,$C$8:$D$8,I$13))*(About!$A$53) -> 880.46002 | J15: =(TREND($C$10:$D$10,$C$8:$D$8,J$13))*(About!$A$53) -> 875.77672 | ... L15: =(TREND($C$10:$D$10,$C$8:$D$8,L$13))*(About!$A$53) -> 866.41013 | M15: =(TREND($D$10:$F$10,$D$8:$F$8,M$13))*(About!$A$53) -> 866.41013 | N15: =(TREND($D$10:$F$10,$D$8:$F$8,N$13))*(About!$A$53) -> 866.41013 | O15: =(TREND($D$10:$F$10,$D$8:$F$8,O$13))*(About!$A$53) -> 866.41013 | P15: =(TREND($D$10:$F$10,$D$8:$F$8,P$13))*(About!$A$53) -> 866.41013 | Q15: =(TREND($D$10:$F$10,$D$8:$F$8,Q$13))*(About!$A$53) -> 866.41013 | R15: =(TREND($D$10:$F$10,$D$8:$F$8,R$13))*(About!$A$53) -> 866.41013 | S15: =(TREND($D$10:$F$10,$D$8:$F$8,S$13))*(About!$A$53) -> 866.41013 | T15: =(TREND($D$10:$F$10,$D$8:$F$8,T$13))*(About!$A$53) -> 866.41013 | ... AF15: =(TREND($D$10:$F$10,$D$8:$F$8,AF$13))*(About!$A$53) -> 866.41013
A16: biomass (2012 USD) | B16: =(TREND($B$11:$C$11,$B$8:$C$8,B$13))*(About!$A$53) -> 374.66384 | C16: =(TREND($C$11:$D$11,$C$8:$D$8,C$13))*(About!$A$53) -> 369.98054 | D16: =(TREND($C$11:$D$11,$C$8:$D$8,D$13))*(About!$A$53) -> 365.29724 | E16: =(TREND($C$11:$D$11,$C$8:$D$8,E$13))*(About!$A$53) -> 360.61394 | F16: =(TREND($C$11:$D$11,$C$8:$D$8,F$13))*(About!$A$53) -> 355.93065 | G16: =(TREND($C$11:$D$11,$C$8:$D$8,G$13))*(About!$A$53) -> 351.24735 | H16: =(TREND($C$11:$D$11,$C$8:$D$8,H$13))*(About!$A$53) -> 346.56405 | I16: =(TREND($C$11:$D$11,$C$8:$D$8,I$13))*(About!$A$53) -> 341.88075 | J16: =(TREND($C$11:$D$11,$C$8:$D$8,J$13))*(About!$A$53) -> 337.19745 | ... L16: =(TREND($C$11:$D$11,$C$8:$D$8,L$13))*(About!$A$53) -> 327.83086 | M16: =(TREND($D$11:$F$11,$D$8:$F$8,M$13))*(About!$A$53) -> 318.46426 | N16: =(TREND($D$11:$F$11,$D$8:$F$8,N$13))*(About!$A$53) -> 309.09767 | O16: =(TREND($D$11:$F$11,$D$8:$F$8,O$13))*(About!$A$53) -> 299.73107 | P16: =(TREND($D$11:$F$11,$D$8:$F$8,P$13))*(About!$A$53) -> 290.36447 | Q16: =(TREND($D$11:$F$11,$D$8:$F$8,Q$13))*(About!$A$53) -> 280.99788 | R16: =(TREND($D$11:$F$11,$D$8:$F$8,R$13))*(About!$A$53) -> 271.63128 | S16: =(TREND($D$11:$F$11,$D$8:$F$8,S$13))*(About!$A$53) -> 262.26469 | T16: =(TREND($D$11:$F$11,$D$8:$F$8,T$13))*(About!$A$53) -> 252.89809 | ... AF16: =(TREND($D$11:$F$11,$D$8:$F$8,AF$13))*(About!$A$53) -> 140.49894
A18: Annualized Incremental Cost per BTU Shifted | B18: 2020 | C18: 2021 | D18: 2022 | E18: 2023 | F18: 2024 | G18: 2025 | H18: 2026 | I18: 2027 | J18: 2028 | K18: 2029 | L18: 2030 | M18: 2031 | N18: 2032 | O18: 2033 | P18: 2034 | Q18: 2035 | R18: 2036 | S18: 2037 | T18: 2038 | U18: 2039 | V18: 2040 | W18: 2041 | X18: 2042 | Y18: 2043 | Z18: 2044 | AA18: 2045 | AB18: 2046 | AC18: 2047 | AD18: 2048 | AE18: 2049 | AF18: 2050
A19: natural gas | C19: =C14/C4 -> #DIV/0! | D19: =D14/D4 -> #DIV/0! | E19: =E14/E4 -> #DIV/0! | F19: =F14/F4 -> 6.5014456e-05 | G19: =G14/G4 -> 5.8631075e-05 | H19: =H14/H4 -> 5.9244761e-05 | I19: =I14/I4 -> 6.0045832e-05 | J19: =J14/J4 -> 6.1016312e-05 | ... AF19: =AF14/AF4 -> 9.2887523e-05
A20: oil | C20: =C15/C5 -> #DIV/0! | D20: =D15/D5 -> #DIV/0! | E20: =E15/E5 -> #DIV/0! | F20: =F15/F5 -> 1.1230047e-05 | G20: =G15/G5 -> 1.0233027e-05 | H20: =H15/H5 -> 1.020635e-05 | I20: =I15/I5 -> 1.0235544e-05 | J20: =J15/J5 -> 1.0296908e-05 | ... AF20: =AF15/AF5 -> 1.219837e-05
A21: biomass | C21: =C16/C6 -> #DIV/0! | D21: =D16/D6 -> #DIV/0! | E21: =E16/E6 -> #DIV/0! | F21: =F16/F6 -> 2.2103757e-06 | G21: =G16/G6 -> 2.1287219e-06 | H21: =H16/H6 -> 2.166754e-06 | I21: =I16/I6 -> 2.1628074e-06 | J21: =J16/J6 -> 2.1354158e-06 | ... AF21: =AF16/AF6 -> 1.0614188e-06
A23: Appliances (water heaters)
A24: Appliances Energy Consumption per Unit per Year by Fuel (btu/unit) | B24: 2020 | C24: 2021 | D24: 2022 | E24: 2023 | F24: 2024 | G24: 2025 | H24: 2026 | I24: 2027 | J24: 2028 | K24: 2029 | L24: 2030 | M24: 2031 | N24: 2032 | O24: 2033 | P24: 2034 | Q24: 2035 | R24: 2036 | S24: 2037 | T24: 2038 | U24: 2039 | V24: 2040 | W24: 2041 | X24: 2042 | Y24: 2043 | Z24: 2044 | AA24: 2045 | AB24: 2046 | AC24: 2047 | AD24: 2048 | AE24: 2049 | AF24: 2050
A25: natural gas | C25: 0 | D25: 0 | E25: 0 | F25: =Table_4._Residential_Sector_Key!F43/Table_21._Residential_Sector_Eq!F27*10^15/10^6 -> 15962001 | G25: =Table_4._Residential_Sector_Key!G43/Table_21._Residential_Sector_Eq!G27*10^15/10^6 -> 15880822 | H25: =Table_4._Residential_Sector_Key!H43/Table_21._Residential_Sector_Eq!H27*10^15/10^6 -> 15822259 | I25: =Table_4._Residential_Sector_Key!I43/Table_21._Residential_Sector_Eq!I27*10^15/10^6 -> 15739687 | J25: =Table_4._Residential_Sector_Key!J43/Table_21._Residential_Sector_Eq!J27*10^15/10^6 -> 15653645 | K25: =Table_4._Residential_Sector_Key!K43/Table_21._Residential_Sector_Eq!K27*10^15/10^6 -> 15501590 | L25: =Table_4._Residential_Sector_Key!L43/Table_21._Residential_Sector_Eq!L27*10^15/10^6 -> 15338298 | M25: =Table_4._Residential_Sector_Key!M43/Table_21._Residential_Sector_Eq!M27*10^15/10^6 -> 15163531 | ... AF25: =Table_4._Residential_Sector_Key!AF43/Table_21._Residential_Sector_Eq!AF27*10^15/10^6 -> 13085100
A26: oil | C26: 0 | D26: 0 | E26: 0 | F26: =Table_4._Residential_Sector_Key!F50/Table_21._Residential_Sector_Eq!F28*10^15/10^6 -> 17296373 | G26: =Table_4._Residential_Sector_Key!G50/Table_21._Residential_Sector_Eq!G28*10^15/10^6 -> 17115287 | H26: =Table_4._Residential_Sector_Key!H50/Table_21._Residential_Sector_Eq!H28*10^15/10^6 -> 16815668 | I26: =Table_4._Residential_Sector_Key!I50/Table_21._Residential_Sector_Eq!I28*10^15/10^6 -> 16424599 | J26: =Table_4._Residential_Sector_Key!J50/Table_21._Residential_Sector_Eq!J28*10^15/10^6 -> 16010844 | K26: =Table_4._Residential_Sector_Key!K50/Table_21._Residential_Sector_Eq!K28*10^15/10^6 -> 15583548 | L26: =Table_4._Residential_Sector_Key!L50/Table_21._Residential_Sector_Eq!L28*10^15/10^6 -> 15192253 | M26: =Table_4._Residential_Sector_Key!M50/Table_21._Residential_Sector_Eq!M28*10^15/10^6 -> 14882813 | ... AF26: =Table_4._Residential_Sector_Key!AF50/Table_21._Residential_Sector_Eq!AF28*10^15/10^6 -> 12661402
A28: Incremental Equipment Cost | B28: 2017 | C28: 2020 | D28: 2030 | E28: 2040 | F28: 2050
A29: natural gas (2017 USD) | B29: =AVERAGE('EIA Costs'!D88:D89)-AVERAGE('EIA Costs'!E61:E62) -> 150 | C29: =AVERAGE('EIA Costs'!G88:G89)-AVERAGE('EIA Costs'!H61:H62) -> 150 | D29: =AVERAGE('EIA Costs'!I88:I89)-AVERAGE('EIA Costs'!J61:J62) -> 150 | E29: =AVERAGE('EIA Costs'!K88:K89)-AVERAGE('EIA Costs'!L61:L62) -> 150 | F29: =AVERAGE('EIA Costs'!M88:M89)-AVERAGE('EIA Costs'!N61:N62) -> 150
A30: oil (2017 USD) | B30: =AVERAGE('EIA Costs'!D88:D89)-AVERAGE('EIA Costs'!E75:E76) -> -475 | C30: =AVERAGE('EIA Costs'!G88:G89)-AVERAGE('EIA Costs'!G75:G76) -> -475 | D30: =AVERAGE('EIA Costs'!I88:I89)-AVERAGE('EIA Costs'!I75:I76) -> -475 | E30: =AVERAGE('EIA Costs'!K88:K89)-AVERAGE('EIA Costs'!K75:K76) -> -475 | F30: =AVERAGE('EIA Costs'!M88:M89)-AVERAGE('EIA Costs'!M75:M76) -> -475
A32: Annualized Incremental Equipment Cost | B32: 2020 | C32: 2021 | D32: 2022 | E32: 2023 | F32: 2024 | G32: 2025 | H32: 2026 | I32: 2027 | J32: 2028 | K32: 2029 | L32: 2030 | M32: 2031 | N32: 2032 | O32: 2033 | P32: 2034 | Q32: 2035 | R32: 2036 | S32: 2037 | T32: 2038 | U32: 2039 | V32: 2040 | W32: 2041 | X32: 2042 | Y32: 2043 | Z32: 2044 | AA32: 2045 | AB32: 2046 | AC32: 2047 | AD32: 2048 | AE32: 2049 | AF32: 2050
A33: natural gas (2012 USD) | B33: =TREND($B$29:$C$29,$B$28:$C$28,B$32) -> 150 | C33: =TREND($C$29:$D$29,$C$28:$D$28,C$32) -> 150 | D33: =TREND($C$29:$D$29,$C$28:$D$28,D$32) -> 150 | E33: =TREND($C$29:$D$29,$C$28:$D$28,E$32) -> 150 | F33: =TREND($C$29:$D$29,$C$28:$D$28,F$32) -> 150 | G33: =TREND($C$29:$D$29,$C$28:$D$28,G$32) -> 150 | H33: =TREND($C$29:$D$29,$C$28:$D$28,H$32) -> 150 | I33: =TREND($C$29:$D$29,$C$28:$D$28,I$32) -> 150 | J33: =TREND($C$29:$D$29,$C$28:$D$28,J$32) -> 150 | ... L33: =TREND($C$29:$D$29,$C$28:$D$28,L$32) -> 150 | M33: =TREND($D$29:$F$29,$D$28:$F$28,M$32) -> 150 | N33: =TREND($D$29:$F$29,$D$28:$F$28,N$32) -> 150 | O33: =TREND($D$29:$F$29,$D$28:$F$28,O$32) -> 150 | P33: =TREND($D$29:$F$29,$D$28:$F$28,P$32) -> 150 | Q33: =TREND($D$29:$F$29,$D$28:$F$28,Q$32) -> 150 | R33: =TREND($D$29:$F$29,$D$28:$F$28,R$32) -> 150 | S33: =TREND($D$29:$F$29,$D$28:$F$28,S$32) -> 150 | T33: =TREND($D$29:$F$29,$D$28:$F$28,T$32) -> 150 | ... AF33: =TREND($D$29:$F$29,$D$28:$F$28,AF$32) -> 150
A34: oil (2012 USD) | B34: =TREND($B$30:$C$30,$B$28:$C$28,B$32) -> -475 | C34: =TREND($C$30:$D$30,$C$28:$D$28,C$32) -> -475 | D34: =TREND($C$30:$D$30,$C$28:$D$28,D$32) -> -475 | E34: =TREND($C$30:$D$30,$C$28:$D$28,E$32) -> -475 | F34: =TREND($C$30:$D$30,$C$28:$D$28,F$32) -> -475 | G34: =TREND($C$30:$D$30,$C$28:$D$28,G$32) -> -475 | H34: =TREND($C$30:$D$30,$C$28:$D$28,H$32) -> -475 | I34: =TREND($C$30:$D$30,$C$28:$D$28,I$32) -> -475 | J34: =TREND($C$30:$D$30,$C$28:$D$28,J$32) -> -475 | ... L34: =TREND($C$30:$D$30,$C$28:$D$28,L$32) -> -475 | M34: =TREND($D$30:$F$30,$D$28:$F$28,M$32) -> -475 | N34: =TREND($D$30:$F$30,$D$28:$F$28,N$32) -> -475 | O34: =TREND($D$30:$F$30,$D$28:$F$28,O$32) -> -475 | P34: =TREND($D$30:$F$30,$D$28:$F$28,P$32) -> -475 | Q34: =TREND($D$30:$F$30,$D$28:$F$28,Q$32) -> -475 | R34: =TREND($D$30:$F$30,$D$28:$F$28,R$32) -> -475 | S34: =TREND($D$30:$F$30,$D$28:$F$28,S$32) -> -475 | T34: =TREND($D$30:$F$30,$D$28:$F$28,T$32) -> -475 | ... AF34: =TREND($D$30:$F$30,$D$28:$F$28,AF$32) -> -475
A36: Annualized Incremental Cost per BTU Shifted | B36: 2020 | C36: 2021 | D36: 2022 | E36: 2023 | F36: 2024 | G36: 2025 | H36: 2026 | I36: 2027 | J36: 2028 | K36: 2029 | L36: 2030 | M36: 2031 | N36: 2032 | O36: 2033 | P36: 2034 | Q36: 2035 | R36: 2036 | S36: 2037 | T36: 2038 | U36: 2039 | V36: 2040 | W36: 2041 | X36: 2042 | Y36: 2043 | Z36: 2044 | AA36: 2045 | AB36: 2046 | AC36: 2047 | AD36: 2048 | AE36: 2049 | AF36: 2050
A37: natural gas | C37: =C33/C25 -> #DIV/0! | D37: =D33/D25 -> #DIV/0! | E37: =E33/E25 -> #DIV/0! | F37: =F33/F25 -> 9.3973178e-06 | G37: =G33/G25 -> 9.4453546e-06 | H37: =H33/H25 -> 9.480315e-06 | I37: =I33/I25 -> 9.5300499e-06 | J37: =J33/J25 -> 9.5824326e-06 | ... AF37: =AF33/AF25 -> 1.146342e-05
A38: oil | C38: =C34/C26 -> #DIV/0! | D38: =D34/D26 -> #DIV/0! | E38: =E34/E26 -> #DIV/0! | F38: =F34/F26 -> -2.7462406e-05 | G38: =G34/G26 -> -2.7752967e-05 | H38: =H34/H26 -> -2.8247466e-05 | I38: =I34/I26 -> -2.8920036e-05 | J38: =J34/J26 -> -2.9667393e-05 | ... AF38: =AF34/AF26 -> -3.7515594e-05
A40: Commercial Equipment
A41: Heating
A42: Utilization Assumption
A43: space heating | B43: 0.08
A44: water heating | B44: 0.25
A47: Installed Cost ($/kBTU/hr) | B47: 2015 | C47: 2017 | D47: 2020 | E47: 2030 | F47: 2040 | G47: 2050
A48: natural gas (2017 USD) | C48: ='EIA Costs'!D100/'EIA Costs'!D96 -> 5.375 | D48: ='EIA Costs'!F100/'EIA Costs'!F96 -> 5.375 | E48: ='EIA Costs'!H100/'EIA Costs'!H96 -> 5.5 | F48: ='EIA Costs'!J100/'EIA Costs'!J96 -> 5.5 | G48: ='EIA Costs'!L100/'EIA Costs'!L96 -> 5.5
A49: oil (2017 USD) | C49: ='EIA Costs'!D111/'EIA Costs'!D107 -> 16.5 | D49: ='EIA Costs'!F111/'EIA Costs'!F107 -> 16.5 | E49: ='EIA Costs'!G111/'EIA Costs'!G107 -> 16.5 | F49: ='EIA Costs'!H111/'EIA Costs'!H107 -> 16.5 | G49: ='EIA Costs'!I111/'EIA Costs'!I107 -> 16.5
A50: ASHP (2016 USD) | B50: ='NREL EF Table 22'!D5 -> 96 | D50: ='NREL EF Table 22'!D11 -> 85 | E50: ='NREL EF Table 22'!D17 -> 73 | F50: ='NREL EF Table 22'!D23 -> 65 | G50: ='NREL EF Table 22'!D29 -> 60.296369
A52: Annualized Installed Cost ($/kBTU/hr) | B52: 2020 | C52: 2021 | D52: 2022 | E52: 2023 | F52: 2024 | G52: 2025 | H52: 2026 | I52: 2027 | J52: 2028 | K52: 2029 | L52: 2030 | M52: 2031 | N52: 2032 | O52: 2033 | P52: 2034 | Q52: 2035 | R52: 2036 | S52: 2037 | T52: 2038 | U52: 2039 | V52: 2040 | W52: 2041 | X52: 2042 | Y52: 2043 | Z52: 2044 | AA52: 2045 | AB52: 2046 | AC52: 2047 | AD52: 2048 | AE52: 2049 | AF52: 2050
A53: natural gas (2012 USD) | B53: =(TREND($C$48:$D$48,$C$47:$D$47,B$32))*(About!$A$53) -> 5.0345453 | C53: =(TREND($D$48:$E$48,$D$47:$E$47,C$32))*(About!$A$53) -> 5.0462536 | D53: =(TREND($D$48:$E$48,$D$47:$E$47,D$32))*(About!$A$53) -> 5.0579618 | E53: =(TREND($D$48:$E$48,$D$47:$E$47,E$32))*(About!$A$53) -> 5.0696701 | F53: =(TREND($D$48:$E$48,$D$47:$E$47,F$32))*(About!$A$53) -> 5.0813783 | G53: =(TREND($D$48:$E$48,$D$47:$E$47,G$32))*(About!$A$53) -> 5.0930865 | H53: =(TREND($D$48:$E$48,$D$47:$E$47,H$32))*(About!$A$53) -> 5.1047948 | I53: =(TREND($D$48:$E$48,$D$47:$E$47,I$32))*(About!$A$53) -> 5.116503 | J53: =(TREND($D$48:$E$48,$D$47:$E$47,J$32))*(About!$A$53) -> 5.1282113 | ... L53: =(TREND($D$48:$E$48,$D$47:$E$47,L$32))*(About!$A$53) -> 5.1516278 | M53: =(TREND($E$48:$G$48,$E$47:$G$47,M$32))*(About!$A$53) -> 5.1516278 | N53: =(TREND($E$48:$G$48,$E$47:$G$47,N$32))*(About!$A$53) -> 5.1516278 | O53: =(TREND($E$48:$G$48,$E$47:$G$47,O$32))*(About!$A$53) -> 5.1516278 | P53: =(TREND($E$48:$G$48,$E$47:$G$47,P$32))*(About!$A$53) -> 5.1516278 | Q53: =(TREND($E$48:$G$48,$E$47:$G$47,Q$32))*(About!$A$53) -> 5.1516278 | R53: =(TREND($E$48:$G$48,$E$47:$G$47,R$32))*(About!$A$53) -> 5.1516278 | S53: =(TREND($E$48:$G$48,$E$47:$G$47,S$32))*(About!$A$53) -> 5.1516278 | T53: =(TREND($E$48:$G$48,$E$47:$G$47,T$32))*(About!$A$53) -> 5.1516278 | ... AF53: =(TREND($E$48:$G$48,$E$47:$G$47,AF$32))*(About!$A$53) -> 5.1516278
A54: oil (2012 USD) | B54: =(TREND($C$49:$D$49,$C$47:$D$47,B$32))*(About!$A$53) -> 15.454883 | C54: =(TREND($D$49:$E$49,$D$47:$E$47,C$32))*(About!$A$53) -> 15.454883 | D54: =(TREND($D$49:$E$49,$D$47:$E$47,D$32))*(About!$A$53) -> 15.454883 | E54: =(TREND($D$49:$E$49,$D$47:$E$47,E$32))*(About!$A$53) -> 15.454883 | F54: =(TREND($D$49:$E$49,$D$47:$E$47,F$32))*(About!$A$53) -> 15.454883 | G54: =(TREND($D$49:$E$49,$D$47:$E$47,G$32))*(About!$A$53) -> 15.454883 | H54: =(TREND($D$49:$E$49,$D$47:$E$47,H$32))*(About!$A$53) -> 15.454883 | I54: =(TREND($D$49:$E$49,$D$47:$E$47,I$32))*(About!$A$53) -> 15.454883 | J54: =(TREND($D$49:$E$49,$D$47:$E$47,J$32))*(About!$A$53) -> 15.454883 | ... L54: =(TREND($D$49:$E$49,$D$47:$E$47,L$32))*(About!$A$53) -> 15.454883 | M54: =(TREND($E$49:$G$49,$E$47:$G$47,M$32))*(About!$A$53) -> 15.454883 | N54: =(TREND($E$49:$G$49,$E$47:$G$47,N$32))*(About!$A$53) -> 15.454883 | O54: =(TREND($E$49:$G$49,$E$47:$G$47,O$32))*(About!$A$53) -> 15.454883 | P54: =(TREND($E$49:$G$49,$E$47:$G$47,P$32))*(About!$A$53) -> 15.454883 | Q54: =(TREND($E$49:$G$49,$E$47:$G$47,Q$32))*(About!$A$53) -> 15.454883 | R54: =(TREND($E$49:$G$49,$E$47:$G$47,R$32))*(About!$A$53) -> 15.454883 | S54: =(TREND($E$49:$G$49,$E$47:$G$47,S$32))*(About!$A$53) -> 15.454883 | T54: =(TREND($E$49:$G$49,$E$47:$G$47,T$32))*(About!$A$53) -> 15.454883 | ... AF54: =(TREND($E$49:$G$49,$E$47:$G$47,AF$32))*(About!$A$53) -> 15.454883
A55: ASHP (2012 USD) | B55: =(TREND($D$50:$E$50,$D$47:$E$47,B$32))*(About!$A$55) -> 81.31217 | C55: =(TREND($D$50:$E$50,$D$47:$E$47,C$32))*(About!$A$55) -> 80.164234 | D55: =(TREND($D$50:$E$50,$D$47:$E$47,D$32))*(About!$A$55) -> 79.016297 | E55: =(TREND($D$50:$E$50,$D$47:$E$47,E$32))*(About!$A$55) -> 77.868361 | F55: =(TREND($D$50:$E$50,$D$47:$E$47,F$32))*(About!$A$55) -> 76.720424 | G55: =(TREND($D$50:$E$50,$D$47:$E$47,G$32))*(About!$A$55) -> 75.572487 | H55: =(TREND($D$50:$E$50,$D$47:$E$47,H$32))*(About!$A$55) -> 74.424551 | I55: =(TREND($D$50:$E$50,$D$47:$E$47,I$32))*(About!$A$55) -> 73.276614 | ... L55: =(TREND($D$50:$E$50,$D$47:$E$47,L$32))*(About!$A$55) -> 69.832805 | M55: =(TREND($E$50:$G$50,$E$47:$G$47,M$32))*(About!$A$55) -> 68.699623 | N55: =(TREND($E$50:$G$50,$E$47:$G$47,N$32))*(About!$A$55) -> 68.091999 | O55: =(TREND($E$50:$G$50,$E$47:$G$47,O$32))*(About!$A$55) -> 67.484376 | P55: =(TREND($E$50:$G$50,$E$47:$G$47,P$32))*(About!$A$55) -> 66.876753 | Q55: =(TREND($E$50:$G$50,$E$47:$G$47,Q$32))*(About!$A$55) -> 66.269129 | R55: =(TREND($E$50:$G$50,$E$47:$G$47,R$32))*(About!$A$55) -> 65.661506 | S55: =(TREND($E$50:$G$50,$E$47:$G$47,S$32))*(About!$A$55) -> 65.053882 | T55: =(TREND($E$50:$G$50,$E$47:$G$47,T$32))*(About!$A$55) -> 64.446259 | ... AF55: =(TREND($E$50:$G$50,$E$47:$G$47,AF$32))*(About!$A$55) -> 57.154778
A57: Annualized Incremental Capital Cost per BTU Shifted | B57: 2020 | C57: 2021 | D57: 2022 | E57: 2023 | F57: 2024 | G57: 2025 | H57: 2026 | I57: 2027 | J57: 2028 | K57: 2029 | L57: 2030 | M57: 2031 | N57: 2032 | O57: 2033 | P57: 2034 | Q57: 2035 | R57: 2036 | S57: 2037 | T57: 2038 | U57: 2039 | V57: 2040 | W57: 2041 | X57: 2042 | Y57: 2043 | Z57: 2044 | AA57: 2045 | AB57: 2046 | AC57: 2047 | AD57: 2048 | AE57: 2049 | AF57: 2050
A58: natural gas | B58: =(B55-B53)/(8760*10^3*$B$43) -> 0.00010884364 | C58: =(C55-C53)/(8760*10^3*$B$43) -> 0.0001071889 | D58: =(D55-D53)/(8760*10^3*$B$43) -> 0.00010553415 | E58: =(E55-E53)/(8760*10^3*$B$43) -> 0.00010387941 | F58: =(F55-F53)/(8760*10^3*$B$43) -> 0.00010222467 | G58: =(G55-G53)/(8760*10^3*$B$43) -> 0.00010056992 | H58: =(H55-H53)/(8760*10^3*$B$43) -> 9.8915177e-05 | I58: =(I55-I53)/(8760*10^3*$B$43) -> 9.7260433e-05 | ... AF58: =(AF55-AF53)/(8760*10^3*$B$43) -> 7.4205409e-05
A59: oil | B59: =(B55-B54)/(8760*10^3*$B$43) -> 9.3974439e-05 | C59: =(C55-C54)/(8760*10^3*$B$43) -> 9.2336402e-05 | D59: =(D55-D54)/(8760*10^3*$B$43) -> 9.0698364e-05 | E59: =(E55-E54)/(8760*10^3*$B$43) -> 8.9060327e-05 | F59: =(F55-F54)/(8760*10^3*$B$43) -> 8.742229e-05 | G59: =(G55-G54)/(8760*10^3*$B$43) -> 8.5784252e-05 | H59: =(H55-H54)/(8760*10^3*$B$43) -> 8.4146215e-05 | I59: =(I55-I54)/(8760*10^3*$B$43) -> 8.2508178e-05 | ... AF59: =(AF55-AF54)/(8760*10^3*$B$43) -> 5.9503275e-05
A61: Appliances (water heaters)
A62: Utilization Assumption
A63: space heating | B63: 0.08
A64: water heating | B64: 0.25
A67: Installed Cost ($/kBTU/hr) | B67: 2015 | C67: 2017 | D67: 2020 | E67: 2030 | F67: 2040 | G67: 2050
A68: natural gas (2017 USD) | C68: =AVERAGE('EIA Costs'!D134:D135)/'EIA Costs'!D131 -> 19.472362 | D68: =AVERAGE('EIA Costs'!G134:G135)/'EIA Costs'!G131 -> 19.472362 | E68: =AVERAGE('EIA Costs'!I134:I135)/'EIA Costs'!I131 -> 19.472362 | F68: =AVERAGE('EIA Costs'!K134:K135)/'EIA Costs'!K131 -> 19.472362 | G68: =AVERAGE('EIA Costs'!M134:M135)/'EIA Costs'!M131 -> 19.472362
A69: oil (2017 USD) | C69: ='EIA Costs'!D148/'EIA Costs'!D144 -> 17.333333 | D69: ='EIA Costs'!F148/'EIA Costs'!F144 -> 17.333333 | E69: ='EIA Costs'!H148/'EIA Costs'!H144 -> 17.333333 | F69: ='EIA Costs'!J148/'EIA Costs'!J144 -> 17.333333 | G69: ='EIA Costs'!L148/'EIA Costs'!L144 -> 17.333333
A70: ASHP (2016 USD) | B70: ='NREL EF Table 23'!D5 -> 310 | D70: ='NREL EF Table 23'!D8 -> 287.51781 | E70: ='NREL EF Table 23'!D11 -> 247.32663 | F70: ='NREL EF Table 23'!D14 -> 212.75364 | G70: ='NREL EF Table 23'!D17 -> 184.45
A72: Annualized Installed Cost ($/kBTU/hr) | B72: 2020 | C72: 2021 | D72: 2022 | E72: 2023 | F72: 2024 | G72: 2025 | H72: 2026 | I72: 2027 | J72: 2028 | K72: 2029 | L72: 2030 | M72: 2031 | N72: 2032 | O72: 2033 | P72: 2034 | Q72: 2035 | R72: 2036 | S72: 2037 | T72: 2038 | U72: 2039 | V72: 2040 | W72: 2041 | X72: 2042 | Y72: 2043 | Z72: 2044 | AA72: 2045 | AB72: 2046 | AC72: 2047 | AD72: 2048 | AE72: 2049 | AF72: 2050
A73: natural gas (2012 USD) | B73: =(TREND($C$68:$D$68,$C$67:$D$67,B$32))*(About!$A$53) -> 18.238975 | C73: =(TREND($D$68:$E$68,$D$67:$E$67,C$32))*(About!$A$53) -> 18.238975 | D73: =(TREND($D$68:$E$68,$D$67:$E$67,D$32))*(About!$A$53) -> 18.238975 | E73: =(TREND($D$68:$E$68,$D$67:$E$67,E$32))*(About!$A$53) -> 18.238975 | F73: =(TREND($D$68:$E$68,$D$67:$E$67,F$32))*(About!$A$53) -> 18.238975 | G73: =(TREND($D$68:$E$68,$D$67:$E$67,G$32))*(About!$A$53) -> 18.238975 | H73: =(TREND($D$68:$E$68,$D$67:$E$67,H$32))*(About!$A$53) -> 18.238975 | I73: =(TREND($D$68:$E$68,$D$67:$E$67,I$32))*(About!$A$53) -> 18.238975 | J73: =(TREND($D$68:$E$68,$D$67:$E$67,J$32))*(About!$A$53) -> 18.238975 | ... L73: =(TREND($D$68:$E$68,$D$67:$E$67,L$32))*(About!$A$53) -> 18.238975 | M73: =(TREND($E$68:$G$68,$E$67:$G$67,M$32))*(About!$A$53) -> 18.238975 | N73: =(TREND($E$68:$G$68,$E$67:$G$67,N$32))*(About!$A$53) -> 18.238975 | O73: =(TREND($E$68:$G$68,$E$67:$G$67,O$32))*(About!$A$53) -> 18.238975 | P73: =(TREND($E$68:$G$68,$E$67:$G$67,P$32))*(About!$A$53) -> 18.238975 | Q73: =(TREND($E$68:$G$68,$E$67:$G$67,Q$32))*(About!$A$53) -> 18.238975 | R73: =(TREND($E$68:$G$68,$E$67:$G$67,R$32))*(About!$A$53) -> 18.238975 | S73: =(TREND($E$68:$G$68,$E$67:$G$67,S$32))*(About!$A$53) -> 18.238975 | T73: =(TREND($E$68:$G$68,$E$67:$G$67,T$32))*(About!$A$53) -> 18.238975 | ... AF73: =(TREND($E$68:$G$68,$E$67:$G$67,AF$32))*(About!$A$53) -> 18.238975
A74: oil (2012 USD) | B74: =(TREND($C$69:$D$69,$C$67:$D$67,B$32))*(About!$A$53) -> 16.235433 | C74: =(TREND($D$69:$E$69,$D$67:$E$67,C$32))*(About!$A$53) -> 16.235433 | D74: =(TREND($D$69:$E$69,$D$67:$E$67,D$32))*(About!$A$53) -> 16.235433 | E74: =(TREND($D$69:$E$69,$D$67:$E$67,E$32))*(About!$A$53) -> 16.235433 | F74: =(TREND($D$69:$E$69,$D$67:$E$67,F$32))*(About!$A$53) -> 16.235433 | G74: =(TREND($D$69:$E$69,$D$67:$E$67,G$32))*(About!$A$53) -> 16.235433 | H74: =(TREND($D$69:$E$69,$D$67:$E$67,H$32))*(About!$A$53) -> 16.235433 | I74: =(TREND($D$69:$E$69,$D$67:$E$67,I$32))*(About!$A$53) -> 16.235433 | J74: =(TREND($D$69:$E$69,$D$67:$E$67,J$32))*(About!$A$53) -> 16.235433 | ... L74: =(TREND($D$69:$E$69,$D$67:$E$67,L$32))*(About!$A$53) -> 16.235433 | M74: =(TREND($E$69:$G$69,$E$67:$G$67,M$32))*(About!$A$53) -> 16.235433 | N74: =(TREND($E$69:$G$69,$E$67:$G$67,N$32))*(About!$A$53) -> 16.235433 | O74: =(TREND($E$69:$G$69,$E$67:$G$67,O$32))*(About!$A$53) -> 16.235433 | P74: =(TREND($E$69:$G$69,$E$67:$G$67,P$32))*(About!$A$53) -> 16.235433 | Q74: =(TREND($E$69:$G$69,$E$67:$G$67,Q$32))*(About!$A$53) -> 16.235433 | R74: =(TREND($E$69:$G$69,$E$67:$G$67,R$32))*(About!$A$53) -> 16.235433 | S74: =(TREND($E$69:$G$69,$E$67:$G$67,S$32))*(About!$A$53) -> 16.235433 | T74: =(TREND($E$69:$G$69,$E$67:$G$67,T$32))*(About!$A$53) -> 16.235433 | ... AF74: =(TREND($E$69:$G$69,$E$67:$G$67,AF$32))*(About!$A$53) -> 16.235433
A75: ASHP (2012 USD) | B75: =(TREND($D$70:$E$70,$D$67:$E$67,B$32))*(About!$A$55) -> 275.0435 | C75: =(TREND($D$70:$E$70,$D$67:$E$67,C$32))*(About!$A$55) -> 271.19875 | D75: =(TREND($D$70:$E$70,$D$67:$E$67,D$32))*(About!$A$55) -> 267.35401 | E75: =(TREND($D$70:$E$70,$D$67:$E$67,E$32))*(About!$A$55) -> 263.50926 | F75: =(TREND($D$70:$E$70,$D$67:$E$67,F$32))*(About!$A$55) -> 259.66452 | G75: =(TREND($D$70:$E$70,$D$67:$E$67,G$32))*(About!$A$55) -> 255.81978 | H75: =(TREND($D$70:$E$70,$D$67:$E$67,H$32))*(About!$A$55) -> 251.97503 | I75: =(TREND($D$70:$E$70,$D$67:$E$67,I$32))*(About!$A$55) -> 248.13029 | ... L75: =(TREND($D$70:$E$70,$D$67:$E$67,L$32))*(About!$A$55) -> 236.59606 | M75: =(TREND($E$70:$G$70,$E$67:$G$67,M$32))*(About!$A$55) -> 232.58907 | N75: =(TREND($E$70:$G$70,$E$67:$G$67,N$32))*(About!$A$55) -> 229.58163 | O75: =(TREND($E$70:$G$70,$E$67:$G$67,O$32))*(About!$A$55) -> 226.5742 | P75: =(TREND($E$70:$G$70,$E$67:$G$67,P$32))*(About!$A$55) -> 223.56677 | Q75: =(TREND($E$70:$G$70,$E$67:$G$67,Q$32))*(About!$A$55) -> 220.55934 | R75: =(TREND($E$70:$G$70,$E$67:$G$67,R$32))*(About!$A$55) -> 217.5519 | S75: =(TREND($E$70:$G$70,$E$67:$G$67,S$32))*(About!$A$55) -> 214.54447 | T75: =(TREND($E$70:$G$70,$E$67:$G$67,T$32))*(About!$A$55) -> 211.53704 | ... AF75: =(TREND($E$70:$G$70,$E$67:$G$67,AF$32))*(About!$A$55) -> 175.44785
A77: Annualized Incremental Capital Cost per BTU Shifted | B77: 2020 | C77: 2021 | D77: 2022 | E77: 2023 | F77: 2024 | G77: 2025 | H77: 2026 | I77: 2027 | J77: 2028 | K77: 2029 | L77: 2030 | M77: 2031 | N77: 2032 | O77: 2033 | P77: 2034 | Q77: 2035 | R77: 2036 | S77: 2037 | T77: 2038 | U77: 2039 | V77: 2040 | W77: 2041 | X77: 2042 | Y77: 2043 | Z77: 2044 | AA77: 2045 | AB77: 2046 | AC77: 2047 | AD77: 2048 | AE77: 2049 | AF77: 2050
A78: natural gas | B78: =(B75-B73)/(8760*10^3*$B$64) -> 0.00011726234 | C78: =(C75-C73)/(8760*10^3*$B$64) -> 0.00011550675 | D78: =(D75-D73)/(8760*10^3*$B$64) -> 0.00011375116 | E78: =(E75-E73)/(8760*10^3*$B$64) -> 0.00011199557 | F78: =(F75-F73)/(8760*10^3*$B$64) -> 0.00011023998 | G78: =(G75-G73)/(8760*10^3*$B$64) -> 0.00010848438 | H78: =(H75-H73)/(8760*10^3*$B$64) -> 0.00010672879 | I78: =(I75-I73)/(8760*10^3*$B$64) -> 0.0001049732 | ... AF78: =(AF75-AF73)/(8760*10^3*$B$64) -> 7.1784875e-05
A79: oil | B79: =(B75-B74)/(8760*10^3*$B$64) -> 0.0001181772 | C79: =(C75-C74)/(8760*10^3*$B$64) -> 0.00011642161 | D79: =(D75-D74)/(8760*10^3*$B$64) -> 0.00011466602 | E79: =(E75-E74)/(8760*10^3*$B$64) -> 0.00011291043 | F79: =(F75-F74)/(8760*10^3*$B$64) -> 0.00011115483 | G79: =(G75-G74)/(8760*10^3*$B$64) -> 0.00010939924 | H79: =(H75-H74)/(8760*10^3*$B$64) -> 0.00010764365 | I79: =(I75-I74)/(8760*10^3*$B$64) -> 0.00010588806 | ... AF79: =(AF75-AF74)/(8760*10^3*$B$64) -> 7.2699734e-05

Sheet ICpUEfEBE-urb-res-heating
A1: Unit: $/(BTU/yr) - a measure of capacity of the fuel-burning equipment that would have been purchased in the absence of an electrification policy | B1: 2024 | C1: 2025 | D1: 2026 | E1: 2027 | F1: 2028 | G1: 2029 | H1: 2030 | I1: 2031 | J1: 2032 | K1: 2033 | L1: 2034 | M1: 2035 | N1: 2036 | O1: 2037 | P1: 2038 | Q1: 2039 | R1: 2040 | S1: 2041 | T1: 2042 | U1: 2043 | V1: 2044 | W1: 2045 | X1: 2046 | Y1: 2047 | Z1: 2048 | AA1: 2049 | AB1: 2050
A2: electricity | B2: 0 | C2: 0 | D2: 0 | E2: 0 | F2: 0 | G2: 0 | H2: 0 | I2: 0 | J2: 0 | K2: 0 | L2: 0 | M2: 0 | N2: 0 | O2: 0 | P2: 0 | Q2: 0 | R2: 0 | S2: 0 | T2: 0 | U2: 0 | V2: 0 | W2: 0 | X2: 0 | Y2: 0 | Z2: 0 | AA2: 0 | AB2: 0
A3: coal | B3: =B4 -> 6.5014456e-05 | C3: =C4 -> 5.8631075e-05 | D3: =D4 -> 5.9244761e-05 | E3: =E4 -> 6.0045832e-05 | F3: =F4 -> 6.1016312e-05 | G3: =G4 -> 6.2266561e-05 | H3: =H4 -> 6.3672427e-05 | I3: =I4 -> 6.519541e-05 | ... AB3: =AB4 -> 9.2887523e-05
A4: natural gas | B4: =Calculations!F19 -> 6.5014456e-05 | C4: =Calculations!G19 -> 5.8631075e-05 | D4: =Calculations!H19 -> 5.9244761e-05 | E4: =Calculations!I19 -> 6.0045832e-05 | F4: =Calculations!J19 -> 6.1016312e-05 | G4: =Calculations!K19 -> 6.2266561e-05 | H4: =Calculations!L19 -> 6.3672427e-05 | I4: =Calculations!M19 -> 6.519541e-05 | ... AB4: =Calculations!AF19 -> 9.2887523e-05
A5: petroleum diesel | B5: =Calculations!F20 -> 1.1230047e-05 | C5: =Calculations!G20 -> 1.0233027e-05 | D5: =Calculations!H20 -> 1.020635e-05 | E5: =Calculations!I20 -> 1.0235544e-05 | F5: =Calculations!J20 -> 1.0296908e-05 | G5: =Calculations!K20 -> 1.036844e-05 | H5: =Calculations!L20 -> 1.0440109e-05 | I5: =Calculations!M20 -> 1.0545292e-05 | ... AB5: =Calculations!AF20 -> 1.219837e-05
A6: heat | B6: =B4 -> 6.5014456e-05 | C6: =C4 -> 5.8631075e-05 | D6: =D4 -> 5.9244761e-05 | E6: =E4 -> 6.0045832e-05 | F6: =F4 -> 6.1016312e-05 | G6: =G4 -> 6.2266561e-05 | H6: =H4 -> 6.3672427e-05 | I6: =I4 -> 6.519541e-05 | ... AB6: =AB4 -> 9.2887523e-05
A7: biomass | B7: =Calculations!F21 -> 2.2103757e-06 | C7: =Calculations!G21 -> 2.1287219e-06 | D7: =Calculations!H21 -> 2.166754e-06 | E7: =Calculations!I21 -> 2.1628074e-06 | F7: =Calculations!J21 -> 2.1354158e-06 | G7: =Calculations!K21 -> 2.0997322e-06 | H7: =Calculations!L21 -> 2.0642521e-06 | I7: =Calculations!M21 -> 2.0146452e-06 | ... AB7: =Calculations!AF21 -> 1.0614188e-06
A8: kerosene | B8: =B5 -> 1.1230047e-05 | C8: =C5 -> 1.0233027e-05 | D8: =D5 -> 1.020635e-05 | E8: =E5 -> 1.0235544e-05 | F8: =F5 -> 1.0296908e-05 | G8: =G5 -> 1.036844e-05 | H8: =H5 -> 1.0440109e-05 | I8: =I5 -> 1.0545292e-05 | ... AB8: =AB5 -> 1.219837e-05
A9: heavy or residual fuel oil | B9: =B5 -> 1.1230047e-05 | C9: =C5 -> 1.0233027e-05 | D9: =D5 -> 1.020635e-05 | E9: =E5 -> 1.0235544e-05 | F9: =F5 -> 1.0296908e-05 | G9: =G5 -> 1.036844e-05 | H9: =H5 -> 1.0440109e-05 | I9: =I5 -> 1.0545292e-05 | ... AB9: =AB5 -> 1.219837e-05
A10: LPG propane or butane | B10: =B4 -> 6.5014456e-05 | C10: =C4 -> 5.8631075e-05 | D10: =D4 -> 5.9244761e-05 | E10: =E4 -> 6.0045832e-05 | F10: =F4 -> 6.1016312e-05 | G10: =G4 -> 6.2266561e-05 | H10: =H4 -> 6.3672427e-05 | I10: =I4 -> 6.519541e-05 | ... AB10: =AB4 -> 9.2887523e-05
A11: hydrogen | B11: =B4 -> 6.5014456e-05 | C11: =C4 -> 5.8631075e-05 | D11: =D4 -> 5.9244761e-05 | E11: =E4 -> 6.0045832e-05 | F11: =F4 -> 6.1016312e-05 | G11: =G4 -> 6.2266561e-05 | H11: =H4 -> 6.3672427e-05 | I11: =I4 -> 6.519541e-05 | ... AB11: =AB4 -> 9.2887523e-05

Sheet ICpUEfEBE-urb-res-appl
A1: Unit: $/(BTU/yr) - a measure of capacity of the fuel-burning equipment that would have been purchased in the absence of an electrification policy | B1: 2024 | C1: 2025 | D1: 2026 | E1: 2027 | F1: 2028 | G1: 2029 | H1: 2030 | I1: 2031 | J1: 2032 | K1: 2033 | L1: 2034 | M1: 2035 | N1: 2036 | O1: 2037 | P1: 2038 | Q1: 2039 | R1: 2040 | S1: 2041 | T1: 2042 | U1: 2043 | V1: 2044 | W1: 2045 | X1: 2046 | Y1: 2047 | Z1: 2048 | AA1: 2049 | AB1: 2050
A2: electricity | B2: 0 | C2: 0 | D2: 0 | E2: 0 | F2: 0 | G2: 0 | H2: 0 | I2: 0 | J2: 0 | K2: 0 | L2: 0 | M2: 0 | N2: 0 | O2: 0 | P2: 0 | Q2: 0 | R2: 0 | S2: 0 | T2: 0 | U2: 0 | V2: 0 | W2: 0 | X2: 0 | Y2: 0 | Z2: 0 | AA2: 0 | AB2: 0
A3: coal | B3: =B4 -> 9.3973178e-06 | C3: =C4 -> 9.4453546e-06 | D3: =D4 -> 9.480315e-06 | E3: =E4 -> 9.5300499e-06 | F3: =F4 -> 9.5824326e-06 | G3: =G4 -> 9.6764267e-06 | H3: =H4 -> 9.779442e-06 | I3: =I4 -> 9.892155e-06 | ... AB3: =AB4 -> 1.146342e-05
A4: natural gas | B4: =Calculations!F37 -> 9.3973178e-06 | C4: =Calculations!G37 -> 9.4453546e-06 | D4: =Calculations!H37 -> 9.480315e-06 | E4: =Calculations!I37 -> 9.5300499e-06 | F4: =Calculations!J37 -> 9.5824326e-06 | G4: =Calculations!K37 -> 9.6764267e-06 | H4: =Calculations!L37 -> 9.779442e-06 | I4: =Calculations!M37 -> 9.892155e-06 | ... AB4: =Calculations!AF37 -> 1.146342e-05
A5: petroleum diesel | B5: =Calculations!F38 -> -2.7462406e-05 | C5: =Calculations!G38 -> -2.7752967e-05 | D5: =Calculations!H38 -> -2.8247466e-05 | E5: =Calculations!I38 -> -2.8920036e-05 | F5: =Calculations!J38 -> -2.9667393e-05 | G5: =Calculations!K38 -> -3.0480863e-05 | H5: =Calculations!L38 -> -3.1265934e-05 | I5: =Calculations!M38 -> -3.1916008e-05 | ... AB5: =Calculations!AF38 -> -3.7515594e-05
A6: heat | B6: =B4 -> 9.3973178e-06 | C6: =C4 -> 9.4453546e-06 | D6: =D4 -> 9.480315e-06 | E6: =E4 -> 9.5300499e-06 | F6: =F4 -> 9.5824326e-06 | G6: =G4 -> 9.6764267e-06 | H6: =H4 -> 9.779442e-06 | I6: =I4 -> 9.892155e-06 | ... AB6: =AB4 -> 1.146342e-05
A7: biomass | B7: =B5 -> -2.7462406e-05 | C7: =C5 -> -2.7752967e-05 | D7: =D5 -> -2.8247466e-05 | E7: =E5 -> -2.8920036e-05 | F7: =F5 -> -2.9667393e-05 | G7: =G5 -> -3.0480863e-05 | H7: =H5 -> -3.1265934e-05 | I7: =I5 -> -3.1916008e-05 | ... AB7: =AB5 -> -3.7515594e-05
A8: kerosene | B8: =B5 -> -2.7462406e-05 | C8: =C5 -> -2.7752967e-05 | D8: =D5 -> -2.8247466e-05 | E8: =E5 -> -2.8920036e-05 | F8: =F5 -> -2.9667393e-05 | G8: =G5 -> -3.0480863e-05 | H8: =H5 -> -3.1265934e-05 | I8: =I5 -> -3.1916008e-05 | ... AB8: =AB5 -> -3.7515594e-05
A9: heavy or residual fuel oil | B9: =B5 -> -2.7462406e-05 | C9: =C5 -> -2.7752967e-05 | D9: =D5 -> -2.8247466e-05 | E9: =E5 -> -2.8920036e-05 | F9: =F5 -> -2.9667393e-05 | G9: =G5 -> -3.0480863e-05 | H9: =H5 -> -3.1265934e-05 | I9: =I5 -> -3.1916008e-05 | ... AB9: =AB5 -> -3.7515594e-05
A10: LPG propane or butane | B10: =B4 -> 9.3973178e-06 | C10: =C4 -> 9.4453546e-06 | D10: =D4 -> 9.480315e-06 | E10: =E4 -> 9.5300499e-06 | F10: =F4 -> 9.5824326e-06 | G10: =G4 -> 9.6764267e-06 | H10: =H4 -> 9.779442e-06 | I10: =I4 -> 9.892155e-06 | ... AB10: =AB4 -> 1.146342e-05
A11: hydrogen | B11: =B4 -> 9.3973178e-06 | C11: =C4 -> 9.4453546e-06 | D11: =D4 -> 9.480315e-06 | E11: =E4 -> 9.5300499e-06 | F11: =F4 -> 9.5824326e-06 | G11: =G4 -> 9.6764267e-06 | H11: =H4 -> 9.779442e-06 | I11: =I4 -> 9.892155e-06 | ... AB11: =AB4 -> 1.146342e-05

Sheet ICpUEfEBE-urb-res-other
A1: Unit: $/(BTU/yr) - a measure of capacity of the fuel-burning equipment that would have been purchased in the absence of an electrification policy | B1: 2024 | C1: 2025 | D1: 2026 | E1: 2027 | F1: 2028 | G1: 2029 | H1: 2030 | I1: 2031 | J1: 2032 | K1: 2033 | L1: 2034 | M1: 2035 | N1: 2036 | O1: 2037 | P1: 2038 | Q1: 2039 | R1: 2040 | S1: 2041 | T1: 2042 | U1: 2043 | V1: 2044 | W1: 2045 | X1: 2046 | Y1: 2047 | Z1: 2048 | AA1: 2049 | AB1: 2050
A2: electricity | B2: 0 | C2: 0 | D2: 0 | E2: 0 | F2: 0 | G2: 0 | H2: 0 | I2: 0 | J2: 0 | K2: 0 | L2: 0 | M2: 0 | N2: 0 | O2: 0 | P2: 0 | Q2: 0 | R2: 0 | S2: 0 | T2: 0 | U2: 0 | V2: 0 | W2: 0 | X2: 0 | Y2: 0 | Z2: 0 | AA2: 0 | AB2: 0
A3: coal | B3: =B4 -> 9.3973178e-06 | C3: =C4 -> 9.4453546e-06 | D3: =D4 -> 9.480315e-06 | E3: =E4 -> 9.5300499e-06 | F3: =F4 -> 9.5824326e-06 | G3: =G4 -> 9.6764267e-06 | H3: =H4 -> 9.779442e-06 | I3: =I4 -> 9.892155e-06 | ... AB3: =AB4 -> 1.146342e-05
A4: natural gas | B4: =Calculations!F37 -> 9.3973178e-06 | C4: =Calculations!G37 -> 9.4453546e-06 | D4: =Calculations!H37 -> 9.480315e-06 | E4: =Calculations!I37 -> 9.5300499e-06 | F4: =Calculations!J37 -> 9.5824326e-06 | G4: =Calculations!K37 -> 9.6764267e-06 | H4: =Calculations!L37 -> 9.779442e-06 | I4: =Calculations!M37 -> 9.892155e-06 | ... AB4: =Calculations!AF37 -> 1.146342e-05
A5: petroleum diesel | B5: =Calculations!F38 -> -2.7462406e-05 | C5: =Calculations!G38 -> -2.7752967e-05 | D5: =Calculations!H38 -> -2.8247466e-05 | E5: =Calculations!I38 -> -2.8920036e-05 | F5: =Calculations!J38 -> -2.9667393e-05 | G5: =Calculations!K38 -> -3.0480863e-05 | H5: =Calculations!L38 -> -3.1265934e-05 | I5: =Calculations!M38 -> -3.1916008e-05 | ... AB5: =Calculations!AF38 -> -3.7515594e-05
A6: heat | B6: =B4 -> 9.3973178e-06 | C6: =C4 -> 9.4453546e-06 | D6: =D4 -> 9.480315e-06 | E6: =E4 -> 9.5300499e-06 | F6: =F4 -> 9.5824326e-06 | G6: =G4 -> 9.6764267e-06 | H6: =H4 -> 9.779442e-06 | I6: =I4 -> 9.892155e-06 | ... AB6: =AB4 -> 1.146342e-05
A7: biomass | B7: =B5 -> -2.7462406e-05 | C7: =C5 -> -2.7752967e-05 | D7: =D5 -> -2.8247466e-05 | E7: =E5 -> -2.8920036e-05 | F7: =F5 -> -2.9667393e-05 | G7: =G5 -> -3.0480863e-05 | H7: =H5 -> -3.1265934e-05 | I7: =I5 -> -3.1916008e-05 | ... AB7: =AB5 -> -3.7515594e-05
A8: kerosene | B8: =B5 -> -2.7462406e-05 | C8: =C5 -> -2.7752967e-05 | D8: =D5 -> -2.8247466e-05 | E8: =E5 -> -2.8920036e-05 | F8: =F5 -> -2.9667393e-05 | G8: =G5 -> -3.0480863e-05 | H8: =H5 -> -3.1265934e-05 | I8: =I5 -> -3.1916008e-05 | ... AB8: =AB5 -> -3.7515594e-05
A9: heavy or residual fuel oil | B9: =B5 -> -2.7462406e-05 | C9: =C5 -> -2.7752967e-05 | D9: =D5 -> -2.8247466e-05 | E9: =E5 -> -2.8920036e-05 | F9: =F5 -> -2.9667393e-05 | G9: =G5 -> -3.0480863e-05 | H9: =H5 -> -3.1265934e-05 | I9: =I5 -> -3.1916008e-05 | ... AB9: =AB5 -> -3.7515594e-05
A10: LPG propane or butane | B10: =B4 -> 9.3973178e-06 | C10: =C4 -> 9.4453546e-06 | D10: =D4 -> 9.480315e-06 | E10: =E4 -> 9.5300499e-06 | F10: =F4 -> 9.5824326e-06 | G10: =G4 -> 9.6764267e-06 | H10: =H4 -> 9.779442e-06 | I10: =I4 -> 9.892155e-06 | ... AB10: =AB4 -> 1.146342e-05
A11: hydrogen | B11: =B4 -> 9.3973178e-06 | C11: =C4 -> 9.4453546e-06 | D11: =D4 -> 9.480315e-06 | E11: =E4 -> 9.5300499e-06 | F11: =F4 -> 9.5824326e-06 | G11: =G4 -> 9.6764267e-06 | H11: =H4 -> 9.779442e-06 | I11: =I4 -> 9.892155e-06 | ... AB11: =AB4 -> 1.146342e-05

Sheet ICpUEfEBE-rur-res-heating
A1: Unit: $/(BTU/yr) - a measure of capacity of the fuel-burning equipment that would have been purchased in the absence of an electrification policy | B1: 2024 | C1: 2025 | D1: 2026 | E1: 2027 | F1: 2028 | G1: 2029 | H1: 2030 | I1: 2031 | J1: 2032 | K1: 2033 | L1: 2034 | M1: 2035 | N1: 2036 | O1: 2037 | P1: 2038 | Q1: 2039 | R1: 2040 | S1: 2041 | T1: 2042 | U1: 2043 | V1: 2044 | W1: 2045 | X1: 2046 | Y1: 2047 | Z1: 2048 | AA1: 2049 | AB1: 2050
A2: electricity | B2: 0 | C2: 0 | D2: 0 | E2: 0 | F2: 0 | G2: 0 | H2: 0 | I2: 0 | J2: 0 | K2: 0 | L2: 0 | M2: 0 | N2: 0 | O2: 0 | P2: 0 | Q2: 0 | R2: 0 | S2: 0 | T2: 0 | U2: 0 | V2: 0 | W2: 0 | X2: 0 | Y2: 0 | Z2: 0 | AA2: 0 | AB2: 0
A3: coal | B3: =B4 -> 6.5014456e-05 | C3: =C4 -> 5.8631075e-05 | D3: =D4 -> 5.9244761e-05 | E3: =E4 -> 6.0045832e-05 | F3: =F4 -> 6.1016312e-05 | G3: =G4 -> 6.2266561e-05 | H3: =H4 -> 6.3672427e-05 | I3: =I4 -> 6.519541e-05 | ... AB3: =AB4 -> 9.2887523e-05
A4: natural gas | B4: =Calculations!F19 -> 6.5014456e-05 | C4: =Calculations!G19 -> 5.8631075e-05 | D4: =Calculations!H19 -> 5.9244761e-05 | E4: =Calculations!I19 -> 6.0045832e-05 | F4: =Calculations!J19 -> 6.1016312e-05 | G4: =Calculations!K19 -> 6.2266561e-05 | H4: =Calculations!L19 -> 6.3672427e-05 | I4: =Calculations!M19 -> 6.519541e-05 | ... AB4: =Calculations!AF19 -> 9.2887523e-05
A5: petroleum diesel | B5: =Calculations!F20 -> 1.1230047e-05 | C5: =Calculations!G20 -> 1.0233027e-05 | D5: =Calculations!H20 -> 1.020635e-05 | E5: =Calculations!I20 -> 1.0235544e-05 | F5: =Calculations!J20 -> 1.0296908e-05 | G5: =Calculations!K20 -> 1.036844e-05 | H5: =Calculations!L20 -> 1.0440109e-05 | I5: =Calculations!M20 -> 1.0545292e-05 | ... AB5: =Calculations!AF20 -> 1.219837e-05
A6: heat | B6: =B4 -> 6.5014456e-05 | C6: =C4 -> 5.8631075e-05 | D6: =D4 -> 5.9244761e-05 | E6: =E4 -> 6.0045832e-05 | F6: =F4 -> 6.1016312e-05 | G6: =G4 -> 6.2266561e-05 | H6: =H4 -> 6.3672427e-05 | I6: =I4 -> 6.519541e-05 | ... AB6: =AB4 -> 9.2887523e-05
A7: biomass | B7: =Calculations!F21 -> 2.2103757e-06 | C7: =Calculations!G21 -> 2.1287219e-06 | D7: =Calculations!H21 -> 2.166754e-06 | E7: =Calculations!I21 -> 2.1628074e-06 | F7: =Calculations!J21 -> 2.1354158e-06 | G7: =Calculations!K21 -> 2.0997322e-06 | H7: =Calculations!L21 -> 2.0642521e-06 | I7: =Calculations!M21 -> 2.0146452e-06 | ... AB7: =Calculations!AF21 -> 1.0614188e-06
A8: kerosene | B8: =B5 -> 1.1230047e-05 | C8: =C5 -> 1.0233027e-05 | D8: =D5 -> 1.020635e-05 | E8: =E5 -> 1.0235544e-05 | F8: =F5 -> 1.0296908e-05 | G8: =G5 -> 1.036844e-05 | H8: =H5 -> 1.0440109e-05 | I8: =I5 -> 1.0545292e-05 | ... AB8: =AB5 -> 1.219837e-05
A9: heavy or residual fuel oil | B9: =B5 -> 1.1230047e-05 | C9: =C5 -> 1.0233027e-05 | D9: =D5 -> 1.020635e-05 | E9: =E5 -> 1.0235544e-05 | F9: =F5 -> 1.0296908e-05 | G9: =G5 -> 1.036844e-05 | H9: =H5 -> 1.0440109e-05 | I9: =I5 -> 1.0545292e-05 | ... AB9: =AB5 -> 1.219837e-05
A10: LPG propane or butane | B10: =B4 -> 6.5014456e-05 | C10: =C4 -> 5.8631075e-05 | D10: =D4 -> 5.9244761e-05 | E10: =E4 -> 6.0045832e-05 | F10: =F4 -> 6.1016312e-05 | G10: =G4 -> 6.2266561e-05 | H10: =H4 -> 6.3672427e-05 | I10: =I4 -> 6.519541e-05 | ... AB10: =AB4 -> 9.2887523e-05
A11: hydrogen | B11: =B4 -> 6.5014456e-05 | C11: =C4 -> 5.8631075e-05 | D11: =D4 -> 5.9244761e-05 | E11: =E4 -> 6.0045832e-05 | F11: =F4 -> 6.1016312e-05 | G11: =G4 -> 6.2266561e-05 | H11: =H4 -> 6.3672427e-05 | I11: =I4 -> 6.519541e-05 | ... AB11: =AB4 -> 9.2887523e-05

Sheet ICpUEfEBE-rur-res-appl
A1: Unit: $/(BTU/yr) - a measure of capacity of the fuel-burning equipment that would have been purchased in the absence of an electrification policy | B1: 2024 | C1: 2025 | D1: 2026 | E1: 2027 | F1: 2028 | G1: 2029 | H1: 2030 | I1: 2031 | J1: 2032 | K1: 2033 | L1: 2034 | M1: 2035 | N1: 2036 | O1: 2037 | P1: 2038 | Q1: 2039 | R1: 2040 | S1: 2041 | T1: 2042 | U1: 2043 | V1: 2044 | W1: 2045 | X1: 2046 | Y1: 2047 | Z1: 2048 | AA1: 2049 | AB1: 2050
A2: electricity | B2: 0 | C2: 0 | D2: 0 | E2: 0 | F2: 0 | G2: 0 | H2: 0 | I2: 0 | J2: 0 | K2: 0 | L2: 0 | M2: 0 | N2: 0 | O2: 0 | P2: 0 | Q2: 0 | R2: 0 | S2: 0 | T2: 0 | U2: 0 | V2: 0 | W2: 0 | X2: 0 | Y2: 0 | Z2: 0 | AA2: 0 | AB2: 0
A3: coal | B3: =B4 -> 9.3973178e-06 | C3: =C4 -> 9.4453546e-06 | D3: =D4 -> 9.480315e-06 | E3: =E4 -> 9.5300499e-06 | F3: =F4 -> 9.5824326e-06 | G3: =G4 -> 9.6764267e-06 | H3: =H4 -> 9.779442e-06 | I3: =I4 -> 9.892155e-06 | ... AB3: =AB4 -> 1.146342e-05
A4: natural gas | B4: =Calculations!F37 -> 9.3973178e-06 | C4: =Calculations!G37 -> 9.4453546e-06 | D4: =Calculations!H37 -> 9.480315e-06 | E4: =Calculations!I37 -> 9.5300499e-06 | F4: =Calculations!J37 -> 9.5824326e-06 | G4: =Calculations!K37 -> 9.6764267e-06 | H4: =Calculations!L37 -> 9.779442e-06 | I4: =Calculations!M37 -> 9.892155e-06 | ... AB4: =Calculations!AF37 -> 1.146342e-05
A5: petroleum diesel | B5: =Calculations!F38 -> -2.7462406e-05 | C5: =Calculations!G38 -> -2.7752967e-05 | D5: =Calculations!H38 -> -2.8247466e-05 | E5: =Calculations!I38 -> -2.8920036e-05 | F5: =Calculations!J38 -> -2.9667393e-05 | G5: =Calculations!K38 -> -3.0480863e-05 | H5: =Calculations!L38 -> -3.1265934e-05 | I5: =Calculations!M38 -> -3.1916008e-05 | ... AB5: =Calculations!AF38 -> -3.7515594e-05
A6: heat | B6: =B4 -> 9.3973178e-06 | C6: =C4 -> 9.4453546e-06 | D6: =D4 -> 9.480315e-06 | E6: =E4 -> 9.5300499e-06 | F6: =F4 -> 9.5824326e-06 | G6: =G4 -> 9.6764267e-06 | H6: =H4 -> 9.779442e-06 | I6: =I4 -> 9.892155e-06 | ... AB6: =AB4 -> 1.146342e-05
A7: biomass | B7: =B5 -> -2.7462406e-05 | C7: =C5 -> -2.7752967e-05 | D7: =D5 -> -2.8247466e-05 | E7: =E5 -> -2.8920036e-05 | F7: =F5 -> -2.9667393e-05 | G7: =G5 -> -3.0480863e-05 | H7: =H5 -> -3.1265934e-05 | I7: =I5 -> -3.1916008e-05 | ... AB7: =AB5 -> -3.7515594e-05
A8: kerosene | B8: =B5 -> -2.7462406e-05 | C8: =C5 -> -2.7752967e-05 | D8: =D5 -> -2.8247466e-05 | E8: =E5 -> -2.8920036e-05 | F8: =F5 -> -2.9667393e-05 | G8: =G5 -> -3.0480863e-05 | H8: =H5 -> -3.1265934e-05 | I8: =I5 -> -3.1916008e-05 | ... AB8: =AB5 -> -3.7515594e-05
A9: heavy or residual fuel oil | B9: =B5 -> -2.7462406e-05 | C9: =C5 -> -2.7752967e-05 | D9: =D5 -> -2.8247466e-05 | E9: =E5 -> -2.8920036e-05 | F9: =F5 -> -2.9667393e-05 | G9: =G5 -> -3.0480863e-05 | H9: =H5 -> -3.1265934e-05 | I9: =I5 -> -3.1916008e-05 | ... AB9: =AB5 -> -3.7515594e-05
A10: LPG propane or butane | B10: =B4 -> 9.3973178e-06 | C10: =C4 -> 9.4453546e-06 | D10: =D4 -> 9.480315e-06 | E10: =E4 -> 9.5300499e-06 | F10: =F4 -> 9.5824326e-06 | G10: =G4 -> 9.6764267e-06 | H10: =H4 -> 9.779442e-06 | I10: =I4 -> 9.892155e-06 | ... AB10: =AB4 -> 1.146342e-05
A11: hydrogen | B11: =B4 -> 9.3973178e-06 | C11: =C4 -> 9.4453546e-06 | D11: =D4 -> 9.480315e-06 | E11: =E4 -> 9.5300499e-06 | F11: =F4 -> 9.5824326e-06 | G11: =G4 -> 9.6764267e-06 | H11: =H4 -> 9.779442e-06 | I11: =I4 -> 9.892155e-06 | ... AB11: =AB4 -> 1.146342e-05

Sheet ICpUEfEBE-rur-res-other
A1: Unit: $/(BTU/yr) - a measure of capacity of the fuel-burning equipment that would have been purchased in the absence of an electrification policy | B1: 2024 | C1: 2025 | D1: 2026 | E1: 2027 | F1: 2028 | G1: 2029 | H1: 2030 | I1: 2031 | J1: 2032 | K1: 2033 | L1: 2034 | M1: 2035 | N1: 2036 | O1: 2037 | P1: 2038 | Q1: 2039 | R1: 2040 | S1: 2041 | T1: 2042 | U1: 2043 | V1: 2044 | W1: 2045 | X1: 2046 | Y1: 2047 | Z1: 2048 | AA1: 2049 | AB1: 2050
A2: electricity | B2: 0 | C2: 0 | D2: 0 | E2: 0 | F2: 0 | G2: 0 | H2: 0 | I2: 0 | J2: 0 | K2: 0 | L2: 0 | M2: 0 | N2: 0 | O2: 0 | P2: 0 | Q2: 0 | R2: 0 | S2: 0 | T2: 0 | U2: 0 | V2: 0 | W2: 0 | X2: 0 | Y2: 0 | Z2: 0 | AA2: 0 | AB2: 0
A3: coal | B3: =B4 -> 9.3973178e-06 | C3: =C4 -> 9.4453546e-06 | D3: =D4 -> 9.480315e-06 | E3: =E4 -> 9.5300499e-06 | F3: =F4 -> 9.5824326e-06 | G3: =G4 -> 9.6764267e-06 | H3: =H4 -> 9.779442e-06 | I3: =I4 -> 9.892155e-06 | ... AB3: =AB4 -> 1.146342e-05
A4: natural gas | B4: =Calculations!F37 -> 9.3973178e-06 | C4: =Calculations!G37 -> 9.4453546e-06 | D4: =Calculations!H37 -> 9.480315e-06 | E4: =Calculations!I37 -> 9.5300499e-06 | F4: =Calculations!J37 -> 9.5824326e-06 | G4: =Calculations!K37 -> 9.6764267e-06 | H4: =Calculations!L37 -> 9.779442e-06 | I4: =Calculations!M37 -> 9.892155e-06 | ... AB4: =Calculations!AF37 -> 1.146342e-05
A5: petroleum diesel | B5: =Calculations!F38 -> -2.7462406e-05 | C5: =Calculations!G38 -> -2.7752967e-05 | D5: =Calculations!H38 -> -2.8247466e-05 | E5: =Calculations!I38 -> -2.8920036e-05 | F5: =Calculations!J38 -> -2.9667393e-05 | G5: =Calculations!K38 -> -3.0480863e-05 | H5: =Calculations!L38 -> -3.1265934e-05 | I5: =Calculations!M38 -> -3.1916008e-05 | ... AB5: =Calculations!AF38 -> -3.7515594e-05
A6: heat | B6: =B4 -> 9.3973178e-06 | C6: =C4 -> 9.4453546e-06 | D6: =D4 -> 9.480315e-06 | E6: =E4 -> 9.5300499e-06 | F6: =F4 -> 9.5824326e-06 | G6: =G4 -> 9.6764267e-06 | H6: =H4 -> 9.779442e-06 | I6: =I4 -> 9.892155e-06 | ... AB6: =AB4 -> 1.146342e-05
A7: biomass | B7: =B5 -> -2.7462406e-05 | C7: =C5 -> -2.7752967e-05 | D7: =D5 -> -2.8247466e-05 | E7: =E5 -> -2.8920036e-05 | F7: =F5 -> -2.9667393e-05 | G7: =G5 -> -3.0480863e-05 | H7: =H5 -> -3.1265934e-05 | I7: =I5 -> -3.1916008e-05 | ... AB7: =AB5 -> -3.7515594e-05
A8: kerosene | B8: =B5 -> -2.7462406e-05 | C8: =C5 -> -2.7752967e-05 | D8: =D5 -> -2.8247466e-05 | E8: =E5 -> -2.8920036e-05 | F8: =F5 -> -2.9667393e-05 | G8: =G5 -> -3.0480863e-05 | H8: =H5 -> -3.1265934e-05 | I8: =I5 -> -3.1916008e-05 | ... AB8: =AB5 -> -3.7515594e-05
A9: heavy or residual fuel oil | B9: =B5 -> -2.7462406e-05 | C9: =C5 -> -2.7752967e-05 | D9: =D5 -> -2.8247466e-05 | E9: =E5 -> -2.8920036e-05 | F9: =F5 -> -2.9667393e-05 | G9: =G5 -> -3.0480863e-05 | H9: =H5 -> -3.1265934e-05 | I9: =I5 -> -3.1916008e-05 | ... AB9: =AB5 -> -3.7515594e-05
A10: LPG propane or butane | B10: =B4 -> 9.3973178e-06 | C10: =C4 -> 9.4453546e-06 | D10: =D4 -> 9.480315e-06 | E10: =E4 -> 9.5300499e-06 | F10: =F4 -> 9.5824326e-06 | G10: =G4 -> 9.6764267e-06 | H10: =H4 -> 9.779442e-06 | I10: =I4 -> 9.892155e-06 | ... AB10: =AB4 -> 1.146342e-05
A11: hydrogen | B11: =B4 -> 9.3973178e-06 | C11: =C4 -> 9.4453546e-06 | D11: =D4 -> 9.480315e-06 | E11: =E4 -> 9.5300499e-06 | F11: =F4 -> 9.5824326e-06 | G11: =G4 -> 9.6764267e-06 | H11: =H4 -> 9.779442e-06 | I11: =I4 -> 9.892155e-06 | ... AB11: =AB4 -> 1.146342e-05

Sheet ICpUEfEBE-com-heating
A1: Unit: $/(BTU/yr) - a measure of capacity of the fuel-burning equipment that would have been purchased in the absence of an electrification policy | B1: 2024 | C1: 2025 | D1: 2026 | E1: 2027 | F1: 2028 | G1: 2029 | H1: 2030 | I1: 2031 | J1: 2032 | K1: 2033 | L1: 2034 | M1: 2035 | N1: 2036 | O1: 2037 | P1: 2038 | Q1: 2039 | R1: 2040 | S1: 2041 | T1: 2042 | U1: 2043 | V1: 2044 | W1: 2045 | X1: 2046 | Y1: 2047 | Z1: 2048 | AA1: 2049 | AB1: 2050
A2: electricity | B2: 0 | C2: 0 | D2: 0 | E2: 0 | F2: 0 | G2: 0 | H2: 0 | I2: 0 | J2: 0 | K2: 0 | L2: 0 | M2: 0 | N2: 0 | O2: 0 | P2: 0 | Q2: 0 | R2: 0 | S2: 0 | T2: 0 | U2: 0 | V2: 0 | W2: 0 | X2: 0 | Y2: 0 | Z2: 0 | AA2: 0 | AB2: 0
A3: coal | B3: =B4 -> 0.00010222467 | C3: =C4 -> 0.00010056992 | D3: =D4 -> 9.8915177e-05 | E3: =E4 -> 9.7260433e-05 | F3: =F4 -> 9.5605689e-05 | G3: =G4 -> 9.3950944e-05 | H3: =H4 -> 9.22962e-05 | I3: =I4 -> 9.0679217e-05 | ... AB3: =AB4 -> 7.4205409e-05
A4: natural gas | B4: =Calculations!F58 -> 0.00010222467 | C4: =Calculations!G58 -> 0.00010056992 | D4: =Calculations!H58 -> 9.8915177e-05 | E4: =Calculations!I58 -> 9.7260433e-05 | F4: =Calculations!J58 -> 9.5605689e-05 | G4: =Calculations!K58 -> 9.3950944e-05 | H4: =Calculations!L58 -> 9.22962e-05 | I4: =Calculations!M58 -> 9.0679217e-05 | ... AB4: =Calculations!AF58 -> 7.4205409e-05
A5: petroleum diesel | B5: =Calculations!F59 -> 8.742229e-05 | C5: =Calculations!G59 -> 8.5784252e-05 | D5: =Calculations!H59 -> 8.4146215e-05 | E5: =Calculations!I59 -> 8.2508178e-05 | F5: =Calculations!J59 -> 8.0870141e-05 | G5: =Calculations!K59 -> 7.9232103e-05 | H5: =Calculations!L59 -> 7.7594066e-05 | I5: =Calculations!M59 -> 7.5977083e-05 | ... AB5: =Calculations!AF59 -> 5.9503275e-05
A6: heat | B6: =B4 -> 0.00010222467 | C6: =C4 -> 0.00010056992 | D6: =D4 -> 9.8915177e-05 | E6: =E4 -> 9.7260433e-05 | F6: =F4 -> 9.5605689e-05 | G6: =G4 -> 9.3950944e-05 | H6: =H4 -> 9.22962e-05 | I6: =I4 -> 9.0679217e-05 | ... AB6: =AB4 -> 7.4205409e-05
A7: biomass | B7: =B5 -> 8.742229e-05 | C7: =C5 -> 8.5784252e-05 | D7: =D5 -> 8.4146215e-05 | E7: =E5 -> 8.2508178e-05 | F7: =F5 -> 8.0870141e-05 | G7: =G5 -> 7.9232103e-05 | H7: =H5 -> 7.7594066e-05 | I7: =I5 -> 7.5977083e-05 | ... AB7: =AB5 -> 5.9503275e-05
A8: kerosene | B8: =B5 -> 8.742229e-05 | C8: =C5 -> 8.5784252e-05 | D8: =D5 -> 8.4146215e-05 | E8: =E5 -> 8.2508178e-05 | F8: =F5 -> 8.0870141e-05 | G8: =G5 -> 7.9232103e-05 | H8: =H5 -> 7.7594066e-05 | I8: =I5 -> 7.5977083e-05 | ... AB8: =AB5 -> 5.9503275e-05
A9: heavy or residual fuel oil | B9: =B5 -> 8.742229e-05 | C9: =C5 -> 8.5784252e-05 | D9: =D5 -> 8.4146215e-05 | E9: =E5 -> 8.2508178e-05 | F9: =F5 -> 8.0870141e-05 | G9: =G5 -> 7.9232103e-05 | H9: =H5 -> 7.7594066e-05 | I9: =I5 -> 7.5977083e-05 | ... AB9: =AB5 -> 5.9503275e-05
A10: LPG propane or butane | B10: =B4 -> 0.00010222467 | C10: =C4 -> 0.00010056992 | D10: =D4 -> 9.8915177e-05 | E10: =E4 -> 9.7260433e-05 | F10: =F4 -> 9.5605689e-05 | G10: =G4 -> 9.3950944e-05 | H10: =H4 -> 9.22962e-05 | I10: =I4 -> 9.0679217e-05 | ... AB10: =AB4 -> 7.4205409e-05
A11: hydrogen | B11: =B4 -> 0.00010222467 | C11: =C4 -> 0.00010056992 | D11: =D4 -> 9.8915177e-05 | E11: =E4 -> 9.7260433e-05 | F11: =F4 -> 9.5605689e-05 | G11: =G4 -> 9.3950944e-05 | H11: =H4 -> 9.22962e-05 | I11: =I4 -> 9.0679217e-05 | ... AB11: =AB4 -> 7.4205409e-05

Sheet ICpUEfEBE-com-appl
A1: Unit: $/(BTU/yr) - a measure of capacity of the fuel-burning equipment that would have been purchased in the absence of an electrification policy | B1: 2024 | C1: 2025 | D1: 2026 | E1: 2027 | F1: 2028 | G1: 2029 | H1: 2030 | I1: 2031 | J1: 2032 | K1: 2033 | L1: 2034 | M1: 2035 | N1: 2036 | O1: 2037 | P1: 2038 | Q1: 2039 | R1: 2040 | S1: 2041 | T1: 2042 | U1: 2043 | V1: 2044 | W1: 2045 | X1: 2046 | Y1: 2047 | Z1: 2048 | AA1: 2049 | AB1: 2050
A2: electricity | B2: 0 | C2: 0 | D2: 0 | E2: 0 | F2: 0 | G2: 0 | H2: 0 | I2: 0 | J2: 0 | K2: 0 | L2: 0 | M2: 0 | N2: 0 | O2: 0 | P2: 0 | Q2: 0 | R2: 0 | S2: 0 | T2: 0 | U2: 0 | V2: 0 | W2: 0 | X2: 0 | Y2: 0 | Z2: 0 | AA2: 0 | AB2: 0
A3: coal | B3: =B4 -> 0.00011023998 | C3: =C4 -> 0.00010848438 | D3: =D4 -> 0.00010672879 | E3: =E4 -> 0.0001049732 | F3: =F4 -> 0.00010321761 | G3: =G4 -> 0.00010146202 | H3: =H4 -> 9.970643e-05 | I3: =I4 -> 9.7876754e-05 | ... AB3: =AB4 -> 7.1784875e-05
A4: natural gas | B4: =Calculations!F78 -> 0.00011023998 | C4: =Calculations!G78 -> 0.00010848438 | D4: =Calculations!H78 -> 0.00010672879 | E4: =Calculations!I78 -> 0.0001049732 | F4: =Calculations!J78 -> 0.00010321761 | G4: =Calculations!K78 -> 0.00010146202 | H4: =Calculations!L78 -> 9.970643e-05 | I4: =Calculations!M78 -> 9.7876754e-05 | ... AB4: =Calculations!AF78 -> 7.1784875e-05
A5: petroleum diesel | B5: =Calculations!F79 -> 0.00011115483 | C5: =Calculations!G79 -> 0.00010939924 | D5: =Calculations!H79 -> 0.00010764365 | E5: =Calculations!I79 -> 0.00010588806 | F5: =Calculations!J79 -> 0.00010413247 | G5: =Calculations!K79 -> 0.00010237688 | H5: =Calculations!L79 -> 0.00010062129 | I5: =Calculations!M79 -> 9.8791613e-05 | ... AB5: =Calculations!AF79 -> 7.2699734e-05
A6: heat | B6: =B4 -> 0.00011023998 | C6: =C4 -> 0.00010848438 | D6: =D4 -> 0.00010672879 | E6: =E4 -> 0.0001049732 | F6: =F4 -> 0.00010321761 | G6: =G4 -> 0.00010146202 | H6: =H4 -> 9.970643e-05 | I6: =I4 -> 9.7876754e-05 | ... AB6: =AB4 -> 7.1784875e-05
A7: biomass | B7: =B5 -> 0.00011115483 | C7: =C5 -> 0.00010939924 | D7: =D5 -> 0.00010764365 | E7: =E5 -> 0.00010588806 | F7: =F5 -> 0.00010413247 | G7: =G5 -> 0.00010237688 | H7: =H5 -> 0.00010062129 | I7: =I5 -> 9.8791613e-05 | ... AB7: =AB5 -> 7.2699734e-05
A8: kerosene | B8: =B5 -> 0.00011115483 | C8: =C5 -> 0.00010939924 | D8: =D5 -> 0.00010764365 | E8: =E5 -> 0.00010588806 | F8: =F5 -> 0.00010413247 | G8: =G5 -> 0.00010237688 | H8: =H5 -> 0.00010062129 | I8: =I5 -> 9.8791613e-05 | ... AB8: =AB5 -> 7.2699734e-05
A9: heavy or residual fuel oil | B9: =B5 -> 0.00011115483 | C9: =C5 -> 0.00010939924 | D9: =D5 -> 0.00010764365 | E9: =E5 -> 0.00010588806 | F9: =F5 -> 0.00010413247 | G9: =G5 -> 0.00010237688 | H9: =H5 -> 0.00010062129 | I9: =I5 -> 9.8791613e-05 | ... AB9: =AB5 -> 7.2699734e-05
A10: LPG propane or butane | B10: =B4 -> 0.00011023998 | C10: =C4 -> 0.00010848438 | D10: =D4 -> 0.00010672879 | E10: =E4 -> 0.0001049732 | F10: =F4 -> 0.00010321761 | G10: =G4 -> 0.00010146202 | H10: =H4 -> 9.970643e-05 | I10: =I4 -> 9.7876754e-05 | ... AB10: =AB4 -> 7.1784875e-05
A11: hydrogen | B11: =B4 -> 0.00011023998 | C11: =C4 -> 0.00010848438 | D11: =D4 -> 0.00010672879 | E11: =E4 -> 0.0001049732 | F11: =F4 -> 0.00010321761 | G11: =G4 -> 0.00010146202 | H11: =H4 -> 9.970643e-05 | I11: =I4 -> 9.7876754e-05 | ... AB11: =AB4 -> 7.1784875e-05

Sheet ICpUEfEBE-com-other
A1: Unit: $/(BTU/yr) - a measure of capacity of the fuel-burning equipment that would have been purchased in the absence of an electrification policy | B1: 2024 | C1: 2025 | D1: 2026 | E1: 2027 | F1: 2028 | G1: 2029 | H1: 2030 | I1: 2031 | J1: 2032 | K1: 2033 | L1: 2034 | M1: 2035 | N1: 2036 | O1: 2037 | P1: 2038 | Q1: 2039 | R1: 2040 | S1: 2041 | T1: 2042 | U1: 2043 | V1: 2044 | W1: 2045 | X1: 2046 | Y1: 2047 | Z1: 2048 | AA1: 2049 | AB1: 2050
A2: electricity | B2: 0 | C2: 0 | D2: 0 | E2: 0 | F2: 0 | G2: 0 | H2: 0 | I2: 0 | J2: 0 | K2: 0 | L2: 0 | M2: 0 | N2: 0 | O2: 0 | P2: 0 | Q2: 0 | R2: 0 | S2: 0 | T2: 0 | U2: 0 | V2: 0 | W2: 0 | X2: 0 | Y2: 0 | Z2: 0 | AA2: 0 | AB2: 0
A3: coal | B3: =B4 -> 0.00011023998 | C3: =C4 -> 0.00010848438 | D3: =D4 -> 0.00010672879 | E3: =E4 -> 0.0001049732 | F3: =F4 -> 0.00010321761 | G3: =G4 -> 0.00010146202 | H3: =H4 -> 9.970643e-05 | I3: =I4 -> 9.7876754e-05 | ... AB3: =AB4 -> 7.1784875e-05
A4: natural gas | B4: =Calculations!F78 -> 0.00011023998 | C4: =Calculations!G78 -> 0.00010848438 | D4: =Calculations!H78 -> 0.00010672879 | E4: =Calculations!I78 -> 0.0001049732 | F4: =Calculations!J78 -> 0.00010321761 | G4: =Calculations!K78 -> 0.00010146202 | H4: =Calculations!L78 -> 9.970643e-05 | I4: =Calculations!M78 -> 9.7876754e-05 | ... AB4: =Calculations!AF78 -> 7.1784875e-05
A5: petroleum diesel | B5: =Calculations!F79 -> 0.00011115483 | C5: =Calculations!G79 -> 0.00010939924 | D5: =Calculations!H79 -> 0.00010764365 | E5: =Calculations!I79 -> 0.00010588806 | F5: =Calculations!J79 -> 0.00010413247 | G5: =Calculations!K79 -> 0.00010237688 | H5: =Calculations!L79 -> 0.00010062129 | I5: =Calculations!M79 -> 9.8791613e-05 | ... AB5: =Calculations!AF79 -> 7.2699734e-05
A6: heat | B6: =B4 -> 0.00011023998 | C6: =C4 -> 0.00010848438 | D6: =D4 -> 0.00010672879 | E6: =E4 -> 0.0001049732 | F6: =F4 -> 0.00010321761 | G6: =G4 -> 0.00010146202 | H6: =H4 -> 9.970643e-05 | I6: =I4 -> 9.7876754e-05 | ... AB6: =AB4 -> 7.1784875e-05
A7: biomass | B7: =B5 -> 0.00011115483 | C7: =C5 -> 0.00010939924 | D7: =D5 -> 0.00010764365 | E7: =E5 -> 0.00010588806 | F7: =F5 -> 0.00010413247 | G7: =G5 -> 0.00010237688 | H7: =H5 -> 0.00010062129 | I7: =I5 -> 9.8791613e-05 | ... AB7: =AB5 -> 7.2699734e-05
A8: kerosene | B8: =B5 -> 0.00011115483 | C8: =C5 -> 0.00010939924 | D8: =D5 -> 0.00010764365 | E8: =E5 -> 0.00010588806 | F8: =F5 -> 0.00010413247 | G8: =G5 -> 0.00010237688 | H8: =H5 -> 0.00010062129 | I8: =I5 -> 9.8791613e-05 | ... AB8: =AB5 -> 7.2699734e-05
A9: heavy or residual fuel oil | B9: =B5 -> 0.00011115483 | C9: =C5 -> 0.00010939924 | D9: =D5 -> 0.00010764365 | E9: =E5 -> 0.00010588806 | F9: =F5 -> 0.00010413247 | G9: =G5 -> 0.00010237688 | H9: =H5 -> 0.00010062129 | I9: =I5 -> 9.8791613e-05 | ... AB9: =AB5 -> 7.2699734e-05
A10: LPG propane or butane | B10: =B4 -> 0.00011023998 | C10: =C4 -> 0.00010848438 | D10: =D4 -> 0.00010672879 | E10: =E4 -> 0.0001049732 | F10: =F4 -> 0.00010321761 | G10: =G4 -> 0.00010146202 | H10: =H4 -> 9.970643e-05 | I10: =I4 -> 9.7876754e-05 | ... AB10: =AB4 -> 7.1784875e-05
A11: hydrogen | B11: =B4 -> 0.00011023998 | C11: =C4 -> 0.00010848438 | D11: =D4 -> 0.00010672879 | E11: =E4 -> 0.0001049732 | F11: =F4 -> 0.00010321761 | G11: =G4 -> 0.00010146202 | H11: =H4 -> 9.970643e-05 | I11: =I4 -> 9.7876754e-05 | ... AB11: =AB4 -> 7.1784875e-05
