Workbook

Sheet About
A1: GaHEbIC Government and Household Expenditures by ISIC Code (42-code)
A3: Sources: | B3: Government (GGFC) and household (HFCE) final consumption by industry, 2022
B4: OECD
B5: OECD Input-Output Tables (latest edition), total table
B6: 2024
B7: https://www.oecd.org/en/data/datasets/input-output-tables.html
B8: Tab OECD_TTL, verbatim. Government = GGFC column; household = HFCE column. 42-code output: the six OECD-native splits are summed back to their parent (01T03/07T08/30/49T53/69T82/90T96); the C23 and D carves stay split.
B10: Carve-child shares (231/239, 351/352T353)
B11: U.S. Bureau of Economic Analysis
B12: 2017 benchmark Use table: government final-demand columns (F06*/F07*/F10*) and PCE (F01000)
B13: 2023
B14: https://www.bea.gov/industry/input-output-accounts-data
B15: Tab 'BEA Use 2017', verbatim with crosswalk helpers. Carve children retained as their own 42 codes (not collapsed).
A18: Notes:
A19: Currency | B19: 2022 USD -> 2012 USD conversion factor below (editable): CPI-U annual averages 2012/2022 from InputData/cpi.xlsx (229.594/292.655) — the model-canonical currency converter, matching every stock factor.
A20: 0.78452102 | B20: 2012 USD per 2022 USD
A22: Collapse | B22: 42-code = 52-code with six OECD-native parents un-split. GaHEbIC is a level ($), so each 42 column is the exact sum of its 52 children (no re-weighting). Conservation of gov + hh totals vs the 52 build is verified in build_gahebic_42 (and the per-carve reaggregation on the Checks tab).

Sheet OECD_TTL
B1: A01 | C1: A02 | D1: A03 | E1: B05 | F1: B06 | G1: B07 | H1: B08 | I1: B09 | J1: C10T12 | K1: C13T15 | L1: C16 | M1: C17_18 | N1: C19 | O1: C20 | P1: C21 | Q1: C22 | R1: C23 | S1: C24A | T1: C24B | U1: C25 | V1: C26 | W1: C27 | X1: C28 | Y1: C29 | Z1: C301 | AA1: C302T309 | AB1: C31T33 | AC1: D | AD1: E | AE1: F | AF1: G | AG1: H49 | AH1: H50 | AI1: H51 | AJ1: H52 | AK1: H53 | AL1: I | AM1: J58T60 | AN1: J61 | AO1: J62_63 | AP1: K | AQ1: L | AR1: M | AS1: N | AT1: O | AU1: P | AV1: Q | AW1: R | AX1: S | AY1: T | AZ1: HFCE | BA1: NPISH | BB1: GGFC | BC1: GFCF | BD1: INVNT | BE1: DPABR | BF1: CONS_NONRES | BG1: EXPO | BH1: IMPO | BI1: TOTAL
A2: TTL_A01 | B2: 74779.371 | C2: 729.474 | D2: 48.606 | E2: 3.371 | F2: 32.701 | G2: 1.71 | H2: 8.438 | I2: 2.685 | J2: 244020.02 | K2: 1261.74 | L2: 765.633 | M2: 104.3 | N2: 10.732 | O2: 986.888 | P2: 750.978 | Q2: 567.622 | R2: 9.34 | S2: 2.31 | T2: 2.514 | U2: 8.955 | V2: 8.138 | W2: 3.681 | X2: 35.538 | Y2: 33.355 | Z2: 1.405 | AA2: 8.152 | AB2: 179.08 | AC2: 162.945 | AD2: 55.649 | AE2: 689.944 | AF2: 9434.576 | AG2: 113.147 | AH2: 14.435 | AI2: 4.136 | AJ2: 65.436 | AK2: 7.285 | AL2: 52185.807 | AM2: 78.16 | AN2: 19.382 | AO2: 17.162 | AP2: 74.636 | AQ2: 395.058 | AR2: 1051.573 | AS2: 1513.491 | AT2: 2681.544 | AU2: 1303.299 | AV2: 5182.226 | AW2: 586.576 | AX2: 834.92 | AY2: 0 | AZ2: 212576.91 | BA2: 517.39 | BB2: 0.473 | BC2: 98.44 | BD2: 208.618 | BE2: 1567.22 | BF2: 426.017 | BG2: 65992.048 | BH2: -51305.832 | BI2: 630919.41
A3: TTL_A02 | B3: 653.615 | C3: 2244.103 | D3: 0.905 | E3: 10.943 | F3: 19.423 | G3: 1.665 | H3: 2.56 | I3: 0.076 | J3: 767.453 | K3: 12.704 | L3: 7209.622 | M3: 661.867 | N3: 0.791 | O3: 47.507 | P3: 8.773 | Q3: 242.507 | R3: 11.813 | S3: 2.523 | T3: 2.073 | U3: 2.45 | V3: 0.286 | W3: 0.444 | X3: 2.963 | Y3: 2.663 | Z3: 0.552 | AA3: 0.803 | AB3: 297.692 | AC3: 208.093 | AD3: 1.209 | AE3: 209.583 | AF3: 448.729 | AG3: 3.267 | AH3: 0.483 | AI3: 0.252 | AJ3: 2.069 | AK3: 0.42 | AL3: 336.258 | AM3: 7.112 | AN3: 4.012 | AO3: 5.372 | AP3: 3.447 | AQ3: 42.151 | AR3: 14.444 | AS3: 25.652 | AT3: 245.703 | AU3: 49.752 | AV3: 66.658 | AW3: 37.577 | AX3: 34.3 | AY3: 0 | AZ3: 14849.907 | BA3: 150.645 | BB3: 0.067 | BC3: 48.963 | BD3: 5.547 | BE3: 22.263 | BF3: 0.025 | BG3: 1290.846 | BH3: -3873.05 | BI3: 26450.533
A4: TTL_A03 | B4: 23.876 | C4: 1.913 | D4: 92.259 | E4: 0.145 | F4: 1.362 | G4: 0.209 | H4: 0.239 | I4: 0.021 | J4: 8300.546 | K4: 0.37 | L4: 0.309 | M4: 0.459 | N4: 0.978 | O4: 2.989 | P4: 1.752 | Q4: 0.705 | R4: 0.382 | S4: 0.226 | T4: 0.215 | U4: 0.647 | V4: 0.218 | W4: 0.202 | X4: 0.632 | Y4: 0.465 | Z4: 0.271 | AA4: 0.236 | AB4: 0.524 | AC4: 0.461 | AD4: 0.274 | AE4: 2.689 | AF4: 179.46 | AG4: 2.043 | AH4: 4.171 | AI4: 0.243 | AJ4: 2.951 | AK4: 0.091 | AL4: 3857.341 | AM4: 3.326 | AN4: 0.933 | AO4: 2.532 | AP4: 5.635 | AQ4: 15.058 | AR4: 6.209 | AS4: 3.42 | AT4: 171.368 | AU4: 26.86 | AV4: 122.228 | AW4: 6.878 | AX4: 13.061 | AY4: 0 | AZ4: 6908.574 | BA4: 42.877 | BB4: 0.008 | BC4: 4.275 | BD4: 7.225 | BE4: 96.871 | BF4: 10.609 | BG4: 2385.951 | BH4: -15796.516 | BI4: 6519.255
A5: TTL_B05 | B5: 51.576 | C5: 2.362 | D5: 0.152 | E5: 418.917 | F5: 479.784 | G5: 40.782 | H5: 40.222 | I5: 38.481 | J5: 138.844 | K5: 11.553 | L5: 8.132 | M5: 95.255 | N5: 2046.457 | O5: 293.826 | P5: 6.161 | Q5: 31.046 | R5: 466.826 | S5: 1924.388 | T5: 306.992 | U5: 10.866 | V5: 2.089 | W5: 5.181 | X5: 14.052 | Y5: 16.93 | Z5: 1.96 | AA5: 12.526 | AB5: 6.004 | AC5: 12957.678 | AD5: 10.056 | AE5: 717.799 | AF5: 130.599 | AG5: 31.915 | AH5: 0.514 | AI5: 1.316 | AJ5: 17.128 | AK5: 1.676 | AL5: 47.221 | AM5: 5.173 | AN5: 15.351 | AO5: 4.489 | AP5: 21.679 | AQ5: 490.661 | AR5: 48.845 | AS5: 22.127 | AT5: 405.155 | AU5: 128.508 | AV5: 83.48 | AW5: 6.388 | AX5: 50.899 | AY5: 0 | AZ5: 18.116 | BA5: 0.709 | BB5: 0.033 | BC5: 5851.996 | BD5: 0.34 | BE5: 3.809 | BF5: 0.01 | BG5: 13417.78 | BH5: -461.32 | BI5: 40501.495
A6: TTL_B06 | B6: 1337.669 | C6: 80.35 | D6: 34.976 | E6: 608.574 | F6: 44951.12 | G6: 457.205 | H6: 800.07 | I6: 833.579 | J6: 2743.208 | K6: 118.636 | L6: 278.17 | M6: 1531.424 | N6: 460643.68 | O6: 13736.478 | P6: 199.208 | Q6: 773.971 | R6: 3251.794 | S6: 3524.119 | T6: 2182.671 | U6: 1054.101 | V6: 75.213 | W6: 125.611 | X6: 371.039 | Y6: 864.442 | Z6: 31.587 | AA6: 242.473 | AB6: 376.688 | AC6: 97219.223 | AD6: 479.417 | AE6: 3239.622 | AF6: 9710.059 | AG6: 7263.486 | AH6: 701.687 | AI6: 2661 | AJ6: 1246.527 | AK6: 305.473 | AL6: 1202.682 | AM6: 303.544 | AN6: 266.148 | AO6: 375.681 | AP6: 1055.687 | AQ6: 2669.84 | AR6: 2106.796 | AS6: 1946.822 | AT6: 6811.557 | AU6: 1427.372 | AV6: 1911.932 | AW6: 254.969 | AX6: 600.477 | AY6: 0 | AZ6: 15958.877 | BA6: 3.662 | BB6: 0.413 | BC6: 23691.18 | BD6: 10.843 | BE6: 29.63 | BF6: 115.74 | BG6: 177625.12 | BH6: -188381.39 | BI6: 714042.13
A7: TTL_B07 | B7: 21.136 | C7: 0.533 | D7: 0.107 | E7: 46.165 | F7: 391.474 | G7: 873.276 | H7: 175.266 | I7: 58.339 | J7: 87.68 | K7: 4.093 | L7: 3.291 | M7: 8.037 | N7: 445.071 | O7: 517.92 | P7: 11.419 | Q7: 21.192 | R7: 691.063 | S7: 8228.601 | T7: 11291.735 | U7: 586.573 | V7: 34.599 | W7: 72.131 | X7: 130.605 | Y7: 156.905 | Z7: 3.453 | AA7: 35.249 | AB7: 67.326 | AC7: 303.59 | AD7: 21.124 | AE7: 1234.964 | AF7: 91.334 | AG7: 17.811 | AH7: 0.485 | AI7: 1.429 | AJ7: 9.101 | AK7: 1.014 | AL7: 31.867 | AM7: 6.111 | AN7: 8.343 | AO7: 9.828 | AP7: 21.693 | AQ7: 190.596 | AR7: 66.025 | AS7: 30.671 | AT7: 105.289 | AU7: 21.494 | AV7: 30.898 | AW7: 5.304 | AX7: 21.159 | AY7: 0 | AZ7: 18.255 | BA7: 0.442 | BB7: 0.149 | BC7: 2085.398 | BD7: 0.909 | BE7: 12.043 | BF7: 0.007 | BG7: 9919.664 | BH7: -3762.406 | BI7: 34467.828
A8: TTL_B08 | B8: 657.848 | C8: 11.285 | D8: 3.064 | E8: 78.103 | F8: 1284.831 | G8: 160.48 | H8: 1619.92 | I8: 145.081 | J8: 641.961 | K8: 43.046 | L8: 26.572 | M8: 262.977 | N8: 957.263 | O8: 2588.614 | P8: 100.173 | Q8: 341.829 | R8: 10621.362 | S8: 1700.216 | T8: 655.116 | U8: 196.936 | V8: 29.023 | W8: 47.668 | X8: 90.372 | Y8: 114.291 | Z8: 5.087 | AA8: 21.409 | AB8: 174.778 | AC8: 779.713 | AD8: 133.34 | AE8: 20343.021 | AF8: 315.39 | AG8: 58.431 | AH8: 4.151 | AI8: 2.464 | AJ8: 33.276 | AK8: 2.734 | AL8: 155.171 | AM8: 23.325 | AN8: 19.451 | AO8: 9.824 | AP8: 30.602 | AQ8: 1663.727 | AR8: 163.819 | AS8: 492.267 | AT8: 1005.297 | AU8: 99.175 | AV8: 215.879 | AW8: 21.187 | AX8: 74.717 | AY8: 0 | AZ8: 835.751 | BA8: 1.271 | BB8: 0.087 | BC8: 7637.615 | BD8: 3.524 | BE8: 11.454 | BF8: 1.317 | BG8: 2273.556 | BH8: -6083.596 | BI8: 52907.245
A9: TTL_B09 | B9: 55.882 | C9: 3.645 | D9: 2.903 | E9: 134.428 | F9: 12123.063 | G9: 123.964 | H9: 308.364 | I9: 687.272 | J9: 69.293 | K9: 2.968 | L9: 10.614 | M9: 36.926 | N9: 877.196 | O9: 46.042 | P9: 7.316 | Q9: 25.535 | R9: 197.437 | S9: 66.588 | T9: 43.763 | U9: 120.43 | V9: 12.298 | W9: 12.56 | X9: 81.173 | Y9: 95.852 | Z9: 5.505 | AA9: 27.148 | AB9: 26.296 | AC9: 371.083 | AD9: 19.824 | AE9: 1911.021 | AF9: 234.337 | AG9: 54.741 | AH9: 3.407 | AI9: 7.854 | AJ9: 40.489 | AK9: 7.239 | AL9: 69.438 | AM9: 22.666 | AN9: 40.65 | AO9: 15.644 | AP9: 64.399 | AQ9: 1231.444 | AR9: 156.057 | AS9: 63.82 | AT9: 650.562 | AU9: 115.548 | AV9: 146.814 | AW9: 16.077 | AX9: 28.731 | AY9: 0 | AZ9: 316.966 | BA9: 2.393 | BB9: 0.239 | BC9: 44724.572 | BD9: 9.369 | BE9: 6.612 | BF9: 0.716 | BG9: 1828.476 | BH9: -3726.442 | BI9: 63639.207
A10: TTL_C10T12 | B10: 23749.497 | C10: 21.377 | D10: 104.292 | E10: 7.941 | F10: 139.048 | G10: 10.165 | H10: 19.262 | I10: 6.929 | J10: 73351.166 | K10: 164.633 | L10: 68.485 | M10: 327.96 | N10: 160.633 | O10: 1908.486 | P10: 838.38 | Q10: 376.828 | R10: 78.062 | S10: 47.314 | T10: 38.913 | U10: 121.907 | V10: 67.323 | W10: 40.203 | X10: 128.333 | Y10: 179.42 | Z10: 9.776 | AA10: 68.081 | AB10: 169.901 | AC10: 71.939 | AD10: 77.559 | AE10: 463.247 | AF10: 8331.551 | AG10: 193.764 | AH10: 66.607 | AI10: 46.558 | AJ10: 132.102 | AK10: 32.534 | AL10: 96328.35 | AM10: 554.378 | AN10: 183.999 | AO10: 288.438 | AP10: 469.104 | AQ10: 1077.84 | AR10: 824.711 | AS10: 790.394 | AT10: 3978.887 | AU10: 3191.159 | AV10: 7598.644 | AW10: 1038.856 | AX10: 854.465 | AY10: 0 | AZ10: 968789.27 | BA10: 984.672 | BB10: 3.673 | BC10: 1049.887 | BD10: 448.556 | BE10: 4784.054 | BF10: 2628.502 | BG10: 63542.457 | BH10: -145888.8 | BI10: 1125141.7
A11: TTL_C13T15 | B11: 423.683 | C11: 12.743 | D11: 13.901 | E11: 12.378 | F11: 188.667 | G11: 19.021 | H11: 15.732 | I11: 8.359 | J11: 397.391 | K11: 7337.367 | L11: 106.907 | M11: 763.498 | N11: 93.229 | O11: 981.663 | P11: 201.119 | Q11: 1050.294 | R11: 196.72 | S11: 47.963 | T11: 30.208 | U11: 189.439 | V11: 83.141 | W11: 57.98 | X11: 199.721 | Y11: 1639.653 | Z11: 32.226 | AA11: 159.676 | AB11: 1657.128 | AC11: 45.135 | AD11: 62.756 | AE11: 847.621 | AF11: 2868.688 | AG11: 93.392 | AH11: 7.01 | AI11: 18.703 | AJ11: 66.775 | AK11: 36.353 | AL11: 1408.628 | AM11: 161.295 | AN11: 54.848 | AO11: 74.25 | AP11: 156.54 | AQ11: 447.165 | AR11: 727.695 | AS11: 997.591 | AT11: 2368.708 | AU11: 576.602 | AV11: 2824.933 | AW11: 416.885 | AX11: 956.039 | AY11: 0 | AZ11: 187948.66 | BA11: 55.915 | BB11: 2.504 | BC11: 4284.175 | BD11: 591.696 | BE11: 1847.983 | BF11: 370.502 | BG11: 14412.892 | BH11: -168328.41 | BI11: 72323.338
A12: TTL_C16 | B12: 1370.992 | C12: 250.222 | D12: 6.42 | E12: 80.038 | F12: 413.417 | G12: 59.921 | H12: 65.011 | I12: 21.885 | J12: 2620.526 | K12: 158.071 | L12: 35331.09 | M12: 4414.547 | N12: 52.925 | O12: 1134.51 | P12: 180.322 | Q12: 786.795 | R12: 1204.839 | S12: 124.72 | T12: 167.017 | U12: 1237.41 | V12: 204.245 | W12: 288.456 | X12: 728.74 | Y12: 2710.93 | Z12: 307.637 | AA12: 400.221 | AB12: 16380.022 | AC12: 545.32 | AD12: 131.397 | AE12: 56706.308 | AF12: 7515.633 | AG12: 455.581 | AH12: 13.071 | AI12: 30.557 | AJ12: 705.158 | AK12: 22.385 | AL12: 2462.48 | AM12: 553.071 | AN12: 147.408 | AO12: 165.695 | AP12: 336.02 | AQ12: 7227.976 | AR12: 2783.534 | AS12: 1946.892 | AT12: 1349.059 | AU12: 1106.632 | AV12: 2128.705 | AW12: 417.824 | AX12: 2058.027 | AY12: 0 | AZ12: 13170.585 | BA12: 1.262 | BB12: 13.303 | BC12: 23976.196 | BD12: 2004.728 | BE12: 185.783 | BF12: 138.729 | BG12: 6137.611 | BH12: -32413.007 | BI12: 172724.85
A13: TTL_C17_18 | B13: 859.992 | C13: 19.611 | D13: 9.324 | E13: 16.102 | F13: 541.076 | G13: 43.629 | H13: 32.552 | I13: 19.372 | J13: 15327.946 | K13: 562.347 | L13: 773.943 | M13: 51164.289 | N13: 178.812 | O13: 1875.671 | P13: 2136.615 | Q13: 1634.007 | R13: 1226.791 | S13: 164.819 | T13: 175.347 | U13: 1127.231 | V13: 562.906 | W13: 430.81 | X13: 1086.086 | Y13: 1628.998 | Z13: 39.775 | AA13: 395.315 | AB13: 1772.799 | AC13: 338.533 | AD13: 261.248 | AE13: 2434.654 | AF13: 21436.154 | AG13: 736.798 | AH13: 64.025 | AI13: 95.047 | AJ13: 637.625 | AK13: 617.288 | AL13: 4624.998 | AM13: 26113.503 | AN13: 1820.503 | AO13: 4495.782 | AP13: 10753.952 | AQ13: 3422.122 | AR13: 12625.146 | AS13: 10049.4 | AT13: 19370.123 | AU13: 12128.673 | AV13: 11480.726 | AW13: 1600.043 | AX13: 3824.653 | AY13: 0 | AZ13: 62578.522 | BA13: 6.275 | BB13: 9.314 | BC13: 1503.291 | BD13: 122.618 | BE13: 609.33 | BF13: 542.306 | BG13: 25795.812 | BH13: -32256.014 | BI13: 291648.62
... A60: OUTPUT | B60: 630919.34 | C60: 26450.53 | D60: 6519.255 | E60: 40501.495 | F60: 714042.12 | G60: 34467.829 | H60: 52907.241 | I60: 63639.201 | J60: 1125141.5 | K60: 72323.331 | L60: 172724.83 | M60: 291648.59 | N60: 881098.57 | O60: 637748.79 | P60: 360489.35 | Q60: 303657.86 | R60: 190055.6 | S60: 198465.51 | T60: 161745.51 | U60: 453544.3 | V60: 489552.04 | W60: 156843.22 | X60: 446815.25 | Y60: 733534.89 | Z60: 48269.629 | AA60: 305724.2 | AB60: 309942.68 | AC60: 688239.61 | AD60: 154252.56 | AE60: 2164368 | AF60: 4883363.6 | AG60: 807593.73 | AH60: 66024.925 | AI60: 252594.38 | AJ60: 428397.57 | AK60: 206299.23 | AL60: 1397055.9 | AM60: 957179.2 | AN60: 674242.33 | AO60: 1337497.2 | AP60: 3528094 | AQ60: 4501781.2 | AR60: 3258688.3 | AS60: 1849347.7 | AT60: 3428364.4 | AU60: 1717572.2 | AV60: 3028529.7 | AW60: 430560.73 | AX60: 605611.37 | AY60: 25206.277 | AZ60: 0 | BA60: 0 | BB60: 0 | BC60: 0 | BD60: 0 | BE60: 0 | BF60: 0 | BG60: 0 | BH60: 0 | BI60: 45299637

Sheet BEA Use 2017
A1: The Use Table (Supply-Use Framework), 2017
A2: [Millions of dollars]
A3: Bureau of Economic Analysis
A5: Commodities/Industries | C5: Oilseed farming | D5: Grain farming | E5: Vegetable and melon farming | F5: Fruit and tree nut farming | G5: Greenhouse, nursery, and floriculture production | H5: Other crop farming | I5: Dairy cattle and milk production | J5: Beef cattle ranching and farming, including feedlots and dual-purpose ranching and farming | K5: Poultry and egg production | L5: Animal production, except cattle and poultry and eggs | M5: Forestry and logging | N5: Fishing, hunting and trapping | O5: Support activities for agriculture and forestry | P5: Oil and gas extraction | Q5: Coal mining | R5: Copper, nickel, lead, and zinc mining | S5: Iron, gold, silver, and other metal ore mining | T5: Stone mining and quarrying | U5: Other nonmetallic mineral mining and quarrying | V5: Drilling oil and gas wells | W5: Other support activities for mining | X5: Electric power generation, transmission, and distribution | Y5: Natural gas distribution | Z5: Water, sewage and other systems | AA5: Health care structures | AB5: Educational and vocational structures | AC5: Nonresidential maintenance and repair | AD5: Residential maintenance and repair | AE5: Office and commercial structures | AF5: Multifamily residential structures | AG5: Other residential structures | AH5: Manufacturing structures | AI5: Other nonresidential structures | AJ5: Power and communication structures | AK5: Single-family residential structures | AL5: Transportation structures and highways and streets | AM5: Sawmills and wood preservation | AN5: Veneer, plywood, and engineered wood product manufacturing | AO5: Millwork | AP5: All other wood product manufacturing | AQ5: Clay product and refractory manufacturing | AR5: Glass and glass product manufacturing | AS5: Cement manufacturing | AT5: Ready-mix concrete manufacturing | AU5: Concrete pipe, brick, and block manufacturing | AV5: Other concrete product manufacturing | AW5: Lime and gypsum product manufacturing | AX5: Abrasive product manufacturing | AY5: Cut stone and stone product manufacturing | AZ5: Ground or treated mineral and earth manufacturing | BA5: Mineral wool manufacturing | BB5: Miscellaneous nonmetallic mineral products | BC5: Iron and steel mills and ferroalloy manufacturing | BD5: Steel product manufacturing from purchased steel | BE5: Secondary smelting and alloying of aluminum | BF5: Alumina refining and primary aluminum production | BG5: Aluminum product manufacturing from purchased aluminum | BH5: Nonferrous metal (except aluminum) smelting and refining | BI5: Copper rolling, drawing, extruding and alloying | BJ5: Nonferrous metal (except copper and aluminum) rolling, drawing, extruding and alloying | BK5: Ferrous metal foundries | BL5: Nonferrous metal foundries | BM5: Custom roll forming | BN5: All other forging, stamping, and sintering | BO5: Metal crown, closure, and other metal stamping (except automotive) | BP5: Cutlery and handtool manufacturing | BQ5: Plate work and fabricated structural product manufacturing | BR5: Ornamental and architectural metal products manufacturing | BS5: Power boiler and heat exchanger manufacturing | BT5: Metal tank (heavy gauge) manufacturing | BU5: Metal can, box, and other metal container (light gauge) manufacturing | BV5: Hardware manufacturing | BW5: Spring and wire product manufacturing | BX5: Machine shops | BY5: Turned product and screw, nut, and bolt manufacturing | BZ5: Coating, engraving, heat treating and allied activities | CA5: Plumbing fixture fitting and trim manufacturing | CB5: Valve and fittings other than plumbing | CC5: Ball and roller bearing manufacturing | CD5: Fabricated pipe and pipe fitting manufacturing | CE5: Ammunition, arms, ordnance, and accessories manufacturing | CF5: Other fabricated metal manufacturing | CG5: Farm machinery and equipment manufacturing | CH5: Lawn and garden equipment manufacturing | CI5: Construction machinery manufacturing | CJ5: Mining and oil and gas field machinery manufacturing | CK5: Semiconductor machinery manufacturing | CL5: Other industrial machinery manufacturing | CM5: Optical instrument and lens manufacturing | CN5: Photographic and photocopying equipment manufacturing | CO5: Other commercial and service industry machinery manufacturing | CP5: Heating equipment (except warm air furnaces) manufacturing | CQ5: Air conditioning, refrigeration, and warm air heating equipment manufacturing | CR5: Industrial and commercial fan and blower and air purification equipment manufacturing | CS5: Industrial mold manufacturing | CT5: Special tool, die, jig, and fixture manufacturing | CU5: Machine tool manufacturing | CV5: Cutting and machine tool accessory, rolling mill, and other metalworking machinery manufacturing | CW5: Turbine and turbine generator set units manufacturing | CX5: Speed changer, industrial high-speed drive, and gear manufacturing | CY5: Mechanical power transmission equipment manufacturing | CZ5: Other engine equipment manufacturing | DA5: Air and gas compressor manufacturing | DB5: Measuring, dispensing, and other pumping equipment manufacturing | DC5: Material handling equipment manufacturing | DD5: Power-driven handtool manufacturing | DE5: Packaging machinery manufacturing | DF5: Industrial process furnace and oven manufacturing | DG5: Other general purpose machinery manufacturing | DH5: Fluid power process machinery | DI5: Electronic computer manufacturing | DJ5: Computer storage device manufacturing | DK5: Computer terminals and other computer peripheral equipment manufacturing | DL5: Telephone apparatus manufacturing | DM5: Broadcast and wireless communications equipment | DN5: Other communications equipment manufacturing | DO5: Semiconductor and related device manufacturing | DP5: Printed circuit assembly (electronic assembly) manufacturing | DQ5: Other electronic component manufacturing | DR5: Electromedical and electrotherapeutic apparatus manufacturing | DS5: Search, detection, and navigation instruments manufacturing | DT5: Automatic environmental control manufacturing | DU5: Industrial process variable instruments manufacturing | DV5: Totalizing fluid meter and counting device manufacturing | DW5: Electricity and signal testing instruments manufacturing | DX5: Analytical laboratory instrument manufacturing | DY5: Irradiation apparatus manufacturing | DZ5: Watch, clock, and other measuring and controlling device manufacturing | EA5: Audio and video equipment manufacturing | EB5: Manufacturing and reproducing magnetic and optical media | EC5: Electric lamp bulb and part manufacturing | ED5: Lighting fixture manufacturing | EE5: Small electrical appliance manufacturing | EF5: Major household appliance manufacturing | EG5: Power, distribution, and specialty transformer manufacturing | EH5: Motor and generator manufacturing | EI5: Switchgear and switchboard apparatus manufacturing | EJ5: Relay and industrial control manufacturing | EK5: Storage battery manufacturing | EL5: Primary battery manufacturing | EM5: Communication and energy wire and cable manufacturing | EN5: Wiring device manufacturing | EO5: Carbon and graphite product manufacturing | EP5: All other miscellaneous electrical equipment and component manufacturing | EQ5: Automobile manufacturing | ER5: Light truck and utility vehicle manufacturing | ES5: Heavy duty truck manufacturing | ET5: Motor vehicle body manufacturing | EU5: Truck trailer manufacturing | EV5: Motor home manufacturing | EW5: Travel trailer and camper manufacturing | EX5: Motor vehicle gasoline engine and engine parts manufacturing | EY5: Motor vehicle electrical and electronic equipment manufacturing | EZ5: Motor vehicle transmission and power train parts manufacturing | FA5: Motor vehicle seating and interior trim manufacturing | FB5: Motor vehicle metal stamping | FC5: Other motor vehicle parts manufacturing | FD5: Motor vehicle steering, suspension component (except spring), and brake systems manufacturing | FE5: Aircraft manufacturing | FF5: Aircraft engine and engine parts manufacturing | FG5: Other aircraft parts and auxiliary equipment manufacturing | FH5: Guided missile and space vehicle manufacturing | FI5: Propulsion units and parts for space vehicles and guided missiles | FJ5: Railroad rolling stock manufacturing | FK5: Ship building and repairing | FL5: Boat building | FM5: Motorcycle, bicycle, and parts manufacturing | FN5: Military armored vehicle, tank, and tank component manufacturing | FO5: All other transportation equipment manufacturing | FP5: Wood kitchen cabinet and countertop manufacturing | FQ5: Upholstered household furniture manufacturing | FR5: Nonupholstered wood household furniture manufacturing | FS5: Institutional furniture manufacturing | FT5: Other household nonupholstered furniture | FU5: Showcase, partition, shelving, and locker manufacturing | FV5: Office furniture and custom architectural woodwork and millwork manufacturing | FW5: Other furniture related product manufacturing | FX5: Surgical and medical instrument manufacturing | FY5: Surgical appliance and supplies manufacturing | FZ5: Dental equipment and supplies manufacturing | GA5: Ophthalmic goods manufacturing | GB5: Dental laboratories | GC5: Jewelry and silverware manufacturing | GD5: Sporting and athletic goods manufacturing | GE5: Doll, toy, and game manufacturing | GF5: Office supplies (except paper) manufacturing | GG5: Sign manufacturing | GH5: All other miscellaneous manufacturing | GI5: Dog and cat food manufacturing | GJ5: Other animal food manufacturing | GK5: Flour milling and malt manufacturing | GL5: Wet corn milling | GM5: Fats and oils refining and blending | GN5: Soybean and other oilseed processing | GO5: Breakfast cereal manufacturing | GP5: Sugar and confectionery product manufacturing | GQ5: Frozen food manufacturing | GR5: Fruit and vegetable canning, pickling, and drying | GS5: Cheese manufacturing | GT5: Dry, condensed, and evaporated dairy product manufacturing | GU5: Fluid milk and butter manufacturing | GV5: Ice cream and frozen dessert manufacturing | GW5: Poultry processing | GX5: Animal (except poultry) slaughtering, rendering, and processing | GY5: Seafood product preparation and packaging | GZ5: Bread and bakery product manufacturing | HA5: Cookie, cracker, pasta, and tortilla manufacturing | HB5: Snack food manufacturing | HC5: Coffee and tea manufacturing | HD5: Flavoring syrup and concentrate manufacturing | HE5: Seasoning and dressing manufacturing | HF5: All other food manufacturing | HG5: Soft drink and ice manufacturing | HH5: Breweries | HI5: Wineries | HJ5: Distilleries | HK5: Tobacco manufacturing | HL5: Fiber, yarn, and thread mills | HM5: Fabric mills | HN5: Textile and fabric finishing and fabric coating mills | HO5: Carpet and rug mills | HP5: Curtain and linen mills | HQ5: Other textile product mills | HR5: Apparel manufacturing | HS5: Leather and allied product manufacturing | HT5: Pulp mills | HU5: Paper mills | HV5: Paperboard mills | HW5: Paperboard container manufacturing | HX5: Paper bag and coated and treated paper manufacturing | HY5: Stationery product manufacturing | HZ5: Sanitary paper product manufacturing | IA5: All other converted paper product manufacturing | IB5: Printing | IC5: Support activities for printing | ID5: Petroleum refineries | IE5: Asphalt paving mixture and block manufacturing | IF5: Asphalt shingle and coating materials manufacturing | IG5: Other petroleum and coal products manufacturing | IH5: Petrochemical manufacturing | II5: Industrial gas manufacturing | IJ5: Synthetic dye and pigment manufacturing | IK5: Other basic inorganic chemical manufacturing | IL5: Other basic organic chemical manufacturing | IM5: Plastics material and resin manufacturing | IN5: Synthetic rubber and artificial and synthetic fibers and filaments manufacturing | IO5: Medicinal and botanical manufacturing | IP5: Pharmaceutical preparation manufacturing | IQ5: In-vitro diagnostic substance manufacturing | IR5: Biological product (except diagnostic) manufacturing | IS5: Fertilizer manufacturing | IT5: Pesticide and other agricultural chemical manufacturing | IU5: Paint and coating manufacturing | IV5: Adhesive manufacturing | IW5: Soap and cleaning compound manufacturing | IX5: Toilet preparation manufacturing | IY5: Printing ink manufacturing | IZ5: All other chemical product and preparation manufacturing | JA5: Plastics packaging materials and unlaminated film and sheet manufacturing | JB5: Plastics pipe, pipe fitting, and unlaminated profile shape manufacturing | JC5: Laminated plastics plate, sheet (except packaging), and shape manufacturing | JD5: Polystyrene foam product manufacturing | JE5: Urethane and other foam product (except polystyrene) manufacturing | JF5: Plastics bottle manufacturing | JG5: Other plastics product manufacturing | JH5: Tire manufacturing | JI5: Rubber and plastics hoses and belting manufacturing | JJ5: Other rubber product manufacturing | JK5: Motor vehicle and motor vehicle parts and supplies | JL5: Professional and commercial equipment and supplies | JM5: Household appliances and electrical and electronic goods | JN5: Machinery, equipment, and supplies | JO5: Other durable goods merchant wholesalers | JP5: Drugs and druggists’ sundries | JQ5: Grocery and related product wholesalers | JR5: Petroleum and petroleum products | JS5: Other nondurable goods merchant wholesalers | JT5: Wholesale electronic markets and agents and brokers | JU5: Customs duties | JV5: Motor vehicle and parts dealers | JW5: Food and beverage stores | JX5: General merchandise stores | JY5: Building material and garden equipment and supplies dealers | JZ5: Health and personal care stores | KA5: Gasoline stations | KB5: Clothing and clothing accessories stores | KC5: Nonstore retailers | KD5: All other retail | KE5: Air transportation | KF5: Rail transportation | KG5: Water transportation | KH5: Truck transportation | KI5: Transit and ground passenger transportation | KJ5: Pipeline transportation | KK5: Scenic and sightseeing transportation and support activities for transportation | KL5: Couriers and messengers | KM5: Warehousing and storage | KN5: Newspaper publishers | KO5: Periodical Publishers | KP5: Book publishers | KQ5: Directory, mailing list, and other publishers | KR5: Software publishers | KS5: Motion picture and video industries | KT5: Sound recording industries | KU5: Radio and television broadcasting | KV5: Cable and other subscription programming | KW5: Wired telecommunications carriers | KX5: Wireless telecommunications carriers (except satellite) | KY5: Satellite, telecommunications resellers, and all other telecommunications | KZ5: Data processing, hosting, and related services | LA5: Internet publishing and broadcasting and Web search portals | LB5: News syndicates, libraries, archives and all other information services | LC5: Nondepository credit intermediation and related activities | LD5: Monetary authorities and depository credit intermediation | LE5: Other financial investment activities | LF5: Securities and commodity contracts intermediation and brokerage | LG5: Direct life insurance carriers | LH5: Insurance carriers, except direct life | LI5: Insurance agencies, brokerages, and related activities | LJ5: Funds, trusts, and other financial vehicles | LK5: Owner-occupied housing | LL5: Tenant-occupied housing | LM5: Other real estate | LN5: Automotive equipment rental and leasing | LO5: Commercial and industrial machinery and equipment rental and leasing | LP5: General and consumer goods rental | LQ5: Lessors of nonfinancial intangible assets | LR5: Legal services | LS5: Custom computer programming services | LT5: Computer systems design services | LU5: Other computer related services, including facilities management | LV5: Accounting, tax preparation, bookkeeping, and payroll services | LW5: Architectural, engineering, and related services | LX5: Management consulting services | LY5: Environmental and other technical consulting services | LZ5: Scientific research and development services | MA5: Advertising, public relations, and related services | MB5: Specialized design services | MC5: Photographic services | MD5: Veterinary services | ME5: All other miscellaneous professional, scientific, and technical services | MF5: Management of companies and enterprises | MG5: Employment services | MH5: Services to buildings and dwellings | MI5: Office administrative services | MJ5: Facilities support services | MK5: Business support services | ML5: Travel arrangement and reservation services | MM5: Investigation and security services | MN5: Other support services | MO5: Waste management and remediation services | MP5: Elementary and secondary schools | MQ5: Junior colleges, colleges, universities, and professional schools | MR5: Other educational services | MS5: Offices of physicians | MT5: Offices of dentists | MU5: Offices of other health practitioners | MV5: Outpatient care centers | MW5: Medical and diagnostic laboratories | MX5: Home health care services | MY5: Other ambulatory health care services | MZ5: Hospitals | NA5: Nursing and community care facilities | NB5: Residential mental health, substance abuse, and other residential care facilities | NC5: Individual and family services | ND5: Child day care services | NE5: Community food, housing, and other relief services, including rehabilitation services | NF5: Performing arts companies | NG5: Spectator sports | NH5: Independent artists, writers, and performers | NI5: Promoters of performing arts and sports and agents for public figures | NJ5: Museums, historical sites, zoos, and parks | NK5: Amusement parks and arcades | NL5: Gambling industries (except casino hotels) | NM5: Other amusement and recreation industries | NN5: Accommodation | NO5: Full-service restaurants | NP5: Limited-service restaurants | NQ5: All other food and drinking places | NR5: Automotive repair and maintenance (including car washes) | NS5: Electronic and precision equipment repair and maintenance | NT5: Commercial and industrial machinery and equipment repair and maintenance | NU5: Personal and household goods repair and maintenance | NV5: Personal care services | NW5: Death care services | NX5: Dry-cleaning and laundry services | NY5: Other personal services | NZ5: Religious organizations | OA5: Grantmaking, giving, and social advocacy organizations | OB5: Civic, social, professional, and similar organizations | OC5: Private households | OD5: Federal general government (defense) | OE5: Federal general government (nondefense) | OF5: Postal service | OG5: Federal electric utilities | OH5: Other federal government enterprises | OI5: State and local government (educational services) | OJ5: State and local government (hospitals and health services) | OK5: State and local government (other services) | OL5: State and local government passenger transit | OM5: State and local government electric utilities | ON5: Other state and local government enterprises | OO5: Total Intermediate | OP5: Personal consumption expenditures | OQ5: Nonresidential private fixed investment in equipment | OR5: Nonresidential private fixed investment in intellectual property products | OS5: Residential private fixed investment | OT5: Nonresidential private fixed investment in structures | OU5: Change in private inventories | OV5: Exports of goods and services | OW5: Federal Government defense: Consumption expenditures | OX5: Federal national defense: Gross investment in equipment | OY5: Federal national defense: Gross investment in intellectual property products | OZ5: Federal national defense: Gross investment in structures | PA5: Federal Government nondefense: Consumption expenditures | PB5: Federal nondefense: Gross investment in equipment | PC5: Federal nondefense: Gross investment in intellectual property products | PD5: Federal nondefense: Gross investment in structures | PE5: State and local government consumption expenditures | PF5: State and local: Gross investment in equipment | PG5: State and local: Gross investment in intellectual property products | PH5: State and local: Gross investment in structures | PI5: Total use of products
A6: Code | B6: Commodity Description | C6: 1111A0 | D6: 1111B0 | E6: 111200 | F6: 111300 | G6: 111400 | H6: 111900 | I6: 112120 | J6: 1121A0 | K6: 112300 | L6: 112A00 | M6: 113000 | N6: 114000 | O6: 115000 | P6: 211000 | Q6: 212100 | R6: 212230 | S6: 2122A0 | T6: 212310 | U6: 2123A0 | V6: 213111 | W6: 21311A | X6: 221100 | Y6: 221200 | Z6: 221300 | AA6: 233210 | AB6: 233262 | AC6: 230301 | AD6: 230302 | AE6: 2332A0 | AF6: 233412 | AG6: 2334A0 | AH6: 233230 | AI6: 2332D0 | AJ6: 233240 | AK6: 233411 | AL6: 2332C0 | AM6: 321100 | AN6: 321200 | AO6: 321910 | AP6: 3219A0 | AQ6: 327100 | AR6: 327200 | AS6: 327310 | AT6: 327320 | AU6: 327330 | AV6: 327390 | AW6: 327400 | AX6: 327910 | AY6: 327991 | AZ6: 327992 | BA6: 327993 | BB6: 327999 | BC6: 331110 | BD6: 331200 | BE6: 331314 | BF6: 331313 | BG6: 33131B | BH6: 331410 | BI6: 331420 | BJ6: 331490 | BK6: 331510 | BL6: 331520 | BM6: 332114 | BN6: 33211A | BO6: 332119 | BP6: 332200 | BQ6: 332310 | BR6: 332320 | BS6: 332410 | BT6: 332420 | BU6: 332430 | BV6: 332500 | BW6: 332600 | BX6: 332710 | BY6: 332720 | BZ6: 332800 | CA6: 332913 | CB6: 33291A | CC6: 332991 | CD6: 332996 | CE6: 33299A | CF6: 332999 | CG6: 333111 | CH6: 333112 | CI6: 333120 | CJ6: 333130 | CK6: 333242 | CL6: 33329A | CM6: 333314 | CN6: 333316 | CO6: 333318 | CP6: 333414 | CQ6: 333415 | CR6: 333413 | CS6: 333511 | CT6: 333514 | CU6: 333517 | CV6: 33351B | CW6: 333611 | CX6: 333612 | CY6: 333613 | CZ6: 333618 | DA6: 333912 | DB6: 333914 | DC6: 333920 | DD6: 333991 | DE6: 333993 | DF6: 333994 | DG6: 33399A | DH6: 33399B | DI6: 334111 | DJ6: 334112 | DK6: 334118 | DL6: 334210 | DM6: 334220 | DN6: 334290 | DO6: 334413 | DP6: 334418 | DQ6: 33441A | DR6: 334510 | DS6: 334511 | DT6: 334512 | DU6: 334513 | DV6: 334514 | DW6: 334515 | DX6: 334516 | DY6: 334517 | DZ6: 33451A | EA6: 334300 | EB6: 334610 | EC6: 335110 | ED6: 335120 | EE6: 335210 | EF6: 335220 | EG6: 335311 | EH6: 335312 | EI6: 335313 | EJ6: 335314 | EK6: 335911 | EL6: 335912 | EM6: 335920 | EN6: 335930 | EO6: 335991 | EP6: 335999 | EQ6: 336111 | ER6: 336112 | ES6: 336120 | ET6: 336211 | EU6: 336212 | EV6: 336213 | EW6: 336214 | EX6: 336310 | EY6: 336320 | EZ6: 336350 | FA6: 336360 | FB6: 336370 | FC6: 336390 | FD6: 3363A0 | FE6: 336411 | FF6: 336412 | FG6: 336413 | FH6: 336414 | FI6: 33641A | FJ6: 336500 | FK6: 336611 | FL6: 336612 | FM6: 336991 | FN6: 336992 | FO6: 336999 | FP6: 337110 | FQ6: 337121 | FR6: 337122 | FS6: 337127 | FT6: 33712N | FU6: 337215 | FV6: 33721A | FW6: 337900 | FX6: 339112 | FY6: 339113 | FZ6: 339114 | GA6: 339115 | GB6: 339116 | GC6: 339910 | GD6: 339920 | GE6: 339930 | GF6: 339940 | GG6: 339950 | GH6: 339990 | GI6: 311111 | GJ6: 311119 | GK6: 311210 | GL6: 311221 | GM6: 311225 | GN6: 311224 | GO6: 311230 | GP6: 311300 | GQ6: 311410 | GR6: 311420 | GS6: 311513 | GT6: 311514 | GU6: 31151A | GV6: 311520 | GW6: 311615 | GX6: 31161A | GY6: 311700 | GZ6: 311810 | HA6: 3118A0 | HB6: 311910 | HC6: 311920 | HD6: 311930 | HE6: 311940 | HF6: 311990 | HG6: 312110 | HH6: 312120 | HI6: 312130 | HJ6: 312140 | HK6: 312200 | HL6: 313100 | HM6: 313200 | HN6: 313300 | HO6: 314110 | HP6: 314120 | HQ6: 314900 | HR6: 315000 | HS6: 316000 | HT6: 322110 | HU6: 322120 | HV6: 322130 | HW6: 322210 | HX6: 322220 | HY6: 322230 | HZ6: 322291 | IA6: 322299 | IB6: 323110 | IC6: 323120 | ID6: 324110 | IE6: 324121 | IF6: 324122 | IG6: 324190 | IH6: 325110 | II6: 325120 | IJ6: 325130 | IK6: 325180 | IL6: 325190 | IM6: 325211 | IN6: 3252A0 | IO6: 325411 | IP6: 325412 | IQ6: 325413 | IR6: 325414 | IS6: 325310 | IT6: 325320 | IU6: 325510 | IV6: 325520 | IW6: 325610 | IX6: 325620 | IY6: 325910 | IZ6: 3259A0 | JA6: 326110 | JB6: 326120 | JC6: 326130 | JD6: 326140 | JE6: 326150 | JF6: 326160 | JG6: 326190 | JH6: 326210 | JI6: 326220 | JJ6: 326290 | JK6: 423100 | JL6: 423400 | JM6: 423600 | JN6: 423800 | JO6: 423A00 | JP6: 424200 | JQ6: 424400 | JR6: 424700 | JS6: 424A00 | JT6: 425000 | JU6: 4200ID | JV6: 441000 | JW6: 445000 | JX6: 452000 | JY6: 444000 | JZ6: 446000 | KA6: 447000 | KB6: 448000 | KC6: 454000 | KD6: 4B0000 | KE6: 481000 | KF6: 482000 | KG6: 483000 | KH6: 484000 | KI6: 485000 | KJ6: 486000 | KK6: 48A000 | KL6: 492000 | KM6: 493000 | KN6: 511110 | KO6: 511120 | KP6: 511130 | KQ6: 5111A0 | KR6: 511200 | KS6: 512100 | KT6: 512200 | KU6: 515100 | KV6: 515200 | KW6: 517110 | KX6: 517210 | KY6: 517A00 | KZ6: 518200 | LA6: 519130 | LB6: 5191A0 | LC6: 522A00 | LD6: 52A000 | LE6: 523900 | LF6: 523A00 | LG6: 524113 | LH6: 5241XX | LI6: 524200 | LJ6: 525000 | LK6: 531HSO | LL6: 531HST | LM6: 531ORE | LN6: 532100 | LO6: 532400 | LP6: 532A00 | LQ6: 533000 | LR6: 541100 | LS6: 541511 | LT6: 541512 | LU6: 54151A | LV6: 541200 | LW6: 541300 | LX6: 541610 | LY6: 5416A0 | LZ6: 541700 | MA6: 541800 | MB6: 541400 | MC6: 541920 | MD6: 541940 | ME6: 5419A0 | MF6: 550000 | MG6: 561300 | MH6: 561700 | MI6: 561100 | MJ6: 561200 | MK6: 561400 | ML6: 561500 | MM6: 561600 | MN6: 561900 | MO6: 562000 | MP6: 611100 | MQ6: 611A00 | MR6: 611B00 | MS6: 621100 | MT6: 621200 | MU6: 621300 | MV6: 621400 | MW6: 621500 | MX6: 621600 | MY6: 621900 | MZ6: 622000 | NA6: 623A00 | NB6: 623B00 | NC6: 624100 | ND6: 624400 | NE6: 624A00 | NF6: 711100 | NG6: 711200 | NH6: 711500 | NI6: 711A00 | NJ6: 712000 | NK6: 713100 | NL6: 713200 | NM6: 713900 | NN6: 721000 | NO6: 722110 | NP6: 722211 | NQ6: 722A00 | NR6: 811100 | NS6: 811200 | NT6: 811300 | NU6: 811400 | NV6: 812100 | NW6: 812200 | NX6: 812300 | NY6: 812900 | NZ6: 813100 | OA6: 813A00 | OB6: 813B00 | OC6: 814000 | OD6: S00500 | OE6: S00600 | OF6: 491000 | OG6: S00101 | OH6: S00102 | OI6: GSLGE | OJ6: GSLGH | OK6: GSLGO | OL6: S00201 | OM6: S00202 | ON6: S00203 | OO6: T001 | OP6: F01000 | OQ6: F02E00 | OR6: F02N00 | OS6: F02R00 | OT6: F02S00 | OU6: F03000 | OV6: F04000 | OW6: F06C00 | OX6: F06E00 | OY6: F06N00 | OZ6: F06S00 | PA6: F07C00 | PB6: F07E00 | PC6: F07N00 | PD6: F07S00 | PE6: F10C00 | PF6: F10E00 | PG6: F10N00 | PH6: F10S00 | PI6: T019 | PM6: EPS ISIC (commodity)
A7: 1111A0 | B7: Oilseed farming | C7: 12160 | D7: 665 | E7: 59 | H7: 4 | GL7: 1207 | GM7: 913 | GN7: 24360 | HB7: 328 | HD7: 13 | HE7: 12 | HF7: 13 | IH7: 4 | II7: 0 | IJ7: 0 | IL7: 1421 | IO7: 28 | IP7: 0 | IQ7: 0 | IR7: 3 | OE7: -240 | OO7: 40949 | OU7: -1032 | OV7: 21287 | PI7: 61204 | PM7: =IFERROR(VLOOKUP($A7&"",Key!$A:$C,3,FALSE),"") -> ISIC 01
A8: 1111B0 | B8: Grain farming | D8: 11802 | H8: 692 | I8: 2579 | J8: 6513 | K8: 2436 | L8: 267 | GI8: 1888 | GJ8: 10292 | GK8: 10083 | GL8: 4774 | GM8: 142 | GN8: 10 | GO8: 383 | GQ8: 4174 | GR8: 213 | GT8: 3 | GV8: 6 | GZ8: 1948 | HA8: 746 | HB8: 1392 | HF8: 1306 | HH8: 921 | HJ8: 241 | II8: 38 | IL8: 11805 | JQ8: 0 | JR8: 0 | JS8: 0 | JW8: 643 | JX8: 154 | KC8: 0 | LZ8: 204 | MF8: 5 | MP8: 2 | MQ8: 25 | NN8: 11 | NO8: 0 | NP8: 1 | OE8: -32 | OI8: 144 | OJ8: 0 | OK8: 138 | OO8: 75948 | OP8: 4939 | OU8: -1547 | OV8: 16940 | PI8: 96281 | PM8: =IFERROR(VLOOKUP($A8&"",Key!$A:$C,3,FALSE),"") -> ISIC 01
A9: 111200 | B9: Vegetable and melon farming | E9: 962 | F9: 3 | GQ9: 1860 | GR9: 188 | GT9: 5 | HA9: 12 | HB9: 1028 | HD9: 37 | HE9: 144 | HF9: 2922 | JW9: 12 | KA9: 20 | KK9: 12 | MP9: 10 | MQ9: 27 | NM9: 1 | NN9: 4 | NO9: 135 | NP9: 165 | NQ9: 25 | NZ9: 2 | OB9: 2 | OI9: 96 | OJ9: 49 | OK9: 36 | OO9: 7756 | OP9: 39518 | OU9: -585 | OV9: 3649 | PI9: 50338 | PM9: =IFERROR(VLOOKUP($A9&"",Key!$A:$C,3,FALSE),"") -> ISIC 01
A10: 111300 | B10: Fruit and tree nut farming | F10: 1037 | GO10: 102 | GP10: 1438 | GQ10: 1733 | GR10: 3163 | GT10: 22 | GV10: 35 | GZ10: 192 | HA10: 177 | HB10: 2715 | HC10: 4156 | HD10: 43 | HE10: 1130 | HF10: 4696 | HI10: 5595 | HJ10: 4 | KK10: 32 | LZ10: 2 | MP10: 14 | MQ10: 116 | NM10: 5 | NN10: 16 | NO10: 122 | NP10: 132 | NQ10: 154 | NZ10: 8 | OI10: 185 | OJ10: 165 | OK10: 142 | OO10: 27330 | OP10: 48125 | OU10: -676 | OV10: 7907 | PI10: 82686 | PM10: =IFERROR(VLOOKUP($A10&"",Key!$A:$C,3,FALSE),"") -> ISIC 01
A11: 111400 | B11: Greenhouse, nursery, and floriculture production | G11: 3604 | O11: 134 | AD11: 36 | AG11: 163 | AK11: 72 | GH11: 222 | GR11: 1 | HB11: 159 | HF11: 311 | IL11: 2688 | JL11: 1 | JQ11: 2 | JR11: 2 | JS11: 49 | JT11: 1 | JV11: 744 | JW11: 312 | KA11: 346 | KD11: 23 | LD11: 1 | LK11: 0 | LL11: 0 | LM11: 7 | LR11: 2 | LU11: 1 | LV11: 13 | LW11: 18 | LX11: 10 | MA11: 29 | MH11: 1473 | MI11: 1 | MK11: 1 | MN11: 1 | MP11: 0 | MQ11: 1 | NK11: 9 | NL11: 14 | NM11: 6 | NN11: 0 | NZ11: 9 | OB11: 4 | OI11: 5 | OK11: 1406 | OO11: 11879 | OP11: 31499 | OU11: 119 | OV11: 995 | PI11: 44491 | PM11: =IFERROR(VLOOKUP($A11&"",Key!$A:$C,3,FALSE),"") -> ISIC 01
A12: 111900 | B12: Other crop farming | C12: 197 | D12: 797 | G12: 0 | H12: 1190 | I12: 535 | J12: 612 | L12: 29 | Q12: 5 | R12: 1 | S12: 8 | T12: 3 | U12: 8 | V12: 6 | W12: 14 | AA12: 17 | AB12: 16 | AC12: 118 | AD12: 515 | AE12: 58 | AF12: 16 | AG12: 416 | AH12: 14 | AI12: 46 | AJ12: 30 | AK12: 167 | AL12: 32 | GM12: 73 | GN12: 273 | GO12: 1 | GP12: 2750 | GV12: 3 | HA12: 8 | HB12: 3125 | HC12: 1149 | HD12: 65 | HE12: 1578 | HF12: 14 | HH12: 633 | HK12: 2156 | HL12: 1928 | HM12: 300 | II12: 52 | IJ12: 0 | IL12: 4699 | IO12: 30 | JX12: 17 | KD12: 0 | LZ12: 47 | MF12: 1 | MH12: 77 | MP12: 1 | MQ12: 1 | NK12: 3 | NM12: 19 | OE12: 252 | OI12: 21 | OK12: 320 | OO12: 24449 | OP12: 7475 | OU12: -754 | OV12: 7368 | PI12: 38538 | PM12: =IFERROR(VLOOKUP($A12&"",Key!$A:$C,3,FALSE),"") -> ISIC 01
A13: 112120 | B13: Dairy cattle and milk production | L13: 10 | GS13: 19471 | GT13: 5497 | GU13: 19215 | GV13: 591 | HF13: 813 | LZ13: 10 | MP13: 3 | MQ13: 3 | OI13: 18 | OO13: 45632 | OP13: 165 | OU13: 122 | OV13: 70 | PI13: 45989 | PM13: =IFERROR(VLOOKUP($A13&"",Key!$A:$C,3,FALSE),"") -> ISIC 01
A14: 1121A0 | B14: Beef cattle ranching and farming, including feedlots and dual-purpose ranching and farming | C14: 37 | D14: 245 | E14: 20 | F14: 84 | G14: 22 | H14: 29 | I14: 3088 | J14: 36030 | L14: 724 | O14: 42 | GX14: 58747 | JQ14: 576 | LZ14: 303 | MF14: 10 | OO14: 99956 | OP14: 97 | OU14: 1214 | OV14: 192 | PI14: 101458 | PM14: =IFERROR(VLOOKUP($A14&"",Key!$A:$C,3,FALSE),"") -> ISIC 01
A15: 112300 | B15: Poultry and egg production | C15: 12 | H15: 5 | K15: 10227 | GI15: 1 | GP15: 52 | GQ15: 146 | GR15: 31 | GV15: 188 | GW15: 30467 | GZ15: 347 | HA15: 393 | HE15: 455 | HF15: 370 | JQ15: 1 | JW15: 114 | JX15: 27 | LZ15: 7 | MP15: 1 | MQ15: 48 | NN15: 19 | NO15: 34 | NP15: 71 | OB15: 1 | OI15: 22 | OJ15: 131 | OK15: 244 | OO15: 43415 | OP15: 8774 | OU15: 357 | OV15: 778 | PI15: 53324 | PM15: =IFERROR(VLOOKUP($A15&"",Key!$A:$C,3,FALSE),"") -> ISIC 01
A16: 112A00 | B16: Animal production, except cattle and poultry and eggs | C16: 20 | D16: 163 | E16: 10 | F16: 44 | G16: 10 | H16: 59 | I16: 334 | J16: 542 | L16: 2961 | M16: 0 | O16: 438 | GH16: 14 | GW16: 184 | GX16: 24168 | GY16: 407 | GZ16: 2 | HA16: 2 | HB16: 60 | HD16: 21 | HE16: 153 | HF16: 1114 | HG16: 3 | HL16: 102 | HM16: 173 | HQ16: 80 | JQ16: 230 | JX16: 3 | KK16: 17 | LZ16: 659 | MF16: 19 | MM16: 12 | MQ16: 3 | NK16: 72 | NL16: 57 | NM16: 301 | NN16: 4 | NO16: 1020 | NP16: 1907 | NQ16: 356 | OD16: 14 | OK16: 106 | OO16: 35842 | OP16: 12574 | OU16: 474 | OV16: 1522 | PI16: 50413 | PM16: =IFERROR(VLOOKUP($A16&"",Key!$A:$C,3,FALSE),"") -> ISIC 01
A17: 113000 | B17: Forestry and logging | M17: 4822 | O17: 4 | Q17: 101 | AM17: 10990 | AN17: 2288 | AO17: 1342 | AP17: 606 | BB17: 1 | FT17: 122 | GD17: 109 | GH17: 187 | GP17: 57 | HB17: 17 | HD17: 682 | HE17: 54 | HF17: 37 | HG17: 140 | HR17: 58 | HS17: 6 | HT17: 677 | HU17: 772 | HV17: 2393 | IC17: 30 | IH17: 1 | IL17: 276 | IN17: 9 | IT17: 35 | IU17: 82 | IV17: 25 | IZ17: 7 | JH17: 1719 | JI17: 61 | JJ17: 615 | KB17: 0 | LZ17: 27 | MH17: 2 | MQ17: 4 | OI17: 42 | OK17: 125 | OO17: 28528 | OU17: 596 | OV17: 2551 | PI17: 31674 | PM17: =IFERROR(VLOOKUP($A17&"",Key!$A:$C,3,FALSE),"") -> ISIC 02
A18: 114000 | B18: Fishing, hunting and trapping | GI18: 16 | GJ18: 419 | GQ18: 97 | GR18: 420 | GW18: 192 | GX18: 1143 | GY18: 6285 | IS18: 17 | JW18: 818 | KK18: 1 | LZ18: 24 | MF18: 0 | MP18: 53 | MQ18: 16 | NK18: 29 | NL18: 26 | NM18: 186 | NN18: 443 | NO18: 2635 | NP18: 2559 | NQ18: 239 | NZ18: 34 | OB18: 96 | OH18: 18 | OI18: 59 | OJ18: 303 | OK18: 174 | OO18: 16304 | OP18: 8695 | OU18: 59 | OV18: 5391 | PI18: 30450 | PM18: =IFERROR(VLOOKUP($A18&"",Key!$A:$C,3,FALSE),"") -> ISIC 03
A19: 115000 | B19: Support activities for agriculture and forestry | C19: 1326 | D19: 8007 | E19: 2320 | F19: 3658 | G19: 1218 | H19: 3169 | I19: 1087 | J19: 913 | K19: 720 | L19: 497 | M19: 2963 | N19: 9 | LZ19: 245 | MF19: 21 | OE19: 51 | OK19: 3444 | OO19: 29649 | OP19: 124 | OV19: 86 | PI19: 29859 | PM19: =IFERROR(VLOOKUP($A19&"",Key!$A:$C,3,FALSE),"") -> ISIC 01
A20: 211000 | B20: Oil and gas extraction | P20: 21742 | S20: 0 | T20: 0 | U20: 0 | V20: 0 | W20: 4 | X20: 7017 | Y20: 5089 | Z20: 308 | AM20: 1 | AN20: 0 | AO20: 2 | AS20: 0 | BC20: 0 | BF20: 2 | BN20: 0 | BZ20: 0 | EQ20: 0 | GL20: 0 | GX20: 0 | GY20: 0 | HH20: 0 | HT20: 0 | HU20: 0 | HV20: 0 | IB20: 0 | ID20: 322173 | IG20: 1460 | IH20: 4463 | II20: 91 | IJ20: 5 | IK20: 231 | IL20: 699 | IM20: 10 | IN20: 5 | IO20: 0 | IP20: 3 | IQ20: 0 | IR20: 2 | IS20: 1 | IT20: 0 | IU20: 0 | IV20: 1 | IW20: 2 | IX20: 0 | IZ20: 52 | JA20: 0 | JD20: 0 | JG20: 0 | JH20: 0 | JJ20: 0 | JK20: 0 | JL20: 0 | JM20: 1 | JN20: 0 | JO20: 0 | JQ20: 0 | JR20: 0 | JS20: 1 | JT20: 0 | JV20: 4 | JW20: 0 | JX20: 1 | JY20: 4 | JZ20: 0 | KB20: 0 | KC20: 0 | KD20: 0 | KJ20: 7 | KM20: 80 | KN20: 0 | KO20: 0 | KP20: 2 | KQ20: 0 | KR20: 2 | KS20: 0 | KT20: 0 | KU20: 0 | KV20: 0 | KW20: 0 | KX20: 0 | KY20: 2 | KZ20: 1 | LA20: 6 | LB20: 0 | LM20: 35 | LS20: 0 | LV20: 2 | LW20: 1 | LX20: 0 | LZ20: 1 | MA20: 0 | MD20: 0 | MF20: 3 | MG20: 0 | MI20: 0 | MN20: 0 | MO20: 2 | MQ20: 7 | MR20: 189 | MS20: 1 | MT20: 0 | MU20: 0 | MV20: 0 | MW20: 0 | MX20: 0 | MY20: 0 | MZ20: 0 | NA20: 0 | NB20: 0 | NC20: 0 | ND20: 0 | NE20: 0 | NF20: 0 | NG20: 0 | NI20: 0 | NJ20: 0 | NK20: 0 | NL20: 1 | NM20: 22 | NN20: 0 | NO20: 0 | NP20: 0 | NQ20: 0 | NR20: 0 | NS20: 0 | NT20: 0 | NU20: 0 | NV20: 0 | NW20: 0 | NX20: 1 | NY20: 0 | OA20: 0 | OB20: 1 | OE20: 0 | OF20: 0 | OG20: 1910 | OH20: 0 | OM20: 20045 | ON20: 3340 | OO20: 389039 | OU20: -7577 | OV20: 41909 | PI20: 423371 | PM20: =IFERROR(VLOOKUP($A20&"",Key!$A:$C,3,FALSE),"") -> ISIC 06
A21: 212100 | B21: Coal mining | K21: 596 | M21: 0 | P21: 110 | Q21: 3167 | R21: 80 | S21: 42 | T21: 17 | U21: 66 | V21: 6 | W21: 17 | X21: 3973 | Z21: 0 | AM21: 6 | AN21: 5 | AO21: 3 | AP21: 4 | AQ21: 141 | AR21: 412 | AS21: 447 | AT21: 179 | AU21: 30 | AV21: 36 | AW21: 373 | AX21: 11 | AY21: 11 | AZ21: 65 | BA21: 72 | BB21: 34 | BC21: 2119 | BD21: 61 | BE21: 42 | BF21: 58 | BG21: 120 | BH21: 39 | BI21: 27 | BJ21: 43 | BK21: 60 | BL21: 68 | BN21: 2 | BQ21: 2 | BR21: 3 | BX21: 2 | BY21: 2 | BZ21: 4 | CB21: 1 | CD21: 1 | EC21: 0 | ED21: 2 | EF21: 0 | EG21: 0 | EI21: 1 | EK21: 3 | EN21: 2 | EO21: 1 | EP21: 1 | EQ21: 0 | ER21: 10 | ET21: 2 | EW21: 1 | EX21: 7 | EY21: 3 | EZ21: 5 | FB21: 6 | FC21: 7 | FD21: 4 | FE21: 6 | FF21: 14 | FI21: 6 | FJ21: 2 | FK21: 4 | FP21: 4 | FR21: 1 | FT21: 2 | FU21: 2 | FV21: 2 | GI21: 42 | GJ21: 45 | GK21: 25 | GL21: 81 | GM21: 8 | GN21: 50 | GO21: 79 | GP21: 211 | GQ21: 77 | GR21: 120 | GS21: 69 | GT21: 74 | GU21: 77 | GV21: 13 | GW21: 56 | GX21: 167 | GY21: 65 | GZ21: 128 | HA21: 58 | HB21: 86 | HC21: 12 | HD21: 12 | HE21: 21 | HF21: 45 | HG21: 66 | HH21: 65 | HI21: 16 | HJ21: 24 | HK21: 60 | HL21: 8 | HM21: 32 | HN21: 30 | HO21: 4 | HQ21: 2 | HT21: 142 | HU21: 871 | HV21: 746 | HW21: 188 | HX21: 86 | HY21: 3 | HZ21: 27 | IA21: 22 | ID21: 1663 | IE21: 108 | IF21: 20 | IG21: 318 | IH21: 109 | II21: 30 | IJ21: 4 | IK21: 32 | IL21: 327 | IM21: 103 | IN21: 10 | IO21: 3 | IP21: 10 | IR21: 5 | IS21: 17 | IT21: 2 | IU21: 2 | IV21: 3 | IW21: 9 | IX21: 2 | IZ21: 10 | JA21: 39 | JB21: 15 | JC21: 7 | JD21: 19 | JE21: 10 | JF21: 9 | JG21: 89 | JH21: 40 | JI21: 7 | JJ21: 21 | JL21: 4 | JO21: 4 | JQ21: 4 | JS21: 7 | KM21: 4 | KV21: 2 | LW21: 23 | LZ21: 114 | MF21: 50 | MG21: 0 | MJ21: 10 | MO21: 20 | MP21: 17 | MQ21: 4 | MZ21: 34 | NA21: 15 | NB21: 2 | NC21: 2 | ND21: 4 | NE21: 1 | NJ21: 2 | NL21: 4 | NM21: 8 | NN21: 23 | NO21: 563 | NP21: 542 | NQ21: 145 | NR21: 9 | NT21: 4 | NW21: 0 | NX21: 8 | OB21: 13 | OE21: 4456 | OI21: 416 | OJ21: 537 | OK21: 210 | OM21: 6995 | OO21: 33971 | OP21: 221 | OU21: -1172 | OV21: 9597 | PI21: 42616 | PM21: =IFERROR(VLOOKUP($A21&"",Key!$A:$C,3,FALSE),"") -> ISIC 05
A22: 212230 | B22: Copper, nickel, lead, and zinc mining | R22: 408 | S22: 4 | AQ22: 3 | AZ22: 41 | BC22: 389 | BD22: 22 | BE22: 117 | BH22: 261 | BI22: 66 | BJ22: 485 | BW22: 72 | BZ22: 418 | CF22: 46 | CG22: 52 | CJ22: 35 | CU22: 15 | DL22: 2 | EA22: 2 | EH22: 7 | EJ22: 22 | FF22: 3 | FY22: 26 | II22: 285 | IJ22: 744 | IK22: 171 | IL22: 11 | IU22: 65 | KN22: 9 | KP22: 19 | KQ22: 12 | KR22: 0 | KS22: 12 | KT22: 10 | KU22: 88 | KV22: 42 | KW22: 181 | KY22: 43 | KZ22: 36 | LA22: 417 | LB22: 0 | LW22: 292 | LZ22: 174 | MF22: 2 | MH22: 611 | MM22: 404 | MO22: 70 | MR22: 471 | MZ22: 6 | NA22: 7 | NB22: 24 | NF22: 299 | NG22: 5 | NH22: 2 | NI22: 19 | NK22: 2 | NM22: 1022 | NN22: 175 | NO22: 15 | NP22: 12 | NQ22: 2 | NR22: 10 | NS22: 123 | NT22: 58 | NV22: 1027 | NW22: 0 | NY22: 22 | OA22: 17 | OB22: 209 | OO22: 9722 | OU22: 108 | OV22: 4060 | PI22: 13889 | PM22: =IFERROR(VLOOKUP($A22&"",Key!$A:$C,3,FALSE),"") -> ISIC 07
A23: 2122A0 | B23: Iron, gold, silver, and other metal ore mining | R23: 2401 | S23: 2004 | AQ23: 3 | AR23: 2 | AS23: 2 | AX23: 57 | AZ23: 26 | BC23: 3816 | BD23: 137 | BE23: 22 | BF23: 152 | BH23: 550 | BI23: 5 | BJ23: 1859 | BW23: 13 | CF23: 4 | CU23: 19 | DK23: 0 | DL23: 1 | EJ23: 34 | EP23: 2 | EX23: 12 | EZ23: 7 | FC23: 10 | FD23: 17 | FZ23: 2 | GB23: 1 | GC23: 24 | ID23: 29 | IH23: 13 | II23: 87 | IJ23: 868 | IK23: 928 | IL23: 44 | IS23: 54 | IU23: 79 | IZ23: 28 | JO23: 10 | KB23: 2 | LW23: 95 | LZ23: 181 | MF23: 1 | OE23: 2 | OO23: 13604 | OQ23: 121 | OU23: -205 | OV23: 6797 | PI23: 20317 | PM23: =IFERROR(VLOOKUP($A23&"",Key!$A:$C,3,FALSE),"") -> ISIC 07
A24: 212310 | B24: Stone mining and quarrying | C24: 30 | D24: 261 | E24: 47 | F24: 22 | G24: 15 | H24: 68 | I24: 39 | J24: 36 | K24: 6 | L24: 34 | Q24: 270 | R24: 0 | S24: 0 | T24: 585 | U24: 162 | W24: 46 | X24: 55 | Z24: 10 | AA24: 21 | AB24: 34 | AC24: 3324 | AD24: 587 | AE24: 1513 | AF24: 523 | AG24: 2233 | AH24: 547 | AI24: 392 | AJ24: 372 | AK24: 2069 | AL24: 2588 | AS24: 464 | AT24: 939 | AU24: 143 | AV24: 77 | AW24: 428 | AY24: 628 | AZ24: 278 | FS24: 12 | FZ24: 4 | GB24: 4 | IE24: 11 | IF24: 26 | IZ24: 797 | JK24: 0 | JL24: 0 | JM24: 0 | JN24: 0 | JR24: 0 | JT24: 0 | KC24: 0 | KD24: 0 | KF24: 128 | KG24: 0 | KH24: 7 | KI24: 1 | KK24: 3 | KO24: 0 | KP24: 0 | KQ24: 0 | KR24: 0 | KV24: 2 | KW24: 4 | KX24: 0 | KY24: 1 | KZ24: 3 | LK24: 4 | LL24: 0 | LW24: 134 | LZ24: 53 | MF24: 1 | OK24: 174 | ON24: 125 | OO24: 20342 | OU24: -11 | OV24: 140 | PI24: 20470 | PM24: =IFERROR(VLOOKUP($A24&"",Key!$A:$C,3,FALSE),"") -> ISIC 08
A25: 2123A0 | B25: Other nonmetallic mineral mining and quarrying | C25: 1 | D25: 482 | E25: 2 | F25: 5 | H25: 192 | I25: 3 | L25: 2 | Q25: 10 | R25: 1 | S25: 1 | T25: 34 | U25: 515 | V25: 23 | W25: 38 | X25: 982 | Y25: 29 | Z25: 260 | AA25: 66 | AB25: 173 | AC25: 127 | AD25: 171 | AE25: 595 | AF25: 209 | AG25: 670 | AH25: 215 | AI25: 152 | AJ25: 122 | AK25: 2250 | AL25: 406 | AQ25: 860 | AR25: 214 | AS25: 106 | AT25: 5023 | AU25: 542 | AV25: 252 | AW25: 463 | AX25: 83 | AY25: 176 | AZ25: 289 | BA25: 243 | BB25: 428 | BC25: 343 | BK25: 550 | BL25: 19 | BP25: 2 | CF25: 8 | CP25: 1 | CS25: 0 | CT25: 0 | CU25: 1 | CV25: 8 | DL25: 3 | DQ25: 0 | EE25: 21 | EF25: 4 | FE25: 152 | FF25: 1 | FG25: 61 | FH25: 1 | FI25: 4 | FZ25: 17 | GB25: 17 | GF25: 1 | GI25: 10 | GJ25: 278 | HU25: 337 | HV25: 132 | ID25: 106 | IE25: 2065 | IF25: 818 | II25: 14 | IJ25: 28 | IK25: 614 | IL25: 8 | IS25: 1043 | IU25: 569 | IV25: 379 | IX25: 42 | KD25: 0 | KW25: 3 | KX25: 18 | LK25: 1 | LL25: 6 | LW25: 126 | LZ25: 316 | MF25: 15 | ND25: 175 | OE25: 199 | OK25: 1318 | ON25: 85 | OO25: 26331 | OP25: 113 | OU25: -454 | OV25: 2030 | PI25: 28021 | PM25: =IFERROR(VLOOKUP($A25&"",Key!$A:$C,3,FALSE),"") -> ISIC 08
A26: 213111 | B26: Drilling oil and gas wells | P26: 39 | OO26: 39 | OT26: 28550 | OU26: -10 | PI26: 28579 | PM26: =IFERROR(VLOOKUP($A26&"",Key!$A:$C,3,FALSE),"") -> ISIC 09
A27: 21311A | B27: Other support activities for mining | P27: 12471 | Q27: 186 | R27: 151 | S27: 139 | T27: 361 | U27: 203 | V27: 1112 | W27: 1808 | LZ27: 22 | MF27: 2 | OO27: 16455 | OQ27: 2288 | OT27: 69029 | OU27: -77 | OV27: 3045 | PI27: 90739 | PM27: =IFERROR(VLOOKUP($A27&"",Key!$A:$C,3,FALSE),"") -> ISIC 09
A28: 221100 | B28: Electric power generation, transmission, and distribution | C28: 153 | D28: 204 | E28: 318 | F28: 331 | G28: 75 | H28: 392 | I28: 1021 | J28: 187 | K28: 236 | L28: 153 | M28: 8 | N28: 9 | O28: 67 | P28: 2613 | Q28: 880 | R28: 325 | S28: 1183 | T28: 510 | U28: 665 | V28: 156 | W28: 504 | X28: 9500 | Y28: 102 | Z28: 268 | AA28: 169 | AB28: 494 | AC28: 1058 | AD28: 405 | AE28: 826 | AF28: 464 | AG28: 1465 | AH28: 252 | AI28: 480 | AJ28: 364 | AK28: 1579 | AL28: 678 | AM28: 621 | AN28: 529 | AO28: 266 | AP28: 249 | AQ28: 227 | AR28: 1128 | AS28: 703 | AT28: 193 | AU28: 72 | AV28: 89 | AW28: 238 | AX28: 62 | AY28: 45 | AZ28: 200 | BA28: 252 | BB28: 93 | BC28: 2149 | BD28: 321 | BE28: 50 | BF28: 430 | BG28: 407 | BH28: 282 | BI28: 169 | BJ28: 172 | BK28: 465 | BL28: 310 | BM28: 109 | BN28: 331 | BO28: 144 | BP28: 109 | BQ28: 341 | BR28: 307 | BS28: 54 | BT28: 65 | BU28: 201 | BV28: 71 | BW28: 98 | BX28: 481 | BY28: 476 | BZ28: 607 | CA28: 38 | CB28: 227 | CC28: 97 | CD28: 53 | CE28: 114 | CF28: 148 | CG28: 126 | CH28: 18 | CI28: 149 | CJ28: 147 | CK28: 20 | CL28: 243 | CM28: 36 | CN28: 4 | CO28: 121 | CP28: 39 | CQ28: 150 | CR28: 40 | CS28: 107 | CT28: 104 | CU28: 48 | CV28: 118 | CW28: 73 | CX28: 30 | CY28: 60 | CZ28: 171 | DA28: 42 | DB28: 120 | DC28: 132 | DD28: 22 | DE28: 30 | DF28: 18 | DG28: 157 | DH28: 98 | DI28: 4 | DJ28: 4 | DK28: 11 | DL28: 7 | DM28: 68 | DN28: 3 | DO28: 1180 | DP28: 38 | DQ28: 114 | DR28: 89 | DS28: 153 | DT28: 0 | DU28: 9 | DV28: 10 | DW28: 21 | DX28: 39 | DY28: 25 | DZ28: 20 | EA28: 0 | EB28: 3 | EC28: 1 | ED28: 53 | EE28: 7 | EF28: 72 | EG28: 21 | EH28: 44 | EI28: 53 | EJ28: 31 | EK28: 88 | EL28: 1 | EM28: 59 | EN28: 92 | EO28: 55 | EP28: 74 | EQ28: 51 | ER28: 241 | ES28: 32 | ET28: 63 | EU28: 46 | EV28: 1 | EW28: 63 | EX28: 407 | EY28: 172 | EZ28: 305 | FA28: 367 | FB28: 326 | FC28: 402 | FD28: 239 | FE28: 490 | FF28: 561 | FG28: 188 | FH28: 171 | FI28: 247 | FJ28: 90 | FK28: 185 | FL28: 60 | FM28: 39 | FN28: 23 | FO28: 28 | FP28: 142 | FQ28: 65 | FR28: 35 | FS28: 44 | FT28: 27 | FU28: 77 | FV28: 142 | FW28: 40 | FX28: 191 | FY28: 124 | FZ28: 30 | GA28: 33 | GB28: 34 | GC28: 30 | GD28: 106 | GE28: 5 | GF28: 25 | GG28: 82 | GH28: 193 | GI28: 139 | GJ28: 223 | GK28: 229 | GL28: 285 | GM28: 22 | GN28: 91 | GO28: 93 | GP28: 432 | GQ28: 353 | GR28: 272 | GS28: 271 | GT28: 186 | GU28: 328 | GV28: 106 | GW28: 403 | GX28: 755 | GY28: 102 | GZ28: 485 | HA28: 285 | HB28: 244 | HC28: 56 | HD28: 52 | HE28: 112 | HF28: 207 | HG28: 420 | HH28: 230 | HI28: 95 | HJ28: 49 | HK28: 211 | HL28: 175 | HM28: 293 | HN28: 109 | HO28: 89 | HP28: 20 | HQ28: 90 | HR28: 4 | HS28: 13 | HT28: 230 | HU28: 1245 | HV28: 2280 | HW28: 870 | HX28: 250 | HY28: 79 | HZ28: 134 | IA28: 106 | IB28: 1279 | IC28: 42 | ID28: 3932 | IE28: 305 | IF28: 98 | IG28: 124 | IH28: 503 | II28: 1469 | IJ28: 132 | IK28: 1598 | IL28: 2282 | IM28: 1919 | IN28: 262 | IO28: 153 | IP28: 532 | IQ28: 37 | IR28: 264 | IS28: 432 | IT28: 69 | IU28: 126 | IV28: 110 | IW28: 296 | IX28: 137 | IY28: 28 | IZ28: 478 | JA28: 787 | JB28: 370 | JC28: 61 | JD28: 168 | JE28: 93 | JF28: 440 | JG28: 1959 | JH28: 278 | JI28: 68 | JJ28: 274 | JK28: 943 | JL28: 959 | JM28: 1055 | JN28: 1292 | JO28: 2566 | JP28: 1142 | JQ28: 2089 | JR28: 322 | JS28: 3089 | JT28: 445 | JV28: 4475 | JW28: 9322 | JX28: 8193 | JY28: 2037 | JZ28: 2024 | KA28: 4693 | KB28: 1872 | KC28: 2485 | KD28: 2977 | KE28: 240 | KF28: 26 | KG28: 103 | KH28: 3635 | KI28: 251 | KJ28: 528 | KK28: 830 | KL28: 233 | KM28: 2174 | KN28: 109 | KO28: 59 | KP28: 148 | KQ28: 50 | KR28: 626 | KS28: 489 | KT28: 4 | KU28: 294 | KV28: 99 | KW28: 2603 | KX28: 1017 | KY28: 165 | KZ28: 1440 | LA28: 744 | LB28: 22 | LC28: 708 | LD28: 3411 | LE28: 692 | LF28: 242 | LG28: 67 | LH28: 329 | LI28: 308 | LJ28: 7 | LL28: 602 | LM28: 36155 | LN28: 216 | LO28: 347 | LP28: 264 | LQ28: 113 | LR28: 687 | LS28: 249 | LT28: 210 | LU28: 45 | LV28: 381 | LW28: 799 | LX28: 1124 | LY28: 110 | LZ28: 1923 | MA28: 440 | MB28: 119 | MC28: 100 | MD28: 111 | ME28: 398 | MF28: 5064 | MG28: 291 | MH28: 735 | MI28: 366 | MJ28: 214 | MK28: 441 | ML28: 168 | MM28: 151 | MN28: 348 | MO28: 679 | MP28: 240 | MQ28: 2483 | MR28: 96 | MS28: 1585 | MT28: 383 | MU28: 390 | MV28: 1498 | MW28: 121 | MX28: 162 | MY28: 159 | MZ28: 8314 | NA28: 3165 | NB28: 480 | NC28: 424 | ND28: 607 | NE28: 266 | NF28: 79 | NG28: 211 | NH28: 58 | NI28: 324 | NJ28: 289 | NK28: 373 | NL28: 427 | NM28: 2379 | NN28: 5840 | NO28: 6833 | NP28: 10455 | NQ28: 879 | NR28: 1421 | NS28: 99 | NT28: 225 | NU28: 187 | NV28: 1028 | NW28: 42 | NX28: 606 | NY28: 541 | NZ28: 54 | OA28: 86 | OB28: 1111 | OD28: 1580 | OE28: 302 | OF28: 65 | OG28: 1723 | OH28: 138 | OI28: 2981 | OJ28: 622 | OK28: 1897 | OL28: 103 | OM28: 258 | ON28: 903 | OO28: 277787 | OP28: 177661 | OV28: 2744 | PI28: 458193 | PM28: =IFERROR(VLOOKUP($A28&"",Key!$A:$C,3,FALSE),"") -> ISIC 351
A29: 221200 | B29: Natural gas distribution | C29: 23 | D29: 326 | E29: 23 | F29: 59 | G29: 175 | H29: 123 | I29: 71 | J29: 141 | K29: 182 | L29: 37 | M29: 2 | N29: 3 | O29: 5 | P29: 226 | Q29: 11 | R29: 15 | S29: 19 | T29: 11 | U29: 68 | V29: 4 | W29: 31 | X29: 47 | Y29: 1 | Z29: 41 | AA29: 4 | AB29: 0 | AC29: 42 | AD29: 6 | AE29: 21 | AF29: 7 | AG29: 35 | AH29: 7 | AI29: 14 | AJ29: 9 | AK29: 23 | AL29: 37 | AM29: 51 | AN29: 47 | AO29: 19 | AP29: 28 | AQ29: 37 | AR29: 109 | AS29: 118 | AT29: 47 | AU29: 8 | AV29: 9 | AW29: 99 | AX29: 3 | AY29: 4 | AZ29: 17 | BA29: 19 | BB29: 9 | BC29: 146 | BD29: 16 | BE29: 11 | BF29: 16 | BG29: 32 | BH29: 11 | BI29: 7 | BJ29: 11 | BK29: 16 | BL29: 18 | BM29: 31 | BN29: 57 | BO29: 18 | BP29: 20 | BQ29: 46 | BR29: 44 | BS29: 6 | BT29: 12 | BU29: 16 | BV29: 9 | BW29: 15 | BX29: 57 | BY29: 38 | BZ29: 133 | CA29: 6 | CB29: 18 | CC29: 10 | CD29: 7 | CE29: 16 | CF29: 23 | CG29: 17 | CH29: 1 | CI29: 19 | CJ29: 17 | CK29: 1 | CL29: 23 | CM29: 3 | CN29: 0 | CO29: 12 | CP29: 6 | CQ29: 17 | CR29: 5 | CS29: 9 | CT29: 5 | CU29: 4 | CV29: 9 | CW29: 7 | CX29: 3 | CY29: 5 | CZ29: 16 | DA29: 4 | DB29: 11 | DC29: 18 | DD29: 2 | DE29: 5 | DF29: 2 | DG29: 16 | DH29: 7 | DI29: 0 | DJ29: 1 | DK29: 0 | DL29: 0 | DM29: 1 | DN29: 0 | DO29: 45 | DP29: 3 | DQ29: 2 | DR29: 6 | DS29: 34 | DT29: 0 | DU29: 1 | DV29: 0 | DW29: 0 | DX29: 6 | DY29: 0 | DZ29: 0 | EA29: 0 | EB29: 0 | EC29: 1 | ED29: 9 | EE29: 0 | EF29: 6 | EG29: 2 | EH29: 6 | EI29: 7 | EJ29: 1 | EK29: 28 | EL29: 1 | EM29: 3 | EN29: 7 | EO29: 9 | EP29: 4 | EQ29: 2 | ER29: 48 | ES29: 5 | ET29: 14 | EU29: 6 | EV29: 0 | EW29: 7 | EX29: 32 | EY29: 11 | EZ29: 25 | FA29: 32 | FB29: 31 | FC29: 35 | FD29: 18 | FE29: 25 | FF29: 59 | FG29: 30 | FH29: 18 | FI29: 28 | FJ29: 16 | FK29: 16 | FL29: 10 | FM29: 9 | FN29: 5 | FO29: 3 | FP29: 19 | FQ29: 6 | FR29: 3 | FS29: 6 | FT29: 4 | FU29: 11 | FV29: 22 | FW29: 4 | FX29: 11 | FY29: 5 | FZ29: 2 | GA29: 0 | GB29: 4 | GC29: 2 | GD29: 12 | GE29: 1 | GF29: 2 | GG29: 13 | GH29: 21 | GI29: 25 | GJ29: 28 | GK29: 14 | GL29: 49 | GM29: 5 | GN29: 30 | GO29: 47 | GP29: 127 | GQ29: 46 | GR29: 71 | GS29: 41 | GT29: 43 | GU29: 45 | GV29: 8 | GW29: 34 | GX29: 99 | GY29: 38 | GZ29: 76 | HA29: 34 | HB29: 51 | HC29: 8 | HD29: 7 | HE29: 13 | HF29: 26 | HG29: 34 | HH29: 33 | HI29: 8 | HJ29: 12 | HK29: 30 | HL29: 5 | HM29: 21 | HN29: 20 | HO29: 7 | HP29: 3 | HQ29: 6 | HR29: 1 | HS29: 1 | HT29: 58 | HU29: 358 | HV29: 307 | HW29: 76 | HX29: 35 | HY29: 2 | HZ29: 11 | IA29: 9 | IB29: 67 | IC29: 2 | ID29: 1136 | IE29: 74 | IF29: 13 | IG29: 31 | IH29: 627 | II29: 70 | IJ29: 14 | IK29: 290 | IL29: 570 | IM29: 241 | IN29: 24 | IO29: 6 | IP29: 24 | IQ29: 1 | IR29: 11 | IS29: 696 | IT29: 5 | IU29: 6 | IV29: 5 | IW29: 20 | IX29: 3 | IY29: 0 | IZ29: 23 | JA29: 44 | JB29: 17 | JC29: 8 | JD29: 21 | JE29: 11 | JF29: 9 | JG29: 98 | JH29: 44 | JI29: 8 | JJ29: 23 | JK29: 10 | JL29: 8 | JM29: 40 | JN29: 3 | JO29: 35 | JP29: 1 | JQ29: 23 | JR29: 14 | JS29: 51 | JT29: 3 | JV29: 206 | JW29: 25 | JX29: 29 | JY29: 56 | JZ29: 7 | KA29: 4 | KB29: 7 | KC29: 10 | KD29: 31 | KE29: 42 | KF29: 30 | KG29: 166 | KH29: 631 | KI29: 16 | KJ29: 163 | KK29: 442 | KL29: 62 | KM29: 527 | KN29: 6 | KO29: 0 | KP29: 3 | KQ29: 1 | KR29: 1 | KS29: 6 | KT29: 0 | KU29: 3 | KV29: 3 | KW29: 9 | KX29: 3 | KY29: 13 | KZ29: 5 | LA29: 6 | LB29: 0 | LC29: 31 | LD29: 329 | LE29: 30 | LF29: 4 | LG29: 5 | LH29: 25 | LI29: 42 | LJ29: 1272 | LK29: 0 | LL29: 0 | LM29: 4820 | LN29: 326 | LO29: 51 | LP29: 25 | LQ29: 15 | LR29: 6 | LS29: 2 | LU29: 0 | LV29: 20 | LW29: 14 | LX29: 1 | LY29: 1 | LZ29: 10 | MA29: 3 | MB29: 2 | MC29: 1 | MD29: 1 | ME29: 8 | MF29: 79 | MG29: 9 | MH29: 119 | MI29: 35 | MJ29: 44 | MK29: 9 | ML29: 8 | MM29: 20 | MN29: 17 | MO29: 202 | MP29: 481 | MQ29: 656 | MR29: 76 | MS29: 14 | MT29: 1 | MU29: 3 | MV29: 14 | MW29: 0 | MX29: 1 | MY29: 13 | MZ29: 118 | NA29: 64 | NB29: 11 | NC29: 9 | ND29: 24 | NE29: 4 | NF29: 3 | NG29: 2 | NH29: 1 | NI29: 6 | NJ29: 8 | NK29: 7 | NL29: 8 | NM29: 32 | NN29: 137 | NO29: 203 | NP29: 178 | NQ29: 12 | NR29: 50 | NS29: 2 | NT29: 16 | NU29: 5 | NV29: 17 | NW29: 2 | NX29: 39 | NY29: 13 | NZ29: 64 | OA29: 1 | OB29: 49 | OD29: 653 | OE29: 308 | OF29: 326 | OG29: 76 | OH29: 136 | OI29: 3143 | OJ29: 1057 | OK29: 2211 | OL29: 42 | OM29: 3 | ON29: 264 | OO29: 31503 | OP29: 48152 | OV29: 559 | PI29: 80214 | PM29: =IFERROR(VLOOKUP($A29&"",Key!$A:$C,3,FALSE),"") -> ISIC 352T353
A30: 221300 | B30: Water, sewage and other systems | C30: 570 | D30: 1847 | E30: 633 | F30: 709 | G30: 90 | H30: 919 | I30: 66 | J30: 85 | K30: 77 | L30: 28 | M30: 0 | N30: 2 | O30: 7 | P30: 1221 | Q30: 7 | R30: 0 | S30: 6 | T30: 20 | U30: 20 | V30: 16 | W30: 16 | X30: 1186 | Y30: 63 | Z30: 130 | AA30: 8 | AB30: 8 | AC30: 111 | AD30: 51 | AE30: 59 | AF30: 29 | AG30: 245 | AH30: 40 | AI30: 34 | AJ30: 46 | AK30: 171 | AL30: 87 | AM30: 12 | AN30: 15 | AO30: 11 | AP30: 12 | AQ30: 13 | AR30: 49 | AS30: 2 | AT30: 23 | AU30: 3 | AV30: 9 | AW30: 5 | AX30: 2 | AY30: 5 | AZ30: 3 | BA30: 13 | BB30: 6 | BC30: 69 | BD30: 13 | BE30: 4 | BF30: 1 | BG30: 12 | BH30: 4 | BI30: 6 | BJ30: 9 | BK30: 16 | BL30: 13 | BM30: 8 | BN30: 9 | BO30: 7 | BP30: 7 | BQ30: 16 | BR30: 17 | BS30: 6 | BT30: 4 | BU30: 4 | BV30: 6 | BW30: 6 | BX30: 20 | BY30: 20 | BZ30: 46 | CA30: 5 | CB30: 11 | CC30: 5 | CD30: 2 | CE30: 9 | CF30: 8 | CG30: 5 | CH30: 2 | CI30: 6 | CJ30: 5 | CK30: 4 | CL30: 13 | CM30: 2 | CN30: 0 | CO30: 5 | CP30: 3 | CQ30: 6 | CR30: 2 | CS30: 3 | CT30: 4 | CU30: 2 | CV30: 4 | CW30: 3 | CX30: 1 | CY30: 2 | CZ30: 6 | DA30: 1 | DB30: 5 | DC30: 4 | DD30: 1 | DE30: 2 | DF30: 1 | DG30: 9 | DH30: 3 | DI30: 0 | DJ30: 0 | DK30: 0 | DL30: 0 | DM30: 2 | DN30: 0 | DO30: 29 | DP30: 1 | DQ30: 2 | DR30: 5 | DS30: 33 | DT30: 0 | DU30: 0 | DV30: 0 | DW30: 4 | DX30: 3 | DY30: 0 | DZ30: 2 | EA30: 0 | EB30: 0 | EC30: 0 | ED30: 6 | EE30: 0 | EF30: 3 | EG30: 0 | EH30: 2 | EI30: 3 | EJ30: 1 | EK30: 4 | EL30: 0 | EM30: 1 | EN30: 3 | EO30: 4 | EP30: 4 | EQ30: 3 | ER30: 29 | ES30: 2 | ET30: 6 | EU30: 3 | EV30: 4 | EW30: 201 | EX30: 15 | EY30: 6 | EZ30: 10 | FA30: 20 | FB30: 10 | FC30: 17 | FD30: 10 | FE30: 13 | FF30: 47 | FG30: 13 | FH30: 20 | FI30: 49 | FJ30: 5 | FK30: 15 | FL30: 5 | FM30: 3 | FN30: 3 | FO30: 0 | FP30: 10 | FQ30: 5 | FR30: 1 | FS30: 3 | FT30: 2 | FU30: 3 | FV30: 11 | FW30: 5 | FX30: 11 | FY30: 12 | FZ30: 2 | GA30: 3 | GB30: 3 | GC30: 1 | GD30: 4 | GE30: 1 | GF30: 2 | GG30: 8 | GH30: 11 | GI30: 12 | GJ30: 9 | GK30: 8 | GL30: 17 | GM30: 2 | GN30: 5 | GO30: 6 | GP30: 33 | GQ30: 29 | GR30: 41 | GS30: 28 | GT30: 24 | GU30: 53 | GV30: 13 | GW30: 69 | GX30: 79 | GY30: 10 | GZ30: 36 | HA30: 20 | HB30: 28 | HC30: 4 | HD30: 10 | HE30: 18 | HF30: 27 | HG30: 54 | HH30: 32 | HI30: 8 | HJ30: 10 | HK30: 16 | HL30: 4 | HM30: 13 | HN30: 10 | HO30: 9 | HP30: 2 | HQ30: 6 | HR30: 0 | HS30: 1 | HT30: 9 | HU30: 36 | HV30: 54 | HW30: 37 | HX30: 16 | HY30: 2 | HZ30: 6 | IA30: 7 | IB30: 46 | IC30: 3 | ID30: 236 | IE30: 8 | IF30: 13 | IG30: 26 | IH30: 30 | II30: 21 | IJ30: 9 | IK30: 90 | IL30: 634 | IM30: 103 | IN30: 18 | IO30: 11 | IP30: 45 | IQ30: 5 | IR30: 25 | IS30: 11 | IT30: 13 | IU30: 19 | IV30: 13 | IW30: 24 | IX30: 13 | IY30: 2 | IZ30: 63 | JA30: 24 | JB30: 16 | JC30: 7 | JD30: 7 | JE30: 7 | JF30: 6 | JG30: 65 | JH30: 14 | JI30: 6 | JJ30: 12 | JK30: 10 | JL30: 56 | JM30: 393 | JN30: 71 | JO30: 221 | JP30: 33 | JQ30: 180 | JR30: 19 | JS30: 170 | JT30: 28 | JV30: 433 | JW30: 255 | JX30: 140 | JY30: 87 | JZ30: 95 | KA30: 211 | KB30: 84 | KC30: 74 | KD30: 157 | KE30: 2 | KF30: 14 | KG30: 5 | KH30: 95 | KI30: 36 | KJ30: 7 | KK30: 25 | KL30: 42 | KM30: 49 | KN30: 5 | KO30: 4 | KP30: 15 | KQ30: 1 | KR30: 21 | KS30: 40 | KT30: 1 | KU30: 23 | KV30: 25 | KW30: 62 | KX30: 17 | KY30: 35 | KZ30: 31 | LA30: 29 | LB30: 0 | LC30: 50 | LD30: 131 | LE30: 62 | LF30: 16 | LG30: 13 | LH30: 44 | LI30: 21 | LJ30: 1562 | LK30: 1 | LL30: 0 | LM30: 1271 | LN30: 33 | LO30: 43 | LP30: 35 | LQ30: 64 | LR30: 80 | LS30: 12 | LT30: 22 | LU30: 6 | LV30: 40 | LW30: 84 | LX30: 66 | LY30: 22 | LZ30: 61 | MA30: 9 | MB30: 20 | MC30: 10 | MD30: 4 | ME30: 24 | MF30: 109 | MG30: 16 | MH30: 167 | MI30: 28 | MJ30: 148 | MK30: 48 | ML30: 22 | MM30: 17 | MN30: 30 | MO30: 614 | MP30: 139 | MQ30: 2629 | MR30: 12 | MS30: 154 | MT30: 32 | MU30: 2 | MV30: 67 | MW30: 12 | MX30: 14 | MY30: 11 | MZ30: 638 | NA30: 303 | NB30: 53 | NC30: 2 | ND30: 18 | NE30: 23 | NF30: 7 | NG30: 13 | NH30: 4 | NI30: 41 | NJ30: 20 | NK30: 24 | NL30: 45 | NM30: 139 | NN30: 608 | NO30: 598 | NP30: 492 | NQ30: 52 | NR30: 162 | NS30: 7 | NT30: 19 | NU30: 20 | NV30: 121 | NW30: 5 | NX30: 129 | NY30: 22 | NZ30: 93 | OA30: 6 | OB30: 271 | OD30: 1278 | OE30: 591 | OF30: 141 | OG30: 75 | OH30: 112 | OI30: 1960 | OJ30: 1824 | OK30: 5566 | OL30: 23 | OM30: 835 | ON30: 415 | OO30: 40658 | OP30: 39603 | OV30: 705 | PI30: 80967 | PM30: =IFERROR(VLOOKUP($A30&"",Key!$A:$C,3,FALSE),"") -> ISIC 36T39
A31: 233210 | B31: Health care structures | OT31: 37725 | OZ31: 1146 | PD31: 2098 | PH31: 6153 | PI31: 47123 | PM31: =IFERROR(VLOOKUP($A31&"",Key!$A:$C,3,FALSE),"") -> ISIC 41T43
A32: 233262 | B32: Educational and vocational structures | OT32: 20501 | OZ32: 1256 | PD32: 211 | PH32: 79213 | PI32: 101181 | PM32: =IFERROR(VLOOKUP($A32&"",Key!$A:$C,3,FALSE),"") -> ISIC 41T43
A33: 230301 | B33: Nonresidential maintenance and repair | C33: 198 | D33: 354 | E33: 184 | F33: 159 | G33: 155 | H33: 250 | I33: 93 | K33: 39 | L33: 112 | M33: 0 | N33: 14 | O33: 19 | P33: 180 | Q33: 967 | R33: 480 | S33: 180 | T33: 481 | U33: 580 | V33: 236 | W33: 1868 | X33: 6988 | Y33: 388 | Z33: 23 | AA33: 2 | AB33: 2 | AC33: 50 | AD33: 7 | AE33: 26 | AF33: 10 | AG33: 39 | AH33: 13 | AI33: 19 | AJ33: 19 | AK33: 32 | AL33: 29 | AM33: 132 | AN33: 72 | AO33: 54 | AP33: 50 | AQ33: 60 | AR33: 186 | AS33: 87 | AT33: 197 | AU33: 46 | AV33: 62 | AW33: 43 | AX33: 13 | AY33: 22 | AZ33: 28 | BA33: 39 | BB33: 33 | BC33: 369 | BD33: 93 | BE33: 30 | BF33: 11 | BG33: 85 | BH33: 30 | BI33: 34 | BJ33: 44 | BK33: 104 | BL33: 82 | BM33: 43 | BN33: 84 | BO33: 45 | BP33: 42 | BQ33: 134 | BR33: 102 | BS33: 16 | BT33: 18 | BU33: 29 | BV33: 23 | BW33: 41 | BX33: 164 | BY33: 166 | BZ33: 138 | CA33: 14 | CB33: 72 | CC33: 32 | CD33: 18 | CE33: 31 | CF33: 44 | CG33: 51 | CH33: 7 | CI33: 79 | CJ33: 59 | CK33: 7 | CL33: 72 | CM33: 15 | CN33: 4 | CO33: 51 | CP33: 8 | CQ33: 54 | CR33: 14 | CS33: 33 | CT33: 28 | CU33: 19 | CV33: 38 | CW33: 33 | CX33: 12 | CY33: 27 | CZ33: 59 | DA33: 11 | DB33: 54 | DC33: 52 | DD33: 11 | DE33: 11 | DF33: 5 | DG33: 51 | DH33: 35 | DI33: 0 | DJ33: 0 | DK33: 3 | DL33: 0 | DM33: 16 | DN33: 1 | DO33: 232 | DP33: 18 | DQ33: 52 | DR33: 42 | DS33: 53 | DT33: 0 | DU33: 6 | DV33: 69 | DW33: 6 | DX33: 15 | DY33: 4 | DZ33: 10 | EA33: 0 | EB33: 0 | EC33: 1 | ED33: 14 | EE33: 0 | EF33: 22 | EG33: 8 | EH33: 9 | EI33: 15 | EJ33: 9 | EK33: 17 | EL33: 0 | EM33: 10 | EN33: 21 | EO33: 6 | EP33: 10 | EQ33: 13 | ER33: 125 | ES33: 9 | ET33: 18 | EU33: 13 | EV33: 0 | EW33: 15 | EX33: 97 | EY33: 31 | EZ33: 78 | FA33: 82 | FB33: 108 | FC33: 98 | FD33: 72 | FE33: 59 | FF33: 198 | FG33: 43 | FH33: 24 | FI33: 37 | FJ33: 26 | FK33: 88 | FL33: 11 | FM33: 14 | FN33: 7 | FO33: 6 | FP33: 27 | FQ33: 17 | FR33: 5 | FS33: 9 | FT33: 9 | FU33: 14 | FV33: 33 | FW33: 12 | FX33: 74 | FY33: 54 | FZ33: 14 | GA33: 12 | GB33: 14 | GC33: 14 | GD33: 18 | GE33: 1 | GF33: 7 | GG33: 30 | GH33: 56 | GI33: 45 | GJ33: 46 | GK33: 29 | GL33: 21 | GM33: 4 | GN33: 12 | GO33: 12 | GP33: 93 | GQ33: 61 | GR33: 68 | GS33: 52 | GT33: 47 | GU33: 101 | GV33: 30 | GW33: 102 | GX33: 241 | GY33: 33 | GZ33: 120 | HA33: 53 | HB33: 81 | HC33: 15 | HD33: 15 | HE33: 39 | HF33: 62 | HG33: 87 | HH33: 32 | HI33: 25 | HJ33: 15 | HK33: 68 | HL33: 10 | HM33: 32 | HN33: 18 | HO33: 10 | HP33: 5 | HQ33: 12 | HR33: 1 | HS33: 3 | HT33: 74 | HU33: 145 | HV33: 275 | HW33: 299 | HX33: 56 | HY33: 13 | HZ33: 26 | IA33: 15 | IB33: 284 | IC33: 11 | ID33: 9096 | IE33: 68 | IF33: 34 | IG33: 81 | IH33: 241 | II33: 70 | IJ33: 28 | IK33: 189 | IL33: 456 | IM33: 331 | IN33: 38 | IO33: 27 | IP33: 141 | IQ33: 12 | IR33: 77 | IS33: 79 | IT33: 24 | IU33: 28 | IV33: 21 | IW33: 69 | IX33: 37 | IY33: 6 | IZ33: 114 | JA33: 112 | JB33: 63 | JC33: 11 | JD33: 26 | JE33: 21 | JF33: 45 | JG33: 290 | JH33: 65 | JI33: 12 | JJ33: 40 | JK33: 518 | JL33: 171 | JM33: 306 | JN33: 446 | JO33: 525 | JP33: 137 | JQ33: 284 | JR33: 200 | JS33: 693 | JT33: 83 | JV33: 1383 | JW33: 911 | JX33: 1876 | JY33: 506 | JZ33: 293 | KA33: 1348 | KB33: 410 | KC33: 288 | KD33: 526 | KE33: 227 | KF33: 2394 | KG33: 68 | KH33: 561 | KI33: 313 | KJ33: 470 | KK33: 965 | KL33: 344 | KM33: 813 | KN33: 19 | KO33: 16 | KP33: 29 | KQ33: 3 | KR33: 67 | KS33: 106 | KT33: 2 | KU33: 30 | KV33: 21 | KW33: 513 | KX33: 1611 | KY33: 162 | KZ33: 184 | LA33: 368 | LB33: 1 | LC33: 850 | LD33: 5080 | LE33: 929 | LF33: 360 | LG33: 205 | LH33: 74 | LI33: 385 | LJ33: 103 | LK33: 0 | LL33: 0 | LM33: 43151 | LN33: 95 | LO33: 426 | LP33: 116 | LR33: 177 | LS33: 19 | LT33: 35 | LU33: 5 | LV33: 123 | LW33: 687 | LX33: 37 | LY33: 9 | LZ33: 357 | MA33: 39 | MB33: 59 | MC33: 24 | MD33: 76 | ME33: 139 | MF33: 737 | MG33: 69 | MH33: 183 | MI33: 29 | MJ33: 305 | MK33: 36 | ML33: 80 | MM33: 46 | MN33: 51 | MO33: 130 | MP33: 24 | MQ33: 1696 | MR33: 270 | MS33: 257 | MT33: 52 | MU33: 49 | MV33: 295 | MW33: 25 | MX33: 17 | MY33: 22 | MZ33: 1110 | NA33: 423 | NB33: 158 | NC33: 130 | ND33: 281 | NE33: 68 | NF33: 9 | NG33: 31 | NH33: 5 | NI33: 75 | NJ33: 92 | NK33: 70 | NL33: 100 | NM33: 313 | NN33: 2809 | NO33: 668 | NP33: 887 | NQ33: 119 | NR33: 343 | NS33: 37 | NT33: 101 | NU33: 35 | NV33: 324 | NW33: 35 | NX33: 98 | NY33: 100 | NZ33: 1124 | OA33: 80 | OB33: 1043 | OD33: 6137 | OE33: 362 | OF33: 10 | OG33: 530 | OI33: 9603 | OJ33: 4506 | OK33: 17479 | OL33: 2 | OM33: 92 | ON33: 41262 | OO33: 204348 | OV33: 81 | PI33: 204428 | PM33: =IFERROR(VLOOKUP($A33&"",Key!$A:$C,3,FALSE),"") -> ISIC 41T43
A34: 230302 | B34: Residential maintenance and repair | LK34: 71972 | LL34: 3791 | OD34: 1597 | OE34: 124 | ON34: 6966 | OO34: 84450 | OV34: 18 | PI34: 84468 | PM34: =IFERROR(VLOOKUP($A34&"",Key!$A:$C,3,FALSE),"") -> ISIC 41T43
A35: 2332A0 | B35: Office and commercial structures | OT35: 143467 | OZ35: 1421 | PD35: 2352 | PH35: 22145 | PI35: 169386 | PM35: =IFERROR(VLOOKUP($A35&"",Key!$A:$C,3,FALSE),"") -> ISIC 41T43
A36: 233412 | B36: Multifamily residential structures | OS36: 74011 | OZ36: 610 | PH36: 5151 | PI36: 79772 | PM36: =IFERROR(VLOOKUP($A36&"",Key!$A:$C,3,FALSE),"") -> ISIC 41T43
A37: 2334A0 | B37: Other residential structures | OD37: 2104 | OE37: 165 | ON37: 3526 | OO37: 5795 | OS37: 242834 | OZ37: 65 | PH37: 3601 | PI37: 252295 | PM37: =IFERROR(VLOOKUP($A37&"",Key!$A:$C,3,FALSE),"") -> ISIC 41T43
A38: 233230 | B38: Manufacturing structures | OT38: 69970 | OZ38: 401 | PD38: 296 | PH38: 1 | PI38: 70668 | PM38: =IFERROR(VLOOKUP($A38&"",Key!$A:$C,3,FALSE),"") -> ISIC 41T43
A39: 2332D0 | B39: Other nonresidential structures | OT39: 66380 | OZ39: 2103 | PD39: 4990 | PH39: 49737 | PI39: 123210 | PM39: =IFERROR(VLOOKUP($A39&"",Key!$A:$C,3,FALSE),"") -> ISIC 41T43
A40: 233240 | B40: Power and communication structures | OT40: 113346 | OZ40: 62 | PD40: 714 | PH40: 9507 | PI40: 123629 | PM40: =IFERROR(VLOOKUP($A40&"",Key!$A:$C,3,FALSE),"") -> ISIC 41T43
A41: 233411 | B41: Single-family residential structures | OS41: 270163 | OZ41: 26 | PH41: 281 | PI41: 270471 | PM41: =IFERROR(VLOOKUP($A41&"",Key!$A:$C,3,FALSE),"") -> ISIC 41T43
A42: 2332C0 | B42: Transportation structures and highways and streets | OT42: 14795 | OZ42: 871 | PD42: 2183 | PH42: 125205 | PI42: 143054 | PM42: =IFERROR(VLOOKUP($A42&"",Key!$A:$C,3,FALSE),"") -> ISIC 41T43
A43: 321100 | B43: Sawmills and wood preservation | I43: 4 | L43: 1 | N43: 1 | Q43: 9 | R43: 0 | S43: 3 | V43: 3 | W43: 5 | Z43: 0 | AA43: 608 | AB43: 2719 | AC43: 2740 | AD43: 479 | AE43: 1576 | AF43: 471 | AG43: 1772 | AH43: 200 | AI43: 1176 | AJ43: 418 | AK43: 2352 | AL43: 1037 | AM43: 6418 | AN43: 3072 | AO43: 5415 | AP43: 5263 | AQ43: 3 | AU43: 2 | AV43: 14 | AW43: 0 | BA43: 1 | BB43: 1 | BK43: 5 | CE43: 16 | CF43: 4 | CZ43: 90 | ET43: 208 | EU43: 48 | EV43: 0 | EW43: 94 | FA43: 2 | FC43: 93 | FD43: 116 | FK43: 57 | FL43: 38 | FN43: 4 | FP43: 1146 | FQ43: 421 | FR43: 323 | FS43: 180 | FT43: 26 | FU43: 182 | FV43: 1033 | GD43: 163 | GE43: 19 | GF43: 65 | GG43: 87 | GH43: 206 | HK43: 7 | HT43: 873 | HU43: 1714 | HV43: 2391 | II43: 28 | IL43: 171 | JG43: 169 | JK43: 8 | JL43: 3 | JM43: 1 | JN43: 1 | JO43: 35 | JR43: 0 | JT43: 0 | JY43: 1 | KB43: 1 | KC43: 0 | KD43: 2 | KF43: 2377 | KS43: 18 | KW43: 18 | KX43: 114 | KZ43: 27 | LK43: 5 | LL43: 4 | LO43: 127 | LW43: 194 | LZ43: 66 | MF43: 3 | MH43: 3 | MK43: 8 | MN43: 10 | MO43: 5 | MQ43: 2 | MR43: 0 | MS43: 245 | MT43: 1 | MV43: 9 | MY43: 3 | MZ43: 54 | NC43: 5 | ND43: 32 | NE43: 123 | NF43: 5 | NK43: 2 | NL43: 12 | NM43: 59 | NN43: 12 | NO43: 28 | NP43: 5 | NQ43: 2 | NU43: 30 | NZ43: 25 | OB43: 42 | OD43: 2 | OE43: 20 | OI43: 49 | OK43: 77 | OM43: 1 | ON43: 146 | OO43: 49764 | OU43: -51 | OV43: 4467 | PI43: 54181 | PM43: =IFERROR(VLOOKUP($A43&"",Key!$A:$C,3,FALSE),"") -> ISIC 16
A44: 321200 | B44: Veneer, plywood, and engineered wood product manufacturing | Z44: 0 | AA44: 815 | AB44: 2532 | AC44: 2227 | AD44: 1154 | AE44: 2593 | AF44: 1278 | AG44: 4693 | AH44: 720 | AI44: 1174 | AJ44: 668 | AK44: 4990 | AL44: 1876 | AN44: 3509 | AO44: 1197 | AP44: 792 | AQ44: 8 | CQ44: 3 | CR44: 0 | CZ44: 236 | DC44: 32 | EV44: 0 | EW44: 120 | FA44: 807 | FC44: 540 | FG44: 1 | FL44: 73 | FP44: 1419 | FQ44: 368 | FR44: 143 | FS44: 210 | FT44: 110 | FU44: 177 | FV44: 1247 | FY44: 361 | GF44: 7 | GG44: 160 | GH44: 92 | JB44: 14 | JF44: 3 | JG44: 655 | JK44: 0 | JL44: 4 | JM44: 1 | JN44: 1 | JO44: 5 | JR44: 0 | JT44: 0 | KB44: 11 | KC44: 0 | KD44: 4 | KO44: 0 | KP44: 0 | KQ44: 0 | KR44: 0 | KS44: 1 | KW44: 34 | KX44: 221 | KZ44: 396 | LK44: 6 | LL44: 4 | LO44: 177 | LZ44: 20 | MB44: 56 | MJ44: 205 | MQ44: 7 | MS44: 3 | MT44: 0 | MV44: 2 | MY44: 4 | MZ44: 160 | NC44: 50 | ND44: 78 | NE44: 227 | NF44: 1 | NM44: 76 | NN44: 1 | NO44: 276 | NP44: 16 | NQ44: 3 | NU44: 19 | NZ44: 21 | OB44: 91 | OE44: 3 | OI44: 980 | OJ44: 3 | OK44: 9 | ON44: 79 | OO44: 40258 | OU44: 66 | OV44: 1274 | PI44: 41599 | PM44: =IFERROR(VLOOKUP($A44&"",Key!$A:$C,3,FALSE),"") -> ISIC 16
A45: 321910 | B45: Millwork | C45: 2 | H45: 28 | N45: 133 | R45: 0 | V45: 3 | W45: 5 | AA45: 447 | AB45: 568 | AC45: 2326 | AD45: 1272 | AE45: 2555 | AF45: 1905 | AG45: 4760 | AH45: 32 | AI45: 965 | AJ45: 187 | AK45: 2818 | AL45: 488 | AM45: 1 | AN45: 38 | AO45: 1840 | AP45: 179 | AQ45: 2 | AU45: 1 | AV45: 1 | AW45: 0 | AY45: 1 | BA45: 1 | BB45: 1 | BC45: 2 | BE45: 2 | BI45: 0 | BJ45: 1 | BK45: 1 | BP45: 0 | BW45: 2 | CB45: 1 | CL45: 56 | CZ45: 181 | DG45: 1 | DS45: 0 | EU45: 94 | EV45: 3 | EW45: 114 | FA45: 505 | FC45: 461 | FD45: 58 | FJ45: 23 | FK45: 91 | FP45: 381 | FQ45: 2 | FR45: 1 | FS45: 2 | FV45: 7 | FW45: 260 | GF45: 6 | GH45: 2 | GZ45: 0 | IB45: 0 | JG45: 325 | JK45: 3 | JL45: 3 | JM45: 1 | JN45: 1 | JO45: 517 | JR45: 0 | JT45: 0 | JV45: 0 | JX45: 23 | JY45: 12 | KB45: 7 | KC45: 43 | KD45: 15 | KF45: 306 | KN45: 15 | KO45: 0 | KP45: 13 | KQ45: 20 | KR45: 0 | KS45: 30 | KT45: 11 | KU45: 130 | KV45: 21 | KW45: 84 | KX45: 161 | KY45: 16 | KZ45: 349 | LA45: 95 | LB45: 0 | LK45: 12 | LL45: 6 | LM45: 7362 | LN45: 2 | LO45: 57 | LR45: 0 | LW45: 144 | LZ45: 138 | MB45: 246 | MD45: 0 | MF45: 3 | MG45: 0 | MK45: 312 | MN45: 439 | MP45: 3 | MQ45: 13 | MR45: 1 | MS45: 2 | MT45: 0 | MU45: 0 | MV45: 2 | MW45: 0 | MY45: 6 | MZ45: 91 | NC45: 31 | ND45: 51 | NE45: 49 | NF45: 1 | NK45: 0 | NL45: 1 | NM45: 48 | NN45: 46 | NO45: 238 | NP45: 35 | NQ45: 12 | NR45: 0 | NS45: 0 | NY45: 0 | NZ45: 10 | OA45: 1 | OB45: 113 | OD45: 3 | OE45: 2 | OI45: 37 | OJ45: 1 | OK45: 38 | ON45: 67 | OO45: 34643 | OU45: 164 | OV45: 347 | PI45: 35155 | PM45: =IFERROR(VLOOKUP($A45&"",Key!$A:$C,3,FALSE),"") -> ISIC 16
A46: 3219A0 | B46: All other wood product manufacturing | C46: 6 | D46: 7 | E46: 248 | F46: 205 | G46: 1 | H46: 21 | I46: 10 | J46: 5 | K46: 2 | M46: 0 | O46: 0 | R46: 4 | S46: 204 | T46: 85 | U46: 45 | V46: 119 | W46: 268 | X46: 5 | AA46: 26 | AB46: 75 | AC46: 702 | AD46: 217 | AE46: 195 | AF46: 72 | AG46: 672 | AH46: 50 | AI46: 374 | AJ46: 35 | AK46: 265 | AL46: 128 | AM46: 11 | AN46: 148 | AO46: 1457 | AP46: 771 | AQ46: 12 | AR46: 87 | AS46: 16 | AU46: 3 | AV46: 21 | AW46: 6 | BA46: 30 | BB46: 9 | BC46: 7 | BE46: 6 | BI46: 87 | BJ46: 176 | BK46: 4 | BL46: 101 | BP46: 125 | BW46: 4 | BZ46: 37 | CL46: 13 | CO46: 6 | CQ46: 108 | CR46: 27 | CU46: 25 | CV46: 6 | CZ46: 215 | DL46: 0 | DM46: 14 | DN46: 25 | DO46: 11 | DP46: 36 | DQ46: 52 | DS46: 31 | EA46: 196 | EM46: 528 | FA46: 1 | FB46: 364 | FC46: 6 | FD46: 174 | FE46: 1 | FG46: 0 | FP46: 214 | FT46: 9 | FU46: 20 | FW46: 56 | FX46: 20 | GD46: 37 | GF46: 6 | GH46: 110 | GI46: 10 | GV46: 55 | HI46: 53 | HJ46: 196 | HP46: 57 | HS46: 0 | HT46: 35 | HU46: 403 | HV46: 294 | HW46: 10 | HY46: 29 | IB46: 2 | IL46: 3 | IN46: 2 | IO46: 0 | IP46: 0 | IQ46: 0 | IR46: 2 | IS46: 2 | IT46: 1 | IU46: 8 | IV46: 10 | IW46: 6 | IY46: 3 | IZ46: 20 | JB46: 2 | JC46: 1 | JG46: 194 | JI46: 1 | JJ46: 7 | JK46: 773 | JL46: 235 | JM46: 450 | JN46: 435 | JO46: 1164 | JP46: 297 | JQ46: 977 | JR46: 292 | JS46: 1281 | JT46: 146 | JV46: 169 | JW46: 617 | JX46: 140 | JY46: 56 | JZ46: 190 | KA46: 51 | KB46: 127 | KC46: 331 | KD46: 133 | KH46: 175 | KJ46: 3 | KK46: 22 | KL46: 66 | KM46: 109 | KN46: 0 | KO46: 3 | KP46: 0 | KQ46: 2 | KR46: 8 | KS46: 2 | KU46: 0 | KW46: 9 | KX46: 58 | KZ46: 21 | LB46: 1 | LC46: 66 | LD46: 79 | LE46: 3 | LF46: 1 | LK46: 1 | LL46: 0 | LM46: 123 | LN46: 3 | LO46: 53 | LR46: 10 | LS46: 1 | LT46: 22 | LU46: 2 | LV46: 2 | LW46: 25 | LX46: 11 | LY46: 2 | LZ46: 33 | MA46: 13 | MB46: 2 | MC46: 7 | MD46: 3 | ME46: 6 | MF46: 0 | MG46: 6 | MH46: 50 | MI46: 2 | MJ46: 116 | MK46: 40 | ML46: 1 | MM46: 5 | MN46: 15 | MO46: 20 | MQ46: 10 | MR46: 1 | MS46: 17 | MT46: 30 | MU46: 5 | MV46: 55 | MW46: 0 | MX46: 1 | MY46: 22 | MZ46: 52 | NA46: 3 | NB46: 1 | NC46: 1 | ND46: 13 | NE46: 69 | NJ46: 0 | NL46: 0 | NM46: 7 | NN46: 664 | NO46: 61 | NP46: 69 | NR46: 8 | NS46: 5 | NT46: 5 | NV46: 17 | NW46: 0 | NX46: 0 | NY46: 3 | NZ46: 42 | OA46: 12 | OB46: 35 | OD46: 15 | OE46: 44 | OG46: 1 | OH46: 4 | OI46: 1005 | OJ46: 22 | OK46: 387 | OO46: 22631 | OP46: 6760 | OS46: 9663 | OT46: 619 | OU46: 115 | OV46: 918 | PB46: 20 | PI46: 40727 | PM46: =IFERROR(VLOOKUP($A46&"",Key!$A:$C,3,FALSE),"") -> ISIC 16
A47: 327100 | B47: Clay product and refractory manufacturing | Z47: 0 | AA47: 1185 | AB47: 1213 | AC47: 524 | AD47: 263 | AE47: 1411 | AF47: 370 | AG47: 1906 | AH47: 523 | AI47: 558 | AJ47: 469 | AK47: 1210 | AL47: 789 | AP47: 7 | AQ47: 733 | AR47: 115 | AS47: 66 | AT47: 53 | AU47: 10 | AV47: 19 | AW47: 15 | AY47: 82 | BB47: 1 | BC47: 463 | BD47: 82 | BH47: 164 | BI47: 8 | BK47: 29 | BQ47: 13 | BS47: 31 | BT47: 17 | BX47: 8 | BZ47: 24 | CF47: 4 | CQ47: 1 | CZ47: 58 | DK47: 10 | DO47: 15 | EG47: 20 | EH47: 3 | EI47: 52 | EJ47: 1 | EQ47: 0 | ER47: 9 | EX47: 10 | EY47: 10 | EZ47: 10 | FC47: 177 | FD47: 39 | FZ47: 8 | GB47: 7 | GG47: 5 | IE47: 3 | II47: 3 | IM47: 11 | JG47: 129 | JV47: 67 | JW47: 21 | JX47: 17 | JY47: 11 | KB47: 7 | KC47: 67 | KD47: 39 | KK47: 1 | KV47: 484 | KW47: 1222 | KX47: 75 | KZ47: 36 | LK47: 2 | LW47: 132 | LZ47: 58 | MF47: 1 | MG47: 0 | MP47: 8 | MQ47: 2 | MR47: 0 | MU47: 18 | MW47: 0 | MZ47: 1114 | NA47: 55 | NB47: 7 | NC47: 5 | ND47: 16 | NE47: 5 | NM47: 28 | NN47: 2 | NO47: 193 | NP47: 73 | NQ47: 22 | NR47: 0 | NT47: 2 | NZ47: 1 | OB47: 16 | OD47: 60 | OE47: 73 | OI47: 81 | OJ47: 25 | OK47: 1 | OM47: 2 | ON47: 74 | OO47: 17071 | OP47: 4685 | OU47: 135 | OV47: 1990 | PI47: 23880 | PM47: =IFERROR(VLOOKUP($A47&"",Key!$A:$C,3,FALSE),"") -> ISIC 239
A48: 327200 | B48: Glass and glass product manufacturing | O48: 0 | AA48: 128 | AB48: 1313 | AC48: 102 | AD48: 39 | AE48: 2443 | AF48: 159 | AG48: 270 | AH48: 35 | AI48: 235 | AK48: 157 | AL48: 70 | AO48: 251 | AP48: 14 | AQ48: 12 | AR48: 3058 | AS48: 28 | AT48: 206 | AU48: 30 | AV48: 43 | AW48: 11 | BA48: 597 | BB48: 4 | BD48: 17 | BK48: 5 | BR48: 430 | BV48: 5 | BX48: 32 | CF48: 15 | CM48: 151 | CO48: 5 | DO48: 102 | DP48: 4 | DQ48: 32 | DS48: 6 | DU48: 26 | DV48: 4 | DW48: 19 | DX48: 57 | DZ48: 52 | EC48: 58 | ED48: 11 | EM48: 1155 | EQ48: 2058 | ER48: 1546 | ES48: 255 | ET48: 230 | EU48: 2 | EV48: 15 | EW48: 73 | EX48: 46 | EY48: 44 | EZ48: 34 | FC48: 519 | FD48: 168 | FK48: 274 | FL48: 111 | FQ48: 13 | FR48: 63 | FS48: 2 | FT48: 25 | FU48: 44 | FV48: 88 | FX48: 4 | FY48: 73 | FZ48: 10 | GA48: 6 | GB48: 9 | GM48: 2 | GP48: 6 | GR48: 163 | GS48: 74 | GT48: 142 | GU48: 31 | HA48: 9 | HB48: 146 | HC48: 49 | HD48: 0 | HE48: 87 | HF48: 23 | HG48: 115 | HH48: 2195 | HI48: 895 | HJ48: 639 | HM48: 44 | IE48: 4 | IF48: 821 | II48: 2 | IK48: 6 | IL48: 21 | IM48: 87 | IO48: 23 | IP48: 22 | IQ48: 41 | IR48: 228 | IT48: 1 | IV48: 2 | IX48: 150 | IZ48: 343 | JA48: 1 | JB48: 67 | JC48: 40 | JD48: 19 | JE48: 52 | JG48: 729 | JL48: 0 | JN48: 2 | JO48: 1 | JP48: 1 | JQ48: 21 | JS48: 38 | JV48: 53 | JW48: 47 | JZ48: 0 | KC48: 45 | KH48: 31 | KI48: 0 | KK48: 10 | KL48: 22 | KM48: 12 | KO48: 0 | KP48: 0 | KQ48: 2 | KR48: 3 | KS48: 2 | KW48: 56 | KX48: 324 | KZ48: 3 | LC48: 40 | LD48: 43 | LE48: 27 | LF48: 18 | LI48: 23 | LN48: 39 | LO48: 5 | LP48: 5 | LQ48: 56 | LR48: 1 | LU48: 2 | LW48: 51 | LX48: 17 | LY48: 574 | LZ48: 884 | MA48: 27 | MB48: 270 | ME48: 4 | MF48: 59 | MG48: 0 | MH48: 73 | MI48: 97 | MJ48: 33 | MK48: 34 | MN48: 19 | MO48: 10 | MP48: 22 | MQ48: 17 | MR48: 70 | MS48: 971 | MT48: 519 | MU48: 167 | MV48: 32 | MW48: 46 | MX48: 1247 | MY48: 20 | MZ48: 1468 | NA48: 148 | NB48: 20 | NC48: 3 | ND48: 4 | NE48: 1 | NH48: 5 | NM48: 9 | NN48: 161 | NO48: 88 | NP48: 718 | NQ48: 232 | NR48: 422 | NS48: 2 | NT48: 3 | NU48: 2 | NV48: 6 | NW48: 0 | NX48: 0 | NZ48: 10 | OB48: 21 | OD48: 6 | OE48: 623 | OI48: 61 | OJ48: 89 | OK48: 174 | ON48: 1 | OO48: 34848 | OP48: 10837 | OU48: 333 | OV48: 5131 | PI48: 51149 | PM48: =IFERROR(VLOOKUP($A48&"",Key!$A:$C,3,FALSE),"") -> ISIC 231
A49: 327310 | B49: Cement manufacturing | N49: 1 | P49: 658 | Q49: 1 | R49: 1 | V49: 101 | W49: 399 | Z49: 0 | AA49: 35 | AB49: 106 | AC49: 314 | AD49: 96 | AE49: 173 | AF49: 47 | AG49: 239 | AH49: 24 | AI49: 108 | AJ49: 126 | AK49: 298 | AL49: 135 | AS49: 111 | AT49: 6908 | AU49: 581 | AV49: 657 | AW49: 27 | AZ49: 13 | BA49: 3 | BB49: 783 | CZ49: 39 | DK49: 1 | DO49: 4 | FC49: 40 | JG49: 53 | JK49: 0 | JL49: 0 | JM49: 0 | JN49: 0 | JR49: 0 | JT49: 0 | JY49: 1 | KB49: 1 | KC49: 1 | KD49: 2 | KF49: 16 | KW49: 3 | KX49: 19 | KZ49: 23 | LK49: 0 | LO49: 22 | LW49: 92 | LZ49: 10 | MQ49: 1 | MS49: 7 | MY49: 1 | MZ49: 6 | NC49: 3 | ND49: 4 | NE49: 4 | NM49: 5 | NO49: 23 | NP49: 10 | NQ49: 4 | OB49: 3 | OL49: 7 | ON49: 15 | OO49: 12368 | OU49: 45 | OV49: 163 | PI49: 12575 | PM49: =IFERROR(VLOOKUP($A49&"",Key!$A:$C,3,FALSE),"") -> ISIC 239
A50: 327320 | B50: Ready-mix concrete manufacturing | M50: 44 | O50: 28 | Q50: 29 | X50: 2 | Z50: 0 | AA50: 66 | AB50: 19 | AC50: 3530 | AD50: 2339 | AE50: 2206 | AF50: 5590 | AG50: 13567 | AH50: 2128 | AI50: 2086 | AJ50: 983 | AK50: 7337 | AL50: 4707 | AT50: 339 | AU50: 84 | AV50: 480 | CZ50: 9 | FA50: 10 | FC50: 23 | GG50: 12 | JG50: 10 | JK50: 0 | JL50: 5 | JM50: 1 | JN50: 1 | JO50: 32 | JR50: 0 | JT50: 0 | JY50: 60 | KB50: 10 | KC50: 158 | KD50: 66 | KF50: 0 | KO50: 0 | KP50: 0 | KQ50: 0 | KR50: 0 | KW50: 40 | KX50: 254 | KY50: 9 | KZ50: 416 | LK50: 151 | LL50: 24 | LM50: 110 | LO50: 250 | LR50: 0 | LW50: 736 | LZ50: 240 | MF50: 5 | MP50: 0 | MQ50: 10 | MR50: 0 | MS50: 111 | MY50: 2 | MZ50: 34 | NA50: 0 | NB50: 0 | NC50: 45 | ND50: 115 | NE50: 51 | NF50: 3 | NM50: 63 | NO50: 132 | NP50: 32 | NQ50: 10 | NR50: 1 | NS50: 0 | NT50: 5 | NU50: 1 | NZ50: 22 | OB50: 35 | OD50: 0 | OE50: 17 | OI50: 36 | OK50: 446 | OL50: 107 | ON50: 1481 | OO50: 50962 | OU50: 143 | OV50: 92 | PI50: 51196 | PM50: =IFERROR(VLOOKUP($A50&"",Key!$A:$C,3,FALSE),"") -> ISIC 239
A51: 327330 | B51: Concrete pipe, brick, and block manufacturing | C51: 1 | H51: 33 | Q51: 11 | Z51: 0 | AA51: 25 | AB51: 59 | AC51: 713 | AD51: 363 | AE51: 954 | AF51: 403 | AG51: 1704 | AH51: 78 | AI51: 650 | AJ51: 56 | AK51: 2002 | AL51: 453 | AU51: 13 | DK51: 4 | DO51: 23 | FC51: 147 | JG51: 281 | JK51: 0 | JL51: 1 | JM51: 0 | JN51: 0 | JR51: 0 | JT51: 0 | JV51: 29 | JY51: 2 | KB51: 13 | KC51: 76 | KD51: 41 | KF51: 1 | KW51: 21 | KX51: 137 | KY51: 3 | KZ51: 57 | LK51: 1 | LL51: 4 | LW51: 585 | LZ51: 62 | MF51: 1 | MO51: 0 | MP51: 1 | MQ51: 6 | MR51: 0 | MS51: 20 | MU51: 40 | MZ51: 17 | NA51: 0 | NC51: 7 | ND51: 16 | NE51: 9 | NF51: 2 | NM51: 21 | NN51: 2 | NO51: 74 | NP51: 136 | NQ51: 39 | OB51: 31 | OI51: 6 | OK51: 52 | OL51: 9 | ON51: 379 | OO51: 9872 | OU51: 22 | OV51: 46 | PI51: 9940 | PM51: =IFERROR(VLOOKUP($A51&"",Key!$A:$C,3,FALSE),"") -> ISIC 239
A52: 327390 | B52: Other concrete product manufacturing | Q52: 0 | X52: 77 | Z52: 1 | AA52: 52 | AB52: 61 | AC52: 894 | AD52: 268 | AE52: 3140 | AF52: 1803 | AG52: 644 | AH52: 664 | AI52: 1463 | AJ52: 233 | AK52: 970 | AL52: 1968 | AQ52: 2 | AS52: 5 | AT52: 42 | AU52: 15 | AV52: 154 | BB52: 80 | BD52: 3 | BK52: 1 | CZ52: 198 | DK52: 12 | DO52: 29 | ER52: 7 | EX52: 10 | EY52: 11 | EZ52: 7 | FA52: 45 | FC52: 157 | FD52: 35 | FZ52: 2 | GB52: 1 | GD52: 0 | JG52: 659 | JK52: 0 | JL52: 1 | JM52: 0 | JN52: 39 | JO52: 6 | JQ52: 2 | JR52: 2 | JS52: 1 | JT52: 0 | JV52: 120 | JW52: 1 | JX52: 439 | JY52: 11 | JZ52: 0 | KA52: 1 | KB52: 25 | KC52: 72 | KD52: 67 | KJ52: 0 | KN52: 0 | KU52: 1 | KW52: 73 | KX52: 467 | KZ52: 239 | LB52: 0 | LM52: 9 | LO52: 114 | LR52: 0 | LT52: 0 | LV52: 0 | LW52: 396 | LX52: 0 | LZ52: 128 | MF52: 6 | MH52: 129 | MK52: 1 | MO52: 208 | MR52: 0 | MS52: 5 | MT52: 2 | MU52: 54 | MV52: 1 | MX52: 0 | MY52: 4 | MZ52: 92 | NA52: 0 | NB52: 0 | NC52: 28 | ND52: 38 | NE52: 35 | NF52: 1 | NG52: 0 | NJ52: 0 | NK52: 0 | NL52: 1 | NM52: 37 | NN52: 5 | NO52: 142 | NP52: 218 | NQ52: 63 | NR52: 0 | NS52: 0 | NV52: 2 | NW52: 684 | OA52: 0 | OB52: 68 | OE52: 0 | OI52: 0 | OK52: 204 | OM52: 35 | ON52: 681 | OO52: 18674 | OP52: 143 | OU52: 42 | OV52: 277 | PI52: 19136 | PM52: =IFERROR(VLOOKUP($A52&"",Key!$A:$C,3,FALSE),"") -> ISIC 239
A53: 327400 | B53: Lime and gypsum product manufacturing | C53: 1 | N53: 5 | R53: 32 | S53: 176 | AA53: 13 | AB53: 10 | AC53: 769 | AD53: 436 | AE53: 416 | AF53: 177 | AG53: 1393 | AH53: 39 | AI53: 375 | AJ53: 99 | AK53: 1200 | AL53: 148 | AN53: 19 | AP53: 93 | AQ53: 13 | AR53: 72 | AS53: 81 | AW53: 11 | AX53: 2 | AZ53: 30 | BB53: 32 | BC53: 643 | BD53: 9 | CZ53: 124 | DK53: 2 | DO53: 2 | FA53: 29 | FC53: 129 | FY53: 208 | FZ53: 21 | GB53: 10 | HT53: 113 | HU53: 136 | HV53: 437 | JG53: 136 | JK53: 2 | JL53: 1 | JM53: 0 | JN53: 0 | JR53: 0 | JT53: 0 | JY53: 7 | KB53: 6 | KC53: 4 | KD53: 15 | KW53: 51 | KX53: 329 | KY53: 9 | KZ53: 3 | LA53: 3 | LK53: 2 | LO53: 117 | LT53: 274 | LW53: 316 | LY53: 52 | LZ53: 65 | MF53: 3 | MH53: 11 | MJ53: 791 | MO53: 20 | MQ53: 2 | MY53: 2 | MZ53: 88 | NC53: 20 | ND53: 43 | NE53: 27 | NM53: 28 | NO53: 85 | NP53: 240 | NQ53: 60 | OB53: 101 | OD53: 0 | OE53: 42 | OI53: 1 | OJ53: 30 | ON53: 371 | OO53: 10865 | OP53: 71 | OU53: 55 | OV53: 283 | PI53: 11274 | PM53: =IFERROR(VLOOKUP($A53&"",Key!$A:$C,3,FALSE),"") -> ISIC 239
A54: 327910 | B54: Abrasive product manufacturing | P54: 32 | AA54: 11 | AB54: 258 | AC54: 110 | AD54: 25 | AE54: 74 | AF54: 29 | AG54: 77 | AH54: 17 | AI54: 244 | AJ54: 35 | AK54: 152 | AL54: 200 | AM54: 96 | AN54: 22 | AO54: 22 | AP54: 38 | AQ54: 12 | AR54: 4 | AS54: 15 | AT54: 74 | AU54: 16 | AV54: 34 | AW54: 23 | AX54: 318 | AY54: 71 | BA54: 42 | BC54: 27 | BD54: 5 | BE54: 6 | BF54: 0 | BG54: 8 | BI54: 4 | BJ54: 5 | BK54: 161 | BL54: 17 | BN54: 4 | BO54: 20 | BP54: 35 | BQ54: 319 | BR54: 47 | BS54: 17 | BT54: 10 | BU54: 6 | BV54: 104 | BW54: 3 | BX54: 147 | BY54: 138 | BZ54: 146 | CA54: 15 | CB54: 50 | CC54: 21 | CD54: 4 | CE54: 56 | CF54: 55 | CG54: 14 | CH54: 7 | CI54: 29 | CJ54: 84 | CK54: 20 | CL54: 191 | CO54: 26 | CP54: 6 | CQ54: 38 | CR54: 7 | CS54: 49 | CT54: 39 | CU54: 78 | CV54: 84 | CW54: 162 | CX54: 3 | CY54: 3 | CZ54: 28 | DA54: 26 | DB54: 85 | DC54: 59 | DD54: 11 | DE54: 7 | DF54: 1 | DG54: 51 | DH54: 211 | DK54: 0 | DM54: 14 | DO54: 10 | DP54: 6 | DQ54: 7 | DS54: 23 | DT54: 0 | DU54: 5 | DV54: 1 | DW54: 9 | DX54: 7 | DZ54: 10 | EC54: 0 | EE54: 6 | EF54: 3 | EG54: 2 | EH54: 4 | EI54: 5 | EJ54: 12 | EM54: 0 | EN54: 72 | EP54: 4 | ER54: 8 | ES54: 15 | ET54: 62 | EU54: 3 | EV54: 1 | EW54: 3 | EX54: 17 | EY54: 13 | EZ54: 8 | FA54: 24 | FB54: 45 | FC54: 187 | FD54: 48 | FE54: 124 | FF54: 0 | FG54: 17 | FI54: 1 | FJ54: 7 | FK54: 15 | FL54: 7 | FN54: 0 | FO54: 2 | FP54: 11 | FQ54: 37 | FR54: 10 | FS54: 17 | FT54: 37 | FU54: 23 | FV54: 64 | FW54: 14 | FX54: 114 | FY54: 48 | FZ54: 6 | GA54: 4 | GB54: 6 | GC54: 4 | GD54: 31 | GE54: 2 | GF54: 6 | GG54: 197 | GH54: 75 | GO54: 3 | GP54: 0 | GQ54: 0 | GW54: 1 | HA54: 0 | HH54: 0 | HU54: 11 | HV54: 10 | IB54: 1 | IL54: 2 | IM54: 1 | IN54: 1 | IW54: 0 | IX54: 0 | IZ54: 8 | JA54: 9 | JB54: 6 | JD54: 4 | JE54: 1 | JF54: 2 | JG54: 46 | JJ54: 7 | JL54: 3 | JN54: 4 | JO54: 6 | JV54: 6 | JZ54: 2 | KD54: 2 | KM54: 81 | KW54: 3 | KX54: 19 | KZ54: 9 | LN54: 34 | LO54: 62 | LZ54: 20 | MA54: 10 | ME54: 1 | MH54: 0 | MK54: 9 | MM54: 18 | MN54: 6 | MQ54: 0 | MZ54: 0 | NC54: 1 | NE54: 1 | NM54: 4 | NR54: 3 | NT54: 186 | NU54: 100 | OD54: 3 | OE54: 83 | OI54: 15 | OJ54: 552 | OK54: 6 | ON54: 4 | OO54: 7686 | OP54: 382 | OU54: 45 | OV54: 1214 | PI54: 9326 | PM54: =IFERROR(VLOOKUP($A54&"",Key!$A:$C,3,FALSE),"") -> ISIC 239
A55: 327991 | B55: Cut stone and stone product manufacturing | AA55: 349 | AB55: 2985 | AC55: 44 | AD55: 20 | AE55: 584 | AF55: 187 | AG55: 386 | AI55: 33 | AJ55: 44 | AK55: 725 | AL55: 1 | AQ55: 17 | AY55: 295 | FZ55: 15 | GB55: 14 | KW55: 38 | KX55: 244 | KY55: 7 | LZ55: 60 | MF55: 2 | MQ55: 2 | NF55: 2 | NP55: 117 | NQ55: 40 | OD55: 72 | OI55: 123 | OK55: 3 | ON55: 29 | OO55: 6440 | OP55: 5100 | OU55: 22 | OV55: 96 | PI55: 11659 | PM55: =IFERROR(VLOOKUP($A55&"",Key!$A:$C,3,FALSE),"") -> ISIC 239
A56: 327992 | B56: Ground or treated mineral and earth manufacturing | Q56: 321 | R56: 23 | V56: 310 | W56: 517 | AC56: 2 | AD56: 78 | AG56: 163 | AJ56: 1 | AK56: 31 | AQ56: 128 | AR56: 149 | AS56: 123 | AT56: 49 | AU56: 12 | AV56: 22 | AW56: 248 | AX56: 23 | AY56: 109 | AZ56: 437 | BC56: 769 | BD56: 159 | BK56: 2 | EO56: 278 | ER56: 2 | EX56: 8 | EY56: 8 | EZ56: 2 | FC56: 94 | FD56: 49 | FS56: 5 | FZ56: 9 | GB56: 9 | GF56: 4 | GH56: 245 | IF56: 133 | IG56: 11 | IM56: 2 | IS56: 202 | IU56: 1004 | IZ56: 112 | LK56: 0 | OE56: 2 | OO56: 5851 | OP56: 80 | OU56: -116 | OV56: 352 | PI56: 6167 | PM56: =IFERROR(VLOOKUP($A56&"",Key!$A:$C,3,FALSE),"") -> ISIC 239
A57: 327993 | B57: Mineral wool manufacturing | AA57: 63 | AB57: 241 | AC57: 8 | AD57: 272 | AE57: 251 | AF57: 212 | AG57: 2846 | AH57: 220 | AI57: 187 | AJ57: 29 | AK57: 1565 | AL57: 92 | AN57: 3 | AO57: 217 | AP57: 75 | AQ57: 10 | AR57: 181 | AS57: 39 | AT57: 182 | AU57: 41 | AV57: 84 | AW57: 6 | BA57: 7 | BC57: 1 | BD57: 12 | BK57: 5 | CQ57: 105 | EE57: 37 | EF57: 139 | EM57: 17 | EQ57: 2 | ER57: 32 | EX57: 36 | EY57: 35 | EZ57: 31 | FC57: 523 | FD57: 134 | FZ57: 1 | GB57: 1 | IE57: 6 | KD57: 0 | LK57: 2 | LL57: 1 | LW57: 29 | LZ57: 27 | MF57: 1 | MH57: 38 | MO57: 63 | OM57: 21 | ON57: 67 | OO57: 8189 | OU57: 20 | OV57: 970 | PI57: 9178 | PM57: =IFERROR(VLOOKUP($A57&"",Key!$A:$C,3,FALSE),"") -> ISIC 239
A58: 327999 | B58: Miscellaneous nonmetallic mineral products | AA58: 0 | AB58: 15 | AC58: 21 | AD58: 8 | AE58: 124 | AF58: 554 | AG58: 194 | AH58: 54 | AI58: 226 | AJ58: 35 | AK58: 1219 | AL58: 713 | AQ58: 12 | AS58: 25 | AT58: 121 | AU58: 10 | AV58: 28 | AW58: 15 | AX58: 8 | AY58: 35 | BB58: 156 | BD58: 7 | BK58: 2 | CG58: 312 | CJ58: 531 | CT58: 21 | CV58: 69 | EO58: 208 | EQ58: 0 | ER58: 18 | ES58: 1 | EX58: 21 | EY58: 21 | EZ58: 17 | FC58: 279 | FD58: 80 | FZ58: 4 | GB58: 4 | IE58: 56 | IF58: 1184 | JN58: 0 | KH58: 192 | LA58: 0 | LB58: 0 | LM58: 11 | LY58: 4 | LZ58: 22 | MQ58: 0 | MZ58: 66 | OD58: 11 | ON58: 84 | OO58: 6801 | OU58: 13 | OV58: 618 | PI58: 7431 | PM58: =IFERROR(VLOOKUP($A58&"",Key!$A:$C,3,FALSE),"") -> ISIC 239
A59: 331110 | B59: Iron and steel mills and ferroalloy manufacturing | P59: 1735 | Q59: 28 | R59: 23 | S59: 140 | T59: 84 | U59: 239 | V59: 238 | W59: 284 | AA59: 5 | AB59: 2 | AC59: 550 | AE59: 12 | AF59: 235 | AG59: 147 | AI59: 192 | AJ59: 46 | AK59: 227 | AL59: 40 | AO59: 5 | AP59: 113 | AU59: 30 | AV59: 102 | AX59: 47 | AZ59: 214 | BA59: 26 | BB59: 3 | BC59: 8615 | BD59: 8992 | BG59: 58 | BJ59: 71 | BK59: 984 | BM59: 2287 | BN59: 2084 | BO59: 2778 | BP59: 1268 | BQ59: 13942 | BR59: 8728 | BS59: 794 | BT59: 1708 | BU59: 972 | BV59: 949 | BW59: 689 | BX59: 2326 | BY59: 2839 | BZ59: 1078 | CA59: 11 | CB59: 949 | CC59: 302 | CD59: 1218 | CE59: 153 | CF59: 2077 | CG59: 3076 | CH59: 339 | CI59: 3609 | CJ59: 1784 | CK59: 37 | CL59: 1104 | CM59: 39 | CN59: 2 | CO59: 681 | CP59: 576 | CQ59: 1717 | CR59: 476 | CS59: 292 | CT59: 262 | CU59: 497 | CV59: 383 | CW59: 369 | CX59: 55 | CY59: 344 | CZ59: 619 | DA59: 138 | DB59: 519 | DC59: 4902 | DD59: 188 | DE59: 28 | DF59: 133 | DG59: 2070 | DH59: 533 | DJ59: 1 | DK59: 2 | DL59: 71 | DM59: 42 | DN59: 9 | DO59: 64 | DP59: 60 | DQ59: 183 | DR59: 60 | DS59: 13 | DT59: 8 | DU59: 30 | DV59: 17 | DW59: 6 | DX59: 103 | DY59: 41 | DZ59: 9 | EA59: 15 | EB59: 0 | ED59: 102 | EE59: 37 | EF59: 1233 | EG59: 370 | EH59: 129 | EI59: 742 | EJ59: 222 | EK59: 340 | EL59: 23 | EM59: 17 | EN59: 554 | EP59: 32 | EQ59: 12 | ER59: 2177 | ES59: 97 | ET59: 901 | EU59: 674 | EV59: 5 | EW59: 344 | EX59: 476 | EY59: 246 | EZ59: 525 | FA59: 59 | FB59: 13254 | FC59: 1828 | FD59: 1476 | FE59: 4190 | FF59: 20 | FG59: 204 | FH59: 19 | FI59: 14 | FJ59: 1002 | FK59: 377 | FL59: 56 | FM59: 261 | FN59: 749 | FO59: 452 | FQ59: 204 | FR59: 0 | FS59: 191 | FT59: 203 | FU59: 632 | FV59: 648 | FW59: 23 | FX59: 263 | FY59: 150 | FZ59: 11 | GB59: 17 | GC59: 6 | GD59: 166 | GE59: 5 | GF59: 9 | GG59: 553 | GH59: 1062 | HQ59: 17 | HW59: 61 | IB59: 1 | IC59: 15 | IJ59: 11 | IK59: 41 | IL59: 1 | IZ59: 1 | JG59: 73 | JJ59: 862 | JL59: 0 | JN59: 0 | JO59: 251 | JP59: 23 | JQ59: 1 | JS59: 4 | JV59: 6 | JX59: 0 | KB59: 1 | KC59: 0 | KD59: 0 | KF59: 229 | KK59: 152 | KN59: 2 | KP59: 5 | KQ59: 3 | KS59: 1 | KT59: 2 | KU59: 23 | KV59: 10 | KW59: 49 | KX59: 12 | KY59: 11 | KZ59: 13 | LA59: 113 | LB59: 0 | LM59: 2775 | LO59: 62 | LV59: 4 | LW59: 468 | LZ59: 175 | MF59: 31 | MH59: 260 | MM59: 215 | MO59: 303 | MR59: 159 | MS59: 4 | MT59: 7 | MU59: 26 | MV59: 62 | MW59: 2 | MX59: 9 | MY59: 33 | MZ59: 3 | NA59: 8 | NB59: 7 | NC59: 8 | ND59: 20 | NE59: 214 | NG59: 1 | NI59: 21 | NK59: 0 | NL59: 23 | NM59: 255 | NN59: 31 | NO59: 2 | NP59: 10 | NQ59: 3 | NR59: 12 | NS59: 31 | NT59: 111 | NU59: 63 | NV59: 105 | NW59: 0 | NX59: 0 | NY59: 7 | OA59: 4 | OB59: 26 | OI59: 9 | ON59: 175 | OO59: 141254 | OU59: 1200 | OV59: 13196 | PI59: 155649 | PM59: =IFERROR(VLOOKUP($A59&"",Key!$A:$C,3,FALSE),"") -> ISIC 241
A60: 331200 | B60: Steel product manufacturing from purchased steel | C60: 3 | D60: 30 | E60: 3 | F60: 2 | G60: 3 | H60: 17 | I60: 16 | J60: 7 | K60: 1 | L60: 1 | P60: 1273 | Q60: 5 | R60: 1 | S60: 14 | T60: 9 | U60: 24 | V60: 18 | W60: 17 | AA60: 162 | AB60: 725 | AC60: 435 | AD60: 140 | AE60: 274 | AF60: 48 | AG60: 322 | AH60: 13 | AI60: 110 | AJ60: 85 | AK60: 272 | AL60: 68 | AN60: 4 | AU60: 192 | AV60: 854 | BC60: 744 | BD60: 270 | BJ60: 3 | BO60: 38 | BP60: 70 | BQ60: 1019 | BR60: 49 | BS60: 12 | BT60: 8 | BV60: 51 | BW60: 1723 | BX60: 301 | BY60: 1836 | CB60: 8 | CE60: 18 | CF60: 168 | CK60: 11 | CL60: 391 | CQ60: 100 | CR60: 1 | DG60: 162 | DP60: 6 | DQ60: 5 | ED60: 305 | EE60: 3 | EG60: 1 | EH60: 93 | EM60: 89 | EX60: 16 | EY60: 4 | EZ60: 1 | FB60: 114 | FC60: 16 | FD60: 1 | FR60: 4 | FS60: 7 | FY60: 2 | GG60: 4 | GH60: 30 | HQ60: 70 | JG60: 3 | JH60: 385 | JI60: 117 | JJ60: 119 | JK60: 4 | JL60: 3 | JM60: 1 | JO60: 33 | JS60: 12 | JT60: 2 | JV60: 1 | JZ60: 1 | KB60: 1 | KQ60: 1 | KW60: 1 | KX60: 10 | KZ60: 17 | LK60: 0 | LO60: 10 | LX60: 3 | LZ60: 0 | MA60: 7 | MN60: 3 | MQ60: 1 | MS60: 1 | MT60: 1 | MV60: 49 | MZ60: 8 | NC60: 2 | ND60: 1 | NE60: 3 | NF60: 0 | NM60: 2 | NN60: 1 | NO60: 3 | NT60: 0 | OA60: 1 | OB60: 5 | OE60: 32 | OI60: 10 | OJ60: 14 | OK60: 35 | ON60: 1 | OO60: 13806 | OP60: 1300 | OU60: -53 | OV60: 819 | PI60: 15872 | PM60: =IFERROR(VLOOKUP($A60&"",Key!$A:$C,3,FALSE),"") -> ISIC 241
A61: 331313 | B61: Alumina refining and primary aluminum production | AC61: 14 | AP61: 34 | BC61: 400 | BD61: 66 | BE61: 805 | BF61: 803 | BG61: 9560 | BI61: 10 | BJ61: 1 | BK61: 14 | BL61: 1339 | BM61: 73 | BN61: 419 | BO61: 32 | BP61: 57 | BR61: 74 | BS61: 140 | BT61: 8 | BU61: 1082 | BV61: 86 | BW61: 27 | BX61: 277 | BZ61: 25 | CB61: 20 | CD61: 8 | CE61: 79 | CF61: 6 | CK61: 6 | CL61: 56 | CM61: 53 | CO61: 1 | CP61: 11 | CQ61: 32 | CR61: 52 | CS61: 35 | CT61: 20 | CV61: 7 | DA61: 39 | DB61: 121 | DC61: 70 | DE61: 18 | DF61: 12 | DG61: 234 | DH61: 3 | DJ61: 0 | DK61: 0 | DL61: 9 | DM61: 28 | DN61: 6 | DO61: 1 | DP61: 2 | DQ61: 41 | DS61: 21 | DT61: 1 | DU61: 15 | DV61: 6 | DW61: 3 | DX61: 43 | DZ61: 2 | EB61: 0 | ED61: 28 | EE61: 1 | EF61: 88 | EG61: 1 | EH61: 24 | EN61: 24 | EP61: 94 | EQ61: 3 | ER61: 544 | ES61: 20 | ET61: 5 | EU61: 10 | EV61: 19 | EW61: 333 | EX61: 54 | EY61: 63 | EZ61: 363 | FA61: 5 | FB61: 22 | FC61: 84 | FD61: 90 | FE61: 9 | FF61: 0 | FG61: 39 | FH61: 34 | FI61: 3 | FK61: 13 | FL61: 12 | FM61: 55 | FN61: 1250 | FO61: 45 | FQ61: 46 | FR61: 0 | FS61: 90 | FT61: 137 | FU61: 117 | FV61: 118 | FW61: 70 | FY61: 4 | FZ61: 1 | GB61: 1 | GC61: 1 | GD61: 18 | GH61: 55 | GI61: 1 | GJ61: 1 | GO61: 1 | GP61: 2 | GR61: 1 | GS61: 1 | GT61: 1 | GU61: 1 | GV61: 1 | GW61: 0 | GX61: 1 | GY61: 1 | HA61: 1 | HB61: 1 | HC61: 1 | HD61: 1 | HE61: 1 | HF61: 1 | HG61: 1 | IE61: 3 | KN61: 3 | KP61: 6 | KQ61: 3 | KS61: 1 | KT61: 3 | KU61: 25 | KV61: 12 | KW61: 51 | KY61: 12 | KZ61: 11 | LA61: 118 | LB61: 0 | LW61: 87 | LZ61: 23 | MF61: 9 | MH61: 41 | MM61: 1 | MO61: 67 | NT61: 13 | OD61: 115 | OE61: 51 | OM61: 9 | ON61: 41 | OO61: 21122 | OU61: 157 | OV61: 742 | PI61: 22021 | PM61: =IFERROR(VLOOKUP($A61&"",Key!$A:$C,3,FALSE),"") -> ISIC 242
A62: 33131B | B62: Aluminum product manufacturing from purchased aluminum | AA62: 7 | AB62: 20 | AC62: 40 | AD62: 6 | AE62: 13 | AF62: 3 | AG62: 36 | AI62: 6 | AJ62: 26 | AK62: 23 | AL62: 6 | AO62: 20 | AP62: 31 | AV62: 42 | BA62: 20 | BE62: 235 | BF62: 41 | BG62: 3944 | BI62: 10 | BJ62: 2 | BM62: 394 | BN62: 16 | BO62: 245 | BP62: 90 | BQ62: 476 | BR62: 2416 | BS62: 342 | BT62: 165 | BU62: 4005 | BV62: 201 | BW62: 60 | BX62: 575 | BY62: 620 | CA62: 11 | CB62: 2 | CD62: 42 | CE62: 3 | CF62: 1248 | CG62: 2 | CK62: 89 | CL62: 225 | CM62: 26 | CO62: 104 | CP62: 7 | CQ62: 998 | CR62: 48 | CS62: 147 | CT62: 310 | CV62: 71 | CW62: 111 | CX62: 9 | CY62: 19 | CZ62: 6 | DA62: 15 | DB62: 151 | DC62: 31 | DE62: 6 | DF62: 54 | DG62: 51 | DH62: 103 | DJ62: 0 | DK62: 1 | DL62: 0 | DM62: 31 | DN62: 3 | DO62: 17 | DP62: 130 | DQ62: 52 | DS62: 12 | DT62: 1 | DU62: 5 | DV62: 5 | DW62: 2 | DX62: 44 | DZ62: 2 | EB62: 0 | ED62: 734 | EE62: 0 | EF62: 61 | EG62: 13 | EH62: 7 | EI62: 119 | EJ62: 38 | EM62: 575 | EN62: 5 | EQ62: 7 | ER62: 1241 | ES62: 53 | ET62: 467 | EU62: 1027 | EV62: 6 | EW62: 50 | EX62: 22 | EY62: 41 | EZ62: 43 | FA62: 19 | FB62: 893 | FC62: 71 | FD62: 13 | FE62: 164 | FF62: 2 | FG62: 513 | FI62: 8 | FK62: 489 | FL62: 428 | FM62: 394 | FN62: 81 | FO62: 28 | FP62: 86 | FQ62: 262 | FR62: 1 | FS62: 92 | FT62: 204 | FU62: 139 | FV62: 209 | FW62: 118 | FY62: 8 | FZ62: 1 | GB62: 1 | GC62: 1 | GD62: 158 | GF62: 2 | GH62: 70 | GI62: 2 | GJ62: 3 | GO62: 3 | GP62: 5 | GR62: 2 | GS62: 3 | GT62: 3 | GU62: 2 | GV62: 2 | GW62: 1 | GX62: 2 | GY62: 2 | HA62: 3 | HB62: 3 | HC62: 2 | HD62: 2 | HE62: 2 | HF62: 2 | HG62: 2031 | HW62: 109 | HX62: 872 | JA62: 193 | JG62: 125 | JO62: 7 | KZ62: 6 | NO62: 1 | NP62: 25 | NQ62: 12 | OD62: 23 | OE62: 6 | OK62: 5 | OO62: 30752 | OU62: 211 | OV62: 4820 | PI62: 35783 | PM62: =IFERROR(VLOOKUP($A62&"",Key!$A:$C,3,FALSE),"") -> ISIC 242
A63: 331410 | B63: Nonferrous metal (except aluminum) smelting and refining | AC63: 5 | AP63: 27 | AX63: 3 | BA63: 12 | BC63: 3509 | BD63: 679 | BF63: 63 | BG63: 1135 | BH63: 4273 | BI63: 8081 | BJ63: 3800 | BK63: 730 | BL63: 326 | BN63: 5 | BQ63: 7 | BS63: 12 | BT63: 1 | BW63: 2 | BX63: 17 | BZ63: 44 | CA63: 34 | CB63: 40 | CD63: 19 | CF63: 28 | CK63: 176 | CL63: 10 | CM63: 7 | CO63: 1 | CQ63: 156 | CR63: 55 | DG63: 2 | DJ63: 0 | DK63: 1 | DO63: 1347 | DP63: 229 | DQ63: 714 | DT63: 4 | DU63: 2 | DV63: 3 | DW63: 1 | DX63: 19 | DZ63: 6 | EH63: 1 | EI63: 863 | EJ63: 96 | EK63: 2214 | EL63: 14 | EM63: 149 | EN63: 82 | EQ63: 6 | ER63: 905 | ES63: 35 | EX63: 0 | EZ63: 733 | FA63: 39 | FC63: 84 | FD63: 1 | FE63: 32 | FF63: 1 | FG63: 16 | FI63: 7 | FJ63: 82 | FM63: 90 | FZ63: 326 | GB63: 432 | GC63: 641 | GH63: 19 | HK63: 2 | IE63: 13 | JO63: 19 | JT63: 22 | KB63: 303 | LW63: 450 | LZ63: 98 | MF63: 1 | MM63: 7 | NT63: 28 | NU63: 307 | OD63: 9 | OE63: 166 | OI63: 12 | ON63: 208 | OO63: 34095 | OU63: 282 | OV63: 4683 | PI63: 39059 | PM63: =IFERROR(VLOOKUP($A63&"",Key!$A:$C,3,FALSE),"") -> ISIC 242
A64: 331420 | B64: Copper rolling, drawing, extruding and alloying | X64: 1 | Z64: 0 | AA64: 22 | AB64: 3 | AC64: 161 | AD64: 58 | AE64: 2 | AF64: 37 | AG64: 173 | AH64: 2 | AI64: 67 | AJ64: 352 | AK64: 198 | AL64: 53 | BG64: 123 | BI64: 6456 | BJ64: 10 | BL64: 292 | BN64: 6 | BO64: 101 | BP64: 18 | BQ64: 474 | BR64: 145 | BS64: 136 | BT64: 123 | BV64: 37 | BW64: 62 | BX64: 185 | BY64: 450 | CA64: 672 | CB64: 225 | CD64: 200 | CE64: 492 | CF64: 90 | CG64: 76 | CH64: 27 | CK64: 2 | CM64: 65 | CO64: 10 | CP64: 61 | CQ64: 1079 | CR64: 261 | CX64: 54 | CY64: 82 | CZ64: 89 | DC64: 34 | DD64: 83 | DG64: 74 | DI64: 4 | DJ64: 1 | DK64: 9 | DL64: 0 | DM64: 123 | DN64: 12 | DO64: 2 | DP64: 47 | DQ64: 155 | DR64: 601 | DS64: 75 | DT64: 13 | DU64: 24 | DV64: 41 | DW64: 20 | DX64: 115 | DY64: 116 | DZ64: 11 | EA64: 2 | ED64: 91 | EE64: 13 | EF64: 90 | EG64: 627 | EH64: 244 | EM64: 2843 | EN64: 105 | EP64: 275 | EX64: 62 | EY64: 1442 | EZ64: 538 | FB64: 292 | FC64: 108 | FD64: 934 | FE64: 142 | FF64: 0 | FG64: 5 | FN64: 17 | FZ64: 1 | GB64: 1 | GC64: 1 | GG64: 25 | GH64: 42 | JG64: 125 | JK64: 9 | JO64: 26 | JT64: 1 | KB64: 1 | KC64: 1 | KD64: 3 | KF64: 1 | KZ64: 49 | LK64: 0 | LZ64: 13 | MZ64: 8 | NC64: 4 | ND64: 3 | NE64: 9 | NL64: 3 | NM64: 7 | NN64: 1 | NO64: 30 | NP64: 6 | NQ64: 2 | NS64: 2 | OB64: 14 | OD64: 3 | OE64: 215 | ON64: 19 | OO64: 23246 | OU64: 59 | OV64: 2834 | PI64: 26138 | PM64: =IFERROR(VLOOKUP($A64&"",Key!$A:$C,3,FALSE),"") -> ISIC 242
A65: 331490 | B65: Nonferrous metal (except copper and aluminum) rolling, drawing, extruding and alloying | X65: 4 | AA65: 0 | AB65: 0 | AC65: 19 | AD65: 0 | AE65: 3 | AF65: 0 | AG65: 1 | AH65: 0 | AI65: 0 | AJ65: 2 | AK65: 0 | AL65: 2 | AU65: 1 | AV65: 16 | BC65: 328 | BD65: 274 | BG65: 34 | BH65: 120 | BI65: 94 | BJ65: 703 | BK65: 53 | BL65: 222 | BM65: 25 | BN65: 1189 | BO65: 70 | BP65: 38 | BQ65: 10 | BR65: 211 | BS65: 10 | BT65: 5 | BU65: 36 | BV65: 283 | BW65: 28 | BX65: 58 | BY65: 219 | BZ65: 261 | CA65: 6 | CB65: 10 | CC65: 2 | CD65: 17 | CE65: 96 | CF65: 57 | CG65: 44 | CH65: 24 | CI65: 4 | CJ65: 182 | CK65: 16 | CL65: 15 | CN65: 0 | CO65: 18 | CP65: 4 | CQ65: 54 | CR65: 13 | CS65: 8 | CT65: 87 | CU65: 4 | CV65: 132 | CW65: 47 | CY65: 1 | CZ65: 194 | DA65: 0 | DB65: 7 | DC65: 78 | DE65: 0 | DF65: 5 | DG65: 15 | DH65: 24 | DK65: 7 | DL65: 47 | DM65: 63 | DN65: 3 | DO65: 78 | DP65: 62 | DQ65: 208 | DR65: 95 | DS65: 101 | DT65: 31 | DU65: 19 | DV65: 45 | DW65: 5 | DX65: 24 | DY65: 4 | DZ65: 14 | EA65: 5 | EC65: 23 | ED65: 40 | EE65: 4 | EF65: 66 | EG65: 26 | EH65: 29 | EI65: 77 | EJ65: 63 | EK65: 76 | EL65: 103 | EM65: 1 | EN65: 49 | EO65: 1 | EP65: 446 | EQ65: 0 | ER65: 135 | ES65: 5 | ET65: 2 | EU65: 14 | EV65: 0 | EW65: 6 | EX65: 21 | EY65: 127 | EZ65: 225 | FA65: 27 | FB65: 31 | FC65: 20 | FD65: 115 | FE65: 22 | FF65: 1 | FG65: 2 | FH65: 20 | FJ65: 2 | FK65: 215 | FL65: 6 | FM65: 12 | FN65: 4 | FO65: 0 | FX65: 28 | FY65: 74 | FZ65: 16 | GB65: 15 | GC65: 17 | GD65: 10 | GG65: 42 | GH65: 292 | GI65: 7 | GJ65: 9 | GO65: 9 | GP65: 16 | GR65: 6 | GS65: 8 | GT65: 9 | GU65: 7 | GV65: 7 | GW65: 4 | GX65: 8 | GY65: 6 | HA65: 8 | HB65: 8 | HC65: 8 | HD65: 6 | HE65: 7 | HF65: 5 | HG65: 10 | JG65: 0 | JJ65: 4 | JO65: 80 | KB65: 0 | KW65: 206 | KX65: 39 | KY65: 24 | KZ65: 2 | LK65: 0 | LZ65: 80 | MF65: 3 | MM65: 10 | NC65: 0 | ND65: 0 | NE65: 0 | NK65: 17 | NL65: 5 | NM65: 42 | NO65: 0 | NP65: 13 | NQ65: 6 | NT65: 34 | NU65: 19 | OB65: 0 | OE65: 66 | ON65: 137 | OO65: 9738 | OP65: 90 | OU65: 87 | OV65: 4917 | PI65: 14832 | PM65: =IFERROR(VLOOKUP($A65&"",Key!$A:$C,3,FALSE),"") -> ISIC 242
A66: 331510 | B66: Ferrous metal foundries | S66: 11 | AA66: 1 | AC66: 130 | AD66: 7 | AE66: 1 | AG66: 32 | AI66: 8 | AJ66: 6 | AK66: 4 | AL66: 1 | AO66: 1 | AP66: 1 | BC66: 180 | BD66: 13 | BK66: 42 | BL66: 109 | BM66: 16 | BN66: 33 | BO66: 4 | BP66: 45 | BQ66: 38 | BR66: 245 | BS66: 45 | BT66: 85 | BV66: 64 | BW66: 11 | BX66: 86 | BY66: 622 | BZ66: 29 | CA66: 381 | CB66: 1136 | CC66: 55 | CD66: 32 | CE66: 99 | CF66: 89 | CG66: 115 | CH66: 38 | CI66: 269 | CJ66: 391 | CK66: 19 | CL66: 470 | CM66: 14 | CN66: 2 | CO66: 103 | CP66: 100 | CQ66: 899 | CR66: 12 | CS66: 153 | CT66: 122 | CU66: 108 | CV66: 147 | CW66: 155 | CX66: 31 | CY66: 193 | CZ66: 1230 | DA66: 681 | DB66: 476 | DC66: 298 | DD66: 98 | DE66: 21 | DF66: 19 | DG66: 244 | DH66: 452 | DL66: 25 | DM66: 2 | DN66: 10 | DO66: 33 | DP66: 0 | DQ66: 48 | DR66: 45 | DS66: 30 | DT66: 10 | DU66: 14 | DV66: 17 | DW66: 5 | DX66: 9 | DY66: 7 | DZ66: 10 | EA66: 10 | ED66: 32 | EE66: 10 | EF66: 47 | EG66: 6 | EH66: 12 | EI66: 54 | EJ66: 14 | EL66: 0 | EN66: 29 | EO66: 1 | EP66: 4 | EQ66: 6 | ER66: 50 | ET66: 30 | EU66: 5 | EV66: 0 | EW66: 4 | EX66: 544 | EY66: 279 | EZ66: 1752 | FA66: 8 | FB66: 281 | FC66: 604 | FD66: 1735 | FF66: 13 | FG66: 559 | FH66: 0 | FI66: 9 | FJ66: 191 | FK66: 6 | FL66: 14 | FM66: 15 | FN66: 59 | FO66: 39 | FQ66: 1 | FS66: 8 | FT66: 2 | FU66: 7 | FV66: 24 | FX66: 132 | FY66: 208 | FZ66: 6 | GB66: 6 | GC66: 4 | GD66: 66 | GG66: 1 | GH66: 8 | JN66: 0 | JO66: 26 | KF66: 492 | KK66: 115 | MO66: 5 | NT66: 3 | OO66: 18325 | OU66: 62 | OV66: 1202 | PI66: 19589 | PM66: =IFERROR(VLOOKUP($A66&"",Key!$A:$C,3,FALSE),"") -> ISIC 241
A67: 331520 | B67: Nonferrous metal foundries | AC67: 1 | AP67: 1 | BL67: 55 | BM67: 21 | BN67: 3 | BO67: 52 | BP67: 78 | BQ67: 13 | BR67: 128 | BS67: 35 | BT67: 19 | BV67: 31 | BW67: 12 | BX67: 862 | BY67: 223 | BZ67: 41 | CA67: 183 | CB67: 324 | CC67: 15 | CD67: 5 | CE67: 76 | CF67: 26 | CG67: 12 | CH67: 12 | CI67: 40 | CJ67: 34 | CK67: 13 | CL67: 394 | CM67: 19 | CN67: 0 | CO67: 187 | CP67: 13 | CQ67: 98 | CR67: 18 | CS67: 187 | CT67: 87 | CU67: 153 | CV67: 124 | CW67: 10 | CX67: 14 | CY67: 27 | CZ67: 1024 | DA67: 40 | DB67: 77 | DC67: 77 | DD67: 79 | DE67: 4 | DF67: 15 | DG67: 413 | DH67: 41 | DK67: 0 | DL67: 9 | DM67: 4 | DN67: 3 | DO67: 12 | DP67: 1 | DQ67: 7 | DR67: 12 | DS67: 8 | DT67: 0 | DU67: 6 | DV67: 18 | DW67: 1 | DX67: 8 | DY67: 5 | DZ67: 1 | EA67: 2 | ED67: 172 | EE67: 42 | EF67: 83 | EG67: 1 | EH67: 16 | EI67: 74 | EJ67: 16 | EK67: 2 | EL67: 0 | EN67: 663 | EO67: 2 | EP67: 3 | EQ67: 10 | ER67: 70 | ES67: 0 | ET67: 12 | EU67: 5 | EV67: 0 | EW67: 4 | EX67: 2682 | EY67: 448 | EZ67: 923 | FA67: 1 | FB67: 26 | FC67: 1051 | FD67: 1544 | FE67: 14 | FF67: 2 | FG67: 22 | FH67: 0 | FI67: 23 | FJ67: 10 | FK67: 35 | FL67: 6 | FM67: 22 | FN67: 0 | FO67: 50 | FQ67: 1 | FR67: 1 | FS67: 11 | FT67: 1 | FU67: 10 | FV67: 26 | FX67: 37 | FY67: 26 | FZ67: 1 | GB67: 1 | GC67: 1 | GD67: 99 | GG67: 0 | GH67: 6 | GI67: 1 | GJ67: 1 | GO67: 1 | GP67: 2 | GR67: 1 | GS67: 1 | GT67: 1 | GU67: 1 | GV67: 1 | GW67: 0 | GX67: 1 | GY67: 1 | HA67: 1 | HB67: 1 | HC67: 1 | HD67: 1 | HE67: 1 | HF67: 1 | HG67: 1 | IZ67: 9 | JK67: 1 | KD67: 0 | KK67: 1 | LT67: 0 | LU67: 0 | LZ67: 4 | MF67: 0 | MM67: 2 | MZ67: 1 | NM67: 5 | NT67: 22 | NU67: 9 | OE67: 24 | OK67: 3 | ON67: 12 | OO67: 13878 | OP67: 25 | OU67: 21 | OV67: 85 | PI67: 14008 | PM67: =IFERROR(VLOOKUP($A67&"",Key!$A:$C,3,FALSE),"") -> ISIC 242
A68: 332114 | B68: Custom roll forming | AA68: 2 | AB68: 0 | AC68: 79 | AD68: 2 | AE68: 70 | AF68: 9 | AG68: 8 | AH68: 4 | AI68: 17 | AJ68: 17 | AK68: 8 | AL68: 3 | AP68: 2 | AU68: 9 | AV68: 58 | BI68: 2 | BL68: 118 | BM68: 179 | BN68: 31 | BO68: 17 | BP68: 8 | BQ68: 144 | BR68: 115 | BS68: 51 | BT68: 23 | BU68: 95 | BV68: 3 | BW68: 39 | BX68: 43 | BY68: 70 | BZ68: 284 | CA68: 3 | CB68: 57 | CC68: 18 | CD68: 8 | CE68: 43 | CF68: 11 | CG68: 6 | CH68: 2 | CI68: 7 | CJ68: 192 | CK68: 13 | CL68: 54 | CN68: 1 | CO68: 117 | CP68: 3 | CQ68: 16 | CR68: 2 | CS68: 13 | CT68: 9 | CU68: 18 | CV68: 7 | CW68: 139 | CX68: 1 | CY68: 8 | CZ68: 41 | DA68: 3 | DB68: 3 | DC68: 41 | DD68: 9 | DE68: 24 | DF68: 18 | DG68: 38 | DH68: 7 | DJ68: 0 | DK68: 1 | DM68: 4 | DN68: 0 | DO68: 0 | DP68: 1 | DQ68: 16 | DR68: 421 | DS68: 10 | DY68: 34 | DZ68: 4 | EA68: 1 | ED68: 7 | EE68: 1 | EF68: 58 | EG68: 4 | EH68: 4 | EI68: 105 | EJ68: 30 | EK68: 6 | EL68: 11 | EM68: 20 | EN68: 19 | EO68: 8 | EP68: 7 | EQ68: 5 | ER68: 22 | ES68: 7 | ET68: 17 | EU68: 11 | EV68: 1 | EW68: 20 | EX68: 63 | EY68: 17 | EZ68: 2345 | FA68: 28 | FB68: 86 | FC68: 35 | FD68: 267 | FE68: 15 | FF68: 0 | FG68: 23 | FI68: 4 | FJ68: 45 | FK68: 8 | FL68: 4 | FM68: 3 | FN68: 40 | FO68: 7 | FQ68: 10 | FR68: 0 | FS68: 7 | FT68: 2 | FU68: 16 | FV68: 27 | FW68: 1 | FX68: 216 | FY68: 307 | FZ68: 1 | GB68: 2 | GC68: 1 | GD68: 11 | GE68: 0 | GF68: 1 | GG68: 354 | GH68: 22 | GI68: 1 | GJ68: 1 | GO68: 1 | GP68: 2 | GR68: 1 | GS68: 1 | GT68: 1 | GU68: 1 | GV68: 1 | GW68: 0 | GX68: 1 | GY68: 1 | HA68: 1 | HB68: 1 | HC68: 1 | HD68: 1 | HE68: 1 | HF68: 1 | HG68: 1 | IZ68: 1 | JH68: 9 | JJ68: 70 | JL68: 0 | KB68: 2 | KD68: 1 | KZ68: 78 | LO68: 47 | MY68: 1 | NC68: 8 | ND68: 8 | NE68: 13 | NM68: 15 | OO68: 7540 | OU68: 9 | OV68: 24 | PI68: 7573 | PM68: =IFERROR(VLOOKUP($A68&"",Key!$A:$C,3,FALSE),"") -> ISIC 25
A69: 33211A | B69: All other forging, stamping, and sintering | O69: 3 | S69: 27 | AA69: 0 | AB69: 0 | AC69: 43 | AD69: 15 | AE69: 25 | AF69: 9 | AG69: 135 | AI69: 51 | AK69: 46 | AL69: 4 | AP69: 3 | AW69: 4 | BA69: 6 | BB69: 3 | BL69: 43 | BM69: 240 | BN69: 1626 | BO69: 34 | BP69: 104 | BQ69: 32 | BR69: 25 | BS69: 55 | BT69: 72 | BU69: 3 | BV69: 116 | BW69: 15 | BX69: 330 | BY69: 553 | BZ69: 72 | CA69: 356 | CB69: 318 | CC69: 104 | CD69: 148 | CE69: 301 | CF69: 39 | CG69: 147 | CH69: 16 | CI69: 1 | CJ69: 945 | CK69: 6 | CL69: 234 | CM69: 4 | CN69: 1 | CO69: 52 | CP69: 11 | CQ69: 57 | CR69: 15 | CS69: 54 | CT69: 24 | CU69: 27 | CV69: 22 | CW69: 181 | CX69: 33 | CY69: 93 | CZ69: 1111 | DA69: 98 | DB69: 283 | DC69: 174 | DD69: 24 | DE69: 34 | DF69: 13 | DG69: 71 | DH69: 95 | DI69: 6 | DK69: 15 | DL69: 12 | DM69: 90 | DN69: 25 | DO69: 9 | DP69: 0 | DQ69: 17 | DR69: 83 | DS69: 28 | DT69: 5 | DU69: 34 | DV69: 30 | DW69: 2 | DX69: 7 | DY69: 239 | DZ69: 20 | EA69: 2 | ED69: 152 | EE69: 3 | EF69: 52 | EG69: 12 | EH69: 18 | EI69: 168 | EJ69: 22 | EK69: 38 | EL69: 5 | EN69: 95 | EP69: 10 | EQ69: 2 | ER69: 10 | ES69: 4 | ET69: 5 | EU69: 3 | EV69: 0 | EW69: 5 | EX69: 784 | EY69: 93 | EZ69: 59 | FA69: 162 | FB69: 37 | FC69: 171 | FD69: 122 | FE69: 136 | FF69: 795 | FG69: 153 | FH69: 156 | FI69: 47 | FJ69: 116 | FK69: 217 | FL69: 49 | FM69: 1 | FN69: 14 | FO69: 31 | FQ69: 17 | FS69: 13 | FT69: 3 | FU69: 27 | FV69: 44 | FW69: 2 | FX69: 11 | FY69: 62 | FZ69: 0 | GB69: 1 | GC69: 1 | GD69: 1 | GE69: 1 | GF69: 3 | GG69: 3 | GH69: 27 | JH69: 4 | JJ69: 30 | JN69: 0 | KM69: 6 | KW69: 19 | KX69: 120 | KY69: 4 | KZ69: 2 | LW69: 273 | LY69: 6 | LZ69: 45 | MF69: 4 | MK69: 3 | MM69: 1 | MN69: 3 | MO69: 129 | MZ69: 4 | NP69: 156 | NQ69: 31 | NT69: 74 | NU69: 2 | OB69: 3 | OE69: 23 | OM69: 29 | ON69: 104 | OO69: 14449 | OU69: 136 | OV69: 24 | PI69: 14609 | PM69: =IFERROR(VLOOKUP($A69&"",Key!$A:$C,3,FALSE),"") -> ISIC 25
A70: 332119 | B70: Metal crown, closure, and other metal stamping (except automotive) | I70: 4 | AE70: 8 | AK70: 0 | AP70: 31 | AQ70: 26 | BK70: 0 | BM70: 11 | BN70: 9 | BO70: 357 | BP70: 25 | BQ70: 127 | BR70: 21 | BS70: 29 | BT70: 9 | BU70: 6 | BV70: 35 | BW70: 25 | BX70: 57 | BY70: 18 | BZ70: 46 | CA70: 135 | CB70: 26 | CC70: 7 | CD70: 4 | CE70: 54 | CF70: 82 | CG70: 482 | CH70: 172 | CI70: 21 | CJ70: 127 | CK70: 25 | CL70: 166 | CM70: 15 | CN70: 4 | CO70: 34 | CP70: 10 | CQ70: 325 | CR70: 5 | CS70: 9 | CT70: 8 | CU70: 6 | CV70: 8 | CW70: 27 | CX70: 2 | CY70: 9 | CZ70: 38 | DA70: 6 | DB70: 6 | DC70: 62 | DD70: 9 | DE70: 21 | DF70: 10 | DG70: 23 | DH70: 9 | DI70: 1 | DJ70: 1 | DK70: 15 | DL70: 3 | DM70: 32 | DN70: 8 | DO70: 24 | DP70: 13 | DQ70: 102 | DR70: 75 | DS70: 83 | DT70: 42 | DU70: 31 | DV70: 13 | DW70: 37 | DX70: 12 | DY70: 137 | DZ70: 12 | EA70: 6 | ED70: 23 | EE70: 45 | EF70: 1173 | EG70: 17 | EH70: 120 | EI70: 164 | EJ70: 56 | EK70: 91 | EL70: 59 | EN70: 343 | EP70: 305 | EQ70: 3 | ER70: 13 | ES70: 5 | ET70: 6 | EU70: 3 | EV70: 2 | EW70: 39 | EX70: 38 | EY70: 19 | EZ70: 22 | FA70: 909 | FB70: 105 | FC70: 213 | FD70: 73 | FE70: 15 | FF70: 20 | FG70: 27 | FH70: 4 | FI70: 3 | FJ70: 5 | FK70: 5 | FL70: 4 | FM70: 7 | FN70: 22 | FO70: 8 | FP70: 2 | FQ70: 78 | FR70: 2 | FS70: 11 | FT70: 43 | FU70: 118 | FV70: 440 | FW70: 4 | FX70: 24 | FY70: 20 | FZ70: 5 | GB70: 5 | GC70: 4 | GD70: 7 | GE70: 4 | GF70: 8 | GG70: 7 | GH70: 33 | GN70: 3 | GQ70: 1 | GR70: 1 | GS70: 2 | GW70: 1 | HB70: 4 | HE70: 3 | HR70: 1 | HU70: 724 | HW70: 75 | IM70: 182 | IO70: 2 | IP70: 11 | IQ70: 17 | IU70: 105 | IX70: 268 | IZ70: 8 | JG70: 10 | JH70: 11 | JJ70: 411 | JN70: 250 | JO70: 61 | JT70: 12 | KB70: 9 | KD70: 3 | KR70: 0 | KV70: 370 | KW70: 278 | KX70: 120 | KY70: 4 | KZ70: 234 | LO70: 193 | LZ70: 63 | MF70: 2 | MM70: 2 | MZ70: 755 | NB70: 2 | NC70: 36 | ND70: 28 | NE70: 48 | NM70: 54 | NO70: 16 | NS70: 58 | NT70: 49 | NU70: 57 | OD70: 244 | OE70: 37 | OH70: 1 | OI70: 16 | OJ70: 554 | OK70: 74 | OM70: 16 | ON70: 190 | OO70: 13899 | OP70: 279 | OU70: 138 | OV70: 529 | PI70: 14844 | PM70: =IFERROR(VLOOKUP($A70&"",Key!$A:$C,3,FALSE),"") -> ISIC 25
A71: 332200 | B71: Cutlery and handtool manufacturing | C71: 36 | D71: 106 | E71: 36 | F71: 28 | G71: 40 | H71: 41 | I71: 204 | J71: 155 | K71: 20 | L71: 20 | N71: 3 | O71: 0 | P71: 532 | Q71: 28 | S71: 22 | V71: 71 | W71: 471 | X71: 2 | AA71: 93 | AB71: 217 | AC71: 48 | AD71: 109 | AE71: 144 | AF71: 61 | AG71: 733 | AH71: 49 | AI71: 79 | AJ71: 63 | AK71: 635 | AL71: 73 | AM71: 58 | AN71: 2 | AO71: 4 | AP71: 7 | AR71: 1 | AT71: 5 | AU71: 0 | AV71: 3 | AY71: 96 | AZ71: 1 | BA71: 1 | BC71: 25 | BD71: 1 | BE71: 2 | BF71: 0 | BG71: 2 | BI71: 2 | BJ71: 2 | BK71: 7 | BL71: 7 | BM71: 14 | BN71: 14 | BO71: 28 | BP71: 26 | BQ71: 64 | BR71: 25 | BS71: 40 | BT71: 13 | BU71: 17 | BV71: 50 | BW71: 31 | BX71: 86 | BY71: 24 | BZ71: 65 | CA71: 13 | CB71: 94 | CC71: 5 | CD71: 17 | CE71: 81 | CF71: 18 | CG71: 7 | CH71: 5 | CI71: 6 | CJ71: 97 | CK71: 26 | CL71: 59 | CM71: 9 | CN71: 3 | CO71: 42 | CP71: 11 | CQ71: 26 | CR71: 4 | CS71: 13 | CT71: 11 | CU71: 9 | CV71: 9 | CW71: 33 | CX71: 2 | CY71: 14 | CZ71: 21 | DA71: 8 | DB71: 8 | DC71: 25 | DD71: 13 | DE71: 58 | DF71: 12 | DG71: 25 | DH71: 11 | DJ71: 0 | DK71: 0 | DM71: 5 | DN71: 1 | DO71: 2 | DP71: 1 | DQ71: 2 | DR71: 25 | DS71: 9 | DT71: 0 | DU71: 20 | DV71: 5 | DW71: 5 | DX71: 22 | DY71: 47 | DZ71: 59 | EA71: 0 | EC71: 0 | ED71: 1 | EE71: 3 | EF71: 15 | EG71: 6 | EH71: 7 | EI71: 46 | EJ71: 22 | EK71: 10 | EL71: 3 | EM71: 1 | EN71: 27 | EO71: 0 | EP71: 2 | EQ71: 9 | ER71: 32 | ES71: 13 | ET71: 17 | EU71: 11 | EV71: 0 | EW71: 10 | EX71: 34 | EY71: 16 | EZ71: 18 | FA71: 47 | FB71: 131 | FC71: 32 | FD71: 43 | FE71: 20 | FF71: 20 | FG71: 34 | FI71: 3 | FJ71: 295 | FK71: 10 | FL71: 7 | FM71: 9 | FN71: 41 | FO71: 12 | FP71: 1 | FQ71: 10 | FS71: 8 | FT71: 14 | FU71: 32 | FV71: 60 | FW71: 6 | FX71: 39 | FY71: 35 | FZ71: 7 | GA71: 1 | GB71: 5 | GC71: 5 | GD71: 9 | GE71: 4 | GF71: 4 | GG71: 15 | GH71: 32 | GP71: 2 | GR71: 1 | GW71: 22 | GX71: 40 | GZ71: 6 | HA71: 2 | HB71: 2 | HE71: 1 | HG71: 8 | HH71: 0 | HI71: 0 | HP71: 0 | HQ71: 1 | HT71: 1 | HU71: 44 | HV71: 20 | HW71: 9 | HX71: 3 | HY71: 1 | HZ71: 1 | IA71: 1 | IB71: 2 | IK71: 1 | IL71: 1 | IM71: 4 | IN71: 1 | IW71: 2 | IX71: 1 | IZ71: 9 | JA71: 13 | JB71: 7 | JC71: 2 | JD71: 5 | JE71: 2 | JF71: 4 | JG71: 171 | JH71: 14 | JI71: 2 | JJ71: 112 | JL71: 225 | JN71: 7 | JO71: 32 | JQ71: 108 | JS71: 19 | JT71: 17 | JV71: 13 | JW71: 65 | JX71: 90 | JY71: 2 | JZ71: 26 | KA71: 15 | KD71: 0 | KE71: 5 | KF71: 17 | KH71: 35 | KI71: 28 | KJ71: 61 | KK71: 2 | KM71: 20 | KO71: 61 | KQ71: 18 | KW71: 2 | KX71: 11 | LA71: 104 | LC71: 13 | LD71: 25 | LE71: 9 | LF71: 1 | LK71: 1 | LL71: 0 | LM71: 1389 | LN71: 154 | LO71: 137 | LW71: 6 | LX71: 17 | LY71: 5 | LZ71: 91 | MA71: 14 | ME71: 3 | MF71: 17 | MH71: 182 | MI71: 4 | MK71: 22 | MM71: 17 | MN71: 19 | MO71: 2 | MP71: 11 | MQ71: 39 | MR71: 26 | MZ71: 16 | NA71: 8 | NC71: 2 | ND71: 8 | NE71: 381 | NK71: 4 | NL71: 9 | NM71: 129 | NN71: 69 | NO71: 223 | NP71: 401 | NQ71: 81 | NR71: 55 | NS71: 4 | NT71: 177 | NU71: 156 | NV71: 270 | NY71: 4 | NZ71: 30 | OA71: 2 | OB71: 87 | OD71: 1404 | OE71: 237 | OH71: 5 | OI71: 502 | OJ71: 107 | OK71: 1368 | ON71: 1 | OO71: 16576 | OP71: 16127 | OQ71: 197 | OU71: 242 | OV71: 2264 | OX71: 1 | PB71: 2 | PF71: 41 | PI71: 35449 | PM71: =IFERROR(VLOOKUP($A71&"",Key!$A:$C,3,FALSE),"") -> ISIC 25
A72: 332310 | B72: Plate work and fabricated structural product manufacturing | C72: 19 | D72: 33 | E72: 11 | F72: 10 | G72: 12 | H72: 14 | I72: 67 | J72: 36 | K72: 7 | L72: 6 | M72: 42 | O72: 26 | P72: 1024 | R72: 12 | S72: 4 | V72: 143 | W72: 52 | X72: 10 | Z72: 0 | AA72: 1328 | AB72: 406 | AC72: 1850 | AD72: 449 | AE72: 5049 | AF72: 851 | AG72: 3566 | AH72: 206 | AI72: 3367 | AJ72: 4583 | AK72: 1504 | AL72: 8074 | AN72: 68 | AP72: 35 | AU72: 4 | AV72: 139 | BD72: 29 | BM72: 20 | BN72: 23 | BO72: 107 | BP72: 9 | BQ72: 1536 | BR72: 22 | BS72: 52 | BT72: 16 | BU72: 8 | BV72: 38 | BW72: 25 | BX72: 672 | BY72: 16 | BZ72: 45 | CA72: 8 | CB72: 73 | CC72: 3 | CD72: 9 | CE72: 47 | CF72: 9 | CG72: 2 | CH72: 2 | CI72: 108 | CJ72: 41 | CK72: 11 | CL72: 352 | CN72: 2 | CO72: 29 | CP72: 3 | CQ72: 203 | CR72: 49 | CS72: 8 | CT72: 6 | CU72: 5 | CV72: 5 | CW72: 141 | CX72: 2 | CY72: 6 | CZ72: 203 | DA72: 98 | DB72: 92 | DC72: 355 | DD72: 7 | DE72: 22 | DF72: 8 | DG72: 33 | DH72: 6 | DI72: 1 | DJ72: 1 | DK72: 3 | DM72: 9 | DN72: 1 | DO72: 102 | DP72: 7 | DQ72: 32 | DR72: 18 | DS72: 5 | DY72: 16 | DZ72: 6 | EA72: 5 | ED72: 31 | EE72: 2 | EF72: 21 | EG72: 15 | EH72: 15 | EI72: 130 | EJ72: 43 | EK72: 53 | EL72: 15 | EN72: 59 | EP72: 23 | EQ72: 4 | ER72: 18 | ES72: 8 | ET72: 16 | EU72: 7 | EV72: 0 | EW72: 3 | EX72: 753 | EY72: 18 | EZ72: 207 | FA72: 8 | FB72: 92 | FC72: 41 | FD72: 46 | FE72: 1967 | FF72: 1 | FG72: 611 | FH72: 210 | FI72: 3 | FJ72: 364 | FK72: 219 | FL72: 238 | FM72: 3 | FN72: 38 | FO72: 7 | FQ72: 11 | FS72: 8 | FT72: 2 | FU72: 18 | FV72: 28 | FW72: 2 | FZ72: 8 | GB72: 9 | GC72: 6 | GD72: 16 | GE72: 2 | GF72: 3 | GG72: 6 | GH72: 16 | IZ72: 1 | JG72: 186 | JH72: 9 | JJ72: 69 | JK72: 2 | JL72: 5 | JM72: 39 | JN72: 872 | JO72: 101 | JP72: 5 | JQ72: 1 | JR72: 18 | JS72: 9 | JT72: 31 | JV72: 1 | JX72: 41 | JY72: 6 | KB72: 10 | KC72: 0 | KD72: 10 | KF72: 6 | KG72: 2133 | KJ72: 1751 | KK72: 1 | KL72: 1 | KM72: 7 | KO72: 0 | KP72: 0 | KQ72: 0 | KR72: 0 | KU72: 0 | KV72: 1 | KW72: 17 | KX72: 100 | KY72: 1 | KZ72: 56 | LK72: 1 | LL72: 0 | LN72: 268 | LO72: 138 | LR72: 0 | LT72: 691 | LV72: 0 | LW72: 847 | LX72: 0 | LY72: 1 | LZ72: 395 | ME72: 1 | MF72: 13 | MG72: 0 | MH72: 6 | MI72: 3 | MJ72: 188 | MK72: 0 | MO72: 407 | MQ72: 28 | MS72: 3 | MT72: 0 | MV72: 2 | MY72: 4 | MZ72: 142 | NA72: 4 | NB72: 0 | NC72: 46 | ND72: 29 | NE72: 51 | NF72: 9 | NG72: 2 | NH72: 2 | NI72: 6 | NJ72: 3 | NK72: 9 | NL72: 3 | NM72: 59 | NN72: 5 | NO72: 213 | NP72: 4 | NQ72: 1 | NR72: 0 | NS72: 0 | NT72: 2 | NU72: 0 | OB72: 168 | OD72: 126 | OE72: 33 | OI72: 56 | OK72: 275 | OM72: 4 | ON72: 2184 | OO72: 55120 | OP72: 290 | OQ72: 167 | OU72: 97 | OV72: 1200 | PB72: 12 | PI72: 56885 | PM72: =IFERROR(VLOOKUP($A72&"",Key!$A:$C,3,FALSE),"") -> ISIC 25
A73: 332320 | B73: Ornamental and architectural metal products manufacturing | N73: 2 | R73: 14 | V73: 67 | W73: 125 | Z73: 0 | AA73: 619 | AB73: 1128 | AC73: 5800 | AD73: 1247 | AE73: 7422 | AF73: 1868 | AG73: 6375 | AH73: 1462 | AI73: 2024 | AJ73: 728 | AK73: 6669 | AL73: 1117 | AN73: 12 | AO73: 114 | AP73: 168 | AR73: 2 | AU73: 5 | AV73: 40 | BB73: 3 | BC73: 5 | BE73: 4 | BI73: 1 | BJ73: 3 | BM73: 48 | BN73: 1 | BO73: 24 | BQ73: 126 | BR73: 437 | BS73: 12 | BT73: 4 | BU73: 7 | BW73: 44 | BX73: 118 | BY73: 6 | CB73: 43 | CD73: 1 | CF73: 25 | CG73: 29 | CH73: 1 | CI73: 11 | CK73: 12 | CL73: 172 | CM73: 24 | CO73: 1072 | CP73: 2 | CQ73: 8 | CR73: 57 | CT73: 3 | CU73: 1 | CV73: 0 | CX73: 0 | CY73: 1 | CZ73: 489 | DA73: 2 | DC73: 44 | DF73: 1 | DG73: 120 | DI73: 35 | DJ73: 215 | DK73: 29 | DL73: 8 | DM73: 156 | DN73: 24 | DO73: 111 | DP73: 54 | DQ73: 167 | DR73: 14 | DS73: 221 | DT73: 122 | DU73: 43 | DV73: 15 | DW73: 48 | DX73: 96 | DZ73: 24 | ED73: 7 | EE73: 2 | EF73: 18 | EH73: 13 | EI73: 598 | EJ73: 445 | EN73: 26 | EP73: 247 | EQ73: 10 | ER73: 5 | ES73: 3 | ET73: 81 | EU73: 2 | EV73: 12 | EW73: 247 | EX73: 48 | EY73: 2 | EZ73: 17 | FA73: 132 | FB73: 168 | FC73: 386 | FD73: 19 | FE73: 1 | FF73: 3 | FJ73: 1 | FK73: 1 | FN73: 87 | FO73: 1 | FS73: 41 | FT73: 0 | FU73: 72 | FV73: 24 | FX73: 229 | FY73: 267 | GD73: 1 | II73: 7 | IL73: 73 | JG73: 1467 | JK73: 11 | JL73: 5 | JM73: 1 | JN73: 18 | JO73: 94 | JR73: 0 | JT73: 1 | JV73: 1 | KB73: 19 | KC73: 0 | KD73: 5 | KF73: 2 | KN73: 0 | KO73: 3 | KP73: 0 | KQ73: 0 | KR73: 0 | KV73: 0 | KW73: 182 | KX73: 1260 | KY73: 18 | KZ73: 535 | LA73: 6 | LK73: 12 | LL73: 0 | LO73: 143 | LT73: 1456 | LW73: 972 | LX73: 1 | LZ73: 315 | MF73: 17 | MH73: 17 | MI73: 0 | MO73: 1977 | MQ73: 34 | MU73: 1 | MY73: 4 | MZ73: 273 | NC73: 86 | ND73: 178 | NE73: 89 | NF73: 7 | NH73: 1 | NI73: 2 | NJ73: 1 | NK73: 4 | NM73: 125 | NN73: 21 | NO73: 558 | NP73: 562 | NQ73: 59 | NS73: 44 | OB73: 272 | OD73: 21 | OE73: 117 | OI73: 0 | OJ73: 0 | OK73: 51 | OL73: 4 | OM73: 37 | ON73: 1178 | OO73: 56922 | OQ73: 637 | OU73: 304 | OV73: 1083 | PI73: 58946 | PM73: =IFERROR(VLOOKUP($A73&"",Key!$A:$C,3,FALSE),"") -> ISIC 25
A74: 332410 | B74: Power boiler and heat exchanger manufacturing | X74: 0 | AA74: 84 | AB74: 935 | AC74: 97 | AD74: 25 | AE74: 562 | AF74: 69 | AG74: 259 | AH74: 473 | AI74: 69 | AJ74: 38 | AK74: 79 | AL74: 47 | BS74: 64 | BT74: 20 | BW74: 4 | BX74: 60 | CB74: 4 | CF74: 2 | CK74: 14 | CL74: 500 | CP74: 15 | CQ74: 6 | CW74: 47 | CZ74: 59 | DG74: 13 | FK74: 2 | GM74: 5 | GN74: 3 | HU74: 3 | IG74: 19 | IJ74: 12 | IK74: 7 | IL74: 103 | IP74: 2 | IR74: 17 | IT74: 5 | IU74: 233 | IV74: 67 | IW74: 275 | IX74: 120 | IY74: 32 | IZ74: 47 | KW74: 5 | KX74: 34 | LL74: 0 | LT74: 12 | LW74: 14 | LZ74: 36 | MF74: 2 | MO74: 374 | MQ74: 1 | NP74: 31 | NQ74: 9 | OE74: 18 | ON74: 161 | OO74: 5194 | OQ74: 6290 | OU74: 135 | OV74: 1482 | PB74: 130 | PI74: 13231 | PM74: =IFERROR(VLOOKUP($A74&"",Key!$A:$C,3,FALSE),"") -> ISIC 25
A75: 332420 | B75: Metal tank (heavy gauge) manufacturing | Z75: 0 | AA75: 36 | AB75: 83 | AC75: 248 | AD75: 97 | AE75: 153 | AF75: 51 | AG75: 488 | AH75: 25 | AI75: 674 | AJ75: 6 | AK75: 312 | AL75: 20 | BS75: 39 | BT75: 455 | BW75: 12 | BX75: 23 | CB75: 13 | CF75: 0 | CK75: 13 | CL75: 441 | CW75: 41 | CZ75: 48 | DG75: 15 | EX75: 34 | FK75: 4 | GM75: 4 | ID75: 6 | IG75: 95 | IJ75: 1 | IK75: 18 | IL75: 87 | IP75: 2 | IQ75: 3 | IT75: 38 | IU75: 160 | IV75: 36 | IW75: 70 | IX75: 26 | IY75: 20 | IZ75: 103 | LK75: 0 | LL75: 0 | LZ75: 0 | MO75: 1 | MQ75: 0 | NN75: 1 | OE75: 827 | OK75: 107 | OL75: 0 | ON75: 1 | OO75: 4935 | OQ75: 3854 | OU75: 12 | OV75: 1271 | PF75: 4 | PI75: 10076 | PM75: =IFERROR(VLOOKUP($A75&"",Key!$A:$C,3,FALSE),"") -> ISIC 25
A76: 332430 | B76: Metal can, box, and other metal container (light gauge) manufacturing | AA76: 1 | AC76: 1 | AF76: 17 | AG76: 3 | AK76: 4 | AP76: 4 | BM76: 11 | BN76: 14 | BO76: 21 | BP76: 12 | BQ76: 75 | BR76: 7 | BS76: 54 | BT76: 16 | BU76: 3786 | BV76: 41 | BW76: 16 | BX76: 36 | BY76: 20 | BZ76: 50 | CA76: 10 | CB76: 67 | CC76: 4 | CD76: 13 | CE76: 59 | CF76: 14 | CG76: 5 | CH76: 3 | CI76: 85 | CJ76: 43 | CK76: 16 | CL76: 79 | CN76: 1 | CO76: 34 | CP76: 4 | CQ76: 22 | CR76: 49 | CS76: 10 | CT76: 9 | CU76: 8 | CV76: 8 | CW76: 154 | CX76: 2 | CY76: 10 | CZ76: 152 | DA76: 91 | DB76: 90 | DC76: 173 | DD76: 10 | DE76: 25 | DF76: 9 | DG76: 16 | DH76: 11 | DJ76: 0 | DK76: 1 | DL76: 0 | DM76: 11 | DN76: 8 | DO76: 1 | DP76: 2 | DQ76: 23 | DR76: 22 | DS76: 37 | DT76: 0 | DV76: 0 | DX76: 0 | DY76: 33 | DZ76: 1 | EA76: 0 | ED76: 9 | EE76: 2 | EF76: 23 | EG76: 4 | EH76: 5 | EI76: 27 | EJ76: 15 | EK76: 6 | EL76: 1 | EN76: 27 | EP76: 8 | EQ76: 6 | ER76: 26 | ES76: 11 | ET76: 16 | EU76: 7 | EV76: 0 | EW76: 6 | EX76: 5 | EY76: 22 | EZ76: 24 | FA76: 34 | FB76: 101 | FC76: 41 | FD76: 51 | FE76: 16 | FF76: 11 | FG76: 25 | FH76: 1 | FI76: 4 | FJ76: 5 | FK76: 5 | FL76: 5 | FM76: 8 | FN76: 51 | FO76: 10 | FQ76: 14 | FR76: 0 | FS76: 11 | FT76: 5 | FU76: 19 | FV76: 37 | FW76: 3 | FY76: 4 | FZ76: 5 | GB76: 4 | GC76: 3 | GD76: 5 | GE76: 2 | GF76: 3 | GG76: 8 | GH76: 26 | GI76: 1361 | GJ76: 8 | GM76: 9 | GN76: 3 | GP76: 40 | GQ76: 28 | GR76: 2630 | GS76: 89 | GT76: 137 | GU76: 254 | GV76: 1 | GW76: 28 | GX76: 6 | GY76: 112 | HA76: 12 | HB76: 251 | HC76: 59 | HD76: 51 | HE76: 63 | HF76: 85 | HG76: 117 | HH76: 3576 | HK76: 1977 | ID76: 34 | IE76: 2 | IF76: 1 | IG76: 209 | IH76: 0 | II76: 10 | IJ76: 4 | IK76: 33 | IL76: 195 | IO76: 3 | IP76: 5 | IQ76: 19 | IR76: 10 | IT76: 86 | IU76: 352 | IV76: 77 | IW76: 156 | IX76: 10 | IY76: 41 | IZ76: 230 | JG76: 38 | JH76: 12 | JJ76: 99 | JK76: 2 | JN76: 12 | JS76: 49 | JV76: 10 | JW76: 0 | JY76: 3 | KB76: 2 | KK76: 1 | KL76: 12 | KM76: 6 | KZ76: 7 | LX76: 2 | MA76: 1 | MN76: 1 | MO76: 4 | MY76: 1 | OD76: 43 | OO76: 19064 | OP76: 513 | OQ76: 215 | OU76: 214 | OV76: 1073 | OX76: 0 | PB76: 4 | PF76: 34 | PI76: 21117 | PM76: =IFERROR(VLOOKUP($A76&"",Key!$A:$C,3,FALSE),"") -> ISIC 25
A77: 332500 | B77: Hardware manufacturing | J77: 5 | M77: 0 | N77: 93 | O77: 5 | P77: 51 | Q77: 24 | T77: 16 | Z77: 0 | AA77: 194 | AB77: 165 | AC77: 1494 | AD77: 587 | AE77: 107 | AF77: 898 | AG77: 1518 | AH77: 47 | AI77: 478 | AJ77: 250 | AK77: 1997 | AL77: 100 | AN77: 127 | AO77: 192 | AP77: 223 | AS77: 1 | AT77: 9 | BO77: 1 | BQ77: 4 | BR77: 659 | BS77: 2 | BU77: 1 | BV77: 745 | BW77: 11 | BX77: 75 | BY77: 538 | BZ77: 1 | CA77: 1 | CB77: 13 | CD77: 1 | CE77: 2 | CF77: 6 | CG77: 1 | CH77: 1 | CI77: 29 | CJ77: 2 | CK77: 7 | CL77: 2 | CN77: 0 | CO77: 2 | CP77: 1 | CQ77: 146 | CT77: 1 | CW77: 0 | CZ77: 53 | DA77: 1 | DC77: 0 | DD77: 1 | DE77: 1 | DG77: 12 | DH77: 0 | DK77: 14 | DO77: 16 | DR77: 17 | DY77: 2 | EF77: 2 | EH77: 1 | EQ77: 146 | ER77: 498 | ES77: 74 | ET77: 259 | EU77: 218 | EV77: 0 | EW77: 1 | EX77: 2 | EY77: 6 | EZ77: 1 | FA77: 6 | FB77: 1 | FC77: 112 | FD77: 4 | FE77: 363 | FF77: 131 | FG77: 409 | FJ77: 0 | FK77: 4 | FL77: 370 | FM77: 1 | FN77: 2 | FO77: 1 | FP77: 275 | FQ77: 369 | FR77: 72 | FS77: 35 | FT77: 47 | FU77: 57 | FV77: 459 | FX77: 2 | FY77: 2 | GD77: 1 | GG77: 154 | GH77: 35 | GS77: 10 | GU77: 7 | GZ77: 11 | HG77: 39 | HH77: 4 | HS77: 5 | IX77: 136 | JG77: 247 | JI77: 469 | JK77: 0 | JL77: 2 | JM77: 2 | JN77: 16 | JO77: 16 | JQ77: 101 | JR77: 8 | JS77: 40 | JT77: 3 | JV77: 31 | JW77: 96 | JX77: 20 | JY77: 84 | JZ77: 30 | KA77: 95 | KB77: 11 | KC77: 169 | KD77: 1209 | KF77: 87 | KH77: 119 | KK77: 3 | KL77: 8 | KM77: 19 | KN77: 1 | KQ77: 17 | KW77: 263 | KX77: 323 | KY77: 11 | KZ77: 7 | LK77: 4 | LN77: 14 | LO77: 93 | LT77: 101 | LW77: 274 | LX77: 6 | LZ77: 143 | MA77: 9 | MB77: 158 | MD77: 6 | MF77: 4 | MG77: 23 | MH77: 339 | MI77: 7 | MJ77: 2 | MK77: 44 | MM77: 26 | MN77: 28 | MO77: 144 | MQ77: 1 | MW77: 2 | MX77: 9 | MY77: 12 | MZ77: 143 | NC77: 343 | ND77: 31 | NE77: 1086 | NL77: 2 | NM77: 38 | NN77: 9 | NO77: 245 | NP77: 180 | NQ77: 42 | NR77: 210 | NS77: 0 | NT77: 34 | NU77: 14 | NX77: 8 | OA77: 88 | OB77: 91 | OD77: 377 | OE77: 8 | OJ77: 8 | OK77: 0 | OL77: 50 | OM77: 35 | ON77: 58 | OO77: 23334 | OP77: 3572 | OQ77: 792 | OU77: 226 | OV77: 2602 | PI77: 30526 | PM77: =IFERROR(VLOOKUP($A77&"",Key!$A:$C,3,FALSE),"") -> ISIC 25
A78: 332600 | B78: Spring and wire product manufacturing | J78: 1041 | N78: 19 | R78: 2 | V78: 8 | W78: 13 | AA78: 2 | AB78: 13 | AC78: 53 | AD78: 32 | AE78: 27 | AF78: 1 | AG78: 23 | AH78: 5 | AI78: 3 | AJ78: 12 | AK78: 19 | AL78: 25 | AP78: 1 | BD78: 153 | BL78: 2 | BM78: 1 | BN78: 1 | BO78: 4 | BP78: 7 | BQ78: 2 | BR78: 5 | BS78: 2 | BT78: 1 | BU78: 0 | BV78: 17 | BW78: 497 | BX78: 47 | BY78: 147 | BZ78: 2 | CA78: 1 | CB78: 27 | CC78: 0 | CD78: 1 | CE78: 4 | CF78: 4 | CG78: 1 | CH78: 1 | CI78: 1 | CJ78: 3 | CK78: 26 | CL78: 11 | CM78: 1 | CN78: 1 | CO78: 2 | CP78: 1 | CQ78: 9 | CR78: 0 | CS78: 1 | CT78: 1 | CU78: 1 | CV78: 1 | CW78: 1 | CX78: 0 | CY78: 1 | CZ78: 1 | DA78: 1 | DB78: 1 | DD78: 1 | DE78: 1 | DF78: 1 | DG78: 40 | DH78: 1 | DM78: 0 | DQ78: 0 | DR78: 87 | DS78: 1 | DU78: 0 | DX78: 0 | DY78: 1 | DZ78: 1 | ED78: 3 | EE78: 1 | EF78: 2 | EG78: 0 | EH78: 3 | EI78: 5 | EJ78: 1 | EK78: 1 | EL78: 1 | EN78: 2 | EP78: 0 | EQ78: 32 | ER78: 573 | ES78: 48 | ET78: 331 | EV78: 0 | EW78: 3 | EX78: 3 | EY78: 1 | EZ78: 1 | FA78: 3 | FB78: 12 | FC78: 3 | FD78: 3 | FE78: 372 | FF78: 566 | FG78: 374 | FJ78: 468 | FK78: 1 | FM78: 1 | FN78: 3 | FO78: 1 | FQ78: 201 | FR78: 4 | FS78: 8 | FT78: 2 | FU78: 1 | FV78: 1 | FW78: 503 | FX78: 2 | FY78: 2 | FZ78: 0 | GB78: 0 | GC78: 1 | GD78: 1 | GE78: 1 | GF78: 0 | GG78: 1 | GH78: 8 | HU78: 21 | HX78: 105 | IK78: 44 | JJ78: 3 | JK78: 1 | JL78: 0 | JM78: 1 | JN78: 1 | JO78: 1 | JP78: 0 | JQ78: 11 | JS78: 2 | JT78: 0 | JV78: 66 | JW78: 3 | JX78: 4 | JY78: 0 | JZ78: 0 | KA78: 5 | KB78: 0 | KC78: 0 | KD78: 0 | KE78: 0 | KH78: 55 | KI78: 34 | KJ78: 0 | KL78: 1 | KM78: 16 | KW78: 1 | KX78: 7 | KZ78: 31 | LK78: 1 | LL78: 0 | LN78: 7 | LT78: 20 | LW78: 31 | LZ78: 67 | MF78: 18 | MH78: 55 | MK78: 6 | MN78: 7 | MO78: 91 | MZ78: 21 | NA78: 0 | NC78: 2 | ND78: 2 | NE78: 7 | NH78: 8 | NM78: 6 | NO78: 6 | NP78: 10 | NR78: 207 | NS78: 0 | NT78: 2 | NU78: 5 | OE78: 0 | OI78: 8 | OJ78: 1 | OK78: 1 | OL78: 1 | OM78: 29 | ON78: 146 | OO78: 7153 | OP78: 239 | OU78: 80 | OV78: 930 | PI78: 8402 | PM78: =IFERROR(VLOOKUP($A78&"",Key!$A:$C,3,FALSE),"") -> ISIC 25
A79: 332710 | B79: Machine shops | C79: 2 | D79: 11 | E79: 2 | F79: 2 | G79: 2 | H79: 4 | I79: 12 | J79: 2 | K79: 0 | L79: 1 | N79: 5 | O79: 1 | P79: 22 | Q79: 12 | R79: 5 | S79: 37 | T79: 7 | U79: 24 | V79: 11 | W79: 29 | X79: 36 | Z79: 0 | AA79: 5 | AB79: 1 | AC79: 326 | AD79: 150 | AE79: 275 | AF79: 52 | AG79: 1013 | AH79: 44 | AI79: 135 | AJ79: 96 | AK79: 297 | AL79: 109 | AM79: 297 | AN79: 253 | AO79: 25 | AP79: 71 | AQ79: 15 | AR79: 41 | AS79: 24 | AT79: 132 | AU79: 18 | AV79: 39 | AW79: 15 | AX79: 8 | AY79: 15 | AZ79: 47 | BA79: 24 | BB79: 5 | BC79: 255 | BD79: 98 | BE79: 64 | BF79: 5 | BG79: 522 | BH79: 68 | BI79: 87 | BJ79: 90 | BK79: 281 | BL79: 208 | BM79: 40 | BN79: 80 | BO79: 114 | BP79: 74 | BQ79: 379 | BR79: 1078 | BS79: 156 | BT79: 43 | BU79: 41 | BV79: 264 | BW79: 90 | BX79: 539 | BY79: 213 | BZ79: 356 | CA79: 59 | CB79: 393 | CC79: 48 | CD79: 50 | CE79: 285 | CF79: 91 | CG79: 18 | CH79: 11 | CI79: 90 | CJ79: 316 | CK79: 70 | CL79: 995 | CM79: 28 | CN79: 0 | CO79: 231 | CP79: 22 | CQ79: 188 | CR79: 21 | CS79: 106 | CT79: 88 | CU79: 66 | CV79: 49 | CW79: 58 | CX79: 10 | CY79: 61 | CZ79: 61 | DA79: 26 | DB79: 43 | DC79: 488 | DD79: 63 | DE79: 193 | DF79: 52 | DG79: 76 | DH79: 123 | DI79: 11 | DJ79: 5 | DK79: 8 | DL79: 5 | DM79: 193 | DN79: 27 | DO79: 38 | DP79: 40 | DQ79: 115 | DR79: 107 | DS79: 35 | DT79: 2 | DU79: 95 | DV79: 44 | DW79: 79 | DX79: 116 | DY79: 187 | DZ79: 19 | EA79: 3 | EB79: 1 | EC79: 5 | ED79: 56 | EE79: 31 | EF79: 113 | EG79: 33 | EH79: 36 | EI79: 151 | EJ79: 123 | EK79: 44 | EL79: 3 | EM79: 40 | EN79: 339 | EO79: 20 | EP79: 75 | EQ79: 32 | ER79: 135 | ES79: 51 | ET79: 147 | EU79: 51 | EV79: 1 | EW79: 20 | EX79: 773 | EY79: 137 | EZ79: 250 | FA79: 288 | FB79: 580 | FC79: 799 | FD79: 349 | FE79: 159 | FF79: 4 | FG79: 169 | FH79: 66 | FI79: 57 | FJ79: 105 | FK79: 21 | FL79: 76 | FM79: 18 | FN79: 229 | FO79: 39 | FP79: 107 | FQ79: 147 | FR79: 6 | FS79: 91 | FT79: 10 | FU79: 119 | FV79: 183 | FW79: 44 | FX79: 296 | FY79: 188 | FZ79: 8 | GA79: 19 | GB79: 10 | GC79: 4 | GD79: 20 | GE79: 1 | GF79: 20 | GG79: 42 | GH79: 330 | GI79: 2 | GJ79: 3 | GO79: 3 | GP79: 80 | GQ79: 5 | GR79: 31 | GS79: 5 | GU79: 6 | GW79: 6 | GX79: 6 | GY79: 0 | GZ79: 102 | HB79: 113 | HD79: 14 | HE79: 33 | HF79: 9 | HG79: 328 | HH79: 15 | HI79: 16 | HJ79: 53 | HK79: 215 | HL79: 8 | HM79: 11 | HN79: 29 | HO79: 28 | HP79: 20 | HQ79: 44 | HR79: 3 | HS79: 6 | HT79: 62 | HU79: 435 | HV79: 498 | HW79: 562 | HX79: 361 | HY79: 63 | HZ79: 144 | IA79: 56 | IB79: 349 | IC79: 41 | ID79: 137 | IE79: 1 | IF79: 30 | IG79: 22 | IH79: 13 | II79: 18 | IJ79: 47 | IK79: 59 | IL79: 164 | IM79: 220 | IN79: 106 | IO79: 2 | IP79: 1 | IQ79: 1 | IR79: 5 | IS79: 22 | IT79: 17 | IU79: 121 | IV79: 158 | IW79: 673 | IX79: 148 | IY79: 38 | IZ79: 272 | JA79: 250 | JB79: 78 | JC79: 24 | JD79: 65 | JE79: 29 | JF79: 58 | JG79: 836 | JH79: 85 | JI79: 25 | JJ79: 485 | JK79: 0 | JL79: 84 | JM79: 32 | JN79: 23 | JO79: 79 | JP79: 2 | JQ79: 34 | JR79: 8 | JS79: 34 | JT79: 4 | JV79: 94 | JW79: 6 | JX79: 17 | JZ79: 34 | KA79: 3 | KB79: 5 | KC79: 6 | KD79: 4 | KE79: 192 | KF79: 275 | KG79: 32 | KH79: 489 | KI79: 152 | KJ79: 7 | KK79: 126 | KL79: 27 | KM79: 60 | KN79: 50 | KO79: 41 | KP79: 37 | KQ79: 31 | KR79: 41 | KS79: 3 | KT79: 4 | KW79: 394 | KX79: 250 | KY79: 49 | KZ79: 17 | LA79: 6 | LC79: 15 | LD79: 8 | LE79: 5 | LF79: 1 | LK79: 1 | LL79: 0 | LM79: 23 | LN79: 7 | LO79: 144 | LS79: 5 | LT79: 102 | LU79: 6 | LW79: 144 | LX79: 61 | LY79: 15 | LZ79: 377 | MA79: 22 | MB79: 18 | MD79: 5 | ME79: 12 | MF79: 392 | MG79: 20 | MH79: 234 | MI79: 25 | MJ79: 5 | MK79: 126 | ML79: 2 | MM79: 24 | MN79: 48 | MO79: 10 | MP79: 11 | MQ79: 3 | MR79: 247 | MS79: 6 | MV79: 60 | MW79: 5 | MX79: 10 | MY79: 5 | MZ79: 6 | NA79: 6 | NB79: 2 | NK79: 1 | NL79: 3 | NM79: 19 | NN79: 2 | NR79: 154 | NS79: 14 | NT79: 177 | NU79: 235 | NX79: 7 | NY79: 22 | OB79: 8 | OF79: 21 | OG79: 3 | OI79: 5 | OK79: 697 | OL79: 29 | OM79: 3 | ON79: 531 | OO79: 36652 | OU79: -50 | OV79: 353 | PB79: 1135 | PI79: 38090 | PM79: =IFERROR(VLOOKUP($A79&"",Key!$A:$C,3,FALSE),"") -> ISIC 25
A80: 332720 | B80: Turned product and screw, nut, and bolt manufacturing | P80: 75 | Q80: 443 | R80: 12 | S80: 103 | T80: 10 | U80: 60 | V80: 40 | W80: 99 | X80: 19 | Z80: 1 | AA80: 12 | AB80: 15 | AC80: 159 | AD80: 74 | AE80: 89 | AF80: 25 | AG80: 257 | AH80: 16 | AI80: 71 | AJ80: 2595 | AK80: 146 | AL80: 41 | AM80: 132 | AN80: 88 | AO80: 105 | AP80: 125 | AQ80: 6 | AR80: 15 | AS80: 10 | AT80: 55 | AU80: 8 | AV80: 17 | AW80: 6 | AX80: 3 | AY80: 6 | AZ80: 19 | BA80: 11 | BB80: 2 | BC80: 145 | BD80: 26 | BE80: 13 | BF80: 1 | BG80: 28 | BH80: 15 | BI80: 20 | BJ80: 8 | BK80: 40 | BL80: 38 | BM80: 355 | BN80: 40 | BO80: 159 | BP80: 132 | BQ80: 564 | BR80: 944 | BS80: 127 | BT80: 30 | BU80: 33 | BV80: 242 | BW80: 112 | BX80: 567 | BY80: 1487 | BZ80: 216 | CA80: 35 | CB80: 630 | CC80: 100 | CD80: 11 | CE80: 107 | CF80: 453 | CG80: 130 | CH80: 94 | CI80: 108 | CJ80: 31 | CK80: 229 | CL80: 581 | CM80: 24 | CN80: 1 | CO80: 303 | CP80: 27 | CQ80: 408 | CR80: 19 | CS80: 66 | CT80: 52 | CU80: 61 | CV80: 36 | CW80: 43 | CX80: 21 | CY80: 62 | CZ80: 204 | DA80: 130 | DB80: 162 | DC80: 157 | DD80: 64 | DE80: 97 | DF80: 36 | DG80: 543 | DH80: 254 | DI80: 1 | DJ80: 2 | DK80: 6 | DL80: 17 | DM80: 275 | DN80: 218 | DO80: 5 | DP80: 59 | DQ80: 282 | DR80: 521 | DS80: 112 | DT80: 5 | DU80: 173 | DV80: 123 | DW80: 75 | DX80: 149 | DY80: 550 | DZ80: 49 | EA80: 8 | EB80: 1 | EC80: 1 | ED80: 250 | EE80: 56 | EF80: 634 | EG80: 237 | EH80: 228 | EI80: 180 | EJ80: 109 | EK80: 164 | EL80: 2 | EM80: 7 | EN80: 270 | EO80: 6 | EP80: 37 | EQ80: 185 | ER80: 515 | ES80: 463 | ET80: 670 | EU80: 316 | EV80: 2 | EW80: 80 | EX80: 570 | EY80: 49 | EZ80: 375 | FA80: 138 | FB80: 1394 | FC80: 2736 | FD80: 586 | FE80: 499 | FF80: 16 | FG80: 617 | FH80: 7 | FI80: 41 | FJ80: 596 | FK80: 47 | FL80: 312 | FM80: 15 | FN80: 39 | FO80: 32 | FP80: 46 | FQ80: 51 | FR80: 2 | FS80: 36 | FT80: 8 | FU80: 80 | FV80: 131 | FW80: 21 | FX80: 275 | FY80: 193 | FZ80: 11 | GA80: 3 | GB80: 8 | GC80: 3 | GD80: 183 | GE80: 1 | GF80: 7 | GG80: 29 | GH80: 80 | HG80: 602 | HH80: 39 | HI80: 7 | HJ80: 24 | HL80: 4 | HM80: 7 | HN80: 15 | HO80: 12 | HP80: 9 | HQ80: 19 | HR80: 1 | HS80: 3 | HT80: 20 | HU80: 122 | HV80: 144 | HW80: 170 | HX80: 101 | HY80: 17 | HZ80: 50 | IA80: 16 | IB80: 141 | IC80: 14 | ID80: 138 | IE80: 1 | IF80: 34 | IG80: 9 | IH80: 10 | II80: 7 | IJ80: 21 | IK80: 26 | IL80: 70 | IM80: 70 | IN80: 22 | IP80: 0 | IS80: 10 | IT80: 7 | IU80: 52 | IV80: 69 | IW80: 282 | IX80: 65 | IY80: 17 | IZ80: 106 | JA80: 107 | JB80: 35 | JC80: 10 | JD80: 28 | JE80: 12 | JF80: 17 | JG80: 293 | JH80: 55 | JI80: 11 | JJ80: 367 | JK80: 11 | JO80: 2 | JP80: 17 | JS80: 4 | JV80: 10 | JW80: 41 | JZ80: 3 | KB80: 3 | KC80: 2 | KD80: 4 | KE80: 1 | KF80: 2 | KG80: 14 | KH80: 215 | KI80: 2 | KJ80: 3 | KK80: 167 | KL80: 334 | KM80: 304 | KN80: 21 | KO80: 19 | KP80: 15 | KQ80: 19 | KR80: 80 | KS80: 12 | KT80: 1 | KV80: 2 | KW80: 113 | KX80: 50 | KY80: 9 | KZ80: 39 | LA80: 146 | LK80: 0 | LN80: 5 | LO80: 56 | LP80: 14 | LT80: 6 | LW80: 2 | LX80: 47 | LY80: 6 | LZ80: 8 | MA80: 33 | MB80: 3 | MC80: 6 | ME80: 18 | MG80: 20 | MH80: 49 | MI80: 2 | MK80: 23 | MM80: 16 | MN80: 51 | MO80: 34 | MQ80: 2 | MS80: 21 | MT80: 19 | MU80: 2 | MV80: 12 | MW80: 2 | MX80: 9 | MY80: 1 | MZ80: 3 | NA80: 2 | NE80: 111 | NJ80: 1 | NM80: 4 | NN80: 11 | NO80: 7 | NP80: 35 | NQ80: 2 | NR80: 138 | NS80: 20 | NT80: 484 | NU80: 158 | NV80: 33 | NW80: 0 | NX80: 1 | NY80: 2 | OB80: 4 | OD80: 29 | OE80: 24 | OF80: 6 | OI80: 38 | OJ80: 38 | OK80: 54 | OO80: 38698 | OP80: 2157 | OU80: 98 | OV80: 4012 | PI80: 44965 | PM80: =IFERROR(VLOOKUP($A80&"",Key!$A:$C,3,FALSE),"") -> ISIC 25
A81: 332800 | B81: Coating, engraving, heat treating and allied activities | P81: 58 | Q81: 29 | R81: 7 | S81: 99 | T81: 18 | U81: 65 | V81: 31 | W81: 77 | X81: 35 | AA81: 5 | AB81: 2 | AC81: 385 | AD81: 172 | AE81: 223 | AF81: 57 | AG81: 1209 | AH81: 48 | AI81: 178 | AJ81: 68 | AK81: 339 | AL81: 122 | AM81: 248 | AN81: 190 | AO81: 113 | AP81: 66 | AQ81: 13 | AR81: 38 | AS81: 25 | AT81: 149 | AU81: 20 | AV81: 44 | AW81: 17 | AX81: 9 | AY81: 17 | AZ81: 52 | BA81: 27 | BB81: 5 | BC81: 387 | BD81: 68 | BE81: 34 | BF81: 4 | BG81: 151 | BH81: 63 | BI81: 50 | BJ81: 27 | BK81: 130 | BL81: 137 | BM81: 25 | BN81: 39 | BO81: 62 | BP81: 32 | BQ81: 232 | BR81: 15 | BS81: 91 | BT81: 24 | BU81: 25 | BV81: 133 | BW81: 45 | BX81: 193 | BY81: 64 | BZ81: 890 | CA81: 27 | CB81: 205 | CC81: 7 | CD81: 28 | CE81: 153 | CF81: 40 | CG81: 9 | CH81: 6 | CI81: 13 | CJ81: 253 | CK81: 22 | CL81: 138 | CM81: 16 | CN81: 2 | CO81: 97 | CP81: 12 | CQ81: 65 | CR81: 4 | CS81: 30 | CT81: 23 | CU81: 18 | CV81: 13 | CW81: 100 | CX81: 2 | CY81: 22 | CZ81: 31 | DA81: 9 | DB81: 7 | DC81: 248 | DD81: 23 | DE81: 73 | DF81: 26 | DG81: 25 | DH81: 23 | DI81: 6 | DJ81: 3 | DK81: 5 | DL81: 4 | DM81: 67 | DN81: 14 | DO81: 12 | DP81: 19 | DQ81: 64 | DR81: 79 | DS81: 83 | DT81: 1 | DU81: 52 | DV81: 20 | DW81: 33 | DX81: 69 | DY81: 116 | DZ81: 10 | EA81: 2 | EB81: 1 | EC81: 2 | ED81: 33 | EE81: 14 | EF81: 79 | EG81: 47 | EH81: 19 | EI81: 90 | EJ81: 60 | EK81: 26 | EL81: 39 | EM81: 19 | EN81: 124 | EO81: 14 | EP81: 30 | EQ81: 25 | ER81: 99 | ES81: 35 | ET81: 201 | EU81: 31 | EV81: 0 | EW81: 13 | EX81: 119 | EY81: 75 | EZ81: 158 | FA81: 97 | FB81: 535 | FC81: 124 | FD81: 164 | FE81: 95 | FF81: 2 | FG81: 109 | FH81: 284 | FI81: 29 | FJ81: 21 | FK81: 10 | FL81: 36 | FM81: 11 | FN81: 138 | FO81: 24 | FP81: 119 | FQ81: 86 | FR81: 6 | FS81: 52 | FT81: 7 | FU81: 70 | FV81: 114 | FW81: 46 | FX81: 139 | FY81: 100 | FZ81: 4 | GA81: 8 | GB81: 7 | GC81: 2 | GD81: 18 | GE81: 1 | GF81: 9 | GG81: 22 | GH81: 76 | HG81: 1494 | HH81: 97 | HI81: 17 | HK81: 237 | HL81: 9 | HM81: 20 | HN81: 32 | HO81: 31 | HP81: 22 | HQ81: 49 | HR81: 3 | HS81: 4 | HT81: 54 | HU81: 328 | HV81: 376 | HW81: 444 | HX81: 252 | HY81: 45 | HZ81: 133 | IA81: 38 | IB81: 319 | IC81: 35 | ID81: 385 | IE81: 4 | IF81: 89 | IG81: 24 | IH81: 15 | II81: 20 | IJ81: 53 | IK81: 69 | IL81: 184 | IM81: 189 | IN81: 65 | IO81: 2 | IP81: 1 | IQ81: 1 | IS81: 20 | IT81: 19 | IU81: 136 | IV81: 177 | IW81: 753 | IX81: 166 | IY81: 34 | IZ81: 279 | JA81: 279 | JB81: 87 | JC81: 26 | JD81: 72 | JE81: 32 | JF81: 47 | JG81: 473 | JH81: 61 | JI81: 29 | JJ81: 272 | JK81: 3 | JL81: 0 | JM81: 1 | JN81: 0 | JO81: 10 | JR81: 3 | JS81: 1 | JT81: 0 | JV81: 125 | JY81: 4 | JZ81: 1 | KA81: 19 | KB81: 2 | KC81: 30 | KD81: 0 | KE81: 22 | KF81: 2 | KG81: 373 | KH81: 711 | KI81: 17 | KJ81: 8 | KK81: 39 | KM81: 70 | KN81: 52 | KO81: 46 | KP81: 36 | KQ81: 29 | KR81: 509 | KT81: 7 | KU81: 60 | KV81: 7 | KW81: 875 | KX81: 416 | KY81: 58 | LA81: 68 | LK81: 1 | LL81: 0 | LO81: 18 | LT81: 35 | LW81: 41 | LX81: 1 | LY81: 2 | LZ81: 34 | MJ81: 3 | MK81: 12 | MM81: 225 | MN81: 8 | MQ81: 0 | MR81: 3 | MZ81: 2 | NA81: 1 | NR81: 174 | NS81: 21 | NT81: 251 | NU81: 171 | OE81: 15 | OF81: 126 | ON81: 87 | OO81: 26467 | OU81: 199 | OV81: 179 | PI81: 26845 | PM81: =IFERROR(VLOOKUP($A81&"",Key!$A:$C,3,FALSE),"") -> ISIC 25
A82: 332913 | B82: Plumbing fixture fitting and trim manufacturing | AA82: 159 | AB82: 363 | AC82: 1521 | AD82: 608 | AE82: 922 | AF82: 739 | AG82: 1651 | AH82: 120 | AI82: 480 | AJ82: 80 | AK82: 1952 | AL82: 258 | AP82: 28 | BW82: 4 | CA82: 9 | CB82: 4 | CK82: 5 | CZ82: 41 | DG82: 4 | DK82: 7 | DO82: 17 | EV82: 0 | EW82: 28 | FC82: 41 | JG82: 314 | JK82: 0 | JL82: 3 | JM82: 0 | JN82: 0 | JR82: 0 | JT82: 0 | JY82: 2 | KB82: 5 | KC82: 1 | KD82: 4 | KF82: 1 | KW82: 29 | KX82: 187 | KY82: 3 | KZ82: 154 | LK82: 5 | LO82: 44 | LZ82: 72 | MH82: 17 | MO82: 32 | MP82: 49 | MQ82: 7 | MS82: 58 | MZ82: 64 | NC82: 23 | ND82: 24 | NE82: 26 | NF82: 2 | NM82: 32 | NN82: 10 | NO82: 194 | NP82: 48 | NQ82: 16 | OB82: 113 | OM82: 6 | OO82: 10588 | OU82: 87 | OV82: 312 | PI82: 10987 | PM82: =IFERROR(VLOOKUP($A82&"",Key!$A:$C,3,FALSE),"") -> ISIC 25
A83: 33291A | B83: Valve and fittings other than plumbing | P83: 4107 | R83: 7 | V83: 32 | W83: 53 | Y83: 747 | AA83: 484 | AB83: 1435 | AC83: 376 | AD83: 44 | AE83: 650 | AF83: 166 | AG83: 490 | AH83: 381 | AI83: 1753 | AJ83: 61 | AK83: 1072 | AL83: 900 | AP83: 35 | AV83: 0 | BC83: 89 | BD83: 2 | BF83: 1 | BK83: 13 | BM83: 18 | BN83: 25 | BO83: 34 | BP83: 30 | BQ83: 258 | BR83: 120 | BS83: 111 | BT83: 103 | BU83: 5 | BV83: 37 | BW83: 40 | BX83: 206 | BY83: 19 | BZ83: 31 | CA83: 15 | CB83: 2260 | CC83: 11 | CD83: 104 | CE83: 89 | CF83: 15 | CG83: 131 | CH83: 24 | CI83: 1106 | CJ83: 283 | CK83: 214 | CL83: 497 | CM83: 23 | CN83: 6 | CO83: 559 | CP83: 9 | CQ83: 267 | CR83: 130 | CS83: 21 | CT83: 20 | CU83: 54 | CV83: 46 | CW83: 416 | CX83: 0 | CY83: 14 | CZ83: 151 | DA83: 443 | DB83: 107 | DC83: 324 | DD83: 16 | DE83: 15 | DF83: 17 | DG83: 536 | DH83: 50 | DJ83: 0 | DK83: 1 | DL83: 10 | DM83: 73 | DN83: 2 | DO83: 0 | DP83: 1 | DQ83: 9 | DR83: 13 | DS83: 2 | DT83: 0 | DU83: 29 | DV83: 8 | DW83: 6 | DX83: 31 | DY83: 13 | DZ83: 73 | ED83: 11 | EE83: 1 | EF83: 25 | EG83: 28 | EH83: 3 | EK83: 91 | EL83: 23 | EP83: 17 | EQ83: 232 | ER83: 638 | ES83: 117 | ET83: 61 | EU83: 27 | EV83: 0 | EW83: 2 | EX83: 312 | EY83: 101 | EZ83: 36 | FB83: 167 | FC83: 189 | FD83: 373 | FE83: 2049 | FF83: 27 | FG83: 552 | FH83: 149 | FI83: 36 | FJ83: 37 | FK83: 201 | FL83: 3 | FM83: 13 | FN83: 486 | FO83: 15 | FQ83: 7 | FS83: 5 | FT83: 1 | FU83: 11 | FV83: 19 | FW83: 2 | FX83: 59 | FY83: 58 | FZ83: 11 | GC83: 0 | GD83: 11 | GE83: 2 | GF83: 3 | GH83: 15 | GP83: 14 | GS83: 12 | GT83: 31 | GU83: 12 | GV83: 3 | HB83: 12 | HD83: 14 | HG83: 269 | HH83: 32 | HI83: 4 | HK83: 3 | HT83: 72 | HU83: 241 | HV83: 270 | IE83: 14 | IH83: 14 | II83: 19 | IJ83: 29 | IK83: 76 | IL83: 239 | IM83: 42 | IN83: 6 | IS83: 2 | IT83: 13 | IU83: 43 | IX83: 531 | IZ83: 206 | JE83: 23 | JG83: 215 | JH83: 15 | JJ83: 117 | JK83: 0 | JL83: 0 | JM83: 1 | JN83: 0 | JO83: 2 | JR83: 0 | JS83: 27 | JT83: 0 | JV83: 42 | JW83: 11 | KB83: 3 | KD83: 1 | KE83: 1 | KH83: 326 | KI83: 8 | KL83: 7 | KM83: 75 | KO83: 13 | KV83: 3444 | KW83: 869 | KX83: 159 | KY83: 2 | KZ83: 33 | LA83: 29 | LK83: 0 | LO83: 44 | LT83: 259 | LW83: 260 | LZ83: 157 | MD83: 0 | MF83: 9 | MH83: 109 | MO83: 198 | MQ83: 2 | MZ83: 4 | NC83: 5 | ND83: 29 | NE83: 16 | NM83: 7 | NN83: 14 | NO83: 23 | NP83: 14 | NR83: 130 | NS83: 0 | NT83: 656 | NU83: 142 | NZ83: 0 | OA83: 0 | OB83: 18 | OD83: 782 | OE83: 1 | OJ83: 4 | OK83: 21 | OM83: 57 | ON83: 1002 | OO83: 40015 | OQ83: 3671 | OU83: 250 | OV83: 11108 | OX83: 347 | PB83: 1 | PF83: 17 | PI83: 55410 | PM83: =IFERROR(VLOOKUP($A83&"",Key!$A:$C,3,FALSE),"") -> ISIC 25
A84: 332991 | B84: Ball and roller bearing manufacturing | P84: 161 | AP84: 3 | BD84: 88 | BM84: 8 | BN84: 14 | BO84: 23 | BP84: 11 | BQ84: 89 | BR84: 6 | BS84: 35 | BT84: 8 | BU84: 10 | BV84: 45 | BW84: 13 | BX84: 42 | BY84: 16 | BZ84: 57 | CA84: 9 | CB84: 71 | CC84: 1326 | CD84: 11 | CE84: 55 | CF84: 12 | CG84: 221 | CH84: 93 | CI84: 59 | CJ84: 39 | CK84: 26 | CL84: 168 | CM84: 8 | CN84: 3 | CO84: 35 | CP84: 5 | CQ84: 136 | CR84: 13 | CS84: 10 | CT84: 7 | CU84: 49 | CV84: 26 | CW84: 166 | CX84: 26 | CY84: 166 | CZ84: 24 | DA84: 80 | DB84: 71 | DC84: 115 | DD84: 63 | DE84: 126 | DF84: 10 | DG84: 17 | DH84: 230 | DJ84: 1 | DK84: 1 | DM84: 8 | DN84: 2 | DO84: 0 | DP84: 1 | DQ84: 34 | DR84: 27 | DS84: 7 | DT84: 0 | DU84: 18 | DV84: 5 | DW84: 6 | DX84: 20 | DY84: 24 | DZ84: 37 | EA84: 5 | ED84: 19 | EF84: 29 | EG84: 15 | EH84: 94 | EI84: 116 | EJ84: 43 | EK84: 14 | EL84: 12 | EN84: 63 | EP84: 22 | EQ84: 20 | ER84: 42 | ES84: 25 | ET84: 18 | EU84: 10 | EV84: 0 | EW84: 4 | EX84: 162 | EY84: 99 | EZ84: 100 | FA84: 37 | FB84: 113 | FC84: 417 | FD84: 268 | FE84: 177 | FF84: 11 | FG84: 112 | FI84: 5 | FJ84: 23 | FK84: 4 | FL84: 5 | FM84: 5 | FN84: 16 | FO84: 8 | FQ84: 11 | FS84: 10 | FT84: 3 | FU84: 22 | FV84: 35 | FW84: 4 | FX84: 37 | FY84: 31 | FZ84: 2 | GB84: 5 | GC84: 3 | GD84: 4 | GE84: 3 | GF84: 5 | GG84: 8 | GH84: 26 | IZ84: 1 | JH84: 15 | JJ84: 110 | JV84: 4 | KB84: 1 | KI84: 83 | KJ84: 2 | KV84: 16 | KW84: 264 | KX84: 1225 | KY84: 46 | LZ84: 38 | MF84: 2 | MM84: 7 | MO84: 146 | NR84: 12 | NS84: 40 | NT84: 231 | NU84: 29 | OD84: 657 | OE84: 1 | OH84: 2 | ON84: 42 | OO84: 9590 | OU84: 104 | OV84: 2030 | PI84: 11724 | PM84: =IFERROR(VLOOKUP($A84&"",Key!$A:$C,3,FALSE),"") -> ISIC 25
A85: 332996 | B85: Fabricated pipe and pipe fitting manufacturing | Z85: 0 | AA85: 6 | AB85: 6 | AC85: 540 | AD85: 262 | AE85: 364 | AF85: 117 | AG85: 638 | AH85: 553 | AI85: 172 | AJ85: 108 | AK85: 811 | AL85: 296 | BQ85: 141 | BS85: 88 | BT85: 239 | BW85: 1 | CB85: 1071 | CD85: 447 | CF85: 9 | CK85: 1 | CO85: 69 | CP85: 19 | CQ85: 36 | DG85: 1 | ED85: 189 | EY85: 5 | FG85: 139 | JK85: 1 | JL85: 1 | JM85: 0 | JN85: 0 | JR85: 0 | JT85: 0 | KB85: 3 | KD85: 2 | KM85: 15 | KV85: 1 | KW85: 13 | KX85: 54 | KY85: 2 | KZ85: 1 | LK85: 2 | LO85: 79 | LT85: 105 | LW85: 120 | LZ85: 8 | MP85: 0 | MQ85: 0 | MR85: 0 | MS85: 31 | MY85: 1 | NC85: 14 | ND85: 10 | NE85: 18 | NF85: 1 | NM85: 18 | NN85: 1 | OE85: 0 | OI85: 1 | ON85: 20 | OO85: 6851 | OQ85: 766 | OU85: -53 | OV85: 97 | OX85: 2 | PB85: 0 | PF85: 2 | PI85: 7665 | PM85: =IFERROR(VLOOKUP($A85&"",Key!$A:$C,3,FALSE),"") -> ISIC 25
A86: 33299A | B86: Ammunition, arms, ordnance, and accessories manufacturing | BW86: 0 | CB86: 0 | CE86: 1254 | DG86: 0 | KK86: 1 | ML86: 10 | MM86: 380 | NM86: 15 | NU86: 1035 | OD86: 3646 | OE86: 82 | OJ86: 8 | OK86: 992 | OO86: 7423 | OP86: 16439 | OU86: -132 | OV86: 4164 | OX86: 393 | PI86: 28288 | PM86: =IFERROR(VLOOKUP($A86&"",Key!$A:$C,3,FALSE),"") -> ISIC 25
A87: 332999 | B87: Other fabricated metal manufacturing | C87: 3 | D87: 12 | E87: 3 | F87: 2 | G87: 2 | H87: 3 | I87: 17 | J87: 1 | K87: 1 | L87: 1 | M87: 0 | N87: 5 | O87: 2 | P87: 76 | Q87: 6 | R87: 1 | S87: 14 | T87: 1 | U87: 1 | V87: 3 | W87: 32 | Y87: 244 | AA87: 111 | AB87: 799 | AC87: 305 | AD87: 111 | AE87: 435 | AF87: 35 | AG87: 224 | AH87: 1886 | AI87: 231 | AJ87: 55 | AK87: 248 | AL87: 210 | AM87: 51 | AN87: 59 | AO87: 18 | AP87: 26 | AQ87: 35 | AR87: 9 | AS87: 7 | AT87: 34 | AU87: 42 | AV87: 307 | AW87: 3 | AX87: 1 | AY87: 4 | AZ87: 11 | BA87: 26 | BB87: 26 | BC87: 4 | BD87: 51 | BE87: 7 | BF87: 1 | BG87: 15 | BH87: 35 | BI87: 9 | BJ87: 7 | BK87: 117 | BL87: 525 | BM87: 8 | BN87: 10 | BO87: 17 | BP87: 32 | BQ87: 75 | BR87: 15 | BS87: 27 | BT87: 8 | BU87: 8 | BV87: 30 | BW87: 28 | BX87: 51 | BY87: 36 | BZ87: 47 | CA87: 12 | CB87: 64 | CC87: 5 | CD87: 9 | CE87: 44 | CF87: 677 | CG87: 28 | CH87: 35 | CI87: 7 | CJ87: 58 | CK87: 23 | CL87: 208 | CM87: 5 | CN87: 3 | CO87: 32 | CP87: 11 | CQ87: 23 | CR87: 6 | CS87: 6 | CT87: 9 | CU87: 6 | CV87: 7 | CW87: 36 | CX87: 1 | CY87: 15 | CZ87: 57 | DA87: 13 | DB87: 7 | DC87: 157 | DD87: 15 | DE87: 21 | DF87: 5 | DG87: 73 | DH87: 8 | DJ87: 0 | DK87: 4 | DL87: 7 | DM87: 22 | DN87: 4 | DO87: 6 | DP87: 0 | DQ87: 52 | DR87: 30 | DS87: 92 | DT87: 0 | DU87: 14 | DV87: 9 | DW87: 21 | DX87: 24 | DY87: 12 | DZ87: 5 | EA87: 6 | EB87: 0 | EC87: 1 | ED87: 33 | EE87: 6 | EF87: 23 | EG87: 10 | EH87: 7 | EI87: 131 | EJ87: 54 | EK87: 27 | EL87: 7 | EM87: 4 | EN87: 42 | EO87: 4 | EP87: 16 | EQ87: 5 | ER87: 21 | ES87: 9 | ET87: 18 | EU87: 3 | EV87: 0 | EW87: 5 | EX87: 33 | EY87: 19 | EZ87: 20 | FA87: 90 | FB87: 89 | FC87: 40 | FD87: 43 | FE87: 16 | FF87: 20 | FG87: 25 | FH87: 7 | FI87: 3 | FJ87: 3 | FK87: 5 | FL87: 45 | FM87: 17 | FN87: 36 | FO87: 80 | FP87: 26 | FQ87: 9 | FS87: 8 | FT87: 15 | FU87: 20 | FV87: 37 | FW87: 16 | FX87: 70 | FY87: 35 | FZ87: 6 | GB87: 5 | GC87: 8 | GD87: 11 | GE87: 4 | GF87: 3 | GG87: 8 | GH87: 481 | GI87: 9 | GJ87: 39 | GK87: 6 | GL87: 17 | GM87: 2 | GN87: 32 | GO87: 1 | GP87: 158 | GQ87: 3 | GR87: 41 | GS87: 75 | GT87: 124 | GU87: 9 | GV87: 30 | GW87: 33 | GX87: 99 | GY87: 3 | GZ87: 55 | HA87: 79 | HB87: 123 | HC87: 196 | HD87: 40 | HE87: 117 | HF87: 61 | HG87: 29 | HI87: 5 | HJ87: 13 | HK87: 72 | HL87: 2 | HM87: 5 | HN87: 10 | HO87: 7 | HP87: 5 | HQ87: 15 | HR87: 1 | HS87: 2 | HT87: 11 | HU87: 14 | HV87: 54 | HW87: 93 | HX87: 17 | HY87: 8 | HZ87: 220 | IA87: 7 | IB87: 37 | IC87: 10 | IE87: 2 | IF87: 26 | IG87: 7 | II87: 4 | IJ87: 13 | IK87: 93 | IL87: 10 | IM87: 55 | IN87: 13 | IO87: 9 | IQ87: 4 | IR87: 24 | IS87: 7 | IT87: 4 | IU87: 40 | IV87: 39 | IW87: 68 | IX87: 1 | IY87: 13 | IZ87: 82 | JA87: 43 | JB87: 13 | JC87: 4 | JD87: 1 | JE87: 5 | JF87: 7 | JG87: 87 | JH87: 35 | JI87: 4 | JJ87: 145 | JK87: 18 | JL87: 17 | JM87: 23 | JN87: 29 | JO87: 69 | JP87: 56 | JQ87: 27 | JR87: 53 | JS87: 60 | JT87: 3 | JV87: 52 | JW87: 35 | JX87: 14 | JY87: 11 | JZ87: 16 | KA87: 32 | KB87: 20 | KC87: 34 | KD87: 39 | KF87: 73 | KG87: 8 | KH87: 9 | KI87: 70 | KJ87: 8 | KK87: 8 | KL87: 2 | KM87: 301 | KN87: 0 | KO87: 1 | KQ87: 2 | KR87: 23 | KS87: 0 | KW87: 827 | KX87: 137 | KY87: 2 | KZ87: 25 | LA87: 24 | LB87: 2 | LC87: 203 | LD87: 145 | LE87: 133 | LF87: 29 | LJ87: 40 | LK87: 1 | LL87: 1 | LM87: 1469 | LN87: 2 | LO87: 26 | LR87: 32 | LS87: 6 | LT87: 176 | LU87: 6 | LV87: 18 | LW87: 260 | LX87: 7 | LY87: 2 | LZ87: 68 | MA87: 14 | MB87: 7 | MC87: 14 | MD87: 18 | ME87: 14 | MF87: 119 | MG87: 8 | MH87: 146 | MI87: 4 | MJ87: 5 | MK87: 156 | ML87: 3 | MM87: 8 | MN87: 9 | MO87: 294 | MP87: 1 | MR87: 25 | MS87: 37 | MT87: 46 | MU87: 10 | MV87: 10 | MX87: 3 | MY87: 24 | MZ87: 69 | NA87: 5 | NB87: 2 | NC87: 7 | ND87: 20 | NE87: 44 | NF87: 4 | NG87: 0 | NJ87: 1 | NM87: 62 | NN87: 1486 | NO87: 215 | NP87: 26 | NQ87: 6 | NR87: 5 | NS87: 4 | NT87: 6 | NV87: 33 | NX87: 0 | NY87: 4 | NZ87: 48 | OA87: 4 | OB87: 43 | OD87: 6 | OF87: 60 | OI87: 11 | OK87: 68 | OM87: 5 | ON87: 50 | OO87: 21539 | OP87: 4643 | OQ87: 627 | OU87: -63 | OV87: 6048 | OX87: 2 | PB87: 187 | PF87: 246 | PI87: 33228 | PM87: =IFERROR(VLOOKUP($A87&"",Key!$A:$C,3,FALSE),"") -> ISIC 25
A88: 333111 | B88: Farm machinery and equipment manufacturing | C88: 201 | D88: 705 | E88: 92 | F88: 99 | G88: 112 | H88: 283 | I88: 568 | J88: 33 | K88: 22 | L88: 145 | M88: 0 | N88: 9 | AC88: 0 | CG88: 1540 | CH88: 231 | JN88: 0 | JO88: 16 | LZ88: 69 | MF88: 6 | MM88: 1 | MO88: 264 | NG88: 21 | NT88: 10 | OI88: 526 | OK88: 346 | ON88: 801 | OO88: 6102 | OQ88: 33769 | OU88: 106 | OV88: 8405 | OX88: 0 | PB88: 77 | PF88: 123 | PI88: 48582 | PM88: =IFERROR(VLOOKUP($A88&"",Key!$A:$C,3,FALSE),"") -> ISIC 28
A89: 333112 | B89: Lawn and garden equipment manufacturing | H89: 0 | N89: 14 | O89: 16 | CH89: 0 | JN89: 0 | JV89: 10 | JY89: 9 | KD89: 12 | KE89: 12 | KW89: 0 | KX89: 0 | LK89: 111 | LL89: 10 | LO89: 534 | LP89: 24 | LZ89: 27 | MF89: 1 | MH89: 120 | MM89: 16 | NU89: 359 | OK89: 58 | ON89: 0 | OO89: 1336 | OP89: 4158 | OQ89: 19601 | OU89: 150 | OV89: 89 | OX89: 0 | PB89: 0 | PF89: 21 | PI89: 25355 | PM89: =IFERROR(VLOOKUP($A89&"",Key!$A:$C,3,FALSE),"") -> ISIC 28
A90: 333120 | B90: Construction machinery manufacturing | P90: 455 | Q90: 572 | R90: 87 | S90: 442 | T90: 346 | U90: 475 | V90: 560 | W90: 1048 | Z90: 0 | AA90: 10 | AC90: 117 | AD90: 139 | AE90: 13 | AG90: 1695 | AI90: 80 | AJ90: 77 | AK90: 423 | AL90: 19 | CG90: 4 | CI90: 242 | CJ90: 1 | FK90: 287 | JN90: 0 | JT90: 0 | KD90: 0 | KX90: 9 | LW90: 242 | LZ90: 50 | MF90: 1 | MO90: 868 | OM90: 4 | OO90: 8268 | OQ90: 31748 | OU90: 885 | OV90: 10444 | OX90: 480 | PB90: 2 | PF90: 12704 | PI90: 64532 | PM90: =IFERROR(VLOOKUP($A90&"",Key!$A:$C,3,FALSE),"") -> ISIC 28
A91: 333130 | B91: Mining and oil and gas field machinery manufacturing | P91: 2135 | Q91: 1017 | R91: 242 | S91: 69 | T91: 82 | U91: 70 | V91: 285 | W91: 1917 | Z91: 0 | AC91: 19 | AJ91: 3 | CG91: 20 | CJ91: 92 | LW91: 55 | LZ91: 6 | MO91: 322 | OD91: 29 | OO91: 6364 | OQ91: 22308 | OU91: -55 | OV91: 3829 | PI91: 32445 | PM91: =IFERROR(VLOOKUP($A91&"",Key!$A:$C,3,FALSE),"") -> ISIC 28
A92: 333242 | B92: Semiconductor machinery manufacturing | CK92: 317 | DO92: 21 | DQ92: 1 | KM92: 4 | KN92: 11 | KP92: 20 | KQ92: 8 | KR92: 37 | KS92: 31 | KT92: 7 | KU92: 98 | KV92: 41 | KW92: 26 | KY92: 6 | KZ92: 34 | LA92: 372 | LB92: 34 | LT92: 257 | LW92: 43 | LZ92: 119 | MF92: 3 | OK92: 4 | OO92: 1492 | OQ92: 6564 | OU92: 365 | OV92: 13639 | PI92: 22060 | PM92: =IFERROR(VLOOKUP($A92&"",Key!$A:$C,3,FALSE),"") -> ISIC 28
A93: 33329A | B93: Other industrial machinery manufacturing | H93: 12 | AC93: 7 | AD93: 8 | BF93: 0 | BK93: 48 | BL93: 126 | CL93: 894 | DP93: 160 | FR93: 6 | FS93: 4 | FY93: 0 | GU93: 138 | HM93: 1 | HU93: 228 | HV93: 355 | IB93: 773 | IC93: 14 | IH93: 136 | II93: 52 | IJ93: 149 | IK93: 586 | IL93: 286 | IM93: 189 | IU93: 394 | IZ93: 128 | JA93: 64 | JB93: 146 | JC93: 10 | JE93: 5 | JF93: 36 | JG93: 431 | JN93: 362 | JT93: 2 | JV93: 0 | JW93: 0 | JX93: 6 | KA93: 0 | KB93: 278 | KM93: 2 | KO93: 0 | KR93: 1 | KW93: 0 | KZ93: 0 | LO93: 14 | LS93: 0 | LT93: 0 | LU93: 0 | LX93: 0 | LZ93: 39 | MB93: 183 | MF93: 3 | MI93: 0 | MJ93: 0 | MK93: 0 | MN93: 0 | MS93: 1 | MU93: 0 | NN93: 1 | NO93: 36 | NP93: 106 | NQ93: 22 | NV93: 8 | NX93: 2 | NY93: 4 | OB93: 47 | OE93: 0 | OI93: 130 | ON93: 62 | OO93: 6697 | OP93: 1033 | OQ93: 30737 | OU93: 253 | OV93: 11580 | OX93: 24 | PB93: 50 | PF93: 330 | PI93: 50703 | PM93: =IFERROR(VLOOKUP($A93&"",Key!$A:$C,3,FALSE),"") -> ISIC 28
A94: 333314 | B94: Optical instrument and lens manufacturing | AC94: 34 | AD94: 31 | CM94: 662 | CN94: 125 | CU94: 0 | CV94: 1 | DO94: 0 | DP94: 1 | DQ94: 11 | DT94: 0 | DU94: 5 | DV94: 2 | DW94: 3 | DX94: 21 | DZ94: 6 | EP94: 391 | FY94: 467 | GA94: 76 | IZ94: 52 | LL94: 0 | LZ94: 0 | MF94: 0 | MU94: 34 | MW94: 265 | OO94: 2189 | OP94: 45 | OQ94: 5797 | OU94: 71 | OV94: 4279 | OX94: 558 | PF94: 63 | PI94: 13002 | PM94: =IFERROR(VLOOKUP($A94&"",Key!$A:$C,3,FALSE),"") -> ISIC 28
A95: 333316 | B95: Photographic and photocopying equipment manufacturing | CN95: 11 | IB95: 1 | IC95: 24 | KW95: 3 | KX95: 24 | LP95: 0 | MK95: 66 | MM95: 17 | MP95: 2 | NS95: 62 | NY95: 275 | OK95: 1 | OO95: 485 | OP95: 1279 | OQ95: 1641 | OU95: -34 | OV95: 464 | OX95: 4 | PB95: 1 | PF95: 247 | PI95: 4088 | PM95: =IFERROR(VLOOKUP($A95&"",Key!$A:$C,3,FALSE),"") -> ISIC 28
A96: 333318 | B96: Other commercial and service industry machinery manufacturing | P96: 76 | Q96: 0 | R96: 0 | S96: 1 | T96: 0 | U96: 1 | V96: 0 | W96: 1 | X96: 2 | Y96: 0 | Z96: 0 | AA96: 2 | AB96: 1 | AC96: 5 | AD96: 2 | AE96: 140 | AF96: 2 | AG96: 5 | AH96: 31 | AI96: 3176 | AJ96: 3 | AK96: 1033 | AL96: 2 | AM96: 0 | AN96: 1 | AO96: 0 | AP96: 1 | AQ96: 0 | AR96: 1 | AS96: 0 | AT96: 0 | AU96: 0 | AV96: 0 | AW96: 0 | AX96: 0 | AY96: 0 | AZ96: 0 | BA96: 0 | BB96: 0 | BC96: 1 | BD96: 1 | BE96: 1 | BF96: 0 | BG96: 1 | BH96: 0 | BI96: 0 | BJ96: 1 | BK96: 2 | BL96: 4 | BM96: 0 | BN96: 1 | BO96: 1 | BP96: 2 | BQ96: 2 | BR96: 297 | BS96: 1 | BT96: 1 | BU96: 1 | BV96: 3 | BW96: 1 | BX96: 14 | BY96: 12 | BZ96: 10 | CA96: 1 | CB96: 7 | CC96: 3 | CD96: 1 | CE96: 2 | CF96: 2 | CG96: 1 | CH96: 1 | CI96: 3 | CJ96: 3 | CK96: 3 | CL96: 33 | CM96: 0 | CN96: 0 | CO96: 43 | CP96: 0 | CQ96: 4 | CR96: 2 | CS96: 4 | CT96: 11 | CU96: 7 | CV96: 3 | CW96: 8 | CX96: 1 | CY96: 2 | CZ96: 1 | DA96: 4 | DB96: 14 | DC96: 11 | DD96: 1 | DE96: 2 | DF96: 0 | DG96: 8 | DH96: 31 | DI96: 0 | DJ96: 0 | DK96: 0 | DL96: 0 | DM96: 3 | DN96: 0 | DO96: 0 | DP96: 0 | DQ96: 1 | DR96: 0 | DS96: 2 | DT96: 0 | DU96: 1 | DV96: 2 | DW96: 2 | DX96: 1 | DY96: 0 | DZ96: 4 | EA96: 0 | EB96: 0 | EC96: 0 | ED96: 0 | EE96: 1 | EF96: 0 | EG96: 0 | EH96: 0 | EI96: 0 | EJ96: 1 | EK96: 0 | EL96: 0 | EM96: 0 | EN96: 7 | EO96: 0 | EP96: 1 | EQ96: 0 | ER96: 0 | ES96: 0 | ET96: 3 | EU96: 0 | EV96: 0 | EW96: 0 | EX96: 16 | EY96: 0 | EZ96: 26 | FA96: 0 | FB96: 2 | FC96: 38 | FD96: 1 | FE96: 6 | FF96: 0 | FG96: 0 | FH96: 0 | FI96: 1 | FJ96: 1 | FK96: 2 | FL96: 1 | FM96: 0 | FN96: 0 | FO96: 0 | FP96: 0 | FQ96: 0 | FR96: 0 | FS96: 0 | FT96: 0 | FU96: 0 | FV96: 1 | FW96: 1 | FX96: 6 | FY96: 4 | FZ96: 0 | GA96: 1 | GB96: 0 | GC96: 0 | GD96: 0 | GE96: 0 | GF96: 0 | GG96: 8 | GH96: 6 | GI96: 0 | GJ96: 0 | GK96: 0 | GL96: 0 | GM96: 0 | GN96: 0 | GO96: 0 | GP96: 1 | GQ96: 0 | GR96: 1 | GS96: 0 | GT96: 0 | GU96: 0 | GV96: 0 | GW96: 0 | GX96: 0 | GY96: 0 | GZ96: 1 | HA96: 0 | HB96: 0 | HC96: 0 | HD96: 0 | HE96: 0 | HF96: 0 | HG96: 2 | HH96: 0 | HI96: 0 | HJ96: 0 | HK96: 0 | HL96: 0 | HM96: 1 | HN96: 0 | HO96: 0 | HP96: 0 | HQ96: 1 | HR96: 1 | HS96: 0 | HT96: 0 | HU96: 0 | HV96: 0 | HW96: 1 | HX96: 0 | HY96: 0 | HZ96: 0 | IA96: 0 | IB96: 1 | IC96: 0 | ID96: 0 | IE96: 0 | IF96: 0 | IG96: 1 | IH96: 1 | II96: 0 | IJ96: 0 | IK96: 0 | IL96: 0 | IM96: 0 | IN96: 0 | IO96: 0 | IP96: 0 | IQ96: 0 | IR96: 0 | IS96: 1 | IT96: 0 | IU96: 0 | IV96: 0 | IW96: 0 | IX96: 0 | IY96: 0 | IZ96: 1 | JA96: 1 | JB96: 0 | JC96: 0 | JD96: 0 | JE96: 0 | JF96: 0 | JG96: 0 | JH96: 0 | JI96: 0 | JJ96: 0 | JQ96: 3 | JV96: 10 | JW96: 8 | JX96: 17 | JY96: 5 | JZ96: 0 | KA96: 11 | KD96: 0 | KG96: 21 | KH96: 23 | KK96: 3726 | KL96: 0 | KM96: 75 | KN96: 0 | KO96: 0 | KP96: 0 | KQ96: 0 | KR96: 0 | KS96: 1 | KT96: 0 | KU96: 2 | KV96: 1 | KW96: 38 | KX96: 228 | KY96: 9 | KZ96: 1 | LA96: 1 | LB96: 0 | LH96: 627 | LM96: 70 | LP96: 0 | LV96: 81 | LZ96: 8 | MA96: 2 | ME96: 2 | MF96: 196 | MG96: 0 | MH96: 59 | ML96: 459 | MP96: 1056 | MR96: 114 | MS96: 3 | MZ96: 7 | NC96: 1 | NN96: 0 | NO96: 0 | NP96: 0 | NQ96: 0 | NR96: 20 | NT96: 623 | NX96: 100 | NY96: 203 | OD96: 0 | OE96: 5 | OF96: 64 | OG96: 2 | OH96: 1 | OI96: 756 | OJ96: 144 | OK96: 64 | OL96: 16 | OM96: 4 | ON96: 1 | OO96: 14115 | OP96: 346 | OQ96: 19273 | OU96: 562 | OV96: 2197 | OX96: 377 | PB96: 21 | PF96: 871 | PI96: 37762 | PM96: =IFERROR(VLOOKUP($A96&"",Key!$A:$C,3,FALSE),"") -> ISIC 28
A97: 333414 | B97: Heating equipment (except warm air furnaces) manufacturing | D97: 0 | I97: 0 | AA97: 143 | AB97: 507 | AC97: 565 | AD97: 272 | AE97: 594 | AF97: 189 | AG97: 900 | AH97: 238 | AI97: 339 | AJ97: 29 | AK97: 684 | AL97: 206 | AO97: 9 | AP97: 17 | CP97: 253 | CQ97: 438 | EV97: 1 | EW97: 26 | FC97: 1 | IE97: 6 | IM97: 32 | JG97: 0 | KB97: 0 | KW97: 16 | KX97: 112 | KZ97: 9 | LC97: 0 | LD97: 0 | LE97: 0 | LF97: 0 | LK97: 0 | LL97: 0 | LM97: 1 | LW97: 152 | LZ97: 33 | MF97: 3 | MH97: 9 | MO97: 199 | MP97: 124 | MQ97: 212 | MS97: 25 | MZ97: 22 | NC97: 1 | ND97: 0 | NE97: 3 | NF97: 0 | NM97: 2 | NN97: 2 | NO97: 0 | NP97: 14 | NQ97: 5 | NZ97: 0 | OD97: 1 | OE97: 1 | OK97: 129 | ON97: 11 | OO97: 6539 | OP97: 2528 | OQ97: 103 | OU97: 64 | OV97: 444 | PF97: 0 | PI97: 9678 | PM97: =IFERROR(VLOOKUP($A97&"",Key!$A:$C,3,FALSE),"") -> ISIC 28
A98: 333415 | B98: Air conditioning, refrigeration, and warm air heating equipment manufacturing | P98: 11 | Z98: 0 | AA98: 326 | AB98: 2151 | AC98: 2857 | AD98: 1375 | AE98: 2852 | AF98: 774 | AG98: 3452 | AH98: 403 | AI98: 986 | AJ98: 284 | AK98: 2480 | AL98: 509 | AM98: 1 | AO98: 60 | AP98: 159 | AR98: 5 | AT98: 3 | BC98: 10 | BF98: 0 | BG98: 0 | BH98: 9 | BJ98: 0 | BK98: 0 | BL98: 1 | BM98: 5 | BO98: 6 | BP98: 1 | BQ98: 21 | BR98: 48 | BS98: 2 | BT98: 6 | BV98: 0 | BW98: 0 | BX98: 2 | BY98: 3 | BZ98: 2 | CB98: 2 | CD98: 1 | CF98: 6 | CG98: 5 | CH98: 4 | CI98: 3 | CL98: 4 | CN98: 0 | CO98: 121 | CP98: 1 | CQ98: 4551 | CR98: 3 | CT98: 1 | CU98: 1 | CW98: 2 | CX98: 0 | CY98: 0 | CZ98: 46 | DA98: 0 | DB98: 0 | DC98: 7 | DG98: 2 | DL98: 0 | DM98: 1 | DO98: 0 | DP98: 2 | DQ98: 3 | DR98: 2 | DS98: 1 | DU98: 0 | DX98: 0 | DZ98: 0 | EA98: 1 | ED98: 26 | EF98: 181 | EH98: 5 | EI98: 1 | EL98: 0 | EN98: 8 | EQ98: 288 | ER98: 2028 | ES98: 216 | ET98: 2 | EU98: 102 | EV98: 0 | EW98: 5 | EX98: 6 | EZ98: 15 | FA98: 36 | FB98: 51 | FC98: 245 | FD98: 3 | FE98: 1 | FF98: 1 | FG98: 2 | FJ98: 2 | FK98: 0 | FO98: 0 | FP98: 0 | FR98: 0 | FS98: 1 | FU98: 5 | FV98: 14 | FX98: 41 | FY98: 21 | GD98: 4 | GE98: 4 | GG98: 56 | GH98: 21 | GI98: 18 | GJ98: 1 | GL98: 0 | GM98: 1 | GO98: 38 | GP98: 68 | GQ98: 30 | GR98: 608 | GS98: 36 | GT98: 88 | GU98: 43 | GV98: 69 | GW98: 1 | GX98: 1 | GY98: 2 | GZ98: 68 | HA98: 117 | HB98: 171 | HF98: 3 | HG98: 574 | HH98: 28 | HI98: 0 | HK98: 1 | HQ98: 0 | HU98: 1 | HV98: 1 | HW98: 3 | HZ98: 0 | IB98: 3 | ID98: 2 | IE98: 4 | IH98: 0 | IK98: 2 | IL98: 6 | IM98: 11 | IO98: 1 | IS98: 0 | IT98: 0 | IV98: 47 | IW98: 234 | IX98: 35 | IZ98: 397 | JA98: 32 | JD98: 13 | JE98: 227 | JF98: 16 | JG98: 126 | JJ98: 0 | JK98: 7 | JL98: 92 | JM98: 119 | JN98: 170 | JO98: 188 | JP98: 9 | JQ98: 170 | JR98: 34 | JS98: 165 | JT98: 11 | JV98: 101 | JW98: 81 | JX98: 120 | JY98: 41 | JZ98: 24 | KA98: 93 | KB98: 26 | KC98: 79 | KD98: 48 | KH98: 2 | KJ98: 58 | KK98: 6 | KL98: 0 | KN98: 2 | KO98: 1 | KP98: 3 | KQ98: 0 | KR98: 5 | KS98: 11 | KT98: 0 | KU98: 0 | KV98: 784 | KW98: 44 | KX98: 72 | KZ98: 198 | LD98: 6 | LE98: 45 | LK98: 6 | LL98: 0 | LM98: 63 | LO98: 148 | LR98: 29 | LS98: 3 | LT98: 551 | LU98: 8 | LV98: 37 | LW98: 34 | LX98: 139 | LY98: 10 | LZ98: 37 | MA98: 43 | MB98: 9 | MD98: 4 | ME98: 9 | MF98: 21 | MG98: 65 | MH98: 2293 | MI98: 4 | MJ98: 4 | MK98: 7 | ML98: 9 | MM98: 3 | MN98: 7 | MO98: 587 | MP98: 4 | MQ98: 126 | MR98: 7 | MS98: 154 | MT98: 13 | MU98: 10 | MV98: 97 | MW98: 2 | MX98: 8 | MY98: 38 | MZ98: 590 | NA98: 87 | NB98: 91 | NC98: 58 | ND98: 40 | NE98: 55 | NF98: 3 | NG98: 5 | NI98: 2 | NJ98: 3 | NK98: 5 | NL98: 25 | NM98: 52 | NN98: 97 | NO98: 222 | NP98: 236 | NQ98: 18 | NR98: 18 | NS98: 2 | NT98: 592 | NV98: 16 | NW98: 0 | NX98: 5 | NY98: 5 | NZ98: 4 | OA98: 1 | OB98: 300 | OD98: 100 | OE98: 161 | OI98: 508 | OJ98: 803 | OK98: 567 | OL98: 4 | ON98: 115 | OO98: 42294 | OP98: 5636 | OQ98: 14415 | OU98: 770 | OV98: 5626 | OX98: 165 | PF98: 350 | PI98: 69255 | PM98: =IFERROR(VLOOKUP($A98&"",Key!$A:$C,3,FALSE),"") -> ISIC 28
A99: 333413 | B99: Industrial and commercial fan and blower and air purification equipment manufacturing | X99: 1 | Z99: 0 | AA99: 179 | AB99: 236 | AE99: 320 | AF99: 97 | AG99: 572 | AH99: 243 | AI99: 149 | AJ99: 33 | AK99: 93 | AL99: 218 | BK99: 12 | CO99: 75 | CQ99: 238 | CR99: 82 | FC99: 64 | HR99: 1 | II99: 15 | IL99: 143 | IM99: 80 | IZ99: 165 | JG99: 355 | JN99: 0 | JO99: 16 | JT99: 2 | KF99: 1 | KK99: 7 | KM99: 43 | KZ99: 9 | LN99: 0 | LT99: 1510 | LW99: 163 | LZ99: 34 | MF99: 3 | MH99: 109 | MO99: 472 | MP99: 4 | MQ99: 0 | NT99: 70 | OD99: 1 | OH99: 56 | OI99: 71 | OK99: 59 | OM99: 85 | ON99: 109 | OO99: 6194 | OQ99: 3506 | OU99: 69 | OV99: 1396 | PF99: 0 | PI99: 11165 | PM99: =IFERROR(VLOOKUP($A99&"",Key!$A:$C,3,FALSE),"") -> ISIC 28
A100: 333511 | B100: Industrial mold manufacturing | AR100: 4 | BC100: 43 | BD100: 1 | BK100: 11 | BL100: 100 | BQ100: 92 | BX100: 217 | BY100: 1244 | CF100: 94 | CS100: 115 | CT100: 117 | ES100: 6 | JG100: 4 | KM100: 51 | LW100: 380 | LZ100: 65 | MF100: 6 | ON100: 175 | OO100: 2724 | OQ100: 7157 | OU100: 0 | OV100: 890 | PI100: 10771 | PM100: =IFERROR(VLOOKUP($A100&"",Key!$A:$C,3,FALSE),"") -> ISIC 28
A101: 333514 | B101: Special tool, die, jig, and fixture manufacturing | AR101: 25 | BC101: 276 | BD101: 16 | BK101: 87 | BL101: 533 | BN101: 104 | BO101: 39 | BX101: 10 | BY101: 230 | CC101: 93 | CK101: 32 | CL101: 161 | CO101: 2 | CQ101: 33 | CS101: 162 | CT101: 529 | CX101: 2 | CY101: 15 | DO101: 12 | EQ101: 10 | ER101: 35 | ES101: 19 | EX101: 35 | EZ101: 67 | FB101: 71 | FC101: 131 | JG101: 2 | OD101: 2 | OE101: 0 | OI101: 9 | OO101: 2742 | OQ101: 10775 | OU101: 110 | OV101: 593 | PI101: 14219 | PM101: =IFERROR(VLOOKUP($A101&"",Key!$A:$C,3,FALSE),"") -> ISIC 28
...

Sheet Key
A1: BEA detail code | B1: Description (from BEA) | C1: EPS ISIC code (editable) | E1: # | F1: EPS ISIC code (canonical order) | G1: OECD source (blank = carve child) | I1: Carve parent (OECD) | J1: Child 1 | K1: Child 2
A2: 1111A0 | B2: Oilseed farming | C2: ISIC 01 | E2: 1 | F2: ISIC 01 | G2: A01 | I2: C23 | J2: ISIC 231 | K2: ISIC 239
A3: 1111B0 | B3: Grain farming | C3: ISIC 01 | E3: 2 | F3: ISIC 02 | G3: A02 | I3: D | J3: ISIC 351 | K3: ISIC 352T353
A4: 111200 | B4: Vegetable and melon farming | C4: ISIC 01 | E4: 3 | F4: ISIC 03 | G4: A03
A5: 111300 | B5: Fruit and tree nut farming | C5: ISIC 01 | E5: 4 | F5: ISIC 05 | G5: B05
A6: 111400 | B6: Greenhouse, nursery, and floriculture production | C6: ISIC 01 | E6: 5 | F6: ISIC 06 | G6: B06
A7: 111900 | B7: Other crop farming | C7: ISIC 01 | E7: 6 | F7: ISIC 07 | G7: B07
A8: 112120 | B8: Dairy cattle and milk production | C8: ISIC 01 | E8: 7 | F8: ISIC 08 | G8: B08
A9: 1121A0 | B9: Beef cattle ranching and farming, including feedlots and dual-purpose ranching and farming | C9: ISIC 01 | E9: 8 | F9: ISIC 09 | G9: B09
A10: 112300 | B10: Poultry and egg production | C10: ISIC 01 | E10: 9 | F10: ISIC 10T12 | G10: C10T12
A11: 112A00 | B11: Animal production, except cattle and poultry and eggs | C11: ISIC 01 | E11: 10 | F11: ISIC 13T15 | G11: C13T15
A12: 113000 | B12: Forestry and logging | C12: ISIC 02 | E12: 11 | F12: ISIC 16 | G12: C16
A13: 114000 | B13: Fishing, hunting and trapping | C13: ISIC 03 | E13: 12 | F13: ISIC 17T18 | G13: C17_18
A14: 115000 | B14: Support activities for agriculture and forestry | C14: ISIC 01 | E14: 13 | F14: ISIC 19 | G14: C19
A15: 211000 | B15: Oil and gas extraction | C15: ISIC 06 | E15: 14 | F15: ISIC 20 | G15: C20
... A17: 212230 | B17: Copper, nickel, lead, and zinc mining | C17: ISIC 07 | E17: 16 | F17: ISIC 22 | G17: C22
A18: 2122A0 | B18: Iron, gold, silver, and other metal ore mining | C18: ISIC 07 | E18: 17 | F18: ISIC 231
A19: 212310 | B19: Stone mining and quarrying | C19: ISIC 08 | E19: 18 | F19: ISIC 239
A20: 2123A0 | B20: Other nonmetallic mineral mining and quarrying | C20: ISIC 08 | E20: 19 | F20: ISIC 241 | G20: C24A
A21: 213111 | B21: Drilling oil and gas wells | C21: ISIC 09 | E21: 20 | F21: ISIC 242 | G21: C24B
A22: 21311A | B22: Other support activities for mining | C22: ISIC 09 | E22: 21 | F22: ISIC 25 | G22: C25
A23: 221100 | B23: Electric power generation, transmission, and distribution | C23: ISIC 351 | E23: 22 | F23: ISIC 26 | G23: C26
A24: 221200 | B24: Natural gas distribution | C24: ISIC 352T353 | E24: 23 | F24: ISIC 27 | G24: C27
A25: 221300 | B25: Water, sewage and other systems | C25: ISIC 36T39 | E25: 24 | F25: ISIC 28 | G25: C28
A26: 230301 | B26: Nonresidential maintenance and repair | C26: ISIC 41T43 | E26: 25 | F26: ISIC 29 | G26: C29
A27: 230302 | B27: Residential maintenance and repair | C27: ISIC 41T43 | E27: 26 | F27: ISIC 301 | G27: C301
A28: 233210 | B28: Health care structures | C28: ISIC 41T43 | E28: 27 | F28: ISIC 302T309 | G28: C302T309
A29: 233230 | B29: Manufacturing structures | C29: ISIC 41T43 | E29: 28 | F29: ISIC 31T33 | G29: C31T33
A30: 233240 | B30: Power and communication structures | C30: ISIC 41T43 | E30: 29 | F30: ISIC 351
A31: 233262 | B31: Educational and vocational structures | C31: ISIC 41T43 | E31: 30 | F31: ISIC 352T353
A32: 2332A0 | B32: Office and commercial structures | C32: ISIC 41T43 | E32: 31 | F32: ISIC 36T39 | G32: E
A33: 2332C0 | B33: Transportation structures and highways and streets | C33: ISIC 41T43 | E33: 32 | F33: ISIC 41T43 | G33: F
A34: 2332D0 | B34: Other nonresidential structures | C34: ISIC 41T43 | E34: 33 | F34: ISIC 45T47 | G34: G
A35: 233411 | B35: Single-family residential structures | C35: ISIC 41T43 | E35: 34 | F35: ISIC 49 | G35: H49
A36: 233412 | B36: Multifamily residential structures | C36: ISIC 41T43 | E36: 35 | F36: ISIC 50 | G36: H50
A37: 2334A0 | B37: Other residential structures | C37: ISIC 41T43 | E37: 36 | F37: ISIC 51 | G37: H51
A38: 311111 | B38: Dog and cat food manufacturing | C38: ISIC 10T12 | E38: 37 | F38: ISIC 52 | G38: H52
A39: 311119 | B39: Other animal food manufacturing | C39: ISIC 10T12 | E39: 38 | F39: ISIC 53 | G39: H53
A40: 311210 | B40: Flour milling and malt manufacturing | C40: ISIC 10T12 | E40: 39 | F40: ISIC 55T56 | G40: I
A41: 311221 | B41: Wet corn milling | C41: ISIC 10T12 | E41: 40 | F41: ISIC 58T60 | G41: J58T60
A42: 311224 | B42: Soybean and other oilseed processing | C42: ISIC 10T12 | E42: 41 | F42: ISIC 61 | G42: J61
A43: 311225 | B43: Fats and oils refining and blending | C43: ISIC 10T12 | E43: 42 | F43: ISIC 62T63 | G43: J62_63
... A53: 31161A | B53: Animal (except poultry) slaughtering, rendering, and processing | C53: ISIC 10T12 | E53: 52 | F53: ISIC 97T98 | G53: T
A54: 311700 | B54: Seafood product preparation and packaging | C54: ISIC 10T12
A55: 311810 | B55: Bread and bakery product manufacturing | C55: ISIC 10T12
A56: 3118A0 | B56: Cookie, cracker, pasta, and tortilla manufacturing | C56: ISIC 10T12
A57: 311910 | B57: Snack food manufacturing | C57: ISIC 10T12
A58: 311920 | B58: Coffee and tea manufacturing | C58: ISIC 10T12
A59: 311930 | B59: Flavoring syrup and concentrate manufacturing | C59: ISIC 10T12
A60: 311940 | B60: Seasoning and dressing manufacturing | C60: ISIC 10T12
A61: 311990 | B61: All other food manufacturing | C61: ISIC 10T12
A62: 312110 | B62: Soft drink and ice manufacturing | C62: ISIC 10T12
A63: 312120 | B63: Breweries | C63: ISIC 10T12
A64: 312130 | B64: Wineries | C64: ISIC 10T12
A65: 312140 | B65: Distilleries | C65: ISIC 10T12
... A185: 333914 | B185: Measuring, dispensing, and other pumping equipment manufacturing | C185: ISIC 28
A186: 33391A | C186: ISIC 28
A187: 333920 | B187: Material handling equipment manufacturing | C187: ISIC 28
A188: 333991 | B188: Power-driven handtool manufacturing | C188: ISIC 28
A189: 333993 | B189: Packaging machinery manufacturing | C189: ISIC 28
A190: 333994 | B190: Industrial process furnace and oven manufacturing | C190: ISIC 28
A191: 33399A | B191: Other general purpose machinery manufacturing | C191: ISIC 28
A192: 33399B | B192: Fluid power process machinery | C192: ISIC 28
A193: 334111 | B193: Electronic computer manufacturing | C193: ISIC 26
A194: 334112 | B194: Computer storage device manufacturing | C194: ISIC 26
A195: 334118 | B195: Computer terminals and other computer peripheral equipment manufacturing | C195: ISIC 26
A196: 334210 | B196: Telephone apparatus manufacturing | C196: ISIC 26
A197: 334220 | B197: Broadcast and wireless communications equipment | C197: ISIC 26
A198: 334290 | B198: Other communications equipment manufacturing | C198: ISIC 26
... A216: 335220 | B216: Major household appliance manufacturing | C216: ISIC 27
A217: 335221 | C217: ISIC 27
A218: 335222 | C218: ISIC 27
A219: 335224 | C219: ISIC 27
A220: 335228 | C220: ISIC 27
A221: 335311 | B221: Power, distribution, and specialty transformer manufacturing | C221: ISIC 27
A222: 335312 | B222: Motor and generator manufacturing | C222: ISIC 27
A223: 335313 | B223: Switchgear and switchboard apparatus manufacturing | C223: ISIC 27
A224: 335314 | B224: Relay and industrial control manufacturing | C224: ISIC 27
A225: 335911 | B225: Storage battery manufacturing | C225: ISIC 27
A226: 335912 | B226: Primary battery manufacturing | C226: ISIC 27
A227: 335920 | B227: Communication and energy wire and cable manufacturing | C227: ISIC 27
A228: 335930 | B228: Wiring device manufacturing | C228: ISIC 27
A229: 335991 | B229: Carbon and graphite product manufacturing | C229: ISIC 27
A230: 335999 | B230: All other miscellaneous electrical equipment and component manufacturing | C230: ISIC 27
A231: 336111 | B231: Automobile manufacturing | C231: ISIC 29
A232: 336112 | B232: Light truck and utility vehicle manufacturing | C232: ISIC 29
... A410: S00600 | B410: Federal general government (nondefense) | C410: ISIC 84

Sheet Calculations
A1: Carve-child final-demand shares (BEA 2017 Use)
A2: Child | B2: gov FD purchases | C2: hh FD purchases | D2: gov share | E2: hh share
A3: ISIC 231 | B3: =SUMIFS('BEA Use 2017'!$OW$7:$OW$408,'BEA Use 2017'!$PM$7:$PM$408,$A3)+SUMIFS('BEA Use 2017'!$OX$7:$OX$408,'BEA Use 2017'!$PM$7:$PM$408,$A3)+SUMIFS('BEA Use 2017'!$OY$7:$OY$408,'BEA Use 2017'!$PM$7:$PM$408,$A3)+SUMIFS('BEA Use 2017'!$OZ$7:$OZ$408,'BEA Use 2017'!$PM$7:$PM$408,$A3)+SUMIFS('BEA Use 2017'!$PA$7:$PA$408,'BEA Use 2017'!$PM$7:$PM$408,$A3)+SUMIFS('BEA Use 2017'!$PB$7:$PB$408,'BEA Use 2017'!$PM$7:$PM$408,$A3)+SUMIFS('BEA Use 2017'!$PC$7:$PC$408,'BEA Use 2017'!$PM$7:$PM$408,$A3)+SUMIFS('BEA Use 2017'!$PD$7:$PD$408,'BEA Use 2017'!$PM$7:$PM$408,$A3)+SUMIFS('BEA Use 2017'!$PE$7:$PE$408,'BEA Use 2017'!$PM$7:$PM$408,$A3)+SUMIFS('BEA Use 2017'!$PF$7:$PF$408,'BEA Use 2017'!$PM$7:$PM$408,$A3)+SUMIFS('BEA Use 2017'!$PG$7:$PG$408,'BEA Use 2017'!$PM$7:$PM$408,$A3)+SUMIFS('BEA Use 2017'!$PH$7:$PH$408,'BEA Use 2017'!$PM$7:$PM$408,$A3) -> 0 | C3: =SUMIFS('BEA Use 2017'!$OP$7:$OP$408,'BEA Use 2017'!$PM$7:$PM$408,$A3) -> 10837 | D3: =IF((B3+B4)>0,B3/(B3+B4),0.5) -> 0.5 | E3: =IF((C3+C4)>0,C3/(C3+C4),0.5) -> 0.50882712
A4: ISIC 239 | B4: =SUMIFS('BEA Use 2017'!$OW$7:$OW$408,'BEA Use 2017'!$PM$7:$PM$408,$A4)+SUMIFS('BEA Use 2017'!$OX$7:$OX$408,'BEA Use 2017'!$PM$7:$PM$408,$A4)+SUMIFS('BEA Use 2017'!$OY$7:$OY$408,'BEA Use 2017'!$PM$7:$PM$408,$A4)+SUMIFS('BEA Use 2017'!$OZ$7:$OZ$408,'BEA Use 2017'!$PM$7:$PM$408,$A4)+SUMIFS('BEA Use 2017'!$PA$7:$PA$408,'BEA Use 2017'!$PM$7:$PM$408,$A4)+SUMIFS('BEA Use 2017'!$PB$7:$PB$408,'BEA Use 2017'!$PM$7:$PM$408,$A4)+SUMIFS('BEA Use 2017'!$PC$7:$PC$408,'BEA Use 2017'!$PM$7:$PM$408,$A4)+SUMIFS('BEA Use 2017'!$PD$7:$PD$408,'BEA Use 2017'!$PM$7:$PM$408,$A4)+SUMIFS('BEA Use 2017'!$PE$7:$PE$408,'BEA Use 2017'!$PM$7:$PM$408,$A4)+SUMIFS('BEA Use 2017'!$PF$7:$PF$408,'BEA Use 2017'!$PM$7:$PM$408,$A4)+SUMIFS('BEA Use 2017'!$PG$7:$PG$408,'BEA Use 2017'!$PM$7:$PM$408,$A4)+SUMIFS('BEA Use 2017'!$PH$7:$PH$408,'BEA Use 2017'!$PM$7:$PM$408,$A4) -> 0 | C4: =SUMIFS('BEA Use 2017'!$OP$7:$OP$408,'BEA Use 2017'!$PM$7:$PM$408,$A4) -> 10461 | D4: =IF((B4+B3)>0,B4/(B4+B3),0.5) -> 0.5 | E4: =IF((C4+C3)>0,C4/(C4+C3),0.5) -> 0.49117288
A5: ISIC 351 | B5: =SUMIFS('BEA Use 2017'!$OW$7:$OW$408,'BEA Use 2017'!$PM$7:$PM$408,$A5)+SUMIFS('BEA Use 2017'!$OX$7:$OX$408,'BEA Use 2017'!$PM$7:$PM$408,$A5)+SUMIFS('BEA Use 2017'!$OY$7:$OY$408,'BEA Use 2017'!$PM$7:$PM$408,$A5)+SUMIFS('BEA Use 2017'!$OZ$7:$OZ$408,'BEA Use 2017'!$PM$7:$PM$408,$A5)+SUMIFS('BEA Use 2017'!$PA$7:$PA$408,'BEA Use 2017'!$PM$7:$PM$408,$A5)+SUMIFS('BEA Use 2017'!$PB$7:$PB$408,'BEA Use 2017'!$PM$7:$PM$408,$A5)+SUMIFS('BEA Use 2017'!$PC$7:$PC$408,'BEA Use 2017'!$PM$7:$PM$408,$A5)+SUMIFS('BEA Use 2017'!$PD$7:$PD$408,'BEA Use 2017'!$PM$7:$PM$408,$A5)+SUMIFS('BEA Use 2017'!$PE$7:$PE$408,'BEA Use 2017'!$PM$7:$PM$408,$A5)+SUMIFS('BEA Use 2017'!$PF$7:$PF$408,'BEA Use 2017'!$PM$7:$PM$408,$A5)+SUMIFS('BEA Use 2017'!$PG$7:$PG$408,'BEA Use 2017'!$PM$7:$PM$408,$A5)+SUMIFS('BEA Use 2017'!$PH$7:$PH$408,'BEA Use 2017'!$PM$7:$PM$408,$A5) -> 0 | C5: =SUMIFS('BEA Use 2017'!$OP$7:$OP$408,'BEA Use 2017'!$PM$7:$PM$408,$A5) -> 177661 | D5: =IF((B5+B6)>0,B5/(B5+B6),0.5) -> 0.5 | E5: =IF((C5+C6)>0,C5/(C5+C6),0.5) -> 0.78676161
A6: ISIC 352T353 | B6: =SUMIFS('BEA Use 2017'!$OW$7:$OW$408,'BEA Use 2017'!$PM$7:$PM$408,$A6)+SUMIFS('BEA Use 2017'!$OX$7:$OX$408,'BEA Use 2017'!$PM$7:$PM$408,$A6)+SUMIFS('BEA Use 2017'!$OY$7:$OY$408,'BEA Use 2017'!$PM$7:$PM$408,$A6)+SUMIFS('BEA Use 2017'!$OZ$7:$OZ$408,'BEA Use 2017'!$PM$7:$PM$408,$A6)+SUMIFS('BEA Use 2017'!$PA$7:$PA$408,'BEA Use 2017'!$PM$7:$PM$408,$A6)+SUMIFS('BEA Use 2017'!$PB$7:$PB$408,'BEA Use 2017'!$PM$7:$PM$408,$A6)+SUMIFS('BEA Use 2017'!$PC$7:$PC$408,'BEA Use 2017'!$PM$7:$PM$408,$A6)+SUMIFS('BEA Use 2017'!$PD$7:$PD$408,'BEA Use 2017'!$PM$7:$PM$408,$A6)+SUMIFS('BEA Use 2017'!$PE$7:$PE$408,'BEA Use 2017'!$PM$7:$PM$408,$A6)+SUMIFS('BEA Use 2017'!$PF$7:$PF$408,'BEA Use 2017'!$PM$7:$PM$408,$A6)+SUMIFS('BEA Use 2017'!$PG$7:$PG$408,'BEA Use 2017'!$PM$7:$PM$408,$A6)+SUMIFS('BEA Use 2017'!$PH$7:$PH$408,'BEA Use 2017'!$PM$7:$PM$408,$A6) -> 0 | C6: =SUMIFS('BEA Use 2017'!$OP$7:$OP$408,'BEA Use 2017'!$PM$7:$PM$408,$A6) -> 48152 | D6: =IF((B6+B5)>0,B6/(B6+B5),0.5) -> 0.5 | E6: =IF((C6+C5)>0,C6/(C6+C5),0.5) -> 0.21323839
A9: OECD 2022 GDP (2012 USD; = VALU row x 1e6 x CPI factor) | B9: =SUM(OECD_TTL!$B$55:$AY$55)*10^6*About!$A$20 -> 1.9484506e+13
A10: BGDP 2025 (pasted from io-model/BGDP.csv — repaste on update) | B10: 21825500000000
A11: Projection factor 2022->2025 | B11: =B10/B9 -> 1.1201464

Sheet Checks
A1: Validation
A3: Carve conservation (children sum = OECD parent x factor), gov + hh
A4: C23 / GGFC | B4: =ABS(('GaHEbIC-government'!O2+'GaHEbIC-government'!P2)/(INDEX(OECD_TTL!$B$2:$BI$60,MATCH("TTL_C23",OECD_TTL!$A$2:$A$60,0),MATCH("GGFC",OECD_TTL!$B$1:$BI$1,0))*10^6*About!$A$20*Calculations!$B$11)-1) -> 0 | C4: =IF(B4<0.000000001,"PASS","FAIL") -> PASS
A5: C23 / HFCE | B5: =ABS(('GaHEbIC-household'!O2+'GaHEbIC-household'!P2)/(INDEX(OECD_TTL!$B$2:$BI$60,MATCH("TTL_C23",OECD_TTL!$A$2:$A$60,0),MATCH("HFCE",OECD_TTL!$B$1:$BI$1,0))*10^6*About!$A$20*Calculations!$B$11)-1) -> 0 | C5: =IF(B5<0.000000001,"PASS","FAIL") -> PASS
A6: D / GGFC | B6: =ABS(('GaHEbIC-government'!Z2+'GaHEbIC-government'!AA2)/(INDEX(OECD_TTL!$B$2:$BI$60,MATCH("TTL_D",OECD_TTL!$A$2:$A$60,0),MATCH("GGFC",OECD_TTL!$B$1:$BI$1,0))*10^6*About!$A$20*Calculations!$B$11)-1) -> 0 | C6: =IF(B6<0.000000001,"PASS","FAIL") -> PASS
A7: D / HFCE | B7: =ABS(('GaHEbIC-household'!Z2+'GaHEbIC-household'!AA2)/(INDEX(OECD_TTL!$B$2:$BI$60,MATCH("TTL_D",OECD_TTL!$A$2:$A$60,0),MATCH("HFCE",OECD_TTL!$B$1:$BI$1,0))*10^6*About!$A$20*Calculations!$B$11)-1) -> 2.220446e-16 | C7: =IF(B7<0.000000001,"PASS","FAIL") -> PASS

Sheet GaHEbIC-government
A1: Unit: USD | B1: ISIC 01T03 | C1: ISIC 05 | D1: ISIC 06 | E1: ISIC 07T08 | F1: ISIC 09 | G1: ISIC 10T12 | H1: ISIC 13T15 | I1: ISIC 16 | J1: ISIC 17T18 | K1: ISIC 19 | L1: ISIC 20 | M1: ISIC 21 | N1: ISIC 22 | O1: ISIC 231 | P1: ISIC 239 | Q1: ISIC 241 | R1: ISIC 242 | S1: ISIC 25 | T1: ISIC 26 | U1: ISIC 27 | V1: ISIC 28 | W1: ISIC 29 | X1: ISIC 30 | Y1: ISIC 31T33 | Z1: ISIC 351 | AA1: ISIC 352T353 | AB1: ISIC 36T39 | AC1: ISIC 41T43 | AD1: ISIC 45T47 | AE1: ISIC 49T53 | AF1: ISIC 55T56 | AG1: ISIC 58T60 | AH1: ISIC 61 | AI1: ISIC 62T63 | AJ1: ISIC 64T66 | AK1: ISIC 68 | AL1: ISIC 69T82 | AM1: ISIC 84 | AN1: ISIC 85 | AO1: ISIC 86T88 | AP1: ISIC 90T96 | AQ1: ISIC 97T98
A2: Government Expenditures | B2: =(INDEX(OECD_TTL!$B$2:$BI$60,MATCH("TTL_A01",OECD_TTL!$A$2:$A$60,0),MATCH("GGFC",OECD_TTL!$B$1:$BI$1,0))+INDEX(OECD_TTL!$B$2:$BI$60,MATCH("TTL_A02",OECD_TTL!$A$2:$A$60,0),MATCH("GGFC",OECD_TTL!$B$1:$BI$1,0))+INDEX(OECD_TTL!$B$2:$BI$60,MATCH("TTL_A03",OECD_TTL!$A$2:$A$60,0),MATCH("GGFC",OECD_TTL!$B$1:$BI$1,0)))*10^6*About!$A$20*Calculations!$B$11 -> 481570.58 | C2: =INDEX(OECD_TTL!$B$2:$BI$60,MATCH("TTL_B05",OECD_TTL!$A$2:$A$60,0),MATCH("GGFC",OECD_TTL!$B$1:$BI$1,0))*10^6*About!$A$20*Calculations!$B$11 -> 28999.688 | D2: =INDEX(OECD_TTL!$B$2:$BI$60,MATCH("TTL_B06",OECD_TTL!$A$2:$A$60,0),MATCH("GGFC",OECD_TTL!$B$1:$BI$1,0))*10^6*About!$A$20*Calculations!$B$11 -> 362935.49 | E2: =(INDEX(OECD_TTL!$B$2:$BI$60,MATCH("TTL_B07",OECD_TTL!$A$2:$A$60,0),MATCH("GGFC",OECD_TTL!$B$1:$BI$1,0))+INDEX(OECD_TTL!$B$2:$BI$60,MATCH("TTL_B08",OECD_TTL!$A$2:$A$60,0),MATCH("GGFC",OECD_TTL!$B$1:$BI$1,0)))*10^6*About!$A$20*Calculations!$B$11 -> 207391.71 | F2: =INDEX(OECD_TTL!$B$2:$BI$60,MATCH("TTL_B09",OECD_TTL!$A$2:$A$60,0),MATCH("GGFC",OECD_TTL!$B$1:$BI$1,0))*10^6*About!$A$20*Calculations!$B$11 -> 210028.04 | G2: =INDEX(OECD_TTL!$B$2:$BI$60,MATCH("TTL_C10T12",OECD_TTL!$A$2:$A$60,0),MATCH("GGFC",OECD_TTL!$B$1:$BI$1,0))*10^6*About!$A$20*Calculations!$B$11 -> 3227753.2 | H2: =INDEX(OECD_TTL!$B$2:$BI$60,MATCH("TTL_C13T15",OECD_TTL!$A$2:$A$60,0),MATCH("GGFC",OECD_TTL!$B$1:$BI$1,0))*10^6*About!$A$20*Calculations!$B$11 -> 2200461.2 | I2: =INDEX(OECD_TTL!$B$2:$BI$60,MATCH("TTL_C16",OECD_TTL!$A$2:$A$60,0),MATCH("GGFC",OECD_TTL!$B$1:$BI$1,0))*10^6*About!$A$20*Calculations!$B$11 -> 11690389 | J2: =INDEX(OECD_TTL!$B$2:$BI$60,MATCH("TTL_C17_18",OECD_TTL!$A$2:$A$60,0),MATCH("GGFC",OECD_TTL!$B$1:$BI$1,0))*10^6*About!$A$20*Calculations!$B$11 -> 8184942.3 | K2: =INDEX(OECD_TTL!$B$2:$BI$60,MATCH("TTL_C19",OECD_TTL!$A$2:$A$60,0),MATCH("GGFC",OECD_TTL!$B$1:$BI$1,0))*10^6*About!$A$20*Calculations!$B$11 -> 2312944.8 | L2: =INDEX(OECD_TTL!$B$2:$BI$60,MATCH("TTL_C20",OECD_TTL!$A$2:$A$60,0),MATCH("GGFC",OECD_TTL!$B$1:$BI$1,0))*10^6*About!$A$20*Calculations!$B$11 -> 6482748.5 | M2: =INDEX(OECD_TTL!$B$2:$BI$60,MATCH("TTL_C21",OECD_TTL!$A$2:$A$60,0),MATCH("GGFC",OECD_TTL!$B$1:$BI$1,0))*10^6*About!$A$20*Calculations!$B$11 -> 7264861.3 | N2: =INDEX(OECD_TTL!$B$2:$BI$60,MATCH("TTL_C22",OECD_TTL!$A$2:$A$60,0),MATCH("GGFC",OECD_TTL!$B$1:$BI$1,0))*10^6*About!$A$20*Calculations!$B$11 -> 13579763 | O2: =INDEX(OECD_TTL!$B$2:$BI$60,MATCH("TTL_C23",OECD_TTL!$A$2:$A$60,0),MATCH("GGFC",OECD_TTL!$B$1:$BI$1,0))*Calculations!$D$3*10^6*About!$A$20*Calculations!$B$11 -> 1044867.5 | P2: =INDEX(OECD_TTL!$B$2:$BI$60,MATCH("TTL_C23",OECD_TTL!$A$2:$A$60,0),MATCH("GGFC",OECD_TTL!$B$1:$BI$1,0))*Calculations!$D$4*10^6*About!$A$20*Calculations!$B$11 -> 1044867.5 | Q2: =INDEX(OECD_TTL!$B$2:$BI$60,MATCH("TTL_C24A",OECD_TTL!$A$2:$A$60,0),MATCH("GGFC",OECD_TTL!$B$1:$BI$1,0))*10^6*About!$A$20*Calculations!$B$11 -> 441146.77 | R2: =INDEX(OECD_TTL!$B$2:$BI$60,MATCH("TTL_C24B",OECD_TTL!$A$2:$A$60,0),MATCH("GGFC",OECD_TTL!$B$1:$BI$1,0))*10^6*About!$A$20*Calculations!$B$11 -> 13260766 | S2: =INDEX(OECD_TTL!$B$2:$BI$60,MATCH("TTL_C25",OECD_TTL!$A$2:$A$60,0),MATCH("GGFC",OECD_TTL!$B$1:$BI$1,0))*10^6*About!$A$20*Calculations!$B$11 -> 6435294.4 | T2: =INDEX(OECD_TTL!$B$2:$BI$60,MATCH("TTL_C26",OECD_TTL!$A$2:$A$60,0),MATCH("GGFC",OECD_TTL!$B$1:$BI$1,0))*10^6*About!$A$20*Calculations!$B$11 -> 37406083 | U2: =INDEX(OECD_TTL!$B$2:$BI$60,MATCH("TTL_C27",OECD_TTL!$A$2:$A$60,0),MATCH("GGFC",OECD_TTL!$B$1:$BI$1,0))*10^6*About!$A$20*Calculations!$B$11 -> 3262025.5 | V2: =INDEX(OECD_TTL!$B$2:$BI$60,MATCH("TTL_C28",OECD_TTL!$A$2:$A$60,0),MATCH("GGFC",OECD_TTL!$B$1:$BI$1,0))*10^6*About!$A$20*Calculations!$B$11 -> 6786805.8 | W2: =INDEX(OECD_TTL!$B$2:$BI$60,MATCH("TTL_C29",OECD_TTL!$A$2:$A$60,0),MATCH("GGFC",OECD_TTL!$B$1:$BI$1,0))*10^6*About!$A$20*Calculations!$B$11 -> 1131866.6 | X2: =(INDEX(OECD_TTL!$B$2:$BI$60,MATCH("TTL_C301",OECD_TTL!$A$2:$A$60,0),MATCH("GGFC",OECD_TTL!$B$1:$BI$1,0))+INDEX(OECD_TTL!$B$2:$BI$60,MATCH("TTL_C302T309",OECD_TTL!$A$2:$A$60,0),MATCH("GGFC",OECD_TTL!$B$1:$BI$1,0)))*10^6*About!$A$20*Calculations!$B$11 -> 1189866 | Y2: =INDEX(OECD_TTL!$B$2:$BI$60,MATCH("TTL_C31T33",OECD_TTL!$A$2:$A$60,0),MATCH("GGFC",OECD_TTL!$B$1:$BI$1,0))*10^6*About!$A$20*Calculations!$B$11 -> 1.4019258e+09 | Z2: =INDEX(OECD_TTL!$B$2:$BI$60,MATCH("TTL_D",OECD_TTL!$A$2:$A$60,0),MATCH("GGFC",OECD_TTL!$B$1:$BI$1,0))*Calculations!$D$5*10^6*About!$A$20*Calculations!$B$11 -> 710052.97 | AA2: =INDEX(OECD_TTL!$B$2:$BI$60,MATCH("TTL_D",OECD_TTL!$A$2:$A$60,0),MATCH("GGFC",OECD_TTL!$B$1:$BI$1,0))*Calculations!$D$6*10^6*About!$A$20*Calculations!$B$11 -> 710052.97 | AB2: =INDEX(OECD_TTL!$B$2:$BI$60,MATCH("TTL_E",OECD_TTL!$A$2:$A$60,0),MATCH("GGFC",OECD_TTL!$B$1:$BI$1,0))*10^6*About!$A$20*Calculations!$B$11 -> 1.9358173e+10 | AC2: =INDEX(OECD_TTL!$B$2:$BI$60,MATCH("TTL_F",OECD_TTL!$A$2:$A$60,0),MATCH("GGFC",OECD_TTL!$B$1:$BI$1,0))*10^6*About!$A$20*Calculations!$B$11 -> 926232.46 | AD2: =INDEX(OECD_TTL!$B$2:$BI$60,MATCH("TTL_G",OECD_TTL!$A$2:$A$60,0),MATCH("GGFC",OECD_TTL!$B$1:$BI$1,0))*10^6*About!$A$20*Calculations!$B$11 -> 2.0824237e+09 | AE2: =(INDEX(OECD_TTL!$B$2:$BI$60,MATCH("TTL_H49",OECD_TTL!$A$2:$A$60,0),MATCH("GGFC",OECD_TTL!$B$1:$BI$1,0))+INDEX(OECD_TTL!$B$2:$BI$60,MATCH("TTL_H50",OECD_TTL!$A$2:$A$60,0),MATCH("GGFC",OECD_TTL!$B$1:$BI$1,0))+INDEX(OECD_TTL!$B$2:$BI$60,MATCH("TTL_H51",OECD_TTL!$A$2:$A$60,0),MATCH("GGFC",OECD_TTL!$B$1:$BI$1,0))+INDEX(OECD_TTL!$B$2:$BI$60,MATCH("TTL_H52",OECD_TTL!$A$2:$A$60,0),MATCH("GGFC",OECD_TTL!$B$1:$BI$1,0))+INDEX(OECD_TTL!$B$2:$BI$60,MATCH("TTL_H53",OECD_TTL!$A$2:$A$60,0),MATCH("GGFC",OECD_TTL!$B$1:$BI$1,0)))*10^6*About!$A$20*Calculations!$B$11 -> 9.2916143e+08 | AF2: =INDEX(OECD_TTL!$B$2:$BI$60,MATCH("TTL_I",OECD_TTL!$A$2:$A$60,0),MATCH("GGFC",OECD_TTL!$B$1:$BI$1,0))*10^6*About!$A$20*Calculations!$B$11 -> 5.3245246e+09 | AG2: =INDEX(OECD_TTL!$B$2:$BI$60,MATCH("TTL_J58T60",OECD_TTL!$A$2:$A$60,0),MATCH("GGFC",OECD_TTL!$B$1:$BI$1,0))*10^6*About!$A$20*Calculations!$B$11 -> 2.4394175e+10 | AH2: =INDEX(OECD_TTL!$B$2:$BI$60,MATCH("TTL_J61",OECD_TTL!$A$2:$A$60,0),MATCH("GGFC",OECD_TTL!$B$1:$BI$1,0))*10^6*About!$A$20*Calculations!$B$11 -> 2729485.8 | AI2: =INDEX(OECD_TTL!$B$2:$BI$60,MATCH("TTL_J62_63",OECD_TTL!$A$2:$A$60,0),MATCH("GGFC",OECD_TTL!$B$1:$BI$1,0))*10^6*About!$A$20*Calculations!$B$11 -> 7.4948121e+09 | AJ2: =INDEX(OECD_TTL!$B$2:$BI$60,MATCH("TTL_K",OECD_TTL!$A$2:$A$60,0),MATCH("GGFC",OECD_TTL!$B$1:$BI$1,0))*10^6*About!$A$20*Calculations!$B$11 -> 12403957 | AK2: =INDEX(OECD_TTL!$B$2:$BI$60,MATCH("TTL_L",OECD_TTL!$A$2:$A$60,0),MATCH("GGFC",OECD_TTL!$B$1:$BI$1,0))*10^6*About!$A$20*Calculations!$B$11 -> 585266.43 | AL2: =(INDEX(OECD_TTL!$B$2:$BI$60,MATCH("TTL_M",OECD_TTL!$A$2:$A$60,0),MATCH("GGFC",OECD_TTL!$B$1:$BI$1,0))+INDEX(OECD_TTL!$B$2:$BI$60,MATCH("TTL_N",OECD_TTL!$A$2:$A$60,0),MATCH("GGFC",OECD_TTL!$B$1:$BI$1,0)))*10^6*About!$A$20*Calculations!$B$11 -> 8.8989893e+09 | AM2: =INDEX(OECD_TTL!$B$2:$BI$60,MATCH("TTL_O",OECD_TTL!$A$2:$A$60,0),MATCH("GGFC",OECD_TTL!$B$1:$BI$1,0))*10^6*About!$A$20*Calculations!$B$11 -> 2.1292966e+12 | AN2: =INDEX(OECD_TTL!$B$2:$BI$60,MATCH("TTL_P",OECD_TTL!$A$2:$A$60,0),MATCH("GGFC",OECD_TTL!$B$1:$BI$1,0))*10^6*About!$A$20*Calculations!$B$11 -> 7.3495233e+11 | AO2: =INDEX(OECD_TTL!$B$2:$BI$60,MATCH("TTL_Q",OECD_TTL!$A$2:$A$60,0),MATCH("GGFC",OECD_TTL!$B$1:$BI$1,0))*10^6*About!$A$20*Calculations!$B$11 -> 1.8596447e+11 | AP2: =(INDEX(OECD_TTL!$B$2:$BI$60,MATCH("TTL_R",OECD_TTL!$A$2:$A$60,0),MATCH("GGFC",OECD_TTL!$B$1:$BI$1,0))+INDEX(OECD_TTL!$B$2:$BI$60,MATCH("TTL_S",OECD_TTL!$A$2:$A$60,0),MATCH("GGFC",OECD_TTL!$B$1:$BI$1,0)))*10^6*About!$A$20*Calculations!$B$11 -> 1.7145566e+10 | AQ2: =INDEX(OECD_TTL!$B$2:$BI$60,MATCH("TTL_T",OECD_TTL!$A$2:$A$60,0),MATCH("GGFC",OECD_TTL!$B$1:$BI$1,0))*10^6*About!$A$20*Calculations!$B$11 -> 0

Sheet GaHEbIC-household
A1: Unit: USD | B1: ISIC 01T03 | C1: ISIC 05 | D1: ISIC 06 | E1: ISIC 07T08 | F1: ISIC 09 | G1: ISIC 10T12 | H1: ISIC 13T15 | I1: ISIC 16 | J1: ISIC 17T18 | K1: ISIC 19 | L1: ISIC 20 | M1: ISIC 21 | N1: ISIC 22 | O1: ISIC 231 | P1: ISIC 239 | Q1: ISIC 241 | R1: ISIC 242 | S1: ISIC 25 | T1: ISIC 26 | U1: ISIC 27 | V1: ISIC 28 | W1: ISIC 29 | X1: ISIC 30 | Y1: ISIC 31T33 | Z1: ISIC 351 | AA1: ISIC 352T353 | AB1: ISIC 36T39 | AC1: ISIC 41T43 | AD1: ISIC 45T47 | AE1: ISIC 49T53 | AF1: ISIC 55T56 | AG1: ISIC 58T60 | AH1: ISIC 61 | AI1: ISIC 62T63 | AJ1: ISIC 64T66 | AK1: ISIC 68 | AL1: ISIC 69T82 | AM1: ISIC 84 | AN1: ISIC 85 | AO1: ISIC 86T88 | AP1: ISIC 90T96 | AQ1: ISIC 97T98
A2: Household Expenditures | B2: =(INDEX(OECD_TTL!$B$2:$BI$60,MATCH("TTL_A01",OECD_TTL!$A$2:$A$60,0),MATCH("HFCE",OECD_TTL!$B$1:$BI$1,0))+INDEX(OECD_TTL!$B$2:$BI$60,MATCH("TTL_A02",OECD_TTL!$A$2:$A$60,0),MATCH("HFCE",OECD_TTL!$B$1:$BI$1,0))+INDEX(OECD_TTL!$B$2:$BI$60,MATCH("TTL_A03",OECD_TTL!$A$2:$A$60,0),MATCH("HFCE",OECD_TTL!$B$1:$BI$1,0)))*10^6*About!$A$20*Calculations!$B$11 -> 2.0592888e+11 | C2: =INDEX(OECD_TTL!$B$2:$BI$60,MATCH("TTL_B05",OECD_TTL!$A$2:$A$60,0),MATCH("HFCE",OECD_TTL!$B$1:$BI$1,0))*10^6*About!$A$20*Calculations!$B$11 -> 15919950 | D2: =INDEX(OECD_TTL!$B$2:$BI$60,MATCH("TTL_B06",OECD_TTL!$A$2:$A$60,0),MATCH("HFCE",OECD_TTL!$B$1:$BI$1,0))*10^6*About!$A$20*Calculations!$B$11 -> 1.4024317e+10 | E2: =(INDEX(OECD_TTL!$B$2:$BI$60,MATCH("TTL_B07",OECD_TTL!$A$2:$A$60,0),MATCH("HFCE",OECD_TTL!$B$1:$BI$1,0))+INDEX(OECD_TTL!$B$2:$BI$60,MATCH("TTL_B08",OECD_TTL!$A$2:$A$60,0),MATCH("HFCE",OECD_TTL!$B$1:$BI$1,0)))*10^6*About!$A$20*Calculations!$B$11 -> 7.5048205e+08 | F2: =INDEX(OECD_TTL!$B$2:$BI$60,MATCH("TTL_B09",OECD_TTL!$A$2:$A$60,0),MATCH("HFCE",OECD_TTL!$B$1:$BI$1,0))*10^6*About!$A$20*Calculations!$B$11 -> 2.7854288e+08 | G2: =INDEX(OECD_TTL!$B$2:$BI$60,MATCH("TTL_C10T12",OECD_TTL!$A$2:$A$60,0),MATCH("HFCE",OECD_TTL!$B$1:$BI$1,0))*10^6*About!$A$20*Calculations!$B$11 -> 8.5135111e+11 | H2: =INDEX(OECD_TTL!$B$2:$BI$60,MATCH("TTL_C13T15",OECD_TTL!$A$2:$A$60,0),MATCH("HFCE",OECD_TTL!$B$1:$BI$1,0))*10^6*About!$A$20*Calculations!$B$11 -> 1.6516523e+11 | I2: =INDEX(OECD_TTL!$B$2:$BI$60,MATCH("TTL_C16",OECD_TTL!$A$2:$A$60,0),MATCH("HFCE",OECD_TTL!$B$1:$BI$1,0))*10^6*About!$A$20*Calculations!$B$11 -> 1.1574026e+10 | J2: =INDEX(OECD_TTL!$B$2:$BI$60,MATCH("TTL_C17_18",OECD_TTL!$A$2:$A$60,0),MATCH("HFCE",OECD_TTL!$B$1:$BI$1,0))*10^6*About!$A$20*Calculations!$B$11 -> 5.4992655e+10 | K2: =INDEX(OECD_TTL!$B$2:$BI$60,MATCH("TTL_C19",OECD_TTL!$A$2:$A$60,0),MATCH("HFCE",OECD_TTL!$B$1:$BI$1,0))*10^6*About!$A$20*Calculations!$B$11 -> 1.9723432e+11 | L2: =INDEX(OECD_TTL!$B$2:$BI$60,MATCH("TTL_C20",OECD_TTL!$A$2:$A$60,0),MATCH("HFCE",OECD_TTL!$B$1:$BI$1,0))*10^6*About!$A$20*Calculations!$B$11 -> 1.5729764e+11 | M2: =INDEX(OECD_TTL!$B$2:$BI$60,MATCH("TTL_C21",OECD_TTL!$A$2:$A$60,0),MATCH("HFCE",OECD_TTL!$B$1:$BI$1,0))*10^6*About!$A$20*Calculations!$B$11 -> 2.6538473e+11 | N2: =INDEX(OECD_TTL!$B$2:$BI$60,MATCH("TTL_C22",OECD_TTL!$A$2:$A$60,0),MATCH("HFCE",OECD_TTL!$B$1:$BI$1,0))*10^6*About!$A$20*Calculations!$B$11 -> 6.809226e+10 | O2: =INDEX(OECD_TTL!$B$2:$BI$60,MATCH("TTL_C23",OECD_TTL!$A$2:$A$60,0),MATCH("HFCE",OECD_TTL!$B$1:$BI$1,0))*Calculations!$E$3*10^6*About!$A$20*Calculations!$B$11 -> 1.2264078e+10 | P2: =INDEX(OECD_TTL!$B$2:$BI$60,MATCH("TTL_C23",OECD_TTL!$A$2:$A$60,0),MATCH("HFCE",OECD_TTL!$B$1:$BI$1,0))*Calculations!$E$4*10^6*About!$A$20*Calculations!$B$11 -> 1.1838564e+10 | Q2: =INDEX(OECD_TTL!$B$2:$BI$60,MATCH("TTL_C24A",OECD_TTL!$A$2:$A$60,0),MATCH("HFCE",OECD_TTL!$B$1:$BI$1,0))*10^6*About!$A$20*Calculations!$B$11 -> 1.0241503e+09 | R2: =INDEX(OECD_TTL!$B$2:$BI$60,MATCH("TTL_C24B",OECD_TTL!$A$2:$A$60,0),MATCH("HFCE",OECD_TTL!$B$1:$BI$1,0))*10^6*About!$A$20*Calculations!$B$11 -> 2.683661e+09 | S2: =INDEX(OECD_TTL!$B$2:$BI$60,MATCH("TTL_C25",OECD_TTL!$A$2:$A$60,0),MATCH("HFCE",OECD_TTL!$B$1:$BI$1,0))*10^6*About!$A$20*Calculations!$B$11 -> 5.886137e+10 | T2: =INDEX(OECD_TTL!$B$2:$BI$60,MATCH("TTL_C26",OECD_TTL!$A$2:$A$60,0),MATCH("HFCE",OECD_TTL!$B$1:$BI$1,0))*10^6*About!$A$20*Calculations!$B$11 -> 1.3013048e+11 | U2: =INDEX(OECD_TTL!$B$2:$BI$60,MATCH("TTL_C27",OECD_TTL!$A$2:$A$60,0),MATCH("HFCE",OECD_TTL!$B$1:$BI$1,0))*10^6*About!$A$20*Calculations!$B$11 -> 8.1893095e+10 | V2: =INDEX(OECD_TTL!$B$2:$BI$60,MATCH("TTL_C28",OECD_TTL!$A$2:$A$60,0),MATCH("HFCE",OECD_TTL!$B$1:$BI$1,0))*10^6*About!$A$20*Calculations!$B$11 -> 2.5389078e+10 | W2: =INDEX(OECD_TTL!$B$2:$BI$60,MATCH("TTL_C29",OECD_TTL!$A$2:$A$60,0),MATCH("HFCE",OECD_TTL!$B$1:$BI$1,0))*10^6*About!$A$20*Calculations!$B$11 -> 2.7208812e+11 | X2: =(INDEX(OECD_TTL!$B$2:$BI$60,MATCH("TTL_C301",OECD_TTL!$A$2:$A$60,0),MATCH("HFCE",OECD_TTL!$B$1:$BI$1,0))+INDEX(OECD_TTL!$B$2:$BI$60,MATCH("TTL_C302T309",OECD_TTL!$A$2:$A$60,0),MATCH("HFCE",OECD_TTL!$B$1:$BI$1,0)))*10^6*About!$A$20*Calculations!$B$11 -> 4.3841604e+10 | Y2: =INDEX(OECD_TTL!$B$2:$BI$60,MATCH("TTL_C31T33",OECD_TTL!$A$2:$A$60,0),MATCH("HFCE",OECD_TTL!$B$1:$BI$1,0))*10^6*About!$A$20*Calculations!$B$11 -> 1.7452544e+11 | Z2: =INDEX(OECD_TTL!$B$2:$BI$60,MATCH("TTL_D",OECD_TTL!$A$2:$A$60,0),MATCH("HFCE",OECD_TTL!$B$1:$BI$1,0))*Calculations!$E$5*10^6*About!$A$20*Calculations!$B$11 -> 1.4974091e+11 | AA2: =INDEX(OECD_TTL!$B$2:$BI$60,MATCH("TTL_D",OECD_TTL!$A$2:$A$60,0),MATCH("HFCE",OECD_TTL!$B$1:$BI$1,0))*Calculations!$E$6*10^6*About!$A$20*Calculations!$B$11 -> 4.0584734e+10 | AB2: =INDEX(OECD_TTL!$B$2:$BI$60,MATCH("TTL_E",OECD_TTL!$A$2:$A$60,0),MATCH("HFCE",OECD_TTL!$B$1:$BI$1,0))*10^6*About!$A$20*Calculations!$B$11 -> 5.3236132e+10 | AC2: =INDEX(OECD_TTL!$B$2:$BI$60,MATCH("TTL_F",OECD_TTL!$A$2:$A$60,0),MATCH("HFCE",OECD_TTL!$B$1:$BI$1,0))*10^6*About!$A$20*Calculations!$B$11 -> 4.1049322e+08 | AD2: =INDEX(OECD_TTL!$B$2:$BI$60,MATCH("TTL_G",OECD_TTL!$A$2:$A$60,0),MATCH("HFCE",OECD_TTL!$B$1:$BI$1,0))*10^6*About!$A$20*Calculations!$B$11 -> 1.7528001e+12 | AE2: =(INDEX(OECD_TTL!$B$2:$BI$60,MATCH("TTL_H49",OECD_TTL!$A$2:$A$60,0),MATCH("HFCE",OECD_TTL!$B$1:$BI$1,0))+INDEX(OECD_TTL!$B$2:$BI$60,MATCH("TTL_H50",OECD_TTL!$A$2:$A$60,0),MATCH("HFCE",OECD_TTL!$B$1:$BI$1,0))+INDEX(OECD_TTL!$B$2:$BI$60,MATCH("TTL_H51",OECD_TTL!$A$2:$A$60,0),MATCH("HFCE",OECD_TTL!$B$1:$BI$1,0))+INDEX(OECD_TTL!$B$2:$BI$60,MATCH("TTL_H52",OECD_TTL!$A$2:$A$60,0),MATCH("HFCE",OECD_TTL!$B$1:$BI$1,0))+INDEX(OECD_TTL!$B$2:$BI$60,MATCH("TTL_H53",OECD_TTL!$A$2:$A$60,0),MATCH("HFCE",OECD_TTL!$B$1:$BI$1,0)))*10^6*About!$A$20*Calculations!$B$11 -> 3.6167958e+11 | AF2: =INDEX(OECD_TTL!$B$2:$BI$60,MATCH("TTL_I",OECD_TTL!$A$2:$A$60,0),MATCH("HFCE",OECD_TTL!$B$1:$BI$1,0))*10^6*About!$A$20*Calculations!$B$11 -> 1.0185222e+12 | AG2: =INDEX(OECD_TTL!$B$2:$BI$60,MATCH("TTL_J58T60",OECD_TTL!$A$2:$A$60,0),MATCH("HFCE",OECD_TTL!$B$1:$BI$1,0))*10^6*About!$A$20*Calculations!$B$11 -> 1.7950077e+11 | AH2: =INDEX(OECD_TTL!$B$2:$BI$60,MATCH("TTL_J61",OECD_TTL!$A$2:$A$60,0),MATCH("HFCE",OECD_TTL!$B$1:$BI$1,0))*10^6*About!$A$20*Calculations!$B$11 -> 3.3273802e+11 | AI2: =INDEX(OECD_TTL!$B$2:$BI$60,MATCH("TTL_J62_63",OECD_TTL!$A$2:$A$60,0),MATCH("HFCE",OECD_TTL!$B$1:$BI$1,0))*10^6*About!$A$20*Calculations!$B$11 -> 3.7144673e+10 | AJ2: =INDEX(OECD_TTL!$B$2:$BI$60,MATCH("TTL_K",OECD_TTL!$A$2:$A$60,0),MATCH("HFCE",OECD_TTL!$B$1:$BI$1,0))*10^6*About!$A$20*Calculations!$B$11 -> 1.1827361e+12 | AK2: =INDEX(OECD_TTL!$B$2:$BI$60,MATCH("TTL_L",OECD_TTL!$A$2:$A$60,0),MATCH("HFCE",OECD_TTL!$B$1:$BI$1,0))*10^6*About!$A$20*Calculations!$B$11 -> 2.3352385e+12 | AL2: =(INDEX(OECD_TTL!$B$2:$BI$60,MATCH("TTL_M",OECD_TTL!$A$2:$A$60,0),MATCH("HFCE",OECD_TTL!$B$1:$BI$1,0))+INDEX(OECD_TTL!$B$2:$BI$60,MATCH("TTL_N",OECD_TTL!$A$2:$A$60,0),MATCH("HFCE",OECD_TTL!$B$1:$BI$1,0)))*10^6*About!$A$20*Calculations!$B$11 -> 2.9243572e+11 | AM2: =INDEX(OECD_TTL!$B$2:$BI$60,MATCH("TTL_O",OECD_TTL!$A$2:$A$60,0),MATCH("HFCE",OECD_TTL!$B$1:$BI$1,0))*10^6*About!$A$20*Calculations!$B$11 -> 3.975462e+11 | AN2: =INDEX(OECD_TTL!$B$2:$BI$60,MATCH("TTL_P",OECD_TTL!$A$2:$A$60,0),MATCH("HFCE",OECD_TTL!$B$1:$BI$1,0))*10^6*About!$A$20*Calculations!$B$11 -> 5.4729878e+11 | AO2: =INDEX(OECD_TTL!$B$2:$BI$60,MATCH("TTL_Q",OECD_TTL!$A$2:$A$60,0),MATCH("HFCE",OECD_TTL!$B$1:$BI$1,0))*10^6*About!$A$20*Calculations!$B$11 -> 2.1050622e+12 | AP2: =(INDEX(OECD_TTL!$B$2:$BI$60,MATCH("TTL_R",OECD_TTL!$A$2:$A$60,0),MATCH("HFCE",OECD_TTL!$B$1:$BI$1,0))+INDEX(OECD_TTL!$B$2:$BI$60,MATCH("TTL_S",OECD_TTL!$A$2:$A$60,0),MATCH("HFCE",OECD_TTL!$B$1:$BI$1,0)))*10^6*About!$A$20*Calculations!$B$11 -> 5.3565844e+11 | AQ2: =INDEX(OECD_TTL!$B$2:$BI$60,MATCH("TTL_T",OECD_TTL!$A$2:$A$60,0),MATCH("HFCE",OECD_TTL!$B$1:$BI$1,0))*10^6*About!$A$20*Calculations!$B$11 -> 2.2150732e+10
