Workbook

Sheet About
A1: BObIC BAU Output by ISIC Code
A3: Sources: | B3: Gross output by industry, detail level (2024) -> SYObIC
B4: BEA
B5: Underlying Detail: Gross Output by Industry (Industry File Download), September 2025 revision
B6: 2025
B7: https://apps.bea.gov/histdata/index.cfm
B8: Tab '2024 Data', verbatim; column E = editable 52-code assignment. IT-YEAR CONVENTION: the model's Initial Time is 2025; 'SY Start Year' variables hold the prior year (2024). SYObIC = this 2024 data directly.
B10: 2024->2025 growth per code -> BObIC
B11: Energy Innovation, io-model/BPCiOaDCSbIC
B12: Scaled 2025 growth rates (AEO 2026 ELECTRNP / BLS 2.11 with the per-year GDP-fit factor) from the BPCiObIC workbook
B13: 2026
B14: https://www.eia.gov/outlooks/aeo/tables_ref.php
B15: Tab 'g2025 derivation' — computed LIVE from the embedded raw sources (BLS Table 2.11 + both AEO tabs, identical machinery to the BPCiObIC workbook); the only imported number is the single 2025 GDP-fit scalar (editable cell B2 with provenance). BObIC (non-SY = 2025 level) = SYObIC x (1 + g2025). BPCiObIC itself is rebased to 2025 = 0 — no double count.
A18: Notes:
A19: Currency | B19: 2024 USD -> 2012 USD factor below (editable; CPI-U from InputData/cpi.xlsx):
A20: 0.73191601 | B20: 2012 USD per 2024 USD
A21: Export | B21: SYObIC.csv = tab SYObIC; BObIC.csv = tab BObIC. Canonical 52-code column order (positional Vensim read).

Sheet 2024 Data
A1: U.Real Gross Output by Industry - Detail Level (BEA, Sep 2025 revision) — pasted from stock workbook
A3: Line | B3: Industry | C3: 2024 (millions of 2024 USD) | E3: ISIC Code (editable)
A4: 1 | B4: Oilseed farming | C4: 50014 | E4: ISIC 01
A5: 2 | B5: Grain farming | C5: 82647 | E5: ISIC 01
A6: 3 | B6: Vegetable and melon farming | C6: 26862 | E6: ISIC 01
A7: 4 | B7: Fruit and tree nut farming | C7: 30307 | E7: ISIC 01
A8: 5 | B8: Greenhouse, nursery, and floriculture production | C8: 31895 | E8: ISIC 01
A9: 6 | B9: Other crop farming | C9: 29353 | E9: ISIC 01
A10: 7 | B10: Dairy cattle and milk production | C10: 52126 | E10: ISIC 01
A11: 8 | B11: Beef cattle ranching and farming, including feedlots and dual-purpose ranching and farming | C11: 141304 | E11: ISIC 01
A12: 9 | B12: Poultry and egg production | C12: 75391 | E12: ISIC 01
A13: 10 | B13: Animal production, except cattle and poultry and eggs | C13: 45807 | E13: ISIC 01
A14: 11 | B14: Forestry and logging | C14: 26473 | E14: ISIC 02
A15: 12 | B15: Fishing, hunting and trapping | C15: 9657 | E15: ISIC 03
... A417: 414 | B417: Other state and local government enterprises | C417: 398367 | E417: ISIC 84

Sheet BLS Table 2.11
A1: Table 2.11 Employment and output by industry (Employment in thousands; Output in billion of chained 2017 dollars)
A2: 2024 National Employment Matrix title | B2: 2024 National Employment Matrix code | C2: Industry type | D2: Employment, 2024 | E2: Employment, 2034 | F2: Employment change, numeric, 2024–34 | G2: Employment change, percent, 2024–34 | H2: Compound annual rate of change, employment, 2024–34 | I2: Output, 2024 | J2: Output, 2034 | K2: Compound annual rate of change, output, 2024–34 | L2: Assigned ISIC Code (editable)
A3: Total, all industries | B3: TE1000 | C3: Summary | D3: 169956.1 | E3: 175167.9 | F3: 5211.8 | G3: 3.1 | H3: 0.3 | I3: 40174.8 | J3: 48622.4 | K3: 1.9
A4: Self-employed workers | B4: TE1100 | C4: Line item | D4: 9906.4 | E4: 10122.8 | F4: 216.4 | G4: 2.2 | H4: 0.2 | I4: — | J4: — | K4: —
A5: Total wage and salary employment | B5: TE1200 | C5: Summary | D5: 160049.7 | E5: 165045.1 | F5: 4995.4 | G5: 3.1 | H5: 0.3 | I5: — | J5: — | K5: —
A6: Agriculture, forestry, fishing, and hunting | B6: 110000 | C6: Summary | D6: 1480.7 | E6: 1482.1 | F6: 1.4 | G6: 0.1 | H6: 0 | I6: 447.9 | J6: 538.8 | K6: 1.9
A7: Crop production | B7: 111000 | C7: Line item | D7: 863.9 | E7: 881.2 | F7: 17.3 | G7: 2 | H7: 0.2 | I7: 175.8 | J7: 201.8 | K7: 1.4 | L7: ISIC 01
A8: Animal production and aquaculture | B8: 112000 | C8: Line item | D8: 442.4 | E8: 427.6 | F8: -14.8 | G8: -3.3 | H8: -0.3 | I8: 220 | J8: 277.6 | K8: 2.4 | L8: ISIC 01
A9: Forestry and logging | B9: 113000 | C9: Summary | D9: 47.2 | E9: 45.1 | F9: -2.1 | G9: -4.4 | H9: -0.5 | I9: — | J9: — | K9: —
A10: Forestry | B10: 1131-2 | C10: Line item | D10: 7 | E10: 6.9 | F10: -0.1 | G10: -2 | H10: -0.1 | I10: 3.9 | J10: 4.6 | K10: 1.6 | L10: ISIC 02
A11: Logging | B11: 113300 | C11: Line item | D11: 40.2 | E11: 38.2 | F11: -2 | G11: -4.9 | H11: -0.5 | I11: 18.9 | J11: 22.1 | K11: 1.6 | L11: ISIC 02
A12: Fishing, hunting and trapping | B12: 114000 | C12: Line item | D12: 20.9 | E12: 20.8 | F12: -0.1 | G12: -0.3 | H12: 0 | I12: 7.4 | J12: 8.6 | K12: 1.5 | L12: ISIC 03
A13: Support activities for agriculture and forestry | B13: 115000 | C13: Line item | D13: 106.2 | E13: 107.3 | F13: 1.1 | G13: 1 | H13: 0.1 | I13: 23.6 | J13: 27.6 | K13: 1.6 | L13: ISIC 01
A14: Mining, quarrying, and oil and gas extraction | B14: 210000 | C14: Summary | D14: 586.1 | E14: 576.8 | F14: -9.3 | G14: -1.6 | H14: -0.2 | I14: 564.6 | J14: 634.5 | K14: 1.2
A15: Oil and gas extraction | B15: 211000 | C15: Line item | D15: 122.5 | E15: 115.7 | F15: -6.8 | G15: -5.5 | H15: -0.6 | I15: 383.8 | J15: 450.7 | K15: 1.6 | L15: ISIC 06
A16: Mining (except oil and gas) | B16: 212000 | C16: Summary | D16: 191.7 | E16: 182.6 | F16: -9.1 | G16: -4.7 | H16: -0.5 | I16: 92.8 | J16: 99.9 | K16: 0.7
A17: Coal mining | B17: 212100 | C17: Line item | D17: 42.5 | E17: 23.2 | F17: -19.3 | G17: -45.3 | H17: -5.9 | I17: 29.8 | J17: 24.6 | K17: -1.9 | L17: ISIC 05
A18: Metal ore mining | B18: 212200 | C18: Line item | D18: 44.9 | E18: 48.4 | F18: 3.5 | G18: 7.9 | H18: 0.8 | I18: 26 | J18: 33.5 | K18: 2.6 | L18: ISIC 07
A19: Nonmetallic mineral mining and quarrying | B19: 212300 | C19: Line item | D19: 104.3 | E19: 111 | F19: 6.7 | G19: 6.4 | H19: 0.6 | I19: 36.9 | J19: 41.5 | K19: 1.2 | L19: ISIC 08
A20: Support activities for mining | B20: 213000 | C20: Line item | D20: 271.9 | E20: 278.4 | F20: 6.5 | G20: 2.4 | H20: 0.2 | I20: 95.6 | J20: 90.6 | K20: -0.5 | L20: ISIC 09
A21: Utilities | B21: 220000 | C21: Summary | D21: 591.3 | E21: 620 | F21: 28.7 | G21: 4.9 | H21: 0.5 | I21: 507.1 | J21: 602.2 | K21: 1.7
A22: Utilities | B22: 221000 | C22: Summary | D22: 591.3 | E22: 620 | F22: 28.7 | G22: 4.9 | H22: 0.5 | I22: 507.1 | J22: 602.2 | K22: 1.7
A23: Electric power generation, transmission and distribution | B23: 221100 | C23: Summary | D23: 413.1 | E23: 445.6 | F23: 32.5 | G23: 7.9 | H23: 0.8 | I23: 411.4 | J23: 501.2 | K23: 2 | L23: ISIC 351
A24: Electric power generation | B24: 221110 | C24: Summary | D24: 157.3 | E24: 169.2 | F24: 11.9 | G24: 7.6 | H24: 0.7 | I24: — | J24: — | K24: —
A25: Hydroelectric power generation | B25: 221111 | C25: Line item | D25: 8.2 | E25: 8.2 | F25: 0 | G25: 0.4 | H25: 0 | I25: — | J25: — | K25: —
A26: Fossil fuel electric power generation | B26: 221112 | C26: Line item | D26: 74.5 | E26: 51.5 | F26: -23 | G26: -30.9 | H26: -3.6 | I26: — | J26: — | K26: —
A27: Nuclear electric power generation | B27: 221113 | C27: Line item | D27: 38.2 | E27: 31.5 | F27: -6.7 | G27: -17.6 | H27: -1.9 | I27: — | J27: — | K27: —
A28: Solar electric power generation | B28: 221114 | C28: Line item | D28: 16.9 | E28: 47.2 | F28: 30.4 | G28: 180.2 | H28: 10.8 | I28: — | J28: — | K28: —
A29: Wind electric power generation | B29: 221115 | C29: Line item | D29: 11.2 | E29: 20.4 | F29: 9.2 | G29: 81.4 | H29: 6.2 | I29: — | J29: — | K29: —
A30: Geothermal electric power generation | B30: 221116 | C30: Line item | D30: 1.2 | E30: 1.6 | F30: 0.5 | G30: 41.4 | H30: 2.9 | I30: — | J30: — | K30: —
A31: Biomass electric power generation | B31: 221117 | C31: Line item | D31: 2.4 | E31: 2.5 | F31: 0 | G31: 1.9 | H31: 0.4 | I31: — | J31: — | K31: —
A32: Other electric power generation | B32: 221118 | C32: Line item | D32: 4.7 | E32: 6.2 | F32: 1.5 | G32: 32.9 | H32: 2.8 | I32: — | J32: — | K32: —
A33: Natural gas distribution | B33: 221200 | C33: Line item | D33: 116.1 | E33: 112.4 | F33: -3.7 | G33: -3.2 | H33: -0.3 | I33: 80.4 | J33: 86.5 | K33: 0.7 | L33: ISIC 352T353
A34: Water, sewage and other systems | B34: 221300 | C34: Line item | D34: 62.1 | E34: 62 | F34: -0.1 | G34: -0.1 | H34: 0 | I34: 15.6 | J34: 16.3 | K34: 0.5 | L34: ISIC 36T39
A35: Construction | B35: 230000 | C35: Summary | D35: 8211.7 | E35: 8572.2 | F35: 360.5 | G35: 4.4 | H35: 0.4 | I35: 1720.9 | J35: 1874.7 | K35: 0.9 | L35: ISIC 41T43
A36: Construction of buildings | B36: 236000 | C36: Summary | D36: 1853.6 | E36: 1938.2 | F36: 84.6 | G36: 4.6 | H36: 0.4 | I36: — | J36: — | K36: —
A37: Residential building construction | B37: 236100 | C37: Line item | D37: 943.1 | E37: 982.4 | F37: 39.3 | G37: 4.2 | H37: 0.4 | I37: — | J37: — | K37: —
A38: Nonresidential building construction | B38: 236200 | C38: Line item | D38: 910.5 | E38: 955.8 | F38: 45.3 | G38: 5 | H38: 0.5 | I38: — | J38: — | K38: —
A39: Heavy and civil engineering construction | B39: 237000 | C39: Summary | D39: 1154.4 | E39: 1206.1 | F39: 51.7 | G39: 4.5 | H39: 0.4 | I39: — | J39: — | K39: —
A40: Utility system construction | B40: 237100 | C40: Summary | D40: 602.8 | E40: 634.3 | F40: 31.5 | G40: 5.2 | H40: 0.5 | I40: — | J40: — | K40: —
A41: Power and communication line and related structures construction | B41: 237130 | C41: Line item | D41: 238.4 | E41: 257.2 | F41: 18.8 | G41: 7.9 | H41: 0.8 | I41: — | J41: — | K41: —
A42: Land subdivision | B42: 237200 | C42: Line item | D42: 37.1 | E42: 37.7 | F42: 0.6 | G42: 1.7 | H42: 0.2 | I42: — | J42: — | K42: —
A43: Highway, street, and bridge construction | B43: 237300 | C43: Line item | D43: 377.9 | E43: 390.9 | F43: 13 | G43: 3.4 | H43: 0.3 | I43: — | J43: — | K43: —
A44: Other heavy and civil engineering construction | B44: 237900 | C44: Line item | D44: 136.6 | E44: 143.2 | F44: 6.6 | G44: 4.8 | H44: 0.5 | I44: — | J44: — | K44: —
A45: Specialty trade contractors | B45: 238000 | C45: Summary | D45: 5203.7 | E45: 5427.9 | F45: 224.2 | G45: 4.3 | H45: 0.4 | I45: — | J45: — | K45: —
A46: Foundation, structure, and building exterior contractors | B46: 238100 | C46: Summary | D46: 992.5 | E46: 1032.1 | F46: 39.6 | G46: 4 | H46: 0.4 | I46: — | J46: — | K46: —
A47: Poured concrete foundation and structure contractors | B47: 238110 | C47: Line item | D47: 258.2 | E47: 273.5 | F47: 15.3 | G47: 5.9 | H47: 0.6 | I47: — | J47: — | K47: —
... A57: Other specialty trade contractors | B57: 238900 | C57: Line item | D57: 805.6 | E57: 848.6 | F57: 43 | G57: 5.3 | H57: 0.5 | I57: — | J57: — | K57: —
A58: Manufacturing | B58: 31-330 | C58: Summary | D58: 12817.2 | E58: 12816.8 | F58: -0.4 | G58: 0 | H58: 0 | I58: 5696.8 | J58: 6486.2 | K58: 1.3
A59: Food manufacturing | B59: 311000 | C59: Summary | D59: 1767.6 | E59: 1860.1 | F59: 92.5 | G59: 5.2 | H59: 0.5 | I59: 757.1 | J59: 910.3 | K59: 1.9 | L59: ISIC 10T12
A60: Animal food manufacturing | B60: 311100 | C60: Line item | D60: 75.4 | E60: 80.6 | F60: 5.2 | G60: 6.9 | H60: 0.7 | I60: 50.8 | J60: 60.7 | K60: 1.8
A61: Grain and oilseed milling | B61: 311200 | C61: Line item | D61: 67.4 | E61: 67.7 | F61: 0.3 | G61: 0.5 | H61: 0 | I61: 81.2 | J61: 93.9 | K61: 1.5
A62: Sugar and confectionery product manufacturing | B62: 311300 | C62: Line item | D62: 82.2 | E62: 84.2 | F62: 2 | G62: 2.4 | H62: 0.2 | I62: 32.6 | J62: 35.8 | K62: 0.9
A63: Fruit and vegetable preserving and specialty food manufacturing | B63: 311400 | C63: Line item | D63: 173.8 | E63: 172.6 | F63: -1.2 | G63: -0.7 | H63: -0.1 | I63: 57.1 | J63: 65.9 | K63: 1.4
A64: Dairy product manufacturing | B64: 311500 | C64: Line item | D64: 168 | E64: 178.8 | F64: 10.8 | G64: 6.4 | H64: 0.6 | I64: 130.4 | J64: 171.1 | K64: 2.8
A65: Animal slaughtering and processing | B65: 311600 | C65: Line item | D65: 556.4 | E65: 591.8 | F65: 35.4 | G65: 6.4 | H65: 0.6 | I65: 221.4 | J65: 265.1 | K65: 1.8
A66: Seafood product preparation and packaging | B66: 311700 | C66: Line item | D66: 31.5 | E66: 30.7 | F66: -0.8 | G66: -2.5 | H66: -0.3 | I66: 12.2 | J66: 14 | K66: 1.3
A67: Bakeries and tortilla manufacturing | B67: 311800 | C67: Line item | D67: 350.4 | E67: 369.2 | F67: 18.8 | G67: 5.4 | H67: 0.5 | I67: 62.1 | J67: 74.4 | K67: 1.8
A68: Other food manufacturing | B68: 311900 | C68: Line item | D68: 262.5 | E68: 284.4 | F68: 21.9 | G68: 8.4 | H68: 0.8 | I68: 109 | J68: 131 | K68: 1.9
A69: Beverage and tobacco product manufacturing | B69: 312000 | C69: Summary | D69: 343.4 | E69: 379.7 | F69: 36.3 | G69: 10.6 | H69: 1 | I69: 181.9 | J69: 203 | K69: 1.1 | L69: ISIC 10T12
A70: Beverage manufacturing | B70: 312100 | C70: Line item | D70: 333 | E70: 370.8 | F70: 37.8 | G70: 11.4 | H70: 1.1 | I70: 115.7 | J70: 150.5 | K70: 2.7
A71: Tobacco manufacturing | B71: 312200 | C71: Line item | D71: 10.4 | E71: 8.8 | F71: -1.6 | G71: -15 | H71: -1.7 | I71: 65.2 | J71: 54.6 | K71: -1.8
A72: Textile mills | B72: 313000 | C72: Line item | D72: 86.6 | E72: 78.3 | F72: -8.3 | G72: -9.5 | H72: -1 | I72: 19.4 | J72: 20 | K72: 0.3 | L72: ISIC 13T15
A73: Textile product mills | B73: 314000 | C73: Line item | D73: 99.5 | E73: 89 | F73: -10.5 | G73: -10.5 | H73: -1.1 | I73: 21 | J73: 21.9 | K73: 0.4 | L73: ISIC 13T15
A74: Apparel manufacturing | B74: 315000 | C74: Line item | D74: 84.5 | E74: 58.8 | F74: -25.7 | G74: -30.4 | H74: -3.6 | I74: 12.3 | J74: 10.1 | K74: -1.9 | L74: ISIC 13T15
A75: Leather and allied product manufacturing | B75: 316000 | C75: Line item | D75: 25.1 | E75: 23.8 | F75: -1.3 | G75: -5.2 | H75: -0.5 | I75: 11.9 | J75: 14.2 | K75: 1.8 | L75: ISIC 13T15
A76: Wood product manufacturing | B76: 321000 | C76: Summary | D76: 417 | E76: 417.6 | F76: 0.6 | G76: 0.1 | H76: 0 | I76: 126.5 | J76: 150.1 | K76: 1.7 | L76: ISIC 16
A77: Sawmills and wood preservation | B77: 321100 | C77: Line item | D77: 90.6 | E77: 89.2 | F77: -1.4 | G77: -1.6 | H77: -0.2 | I77: 47.2 | J77: 56.4 | K77: 1.8
A78: Veneer, plywood, and engineered wood product manufacturing | B78: 321200 | C78: Line item | D78: 82.2 | E78: 81.3 | F78: -0.9 | G78: -1.1 | H78: -0.1 | I78: 24.3 | J78: 28.6 | K78: 1.7
A79: Other wood product manufacturing | B79: 321900 | C79: Line item | D79: 244.2 | E79: 247.1 | F79: 2.9 | G79: 1.2 | H79: 0.1 | I79: 56.8 | J79: 67.3 | K79: 1.7
A80: Paper manufacturing | B80: 322000 | C80: Summary | D80: 354.6 | E80: 328.9 | F80: -25.7 | G80: -7.3 | H80: -0.7 | I80: 163 | J80: 180.2 | K80: 1 | L80: ISIC 17T18
A81: Pulp, paper, and paperboard mills | B81: 322100 | C81: Line item | D81: 84.7 | E81: 73.6 | F81: -11.1 | G81: -13.1 | H81: -1.4 | I81: 63.9 | J81: 63.1 | K81: -0.1
A82: Converted paper product manufacturing | B82: 322200 | C82: Line item | D82: 269.9 | E82: 255.3 | F82: -14.6 | G82: -5.4 | H82: -0.6 | I82: 99 | J82: 116.9 | K82: 1.7
A83: Printing and related support activities | B83: 323000 | C83: Line item | D83: 357.2 | E83: 301.9 | F83: -55.3 | G83: -15.5 | H83: -1.7 | I83: 67 | J83: 71.1 | K83: 0.6 | L83: ISIC 17T18
A84: Petroleum and coal products manufacturing | B84: 324000 | C84: Line item | D84: 109.4 | E84: 106.2 | F84: -3.2 | G84: -3 | H84: -0.3 | I84: 483.5 | J84: 535 | K84: 1 | L84: ISIC 19
A85: Chemical manufacturing | B85: 325000 | C85: Summary | D85: 897.9 | E85: 928.9 | F85: 31 | G85: 3.5 | H85: 0.3 | I85: 849.6 | J85: 1004 | K85: 1.7
A86: Chemical manufacturing (3251,2,3,9) | B86: 3250A1 | C86: Line item | D86: 368.7 | E86: 376.7 | F86: 8 | G86: 2.2 | H86: 0.2 | I86: 390.8 | J86: 431.5 | K86: 1 | L86: ISIC 20
A87: Chemical manufacturing (3255,6) | B87: 3250A2 | C87: Line item | D87: 178.7 | E87: 182.7 | F87: 4 | G87: 2.3 | H87: 0.2 | I87: 114.5 | J87: 139.5 | K87: 2 | L87: ISIC 20
A88: Pharmaceutical and medicine manufacturing | B88: 325400 | C88: Line item | D88: 350.5 | E88: 369.5 | F88: 19 | G88: 5.4 | H88: 0.5 | I88: 346.7 | J88: 438.5 | K88: 2.4 | L88: ISIC 21
A89: Plastics and rubber products manufacturing | B89: 326000 | C89: Summary | D89: 725.1 | E89: 753.4 | F89: 28.3 | G89: 3.9 | H89: 0.4 | I89: 229.7 | J89: 252.1 | K89: 0.9 | L89: ISIC 22
A90: Plastics product manufacturing | B90: 326100 | C90: Line item | D90: 592.5 | E90: 618.8 | F90: 26.3 | G90: 4.4 | H90: 0.4 | I90: 190.7 | J90: 212.4 | K90: 1.1
A91: Rubber product manufacturing | B91: 326200 | C91: Line item | D91: 132.6 | E91: 134.6 | F91: 2 | G91: 1.5 | H91: 0.1 | I91: 39.1 | J91: 39.7 | K91: 0.2
A92: Nonmetallic mineral product manufacturing | B92: 327000 | C92: Line item | D92: 422.3 | E92: 429 | F92: 6.7 | G92: 1.6 | H92: 0.2 | I92: 113.5 | J92: 132.3 | K92: 1.5 | L92: ISIC 239
A93: Primary metal manufacturing | B93: 331000 | C93: Summary | D93: 373.2 | E93: 360.2 | F93: -13 | G93: -3.5 | H93: -0.4 | I93: 246.6 | J93: 287.3 | K93: 1.5
A94: Iron and steel mills and ferroalloy manufacturing | B94: 331100 | C94: Line item | D94: 85.6 | E94: 86.9 | F94: 1.3 | G94: 1.5 | H94: 0.2 | I94: 103.9 | J94: 124.3 | K94: 1.8 | L94: ISIC 241
A95: Steel product manufacturing from purchased steel | B95: 331200 | C95: Line item | D95: 59.8 | E95: 60.9 | F95: 1.1 | G95: 1.9 | H95: 0.2 | I95: 25.6 | J95: 30.9 | K95: 1.9 | L95: ISIC 241
A96: Alumina and aluminum production and processing | B96: 331300 | C96: Line item | D96: 59.3 | E96: 58.4 | F96: -0.9 | G96: -1.5 | H96: -0.2 | I96: 38.1 | J96: 39.9 | K96: 0.5 | L96: ISIC 242
A97: Nonferrous metal (except aluminum) production and processing | B97: 331400 | C97: Line item | D97: 62.5 | E97: 63.6 | F97: 1.1 | G97: 1.8 | H97: 0.2 | I97: 50.3 | J97: 64.1 | K97: 2.4 | L97: ISIC 242
A98: Foundries | B98: 331500 | C98: Line item | D98: 106 | E98: 90.4 | F98: -15.6 | G98: -14.7 | H98: -1.6 | I98: 26.9 | J98: 24.8 | K98: -0.8
A99: Fabricated metal product manufacturing | B99: 332000 | C99: Summary | D99: 1442.1 | E99: 1385.3 | F99: -56.8 | G99: -3.9 | H99: -0.4 | I99: 303.5 | J99: 329.5 | K99: 0.8 | L99: ISIC 25
A100: Fabricated metal product manufacturing (3321,2,5,6,9) | B100: 3320A1 | C100: Line item | D100: 467.8 | E100: 423.2 | F100: -44.6 | G100: -9.5 | H100: -1 | I100: 123.8 | J100: 129.6 | K100: 0.5
A101: Fabricated metal product manufacturing (3323,4) | B101: 3320A2 | C101: Line item | D101: 511.5 | E101: 526.3 | F101: 14.8 | G101: 2.9 | H101: 0.3 | I101: 97.4 | J101: 109.1 | K101: 1.1
A102: Machine shops; turned product; and screw, nut, and bolt manufacturing | B102: 332700 | C102: Summary | D102: 333.2 | E102: 319.8 | F102: -13.4 | G102: -4 | H102: -0.4 | I102: 59.1 | J102: 65.9 | K102: 1.1
A103: Machine shops | B103: 332710 | C103: Line item | D103: 259 | E103: 260.1 | F103: 1.1 | G103: 0.4 | H103: 0 | I103: 37.1 | J103: 41.3 | K103: 1.1
A104: Turned product and screw, nut, and bolt manufacturing | B104: 332720 | C104: Line item | D104: 74.2 | E104: 59.8 | F104: -14.4 | G104: -19.5 | H104: -2.1 | I104: 22.2 | J104: 24.7 | K104: 1.1
A105: Coating, engraving, heat treating, and allied activities | B105: 332800 | C105: Line item | D105: 129.6 | E105: 115.9 | F105: -13.7 | G105: -10.6 | H105: -1.1 | I105: 25.1 | J105: 26.1 | K105: 0.4
A106: Machinery manufacturing | B106: 333000 | C106: Summary | D106: 1118.8 | E106: 1108.2 | F106: -10.6 | G106: -0.9 | H106: -0.1 | I106: 330.1 | J106: 366.9 | K106: 1.1 | L106: ISIC 28
A107: Machinery manufacturing (3331,2,4,9) | B107: 3330A1 | C107: Line item | D107: 780.2 | E107: 782.8 | F107: 2.6 | G107: 0.3 | H107: 0 | I107: 241.2 | J107: 266.8 | K107: 1
A108: Commercial and service industry machinery manufacturing | B108: 333300 | C108: Line item | D108: 88.7 | E108: 89.6 | F108: 0.9 | G108: 1 | H108: 0.1 | I108: 23.5 | J108: 26.4 | K108: 1.2
A109: Metalworking machinery manufacturing | B109: 333500 | C109: Line item | D109: 157.1 | E109: 147.4 | F109: -9.7 | G109: -6.2 | H109: -0.6 | I109: 27.3 | J109: 30.6 | K109: 1.1
...

Sheet AEO25 Table 23
C1: Table 23. Industrial Sector Macroeconomic Indicators
C2: https://www.eia.gov/outlooks/aeo/data/browser/#/?id=34-AEO2025&cases=highZTC&sourcekey=0
C3: Tue Dec 02 2025 13:21:59 GMT-0800 (Pacific Standard Time)
C4: Source: U.S. Energy Information Administration
B5: ISIC assignment (editable) | D5: full name | E5: api key | F5: units | G5: 2023 | H5: 2024 | I5: 2025 | J5: 2026 | K5: 2027 | L5: 2028 | M5: 2029 | N5: 2030 | O5: 2031 | P5: 2032 | Q5: 2033 | R5: 2034 | S5: 2035 | T5: 2036 | U5: 2037 | V5: 2038 | W5: 2039 | X5: 2040 | Y5: 2041 | Z5: 2042 | AA5: 2043 | AB5: 2044 | AC5: 2045 | AD5: 2046 | AE5: 2047 | AF5: 2048 | AG5: 2049 | AH5: 2050 | AI5: Growth (2024-2050)
A6: ISM000:ba_GDP(billionm_ | C6: Gross Domestic Product (billion 2012 dollars) | D6: Industrial Macroeconomic: Gross Domestic Product: High Zero-Carbon Technology Cost | E6: AEO.2025.HIGHZTC.ECI_GDP_NA_NA_NA_NA_NA_BLNY09DLR.A | F6: billion 2012 $ | H6: 21699.672 | I6: 22171.93 | J6: 22685.953 | K6: 23162.596 | L6: 23590.016 | M6: 24042.869 | N6: 24479.318 | O6: 24877.939 | P6: 25299.824 | Q6: 25731.902 | R6: 26166.297 | S6: 26621.836 | T6: 27077.875 | U6: 27546.342 | V6: 28018.711 | W6: 28503.035 | X6: 29003.939 | Y6: 29486.92 | Z6: 29991.914 | AA6: 30494.672 | AB6: 30998.293 | AC6: 31501.85 | AD6: 32021.367 | AE6: 32546.51 | AF6: 33074.625 | AG6: 33617.656 | AH6: 34162.723 | AI6: 0.018
A7: ISM000:ca_NonfarmEmploy | C7: Nonfarm Employment (millions) | D7: Industrial Macroeconomic: Employment, Nonfarm: High Zero-Carbon Technology Cost | E7: AEO.2025.HIGHZTC.ECI_NFE_NA_NA_NA_NA_NA_MILL.A | F7: millions | H7: 159.5452 | I7: 160.89847 | J7: 161.43066 | K7: 161.69711 | L7: 161.99791 | M7: 162.5314 | N7: 163.24155 | O7: 163.92671 | P7: 164.54892 | Q7: 164.98477 | R7: 165.29776 | S7: 165.56593 | T7: 166.08339 | U7: 166.7914 | V7: 167.5314 | W7: 168.18655 | X7: 169.00385 | Y7: 169.65865 | Z7: 170.29732 | AA7: 170.74045 | AB7: 171.20613 | AC7: 171.65497 | AD7: 172.12753 | AE7: 172.64163 | AF7: 173.16328 | AG7: 173.71744 | AH7: 174.28783 | AI7: 0.003
C8: Value of Shipments (billion 2012 dollars)
C9: Nonmanufacturing Sector
A10: ISM000:ea_Agricultural | B10: ,ISIC 01, | C10: Agriculture/Forestry/Fishing/Hunting | D10: Industrial Macroeconomic: Nonmanufacturing: Agriculture/Forestry/Fishing/Hunting: High Zero-Carbon Technology Cost | E10: AEO.2025.HIGHZTC.ECI_VOS_NMFG_AFF_NA_NA_NA_BLNY09DLR.A | F10: billion 2012 $ | H10: 538.8266 | I10: 544.76807 | J10: 552.01935 | K10: 559.25311 | L10: 565.51892 | M10: 573.79547 | N10: 581.47052 | O10: 587.56146 | P10: 593.56909 | Q10: 599.28235 | R10: 606.56781 | S10: 614.13873 | T10: 623.17743 | U10: 630.44727 | V10: 636.67987 | W10: 643.48901 | X10: 649.69403 | Y10: 654.328 | Z10: 659.78339 | AA10: 665.28345 | AB10: 671.34363 | AC10: 678.96008 | AD10: 686.82513 | AE10: 694.61627 | AF10: 702.28125 | AG10: 710.2558 | AH10: 718.01489 | AI10: 0.011
A11: ISM000:ea_Mining | B11: ,ISIC 05,ISIC 06,ISIC 08, | C11: Mining | D11: Industrial Macroeconomic: Nonmanufacturing: Mining: High Zero-Carbon Technology Cost | E11: AEO.2025.HIGHZTC.ECI_VOS_NMFG_MING_NA_NA_NA_BLNY09DLR.A | F11: billion 2012 $ | H11: 738.6261 | I11: 800.09271 | J11: 807.26276 | K11: 812.87158 | L11: 822.88531 | M11: 830.664 | N11: 837.44684 | O11: 834.11847 | P11: 842.65662 | Q11: 842.87884 | R11: 843.77454 | S11: 839.43475 | T11: 833.55817 | U11: 824.76233 | V11: 820.58246 | W11: 815.21143 | X11: 817.20264 | Y11: 820.17926 | Z11: 823.91998 | AA11: 823.77704 | AB11: 825.68115 | AC11: 828.09149 | AD11: 834.33093 | AE11: 835.11914 | AF11: 834.69672 | AG11: 836.80615 | AH11: 839.41028 | AI11: 0.005
A12: ISM000:ea_Construction | B12: ,ISIC 41T43, | C12: Construction | D12: Industrial Macroeconomic: Nonmanufacturing: Construction: High Zero-Carbon Technology Cost | E12: AEO.2025.HIGHZTC.ECI_VOS_NMFG_CNS_NA_NA_NA_BLNY09DLR.A | F12: billion 2012 $ | H12: 1440.7977 | I12: 1433.0573 | J12: 1444.2264 | K12: 1467.1532 | L12: 1502.7834 | M12: 1544.0198 | N12: 1573.1925 | O12: 1598.66 | P12: 1617.2603 | Q12: 1624.0387 | R12: 1624.3893 | S12: 1639.5165 | T12: 1660.5125 | U12: 1673.6357 | V12: 1687.7023 | W12: 1700.454 | X12: 1710.2748 | Y12: 1717.3003 | Z12: 1728.8163 | AA12: 1737.1105 | AB12: 1744.9568 | AC12: 1762.099 | AD12: 1781.2562 | AE12: 1803.2469 | AF12: 1826.4515 | AG12: 1851.1388 | AH12: 1872.7469 | AI12: 0.01
C13: Manufacturing Sector
A14: ISM000:fa_FoodandKindre | B14: ,ISIC 10T12, | C14: Food Products | D14: Industrial Macroeconomic: Manufacturing: Food Products: High Zero-Carbon Technology Cost | E14: AEO.2025.HIGHZTC.ECI_VOS_MANF_FPA_NA_NA_NA_BLNY09DLR.A | F14: billion 2012 $ | H14: 821.565 | I14: 826.25629 | J14: 829.60242 | K14: 837.90674 | L14: 844.65008 | M14: 853.04797 | N14: 861.58227 | O14: 869.4892 | P14: 877.76154 | Q14: 885.73114 | R14: 894.01611 | S14: 901.54547 | T14: 911.37494 | U14: 920.41272 | V14: 929.09497 | W14: 938.25281 | X14: 947.32989 | Y14: 956.4433 | Z14: 965.737 | AA14: 974.68512 | AB14: 983.68793 | AC14: 992.50006 | AD14: 1001.4976 | AE14: 1010.5715 | AF14: 1019.6702 | AG14: 1029.1584 | AH14: 1038.4718 | AI14: 0.009
A15: ISM000:fa_BeveragesandT | B15: ,ISIC 10T12, | C15: Beverages and Tobacco Products | D15: Industrial Macroeconomic: Manufacturing: Beverages and Tobacco Products: High Zero-Carbon Technology Cost | E15: AEO.2025.HIGHZTC.ECI_VOS_MANF_BVTP_NA_NA_NA_BLNY09DLR.A | F15: billion 2012 $ | H15: 141.90608 | I15: 139.8526 | J15: 138.7114 | K15: 138.03377 | L15: 137.52714 | M15: 136.83862 | N15: 136.09837 | O15: 135.32722 | P15: 134.48689 | Q15: 133.75133 | R15: 133.0681 | S15: 132.55055 | T15: 131.98662 | U15: 131.44885 | V15: 130.93477 | W15: 130.42633 | X15: 129.9326 | Y15: 129.43793 | Z15: 128.93127 | AA15: 128.3781 | AB15: 127.79433 | AC15: 127.17438 | AD15: 126.60002 | AE15: 126.07458 | AF15: 125.57433 | AG15: 125.09577 | AH15: 124.58905 | AI15: -0.005
A16: ISM000:fa_TextileMillPr | B16: ,ISIC 13T15, | C16: Textile Mills and Products | D16: Industrial Macroeconomic: Manufacturing: Textile Mills and Products: High Zero-Carbon Technology Cost | E16: AEO.2025.HIGHZTC.ECI_VOS_MANF_TMP_NA_NA_NA_BLNY09DLR.A | F16: billion 2012 $ | H16: 66.089165 | I16: 66.538513 | J16: 65.8992 | K16: 65.924271 | L16: 64.83783 | M16: 64.166801 | N16: 63.704239 | O16: 63.158009 | P16: 62.414116 | Q16: 61.727993 | R16: 61.319778 | S16: 60.568184 | T16: 59.831409 | U16: 59.532326 | V16: 59.14883 | W16: 58.90044 | X16: 58.791424 | Y16: 58.565128 | Z16: 58.345596 | AA16: 57.977749 | AB16: 57.632816 | AC16: 57.247356 | AD16: 56.93322 | AE16: 56.724243 | AF16: 56.464836 | AG16: 56.23605 | AH16: 55.887161 | AI16: -0.006
A17: ISM000:fa_LumberandWood | B17: ,ISIC 16, | C17: Wood Products | D17: Industrial Macroeconomic: Manufacturing: Wood Products: High Zero-Carbon Technology Cost | E17: AEO.2025.HIGHZTC.ECI_VOS_MANF_WDP_NA_NA_NA_BLNY09DLR.A | F17: billion 2012 $ | H17: 98.40712 | I17: 99.04071 | J17: 101.04065 | K17: 102.24693 | L17: 103.98792 | M17: 107.2435 | N17: 109.76388 | O17: 111.44402 | P17: 112.56998 | Q17: 112.37907 | R17: 113.57045 | S17: 115.05647 | T17: 118.32752 | U17: 120.52498 | V17: 121.29505 | W17: 122.2 | X17: 122.0394 | Y17: 119.66293 | Z17: 118.0938 | AA17: 115.15807 | AB17: 113.1279 | AC17: 113.01455 | AD17: 113.40658 | AE17: 114.63775 | AF17: 115.77583 | AG17: 117.22973 | AH17: 118.1262 | AI17: 0.007
A18: ISM000:fa_FurnitureandF | B18: ,ISIC 31T33, | C18: Furniture and Related Products | D18: Industrial Macroeconomic: Manufacturing: Furniture and Related Products: High Zero-Carbon Technology Cost | E18: AEO.2025.HIGHZTC.ECI_VOS_MANF_FRP_NA_NA_NA_BLNY09DLR.A | F18: billion 2012 $ | H18: 53.271854 | I18: 52.269444 | J18: 53.980427 | K18: 55.926292 | L18: 56.093472 | M18: 56.599045 | N18: 58.34198 | O18: 58.92627 | P18: 59.556118 | Q18: 59.890476 | R18: 61.148804 | S18: 61.658676 | T18: 62.141407 | U18: 63.414036 | V18: 64.388123 | W18: 65.334251 | X18: 66.700745 | Y18: 67.731552 | Z18: 68.640739 | AA18: 69.677574 | AB18: 70.932808 | AC18: 71.805748 | AD18: 72.815346 | AE18: 74.188431 | AF18: 74.879402 | AG18: 76.066422 | AH18: 76.886627 | AI18: 0.014
A19: ISM000:fa_PaperandAllie | B19: ,ISIC 17T18, | C19: Paper Products | D19: Industrial Macroeconomic: Manufacturing: Paper Products: High Zero-Carbon Technology Cost | E19: AEO.2025.HIGHZTC.ECI_VOS_MANF_PPM_NA_NA_NA_BLNY09DLR.A | F19: billion 2012 $ | H19: 161.46919 | I19: 162.7692 | J19: 164.02576 | K19: 162.47028 | L19: 161.55638 | M19: 161.47072 | N19: 161.8098 | O19: 162.97775 | P19: 163.75282 | Q19: 164.06697 | R19: 165.19106 | S19: 166.25287 | T19: 167.39653 | U19: 168.34885 | V19: 169.4716 | W19: 171.07837 | X19: 172.76543 | Y19: 174.02237 | Z19: 175.34892 | AA19: 176.49817 | AB19: 178.14328 | AC19: 179.31845 | AD19: 180.70677 | AE19: 182.0945 | AF19: 183.34045 | AG19: 184.40793 | AH19: 185.49396 | AI19: 0.005
A20: ISM000:fa_PrintingandPu | B20: ,ISIC 17T18, | C20: Printing | D20: Industrial Macroeconomic: Manufacturing: Printing: High Zero-Carbon Technology Cost | E20: AEO.2025.HIGHZTC.ECI_VOS_MANF_PRN_NA_NA_NA_BLNY09DLR.A | F20: billion 2012 $ | H20: 60.525852 | I20: 57.448959 | J20: 56.292637 | K20: 54.877972 | L20: 53.651821 | M20: 52.613571 | N20: 51.594307 | O20: 50.581692 | P20: 49.633221 | Q20: 48.66946 | R20: 47.801643 | S20: 46.996117 | T20: 46.399475 | U20: 45.814659 | V20: 45.239269 | W20: 44.861446 | X20: 44.471886 | Y20: 44.081989 | Z20: 43.735256 | AA20: 43.354687 | AB20: 43.027943 | AC20: 42.731819 | AD20: 42.579571 | AE20: 42.327194 | AF20: 42.10128 | AG20: 41.857502 | AH20: 41.633499 | AI20: -0.014
A21: ISM000:fa_ChemicalandAl | B21: ,ISIC 20, | C21: Chemical Manufacturing | D21: Industrial Macroeconomic: Manufacturing: Chemical Manufacturing: High Zero-Carbon Technology Cost | E21: AEO.2025.HIGHZTC.ECI_VOS_MANF_CHE_NA_NA_NA_BLNY09DLR.A | F21: billion 2012 $ | H21: 808.21368 | I21: 812.38934 | J21: 806.69074 | K21: 804.93176 | L21: 803.34943 | M21: 806.09863 | N21: 813.56812 | O21: 823.25134 | P21: 834.16455 | Q21: 843.79175 | R21: 855.42957 | S21: 865.72815 | T21: 874.20136 | U21: 885.51782 | V21: 896.98572 | W21: 909.44946 | X21: 923.43683 | Y21: 936.80664 | Z21: 950.84143 | AA21: 963.14319 | AB21: 974.9859 | AC21: 984.60706 | AD21: 994.83899 | AE21: 1008.811 | AF21: 1020.662 | AG21: 1031.7502 | AH21: 1041.1604 | AI21: 0.01
A22: ISM000:fa_BulkChemicals | C22: Bulk Chemicals | D22: Industrial Macroeconomic: Manufacturing: Chemicals: Bulk Chemicals: High Zero-Carbon Technology Cost | E22: AEO.2025.HIGHZTC.ECI_VOS_MANF_BCH_NA_NA_NA_BLNY09DLR.A | F22: billion 2012 $ | H22: 367.32217 | I22: 372.95435 | J22: 365.47006 | K22: 360.02753 | L22: 354.24496 | M22: 352.82477 | N22: 355.28152 | O22: 359.69891 | P22: 364.24594 | Q22: 367.19061 | R22: 373.40387 | S22: 379.88586 | T22: 384.06592 | U22: 389.13483 | V22: 394.53491 | W22: 400.9906 | X22: 408.14343 | Y22: 414.30145 | Z22: 420.51334 | AA22: 425.35037 | AB22: 430.8327 | AC22: 435.23618 | AD22: 439.59573 | AE22: 446.34097 | AF22: 451.72757 | AG22: 456.2446 | AH22: 460.80216 | AI22: 0.009
A23: ISM000:fa_Inorganic | C23: Inorganic | D23: Industrial Macroeconomic: Manufacturing: Chemicals: Bulk Chemicals: Inorganic: High Zero-Carbon Technology Cost | E23: AEO.2025.HIGHZTC.ECI_VOS_MANF_CHEIN_NA_NA_NA_BLNY09DLR.A | F23: billion 2012 $ | H23: 50.760822 | I23: 51.478336 | J23: 52.328194 | K23: 52.508663 | L23: 52.006046 | M23: 51.169857 | N23: 51.473831 | O23: 51.551136 | P23: 51.466038 | Q23: 51.676189 | R23: 51.725769 | S23: 52.104076 | T23: 52.200466 | U23: 51.96347 | V23: 52.269703 | W23: 52.373104 | X23: 52.339554 | Y23: 52.473537 | Z23: 52.384289 | AA23: 52.293137 | AB23: 52.097511 | AC23: 51.880245 | AD23: 51.748787 | AE23: 51.814064 | AF23: 51.907967 | AG23: 51.836624 | AH23: 51.954746 | AI23: 0.001
A24: ISM000:fa_Organic | C24: Organic | D24: Industrial Macroeconomic: Manufacturing: Chemicals: Bulk Chemicals: Organic: High Zero-Carbon Technology Cost | E24: AEO.2025.HIGHZTC.ECI_VOS_MANF_CHEOR_NA_NA_NA_BLNY09DLR.A | F24: billion 2012 $ | H24: 179.6485 | I24: 184.1534 | J24: 172.36072 | K24: 167.71588 | L24: 163.97459 | M24: 162.34164 | N24: 162.01833 | O24: 164.70097 | P24: 167.63568 | Q24: 169.28833 | R24: 172.1774 | S24: 176.19098 | T24: 179.03477 | U24: 181.7184 | V24: 185.00465 | W24: 189.10175 | X24: 193.48135 | Y24: 197.50008 | Z24: 201.28572 | AA24: 205.21362 | AB24: 209.58937 | AC24: 213.81535 | AD24: 216.95627 | AE24: 221.06383 | AF24: 224.53114 | AG24: 227.09778 | AH24: 230.2061 | AI24: 0.01
A25: ISM000:fa_Resins | C25: Resin | D25: Synthetic Rubber | E25: and Fibers | F25: Industrial Macroeconomic: Manufacturing: Chemicals: Bulk Chemicals: Resin, Synthetic Rubber, and Fibers: High Zero-Carbon Technology Cost | G25: AEO.2025.HIGHZTC.ECI_VOS_MANF_CHEBR_NA_NA_NA_BLNY09DLR.A | H25: 98.834442 | I25: 97.966858 | J25: 99.326225 | K25: 97.665497 | L25: 95.804192 | M25: 96.423264 | N25: 98.262207 | O25: 99.258095 | P25: 100.285 | Q25: 100.9119 | R25: 103.31385 | S25: 104.717 | T25: 105.34988 | U25: 107.17442 | V25: 108.3623 | W25: 110.00505 | X25: 112.15402 | Y25: 113.5902 | Z25: 115.5398 | AA25: 116.0079 | AB25: 116.68415 | AC25: 116.62328 | AD25: 117.465 | AE25: 119.5488 | AF25: 120.94505 | AG25: 122.55138 | AH25: 123.52005 | AI25: 0.009
A26: ISM000:fa_AgriculturalC | C26: Agricultural Chemicals | D26: Industrial Macroeconomic: Manufacturing: Chemicals: Bulk Chemicals: Agricultural Chemicals: High Zero-Carbon Technology Cost | E26: AEO.2025.HIGHZTC.ECI_VOS_MANF_AGC_NA_NA_NA_BLNY09DLR.A | F26: billion 2012 $ | H26: 38.078388 | I26: 39.355778 | J26: 41.454929 | K26: 42.137497 | L26: 42.460148 | M26: 42.890003 | N26: 43.527168 | O26: 44.188728 | P26: 44.859222 | Q26: 45.314175 | R26: 46.186852 | S26: 46.873821 | T26: 47.480816 | U26: 48.278534 | V26: 48.898262 | W26: 49.510666 | X26: 50.168533 | Y26: 50.737656 | Z26: 51.303539 | AA26: 51.835686 | AB26: 52.461685 | AC26: 52.917336 | AD26: 53.425697 | AE26: 53.914276 | AF26: 54.343407 | AG26: 54.758823 | AH26: 55.121239 | AI26: 0.014
A27: ISM000:fa_OtherChemical | C27: Other Chemical Products | D27: Industrial Macroeconomic: Manufacturing: Chemicals: Other Chemical Products: High Zero-Carbon Technology Cost | E27: AEO.2025.HIGHZTC.ECI_VOS_MANF_CHEO_NA_NA_NA_BLNY09DLR.A | F27: billion 2012 $ | H27: 440.89151 | I27: 439.435 | J27: 441.22067 | K27: 444.9042 | L27: 449.10446 | M27: 453.27383 | N27: 458.28656 | O27: 463.5524 | P27: 469.91864 | Q27: 476.60113 | R27: 482.02567 | S27: 485.84226 | T27: 490.13544 | U27: 496.383 | V27: 502.45084 | W27: 508.45886 | X27: 515.2934 | Y27: 522.50519 | Z27: 530.32806 | AA27: 537.79279 | AB27: 544.1532 | AC27: 549.37085 | AD27: 555.24323 | AE27: 562.47003 | AF27: 568.93445 | AG27: 575.50562 | AH27: 580.35828 | AI27: 0.011
A28: ISM000:fa_PetroleumandC | C28: Petroleum and Coal Products | D28: Industrial Macroeconomic: Manufacturing: Petroleum and Coal Products: High Zero-Carbon Technology Cost | E28: AEO.2025.HIGHZTC.ECI_VOS_MANF_PCL_NA_NA_NA_BLNY09DLR.A | F28: billion 2012 $ | H28: 816.09601 | I28: 829.73065 | J28: 826.35809 | K28: 822.63525 | L28: 818.11365 | M28: 811.7898 | N28: 801.87268 | O28: 790.94 | P28: 777.92773 | Q28: 764.57977 | R28: 753.02173 | S28: 741.50934 | T28: 729.7876 | U28: 718.6405 | V28: 709.41724 | W28: 702.5293 | X28: 697.51465 | Y28: 692.16034 | Z28: 686.87671 | AA28: 682.12921 | AB28: 678.85687 | AC28: 674.4317 | AD28: 672.45917 | AE28: 673.33466 | AF28: 671.36792 | AG28: 672.13104 | AH28: 673.04504 | AI28: -0.007
A29: ISM000:fa_PetroleumRefi | B29: ,ISIC 19, | C29: Petroleum Refineries | D29: Industrial Macroeconomic: Manufacturing: Petroleum and Coal: Petroleum Refineries: High Zero-Carbon Technology Cost | E29: AEO.2025.HIGHZTC.ECI_VOS_MANF_REF_NA_NA_NA_BLNY09DLR.A | F29: billion 2012 $ | H29: 773.8219 | I29: 786.61841 | J29: 783.18323 | K29: 779.68903 | L29: 775.45001 | M29: 769.39807 | N29: 759.90216 | O29: 749.35315 | P29: 736.87854 | Q29: 724.18066 | R29: 713.24438 | S29: 702.289 | T29: 691.01855 | U29: 680.32849 | V29: 671.50891 | W29: 664.93426 | X29: 660.10657 | Y29: 654.97394 | Z29: 650.02429 | AA29: 645.57031 | AB29: 642.4895 | AC29: 638.2727 | AD29: 636.51154 | AE29: 637.53351 | AF29: 635.75726 | AG29: 636.62994 | AH29: 637.6333 | AI29: -0.007
A30: ISM000:fa_OtherPetroleu | B30: ,ISIC 241, | C30: Other Petroleum and Coal Products | D30: Industrial Macroeconomic: Manufacturing: Petroleum and Coal: Other Petroleum & Coal Products: High Zero-Carbon Technology Cost | E30: AEO.2025.HIGHZTC.ECI_VOS_MANF_PCLO_NA_NA_NA_BLNY09DLR.A | F30: billion 2012 $ | H30: 42.27409 | I30: 43.112217 | J30: 43.174866 | K30: 42.94622 | L30: 42.663628 | M30: 42.391701 | N30: 41.970547 | O30: 41.586861 | P30: 41.049202 | Q30: 40.399086 | R30: 39.777332 | S30: 39.220341 | T30: 38.769024 | U30: 38.312031 | V30: 37.90834 | W30: 37.595055 | X30: 37.408058 | Y30: 37.186394 | Z30: 36.85239 | AA30: 36.558922 | AB30: 36.367348 | AC30: 36.158981 | AD30: 35.947632 | AE30: 35.801125 | AF30: 35.610645 | AG30: 35.501125 | AH30: 35.411743 | AI30: -0.007
A31: ISM000:fa_RubberandMisc | B31: ,ISIC 22, | C31: Plastics and Rubber Products | D31: Industrial Macroeconomic: Manufacturing: Plastics and Rubber Products: High Zero-Carbon Technology Cost | E31: AEO.2025.HIGHZTC.ECI_VOS_MANF_PRP_NA_NA_NA_BLNY09DLR.A | F31: billion 2012 $ | H31: 212.32913 | I31: 217.69611 | J31: 224.71417 | K31: 228.99838 | L31: 231.00073 | M31: 233.92827 | N31: 237.69215 | O31: 241.49115 | P31: 245.09897 | Q31: 248.24377 | R31: 252.30617 | S31: 255.40613 | T31: 257.66836 | U31: 260.66455 | V31: 263.21542 | W31: 265.90036 | X31: 268.94296 | Y31: 271.58008 | Z31: 274.43543 | AA31: 276.42465 | AB31: 278.5116 | AC31: 280.17221 | AD31: 282.02731 | AE31: 284.19464 | AF31: 286.12378 | AG31: 288.19809 | AH31: 289.85263 | AI31: 0.012
A32: ISM000:fa_Stone,Clay,an | C32: Non-metallic minerals | D32: Industrial Macroeconomic: Manufacturing: Stone, Clay, and Glass Products: High Zero-Carbon Technology Cost | E32: AEO.2025.HIGHZTC.ECI_VOS_MANF_SCG_NA_NA_NA_BLNY09DLR.A | F32: billion 2012 $ | H32: 111.54769 | I32: 111.64612 | J32: 111.83931 | K32: 112.53001 | L32: 113.1917 | M32: 113.50225 | N32: 114.45515 | O32: 115.9222 | P32: 117.23323 | Q32: 118.13599 | R32: 118.88231 | S32: 119.85504 | T32: 120.86804 | U32: 121.95155 | V32: 123.17243 | W32: 124.29541 | X32: 125.05119 | Y32: 125.54099 | Z32: 125.83267 | AA32: 125.66972 | AB32: 125.18317 | AC32: 125.38245 | AD32: 126.04735 | AE32: 126.8273 | AF32: 127.72215 | AG32: 128.63948 | AH32: 129.61243 | AI32: 0.006
A33: ISM000:fa_GlassandGlass | B33: ,ISIC 231, | C33: Glass and Glass Products | D33: Industrial Macroeconomic: Manufacturing: Stone, Clay, and Glass: Glass and Glass Products: High Zero-Carbon Technology Cost | E33: AEO.2025.HIGHZTC.ECI_VOS_MANF_SCGG_NA_NA_NA_BLNY09DLR.A | F33: billion 2012 $ | H33: 21.45093 | I33: 21.290245 | J33: 21.242983 | K33: 21.230724 | L33: 21.263985 | M33: 21.310061 | N33: 21.371811 | O33: 21.476692 | P33: 21.61256 | Q33: 21.745703 | R33: 21.89089 | S33: 22.055412 | T33: 22.216677 | U33: 22.39768 | V33: 22.595711 | W33: 22.798956 | X33: 23.015873 | Y33: 23.23588 | Z33: 23.452274 | AA33: 23.653669 | AB33: 23.834209 | AC33: 23.998465 | AD33: 24.153 | AE33: 24.320282 | AF33: 24.498272 | AG33: 24.677088 | AH33: 24.843611 | AI33: 0.006
A34: ISM000:fa_CementandHydr | B34: ,ISIC 239, | C34: Cement and Lime | D34: Industrial Macroeconomic: Manufacturing: Stone, Clay, and Glass: Cement and Lime: High Zero-Carbon Technology Cost | E34: AEO.2025.HIGHZTC.ECI_VOS_MANF_SCGCL_NA_NA_NA_BLNY09DLR.A | F34: billion 2012 $ | H34: 9.305412 | I34: 9.341552 | J34: 9.271192 | K34: 9.279629 | L34: 9.351248 | M34: 9.433073 | N34: 9.557519 | O34: 9.703686 | P34: 9.855732 | Q34: 9.999584 | R34: 10.13154 | S34: 10.260571 | T34: 10.38773 | U34: 10.523909 | V34: 10.673493 | W34: 10.821849 | X34: 10.946848 | Y34: 11.046646 | Z34: 11.118332 | AA34: 11.14825 | AB34: 11.14453 | AC34: 11.16645 | AD34: 11.222955 | AE34: 11.310638 | AF34: 11.422865 | AG34: 11.550447 | AH34: 11.685319 | AI34: 0.009
A35: ISM000:fa_OtherStone,Cl | B35: ,ISIC 239, | C35: Other Nonmetallic Mineral Products | D35: Industrial Macroeconomic: Manufacturing: Stone, Clay, and Glass: Other Nonmetallic Mineral Products: High Zero-Carbon Technology Cost | E35: AEO.2025.HIGHZTC.ECI_VOS_MANF_SCGOM_NA_NA_NA_BLNY09DLR.A | F35: billion 2012 $ | H35: 80.791351 | I35: 81.01432 | J35: 81.325134 | K35: 82.019653 | L35: 82.576469 | M35: 82.759117 | N35: 83.525826 | O35: 84.741814 | P35: 85.764938 | Q35: 86.390701 | R35: 86.859879 | S35: 87.539062 | T35: 88.263634 | U35: 89.029968 | V35: 89.903229 | W35: 90.674606 | X35: 91.088463 | Y35: 91.258469 | Z35: 91.26207 | AA35: 90.867805 | AB35: 90.204437 | AC35: 90.217529 | AD35: 90.671394 | AE35: 91.196381 | AF35: 91.801018 | AG35: 92.411949 | AH35: 93.083488 | AI35: 0.005
A36: ISM000:ga_PrimaryMetals | C36: Primary Metals Industry | D36: Industrial Macroeconomic: Manufacturing: Primary Metals Industry: High Zero-Carbon Technology Cost | E36: AEO.2025.HIGHZTC.ECI_VOS_MANF_PMM_NA_NA_NA_BLNY09DLR.A | F36: billion 2012 $ | H36: 244.86504 | I36: 248.52803 | J36: 255.5425 | K36: 258.2749 | L36: 258.45053 | M36: 259.36414 | N36: 262.41397 | O36: 266.26843 | P36: 270.27884 | Q36: 271.53186 | R36: 274.66315 | S36: 277.69369 | T36: 280.42725 | U36: 284.75626 | V36: 288.45294 | W36: 292.01385 | X36: 297.0069 | Y36: 300.80423 | Z36: 303.9722 | AA36: 308.31238 | AB36: 311.88547 | AC36: 314.56079 | AD36: 316.64414 | AE36: 319.67554 | AF36: 321.56711 | AG36: 322.92242 | AH36: 324.23212 | AI36: 0.011
A37: ISM000:ga_BlastFurnacea | B37: ,ISIC 241, | C37: Iron and Steel Mills and Products | D37: Industrial Macroeconomic: Manufacturing: Primary Metals: Iron and Steel Mills and Products: High Zero-Carbon Technology Cost | E37: AEO.2025.HIGHZTC.ECI_VOS_MANF_ISM_NA_NA_NA_BLNY09DLR.A | F37: billion 2012 $ | H37: 131.32573 | I37: 134.93411 | J37: 141.45989 | K37: 142.77377 | L37: 141.88794 | M37: 141.74979 | N37: 143.73824 | O37: 146.53499 | P37: 149.38496 | Q37: 149.45511 | R37: 151.37814 | S37: 153.10629 | T37: 154.5363 | U37: 157.53503 | V37: 159.87338 | W37: 162.08472 | X37: 165.73244 | Y37: 168.19681 | Z37: 170.0643 | AA37: 173.14265 | AB37: 175.5089 | AC37: 177.0495 | AD37: 178.07887 | AE37: 180.09767 | AF37: 181.03627 | AG37: 181.49979 | AH37: 181.98811 | AI37: 0.013
A38: ISM000:ga_Aluminum | B38: ,ISIC 242, | C38: Alumina and Aluminum Products | D38: Industrial Macroeconomic: Manufacturing: Primary Metals: Alumina and Aluminum Products: High Zero-Carbon Technology Cost | E38: AEO.2025.HIGHZTC.ECI_VOS_MANF_AAP_NA_NA_NA_BLNY09DLR.A | F38: billion 2012 $ | H38: 34.597599 | I38: 34.167324 | J38: 34.714939 | K38: 35.325741 | L38: 35.804806 | M38: 36.362534 | N38: 36.869461 | O38: 37.424278 | P38: 38.041748 | Q38: 38.662601 | R38: 39.322857 | S38: 40.049435 | T38: 40.793427 | U38: 41.567074 | V38: 42.354301 | W38: 43.131817 | X38: 43.905979 | Y38: 44.671326 | Z38: 45.415844 | AA38: 46.116341 | AB38: 46.751091 | AC38: 47.299404 | AD38: 47.767883 | AE38: 48.191673 | AF38: 48.568092 | AG38: 48.904499 | AH38: 49.198971 | AI38: 0.014
A39: ISM000:ga_OtherPrimaryM | B39: ,ISIC 242, | C39: Other Primary Metal Products | D39: Industrial Macroeconomic: Manufacturing: Primary Metals: Other Primary Metal Products: High Zero-Carbon Technology Cost | E39: AEO.2025.HIGHZTC.ECI_VOS_MANF_PMO_NA_NA_NA_BLNY09DLR.A | F39: billion 2012 $ | H39: 78.941711 | I39: 79.426582 | J39: 79.367668 | K39: 80.175369 | L39: 80.75779 | M39: 81.251801 | N39: 81.806282 | O39: 82.309166 | P39: 82.852135 | Q39: 83.414146 | R39: 83.962135 | S39: 84.537956 | T39: 85.097519 | U39: 85.654175 | V39: 86.225258 | W39: 86.797302 | X39: 87.368469 | Y39: 87.936096 | Z39: 88.492043 | AA39: 89.053383 | AB39: 89.625504 | AC39: 90.211868 | AD39: 90.797394 | AE39: 91.3862 | AF39: 91.962723 | AG39: 92.518127 | AH39: 93.045013 | AI39: 0.006
A40: ISM000:ga_FabricatedMet | B40: ,ISIC 25, | C40: Fabricated Metal Products | D40: Industrial Macroeconomic: Manufacturing: Fabricated Metal Products: High Zero-Carbon Technology Cost | E40: AEO.2025.HIGHZTC.ECI_VOS_MANF_FBP_NA_NA_NA_BLNY09DLR.A | F40: billion 2012 $ | H40: 302.45358 | I40: 308.42365 | J40: 320.7533 | K40: 328.51697 | L40: 329.17981 | M40: 329.98978 | N40: 332.51956 | O40: 335.4873 | P40: 338.85028 | Q40: 339.64154 | R40: 343.30469 | S40: 344.99402 | T40: 347.50638 | U40: 351.45007 | V40: 354.34689 | W40: 357.36279 | X40: 361.16931 | Y40: 363.91495 | Z40: 366.68784 | AA40: 368.30096 | AB40: 371.01907 | AC40: 372.19131 | AD40: 374.32022 | AE40: 376.14328 | AF40: 377.55277 | AG40: 379.67996 | AH40: 379.72183 | AI40: 0.009
A41: ISM000:ga_IndustrialMac | B41: ,ISIC 28, | C41: Machinery | D41: Industrial Macroeconomic: Manufacturing: Machinery: High Zero-Carbon Technology Cost | E41: AEO.2025.HIGHZTC.ECI_VOS_MANF_MCHI_NA_NA_NA_BLNY09DLR.A | F41: billion 2012 $ | H41: 298.00757 | I41: 301.46787 | J41: 307.617 | K41: 319.3667 | L41: 326.12961 | M41: 331.91284 | N41: 338.64636 | O41: 343.72708 | P41: 348.29407 | Q41: 349.59146 | R41: 352.93121 | S41: 355.55087 | T41: 358.41681 | U41: 361.28418 | V41: 362.44919 | W41: 363.33536 | X41: 364.77499 | Y41: 365.61197 | Z41: 366.47958 | AA41: 366.93137 | AB41: 367.69513 | AC41: 367.91858 | AD41: 368.88498 | AE41: 370.44449 | AF41: 370.69086 | AG41: 371.66428 | AH41: 371.93857 | AI41: 0.009
A42: ISM000:ga_Electronicand | B42: ,ISIC 26, | C42: Computers and Electronics | D42: Industrial Macroeconomic: Manufacturing: Computers and Electronics: High Zero-Carbon Technology Cost | E42: AEO.2025.HIGHZTC.ECI_VOS_MANF_CMPEL_NA_NA_NA_BLNY09DLR.A | F42: billion 2012 $ | H42: 440.02228 | I42: 457.77365 | J42: 467.24835 | K42: 485.61023 | L42: 505.60599 | M42: 521.77954 | N42: 537.289 | O42: 552.02997 | P42: 567.71088 | Q42: 579.98846 | R42: 593.50488 | S42: 608.81079 | T42: 626.12176 | U42: 643.88788 | V42: 661.97846 | W42: 681.56665 | X42: 702.5965 | Y42: 724.23218 | Z42: 746.66785 | AA42: 768.78619 | AB42: 792.41302 | AC42: 815.7619 | AD42: 841.44476 | AE42: 868.17761 | AF42: 895.31726 | AG42: 922.96326 | AH42: 950.84961 | AI42: 0.03
A43: ISM000:ga_Transportatio | B43: ,ISIC 29,ISIC 302T309, | C43: Transportation Equipment | D43: Industrial Macroeconomic: Manufacturing: Transportation Equipment: High Zero-Carbon Technology Cost | E43: AEO.2025.HIGHZTC.ECI_VOS_MANF_TEQ_NA_NA_NA_BLNY09DLR.A | F43: billion 2012 $ | H43: 1067.6899 | I43: 1135.0959 | J43: 1211.5575 | K43: 1234.714 | L43: 1260.626 | M43: 1284.1858 | N43: 1298.3617 | O43: 1299.6274 | P43: 1310.2197 | Q43: 1323.2843 | R43: 1352.7478 | S43: 1371.8915 | T43: 1384.062 | U43: 1398.4255 | V43: 1415.8612 | W43: 1434.6405 | X43: 1452.1932 | Y43: 1466.6412 | Z43: 1482.1952 | AA43: 1494.6827 | AB43: 1508.6281 | AC43: 1524.235 | AD43: 1539.3557 | AE43: 1554.1062 | AF43: 1568.6698 | AG43: 1581.3815 | AH43: 1589.3907 | AI43: 0.015
A44: ISM000:ga_Instrumentsan | B44: ,ISIC 27, | C44: Electrical Equipment | D44: Industrial Macroeconomic: Manufacturing: Electrical Equipment: High Zero-Carbon Technology Cost | E44: AEO.2025.HIGHZTC.ECI_VOS_MANF_EEQ_NA_NA_NA_BLNY09DLR.A | F44: billion 2012 $ | H44: 117.17452 | I44: 117.89025 | J44: 117.05665 | K44: 118.63743 | L44: 121.1516 | M44: 122.9899 | N44: 124.64062 | O44: 125.65285 | P44: 126.7785 | Q44: 126.76083 | R44: 126.97958 | S44: 127.5349 | T44: 128.18622 | U44: 128.97725 | V44: 129.6022 | W44: 130.39653 | X44: 131.37585 | Y44: 132.2148 | Z44: 133.01923 | AA44: 133.66067 | AB44: 134.38882 | AC44: 134.90305 | AD44: 135.61032 | AE44: 136.45515 | AF44: 137.00888 | AG44: 137.57597 | AH44: 137.9623 | AI44: 0.006
A45: ISM000:ga_Miscellaneous | B45: ,ISIC 31T33, | C45: Miscellaneous Manufacturing | D45: Industrial Macroeconomic: Manufacturing: Miscellaneous Manufacturing: High Zero-Carbon Technology Cost | E45: AEO.2025.HIGHZTC.ECI_VOS_MANF_MISC_NA_NA_NA_BLNY09DLR.A | F45: billion 2012 $ | H45: 153.33037 | I45: 157.28622 | J45: 161.45157 | K45: 166.08694 | L45: 170.00337 | M45: 172.20496 | N45: 174.9388 | O45: 177.68588 | P45: 181.15735 | Q45: 182.86475 | R45: 184.45093 | S45: 186.48675 | T45: 188.98085 | U45: 191.5983 | V45: 193.246 | W45: 194.85245 | X45: 196.92516 | Y45: 199.0097 | Z45: 201.02315 | AA45: 202.8374 | AB45: 204.95595 | AC45: 206.37453 | AD45: 208.37825 | AE45: 210.46848 | AF45: 211.74797 | AG45: 214.56938 | AH45: 214.75027 | AI45: 0.013
A46: ISM000:ha_TotalIndustri | C46: Total Industrial Value of Shipments | D46: Industrial Macroeconomic: Total Industrial Value of Shipments: High Zero-Carbon Technology Cost | E46: AEO.2025.HIGHZTC.ECI_VOS_IDAL_NA_NA_NA_NA_BLNY09DLR.A | F46: billion 2012 $ | H46: 8693.2158 | I46: 8880.0215 | J46: 9023.8906 | K46: 9136.9668 | L46: 9250.2939 | M46: 9368.2061 | N46: 9471.4023 | O46: 9544.3271 | P46: 9631.375 | Q46: 9680.8301 | R46: 9759.0693 | S46: 9833.1797 | T46: 9910.9326 | U46: 9985.4961 | V46: 10063.266 | W46: 10146.551 | X46: 10240.19 | Y46: 10320.271 | Z46: 10409.384 | AA46: 10482.779 | AB46: 10564.851 | AC46: 10653.482 | AD46: 10756.961 | AE46: 10868.238 | AF46: 10969.666 | AG46: 11079.728 | AH46: 11173.775 | AI46: 0.01

Sheet AEO 2026 Table 23 
C1: Table 23. Industrial Sector Macroeconomic Indicators
C2: https://www.eia.gov/outlooks/aeo/data/browser/#/?id=34-AEO2026&cases=electrnp&sourcekey=0
C3: Thu Apr 23 2026 15:01:03 GMT-0700 (Pacific Daylight Time)
C4: Source: U.S. Energy Information Administration
B5: ISIC assignment (editable) | D5: full name | E5: api key | F5: units | G5: 2025 | H5: 2026 | I5: 2027 | J5: 2028 | K5: 2029 | L5: 2030 | M5: 2031 | N5: 2032 | O5: 2033 | P5: 2034 | Q5: 2035 | R5: 2036 | S5: 2037 | T5: 2038 | U5: 2039 | V5: 2040 | W5: 2041 | X5: 2042 | Y5: 2043 | Z5: 2044 | AA5: 2045 | AB5: 2046 | AC5: 2047 | AD5: 2048 | AE5: 2049 | AF5: 2050 | AG5: Growth (2025-2050)
A6: ISM000:ba_GDP(billionm_ | C6: Gross Domestic Product (billion 2012 dollars) | D6: Industrial Macroeconomic: Gross Domestic Product: Alternative Electricity and Transportation | E6: AEO.2026.ELECTRNP.ECI_GDP_NA_NA_NA_NA_NA_BLNY09DLR.A | F6: billion 2012 $ | G6: 22086.084 | H6: 22669.975 | I6: 23095.641 | J6: 23390.617 | K6: 23750.76 | L6: 24166.652 | M6: 24572.645 | N6: 25034.145 | O6: 25522.301 | P6: 26041.154 | Q6: 26595.578 | R6: 27063.66 | S6: 27531.34 | T6: 28000.277 | U6: 28461.051 | V6: 28925.545 | W6: 29375.912 | X6: 29841.965 | Y6: 30321.672 | Z6: 30806.215 | AA6: 31294.172 | AB6: 31769.938 | AC6: 32226.467 | AD6: 32681.023 | AE6: 33125.082 | AF6: 33582.949 | AG6: 0.017
A7: ISM000:ca_NonfarmEmploy | C7: Nonfarm Employment (millions) | D7: Industrial Macroeconomic: Employment, Nonfarm: Alternative Electricity and Transportation | E7: AEO.2026.ELECTRNP.ECI_NFE_NA_NA_NA_NA_NA_MILL.A | F7: millions | G7: 160.34007 | H7: 161.28101 | I7: 162.17047 | J7: 162.60861 | K7: 163.08629 | L7: 163.62587 | M7: 164.11606 | N7: 164.78729 | O7: 165.46202 | P7: 166.1698 | Q7: 166.88487 | R7: 167.66199 | S7: 168.56576 | T7: 169.43977 | U7: 170.1514 | V7: 170.95247 | W7: 171.58038 | X7: 172.17842 | Y7: 172.70612 | Z7: 173.32774 | AA7: 174.0012 | AB7: 174.60243 | AC7: 175.09766 | AD7: 175.47995 | AE7: 175.77896 | AF7: 176.12506 | AG7: 0.004
C8: Value of Shipments (billion 2012 dollars)
C9: Nonmanufacturing Sector
A10: ISM000:ea_Agricultural | B10: ,ISIC 01, | C10: Agriculture/Forestry/Fishing/Hunting | D10: Industrial Macroeconomic: Nonmanufacturing: Agriculture/Forestry/Fishing/Hunting: Alternative Electricity and Transportation | E10: AEO.2026.ELECTRNP.ECI_VOS_NMFG_AFF_NA_NA_NA_BLNY09DLR.A | F10: billion 2012 $ | G10: 485.34998 | H10: 486.52557 | I10: 493.37537 | J10: 503.25858 | K10: 509.90396 | L10: 516.43335 | M10: 522.85254 | N10: 529.38611 | O10: 532.95337 | P10: 539.97076 | Q10: 547.71857 | R10: 555.45874 | S10: 562.9729 | T10: 570.92297 | U10: 579.125 | V10: 586.07172 | W10: 592.65619 | X10: 599.99512 | Y10: 606.93585 | Z10: 614.49286 | AA10: 623.08154 | AB10: 632.104 | AC10: 641.20709 | AD10: 650.44 | AE10: 659.60828 | AF10: 668.85413 | AG10: 0.013
A11: ISM000:ea_Mining | B11: ,ISIC 05,ISIC 06,ISIC 08, | C11: Mining | D11: Industrial Macroeconomic: Nonmanufacturing: Mining: Alternative Electricity and Transportation | E11: AEO.2026.ELECTRNP.ECI_VOS_NMFG_MING_NA_NA_NA_BLNY09DLR.A | F11: billion 2012 $ | G11: 791.22412 | H11: 863.60974 | I11: 857.47864 | J11: 862.24182 | K11: 867.37317 | L11: 886.0852 | M11: 900.35944 | N11: 913.71997 | O11: 923.65027 | P11: 935.96826 | Q11: 939.37109 | R11: 943.46912 | S11: 948.6922 | T11: 953.50342 | U11: 959.69214 | V11: 971.02344 | W11: 984.75244 | X11: 992.50195 | Y11: 1001.0425 | Z11: 1006.1229 | AA11: 1009.7766 | AB11: 1013.5451 | AC11: 1019.1384 | AD11: 1021.3472 | AE11: 1021.3635 | AF11: 1019.4868 | AG11: 0.01
A12: ISM000:ea_Construction | B12: ,ISIC 41T43, | C12: Construction | D12: Industrial Macroeconomic: Nonmanufacturing: Construction: Alternative Electricity and Transportation | E12: AEO.2026.ELECTRNP.ECI_VOS_NMFG_CNS_NA_NA_NA_BLNY09DLR.A | F12: billion 2012 $ | G12: 1526.77 | H12: 1521.3313 | I12: 1530.4597 | J12: 1540.0048 | K12: 1565.4055 | L12: 1591.653 | M12: 1615.953 | N12: 1640.3335 | O12: 1660.85 | P12: 1674.0291 | Q12: 1692.3223 | R12: 1708.3278 | S12: 1722.0208 | T12: 1733.7163 | U12: 1743.8199 | V12: 1750.1165 | W12: 1754.2722 | X12: 1764.618 | Y12: 1772.1407 | Z12: 1781.1648 | AA12: 1798.493 | AB12: 1816.6458 | AC12: 1833.3215 | AD12: 1850.2052 | AE12: 1869.444 | AF12: 1891.599 | AG12: 0.009
C13: Manufacturing Sector
A14: ISM000:fa_FoodandKindre | B14: ,ISIC 10T12, | C14: Food Products | D14: Industrial Macroeconomic: Manufacturing: Food Products: Alternative Electricity and Transportation | E14: AEO.2026.ELECTRNP.ECI_VOS_MANF_FPA_NA_NA_NA_BLNY09DLR.A | F14: billion 2012 $ | G14: 762.71002 | H14: 766.6488 | I14: 776.75324 | J14: 786.11645 | K14: 792.97131 | L14: 801.68433 | M14: 810.93811 | N14: 819.74689 | O14: 828.72485 | P14: 838.03882 | Q14: 846.84888 | R14: 856.58661 | S14: 866.08649 | T14: 875.84137 | U14: 885.78131 | V14: 894.87964 | W14: 903.73852 | X14: 912.51666 | Y14: 921.0224 | Z14: 929.5047 | AA14: 937.15027 | AB14: 945.1366 | AC14: 953.13153 | AD14: 961.09613 | AE14: 969.4184 | AF14: 977.19104 | AG14: 0.01
A15: ISM000:fa_BeveragesandT | B15: ,ISIC 10T12, | C15: Beverages and Tobacco Products | D15: Industrial Macroeconomic: Manufacturing: Beverages and Tobacco Products: Alternative Electricity and Transportation | E15: AEO.2026.ELECTRNP.ECI_VOS_MANF_BVTP_NA_NA_NA_BLNY09DLR.A | F15: billion 2012 $ | G15: 145.14 | H15: 143.29698 | I15: 141.07892 | J15: 139.88065 | K15: 138.8069 | L15: 137.82715 | M15: 136.89218 | N15: 136.1991 | O15: 135.47145 | P15: 134.65437 | Q15: 133.95633 | R15: 133.1942 | S15: 132.51904 | T15: 131.79112 | U15: 130.83189 | V15: 130.09213 | W15: 129.5887 | X15: 129.14653 | Y15: 128.57558 | Z15: 128.06078 | AA15: 127.7637 | AB15: 127.40795 | AC15: 126.8901 | AD15: 126.3991 | AE15: 125.8749 | AF15: 125.28133 | AG15: -0.006
A16: ISM000:fa_TextileMillPr | B16: ,ISIC 13T15, | C16: Textile Mills and Products | D16: Industrial Macroeconomic: Manufacturing: Textile Mills and Products: Alternative Electricity and Transportation | E16: AEO.2026.ELECTRNP.ECI_VOS_MANF_TMP_NA_NA_NA_BLNY09DLR.A | F16: billion 2012 $ | G16: 58.60323 | H16: 59.344818 | I16: 60.159962 | J16: 58.416599 | K16: 56.206123 | L16: 55.21006 | M16: 54.903446 | N16: 54.746746 | O16: 54.889694 | P16: 55.283863 | Q16: 55.522114 | R16: 55.493893 | S16: 55.565697 | T16: 55.676113 | U16: 55.728962 | V16: 55.944988 | W16: 56.146873 | X16: 56.280396 | Y16: 56.407085 | Z16: 56.575737 | AA16: 56.78751 | AB16: 56.890766 | AC16: 56.785236 | AD16: 56.510384 | AE16: 56.437035 | AF16: 56.381992 | AG16: -0.002
A17: ISM000:fa_LumberandWood | B17: ,ISIC 16, | C17: Wood Products | D17: Industrial Macroeconomic: Manufacturing: Wood Products: Alternative Electricity and Transportation | E17: AEO.2026.ELECTRNP.ECI_VOS_MANF_WDP_NA_NA_NA_BLNY09DLR.A | F17: billion 2012 $ | G17: 118.725 | H17: 99.63253 | I17: 93.661903 | J17: 98.211769 | K17: 105.91305 | L17: 107.0631 | M17: 104.34275 | N17: 104.02138 | O17: 106.39807 | P17: 110.546 | Q17: 113.7761 | R17: 117.1022 | S17: 119.56847 | T17: 122.23325 | U17: 124.19093 | V17: 124.83405 | W17: 122.58537 | X17: 121.28372 | Y17: 118.8681 | Z17: 117.27795 | AA17: 118.01935 | AB17: 118.72787 | AC17: 119.79555 | AD17: 120.763 | AE17: 122.42195 | AF17: 123.7975 | AG17: 0.002
A18: ISM000:fa_FurnitureandF | B18: ,ISIC 31T33, | C18: Furniture and Related Products | D18: Industrial Macroeconomic: Manufacturing: Furniture and Related Products: Alternative Electricity and Transportation | E18: AEO.2026.ELECTRNP.ECI_VOS_MANF_FRP_NA_NA_NA_BLNY09DLR.A | F18: billion 2012 $ | G18: 58.322498 | H18: 59.011951 | I18: 60.173313 | J18: 59.152695 | K18: 59.48531 | L18: 60.807999 | M18: 61.878868 | N18: 63.159161 | O18: 64.566895 | P18: 65.938286 | Q18: 68.118446 | R18: 69.331093 | S18: 70.475876 | T18: 72.192848 | U18: 73.151497 | V18: 74.659355 | W18: 76.165657 | X18: 77.674377 | Y18: 79.193832 | Z18: 80.946732 | AA18: 83.448448 | AB18: 84.887985 | AC18: 86.415627 | AD18: 87.191368 | AE18: 88.336067 | AF18: 89.970726 | AG18: 0.017
A19: ISM000:fa_PaperandAllie | B19: ,ISIC 17T18, | C19: Paper Products | D19: Industrial Macroeconomic: Manufacturing: Paper Products: Alternative Electricity and Transportation | E19: AEO.2026.ELECTRNP.ECI_VOS_MANF_PPM_NA_NA_NA_BLNY09DLR.A | F19: billion 2012 $ | G19: 146.52499 | H19: 146.30009 | I19: 148.3551 | J19: 148.39004 | K19: 148.27515 | L19: 148.2298 | M19: 149.00885 | N19: 149.76033 | O19: 150.41437 | P19: 151.04452 | Q19: 151.76538 | R19: 152.44345 | S19: 152.84227 | T19: 153.86858 | U19: 155.21448 | V19: 156.88922 | W19: 158.34563 | X19: 159.91808 | Y19: 161.62904 | Z19: 163.46222 | AA19: 165.47505 | AB19: 167.21362 | AC19: 169.04817 | AD19: 170.64967 | AE19: 172.45003 | AF19: 174.19078 | AG19: 0.007
A20: ISM000:fa_PrintingandPu | B20: ,ISIC 17T18, | C20: Printing | D20: Industrial Macroeconomic: Manufacturing: Printing: Alternative Electricity and Transportation | E20: AEO.2026.ELECTRNP.ECI_VOS_MANF_PRN_NA_NA_NA_BLNY09DLR.A | F20: billion 2012 $ | G20: 64.357498 | H20: 62.670582 | I20: 60.88274 | J20: 59.342823 | K20: 58.132961 | L20: 56.884991 | M20: 55.614899 | N20: 54.24551 | O20: 52.755295 | P20: 51.431721 | Q20: 50.014038 | R20: 48.692402 | S20: 47.663521 | T20: 46.690609 | U20: 46.016659 | V20: 45.447735 | W20: 44.834614 | X20: 44.365486 | Y20: 43.841122 | Z20: 43.243725 | AA20: 42.610481 | AB20: 42.079239 | AC20: 41.707779 | AD20: 41.560303 | AE20: 41.430828 | AF20: 41.002571 | AG20: -0.018
A21: ISM000:fa_ChemicalandAl | B21: ,ISIC 20, | C21: Chemical Manufacturing | D21: Industrial Macroeconomic: Manufacturing: Chemical Manufacturing: Alternative Electricity and Transportation | E21: AEO.2026.ELECTRNP.ECI_VOS_MANF_CHE_NA_NA_NA_BLNY09DLR.A | F21: billion 2012 $ | G21: 866.14447 | H21: 854.60504 | I21: 844.64343 | J21: 841.27881 | K21: 834.1626 | L21: 833.86487 | M21: 837.70923 | N21: 842.62769 | O21: 851.86352 | P21: 861.18933 | Q21: 871.22015 | R21: 881.64966 | S21: 893.15485 | T21: 904.77008 | U21: 918.34717 | V21: 932.80969 | W21: 949.00275 | X21: 967.69165 | Y21: 985.70813 | Z21: 1004.382 | AA21: 1024.8037 | AB21: 1046.9314 | AC21: 1070.0601 | AD21: 1091.0392 | AE21: 1111.1675 | AF21: 1133.6318 | AG21: 0.011
A22: ISM000:fa_BulkChemicals | C22: Bulk Chemicals | D22: Industrial Macroeconomic: Manufacturing: Chemicals: Bulk Chemicals: Alternative Electricity and Transportation | E22: AEO.2026.ELECTRNP.ECI_VOS_MANF_BCH_NA_NA_NA_BLNY09DLR.A | F22: billion 2012 $ | G22: 389.91446 | H22: 374.33463 | I22: 368.80945 | J22: 367.27594 | K22: 361.54742 | L22: 361.8844 | M22: 365.39737 | N22: 366.77454 | O22: 369.9859 | P22: 373.71805 | Q22: 378.38687 | R22: 383.46777 | S22: 388.05298 | T22: 392.6192 | U22: 399.43426 | V22: 406.02402 | W22: 412.86163 | X22: 420.91342 | Y22: 427.61038 | Z22: 434.30237 | AA22: 442.08344 | AB22: 450.44989 | AC22: 459.5007 | AD22: 467.66095 | AE22: 474.06464 | AF22: 482.12265 | AG22: 0.009
A23: ISM000:fa_Inorganic | C23: Inorganic | D23: Industrial Macroeconomic: Manufacturing: Chemicals: Bulk Chemicals: Inorganic: Alternative Electricity and Transportation | E23: AEO.2026.ELECTRNP.ECI_VOS_MANF_CHEIN_NA_NA_NA_BLNY09DLR.A | F23: billion 2012 $ | G23: 51.491623 | H23: 52.255329 | I23: 51.697498 | J23: 51.97789 | K23: 51.210506 | L23: 50.927029 | M23: 51.219692 | N23: 51.075771 | O23: 51.268539 | P23: 51.611919 | Q23: 51.78804 | R23: 51.978779 | S23: 51.913784 | T23: 51.978077 | U23: 52.200249 | V23: 52.240593 | W23: 52.3074 | X23: 52.404572 | Y23: 52.432655 | Z23: 52.335209 | AA23: 52.231144 | AB23: 52.381222 | AC23: 52.576962 | AD23: 52.698147 | AE23: 52.773537 | AF23: 52.96476 | AG23: 0.001
A24: ISM000:fa_Organic | C24: Organic | D24: Industrial Macroeconomic: Manufacturing: Chemicals: Bulk Chemicals: Organic: Alternative Electricity and Transportation | E24: AEO.2026.ELECTRNP.ECI_VOS_MANF_CHEOR_NA_NA_NA_BLNY09DLR.A | F24: billion 2012 $ | G24: 184.63533 | H24: 169.54507 | I24: 162.99795 | J24: 163.28098 | K24: 159.4751 | L24: 158.51843 | M24: 160.61568 | N24: 162.61992 | O24: 165.4667 | P24: 168.74754 | Q24: 171.98885 | R24: 176.30659 | S24: 178.54918 | T24: 181.37653 | U24: 186.22255 | V24: 190.33916 | W24: 194.99503 | X24: 200.03682 | Y24: 205.30133 | Z24: 211.08353 | AA24: 217.31682 | AB24: 223.62242 | AC24: 229.46664 | AD24: 235.0215 | AE24: 239.40428 | AF24: 244.6778 | AG24: 0.011
A25: ISM000:fa_Resins | C25: Resin | D25: Synthetic Rubber | E25: and Fibers | F25: Industrial Macroeconomic: Manufacturing: Chemicals: Bulk Chemicals: Resin, Synthetic Rubber, and Fibers: Alternative Electricity and Transportation | G25: AEO.2026.ELECTRNP.ECI_VOS_MANF_CHEBR_NA_NA_NA_BLNY09DLR.A | H25: billion 2012 $ | I25: 112.3475 | J25: 111.06512 | K25: 112.16788 | L25: 110.21043 | M25: 109.01678 | N25: 110.27058 | O25: 111.02355 | P25: 110.38338 | Q25: 110.30038 | R25: 110.13205 | S25: 110.97907 | T25: 111.197 | U25: 113.11678 | V25: 114.37852 | W25: 115.73042 | X25: 117.6879 | Y25: 119.25335 | Z25: 121.62275 | AA25: 122.51125 | AB25: 123.04223 | AC25: 123.99895 | AD25: 125.265 | AE25: 127.58845 | AF25: 129.46645 | AG25: 130.94455 | AH25: 132.97212 | AI25: 0.007
A26: ISM000:fa_AgriculturalC | C26: Agricultural Chemicals | D26: Industrial Macroeconomic: Manufacturing: Chemicals: Bulk Chemicals: Agricultural Chemicals: Alternative Electricity and Transportation | E26: AEO.2026.ELECTRNP.ECI_VOS_MANF_AGC_NA_NA_NA_BLNY09DLR.A | F26: billion 2012 $ | G26: 41.439999 | H26: 41.469086 | I26: 41.946102 | J26: 41.806648 | K26: 41.845043 | L26: 42.168369 | M26: 42.538464 | N26: 42.695454 | O26: 42.950291 | P26: 43.226524 | Q26: 43.630913 | R26: 43.985401 | S26: 44.473221 | T26: 44.886093 | U26: 45.281067 | V26: 45.756378 | W26: 46.305859 | X26: 46.84927 | Y26: 47.365139 | Z26: 47.841415 | AA26: 48.536507 | AB26: 49.181259 | AC26: 49.868652 | AD26: 50.474846 | AE26: 50.942249 | AF26: 51.507961 | AG26: 0.009
A27: ISM000:fa_OtherChemical | C27: Other Chemical Products | D27: Industrial Macroeconomic: Manufacturing: Chemicals: Other Chemical Products: Alternative Electricity and Transportation | E27: AEO.2026.ELECTRNP.ECI_VOS_MANF_CHEO_NA_NA_NA_BLNY09DLR.A | F27: billion 2012 $ | G27: 476.23001 | H27: 480.27042 | I27: 475.83402 | J27: 474.00284 | K27: 472.61517 | L27: 471.9805 | M27: 472.31189 | N27: 475.85318 | O27: 481.87759 | P27: 487.47125 | Q27: 492.83328 | R27: 498.18185 | S27: 505.10187 | T27: 512.15088 | U27: 518.9129 | V27: 526.78571 | W27: 536.14111 | X27: 546.7782 | Y27: 558.09772 | Z27: 570.07965 | AA27: 582.72028 | AB27: 596.48151 | AC27: 610.55933 | AD27: 623.37824 | AE27: 637.10284 | AF27: 651.50915 | AG27: 0.013
A28: ISM000:fa_PetroleumandC | C28: Petroleum and Coal Products | D28: Industrial Macroeconomic: Manufacturing: Petroleum and Coal Products: Alternative Electricity and Transportation | E28: AEO.2026.ELECTRNP.ECI_VOS_MANF_PCL_NA_NA_NA_BLNY09DLR.A | F28: billion 2012 $ | G28: 812.46875 | H28: 815.59912 | I28: 814.62958 | J28: 812.44067 | K28: 805.56982 | L28: 801.77545 | M28: 797.0885 | N28: 795.29706 | O28: 793.849 | P28: 794.52423 | Q28: 795.7514 | R28: 793.12036 | S28: 787.33997 | T28: 781.7132 | U28: 778.87054 | V28: 777.97797 | W28: 779.20483 | X28: 777.89734 | Y28: 774.04761 | Z28: 769.80383 | AA28: 765.90613 | AB28: 766.34454 | AC28: 767.62952 | AD28: 764.87122 | AE28: 763.11072 | AF28: 762.69849 | AG28: -0.003
A29: ISM000:fa_PetroleumRefi | B29: ,ISIC 19, | C29: Petroleum Refineries | D29: Industrial Macroeconomic: Manufacturing: Petroleum and Coal: Petroleum Refineries: Alternative Electricity and Transportation | E29: AEO.2026.ELECTRNP.ECI_VOS_MANF_REF_NA_NA_NA_BLNY09DLR.A | F29: billion 2012 $ | G29: 774.53998 | H29: 777.53735 | I29: 776.06775 | J29: 773.3844 | K29: 766.23871 | L29: 762.01086 | M29: 756.96893 | N29: 754.9978 | O29: 753.4519 | P29: 754.0094 | Q29: 755.11731 | R29: 752.42364 | S29: 746.49103 | T29: 740.76801 | U29: 737.8125 | V29: 736.7052 | W29: 737.79657 | X29: 736.50989 | Y29: 732.66779 | Z29: 728.45471 | AA29: 724.67084 | AB29: 725.17279 | AC29: 726.47797 | AD29: 723.81842 | AE29: 722.17981 | AF29: 721.8551 | AG29: -0.003
A30: ISM000:fa_OtherPetroleu | B30: ,ISIC 241, | C30: Other Petroleum and Coal Products | D30: Industrial Macroeconomic: Manufacturing: Petroleum and Coal: Other Petroleum & Coal Products: Alternative Electricity and Transportation | E30: AEO.2026.ELECTRNP.ECI_VOS_MANF_PCLO_NA_NA_NA_BLNY09DLR.A | F30: billion 2012 $ | G30: 37.928802 | H30: 38.061752 | I30: 38.561806 | J30: 39.056305 | K30: 39.331112 | L30: 39.764568 | M30: 40.11956 | N30: 40.299236 | O30: 40.397125 | P30: 40.514839 | Q30: 40.634068 | R30: 40.696747 | S30: 40.848927 | T30: 40.945206 | U30: 41.058052 | V30: 41.272781 | W30: 41.408283 | X30: 41.387432 | Y30: 41.379841 | Z30: 41.349102 | AA30: 41.235302 | AB30: 41.17173 | AC30: 41.151543 | AD30: 41.052803 | AE30: 40.930908 | AF30: 40.843361 | AG30: 0.003
A31: ISM000:fa_RubberandMisc | B31: ,ISIC 22, | C31: Plastics and Rubber Products | D31: Industrial Macroeconomic: Manufacturing: Plastics and Rubber Products: Alternative Electricity and Transportation | E31: AEO.2026.ELECTRNP.ECI_VOS_MANF_PRP_NA_NA_NA_BLNY09DLR.A | F31: billion 2012 $ | G31: 216.0925 | H31: 214.8234 | I31: 219.6775 | J31: 222.33086 | K31: 223.29581 | L31: 225.64897 | M31: 228.33862 | N31: 229.98912 | O31: 231.52588 | P31: 232.55505 | Q31: 234.36923 | R31: 237.0793 | S31: 240.29485 | T31: 243.16901 | U31: 245.56535 | V31: 248.44893 | W31: 251.36266 | X31: 254.49283 | Y31: 257.41254 | Z31: 260.39548 | AA31: 263.66223 | AB31: 266.49383 | AC31: 269.10242 | AD31: 271.19577 | AE31: 274.12976 | AF31: 277.05692 | AG31: 0.01
A32: ISM000:fa_Stone,Clay,an | C32: Non-metallic minerals | D32: Industrial Macroeconomic: Manufacturing: Stone, Clay, and Glass Products: Alternative Electricity and Transportation | E32: AEO.2026.ELECTRNP.ECI_VOS_MANF_SCG_NA_NA_NA_BLNY09DLR.A | F32: billion 2012 $ | G32: 111.71762 | H32: 110.27509 | I32: 108.78667 | J32: 108.49378 | K32: 108.21488 | L32: 108.48045 | M32: 109.16854 | N32: 109.853 | O32: 110.82516 | P32: 111.88461 | Q32: 112.97219 | R32: 114.1003 | S32: 115.13226 | T32: 116.23027 | U32: 117.29462 | V32: 117.99434 | W32: 118.39089 | X32: 118.60862 | Y32: 118.44074 | Z32: 118.10147 | AA32: 118.49583 | AB32: 119.35685 | AC32: 120.24088 | AD32: 121.14365 | AE32: 122.01753 | AF32: 122.99197 | AG32: 0.004
A33: ISM000:fa_GlassandGlass | B33: ,ISIC 231, | C33: Glass and Glass Products | D33: Industrial Macroeconomic: Manufacturing: Stone, Clay, and Glass: Glass and Glass Products: Alternative Electricity and Transportation | E33: AEO.2026.ELECTRNP.ECI_VOS_MANF_SCGG_NA_NA_NA_BLNY09DLR.A | F33: billion 2012 $ | G33: 21.317434 | H33: 21.330378 | I33: 21.382898 | J33: 21.358 | K33: 21.324633 | L33: 21.333778 | M33: 21.370119 | N33: 21.456921 | O33: 21.599215 | P33: 21.778683 | Q33: 22.004484 | R33: 22.229578 | S33: 22.444937 | T33: 22.672058 | U33: 22.897127 | V33: 23.127674 | W33: 23.370462 | X33: 23.622248 | Y33: 23.883127 | Z33: 24.140699 | AA33: 24.406715 | AB33: 24.67695 | AC33: 24.94762 | AD33: 25.221365 | AE33: 25.484995 | AF33: 25.749542 | AG33: 0.008
A34: ISM000:fa_CementandHydr | B34: ,ISIC 239, | C34: Cement and Lime | D34: Industrial Macroeconomic: Manufacturing: Stone, Clay, and Glass: Cement and Lime: Alternative Electricity and Transportation | E34: AEO.2026.ELECTRNP.ECI_VOS_MANF_SCGCL_NA_NA_NA_BLNY09DLR.A | F34: billion 2012 $ | G34: 9.336027 | H34: 9.138749 | I34: 8.976787 | J34: 8.899744 | K34: 8.858376 | L34: 8.879111 | M34: 8.939971 | N34: 9.02407 | O34: 9.135289 | P34: 9.258553 | Q34: 9.389754 | R34: 9.524654 | S34: 9.657454 | T34: 9.793234 | U34: 9.925656 | V34: 10.036542 | W34: 10.121435 | X34: 10.178687 | Y34: 10.198941 | Z34: 10.195507 | AA34: 10.222628 | AB34: 10.289026 | AC34: 10.381219 | AD34: 10.489734 | AE34: 10.605895 | AF34: 10.7287 | AG34: 0.006
A35: ISM000:fa_OtherStone,Cl | B35: ,ISIC 239, | C35: Other Nonmetallic Mineral Products | D35: Industrial Macroeconomic: Manufacturing: Stone, Clay, and Glass: Other Nonmetallic Mineral Products: Alternative Electricity and Transportation | E35: AEO.2026.ELECTRNP.ECI_VOS_MANF_SCGOM_NA_NA_NA_BLNY09DLR.A | F35: billion 2012 $ | G35: 81.064156 | H35: 79.805962 | I35: 78.426987 | J35: 78.236038 | K35: 78.031876 | L35: 78.267563 | M35: 78.858452 | N35: 79.372017 | O35: 80.090652 | P35: 80.847382 | Q35: 81.57795 | R35: 82.346069 | S35: 83.029869 | T35: 83.764977 | U35: 84.47184 | V35: 84.830124 | W35: 84.898994 | X35: 84.807686 | Y35: 84.358673 | Z35: 83.765266 | AA35: 83.866486 | AB35: 84.390877 | AC35: 84.912033 | AD35: 85.432556 | AE35: 85.926636 | AF35: 86.513733 | AG35: 0.003
A36: ISM000:ga_PrimaryMetals | C36: Primary Metals Industry | D36: Industrial Macroeconomic: Manufacturing: Primary Metals Industry: Alternative Electricity and Transportation | E36: AEO.2026.ELECTRNP.ECI_VOS_MANF_PMM_NA_NA_NA_BLNY09DLR.A | F36: billion 2012 $ | G36: 246.75572 | H36: 250.08716 | I36: 255.74016 | J36: 255.59541 | K36: 257.12192 | L36: 260.64471 | M36: 263.58637 | N36: 267.5704 | O36: 271.29825 | P36: 273.56982 | Q36: 276.89011 | R36: 279.22003 | S36: 281.90106 | T36: 284.14255 | U36: 286.10419 | V36: 289.0296 | W36: 292.31088 | X36: 295.6189 | Y36: 298.47379 | Z36: 301.26617 | AA36: 305.13907 | AB36: 308.23111 | AC36: 311.82584 | AD36: 314.93536 | AE36: 316.96918 | AF36: 319.74112 | AG36: 0.01
A37: ISM000:ga_BlastFurnacea | B37: ,ISIC 241, | C37: Iron and Steel Mills and Products | D37: Industrial Macroeconomic: Manufacturing: Primary Metals: Iron and Steel Mills and Products: Alternative Electricity and Transportation | E37: AEO.2026.ELECTRNP.ECI_VOS_MANF_ISM_NA_NA_NA_BLNY09DLR.A | F37: billion 2012 $ | G37: 133.18527 | H37: 136.57104 | I37: 141.48924 | J37: 140.72696 | K37: 141.82077 | L37: 144.79961 | M37: 147.15262 | N37: 150.40752 | O37: 153.23759 | P37: 154.47896 | Q37: 156.599 | R37: 157.66631 | S37: 159.09126 | T37: 160.06988 | U37: 160.77774 | V37: 162.43938 | W37: 164.43352 | X37: 166.44513 | Y37: 168.00439 | Z37: 169.521 | AA37: 172.14064 | AB37: 174.01265 | AC37: 176.44012 | AD37: 178.45138 | AE37: 179.46309 | AF37: 181.26073 | AG37: 0.012
A38: ISM000:ga_Aluminum | B38: ,ISIC 242, | C38: Alumina and Aluminum Products | D38: Industrial Macroeconomic: Manufacturing: Primary Metals: Alumina and Aluminum Products: Alternative Electricity and Transportation | E38: AEO.2026.ELECTRNP.ECI_VOS_MANF_AAP_NA_NA_NA_BLNY09DLR.A | F38: billion 2012 $ | G38: 34.303463 | H38: 34.704796 | I38: 35.137936 | J38: 35.538319 | K38: 35.894688 | L38: 36.223057 | M38: 36.590855 | N38: 37.023113 | O38: 37.529774 | P38: 38.114296 | Q38: 38.792519 | R38: 39.503159 | S38: 40.215851 | T38: 40.931011 | U38: 41.635021 | V38: 42.331554 | W38: 43.032452 | X38: 43.73204 | Y38: 44.414871 | Z38: 45.054203 | AA38: 45.637836 | AB38: 46.167351 | AC38: 46.650509 | AD38: 47.085503 | AE38: 47.473671 | AF38: 47.835384 | AG38: 0.013
A39: ISM000:ga_OtherPrimaryM | B39: ,ISIC 242, | C39: Other Primary Metal Products | D39: Industrial Macroeconomic: Manufacturing: Primary Metals: Other Primary Metal Products: Alternative Electricity and Transportation | E39: AEO.2026.ELECTRNP.ECI_VOS_MANF_PMO_NA_NA_NA_BLNY09DLR.A | F39: billion 2012 $ | G39: 79.266983 | H39: 78.811302 | I39: 79.112976 | J39: 79.330147 | K39: 79.406471 | L39: 79.622047 | M39: 79.842896 | N39: 80.139786 | O39: 80.530861 | P39: 80.976562 | Q39: 81.498573 | R39: 82.050552 | S39: 82.593948 | T39: 83.141647 | U39: 83.691399 | V39: 84.258675 | W39: 84.844894 | X39: 85.441742 | Y39: 86.05452 | Z39: 86.690979 | AA39: 87.360611 | AB39: 88.051102 | AC39: 88.735176 | AD39: 89.398453 | AE39: 90.03241 | AF39: 90.644989 | AG39: 0.005
A40: ISM000:ga_FabricatedMet | B40: ,ISIC 25, | C40: Fabricated Metal Products | D40: Industrial Macroeconomic: Manufacturing: Fabricated Metal Products: Alternative Electricity and Transportation | E40: AEO.2026.ELECTRNP.ECI_VOS_MANF_FBP_NA_NA_NA_BLNY09DLR.A | F40: billion 2012 $ | G40: 310.26749 | H40: 316.87705 | I40: 322.38943 | J40: 319.58441 | K40: 318.39221 | L40: 318.3259 | M40: 318.72214 | N40: 321.75366 | O40: 324.08569 | P40: 328.129 | Q40: 332.0043 | R40: 334.63113 | S40: 337.58502 | T40: 341.10525 | U40: 343.53482 | V40: 346.93414 | W40: 350.07004 | X40: 353.55838 | Y40: 357.13855 | Z40: 362.2135 | AA40: 367.13599 | AB40: 371.48428 | AC40: 373.76889 | AD40: 375.0892 | AE40: 379.121 | AF40: 382.78116 | AG40: 0.008
A41: ISM000:ga_IndustrialMac | B41: ,ISIC 28, | C41: Machinery | D41: Industrial Macroeconomic: Manufacturing: Machinery: Alternative Electricity and Transportation | E41: AEO.2026.ELECTRNP.ECI_VOS_MANF_MCHI_NA_NA_NA_BLNY09DLR.A | F41: billion 2012 $ | G41: 305.26001 | H41: 299.01385 | I41: 306.22296 | J41: 311.98895 | K41: 318.05756 | L41: 322.15585 | M41: 328.44147 | N41: 333.77564 | O41: 334.12036 | P41: 336.71985 | Q41: 341.10483 | R41: 344.25717 | S41: 346.36883 | T41: 347.21533 | U41: 347.32306 | V41: 348.83164 | W41: 350.16537 | X41: 351.42816 | Y41: 352.08035 | Z41: 352.5993 | AA41: 353.70801 | AB41: 355.37061 | AC41: 357.26349 | AD41: 358.30631 | AE41: 358.59338 | AF41: 358.35907 | AG41: 0.006
A42: ISM000:ga_Electronicand | B42: ,ISIC 26, | C42: Computers and Electronics | D42: Industrial Macroeconomic: Manufacturing: Computers and Electronics: Alternative Electricity and Transportation | E42: AEO.2026.ELECTRNP.ECI_VOS_MANF_CMPEL_NA_NA_NA_BLNY09DLR.A | F42: billion 2012 $ | G42: 411.20252 | H42: 415.517 | I42: 431.08682 | J42: 441.41235 | K42: 452.64929 | L42: 461.90463 | M42: 469.32001 | N42: 478.32999 | O42: 484.94519 | P42: 493.50339 | Q42: 503.60901 | R42: 513.61682 | S42: 524.40851 | T42: 535.19141 | U42: 546.87024 | V42: 559.02667 | W42: 570.98047 | X42: 583.86047 | Y42: 597.45813 | Z42: 612.4939 | AA42: 628.37769 | AB42: 645.09314 | AC42: 661.21069 | AD42: 677.41119 | AE42: 693.93957 | AF42: 708.70209 | AG42: 0.022
A43: ISM000:ga_Transportatio | B43: ,ISIC 29,ISIC 302T309, | C43: Transportation Equipment | D43: Industrial Macroeconomic: Manufacturing: Transportation Equipment: Alternative Electricity and Transportation | E43: AEO.2026.ELECTRNP.ECI_VOS_MANF_TEQ_NA_NA_NA_BLNY09DLR.A | F43: billion 2012 $ | G43: 1002.355 | H43: 1005.3 | I43: 1068.975 | J43: 1089.9318 | K43: 1107.297 | L43: 1125.724 | M43: 1133.2688 | N43: 1151.2688 | O43: 1159.2283 | P43: 1162.537 | Q43: 1167.0085 | R43: 1179.002 | S43: 1203.2567 | T43: 1225.7577 | U43: 1248.693 | V43: 1269.9425 | W43: 1288.6895 | X43: 1307.5587 | Y43: 1324.1825 | Z43: 1341.2595 | AA43: 1359.183 | AB43: 1376.2032 | AC43: 1391.7977 | AD43: 1407.7498 | AE43: 1422.3308 | AF43: 1434.1357 | AG43: 0.014
A44: ISM000:ga_Instrumentsan | B44: ,ISIC 27, | C44: Electrical Equipment | D44: Industrial Macroeconomic: Manufacturing: Electrical Equipment: Alternative Electricity and Transportation | E44: AEO.2026.ELECTRNP.ECI_VOS_MANF_EEQ_NA_NA_NA_BLNY09DLR.A | F44: billion 2012 $ | G44: 118.2975 | H44: 116.73825 | I44: 116.09667 | J44: 114.2786 | K44: 113.85622 | L44: 115.90938 | M44: 117.77843 | N44: 119.75828 | O44: 120.4133 | P44: 120.94665 | Q44: 122.24272 | R44: 123.16823 | S44: 124.02395 | T44: 124.64645 | U44: 125.23923 | V44: 126.064 | W44: 126.7776 | X44: 127.61202 | Y44: 128.32378 | Z44: 129.0089 | AA44: 129.82159 | AB44: 130.85539 | AC44: 131.88008 | AD44: 132.77362 | AE44: 133.50012 | AF44: 134.00803 | AG44: 0.005
A45: ISM000:ga_Miscellaneous | B45: ,ISIC 31T33, | C45: Miscellaneous Manufacturing | D45: Industrial Macroeconomic: Manufacturing: Miscellaneous Manufacturing: Alternative Electricity and Transportation | E45: AEO.2026.ELECTRNP.ECI_VOS_MANF_MISC_NA_NA_NA_BLNY09DLR.A | F45: billion 2012 $ | G45: 144.9075 | H45: 145.35612 | I45: 149.45869 | J45: 152.8595 | K45: 155.88032 | L45: 159.69968 | M45: 164.2225 | N45: 165.36556 | O45: 164.92943 | P45: 163.96925 | Q45: 163.58032 | R45: 164.35375 | S45: 165.49033 | T45: 166.50532 | U45: 166.7278 | V45: 167.80901 | W45: 168.99103 | X45: 169.76718 | Y45: 170.3938 | Z45: 171.00638 | AA45: 171.54739 | AB45: 172.19408 | AC45: 172.57062 | AD45: 172.60996 | AE45: 174.43875 | AF45: 173.48642 | AG45: 0.007
A46: ISM000:ha_TotalIndustri | C46: Total Industrial Value of Shipments | D46: Industrial Macroeconomic: Total Industrial Value of Shipments: Alternative Electricity and Transportation | E46: AEO.2026.ELECTRNP.ECI_VOS_IDAL_NA_NA_NA_NA_BLNY09DLR.A | F46: billion 2012 $ | G46: 8703.1973 | H46: 8752.5645 | I46: 8860.0869 | J46: 8925.21 | K46: 8996.9707 | L46: 9096.0107 | M46: 9180.3877 | N46: 9280.9062 | O46: 9357.7588 | P46: 9436.4336 | Q46: 9520.167 | R46: 9604.2969 | S46: 9697.3643 | T46: 9786.8838 | U46: 9878.123 | V46: 9974.8262 | W46: 10069.032 | X46: 10166.396 | Y46: 10253.317 | Z46: 10343.383 | AA46: 10450.387 | AB46: 10563.197 | AC46: 10674.791 | AD46: 10773.288 | AE46: 10876.104 | AF46: 10975.349 | AG46: 0.009

Sheet g2025 derivation
A1: 2024->2025 output growth per code, derived LIVE from the raw sources (same machinery as the BPCiObIC workbook). Row 4 = BLS compound rate; row 5 = AEO 2025 rate (2026-edition ELECTRNP vs 2025-edition HIGHZTC base-year splice); row 6 = g2025.
A2: f2025 (2025 GDP-fit factor — the ONE imported number; from the BPCiObIC workbook 'Rescale to Fit GDP Proj' row 5, col D. Repaste on BPCiObIC source updates.) | B2: 0.91577978
A3: ISIC | B3: ISIC 01 | C3: ISIC 02 | D3: ISIC 03 | E3: ISIC 05 | F3: ISIC 06 | G3: ISIC 07 | H3: ISIC 08 | I3: ISIC 09 | J3: ISIC 10T12 | K3: ISIC 13T15 | L3: ISIC 16 | M3: ISIC 17T18 | N3: ISIC 19 | O3: ISIC 20 | P3: ISIC 21 | Q3: ISIC 22 | R3: ISIC 231 | S3: ISIC 239 | T3: ISIC 241 | U3: ISIC 242 | V3: ISIC 25 | W3: ISIC 26 | X3: ISIC 27 | Y3: ISIC 28 | Z3: ISIC 29 | AA3: ISIC 301 | AB3: ISIC 302T309 | AC3: ISIC 31T33 | AD3: ISIC 351 | AE3: ISIC 352T353 | AF3: ISIC 36T39 | AG3: ISIC 41T43 | AH3: ISIC 45T47 | AI3: ISIC 49 | AJ3: ISIC 50 | AK3: ISIC 51 | AL3: ISIC 52 | AM3: ISIC 53 | AN3: ISIC 55T56 | AO3: ISIC 58T60 | AP3: ISIC 61 | AQ3: ISIC 62T63 | AR3: ISIC 64T66 | AS3: ISIC 68 | AT3: ISIC 69T75 | AU3: ISIC 77T82 | AV3: ISIC 84 | AW3: ISIC 85 | AX3: ISIC 86T88 | AY3: ISIC 90T93 | AZ3: ISIC 94T96 | BA3: ISIC 97T98
A4: BLS compound rate | B4: =IFERROR(SUMPRODUCT(--('BLS Table 2.11'!$L$1:$L$426=B$3),'BLS Table 2.11'!$J$1:$J$426,'BLS Table 2.11'!$K$1:$K$426)/SUMIFS('BLS Table 2.11'!$J$1:$J$426,'BLS Table 2.11'!$L$1:$L$426,B$3)/100,0) -> 0.019584221 | C4: =IFERROR(SUMPRODUCT(--('BLS Table 2.11'!$L$1:$L$426=C$3),'BLS Table 2.11'!$J$1:$J$426,'BLS Table 2.11'!$K$1:$K$426)/SUMIFS('BLS Table 2.11'!$J$1:$J$426,'BLS Table 2.11'!$L$1:$L$426,C$3)/100,0) -> 0.016 | D4: =IFERROR(SUMPRODUCT(--('BLS Table 2.11'!$L$1:$L$426=D$3),'BLS Table 2.11'!$J$1:$J$426,'BLS Table 2.11'!$K$1:$K$426)/SUMIFS('BLS Table 2.11'!$J$1:$J$426,'BLS Table 2.11'!$L$1:$L$426,D$3)/100,0) -> 0.015 | E4: =IFERROR(SUMPRODUCT(--('BLS Table 2.11'!$L$1:$L$426=E$3),'BLS Table 2.11'!$J$1:$J$426,'BLS Table 2.11'!$K$1:$K$426)/SUMIFS('BLS Table 2.11'!$J$1:$J$426,'BLS Table 2.11'!$L$1:$L$426,E$3)/100,0) -> -0.019 | F4: =IFERROR(SUMPRODUCT(--('BLS Table 2.11'!$L$1:$L$426=F$3),'BLS Table 2.11'!$J$1:$J$426,'BLS Table 2.11'!$K$1:$K$426)/SUMIFS('BLS Table 2.11'!$J$1:$J$426,'BLS Table 2.11'!$L$1:$L$426,F$3)/100,0) -> 0.016 | G4: =IFERROR(SUMPRODUCT(--('BLS Table 2.11'!$L$1:$L$426=G$3),'BLS Table 2.11'!$J$1:$J$426,'BLS Table 2.11'!$K$1:$K$426)/SUMIFS('BLS Table 2.11'!$J$1:$J$426,'BLS Table 2.11'!$L$1:$L$426,G$3)/100,0) -> 0.026 | H4: =IFERROR(SUMPRODUCT(--('BLS Table 2.11'!$L$1:$L$426=H$3),'BLS Table 2.11'!$J$1:$J$426,'BLS Table 2.11'!$K$1:$K$426)/SUMIFS('BLS Table 2.11'!$J$1:$J$426,'BLS Table 2.11'!$L$1:$L$426,H$3)/100,0) -> 0.012 | I4: =IFERROR(SUMPRODUCT(--('BLS Table 2.11'!$L$1:$L$426=I$3),'BLS Table 2.11'!$J$1:$J$426,'BLS Table 2.11'!$K$1:$K$426)/SUMIFS('BLS Table 2.11'!$J$1:$J$426,'BLS Table 2.11'!$L$1:$L$426,I$3)/100,0) -> -0.005 | ... BA4: =IFERROR(SUMPRODUCT(--('BLS Table 2.11'!$L$1:$L$426=BA$3),'BLS Table 2.11'!$J$1:$J$426,'BLS Table 2.11'!$K$1:$K$426)/SUMIFS('BLS Table 2.11'!$J$1:$J$426,'BLS Table 2.11'!$L$1:$L$426,BA$3)/100,0) -> 0.018
A5: AEO 2025 rate | B5: =IFERROR((SUMIFS('AEO 2026 Table 23 '!G:G,'AEO 2026 Table 23 '!$B:$B,"*,"&B$3&",*")-SUMIFS('AEO25 Table 23'!H:H,'AEO25 Table 23'!$B:$B,"*,"&B$3&",*"))/SUMIFS('AEO25 Table 23'!H:H,'AEO25 Table 23'!$B:$B,"*,"&B$3&",*"),"") -> -0.099246442 | C5: =IFERROR((SUMIFS('AEO 2026 Table 23 '!G:G,'AEO 2026 Table 23 '!$B:$B,"*,"&C$3&",*")-SUMIFS('AEO25 Table 23'!H:H,'AEO25 Table 23'!$B:$B,"*,"&C$3&",*"))/SUMIFS('AEO25 Table 23'!H:H,'AEO25 Table 23'!$B:$B,"*,"&C$3&",*"),"") | D5: =IFERROR((SUMIFS('AEO 2026 Table 23 '!G:G,'AEO 2026 Table 23 '!$B:$B,"*,"&D$3&",*")-SUMIFS('AEO25 Table 23'!H:H,'AEO25 Table 23'!$B:$B,"*,"&D$3&",*"))/SUMIFS('AEO25 Table 23'!H:H,'AEO25 Table 23'!$B:$B,"*,"&D$3&",*"),"") | E5: =IFERROR((SUMIFS('AEO 2026 Table 23 '!G:G,'AEO 2026 Table 23 '!$B:$B,"*,"&E$3&",*")-SUMIFS('AEO25 Table 23'!H:H,'AEO25 Table 23'!$B:$B,"*,"&E$3&",*"))/SUMIFS('AEO25 Table 23'!H:H,'AEO25 Table 23'!$B:$B,"*,"&E$3&",*"),"") -> 0.071210619 | F5: =IFERROR((SUMIFS('AEO 2026 Table 23 '!G:G,'AEO 2026 Table 23 '!$B:$B,"*,"&F$3&",*")-SUMIFS('AEO25 Table 23'!H:H,'AEO25 Table 23'!$B:$B,"*,"&F$3&",*"))/SUMIFS('AEO25 Table 23'!H:H,'AEO25 Table 23'!$B:$B,"*,"&F$3&",*"),"") -> 0.071210619 | G5: =IFERROR((SUMIFS('AEO 2026 Table 23 '!G:G,'AEO 2026 Table 23 '!$B:$B,"*,"&G$3&",*")-SUMIFS('AEO25 Table 23'!H:H,'AEO25 Table 23'!$B:$B,"*,"&G$3&",*"))/SUMIFS('AEO25 Table 23'!H:H,'AEO25 Table 23'!$B:$B,"*,"&G$3&",*"),"") | H5: =IFERROR((SUMIFS('AEO 2026 Table 23 '!G:G,'AEO 2026 Table 23 '!$B:$B,"*,"&H$3&",*")-SUMIFS('AEO25 Table 23'!H:H,'AEO25 Table 23'!$B:$B,"*,"&H$3&",*"))/SUMIFS('AEO25 Table 23'!H:H,'AEO25 Table 23'!$B:$B,"*,"&H$3&",*"),"") -> 0.071210619 | I5: =IFERROR((SUMIFS('AEO 2026 Table 23 '!G:G,'AEO 2026 Table 23 '!$B:$B,"*,"&I$3&",*")-SUMIFS('AEO25 Table 23'!H:H,'AEO25 Table 23'!$B:$B,"*,"&I$3&",*"))/SUMIFS('AEO25 Table 23'!H:H,'AEO25 Table 23'!$B:$B,"*,"&I$3&",*"),"") | ... BA5: =IFERROR((SUMIFS('AEO 2026 Table 23 '!G:G,'AEO 2026 Table 23 '!$B:$B,"*,"&BA$3&",*")-SUMIFS('AEO25 Table 23'!H:H,'AEO25 Table 23'!$B:$B,"*,"&BA$3&",*"))/SUMIFS('AEO25 Table 23'!H:H,'AEO25 Table 23'!$B:$B,"*,"&BA$3&",*"),"")
A6: g2025 | B6: =IF(B5="",B4*$B$2,B5) -> -0.099246442 | C6: =IF(C5="",C4*$B$2,C5) -> 0.014652477 | D6: =IF(D5="",D4*$B$2,D5) -> 0.013736697 | E6: =IF(E5="",E4*$B$2,E5) -> 0.071210619 | F6: =IF(F5="",F4*$B$2,F5) -> 0.071210619 | G6: =IF(G5="",G4*$B$2,G5) -> 0.023810274 | H6: =IF(H5="",H4*$B$2,H5) -> 0.071210619 | I6: =IF(I5="",I4*$B$2,I5) -> -0.0045788989 | ... BA6: =IF(BA5="",BA4*$B$2,BA5) -> 0.016484036

Sheet Calculations
A1: Per-code 2024 gross output (millions, 2024 USD)
A2: ISIC | B2: ISIC 01 | C2: ISIC 02 | D2: ISIC 03 | E2: ISIC 05 | F2: ISIC 06 | G2: ISIC 07 | H2: ISIC 08 | I2: ISIC 09 | J2: ISIC 10T12 | K2: ISIC 13T15 | L2: ISIC 16 | M2: ISIC 17T18 | N2: ISIC 19 | O2: ISIC 20 | P2: ISIC 21 | Q2: ISIC 22 | R2: ISIC 231 | S2: ISIC 239 | T2: ISIC 241 | U2: ISIC 242 | V2: ISIC 25 | W2: ISIC 26 | X2: ISIC 27 | Y2: ISIC 28 | Z2: ISIC 29 | AA2: ISIC 301 | AB2: ISIC 302T309 | AC2: ISIC 31T33 | AD2: ISIC 351 | AE2: ISIC 352T353 | AF2: ISIC 36T39 | AG2: ISIC 41T43 | AH2: ISIC 45T47 | AI2: ISIC 49 | AJ2: ISIC 50 | AK2: ISIC 51 | AL2: ISIC 52 | AM2: ISIC 53 | AN2: ISIC 55T56 | AO2: ISIC 58T60 | AP2: ISIC 61 | AQ2: ISIC 62T63 | AR2: ISIC 64T66 | AS2: ISIC 68 | AT2: ISIC 69T75 | AU2: ISIC 77T82 | AV2: ISIC 84 | AW2: ISIC 85 | AX2: ISIC 86T88 | AY2: ISIC 90T93 | AZ2: ISIC 94T96 | BA2: ISIC 97T98
A3: sum | B3: =SUMIFS('2024 Data'!$C$4:$C$417,'2024 Data'!$E$4:$E$417,B2) -> 597715 | C3: =SUMIFS('2024 Data'!$C$4:$C$417,'2024 Data'!$E$4:$E$417,C2) -> 26473 | D3: =SUMIFS('2024 Data'!$C$4:$C$417,'2024 Data'!$E$4:$E$417,D2) -> 9657 | E3: =SUMIFS('2024 Data'!$C$4:$C$417,'2024 Data'!$E$4:$E$417,E2) -> 46019 | F3: =SUMIFS('2024 Data'!$C$4:$C$417,'2024 Data'!$E$4:$E$417,F2) -> 455994 | G3: =SUMIFS('2024 Data'!$C$4:$C$417,'2024 Data'!$E$4:$E$417,G2) -> 40605 | H3: =SUMIFS('2024 Data'!$C$4:$C$417,'2024 Data'!$E$4:$E$417,H2) -> 53228 | I3: =SUMIFS('2024 Data'!$C$4:$C$417,'2024 Data'!$E$4:$E$417,I2) -> 110561 | ... BA3: =SUMIFS('2024 Data'!$C$4:$C$417,'2024 Data'!$E$4:$E$417,BA2) -> 27382

Sheet Checks
A1: Validation checks
A3: Unassigned output (2024 value but no ISIC code) — should be 0
B4: =SUMIFS('2024 Data'!$C$4:$C$417,'2024 Data'!$E$4:$E$417,"") -> 0 | C4: =IF(B4=0,"PASS","INSPECT") -> PASS
A6: Coverage: per-code totals = assigned rows total
B7: =SUM(Calculations!B3:BA3)-(SUM('2024 Data'!$C$4:$C$417)-B4) -> 0 | C7: =IF(ABS(B7)<0.01,"PASS","FAIL") -> PASS
A9: BObIC/SYObIC economy growth (should be ~2%)
B10: =SUM(BObIC!B2:BA2)/SUM(SYObIC!B2:BA2)-1 -> 0.015981174

Sheet SYObIC
A1: Unit: USD | B1: ISIC 01 | C1: ISIC 02 | D1: ISIC 03 | E1: ISIC 05 | F1: ISIC 06 | G1: ISIC 07 | H1: ISIC 08 | I1: ISIC 09 | J1: ISIC 10T12 | K1: ISIC 13T15 | L1: ISIC 16 | M1: ISIC 17T18 | N1: ISIC 19 | O1: ISIC 20 | P1: ISIC 21 | Q1: ISIC 22 | R1: ISIC 231 | S1: ISIC 239 | T1: ISIC 241 | U1: ISIC 242 | V1: ISIC 25 | W1: ISIC 26 | X1: ISIC 27 | Y1: ISIC 28 | Z1: ISIC 29 | AA1: ISIC 301 | AB1: ISIC 302T309 | AC1: ISIC 31T33 | AD1: ISIC 351 | AE1: ISIC 352T353 | AF1: ISIC 36T39 | AG1: ISIC 41T43 | AH1: ISIC 45T47 | AI1: ISIC 49 | AJ1: ISIC 50 | AK1: ISIC 51 | AL1: ISIC 52 | AM1: ISIC 53 | AN1: ISIC 55T56 | AO1: ISIC 58T60 | AP1: ISIC 61 | AQ1: ISIC 62T63 | AR1: ISIC 64T66 | AS1: ISIC 68 | AT1: ISIC 69T75 | AU1: ISIC 77T82 | AV1: ISIC 84 | AW1: ISIC 85 | AX1: ISIC 86T88 | AY1: ISIC 90T93 | AZ1: ISIC 94T96 | BA1: ISIC 97T98
A2: Output | B2: =Calculations!B3*10^6*About!$A$20 -> 4.3747718e+11 | C2: =Calculations!C3*10^6*About!$A$20 -> 1.9376012e+10 | D2: =Calculations!D3*10^6*About!$A$20 -> 7.0681129e+09 | E2: =Calculations!E3*10^6*About!$A$20 -> 3.3682043e+10 | F2: =Calculations!F3*10^6*About!$A$20 -> 3.3374931e+11 | G2: =Calculations!G3*10^6*About!$A$20 -> 2.9719449e+10 | H2: =Calculations!H3*10^6*About!$A$20 -> 3.8958425e+10 | I2: =Calculations!I3*10^6*About!$A$20 -> 8.0921366e+10 | ... BA2: =Calculations!BA3*10^6*About!$A$20 -> 2.0041324e+10

Sheet BObIC
A1: Unit: USD | B1: ISIC 01 | C1: ISIC 02 | D1: ISIC 03 | E1: ISIC 05 | F1: ISIC 06 | G1: ISIC 07 | H1: ISIC 08 | I1: ISIC 09 | J1: ISIC 10T12 | K1: ISIC 13T15 | L1: ISIC 16 | M1: ISIC 17T18 | N1: ISIC 19 | O1: ISIC 20 | P1: ISIC 21 | Q1: ISIC 22 | R1: ISIC 231 | S1: ISIC 239 | T1: ISIC 241 | U1: ISIC 242 | V1: ISIC 25 | W1: ISIC 26 | X1: ISIC 27 | Y1: ISIC 28 | Z1: ISIC 29 | AA1: ISIC 301 | AB1: ISIC 302T309 | AC1: ISIC 31T33 | AD1: ISIC 351 | AE1: ISIC 352T353 | AF1: ISIC 36T39 | AG1: ISIC 41T43 | AH1: ISIC 45T47 | AI1: ISIC 49 | AJ1: ISIC 50 | AK1: ISIC 51 | AL1: ISIC 52 | AM1: ISIC 53 | AN1: ISIC 55T56 | AO1: ISIC 58T60 | AP1: ISIC 61 | AQ1: ISIC 62T63 | AR1: ISIC 64T66 | AS1: ISIC 68 | AT1: ISIC 69T75 | AU1: ISIC 77T82 | AV1: ISIC 84 | AW1: ISIC 85 | AX1: ISIC 86T88 | AY1: ISIC 90T93 | AZ1: ISIC 94T96 | BA1: ISIC 97T98
A2: Output | B2: =SYObIC!B2*(1+'g2025 derivation'!B$6) -> 3.9405912e+11 | C2: =SYObIC!C2*(1+'g2025 derivation'!C$6) -> 1.9659919e+10 | D2: =SYObIC!D2*(1+'g2025 derivation'!D$6) -> 7.1652054e+09 | E2: =SYObIC!E2*(1+'g2025 derivation'!E$6) -> 3.6080562e+10 | F2: =SYObIC!F2*(1+'g2025 derivation'!F$6) -> 3.575158e+11 | G2: =SYObIC!G2*(1+'g2025 derivation'!G$6) -> 3.0427078e+10 | H2: =SYObIC!H2*(1+'g2025 derivation'!H$6) -> 4.1732679e+10 | I2: =SYObIC!I2*(1+'g2025 derivation'!I$6) -> 8.0550835e+10 | ... BA2: =SYObIC!BA2*(1+'g2025 derivation'!BA$6) -> 2.0371686e+10
