Workbook

Sheet About
A1: COSP Cost of Service vs Procurement Shares (2024)
A3: Sources: | B3: Retail electricity sales by serving entity (utility / marketer / CCA)
B4: U.S. Energy Information Administration (EIA)
B5: Form EIA-861 detailed data, Sales_Ult_Cust_2024.xlsx (sheet 'States')
B6: 2024
B7: https://www.eia.gov/electricity/data/eia861/
B8: Authoritative source from which EIA's published Table 10 (utility bundled sales) and Table 16 (power marketers) are built. 'Service Type' = Bundled / Energy / Delivery; 'Ownership' = Investor Owned, Municipal, Cooperative, Federal, State, Political Subdivision, Retail Power Marketer, Community Choice Aggregator, Behind the Meter. TOTAL sales (MWh) is column W.
B10: Validation benchmark — published state retail sales (all sectors)
B11: U.S. Energy Information Administration (EIA)
B12: EIA API v2, electricity/retail-sales
B13: 2024
B14: https://www.eia.gov/opendata/
B15: Used by validate_against_eia.py. The detailed file (Bundled+Energy incl. EIA Adjustment rows) ties to these published state totals to within 0.00%.
A18: Notes:
A19: Question | B19: Share of each state's retail electricity sales served by cost-of-service providers (embedded-cost recovery) vs. procurement-based providers, attributed by the entity that sells to the retail customer (LSE-based).
A20: Double-count fix | B20: Retail total = rows with Service Type Bundled or Energy. 'Delivery' rows are the wires-only half of choice-state load already counted under 'Energy'; they are classified 'excluded' so they never enter the totals (including Delivery would overstate sales ~14% nationally).
A21: Cost-of-service | B21: Bundled sales of municipals, cooperatives, federal, state, and political-subdivision utilities, plus Investor Owned utilities in states NOT on the restructured list (and the TX override utilities below).
A22: Procurement | B22: Retail Power Marketers + Community Choice Aggregators (and any 'Energy' service-type sales), plus Investor Owned utilities in restructured states.
A23: Restructured states | B23: Editable on the Parameters tab (column A). Baseline: CT, DC, DE, IL, MA, MD, ME, NH, NJ, NY, OH, PA, RI, TX.
A24: Texas override | B24: Non-ERCOT, vertically integrated, regulated TX IOUs are held as cost-of-service despite TX being restructured. Keyed on EIA Utility Number (Parameters column B): 55937 Entergy Texas, 17718 Southwestern Public Service, 17698 Southwestern Electric Power, 5701 El Paso Electric. ERCOT wires-only IOUs carry zero bundled sales, so they need no override.
A25: Exclusions | B25: EIA 'Adjustment' reconciliation rows (utility name contains 'Adjustment') and 'Behind the Meter' ownership are classified 'excluded' (~3.5% of US load). They are visible in the source tab but kept out of the share basis.
A26: How it computes | B26: Source tab column 'bucket' classifies each row via formula reading the Parameters tab (COUNTIF on the restructured-state and override-utility ranges). 'State Shares' and 'US National' use SUMIFS over that bucket column. Edit a Parameters cell -> all outputs recompute.
A27: Method precedent | B27: EPA's Retail Price Model (ICF) uses the same approach: blend a competitive price and a cost-of-service price by each region's deregulation vs. cost-of-service share. See EXTERNAL_VALIDATION.md.
A28: EPS usage (SoEDtICoS) | B28: In the EPS, total electricity rates = cost-of-service costs x (share that is cost of service) + capacity-market costs x (1 - that share). The 'SoEDtICoS' tab supplies that share to eps-us, held flat at the latest data-year value across 2021-2050.
A29: This rebuild | B29: This SoEDtICoS file was rebuilt from EIA-861, replacing the prior version (EPA Retail Price Model regional shares x AEO net-load weighting) with the EIA-861 LSE-based national cost-of-service share.
A30: Caveat | B30: Output is an input for analysis; verify against EIA primary sources. The restructured-state list and TX overrides are adjustable assumptions.

Sheet Parameters
A1: Parameters (editable — outputs recompute)
A3: Fully Restructured States | B3: Override Utility # | C3: Override Utility Name (reference)
A4: CT | B4: 55937 | C4: Entergy Texas Inc.
A5: DC | B5: 17718 | C5: Southwestern Public Service Co
A6: DE | B6: 17698 | C6: Southwestern Electric Power Co
A7: IL | B7: 5701 | C7: El Paso Electric Co
A8: MA
A9: MD
A10: ME
A11: NH
A12: NJ
A13: NY
A14: OH
A15: PA
A16: RI
A17: TX
A20: Ownership classes (fixed EIA taxonomy, hardcoded in the bucket formula):
A21: Procurement: Retail Power Marketer, Community Choice Aggregator. Cost-of-service (non-IOU): Municipal, Cooperative, Federal, State, Political Subdivision. Excluded: Behind the Meter, Adjustment rows.

Sheet EIA-861 Sales 2024
A1: Utility Characteristics | J1: RESIDENTIAL | M1: COMMERCIAL | P1: INDUSTRIAL | S1: TRANSPORTATION | V1: TOTAL
J2: Revenues | K2: Sales | L2: Customers | M2: Revenues | N2: Sales | O2: Customers | P2: Revenues | Q2: Sales | R2: Customers | S2: Revenues | T2: Sales | U2: Customers | V2: Revenues | W2: Sales | X2: Customers
A3: Data Year | B3: Utility Number | C3: Utility Name | D3: Part | E3: Service Type | F3: Data Type O = Observed I = Imputed | G3: State | H3: Ownership | I3: BA Code | J3: Thousand Dollars | K3: Megawatthours | L3: Count | M3: Thousand Dollars | N3: Megawatthours | O3: Count | P3: Thousand Dollars | Q3: Megawatthours | R3: Count | S3: Thousand Dollars | T3: Megawatthours | U3: Count | V3: Thousand Dollars | W3: Megawatthours | X3: Count | Y3: sales_mwh (derived) | Z3: bucket (derived)
A4: 2024 | B4: 55 | C4: City of Aberdeen - (MS) | D4: A | E4: Bundled | F4: O | G4: MS | H4: Municipal | I4: TVA | J4: 4211 | K4: 34239 | L4: 2592 | M4: 3550 | N4: 29391 | O4: 736 | P4: 7185 | Q4: 127260 | R4: 2 | S4: 0 | T4: 0 | U4: 0 | V4: 14946 | W4: 190890 | X4: 3330 | Y4: =IF(ISNUMBER($W4),$W4,0) -> 190890 | Z4: =IF(ISNUMBER(SEARCH("Adjustment",$C4)),"excluded",IF($H4="Behind the Meter","excluded",IF(NOT(OR($E4="Bundled",$E4="Energy")),"excluded",IF(OR($H4="Retail Power Marketer",$H4="Community Choice Aggregator",$E4="Energy"),"procurement",IF(OR($H4="Municipal",$H4="Cooperative",$H4="Federal",$H4="State",$H4="Political Subdivision"),"cost_service",IF($H4="Investor Owned",IF(AND(COUNTIF(Parameters!$A$4:$A$33,$G4)>0,COUNTIF(Parameters!$B$4:$B$33,$B4)=0),"procurement","cost_service"),"unclassified")))))) -> cost_service
A5: 2024 | B5: 84 | C5: A & N Electric Coop | D5: A | E5: Bundled | F5: O | G5: MD | H5: Cooperative | I5: PJM | J5: 304.8 | K5: 2226 | L5: 253 | M5: 76.8 | N5: 567 | O5: 42 | P5: 0 | Q5: 0 | R5: 0 | S5: 0 | T5: 0 | U5: 0 | V5: 381.6 | W5: 2793 | X5: 295 | Y5: =IF(ISNUMBER($W5),$W5,0) -> 2793 | Z5: =IF(ISNUMBER(SEARCH("Adjustment",$C5)),"excluded",IF($H5="Behind the Meter","excluded",IF(NOT(OR($E5="Bundled",$E5="Energy")),"excluded",IF(OR($H5="Retail Power Marketer",$H5="Community Choice Aggregator",$E5="Energy"),"procurement",IF(OR($H5="Municipal",$H5="Cooperative",$H5="Federal",$H5="State",$H5="Political Subdivision"),"cost_service",IF($H5="Investor Owned",IF(AND(COUNTIF(Parameters!$A$4:$A$33,$G5)>0,COUNTIF(Parameters!$B$4:$B$33,$B5)=0),"procurement","cost_service"),"unclassified")))))) -> cost_service
A6: 2024 | B6: 84 | C6: A & N Electric Coop | D6: A | E6: Bundled | F6: O | G6: VA | H6: Cooperative | I6: PJM | J6: 47920.5 | K6: 368014 | L6: 33096 | M6: 20100.4 | N6: 172568 | O6: 4238 | P6: 16022 | Q6: 165066 | R6: 7 | S6: 0 | T6: 0 | U6: 0 | V6: 84042.9 | W6: 705648 | X6: 37341 | Y6: =IF(ISNUMBER($W6),$W6,0) -> 705648 | Z6: =IF(ISNUMBER(SEARCH("Adjustment",$C6)),"excluded",IF($H6="Behind the Meter","excluded",IF(NOT(OR($E6="Bundled",$E6="Energy")),"excluded",IF(OR($H6="Retail Power Marketer",$H6="Community Choice Aggregator",$E6="Energy"),"procurement",IF(OR($H6="Municipal",$H6="Cooperative",$H6="Federal",$H6="State",$H6="Political Subdivision"),"cost_service",IF($H6="Investor Owned",IF(AND(COUNTIF(Parameters!$A$4:$A$33,$G6)>0,COUNTIF(Parameters!$B$4:$B$33,$B6)=0),"procurement","cost_service"),"unclassified")))))) -> cost_service
A7: 2024 | B7: 108 | C7: Adams-Columbia Electric Coop | D7: A | E7: Bundled | F7: O | G7: WI | H7: Cooperative | I7: MISO | J7: 46745 | K7: 265097 | L7: 35910 | M7: 11973 | N7: 92563 | O7: 2518 | P7: 22091 | Q7: 241188 | R7: 1027 | S7: . | T7: . | U7: . | V7: 80809 | W7: 598848 | X7: 39455 | Y7: =IF(ISNUMBER($W7),$W7,0) -> 598848 | Z7: =IF(ISNUMBER(SEARCH("Adjustment",$C7)),"excluded",IF($H7="Behind the Meter","excluded",IF(NOT(OR($E7="Bundled",$E7="Energy")),"excluded",IF(OR($H7="Retail Power Marketer",$H7="Community Choice Aggregator",$E7="Energy"),"procurement",IF(OR($H7="Municipal",$H7="Cooperative",$H7="Federal",$H7="State",$H7="Political Subdivision"),"cost_service",IF($H7="Investor Owned",IF(AND(COUNTIF(Parameters!$A$4:$A$33,$G7)>0,COUNTIF(Parameters!$B$4:$B$33,$B7)=0),"procurement","cost_service"),"unclassified")))))) -> cost_service
A8: 2024 | B8: 113 | C8: Agway Energy Services, LLC | D8: B | E8: Energy | F8: O | G8: MD | H8: Retail Power Marketer | I8: PJM | J8: 2.5 | K8: 22 | L8: 2 | M8: 0 | N8: 0 | O8: 0 | P8: 0 | Q8: 0 | R8: 0 | S8: 0 | T8: 0 | U8: 0 | V8: 2.5 | W8: 22 | X8: 2 | Y8: =IF(ISNUMBER($W8),$W8,0) -> 22 | Z8: =IF(ISNUMBER(SEARCH("Adjustment",$C8)),"excluded",IF($H8="Behind the Meter","excluded",IF(NOT(OR($E8="Bundled",$E8="Energy")),"excluded",IF(OR($H8="Retail Power Marketer",$H8="Community Choice Aggregator",$E8="Energy"),"procurement",IF(OR($H8="Municipal",$H8="Cooperative",$H8="Federal",$H8="State",$H8="Political Subdivision"),"cost_service",IF($H8="Investor Owned",IF(AND(COUNTIF(Parameters!$A$4:$A$33,$G8)>0,COUNTIF(Parameters!$B$4:$B$33,$B8)=0),"procurement","cost_service"),"unclassified")))))) -> procurement
A9: 2024 | B9: 113 | C9: Agway Energy Services, LLC | D9: B | E9: Energy | F9: O | G9: NY | H9: Retail Power Marketer | I9: NYIS | J9: 12807.3 | K9: 96155 | L9: 13406 | M9: 3389.3 | N9: 26847 | O9: 2248 | P9: 0 | Q9: 0 | R9: 0 | S9: 0 | T9: 0 | U9: 0 | V9: 16196.6 | W9: 123002 | X9: 15654 | Y9: =IF(ISNUMBER($W9),$W9,0) -> 123002 | Z9: =IF(ISNUMBER(SEARCH("Adjustment",$C9)),"excluded",IF($H9="Behind the Meter","excluded",IF(NOT(OR($E9="Bundled",$E9="Energy")),"excluded",IF(OR($H9="Retail Power Marketer",$H9="Community Choice Aggregator",$E9="Energy"),"procurement",IF(OR($H9="Municipal",$H9="Cooperative",$H9="Federal",$H9="State",$H9="Political Subdivision"),"cost_service",IF($H9="Investor Owned",IF(AND(COUNTIF(Parameters!$A$4:$A$33,$G9)>0,COUNTIF(Parameters!$B$4:$B$33,$B9)=0),"procurement","cost_service"),"unclassified")))))) -> procurement
A10: 2024 | B10: 113 | C10: Agway Energy Services, LLC | D10: B | E10: Energy | F10: O | G10: PA | H10: Retail Power Marketer | I10: PJM | J10: 972.7 | K10: 8449 | L10: 945 | M10: 95.2 | N10: 918 | O10: 46 | P10: 0 | Q10: 0 | R10: 0 | S10: 0 | T10: 0 | U10: 0 | V10: 1067.9 | W10: 9367 | X10: 991 | Y10: =IF(ISNUMBER($W10),$W10,0) -> 9367 | Z10: =IF(ISNUMBER(SEARCH("Adjustment",$C10)),"excluded",IF($H10="Behind the Meter","excluded",IF(NOT(OR($E10="Bundled",$E10="Energy")),"excluded",IF(OR($H10="Retail Power Marketer",$H10="Community Choice Aggregator",$E10="Energy"),"procurement",IF(OR($H10="Municipal",$H10="Cooperative",$H10="Federal",$H10="State",$H10="Political Subdivision"),"cost_service",IF($H10="Investor Owned",IF(AND(COUNTIF(Parameters!$A$4:$A$33,$G10)>0,COUNTIF(Parameters!$B$4:$B$33,$B10)=0),"procurement","cost_service"),"unclassified")))))) -> procurement
A11: 2024 | B11: 155 | C11: Agralite Electric Coop | D11: A | E11: Bundled | F11: O | G11: MN | H11: Cooperative | I11: MISO | J11: 9568 | K11: 68617 | L11: 4333 | M11: 6218 | N11: 68440 | O11: 436 | P11: 9562 | Q11: 105823 | R11: 628 | S11: . | T11: . | U11: . | V11: 25348 | W11: 242880 | X11: 5397 | Y11: =IF(ISNUMBER($W11),$W11,0) -> 242880 | Z11: =IF(ISNUMBER(SEARCH("Adjustment",$C11)),"excluded",IF($H11="Behind the Meter","excluded",IF(NOT(OR($E11="Bundled",$E11="Energy")),"excluded",IF(OR($H11="Retail Power Marketer",$H11="Community Choice Aggregator",$E11="Energy"),"procurement",IF(OR($H11="Municipal",$H11="Cooperative",$H11="Federal",$H11="State",$H11="Political Subdivision"),"cost_service",IF($H11="Investor Owned",IF(AND(COUNTIF(Parameters!$A$4:$A$33,$G11)>0,COUNTIF(Parameters!$B$4:$B$33,$B11)=0),"procurement","cost_service"),"unclassified")))))) -> cost_service
A12: 2024 | B12: 162 | C12: Aiken Electric Coop Inc | D12: A | E12: Bundled | F12: O | G12: SC | H12: Cooperative | I12: SC | J12: 101066.1 | K12: 650960 | L12: 49460 | M12: 18578.6 | N12: 142543 | O12: 3364 | P12: 14478.7 | Q12: 200397 | R12: 15 | S12: . | T12: . | U12: . | V12: 134123.4 | W12: 993900 | X12: 52839 | Y12: =IF(ISNUMBER($W12),$W12,0) -> 993900 | Z12: =IF(ISNUMBER(SEARCH("Adjustment",$C12)),"excluded",IF($H12="Behind the Meter","excluded",IF(NOT(OR($E12="Bundled",$E12="Energy")),"excluded",IF(OR($H12="Retail Power Marketer",$H12="Community Choice Aggregator",$E12="Energy"),"procurement",IF(OR($H12="Municipal",$H12="Cooperative",$H12="Federal",$H12="State",$H12="Political Subdivision"),"cost_service",IF($H12="Investor Owned",IF(AND(COUNTIF(Parameters!$A$4:$A$33,$G12)>0,COUNTIF(Parameters!$B$4:$B$33,$B12)=0),"procurement","cost_service"),"unclassified")))))) -> cost_service
A13: 2024 | B13: 176 | C13: Ajo Improvement Co | D13: A | E13: Bundled | F13: O | G13: AZ | H13: Investor Owned | I13: AZPS | J13: 678 | K13: 5396 | L13: 821 | M13: 379.2 | N13: 3315 | O13: 210 | P13: 0 | Q13: 0 | R13: 0 | S13: 0 | T13: 0 | U13: 0 | V13: 1057.2 | W13: 8711 | X13: 1031 | Y13: =IF(ISNUMBER($W13),$W13,0) -> 8711 | Z13: =IF(ISNUMBER(SEARCH("Adjustment",$C13)),"excluded",IF($H13="Behind the Meter","excluded",IF(NOT(OR($E13="Bundled",$E13="Energy")),"excluded",IF(OR($H13="Retail Power Marketer",$H13="Community Choice Aggregator",$E13="Energy"),"procurement",IF(OR($H13="Municipal",$H13="Cooperative",$H13="Federal",$H13="State",$H13="Political Subdivision"),"cost_service",IF($H13="Investor Owned",IF(AND(COUNTIF(Parameters!$A$4:$A$33,$G13)>0,COUNTIF(Parameters!$B$4:$B$33,$B13)=0),"procurement","cost_service"),"unclassified")))))) -> cost_service
A14: 2024 | B14: 195 | C14: Alabama Power Co | D14: A | E14: Bundled | F14: O | G14: AL | H14: Investor Owned | I14: SOCO | J14: 3028741 | K14: 18058325 | L14: 1332911 | M14: 1979164 | N14: 13336758 | O14: 207465 | P14: 1631001 | Q14: 20504435 | R14: 6107 | S14: . | T14: . | U14: . | V14: 6638906 | W14: 51899518 | X14: 1546483 | Y14: =IF(ISNUMBER($W14),$W14,0) -> 51899518 | Z14: =IF(ISNUMBER(SEARCH("Adjustment",$C14)),"excluded",IF($H14="Behind the Meter","excluded",IF(NOT(OR($E14="Bundled",$E14="Energy")),"excluded",IF(OR($H14="Retail Power Marketer",$H14="Community Choice Aggregator",$E14="Energy"),"procurement",IF(OR($H14="Municipal",$H14="Cooperative",$H14="Federal",$H14="State",$H14="Political Subdivision"),"cost_service",IF($H14="Investor Owned",IF(AND(COUNTIF(Parameters!$A$4:$A$33,$G14)>0,COUNTIF(Parameters!$B$4:$B$33,$B14)=0),"procurement","cost_service"),"unclassified")))))) -> cost_service
A15: 2024 | B15: 207 | C15: Alameda Municipal Power | D15: A | E15: Bundled | F15: O | G15: CA | H15: Municipal | I15: CISO | J15: 32111.2 | K15: 139744 | L15: 33174 | M15: 43430.5 | N15: 216203 | O15: 4052 | P15: . | Q15: . | R15: . | S15: . | T15: . | U15: . | V15: 75541.7 | W15: 355947 | X15: 37226 | Y15: =IF(ISNUMBER($W15),$W15,0) -> 355947 | Z15: =IF(ISNUMBER(SEARCH("Adjustment",$C15)),"excluded",IF($H15="Behind the Meter","excluded",IF(NOT(OR($E15="Bundled",$E15="Energy")),"excluded",IF(OR($H15="Retail Power Marketer",$H15="Community Choice Aggregator",$E15="Energy"),"procurement",IF(OR($H15="Municipal",$H15="Cooperative",$H15="Federal",$H15="State",$H15="Political Subdivision"),"cost_service",IF($H15="Investor Owned",IF(AND(COUNTIF(Parameters!$A$4:$A$33,$G15)>0,COUNTIF(Parameters!$B$4:$B$33,$B15)=0),"procurement","cost_service"),"unclassified")))))) -> cost_service
A16: 2024 | B16: 213 | C16: Alaska Electric Light & Power Co. | D16: A | E16: Bundled | F16: O | G16: AK | H16: Investor Owned | I16: NA | J16: 22067.7 | K16: 170626 | L16: 15407 | M16: 13567 | N16: 126119 | O16: 2459 | P16: 14392.1 | Q16: 130040 | R16: 139 | S16: . | T16: . | U16: . | V16: 50026.8 | W16: 426785 | X16: 18005 | Y16: =IF(ISNUMBER($W16),$W16,0) -> 426785 | Z16: =IF(ISNUMBER(SEARCH("Adjustment",$C16)),"excluded",IF($H16="Behind the Meter","excluded",IF(NOT(OR($E16="Bundled",$E16="Energy")),"excluded",IF(OR($H16="Retail Power Marketer",$H16="Community Choice Aggregator",$E16="Energy"),"procurement",IF(OR($H16="Municipal",$H16="Cooperative",$H16="Federal",$H16="State",$H16="Political Subdivision"),"cost_service",IF($H16="Investor Owned",IF(AND(COUNTIF(Parameters!$A$4:$A$33,$G16)>0,COUNTIF(Parameters!$B$4:$B$33,$B16)=0),"procurement","cost_service"),"unclassified")))))) -> cost_service
A17: 2024 | B17: 219 | C17: Alaska Power and Telephone Co | D17: A | E17: Bundled | F17: O | G17: AK | H17: Investor Owned | I17: NA | J17: 10397 | K17: 27967 | L17: 5737 | M17: 15878 | N17: 50720 | O17: 2719 | P17: 0 | Q17: 0 | R17: 0 | S17: 0 | T17: 0 | U17: 0 | V17: 26275 | W17: 78687 | X17: 8456 | Y17: =IF(ISNUMBER($W17),$W17,0) -> 78687 | Z17: =IF(ISNUMBER(SEARCH("Adjustment",$C17)),"excluded",IF($H17="Behind the Meter","excluded",IF(NOT(OR($E17="Bundled",$E17="Energy")),"excluded",IF(OR($H17="Retail Power Marketer",$H17="Community Choice Aggregator",$E17="Energy"),"procurement",IF(OR($H17="Municipal",$H17="Cooperative",$H17="Federal",$H17="State",$H17="Political Subdivision"),"cost_service",IF($H17="Investor Owned",IF(AND(COUNTIF(Parameters!$A$4:$A$33,$G17)>0,COUNTIF(Parameters!$B$4:$B$33,$B17)=0),"procurement","cost_service"),"unclassified")))))) -> cost_service
A18: 2024 | B18: 221 | C18: Alaska Village Elec Coop, Inc | D18: A | E18: Bundled | F18: O | G18: AK | H18: Cooperative | I18: NA | J18: 30675.3 | K18: 43854 | L18: 7689 | M18: 46345.7 | N18: 81597 | O18: 3829 | P18: 0 | Q18: 0 | R18: 0 | S18: 0 | T18: 0 | U18: 0 | V18: 77021 | W18: 125451 | X18: 11518 | Y18: =IF(ISNUMBER($W18),$W18,0) -> 125451 | Z18: =IF(ISNUMBER(SEARCH("Adjustment",$C18)),"excluded",IF($H18="Behind the Meter","excluded",IF(NOT(OR($E18="Bundled",$E18="Energy")),"excluded",IF(OR($H18="Retail Power Marketer",$H18="Community Choice Aggregator",$E18="Energy"),"procurement",IF(OR($H18="Municipal",$H18="Cooperative",$H18="Federal",$H18="State",$H18="Political Subdivision"),"cost_service",IF($H18="Investor Owned",IF(AND(COUNTIF(Parameters!$A$4:$A$33,$G18)>0,COUNTIF(Parameters!$B$4:$B$33,$B18)=0),"procurement","cost_service"),"unclassified")))))) -> cost_service
A19: 2024 | B19: 230 | C19: Albany Utility Board | D19: A | E19: Bundled | F19: O | G19: GA | H19: Municipal | I19: SOCO | J19: 44345 | K19: 344628 | L19: 29517 | M19: 36021.7 | N19: 489134 | O19: 4386 | P19: 16.1 | Q19: 595 | R19: 18 | S19: . | T19: . | U19: . | V19: 80382.8 | W19: 834357 | X19: 33921 | Y19: =IF(ISNUMBER($W19),$W19,0) -> 834357 | Z19: =IF(ISNUMBER(SEARCH("Adjustment",$C19)),"excluded",IF($H19="Behind the Meter","excluded",IF(NOT(OR($E19="Bundled",$E19="Energy")),"excluded",IF(OR($H19="Retail Power Marketer",$H19="Community Choice Aggregator",$E19="Energy"),"procurement",IF(OR($H19="Municipal",$H19="Cooperative",$H19="Federal",$H19="State",$H19="Political Subdivision"),"cost_service",IF($H19="Investor Owned",IF(AND(COUNTIF(Parameters!$A$4:$A$33,$G19)>0,COUNTIF(Parameters!$B$4:$B$33,$B19)=0),"procurement","cost_service"),"unclassified")))))) -> cost_service
A20: 2024 | B20: 232 | C20: City of Albemarle - (NC) | D20: A | E20: Bundled | F20: O | G20: NC | H20: Municipal | I20: DUK | J20: 15540.1 | K20: 143278 | L20: 11248 | M20: 11813.5 | N20: 124076 | O20: 2325 | P20: 2043.8 | Q20: 26186 | R20: 12 | S20: . | T20: . | U20: . | V20: 29397.4 | W20: 293540 | X20: 13585 | Y20: =IF(ISNUMBER($W20),$W20,0) -> 293540 | Z20: =IF(ISNUMBER(SEARCH("Adjustment",$C20)),"excluded",IF($H20="Behind the Meter","excluded",IF(NOT(OR($E20="Bundled",$E20="Energy")),"excluded",IF(OR($H20="Retail Power Marketer",$H20="Community Choice Aggregator",$E20="Energy"),"procurement",IF(OR($H20="Municipal",$H20="Cooperative",$H20="Federal",$H20="State",$H20="Political Subdivision"),"cost_service",IF($H20="Investor Owned",IF(AND(COUNTIF(Parameters!$A$4:$A$33,$G20)>0,COUNTIF(Parameters!$B$4:$B$33,$B20)=0),"procurement","cost_service"),"unclassified")))))) -> cost_service
A21: 2024 | B21: 240 | C21: Albemarle Electric Member Corp | D21: A | E21: Bundled | F21: O | G21: NC | H21: Cooperative | I21: PJM | J21: 27083 | K21: 187141 | L21: 12728 | M21: 4363 | N21: 34972 | O21: 1117 | P21: 623 | Q21: 6942 | R21: 25 | S21: 0 | T21: 0 | U21: 0 | V21: 32069 | W21: 229055 | X21: 13870 | Y21: =IF(ISNUMBER($W21),$W21,0) -> 229055 | Z21: =IF(ISNUMBER(SEARCH("Adjustment",$C21)),"excluded",IF($H21="Behind the Meter","excluded",IF(NOT(OR($E21="Bundled",$E21="Energy")),"excluded",IF(OR($H21="Retail Power Marketer",$H21="Community Choice Aggregator",$E21="Energy"),"procurement",IF(OR($H21="Municipal",$H21="Cooperative",$H21="Federal",$H21="State",$H21="Political Subdivision"),"cost_service",IF($H21="Investor Owned",IF(AND(COUNTIF(Parameters!$A$4:$A$33,$G21)>0,COUNTIF(Parameters!$B$4:$B$33,$B21)=0),"procurement","cost_service"),"unclassified")))))) -> cost_service
A22: 2024 | B22: 241 | C22: Albertville Municipal Utilities Board | D22: A | E22: Bundled | F22: O | G22: AL | H22: Municipal | I22: TVA | J22: 13258 | K22: 124264 | L22: 8318 | M22: 21539 | N22: 194750 | O22: 2393 | P22: 21329 | Q22: 333519 | R22: 15 | S22: 0 | T22: 0 | U22: 0 | V22: 56126 | W22: 652533 | X22: 10726 | Y22: =IF(ISNUMBER($W22),$W22,0) -> 652533 | Z22: =IF(ISNUMBER(SEARCH("Adjustment",$C22)),"excluded",IF($H22="Behind the Meter","excluded",IF(NOT(OR($E22="Bundled",$E22="Energy")),"excluded",IF(OR($H22="Retail Power Marketer",$H22="Community Choice Aggregator",$E22="Energy"),"procurement",IF(OR($H22="Municipal",$H22="Cooperative",$H22="Federal",$H22="State",$H22="Political Subdivision"),"cost_service",IF($H22="Investor Owned",IF(AND(COUNTIF(Parameters!$A$4:$A$33,$G22)>0,COUNTIF(Parameters!$B$4:$B$33,$B22)=0),"procurement","cost_service"),"unclassified")))))) -> cost_service
A23: 2024 | B23: 261 | C23: AGC Division of APGI Inc | D23: A | E23: Bundled | F23: O | G23: IN | H23: Investor Owned | I23: MISO | J23: 0 | K23: 0 | L23: 0 | M23: 0 | N23: 0 | O23: 0 | P23: 159579.9 | Q23: 2639245 | R23: 2 | S23: 0 | T23: 0 | U23: 0 | V23: 159579.9 | W23: 2639245 | X23: 2 | Y23: =IF(ISNUMBER($W23),$W23,0) -> 2639245 | Z23: =IF(ISNUMBER(SEARCH("Adjustment",$C23)),"excluded",IF($H23="Behind the Meter","excluded",IF(NOT(OR($E23="Bundled",$E23="Energy")),"excluded",IF(OR($H23="Retail Power Marketer",$H23="Community Choice Aggregator",$E23="Energy"),"procurement",IF(OR($H23="Municipal",$H23="Cooperative",$H23="Federal",$H23="State",$H23="Political Subdivision"),"cost_service",IF($H23="Investor Owned",IF(AND(COUNTIF(Parameters!$A$4:$A$33,$G23)>0,COUNTIF(Parameters!$B$4:$B$33,$B23)=0),"procurement","cost_service"),"unclassified")))))) -> cost_service
A24: 2024 | B24: 276 | C24: Alcorn County Elec Power Assn | D24: A | E24: Bundled | F24: O | G24: MS | H24: Cooperative | I24: TVA | J24: 27784 | K24: 214981 | L24: 14965 | M24: 21450 | N24: 156737 | O24: 4209 | P24: 15258 | Q24: 259874 | R24: 7 | S24: 0 | T24: 0 | U24: 0 | V24: 64492 | W24: 631592 | X24: 19181 | Y24: =IF(ISNUMBER($W24),$W24,0) -> 631592 | Z24: =IF(ISNUMBER(SEARCH("Adjustment",$C24)),"excluded",IF($H24="Behind the Meter","excluded",IF(NOT(OR($E24="Bundled",$E24="Energy")),"excluded",IF(OR($H24="Retail Power Marketer",$H24="Community Choice Aggregator",$E24="Energy"),"procurement",IF(OR($H24="Municipal",$H24="Cooperative",$H24="Federal",$H24="State",$H24="Political Subdivision"),"cost_service",IF($H24="Investor Owned",IF(AND(COUNTIF(Parameters!$A$4:$A$33,$G24)>0,COUNTIF(Parameters!$B$4:$B$33,$B24)=0),"procurement","cost_service"),"unclassified")))))) -> cost_service
A25: 2024 | B25: 295 | C25: City of Alexandria - (MN) | D25: A | E25: Bundled | F25: O | G25: MN | H25: Municipal | I25: MISO | J25: 8900.4 | K25: 76955 | L25: 8758 | M25: 3893.7 | N25: 32821 | O25: 1706 | P25: 15171 | Q25: 168628 | R25: 228 | S25: . | T25: . | U25: . | V25: 27965.1 | W25: 278404 | X25: 10692 | Y25: =IF(ISNUMBER($W25),$W25,0) -> 278404 | Z25: =IF(ISNUMBER(SEARCH("Adjustment",$C25)),"excluded",IF($H25="Behind the Meter","excluded",IF(NOT(OR($E25="Bundled",$E25="Energy")),"excluded",IF(OR($H25="Retail Power Marketer",$H25="Community Choice Aggregator",$E25="Energy"),"procurement",IF(OR($H25="Municipal",$H25="Cooperative",$H25="Federal",$H25="State",$H25="Political Subdivision"),"cost_service",IF($H25="Investor Owned",IF(AND(COUNTIF(Parameters!$A$4:$A$33,$G25)>0,COUNTIF(Parameters!$B$4:$B$33,$B25)=0),"procurement","cost_service"),"unclassified")))))) -> cost_service
A26: 2024 | B26: 296 | C26: Alfalfa Electric Coop, Inc | D26: A | E26: Bundled | F26: O | G26: KS | H26: Cooperative | I26: SWPP | J26: 373 | K26: 3583 | L26: 205 | M26: 744 | N26: 4593 | O26: 670 | P26: 1121 | Q26: 12621 | R26: 55 | S26: . | T26: . | U26: . | V26: 2238 | W26: 20797 | X26: 930 | Y26: =IF(ISNUMBER($W26),$W26,0) -> 20797 | Z26: =IF(ISNUMBER(SEARCH("Adjustment",$C26)),"excluded",IF($H26="Behind the Meter","excluded",IF(NOT(OR($E26="Bundled",$E26="Energy")),"excluded",IF(OR($H26="Retail Power Marketer",$H26="Community Choice Aggregator",$E26="Energy"),"procurement",IF(OR($H26="Municipal",$H26="Cooperative",$H26="Federal",$H26="State",$H26="Political Subdivision"),"cost_service",IF($H26="Investor Owned",IF(AND(COUNTIF(Parameters!$A$4:$A$33,$G26)>0,COUNTIF(Parameters!$B$4:$B$33,$B26)=0),"procurement","cost_service"),"unclassified")))))) -> cost_service
A27: 2024 | B27: 296 | C27: Alfalfa Electric Coop, Inc | D27: A | E27: Bundled | F27: O | G27: OK | H27: Cooperative | I27: SWPP | J27: 5044 | K27: 49434 | L27: 2630 | M27: 5371 | N27: 37743 | O27: 4294 | P27: 23807 | Q27: 301906 | R27: 612 | S27: . | T27: . | U27: . | V27: 34222 | W27: 389083 | X27: 7536 | Y27: =IF(ISNUMBER($W27),$W27,0) -> 389083 | Z27: =IF(ISNUMBER(SEARCH("Adjustment",$C27)),"excluded",IF($H27="Behind the Meter","excluded",IF(NOT(OR($E27="Bundled",$E27="Energy")),"excluded",IF(OR($H27="Retail Power Marketer",$H27="Community Choice Aggregator",$E27="Energy"),"procurement",IF(OR($H27="Municipal",$H27="Cooperative",$H27="Federal",$H27="State",$H27="Political Subdivision"),"cost_service",IF($H27="Investor Owned",IF(AND(COUNTIF(Parameters!$A$4:$A$33,$G27)>0,COUNTIF(Parameters!$B$4:$B$33,$B27)=0),"procurement","cost_service"),"unclassified")))))) -> cost_service
A28: 2024 | B28: 298 | C28: City of Alexandria - (LA) | D28: A | E28: Bundled | F28: O | G28: LA | H28: Municipal | I28: MISO | J28: 30931.1 | K28: 278634 | L28: 19541 | M28: 38444.3 | N28: 363017 | O28: 3913 | P28: 479.8 | Q28: 5167 | R28: 6 | S28: . | T28: . | U28: . | V28: 69855.2 | W28: 646818 | X28: 23460 | Y28: =IF(ISNUMBER($W28),$W28,0) -> 646818 | Z28: =IF(ISNUMBER(SEARCH("Adjustment",$C28)),"excluded",IF($H28="Behind the Meter","excluded",IF(NOT(OR($E28="Bundled",$E28="Energy")),"excluded",IF(OR($H28="Retail Power Marketer",$H28="Community Choice Aggregator",$E28="Energy"),"procurement",IF(OR($H28="Municipal",$H28="Cooperative",$H28="Federal",$H28="State",$H28="Political Subdivision"),"cost_service",IF($H28="Investor Owned",IF(AND(COUNTIF(Parameters!$A$4:$A$33,$G28)>0,COUNTIF(Parameters!$B$4:$B$33,$B28)=0),"procurement","cost_service"),"unclassified")))))) -> cost_service
A29: 2024 | B29: 305 | C29: Alger-Delta Coop Electric Assn | D29: A | E29: Bundled | F29: O | G29: MI | H29: Cooperative | I29: MISO | J29: 11995.9 | K29: 51600 | L29: 9817 | M29: 1834.5 | N29: 11320 | O29: 495 | P29: 4014.9 | Q29: 31953 | R29: 1 | S29: 0 | T29: 0 | U29: 0 | V29: 17845.3 | W29: 94873 | X29: 10313 | Y29: =IF(ISNUMBER($W29),$W29,0) -> 94873 | Z29: =IF(ISNUMBER(SEARCH("Adjustment",$C29)),"excluded",IF($H29="Behind the Meter","excluded",IF(NOT(OR($E29="Bundled",$E29="Energy")),"excluded",IF(OR($H29="Retail Power Marketer",$H29="Community Choice Aggregator",$E29="Energy"),"procurement",IF(OR($H29="Municipal",$H29="Cooperative",$H29="Federal",$H29="State",$H29="Political Subdivision"),"cost_service",IF($H29="Investor Owned",IF(AND(COUNTIF(Parameters!$A$4:$A$33,$G29)>0,COUNTIF(Parameters!$B$4:$B$33,$B29)=0),"procurement","cost_service"),"unclassified")))))) -> cost_service
A30: 2024 | B30: 307 | C30: Algoma Utility Comm | D30: A | E30: Bundled | F30: O | G30: WI | H30: Municipal | I30: MISO | J30: 1403.2 | K30: 10775 | L30: 1654 | M30: 1881.4 | N30: 17010 | O30: 395 | P30: 510.1 | Q30: 5869 | R30: 1 | S30: 0 | T30: 0 | U30: 0 | V30: 3794.7 | W30: 33654 | X30: 2050 | Y30: =IF(ISNUMBER($W30),$W30,0) -> 33654 | Z30: =IF(ISNUMBER(SEARCH("Adjustment",$C30)),"excluded",IF($H30="Behind the Meter","excluded",IF(NOT(OR($E30="Bundled",$E30="Energy")),"excluded",IF(OR($H30="Retail Power Marketer",$H30="Community Choice Aggregator",$E30="Energy"),"procurement",IF(OR($H30="Municipal",$H30="Cooperative",$H30="Federal",$H30="State",$H30="Political Subdivision"),"cost_service",IF($H30="Investor Owned",IF(AND(COUNTIF(Parameters!$A$4:$A$33,$G30)>0,COUNTIF(Parameters!$B$4:$B$33,$B30)=0),"procurement","cost_service"),"unclassified")))))) -> cost_service
A31: 2024 | B31: 392 | C31: Alpena Power Co | D31: A | E31: Bundled | F31: O | G31: MI | H31: Investor Owned | I31: MISO | J31: 15157.9 | K31: 86989 | L31: 13763 | M31: 13651.6 | N31: 89556 | O31: 3041 | P31: 7916.1 | Q31: 109161 | R31: 3 | S31: 0 | T31: 0 | U31: 0 | V31: 36725.6 | W31: 285706 | X31: 16807 | Y31: =IF(ISNUMBER($W31),$W31,0) -> 285706 | Z31: =IF(ISNUMBER(SEARCH("Adjustment",$C31)),"excluded",IF($H31="Behind the Meter","excluded",IF(NOT(OR($E31="Bundled",$E31="Energy")),"excluded",IF(OR($H31="Retail Power Marketer",$H31="Community Choice Aggregator",$E31="Energy"),"procurement",IF(OR($H31="Municipal",$H31="Cooperative",$H31="Federal",$H31="State",$H31="Political Subdivision"),"cost_service",IF($H31="Investor Owned",IF(AND(COUNTIF(Parameters!$A$4:$A$33,$G31)>0,COUNTIF(Parameters!$B$4:$B$33,$B31)=0),"procurement","cost_service"),"unclassified")))))) -> cost_service
A32: 2024 | B32: 407 | C32: Altamaha Electric Member Corp | D32: A | E32: Bundled | F32: O | G32: GA | H32: Cooperative | I32: SOCO | J32: 37983.5 | K32: 236866 | L32: 19628 | M32: 29917.2 | N32: 332113 | O32: 1984 | P32: 1234.2 | Q32: 8400 | R32: 258 | S32: . | T32: . | U32: . | V32: 69134.9 | W32: 577379 | X32: 21870 | Y32: =IF(ISNUMBER($W32),$W32,0) -> 577379 | Z32: =IF(ISNUMBER(SEARCH("Adjustment",$C32)),"excluded",IF($H32="Behind the Meter","excluded",IF(NOT(OR($E32="Bundled",$E32="Energy")),"excluded",IF(OR($H32="Retail Power Marketer",$H32="Community Choice Aggregator",$E32="Energy"),"procurement",IF(OR($H32="Municipal",$H32="Cooperative",$H32="Federal",$H32="State",$H32="Political Subdivision"),"cost_service",IF($H32="Investor Owned",IF(AND(COUNTIF(Parameters!$A$4:$A$33,$G32)>0,COUNTIF(Parameters!$B$4:$B$33,$B32)=0),"procurement","cost_service"),"unclassified")))))) -> cost_service
A33: 2024 | B33: 416 | C33: City of Altus - (OK) | D33: A | E33: Bundled | F33: O | G33: OK | H33: Municipal | I33: SWPP | J33: 13567 | K33: 104947 | L33: 8167 | M33: 6814 | N33: 64630 | O33: 1268 | P33: 3079 | Q33: 39809 | R33: 8 | S33: . | T33: . | U33: . | V33: 23460 | W33: 209386 | X33: 9443 | Y33: =IF(ISNUMBER($W33),$W33,0) -> 209386 | Z33: =IF(ISNUMBER(SEARCH("Adjustment",$C33)),"excluded",IF($H33="Behind the Meter","excluded",IF(NOT(OR($E33="Bundled",$E33="Energy")),"excluded",IF(OR($H33="Retail Power Marketer",$H33="Community Choice Aggregator",$E33="Energy"),"procurement",IF(OR($H33="Municipal",$H33="Cooperative",$H33="Federal",$H33="State",$H33="Political Subdivision"),"cost_service",IF($H33="Investor Owned",IF(AND(COUNTIF(Parameters!$A$4:$A$33,$G33)>0,COUNTIF(Parameters!$B$4:$B$33,$B33)=0),"procurement","cost_service"),"unclassified")))))) -> cost_service
A34: 2024 | B34: 471 | C34: Amana Society Service Co | D34: A | E34: Bundled | F34: O | G34: IA | H34: Investor Owned | I34: MISO | J34: 1061 | K34: 6833 | L34: 709 | M34: 1221 | N34: 8358 | O34: 179 | P34: 5506 | Q34: 51780 | R34: 1 | S34: 0 | T34: 0 | U34: 0 | V34: 7788 | W34: 66971 | X34: 889 | Y34: =IF(ISNUMBER($W34),$W34,0) -> 66971 | Z34: =IF(ISNUMBER(SEARCH("Adjustment",$C34)),"excluded",IF($H34="Behind the Meter","excluded",IF(NOT(OR($E34="Bundled",$E34="Energy")),"excluded",IF(OR($H34="Retail Power Marketer",$H34="Community Choice Aggregator",$E34="Energy"),"procurement",IF(OR($H34="Municipal",$H34="Cooperative",$H34="Federal",$H34="State",$H34="Political Subdivision"),"cost_service",IF($H34="Investor Owned",IF(AND(COUNTIF(Parameters!$A$4:$A$33,$G34)>0,COUNTIF(Parameters!$B$4:$B$33,$B34)=0),"procurement","cost_service"),"unclassified")))))) -> cost_service
A35: 2024 | B35: 540 | C35: BP Energy Company | D35: B | E35: Energy | F35: O | G35: WA | H35: Retail Power Marketer | I35: PSEI | J35: . | K35: . | L35: . | M35: . | N35: . | O35: . | P35: 60883.1 | Q35: 887803 | R35: 2 | S35: . | T35: . | U35: . | V35: 60883.1 | W35: 887803 | X35: 2 | Y35: =IF(ISNUMBER($W35),$W35,0) -> 887803 | Z35: =IF(ISNUMBER(SEARCH("Adjustment",$C35)),"excluded",IF($H35="Behind the Meter","excluded",IF(NOT(OR($E35="Bundled",$E35="Energy")),"excluded",IF(OR($H35="Retail Power Marketer",$H35="Community Choice Aggregator",$E35="Energy"),"procurement",IF(OR($H35="Municipal",$H35="Cooperative",$H35="Federal",$H35="State",$H35="Political Subdivision"),"cost_service",IF($H35="Investor Owned",IF(AND(COUNTIF(Parameters!$A$4:$A$33,$G35)>0,COUNTIF(Parameters!$B$4:$B$33,$B35)=0),"procurement","cost_service"),"unclassified")))))) -> procurement
A36: 2024 | B36: 540 | C36: BP Energy Company | D36: D | E36: Bundled | F36: O | G36: TX | H36: Retail Power Marketer | I36: ERCO | J36: . | K36: . | L36: . | M36: . | N36: . | O36: . | P36: 62297 | Q36: 989891 | R36: 1 | S36: . | T36: . | U36: . | V36: 62297 | W36: 989891 | X36: 1 | Y36: =IF(ISNUMBER($W36),$W36,0) -> 989891 | Z36: =IF(ISNUMBER(SEARCH("Adjustment",$C36)),"excluded",IF($H36="Behind the Meter","excluded",IF(NOT(OR($E36="Bundled",$E36="Energy")),"excluded",IF(OR($H36="Retail Power Marketer",$H36="Community Choice Aggregator",$E36="Energy"),"procurement",IF(OR($H36="Municipal",$H36="Cooperative",$H36="Federal",$H36="State",$H36="Political Subdivision"),"cost_service",IF($H36="Investor Owned",IF(AND(COUNTIF(Parameters!$A$4:$A$33,$G36)>0,COUNTIF(Parameters!$B$4:$B$33,$B36)=0),"procurement","cost_service"),"unclassified")))))) -> procurement
A37: 2024 | B37: 554 | C37: City of Ames - (IA) | D37: A | E37: Bundled | F37: O | G37: IA | H37: Municipal | I37: MISO | J37: 20680.5 | K37: 170973 | L37: 24979 | M37: 28463.1 | N37: 334597 | O37: 3121 | P37: 11868.2 | Q37: 145193 | R37: 8 | S37: . | T37: . | U37: . | V37: 61011.8 | W37: 650763 | X37: 28108 | Y37: =IF(ISNUMBER($W37),$W37,0) -> 650763 | Z37: =IF(ISNUMBER(SEARCH("Adjustment",$C37)),"excluded",IF($H37="Behind the Meter","excluded",IF(NOT(OR($E37="Bundled",$E37="Energy")),"excluded",IF(OR($H37="Retail Power Marketer",$H37="Community Choice Aggregator",$E37="Energy"),"procurement",IF(OR($H37="Municipal",$H37="Cooperative",$H37="Federal",$H37="State",$H37="Political Subdivision"),"cost_service",IF($H37="Investor Owned",IF(AND(COUNTIF(Parameters!$A$4:$A$33,$G37)>0,COUNTIF(Parameters!$B$4:$B$33,$B37)=0),"procurement","cost_service"),"unclassified")))))) -> cost_service
A38: 2024 | B38: 562 | C38: Amicalola Electric Member Corp | D38: A | E38: Bundled | F38: O | G38: GA | H38: Cooperative | I38: SOCO | J38: 92851.8 | K38: 748163 | L38: 50337 | M38: 18240.6 | N38: 131462 | O38: 6070 | P38: . | Q38: . | R38: . | S38: . | T38: . | U38: . | V38: 111092.4 | W38: 879625 | X38: 56407 | Y38: =IF(ISNUMBER($W38),$W38,0) -> 879625 | Z38: =IF(ISNUMBER(SEARCH("Adjustment",$C38)),"excluded",IF($H38="Behind the Meter","excluded",IF(NOT(OR($E38="Bundled",$E38="Energy")),"excluded",IF(OR($H38="Retail Power Marketer",$H38="Community Choice Aggregator",$E38="Energy"),"procurement",IF(OR($H38="Municipal",$H38="Cooperative",$H38="Federal",$H38="State",$H38="Political Subdivision"),"cost_service",IF($H38="Investor Owned",IF(AND(COUNTIF(Parameters!$A$4:$A$33,$G38)>0,COUNTIF(Parameters!$B$4:$B$33,$B38)=0),"procurement","cost_service"),"unclassified")))))) -> cost_service
A39: 2024 | B39: 571 | C39: City of Amory | D39: A | E39: Bundled | F39: O | G39: MS | H39: Municipal | I39: TVA | J39: 4410 | K39: 37764 | L39: 2822 | M39: 5977 | N39: 47462 | O39: 1134 | P39: 3039 | Q39: 35349 | R39: 3 | S39: 0 | T39: 0 | U39: 0 | V39: 13426 | W39: 120575 | X39: 3959 | Y39: =IF(ISNUMBER($W39),$W39,0) -> 120575 | Z39: =IF(ISNUMBER(SEARCH("Adjustment",$C39)),"excluded",IF($H39="Behind the Meter","excluded",IF(NOT(OR($E39="Bundled",$E39="Energy")),"excluded",IF(OR($H39="Retail Power Marketer",$H39="Community Choice Aggregator",$E39="Energy"),"procurement",IF(OR($H39="Municipal",$H39="Cooperative",$H39="Federal",$H39="State",$H39="Political Subdivision"),"cost_service",IF($H39="Investor Owned",IF(AND(COUNTIF(Parameters!$A$4:$A$33,$G39)>0,COUNTIF(Parameters!$B$4:$B$33,$B39)=0),"procurement","cost_service"),"unclassified")))))) -> cost_service
A40: 2024 | B40: 577 | C40: City of Alcoa Utilities | D40: A | E40: Bundled | F40: O | G40: TN | H40: Municipal | I40: TVA | J40: 50103 | K40: 410299 | L40: 28183 | M40: 30222 | N40: 261925 | O40: 4543 | P40: 158 | Q40: 1098 | R40: 1 | S40: 0 | T40: 0 | U40: 0 | V40: 80483 | W40: 673322 | X40: 32727 | Y40: =IF(ISNUMBER($W40),$W40,0) -> 673322 | Z40: =IF(ISNUMBER(SEARCH("Adjustment",$C40)),"excluded",IF($H40="Behind the Meter","excluded",IF(NOT(OR($E40="Bundled",$E40="Energy")),"excluded",IF(OR($H40="Retail Power Marketer",$H40="Community Choice Aggregator",$E40="Energy"),"procurement",IF(OR($H40="Municipal",$H40="Cooperative",$H40="Federal",$H40="State",$H40="Political Subdivision"),"cost_service",IF($H40="Investor Owned",IF(AND(COUNTIF(Parameters!$A$4:$A$33,$G40)>0,COUNTIF(Parameters!$B$4:$B$33,$B40)=0),"procurement","cost_service"),"unclassified")))))) -> cost_service
A41: 2024 | B41: 590 | C41: City of Anaheim - (CA) | D41: A | E41: Bundled | F41: O | G41: CA | H41: Municipal | I41: CISO | J41: 101425 | K41: 592710 | L41: 105839 | M41: 128635 | N41: 725751 | O41: 17557 | P41: 127256 | Q41: 819612 | R41: 269 | S41: . | T41: . | U41: . | V41: 357316 | W41: 2138073 | X41: 123665 | Y41: =IF(ISNUMBER($W41),$W41,0) -> 2138073 | Z41: =IF(ISNUMBER(SEARCH("Adjustment",$C41)),"excluded",IF($H41="Behind the Meter","excluded",IF(NOT(OR($E41="Bundled",$E41="Energy")),"excluded",IF(OR($H41="Retail Power Marketer",$H41="Community Choice Aggregator",$E41="Energy"),"procurement",IF(OR($H41="Municipal",$H41="Cooperative",$H41="Federal",$H41="State",$H41="Political Subdivision"),"cost_service",IF($H41="Investor Owned",IF(AND(COUNTIF(Parameters!$A$4:$A$33,$G41)>0,COUNTIF(Parameters!$B$4:$B$33,$B41)=0),"procurement","cost_service"),"unclassified")))))) -> cost_service
A42: 2024 | B42: 604 | C42: City of Andalusia | D42: A | E42: Bundled | F42: O | G42: AL | H42: Municipal | I42: SOCO | J42: 6678 | K42: 42321 | L42: 3605 | M42: 10139 | N42: 59566 | O42: 1068 | P42: 13226 | Q42: 218731 | R42: 2 | S42: . | T42: . | U42: . | V42: 30043 | W42: 320618 | X42: 4675 | Y42: =IF(ISNUMBER($W42),$W42,0) -> 320618 | Z42: =IF(ISNUMBER(SEARCH("Adjustment",$C42)),"excluded",IF($H42="Behind the Meter","excluded",IF(NOT(OR($E42="Bundled",$E42="Energy")),"excluded",IF(OR($H42="Retail Power Marketer",$H42="Community Choice Aggregator",$E42="Energy"),"procurement",IF(OR($H42="Municipal",$H42="Cooperative",$H42="Federal",$H42="State",$H42="Political Subdivision"),"cost_service",IF($H42="Investor Owned",IF(AND(COUNTIF(Parameters!$A$4:$A$33,$G42)>0,COUNTIF(Parameters!$B$4:$B$33,$B42)=0),"procurement","cost_service"),"unclassified")))))) -> cost_service
A43: 2024 | B43: 636 | C43: City of Anderson - (IN) | D43: A | E43: Bundled | F43: O | G43: IN | H43: Municipal | I43: PJM | J43: 38475.9 | K43: 300134 | L43: 29533 | M43: 29869.7 | N43: 269337 | O43: 3875 | P43: 24779.1 | Q43: 282496 | R43: 58 | S43: . | T43: . | U43: . | V43: 93124.7 | W43: 851967 | X43: 33466 | Y43: =IF(ISNUMBER($W43),$W43,0) -> 851967 | Z43: =IF(ISNUMBER(SEARCH("Adjustment",$C43)),"excluded",IF($H43="Behind the Meter","excluded",IF(NOT(OR($E43="Bundled",$E43="Energy")),"excluded",IF(OR($H43="Retail Power Marketer",$H43="Community Choice Aggregator",$E43="Energy"),"procurement",IF(OR($H43="Municipal",$H43="Cooperative",$H43="Federal",$H43="State",$H43="Political Subdivision"),"cost_service",IF($H43="Investor Owned",IF(AND(COUNTIF(Parameters!$A$4:$A$33,$G43)>0,COUNTIF(Parameters!$B$4:$B$33,$B43)=0),"procurement","cost_service"),"unclassified")))))) -> cost_service
A44: 2024 | B44: 689 | C44: Connexus Energy | D44: A | E44: Bundled | F44: O | G44: MN | H44: Cooperative | I44: MISO | J44: 169726.7 | K44: 1242625 | L44: 134095 | M44: 66237.3 | N44: 624680 | O44: 12112 | P44: 14463.1 | Q44: 183925 | R44: 433 | S44: 0 | T44: 0 | U44: 0 | V44: 250427.1 | W44: 2051230 | X44: 146640 | Y44: =IF(ISNUMBER($W44),$W44,0) -> 2051230 | Z44: =IF(ISNUMBER(SEARCH("Adjustment",$C44)),"excluded",IF($H44="Behind the Meter","excluded",IF(NOT(OR($E44="Bundled",$E44="Energy")),"excluded",IF(OR($H44="Retail Power Marketer",$H44="Community Choice Aggregator",$E44="Energy"),"procurement",IF(OR($H44="Municipal",$H44="Cooperative",$H44="Federal",$H44="State",$H44="Political Subdivision"),"cost_service",IF($H44="Investor Owned",IF(AND(COUNTIF(Parameters!$A$4:$A$33,$G44)>0,COUNTIF(Parameters!$B$4:$B$33,$B44)=0),"procurement","cost_service"),"unclassified")))))) -> cost_service
A45: 2024 | B45: 691 | C45: City of Anoka | D45: A | E45: Bundled | F45: O | G45: MN | H45: Municipal | I45: MISO | J45: 12100 | K45: 76211 | L45: 11646 | M45: 9534 | N45: 80286 | O45: 1336 | P45: 12314 | Q45: 101516 | R45: 22 | S45: . | T45: . | U45: . | V45: 33948 | W45: 258013 | X45: 13004 | Y45: =IF(ISNUMBER($W45),$W45,0) -> 258013 | Z45: =IF(ISNUMBER(SEARCH("Adjustment",$C45)),"excluded",IF($H45="Behind the Meter","excluded",IF(NOT(OR($E45="Bundled",$E45="Energy")),"excluded",IF(OR($H45="Retail Power Marketer",$H45="Community Choice Aggregator",$E45="Energy"),"procurement",IF(OR($H45="Municipal",$H45="Cooperative",$H45="Federal",$H45="State",$H45="Political Subdivision"),"cost_service",IF($H45="Investor Owned",IF(AND(COUNTIF(Parameters!$A$4:$A$33,$G45)>0,COUNTIF(Parameters!$B$4:$B$33,$B45)=0),"procurement","cost_service"),"unclassified")))))) -> cost_service
A46: 2024 | B46: 719 | C46: Town of Apex- (NC) | D46: A | E46: Bundled | F46: O | G46: NC | H46: Municipal | I46: CPLE | J46: 33459 | K46: 318140 | L46: 29289 | M46: 15315 | N46: 109744 | O46: 1972 | P46: . | Q46: . | R46: . | S46: . | T46: . | U46: . | V46: 48774 | W46: 427884 | X46: 31261 | Y46: =IF(ISNUMBER($W46),$W46,0) -> 427884 | Z46: =IF(ISNUMBER(SEARCH("Adjustment",$C46)),"excluded",IF($H46="Behind the Meter","excluded",IF(NOT(OR($E46="Bundled",$E46="Energy")),"excluded",IF(OR($H46="Retail Power Marketer",$H46="Community Choice Aggregator",$E46="Energy"),"procurement",IF(OR($H46="Municipal",$H46="Cooperative",$H46="Federal",$H46="State",$H46="Political Subdivision"),"cost_service",IF($H46="Investor Owned",IF(AND(COUNTIF(Parameters!$A$4:$A$33,$G46)>0,COUNTIF(Parameters!$B$4:$B$33,$B46)=0),"procurement","cost_service"),"unclassified")))))) -> cost_service
A47: 2024 | B47: 727 | C47: Appalachian Electric Coop | D47: A | E47: Bundled | F47: O | G47: TN | H47: Cooperative | I47: TVA | J47: 82864 | K47: 640950 | L47: 43709 | M47: 32066 | N47: 248037 | O47: 7650 | P47: 5475 | Q47: 83719 | R47: 7 | S47: 0 | T47: 0 | U47: 0 | V47: 120405 | W47: 972706 | X47: 51366 | Y47: =IF(ISNUMBER($W47),$W47,0) -> 972706 | Z47: =IF(ISNUMBER(SEARCH("Adjustment",$C47)),"excluded",IF($H47="Behind the Meter","excluded",IF(NOT(OR($E47="Bundled",$E47="Energy")),"excluded",IF(OR($H47="Retail Power Marketer",$H47="Community Choice Aggregator",$E47="Energy"),"procurement",IF(OR($H47="Municipal",$H47="Cooperative",$H47="Federal",$H47="State",$H47="Political Subdivision"),"cost_service",IF($H47="Investor Owned",IF(AND(COUNTIF(Parameters!$A$4:$A$33,$G47)>0,COUNTIF(Parameters!$B$4:$B$33,$B47)=0),"procurement","cost_service"),"unclassified")))))) -> cost_service
A48: 2024 | B48: 733 | C48: Appalachian Power Co | D48: A | E48: Bundled | F48: O | G48: VA | H48: Investor Owned | I48: PJM | J48: 995624 | K48: 5850904 | L48: 465283 | M48: 493540 | N48: 3626187 | O48: 81996 | P48: 472252 | Q48: 4527177 | R48: 1939 | S48: . | T48: . | U48: . | V48: 1961416 | W48: 14004268 | X48: 549218 | Y48: =IF(ISNUMBER($W48),$W48,0) -> 14004268 | Z48: =IF(ISNUMBER(SEARCH("Adjustment",$C48)),"excluded",IF($H48="Behind the Meter","excluded",IF(NOT(OR($E48="Bundled",$E48="Energy")),"excluded",IF(OR($H48="Retail Power Marketer",$H48="Community Choice Aggregator",$E48="Energy"),"procurement",IF(OR($H48="Municipal",$H48="Cooperative",$H48="Federal",$H48="State",$H48="Political Subdivision"),"cost_service",IF($H48="Investor Owned",IF(AND(COUNTIF(Parameters!$A$4:$A$33,$G48)>0,COUNTIF(Parameters!$B$4:$B$33,$B48)=0),"procurement","cost_service"),"unclassified")))))) -> cost_service
A49: 2024 | B49: 733 | C49: Appalachian Power Co | D49: A | E49: Bundled | F49: O | G49: WV | H49: Investor Owned | I49: PJM | J49: 776640 | K49: 4632296 | L49: 348946 | M49: 383165 | N49: 3102967 | O49: 67012 | P49: 340280 | Q49: 3883180 | R49: 2180 | S49: . | T49: . | U49: . | V49: 1500085 | W49: 11618443 | X49: 418138 | Y49: =IF(ISNUMBER($W49),$W49,0) -> 11618443 | Z49: =IF(ISNUMBER(SEARCH("Adjustment",$C49)),"excluded",IF($H49="Behind the Meter","excluded",IF(NOT(OR($E49="Bundled",$E49="Energy")),"excluded",IF(OR($H49="Retail Power Marketer",$H49="Community Choice Aggregator",$E49="Energy"),"procurement",IF(OR($H49="Municipal",$H49="Cooperative",$H49="Federal",$H49="State",$H49="Political Subdivision"),"cost_service",IF($H49="Investor Owned",IF(AND(COUNTIF(Parameters!$A$4:$A$33,$G49)>0,COUNTIF(Parameters!$B$4:$B$33,$B49)=0),"procurement","cost_service"),"unclassified")))))) -> cost_service
A50: 2024 | B50: 733 | C50: Appalachian Power Co | D50: C | E50: Delivery | F50: O | G50: VA | H50: Investor Owned | I50: PJM | J50: . | K50: . | L50: . | M50: 820 | N50: 47575 | O50: 47 | P50: 605 | Q50: 255649 | R50: 5 | S50: . | T50: . | U50: . | V50: 1425 | W50: 303224 | X50: 52 | Y50: =IF(ISNUMBER($W50),$W50,0) -> 303224 | Z50: =IF(ISNUMBER(SEARCH("Adjustment",$C50)),"excluded",IF($H50="Behind the Meter","excluded",IF(NOT(OR($E50="Bundled",$E50="Energy")),"excluded",IF(OR($H50="Retail Power Marketer",$H50="Community Choice Aggregator",$E50="Energy"),"procurement",IF(OR($H50="Municipal",$H50="Cooperative",$H50="Federal",$H50="State",$H50="Political Subdivision"),"cost_service",IF($H50="Investor Owned",IF(AND(COUNTIF(Parameters!$A$4:$A$33,$G50)>0,COUNTIF(Parameters!$B$4:$B$33,$B50)=0),"procurement","cost_service"),"unclassified")))))) -> excluded
A51: 2024 | B51: 750 | C51: Arab Electric Coop Inc | D51: A | E51: Bundled | F51: O | G51: AL | H51: Cooperative | I51: TVA | J51: 24986 | K51: 208955 | L51: 14062 | M51: 12392 | N51: 100727 | O51: 2861 | P51: 370 | Q51: 4003 | R51: 2 | S51: 0 | T51: 0 | U51: 0 | V51: 37748 | W51: 313685 | X51: 16925 | Y51: =IF(ISNUMBER($W51),$W51,0) -> 313685 | Z51: =IF(ISNUMBER(SEARCH("Adjustment",$C51)),"excluded",IF($H51="Behind the Meter","excluded",IF(NOT(OR($E51="Bundled",$E51="Energy")),"excluded",IF(OR($H51="Retail Power Marketer",$H51="Community Choice Aggregator",$E51="Energy"),"procurement",IF(OR($H51="Municipal",$H51="Cooperative",$H51="Federal",$H51="State",$H51="Political Subdivision"),"cost_service",IF($H51="Investor Owned",IF(AND(COUNTIF(Parameters!$A$4:$A$33,$G51)>0,COUNTIF(Parameters!$B$4:$B$33,$B51)=0),"procurement","cost_service"),"unclassified")))))) -> cost_service
A52: 2024 | B52: 796 | C52: Arizona Electric Pwr Coop Inc | D52: B | E52: Energy | F52: O | G52: CA | H52: Cooperative | I52: CISO | J52: . | K52: . | L52: . | M52: 18.2 | N52: 809 | O52: 1 | P52: . | Q52: . | R52: . | S52: . | T52: . | U52: . | V52: 18.2 | W52: 809 | X52: 1 | Y52: =IF(ISNUMBER($W52),$W52,0) -> 809 | Z52: =IF(ISNUMBER(SEARCH("Adjustment",$C52)),"excluded",IF($H52="Behind the Meter","excluded",IF(NOT(OR($E52="Bundled",$E52="Energy")),"excluded",IF(OR($H52="Retail Power Marketer",$H52="Community Choice Aggregator",$E52="Energy"),"procurement",IF(OR($H52="Municipal",$H52="Cooperative",$H52="Federal",$H52="State",$H52="Political Subdivision"),"cost_service",IF($H52="Investor Owned",IF(AND(COUNTIF(Parameters!$A$4:$A$33,$G52)>0,COUNTIF(Parameters!$B$4:$B$33,$B52)=0),"procurement","cost_service"),"unclassified")))))) -> procurement
A53: 2024 | B53: 803 | C53: Arizona Public Service Co | D53: A | E53: Bundled | F53: O | G53: AZ | H53: Investor Owned | I53: AZPS | J53: 2562822.5 | K53: 15579131 | L53: 1256120 | M53: 2125533.6 | N53: 16070942 | O53: 141345 | P53: 209390.6 | Q53: 2051331 | R53: 2572 | S53: 0 | T53: 0 | U53: 0 | V53: 4897746.7 | W53: 33701404 | X53: 1400037 | Y53: =IF(ISNUMBER($W53),$W53,0) -> 33701404 | Z53: =IF(ISNUMBER(SEARCH("Adjustment",$C53)),"excluded",IF($H53="Behind the Meter","excluded",IF(NOT(OR($E53="Bundled",$E53="Energy")),"excluded",IF(OR($H53="Retail Power Marketer",$H53="Community Choice Aggregator",$E53="Energy"),"procurement",IF(OR($H53="Municipal",$H53="Cooperative",$H53="Federal",$H53="State",$H53="Political Subdivision"),"cost_service",IF($H53="Investor Owned",IF(AND(COUNTIF(Parameters!$A$4:$A$33,$G53)>0,COUNTIF(Parameters!$B$4:$B$33,$B53)=0),"procurement","cost_service"),"unclassified")))))) -> cost_service
A54: 2024 | B54: 814 | C54: Entergy Arkansas LLC | D54: A | E54: Bundled | F54: O | G54: AR | H54: Investor Owned | I54: MISO | J54: 999636.9 | K54: 7708656 | L54: 608362 | M54: 590191 | N54: 5782232 | O54: 100665 | P54: 632141.6 | Q54: 9932422 | R54: 23636 | S54: 0.8 | T54: 4 | U54: 1 | V54: 2221970.3 | W54: 23423314 | X54: 732664 | Y54: =IF(ISNUMBER($W54),$W54,0) -> 23423314 | Z54: =IF(ISNUMBER(SEARCH("Adjustment",$C54)),"excluded",IF($H54="Behind the Meter","excluded",IF(NOT(OR($E54="Bundled",$E54="Energy")),"excluded",IF(OR($H54="Retail Power Marketer",$H54="Community Choice Aggregator",$E54="Energy"),"procurement",IF(OR($H54="Municipal",$H54="Cooperative",$H54="Federal",$H54="State",$H54="Political Subdivision"),"cost_service",IF($H54="Investor Owned",IF(AND(COUNTIF(Parameters!$A$4:$A$33,$G54)>0,COUNTIF(Parameters!$B$4:$B$33,$B54)=0),"procurement","cost_service"),"unclassified")))))) -> cost_service
A55: 2024 | B55: 814 | C55: Entergy Arkansas LLC | D55: A | E55: Bundled | F55: O | G55: TN | H55: Investor Owned | I55: MISO | J55: 3.7 | K55: 31 | L55: 1 | M55: 4.4 | N55: 24 | O55: 3 | P55: 2.2 | Q55: 9 | R55: 3 | S55: . | T55: . | U55: . | V55: 10.3 | W55: 64 | X55: 7 | Y55: =IF(ISNUMBER($W55),$W55,0) -> 64 | Z55: =IF(ISNUMBER(SEARCH("Adjustment",$C55)),"excluded",IF($H55="Behind the Meter","excluded",IF(NOT(OR($E55="Bundled",$E55="Energy")),"excluded",IF(OR($H55="Retail Power Marketer",$H55="Community Choice Aggregator",$E55="Energy"),"procurement",IF(OR($H55="Municipal",$H55="Cooperative",$H55="Federal",$H55="State",$H55="Political Subdivision"),"cost_service",IF($H55="Investor Owned",IF(AND(COUNTIF(Parameters!$A$4:$A$33,$G55)>0,COUNTIF(Parameters!$B$4:$B$33,$B55)=0),"procurement","cost_service"),"unclassified")))))) -> cost_service
A56: 2024 | B56: 817 | C56: Arkansas Valley Elec Coop Corp | D56: A | E56: Bundled | F56: O | G56: AR | H56: Cooperative | I56: SWPP | J56: 96119.8 | K56: 721279 | L56: 54372 | M56: 22508.1 | N56: 186217 | O56: 4147 | P56: 16641.9 | Q56: 280289 | R56: 48 | S56: 0 | T56: 0 | U56: 0 | V56: 135269.8 | W56: 1187785 | X56: 58567 | Y56: =IF(ISNUMBER($W56),$W56,0) -> 1187785 | Z56: =IF(ISNUMBER(SEARCH("Adjustment",$C56)),"excluded",IF($H56="Behind the Meter","excluded",IF(NOT(OR($E56="Bundled",$E56="Energy")),"excluded",IF(OR($H56="Retail Power Marketer",$H56="Community Choice Aggregator",$E56="Energy"),"procurement",IF(OR($H56="Municipal",$H56="Cooperative",$H56="Federal",$H56="State",$H56="Political Subdivision"),"cost_service",IF($H56="Investor Owned",IF(AND(COUNTIF(Parameters!$A$4:$A$33,$G56)>0,COUNTIF(Parameters!$B$4:$B$33,$B56)=0),"procurement","cost_service"),"unclassified")))))) -> cost_service
A57: 2024 | B57: 817 | C57: Arkansas Valley Elec Coop Corp | D57: A | E57: Bundled | F57: O | G57: OK | H57: Cooperative | I57: SWPP | J57: 7630.9 | K57: 57453 | L57: 4250 | M57: 3405.6 | N57: 31479 | O57: 516 | P57: 0 | Q57: 0 | R57: 0 | S57: 0 | T57: 0 | U57: 0 | V57: 11036.5 | W57: 88932 | X57: 4766 | Y57: =IF(ISNUMBER($W57),$W57,0) -> 88932 | Z57: =IF(ISNUMBER(SEARCH("Adjustment",$C57)),"excluded",IF($H57="Behind the Meter","excluded",IF(NOT(OR($E57="Bundled",$E57="Energy")),"excluded",IF(OR($H57="Retail Power Marketer",$H57="Community Choice Aggregator",$E57="Energy"),"procurement",IF(OR($H57="Municipal",$H57="Cooperative",$H57="Federal",$H57="State",$H57="Political Subdivision"),"cost_service",IF($H57="Investor Owned",IF(AND(COUNTIF(Parameters!$A$4:$A$33,$G57)>0,COUNTIF(Parameters!$B$4:$B$33,$B57)=0),"procurement","cost_service"),"unclassified")))))) -> cost_service
A58: 2024 | B58: 944 | C58: City of Athens - (AL) | D58: A | E58: Bundled | F58: O | G58: AL | H58: Municipal | I58: TVA | J58: 85146 | K58: 695825 | L58: 50985 | M58: 47669 | N58: 407747 | O58: 8122 | P58: 32055 | Q58: 463426 | R58: 14 | S58: 0 | T58: 0 | U58: 0 | V58: 164870 | W58: 1566998 | X58: 59121 | Y58: =IF(ISNUMBER($W58),$W58,0) -> 1566998 | Z58: =IF(ISNUMBER(SEARCH("Adjustment",$C58)),"excluded",IF($H58="Behind the Meter","excluded",IF(NOT(OR($E58="Bundled",$E58="Energy")),"excluded",IF(OR($H58="Retail Power Marketer",$H58="Community Choice Aggregator",$E58="Energy"),"procurement",IF(OR($H58="Municipal",$H58="Cooperative",$H58="Federal",$H58="State",$H58="Political Subdivision"),"cost_service",IF($H58="Investor Owned",IF(AND(COUNTIF(Parameters!$A$4:$A$33,$G58)>0,COUNTIF(Parameters!$B$4:$B$33,$B58)=0),"procurement","cost_service"),"unclassified")))))) -> cost_service
A59: 2024 | B59: 947 | C59: Athens Utility Board | D59: A | E59: Bundled | F59: O | G59: TN | H59: Municipal | I59: TVA | J59: 18977 | K59: 161213 | L59: 11651 | M59: 18877 | N59: 147230 | O59: 2468 | P59: 18919 | Q59: 328142 | R59: 7 | S59: 0 | T59: 0 | U59: 0 | V59: 56773 | W59: 636585 | X59: 14126 | Y59: =IF(ISNUMBER($W59),$W59,0) -> 636585 | Z59: =IF(ISNUMBER(SEARCH("Adjustment",$C59)),"excluded",IF($H59="Behind the Meter","excluded",IF(NOT(OR($E59="Bundled",$E59="Energy")),"excluded",IF(OR($H59="Retail Power Marketer",$H59="Community Choice Aggregator",$E59="Energy"),"procurement",IF(OR($H59="Municipal",$H59="Cooperative",$H59="Federal",$H59="State",$H59="Political Subdivision"),"cost_service",IF($H59="Investor Owned",IF(AND(COUNTIF(Parameters!$A$4:$A$33,$G59)>0,COUNTIF(Parameters!$B$4:$B$33,$B59)=0),"procurement","cost_service"),"unclassified")))))) -> cost_service
A60: 2024 | B60: 963 | C60: Atlantic City Electric Co | D60: A | E60: Bundled | F60: O | G60: NJ | H60: Investor Owned | I60: PJM | J60: 840014.9 | K60: 3587649 | L60: 472020 | M60: 277984.3 | N60: 1419625 | O60: 51306 | P60: 11195.4 | Q60: 81298 | R60: 312 | S60: 0 | T60: 0 | U60: 0 | V60: 1129194.6 | W60: 5088572 | X60: 523638 | Y60: =IF(ISNUMBER($W60),$W60,0) -> 5088572 | Z60: =IF(ISNUMBER(SEARCH("Adjustment",$C60)),"excluded",IF($H60="Behind the Meter","excluded",IF(NOT(OR($E60="Bundled",$E60="Energy")),"excluded",IF(OR($H60="Retail Power Marketer",$H60="Community Choice Aggregator",$E60="Energy"),"procurement",IF(OR($H60="Municipal",$H60="Cooperative",$H60="Federal",$H60="State",$H60="Political Subdivision"),"cost_service",IF($H60="Investor Owned",IF(AND(COUNTIF(Parameters!$A$4:$A$33,$G60)>0,COUNTIF(Parameters!$B$4:$B$33,$B60)=0),"procurement","cost_service"),"unclassified")))))) -> procurement
A61: 2024 | B61: 963 | C61: Atlantic City Electric Co | D61: C | E61: Delivery | F61: O | G61: NJ | H61: Investor Owned | I61: PJM | J61: 27976.6 | K61: 257552 | L61: 34468 | M61: 164954.9 | N61: 2840417 | O61: 14444 | P61: 21205.2 | Q61: 477408 | R61: 225 | S61: 0 | T61: 0 | U61: 0 | V61: 214136.7 | W61: 3575377 | X61: 49137 | Y61: =IF(ISNUMBER($W61),$W61,0) -> 3575377 | Z61: =IF(ISNUMBER(SEARCH("Adjustment",$C61)),"excluded",IF($H61="Behind the Meter","excluded",IF(NOT(OR($E61="Bundled",$E61="Energy")),"excluded",IF(OR($H61="Retail Power Marketer",$H61="Community Choice Aggregator",$E61="Energy"),"procurement",IF(OR($H61="Municipal",$H61="Cooperative",$H61="Federal",$H61="State",$H61="Political Subdivision"),"cost_service",IF($H61="Investor Owned",IF(AND(COUNTIF(Parameters!$A$4:$A$33,$G61)>0,COUNTIF(Parameters!$B$4:$B$33,$B61)=0),"procurement","cost_service"),"unclassified")))))) -> excluded
A62: 2024 | B62: 970 | C62: Homefield Energy | D62: B | E62: Energy | F62: O | G62: IL | H62: Retail Power Marketer | I62: MISO | J62: 137052.5 | K62: 1575796 | L62: 163064 | M62: 235940.1 | N62: 3187220 | O62: 2845 | P62: 1186.6 | Q62: 16090 | R62: 105 | S62: 0 | T62: 0 | U62: 0 | V62: 374179.2 | W62: 4779106 | X62: 166014 | Y62: =IF(ISNUMBER($W62),$W62,0) -> 4779106 | Z62: =IF(ISNUMBER(SEARCH("Adjustment",$C62)),"excluded",IF($H62="Behind the Meter","excluded",IF(NOT(OR($E62="Bundled",$E62="Energy")),"excluded",IF(OR($H62="Retail Power Marketer",$H62="Community Choice Aggregator",$E62="Energy"),"procurement",IF(OR($H62="Municipal",$H62="Cooperative",$H62="Federal",$H62="State",$H62="Political Subdivision"),"cost_service",IF($H62="Investor Owned",IF(AND(COUNTIF(Parameters!$A$4:$A$33,$G62)>0,COUNTIF(Parameters!$B$4:$B$33,$B62)=0),"procurement","cost_service"),"unclassified")))))) -> procurement
A63: 2024 | B63: 994 | C63: City of Auburn - (IN) | D63: A | E63: Bundled | F63: O | G63: IN | H63: Municipal | I63: PJM | J63: 5464.4 | K63: 64148 | L63: 6813 | M63: 2367 | N63: 28735 | O63: 1008 | P63: 44960 | Q63: 256272 | R63: 119 | S63: . | T63: . | U63: . | V63: 52791.4 | W63: 349155 | X63: 7940 | Y63: =IF(ISNUMBER($W63),$W63,0) -> 349155 | Z63: =IF(ISNUMBER(SEARCH("Adjustment",$C63)),"excluded",IF($H63="Behind the Meter","excluded",IF(NOT(OR($E63="Bundled",$E63="Energy")),"excluded",IF(OR($H63="Retail Power Marketer",$H63="Community Choice Aggregator",$E63="Energy"),"procurement",IF(OR($H63="Municipal",$H63="Cooperative",$H63="Federal",$H63="State",$H63="Political Subdivision"),"cost_service",IF($H63="Investor Owned",IF(AND(COUNTIF(Parameters!$A$4:$A$33,$G63)>0,COUNTIF(Parameters!$B$4:$B$33,$B63)=0),"procurement","cost_service"),"unclassified")))))) -> cost_service
A64: 2024 | B64: 1009 | C64: City of Austin - (MN) | D64: A | E64: Bundled | F64: O | G64: MN | H64: Municipal | I64: MISO | J64: 11901 | K64: 77564 | L64: 10795 | M64: 16109 | N64: 131027 | O64: 1214 | P64: 11605 | Q64: 123984 | R64: 1 | S64: . | T64: . | U64: . | V64: 39615 | W64: 332575 | X64: 12010 | Y64: =IF(ISNUMBER($W64),$W64,0) -> 332575 | Z64: =IF(ISNUMBER(SEARCH("Adjustment",$C64)),"excluded",IF($H64="Behind the Meter","excluded",IF(NOT(OR($E64="Bundled",$E64="Energy")),"excluded",IF(OR($H64="Retail Power Marketer",$H64="Community Choice Aggregator",$E64="Energy"),"procurement",IF(OR($H64="Municipal",$H64="Cooperative",$H64="Federal",$H64="State",$H64="Political Subdivision"),"cost_service",IF($H64="Investor Owned",IF(AND(COUNTIF(Parameters!$A$4:$A$33,$G64)>0,COUNTIF(Parameters!$B$4:$B$33,$B64)=0),"procurement","cost_service"),"unclassified")))))) -> cost_service
A65: 2024 | B65: 1015 | C65: Austin Energy | D65: A | E65: Bundled | F65: O | G65: TX | H65: Municipal | I65: ERCO | J65: 638262 | K65: 5074608 | L65: 507291 | M65: 617209.8 | N65: 5909072 | O65: 54586 | P65: 219668.6 | Q65: 3216894 | R65: 127 | S65: 0 | T65: 0 | U65: 0 | V65: 1475140.4 | W65: 14200574 | X65: 562004 | Y65: =IF(ISNUMBER($W65),$W65,0) -> 14200574 | Z65: =IF(ISNUMBER(SEARCH("Adjustment",$C65)),"excluded",IF($H65="Behind the Meter","excluded",IF(NOT(OR($E65="Bundled",$E65="Energy")),"excluded",IF(OR($H65="Retail Power Marketer",$H65="Community Choice Aggregator",$E65="Energy"),"procurement",IF(OR($H65="Municipal",$H65="Cooperative",$H65="Federal",$H65="State",$H65="Political Subdivision"),"cost_service",IF($H65="Investor Owned",IF(AND(COUNTIF(Parameters!$A$4:$A$33,$G65)>0,COUNTIF(Parameters!$B$4:$B$33,$B65)=0),"procurement","cost_service"),"unclassified")))))) -> cost_service
A66: 2024 | B66: 1050 | C66: City of Azusa | D66: A | E66: Bundled | F66: O | G66: CA | H66: Municipal | I66: CISO | J66: 17011 | K66: 89136 | L66: 15599 | M66: 15699 | N66: 83492 | O66: 1957 | P66: 10455 | Q66: 61391 | R66: 27 | S66: . | T66: . | U66: . | V66: 43165 | W66: 234019 | X66: 17583 | Y66: =IF(ISNUMBER($W66),$W66,0) -> 234019 | Z66: =IF(ISNUMBER(SEARCH("Adjustment",$C66)),"excluded",IF($H66="Behind the Meter","excluded",IF(NOT(OR($E66="Bundled",$E66="Energy")),"excluded",IF(OR($H66="Retail Power Marketer",$H66="Community Choice Aggregator",$E66="Energy"),"procurement",IF(OR($H66="Municipal",$H66="Cooperative",$H66="Federal",$H66="State",$H66="Political Subdivision"),"cost_service",IF($H66="Investor Owned",IF(AND(COUNTIF(Parameters!$A$4:$A$33,$G66)>0,COUNTIF(Parameters!$B$4:$B$33,$B66)=0),"procurement","cost_service"),"unclassified")))))) -> cost_service
A67: 2024 | B67: 1149 | C67: Baldwin County El Member Corp | D67: A | E67: Bundled | F67: O | G67: AL | H67: Cooperative | I67: SOCO | J67: 155483 | K67: 1121292 | L67: 83005 | M67: 59304 | N67: 537247 | O67: 8363 | P67: . | Q67: . | R67: . | S67: . | T67: . | U67: . | V67: 214787 | W67: 1658539 | X67: 91368 | Y67: =IF(ISNUMBER($W67),$W67,0) -> 1658539 | Z67: =IF(ISNUMBER(SEARCH("Adjustment",$C67)),"excluded",IF($H67="Behind the Meter","excluded",IF(NOT(OR($E67="Bundled",$E67="Energy")),"excluded",IF(OR($H67="Retail Power Marketer",$H67="Community Choice Aggregator",$E67="Energy"),"procurement",IF(OR($H67="Municipal",$H67="Cooperative",$H67="Federal",$H67="State",$H67="Political Subdivision"),"cost_service",IF($H67="Investor Owned",IF(AND(COUNTIF(Parameters!$A$4:$A$33,$G67)>0,COUNTIF(Parameters!$B$4:$B$33,$B67)=0),"procurement","cost_service"),"unclassified")))))) -> cost_service
A68: 2024 | B68: 1167 | C68: Baltimore Gas & Electric Co | D68: A | E68: Bundled | F68: O | G68: MD | H68: Investor Owned | I68: PJM | J68: 1915002.4 | K68: 10693909 | L68: 1025745 | M68: 456344.2 | N68: 2822301 | O68: 73391 | P68: 19509.2 | Q68: 131159 | R68: 3681 | S68: 0 | T68: 0 | U68: 0 | V68: 2390855.8 | W68: 13647369 | X68: 1102817 | Y68: =IF(ISNUMBER($W68),$W68,0) -> 13647369 | Z68: =IF(ISNUMBER(SEARCH("Adjustment",$C68)),"excluded",IF($H68="Behind the Meter","excluded",IF(NOT(OR($E68="Bundled",$E68="Energy")),"excluded",IF(OR($H68="Retail Power Marketer",$H68="Community Choice Aggregator",$E68="Energy"),"procurement",IF(OR($H68="Municipal",$H68="Cooperative",$H68="Federal",$H68="State",$H68="Political Subdivision"),"cost_service",IF($H68="Investor Owned",IF(AND(COUNTIF(Parameters!$A$4:$A$33,$G68)>0,COUNTIF(Parameters!$B$4:$B$33,$B68)=0),"procurement","cost_service"),"unclassified")))))) -> procurement
A69: 2024 | B69: 1167 | C69: Baltimore Gas & Electric Co | D69: C | E69: Delivery | F69: O | G69: MD | H69: Investor Owned | I69: PJM | J69: 129043.4 | K69: 1987967 | L69: 188355 | M69: 434963.9 | N69: 11760780 | O69: 49081 | P69: 32655.7 | Q69: 1204306 | R69: 2501 | S69: 1408.2 | T69: 165677 | U69: 3 | V69: 598071.2 | W69: 15118730 | X69: 239940 | Y69: =IF(ISNUMBER($W69),$W69,0) -> 15118730 | Z69: =IF(ISNUMBER(SEARCH("Adjustment",$C69)),"excluded",IF($H69="Behind the Meter","excluded",IF(NOT(OR($E69="Bundled",$E69="Energy")),"excluded",IF(OR($H69="Retail Power Marketer",$H69="Community Choice Aggregator",$E69="Energy"),"procurement",IF(OR($H69="Municipal",$H69="Cooperative",$H69="Federal",$H69="State",$H69="Political Subdivision"),"cost_service",IF($H69="Investor Owned",IF(AND(COUNTIF(Parameters!$A$4:$A$33,$G69)>0,COUNTIF(Parameters!$B$4:$B$33,$B69)=0),"procurement","cost_service"),"unclassified")))))) -> excluded
A70: 2024 | B70: 1169 | C70: Bailey County Elec Coop Assn | D70: A | E70: Bundled | F70: O | G70: TX | H70: Cooperative | I70: SWPP | J70: 2216 | K70: 25258 | L70: 3348 | M70: 5019 | N70: 68865 | O70: 860 | P70: 19119 | Q70: 248195 | R70: 4923 | S70: . | T70: . | U70: . | V70: 26354 | W70: 342318 | X70: 9131 | Y70: =IF(ISNUMBER($W70),$W70,0) -> 342318 | Z70: =IF(ISNUMBER(SEARCH("Adjustment",$C70)),"excluded",IF($H70="Behind the Meter","excluded",IF(NOT(OR($E70="Bundled",$E70="Energy")),"excluded",IF(OR($H70="Retail Power Marketer",$H70="Community Choice Aggregator",$E70="Energy"),"procurement",IF(OR($H70="Municipal",$H70="Cooperative",$H70="Federal",$H70="State",$H70="Political Subdivision"),"cost_service",IF($H70="Investor Owned",IF(AND(COUNTIF(Parameters!$A$4:$A$33,$G70)>0,COUNTIF(Parameters!$B$4:$B$33,$B70)=0),"procurement","cost_service"),"unclassified")))))) -> cost_service
A71: 2024 | B71: 1175 | C71: Bandera Electric Coop, Inc | D71: A | E71: Bundled | F71: O | G71: TX | H71: Cooperative | I71: ERCO | J71: 61819 | K71: 498494 | L71: 35346 | M71: 19804 | N71: 189317 | O71: 6612 | P71: 1671 | Q71: 18566 | R71: 65 | S71: . | T71: . | U71: . | V71: 83294 | W71: 706377 | X71: 42023 | Y71: =IF(ISNUMBER($W71),$W71,0) -> 706377 | Z71: =IF(ISNUMBER(SEARCH("Adjustment",$C71)),"excluded",IF($H71="Behind the Meter","excluded",IF(NOT(OR($E71="Bundled",$E71="Energy")),"excluded",IF(OR($H71="Retail Power Marketer",$H71="Community Choice Aggregator",$E71="Energy"),"procurement",IF(OR($H71="Municipal",$H71="Cooperative",$H71="Federal",$H71="State",$H71="Political Subdivision"),"cost_service",IF($H71="Investor Owned",IF(AND(COUNTIF(Parameters!$A$4:$A$33,$G71)>0,COUNTIF(Parameters!$B$4:$B$33,$B71)=0),"procurement","cost_service"),"unclassified")))))) -> cost_service
A72: 2024 | B72: 1179 | C72: Versant Power | D72: A | E72: Bundled | F72: O | G72: ME | H72: Investor Owned | I72: NBSO | J72: 46425 | K72: 175060 | L72: 28935 | M72: 32916.9 | N72: 129769 | O72: 7311 | P72: 858.2 | Q72: 3834 | R72: 11 | S72: 0 | T72: 0 | U72: 0 | V72: 80200.1 | W72: 308663 | X72: 36257 | Y72: =IF(ISNUMBER($W72),$W72,0) -> 308663 | Z72: =IF(ISNUMBER(SEARCH("Adjustment",$C72)),"excluded",IF($H72="Behind the Meter","excluded",IF(NOT(OR($E72="Bundled",$E72="Energy")),"excluded",IF(OR($H72="Retail Power Marketer",$H72="Community Choice Aggregator",$E72="Energy"),"procurement",IF(OR($H72="Municipal",$H72="Cooperative",$H72="Federal",$H72="State",$H72="Political Subdivision"),"cost_service",IF($H72="Investor Owned",IF(AND(COUNTIF(Parameters!$A$4:$A$33,$G72)>0,COUNTIF(Parameters!$B$4:$B$33,$B72)=0),"procurement","cost_service"),"unclassified")))))) -> procurement
A73: 2024 | B73: 1179 | C73: Versant Power | D73: A | E73: Bundled | F73: O | G73: ME | H73: Investor Owned | I73: ISNE | J73: 175796.6 | K73: 616268 | L73: 101697 | M73: 78367.5 | N73: 426820 | O73: 16275 | P73: 5201.2 | Q73: 34312 | R73: 26 | S73: 0 | T73: 0 | U73: 0 | V73: 259365.3 | W73: 1077400 | X73: 117998 | Y73: =IF(ISNUMBER($W73),$W73,0) -> 1077400 | Z73: =IF(ISNUMBER(SEARCH("Adjustment",$C73)),"excluded",IF($H73="Behind the Meter","excluded",IF(NOT(OR($E73="Bundled",$E73="Energy")),"excluded",IF(OR($H73="Retail Power Marketer",$H73="Community Choice Aggregator",$E73="Energy"),"procurement",IF(OR($H73="Municipal",$H73="Cooperative",$H73="Federal",$H73="State",$H73="Political Subdivision"),"cost_service",IF($H73="Investor Owned",IF(AND(COUNTIF(Parameters!$A$4:$A$33,$G73)>0,COUNTIF(Parameters!$B$4:$B$33,$B73)=0),"procurement","cost_service"),"unclassified")))))) -> procurement
A74: 2024 | B74: 1179 | C74: Versant Power | D74: C | E74: Delivery | F74: O | G74: ME | H74: Investor Owned | I74: NBSO | J74: 27.3 | K74: 193 | L74: 29 | M74: 3824.6 | N74: 29535 | O74: 265 | P74: 10025 | Q74: 155945 | R74: 4 | S74: 0 | T74: 0 | U74: 0 | V74: 13876.9 | W74: 185673 | X74: 298 | Y74: =IF(ISNUMBER($W74),$W74,0) -> 185673 | Z74: =IF(ISNUMBER(SEARCH("Adjustment",$C74)),"excluded",IF($H74="Behind the Meter","excluded",IF(NOT(OR($E74="Bundled",$E74="Energy")),"excluded",IF(OR($H74="Retail Power Marketer",$H74="Community Choice Aggregator",$E74="Energy"),"procurement",IF(OR($H74="Municipal",$H74="Cooperative",$H74="Federal",$H74="State",$H74="Political Subdivision"),"cost_service",IF($H74="Investor Owned",IF(AND(COUNTIF(Parameters!$A$4:$A$33,$G74)>0,COUNTIF(Parameters!$B$4:$B$33,$B74)=0),"procurement","cost_service"),"unclassified")))))) -> excluded
A75: 2024 | B75: 1179 | C75: Versant Power | D75: C | E75: Delivery | F75: O | G75: ME | H75: Investor Owned | I75: ISNE | J75: 6591.3 | K75: 40594 | L75: 7245 | M75: 20217.6 | N75: 144616 | O75: 3731 | P75: 14563.7 | Q75: 180541 | R75: 31 | S75: 0 | T75: 0 | U75: 0 | V75: 41372.6 | W75: 365751 | X75: 11007 | Y75: =IF(ISNUMBER($W75),$W75,0) -> 365751 | Z75: =IF(ISNUMBER(SEARCH("Adjustment",$C75)),"excluded",IF($H75="Behind the Meter","excluded",IF(NOT(OR($E75="Bundled",$E75="Energy")),"excluded",IF(OR($H75="Retail Power Marketer",$H75="Community Choice Aggregator",$E75="Energy"),"procurement",IF(OR($H75="Municipal",$H75="Cooperative",$H75="Federal",$H75="State",$H75="Political Subdivision"),"cost_service",IF($H75="Investor Owned",IF(AND(COUNTIF(Parameters!$A$4:$A$33,$G75)>0,COUNTIF(Parameters!$B$4:$B$33,$B75)=0),"procurement","cost_service"),"unclassified")))))) -> excluded
A76: 2024 | B76: 1196 | C76: Village of Baraga - (MI) | D76: A | E76: Bundled | F76: O | G76: MI | H76: Municipal | I76: MISO | J76: 424.7 | K76: 2772 | L76: 555 | M76: 1951.8 | N76: 14206 | O76: 254 | P76: 0 | Q76: 0 | R76: 0 | S76: 0 | T76: 0 | U76: 0 | V76: 2376.5 | W76: 16978 | X76: 809 | Y76: =IF(ISNUMBER($W76),$W76,0) -> 16978 | Z76: =IF(ISNUMBER(SEARCH("Adjustment",$C76)),"excluded",IF($H76="Behind the Meter","excluded",IF(NOT(OR($E76="Bundled",$E76="Energy")),"excluded",IF(OR($H76="Retail Power Marketer",$H76="Community Choice Aggregator",$E76="Energy"),"procurement",IF(OR($H76="Municipal",$H76="Cooperative",$H76="Federal",$H76="State",$H76="Political Subdivision"),"cost_service",IF($H76="Investor Owned",IF(AND(COUNTIF(Parameters!$A$4:$A$33,$G76)>0,COUNTIF(Parameters!$B$4:$B$33,$B76)=0),"procurement","cost_service"),"unclassified")))))) -> cost_service
A77: 2024 | B77: 1251 | C77: Barron Electric Coop | D77: A | E77: Bundled | F77: O | G77: WI | H77: Cooperative | I77: MISO | J77: 30025 | K77: 190990 | L77: 19266 | M77: 3103 | N77: 27675 | O77: 222 | P77: 7171 | Q77: 87706 | R77: 168 | S77: . | T77: . | U77: . | V77: 40299 | W77: 306371 | X77: 19656 | Y77: =IF(ISNUMBER($W77),$W77,0) -> 306371 | Z77: =IF(ISNUMBER(SEARCH("Adjustment",$C77)),"excluded",IF($H77="Behind the Meter","excluded",IF(NOT(OR($E77="Bundled",$E77="Energy")),"excluded",IF(OR($H77="Retail Power Marketer",$H77="Community Choice Aggregator",$E77="Energy"),"procurement",IF(OR($H77="Municipal",$H77="Cooperative",$H77="Federal",$H77="State",$H77="Political Subdivision"),"cost_service",IF($H77="Investor Owned",IF(AND(COUNTIF(Parameters!$A$4:$A$33,$G77)>0,COUNTIF(Parameters!$B$4:$B$33,$B77)=0),"procurement","cost_service"),"unclassified")))))) -> cost_service
A78: 2024 | B78: 1273 | C78: Bartlett Electric Coop, Inc | D78: A | E78: Bundled | F78: O | G78: TX | H78: Cooperative | I78: ERCO | J78: 30344.3 | K78: 188623 | L78: 11527 | M78: 9764.6 | N78: 58796 | O78: 3726 | P78: . | Q78: . | R78: . | S78: . | T78: . | U78: . | V78: 40108.9 | W78: 247419 | X78: 15253 | Y78: =IF(ISNUMBER($W78),$W78,0) -> 247419 | Z78: =IF(ISNUMBER(SEARCH("Adjustment",$C78)),"excluded",IF($H78="Behind the Meter","excluded",IF(NOT(OR($E78="Bundled",$E78="Energy")),"excluded",IF(OR($H78="Retail Power Marketer",$H78="Community Choice Aggregator",$E78="Energy"),"procurement",IF(OR($H78="Municipal",$H78="Cooperative",$H78="Federal",$H78="State",$H78="Political Subdivision"),"cost_service",IF($H78="Investor Owned",IF(AND(COUNTIF(Parameters!$A$4:$A$33,$G78)>0,COUNTIF(Parameters!$B$4:$B$33,$B78)=0),"procurement","cost_service"),"unclassified")))))) -> cost_service
A79: 2024 | B79: 1283 | C79: Bartholomew County Rural E M C | D79: A | E79: Bundled | F79: O | G79: IN | H79: Cooperative | I79: MISO | J79: 22940.4 | K79: 155960 | L79: 11427 | M79: 6318.2 | N79: 47841 | O79: 731 | P79: 21346.2 | Q79: 225890 | R79: 12 | S79: 0 | T79: 0 | U79: 0 | V79: 50604.8 | W79: 429691 | X79: 12170 | Y79: =IF(ISNUMBER($W79),$W79,0) -> 429691 | Z79: =IF(ISNUMBER(SEARCH("Adjustment",$C79)),"excluded",IF($H79="Behind the Meter","excluded",IF(NOT(OR($E79="Bundled",$E79="Energy")),"excluded",IF(OR($H79="Retail Power Marketer",$H79="Community Choice Aggregator",$E79="Energy"),"procurement",IF(OR($H79="Municipal",$H79="Cooperative",$H79="Federal",$H79="State",$H79="Political Subdivision"),"cost_service",IF($H79="Investor Owned",IF(AND(COUNTIF(Parameters!$A$4:$A$33,$G79)>0,COUNTIF(Parameters!$B$4:$B$33,$B79)=0),"procurement","cost_service"),"unclassified")))))) -> cost_service
A80: 2024 | B80: 1300 | C80: City of Bartow - (FL) | D80: A | E80: Bundled | F80: O | G80: FL | H80: Municipal | I80: FPC | J80: 17056.5 | K80: 157492 | L80: 11613 | M80: 8518 | N80: 89833 | O80: 1530 | P80: 6484.1 | Q80: 64218 | R80: 287 | S80: . | T80: . | U80: . | V80: 32058.6 | W80: 311543 | X80: 13430 | Y80: =IF(ISNUMBER($W80),$W80,0) -> 311543 | Z80: =IF(ISNUMBER(SEARCH("Adjustment",$C80)),"excluded",IF($H80="Behind the Meter","excluded",IF(NOT(OR($E80="Bundled",$E80="Energy")),"excluded",IF(OR($H80="Retail Power Marketer",$H80="Community Choice Aggregator",$E80="Energy"),"procurement",IF(OR($H80="Municipal",$H80="Cooperative",$H80="Federal",$H80="State",$H80="Political Subdivision"),"cost_service",IF($H80="Investor Owned",IF(AND(COUNTIF(Parameters!$A$4:$A$33,$G80)>0,COUNTIF(Parameters!$B$4:$B$33,$B80)=0),"procurement","cost_service"),"unclassified")))))) -> cost_service
A81: 2024 | B81: 1307 | C81: Basin Electric Power Coop | D81: A | E81: Bundled | F81: O | G81: ND | H81: Cooperative | I81: SWPP | J81: . | K81: . | L81: . | M81: . | N81: . | O81: . | P81: 56625.2 | Q81: 1170657 | R81: 1 | S81: . | T81: . | U81: . | V81: 56625.2 | W81: 1170657 | X81: 1 | Y81: =IF(ISNUMBER($W81),$W81,0) -> 1170657 | Z81: =IF(ISNUMBER(SEARCH("Adjustment",$C81)),"excluded",IF($H81="Behind the Meter","excluded",IF(NOT(OR($E81="Bundled",$E81="Energy")),"excluded",IF(OR($H81="Retail Power Marketer",$H81="Community Choice Aggregator",$E81="Energy"),"procurement",IF(OR($H81="Municipal",$H81="Cooperative",$H81="Federal",$H81="State",$H81="Political Subdivision"),"cost_service",IF($H81="Investor Owned",IF(AND(COUNTIF(Parameters!$A$4:$A$33,$G81)>0,COUNTIF(Parameters!$B$4:$B$33,$B81)=0),"procurement","cost_service"),"unclassified")))))) -> cost_service
A82: 2024 | B82: 1325 | C82: City of Batavia - (IL) | D82: A | E82: Bundled | F82: O | G82: IL | H82: Municipal | I82: PJM | J82: 12330 | K82: 87561 | L82: 10020 | M82: 15642 | N82: 130597 | O82: 1368 | P82: 17254 | Q82: 184363 | R82: 10 | S82: . | T82: . | U82: . | V82: 45226 | W82: 402521 | X82: 11398 | Y82: =IF(ISNUMBER($W82),$W82,0) -> 402521 | Z82: =IF(ISNUMBER(SEARCH("Adjustment",$C82)),"excluded",IF($H82="Behind the Meter","excluded",IF(NOT(OR($E82="Bundled",$E82="Energy")),"excluded",IF(OR($H82="Retail Power Marketer",$H82="Community Choice Aggregator",$E82="Energy"),"procurement",IF(OR($H82="Municipal",$H82="Cooperative",$H82="Federal",$H82="State",$H82="Political Subdivision"),"cost_service",IF($H82="Investor Owned",IF(AND(COUNTIF(Parameters!$A$4:$A$33,$G82)>0,COUNTIF(Parameters!$B$4:$B$33,$B82)=0),"procurement","cost_service"),"unclassified")))))) -> cost_service
A83: 2024 | B83: 1366 | C83: City of Bay City - (MI) | D83: A | E83: Bundled | F83: O | G83: MI | H83: Municipal | I83: MISO | J83: 19124.1 | K83: 124579 | L83: 18028 | M83: 24793.8 | N83: 131259 | O83: 2205 | P83: 6305.8 | Q83: 53589 | R83: 133 | S83: . | T83: . | U83: . | V83: 50223.7 | W83: 309427 | X83: 20366 | Y83: =IF(ISNUMBER($W83),$W83,0) -> 309427 | Z83: =IF(ISNUMBER(SEARCH("Adjustment",$C83)),"excluded",IF($H83="Behind the Meter","excluded",IF(NOT(OR($E83="Bundled",$E83="Energy")),"excluded",IF(OR($H83="Retail Power Marketer",$H83="Community Choice Aggregator",$E83="Energy"),"procurement",IF(OR($H83="Municipal",$H83="Cooperative",$H83="Federal",$H83="State",$H83="Political Subdivision"),"cost_service",IF($H83="Investor Owned",IF(AND(COUNTIF(Parameters!$A$4:$A$33,$G83)>0,COUNTIF(Parameters!$B$4:$B$33,$B83)=0),"procurement","cost_service"),"unclassified")))))) -> cost_service
A84: 2024 | B84: 1458 | C84: Beauregard Electric Coop, Inc | D84: A | E84: Bundled | F84: O | G84: LA | H84: Cooperative | I84: MISO | J84: 81907 | K84: 598074 | L84: 40051 | M84: 23999 | N84: 176294 | O84: 4455 | P84: 52235 | Q84: 704923 | R84: 4 | S84: . | T84: . | U84: . | V84: 158141 | W84: 1479291 | X84: 44510 | Y84: =IF(ISNUMBER($W84),$W84,0) -> 1479291 | Z84: =IF(ISNUMBER(SEARCH("Adjustment",$C84)),"excluded",IF($H84="Behind the Meter","excluded",IF(NOT(OR($E84="Bundled",$E84="Energy")),"excluded",IF(OR($H84="Retail Power Marketer",$H84="Community Choice Aggregator",$E84="Energy"),"procurement",IF(OR($H84="Municipal",$H84="Cooperative",$H84="Federal",$H84="State",$H84="Political Subdivision"),"cost_service",IF($H84="Investor Owned",IF(AND(COUNTIF(Parameters!$A$4:$A$33,$G84)>0,COUNTIF(Parameters!$B$4:$B$33,$B84)=0),"procurement","cost_service"),"unclassified")))))) -> cost_service
A85: 2024 | B85: 1529 | C85: Beltrami Electric Coop, Inc | D85: A | E85: Bundled | F85: O | G85: MN | H85: Cooperative | I85: MISO | J85: 39669 | K85: 275547 | L85: 20732 | M85: 12338 | N85: 147717 | O85: 1615 | P85: 19 | Q85: 70 | R85: 17 | S85: . | T85: . | U85: . | V85: 52026 | W85: 423334 | X85: 22364 | Y85: =IF(ISNUMBER($W85),$W85,0) -> 423334 | Z85: =IF(ISNUMBER(SEARCH("Adjustment",$C85)),"excluded",IF($H85="Behind the Meter","excluded",IF(NOT(OR($E85="Bundled",$E85="Energy")),"excluded",IF(OR($H85="Retail Power Marketer",$H85="Community Choice Aggregator",$E85="Energy"),"procurement",IF(OR($H85="Municipal",$H85="Cooperative",$H85="Federal",$H85="State",$H85="Political Subdivision"),"cost_service",IF($H85="Investor Owned",IF(AND(COUNTIF(Parameters!$A$4:$A$33,$G85)>0,COUNTIF(Parameters!$B$4:$B$33,$B85)=0),"procurement","cost_service"),"unclassified")))))) -> cost_service
A86: 2024 | B86: 1578 | C86: Benton County | D86: A | E86: Bundled | F86: O | G86: TN | H86: Municipal | I86: TVA | J86: 15567 | K86: 112158 | L86: 8775 | M86: 8168 | N86: 53806 | O86: 1886 | P86: 2668 | Q86: 27312 | R86: 3 | S86: 0 | T86: 0 | U86: 0 | V86: 26403 | W86: 193276 | X86: 10664 | Y86: =IF(ISNUMBER($W86),$W86,0) -> 193276 | Z86: =IF(ISNUMBER(SEARCH("Adjustment",$C86)),"excluded",IF($H86="Behind the Meter","excluded",IF(NOT(OR($E86="Bundled",$E86="Energy")),"excluded",IF(OR($H86="Retail Power Marketer",$H86="Community Choice Aggregator",$E86="Energy"),"procurement",IF(OR($H86="Municipal",$H86="Cooperative",$H86="Federal",$H86="State",$H86="Political Subdivision"),"cost_service",IF($H86="Investor Owned",IF(AND(COUNTIF(Parameters!$A$4:$A$33,$G86)>0,COUNTIF(Parameters!$B$4:$B$33,$B86)=0),"procurement","cost_service"),"unclassified")))))) -> cost_service
A87: 2024 | B87: 1579 | C87: PUD No 1 of Benton County | D87: A | E87: Bundled | F87: O | G87: WA | H87: Political Subdivision | I87: BPAT | J87: 64590.7 | K87: 732971 | L87: 50072 | M87: 39104.9 | N87: 564214 | O87: 6770 | P87: 28517.9 | Q87: 511637 | R87: 985 | S87: . | T87: . | U87: . | V87: 132213.5 | W87: 1808822 | X87: 57827 | Y87: =IF(ISNUMBER($W87),$W87,0) -> 1808822 | Z87: =IF(ISNUMBER(SEARCH("Adjustment",$C87)),"excluded",IF($H87="Behind the Meter","excluded",IF(NOT(OR($E87="Bundled",$E87="Energy")),"excluded",IF(OR($H87="Retail Power Marketer",$H87="Community Choice Aggregator",$E87="Energy"),"procurement",IF(OR($H87="Municipal",$H87="Cooperative",$H87="Federal",$H87="State",$H87="Political Subdivision"),"cost_service",IF($H87="Investor Owned",IF(AND(COUNTIF(Parameters!$A$4:$A$33,$G87)>0,COUNTIF(Parameters!$B$4:$B$33,$B87)=0),"procurement","cost_service"),"unclassified")))))) -> cost_service
A88: 2024 | B88: 1581 | C88: City of Benton - (AR) | D88: A | E88: Bundled | F88: O | G88: AR | H88: Municipal | I88: MISO | J88: 16004 | K88: 155389 | L88: 12972 | M88: 8044 | N88: 89129 | O88: 1777 | P88: 2993 | Q88: 39037 | R88: 7 | S88: . | T88: . | U88: . | V88: 27041 | W88: 283555 | X88: 14756 | Y88: =IF(ISNUMBER($W88),$W88,0) -> 283555 | Z88: =IF(ISNUMBER(SEARCH("Adjustment",$C88)),"excluded",IF($H88="Behind the Meter","excluded",IF(NOT(OR($E88="Bundled",$E88="Energy")),"excluded",IF(OR($H88="Retail Power Marketer",$H88="Community Choice Aggregator",$E88="Energy"),"procurement",IF(OR($H88="Municipal",$H88="Cooperative",$H88="Federal",$H88="State",$H88="Political Subdivision"),"cost_service",IF($H88="Investor Owned",IF(AND(COUNTIF(Parameters!$A$4:$A$33,$G88)>0,COUNTIF(Parameters!$B$4:$B$33,$B88)=0),"procurement","cost_service"),"unclassified")))))) -> cost_service
A89: 2024 | B89: 1582 | C89: City of Benton - (KY) | D89: A | E89: Bundled | F89: O | G89: KY | H89: Municipal | I89: TVA | J89: 3315 | K89: 23554 | L89: 1889 | M89: 4076 | N89: 30935 | O89: 680 | P89: 1263 | Q89: 15345 | R89: 1 | S89: 0 | T89: 0 | U89: 0 | V89: 8654 | W89: 69834 | X89: 2570 | Y89: =IF(ISNUMBER($W89),$W89,0) -> 69834 | Z89: =IF(ISNUMBER(SEARCH("Adjustment",$C89)),"excluded",IF($H89="Behind the Meter","excluded",IF(NOT(OR($E89="Bundled",$E89="Energy")),"excluded",IF(OR($H89="Retail Power Marketer",$H89="Community Choice Aggregator",$E89="Energy"),"procurement",IF(OR($H89="Municipal",$H89="Cooperative",$H89="Federal",$H89="State",$H89="Political Subdivision"),"cost_service",IF($H89="Investor Owned",IF(AND(COUNTIF(Parameters!$A$4:$A$33,$G89)>0,COUNTIF(Parameters!$B$4:$B$33,$B89)=0),"procurement","cost_service"),"unclassified")))))) -> cost_service
A90: 2024 | B90: 1586 | C90: City of Bentonville - (AR) | D90: A | E90: Bundled | F90: O | G90: AR | H90: Municipal | I90: SWPP | J90: 33472 | K90: 287396 | L90: 25103 | M90: 40564 | N90: 448206 | O90: 3921 | P90: . | Q90: . | R90: . | S90: . | T90: . | U90: . | V90: 74036 | W90: 735602 | X90: 29024 | Y90: =IF(ISNUMBER($W90),$W90,0) -> 735602 | Z90: =IF(ISNUMBER(SEARCH("Adjustment",$C90)),"excluded",IF($H90="Behind the Meter","excluded",IF(NOT(OR($E90="Bundled",$E90="Energy")),"excluded",IF(OR($H90="Retail Power Marketer",$H90="Community Choice Aggregator",$E90="Energy"),"procurement",IF(OR($H90="Municipal",$H90="Cooperative",$H90="Federal",$H90="State",$H90="Political Subdivision"),"cost_service",IF($H90="Investor Owned",IF(AND(COUNTIF(Parameters!$A$4:$A$33,$G90)>0,COUNTIF(Parameters!$B$4:$B$33,$B90)=0),"procurement","cost_service"),"unclassified")))))) -> cost_service
A91: 2024 | B91: 1591 | C91: Big Country Electric Coop, Inc | D91: A | E91: Bundled | F91: O | G91: TX | H91: Cooperative | I91: ERCO | J91: 12135.4 | K91: 88439 | L91: 9449 | M91: 24729.2 | N91: 255720 | O91: 3452 | P91: 1274.7 | Q91: 10799 | R91: 695 | S91: . | T91: . | U91: . | V91: 38139.3 | W91: 354958 | X91: 13596 | Y91: =IF(ISNUMBER($W91),$W91,0) -> 354958 | Z91: =IF(ISNUMBER(SEARCH("Adjustment",$C91)),"excluded",IF($H91="Behind the Meter","excluded",IF(NOT(OR($E91="Bundled",$E91="Energy")),"excluded",IF(OR($H91="Retail Power Marketer",$H91="Community Choice Aggregator",$E91="Energy"),"procurement",IF(OR($H91="Municipal",$H91="Cooperative",$H91="Federal",$H91="State",$H91="Political Subdivision"),"cost_service",IF($H91="Investor Owned",IF(AND(COUNTIF(Parameters!$A$4:$A$33,$G91)>0,COUNTIF(Parameters!$B$4:$B$33,$B91)=0),"procurement","cost_service"),"unclassified")))))) -> cost_service
A92: 2024 | B92: 1611 | C92: Messer Energy Services, Inc. | D92: B | E92: Energy | F92: O | G92: DE | H92: Retail Power Marketer | I92: PJM | J92: 0 | K92: 0 | L92: 0 | M92: 0 | N92: 0 | O92: 0 | P92: 7914 | Q92: 178280 | R92: 1 | S92: 0 | T92: 0 | U92: 0 | V92: 7914 | W92: 178280 | X92: 1 | Y92: =IF(ISNUMBER($W92),$W92,0) -> 178280 | Z92: =IF(ISNUMBER(SEARCH("Adjustment",$C92)),"excluded",IF($H92="Behind the Meter","excluded",IF(NOT(OR($E92="Bundled",$E92="Energy")),"excluded",IF(OR($H92="Retail Power Marketer",$H92="Community Choice Aggregator",$E92="Energy"),"procurement",IF(OR($H92="Municipal",$H92="Cooperative",$H92="Federal",$H92="State",$H92="Political Subdivision"),"cost_service",IF($H92="Investor Owned",IF(AND(COUNTIF(Parameters!$A$4:$A$33,$G92)>0,COUNTIF(Parameters!$B$4:$B$33,$B92)=0),"procurement","cost_service"),"unclassified")))))) -> procurement
A93: 2024 | B93: 1611 | C93: Messer Energy Services, Inc. | D93: B | E93: Energy | F93: O | G93: IL | H93: Retail Power Marketer | I93: MISO | J93: 0 | K93: 0 | L93: 0 | M93: 0 | N93: 0 | O93: 0 | P93: 9581 | Q93: 170255 | R93: 3 | S93: 0 | T93: 0 | U93: 0 | V93: 9581 | W93: 170255 | X93: 3 | Y93: =IF(ISNUMBER($W93),$W93,0) -> 170255 | Z93: =IF(ISNUMBER(SEARCH("Adjustment",$C93)),"excluded",IF($H93="Behind the Meter","excluded",IF(NOT(OR($E93="Bundled",$E93="Energy")),"excluded",IF(OR($H93="Retail Power Marketer",$H93="Community Choice Aggregator",$E93="Energy"),"procurement",IF(OR($H93="Municipal",$H93="Cooperative",$H93="Federal",$H93="State",$H93="Political Subdivision"),"cost_service",IF($H93="Investor Owned",IF(AND(COUNTIF(Parameters!$A$4:$A$33,$G93)>0,COUNTIF(Parameters!$B$4:$B$33,$B93)=0),"procurement","cost_service"),"unclassified")))))) -> procurement
A94: 2024 | B94: 1611 | C94: Messer Energy Services, Inc. | D94: B | E94: Energy | F94: O | G94: ME | H94: Retail Power Marketer | I94: ISNE | J94: 0 | K94: 0 | L94: 0 | M94: 0 | N94: 0 | O94: 0 | P94: 5301 | Q94: 94916 | R94: 1 | S94: 0 | T94: 0 | U94: 0 | V94: 5301 | W94: 94916 | X94: 1 | Y94: =IF(ISNUMBER($W94),$W94,0) -> 94916 | Z94: =IF(ISNUMBER(SEARCH("Adjustment",$C94)),"excluded",IF($H94="Behind the Meter","excluded",IF(NOT(OR($E94="Bundled",$E94="Energy")),"excluded",IF(OR($H94="Retail Power Marketer",$H94="Community Choice Aggregator",$E94="Energy"),"procurement",IF(OR($H94="Municipal",$H94="Cooperative",$H94="Federal",$H94="State",$H94="Political Subdivision"),"cost_service",IF($H94="Investor Owned",IF(AND(COUNTIF(Parameters!$A$4:$A$33,$G94)>0,COUNTIF(Parameters!$B$4:$B$33,$B94)=0),"procurement","cost_service"),"unclassified")))))) -> procurement
A95: 2024 | B95: 1611 | C95: Messer Energy Services, Inc. | D95: B | E95: Energy | F95: O | G95: NY | H95: Retail Power Marketer | I95: NYIS | J95: 0 | K95: 0 | L95: 0 | M95: 0 | N95: 0 | O95: 0 | P95: 18 | Q95: 346 | R95: 1 | S95: 0 | T95: 0 | U95: 0 | V95: 18 | W95: 346 | X95: 1 | Y95: =IF(ISNUMBER($W95),$W95,0) -> 346 | Z95: =IF(ISNUMBER(SEARCH("Adjustment",$C95)),"excluded",IF($H95="Behind the Meter","excluded",IF(NOT(OR($E95="Bundled",$E95="Energy")),"excluded",IF(OR($H95="Retail Power Marketer",$H95="Community Choice Aggregator",$E95="Energy"),"procurement",IF(OR($H95="Municipal",$H95="Cooperative",$H95="Federal",$H95="State",$H95="Political Subdivision"),"cost_service",IF($H95="Investor Owned",IF(AND(COUNTIF(Parameters!$A$4:$A$33,$G95)>0,COUNTIF(Parameters!$B$4:$B$33,$B95)=0),"procurement","cost_service"),"unclassified")))))) -> procurement
A96: 2024 | B96: 1611 | C96: Messer Energy Services, Inc. | D96: B | E96: Energy | F96: O | G96: OH | H96: Retail Power Marketer | I96: PJM | J96: 0 | K96: 0 | L96: 0 | M96: 0 | N96: 0 | O96: 0 | P96: 10414 | Q96: 240404 | R96: 5 | S96: 0 | T96: 0 | U96: 0 | V96: 10414 | W96: 240404 | X96: 5 | Y96: =IF(ISNUMBER($W96),$W96,0) -> 240404 | Z96: =IF(ISNUMBER(SEARCH("Adjustment",$C96)),"excluded",IF($H96="Behind the Meter","excluded",IF(NOT(OR($E96="Bundled",$E96="Energy")),"excluded",IF(OR($H96="Retail Power Marketer",$H96="Community Choice Aggregator",$E96="Energy"),"procurement",IF(OR($H96="Municipal",$H96="Cooperative",$H96="Federal",$H96="State",$H96="Political Subdivision"),"cost_service",IF($H96="Investor Owned",IF(AND(COUNTIF(Parameters!$A$4:$A$33,$G96)>0,COUNTIF(Parameters!$B$4:$B$33,$B96)=0),"procurement","cost_service"),"unclassified")))))) -> procurement
A97: 2024 | B97: 1611 | C97: Messer Energy Services, Inc. | D97: B | E97: Energy | F97: O | G97: PA | H97: Retail Power Marketer | I97: PJM | J97: 0 | K97: 0 | L97: 0 | M97: 0 | N97: 0 | O97: 0 | P97: 29609 | Q97: 561049 | R97: 3 | S97: 0 | T97: 0 | U97: 0 | V97: 29609 | W97: 561049 | X97: 3 | Y97: =IF(ISNUMBER($W97),$W97,0) -> 561049 | Z97: =IF(ISNUMBER(SEARCH("Adjustment",$C97)),"excluded",IF($H97="Behind the Meter","excluded",IF(NOT(OR($E97="Bundled",$E97="Energy")),"excluded",IF(OR($H97="Retail Power Marketer",$H97="Community Choice Aggregator",$E97="Energy"),"procurement",IF(OR($H97="Municipal",$H97="Cooperative",$H97="Federal",$H97="State",$H97="Political Subdivision"),"cost_service",IF($H97="Investor Owned",IF(AND(COUNTIF(Parameters!$A$4:$A$33,$G97)>0,COUNTIF(Parameters!$B$4:$B$33,$B97)=0),"procurement","cost_service"),"unclassified")))))) -> procurement
A98: 2024 | B98: 1613 | C98: Berkeley Electric Coop Inc | D98: A | E98: Bundled | F98: O | G98: SC | H98: Cooperative | I98: SC | J98: 235265 | K98: 1575297 | L98: 115117 | M98: 240829 | N98: 3386125 | O98: 18121 | P98: 4263 | Q98: 41760 | R98: 10 | S98: 0 | T98: 0 | U98: 0 | V98: 480357 | W98: 5003182 | X98: 133248 | Y98: =IF(ISNUMBER($W98),$W98,0) -> 5003182 | Z98: =IF(ISNUMBER(SEARCH("Adjustment",$C98)),"excluded",IF($H98="Behind the Meter","excluded",IF(NOT(OR($E98="Bundled",$E98="Energy")),"excluded",IF(OR($H98="Retail Power Marketer",$H98="Community Choice Aggregator",$E98="Energy"),"procurement",IF(OR($H98="Municipal",$H98="Cooperative",$H98="Federal",$H98="State",$H98="Political Subdivision"),"cost_service",IF($H98="Investor Owned",IF(AND(COUNTIF(Parameters!$A$4:$A$33,$G98)>0,COUNTIF(Parameters!$B$4:$B$33,$B98)=0),"procurement","cost_service"),"unclassified")))))) -> cost_service
A99: 2024 | B99: 1625 | C99: Benton Rural Electric Assn | D99: A | E99: Bundled | F99: O | G99: WA | H99: Cooperative | I99: BPAT | J99: 21279.3 | K99: 229481 | L99: 13422 | M99: 12069.9 | N99: 172650 | O99: 1645 | P99: 14599 | Q99: 218406 | R99: 1386 | S99: . | T99: . | U99: . | V99: 47948.2 | W99: 620537 | X99: 16453 | Y99: =IF(ISNUMBER($W99),$W99,0) -> 620537 | Z99: =IF(ISNUMBER(SEARCH("Adjustment",$C99)),"excluded",IF($H99="Behind the Meter","excluded",IF(NOT(OR($E99="Bundled",$E99="Energy")),"excluded",IF(OR($H99="Retail Power Marketer",$H99="Community Choice Aggregator",$E99="Energy"),"procurement",IF(OR($H99="Municipal",$H99="Cooperative",$H99="Federal",$H99="State",$H99="Political Subdivision"),"cost_service",IF($H99="Investor Owned",IF(AND(COUNTIF(Parameters!$A$4:$A$33,$G99)>0,COUNTIF(Parameters!$B$4:$B$33,$B99)=0),"procurement","cost_service"),"unclassified")))))) -> cost_service
A100: 2024 | B100: 1640 | C100: City of Bessemer Utilities | D100: A | E100: Bundled | F100: O | G100: AL | H100: Municipal | I100: TVA | J100: 14276 | K100: 116464 | L100: 9378 | M100: 19580 | N100: 154423 | O100: 1764 | P100: 712 | Q100: 9433 | R100: 1 | S100: 0 | T100: 0 | U100: 0 | V100: 34568 | W100: 280320 | X100: 11143 | Y100: =IF(ISNUMBER($W100),$W100,0) -> 280320 | Z100: =IF(ISNUMBER(SEARCH("Adjustment",$C100)),"excluded",IF($H100="Behind the Meter","excluded",IF(NOT(OR($E100="Bundled",$E100="Energy")),"excluded",IF(OR($H100="Retail Power Marketer",$H100="Community Choice Aggregator",$E100="Energy"),"procurement",IF(OR($H100="Municipal",$H100="Cooperative",$H100="Federal",$H100="State",$H100="Political Subdivision"),"cost_service",IF($H100="Investor Owned",IF(AND(COUNTIF(Parameters!$A$4:$A$33,$G100)>0,COUNTIF(Parameters!$B$4:$B$33,$B100)=0),"procurement","cost_service"),"unclassified")))))) -> cost_service
...

Sheet State Shares
A1: state | B1: cost_service_mwh | C1: procurement_mwh | D1: unclassified_mwh | E1: total_mwh | F1: share_cost_service | G1: share_procurement
A2: AK | B2: =SUMIFS('EIA-861 Sales 2024'!$Y$4:$Y$2819,'EIA-861 Sales 2024'!$G$4:$G$2819,$A2,'EIA-861 Sales 2024'!$Z$4:$Z$2819,"cost_service") -> 5414197 | C2: =SUMIFS('EIA-861 Sales 2024'!$Y$4:$Y$2819,'EIA-861 Sales 2024'!$G$4:$G$2819,$A2,'EIA-861 Sales 2024'!$Z$4:$Z$2819,"procurement") -> 0 | D2: =SUMIFS('EIA-861 Sales 2024'!$Y$4:$Y$2819,'EIA-861 Sales 2024'!$G$4:$G$2819,$A2,'EIA-861 Sales 2024'!$Z$4:$Z$2819,"unclassified") -> 0 | E2: =B2+C2+D2 -> 5414197 | F2: =IF($E2=0,0,B2/$E2) -> 1 | G2: =IF($E2=0,0,C2/$E2) -> 0
A3: AL | B3: =SUMIFS('EIA-861 Sales 2024'!$Y$4:$Y$2819,'EIA-861 Sales 2024'!$G$4:$G$2819,$A3,'EIA-861 Sales 2024'!$Z$4:$Z$2819,"cost_service") -> 86075772 | C3: =SUMIFS('EIA-861 Sales 2024'!$Y$4:$Y$2819,'EIA-861 Sales 2024'!$G$4:$G$2819,$A3,'EIA-861 Sales 2024'!$Z$4:$Z$2819,"procurement") -> 0 | D3: =SUMIFS('EIA-861 Sales 2024'!$Y$4:$Y$2819,'EIA-861 Sales 2024'!$G$4:$G$2819,$A3,'EIA-861 Sales 2024'!$Z$4:$Z$2819,"unclassified") -> 0 | E3: =B3+C3+D3 -> 86075772 | F3: =IF($E3=0,0,B3/$E3) -> 1 | G3: =IF($E3=0,0,C3/$E3) -> 0
A4: AR | B4: =SUMIFS('EIA-861 Sales 2024'!$Y$4:$Y$2819,'EIA-861 Sales 2024'!$G$4:$G$2819,$A4,'EIA-861 Sales 2024'!$Z$4:$Z$2819,"cost_service") -> 49188526 | C4: =SUMIFS('EIA-861 Sales 2024'!$Y$4:$Y$2819,'EIA-861 Sales 2024'!$G$4:$G$2819,$A4,'EIA-861 Sales 2024'!$Z$4:$Z$2819,"procurement") -> 0 | D4: =SUMIFS('EIA-861 Sales 2024'!$Y$4:$Y$2819,'EIA-861 Sales 2024'!$G$4:$G$2819,$A4,'EIA-861 Sales 2024'!$Z$4:$Z$2819,"unclassified") -> 0 | E4: =B4+C4+D4 -> 49188526 | F4: =IF($E4=0,0,B4/$E4) -> 1 | G4: =IF($E4=0,0,C4/$E4) -> 0
A5: AZ | B5: =SUMIFS('EIA-861 Sales 2024'!$Y$4:$Y$2819,'EIA-861 Sales 2024'!$G$4:$G$2819,$A5,'EIA-861 Sales 2024'!$Z$4:$Z$2819,"cost_service") -> 87228368 | C5: =SUMIFS('EIA-861 Sales 2024'!$Y$4:$Y$2819,'EIA-861 Sales 2024'!$G$4:$G$2819,$A5,'EIA-861 Sales 2024'!$Z$4:$Z$2819,"procurement") -> 0 | D5: =SUMIFS('EIA-861 Sales 2024'!$Y$4:$Y$2819,'EIA-861 Sales 2024'!$G$4:$G$2819,$A5,'EIA-861 Sales 2024'!$Z$4:$Z$2819,"unclassified") -> 0 | E5: =B5+C5+D5 -> 87228368 | F5: =IF($E5=0,0,B5/$E5) -> 1 | G5: =IF($E5=0,0,C5/$E5) -> 0
A6: CA | B6: =SUMIFS('EIA-861 Sales 2024'!$Y$4:$Y$2819,'EIA-861 Sales 2024'!$G$4:$G$2819,$A6,'EIA-861 Sales 2024'!$Z$4:$Z$2819,"cost_service") -> 147133678 | C6: =SUMIFS('EIA-861 Sales 2024'!$Y$4:$Y$2819,'EIA-861 Sales 2024'!$G$4:$G$2819,$A6,'EIA-861 Sales 2024'!$Z$4:$Z$2819,"procurement") -> 87940406 | D6: =SUMIFS('EIA-861 Sales 2024'!$Y$4:$Y$2819,'EIA-861 Sales 2024'!$G$4:$G$2819,$A6,'EIA-861 Sales 2024'!$Z$4:$Z$2819,"unclassified") -> 0 | E6: =B6+C6+D6 -> 235074084 | F6: =IF($E6=0,0,B6/$E6) -> 0.62590344 | G6: =IF($E6=0,0,C6/$E6) -> 0.37409656
A7: CO | B7: =SUMIFS('EIA-861 Sales 2024'!$Y$4:$Y$2819,'EIA-861 Sales 2024'!$G$4:$G$2819,$A7,'EIA-861 Sales 2024'!$Z$4:$Z$2819,"cost_service") -> 55242525 | C7: =SUMIFS('EIA-861 Sales 2024'!$Y$4:$Y$2819,'EIA-861 Sales 2024'!$G$4:$G$2819,$A7,'EIA-861 Sales 2024'!$Z$4:$Z$2819,"procurement") -> 0 | D7: =SUMIFS('EIA-861 Sales 2024'!$Y$4:$Y$2819,'EIA-861 Sales 2024'!$G$4:$G$2819,$A7,'EIA-861 Sales 2024'!$Z$4:$Z$2819,"unclassified") -> 0 | E7: =B7+C7+D7 -> 55242525 | F7: =IF($E7=0,0,B7/$E7) -> 1 | G7: =IF($E7=0,0,C7/$E7) -> 0
A8: CT | B8: =SUMIFS('EIA-861 Sales 2024'!$Y$4:$Y$2819,'EIA-861 Sales 2024'!$G$4:$G$2819,$A8,'EIA-861 Sales 2024'!$Z$4:$Z$2819,"cost_service") -> 1420820 | C8: =SUMIFS('EIA-861 Sales 2024'!$Y$4:$Y$2819,'EIA-861 Sales 2024'!$G$4:$G$2819,$A8,'EIA-861 Sales 2024'!$Z$4:$Z$2819,"procurement") -> 24787246 | D8: =SUMIFS('EIA-861 Sales 2024'!$Y$4:$Y$2819,'EIA-861 Sales 2024'!$G$4:$G$2819,$A8,'EIA-861 Sales 2024'!$Z$4:$Z$2819,"unclassified") -> 0 | E8: =B8+C8+D8 -> 26208066 | F8: =IF($E8=0,0,B8/$E8) -> 0.054213081 | G8: =IF($E8=0,0,C8/$E8) -> 0.94578692
A9: DC | B9: =SUMIFS('EIA-861 Sales 2024'!$Y$4:$Y$2819,'EIA-861 Sales 2024'!$G$4:$G$2819,$A9,'EIA-861 Sales 2024'!$Z$4:$Z$2819,"cost_service") -> 0 | C9: =SUMIFS('EIA-861 Sales 2024'!$Y$4:$Y$2819,'EIA-861 Sales 2024'!$G$4:$G$2819,$A9,'EIA-861 Sales 2024'!$Z$4:$Z$2819,"procurement") -> 9751813 | D9: =SUMIFS('EIA-861 Sales 2024'!$Y$4:$Y$2819,'EIA-861 Sales 2024'!$G$4:$G$2819,$A9,'EIA-861 Sales 2024'!$Z$4:$Z$2819,"unclassified") -> 0 | E9: =B9+C9+D9 -> 9751813 | F9: =IF($E9=0,0,B9/$E9) -> 0 | G9: =IF($E9=0,0,C9/$E9) -> 1
A10: DE | B10: =SUMIFS('EIA-861 Sales 2024'!$Y$4:$Y$2819,'EIA-861 Sales 2024'!$G$4:$G$2819,$A10,'EIA-861 Sales 2024'!$Z$4:$Z$2819,"cost_service") -> 3256100 | C10: =SUMIFS('EIA-861 Sales 2024'!$Y$4:$Y$2819,'EIA-861 Sales 2024'!$G$4:$G$2819,$A10,'EIA-861 Sales 2024'!$Z$4:$Z$2819,"procurement") -> 7710796 | D10: =SUMIFS('EIA-861 Sales 2024'!$Y$4:$Y$2819,'EIA-861 Sales 2024'!$G$4:$G$2819,$A10,'EIA-861 Sales 2024'!$Z$4:$Z$2819,"unclassified") -> 0 | E10: =B10+C10+D10 -> 10966896 | F10: =IF($E10=0,0,B10/$E10) -> 0.29690261 | G10: =IF($E10=0,0,C10/$E10) -> 0.70309739
A11: FL | B11: =SUMIFS('EIA-861 Sales 2024'!$Y$4:$Y$2819,'EIA-861 Sales 2024'!$G$4:$G$2819,$A11,'EIA-861 Sales 2024'!$Z$4:$Z$2819,"cost_service") -> 253722435 | C11: =SUMIFS('EIA-861 Sales 2024'!$Y$4:$Y$2819,'EIA-861 Sales 2024'!$G$4:$G$2819,$A11,'EIA-861 Sales 2024'!$Z$4:$Z$2819,"procurement") -> 0 | D11: =SUMIFS('EIA-861 Sales 2024'!$Y$4:$Y$2819,'EIA-861 Sales 2024'!$G$4:$G$2819,$A11,'EIA-861 Sales 2024'!$Z$4:$Z$2819,"unclassified") -> 0 | E11: =B11+C11+D11 -> 253722435 | F11: =IF($E11=0,0,B11/$E11) -> 1 | G11: =IF($E11=0,0,C11/$E11) -> 0
A12: GA | B12: =SUMIFS('EIA-861 Sales 2024'!$Y$4:$Y$2819,'EIA-861 Sales 2024'!$G$4:$G$2819,$A12,'EIA-861 Sales 2024'!$Z$4:$Z$2819,"cost_service") -> 146179036 | C12: =SUMIFS('EIA-861 Sales 2024'!$Y$4:$Y$2819,'EIA-861 Sales 2024'!$G$4:$G$2819,$A12,'EIA-861 Sales 2024'!$Z$4:$Z$2819,"procurement") -> 0 | D12: =SUMIFS('EIA-861 Sales 2024'!$Y$4:$Y$2819,'EIA-861 Sales 2024'!$G$4:$G$2819,$A12,'EIA-861 Sales 2024'!$Z$4:$Z$2819,"unclassified") -> 0 | E12: =B12+C12+D12 -> 146179036 | F12: =IF($E12=0,0,B12/$E12) -> 1 | G12: =IF($E12=0,0,C12/$E12) -> 0
A13: HI | B13: =SUMIFS('EIA-861 Sales 2024'!$Y$4:$Y$2819,'EIA-861 Sales 2024'!$G$4:$G$2819,$A13,'EIA-861 Sales 2024'!$Z$4:$Z$2819,"cost_service") -> 8691377 | C13: =SUMIFS('EIA-861 Sales 2024'!$Y$4:$Y$2819,'EIA-861 Sales 2024'!$G$4:$G$2819,$A13,'EIA-861 Sales 2024'!$Z$4:$Z$2819,"procurement") -> 0 | D13: =SUMIFS('EIA-861 Sales 2024'!$Y$4:$Y$2819,'EIA-861 Sales 2024'!$G$4:$G$2819,$A13,'EIA-861 Sales 2024'!$Z$4:$Z$2819,"unclassified") -> 0 | E13: =B13+C13+D13 -> 8691377 | F13: =IF($E13=0,0,B13/$E13) -> 1 | G13: =IF($E13=0,0,C13/$E13) -> 0
... A52: WY | B52: =SUMIFS('EIA-861 Sales 2024'!$Y$4:$Y$2819,'EIA-861 Sales 2024'!$G$4:$G$2819,$A52,'EIA-861 Sales 2024'!$Z$4:$Z$2819,"cost_service") -> 16066797 | C52: =SUMIFS('EIA-861 Sales 2024'!$Y$4:$Y$2819,'EIA-861 Sales 2024'!$G$4:$G$2819,$A52,'EIA-861 Sales 2024'!$Z$4:$Z$2819,"procurement") -> 0 | D52: =SUMIFS('EIA-861 Sales 2024'!$Y$4:$Y$2819,'EIA-861 Sales 2024'!$G$4:$G$2819,$A52,'EIA-861 Sales 2024'!$Z$4:$Z$2819,"unclassified") -> 0 | E52: =B52+C52+D52 -> 16066797 | F52: =IF($E52=0,0,B52/$E52) -> 1 | G52: =IF($E52=0,0,C52/$E52) -> 0

Sheet US National
A1: region | B1: cost_service_mwh | C1: procurement_mwh | D1: excluded_mwh | E1: total_mwh | F1: share_cost_service | G1: share_procurement
A2: US | B2: =SUMIFS('EIA-861 Sales 2024'!$Y$4:$Y$2819,'EIA-861 Sales 2024'!$Z$4:$Z$2819,"cost_service") -> 2669507383 | C2: =SUMIFS('EIA-861 Sales 2024'!$Y$4:$Y$2819,'EIA-861 Sales 2024'!$Z$4:$Z$2819,"procurement") -> 1165882590 | D2: =SUMIFS('EIA-861 Sales 2024'!$Y$4:$Y$2819,'EIA-861 Sales 2024'!$Z$4:$Z$2819,"excluded") -> 733508256 | E2: =B2+C2 -> 3835389973 | F2: =IF($E2=0,0,B2/$E2) -> 0.69601981 | G2: =IF($E2=0,0,C2/$E2) -> 0.30398019

Sheet SoEDtICoS
A1: Unit: dimensionless (% of demand) | B1: 2021 | C1: 2022 | D1: 2023 | E1: 2024 | F1: 2025 | G1: 2026 | H1: 2027 | I1: 2028 | J1: 2029 | K1: 2030 | L1: 2031 | M1: 2032 | N1: 2033 | O1: 2034 | P1: 2035 | Q1: 2036 | R1: 2037 | S1: 2038 | T1: 2039 | U1: 2040 | V1: 2041 | W1: 2042 | X1: 2043 | Y1: 2044 | Z1: 2045 | AA1: 2046 | AB1: 2047 | AC1: 2048 | AD1: 2049 | AE1: 2050
A2: Share that is Cost of Service | B2: =ROUND('US National'!$F$2,3) -> 0.696 | C2: =ROUND('US National'!$F$2,3) -> 0.696 | D2: =ROUND('US National'!$F$2,3) -> 0.696 | E2: =ROUND('US National'!$F$2,3) -> 0.696 | F2: =ROUND('US National'!$F$2,3) -> 0.696 | G2: =ROUND('US National'!$F$2,3) -> 0.696 | H2: =ROUND('US National'!$F$2,3) -> 0.696 | I2: =ROUND('US National'!$F$2,3) -> 0.696 | ... AE2: =ROUND('US National'!$F$2,3) -> 0.696
