Workbook

Sheet About
A1: TTS Transportation Technology Shareweights
A3: Source: | B3: Onroad modes
B4: See supporting Python calibration file and excel/csv files in this folder.
B5: Given logit exponents from the GCAM model, we use a solver to solve
B6: for historical shareweights given recent sales data. We then allow the
B7: shareweights for BEV and PHEV technologies to grow, as explained below.
B9: passenger rail
B10: See data from EPS file trans/SYVbT
A12: Notes
A13: This variable provides the shareweights used in the modified logit equation for vehicle
A14: technology selection. We base them on estimated potential maximum sales shares in each year.
A15: For more on this, see the "Unmodified Logit" equation description at:
A16: https://jgcri.github.io/gcam-doc/choice.html
A18: When adapting the model to a new country or region, it may be helpful
A19: to calibrate this variable after replacing the input data for other variables.
A21: The solver we used is saved as transport_calibration.py in the TTS folder. It is set up
A22: to take in data on the cost per thing*mile for each vehicle type (taken from Vensim),
A23: the observed sales share (from historical data sets), the exponent (trans/TTLE), and
A24: the number of vehicles of that type demanded each year (taken from Vensim).
A25: The file calibration_parameters specifies all those pieces of input data. Sources for the
... A37: such as those from ICCT.
B39: passenger LDVs
B40: The historical data we use for calibration is for states that do not have
B41: their own vehicle standards (ACCI) that put an additional constraint on sales
B42: that is not purely cost-based. This gives us our 2024 and 2025 shareweights.
B44: passenger rail
B45: We use calculated data from SYVbT to calculate the historical sales shares.
A55: Calibration record (2026-10-16)
A56: On-road anchors (Data tab columns D-E) rewritten by calibration/steps/03-trans-shareweights/solve_base_year.py:
A57: logit inversion at the start year from 'BAU New Vehicle Cost per Mile' in the BAU export and observed technology shares
A58: (calibration/benchmarks/vehicle-technology-shares.csv), ZEV-mandate correction for passenger LDVs (3 passes), then the
A59: existing s-curve formulas carry the trajectory to the unchanged 2050 targets. Confirmed by a headless run after the third pass.
A60: TTS-LDVs-frgt hydrogen vehicle: weight set to 0 - observed share unreachable at placeholder cost inputs (step 3a); provisional
A61: TTS-HDVs-frgt hydrogen vehicle: weight set to 0 - observed share unreachable at placeholder cost inputs (step 3a); provisional
A62: TTS-LDVs-psgr natural gas vehicle: IT-year cell set to =E11 (was an s-curve formula)
A63: TTS-LDVs-psgr gasoline vehicle: IT-year cell set to =E12 (was an s-curve formula)
A64: TTS-LDVs-psgr diesel vehicle: IT-year cell set to =E13 (was an s-curve formula)
A65: TTS-LDVs-psgr plugin hybrid vehicle: 2050 target pinned at its pre-calibration value 0.102391 (was =D14/D10*F10)
A66: TTS-LDVs-psgr LPG vehicle: IT-year cell set to =E15 (was an s-curve formula)
... A70: Passenger rail (2026-10-19): Data!E52 and E55 now read the solved shareweights on 'Calibration rail' (step 3a, observed 2015-2024 deliveries, 8.3% diesel) instead of the start-year fleet shares; pasted SYVbT-passenger refreshed.

Sheet Calibration rail
A1: Passenger-rail shareweights at the start year, solved by eps-calibrate step 3a (solve_base_year.py: logit inversion from 'BAU New Vehicle Cost per Mile' in a BAU export and the observed new-vehicle shares), 2026-10-19. Observed shares: vehicles delivered 2015-2024, NTD transit + Amtrak, 376 diesel of 4,528 (vehicle-vintaging-4.0.7/data/fleet-utilization/ntd-energy/rail_purchase_share.py). Held flat through 2050.
A3: technology | B3: observed share of new vehicles | C3: shareweight (solved)
A4: battery electric vehicle | B4: 0.917 | C4: 1
A5: diesel vehicle | B5: 0.083 | C5: 0.10755845

Sheet SYVbT-passenger
A1: Number of Vehicles | B1: battery electric vehicle | C1: natural gas vehicle | D1: gasoline vehicle | E1: diesel vehicle | F1: plugin hybrid vehicle | G1: LPG vehicle | H1: hydrogen vehicle
A2: LDVs | B2: 4769953 | C2: 14506 | D2: 257649823 | E2: 1553093 | F2: 1417825 | G2: 13525 | H2: 17094
A3: HDVs | B3: 2445 | C3: 67549 | D3: 53161 | E3: 422350 | F3: 0 | G3: 24746 | H3: 91
A4: aircraft | B4: 0 | C4: 0 | D4: 0 | E4: 6767 | F4: 0 | G4: 0 | H4: 0
A5: rail | B5: 18776 | C5: 0 | D5: 0 | E5: 6889 | F5: 0 | G5: 0 | H5: 0
A6: ships | B6: 0 | C6: 0 | D6: 9385963 | E6: 2288110 | F6: 0 | G6: 0 | H6: 0
A7: motorbikes | B7: 0 | C7: 0 | D7: 9261249 | E7: 0 | F7: 0 | G7: 0 | H7: 0

Sheet Data
A1: We use sigmoidal interpolation for relatively new technologies (battery electric vehicles, natural gas vehicles, and | H1: Sigmoidal Curve Values for Vehicle Technologies (all except battery electric passenger LDVs) | N1: Sigmoidal Curve Values for battery electric passenger LDV Technologies | Q1: Sigmoidal Curve Values for battery electric freight HDV Technologies | T1: Sigmoidal Curve Values for PHEV passenger LDV Technologies | W1: Sigmoidal Curve Values for battery electric/PHEV passenger HDV and freight LDV Technologies
A2: plugin hybrid vehicles) and linear interpolation for other vehicle technologies. Technologies with constant values | H2: L | I2: 1 | N2: L | O2: 1 | Q2: L | R2: 1 | T2: L | U2: 1 | W2: L | X2: 1
A3: do not require interpolation. | H3: k | I3: -0.3 | N3: k | O3: -0.3 | P3: -0.35 | Q3: k | R3: -0.3 | T3: k | U3: -0.4 | W3: k | X3: -0.3
A4: The values (to the right) that define the shape of the sigmoidal curve are assumptions, which neatly approach the | H4: Xo | I4: -16 | N4: Xo | O4: -11 | P4: -10 | Q4: Xo | R4: -12 | T4: Xo | U4: -11 | W4: Xo | X4: -14
A5: specified 2050 max sales share with a flattening curve. (Of course, linear interpolation is similarly an assumption.)
E6: Max Potential Sales Share | F6: Max Potential Sales Share | G6: Interpolation Method
C7: Psgr LDVs only | E7: 2020 | F7: 2050
D8: 2024 and 2025 shareweights for onroad vehicle types copied/pasted from the Python solver outputs, explained on the About page | G8: *for passenger LDVs only, see Assumptions page
A9: Vehicle Type | B9: Cargo Type | C9: Vehicle Technology | D9: 2024 | E9: 2025 | F9: 2050 | I9: 2024 | J9: =E9 -> 2025 | K9: =J9+1 -> 2026 | L9: =K9+1 -> 2027 | M9: =L9+1 -> 2028 | N9: =M9+1 -> 2029 | O9: =N9+1 -> 2030 | P9: =O9+1 -> 2031 | Q9: =P9+1 -> 2032 | R9: =Q9+1 -> 2033 | ... AI9: =AH9+1 -> 2050
A10: LDVs | B10: passenger | C10: battery electric vehicle | D10: 0.14828895 | E10: 0.14828895 | F10: 1 | G10: =IF(E10=F10,"n/a",IF(OR(C10="battery electric vehicle",C10="natural gas vehicle",C10="plugin hybrid vehicle"),"s-curve","linear")) -> s-curve | I10: =D10 -> 0.14828895 | J10: =E10 -> 0.14828895 | K10: =IF($G10="s-curve",$E10+($F10-$E10)*$O$2/(1+EXP($O$3*(COUNT($K$9:K$9)+$O$4))),TREND($E10:$F10,$E$9:$F$9,K$9)) -> 0.18868209 | L10: =IF($G10="s-curve",$E10+($F10-$E10)*$O$2/(1+EXP($O$3*(COUNT($K$9:L$9)+$O$4))),TREND($E10:$F10,$E$9:$F$9,L$9)) -> 0.20192405 | M10: =IF($G10="s-curve",$E10+($F10-$E10)*$O$2/(1+EXP($O$3*(COUNT($K$9:M$9)+$O$4))),TREND($E10:$F10,$E$9:$F$9,M$9)) -> 0.21912805 | N10: =IF($G10="s-curve",$E10+($F10-$E10)*$O$2/(1+EXP($O$3*(COUNT($K$9:N$9)+$O$4))),TREND($E10:$F10,$E$9:$F$9,N$9)) -> 0.24120792 | O10: =IF($G10="s-curve",$E10+($F10-$E10)*$O$2/(1+EXP($O$3*(COUNT($K$9:O$9)+$O$4))),TREND($E10:$F10,$E$9:$F$9,O$9)) -> 0.26910507 | P10: =IF($G10="s-curve",$E10+($F10-$E10)*$O$2/(1+EXP($O$3*(COUNT($K$9:P$9)+$O$4))),TREND($E10:$F10,$E$9:$F$9,P$9)) -> 0.30366278 | Q10: =IF($G10="s-curve",$E10+($F10-$E10)*$O$2/(1+EXP($O$3*(COUNT($K$9:Q$9)+$O$4))),TREND($E10:$F10,$E$9:$F$9,Q$9)) -> 0.34543895 | R10: =IF($G10="s-curve",$E10+($F10-$E10)*$O$2/(1+EXP($O$3*(COUNT($K$9:R$9)+$O$4))),TREND($E10:$F10,$E$9:$F$9,R$9)) -> 0.39447645 | ... AI10: =IF($G10="s-curve",$E10+($F10-$E10)*$O$2/(1+EXP($O$3*(COUNT($K$9:AI$9)+$O$4))),TREND($E10:$F10,$E$9:$F$9,AI$9)) -> 0.98741679
C11: natural gas vehicle | D11: 0.00010097 | E11: 0.00010097 | F11: =E11 -> 0.00010097 | G11: =IF(E11=F11,"n/a",IF(OR(C11="battery electric vehicle",C11="natural gas vehicle",C11="plugin hybrid vehicle"),"s-curve","linear")) -> n/a | I11: =E11 -> 0.00010097 | J11: =E11 -> 0.00010097 | K11: =IF($G11="s-curve",$E11+($F11-$E11)*$I$2/(1+EXP($I$3*(COUNT($I$9:K$9)+$I$4))),TREND($E11:$F11,$E$9:$F$9,K$9)) -> 0.00010097 | L11: =IF($G11="s-curve",$E11+($F11-$E11)*$I$2/(1+EXP($I$3*(COUNT($I$9:L$9)+$I$4))),TREND($E11:$F11,$E$9:$F$9,L$9)) -> 0.00010097 | M11: =IF($G11="s-curve",$E11+($F11-$E11)*$I$2/(1+EXP($I$3*(COUNT($I$9:M$9)+$I$4))),TREND($E11:$F11,$E$9:$F$9,M$9)) -> 0.00010097 | N11: =IF($G11="s-curve",$E11+($F11-$E11)*$I$2/(1+EXP($I$3*(COUNT($I$9:N$9)+$I$4))),TREND($E11:$F11,$E$9:$F$9,N$9)) -> 0.00010097 | O11: =IF($G11="s-curve",$E11+($F11-$E11)*$I$2/(1+EXP($I$3*(COUNT($I$9:O$9)+$I$4))),TREND($E11:$F11,$E$9:$F$9,O$9)) -> 0.00010097 | P11: =IF($G11="s-curve",$E11+($F11-$E11)*$I$2/(1+EXP($I$3*(COUNT($I$9:P$9)+$I$4))),TREND($E11:$F11,$E$9:$F$9,P$9)) -> 0.00010097 | Q11: =IF($G11="s-curve",$E11+($F11-$E11)*$I$2/(1+EXP($I$3*(COUNT($I$9:Q$9)+$I$4))),TREND($E11:$F11,$E$9:$F$9,Q$9)) -> 0.00010097 | R11: =IF($G11="s-curve",$E11+($F11-$E11)*$I$2/(1+EXP($I$3*(COUNT($I$9:R$9)+$I$4))),TREND($E11:$F11,$E$9:$F$9,R$9)) -> 0.00010097 | ... AI11: =IF($G11="s-curve",$E11+($F11-$E11)*$I$2/(1+EXP($I$3*(COUNT($I$9:AI$9)+$I$4))),TREND($E11:$F11,$E$9:$F$9,AI$9)) -> 0.00010097
C12: gasoline vehicle | D12: 1 | E12: 1 | F12: 1 | G12: =IF(E12=F12,"n/a",IF(OR(C12="battery electric vehicle",C12="natural gas vehicle",C12="plugin hybrid vehicle"),"s-curve","linear")) -> n/a | I12: =E12 -> 1 | J12: =E12 -> 1 | K12: =IF($G12="s-curve",$E12+($F12-$E12)*$I$2/(1+EXP($I$3*(COUNT($I$9:K$9)+$I$4))),TREND($E12:$F12,$E$9:$F$9,K$9)) -> 1 | L12: =IF($G12="s-curve",$E12+($F12-$E12)*$I$2/(1+EXP($I$3*(COUNT($I$9:L$9)+$I$4))),TREND($E12:$F12,$E$9:$F$9,L$9)) -> 1 | M12: =IF($G12="s-curve",$E12+($F12-$E12)*$I$2/(1+EXP($I$3*(COUNT($I$9:M$9)+$I$4))),TREND($E12:$F12,$E$9:$F$9,M$9)) -> 1 | N12: =IF($G12="s-curve",$E12+($F12-$E12)*$I$2/(1+EXP($I$3*(COUNT($I$9:N$9)+$I$4))),TREND($E12:$F12,$E$9:$F$9,N$9)) -> 1 | O12: =IF($G12="s-curve",$E12+($F12-$E12)*$I$2/(1+EXP($I$3*(COUNT($I$9:O$9)+$I$4))),TREND($E12:$F12,$E$9:$F$9,O$9)) -> 1 | P12: =IF($G12="s-curve",$E12+($F12-$E12)*$I$2/(1+EXP($I$3*(COUNT($I$9:P$9)+$I$4))),TREND($E12:$F12,$E$9:$F$9,P$9)) -> 1 | Q12: =IF($G12="s-curve",$E12+($F12-$E12)*$I$2/(1+EXP($I$3*(COUNT($I$9:Q$9)+$I$4))),TREND($E12:$F12,$E$9:$F$9,Q$9)) -> 1 | R12: =IF($G12="s-curve",$E12+($F12-$E12)*$I$2/(1+EXP($I$3*(COUNT($I$9:R$9)+$I$4))),TREND($E12:$F12,$E$9:$F$9,R$9)) -> 1 | ... AI12: =IF($G12="s-curve",$E12+($F12-$E12)*$I$2/(1+EXP($I$3*(COUNT($I$9:AI$9)+$I$4))),TREND($E12:$F12,$E$9:$F$9,AI$9)) -> 1
C13: diesel vehicle | D13: 0.06738296 | E13: 0.06738296 | F13: =E13 -> 0.06738296 | G13: =IF(E13=F13,"n/a",IF(OR(C13="battery electric vehicle",C13="natural gas vehicle",C13="plugin hybrid vehicle"),"s-curve","linear")) -> n/a | I13: =E13 -> 0.06738296 | J13: =E13 -> 0.06738296 | K13: =IF($G13="s-curve",$E13+($F13-$E13)*$I$2/(1+EXP($I$3*(COUNT($I$9:K$9)+$I$4))),TREND($E13:$F13,$E$9:$F$9,K$9)) -> 0.06738296 | L13: =IF($G13="s-curve",$E13+($F13-$E13)*$I$2/(1+EXP($I$3*(COUNT($I$9:L$9)+$I$4))),TREND($E13:$F13,$E$9:$F$9,L$9)) -> 0.06738296 | M13: =IF($G13="s-curve",$E13+($F13-$E13)*$I$2/(1+EXP($I$3*(COUNT($I$9:M$9)+$I$4))),TREND($E13:$F13,$E$9:$F$9,M$9)) -> 0.06738296 | N13: =IF($G13="s-curve",$E13+($F13-$E13)*$I$2/(1+EXP($I$3*(COUNT($I$9:N$9)+$I$4))),TREND($E13:$F13,$E$9:$F$9,N$9)) -> 0.06738296 | O13: =IF($G13="s-curve",$E13+($F13-$E13)*$I$2/(1+EXP($I$3*(COUNT($I$9:O$9)+$I$4))),TREND($E13:$F13,$E$9:$F$9,O$9)) -> 0.06738296 | P13: =IF($G13="s-curve",$E13+($F13-$E13)*$I$2/(1+EXP($I$3*(COUNT($I$9:P$9)+$I$4))),TREND($E13:$F13,$E$9:$F$9,P$9)) -> 0.06738296 | Q13: =IF($G13="s-curve",$E13+($F13-$E13)*$I$2/(1+EXP($I$3*(COUNT($I$9:Q$9)+$I$4))),TREND($E13:$F13,$E$9:$F$9,Q$9)) -> 0.06738296 | R13: =IF($G13="s-curve",$E13+($F13-$E13)*$I$2/(1+EXP($I$3*(COUNT($I$9:R$9)+$I$4))),TREND($E13:$F13,$E$9:$F$9,R$9)) -> 0.06738296 | ... AI13: =IF($G13="s-curve",$E13+($F13-$E13)*$I$2/(1+EXP($I$3*(COUNT($I$9:AI$9)+$I$4))),TREND($E13:$F13,$E$9:$F$9,AI$9)) -> 0.06738296
C14: plugin hybrid vehicle | D14: 0.014073499 | E14: 0.014073499 | F14: 0.10239067 | G14: =IF(E14=F14,"n/a",IF(OR(C14="battery electric vehicle",C14="natural gas vehicle",C14="plugin hybrid vehicle",C14="hydrogen vehicle"),"s-curve","linear")) -> s-curve | I14: =D14 -> 0.014073499 | J14: =E14 -> 0.014073499 | K14: =IF($G14="s-curve",$E14+($F14-$E14)*$U$2/(1+EXP($U$3*(COUNT($I$9:K$9)+$U$4))),TREND($E14:$F14,$E$9:$F$9,K$9)) -> 0.017532505 | L14: =IF($G14="s-curve",$E14+($F14-$E14)*$U$2/(1+EXP($U$3*(COUNT($I$9:L$9)+$U$4))),TREND($E14:$F14,$E$9:$F$9,L$9)) -> 0.019136208 | M14: =IF($G14="s-curve",$E14+($F14-$E14)*$U$2/(1+EXP($U$3*(COUNT($I$9:M$9)+$U$4))),TREND($E14:$F14,$E$9:$F$9,M$9)) -> 0.021419076 | N14: =IF($G14="s-curve",$E14+($F14-$E14)*$U$2/(1+EXP($U$3*(COUNT($I$9:N$9)+$U$4))),TREND($E14:$F14,$E$9:$F$9,N$9)) -> 0.024601163 | O14: =IF($G14="s-curve",$E14+($F14-$E14)*$U$2/(1+EXP($U$3*(COUNT($I$9:O$9)+$U$4))),TREND($E14:$F14,$E$9:$F$9,O$9)) -> 0.028909159 | P14: =IF($G14="s-curve",$E14+($F14-$E14)*$U$2/(1+EXP($U$3*(COUNT($I$9:P$9)+$U$4))),TREND($E14:$F14,$E$9:$F$9,P$9)) -> 0.034516734 | Q14: =IF($G14="s-curve",$E14+($F14-$E14)*$U$2/(1+EXP($U$3*(COUNT($I$9:Q$9)+$U$4))),TREND($E14:$F14,$E$9:$F$9,Q$9)) -> 0.041454075 | R14: =IF($G14="s-curve",$E14+($F14-$E14)*$U$2/(1+EXP($U$3*(COUNT($I$9:R$9)+$U$4))),TREND($E14:$F14,$E$9:$F$9,R$9)) -> 0.049516268 | ... AI14: =IF($G14="s-curve",$E14+($F14-$E14)*$U$2/(1+EXP($U$3*(COUNT($I$9:AI$9)+$U$4))),TREND($E14:$F14,$E$9:$F$9,AI$9)) -> 0.10224417
C15: LPG vehicle | D15: 0 | E15: 0 | F15: =E15 -> 0 | G15: =IF(E15=F15,"n/a",IF(OR(C15="battery electric vehicle",C15="natural gas vehicle",C15="plugin hybrid vehicle",C15="hydrogen vehicle"),"s-curve","linear")) -> n/a | I15: =E15 -> 0 | J15: =E15 -> 0 | K15: =IF($G15="s-curve",$E15+($F15-$E15)*$I$2/(1+EXP($I$3*(COUNT($I$9:K$9)+$I$4))),TREND($E15:$F15,$E$9:$F$9,K$9)) -> 0 | L15: =IF($G15="s-curve",$E15+($F15-$E15)*$I$2/(1+EXP($I$3*(COUNT($I$9:L$9)+$I$4))),TREND($E15:$F15,$E$9:$F$9,L$9)) -> 0 | M15: =IF($G15="s-curve",$E15+($F15-$E15)*$I$2/(1+EXP($I$3*(COUNT($I$9:M$9)+$I$4))),TREND($E15:$F15,$E$9:$F$9,M$9)) -> 0 | N15: =IF($G15="s-curve",$E15+($F15-$E15)*$I$2/(1+EXP($I$3*(COUNT($I$9:N$9)+$I$4))),TREND($E15:$F15,$E$9:$F$9,N$9)) -> 0 | O15: =IF($G15="s-curve",$E15+($F15-$E15)*$I$2/(1+EXP($I$3*(COUNT($I$9:O$9)+$I$4))),TREND($E15:$F15,$E$9:$F$9,O$9)) -> 0 | P15: =IF($G15="s-curve",$E15+($F15-$E15)*$I$2/(1+EXP($I$3*(COUNT($I$9:P$9)+$I$4))),TREND($E15:$F15,$E$9:$F$9,P$9)) -> 0 | Q15: =IF($G15="s-curve",$E15+($F15-$E15)*$I$2/(1+EXP($I$3*(COUNT($I$9:Q$9)+$I$4))),TREND($E15:$F15,$E$9:$F$9,Q$9)) -> 0 | R15: =IF($G15="s-curve",$E15+($F15-$E15)*$I$2/(1+EXP($I$3*(COUNT($I$9:R$9)+$I$4))),TREND($E15:$F15,$E$9:$F$9,R$9)) -> 0 | ... AI15: =IF($G15="s-curve",$E15+($F15-$E15)*$I$2/(1+EXP($I$3*(COUNT($I$9:AI$9)+$I$4))),TREND($E15:$F15,$E$9:$F$9,AI$9)) -> 0
C16: hydrogen vehicle | D16: 0 | E16: 0 | F16: =E16 -> 0 | G16: =IF(E16=F16,"n/a",IF(OR(C16="battery electric vehicle",C16="natural gas vehicle",C16="plugin hybrid vehicle",C16="hydrogen vehicle"),"s-curve","linear")) -> n/a | I16: =E16 -> 0 | J16: =E16 -> 0 | K16: =IF($G16="s-curve",$E16+($F16-$E16)*$I$2/(1+EXP($I$3*(COUNT($I$9:K$9)+$I$4))),TREND($E16:$F16,$E$9:$F$9,K$9)) -> 0 | L16: =IF($G16="s-curve",$E16+($F16-$E16)*$I$2/(1+EXP($I$3*(COUNT($I$9:L$9)+$I$4))),TREND($E16:$F16,$E$9:$F$9,L$9)) -> 0 | M16: =IF($G16="s-curve",$E16+($F16-$E16)*$I$2/(1+EXP($I$3*(COUNT($I$9:M$9)+$I$4))),TREND($E16:$F16,$E$9:$F$9,M$9)) -> 0 | N16: =IF($G16="s-curve",$E16+($F16-$E16)*$I$2/(1+EXP($I$3*(COUNT($I$9:N$9)+$I$4))),TREND($E16:$F16,$E$9:$F$9,N$9)) -> 0 | O16: =IF($G16="s-curve",$E16+($F16-$E16)*$I$2/(1+EXP($I$3*(COUNT($I$9:O$9)+$I$4))),TREND($E16:$F16,$E$9:$F$9,O$9)) -> 0 | P16: =IF($G16="s-curve",$E16+($F16-$E16)*$I$2/(1+EXP($I$3*(COUNT($I$9:P$9)+$I$4))),TREND($E16:$F16,$E$9:$F$9,P$9)) -> 0 | Q16: =IF($G16="s-curve",$E16+($F16-$E16)*$I$2/(1+EXP($I$3*(COUNT($I$9:Q$9)+$I$4))),TREND($E16:$F16,$E$9:$F$9,Q$9)) -> 0 | R16: =IF($G16="s-curve",$E16+($F16-$E16)*$I$2/(1+EXP($I$3*(COUNT($I$9:R$9)+$I$4))),TREND($E16:$F16,$E$9:$F$9,R$9)) -> 0 | ... AI16: =IF($G16="s-curve",$E16+($F16-$E16)*$I$2/(1+EXP($I$3*(COUNT($I$9:AI$9)+$I$4))),TREND($E16:$F16,$E$9:$F$9,AI$9)) -> 0
A17: LDVs | B17: freight | C17: battery electric vehicle | D17: 0.32863913 | E17: 0.32863913 | F17: 0.3 | G17: =IF(E17=F17,"n/a",IF(OR(C17="battery electric vehicle",C17="natural gas vehicle",C17="plugin hybrid vehicle"),"s-curve","linear")) -> s-curve | I17: =D17 -> 0.32863913 | J17: =E17 -> 0.32863913 | K17: =IF($G17="s-curve",$E17+($F17-$E17)*$X$2/(1+EXP($X$3*(COUNT($I$9:K$9)+$X$4))),TREND($E17:$F17,$E$9:$F$9,K$9)) -> 0.3276204 | L17: =IF($G17="s-curve",$E17+($F17-$E17)*$X$2/(1+EXP($X$3*(COUNT($I$9:L$9)+$X$4))),TREND($E17:$F17,$E$9:$F$9,L$9)) -> 0.32728089 | M17: =IF($G17="s-curve",$E17+($F17-$E17)*$X$2/(1+EXP($X$3*(COUNT($I$9:M$9)+$X$4))),TREND($E17:$F17,$E$9:$F$9,M$9)) -> 0.32683563 | N17: =IF($G17="s-curve",$E17+($F17-$E17)*$X$2/(1+EXP($X$3*(COUNT($I$9:N$9)+$X$4))),TREND($E17:$F17,$E$9:$F$9,N$9)) -> 0.32625713 | O17: =IF($G17="s-curve",$E17+($F17-$E17)*$X$2/(1+EXP($X$3*(COUNT($I$9:O$9)+$X$4))),TREND($E17:$F17,$E$9:$F$9,O$9)) -> 0.32551469 | P17: =IF($G17="s-curve",$E17+($F17-$E17)*$X$2/(1+EXP($X$3*(COUNT($I$9:P$9)+$X$4))),TREND($E17:$F17,$E$9:$F$9,P$9)) -> 0.32457664 | Q17: =IF($G17="s-curve",$E17+($F17-$E17)*$X$2/(1+EXP($X$3*(COUNT($I$9:Q$9)+$X$4))),TREND($E17:$F17,$E$9:$F$9,Q$9)) -> 0.32341462 | R17: =IF($G17="s-curve",$E17+($F17-$E17)*$X$2/(1+EXP($X$3*(COUNT($I$9:R$9)+$X$4))),TREND($E17:$F17,$E$9:$F$9,R$9)) -> 0.32200988 | ... AI17: =IF($G17="s-curve",$E17+($F17-$E17)*$X$2/(1+EXP($X$3*(COUNT($I$9:AI$9)+$X$4))),TREND($E17:$F17,$E$9:$F$9,AI$9)) -> 0.30056821
C18: natural gas vehicle | D18: 0.25047807 | E18: 0.25047807 | F18: =E18 -> 0.25047807 | G18: linear | I18: =D18 -> 0.25047807 | J18: =E18 -> 0.25047807 | K18: =IF($G18="s-curve",$E18+($F18-$E18)*$I$2/(1+EXP($I$3*(COUNT($I$9:K$9)+$I$4))),TREND($E18:$F18,$E$9:$F$9,K$9)) -> 0.25047807 | L18: =IF($G18="s-curve",$E18+($F18-$E18)*$I$2/(1+EXP($I$3*(COUNT($I$9:L$9)+$I$4))),TREND($E18:$F18,$E$9:$F$9,L$9)) -> 0.25047807 | M18: =IF($G18="s-curve",$E18+($F18-$E18)*$I$2/(1+EXP($I$3*(COUNT($I$9:M$9)+$I$4))),TREND($E18:$F18,$E$9:$F$9,M$9)) -> 0.25047807 | N18: =IF($G18="s-curve",$E18+($F18-$E18)*$I$2/(1+EXP($I$3*(COUNT($I$9:N$9)+$I$4))),TREND($E18:$F18,$E$9:$F$9,N$9)) -> 0.25047807 | O18: =IF($G18="s-curve",$E18+($F18-$E18)*$I$2/(1+EXP($I$3*(COUNT($I$9:O$9)+$I$4))),TREND($E18:$F18,$E$9:$F$9,O$9)) -> 0.25047807 | P18: =IF($G18="s-curve",$E18+($F18-$E18)*$I$2/(1+EXP($I$3*(COUNT($I$9:P$9)+$I$4))),TREND($E18:$F18,$E$9:$F$9,P$9)) -> 0.25047807 | Q18: =IF($G18="s-curve",$E18+($F18-$E18)*$I$2/(1+EXP($I$3*(COUNT($I$9:Q$9)+$I$4))),TREND($E18:$F18,$E$9:$F$9,Q$9)) -> 0.25047807 | R18: =IF($G18="s-curve",$E18+($F18-$E18)*$I$2/(1+EXP($I$3*(COUNT($I$9:R$9)+$I$4))),TREND($E18:$F18,$E$9:$F$9,R$9)) -> 0.25047807 | ... AI18: =IF($G18="s-curve",$E18+($F18-$E18)*$I$2/(1+EXP($I$3*(COUNT($I$9:AI$9)+$I$4))),TREND($E18:$F18,$E$9:$F$9,AI$9)) -> 0.25047807
C19: gasoline vehicle | D19: 0.76148266 | E19: 0.76148266 | F19: =E19 -> 0.76148266 | G19: =IF(E19=F19,"n/a",IF(OR(C19="battery electric vehicle",C19="natural gas vehicle",C19="plugin hybrid vehicle"),"s-curve","linear")) -> n/a | I19: =D19 -> 0.76148266 | J19: =E19 -> 0.76148266 | K19: =IF($G19="s-curve",$E19+($F19-$E19)*$I$2/(1+EXP($I$3*(COUNT($I$9:K$9)+$I$4))),TREND($E19:$F19,$E$9:$F$9,K$9)) -> 0.76148266 | L19: =IF($G19="s-curve",$E19+($F19-$E19)*$I$2/(1+EXP($I$3*(COUNT($I$9:L$9)+$I$4))),TREND($E19:$F19,$E$9:$F$9,L$9)) -> 0.76148266 | M19: =IF($G19="s-curve",$E19+($F19-$E19)*$I$2/(1+EXP($I$3*(COUNT($I$9:M$9)+$I$4))),TREND($E19:$F19,$E$9:$F$9,M$9)) -> 0.76148266 | N19: =IF($G19="s-curve",$E19+($F19-$E19)*$I$2/(1+EXP($I$3*(COUNT($I$9:N$9)+$I$4))),TREND($E19:$F19,$E$9:$F$9,N$9)) -> 0.76148266 | O19: =IF($G19="s-curve",$E19+($F19-$E19)*$I$2/(1+EXP($I$3*(COUNT($I$9:O$9)+$I$4))),TREND($E19:$F19,$E$9:$F$9,O$9)) -> 0.76148266 | P19: =IF($G19="s-curve",$E19+($F19-$E19)*$I$2/(1+EXP($I$3*(COUNT($I$9:P$9)+$I$4))),TREND($E19:$F19,$E$9:$F$9,P$9)) -> 0.76148266 | Q19: =IF($G19="s-curve",$E19+($F19-$E19)*$I$2/(1+EXP($I$3*(COUNT($I$9:Q$9)+$I$4))),TREND($E19:$F19,$E$9:$F$9,Q$9)) -> 0.76148266 | R19: =IF($G19="s-curve",$E19+($F19-$E19)*$I$2/(1+EXP($I$3*(COUNT($I$9:R$9)+$I$4))),TREND($E19:$F19,$E$9:$F$9,R$9)) -> 0.76148266 | ... AI19: =IF($G19="s-curve",$E19+($F19-$E19)*$I$2/(1+EXP($I$3*(COUNT($I$9:AI$9)+$I$4))),TREND($E19:$F19,$E$9:$F$9,AI$9)) -> 0.76148266
C20: diesel vehicle | D20: 1 | E20: 1 | F20: 1 | G20: =IF(E20=F20,"n/a",IF(OR(C20="battery electric vehicle",C20="natural gas vehicle",C20="plugin hybrid vehicle"),"s-curve","linear")) -> n/a | I20: =D20 -> 1 | J20: =E20 -> 1 | K20: =IF($G20="s-curve",$E20+($F20-$E20)*$I$2/(1+EXP($I$3*(COUNT($I$9:K$9)+$I$4))),TREND($E20:$F20,$E$9:$F$9,K$9)) -> 1 | L20: =IF($G20="s-curve",$E20+($F20-$E20)*$I$2/(1+EXP($I$3*(COUNT($I$9:L$9)+$I$4))),TREND($E20:$F20,$E$9:$F$9,L$9)) -> 1 | M20: =IF($G20="s-curve",$E20+($F20-$E20)*$I$2/(1+EXP($I$3*(COUNT($I$9:M$9)+$I$4))),TREND($E20:$F20,$E$9:$F$9,M$9)) -> 1 | N20: =IF($G20="s-curve",$E20+($F20-$E20)*$I$2/(1+EXP($I$3*(COUNT($I$9:N$9)+$I$4))),TREND($E20:$F20,$E$9:$F$9,N$9)) -> 1 | O20: =IF($G20="s-curve",$E20+($F20-$E20)*$I$2/(1+EXP($I$3*(COUNT($I$9:O$9)+$I$4))),TREND($E20:$F20,$E$9:$F$9,O$9)) -> 1 | P20: =IF($G20="s-curve",$E20+($F20-$E20)*$I$2/(1+EXP($I$3*(COUNT($I$9:P$9)+$I$4))),TREND($E20:$F20,$E$9:$F$9,P$9)) -> 1 | Q20: =IF($G20="s-curve",$E20+($F20-$E20)*$I$2/(1+EXP($I$3*(COUNT($I$9:Q$9)+$I$4))),TREND($E20:$F20,$E$9:$F$9,Q$9)) -> 1 | R20: =IF($G20="s-curve",$E20+($F20-$E20)*$I$2/(1+EXP($I$3*(COUNT($I$9:R$9)+$I$4))),TREND($E20:$F20,$E$9:$F$9,R$9)) -> 1 | ... AI20: =IF($G20="s-curve",$E20+($F20-$E20)*$I$2/(1+EXP($I$3*(COUNT($I$9:AI$9)+$I$4))),TREND($E20:$F20,$E$9:$F$9,AI$9)) -> 1
C21: plugin hybrid vehicle | D21: 0.001003192 | E21: 0.001003192 | F21: 0.0012357083 | G21: s-curve | I21: =D21 -> 0.001003192 | J21: =E21 -> 0.001003192 | K21: =IF($G21="s-curve",$E21+($F21-$E21)*$X$2/(1+EXP($X$3*(COUNT($I$9:K$9)+$X$4))),TREND($E21:$F21,$E$9:$F$9,K$9)) -> 0.0010114629 | L21: =IF($G21="s-curve",$E21+($F21-$E21)*$X$2/(1+EXP($X$3*(COUNT($I$9:L$9)+$X$4))),TREND($E21:$F21,$E$9:$F$9,L$9)) -> 0.0010142193 | M21: =IF($G21="s-curve",$E21+($F21-$E21)*$X$2/(1+EXP($X$3*(COUNT($I$9:M$9)+$X$4))),TREND($E21:$F21,$E$9:$F$9,M$9)) -> 0.0010178343 | N21: =IF($G21="s-curve",$E21+($F21-$E21)*$X$2/(1+EXP($X$3*(COUNT($I$9:N$9)+$X$4))),TREND($E21:$F21,$E$9:$F$9,N$9)) -> 0.001022531 | O21: =IF($G21="s-curve",$E21+($F21-$E21)*$X$2/(1+EXP($X$3*(COUNT($I$9:O$9)+$X$4))),TREND($E21:$F21,$E$9:$F$9,O$9)) -> 0.0010285588 | P21: =IF($G21="s-curve",$E21+($F21-$E21)*$X$2/(1+EXP($X$3*(COUNT($I$9:P$9)+$X$4))),TREND($E21:$F21,$E$9:$F$9,P$9)) -> 0.0010361747 | Q21: =IF($G21="s-curve",$E21+($F21-$E21)*$X$2/(1+EXP($X$3*(COUNT($I$9:Q$9)+$X$4))),TREND($E21:$F21,$E$9:$F$9,Q$9)) -> 0.0010456089 | R21: =IF($G21="s-curve",$E21+($F21-$E21)*$X$2/(1+EXP($X$3*(COUNT($I$9:R$9)+$X$4))),TREND($E21:$F21,$E$9:$F$9,R$9)) -> 0.0010570138 | ... AI21: =IF($G21="s-curve",$E21+($F21-$E21)*$X$2/(1+EXP($X$3*(COUNT($I$9:AI$9)+$X$4))),TREND($E21:$F21,$E$9:$F$9,AI$9)) -> 0.0012310951
C22: LPG vehicle | D22: 0.000602232 | E22: 0.000602232 | F22: =E22 -> 0.000602232 | G22: =IF(E22=F22,"n/a",IF(OR(C22="battery electric vehicle",C22="natural gas vehicle",C22="plugin hybrid vehicle",C22="hydrogen vehicle"),"s-curve","linear")) -> n/a | I22: =D22 -> 0.000602232 | J22: =E22 -> 0.000602232 | K22: =IF($G22="s-curve",$E22+($F22-$E22)*$I$2/(1+EXP($I$3*(COUNT($I$9:K$9)+$I$4))),TREND($E22:$F22,$E$9:$F$9,K$9)) -> 0.000602232 | L22: =IF($G22="s-curve",$E22+($F22-$E22)*$I$2/(1+EXP($I$3*(COUNT($I$9:L$9)+$I$4))),TREND($E22:$F22,$E$9:$F$9,L$9)) -> 0.000602232 | M22: =IF($G22="s-curve",$E22+($F22-$E22)*$I$2/(1+EXP($I$3*(COUNT($I$9:M$9)+$I$4))),TREND($E22:$F22,$E$9:$F$9,M$9)) -> 0.000602232 | N22: =IF($G22="s-curve",$E22+($F22-$E22)*$I$2/(1+EXP($I$3*(COUNT($I$9:N$9)+$I$4))),TREND($E22:$F22,$E$9:$F$9,N$9)) -> 0.000602232 | O22: =IF($G22="s-curve",$E22+($F22-$E22)*$I$2/(1+EXP($I$3*(COUNT($I$9:O$9)+$I$4))),TREND($E22:$F22,$E$9:$F$9,O$9)) -> 0.000602232 | P22: =IF($G22="s-curve",$E22+($F22-$E22)*$I$2/(1+EXP($I$3*(COUNT($I$9:P$9)+$I$4))),TREND($E22:$F22,$E$9:$F$9,P$9)) -> 0.000602232 | Q22: =IF($G22="s-curve",$E22+($F22-$E22)*$I$2/(1+EXP($I$3*(COUNT($I$9:Q$9)+$I$4))),TREND($E22:$F22,$E$9:$F$9,Q$9)) -> 0.000602232 | R22: =IF($G22="s-curve",$E22+($F22-$E22)*$I$2/(1+EXP($I$3*(COUNT($I$9:R$9)+$I$4))),TREND($E22:$F22,$E$9:$F$9,R$9)) -> 0.000602232 | ... AI22: =IF($G22="s-curve",$E22+($F22-$E22)*$I$2/(1+EXP($I$3*(COUNT($I$9:AI$9)+$I$4))),TREND($E22:$F22,$E$9:$F$9,AI$9)) -> 0.000602232
C23: hydrogen vehicle | D23: 0 | E23: 0 | F23: =E23 -> 0 | G23: =IF(E23=F23,"n/a",IF(OR(C23="battery electric vehicle",C23="natural gas vehicle",C23="plugin hybrid vehicle",C23="hydrogen vehicle"),"s-curve","linear")) -> n/a | I23: =D23 -> 0 | J23: =E23 -> 0 | K23: =IF($G23="s-curve",$E23+($F23-$E23)*$I$2/(1+EXP($I$3*(COUNT($I$9:K$9)+$I$4))),TREND($E23:$F23,$E$9:$F$9,K$9)) -> 0 | L23: =IF($G23="s-curve",$E23+($F23-$E23)*$I$2/(1+EXP($I$3*(COUNT($I$9:L$9)+$I$4))),TREND($E23:$F23,$E$9:$F$9,L$9)) -> 0 | M23: =IF($G23="s-curve",$E23+($F23-$E23)*$I$2/(1+EXP($I$3*(COUNT($I$9:M$9)+$I$4))),TREND($E23:$F23,$E$9:$F$9,M$9)) -> 0 | N23: =IF($G23="s-curve",$E23+($F23-$E23)*$I$2/(1+EXP($I$3*(COUNT($I$9:N$9)+$I$4))),TREND($E23:$F23,$E$9:$F$9,N$9)) -> 0 | O23: =IF($G23="s-curve",$E23+($F23-$E23)*$I$2/(1+EXP($I$3*(COUNT($I$9:O$9)+$I$4))),TREND($E23:$F23,$E$9:$F$9,O$9)) -> 0 | P23: =IF($G23="s-curve",$E23+($F23-$E23)*$I$2/(1+EXP($I$3*(COUNT($I$9:P$9)+$I$4))),TREND($E23:$F23,$E$9:$F$9,P$9)) -> 0 | Q23: =IF($G23="s-curve",$E23+($F23-$E23)*$I$2/(1+EXP($I$3*(COUNT($I$9:Q$9)+$I$4))),TREND($E23:$F23,$E$9:$F$9,Q$9)) -> 0 | R23: =IF($G23="s-curve",$E23+($F23-$E23)*$I$2/(1+EXP($I$3*(COUNT($I$9:R$9)+$I$4))),TREND($E23:$F23,$E$9:$F$9,R$9)) -> 0 | ... AI23: =IF($G23="s-curve",$E23+($F23-$E23)*$I$2/(1+EXP($I$3*(COUNT($I$9:AI$9)+$I$4))),TREND($E23:$F23,$E$9:$F$9,AI$9)) -> 0
A24: HDVs | B24: passenger | C24: battery electric vehicle | D24: 0.1218401 | E24: 0.1218401 | F24: 0.75 | G24: =IF(E24=F24,"n/a",IF(OR(C24="battery electric vehicle",C24="natural gas vehicle",C24="plugin hybrid vehicle"),"s-curve","linear")) -> s-curve | I24: =D24 -> 0.1218401 | J24: =E24 -> 0.1218401 | K24: =IF($G24="s-curve",$E24+($F24-$E24)*$X$2/(1+EXP($X$3*(COUNT($I$9:K$9)+$X$4))),TREND($E24:$F24,$E$9:$F$9,K$9)) -> 0.14418449 | L24: =IF($G24="s-curve",$E24+($F24-$E24)*$X$2/(1+EXP($X$3*(COUNT($I$9:L$9)+$X$4))),TREND($E24:$F24,$E$9:$F$9,L$9)) -> 0.15163113 | M24: =IF($G24="s-curve",$E24+($F24-$E24)*$X$2/(1+EXP($X$3*(COUNT($I$9:M$9)+$X$4))),TREND($E24:$F24,$E$9:$F$9,M$9)) -> 0.16139744 | N24: =IF($G24="s-curve",$E24+($F24-$E24)*$X$2/(1+EXP($X$3*(COUNT($I$9:N$9)+$X$4))),TREND($E24:$F24,$E$9:$F$9,N$9)) -> 0.17408585 | O24: =IF($G24="s-curve",$E24+($F24-$E24)*$X$2/(1+EXP($X$3*(COUNT($I$9:O$9)+$X$4))),TREND($E24:$F24,$E$9:$F$9,O$9)) -> 0.19037035 | P24: =IF($G24="s-curve",$E24+($F24-$E24)*$X$2/(1+EXP($X$3*(COUNT($I$9:P$9)+$X$4))),TREND($E24:$F24,$E$9:$F$9,P$9)) -> 0.21094525 | Q24: =IF($G24="s-curve",$E24+($F24-$E24)*$X$2/(1+EXP($X$3*(COUNT($I$9:Q$9)+$X$4))),TREND($E24:$F24,$E$9:$F$9,Q$9)) -> 0.2364325 | R24: =IF($G24="s-curve",$E24+($F24-$E24)*$X$2/(1+EXP($X$3*(COUNT($I$9:R$9)+$X$4))),TREND($E24:$F24,$E$9:$F$9,R$9)) -> 0.26724355 | ... AI24: =IF($G24="s-curve",$E24+($F24-$E24)*$X$2/(1+EXP($X$3*(COUNT($I$9:AI$9)+$X$4))),TREND($E24:$F24,$E$9:$F$9,AI$9)) -> 0.73753712
C25: natural gas vehicle | D25: 0.015737248 | E25: 0.015737248 | F25: =E25 -> 0.015737248 | G25: =IF(E25=F25,"n/a",IF(OR(C25="battery electric vehicle",C25="natural gas vehicle",C25="plugin hybrid vehicle"),"s-curve","linear")) -> n/a | I25: =D25 -> 0.015737248 | J25: =E25 -> 0.015737248 | K25: =IF($G25="s-curve",$E25+($F25-$E25)*$I$2/(1+EXP($I$3*(COUNT($I$9:K$9)+$I$4))),TREND($E25:$F25,$E$9:$F$9,K$9)) -> 0.015737248 | L25: =IF($G25="s-curve",$E25+($F25-$E25)*$I$2/(1+EXP($I$3*(COUNT($I$9:L$9)+$I$4))),TREND($E25:$F25,$E$9:$F$9,L$9)) -> 0.015737248 | M25: =IF($G25="s-curve",$E25+($F25-$E25)*$I$2/(1+EXP($I$3*(COUNT($I$9:M$9)+$I$4))),TREND($E25:$F25,$E$9:$F$9,M$9)) -> 0.015737248 | N25: =IF($G25="s-curve",$E25+($F25-$E25)*$I$2/(1+EXP($I$3*(COUNT($I$9:N$9)+$I$4))),TREND($E25:$F25,$E$9:$F$9,N$9)) -> 0.015737248 | O25: =IF($G25="s-curve",$E25+($F25-$E25)*$I$2/(1+EXP($I$3*(COUNT($I$9:O$9)+$I$4))),TREND($E25:$F25,$E$9:$F$9,O$9)) -> 0.015737248 | P25: =IF($G25="s-curve",$E25+($F25-$E25)*$I$2/(1+EXP($I$3*(COUNT($I$9:P$9)+$I$4))),TREND($E25:$F25,$E$9:$F$9,P$9)) -> 0.015737248 | Q25: =IF($G25="s-curve",$E25+($F25-$E25)*$I$2/(1+EXP($I$3*(COUNT($I$9:Q$9)+$I$4))),TREND($E25:$F25,$E$9:$F$9,Q$9)) -> 0.015737248 | R25: =IF($G25="s-curve",$E25+($F25-$E25)*$I$2/(1+EXP($I$3*(COUNT($I$9:R$9)+$I$4))),TREND($E25:$F25,$E$9:$F$9,R$9)) -> 0.015737248 | ... AI25: =IF($G25="s-curve",$E25+($F25-$E25)*$I$2/(1+EXP($I$3*(COUNT($I$9:AI$9)+$I$4))),TREND($E25:$F25,$E$9:$F$9,AI$9)) -> 0.015737248
C26: gasoline vehicle | D26: 0.37956814 | E26: 0.37956814 | F26: =E26 -> 0.37956814 | G26: =IF(E26=F26,"n/a",IF(OR(C26="battery electric vehicle",C26="natural gas vehicle",C26="plugin hybrid vehicle"),"s-curve","linear")) -> n/a | I26: =D26 -> 0.37956814 | J26: =E26 -> 0.37956814 | K26: =IF($G26="s-curve",$E26+($F26-$E26)*$I$2/(1+EXP($I$3*(COUNT($I$9:K$9)+$I$4))),TREND($E26:$F26,$E$9:$F$9,K$9)) -> 0.37956814 | L26: =IF($G26="s-curve",$E26+($F26-$E26)*$I$2/(1+EXP($I$3*(COUNT($I$9:L$9)+$I$4))),TREND($E26:$F26,$E$9:$F$9,L$9)) -> 0.37956814 | M26: =IF($G26="s-curve",$E26+($F26-$E26)*$I$2/(1+EXP($I$3*(COUNT($I$9:M$9)+$I$4))),TREND($E26:$F26,$E$9:$F$9,M$9)) -> 0.37956814 | N26: =IF($G26="s-curve",$E26+($F26-$E26)*$I$2/(1+EXP($I$3*(COUNT($I$9:N$9)+$I$4))),TREND($E26:$F26,$E$9:$F$9,N$9)) -> 0.37956814 | O26: =IF($G26="s-curve",$E26+($F26-$E26)*$I$2/(1+EXP($I$3*(COUNT($I$9:O$9)+$I$4))),TREND($E26:$F26,$E$9:$F$9,O$9)) -> 0.37956814 | P26: =IF($G26="s-curve",$E26+($F26-$E26)*$I$2/(1+EXP($I$3*(COUNT($I$9:P$9)+$I$4))),TREND($E26:$F26,$E$9:$F$9,P$9)) -> 0.37956814 | Q26: =IF($G26="s-curve",$E26+($F26-$E26)*$I$2/(1+EXP($I$3*(COUNT($I$9:Q$9)+$I$4))),TREND($E26:$F26,$E$9:$F$9,Q$9)) -> 0.37956814 | R26: =IF($G26="s-curve",$E26+($F26-$E26)*$I$2/(1+EXP($I$3*(COUNT($I$9:R$9)+$I$4))),TREND($E26:$F26,$E$9:$F$9,R$9)) -> 0.37956814 | ... AI26: =IF($G26="s-curve",$E26+($F26-$E26)*$I$2/(1+EXP($I$3*(COUNT($I$9:AI$9)+$I$4))),TREND($E26:$F26,$E$9:$F$9,AI$9)) -> 0.37956814
C27: diesel vehicle | D27: 1 | E27: 1 | F27: 1 | G27: =IF(E27=F27,"n/a",IF(OR(C27="battery electric vehicle",C27="natural gas vehicle",C27="plugin hybrid vehicle"),"s-curve","linear")) -> n/a | I27: =D27 -> 1 | J27: =E27 -> 1 | K27: =IF($G27="s-curve",$E27+($F27-$E27)*$I$2/(1+EXP($I$3*(COUNT($I$9:K$9)+$I$4))),TREND($E27:$F27,$E$9:$F$9,K$9)) -> 1 | L27: =IF($G27="s-curve",$E27+($F27-$E27)*$I$2/(1+EXP($I$3*(COUNT($I$9:L$9)+$I$4))),TREND($E27:$F27,$E$9:$F$9,L$9)) -> 1 | M27: =IF($G27="s-curve",$E27+($F27-$E27)*$I$2/(1+EXP($I$3*(COUNT($I$9:M$9)+$I$4))),TREND($E27:$F27,$E$9:$F$9,M$9)) -> 1 | N27: =IF($G27="s-curve",$E27+($F27-$E27)*$I$2/(1+EXP($I$3*(COUNT($I$9:N$9)+$I$4))),TREND($E27:$F27,$E$9:$F$9,N$9)) -> 1 | O27: =IF($G27="s-curve",$E27+($F27-$E27)*$I$2/(1+EXP($I$3*(COUNT($I$9:O$9)+$I$4))),TREND($E27:$F27,$E$9:$F$9,O$9)) -> 1 | P27: =IF($G27="s-curve",$E27+($F27-$E27)*$I$2/(1+EXP($I$3*(COUNT($I$9:P$9)+$I$4))),TREND($E27:$F27,$E$9:$F$9,P$9)) -> 1 | Q27: =IF($G27="s-curve",$E27+($F27-$E27)*$I$2/(1+EXP($I$3*(COUNT($I$9:Q$9)+$I$4))),TREND($E27:$F27,$E$9:$F$9,Q$9)) -> 1 | R27: =IF($G27="s-curve",$E27+($F27-$E27)*$I$2/(1+EXP($I$3*(COUNT($I$9:R$9)+$I$4))),TREND($E27:$F27,$E$9:$F$9,R$9)) -> 1 | ... AI27: =IF($G27="s-curve",$E27+($F27-$E27)*$I$2/(1+EXP($I$3*(COUNT($I$9:AI$9)+$I$4))),TREND($E27:$F27,$E$9:$F$9,AI$9)) -> 1
C28: plugin hybrid vehicle | D28: 0 | E28: 0 | F28: =E28 -> 0 | G28: =IF(E28=F28,"n/a",IF(OR(C28="battery electric vehicle",C28="natural gas vehicle",C28="plugin hybrid vehicle"),"s-curve","linear")) -> n/a | I28: =D28 -> 0 | J28: =E28 -> 0 | K28: =IF($G28="s-curve",$E28+($F28-$E28)*$I$2/(1+EXP($I$3*(COUNT($I$9:K$9)+$I$4))),TREND($E28:$F28,$E$9:$F$9,K$9)) -> 0 | L28: =IF($G28="s-curve",$E28+($F28-$E28)*$I$2/(1+EXP($I$3*(COUNT($I$9:L$9)+$I$4))),TREND($E28:$F28,$E$9:$F$9,L$9)) -> 0 | M28: =IF($G28="s-curve",$E28+($F28-$E28)*$I$2/(1+EXP($I$3*(COUNT($I$9:M$9)+$I$4))),TREND($E28:$F28,$E$9:$F$9,M$9)) -> 0 | N28: =IF($G28="s-curve",$E28+($F28-$E28)*$I$2/(1+EXP($I$3*(COUNT($I$9:N$9)+$I$4))),TREND($E28:$F28,$E$9:$F$9,N$9)) -> 0 | O28: =IF($G28="s-curve",$E28+($F28-$E28)*$I$2/(1+EXP($I$3*(COUNT($I$9:O$9)+$I$4))),TREND($E28:$F28,$E$9:$F$9,O$9)) -> 0 | P28: =IF($G28="s-curve",$E28+($F28-$E28)*$I$2/(1+EXP($I$3*(COUNT($I$9:P$9)+$I$4))),TREND($E28:$F28,$E$9:$F$9,P$9)) -> 0 | Q28: =IF($G28="s-curve",$E28+($F28-$E28)*$I$2/(1+EXP($I$3*(COUNT($I$9:Q$9)+$I$4))),TREND($E28:$F28,$E$9:$F$9,Q$9)) -> 0 | R28: =IF($G28="s-curve",$E28+($F28-$E28)*$I$2/(1+EXP($I$3*(COUNT($I$9:R$9)+$I$4))),TREND($E28:$F28,$E$9:$F$9,R$9)) -> 0 | ... AI28: =IF($G28="s-curve",$E28+($F28-$E28)*$I$2/(1+EXP($I$3*(COUNT($I$9:AI$9)+$I$4))),TREND($E28:$F28,$E$9:$F$9,AI$9)) -> 0
C29: LPG vehicle | D29: 0.055449391 | E29: 0.055449391 | F29: =E29 -> 0.055449391 | G29: =IF(E29=F29,"n/a",IF(OR(C29="battery electric vehicle",C29="natural gas vehicle",C29="plugin hybrid vehicle",C29="hydrogen vehicle"),"s-curve","linear")) -> n/a | I29: =D29 -> 0.055449391 | J29: =E29 -> 0.055449391 | K29: =IF($G29="s-curve",$E29+($F29-$E29)*$I$2/(1+EXP($I$3*(COUNT($I$9:K$9)+$I$4))),TREND($E29:$F29,$E$9:$F$9,K$9)) -> 0.055449391 | L29: =IF($G29="s-curve",$E29+($F29-$E29)*$I$2/(1+EXP($I$3*(COUNT($I$9:L$9)+$I$4))),TREND($E29:$F29,$E$9:$F$9,L$9)) -> 0.055449391 | M29: =IF($G29="s-curve",$E29+($F29-$E29)*$I$2/(1+EXP($I$3*(COUNT($I$9:M$9)+$I$4))),TREND($E29:$F29,$E$9:$F$9,M$9)) -> 0.055449391 | N29: =IF($G29="s-curve",$E29+($F29-$E29)*$I$2/(1+EXP($I$3*(COUNT($I$9:N$9)+$I$4))),TREND($E29:$F29,$E$9:$F$9,N$9)) -> 0.055449391 | O29: =IF($G29="s-curve",$E29+($F29-$E29)*$I$2/(1+EXP($I$3*(COUNT($I$9:O$9)+$I$4))),TREND($E29:$F29,$E$9:$F$9,O$9)) -> 0.055449391 | P29: =IF($G29="s-curve",$E29+($F29-$E29)*$I$2/(1+EXP($I$3*(COUNT($I$9:P$9)+$I$4))),TREND($E29:$F29,$E$9:$F$9,P$9)) -> 0.055449391 | Q29: =IF($G29="s-curve",$E29+($F29-$E29)*$I$2/(1+EXP($I$3*(COUNT($I$9:Q$9)+$I$4))),TREND($E29:$F29,$E$9:$F$9,Q$9)) -> 0.055449391 | R29: =IF($G29="s-curve",$E29+($F29-$E29)*$I$2/(1+EXP($I$3*(COUNT($I$9:R$9)+$I$4))),TREND($E29:$F29,$E$9:$F$9,R$9)) -> 0.055449391 | ... AI29: =IF($G29="s-curve",$E29+($F29-$E29)*$I$2/(1+EXP($I$3*(COUNT($I$9:AI$9)+$I$4))),TREND($E29:$F29,$E$9:$F$9,AI$9)) -> 0.055449391
C30: hydrogen vehicle | D30: 0.002028695 | E30: 0.002028695 | F30: =E30 -> 0.002028695 | G30: =IF(E30=F30,"n/a",IF(OR(C30="battery electric vehicle",C30="natural gas vehicle",C30="plugin hybrid vehicle",C30="hydrogen vehicle"),"s-curve","linear")) -> n/a | I30: =D30 -> 0.002028695 | J30: =E30 -> 0.002028695 | K30: =IF($G30="s-curve",$E30+($F30-$E30)*$I$2/(1+EXP($I$3*(COUNT($I$9:K$9)+$I$4))),TREND($E30:$F30,$E$9:$F$9,K$9)) -> 0.002028695 | L30: =IF($G30="s-curve",$E30+($F30-$E30)*$I$2/(1+EXP($I$3*(COUNT($I$9:L$9)+$I$4))),TREND($E30:$F30,$E$9:$F$9,L$9)) -> 0.002028695 | M30: =IF($G30="s-curve",$E30+($F30-$E30)*$I$2/(1+EXP($I$3*(COUNT($I$9:M$9)+$I$4))),TREND($E30:$F30,$E$9:$F$9,M$9)) -> 0.002028695 | N30: =IF($G30="s-curve",$E30+($F30-$E30)*$I$2/(1+EXP($I$3*(COUNT($I$9:N$9)+$I$4))),TREND($E30:$F30,$E$9:$F$9,N$9)) -> 0.002028695 | O30: =IF($G30="s-curve",$E30+($F30-$E30)*$I$2/(1+EXP($I$3*(COUNT($I$9:O$9)+$I$4))),TREND($E30:$F30,$E$9:$F$9,O$9)) -> 0.002028695 | P30: =IF($G30="s-curve",$E30+($F30-$E30)*$I$2/(1+EXP($I$3*(COUNT($I$9:P$9)+$I$4))),TREND($E30:$F30,$E$9:$F$9,P$9)) -> 0.002028695 | Q30: =IF($G30="s-curve",$E30+($F30-$E30)*$I$2/(1+EXP($I$3*(COUNT($I$9:Q$9)+$I$4))),TREND($E30:$F30,$E$9:$F$9,Q$9)) -> 0.002028695 | R30: =IF($G30="s-curve",$E30+($F30-$E30)*$I$2/(1+EXP($I$3*(COUNT($I$9:R$9)+$I$4))),TREND($E30:$F30,$E$9:$F$9,R$9)) -> 0.002028695 | ... AI30: =IF($G30="s-curve",$E30+($F30-$E30)*$I$2/(1+EXP($I$3*(COUNT($I$9:AI$9)+$I$4))),TREND($E30:$F30,$E$9:$F$9,AI$9)) -> 0.002028695
A31: HDVs | B31: freight | C31: battery electric vehicle | D31: 0.004808968 | E31: 0.004808968 | F31: 0.25 | G31: =IF(E31=F31,"n/a",IF(OR(C31="battery electric vehicle",C31="natural gas vehicle",C31="plugin hybrid vehicle"),"s-curve","linear")) -> s-curve | I31: =D31 -> 0.004808968 | J31: =E31 -> 0.004808968 | K31: =IF($G31="s-curve",$E31+($F31-$E31)*$R$2/(1+EXP($R$3*(COUNT($K$9:K$9)+$R$4))),TREND($E31:$F31,$E$9:$F$9,K$9)) -> 0.013530705 | L31: =IF($G31="s-curve",$E31+($F31-$E31)*$R$2/(1+EXP($R$3*(COUNT($K$9:L$9)+$R$4))),TREND($E31:$F31,$E$9:$F$9,L$9)) -> 0.016437367 | M31: =IF($G31="s-curve",$E31+($F31-$E31)*$R$2/(1+EXP($R$3*(COUNT($K$9:M$9)+$R$4))),TREND($E31:$F31,$E$9:$F$9,M$9)) -> 0.02024947 | N31: =IF($G31="s-curve",$E31+($F31-$E31)*$R$2/(1+EXP($R$3*(COUNT($K$9:N$9)+$R$4))),TREND($E31:$F31,$E$9:$F$9,N$9)) -> 0.025202167 | O31: =IF($G31="s-curve",$E31+($F31-$E31)*$R$2/(1+EXP($R$3*(COUNT($K$9:O$9)+$R$4))),TREND($E31:$F31,$E$9:$F$9,O$9)) -> 0.03155853 | P31: =IF($G31="s-curve",$E31+($F31-$E31)*$R$2/(1+EXP($R$3*(COUNT($K$9:P$9)+$R$4))),TREND($E31:$F31,$E$9:$F$9,P$9)) -> 0.039589577 | Q31: =IF($G31="s-curve",$E31+($F31-$E31)*$R$2/(1+EXP($R$3*(COUNT($K$9:Q$9)+$R$4))),TREND($E31:$F31,$E$9:$F$9,Q$9)) -> 0.04953807 | R31: =IF($G31="s-curve",$E31+($F31-$E31)*$R$2/(1+EXP($R$3*(COUNT($K$9:R$9)+$R$4))),TREND($E31:$F31,$E$9:$F$9,R$9)) -> 0.061564615 | ... AI31: =IF($G31="s-curve",$E31+($F31-$E31)*$R$2/(1+EXP($R$3*(COUNT($K$9:AI$9)+$R$4))),TREND($E31:$F31,$E$9:$F$9,AI$9)) -> 0.24513533
C32: natural gas vehicle | D32: 0.022159679 | E32: 0.022159679 | F32: =E32 -> 0.022159679 | G32: =IF(E32=F32,"n/a",IF(OR(C32="battery electric vehicle",C32="natural gas vehicle",C32="plugin hybrid vehicle"),"s-curve","linear")) -> n/a | I32: =D32 -> 0.022159679 | J32: =E32 -> 0.022159679 | K32: =IF($G32="s-curve",$E32+($F32-$E32)*$I$2/(1+EXP($I$3*(COUNT($I$9:K$9)+$I$4))),TREND($E32:$F32,$E$9:$F$9,K$9)) -> 0.022159679 | L32: =IF($G32="s-curve",$E32+($F32-$E32)*$I$2/(1+EXP($I$3*(COUNT($I$9:L$9)+$I$4))),TREND($E32:$F32,$E$9:$F$9,L$9)) -> 0.022159679 | M32: =IF($G32="s-curve",$E32+($F32-$E32)*$I$2/(1+EXP($I$3*(COUNT($I$9:M$9)+$I$4))),TREND($E32:$F32,$E$9:$F$9,M$9)) -> 0.022159679 | N32: =IF($G32="s-curve",$E32+($F32-$E32)*$I$2/(1+EXP($I$3*(COUNT($I$9:N$9)+$I$4))),TREND($E32:$F32,$E$9:$F$9,N$9)) -> 0.022159679 | O32: =IF($G32="s-curve",$E32+($F32-$E32)*$I$2/(1+EXP($I$3*(COUNT($I$9:O$9)+$I$4))),TREND($E32:$F32,$E$9:$F$9,O$9)) -> 0.022159679 | P32: =IF($G32="s-curve",$E32+($F32-$E32)*$I$2/(1+EXP($I$3*(COUNT($I$9:P$9)+$I$4))),TREND($E32:$F32,$E$9:$F$9,P$9)) -> 0.022159679 | Q32: =IF($G32="s-curve",$E32+($F32-$E32)*$I$2/(1+EXP($I$3*(COUNT($I$9:Q$9)+$I$4))),TREND($E32:$F32,$E$9:$F$9,Q$9)) -> 0.022159679 | R32: =IF($G32="s-curve",$E32+($F32-$E32)*$I$2/(1+EXP($I$3*(COUNT($I$9:R$9)+$I$4))),TREND($E32:$F32,$E$9:$F$9,R$9)) -> 0.022159679 | ... AI32: =IF($G32="s-curve",$E32+($F32-$E32)*$I$2/(1+EXP($I$3*(COUNT($I$9:AI$9)+$I$4))),TREND($E32:$F32,$E$9:$F$9,AI$9)) -> 0.022159679
C33: gasoline vehicle | D33: 0.000753581 | E33: 0.000753581 | F33: =E33 -> 0.000753581 | G33: =IF(E33=F33,"n/a",IF(OR(C33="battery electric vehicle",C33="natural gas vehicle",C33="plugin hybrid vehicle"),"s-curve","linear")) -> n/a | I33: =D33 -> 0.000753581 | J33: =E33 -> 0.000753581 | K33: =IF($G33="s-curve",$E33+($F33-$E33)*$I$2/(1+EXP($I$3*(COUNT($I$9:K$9)+$I$4))),TREND($E33:$F33,$E$9:$F$9,K$9)) -> 0.000753581 | L33: =IF($G33="s-curve",$E33+($F33-$E33)*$I$2/(1+EXP($I$3*(COUNT($I$9:L$9)+$I$4))),TREND($E33:$F33,$E$9:$F$9,L$9)) -> 0.000753581 | M33: =IF($G33="s-curve",$E33+($F33-$E33)*$I$2/(1+EXP($I$3*(COUNT($I$9:M$9)+$I$4))),TREND($E33:$F33,$E$9:$F$9,M$9)) -> 0.000753581 | N33: =IF($G33="s-curve",$E33+($F33-$E33)*$I$2/(1+EXP($I$3*(COUNT($I$9:N$9)+$I$4))),TREND($E33:$F33,$E$9:$F$9,N$9)) -> 0.000753581 | O33: =IF($G33="s-curve",$E33+($F33-$E33)*$I$2/(1+EXP($I$3*(COUNT($I$9:O$9)+$I$4))),TREND($E33:$F33,$E$9:$F$9,O$9)) -> 0.000753581 | P33: =IF($G33="s-curve",$E33+($F33-$E33)*$I$2/(1+EXP($I$3*(COUNT($I$9:P$9)+$I$4))),TREND($E33:$F33,$E$9:$F$9,P$9)) -> 0.000753581 | Q33: =IF($G33="s-curve",$E33+($F33-$E33)*$I$2/(1+EXP($I$3*(COUNT($I$9:Q$9)+$I$4))),TREND($E33:$F33,$E$9:$F$9,Q$9)) -> 0.000753581 | R33: =IF($G33="s-curve",$E33+($F33-$E33)*$I$2/(1+EXP($I$3*(COUNT($I$9:R$9)+$I$4))),TREND($E33:$F33,$E$9:$F$9,R$9)) -> 0.000753581 | ... AI33: =IF($G33="s-curve",$E33+($F33-$E33)*$I$2/(1+EXP($I$3*(COUNT($I$9:AI$9)+$I$4))),TREND($E33:$F33,$E$9:$F$9,AI$9)) -> 0.000753581
C34: diesel vehicle | D34: 1 | E34: 1 | F34: 1 | G34: =IF(E34=F34,"n/a",IF(OR(C34="battery electric vehicle",C34="natural gas vehicle",C34="plugin hybrid vehicle"),"s-curve","linear")) -> n/a | I34: =D34 -> 1 | J34: =E34 -> 1 | K34: =IF($G34="s-curve",$E34+($F34-$E34)*$I$2/(1+EXP($I$3*(COUNT($I$9:K$9)+$I$4))),TREND($E34:$F34,$E$9:$F$9,K$9)) -> 1 | L34: =IF($G34="s-curve",$E34+($F34-$E34)*$I$2/(1+EXP($I$3*(COUNT($I$9:L$9)+$I$4))),TREND($E34:$F34,$E$9:$F$9,L$9)) -> 1 | M34: =IF($G34="s-curve",$E34+($F34-$E34)*$I$2/(1+EXP($I$3*(COUNT($I$9:M$9)+$I$4))),TREND($E34:$F34,$E$9:$F$9,M$9)) -> 1 | N34: =IF($G34="s-curve",$E34+($F34-$E34)*$I$2/(1+EXP($I$3*(COUNT($I$9:N$9)+$I$4))),TREND($E34:$F34,$E$9:$F$9,N$9)) -> 1 | O34: =IF($G34="s-curve",$E34+($F34-$E34)*$I$2/(1+EXP($I$3*(COUNT($I$9:O$9)+$I$4))),TREND($E34:$F34,$E$9:$F$9,O$9)) -> 1 | P34: =IF($G34="s-curve",$E34+($F34-$E34)*$I$2/(1+EXP($I$3*(COUNT($I$9:P$9)+$I$4))),TREND($E34:$F34,$E$9:$F$9,P$9)) -> 1 | Q34: =IF($G34="s-curve",$E34+($F34-$E34)*$I$2/(1+EXP($I$3*(COUNT($I$9:Q$9)+$I$4))),TREND($E34:$F34,$E$9:$F$9,Q$9)) -> 1 | R34: =IF($G34="s-curve",$E34+($F34-$E34)*$I$2/(1+EXP($I$3*(COUNT($I$9:R$9)+$I$4))),TREND($E34:$F34,$E$9:$F$9,R$9)) -> 1 | ... AI34: =IF($G34="s-curve",$E34+($F34-$E34)*$I$2/(1+EXP($I$3*(COUNT($I$9:AI$9)+$I$4))),TREND($E34:$F34,$E$9:$F$9,AI$9)) -> 1
C35: plugin hybrid vehicle | D35: 0 | E35: 0 | F35: =E35 -> 0 | G35: =IF(E35=F35,"n/a",IF(OR(C35="battery electric vehicle",C35="natural gas vehicle",C35="plugin hybrid vehicle"),"s-curve","linear")) -> n/a | I35: =D35 -> 0 | J35: =E35 -> 0 | K35: =IF($G35="s-curve",$E35+($F35-$E35)*$I$2/(1+EXP($I$3*(COUNT($I$9:K$9)+$I$4))),TREND($E35:$F35,$E$9:$F$9,K$9)) -> 0 | L35: =IF($G35="s-curve",$E35+($F35-$E35)*$I$2/(1+EXP($I$3*(COUNT($I$9:L$9)+$I$4))),TREND($E35:$F35,$E$9:$F$9,L$9)) -> 0 | M35: =IF($G35="s-curve",$E35+($F35-$E35)*$I$2/(1+EXP($I$3*(COUNT($I$9:M$9)+$I$4))),TREND($E35:$F35,$E$9:$F$9,M$9)) -> 0 | N35: =IF($G35="s-curve",$E35+($F35-$E35)*$I$2/(1+EXP($I$3*(COUNT($I$9:N$9)+$I$4))),TREND($E35:$F35,$E$9:$F$9,N$9)) -> 0 | O35: =IF($G35="s-curve",$E35+($F35-$E35)*$I$2/(1+EXP($I$3*(COUNT($I$9:O$9)+$I$4))),TREND($E35:$F35,$E$9:$F$9,O$9)) -> 0 | P35: =IF($G35="s-curve",$E35+($F35-$E35)*$I$2/(1+EXP($I$3*(COUNT($I$9:P$9)+$I$4))),TREND($E35:$F35,$E$9:$F$9,P$9)) -> 0 | Q35: =IF($G35="s-curve",$E35+($F35-$E35)*$I$2/(1+EXP($I$3*(COUNT($I$9:Q$9)+$I$4))),TREND($E35:$F35,$E$9:$F$9,Q$9)) -> 0 | R35: =IF($G35="s-curve",$E35+($F35-$E35)*$I$2/(1+EXP($I$3*(COUNT($I$9:R$9)+$I$4))),TREND($E35:$F35,$E$9:$F$9,R$9)) -> 0 | ... AI35: =IF($G35="s-curve",$E35+($F35-$E35)*$I$2/(1+EXP($I$3*(COUNT($I$9:AI$9)+$I$4))),TREND($E35:$F35,$E$9:$F$9,AI$9)) -> 0
C36: LPG vehicle | D36: 0 | E36: 0 | F36: =E36 -> 0 | G36: =IF(E36=F36,"n/a",IF(OR(C36="battery electric vehicle",C36="natural gas vehicle",C36="plugin hybrid vehicle",C36="hydrogen vehicle"),"s-curve","linear")) -> n/a | I36: =D36 -> 0 | J36: =E36 -> 0 | K36: =IF($G36="s-curve",$E36+($F36-$E36)*$I$2/(1+EXP($I$3*(COUNT($I$9:K$9)+$I$4))),TREND($E36:$F36,$E$9:$F$9,K$9)) -> 0 | L36: =IF($G36="s-curve",$E36+($F36-$E36)*$I$2/(1+EXP($I$3*(COUNT($I$9:L$9)+$I$4))),TREND($E36:$F36,$E$9:$F$9,L$9)) -> 0 | M36: =IF($G36="s-curve",$E36+($F36-$E36)*$I$2/(1+EXP($I$3*(COUNT($I$9:M$9)+$I$4))),TREND($E36:$F36,$E$9:$F$9,M$9)) -> 0 | N36: =IF($G36="s-curve",$E36+($F36-$E36)*$I$2/(1+EXP($I$3*(COUNT($I$9:N$9)+$I$4))),TREND($E36:$F36,$E$9:$F$9,N$9)) -> 0 | O36: =IF($G36="s-curve",$E36+($F36-$E36)*$I$2/(1+EXP($I$3*(COUNT($I$9:O$9)+$I$4))),TREND($E36:$F36,$E$9:$F$9,O$9)) -> 0 | P36: =IF($G36="s-curve",$E36+($F36-$E36)*$I$2/(1+EXP($I$3*(COUNT($I$9:P$9)+$I$4))),TREND($E36:$F36,$E$9:$F$9,P$9)) -> 0 | Q36: =IF($G36="s-curve",$E36+($F36-$E36)*$I$2/(1+EXP($I$3*(COUNT($I$9:Q$9)+$I$4))),TREND($E36:$F36,$E$9:$F$9,Q$9)) -> 0 | R36: =IF($G36="s-curve",$E36+($F36-$E36)*$I$2/(1+EXP($I$3*(COUNT($I$9:R$9)+$I$4))),TREND($E36:$F36,$E$9:$F$9,R$9)) -> 0 | ... AI36: =IF($G36="s-curve",$E36+($F36-$E36)*$I$2/(1+EXP($I$3*(COUNT($I$9:AI$9)+$I$4))),TREND($E36:$F36,$E$9:$F$9,AI$9)) -> 0
C37: hydrogen vehicle | D37: 0 | E37: 0 | F37: =E37 -> 0 | G37: =IF(E37=F37,"n/a",IF(OR(C37="battery electric vehicle",C37="natural gas vehicle",C37="plugin hybrid vehicle",C37="hydrogen vehicle"),"s-curve","linear")) -> n/a | I37: =D37 -> 0 | J37: =E37 -> 0 | K37: =IF($G37="s-curve",$E37+($F37-$E37)*$I$2/(1+EXP($I$3*(COUNT($I$9:K$9)+$I$4))),TREND($E37:$F37,$E$9:$F$9,K$9)) -> 0 | L37: =IF($G37="s-curve",$E37+($F37-$E37)*$I$2/(1+EXP($I$3*(COUNT($I$9:L$9)+$I$4))),TREND($E37:$F37,$E$9:$F$9,L$9)) -> 0 | M37: =IF($G37="s-curve",$E37+($F37-$E37)*$I$2/(1+EXP($I$3*(COUNT($I$9:M$9)+$I$4))),TREND($E37:$F37,$E$9:$F$9,M$9)) -> 0 | N37: =IF($G37="s-curve",$E37+($F37-$E37)*$I$2/(1+EXP($I$3*(COUNT($I$9:N$9)+$I$4))),TREND($E37:$F37,$E$9:$F$9,N$9)) -> 0 | O37: =IF($G37="s-curve",$E37+($F37-$E37)*$I$2/(1+EXP($I$3*(COUNT($I$9:O$9)+$I$4))),TREND($E37:$F37,$E$9:$F$9,O$9)) -> 0 | P37: =IF($G37="s-curve",$E37+($F37-$E37)*$I$2/(1+EXP($I$3*(COUNT($I$9:P$9)+$I$4))),TREND($E37:$F37,$E$9:$F$9,P$9)) -> 0 | Q37: =IF($G37="s-curve",$E37+($F37-$E37)*$I$2/(1+EXP($I$3*(COUNT($I$9:Q$9)+$I$4))),TREND($E37:$F37,$E$9:$F$9,Q$9)) -> 0 | R37: =IF($G37="s-curve",$E37+($F37-$E37)*$I$2/(1+EXP($I$3*(COUNT($I$9:R$9)+$I$4))),TREND($E37:$F37,$E$9:$F$9,R$9)) -> 0 | ... AI37: =IF($G37="s-curve",$E37+($F37-$E37)*$I$2/(1+EXP($I$3*(COUNT($I$9:AI$9)+$I$4))),TREND($E37:$F37,$E$9:$F$9,AI$9)) -> 0
A38: aircraft | B38: passenger | C38: battery electric vehicle | E38: 0 | F38: 0 | G38: =IF(E38=F38,"n/a",IF(OR(C38="battery electric vehicle",C38="natural gas vehicle",C38="plugin hybrid vehicle"),"s-curve","linear")) -> n/a | I38: =E38 -> 0 | J38: =IF($G38="s-curve",$E38+($F38-$E38)*$I$2/(1+EXP($I$3*(COUNT($I$9:J$9)+$I$4))),TREND($E38:$F38,$E$9:$F$9,J$9)) -> 0 | K38: =IF($G38="s-curve",$E38+($F38-$E38)*$I$2/(1+EXP($I$3*(COUNT($I$9:K$9)+$I$4))),TREND($E38:$F38,$E$9:$F$9,K$9)) -> 0 | L38: =IF($G38="s-curve",$E38+($F38-$E38)*$I$2/(1+EXP($I$3*(COUNT($I$9:L$9)+$I$4))),TREND($E38:$F38,$E$9:$F$9,L$9)) -> 0 | M38: =IF($G38="s-curve",$E38+($F38-$E38)*$I$2/(1+EXP($I$3*(COUNT($I$9:M$9)+$I$4))),TREND($E38:$F38,$E$9:$F$9,M$9)) -> 0 | N38: =IF($G38="s-curve",$E38+($F38-$E38)*$I$2/(1+EXP($I$3*(COUNT($I$9:N$9)+$I$4))),TREND($E38:$F38,$E$9:$F$9,N$9)) -> 0 | O38: =IF($G38="s-curve",$E38+($F38-$E38)*$I$2/(1+EXP($I$3*(COUNT($I$9:O$9)+$I$4))),TREND($E38:$F38,$E$9:$F$9,O$9)) -> 0 | P38: =IF($G38="s-curve",$E38+($F38-$E38)*$I$2/(1+EXP($I$3*(COUNT($I$9:P$9)+$I$4))),TREND($E38:$F38,$E$9:$F$9,P$9)) -> 0 | Q38: =IF($G38="s-curve",$E38+($F38-$E38)*$I$2/(1+EXP($I$3*(COUNT($I$9:Q$9)+$I$4))),TREND($E38:$F38,$E$9:$F$9,Q$9)) -> 0 | ... AI38: =IF($G38="s-curve",$E38+($F38-$E38)*$I$2/(1+EXP($I$3*(COUNT($I$9:AI$9)+$I$4))),TREND($E38:$F38,$E$9:$F$9,AI$9)) -> 0
C39: natural gas vehicle | E39: 0 | F39: 0 | G39: =IF(E39=F39,"n/a",IF(OR(C39="battery electric vehicle",C39="natural gas vehicle",C39="plugin hybrid vehicle"),"s-curve","linear")) -> n/a | I39: =E39 -> 0 | J39: =IF($G39="s-curve",$E39+($F39-$E39)*$I$2/(1+EXP($I$3*(COUNT($I$9:J$9)+$I$4))),TREND($E39:$F39,$E$9:$F$9,J$9)) -> 0 | K39: =IF($G39="s-curve",$E39+($F39-$E39)*$I$2/(1+EXP($I$3*(COUNT($I$9:K$9)+$I$4))),TREND($E39:$F39,$E$9:$F$9,K$9)) -> 0 | L39: =IF($G39="s-curve",$E39+($F39-$E39)*$I$2/(1+EXP($I$3*(COUNT($I$9:L$9)+$I$4))),TREND($E39:$F39,$E$9:$F$9,L$9)) -> 0 | M39: =IF($G39="s-curve",$E39+($F39-$E39)*$I$2/(1+EXP($I$3*(COUNT($I$9:M$9)+$I$4))),TREND($E39:$F39,$E$9:$F$9,M$9)) -> 0 | N39: =IF($G39="s-curve",$E39+($F39-$E39)*$I$2/(1+EXP($I$3*(COUNT($I$9:N$9)+$I$4))),TREND($E39:$F39,$E$9:$F$9,N$9)) -> 0 | O39: =IF($G39="s-curve",$E39+($F39-$E39)*$I$2/(1+EXP($I$3*(COUNT($I$9:O$9)+$I$4))),TREND($E39:$F39,$E$9:$F$9,O$9)) -> 0 | P39: =IF($G39="s-curve",$E39+($F39-$E39)*$I$2/(1+EXP($I$3*(COUNT($I$9:P$9)+$I$4))),TREND($E39:$F39,$E$9:$F$9,P$9)) -> 0 | Q39: =IF($G39="s-curve",$E39+($F39-$E39)*$I$2/(1+EXP($I$3*(COUNT($I$9:Q$9)+$I$4))),TREND($E39:$F39,$E$9:$F$9,Q$9)) -> 0 | ... AI39: =IF($G39="s-curve",$E39+($F39-$E39)*$I$2/(1+EXP($I$3*(COUNT($I$9:AI$9)+$I$4))),TREND($E39:$F39,$E$9:$F$9,AI$9)) -> 0
C40: gasoline vehicle | E40: 0 | F40: 0 | G40: =IF(E40=F40,"n/a",IF(OR(C40="battery electric vehicle",C40="natural gas vehicle",C40="plugin hybrid vehicle"),"s-curve","linear")) -> n/a | I40: =E40 -> 0 | J40: =IF($G40="s-curve",$E40+($F40-$E40)*$I$2/(1+EXP($I$3*(COUNT($I$9:J$9)+$I$4))),TREND($E40:$F40,$E$9:$F$9,J$9)) -> 0 | K40: =IF($G40="s-curve",$E40+($F40-$E40)*$I$2/(1+EXP($I$3*(COUNT($I$9:K$9)+$I$4))),TREND($E40:$F40,$E$9:$F$9,K$9)) -> 0 | L40: =IF($G40="s-curve",$E40+($F40-$E40)*$I$2/(1+EXP($I$3*(COUNT($I$9:L$9)+$I$4))),TREND($E40:$F40,$E$9:$F$9,L$9)) -> 0 | M40: =IF($G40="s-curve",$E40+($F40-$E40)*$I$2/(1+EXP($I$3*(COUNT($I$9:M$9)+$I$4))),TREND($E40:$F40,$E$9:$F$9,M$9)) -> 0 | N40: =IF($G40="s-curve",$E40+($F40-$E40)*$I$2/(1+EXP($I$3*(COUNT($I$9:N$9)+$I$4))),TREND($E40:$F40,$E$9:$F$9,N$9)) -> 0 | O40: =IF($G40="s-curve",$E40+($F40-$E40)*$I$2/(1+EXP($I$3*(COUNT($I$9:O$9)+$I$4))),TREND($E40:$F40,$E$9:$F$9,O$9)) -> 0 | P40: =IF($G40="s-curve",$E40+($F40-$E40)*$I$2/(1+EXP($I$3*(COUNT($I$9:P$9)+$I$4))),TREND($E40:$F40,$E$9:$F$9,P$9)) -> 0 | Q40: =IF($G40="s-curve",$E40+($F40-$E40)*$I$2/(1+EXP($I$3*(COUNT($I$9:Q$9)+$I$4))),TREND($E40:$F40,$E$9:$F$9,Q$9)) -> 0 | ... AI40: =IF($G40="s-curve",$E40+($F40-$E40)*$I$2/(1+EXP($I$3*(COUNT($I$9:AI$9)+$I$4))),TREND($E40:$F40,$E$9:$F$9,AI$9)) -> 0
C41: diesel vehicle | E41: 1 | F41: 1 | G41: =IF(E41=F41,"n/a",IF(OR(C41="battery electric vehicle",C41="natural gas vehicle",C41="plugin hybrid vehicle"),"s-curve","linear")) -> n/a | I41: =E41 -> 1 | J41: =IF($G41="s-curve",$E41+($F41-$E41)*$I$2/(1+EXP($I$3*(COUNT($I$9:J$9)+$I$4))),TREND($E41:$F41,$E$9:$F$9,J$9)) -> 1 | K41: =IF($G41="s-curve",$E41+($F41-$E41)*$I$2/(1+EXP($I$3*(COUNT($I$9:K$9)+$I$4))),TREND($E41:$F41,$E$9:$F$9,K$9)) -> 1 | L41: =IF($G41="s-curve",$E41+($F41-$E41)*$I$2/(1+EXP($I$3*(COUNT($I$9:L$9)+$I$4))),TREND($E41:$F41,$E$9:$F$9,L$9)) -> 1 | M41: =IF($G41="s-curve",$E41+($F41-$E41)*$I$2/(1+EXP($I$3*(COUNT($I$9:M$9)+$I$4))),TREND($E41:$F41,$E$9:$F$9,M$9)) -> 1 | N41: =IF($G41="s-curve",$E41+($F41-$E41)*$I$2/(1+EXP($I$3*(COUNT($I$9:N$9)+$I$4))),TREND($E41:$F41,$E$9:$F$9,N$9)) -> 1 | O41: =IF($G41="s-curve",$E41+($F41-$E41)*$I$2/(1+EXP($I$3*(COUNT($I$9:O$9)+$I$4))),TREND($E41:$F41,$E$9:$F$9,O$9)) -> 1 | P41: =IF($G41="s-curve",$E41+($F41-$E41)*$I$2/(1+EXP($I$3*(COUNT($I$9:P$9)+$I$4))),TREND($E41:$F41,$E$9:$F$9,P$9)) -> 1 | Q41: =IF($G41="s-curve",$E41+($F41-$E41)*$I$2/(1+EXP($I$3*(COUNT($I$9:Q$9)+$I$4))),TREND($E41:$F41,$E$9:$F$9,Q$9)) -> 1 | ... AI41: =IF($G41="s-curve",$E41+($F41-$E41)*$I$2/(1+EXP($I$3*(COUNT($I$9:AI$9)+$I$4))),TREND($E41:$F41,$E$9:$F$9,AI$9)) -> 1
C42: plugin hybrid vehicle | E42: 0 | F42: 0 | G42: =IF(E42=F42,"n/a",IF(OR(C42="battery electric vehicle",C42="natural gas vehicle",C42="plugin hybrid vehicle"),"s-curve","linear")) -> n/a | I42: =E42 -> 0 | J42: =IF($G42="s-curve",$E42+($F42-$E42)*$I$2/(1+EXP($I$3*(COUNT($I$9:J$9)+$I$4))),TREND($E42:$F42,$E$9:$F$9,J$9)) -> 0 | K42: =IF($G42="s-curve",$E42+($F42-$E42)*$I$2/(1+EXP($I$3*(COUNT($I$9:K$9)+$I$4))),TREND($E42:$F42,$E$9:$F$9,K$9)) -> 0 | L42: =IF($G42="s-curve",$E42+($F42-$E42)*$I$2/(1+EXP($I$3*(COUNT($I$9:L$9)+$I$4))),TREND($E42:$F42,$E$9:$F$9,L$9)) -> 0 | M42: =IF($G42="s-curve",$E42+($F42-$E42)*$I$2/(1+EXP($I$3*(COUNT($I$9:M$9)+$I$4))),TREND($E42:$F42,$E$9:$F$9,M$9)) -> 0 | N42: =IF($G42="s-curve",$E42+($F42-$E42)*$I$2/(1+EXP($I$3*(COUNT($I$9:N$9)+$I$4))),TREND($E42:$F42,$E$9:$F$9,N$9)) -> 0 | O42: =IF($G42="s-curve",$E42+($F42-$E42)*$I$2/(1+EXP($I$3*(COUNT($I$9:O$9)+$I$4))),TREND($E42:$F42,$E$9:$F$9,O$9)) -> 0 | P42: =IF($G42="s-curve",$E42+($F42-$E42)*$I$2/(1+EXP($I$3*(COUNT($I$9:P$9)+$I$4))),TREND($E42:$F42,$E$9:$F$9,P$9)) -> 0 | Q42: =IF($G42="s-curve",$E42+($F42-$E42)*$I$2/(1+EXP($I$3*(COUNT($I$9:Q$9)+$I$4))),TREND($E42:$F42,$E$9:$F$9,Q$9)) -> 0 | ... AI42: =IF($G42="s-curve",$E42+($F42-$E42)*$I$2/(1+EXP($I$3*(COUNT($I$9:AI$9)+$I$4))),TREND($E42:$F42,$E$9:$F$9,AI$9)) -> 0
C43: LPG vehicle | E43: 0 | F43: 0 | G43: =IF(E43=F43,"n/a",IF(OR(C43="battery electric vehicle",C43="natural gas vehicle",C43="plugin hybrid vehicle",C43="hydrogen vehicle"),"s-curve","linear")) -> n/a | I43: =E43 -> 0 | J43: =IF($G43="s-curve",$E43+($F43-$E43)*$I$2/(1+EXP($I$3*(COUNT($I$9:J$9)+$I$4))),TREND($E43:$F43,$E$9:$F$9,J$9)) -> 0 | K43: =IF($G43="s-curve",$E43+($F43-$E43)*$I$2/(1+EXP($I$3*(COUNT($I$9:K$9)+$I$4))),TREND($E43:$F43,$E$9:$F$9,K$9)) -> 0 | L43: =IF($G43="s-curve",$E43+($F43-$E43)*$I$2/(1+EXP($I$3*(COUNT($I$9:L$9)+$I$4))),TREND($E43:$F43,$E$9:$F$9,L$9)) -> 0 | M43: =IF($G43="s-curve",$E43+($F43-$E43)*$I$2/(1+EXP($I$3*(COUNT($I$9:M$9)+$I$4))),TREND($E43:$F43,$E$9:$F$9,M$9)) -> 0 | N43: =IF($G43="s-curve",$E43+($F43-$E43)*$I$2/(1+EXP($I$3*(COUNT($I$9:N$9)+$I$4))),TREND($E43:$F43,$E$9:$F$9,N$9)) -> 0 | O43: =IF($G43="s-curve",$E43+($F43-$E43)*$I$2/(1+EXP($I$3*(COUNT($I$9:O$9)+$I$4))),TREND($E43:$F43,$E$9:$F$9,O$9)) -> 0 | P43: =IF($G43="s-curve",$E43+($F43-$E43)*$I$2/(1+EXP($I$3*(COUNT($I$9:P$9)+$I$4))),TREND($E43:$F43,$E$9:$F$9,P$9)) -> 0 | Q43: =IF($G43="s-curve",$E43+($F43-$E43)*$I$2/(1+EXP($I$3*(COUNT($I$9:Q$9)+$I$4))),TREND($E43:$F43,$E$9:$F$9,Q$9)) -> 0 | ... AI43: =IF($G43="s-curve",$E43+($F43-$E43)*$I$2/(1+EXP($I$3*(COUNT($I$9:AI$9)+$I$4))),TREND($E43:$F43,$E$9:$F$9,AI$9)) -> 0
C44: hydrogen vehicle | E44: 0 | F44: 0 | G44: =IF(E44=F44,"n/a",IF(OR(C44="battery electric vehicle",C44="natural gas vehicle",C44="plugin hybrid vehicle",C44="hydrogen vehicle"),"s-curve","linear")) -> n/a | I44: =E44 -> 0 | J44: =IF($G44="s-curve",$E44+($F44-$E44)*$I$2/(1+EXP($I$3*(COUNT($I$9:J$9)+$I$4))),TREND($E44:$F44,$E$9:$F$9,J$9)) -> 0 | K44: =IF($G44="s-curve",$E44+($F44-$E44)*$I$2/(1+EXP($I$3*(COUNT($I$9:K$9)+$I$4))),TREND($E44:$F44,$E$9:$F$9,K$9)) -> 0 | L44: =IF($G44="s-curve",$E44+($F44-$E44)*$I$2/(1+EXP($I$3*(COUNT($I$9:L$9)+$I$4))),TREND($E44:$F44,$E$9:$F$9,L$9)) -> 0 | M44: =IF($G44="s-curve",$E44+($F44-$E44)*$I$2/(1+EXP($I$3*(COUNT($I$9:M$9)+$I$4))),TREND($E44:$F44,$E$9:$F$9,M$9)) -> 0 | N44: =IF($G44="s-curve",$E44+($F44-$E44)*$I$2/(1+EXP($I$3*(COUNT($I$9:N$9)+$I$4))),TREND($E44:$F44,$E$9:$F$9,N$9)) -> 0 | O44: =IF($G44="s-curve",$E44+($F44-$E44)*$I$2/(1+EXP($I$3*(COUNT($I$9:O$9)+$I$4))),TREND($E44:$F44,$E$9:$F$9,O$9)) -> 0 | P44: =IF($G44="s-curve",$E44+($F44-$E44)*$I$2/(1+EXP($I$3*(COUNT($I$9:P$9)+$I$4))),TREND($E44:$F44,$E$9:$F$9,P$9)) -> 0 | Q44: =IF($G44="s-curve",$E44+($F44-$E44)*$I$2/(1+EXP($I$3*(COUNT($I$9:Q$9)+$I$4))),TREND($E44:$F44,$E$9:$F$9,Q$9)) -> 0 | ... AI44: =IF($G44="s-curve",$E44+($F44-$E44)*$I$2/(1+EXP($I$3*(COUNT($I$9:AI$9)+$I$4))),TREND($E44:$F44,$E$9:$F$9,AI$9)) -> 0
A45: aircraft | B45: freight | C45: battery electric vehicle | E45: 0 | F45: 0 | G45: =IF(E45=F45,"n/a",IF(OR(C45="battery electric vehicle",C45="natural gas vehicle",C45="plugin hybrid vehicle"),"s-curve","linear")) -> n/a | I45: =E45 -> 0 | J45: =IF($G45="s-curve",$E45+($F45-$E45)*$I$2/(1+EXP($I$3*(COUNT($I$9:J$9)+$I$4))),TREND($E45:$F45,$E$9:$F$9,J$9)) -> 0 | K45: =IF($G45="s-curve",$E45+($F45-$E45)*$I$2/(1+EXP($I$3*(COUNT($I$9:K$9)+$I$4))),TREND($E45:$F45,$E$9:$F$9,K$9)) -> 0 | L45: =IF($G45="s-curve",$E45+($F45-$E45)*$I$2/(1+EXP($I$3*(COUNT($I$9:L$9)+$I$4))),TREND($E45:$F45,$E$9:$F$9,L$9)) -> 0 | M45: =IF($G45="s-curve",$E45+($F45-$E45)*$I$2/(1+EXP($I$3*(COUNT($I$9:M$9)+$I$4))),TREND($E45:$F45,$E$9:$F$9,M$9)) -> 0 | N45: =IF($G45="s-curve",$E45+($F45-$E45)*$I$2/(1+EXP($I$3*(COUNT($I$9:N$9)+$I$4))),TREND($E45:$F45,$E$9:$F$9,N$9)) -> 0 | O45: =IF($G45="s-curve",$E45+($F45-$E45)*$I$2/(1+EXP($I$3*(COUNT($I$9:O$9)+$I$4))),TREND($E45:$F45,$E$9:$F$9,O$9)) -> 0 | P45: =IF($G45="s-curve",$E45+($F45-$E45)*$I$2/(1+EXP($I$3*(COUNT($I$9:P$9)+$I$4))),TREND($E45:$F45,$E$9:$F$9,P$9)) -> 0 | Q45: =IF($G45="s-curve",$E45+($F45-$E45)*$I$2/(1+EXP($I$3*(COUNT($I$9:Q$9)+$I$4))),TREND($E45:$F45,$E$9:$F$9,Q$9)) -> 0 | ... AI45: =IF($G45="s-curve",$E45+($F45-$E45)*$I$2/(1+EXP($I$3*(COUNT($I$9:AI$9)+$I$4))),TREND($E45:$F45,$E$9:$F$9,AI$9)) -> 0
C46: natural gas vehicle | E46: 0 | F46: 0 | G46: =IF(E46=F46,"n/a",IF(OR(C46="battery electric vehicle",C46="natural gas vehicle",C46="plugin hybrid vehicle"),"s-curve","linear")) -> n/a | I46: =E46 -> 0 | J46: =IF($G46="s-curve",$E46+($F46-$E46)*$I$2/(1+EXP($I$3*(COUNT($I$9:J$9)+$I$4))),TREND($E46:$F46,$E$9:$F$9,J$9)) -> 0 | K46: =IF($G46="s-curve",$E46+($F46-$E46)*$I$2/(1+EXP($I$3*(COUNT($I$9:K$9)+$I$4))),TREND($E46:$F46,$E$9:$F$9,K$9)) -> 0 | L46: =IF($G46="s-curve",$E46+($F46-$E46)*$I$2/(1+EXP($I$3*(COUNT($I$9:L$9)+$I$4))),TREND($E46:$F46,$E$9:$F$9,L$9)) -> 0 | M46: =IF($G46="s-curve",$E46+($F46-$E46)*$I$2/(1+EXP($I$3*(COUNT($I$9:M$9)+$I$4))),TREND($E46:$F46,$E$9:$F$9,M$9)) -> 0 | N46: =IF($G46="s-curve",$E46+($F46-$E46)*$I$2/(1+EXP($I$3*(COUNT($I$9:N$9)+$I$4))),TREND($E46:$F46,$E$9:$F$9,N$9)) -> 0 | O46: =IF($G46="s-curve",$E46+($F46-$E46)*$I$2/(1+EXP($I$3*(COUNT($I$9:O$9)+$I$4))),TREND($E46:$F46,$E$9:$F$9,O$9)) -> 0 | P46: =IF($G46="s-curve",$E46+($F46-$E46)*$I$2/(1+EXP($I$3*(COUNT($I$9:P$9)+$I$4))),TREND($E46:$F46,$E$9:$F$9,P$9)) -> 0 | Q46: =IF($G46="s-curve",$E46+($F46-$E46)*$I$2/(1+EXP($I$3*(COUNT($I$9:Q$9)+$I$4))),TREND($E46:$F46,$E$9:$F$9,Q$9)) -> 0 | ... AI46: =IF($G46="s-curve",$E46+($F46-$E46)*$I$2/(1+EXP($I$3*(COUNT($I$9:AI$9)+$I$4))),TREND($E46:$F46,$E$9:$F$9,AI$9)) -> 0
C47: gasoline vehicle | E47: 0 | F47: 0 | G47: =IF(E47=F47,"n/a",IF(OR(C47="battery electric vehicle",C47="natural gas vehicle",C47="plugin hybrid vehicle"),"s-curve","linear")) -> n/a | I47: =E47 -> 0 | J47: =IF($G47="s-curve",$E47+($F47-$E47)*$I$2/(1+EXP($I$3*(COUNT($I$9:J$9)+$I$4))),TREND($E47:$F47,$E$9:$F$9,J$9)) -> 0 | K47: =IF($G47="s-curve",$E47+($F47-$E47)*$I$2/(1+EXP($I$3*(COUNT($I$9:K$9)+$I$4))),TREND($E47:$F47,$E$9:$F$9,K$9)) -> 0 | L47: =IF($G47="s-curve",$E47+($F47-$E47)*$I$2/(1+EXP($I$3*(COUNT($I$9:L$9)+$I$4))),TREND($E47:$F47,$E$9:$F$9,L$9)) -> 0 | M47: =IF($G47="s-curve",$E47+($F47-$E47)*$I$2/(1+EXP($I$3*(COUNT($I$9:M$9)+$I$4))),TREND($E47:$F47,$E$9:$F$9,M$9)) -> 0 | N47: =IF($G47="s-curve",$E47+($F47-$E47)*$I$2/(1+EXP($I$3*(COUNT($I$9:N$9)+$I$4))),TREND($E47:$F47,$E$9:$F$9,N$9)) -> 0 | O47: =IF($G47="s-curve",$E47+($F47-$E47)*$I$2/(1+EXP($I$3*(COUNT($I$9:O$9)+$I$4))),TREND($E47:$F47,$E$9:$F$9,O$9)) -> 0 | P47: =IF($G47="s-curve",$E47+($F47-$E47)*$I$2/(1+EXP($I$3*(COUNT($I$9:P$9)+$I$4))),TREND($E47:$F47,$E$9:$F$9,P$9)) -> 0 | Q47: =IF($G47="s-curve",$E47+($F47-$E47)*$I$2/(1+EXP($I$3*(COUNT($I$9:Q$9)+$I$4))),TREND($E47:$F47,$E$9:$F$9,Q$9)) -> 0 | ... AI47: =IF($G47="s-curve",$E47+($F47-$E47)*$I$2/(1+EXP($I$3*(COUNT($I$9:AI$9)+$I$4))),TREND($E47:$F47,$E$9:$F$9,AI$9)) -> 0
C48: diesel vehicle | E48: 1 | F48: 1 | G48: =IF(E48=F48,"n/a",IF(OR(C48="battery electric vehicle",C48="natural gas vehicle",C48="plugin hybrid vehicle"),"s-curve","linear")) -> n/a | I48: =E48 -> 1 | J48: =IF($G48="s-curve",$E48+($F48-$E48)*$I$2/(1+EXP($I$3*(COUNT($I$9:J$9)+$I$4))),TREND($E48:$F48,$E$9:$F$9,J$9)) -> 1 | K48: =IF($G48="s-curve",$E48+($F48-$E48)*$I$2/(1+EXP($I$3*(COUNT($I$9:K$9)+$I$4))),TREND($E48:$F48,$E$9:$F$9,K$9)) -> 1 | L48: =IF($G48="s-curve",$E48+($F48-$E48)*$I$2/(1+EXP($I$3*(COUNT($I$9:L$9)+$I$4))),TREND($E48:$F48,$E$9:$F$9,L$9)) -> 1 | M48: =IF($G48="s-curve",$E48+($F48-$E48)*$I$2/(1+EXP($I$3*(COUNT($I$9:M$9)+$I$4))),TREND($E48:$F48,$E$9:$F$9,M$9)) -> 1 | N48: =IF($G48="s-curve",$E48+($F48-$E48)*$I$2/(1+EXP($I$3*(COUNT($I$9:N$9)+$I$4))),TREND($E48:$F48,$E$9:$F$9,N$9)) -> 1 | O48: =IF($G48="s-curve",$E48+($F48-$E48)*$I$2/(1+EXP($I$3*(COUNT($I$9:O$9)+$I$4))),TREND($E48:$F48,$E$9:$F$9,O$9)) -> 1 | P48: =IF($G48="s-curve",$E48+($F48-$E48)*$I$2/(1+EXP($I$3*(COUNT($I$9:P$9)+$I$4))),TREND($E48:$F48,$E$9:$F$9,P$9)) -> 1 | Q48: =IF($G48="s-curve",$E48+($F48-$E48)*$I$2/(1+EXP($I$3*(COUNT($I$9:Q$9)+$I$4))),TREND($E48:$F48,$E$9:$F$9,Q$9)) -> 1 | ... AI48: =IF($G48="s-curve",$E48+($F48-$E48)*$I$2/(1+EXP($I$3*(COUNT($I$9:AI$9)+$I$4))),TREND($E48:$F48,$E$9:$F$9,AI$9)) -> 1
C49: plugin hybrid vehicle | E49: 0 | F49: 0 | G49: =IF(E49=F49,"n/a",IF(OR(C49="battery electric vehicle",C49="natural gas vehicle",C49="plugin hybrid vehicle"),"s-curve","linear")) -> n/a | I49: =E49 -> 0 | J49: =IF($G49="s-curve",$E49+($F49-$E49)*$I$2/(1+EXP($I$3*(COUNT($I$9:J$9)+$I$4))),TREND($E49:$F49,$E$9:$F$9,J$9)) -> 0 | K49: =IF($G49="s-curve",$E49+($F49-$E49)*$I$2/(1+EXP($I$3*(COUNT($I$9:K$9)+$I$4))),TREND($E49:$F49,$E$9:$F$9,K$9)) -> 0 | L49: =IF($G49="s-curve",$E49+($F49-$E49)*$I$2/(1+EXP($I$3*(COUNT($I$9:L$9)+$I$4))),TREND($E49:$F49,$E$9:$F$9,L$9)) -> 0 | M49: =IF($G49="s-curve",$E49+($F49-$E49)*$I$2/(1+EXP($I$3*(COUNT($I$9:M$9)+$I$4))),TREND($E49:$F49,$E$9:$F$9,M$9)) -> 0 | N49: =IF($G49="s-curve",$E49+($F49-$E49)*$I$2/(1+EXP($I$3*(COUNT($I$9:N$9)+$I$4))),TREND($E49:$F49,$E$9:$F$9,N$9)) -> 0 | O49: =IF($G49="s-curve",$E49+($F49-$E49)*$I$2/(1+EXP($I$3*(COUNT($I$9:O$9)+$I$4))),TREND($E49:$F49,$E$9:$F$9,O$9)) -> 0 | P49: =IF($G49="s-curve",$E49+($F49-$E49)*$I$2/(1+EXP($I$3*(COUNT($I$9:P$9)+$I$4))),TREND($E49:$F49,$E$9:$F$9,P$9)) -> 0 | Q49: =IF($G49="s-curve",$E49+($F49-$E49)*$I$2/(1+EXP($I$3*(COUNT($I$9:Q$9)+$I$4))),TREND($E49:$F49,$E$9:$F$9,Q$9)) -> 0 | ... AI49: =IF($G49="s-curve",$E49+($F49-$E49)*$I$2/(1+EXP($I$3*(COUNT($I$9:AI$9)+$I$4))),TREND($E49:$F49,$E$9:$F$9,AI$9)) -> 0
C50: LPG vehicle | E50: 0 | F50: 0 | G50: =IF(E50=F50,"n/a",IF(OR(C50="battery electric vehicle",C50="natural gas vehicle",C50="plugin hybrid vehicle",C50="hydrogen vehicle"),"s-curve","linear")) -> n/a | I50: =E50 -> 0 | J50: =IF($G50="s-curve",$E50+($F50-$E50)*$I$2/(1+EXP($I$3*(COUNT($I$9:J$9)+$I$4))),TREND($E50:$F50,$E$9:$F$9,J$9)) -> 0 | K50: =IF($G50="s-curve",$E50+($F50-$E50)*$I$2/(1+EXP($I$3*(COUNT($I$9:K$9)+$I$4))),TREND($E50:$F50,$E$9:$F$9,K$9)) -> 0 | L50: =IF($G50="s-curve",$E50+($F50-$E50)*$I$2/(1+EXP($I$3*(COUNT($I$9:L$9)+$I$4))),TREND($E50:$F50,$E$9:$F$9,L$9)) -> 0 | M50: =IF($G50="s-curve",$E50+($F50-$E50)*$I$2/(1+EXP($I$3*(COUNT($I$9:M$9)+$I$4))),TREND($E50:$F50,$E$9:$F$9,M$9)) -> 0 | N50: =IF($G50="s-curve",$E50+($F50-$E50)*$I$2/(1+EXP($I$3*(COUNT($I$9:N$9)+$I$4))),TREND($E50:$F50,$E$9:$F$9,N$9)) -> 0 | O50: =IF($G50="s-curve",$E50+($F50-$E50)*$I$2/(1+EXP($I$3*(COUNT($I$9:O$9)+$I$4))),TREND($E50:$F50,$E$9:$F$9,O$9)) -> 0 | P50: =IF($G50="s-curve",$E50+($F50-$E50)*$I$2/(1+EXP($I$3*(COUNT($I$9:P$9)+$I$4))),TREND($E50:$F50,$E$9:$F$9,P$9)) -> 0 | Q50: =IF($G50="s-curve",$E50+($F50-$E50)*$I$2/(1+EXP($I$3*(COUNT($I$9:Q$9)+$I$4))),TREND($E50:$F50,$E$9:$F$9,Q$9)) -> 0 | ... AI50: =IF($G50="s-curve",$E50+($F50-$E50)*$I$2/(1+EXP($I$3*(COUNT($I$9:AI$9)+$I$4))),TREND($E50:$F50,$E$9:$F$9,AI$9)) -> 0
C51: hydrogen vehicle | E51: 0 | F51: 0 | G51: =IF(E51=F51,"n/a",IF(OR(C51="battery electric vehicle",C51="natural gas vehicle",C51="plugin hybrid vehicle",C51="hydrogen vehicle"),"s-curve","linear")) -> n/a | I51: =E51 -> 0 | J51: =IF($G51="s-curve",$E51+($F51-$E51)*$I$2/(1+EXP($I$3*(COUNT($I$9:J$9)+$I$4))),TREND($E51:$F51,$E$9:$F$9,J$9)) -> 0 | K51: =IF($G51="s-curve",$E51+($F51-$E51)*$I$2/(1+EXP($I$3*(COUNT($I$9:K$9)+$I$4))),TREND($E51:$F51,$E$9:$F$9,K$9)) -> 0 | L51: =IF($G51="s-curve",$E51+($F51-$E51)*$I$2/(1+EXP($I$3*(COUNT($I$9:L$9)+$I$4))),TREND($E51:$F51,$E$9:$F$9,L$9)) -> 0 | M51: =IF($G51="s-curve",$E51+($F51-$E51)*$I$2/(1+EXP($I$3*(COUNT($I$9:M$9)+$I$4))),TREND($E51:$F51,$E$9:$F$9,M$9)) -> 0 | N51: =IF($G51="s-curve",$E51+($F51-$E51)*$I$2/(1+EXP($I$3*(COUNT($I$9:N$9)+$I$4))),TREND($E51:$F51,$E$9:$F$9,N$9)) -> 0 | O51: =IF($G51="s-curve",$E51+($F51-$E51)*$I$2/(1+EXP($I$3*(COUNT($I$9:O$9)+$I$4))),TREND($E51:$F51,$E$9:$F$9,O$9)) -> 0 | P51: =IF($G51="s-curve",$E51+($F51-$E51)*$I$2/(1+EXP($I$3*(COUNT($I$9:P$9)+$I$4))),TREND($E51:$F51,$E$9:$F$9,P$9)) -> 0 | Q51: =IF($G51="s-curve",$E51+($F51-$E51)*$I$2/(1+EXP($I$3*(COUNT($I$9:Q$9)+$I$4))),TREND($E51:$F51,$E$9:$F$9,Q$9)) -> 0 | ... AI51: =IF($G51="s-curve",$E51+($F51-$E51)*$I$2/(1+EXP($I$3*(COUNT($I$9:AI$9)+$I$4))),TREND($E51:$F51,$E$9:$F$9,AI$9)) -> 0
A52: rail | B52: passenger | C52: battery electric vehicle | E52: ='Calibration rail'!C4 -> 1 | F52: =E52 -> 1 | G52: linear | I52: =E52 -> 1 | J52: =IF($G52="s-curve",$E52+($F52-$E52)*$I$2/(1+EXP($I$3*(COUNT($I$9:J$9)+$I$4))),TREND($E52:$F52,$E$9:$F$9,J$9)) -> 1 | K52: =IF($G52="s-curve",$E52+($F52-$E52)*$I$2/(1+EXP($I$3*(COUNT($I$9:K$9)+$I$4))),TREND($E52:$F52,$E$9:$F$9,K$9)) -> 1 | L52: =IF($G52="s-curve",$E52+($F52-$E52)*$I$2/(1+EXP($I$3*(COUNT($I$9:L$9)+$I$4))),TREND($E52:$F52,$E$9:$F$9,L$9)) -> 1 | M52: =IF($G52="s-curve",$E52+($F52-$E52)*$I$2/(1+EXP($I$3*(COUNT($I$9:M$9)+$I$4))),TREND($E52:$F52,$E$9:$F$9,M$9)) -> 1 | N52: =IF($G52="s-curve",$E52+($F52-$E52)*$I$2/(1+EXP($I$3*(COUNT($I$9:N$9)+$I$4))),TREND($E52:$F52,$E$9:$F$9,N$9)) -> 1 | O52: =IF($G52="s-curve",$E52+($F52-$E52)*$I$2/(1+EXP($I$3*(COUNT($I$9:O$9)+$I$4))),TREND($E52:$F52,$E$9:$F$9,O$9)) -> 1 | P52: =IF($G52="s-curve",$E52+($F52-$E52)*$I$2/(1+EXP($I$3*(COUNT($I$9:P$9)+$I$4))),TREND($E52:$F52,$E$9:$F$9,P$9)) -> 1 | Q52: =IF($G52="s-curve",$E52+($F52-$E52)*$I$2/(1+EXP($I$3*(COUNT($I$9:Q$9)+$I$4))),TREND($E52:$F52,$E$9:$F$9,Q$9)) -> 1 | ... AI52: =IF($G52="s-curve",$E52+($F52-$E52)*$I$2/(1+EXP($I$3*(COUNT($I$9:AI$9)+$I$4))),TREND($E52:$F52,$E$9:$F$9,AI$9)) -> 1
C53: natural gas vehicle | E53: 0 | F53: 0 | G53: =IF(E53=F53,"n/a",IF(OR(C53="battery electric vehicle",C53="natural gas vehicle",C53="plugin hybrid vehicle"),"s-curve","linear")) -> n/a | I53: =E53 -> 0 | J53: =IF($G53="s-curve",$E53+($F53-$E53)*$I$2/(1+EXP($I$3*(COUNT($I$9:J$9)+$I$4))),TREND($E53:$F53,$E$9:$F$9,J$9)) -> 0 | K53: =IF($G53="s-curve",$E53+($F53-$E53)*$I$2/(1+EXP($I$3*(COUNT($I$9:K$9)+$I$4))),TREND($E53:$F53,$E$9:$F$9,K$9)) -> 0 | L53: =IF($G53="s-curve",$E53+($F53-$E53)*$I$2/(1+EXP($I$3*(COUNT($I$9:L$9)+$I$4))),TREND($E53:$F53,$E$9:$F$9,L$9)) -> 0 | M53: =IF($G53="s-curve",$E53+($F53-$E53)*$I$2/(1+EXP($I$3*(COUNT($I$9:M$9)+$I$4))),TREND($E53:$F53,$E$9:$F$9,M$9)) -> 0 | N53: =IF($G53="s-curve",$E53+($F53-$E53)*$I$2/(1+EXP($I$3*(COUNT($I$9:N$9)+$I$4))),TREND($E53:$F53,$E$9:$F$9,N$9)) -> 0 | O53: =IF($G53="s-curve",$E53+($F53-$E53)*$I$2/(1+EXP($I$3*(COUNT($I$9:O$9)+$I$4))),TREND($E53:$F53,$E$9:$F$9,O$9)) -> 0 | P53: =IF($G53="s-curve",$E53+($F53-$E53)*$I$2/(1+EXP($I$3*(COUNT($I$9:P$9)+$I$4))),TREND($E53:$F53,$E$9:$F$9,P$9)) -> 0 | Q53: =IF($G53="s-curve",$E53+($F53-$E53)*$I$2/(1+EXP($I$3*(COUNT($I$9:Q$9)+$I$4))),TREND($E53:$F53,$E$9:$F$9,Q$9)) -> 0 | ... AI53: =IF($G53="s-curve",$E53+($F53-$E53)*$I$2/(1+EXP($I$3*(COUNT($I$9:AI$9)+$I$4))),TREND($E53:$F53,$E$9:$F$9,AI$9)) -> 0
C54: gasoline vehicle | E54: 0 | F54: 0 | G54: =IF(E54=F54,"n/a",IF(OR(C54="battery electric vehicle",C54="natural gas vehicle",C54="plugin hybrid vehicle"),"s-curve","linear")) -> n/a | I54: =E54 -> 0 | J54: =IF($G54="s-curve",$E54+($F54-$E54)*$I$2/(1+EXP($I$3*(COUNT($I$9:J$9)+$I$4))),TREND($E54:$F54,$E$9:$F$9,J$9)) -> 0 | K54: =IF($G54="s-curve",$E54+($F54-$E54)*$I$2/(1+EXP($I$3*(COUNT($I$9:K$9)+$I$4))),TREND($E54:$F54,$E$9:$F$9,K$9)) -> 0 | L54: =IF($G54="s-curve",$E54+($F54-$E54)*$I$2/(1+EXP($I$3*(COUNT($I$9:L$9)+$I$4))),TREND($E54:$F54,$E$9:$F$9,L$9)) -> 0 | M54: =IF($G54="s-curve",$E54+($F54-$E54)*$I$2/(1+EXP($I$3*(COUNT($I$9:M$9)+$I$4))),TREND($E54:$F54,$E$9:$F$9,M$9)) -> 0 | N54: =IF($G54="s-curve",$E54+($F54-$E54)*$I$2/(1+EXP($I$3*(COUNT($I$9:N$9)+$I$4))),TREND($E54:$F54,$E$9:$F$9,N$9)) -> 0 | O54: =IF($G54="s-curve",$E54+($F54-$E54)*$I$2/(1+EXP($I$3*(COUNT($I$9:O$9)+$I$4))),TREND($E54:$F54,$E$9:$F$9,O$9)) -> 0 | P54: =IF($G54="s-curve",$E54+($F54-$E54)*$I$2/(1+EXP($I$3*(COUNT($I$9:P$9)+$I$4))),TREND($E54:$F54,$E$9:$F$9,P$9)) -> 0 | Q54: =IF($G54="s-curve",$E54+($F54-$E54)*$I$2/(1+EXP($I$3*(COUNT($I$9:Q$9)+$I$4))),TREND($E54:$F54,$E$9:$F$9,Q$9)) -> 0 | ... AI54: =IF($G54="s-curve",$E54+($F54-$E54)*$I$2/(1+EXP($I$3*(COUNT($I$9:AI$9)+$I$4))),TREND($E54:$F54,$E$9:$F$9,AI$9)) -> 0
C55: diesel vehicle | E55: ='Calibration rail'!C5 -> 0.10755845 | F55: =E55 -> 0.10755845 | G55: =IF(E55=F55,"n/a",IF(OR(C55="battery electric vehicle",C55="natural gas vehicle",C55="plugin hybrid vehicle"),"s-curve","linear")) -> n/a | I55: =E55 -> 0.10755845 | J55: =IF($G55="s-curve",$E55+($F55-$E55)*$I$2/(1+EXP($I$3*(COUNT($I$9:J$9)+$I$4))),TREND($E55:$F55,$E$9:$F$9,J$9)) -> 0.10755845 | K55: =IF($G55="s-curve",$E55+($F55-$E55)*$I$2/(1+EXP($I$3*(COUNT($I$9:K$9)+$I$4))),TREND($E55:$F55,$E$9:$F$9,K$9)) -> 0.10755845 | L55: =IF($G55="s-curve",$E55+($F55-$E55)*$I$2/(1+EXP($I$3*(COUNT($I$9:L$9)+$I$4))),TREND($E55:$F55,$E$9:$F$9,L$9)) -> 0.10755845 | M55: =IF($G55="s-curve",$E55+($F55-$E55)*$I$2/(1+EXP($I$3*(COUNT($I$9:M$9)+$I$4))),TREND($E55:$F55,$E$9:$F$9,M$9)) -> 0.10755845 | N55: =IF($G55="s-curve",$E55+($F55-$E55)*$I$2/(1+EXP($I$3*(COUNT($I$9:N$9)+$I$4))),TREND($E55:$F55,$E$9:$F$9,N$9)) -> 0.10755845 | O55: =IF($G55="s-curve",$E55+($F55-$E55)*$I$2/(1+EXP($I$3*(COUNT($I$9:O$9)+$I$4))),TREND($E55:$F55,$E$9:$F$9,O$9)) -> 0.10755845 | P55: =IF($G55="s-curve",$E55+($F55-$E55)*$I$2/(1+EXP($I$3*(COUNT($I$9:P$9)+$I$4))),TREND($E55:$F55,$E$9:$F$9,P$9)) -> 0.10755845 | Q55: =IF($G55="s-curve",$E55+($F55-$E55)*$I$2/(1+EXP($I$3*(COUNT($I$9:Q$9)+$I$4))),TREND($E55:$F55,$E$9:$F$9,Q$9)) -> 0.10755845 | ... AI55: =IF($G55="s-curve",$E55+($F55-$E55)*$I$2/(1+EXP($I$3*(COUNT($I$9:AI$9)+$I$4))),TREND($E55:$F55,$E$9:$F$9,AI$9)) -> 0.10755845
C56: plugin hybrid vehicle | E56: 0 | F56: 0 | G56: =IF(E56=F56,"n/a",IF(OR(C56="battery electric vehicle",C56="natural gas vehicle",C56="plugin hybrid vehicle"),"s-curve","linear")) -> n/a | I56: =E56 -> 0 | J56: =IF($G56="s-curve",$E56+($F56-$E56)*$I$2/(1+EXP($I$3*(COUNT($I$9:J$9)+$I$4))),TREND($E56:$F56,$E$9:$F$9,J$9)) -> 0 | K56: =IF($G56="s-curve",$E56+($F56-$E56)*$I$2/(1+EXP($I$3*(COUNT($I$9:K$9)+$I$4))),TREND($E56:$F56,$E$9:$F$9,K$9)) -> 0 | L56: =IF($G56="s-curve",$E56+($F56-$E56)*$I$2/(1+EXP($I$3*(COUNT($I$9:L$9)+$I$4))),TREND($E56:$F56,$E$9:$F$9,L$9)) -> 0 | M56: =IF($G56="s-curve",$E56+($F56-$E56)*$I$2/(1+EXP($I$3*(COUNT($I$9:M$9)+$I$4))),TREND($E56:$F56,$E$9:$F$9,M$9)) -> 0 | N56: =IF($G56="s-curve",$E56+($F56-$E56)*$I$2/(1+EXP($I$3*(COUNT($I$9:N$9)+$I$4))),TREND($E56:$F56,$E$9:$F$9,N$9)) -> 0 | O56: =IF($G56="s-curve",$E56+($F56-$E56)*$I$2/(1+EXP($I$3*(COUNT($I$9:O$9)+$I$4))),TREND($E56:$F56,$E$9:$F$9,O$9)) -> 0 | P56: =IF($G56="s-curve",$E56+($F56-$E56)*$I$2/(1+EXP($I$3*(COUNT($I$9:P$9)+$I$4))),TREND($E56:$F56,$E$9:$F$9,P$9)) -> 0 | Q56: =IF($G56="s-curve",$E56+($F56-$E56)*$I$2/(1+EXP($I$3*(COUNT($I$9:Q$9)+$I$4))),TREND($E56:$F56,$E$9:$F$9,Q$9)) -> 0 | ... AI56: =IF($G56="s-curve",$E56+($F56-$E56)*$I$2/(1+EXP($I$3*(COUNT($I$9:AI$9)+$I$4))),TREND($E56:$F56,$E$9:$F$9,AI$9)) -> 0
C57: LPG vehicle | E57: 0 | F57: 0 | G57: =IF(E57=F57,"n/a",IF(OR(C57="battery electric vehicle",C57="natural gas vehicle",C57="plugin hybrid vehicle",C57="hydrogen vehicle"),"s-curve","linear")) -> n/a | I57: =E57 -> 0 | J57: =IF($G57="s-curve",$E57+($F57-$E57)*$I$2/(1+EXP($I$3*(COUNT($I$9:J$9)+$I$4))),TREND($E57:$F57,$E$9:$F$9,J$9)) -> 0 | K57: =IF($G57="s-curve",$E57+($F57-$E57)*$I$2/(1+EXP($I$3*(COUNT($I$9:K$9)+$I$4))),TREND($E57:$F57,$E$9:$F$9,K$9)) -> 0 | L57: =IF($G57="s-curve",$E57+($F57-$E57)*$I$2/(1+EXP($I$3*(COUNT($I$9:L$9)+$I$4))),TREND($E57:$F57,$E$9:$F$9,L$9)) -> 0 | M57: =IF($G57="s-curve",$E57+($F57-$E57)*$I$2/(1+EXP($I$3*(COUNT($I$9:M$9)+$I$4))),TREND($E57:$F57,$E$9:$F$9,M$9)) -> 0 | N57: =IF($G57="s-curve",$E57+($F57-$E57)*$I$2/(1+EXP($I$3*(COUNT($I$9:N$9)+$I$4))),TREND($E57:$F57,$E$9:$F$9,N$9)) -> 0 | O57: =IF($G57="s-curve",$E57+($F57-$E57)*$I$2/(1+EXP($I$3*(COUNT($I$9:O$9)+$I$4))),TREND($E57:$F57,$E$9:$F$9,O$9)) -> 0 | P57: =IF($G57="s-curve",$E57+($F57-$E57)*$I$2/(1+EXP($I$3*(COUNT($I$9:P$9)+$I$4))),TREND($E57:$F57,$E$9:$F$9,P$9)) -> 0 | Q57: =IF($G57="s-curve",$E57+($F57-$E57)*$I$2/(1+EXP($I$3*(COUNT($I$9:Q$9)+$I$4))),TREND($E57:$F57,$E$9:$F$9,Q$9)) -> 0 | ... AI57: =IF($G57="s-curve",$E57+($F57-$E57)*$I$2/(1+EXP($I$3*(COUNT($I$9:AI$9)+$I$4))),TREND($E57:$F57,$E$9:$F$9,AI$9)) -> 0
C58: hydrogen vehicle | E58: 0 | F58: 0 | G58: =IF(E58=F58,"n/a",IF(OR(C58="battery electric vehicle",C58="natural gas vehicle",C58="plugin hybrid vehicle",C58="hydrogen vehicle"),"s-curve","linear")) -> n/a | I58: =E58 -> 0 | J58: =IF($G58="s-curve",$E58+($F58-$E58)*$I$2/(1+EXP($I$3*(COUNT($I$9:J$9)+$I$4))),TREND($E58:$F58,$E$9:$F$9,J$9)) -> 0 | K58: =IF($G58="s-curve",$E58+($F58-$E58)*$I$2/(1+EXP($I$3*(COUNT($I$9:K$9)+$I$4))),TREND($E58:$F58,$E$9:$F$9,K$9)) -> 0 | L58: =IF($G58="s-curve",$E58+($F58-$E58)*$I$2/(1+EXP($I$3*(COUNT($I$9:L$9)+$I$4))),TREND($E58:$F58,$E$9:$F$9,L$9)) -> 0 | M58: =IF($G58="s-curve",$E58+($F58-$E58)*$I$2/(1+EXP($I$3*(COUNT($I$9:M$9)+$I$4))),TREND($E58:$F58,$E$9:$F$9,M$9)) -> 0 | N58: =IF($G58="s-curve",$E58+($F58-$E58)*$I$2/(1+EXP($I$3*(COUNT($I$9:N$9)+$I$4))),TREND($E58:$F58,$E$9:$F$9,N$9)) -> 0 | O58: =IF($G58="s-curve",$E58+($F58-$E58)*$I$2/(1+EXP($I$3*(COUNT($I$9:O$9)+$I$4))),TREND($E58:$F58,$E$9:$F$9,O$9)) -> 0 | P58: =IF($G58="s-curve",$E58+($F58-$E58)*$I$2/(1+EXP($I$3*(COUNT($I$9:P$9)+$I$4))),TREND($E58:$F58,$E$9:$F$9,P$9)) -> 0 | Q58: =IF($G58="s-curve",$E58+($F58-$E58)*$I$2/(1+EXP($I$3*(COUNT($I$9:Q$9)+$I$4))),TREND($E58:$F58,$E$9:$F$9,Q$9)) -> 0 | ... AI58: =IF($G58="s-curve",$E58+($F58-$E58)*$I$2/(1+EXP($I$3*(COUNT($I$9:AI$9)+$I$4))),TREND($E58:$F58,$E$9:$F$9,AI$9)) -> 0
A59: rail | B59: freight | C59: battery electric vehicle | E59: 0 | F59: 0 | G59: =IF(E59=F59,"n/a",IF(OR(C59="battery electric vehicle",C59="natural gas vehicle",C59="plugin hybrid vehicle"),"s-curve","linear")) -> n/a | I59: =E59 -> 0 | J59: =IF($G59="s-curve",$E59+($F59-$E59)*$I$2/(1+EXP($I$3*(COUNT($I$9:J$9)+$I$4))),TREND($E59:$F59,$E$9:$F$9,J$9)) -> 0 | K59: =IF($G59="s-curve",$E59+($F59-$E59)*$I$2/(1+EXP($I$3*(COUNT($I$9:K$9)+$I$4))),TREND($E59:$F59,$E$9:$F$9,K$9)) -> 0 | L59: =IF($G59="s-curve",$E59+($F59-$E59)*$I$2/(1+EXP($I$3*(COUNT($I$9:L$9)+$I$4))),TREND($E59:$F59,$E$9:$F$9,L$9)) -> 0 | M59: =IF($G59="s-curve",$E59+($F59-$E59)*$I$2/(1+EXP($I$3*(COUNT($I$9:M$9)+$I$4))),TREND($E59:$F59,$E$9:$F$9,M$9)) -> 0 | N59: =IF($G59="s-curve",$E59+($F59-$E59)*$I$2/(1+EXP($I$3*(COUNT($I$9:N$9)+$I$4))),TREND($E59:$F59,$E$9:$F$9,N$9)) -> 0 | O59: =IF($G59="s-curve",$E59+($F59-$E59)*$I$2/(1+EXP($I$3*(COUNT($I$9:O$9)+$I$4))),TREND($E59:$F59,$E$9:$F$9,O$9)) -> 0 | P59: =IF($G59="s-curve",$E59+($F59-$E59)*$I$2/(1+EXP($I$3*(COUNT($I$9:P$9)+$I$4))),TREND($E59:$F59,$E$9:$F$9,P$9)) -> 0 | Q59: =IF($G59="s-curve",$E59+($F59-$E59)*$I$2/(1+EXP($I$3*(COUNT($I$9:Q$9)+$I$4))),TREND($E59:$F59,$E$9:$F$9,Q$9)) -> 0 | ... AI59: =IF($G59="s-curve",$E59+($F59-$E59)*$I$2/(1+EXP($I$3*(COUNT($I$9:AI$9)+$I$4))),TREND($E59:$F59,$E$9:$F$9,AI$9)) -> 0
C60: natural gas vehicle | E60: 0 | F60: 0 | G60: =IF(E60=F60,"n/a",IF(OR(C60="battery electric vehicle",C60="natural gas vehicle",C60="plugin hybrid vehicle"),"s-curve","linear")) -> n/a | I60: =E60 -> 0 | J60: =IF($G60="s-curve",$E60+($F60-$E60)*$I$2/(1+EXP($I$3*(COUNT($I$9:J$9)+$I$4))),TREND($E60:$F60,$E$9:$F$9,J$9)) -> 0 | K60: =IF($G60="s-curve",$E60+($F60-$E60)*$I$2/(1+EXP($I$3*(COUNT($I$9:K$9)+$I$4))),TREND($E60:$F60,$E$9:$F$9,K$9)) -> 0 | L60: =IF($G60="s-curve",$E60+($F60-$E60)*$I$2/(1+EXP($I$3*(COUNT($I$9:L$9)+$I$4))),TREND($E60:$F60,$E$9:$F$9,L$9)) -> 0 | M60: =IF($G60="s-curve",$E60+($F60-$E60)*$I$2/(1+EXP($I$3*(COUNT($I$9:M$9)+$I$4))),TREND($E60:$F60,$E$9:$F$9,M$9)) -> 0 | N60: =IF($G60="s-curve",$E60+($F60-$E60)*$I$2/(1+EXP($I$3*(COUNT($I$9:N$9)+$I$4))),TREND($E60:$F60,$E$9:$F$9,N$9)) -> 0 | O60: =IF($G60="s-curve",$E60+($F60-$E60)*$I$2/(1+EXP($I$3*(COUNT($I$9:O$9)+$I$4))),TREND($E60:$F60,$E$9:$F$9,O$9)) -> 0 | P60: =IF($G60="s-curve",$E60+($F60-$E60)*$I$2/(1+EXP($I$3*(COUNT($I$9:P$9)+$I$4))),TREND($E60:$F60,$E$9:$F$9,P$9)) -> 0 | Q60: =IF($G60="s-curve",$E60+($F60-$E60)*$I$2/(1+EXP($I$3*(COUNT($I$9:Q$9)+$I$4))),TREND($E60:$F60,$E$9:$F$9,Q$9)) -> 0 | ... AI60: =IF($G60="s-curve",$E60+($F60-$E60)*$I$2/(1+EXP($I$3*(COUNT($I$9:AI$9)+$I$4))),TREND($E60:$F60,$E$9:$F$9,AI$9)) -> 0
C61: gasoline vehicle | E61: 0 | F61: 0 | G61: =IF(E61=F61,"n/a",IF(OR(C61="battery electric vehicle",C61="natural gas vehicle",C61="plugin hybrid vehicle"),"s-curve","linear")) -> n/a | I61: =E61 -> 0 | J61: =IF($G61="s-curve",$E61+($F61-$E61)*$I$2/(1+EXP($I$3*(COUNT($I$9:J$9)+$I$4))),TREND($E61:$F61,$E$9:$F$9,J$9)) -> 0 | K61: =IF($G61="s-curve",$E61+($F61-$E61)*$I$2/(1+EXP($I$3*(COUNT($I$9:K$9)+$I$4))),TREND($E61:$F61,$E$9:$F$9,K$9)) -> 0 | L61: =IF($G61="s-curve",$E61+($F61-$E61)*$I$2/(1+EXP($I$3*(COUNT($I$9:L$9)+$I$4))),TREND($E61:$F61,$E$9:$F$9,L$9)) -> 0 | M61: =IF($G61="s-curve",$E61+($F61-$E61)*$I$2/(1+EXP($I$3*(COUNT($I$9:M$9)+$I$4))),TREND($E61:$F61,$E$9:$F$9,M$9)) -> 0 | N61: =IF($G61="s-curve",$E61+($F61-$E61)*$I$2/(1+EXP($I$3*(COUNT($I$9:N$9)+$I$4))),TREND($E61:$F61,$E$9:$F$9,N$9)) -> 0 | O61: =IF($G61="s-curve",$E61+($F61-$E61)*$I$2/(1+EXP($I$3*(COUNT($I$9:O$9)+$I$4))),TREND($E61:$F61,$E$9:$F$9,O$9)) -> 0 | P61: =IF($G61="s-curve",$E61+($F61-$E61)*$I$2/(1+EXP($I$3*(COUNT($I$9:P$9)+$I$4))),TREND($E61:$F61,$E$9:$F$9,P$9)) -> 0 | Q61: =IF($G61="s-curve",$E61+($F61-$E61)*$I$2/(1+EXP($I$3*(COUNT($I$9:Q$9)+$I$4))),TREND($E61:$F61,$E$9:$F$9,Q$9)) -> 0 | ... AI61: =IF($G61="s-curve",$E61+($F61-$E61)*$I$2/(1+EXP($I$3*(COUNT($I$9:AI$9)+$I$4))),TREND($E61:$F61,$E$9:$F$9,AI$9)) -> 0
C62: diesel vehicle | E62: 1 | F62: 1 | G62: =IF(E62=F62,"n/a",IF(OR(C62="battery electric vehicle",C62="natural gas vehicle",C62="plugin hybrid vehicle"),"s-curve","linear")) -> n/a | I62: =E62 -> 1 | J62: =IF($G62="s-curve",$E62+($F62-$E62)*$I$2/(1+EXP($I$3*(COUNT($I$9:J$9)+$I$4))),TREND($E62:$F62,$E$9:$F$9,J$9)) -> 1 | K62: =IF($G62="s-curve",$E62+($F62-$E62)*$I$2/(1+EXP($I$3*(COUNT($I$9:K$9)+$I$4))),TREND($E62:$F62,$E$9:$F$9,K$9)) -> 1 | L62: =IF($G62="s-curve",$E62+($F62-$E62)*$I$2/(1+EXP($I$3*(COUNT($I$9:L$9)+$I$4))),TREND($E62:$F62,$E$9:$F$9,L$9)) -> 1 | M62: =IF($G62="s-curve",$E62+($F62-$E62)*$I$2/(1+EXP($I$3*(COUNT($I$9:M$9)+$I$4))),TREND($E62:$F62,$E$9:$F$9,M$9)) -> 1 | N62: =IF($G62="s-curve",$E62+($F62-$E62)*$I$2/(1+EXP($I$3*(COUNT($I$9:N$9)+$I$4))),TREND($E62:$F62,$E$9:$F$9,N$9)) -> 1 | O62: =IF($G62="s-curve",$E62+($F62-$E62)*$I$2/(1+EXP($I$3*(COUNT($I$9:O$9)+$I$4))),TREND($E62:$F62,$E$9:$F$9,O$9)) -> 1 | P62: =IF($G62="s-curve",$E62+($F62-$E62)*$I$2/(1+EXP($I$3*(COUNT($I$9:P$9)+$I$4))),TREND($E62:$F62,$E$9:$F$9,P$9)) -> 1 | Q62: =IF($G62="s-curve",$E62+($F62-$E62)*$I$2/(1+EXP($I$3*(COUNT($I$9:Q$9)+$I$4))),TREND($E62:$F62,$E$9:$F$9,Q$9)) -> 1 | ... AI62: =IF($G62="s-curve",$E62+($F62-$E62)*$I$2/(1+EXP($I$3*(COUNT($I$9:AI$9)+$I$4))),TREND($E62:$F62,$E$9:$F$9,AI$9)) -> 1
C63: plugin hybrid vehicle | E63: 0 | F63: 0 | G63: =IF(E63=F63,"n/a",IF(OR(C63="battery electric vehicle",C63="natural gas vehicle",C63="plugin hybrid vehicle"),"s-curve","linear")) -> n/a | I63: =E63 -> 0 | J63: =IF($G63="s-curve",$E63+($F63-$E63)*$I$2/(1+EXP($I$3*(COUNT($I$9:J$9)+$I$4))),TREND($E63:$F63,$E$9:$F$9,J$9)) -> 0 | K63: =IF($G63="s-curve",$E63+($F63-$E63)*$I$2/(1+EXP($I$3*(COUNT($I$9:K$9)+$I$4))),TREND($E63:$F63,$E$9:$F$9,K$9)) -> 0 | L63: =IF($G63="s-curve",$E63+($F63-$E63)*$I$2/(1+EXP($I$3*(COUNT($I$9:L$9)+$I$4))),TREND($E63:$F63,$E$9:$F$9,L$9)) -> 0 | M63: =IF($G63="s-curve",$E63+($F63-$E63)*$I$2/(1+EXP($I$3*(COUNT($I$9:M$9)+$I$4))),TREND($E63:$F63,$E$9:$F$9,M$9)) -> 0 | N63: =IF($G63="s-curve",$E63+($F63-$E63)*$I$2/(1+EXP($I$3*(COUNT($I$9:N$9)+$I$4))),TREND($E63:$F63,$E$9:$F$9,N$9)) -> 0 | O63: =IF($G63="s-curve",$E63+($F63-$E63)*$I$2/(1+EXP($I$3*(COUNT($I$9:O$9)+$I$4))),TREND($E63:$F63,$E$9:$F$9,O$9)) -> 0 | P63: =IF($G63="s-curve",$E63+($F63-$E63)*$I$2/(1+EXP($I$3*(COUNT($I$9:P$9)+$I$4))),TREND($E63:$F63,$E$9:$F$9,P$9)) -> 0 | Q63: =IF($G63="s-curve",$E63+($F63-$E63)*$I$2/(1+EXP($I$3*(COUNT($I$9:Q$9)+$I$4))),TREND($E63:$F63,$E$9:$F$9,Q$9)) -> 0 | ... AI63: =IF($G63="s-curve",$E63+($F63-$E63)*$I$2/(1+EXP($I$3*(COUNT($I$9:AI$9)+$I$4))),TREND($E63:$F63,$E$9:$F$9,AI$9)) -> 0
C64: LPG vehicle | E64: 0 | F64: 0 | G64: =IF(E64=F64,"n/a",IF(OR(C64="battery electric vehicle",C64="natural gas vehicle",C64="plugin hybrid vehicle",C64="hydrogen vehicle"),"s-curve","linear")) -> n/a | I64: =E64 -> 0 | J64: =IF($G64="s-curve",$E64+($F64-$E64)*$I$2/(1+EXP($I$3*(COUNT($I$9:J$9)+$I$4))),TREND($E64:$F64,$E$9:$F$9,J$9)) -> 0 | K64: =IF($G64="s-curve",$E64+($F64-$E64)*$I$2/(1+EXP($I$3*(COUNT($I$9:K$9)+$I$4))),TREND($E64:$F64,$E$9:$F$9,K$9)) -> 0 | L64: =IF($G64="s-curve",$E64+($F64-$E64)*$I$2/(1+EXP($I$3*(COUNT($I$9:L$9)+$I$4))),TREND($E64:$F64,$E$9:$F$9,L$9)) -> 0 | M64: =IF($G64="s-curve",$E64+($F64-$E64)*$I$2/(1+EXP($I$3*(COUNT($I$9:M$9)+$I$4))),TREND($E64:$F64,$E$9:$F$9,M$9)) -> 0 | N64: =IF($G64="s-curve",$E64+($F64-$E64)*$I$2/(1+EXP($I$3*(COUNT($I$9:N$9)+$I$4))),TREND($E64:$F64,$E$9:$F$9,N$9)) -> 0 | O64: =IF($G64="s-curve",$E64+($F64-$E64)*$I$2/(1+EXP($I$3*(COUNT($I$9:O$9)+$I$4))),TREND($E64:$F64,$E$9:$F$9,O$9)) -> 0 | P64: =IF($G64="s-curve",$E64+($F64-$E64)*$I$2/(1+EXP($I$3*(COUNT($I$9:P$9)+$I$4))),TREND($E64:$F64,$E$9:$F$9,P$9)) -> 0 | Q64: =IF($G64="s-curve",$E64+($F64-$E64)*$I$2/(1+EXP($I$3*(COUNT($I$9:Q$9)+$I$4))),TREND($E64:$F64,$E$9:$F$9,Q$9)) -> 0 | ... AI64: =IF($G64="s-curve",$E64+($F64-$E64)*$I$2/(1+EXP($I$3*(COUNT($I$9:AI$9)+$I$4))),TREND($E64:$F64,$E$9:$F$9,AI$9)) -> 0
C65: hydrogen vehicle | E65: 0 | F65: 0 | G65: =IF(E65=F65,"n/a",IF(OR(C65="battery electric vehicle",C65="natural gas vehicle",C65="plugin hybrid vehicle",C65="hydrogen vehicle"),"s-curve","linear")) -> n/a | I65: =E65 -> 0 | J65: =IF($G65="s-curve",$E65+($F65-$E65)*$I$2/(1+EXP($I$3*(COUNT($I$9:J$9)+$I$4))),TREND($E65:$F65,$E$9:$F$9,J$9)) -> 0 | K65: =IF($G65="s-curve",$E65+($F65-$E65)*$I$2/(1+EXP($I$3*(COUNT($I$9:K$9)+$I$4))),TREND($E65:$F65,$E$9:$F$9,K$9)) -> 0 | L65: =IF($G65="s-curve",$E65+($F65-$E65)*$I$2/(1+EXP($I$3*(COUNT($I$9:L$9)+$I$4))),TREND($E65:$F65,$E$9:$F$9,L$9)) -> 0 | M65: =IF($G65="s-curve",$E65+($F65-$E65)*$I$2/(1+EXP($I$3*(COUNT($I$9:M$9)+$I$4))),TREND($E65:$F65,$E$9:$F$9,M$9)) -> 0 | N65: =IF($G65="s-curve",$E65+($F65-$E65)*$I$2/(1+EXP($I$3*(COUNT($I$9:N$9)+$I$4))),TREND($E65:$F65,$E$9:$F$9,N$9)) -> 0 | O65: =IF($G65="s-curve",$E65+($F65-$E65)*$I$2/(1+EXP($I$3*(COUNT($I$9:O$9)+$I$4))),TREND($E65:$F65,$E$9:$F$9,O$9)) -> 0 | P65: =IF($G65="s-curve",$E65+($F65-$E65)*$I$2/(1+EXP($I$3*(COUNT($I$9:P$9)+$I$4))),TREND($E65:$F65,$E$9:$F$9,P$9)) -> 0 | Q65: =IF($G65="s-curve",$E65+($F65-$E65)*$I$2/(1+EXP($I$3*(COUNT($I$9:Q$9)+$I$4))),TREND($E65:$F65,$E$9:$F$9,Q$9)) -> 0 | ... AI65: =IF($G65="s-curve",$E65+($F65-$E65)*$I$2/(1+EXP($I$3*(COUNT($I$9:AI$9)+$I$4))),TREND($E65:$F65,$E$9:$F$9,AI$9)) -> 0
A66: ships | B66: passenger | C66: battery electric vehicle | E66: 0 | F66: 0 | G66: =IF(E66=F66,"n/a",IF(OR(C66="battery electric vehicle",C66="natural gas vehicle",C66="plugin hybrid vehicle"),"s-curve","linear")) -> n/a | I66: =E66 -> 0 | J66: =IF($G66="s-curve",$E66+($F66-$E66)*$I$2/(1+EXP($I$3*(COUNT($I$9:J$9)+$I$4))),TREND($E66:$F66,$E$9:$F$9,J$9)) -> 0 | K66: =IF($G66="s-curve",$E66+($F66-$E66)*$I$2/(1+EXP($I$3*(COUNT($I$9:K$9)+$I$4))),TREND($E66:$F66,$E$9:$F$9,K$9)) -> 0 | L66: =IF($G66="s-curve",$E66+($F66-$E66)*$I$2/(1+EXP($I$3*(COUNT($I$9:L$9)+$I$4))),TREND($E66:$F66,$E$9:$F$9,L$9)) -> 0 | M66: =IF($G66="s-curve",$E66+($F66-$E66)*$I$2/(1+EXP($I$3*(COUNT($I$9:M$9)+$I$4))),TREND($E66:$F66,$E$9:$F$9,M$9)) -> 0 | N66: =IF($G66="s-curve",$E66+($F66-$E66)*$I$2/(1+EXP($I$3*(COUNT($I$9:N$9)+$I$4))),TREND($E66:$F66,$E$9:$F$9,N$9)) -> 0 | O66: =IF($G66="s-curve",$E66+($F66-$E66)*$I$2/(1+EXP($I$3*(COUNT($I$9:O$9)+$I$4))),TREND($E66:$F66,$E$9:$F$9,O$9)) -> 0 | P66: =IF($G66="s-curve",$E66+($F66-$E66)*$I$2/(1+EXP($I$3*(COUNT($I$9:P$9)+$I$4))),TREND($E66:$F66,$E$9:$F$9,P$9)) -> 0 | Q66: =IF($G66="s-curve",$E66+($F66-$E66)*$I$2/(1+EXP($I$3*(COUNT($I$9:Q$9)+$I$4))),TREND($E66:$F66,$E$9:$F$9,Q$9)) -> 0 | ... AI66: =IF($G66="s-curve",$E66+($F66-$E66)*$I$2/(1+EXP($I$3*(COUNT($I$9:AI$9)+$I$4))),TREND($E66:$F66,$E$9:$F$9,AI$9)) -> 0
C67: natural gas vehicle | E67: 0 | F67: 0 | G67: =IF(E67=F67,"n/a",IF(OR(C67="battery electric vehicle",C67="natural gas vehicle",C67="plugin hybrid vehicle"),"s-curve","linear")) -> n/a | I67: =E67 -> 0 | J67: =IF($G67="s-curve",$E67+($F67-$E67)*$I$2/(1+EXP($I$3*(COUNT($I$9:J$9)+$I$4))),TREND($E67:$F67,$E$9:$F$9,J$9)) -> 0 | K67: =IF($G67="s-curve",$E67+($F67-$E67)*$I$2/(1+EXP($I$3*(COUNT($I$9:K$9)+$I$4))),TREND($E67:$F67,$E$9:$F$9,K$9)) -> 0 | L67: =IF($G67="s-curve",$E67+($F67-$E67)*$I$2/(1+EXP($I$3*(COUNT($I$9:L$9)+$I$4))),TREND($E67:$F67,$E$9:$F$9,L$9)) -> 0 | M67: =IF($G67="s-curve",$E67+($F67-$E67)*$I$2/(1+EXP($I$3*(COUNT($I$9:M$9)+$I$4))),TREND($E67:$F67,$E$9:$F$9,M$9)) -> 0 | N67: =IF($G67="s-curve",$E67+($F67-$E67)*$I$2/(1+EXP($I$3*(COUNT($I$9:N$9)+$I$4))),TREND($E67:$F67,$E$9:$F$9,N$9)) -> 0 | O67: =IF($G67="s-curve",$E67+($F67-$E67)*$I$2/(1+EXP($I$3*(COUNT($I$9:O$9)+$I$4))),TREND($E67:$F67,$E$9:$F$9,O$9)) -> 0 | P67: =IF($G67="s-curve",$E67+($F67-$E67)*$I$2/(1+EXP($I$3*(COUNT($I$9:P$9)+$I$4))),TREND($E67:$F67,$E$9:$F$9,P$9)) -> 0 | Q67: =IF($G67="s-curve",$E67+($F67-$E67)*$I$2/(1+EXP($I$3*(COUNT($I$9:Q$9)+$I$4))),TREND($E67:$F67,$E$9:$F$9,Q$9)) -> 0 | ... AI67: =IF($G67="s-curve",$E67+($F67-$E67)*$I$2/(1+EXP($I$3*(COUNT($I$9:AI$9)+$I$4))),TREND($E67:$F67,$E$9:$F$9,AI$9)) -> 0
C68: gasoline vehicle | E68: 0 | F68: 0 | G68: =IF(E68=F68,"n/a",IF(OR(C68="battery electric vehicle",C68="natural gas vehicle",C68="plugin hybrid vehicle"),"s-curve","linear")) -> n/a | I68: =E68 -> 0 | J68: =IF($G68="s-curve",$E68+($F68-$E68)*$I$2/(1+EXP($I$3*(COUNT($I$9:J$9)+$I$4))),TREND($E68:$F68,$E$9:$F$9,J$9)) -> 0 | K68: =IF($G68="s-curve",$E68+($F68-$E68)*$I$2/(1+EXP($I$3*(COUNT($I$9:K$9)+$I$4))),TREND($E68:$F68,$E$9:$F$9,K$9)) -> 0 | L68: =IF($G68="s-curve",$E68+($F68-$E68)*$I$2/(1+EXP($I$3*(COUNT($I$9:L$9)+$I$4))),TREND($E68:$F68,$E$9:$F$9,L$9)) -> 0 | M68: =IF($G68="s-curve",$E68+($F68-$E68)*$I$2/(1+EXP($I$3*(COUNT($I$9:M$9)+$I$4))),TREND($E68:$F68,$E$9:$F$9,M$9)) -> 0 | N68: =IF($G68="s-curve",$E68+($F68-$E68)*$I$2/(1+EXP($I$3*(COUNT($I$9:N$9)+$I$4))),TREND($E68:$F68,$E$9:$F$9,N$9)) -> 0 | O68: =IF($G68="s-curve",$E68+($F68-$E68)*$I$2/(1+EXP($I$3*(COUNT($I$9:O$9)+$I$4))),TREND($E68:$F68,$E$9:$F$9,O$9)) -> 0 | P68: =IF($G68="s-curve",$E68+($F68-$E68)*$I$2/(1+EXP($I$3*(COUNT($I$9:P$9)+$I$4))),TREND($E68:$F68,$E$9:$F$9,P$9)) -> 0 | Q68: =IF($G68="s-curve",$E68+($F68-$E68)*$I$2/(1+EXP($I$3*(COUNT($I$9:Q$9)+$I$4))),TREND($E68:$F68,$E$9:$F$9,Q$9)) -> 0 | ... AI68: =IF($G68="s-curve",$E68+($F68-$E68)*$I$2/(1+EXP($I$3*(COUNT($I$9:AI$9)+$I$4))),TREND($E68:$F68,$E$9:$F$9,AI$9)) -> 0
C69: diesel vehicle | E69: 1 | F69: 1 | G69: =IF(E69=F69,"n/a",IF(OR(C69="battery electric vehicle",C69="natural gas vehicle",C69="plugin hybrid vehicle"),"s-curve","linear")) -> n/a | I69: =E69 -> 1 | J69: =IF($G69="s-curve",$E69+($F69-$E69)*$I$2/(1+EXP($I$3*(COUNT($I$9:J$9)+$I$4))),TREND($E69:$F69,$E$9:$F$9,J$9)) -> 1 | K69: =IF($G69="s-curve",$E69+($F69-$E69)*$I$2/(1+EXP($I$3*(COUNT($I$9:K$9)+$I$4))),TREND($E69:$F69,$E$9:$F$9,K$9)) -> 1 | L69: =IF($G69="s-curve",$E69+($F69-$E69)*$I$2/(1+EXP($I$3*(COUNT($I$9:L$9)+$I$4))),TREND($E69:$F69,$E$9:$F$9,L$9)) -> 1 | M69: =IF($G69="s-curve",$E69+($F69-$E69)*$I$2/(1+EXP($I$3*(COUNT($I$9:M$9)+$I$4))),TREND($E69:$F69,$E$9:$F$9,M$9)) -> 1 | N69: =IF($G69="s-curve",$E69+($F69-$E69)*$I$2/(1+EXP($I$3*(COUNT($I$9:N$9)+$I$4))),TREND($E69:$F69,$E$9:$F$9,N$9)) -> 1 | O69: =IF($G69="s-curve",$E69+($F69-$E69)*$I$2/(1+EXP($I$3*(COUNT($I$9:O$9)+$I$4))),TREND($E69:$F69,$E$9:$F$9,O$9)) -> 1 | P69: =IF($G69="s-curve",$E69+($F69-$E69)*$I$2/(1+EXP($I$3*(COUNT($I$9:P$9)+$I$4))),TREND($E69:$F69,$E$9:$F$9,P$9)) -> 1 | Q69: =IF($G69="s-curve",$E69+($F69-$E69)*$I$2/(1+EXP($I$3*(COUNT($I$9:Q$9)+$I$4))),TREND($E69:$F69,$E$9:$F$9,Q$9)) -> 1 | ... AI69: =IF($G69="s-curve",$E69+($F69-$E69)*$I$2/(1+EXP($I$3*(COUNT($I$9:AI$9)+$I$4))),TREND($E69:$F69,$E$9:$F$9,AI$9)) -> 1
C70: plugin hybrid vehicle | E70: 0 | F70: 0 | G70: =IF(E70=F70,"n/a",IF(OR(C70="battery electric vehicle",C70="natural gas vehicle",C70="plugin hybrid vehicle"),"s-curve","linear")) -> n/a | I70: =E70 -> 0 | J70: =IF($G70="s-curve",$E70+($F70-$E70)*$I$2/(1+EXP($I$3*(COUNT($I$9:J$9)+$I$4))),TREND($E70:$F70,$E$9:$F$9,J$9)) -> 0 | K70: =IF($G70="s-curve",$E70+($F70-$E70)*$I$2/(1+EXP($I$3*(COUNT($I$9:K$9)+$I$4))),TREND($E70:$F70,$E$9:$F$9,K$9)) -> 0 | L70: =IF($G70="s-curve",$E70+($F70-$E70)*$I$2/(1+EXP($I$3*(COUNT($I$9:L$9)+$I$4))),TREND($E70:$F70,$E$9:$F$9,L$9)) -> 0 | M70: =IF($G70="s-curve",$E70+($F70-$E70)*$I$2/(1+EXP($I$3*(COUNT($I$9:M$9)+$I$4))),TREND($E70:$F70,$E$9:$F$9,M$9)) -> 0 | N70: =IF($G70="s-curve",$E70+($F70-$E70)*$I$2/(1+EXP($I$3*(COUNT($I$9:N$9)+$I$4))),TREND($E70:$F70,$E$9:$F$9,N$9)) -> 0 | O70: =IF($G70="s-curve",$E70+($F70-$E70)*$I$2/(1+EXP($I$3*(COUNT($I$9:O$9)+$I$4))),TREND($E70:$F70,$E$9:$F$9,O$9)) -> 0 | P70: =IF($G70="s-curve",$E70+($F70-$E70)*$I$2/(1+EXP($I$3*(COUNT($I$9:P$9)+$I$4))),TREND($E70:$F70,$E$9:$F$9,P$9)) -> 0 | Q70: =IF($G70="s-curve",$E70+($F70-$E70)*$I$2/(1+EXP($I$3*(COUNT($I$9:Q$9)+$I$4))),TREND($E70:$F70,$E$9:$F$9,Q$9)) -> 0 | ... AI70: =IF($G70="s-curve",$E70+($F70-$E70)*$I$2/(1+EXP($I$3*(COUNT($I$9:AI$9)+$I$4))),TREND($E70:$F70,$E$9:$F$9,AI$9)) -> 0
C71: LPG vehicle | E71: 0 | F71: 0 | G71: =IF(E71=F71,"n/a",IF(OR(C71="battery electric vehicle",C71="natural gas vehicle",C71="plugin hybrid vehicle",C71="hydrogen vehicle"),"s-curve","linear")) -> n/a | I71: =E71 -> 0 | J71: =IF($G71="s-curve",$E71+($F71-$E71)*$I$2/(1+EXP($I$3*(COUNT($I$9:J$9)+$I$4))),TREND($E71:$F71,$E$9:$F$9,J$9)) -> 0 | K71: =IF($G71="s-curve",$E71+($F71-$E71)*$I$2/(1+EXP($I$3*(COUNT($I$9:K$9)+$I$4))),TREND($E71:$F71,$E$9:$F$9,K$9)) -> 0 | L71: =IF($G71="s-curve",$E71+($F71-$E71)*$I$2/(1+EXP($I$3*(COUNT($I$9:L$9)+$I$4))),TREND($E71:$F71,$E$9:$F$9,L$9)) -> 0 | M71: =IF($G71="s-curve",$E71+($F71-$E71)*$I$2/(1+EXP($I$3*(COUNT($I$9:M$9)+$I$4))),TREND($E71:$F71,$E$9:$F$9,M$9)) -> 0 | N71: =IF($G71="s-curve",$E71+($F71-$E71)*$I$2/(1+EXP($I$3*(COUNT($I$9:N$9)+$I$4))),TREND($E71:$F71,$E$9:$F$9,N$9)) -> 0 | O71: =IF($G71="s-curve",$E71+($F71-$E71)*$I$2/(1+EXP($I$3*(COUNT($I$9:O$9)+$I$4))),TREND($E71:$F71,$E$9:$F$9,O$9)) -> 0 | P71: =IF($G71="s-curve",$E71+($F71-$E71)*$I$2/(1+EXP($I$3*(COUNT($I$9:P$9)+$I$4))),TREND($E71:$F71,$E$9:$F$9,P$9)) -> 0 | Q71: =IF($G71="s-curve",$E71+($F71-$E71)*$I$2/(1+EXP($I$3*(COUNT($I$9:Q$9)+$I$4))),TREND($E71:$F71,$E$9:$F$9,Q$9)) -> 0 | ... AI71: =IF($G71="s-curve",$E71+($F71-$E71)*$I$2/(1+EXP($I$3*(COUNT($I$9:AI$9)+$I$4))),TREND($E71:$F71,$E$9:$F$9,AI$9)) -> 0
C72: hydrogen vehicle | E72: 0 | F72: 0 | G72: =IF(E72=F72,"n/a",IF(OR(C72="battery electric vehicle",C72="natural gas vehicle",C72="plugin hybrid vehicle",C72="hydrogen vehicle"),"s-curve","linear")) -> n/a | I72: =E72 -> 0 | J72: =IF($G72="s-curve",$E72+($F72-$E72)*$I$2/(1+EXP($I$3*(COUNT($I$9:J$9)+$I$4))),TREND($E72:$F72,$E$9:$F$9,J$9)) -> 0 | K72: =IF($G72="s-curve",$E72+($F72-$E72)*$I$2/(1+EXP($I$3*(COUNT($I$9:K$9)+$I$4))),TREND($E72:$F72,$E$9:$F$9,K$9)) -> 0 | L72: =IF($G72="s-curve",$E72+($F72-$E72)*$I$2/(1+EXP($I$3*(COUNT($I$9:L$9)+$I$4))),TREND($E72:$F72,$E$9:$F$9,L$9)) -> 0 | M72: =IF($G72="s-curve",$E72+($F72-$E72)*$I$2/(1+EXP($I$3*(COUNT($I$9:M$9)+$I$4))),TREND($E72:$F72,$E$9:$F$9,M$9)) -> 0 | N72: =IF($G72="s-curve",$E72+($F72-$E72)*$I$2/(1+EXP($I$3*(COUNT($I$9:N$9)+$I$4))),TREND($E72:$F72,$E$9:$F$9,N$9)) -> 0 | O72: =IF($G72="s-curve",$E72+($F72-$E72)*$I$2/(1+EXP($I$3*(COUNT($I$9:O$9)+$I$4))),TREND($E72:$F72,$E$9:$F$9,O$9)) -> 0 | P72: =IF($G72="s-curve",$E72+($F72-$E72)*$I$2/(1+EXP($I$3*(COUNT($I$9:P$9)+$I$4))),TREND($E72:$F72,$E$9:$F$9,P$9)) -> 0 | Q72: =IF($G72="s-curve",$E72+($F72-$E72)*$I$2/(1+EXP($I$3*(COUNT($I$9:Q$9)+$I$4))),TREND($E72:$F72,$E$9:$F$9,Q$9)) -> 0 | ... AI72: =IF($G72="s-curve",$E72+($F72-$E72)*$I$2/(1+EXP($I$3*(COUNT($I$9:AI$9)+$I$4))),TREND($E72:$F72,$E$9:$F$9,AI$9)) -> 0
A73: ships | B73: freight | C73: battery electric vehicle | E73: 0 | F73: 0 | G73: =IF(E73=F73,"n/a",IF(OR(C73="battery electric vehicle",C73="natural gas vehicle",C73="plugin hybrid vehicle"),"s-curve","linear")) -> n/a | I73: =E73 -> 0 | J73: =IF($G73="s-curve",$E73+($F73-$E73)*$I$2/(1+EXP($I$3*(COUNT($I$9:J$9)+$I$4))),TREND($E73:$F73,$E$9:$F$9,J$9)) -> 0 | K73: =IF($G73="s-curve",$E73+($F73-$E73)*$I$2/(1+EXP($I$3*(COUNT($I$9:K$9)+$I$4))),TREND($E73:$F73,$E$9:$F$9,K$9)) -> 0 | L73: =IF($G73="s-curve",$E73+($F73-$E73)*$I$2/(1+EXP($I$3*(COUNT($I$9:L$9)+$I$4))),TREND($E73:$F73,$E$9:$F$9,L$9)) -> 0 | M73: =IF($G73="s-curve",$E73+($F73-$E73)*$I$2/(1+EXP($I$3*(COUNT($I$9:M$9)+$I$4))),TREND($E73:$F73,$E$9:$F$9,M$9)) -> 0 | N73: =IF($G73="s-curve",$E73+($F73-$E73)*$I$2/(1+EXP($I$3*(COUNT($I$9:N$9)+$I$4))),TREND($E73:$F73,$E$9:$F$9,N$9)) -> 0 | O73: =IF($G73="s-curve",$E73+($F73-$E73)*$I$2/(1+EXP($I$3*(COUNT($I$9:O$9)+$I$4))),TREND($E73:$F73,$E$9:$F$9,O$9)) -> 0 | P73: =IF($G73="s-curve",$E73+($F73-$E73)*$I$2/(1+EXP($I$3*(COUNT($I$9:P$9)+$I$4))),TREND($E73:$F73,$E$9:$F$9,P$9)) -> 0 | Q73: =IF($G73="s-curve",$E73+($F73-$E73)*$I$2/(1+EXP($I$3*(COUNT($I$9:Q$9)+$I$4))),TREND($E73:$F73,$E$9:$F$9,Q$9)) -> 0 | ... AI73: =IF($G73="s-curve",$E73+($F73-$E73)*$I$2/(1+EXP($I$3*(COUNT($I$9:AI$9)+$I$4))),TREND($E73:$F73,$E$9:$F$9,AI$9)) -> 0
C74: natural gas vehicle | E74: 0 | F74: 0 | G74: =IF(E74=F74,"n/a",IF(OR(C74="battery electric vehicle",C74="natural gas vehicle",C74="plugin hybrid vehicle"),"s-curve","linear")) -> n/a | I74: =E74 -> 0 | J74: =IF($G74="s-curve",$E74+($F74-$E74)*$I$2/(1+EXP($I$3*(COUNT($I$9:J$9)+$I$4))),TREND($E74:$F74,$E$9:$F$9,J$9)) -> 0 | K74: =IF($G74="s-curve",$E74+($F74-$E74)*$I$2/(1+EXP($I$3*(COUNT($I$9:K$9)+$I$4))),TREND($E74:$F74,$E$9:$F$9,K$9)) -> 0 | L74: =IF($G74="s-curve",$E74+($F74-$E74)*$I$2/(1+EXP($I$3*(COUNT($I$9:L$9)+$I$4))),TREND($E74:$F74,$E$9:$F$9,L$9)) -> 0 | M74: =IF($G74="s-curve",$E74+($F74-$E74)*$I$2/(1+EXP($I$3*(COUNT($I$9:M$9)+$I$4))),TREND($E74:$F74,$E$9:$F$9,M$9)) -> 0 | N74: =IF($G74="s-curve",$E74+($F74-$E74)*$I$2/(1+EXP($I$3*(COUNT($I$9:N$9)+$I$4))),TREND($E74:$F74,$E$9:$F$9,N$9)) -> 0 | O74: =IF($G74="s-curve",$E74+($F74-$E74)*$I$2/(1+EXP($I$3*(COUNT($I$9:O$9)+$I$4))),TREND($E74:$F74,$E$9:$F$9,O$9)) -> 0 | P74: =IF($G74="s-curve",$E74+($F74-$E74)*$I$2/(1+EXP($I$3*(COUNT($I$9:P$9)+$I$4))),TREND($E74:$F74,$E$9:$F$9,P$9)) -> 0 | Q74: =IF($G74="s-curve",$E74+($F74-$E74)*$I$2/(1+EXP($I$3*(COUNT($I$9:Q$9)+$I$4))),TREND($E74:$F74,$E$9:$F$9,Q$9)) -> 0 | ... AI74: =IF($G74="s-curve",$E74+($F74-$E74)*$I$2/(1+EXP($I$3*(COUNT($I$9:AI$9)+$I$4))),TREND($E74:$F74,$E$9:$F$9,AI$9)) -> 0
C75: gasoline vehicle | E75: 0 | F75: 0 | G75: =IF(E75=F75,"n/a",IF(OR(C75="battery electric vehicle",C75="natural gas vehicle",C75="plugin hybrid vehicle"),"s-curve","linear")) -> n/a | I75: =E75 -> 0 | J75: =IF($G75="s-curve",$E75+($F75-$E75)*$I$2/(1+EXP($I$3*(COUNT($I$9:J$9)+$I$4))),TREND($E75:$F75,$E$9:$F$9,J$9)) -> 0 | K75: =IF($G75="s-curve",$E75+($F75-$E75)*$I$2/(1+EXP($I$3*(COUNT($I$9:K$9)+$I$4))),TREND($E75:$F75,$E$9:$F$9,K$9)) -> 0 | L75: =IF($G75="s-curve",$E75+($F75-$E75)*$I$2/(1+EXP($I$3*(COUNT($I$9:L$9)+$I$4))),TREND($E75:$F75,$E$9:$F$9,L$9)) -> 0 | M75: =IF($G75="s-curve",$E75+($F75-$E75)*$I$2/(1+EXP($I$3*(COUNT($I$9:M$9)+$I$4))),TREND($E75:$F75,$E$9:$F$9,M$9)) -> 0 | N75: =IF($G75="s-curve",$E75+($F75-$E75)*$I$2/(1+EXP($I$3*(COUNT($I$9:N$9)+$I$4))),TREND($E75:$F75,$E$9:$F$9,N$9)) -> 0 | O75: =IF($G75="s-curve",$E75+($F75-$E75)*$I$2/(1+EXP($I$3*(COUNT($I$9:O$9)+$I$4))),TREND($E75:$F75,$E$9:$F$9,O$9)) -> 0 | P75: =IF($G75="s-curve",$E75+($F75-$E75)*$I$2/(1+EXP($I$3*(COUNT($I$9:P$9)+$I$4))),TREND($E75:$F75,$E$9:$F$9,P$9)) -> 0 | Q75: =IF($G75="s-curve",$E75+($F75-$E75)*$I$2/(1+EXP($I$3*(COUNT($I$9:Q$9)+$I$4))),TREND($E75:$F75,$E$9:$F$9,Q$9)) -> 0 | ... AI75: =IF($G75="s-curve",$E75+($F75-$E75)*$I$2/(1+EXP($I$3*(COUNT($I$9:AI$9)+$I$4))),TREND($E75:$F75,$E$9:$F$9,AI$9)) -> 0
C76: diesel vehicle | E76: 1 | F76: 1 | G76: =IF(E76=F76,"n/a",IF(OR(C76="battery electric vehicle",C76="natural gas vehicle",C76="plugin hybrid vehicle"),"s-curve","linear")) -> n/a | I76: =E76 -> 1 | J76: =IF($G76="s-curve",$E76+($F76-$E76)*$I$2/(1+EXP($I$3*(COUNT($I$9:J$9)+$I$4))),TREND($E76:$F76,$E$9:$F$9,J$9)) -> 1 | K76: =IF($G76="s-curve",$E76+($F76-$E76)*$I$2/(1+EXP($I$3*(COUNT($I$9:K$9)+$I$4))),TREND($E76:$F76,$E$9:$F$9,K$9)) -> 1 | L76: =IF($G76="s-curve",$E76+($F76-$E76)*$I$2/(1+EXP($I$3*(COUNT($I$9:L$9)+$I$4))),TREND($E76:$F76,$E$9:$F$9,L$9)) -> 1 | M76: =IF($G76="s-curve",$E76+($F76-$E76)*$I$2/(1+EXP($I$3*(COUNT($I$9:M$9)+$I$4))),TREND($E76:$F76,$E$9:$F$9,M$9)) -> 1 | N76: =IF($G76="s-curve",$E76+($F76-$E76)*$I$2/(1+EXP($I$3*(COUNT($I$9:N$9)+$I$4))),TREND($E76:$F76,$E$9:$F$9,N$9)) -> 1 | O76: =IF($G76="s-curve",$E76+($F76-$E76)*$I$2/(1+EXP($I$3*(COUNT($I$9:O$9)+$I$4))),TREND($E76:$F76,$E$9:$F$9,O$9)) -> 1 | P76: =IF($G76="s-curve",$E76+($F76-$E76)*$I$2/(1+EXP($I$3*(COUNT($I$9:P$9)+$I$4))),TREND($E76:$F76,$E$9:$F$9,P$9)) -> 1 | Q76: =IF($G76="s-curve",$E76+($F76-$E76)*$I$2/(1+EXP($I$3*(COUNT($I$9:Q$9)+$I$4))),TREND($E76:$F76,$E$9:$F$9,Q$9)) -> 1 | ... AI76: =IF($G76="s-curve",$E76+($F76-$E76)*$I$2/(1+EXP($I$3*(COUNT($I$9:AI$9)+$I$4))),TREND($E76:$F76,$E$9:$F$9,AI$9)) -> 1
C77: plugin hybrid vehicle | E77: 0 | F77: 0 | G77: =IF(E77=F77,"n/a",IF(OR(C77="battery electric vehicle",C77="natural gas vehicle",C77="plugin hybrid vehicle"),"s-curve","linear")) -> n/a | I77: =E77 -> 0 | J77: =IF($G77="s-curve",$E77+($F77-$E77)*$I$2/(1+EXP($I$3*(COUNT($I$9:J$9)+$I$4))),TREND($E77:$F77,$E$9:$F$9,J$9)) -> 0 | K77: =IF($G77="s-curve",$E77+($F77-$E77)*$I$2/(1+EXP($I$3*(COUNT($I$9:K$9)+$I$4))),TREND($E77:$F77,$E$9:$F$9,K$9)) -> 0 | L77: =IF($G77="s-curve",$E77+($F77-$E77)*$I$2/(1+EXP($I$3*(COUNT($I$9:L$9)+$I$4))),TREND($E77:$F77,$E$9:$F$9,L$9)) -> 0 | M77: =IF($G77="s-curve",$E77+($F77-$E77)*$I$2/(1+EXP($I$3*(COUNT($I$9:M$9)+$I$4))),TREND($E77:$F77,$E$9:$F$9,M$9)) -> 0 | N77: =IF($G77="s-curve",$E77+($F77-$E77)*$I$2/(1+EXP($I$3*(COUNT($I$9:N$9)+$I$4))),TREND($E77:$F77,$E$9:$F$9,N$9)) -> 0 | O77: =IF($G77="s-curve",$E77+($F77-$E77)*$I$2/(1+EXP($I$3*(COUNT($I$9:O$9)+$I$4))),TREND($E77:$F77,$E$9:$F$9,O$9)) -> 0 | P77: =IF($G77="s-curve",$E77+($F77-$E77)*$I$2/(1+EXP($I$3*(COUNT($I$9:P$9)+$I$4))),TREND($E77:$F77,$E$9:$F$9,P$9)) -> 0 | Q77: =IF($G77="s-curve",$E77+($F77-$E77)*$I$2/(1+EXP($I$3*(COUNT($I$9:Q$9)+$I$4))),TREND($E77:$F77,$E$9:$F$9,Q$9)) -> 0 | ... AI77: =IF($G77="s-curve",$E77+($F77-$E77)*$I$2/(1+EXP($I$3*(COUNT($I$9:AI$9)+$I$4))),TREND($E77:$F77,$E$9:$F$9,AI$9)) -> 0
C78: LPG vehicle | E78: 0 | F78: 0 | G78: =IF(E78=F78,"n/a",IF(OR(C78="battery electric vehicle",C78="natural gas vehicle",C78="plugin hybrid vehicle",C78="hydrogen vehicle"),"s-curve","linear")) -> n/a | I78: =E78 -> 0 | J78: =IF($G78="s-curve",$E78+($F78-$E78)*$I$2/(1+EXP($I$3*(COUNT($I$9:J$9)+$I$4))),TREND($E78:$F78,$E$9:$F$9,J$9)) -> 0 | K78: =IF($G78="s-curve",$E78+($F78-$E78)*$I$2/(1+EXP($I$3*(COUNT($I$9:K$9)+$I$4))),TREND($E78:$F78,$E$9:$F$9,K$9)) -> 0 | L78: =IF($G78="s-curve",$E78+($F78-$E78)*$I$2/(1+EXP($I$3*(COUNT($I$9:L$9)+$I$4))),TREND($E78:$F78,$E$9:$F$9,L$9)) -> 0 | M78: =IF($G78="s-curve",$E78+($F78-$E78)*$I$2/(1+EXP($I$3*(COUNT($I$9:M$9)+$I$4))),TREND($E78:$F78,$E$9:$F$9,M$9)) -> 0 | N78: =IF($G78="s-curve",$E78+($F78-$E78)*$I$2/(1+EXP($I$3*(COUNT($I$9:N$9)+$I$4))),TREND($E78:$F78,$E$9:$F$9,N$9)) -> 0 | O78: =IF($G78="s-curve",$E78+($F78-$E78)*$I$2/(1+EXP($I$3*(COUNT($I$9:O$9)+$I$4))),TREND($E78:$F78,$E$9:$F$9,O$9)) -> 0 | P78: =IF($G78="s-curve",$E78+($F78-$E78)*$I$2/(1+EXP($I$3*(COUNT($I$9:P$9)+$I$4))),TREND($E78:$F78,$E$9:$F$9,P$9)) -> 0 | Q78: =IF($G78="s-curve",$E78+($F78-$E78)*$I$2/(1+EXP($I$3*(COUNT($I$9:Q$9)+$I$4))),TREND($E78:$F78,$E$9:$F$9,Q$9)) -> 0 | ... AI78: =IF($G78="s-curve",$E78+($F78-$E78)*$I$2/(1+EXP($I$3*(COUNT($I$9:AI$9)+$I$4))),TREND($E78:$F78,$E$9:$F$9,AI$9)) -> 0
C79: hydrogen vehicle | E79: 0 | F79: 0 | G79: =IF(E79=F79,"n/a",IF(OR(C79="battery electric vehicle",C79="natural gas vehicle",C79="plugin hybrid vehicle",C79="hydrogen vehicle"),"s-curve","linear")) -> n/a | I79: =E79 -> 0 | J79: =IF($G79="s-curve",$E79+($F79-$E79)*$I$2/(1+EXP($I$3*(COUNT($I$9:J$9)+$I$4))),TREND($E79:$F79,$E$9:$F$9,J$9)) -> 0 | K79: =IF($G79="s-curve",$E79+($F79-$E79)*$I$2/(1+EXP($I$3*(COUNT($I$9:K$9)+$I$4))),TREND($E79:$F79,$E$9:$F$9,K$9)) -> 0 | L79: =IF($G79="s-curve",$E79+($F79-$E79)*$I$2/(1+EXP($I$3*(COUNT($I$9:L$9)+$I$4))),TREND($E79:$F79,$E$9:$F$9,L$9)) -> 0 | M79: =IF($G79="s-curve",$E79+($F79-$E79)*$I$2/(1+EXP($I$3*(COUNT($I$9:M$9)+$I$4))),TREND($E79:$F79,$E$9:$F$9,M$9)) -> 0 | N79: =IF($G79="s-curve",$E79+($F79-$E79)*$I$2/(1+EXP($I$3*(COUNT($I$9:N$9)+$I$4))),TREND($E79:$F79,$E$9:$F$9,N$9)) -> 0 | O79: =IF($G79="s-curve",$E79+($F79-$E79)*$I$2/(1+EXP($I$3*(COUNT($I$9:O$9)+$I$4))),TREND($E79:$F79,$E$9:$F$9,O$9)) -> 0 | P79: =IF($G79="s-curve",$E79+($F79-$E79)*$I$2/(1+EXP($I$3*(COUNT($I$9:P$9)+$I$4))),TREND($E79:$F79,$E$9:$F$9,P$9)) -> 0 | Q79: =IF($G79="s-curve",$E79+($F79-$E79)*$I$2/(1+EXP($I$3*(COUNT($I$9:Q$9)+$I$4))),TREND($E79:$F79,$E$9:$F$9,Q$9)) -> 0 | ... AI79: =IF($G79="s-curve",$E79+($F79-$E79)*$I$2/(1+EXP($I$3*(COUNT($I$9:AI$9)+$I$4))),TREND($E79:$F79,$E$9:$F$9,AI$9)) -> 0
A80: motorbikes | B80: passenger | C80: battery electric vehicle | D80: =D10 -> 0.14828895 | E80: =E10 -> 0.14828895 | F80: =F10 -> 1 | G80: =IF(E80=F80,"n/a",IF(OR(C80="battery electric vehicle",C80="natural gas vehicle",C80="plugin hybrid vehicle"),"s-curve","linear")) -> s-curve | I80: =E80 -> 0.14828895 | J80: =IF($G80="s-curve",$E80+($F80-$E80)*$O$2/(1+EXP($O$3*(COUNT($I$9:J$9)+$O$4))),TREND($E80:$F80,$E$9:$F$9,J$9)) -> 0.20192405 | K80: =IF($G80="s-curve",$E80+($F80-$E80)*$O$2/(1+EXP($O$3*(COUNT($I$9:K$9)+$O$4))),TREND($E80:$F80,$E$9:$F$9,K$9)) -> 0.21912805 | L80: =IF($G80="s-curve",$E80+($F80-$E80)*$O$2/(1+EXP($O$3*(COUNT($I$9:L$9)+$O$4))),TREND($E80:$F80,$E$9:$F$9,L$9)) -> 0.24120792 | M80: =IF($G80="s-curve",$E80+($F80-$E80)*$O$2/(1+EXP($O$3*(COUNT($I$9:M$9)+$O$4))),TREND($E80:$F80,$E$9:$F$9,M$9)) -> 0.26910507 | N80: =IF($G80="s-curve",$E80+($F80-$E80)*$O$2/(1+EXP($O$3*(COUNT($I$9:N$9)+$O$4))),TREND($E80:$F80,$E$9:$F$9,N$9)) -> 0.30366278 | O80: =IF($G80="s-curve",$E80+($F80-$E80)*$O$2/(1+EXP($O$3*(COUNT($I$9:O$9)+$O$4))),TREND($E80:$F80,$E$9:$F$9,O$9)) -> 0.34543895 | P80: =IF($G80="s-curve",$E80+($F80-$E80)*$O$2/(1+EXP($O$3*(COUNT($I$9:P$9)+$O$4))),TREND($E80:$F80,$E$9:$F$9,P$9)) -> 0.39447645 | Q80: =IF($G80="s-curve",$E80+($F80-$E80)*$O$2/(1+EXP($O$3*(COUNT($I$9:Q$9)+$O$4))),TREND($E80:$F80,$E$9:$F$9,Q$9)) -> 0.45008739 | ... AI80: =IF($G80="s-curve",$E80+($F80-$E80)*$O$2/(1+EXP($O$3*(COUNT($I$9:AI$9)+$O$4))),TREND($E80:$F80,$E$9:$F$9,AI$9)) -> 0.99304785
C81: natural gas vehicle | D81: =D11 -> 0.00010097 | E81: =E11 -> 0.00010097 | F81: =F11 -> 0.00010097 | G81: =IF(E81=F81,"n/a",IF(OR(C81="battery electric vehicle",C81="natural gas vehicle",C81="plugin hybrid vehicle"),"s-curve","linear")) -> n/a | I81: =E81 -> 0.00010097 | J81: =IF($G81="s-curve",$E81+($F81-$E81)*$I$2/(1+EXP($I$3*(COUNT($I$9:J$9)+$I$4))),TREND($E81:$F81,$E$9:$F$9,J$9)) -> 0.00010097 | K81: =IF($G81="s-curve",$E81+($F81-$E81)*$I$2/(1+EXP($I$3*(COUNT($I$9:K$9)+$I$4))),TREND($E81:$F81,$E$9:$F$9,K$9)) -> 0.00010097 | L81: =IF($G81="s-curve",$E81+($F81-$E81)*$I$2/(1+EXP($I$3*(COUNT($I$9:L$9)+$I$4))),TREND($E81:$F81,$E$9:$F$9,L$9)) -> 0.00010097 | M81: =IF($G81="s-curve",$E81+($F81-$E81)*$I$2/(1+EXP($I$3*(COUNT($I$9:M$9)+$I$4))),TREND($E81:$F81,$E$9:$F$9,M$9)) -> 0.00010097 | N81: =IF($G81="s-curve",$E81+($F81-$E81)*$I$2/(1+EXP($I$3*(COUNT($I$9:N$9)+$I$4))),TREND($E81:$F81,$E$9:$F$9,N$9)) -> 0.00010097 | O81: =IF($G81="s-curve",$E81+($F81-$E81)*$I$2/(1+EXP($I$3*(COUNT($I$9:O$9)+$I$4))),TREND($E81:$F81,$E$9:$F$9,O$9)) -> 0.00010097 | P81: =IF($G81="s-curve",$E81+($F81-$E81)*$I$2/(1+EXP($I$3*(COUNT($I$9:P$9)+$I$4))),TREND($E81:$F81,$E$9:$F$9,P$9)) -> 0.00010097 | Q81: =IF($G81="s-curve",$E81+($F81-$E81)*$I$2/(1+EXP($I$3*(COUNT($I$9:Q$9)+$I$4))),TREND($E81:$F81,$E$9:$F$9,Q$9)) -> 0.00010097 | ... AI81: =IF($G81="s-curve",$E81+($F81-$E81)*$I$2/(1+EXP($I$3*(COUNT($I$9:AI$9)+$I$4))),TREND($E81:$F81,$E$9:$F$9,AI$9)) -> 0.00010097
C82: gasoline vehicle | D82: =D12 -> 1 | E82: =E12 -> 1 | F82: =F12 -> 1 | G82: =IF(E82=F82,"n/a",IF(OR(C82="battery electric vehicle",C82="natural gas vehicle",C82="plugin hybrid vehicle"),"s-curve","linear")) -> n/a | I82: =E82 -> 1 | J82: =IF($G82="s-curve",$E82+($F82-$E82)*$I$2/(1+EXP($I$3*(COUNT($I$9:J$9)+$I$4))),TREND($E82:$F82,$E$9:$F$9,J$9)) -> 1 | K82: =IF($G82="s-curve",$E82+($F82-$E82)*$I$2/(1+EXP($I$3*(COUNT($I$9:K$9)+$I$4))),TREND($E82:$F82,$E$9:$F$9,K$9)) -> 1 | L82: =IF($G82="s-curve",$E82+($F82-$E82)*$I$2/(1+EXP($I$3*(COUNT($I$9:L$9)+$I$4))),TREND($E82:$F82,$E$9:$F$9,L$9)) -> 1 | M82: =IF($G82="s-curve",$E82+($F82-$E82)*$I$2/(1+EXP($I$3*(COUNT($I$9:M$9)+$I$4))),TREND($E82:$F82,$E$9:$F$9,M$9)) -> 1 | N82: =IF($G82="s-curve",$E82+($F82-$E82)*$I$2/(1+EXP($I$3*(COUNT($I$9:N$9)+$I$4))),TREND($E82:$F82,$E$9:$F$9,N$9)) -> 1 | O82: =IF($G82="s-curve",$E82+($F82-$E82)*$I$2/(1+EXP($I$3*(COUNT($I$9:O$9)+$I$4))),TREND($E82:$F82,$E$9:$F$9,O$9)) -> 1 | P82: =IF($G82="s-curve",$E82+($F82-$E82)*$I$2/(1+EXP($I$3*(COUNT($I$9:P$9)+$I$4))),TREND($E82:$F82,$E$9:$F$9,P$9)) -> 1 | Q82: =IF($G82="s-curve",$E82+($F82-$E82)*$I$2/(1+EXP($I$3*(COUNT($I$9:Q$9)+$I$4))),TREND($E82:$F82,$E$9:$F$9,Q$9)) -> 1 | ... AI82: =IF($G82="s-curve",$E82+($F82-$E82)*$I$2/(1+EXP($I$3*(COUNT($I$9:AI$9)+$I$4))),TREND($E82:$F82,$E$9:$F$9,AI$9)) -> 1
C83: diesel vehicle | D83: =D13 -> 0.06738296 | E83: =E13 -> 0.06738296 | F83: =F13 -> 0.06738296 | G83: =IF(E83=F83,"n/a",IF(OR(C83="battery electric vehicle",C83="natural gas vehicle",C83="plugin hybrid vehicle"),"s-curve","linear")) -> n/a | I83: =E83 -> 0.06738296 | J83: =IF($G83="s-curve",$E83+($F83-$E83)*$I$2/(1+EXP($I$3*(COUNT($I$9:J$9)+$I$4))),TREND($E83:$F83,$E$9:$F$9,J$9)) -> 0.06738296 | K83: =IF($G83="s-curve",$E83+($F83-$E83)*$I$2/(1+EXP($I$3*(COUNT($I$9:K$9)+$I$4))),TREND($E83:$F83,$E$9:$F$9,K$9)) -> 0.06738296 | L83: =IF($G83="s-curve",$E83+($F83-$E83)*$I$2/(1+EXP($I$3*(COUNT($I$9:L$9)+$I$4))),TREND($E83:$F83,$E$9:$F$9,L$9)) -> 0.06738296 | M83: =IF($G83="s-curve",$E83+($F83-$E83)*$I$2/(1+EXP($I$3*(COUNT($I$9:M$9)+$I$4))),TREND($E83:$F83,$E$9:$F$9,M$9)) -> 0.06738296 | N83: =IF($G83="s-curve",$E83+($F83-$E83)*$I$2/(1+EXP($I$3*(COUNT($I$9:N$9)+$I$4))),TREND($E83:$F83,$E$9:$F$9,N$9)) -> 0.06738296 | O83: =IF($G83="s-curve",$E83+($F83-$E83)*$I$2/(1+EXP($I$3*(COUNT($I$9:O$9)+$I$4))),TREND($E83:$F83,$E$9:$F$9,O$9)) -> 0.06738296 | P83: =IF($G83="s-curve",$E83+($F83-$E83)*$I$2/(1+EXP($I$3*(COUNT($I$9:P$9)+$I$4))),TREND($E83:$F83,$E$9:$F$9,P$9)) -> 0.06738296 | Q83: =IF($G83="s-curve",$E83+($F83-$E83)*$I$2/(1+EXP($I$3*(COUNT($I$9:Q$9)+$I$4))),TREND($E83:$F83,$E$9:$F$9,Q$9)) -> 0.06738296 | ... AI83: =IF($G83="s-curve",$E83+($F83-$E83)*$I$2/(1+EXP($I$3*(COUNT($I$9:AI$9)+$I$4))),TREND($E83:$F83,$E$9:$F$9,AI$9)) -> 0.06738296
C84: plugin hybrid vehicle | D84: =D14 -> 0.014073499 | E84: =E14 -> 0.014073499 | F84: =F14 -> 0.10239067 | G84: =IF(E84=F84,"n/a",IF(OR(C84="battery electric vehicle",C84="natural gas vehicle",C84="plugin hybrid vehicle"),"s-curve","linear")) -> s-curve | I84: =E84 -> 0.014073499 | J84: =IF($G84="s-curve",$E84+($F84-$E84)*$I$2/(1+EXP($I$3*(COUNT($I$9:J$9)+$I$4))),TREND($E84:$F84,$E$9:$F$9,J$9)) -> 0.0153783 | K84: =IF($G84="s-curve",$E84+($F84-$E84)*$I$2/(1+EXP($I$3*(COUNT($I$9:K$9)+$I$4))),TREND($E84:$F84,$E$9:$F$9,K$9)) -> 0.015825739 | L84: =IF($G84="s-curve",$E84+($F84-$E84)*$I$2/(1+EXP($I$3*(COUNT($I$9:L$9)+$I$4))),TREND($E84:$F84,$E$9:$F$9,L$9)) -> 0.01642247 | M84: =IF($G84="s-curve",$E84+($F84-$E84)*$I$2/(1+EXP($I$3*(COUNT($I$9:M$9)+$I$4))),TREND($E84:$F84,$E$9:$F$9,M$9)) -> 0.017215046 | N84: =IF($G84="s-curve",$E84+($F84-$E84)*$I$2/(1+EXP($I$3*(COUNT($I$9:N$9)+$I$4))),TREND($E84:$F84,$E$9:$F$9,N$9)) -> 0.018262018 | O84: =IF($G84="s-curve",$E84+($F84-$E84)*$I$2/(1+EXP($I$3*(COUNT($I$9:O$9)+$I$4))),TREND($E84:$F84,$E$9:$F$9,O$9)) -> 0.019635127 | P84: =IF($G84="s-curve",$E84+($F84-$E84)*$I$2/(1+EXP($I$3*(COUNT($I$9:P$9)+$I$4))),TREND($E84:$F84,$E$9:$F$9,P$9)) -> 0.021419076 | Q84: =IF($G84="s-curve",$E84+($F84-$E84)*$I$2/(1+EXP($I$3*(COUNT($I$9:Q$9)+$I$4))),TREND($E84:$F84,$E$9:$F$9,Q$9)) -> 0.023708621 | ... AI84: =IF($G84="s-curve",$E84+($F84-$E84)*$I$2/(1+EXP($I$3*(COUNT($I$9:AI$9)+$I$4))),TREND($E84:$F84,$E$9:$F$9,AI$9)) -> 0.099249119
C85: LPG vehicle | D85: =D15 -> 0 | E85: =E15 -> 0 | F85: =F15 -> 0 | G85: =IF(E85=F85,"n/a",IF(OR(C85="battery electric vehicle",C85="natural gas vehicle",C85="plugin hybrid vehicle",C85="hydrogen vehicle"),"s-curve","linear")) -> n/a | I85: =E85 -> 0 | J85: =IF($G85="s-curve",$E85+($F85-$E85)*$I$2/(1+EXP($I$3*(COUNT($I$9:J$9)+$I$4))),TREND($E85:$F85,$E$9:$F$9,J$9)) -> 0 | K85: =IF($G85="s-curve",$E85+($F85-$E85)*$I$2/(1+EXP($I$3*(COUNT($I$9:K$9)+$I$4))),TREND($E85:$F85,$E$9:$F$9,K$9)) -> 0 | L85: =IF($G85="s-curve",$E85+($F85-$E85)*$I$2/(1+EXP($I$3*(COUNT($I$9:L$9)+$I$4))),TREND($E85:$F85,$E$9:$F$9,L$9)) -> 0 | M85: =IF($G85="s-curve",$E85+($F85-$E85)*$I$2/(1+EXP($I$3*(COUNT($I$9:M$9)+$I$4))),TREND($E85:$F85,$E$9:$F$9,M$9)) -> 0 | N85: =IF($G85="s-curve",$E85+($F85-$E85)*$I$2/(1+EXP($I$3*(COUNT($I$9:N$9)+$I$4))),TREND($E85:$F85,$E$9:$F$9,N$9)) -> 0 | O85: =IF($G85="s-curve",$E85+($F85-$E85)*$I$2/(1+EXP($I$3*(COUNT($I$9:O$9)+$I$4))),TREND($E85:$F85,$E$9:$F$9,O$9)) -> 0 | P85: =IF($G85="s-curve",$E85+($F85-$E85)*$I$2/(1+EXP($I$3*(COUNT($I$9:P$9)+$I$4))),TREND($E85:$F85,$E$9:$F$9,P$9)) -> 0 | Q85: =IF($G85="s-curve",$E85+($F85-$E85)*$I$2/(1+EXP($I$3*(COUNT($I$9:Q$9)+$I$4))),TREND($E85:$F85,$E$9:$F$9,Q$9)) -> 0 | ... AI85: =IF($G85="s-curve",$E85+($F85-$E85)*$I$2/(1+EXP($I$3*(COUNT($I$9:AI$9)+$I$4))),TREND($E85:$F85,$E$9:$F$9,AI$9)) -> 0
C86: hydrogen vehicle | D86: =D16 -> 0 | E86: =E16 -> 0 | F86: =F16 -> 0 | G86: =IF(E86=F86,"n/a",IF(OR(C86="battery electric vehicle",C86="natural gas vehicle",C86="plugin hybrid vehicle",C86="hydrogen vehicle"),"s-curve","linear")) -> n/a | I86: =E86 -> 0 | J86: =IF($G86="s-curve",$E86+($F86-$E86)*$I$2/(1+EXP($I$3*(COUNT($I$9:J$9)+$I$4))),TREND($E86:$F86,$E$9:$F$9,J$9)) -> 0 | K86: =IF($G86="s-curve",$E86+($F86-$E86)*$I$2/(1+EXP($I$3*(COUNT($I$9:K$9)+$I$4))),TREND($E86:$F86,$E$9:$F$9,K$9)) -> 0 | L86: =IF($G86="s-curve",$E86+($F86-$E86)*$I$2/(1+EXP($I$3*(COUNT($I$9:L$9)+$I$4))),TREND($E86:$F86,$E$9:$F$9,L$9)) -> 0 | M86: =IF($G86="s-curve",$E86+($F86-$E86)*$I$2/(1+EXP($I$3*(COUNT($I$9:M$9)+$I$4))),TREND($E86:$F86,$E$9:$F$9,M$9)) -> 0 | N86: =IF($G86="s-curve",$E86+($F86-$E86)*$I$2/(1+EXP($I$3*(COUNT($I$9:N$9)+$I$4))),TREND($E86:$F86,$E$9:$F$9,N$9)) -> 0 | O86: =IF($G86="s-curve",$E86+($F86-$E86)*$I$2/(1+EXP($I$3*(COUNT($I$9:O$9)+$I$4))),TREND($E86:$F86,$E$9:$F$9,O$9)) -> 0 | P86: =IF($G86="s-curve",$E86+($F86-$E86)*$I$2/(1+EXP($I$3*(COUNT($I$9:P$9)+$I$4))),TREND($E86:$F86,$E$9:$F$9,P$9)) -> 0 | Q86: =IF($G86="s-curve",$E86+($F86-$E86)*$I$2/(1+EXP($I$3*(COUNT($I$9:Q$9)+$I$4))),TREND($E86:$F86,$E$9:$F$9,Q$9)) -> 0 | ... AI86: =IF($G86="s-curve",$E86+($F86-$E86)*$I$2/(1+EXP($I$3*(COUNT($I$9:AI$9)+$I$4))),TREND($E86:$F86,$E$9:$F$9,AI$9)) -> 0
A87: motorbikes | B87: freight | C87: battery electric vehicle | E87: 0 | F87: 0 | G87: =IF(E87=F87,"n/a",IF(OR(C87="battery electric vehicle",C87="natural gas vehicle",C87="plugin hybrid vehicle"),"s-curve","linear")) -> n/a | I87: =E87 -> 0 | J87: =IF($G87="s-curve",$E87+($F87-$E87)*$I$2/(1+EXP($I$3*(COUNT($I$9:J$9)+$I$4))),TREND($E87:$F87,$E$9:$F$9,J$9)) -> 0 | K87: =IF($G87="s-curve",$E87+($F87-$E87)*$I$2/(1+EXP($I$3*(COUNT($I$9:K$9)+$I$4))),TREND($E87:$F87,$E$9:$F$9,K$9)) -> 0 | L87: =IF($G87="s-curve",$E87+($F87-$E87)*$I$2/(1+EXP($I$3*(COUNT($I$9:L$9)+$I$4))),TREND($E87:$F87,$E$9:$F$9,L$9)) -> 0 | M87: =IF($G87="s-curve",$E87+($F87-$E87)*$I$2/(1+EXP($I$3*(COUNT($I$9:M$9)+$I$4))),TREND($E87:$F87,$E$9:$F$9,M$9)) -> 0 | N87: =IF($G87="s-curve",$E87+($F87-$E87)*$I$2/(1+EXP($I$3*(COUNT($I$9:N$9)+$I$4))),TREND($E87:$F87,$E$9:$F$9,N$9)) -> 0 | O87: =IF($G87="s-curve",$E87+($F87-$E87)*$I$2/(1+EXP($I$3*(COUNT($I$9:O$9)+$I$4))),TREND($E87:$F87,$E$9:$F$9,O$9)) -> 0 | P87: =IF($G87="s-curve",$E87+($F87-$E87)*$I$2/(1+EXP($I$3*(COUNT($I$9:P$9)+$I$4))),TREND($E87:$F87,$E$9:$F$9,P$9)) -> 0 | Q87: =IF($G87="s-curve",$E87+($F87-$E87)*$I$2/(1+EXP($I$3*(COUNT($I$9:Q$9)+$I$4))),TREND($E87:$F87,$E$9:$F$9,Q$9)) -> 0 | ... AI87: =IF($G87="s-curve",$E87+($F87-$E87)*$I$2/(1+EXP($I$3*(COUNT($I$9:AI$9)+$I$4))),TREND($E87:$F87,$E$9:$F$9,AI$9)) -> 0
C88: natural gas vehicle | E88: 0 | F88: 0 | G88: =IF(E88=F88,"n/a",IF(OR(C88="battery electric vehicle",C88="natural gas vehicle",C88="plugin hybrid vehicle"),"s-curve","linear")) -> n/a | I88: =E88 -> 0 | J88: =IF($G88="s-curve",$E88+($F88-$E88)*$I$2/(1+EXP($I$3*(COUNT($I$9:J$9)+$I$4))),TREND($E88:$F88,$E$9:$F$9,J$9)) -> 0 | K88: =IF($G88="s-curve",$E88+($F88-$E88)*$I$2/(1+EXP($I$3*(COUNT($I$9:K$9)+$I$4))),TREND($E88:$F88,$E$9:$F$9,K$9)) -> 0 | L88: =IF($G88="s-curve",$E88+($F88-$E88)*$I$2/(1+EXP($I$3*(COUNT($I$9:L$9)+$I$4))),TREND($E88:$F88,$E$9:$F$9,L$9)) -> 0 | M88: =IF($G88="s-curve",$E88+($F88-$E88)*$I$2/(1+EXP($I$3*(COUNT($I$9:M$9)+$I$4))),TREND($E88:$F88,$E$9:$F$9,M$9)) -> 0 | N88: =IF($G88="s-curve",$E88+($F88-$E88)*$I$2/(1+EXP($I$3*(COUNT($I$9:N$9)+$I$4))),TREND($E88:$F88,$E$9:$F$9,N$9)) -> 0 | O88: =IF($G88="s-curve",$E88+($F88-$E88)*$I$2/(1+EXP($I$3*(COUNT($I$9:O$9)+$I$4))),TREND($E88:$F88,$E$9:$F$9,O$9)) -> 0 | P88: =IF($G88="s-curve",$E88+($F88-$E88)*$I$2/(1+EXP($I$3*(COUNT($I$9:P$9)+$I$4))),TREND($E88:$F88,$E$9:$F$9,P$9)) -> 0 | Q88: =IF($G88="s-curve",$E88+($F88-$E88)*$I$2/(1+EXP($I$3*(COUNT($I$9:Q$9)+$I$4))),TREND($E88:$F88,$E$9:$F$9,Q$9)) -> 0 | ... AI88: =IF($G88="s-curve",$E88+($F88-$E88)*$I$2/(1+EXP($I$3*(COUNT($I$9:AI$9)+$I$4))),TREND($E88:$F88,$E$9:$F$9,AI$9)) -> 0
C89: gasoline vehicle | E89: 0 | F89: 0 | G89: =IF(E89=F89,"n/a",IF(OR(C89="battery electric vehicle",C89="natural gas vehicle",C89="plugin hybrid vehicle"),"s-curve","linear")) -> n/a | I89: =E89 -> 0 | J89: =IF($G89="s-curve",$E89+($F89-$E89)*$I$2/(1+EXP($I$3*(COUNT($I$9:J$9)+$I$4))),TREND($E89:$F89,$E$9:$F$9,J$9)) -> 0 | K89: =IF($G89="s-curve",$E89+($F89-$E89)*$I$2/(1+EXP($I$3*(COUNT($I$9:K$9)+$I$4))),TREND($E89:$F89,$E$9:$F$9,K$9)) -> 0 | L89: =IF($G89="s-curve",$E89+($F89-$E89)*$I$2/(1+EXP($I$3*(COUNT($I$9:L$9)+$I$4))),TREND($E89:$F89,$E$9:$F$9,L$9)) -> 0 | M89: =IF($G89="s-curve",$E89+($F89-$E89)*$I$2/(1+EXP($I$3*(COUNT($I$9:M$9)+$I$4))),TREND($E89:$F89,$E$9:$F$9,M$9)) -> 0 | N89: =IF($G89="s-curve",$E89+($F89-$E89)*$I$2/(1+EXP($I$3*(COUNT($I$9:N$9)+$I$4))),TREND($E89:$F89,$E$9:$F$9,N$9)) -> 0 | O89: =IF($G89="s-curve",$E89+($F89-$E89)*$I$2/(1+EXP($I$3*(COUNT($I$9:O$9)+$I$4))),TREND($E89:$F89,$E$9:$F$9,O$9)) -> 0 | P89: =IF($G89="s-curve",$E89+($F89-$E89)*$I$2/(1+EXP($I$3*(COUNT($I$9:P$9)+$I$4))),TREND($E89:$F89,$E$9:$F$9,P$9)) -> 0 | Q89: =IF($G89="s-curve",$E89+($F89-$E89)*$I$2/(1+EXP($I$3*(COUNT($I$9:Q$9)+$I$4))),TREND($E89:$F89,$E$9:$F$9,Q$9)) -> 0 | ... AI89: =IF($G89="s-curve",$E89+($F89-$E89)*$I$2/(1+EXP($I$3*(COUNT($I$9:AI$9)+$I$4))),TREND($E89:$F89,$E$9:$F$9,AI$9)) -> 0
C90: diesel vehicle | E90: 0 | F90: 0 | G90: =IF(E90=F90,"n/a",IF(OR(C90="battery electric vehicle",C90="natural gas vehicle",C90="plugin hybrid vehicle"),"s-curve","linear")) -> n/a | I90: =E90 -> 0 | J90: =IF($G90="s-curve",$E90+($F90-$E90)*$I$2/(1+EXP($I$3*(COUNT($I$9:J$9)+$I$4))),TREND($E90:$F90,$E$9:$F$9,J$9)) -> 0 | K90: =IF($G90="s-curve",$E90+($F90-$E90)*$I$2/(1+EXP($I$3*(COUNT($I$9:K$9)+$I$4))),TREND($E90:$F90,$E$9:$F$9,K$9)) -> 0 | L90: =IF($G90="s-curve",$E90+($F90-$E90)*$I$2/(1+EXP($I$3*(COUNT($I$9:L$9)+$I$4))),TREND($E90:$F90,$E$9:$F$9,L$9)) -> 0 | M90: =IF($G90="s-curve",$E90+($F90-$E90)*$I$2/(1+EXP($I$3*(COUNT($I$9:M$9)+$I$4))),TREND($E90:$F90,$E$9:$F$9,M$9)) -> 0 | N90: =IF($G90="s-curve",$E90+($F90-$E90)*$I$2/(1+EXP($I$3*(COUNT($I$9:N$9)+$I$4))),TREND($E90:$F90,$E$9:$F$9,N$9)) -> 0 | O90: =IF($G90="s-curve",$E90+($F90-$E90)*$I$2/(1+EXP($I$3*(COUNT($I$9:O$9)+$I$4))),TREND($E90:$F90,$E$9:$F$9,O$9)) -> 0 | P90: =IF($G90="s-curve",$E90+($F90-$E90)*$I$2/(1+EXP($I$3*(COUNT($I$9:P$9)+$I$4))),TREND($E90:$F90,$E$9:$F$9,P$9)) -> 0 | Q90: =IF($G90="s-curve",$E90+($F90-$E90)*$I$2/(1+EXP($I$3*(COUNT($I$9:Q$9)+$I$4))),TREND($E90:$F90,$E$9:$F$9,Q$9)) -> 0 | ... AI90: =IF($G90="s-curve",$E90+($F90-$E90)*$I$2/(1+EXP($I$3*(COUNT($I$9:AI$9)+$I$4))),TREND($E90:$F90,$E$9:$F$9,AI$9)) -> 0
C91: plugin hybrid vehicle | E91: 0 | F91: 0 | G91: =IF(E91=F91,"n/a",IF(OR(C91="battery electric vehicle",C91="natural gas vehicle",C91="plugin hybrid vehicle"),"s-curve","linear")) -> n/a | I91: =E91 -> 0 | J91: =IF($G91="s-curve",$E91+($F91-$E91)*$I$2/(1+EXP($I$3*(COUNT($I$9:J$9)+$I$4))),TREND($E91:$F91,$E$9:$F$9,J$9)) -> 0 | K91: =IF($G91="s-curve",$E91+($F91-$E91)*$I$2/(1+EXP($I$3*(COUNT($I$9:K$9)+$I$4))),TREND($E91:$F91,$E$9:$F$9,K$9)) -> 0 | L91: =IF($G91="s-curve",$E91+($F91-$E91)*$I$2/(1+EXP($I$3*(COUNT($I$9:L$9)+$I$4))),TREND($E91:$F91,$E$9:$F$9,L$9)) -> 0 | M91: =IF($G91="s-curve",$E91+($F91-$E91)*$I$2/(1+EXP($I$3*(COUNT($I$9:M$9)+$I$4))),TREND($E91:$F91,$E$9:$F$9,M$9)) -> 0 | N91: =IF($G91="s-curve",$E91+($F91-$E91)*$I$2/(1+EXP($I$3*(COUNT($I$9:N$9)+$I$4))),TREND($E91:$F91,$E$9:$F$9,N$9)) -> 0 | O91: =IF($G91="s-curve",$E91+($F91-$E91)*$I$2/(1+EXP($I$3*(COUNT($I$9:O$9)+$I$4))),TREND($E91:$F91,$E$9:$F$9,O$9)) -> 0 | P91: =IF($G91="s-curve",$E91+($F91-$E91)*$I$2/(1+EXP($I$3*(COUNT($I$9:P$9)+$I$4))),TREND($E91:$F91,$E$9:$F$9,P$9)) -> 0 | Q91: =IF($G91="s-curve",$E91+($F91-$E91)*$I$2/(1+EXP($I$3*(COUNT($I$9:Q$9)+$I$4))),TREND($E91:$F91,$E$9:$F$9,Q$9)) -> 0 | ... AI91: =IF($G91="s-curve",$E91+($F91-$E91)*$I$2/(1+EXP($I$3*(COUNT($I$9:AI$9)+$I$4))),TREND($E91:$F91,$E$9:$F$9,AI$9)) -> 0
C92: LPG vehicle | E92: 0 | F92: 0 | G92: =IF(E92=F92,"n/a",IF(OR(C92="battery electric vehicle",C92="natural gas vehicle",C92="plugin hybrid vehicle",C92="hydrogen vehicle"),"s-curve","linear")) -> n/a | I92: =E92 -> 0 | J92: =IF($G92="s-curve",$E92+($F92-$E92)*$I$2/(1+EXP($I$3*(COUNT($I$9:J$9)+$I$4))),TREND($E92:$F92,$E$9:$F$9,J$9)) -> 0 | K92: =IF($G92="s-curve",$E92+($F92-$E92)*$I$2/(1+EXP($I$3*(COUNT($I$9:K$9)+$I$4))),TREND($E92:$F92,$E$9:$F$9,K$9)) -> 0 | L92: =IF($G92="s-curve",$E92+($F92-$E92)*$I$2/(1+EXP($I$3*(COUNT($I$9:L$9)+$I$4))),TREND($E92:$F92,$E$9:$F$9,L$9)) -> 0 | M92: =IF($G92="s-curve",$E92+($F92-$E92)*$I$2/(1+EXP($I$3*(COUNT($I$9:M$9)+$I$4))),TREND($E92:$F92,$E$9:$F$9,M$9)) -> 0 | N92: =IF($G92="s-curve",$E92+($F92-$E92)*$I$2/(1+EXP($I$3*(COUNT($I$9:N$9)+$I$4))),TREND($E92:$F92,$E$9:$F$9,N$9)) -> 0 | O92: =IF($G92="s-curve",$E92+($F92-$E92)*$I$2/(1+EXP($I$3*(COUNT($I$9:O$9)+$I$4))),TREND($E92:$F92,$E$9:$F$9,O$9)) -> 0 | P92: =IF($G92="s-curve",$E92+($F92-$E92)*$I$2/(1+EXP($I$3*(COUNT($I$9:P$9)+$I$4))),TREND($E92:$F92,$E$9:$F$9,P$9)) -> 0 | Q92: =IF($G92="s-curve",$E92+($F92-$E92)*$I$2/(1+EXP($I$3*(COUNT($I$9:Q$9)+$I$4))),TREND($E92:$F92,$E$9:$F$9,Q$9)) -> 0 | ... AI92: =IF($G92="s-curve",$E92+($F92-$E92)*$I$2/(1+EXP($I$3*(COUNT($I$9:AI$9)+$I$4))),TREND($E92:$F92,$E$9:$F$9,AI$9)) -> 0
C93: hydrogen vehicle | E93: 0 | F93: 0 | G93: =IF(E93=F93,"n/a",IF(OR(C93="battery electric vehicle",C93="natural gas vehicle",C93="plugin hybrid vehicle",C93="hydrogen vehicle"),"s-curve","linear")) -> n/a | I93: =E93 -> 0 | J93: =IF($G93="s-curve",$E93+($F93-$E93)*$I$2/(1+EXP($I$3*(COUNT($I$9:J$9)+$I$4))),TREND($E93:$F93,$E$9:$F$9,J$9)) -> 0 | K93: =IF($G93="s-curve",$E93+($F93-$E93)*$I$2/(1+EXP($I$3*(COUNT($I$9:K$9)+$I$4))),TREND($E93:$F93,$E$9:$F$9,K$9)) -> 0 | L93: =IF($G93="s-curve",$E93+($F93-$E93)*$I$2/(1+EXP($I$3*(COUNT($I$9:L$9)+$I$4))),TREND($E93:$F93,$E$9:$F$9,L$9)) -> 0 | M93: =IF($G93="s-curve",$E93+($F93-$E93)*$I$2/(1+EXP($I$3*(COUNT($I$9:M$9)+$I$4))),TREND($E93:$F93,$E$9:$F$9,M$9)) -> 0 | N93: =IF($G93="s-curve",$E93+($F93-$E93)*$I$2/(1+EXP($I$3*(COUNT($I$9:N$9)+$I$4))),TREND($E93:$F93,$E$9:$F$9,N$9)) -> 0 | O93: =IF($G93="s-curve",$E93+($F93-$E93)*$I$2/(1+EXP($I$3*(COUNT($I$9:O$9)+$I$4))),TREND($E93:$F93,$E$9:$F$9,O$9)) -> 0 | P93: =IF($G93="s-curve",$E93+($F93-$E93)*$I$2/(1+EXP($I$3*(COUNT($I$9:P$9)+$I$4))),TREND($E93:$F93,$E$9:$F$9,P$9)) -> 0 | Q93: =IF($G93="s-curve",$E93+($F93-$E93)*$I$2/(1+EXP($I$3*(COUNT($I$9:Q$9)+$I$4))),TREND($E93:$F93,$E$9:$F$9,Q$9)) -> 0 | ... AI93: =IF($G93="s-curve",$E93+($F93-$E93)*$I$2/(1+EXP($I$3*(COUNT($I$9:AI$9)+$I$4))),TREND($E93:$F93,$E$9:$F$9,AI$9)) -> 0

Sheet TTS-LDVs-psgr
A1: Max Fraction of Production (dimensionless) | B1: =Data!I9 -> 2024 | C1: =Data!J9 -> 2025 | D1: =Data!K9 -> 2026 | E1: =Data!L9 -> 2027 | F1: =Data!M9 -> 2028 | G1: =Data!N9 -> 2029 | H1: =Data!O9 -> 2030 | I1: =Data!P9 -> 2031 | ... AB1: =Data!AI9 -> 2050
A2: battery electric vehicle | B2: =Data!I10 -> 0.14828895 | C2: =Data!J10 -> 0.14828895 | D2: =Data!K10 -> 0.18868209 | E2: =Data!L10 -> 0.20192405 | F2: =Data!M10 -> 0.21912805 | G2: =Data!N10 -> 0.24120792 | H2: =Data!O10 -> 0.26910507 | I2: =Data!P10 -> 0.30366278 | ... AB2: =Data!AI10 -> 0.98741679
A3: natural gas vehicle | B3: =Data!I11 -> 0.00010097 | C3: =Data!J11 -> 0.00010097 | D3: =Data!K11 -> 0.00010097 | E3: =Data!L11 -> 0.00010097 | F3: =Data!M11 -> 0.00010097 | G3: =Data!N11 -> 0.00010097 | H3: =Data!O11 -> 0.00010097 | I3: =Data!P11 -> 0.00010097 | ... AB3: =Data!AI11 -> 0.00010097
A4: gasoline vehicle | B4: =Data!I12 -> 1 | C4: =Data!J12 -> 1 | D4: =Data!K12 -> 1 | E4: =Data!L12 -> 1 | F4: =Data!M12 -> 1 | G4: =Data!N12 -> 1 | H4: =Data!O12 -> 1 | I4: =Data!P12 -> 1 | ... AB4: =Data!AI12 -> 1
A5: diesel vehicle | B5: =Data!I13 -> 0.06738296 | C5: =Data!J13 -> 0.06738296 | D5: =Data!K13 -> 0.06738296 | E5: =Data!L13 -> 0.06738296 | F5: =Data!M13 -> 0.06738296 | G5: =Data!N13 -> 0.06738296 | H5: =Data!O13 -> 0.06738296 | I5: =Data!P13 -> 0.06738296 | ... AB5: =Data!AI13 -> 0.06738296
A6: plugin hybrid vehicle | B6: =Data!I14 -> 0.014073499 | C6: =Data!J14 -> 0.014073499 | D6: =Data!K14 -> 0.017532505 | E6: =Data!L14 -> 0.019136208 | F6: =Data!M14 -> 0.021419076 | G6: =Data!N14 -> 0.024601163 | H6: =Data!O14 -> 0.028909159 | I6: =Data!P14 -> 0.034516734 | ... AB6: =Data!AI14 -> 0.10224417
A7: LPG vehicle | B7: =Data!I15 -> 0 | C7: =Data!J15 -> 0 | D7: =Data!K15 -> 0 | E7: =Data!L15 -> 0 | F7: =Data!M15 -> 0 | G7: =Data!N15 -> 0 | H7: =Data!O15 -> 0 | I7: =Data!P15 -> 0 | ... AB7: =Data!AI15 -> 0
A8: hydrogen vehicle | B8: =Data!I16 -> 0 | C8: =Data!J16 -> 0 | D8: =Data!K16 -> 0 | E8: =Data!L16 -> 0 | F8: =Data!M16 -> 0 | G8: =Data!N16 -> 0 | H8: =Data!O16 -> 0 | I8: =Data!P16 -> 0 | ... AB8: =Data!AI16 -> 0

Sheet TTS-LDVs-frgt
A1: Max Fraction of Production (dimensionless) | B1: =Data!I9 -> 2024 | C1: =Data!J9 -> 2025 | D1: =Data!K9 -> 2026 | E1: =Data!L9 -> 2027 | F1: =Data!M9 -> 2028 | G1: =Data!N9 -> 2029 | H1: =Data!O9 -> 2030 | I1: =Data!P9 -> 2031 | ... AB1: =Data!AI9 -> 2050
A2: battery electric vehicle | B2: =Data!I17 -> 0.32863913 | C2: =Data!J17 -> 0.32863913 | D2: =Data!K17 -> 0.3276204 | E2: =Data!L17 -> 0.32728089 | F2: =Data!M17 -> 0.32683563 | G2: =Data!N17 -> 0.32625713 | H2: =Data!O17 -> 0.32551469 | I2: =Data!P17 -> 0.32457664 | ... AB2: =Data!AI17 -> 0.30056821
A3: natural gas vehicle | B3: =Data!I18 -> 0.25047807 | C3: =Data!J18 -> 0.25047807 | D3: =Data!K18 -> 0.25047807 | E3: =Data!L18 -> 0.25047807 | F3: =Data!M18 -> 0.25047807 | G3: =Data!N18 -> 0.25047807 | H3: =Data!O18 -> 0.25047807 | I3: =Data!P18 -> 0.25047807 | ... AB3: =Data!AI18 -> 0.25047807
A4: gasoline vehicle | B4: =Data!I19 -> 0.76148266 | C4: =Data!J19 -> 0.76148266 | D4: =Data!K19 -> 0.76148266 | E4: =Data!L19 -> 0.76148266 | F4: =Data!M19 -> 0.76148266 | G4: =Data!N19 -> 0.76148266 | H4: =Data!O19 -> 0.76148266 | I4: =Data!P19 -> 0.76148266 | ... AB4: =Data!AI19 -> 0.76148266
A5: diesel vehicle | B5: =Data!I20 -> 1 | C5: =Data!J20 -> 1 | D5: =Data!K20 -> 1 | E5: =Data!L20 -> 1 | F5: =Data!M20 -> 1 | G5: =Data!N20 -> 1 | H5: =Data!O20 -> 1 | I5: =Data!P20 -> 1 | ... AB5: =Data!AI20 -> 1
A6: plugin hybrid vehicle | B6: =Data!I21 -> 0.001003192 | C6: =Data!J21 -> 0.001003192 | D6: =Data!K21 -> 0.0010114629 | E6: =Data!L21 -> 0.0010142193 | F6: =Data!M21 -> 0.0010178343 | G6: =Data!N21 -> 0.001022531 | H6: =Data!O21 -> 0.0010285588 | I6: =Data!P21 -> 0.0010361747 | ... AB6: =Data!AI21 -> 0.0012310951
A7: LPG vehicle | B7: =Data!I22 -> 0.000602232 | C7: =Data!J22 -> 0.000602232 | D7: =Data!K22 -> 0.000602232 | E7: =Data!L22 -> 0.000602232 | F7: =Data!M22 -> 0.000602232 | G7: =Data!N22 -> 0.000602232 | H7: =Data!O22 -> 0.000602232 | I7: =Data!P22 -> 0.000602232 | ... AB7: =Data!AI22 -> 0.000602232
A8: hydrogen vehicle | B8: =Data!I23 -> 0 | C8: =Data!J23 -> 0 | D8: =Data!K23 -> 0 | E8: =Data!L23 -> 0 | F8: =Data!M23 -> 0 | G8: =Data!N23 -> 0 | H8: =Data!O23 -> 0 | I8: =Data!P23 -> 0 | ... AB8: =Data!AI23 -> 0

Sheet TTS-HDVs-psgr
A1: Max Fraction of Production (dimensionless) | B1: =Data!I9 -> 2024 | C1: =Data!J9 -> 2025 | D1: =Data!K9 -> 2026 | E1: =Data!L9 -> 2027 | F1: =Data!M9 -> 2028 | G1: =Data!N9 -> 2029 | H1: =Data!O9 -> 2030 | I1: =Data!P9 -> 2031 | ... AB1: =Data!AI9 -> 2050
A2: battery electric vehicle | B2: =Data!I24 -> 0.1218401 | C2: =Data!J24 -> 0.1218401 | D2: =Data!K24 -> 0.14418449 | E2: =Data!L24 -> 0.15163113 | F2: =Data!M24 -> 0.16139744 | G2: =Data!N24 -> 0.17408585 | H2: =Data!O24 -> 0.19037035 | I2: =Data!P24 -> 0.21094525 | ... AB2: =Data!AI24 -> 0.73753712
A3: natural gas vehicle | B3: =Data!I25 -> 0.015737248 | C3: =Data!J25 -> 0.015737248 | D3: =Data!K25 -> 0.015737248 | E3: =Data!L25 -> 0.015737248 | F3: =Data!M25 -> 0.015737248 | G3: =Data!N25 -> 0.015737248 | H3: =Data!O25 -> 0.015737248 | I3: =Data!P25 -> 0.015737248 | ... AB3: =Data!AI25 -> 0.015737248
A4: gasoline vehicle | B4: =Data!I26 -> 0.37956814 | C4: =Data!J26 -> 0.37956814 | D4: =Data!K26 -> 0.37956814 | E4: =Data!L26 -> 0.37956814 | F4: =Data!M26 -> 0.37956814 | G4: =Data!N26 -> 0.37956814 | H4: =Data!O26 -> 0.37956814 | I4: =Data!P26 -> 0.37956814 | ... AB4: =Data!AI26 -> 0.37956814
A5: diesel vehicle | B5: =Data!I27 -> 1 | C5: =Data!J27 -> 1 | D5: =Data!K27 -> 1 | E5: =Data!L27 -> 1 | F5: =Data!M27 -> 1 | G5: =Data!N27 -> 1 | H5: =Data!O27 -> 1 | I5: =Data!P27 -> 1 | ... AB5: =Data!AI27 -> 1
A6: plugin hybrid vehicle | B6: =Data!I28 -> 0 | C6: =Data!J28 -> 0 | D6: =Data!K28 -> 0 | E6: =Data!L28 -> 0 | F6: =Data!M28 -> 0 | G6: =Data!N28 -> 0 | H6: =Data!O28 -> 0 | I6: =Data!P28 -> 0 | ... AB6: =Data!AI28 -> 0
A7: LPG vehicle | B7: =Data!I29 -> 0.055449391 | C7: =Data!J29 -> 0.055449391 | D7: =Data!K29 -> 0.055449391 | E7: =Data!L29 -> 0.055449391 | F7: =Data!M29 -> 0.055449391 | G7: =Data!N29 -> 0.055449391 | H7: =Data!O29 -> 0.055449391 | I7: =Data!P29 -> 0.055449391 | ... AB7: =Data!AI29 -> 0.055449391
A8: hydrogen vehicle | B8: =Data!I30 -> 0.002028695 | C8: =Data!J30 -> 0.002028695 | D8: =Data!K30 -> 0.002028695 | E8: =Data!L30 -> 0.002028695 | F8: =Data!M30 -> 0.002028695 | G8: =Data!N30 -> 0.002028695 | H8: =Data!O30 -> 0.002028695 | I8: =Data!P30 -> 0.002028695 | ... AB8: =Data!AI30 -> 0.002028695

Sheet TTS-HDVs-frgt
A1: Max Fraction of Production (dimensionless) | B1: =Data!I9 -> 2024 | C1: =Data!J9 -> 2025 | D1: =Data!K9 -> 2026 | E1: =Data!L9 -> 2027 | F1: =Data!M9 -> 2028 | G1: =Data!N9 -> 2029 | H1: =Data!O9 -> 2030 | I1: =Data!P9 -> 2031 | ... AB1: =Data!AI9 -> 2050
A2: battery electric vehicle | B2: =Data!I31 -> 0.004808968 | C2: =Data!J31 -> 0.004808968 | D2: =Data!K31 -> 0.013530705 | E2: =Data!L31 -> 0.016437367 | F2: =Data!M31 -> 0.02024947 | G2: =Data!N31 -> 0.025202167 | H2: =Data!O31 -> 0.03155853 | I2: =Data!P31 -> 0.039589577 | ... AB2: =Data!AI31 -> 0.24513533
A3: natural gas vehicle | B3: =Data!I32 -> 0.022159679 | C3: =Data!J32 -> 0.022159679 | D3: =Data!K32 -> 0.022159679 | E3: =Data!L32 -> 0.022159679 | F3: =Data!M32 -> 0.022159679 | G3: =Data!N32 -> 0.022159679 | H3: =Data!O32 -> 0.022159679 | I3: =Data!P32 -> 0.022159679 | ... AB3: =Data!AI32 -> 0.022159679
A4: gasoline vehicle | B4: =Data!I33 -> 0.000753581 | C4: =Data!J33 -> 0.000753581 | D4: =Data!K33 -> 0.000753581 | E4: =Data!L33 -> 0.000753581 | F4: =Data!M33 -> 0.000753581 | G4: =Data!N33 -> 0.000753581 | H4: =Data!O33 -> 0.000753581 | I4: =Data!P33 -> 0.000753581 | ... AB4: =Data!AI33 -> 0.000753581
A5: diesel vehicle | B5: =Data!I34 -> 1 | C5: =Data!J34 -> 1 | D5: =Data!K34 -> 1 | E5: =Data!L34 -> 1 | F5: =Data!M34 -> 1 | G5: =Data!N34 -> 1 | H5: =Data!O34 -> 1 | I5: =Data!P34 -> 1 | ... AB5: =Data!AI34 -> 1
A6: plugin hybrid vehicle | B6: =Data!I35 -> 0 | C6: =Data!J35 -> 0 | D6: =Data!K35 -> 0 | E6: =Data!L35 -> 0 | F6: =Data!M35 -> 0 | G6: =Data!N35 -> 0 | H6: =Data!O35 -> 0 | I6: =Data!P35 -> 0 | ... AB6: =Data!AI35 -> 0
A7: LPG vehicle | B7: =Data!I36 -> 0 | C7: =Data!J36 -> 0 | D7: =Data!K36 -> 0 | E7: =Data!L36 -> 0 | F7: =Data!M36 -> 0 | G7: =Data!N36 -> 0 | H7: =Data!O36 -> 0 | I7: =Data!P36 -> 0 | ... AB7: =Data!AI36 -> 0
A8: hydrogen vehicle | B8: =Data!I37 -> 0 | C8: =Data!J37 -> 0 | D8: =Data!K37 -> 0 | E8: =Data!L37 -> 0 | F8: =Data!M37 -> 0 | G8: =Data!N37 -> 0 | H8: =Data!O37 -> 0 | I8: =Data!P37 -> 0 | ... AB8: =Data!AI37 -> 0

Sheet TTS-aircraft-psgr
A1: Max Fraction of Production (dimensionless) | B1: =Data!I9 -> 2024 | C1: =Data!J9 -> 2025 | D1: =Data!K9 -> 2026 | E1: =Data!L9 -> 2027 | F1: =Data!M9 -> 2028 | G1: =Data!N9 -> 2029 | H1: =Data!O9 -> 2030 | I1: =Data!P9 -> 2031 | ... AB1: =Data!AI9 -> 2050
A2: battery electric vehicle | B2: =Data!I38 -> 0 | C2: =Data!J38 -> 0 | D2: =Data!K38 -> 0 | E2: =Data!L38 -> 0 | F2: =Data!M38 -> 0 | G2: =Data!N38 -> 0 | H2: =Data!O38 -> 0 | I2: =Data!P38 -> 0 | ... AB2: =Data!AI38 -> 0
A3: natural gas vehicle | B3: =Data!I39 -> 0 | C3: =Data!J39 -> 0 | D3: =Data!K39 -> 0 | E3: =Data!L39 -> 0 | F3: =Data!M39 -> 0 | G3: =Data!N39 -> 0 | H3: =Data!O39 -> 0 | I3: =Data!P39 -> 0 | ... AB3: =Data!AI39 -> 0
A4: gasoline vehicle | B4: =Data!I40 -> 0 | C4: =Data!J40 -> 0 | D4: =Data!K40 -> 0 | E4: =Data!L40 -> 0 | F4: =Data!M40 -> 0 | G4: =Data!N40 -> 0 | H4: =Data!O40 -> 0 | I4: =Data!P40 -> 0 | ... AB4: =Data!AI40 -> 0
A5: diesel vehicle | B5: =Data!I41 -> 1 | C5: =Data!J41 -> 1 | D5: =Data!K41 -> 1 | E5: =Data!L41 -> 1 | F5: =Data!M41 -> 1 | G5: =Data!N41 -> 1 | H5: =Data!O41 -> 1 | I5: =Data!P41 -> 1 | ... AB5: =Data!AI41 -> 1
A6: plugin hybrid vehicle | B6: =Data!I42 -> 0 | C6: =Data!J42 -> 0 | D6: =Data!K42 -> 0 | E6: =Data!L42 -> 0 | F6: =Data!M42 -> 0 | G6: =Data!N42 -> 0 | H6: =Data!O42 -> 0 | I6: =Data!P42 -> 0 | ... AB6: =Data!AI42 -> 0
A7: LPG vehicle | B7: =Data!I43 -> 0 | C7: =Data!J43 -> 0 | D7: =Data!K43 -> 0 | E7: =Data!L43 -> 0 | F7: =Data!M43 -> 0 | G7: =Data!N43 -> 0 | H7: =Data!O43 -> 0 | I7: =Data!P43 -> 0 | ... AB7: =Data!AI43 -> 0
A8: hydrogen vehicle | B8: =Data!I44 -> 0 | C8: =Data!J44 -> 0 | D8: =Data!K44 -> 0 | E8: =Data!L44 -> 0 | F8: =Data!M44 -> 0 | G8: =Data!N44 -> 0 | H8: =Data!O44 -> 0 | I8: =Data!P44 -> 0 | ... AB8: =Data!AI44 -> 0

Sheet TTS-aircraft-frgt
A1: Max Fraction of Production (dimensionless) | B1: =Data!I9 -> 2024 | C1: =Data!J9 -> 2025 | D1: =Data!K9 -> 2026 | E1: =Data!L9 -> 2027 | F1: =Data!M9 -> 2028 | G1: =Data!N9 -> 2029 | H1: =Data!O9 -> 2030 | I1: =Data!P9 -> 2031 | ... AB1: =Data!AI9 -> 2050
A2: battery electric vehicle | B2: =Data!I45 -> 0 | C2: =Data!J45 -> 0 | D2: =Data!K45 -> 0 | E2: =Data!L45 -> 0 | F2: =Data!M45 -> 0 | G2: =Data!N45 -> 0 | H2: =Data!O45 -> 0 | I2: =Data!P45 -> 0 | ... AB2: =Data!AI45 -> 0
A3: natural gas vehicle | B3: =Data!I46 -> 0 | C3: =Data!J46 -> 0 | D3: =Data!K46 -> 0 | E3: =Data!L46 -> 0 | F3: =Data!M46 -> 0 | G3: =Data!N46 -> 0 | H3: =Data!O46 -> 0 | I3: =Data!P46 -> 0 | ... AB3: =Data!AI46 -> 0
A4: gasoline vehicle | B4: =Data!I47 -> 0 | C4: =Data!J47 -> 0 | D4: =Data!K47 -> 0 | E4: =Data!L47 -> 0 | F4: =Data!M47 -> 0 | G4: =Data!N47 -> 0 | H4: =Data!O47 -> 0 | I4: =Data!P47 -> 0 | ... AB4: =Data!AI47 -> 0
A5: diesel vehicle | B5: =Data!I48 -> 1 | C5: =Data!J48 -> 1 | D5: =Data!K48 -> 1 | E5: =Data!L48 -> 1 | F5: =Data!M48 -> 1 | G5: =Data!N48 -> 1 | H5: =Data!O48 -> 1 | I5: =Data!P48 -> 1 | ... AB5: =Data!AI48 -> 1
A6: plugin hybrid vehicle | B6: =Data!I49 -> 0 | C6: =Data!J49 -> 0 | D6: =Data!K49 -> 0 | E6: =Data!L49 -> 0 | F6: =Data!M49 -> 0 | G6: =Data!N49 -> 0 | H6: =Data!O49 -> 0 | I6: =Data!P49 -> 0 | ... AB6: =Data!AI49 -> 0
A7: LPG vehicle | B7: =Data!I50 -> 0 | C7: =Data!J50 -> 0 | D7: =Data!K50 -> 0 | E7: =Data!L50 -> 0 | F7: =Data!M50 -> 0 | G7: =Data!N50 -> 0 | H7: =Data!O50 -> 0 | I7: =Data!P50 -> 0 | ... AB7: =Data!AI50 -> 0
A8: hydrogen vehicle | B8: =Data!I51 -> 0 | C8: =Data!J51 -> 0 | D8: =Data!K51 -> 0 | E8: =Data!L51 -> 0 | F8: =Data!M51 -> 0 | G8: =Data!N51 -> 0 | H8: =Data!O51 -> 0 | I8: =Data!P51 -> 0 | ... AB8: =Data!AI51 -> 0

Sheet TTS-rail-psgr
A1: Max Fraction of Production (dimensionless) | B1: =Data!I9 -> 2024 | C1: =Data!J9 -> 2025 | D1: =Data!K9 -> 2026 | E1: =Data!L9 -> 2027 | F1: =Data!M9 -> 2028 | G1: =Data!N9 -> 2029 | H1: =Data!O9 -> 2030 | I1: =Data!P9 -> 2031 | ... AB1: =Data!AI9 -> 2050
A2: battery electric vehicle | B2: =Data!I52 -> 1 | C2: =Data!J52 -> 1 | D2: =Data!K52 -> 1 | E2: =Data!L52 -> 1 | F2: =Data!M52 -> 1 | G2: =Data!N52 -> 1 | H2: =Data!O52 -> 1 | I2: =Data!P52 -> 1 | ... AB2: =Data!AI52 -> 1
A3: natural gas vehicle | B3: =Data!I53 -> 0 | C3: =Data!J53 -> 0 | D3: =Data!K53 -> 0 | E3: =Data!L53 -> 0 | F3: =Data!M53 -> 0 | G3: =Data!N53 -> 0 | H3: =Data!O53 -> 0 | I3: =Data!P53 -> 0 | ... AB3: =Data!AI53 -> 0
A4: gasoline vehicle | B4: =Data!I54 -> 0 | C4: =Data!J54 -> 0 | D4: =Data!K54 -> 0 | E4: =Data!L54 -> 0 | F4: =Data!M54 -> 0 | G4: =Data!N54 -> 0 | H4: =Data!O54 -> 0 | I4: =Data!P54 -> 0 | ... AB4: =Data!AI54 -> 0
A5: diesel vehicle | B5: =Data!I55 -> 0.10755845 | C5: =Data!J55 -> 0.10755845 | D5: =Data!K55 -> 0.10755845 | E5: =Data!L55 -> 0.10755845 | F5: =Data!M55 -> 0.10755845 | G5: =Data!N55 -> 0.10755845 | H5: =Data!O55 -> 0.10755845 | I5: =Data!P55 -> 0.10755845 | ... AB5: =Data!AI55 -> 0.10755845
A6: plugin hybrid vehicle | B6: =Data!I56 -> 0 | C6: =Data!J56 -> 0 | D6: =Data!K56 -> 0 | E6: =Data!L56 -> 0 | F6: =Data!M56 -> 0 | G6: =Data!N56 -> 0 | H6: =Data!O56 -> 0 | I6: =Data!P56 -> 0 | ... AB6: =Data!AI56 -> 0
A7: LPG vehicle | B7: =Data!I57 -> 0 | C7: =Data!J57 -> 0 | D7: =Data!K57 -> 0 | E7: =Data!L57 -> 0 | F7: =Data!M57 -> 0 | G7: =Data!N57 -> 0 | H7: =Data!O57 -> 0 | I7: =Data!P57 -> 0 | ... AB7: =Data!AI57 -> 0
A8: hydrogen vehicle | B8: =Data!I58 -> 0 | C8: =Data!J58 -> 0 | D8: =Data!K58 -> 0 | E8: =Data!L58 -> 0 | F8: =Data!M58 -> 0 | G8: =Data!N58 -> 0 | H8: =Data!O58 -> 0 | I8: =Data!P58 -> 0 | ... AB8: =Data!AI58 -> 0

Sheet TTS-rail-frgt
A1: Max Fraction of Production (dimensionless) | B1: =Data!I9 -> 2024 | C1: =Data!J9 -> 2025 | D1: =Data!K9 -> 2026 | E1: =Data!L9 -> 2027 | F1: =Data!M9 -> 2028 | G1: =Data!N9 -> 2029 | H1: =Data!O9 -> 2030 | I1: =Data!P9 -> 2031 | ... AB1: =Data!AI9 -> 2050
A2: battery electric vehicle | B2: =Data!I59 -> 0 | C2: =Data!J59 -> 0 | D2: =Data!K59 -> 0 | E2: =Data!L59 -> 0 | F2: =Data!M59 -> 0 | G2: =Data!N59 -> 0 | H2: =Data!O59 -> 0 | I2: =Data!P59 -> 0 | ... AB2: =Data!AI59 -> 0
A3: natural gas vehicle | B3: =Data!I60 -> 0 | C3: =Data!J60 -> 0 | D3: =Data!K60 -> 0 | E3: =Data!L60 -> 0 | F3: =Data!M60 -> 0 | G3: =Data!N60 -> 0 | H3: =Data!O60 -> 0 | I3: =Data!P60 -> 0 | ... AB3: =Data!AI60 -> 0
A4: gasoline vehicle | B4: =Data!I61 -> 0 | C4: =Data!J61 -> 0 | D4: =Data!K61 -> 0 | E4: =Data!L61 -> 0 | F4: =Data!M61 -> 0 | G4: =Data!N61 -> 0 | H4: =Data!O61 -> 0 | I4: =Data!P61 -> 0 | ... AB4: =Data!AI61 -> 0
A5: diesel vehicle | B5: =Data!I62 -> 1 | C5: =Data!J62 -> 1 | D5: =Data!K62 -> 1 | E5: =Data!L62 -> 1 | F5: =Data!M62 -> 1 | G5: =Data!N62 -> 1 | H5: =Data!O62 -> 1 | I5: =Data!P62 -> 1 | ... AB5: =Data!AI62 -> 1
A6: plugin hybrid vehicle | B6: =Data!I63 -> 0 | C6: =Data!J63 -> 0 | D6: =Data!K63 -> 0 | E6: =Data!L63 -> 0 | F6: =Data!M63 -> 0 | G6: =Data!N63 -> 0 | H6: =Data!O63 -> 0 | I6: =Data!P63 -> 0 | ... AB6: =Data!AI63 -> 0
A7: LPG vehicle | B7: =Data!I64 -> 0 | C7: =Data!J64 -> 0 | D7: =Data!K64 -> 0 | E7: =Data!L64 -> 0 | F7: =Data!M64 -> 0 | G7: =Data!N64 -> 0 | H7: =Data!O64 -> 0 | I7: =Data!P64 -> 0 | ... AB7: =Data!AI64 -> 0
A8: hydrogen vehicle | B8: =Data!I65 -> 0 | C8: =Data!J65 -> 0 | D8: =Data!K65 -> 0 | E8: =Data!L65 -> 0 | F8: =Data!M65 -> 0 | G8: =Data!N65 -> 0 | H8: =Data!O65 -> 0 | I8: =Data!P65 -> 0 | ... AB8: =Data!AI65 -> 0

Sheet TTS-ships-psgr
A1: Max Fraction of Production (dimensionless) | B1: =Data!I9 -> 2024 | C1: =Data!J9 -> 2025 | D1: =Data!K9 -> 2026 | E1: =Data!L9 -> 2027 | F1: =Data!M9 -> 2028 | G1: =Data!N9 -> 2029 | H1: =Data!O9 -> 2030 | I1: =Data!P9 -> 2031 | ... AB1: =Data!AI9 -> 2050
A2: battery electric vehicle | B2: =Data!I66 -> 0 | C2: =Data!J66 -> 0 | D2: =Data!K66 -> 0 | E2: =Data!L66 -> 0 | F2: =Data!M66 -> 0 | G2: =Data!N66 -> 0 | H2: =Data!O66 -> 0 | I2: =Data!P66 -> 0 | ... AB2: =Data!AI66 -> 0
A3: natural gas vehicle | B3: =Data!I67 -> 0 | C3: =Data!J67 -> 0 | D3: =Data!K67 -> 0 | E3: =Data!L67 -> 0 | F3: =Data!M67 -> 0 | G3: =Data!N67 -> 0 | H3: =Data!O67 -> 0 | I3: =Data!P67 -> 0 | ... AB3: =Data!AI67 -> 0
A4: gasoline vehicle | B4: =Data!I68 -> 0 | C4: =Data!J68 -> 0 | D4: =Data!K68 -> 0 | E4: =Data!L68 -> 0 | F4: =Data!M68 -> 0 | G4: =Data!N68 -> 0 | H4: =Data!O68 -> 0 | I4: =Data!P68 -> 0 | ... AB4: =Data!AI68 -> 0
A5: diesel vehicle | B5: =Data!I69 -> 1 | C5: =Data!J69 -> 1 | D5: =Data!K69 -> 1 | E5: =Data!L69 -> 1 | F5: =Data!M69 -> 1 | G5: =Data!N69 -> 1 | H5: =Data!O69 -> 1 | I5: =Data!P69 -> 1 | ... AB5: =Data!AI69 -> 1
A6: plugin hybrid vehicle | B6: =Data!I70 -> 0 | C6: =Data!J70 -> 0 | D6: =Data!K70 -> 0 | E6: =Data!L70 -> 0 | F6: =Data!M70 -> 0 | G6: =Data!N70 -> 0 | H6: =Data!O70 -> 0 | I6: =Data!P70 -> 0 | ... AB6: =Data!AI70 -> 0
A7: LPG vehicle | B7: =Data!I71 -> 0 | C7: =Data!J71 -> 0 | D7: =Data!K71 -> 0 | E7: =Data!L71 -> 0 | F7: =Data!M71 -> 0 | G7: =Data!N71 -> 0 | H7: =Data!O71 -> 0 | I7: =Data!P71 -> 0 | ... AB7: =Data!AI71 -> 0
A8: hydrogen vehicle | B8: =Data!I72 -> 0 | C8: =Data!J72 -> 0 | D8: =Data!K72 -> 0 | E8: =Data!L72 -> 0 | F8: =Data!M72 -> 0 | G8: =Data!N72 -> 0 | H8: =Data!O72 -> 0 | I8: =Data!P72 -> 0 | ... AB8: =Data!AI72 -> 0

Sheet TTS-ships-frgt
A1: Max Fraction of Production (dimensionless) | B1: =Data!I9 -> 2024 | C1: =Data!J9 -> 2025 | D1: =Data!K9 -> 2026 | E1: =Data!L9 -> 2027 | F1: =Data!M9 -> 2028 | G1: =Data!N9 -> 2029 | H1: =Data!O9 -> 2030 | I1: =Data!P9 -> 2031 | ... AB1: =Data!AI9 -> 2050
A2: battery electric vehicle | B2: =Data!I73 -> 0 | C2: =Data!J73 -> 0 | D2: =Data!K73 -> 0 | E2: =Data!L73 -> 0 | F2: =Data!M73 -> 0 | G2: =Data!N73 -> 0 | H2: =Data!O73 -> 0 | I2: =Data!P73 -> 0 | ... AB2: =Data!AI73 -> 0
A3: natural gas vehicle | B3: =Data!I74 -> 0 | C3: =Data!J74 -> 0 | D3: =Data!K74 -> 0 | E3: =Data!L74 -> 0 | F3: =Data!M74 -> 0 | G3: =Data!N74 -> 0 | H3: =Data!O74 -> 0 | I3: =Data!P74 -> 0 | ... AB3: =Data!AI74 -> 0
A4: gasoline vehicle | B4: =Data!I75 -> 0 | C4: =Data!J75 -> 0 | D4: =Data!K75 -> 0 | E4: =Data!L75 -> 0 | F4: =Data!M75 -> 0 | G4: =Data!N75 -> 0 | H4: =Data!O75 -> 0 | I4: =Data!P75 -> 0 | ... AB4: =Data!AI75 -> 0
A5: diesel vehicle | B5: =Data!I76 -> 1 | C5: =Data!J76 -> 1 | D5: =Data!K76 -> 1 | E5: =Data!L76 -> 1 | F5: =Data!M76 -> 1 | G5: =Data!N76 -> 1 | H5: =Data!O76 -> 1 | I5: =Data!P76 -> 1 | ... AB5: =Data!AI76 -> 1
A6: plugin hybrid vehicle | B6: =Data!I77 -> 0 | C6: =Data!J77 -> 0 | D6: =Data!K77 -> 0 | E6: =Data!L77 -> 0 | F6: =Data!M77 -> 0 | G6: =Data!N77 -> 0 | H6: =Data!O77 -> 0 | I6: =Data!P77 -> 0 | ... AB6: =Data!AI77 -> 0
A7: LPG vehicle | B7: =Data!I78 -> 0 | C7: =Data!J78 -> 0 | D7: =Data!K78 -> 0 | E7: =Data!L78 -> 0 | F7: =Data!M78 -> 0 | G7: =Data!N78 -> 0 | H7: =Data!O78 -> 0 | I7: =Data!P78 -> 0 | ... AB7: =Data!AI78 -> 0
A8: hydrogen vehicle | B8: =Data!I79 -> 0 | C8: =Data!J79 -> 0 | D8: =Data!K79 -> 0 | E8: =Data!L79 -> 0 | F8: =Data!M79 -> 0 | G8: =Data!N79 -> 0 | H8: =Data!O79 -> 0 | I8: =Data!P79 -> 0 | ... AB8: =Data!AI79 -> 0

Sheet TTS-motorbikes-psgr
A1: Max Fraction of Production (dimensionless) | B1: =Data!I9 -> 2024 | C1: =Data!J9 -> 2025 | D1: =Data!K9 -> 2026 | E1: =Data!L9 -> 2027 | F1: =Data!M9 -> 2028 | G1: =Data!N9 -> 2029 | H1: =Data!O9 -> 2030 | I1: =Data!P9 -> 2031 | ... AB1: =Data!AI9 -> 2050
A2: battery electric vehicle | B2: =Data!I80 -> 0.14828895 | C2: =Data!J80 -> 0.20192405 | D2: =Data!K80 -> 0.21912805 | E2: =Data!L80 -> 0.24120792 | F2: =Data!M80 -> 0.26910507 | G2: =Data!N80 -> 0.30366278 | H2: =Data!O80 -> 0.34543895 | I2: =Data!P80 -> 0.39447645 | ... AB2: =Data!AI80 -> 0.99304785
A3: natural gas vehicle | B3: =Data!I81 -> 0.00010097 | C3: =Data!J81 -> 0.00010097 | D3: =Data!K81 -> 0.00010097 | E3: =Data!L81 -> 0.00010097 | F3: =Data!M81 -> 0.00010097 | G3: =Data!N81 -> 0.00010097 | H3: =Data!O81 -> 0.00010097 | I3: =Data!P81 -> 0.00010097 | ... AB3: =Data!AI81 -> 0.00010097
A4: gasoline vehicle | B4: =Data!I82 -> 1 | C4: =Data!J82 -> 1 | D4: =Data!K82 -> 1 | E4: =Data!L82 -> 1 | F4: =Data!M82 -> 1 | G4: =Data!N82 -> 1 | H4: =Data!O82 -> 1 | I4: =Data!P82 -> 1 | ... AB4: =Data!AI82 -> 1
A5: diesel vehicle | B5: =Data!I83 -> 0.06738296 | C5: =Data!J83 -> 0.06738296 | D5: =Data!K83 -> 0.06738296 | E5: =Data!L83 -> 0.06738296 | F5: =Data!M83 -> 0.06738296 | G5: =Data!N83 -> 0.06738296 | H5: =Data!O83 -> 0.06738296 | I5: =Data!P83 -> 0.06738296 | ... AB5: =Data!AI83 -> 0.06738296
A6: plugin hybrid vehicle | B6: =Data!I84 -> 0.014073499 | C6: =Data!J84 -> 0.0153783 | D6: =Data!K84 -> 0.015825739 | E6: =Data!L84 -> 0.01642247 | F6: =Data!M84 -> 0.017215046 | G6: =Data!N84 -> 0.018262018 | H6: =Data!O84 -> 0.019635127 | I6: =Data!P84 -> 0.021419076 | ... AB6: =Data!AI84 -> 0.099249119
A7: LPG vehicle | B7: =Data!I85 -> 0 | C7: =Data!J85 -> 0 | D7: =Data!K85 -> 0 | E7: =Data!L85 -> 0 | F7: =Data!M85 -> 0 | G7: =Data!N85 -> 0 | H7: =Data!O85 -> 0 | I7: =Data!P85 -> 0 | ... AB7: =Data!AI85 -> 0
A8: hydrogen vehicle | B8: =Data!I86 -> 0 | C8: =Data!J86 -> 0 | D8: =Data!K86 -> 0 | E8: =Data!L86 -> 0 | F8: =Data!M86 -> 0 | G8: =Data!N86 -> 0 | H8: =Data!O86 -> 0 | I8: =Data!P86 -> 0 | ... AB8: =Data!AI86 -> 0

Sheet TTS-motorbikes-frgt
A1: Max Fraction of Production (dimensionless) | B1: =Data!I9 -> 2024 | C1: =Data!J9 -> 2025 | D1: =Data!K9 -> 2026 | E1: =Data!L9 -> 2027 | F1: =Data!M9 -> 2028 | G1: =Data!N9 -> 2029 | H1: =Data!O9 -> 2030 | I1: =Data!P9 -> 2031 | ... AB1: =Data!AI9 -> 2050
A2: battery electric vehicle | B2: 1 | C2: 1 | D2: 1 | E2: 1 | F2: 1 | G2: 1 | H2: 1 | I2: 1 | J2: 1 | K2: 1 | L2: 1 | M2: 1 | N2: 1 | O2: 1 | P2: 1 | Q2: 1 | R2: 1 | S2: 1 | T2: 1 | U2: 1 | V2: 1 | W2: 1 | X2: 1 | Y2: 1 | Z2: 1 | AA2: 1 | AB2: 1
A3: natural gas vehicle | B3: 1 | C3: 1 | D3: 1 | E3: 1 | F3: 1 | G3: 1 | H3: 1 | I3: 1 | J3: 1 | K3: 1 | L3: 1 | M3: 1 | N3: 1 | O3: 1 | P3: 1 | Q3: 1 | R3: 1 | S3: 1 | T3: 1 | U3: 1 | V3: 1 | W3: 1 | X3: 1 | Y3: 1 | Z3: 1 | AA3: 1 | AB3: 1
A4: gasoline vehicle | B4: 1 | C4: 1 | D4: 1 | E4: 1 | F4: 1 | G4: 1 | H4: 1 | I4: 1 | J4: 1 | K4: 1 | L4: 1 | M4: 1 | N4: 1 | O4: 1 | P4: 1 | Q4: 1 | R4: 1 | S4: 1 | T4: 1 | U4: 1 | V4: 1 | W4: 1 | X4: 1 | Y4: 1 | Z4: 1 | AA4: 1 | AB4: 1
A5: diesel vehicle | B5: 1 | C5: 1 | D5: 1 | E5: 1 | F5: 1 | G5: 1 | H5: 1 | I5: 1 | J5: 1 | K5: 1 | L5: 1 | M5: 1 | N5: 1 | O5: 1 | P5: 1 | Q5: 1 | R5: 1 | S5: 1 | T5: 1 | U5: 1 | V5: 1 | W5: 1 | X5: 1 | Y5: 1 | Z5: 1 | AA5: 1 | AB5: 1
A6: plugin hybrid vehicle | B6: 1 | C6: 1 | D6: 1 | E6: 1 | F6: 1 | G6: 1 | H6: 1 | I6: 1 | J6: 1 | K6: 1 | L6: 1 | M6: 1 | N6: 1 | O6: 1 | P6: 1 | Q6: 1 | R6: 1 | S6: 1 | T6: 1 | U6: 1 | V6: 1 | W6: 1 | X6: 1 | Y6: 1 | Z6: 1 | AA6: 1 | AB6: 1
A7: LPG vehicle | B7: 1 | C7: 1 | D7: 1 | E7: 1 | F7: 1 | G7: 1 | H7: 1 | I7: 1 | J7: 1 | K7: 1 | L7: 1 | M7: 1 | N7: 1 | O7: 1 | P7: 1 | Q7: 1 | R7: 1 | S7: 1 | T7: 1 | U7: 1 | V7: 1 | W7: 1 | X7: 1 | Y7: 1 | Z7: 1 | AA7: 1 | AB7: 1
A8: hydrogen vehicle | B8: 1 | C8: 1 | D8: 1 | E8: 1 | F8: 1 | G8: 1 | H8: 1 | I8: 1 | J8: 1 | K8: 1 | L8: 1 | M8: 1 | N8: 1 | O8: 1 | P8: 1 | Q8: 1 | R8: 1 | S8: 1 | T8: 1 | U8: 1 | V8: 1 | W8: 1 | X8: 1 | Y8: 1 | Z8: 1 | AA8: 1 | AB8: 1
