Workbook
Name CH4_Ar4_to_AR5: #REF!
Name CH4_Ar4_to_AR5: Overview!$B$25
Name CH4_to_CO2e: #REF!
Name Fraction_coal: [1]About!$C$66
Name gal_per_barrel: [2]About!$A$63
Name gwp_ch4: Overview!$B$21
Name gwp_n2o: Overview!$B$20
Name HHV_Adjust: [3]About!$A$203
Name IQ_CH: 110000
Name IQ_CQ: 5000
Name IQ_CY: 10000
Name IQ_DAILY: 500000
Name IQ_FH: 100000
Name IQ_FQ: 500
Name IQ_FY: 1000
Name IQ_LTM: 2000
Name IQ_MONTH: 15000
Name IQ_NTM: 6000
Name IQ_WEEK: 50000
Name IQ_YTD: 3000
Name metricton_to_shortton: [4]Overview!$B$19
Name metricton_to_shortton: Overview!$B$19
Name million: [4]Overview!$B$22
Name million: Overview!$B$22
Name N2O_AR4_to_AR5: Overview!$B$26
Name N2O_to_CO2e: '[5]Cross-Page Data'!$C$13
Name Percent_rural: [1]About!$A$105
Name Percent_urban: [1]About!$A$104
Name quadrillion: [1]About!$B$107
Name Table4_1_22: '[1]AEO23 Table 4'!$C$1:$AG$1
Name Table4_22: '[1]AEO23 Table 4'!$C$34:$AG$74
Name Table4_A_22: '[1]AEO23 Table 4'!$A$34:$A$74
Name Table5_1_22: '[1]AEO23 Table 5'!$C$1:$AG$1
Name Table5_22: '[1]AEO23 Table 5'!$C$29:$AG$58
Name Table5_A_22: '[1]AEO23 Table 5'!$A$29:$A$58
Name unit_conv: [6]About!$A$108

Sheet Overview
B2: This spreadsheet compares start year EPS emissions to EPA and EIA emissions estimates.
B3: EPS Outputs
B4: US EPS
B5: https://us.energypolicy.solutions/
B7: EPA
B8: Inventory of U.S. Greenhouse Gas Emissions and Sinks
B9: https://www.epa.gov/ghgemissions/inventory-us-greenhouse-gas-emissions-and-sinks-1990-2021
B11: EIA
B12: Annual Energy Outlook
B13: 2022
B14: https://www.eia.gov/outlooks/aeo/tables_ref.php
B18: Conversions
B19: 1.10231 | C19: metricton_to_shortton
B20: 265 | C20: GWP N2O
B21: 28 | C21: GWP CH4
B22: =10^6 -> 1000000 | C22: million
B24: GWP Conversions
B25: =28/25 -> 1.12 | C25: CH4_Ar4_to_AR5
B26: =265/298 -> 0.88926174 | C26: N2O_AR4_to_AR5
B28: Toggle AR4 to AR5
B29: AR5 GWP
B30: AR4 GWP | C30: AR5 GWP

Sheet 1. Transportation
H1: Transportation
H2: MMTCO2e
A5: EIA | B5: EPS Sub 4 | C5: EPS Sub 3 | D5: EPS Sub 2 | E5: EPS Sub 1 | F5: EPS Variable | G5: EPA Table
H7: 1.1 | I7: Total Transportation Sector Greenhouse Gas Emissions by Pollutant Type
K8: EPS 2024 | L8: EPA 2023 | M8: EIA 2021
F9: Transportation Pollutant Emissions Disaggregated | G9: EPA_Table 3-7 | J9: CO2 | K9: =SUMIFS(EPS!$L:$L,EPS!$B:$B,F9,EPS!$I:$I,J9) -> 1720.5574 | L9: =SUM('Table 3-13'!F5:F10,'Table 3-13'!F12:F18,'Table 3-13'!F21:F23,'Table 3-13'!F27,'Table 3-13'!F29,'Table 3-13'!F34:F35,'Table 3-13'!F41) -> 1704.5214
F10: Transportation Pollutant Emissions Disaggregated | G10: EPA_Table 3-7 | J10: CH4 | K10: =SUMIFS(EPS!$L:$L,EPS!$B:$B,F10,EPS!$I:$I,J10) -> 2.0116845 | L10: ='Table 3-10'!C6 -> 2.5398312
F11: Transportation Pollutant Emissions Disaggregated | G11: EPA_Table 3-7 | J11: N2O | K11: =SUMIFS(EPS!$L:$L,EPS!$B:$B,F11,EPS!$I:$I,J11) -> 11.32663 | L11: ='Table 3-10'!C7 -> 16.183964
J12: Total CO2e | K12: =SUM(K9:K11) -> 1733.8957 | L12: =SUM(L9:L11) -> 1723.2452 | M12: ='Table 11.5'!M62-'Table 11.5'!L62-M32 -> 1741.377 | N12: *natural gas total removed for EIA
H25: 1.2 | I25: Transportation CO2 Emissions by Fuel Type
K26: EPS 2024 | L26: EPA 2023 | M26: EIA 2021
A27: motor gasoline | B27: petroleum gasoline tf | F27: Transportation Pollutant Emissions Disaggregated | G27: EPA_Table 3-13 | J27: Gasoline | K27: =SUMIFS(EPS!$L:$L,EPS!$B:$B,F27,EPS!$F:$F,"*"&B27&"*",EPS!$I:$I,"CO2") -> 1070.4536 | L27: ='Table 3-13'!F4 -> 1035.6964 | M27: =SUMIFS('Table 11.5'!$62:$62,'Table 11.5'!$1:$1,A27) -> 1024.604
A28: distillate fuel oil | B28: petroleum diesel tf | F28: Transportation Pollutant Emissions Disaggregated | G28: EPA_Table 3-13 | J28: Distillate Fuel Oil | K28: =SUMIFS(EPS!$L:$L,EPS!$B:$B,F28,EPS!$F:$F,"*"&B28&"*",EPS!$I:$I,"CO2") -> 463.07397 | L28: ='Table 3-13'!F11 -> 478.27614 | M28: =SUMIFS('Table 11.5'!$62:$62,'Table 11.5'!$1:$1,A28) -> 459.304
A29: jet fuel | B29: jet fuel tf | F29: Transportation Pollutant Emissions Disaggregated | G29: EPA_Table 3-13 | J29: Jet Fuel | K29: =SUMIFS(EPS!$L:$L,EPS!$B:$B,F29,EPS!$F:$F,"*"&B29&"*",EPS!$I:$I,"CO2") -> 154.9037 | L29: ='Table 3-13'!F20-SUM('Table 3-13'!F24:F25) -> 115.43943 | M29: =SUMIFS('Table 11.5'!$62:$62,'Table 11.5'!$1:$1,A29) -> 204.785
A30: aviation gasoline | B30: aviation gasoline | F30: Transportation Pollutant Emissions Disaggregated | G30: EPA_Table 3-13 | J30: Aviation Gasoline | K30: =SUMIFS(EPS!$L:$L,EPS!$B:$B,F30,EPS!$F:$F,"*"&B30&"*",EPS!$I:$I,"CO2") -> 0 | L30: ='Table 3-13'!F26 -> 1.4636844 | M30: =SUMIFS('Table 11.5'!$62:$62,'Table 11.5'!$1:$1,A30) -> 1.49
A31: residual fuel oil | B31: heavy or residual fuel oil tf | F31: Transportation Pollutant Emissions Disaggregated | G31: EPA_Table 3-13 | J31: Residual Fuel Oil | K31: =SUMIFS(EPS!$L:$L,EPS!$B:$B,F31,EPS!$F:$F,"*"&B31&"*",EPS!$I:$I,"CO2") -> 28.1638 | L31: ='Table 3-13'!F28 -> 39.274714 | M31: =SUMIFS('Table 11.5'!$62:$62,'Table 11.5'!$1:$1,A31) -> 46.172
A32: natural gas | B32: natural gas tf | F32: Transportation Pollutant Emissions Disaggregated | G32: EPA_Table 3-13 | J32: Natural Gas | K32: =SUMIFS(EPS!$L:$L,EPS!$B:$B,F32,EPS!$F:$F,"*"&B32&"*",EPS!$I:$I,"CO2") -> 3.0906256 | L32: ='Table 3-13'!F31-'Table 3-13'!F36 -> 0.40178148 | M32: =SUMIFS('Table 11.5'!$62:$62,'Table 11.5'!$1:$1,A32) -> 65.091 | N32: *EIA includes gas pipeline transport
A33: hydrocarbon gas liquids | B33: LPG propane or butane tf | F33: Transportation Pollutant Emissions Disaggregated | G33: EPA_Table 3-13 | J33: LPG | K33: =SUMIFS(EPS!$L:$L,EPS!$B:$B,F33,EPS!$F:$F,"*"&B33&"*",EPS!$I:$I,"CO2") -> 0.8716378 | L33: ='Table 3-13'!F37 -> 0.70043467 | M33: =SUMIFS('Table 11.5'!$62:$62,'Table 11.5'!$1:$1,A33) -> 0.614
B34: electricity tf | F34: Transportation Pollutant Emissions Disaggregated | G34: EPA_Table 3-13 | J34: Electricity | K34: =SUMIFS(EPS!$L:$L,EPS!$B:$B,F34,EPS!$F:$F,"*"&B34&"*",EPS!$I:$I,"CO2") -> 0
B35: hydrogen tf | F35: Transportation Pollutant Emissions Disaggregated | J35: Hydrogen | K35: =SUMIFS(EPS!$L:$L,EPS!$B:$B,F35,EPS!$F:$F,"*"&B35&"*",EPS!$I:$I,"CO2") -> 0
B36: biofuel gasoline tf | F36: Transportation Pollutant Emissions Disaggregated | J36: Biofuel Ethanol | K36: =SUMIFS(EPS!$L:$L,EPS!$B:$B,F36,EPS!$F:$F,"*"&B36&"*",EPS!$I:$I,"CO2") -> 0
B37: biofuel diesel tf | F37: Transportation Pollutant Emissions Disaggregated | J37: Biofuel Diesel | K37: =SUMIFS(EPS!$L:$L,EPS!$B:$B,F37,EPS!$F:$F,"*"&B37&"*",EPS!$I:$I,"CO2") -> 0
A38: other | J38: Other | K38: =SUMIFS(EPS!$L:$L,EPS!$B:$B,F38,EPS!$F:$F,"*"&B38&"*",EPS!$I:$I,"CO2") -> 0 | M38: =SUMIFS('Table 11.5'!$62:$62,'Table 11.5'!$1:$1,A38) -> 4.408
K39: =SUM(K27:K37) -> 1720.5574 | L39: =SUM(L27:L37) -> 1671.2526 | M39: =SUM(M27:M38) -> 1806.468
L46: =L55/K55 -> 0.99422827
O48: Note: EPS classifies light and medium duty trucks together, whereas
O49: EPA classifies medium and heavy duty trucks together. That leads to the
H50: 1.3 | I50: Transportation CO2 Emissions by Vehicle Type | O50: discrepancy below. See the table to the left, which shows we are aligned for
K51: EPS 2024 | L51: EPA 2023 | O51: combined cars and trucks.
B52: CO2 | E52: LDVs | F52: Transportation Pollutant Emissions Disaggregated | G52: EPA_Table 3-13 | J52: Passenger Cars and Light-Duty Trucks | K52: =SUMIFS(EPS!$L:$L,EPS!$B:$B,F52,EPS!$C:$C,E52,EPS!$I:$I,"CO2") -> 1155.0796 | L52: =SUMIFS('Table 3-13'!$F:$F,'Table 3-13'!$H:$H,J52) -> 1005.3056 | M52: =K52/L52 -> 1.1489836
B53: CO2 | C53: freight | E53: HDVs | F53: Transportation Pollutant Emissions Disaggregated | G53: EPA_Table 3-13 | J53: Medium and Heavy Duty Trucks | K53: =SUMIFS(EPS!$L:$L,EPS!$B:$B,F53,EPS!$C:$C,E53,EPS!$E:$E,C53,EPS!$I:$I,"CO2") -> 299.27887 | L53: =SUMIFS('Table 3-13'!$F:$F,'Table 3-13'!$H:$H,J53) -> 417.98977 | M53: =K53/L53 -> 0.71599567
B54: CO2 | C54: passenger | E54: HDVs | F54: Transportation Pollutant Emissions Disaggregated | G54: EPA_Table 3-13 | J54: All Cars and Trucks | K54: =SUM(K52:K53) -> 1454.3585 | L54: =SUM(L52:L53) -> 1423.2954 | M54: =K54/L54 -> 1.0218248
B55: CO2 | E55: motorbikes | F55: Transportation Pollutant Emissions Disaggregated | G55: EPA_Table 3-13 | J55: Buses | K55: =SUMIFS(EPS!$L:$L,EPS!$B:$B,F54,EPS!$C:$C,E54,EPS!$E:$E,C54,EPS!$I:$I,"CO2") -> 23.941138 | L55: =SUMIFS('Table 3-13'!$F:$F,'Table 3-13'!$H:$H,J55) -> 23.802956 | M55: =K55/L55 -> 1.0058052
B56: CO2 | C56: passenger | E56: ships | F56: Transportation Pollutant Emissions Disaggregated | G56: EPA_Table 3-13 | J56: Motorcycles | K56: =SUMIFS(EPS!$L:$L,EPS!$B:$B,F55,EPS!$C:$C,E55,EPS!$I:$I,"CO2") -> 1.27057 | L56: =SUMIFS('Table 3-13'!$F:$F,'Table 3-13'!$H:$H,J56) -> 8.5536064 | M56: =K56/L56 -> 0.14854202
B57: CO2 | C57: freight | E57: ships | F57: Transportation Pollutant Emissions Disaggregated | G57: EPA_Table 3-13 | J57: Recreational Boats | K57: =SUMIFS(EPS!$L:$L,EPS!$B:$B,F56,EPS!$C:$C,E56,EPS!$E:$E,C56,EPS!$I:$I,"CO2") -> 14.82397 | L57: =SUMIFS('Table 3-13'!$F:$F,'Table 3-13'!$H:$H,J57) -> 13.734628 | M57: =K57/L57 -> 1.0793136
B58: CO2 | E58: rail | F58: Transportation Pollutant Emissions Disaggregated | G58: EPA_Table 3-13 | J58: Rail | K58: =SUMIFS(EPS!$L:$L,EPS!$B:$B,F58,EPS!$C:$C,E58,EPS!$I:$I,"CO2") -> 33.70777 | L58: =SUMIFS('Table 3-13'!$F:$F,'Table 3-13'!$H:$H,J58) -> 30.938897 | M58: =K58/L58 -> 1.0894949
B59: CO2 | E59: aircraft | F59: Transportation Pollutant Emissions Disaggregated | J59: All ships and aircraft | K59: =SUM(K60:K62) -> 192.45543 | L59: =SUM(L60:L62) -> 204.78304 | M59: =K59/L59 -> 0.93980163
B60: CO2 | F60: Transportation Pollutant Emissions Disaggregated | J60: Ships | K60: =SUMIFS(EPS!$L:$L,EPS!$B:$B,F57,EPS!$C:$C,E57,EPS!$E:$E,C57,EPS!$I:$I,"CO2") -> 37.55173 | L60: =SUMIFS('Table 3-13'!$F:$F,'Table 3-13'!$H:$H,J60) -> 24.379925 | M60: =K60/L60 -> 1.5402726
B61: CO2 | C61: passenger | E61: aircraft | F61: Transportation Pollutant Emissions Disaggregated | J61: Passenger Aircraft | K61: =SUMIFS(EPS!$L:$L,EPS!$B:$B,F61,EPS!$C:$C,E61,EPS!$E:$E,C61,EPS!$I:$I,"CO2") -> 133.291 | L61: =SUMIFS('Table 3-13'!$F:$F,'Table 3-13'!$H:$H,J61) -> 129.7 | M61: =K61/L61 -> 1.027687
B62: CO2 | C62: freight | E62: aircraft | F62: Transportation Pollutant Emissions Disaggregated | J62: Military and Other Aircraft | K62: =SUMIFS(EPS!$L:$L,EPS!$B:$B,F62,EPS!$C:$C,E62,EPS!$E:$E,C62,EPS!$I:$I,"CO2") -> 21.6127 | L62: =SUMIFS('Table 3-13'!$F:$F,'Table 3-13'!$H:$H,J62) -> 50.70311 | M62: =K62/L62 -> 0.42625984
M63: =K63/L63 -> #DIV/0!
K64: =SUM(K52:K53,K55:K58,K60:K62) -> 1720.5574 | L64: =SUM(L52:L53,L55:L58,L60:L62) -> 1705.1085 | M64: =K64/L64 -> 1.0090604
J65: *excludes elec
K66: =SUM(K61:K62) -> 154.9037 | L66: =SUM(L61:L62) -> 180.40311
L67: =L66/K66 -> 1.1646146

Sheet 2. Electricity
H1: Electricity
H2: MMTCO2e
M4: =L9-K9 -> -165.68138
A6: EIA | B6: EPS Sub 4 | C6: EPS Sub 3 | D6: EPS Sub 2 | E6: EPS Sub 1 | F6: EPS Variable | G6: EPA Table
H7: 2.1 | I7: Total Electricity Sector Greenhouse Gas Emissions by Pollutant Type
K8: EPS 2024 | L8: EPA 2023 | M8: EIA 2021
E9: CO2 | F9: Electricity Sector Pollutant Emissions | G9: EPA_Table 3-7 | J9: CO2 | K9: =SUMIFS(EPS!$L:$L,EPS!$B:$B,F9,EPS!$I:$I,E9) -> 1592.2839 | L9: ='Table 3-10'!C9+'Table 3-1'!C15 -> 1426.6025 | M9: ='Table 11.6'!J62 -> 1551.144
E10: CH4 | F10: Electricity Sector Pollutant Emissions | G10: EPA_Table 3-7 | J10: CH4 | K10: =SUMIFS(EPS!$L:$L,EPS!$B:$B,F10,EPS!$I:$I,E10) -> 1.8685541 | L10: ='Table 3-10'!C10 -> 1.5057991
E11: N2O | F11: Electricity Sector Pollutant Emissions | G11: EPA_Table 3-7 | J11: N2O | K11: =SUMIFS(EPS!$L:$L,EPS!$B:$B,F11,EPS!$I:$I,E11) -> 17.593559 | L11: ='Table 3-10'!C11+'Table 3-1'!C37 -> 16.910483
J12: Total CO2e | K12: =SUM(K9:K11) -> 1611.746 | L12: =SUM(L9:L11) -> 1445.0188 | M12: =SUM(M9:M11) -> 1551.144
H26: 2.2 | I26: Electric Sector CO2 Emissions by Fuel Type
K27: EPS 2024 | L27: EPA 2023 | M27: EIA 2021
A28: coal | D28: hard coal es | E28: CO2 | F28: Electricity Sector Pollutant Emissions | G28: EPA_Table 3-9 | J28: Coal | K28: =SUM(SUMIFS(EPS!$L:$L,EPS!$B:$B,F29,EPS!$I:$I,E29,EPS!$D:$D,D29),SUMIFS(EPS!$L:$L,EPS!$B:$B,F28,EPS!$I:$I,E28,EPS!$D:$D,D28)) -> 801.2266 | L28: ='Table 3-7'!C5 -> 694.55699 | M28: =SUMIFS('Table 11.6'!$62:$62,'Table 11.6'!$1:$1,A28) -> 909.624
D29: lignite es | E29: CO2 | F29: Electricity Sector Pollutant Emissions | G29: EPA_Table 3-9
A30: natural gas | D30: natural gas | E30: CO2 | F30: Electricity Sector Pollutant Emissions | G30: EPA_Table 3-9 | J30: Natural Gas | K30: =SUMIFS(EPS!$L:$L,EPS!$B:$B,F30,EPS!$I:$I,E30,EPS!$D:$D,"*"&D30&"*") -> 784.997 | L30: ='Table 3-7'!C6 -> 704.54465 | M30: =SUMIFS('Table 11.6'!$62:$62,'Table 11.6'!$1:$1,A30) -> 612.831
A31: petroleum | D31: heavy or residual fuel oil es | E31: CO2 | F31: Electricity Sector Pollutant Emissions | G31: EPA_Table 3-9 | J31: Petroleum | K31: =SUMIFS(EPS!$L:$L,EPS!$B:$B,F31,EPS!$I:$I,E31,EPS!$D:$D,"*"&D31&"*") -> 0 | L31: ='Table 3-7'!C7 -> 14.708588 | M31: =SUMIFS('Table 11.6'!$62:$62,'Table 11.6'!$1:$1,A31) -> 35.429
A32: geothermal | D32: geothermal es | E32: CO2 | F32: Electricity Sector Pollutant Emissions | G32: EPA_Table 3-9 | J32: Geothermal | K32: =SUMIFS(EPS!$L:$L,EPS!$B:$B,F32,EPS!$I:$I,E32,EPS!$D:$D,"*"&D32&"*") -> 0 | L32: ='Table 3-7'!C8 -> 0.36724082 | M32: =SUMIFS('Table 11.6'!$62:$62,'Table 11.6'!$1:$1,A32) -> 0.47
A33: MSW | D33: municipal solid waste es | E33: CO2 | F33: Electricity Sector Pollutant Emissions | J33: MSW | K33: =SUM(SUMIFS(EPS!$L:$L,EPS!$B:$B,F34,EPS!$I:$I,E34,EPS!$D:$D,D34),SUMIFS(EPS!$L:$L,EPS!$B:$B,F33,EPS!$I:$I,E33,EPS!$D:$D,D33)) -> 6.06025 | M33: =SUMIFS('Table 11.6'!$62:$62,'Table 11.6'!$1:$1,A33) -> 10.505
D34: petroleum es | E34: CO2 | F34: Electricity Sector Pollutant Emissions
K35: =SUM(K28:K34) -> 1592.2839 | L35: =SUM(L28:L34) -> 1414.1775 | M35: =SUM(M28:M34) -> 1568.859
H44: 2.3 | I44: Electric Sector CH4 Emissions by Fuel Type
K45: EPS 2024 | L45: EPA 2023
D46: hard coal es | E46: CH4 | F46: Electricity Sector Pollutant Emissions | G46: EPA_Table 3-10 | J46: Coal | K46: =SUM(SUMIFS(EPS!$L:$L,EPS!$B:$B,F47,EPS!$I:$I,E47,EPS!$D:$D,D47),SUMIFS(EPS!$L:$L,EPS!$B:$B,F46,EPS!$I:$I,E46,EPS!$D:$D,D46)) -> 0.1636936 | L46: ='Table 3-8'!C5 -> 0.15473752
D47: lignite | E47: CH4 | F47: Electricity Sector Pollutant Emissions | G47: EPA_Table 3-10
D48: heavy or residual fuel oil es | E48: CH4 | F48: Electricity Sector Pollutant Emissions | G48: EPA_Table 3-10 | J48: Fuel Oil | K48: =SUMIFS(EPS!$L:$L,EPS!$B:$B,F48,EPS!$I:$I,E48,EPS!$D:$D,"*"&D48&"*") -> 0 | L48: ='Table 3-8'!C6 -> 0.000766985
D49: natural gas | E49: CH4 | F49: Electricity Sector Pollutant Emissions | G49: EPA_Table 3-10 | J49: Natural Gas | K49: =SUMIFS(EPS!$L:$L,EPS!$B:$B,F49,EPS!$I:$I,E49,EPS!$D:$D,"*"&D49&"*") -> 1.5459693 | L49: ='Table 3-8'!C7 -> 1.3484968
H51: 2.4 | I51: Electric Sector N2O Emissions by Fuel Type
K52: EPS 2024 | L52: EPA 2023
D53: hard coal es | E53: N2O | F53: Electricity Sector Pollutant Emissions | G53: EPA_Table 3-11 | J53: Coal | K53: =SUM(SUMIFS(EPS!$L:$L,EPS!$B:$B,F54,EPS!$I:$I,E54,EPS!$D:$D,D54),SUMIFS(EPS!$L:$L,EPS!$B:$B,F53,EPS!$I:$I,E53,EPS!$D:$D,D53)) -> 12.357401 | L53: ='Table 3-9'!C5 -> 12.13077
D54: lignite | E54: N2O | F54: Electricity Sector Pollutant Emissions | G54: EPA_Table 3-11
D55: heavy or residual fuel oil es | E55: N2O | F55: Electricity Sector Pollutant Emissions | G55: EPA_Table 3-11 | J55: Fuel Oil | K55: =SUMIFS(EPS!$L:$L,EPS!$B:$B,F55,EPS!$I:$I,E55,EPS!$D:$D,"*"&D55&"*") -> 0 | L55: ='Table 3-9'!C6 -> 0.002999408
D56: natural gas | E56: N2O | F56: Electricity Sector Pollutant Emissions | G56: EPA_Table 3-11 | J56: Natural Gas | K56: =SUMIFS(EPS!$L:$L,EPS!$B:$B,F56,EPS!$I:$I,E56,EPS!$D:$D,"*"&D56&"*") -> 5.0261411 | L56: ='Table 3-9'!C7 -> 4.4324812

Sheet 3. Industry Energy
J1: Industry
J2: MMTCO2e
J3: Note that EIA emissions cateogries are different than EPS and EPA
J4: Note that EIA rebased its AEO model to the most recent MECS in AEO 2022, which is why there is a large discrepancy here
A7: EIA | B7: EPS Sub 4 | C7: EPS Sub 3 | D7: EPS Sub 2 | E7: EPS Sub 1 | F7: Exclude1 | G7: Exclude2 | H7: EPS Variable | I7: EPA Table
J8: 3.1 | K8: Industry Energy Greenhouse Gas Emissions by Pollutant Type
M9: EPS 2021 | N9: EPA 2021 | O9: EIA 2021
H10: Industrial Sector Energy Related Emissions after CCS | I10: EPA_Table 3-7 | L10: CO2 | M10: =SUMIFS(EPS!$L:$L,EPS!$B:$B,H10,EPS!$I:$I,L10) -> #N/A | N10: ='Table 3-10'!C13+'Table 3-13'!F36 -> 863.95131 | O10: ='Table 11.4'!O62-'Table 11.4'!N62 -> 975.411
H11: Industrial Sector Energy Related Emissions after CCS | I11: EPA_Table 3-7 | L11: CH4 | M11: =SUMIFS(EPS!$L:$L,EPS!$B:$B,H11,EPS!$I:$I,L11) -> #N/A | N11: ='Table 3-10'!C14 -> 1.4973585
H12: Industrial Sector Energy Related Emissions after CCS | I12: EPA_Table 3-7 | L12: N2O | M12: =SUMIFS(EPS!$L:$L,EPS!$B:$B,H12,EPS!$I:$I,L12) -> #N/A | N12: ='Table 3-10'!C15 -> 1.9174828
L13: Total CO2e | M13: =SUM(M10:M12) -> #N/A | N13: =SUM(N10:N12) -> 867.36615 | O13: =SUM(O10:O12) -> 975.411
L14: *EPS total roughly 50 MMT higher when considering
L15: emissions from hydrogen production, captured in
L16: the hydrogen sector
J28: 3.2 | K28: Industry Sector CO2 Emissions by Fuel Type
M29: EPS 2021 | N29: EPA 2021 | O29: EIA 2021
A30: coal | C30: CO2 | E30: hard coal if | H30: Industrial Energy Related Emissions Excluding Fuels to Power CCS | I30: EPA_Table 3-9 | L30: Coal | M30: =SUMIFS(EPS!$L:$L,EPS!$B:$B,H30,EPS!$C:$C,E30,EPS!$E:$E,C30) -> 0 | N30: ='Table 3-7'!C10 -> 36.484927 | O30: =SUMIFS('Table 11.4'!$62:$62,'Table 11.4'!$1:$1,A30) -> 91.594
A31: natural gas | C31: CO2 | E31: natural gas if | H31: Industrial Energy Related Emissions Excluding Fuels to Power CCS | I31: EPA_Table 3-9 | L31: Natural Gas | M31: =SUMIFS(EPS!$L:$L,EPS!$B:$B,H31,EPS!$C:$C,E31,EPS!$E:$E,C31) -> 0 | N31: ='Table 3-7'!C11+'Table 3-13'!F36 -> 586.12311 | O31: =SUMIFS('Table 11.4'!$62:$62,'Table 11.4'!$1:$1,A31) -> 537.676 | P31: * + 50 MMT from hydrogen
A32: fuel oil | C32: CO2 | E32: heavy or residual fuel oil if | H32: Industrial Energy Related Emissions Excluding Fuels to Power CCS | I32: EPA_Table 3-9 | L32: Petroleum Products | M32: =SUMIFS(EPS!$L:$L,EPS!$B:$B,H32,EPS!$C:$C,E32,EPS!$E:$E,C32)+SUMIFS(EPS!$L:$L,EPS!$B:$B,H34,EPS!$C:$C,E34,EPS!$E:$E,C34)+SUMIFS(EPS!$L:$L,EPS!$B:$B,H36,EPS!$C:$C,E36,EPS!$E:$E,C36)+SUMIFS(EPS!$L:$L,EPS!$B:$B,H37,EPS!$C:$C,E37,EPS!$E:$E,C37) -> 0 | N32: ='Table 3-7'!C12 -> 241.34327 | O32: =SUMIFS('Table 11.4'!$62:$62,'Table 11.4'!$1:$1,A32)+SUMIFS('Table 11.4'!$62:$62,'Table 11.4'!$1:$1,A34)+SUMIFS('Table 11.4'!$62:$62,'Table 11.4'!$1:$1,A35) -> 142.147
C33: CO2 | E33: biomass if | H33: Industrial Energy Related Emissions Excluding Fuels to Power CCS | I33: EPA_Table 3-9 | L33: biomass | M33: =SUMIFS(EPS!$L:$L,EPS!$B:$B,H33,EPS!$C:$C,E33,EPS!$E:$E,C33) -> 0 | O33: =SUMIFS('Table 11.4'!$62:$62,'Table 11.4'!$1:$1,A33) -> 0
A34: diesel | C34: CO2 | E34: petroleum diesel if | H34: Industrial Energy Related Emissions Excluding Fuels to Power CCS | I34: EPA_Table 3-9 | L34: diesel
A35: crude oil | C35: CO2 | E35: heat if | H35: Industrial Energy Related Emissions Excluding Fuels to Power CCS | I35: EPA_Table 3-9 | L35: heat
C36: CO2 | E36: crude oil if | H36: Industrial Energy Related Emissions Excluding Fuels to Power CCS | I36: EPA_Table 3-9 | L36: crude oil | O36: =SUMIFS('Table 11.4'!$62:$62,'Table 11.4'!$1:$1,A36) -> 0
C37: CO2 | E37: LPG propane or butane if | H37: Industrial Energy Related Emissions Excluding Fuels to Power CCS | I37: EPA_Table 3-9 | L37: LPG | O37: =SUMIFS('Table 11.4'!$62:$62,'Table 11.4'!$1:$1,A37) -> 0
A38: other | L38: other | M38: =SUMIFS(EPS!$L:$L,EPS!$B:$B,H38,EPS!$C:$C,E38,EPS!$E:$E,C38) -> 0 | O38: =SUMIFS('Table 11.4'!$62:$62,'Table 11.4'!$1:$1,A38) -> 203.994
M39: =SUM(M30:M37) -> 0 | N39: =SUM(N30:N37) -> 863.95131 | O39: =SUM(O30:O38) -> 975.411
J51: 3.3 | K51: Industry Sector CH4 Emissions by Fuel Type
M52: EPS 2021 | N52: EPA 2021
C53: CH4 | E53: hard coal if | H53: Industrial Energy Related Emissions Excluding Fuels to Power CCS | I53: EPA_Table 3-10 | L53: Coal | M53: =SUMIFS(EPS!$L:$L,EPS!$B:$B,H53,EPS!$C:$C,E53,EPS!$E:$E,C53) -> 0 | N53: ='Table 3-8'!C10 -> 0.10690672
C54: CH4 | E54: natural gas if | H54: Industrial Energy Related Emissions Excluding Fuels to Power CCS | I54: EPA_Table 3-10 | L54: Natural Gas | M54: =SUMIFS(EPS!$L:$L,EPS!$B:$B,H54,EPS!$C:$C,E54,EPS!$E:$E,C54) -> 0 | N54: ='Table 3-8'!C11 -> 0.14691013
C55: CH4 | E55: heavy or residual fuel oil if | H55: Industrial Energy Related Emissions Excluding Fuels to Power CCS | I55: EPA_Table 3-10 | L55: Fuel Oil | M55: =SUMIFS(EPS!$L:$L,EPS!$B:$B,H55,EPS!$C:$C,E55,EPS!$E:$E,C55) -> 0 | N55: ='Table 3-8'!C12 -> 0.25864888
C56: CH4 | E56: biomass if | H56: Industrial Energy Related Emissions Excluding Fuels to Power CCS | L56: biomass | M56: =SUMIFS(EPS!$L:$L,EPS!$B:$B,H56,EPS!$C:$C,E56,EPS!$E:$E,C56) -> 0
C57: CH4 | E57: petroleum diesel if | H57: Industrial Energy Related Emissions Excluding Fuels to Power CCS | L57: diesel | M57: =SUMIFS(EPS!$L:$L,EPS!$B:$B,H57,EPS!$C:$C,E57,EPS!$E:$E,C57) -> 0
C58: CH4 | E58: heat if | H58: Industrial Energy Related Emissions Excluding Fuels to Power CCS | L58: heat | M58: =SUMIFS(EPS!$L:$L,EPS!$B:$B,H58,EPS!$C:$C,E58,EPS!$E:$E,C58) -> 0
C59: CH4 | E59: crude oil if | H59: Industrial Energy Related Emissions Excluding Fuels to Power CCS | L59: crude oil | M59: =SUMIFS(EPS!$L:$L,EPS!$B:$B,H59,EPS!$C:$C,E59,EPS!$E:$E,C59) -> 0
C60: CH4 | E60: LPG propane or butane if | H60: Industrial Energy Related Emissions Excluding Fuels to Power CCS | L60: LPG | M60: =SUMIFS(EPS!$L:$L,EPS!$B:$B,H60,EPS!$C:$C,E60,EPS!$E:$E,C60) -> 0
M61: =SUM(M53:M60) -> 0 | N61: =SUM(N53:N60) -> 0.51246572
J64: 3.4 | K64: Industry Sector N2O Emissions by Fuel Type
M65: EPS 2021 | N65: EPA 2021
C66: N2O | E66: hard coal if | H66: Industrial Energy Related Emissions Excluding Fuels to Power CCS | I66: EPA_Table 3-11 | L66: Coal | M66: =SUMIFS(EPS!$L:$L,EPS!$B:$B,H66,EPS!$C:$C,E66,EPS!$E:$E,C66)-SUMIFS(EPS!$L:$L,EPS!$B:$B,H66,EPS!$C:$C,E66,EPS!$E:$E,C66,EPS!$D:$D,F66) -> 0 | N66: ='Table 3-9'!C10 -> 0.15176936
C67: N2O | E67: heavy or residual fuel oil if | H67: Industrial Energy Related Emissions Excluding Fuels to Power CCS | I67: EPA_Table 3-11 | L67: Fuel Oil | M67: =SUMIFS(EPS!$L:$L,EPS!$B:$B,H67,EPS!$C:$C,E67,EPS!$E:$E,C67)-SUMIFS(EPS!$L:$L,EPS!$B:$B,H67,EPS!$C:$C,E67,EPS!$E:$E,C67,EPS!$D:$D,F67) -> 0 | N67: ='Table 3-9'!C11 -> 0.27807988
C68: N2O | E68: natural gas if | H68: Industrial Energy Related Emissions Excluding Fuels to Power CCS | I68: EPA_Table 3-11 | L68: Natural Gas | M68: =SUMIFS(EPS!$L:$L,EPS!$B:$B,H68,EPS!$C:$C,E68,EPS!$E:$E,C68)-SUMIFS(EPS!$L:$L,EPS!$B:$B,H68,EPS!$C:$C,E68,EPS!$E:$E,C68,EPS!$D:$D,F68) -> 0 | N68: ='Table 3-9'!C12 -> 0.24479269
C69: N2O | E69: biomass if | H69: Industrial Energy Related Emissions Excluding Fuels to Power CCS | L69: biomass | M69: =SUMIFS(EPS!$L:$L,EPS!$B:$B,H69,EPS!$C:$C,E69,EPS!$E:$E,C69)-SUMIFS(EPS!$L:$L,EPS!$B:$B,H69,EPS!$C:$C,E69,EPS!$E:$E,C69,EPS!$D:$D,F69) -> 0 | N69: ='Table 3-9'!C13 -> 1.2428409
C70: N2O | E70: petroleum diesel if | H70: Industrial Energy Related Emissions Excluding Fuels to Power CCS | L70: diesel | M70: =SUMIFS(EPS!$L:$L,EPS!$B:$B,H70,EPS!$C:$C,E70,EPS!$E:$E,C70)-SUMIFS(EPS!$L:$L,EPS!$B:$B,H70,EPS!$C:$C,E70,EPS!$E:$E,C70,EPS!$D:$D,F70) -> 0 | N70: ='Table 3-9'!C14 -> 0.30078619
C71: N2O | E71: heat if | H71: Industrial Energy Related Emissions Excluding Fuels to Power CCS | L71: heat | M71: =SUMIFS(EPS!$L:$L,EPS!$B:$B,H71,EPS!$C:$C,E71,EPS!$E:$E,C71)-SUMIFS(EPS!$L:$L,EPS!$B:$B,H71,EPS!$C:$C,E71,EPS!$E:$E,C71,EPS!$D:$D,F71) -> 0 | N71: ='Table 3-9'!C15 -> 0.004622018
C72: N2O | E72: crude oil if | H72: Industrial Energy Related Emissions Excluding Fuels to Power CCS | L72: crude oil | M72: =SUMIFS(EPS!$L:$L,EPS!$B:$B,H72,EPS!$C:$C,E72,EPS!$E:$E,C72)-SUMIFS(EPS!$L:$L,EPS!$B:$B,H72,EPS!$C:$C,E72,EPS!$E:$E,C72,EPS!$D:$D,F72) -> 0 | N72: ='Table 3-9'!C16 -> 0.13701442
C73: N2O | E73: LPG propane or butane if | H73: Industrial Energy Related Emissions Excluding Fuels to Power CCS | L73: LPG | M73: =SUMIFS(EPS!$L:$L,EPS!$B:$B,H73,EPS!$C:$C,E73,EPS!$E:$E,C73)-SUMIFS(EPS!$L:$L,EPS!$B:$B,H73,EPS!$C:$C,E73,EPS!$E:$E,C73,EPS!$D:$D,F73) -> 0 | N73: ='Table 3-9'!C17 -> 0.086928685
M74: =SUM(M66:M73) -> 0 | N74: =SUM(N66:N73) -> 2.4468341

Sheet 4. Buildings
I1: Buildings
I2: MMTCO2e
A6: EIA | B6: EPS Sub 4 | C6: EPS Sub 3 | D6: EPS Sub 2 | E6: EPS Sub 1 | F6: EPS Subsector | G6: EPS Variable | H6: EPA Table
I7: 4.1 | J7: Total Residential Sector Greenhouse Gas Emissions by Pollutant Type
L8: EPS 2021 | M8: EPA 2021 | N8: EIA 2021
D9: CO2 | E9: residential | G9: Buildings Sector Pollutant Emissions | H9: EPA_Table 3-7 | K9: CO2 | L9: =SUMIFS(EPS!$L:$L,EPS!$B:$B,G9,EPS!$I:$I,D9,EPS!$C:$C,"*"&E9&"*") -> #N/A | M9: ='Table 3-10'!C17 -> 307.07737 | N9: ='Table 11.2'!I62-'Table 11.2'!H62 -> 324.915
D10: CH4 | E10: residential | G10: Buildings Sector Pollutant Emissions | H10: EPA_Table 3-7 | K10: CH4 | L10: =SUMIFS(EPS!$L:$L,EPS!$B:$B,G10,EPS!$I:$I,D10,EPS!$C:$C,"*"&E10&"*") -> #N/A | M10: ='Table 3-10'!C18 -> 4.459395
D11: N2O | E11: residential | G11: Buildings Sector Pollutant Emissions | H11: EPA_Table 3-7 | K11: N2O | L11: =SUMIFS(EPS!$L:$L,EPS!$B:$B,G11,EPS!$I:$I,D11,EPS!$C:$C,"*"&E11&"*") -> #N/A | M11: ='Table 3-10'!C19 -> 0.71053789
K12: Total CO2e | L12: =SUM(L9:L11) -> #N/A | M12: =SUM(M9:M11) -> 312.2473 | N12: =SUM(N9:N11) -> 324.915
I24: 4.2 | J24: Total Commercial Sector Greenhouse Gas Emissions by Pollutant Type
L25: EPS 2021 | M25: EPA 2021 | N25: EIA 2021
D26: CO2 | E26: commercial | G26: Buildings Sector Pollutant Emissions | H26: EPA_Table 3-7 | K26: CO2 | L26: =SUMIFS(EPS!$L:$L,EPS!$B:$B,G26,EPS!$I:$I,D26,EPS!$C:$C,"*"&E26&"*") -> #N/A | M26: ='Table 3-10'!C21 -> 244.16078 | N26: ='Table 11.3'!L62-'Table 11.3'!K62 -> 245.249
D27: CH4 | E27: commercial | G27: Buildings Sector Pollutant Emissions | H27: EPA_Table 3-7 | K27: CH4 | L27: =SUMIFS(EPS!$L:$L,EPS!$B:$B,G27,EPS!$I:$I,D27,EPS!$C:$C,"*"&E27&"*") -> #N/A | M27: ='Table 3-10'!C22 -> 1.2761028
D28: N2O | E28: commercial | G28: Buildings Sector Pollutant Emissions | H28: EPA_Table 3-7 | K28: N2O | L28: =SUMIFS(EPS!$L:$L,EPS!$B:$B,G28,EPS!$I:$I,D28,EPS!$C:$C,"*"&E28&"*") -> #N/A | M28: ='Table 3-10'!C23 -> 0.30078619
K29: Total CO2e | L29: =SUM(L26:L28) -> #N/A | M29: =SUM(M26:M28) -> 245.73767 | N29: =SUM(N26:N28) -> 245.249

Sheet 5. Industry Process
G1: Industry
G2: MMTCO2e
A6: EPS Sub 4 | B6: EPS Sub 3 | C6: EPS Sub 2 | D6: EPS Sub 1 | E6: EPS Variable | F6: EPA Table
G7: 5.1 | H7: Industry Process Greenhouse Gas Emissions by Pollutant Type
J8: EPS 2021 | K8: EPA 2021
E9: Process Emissions after CCS | F9: EPA Tables 3-1, 4-1, Table 5-1, Table 7-1 | I9: CO2 | J9: =SUMIFS(EPS!$L:$L,EPS!$B:$B,E9,EPS!$I:$I,I9) -> #N/A | K9: =SUM('Table 4-1'!C4,'Table 5-1'!C4)+SUMIFS('Table 3-1'!$C:$C,'Table 3-1'!$D:$D,"process",'Table 3-1'!$F:$F,I9)+SUMIFS('Table 3-24'!K:K,'Table 3-24'!N:N,I9) -> 353.90247
E10: Process Emissions after CCS | F10: EPA Tables 3-1, 4-1, Table 5-1, Table 7-1 | I10: CH4 | J10: =SUMIFS(EPS!$L:$L,EPS!$B:$B,E10,EPS!$I:$I,I10) -> #N/A | K10: =(SUM('Table 4-1'!C25,'Table 5-1'!C7,'Table 7-1'!C4)+SUMIFS('Table 3-1'!$C:$C,'Table 3-1'!$D:$D,"process",'Table 3-1'!$F:$F,I10)) -> 675.30666
E11: Process Emissions after CCS | F11: EPA Tables 3-1, 4-1, Table 5-1, Table 7-1 | I11: N2O | J11: =SUMIFS(EPS!$L:$L,EPS!$B:$B,E11,EPS!$I:$I,I11) -> #N/A | K11: =(SUM('Table 4-1'!C31,'Table 5-1'!C12,'Table 7-1'!C9)+SUMIFS('Table 3-1'!$C:$C,'Table 3-1'!$D:$D,"process",'Table 3-1'!$F:$F,I11)) -> 355.64667
E12: Process Emissions after CCS | F12: EPA Tables 3-1, 4-1, Table 5-1, Table 7-1 | I12: F gases | J12: =SUMIFS(EPS!$L:$L,EPS!$B:$B,E12,EPS!$I:$I,I12) -> #N/A | K12: =SUM('Table 4-1'!C37,'Table 4-1'!C42,'Table 4-1'!C49,'Table 4-1'!C55) -> 192.9
J13: =SUM(J9:J12) -> #N/A | K13: =SUM(K9:K12) -> 1577.7558
K14: =K13+53 -> 1630.7558
I15: *The discrepancy between the EPA total and the
I16: EPA plus ethanol total is due to CCS in gas processing
G26: 5.3 | H26: Industry Process Greenhouse Gas Emissions by Sector | J26: EPS 2021 | K26: EPA 2021
D27: cement and other nonmetallic minerals 239 | E27: Process Emissions after CCS | F27: EPA Tables 3-1, 4-1, Table 5-1, Table 7-1 | I27: cement and other carbonates | J27: =SUMIFS(EPS!$L:$L,EPS!$B:$B,E27,EPS!$C:$C,D27) -> #N/A | K27: =SUMIFS('Table 4-1'!$C:$C,'Table 4-1'!$E:$E,'5. Industry Process'!D27)+SUMIFS('Table 3-1'!$C:$C,'Table 3-1'!$E:$E,'5. Industry Process'!D27) -> 65.5
B28: refined petroleum and coke 19 | C28: oil and gas extraction 06 | D28: energy pipelines and gas processing 352T353 | E28: Process Emissions after CCS | F28: EPA Tables 3-1, 4-1, Table 5-1, Table 7-1 | I28: natural gas and petroleum systems | J28: =SUM(SUMIFS(EPS!$L:$L,EPS!$B:$B,E28,EPS!$C:$C,B28),SUMIFS(EPS!$L:$L,EPS!$B:$B,E28,EPS!$C:$C,C28),SUMIFS(EPS!$L:$L,EPS!$B:$B,E28,EPS!$C:$C,D28)) -> #N/A | K28: =SUM(SUMIFS('Table 3-1'!C:C,'Table 3-1'!E:E,C28),SUMIFS('Table 3-1'!C:C,'Table 3-1'!E:E,D28),SUMIFS('Table 4-1'!C:C,'Table 4-1'!E:E,B28))+SUMIFS('Table 3-24'!$K:$K,'Table 3-24'!$M:$M,'5. Industry Process'!D28)+SUMIFS('Table 3-24'!$K:$K,'Table 3-24'!$M:$M,'5. Industry Process'!B28)+SUMIFS('Table 3-24'!$K:$K,'Table 3-24'!$M:$M,'5. Industry Process'!C28) -> 316.02235 | L28: *EPA total would be 53 MMT higher with the inclusion of ethanol
D29: iron and steel 241 | E29: Process Emissions after CCS | F29: EPA Tables 3-1, 4-1, Table 5-1, Table 7-1 | I29: iron and steel | J29: =SUMIFS(EPS!$L:$L,EPS!$B:$B,E29,EPS!$C:$C,D29) -> #N/A | K29: =SUMIFS('Table 4-1'!$C:$C,'Table 4-1'!$E:$E,'5. Industry Process'!D29)+SUMIFS('Table 3-1'!$C:$C,'Table 3-1'!$E:$E,'5. Industry Process'!D29) -> 40.2
D30: chemicals 20 | E30: Process Emissions after CCS | F30: EPA Tables 3-1, 4-1, Table 5-1, Table 7-1 | I30: chemicals | J30: =SUMIFS(EPS!$L:$L,EPS!$B:$B,E30,EPS!$C:$C,D30) -> #N/A | K30: =SUMIFS('Table 4-1'!$C:$C,'Table 4-1'!$E:$E,'5. Industry Process'!D30)+SUMIFS('Table 3-1'!$C:$C,'Table 3-1'!$E:$E,'5. Industry Process'!D30)+SUMIFS('Table 3-24'!$K:$K,'Table 3-24'!$M:$M,'5. Industry Process'!D30) -> 328.8
D31: coal mining 05 | E31: Process Emissions after CCS | F31: EPA Tables 3-1, 4-1, Table 5-1, Table 7-1 | I31: coal mining | J31: =SUMIFS(EPS!$L:$L,EPS!$B:$B,E31,EPS!$C:$C,D31) -> #N/A | K31: =SUMIFS('Table 4-1'!$C:$C,'Table 4-1'!$E:$E,'5. Industry Process'!D31)+SUMIFS('Table 3-1'!$C:$C,'Table 3-1'!$E:$E,'5. Industry Process'!D31) -> 53.970029
D32: water and waste 36T39 | E32: Process Emissions after CCS | F32: EPA Tables 3-1, 4-1, Table 5-1, Table 7-1 | I32: waste management | J32: =SUMIFS(EPS!$L:$L,EPS!$B:$B,E32,EPS!$C:$C,D32) -> #N/A | K32: =SUMIFS('Table 4-1'!$C:$C,'Table 4-1'!$E:$E,'5. Industry Process'!D32)+SUMIFS('Table 3-1'!$C:$C,'Table 3-1'!$E:$E,'5. Industry Process'!D32)+'Table 7-1'!$C$12 -> 165.84952
D33: agriculture and forestry 01T03 | E33: Process Emissions after CCS | F33: EPA Tables 3-1, 4-1, Table 5-1, Table 7-1 | I33: agriculture | J33: =SUMIFS(EPS!$L:$L,EPS!$B:$B,E33,EPS!$C:$C,D33) -> #N/A | K33: ='Table 5-1'!C16 -> 595.39797
D34: other | E34: Process Emissions after CCS | F34: EPA Tables 3-1, 4-1, Table 5-1, Table 7-1 | I34: other industries | J34: =SUMIFS(EPS!$L:$L,EPS!$B:$B,E34)-SUM(J27:J33) -> #N/A | K34: =SUMIFS('Table 4-1'!$C:$C,'Table 4-1'!$E:$E,'5. Industry Process'!D34)+SUMIFS('Table 3-1'!$C:$C,'Table 3-1'!$E:$E,'5. Industry Process'!D34) -> 0
I35: Total process | J35: =SUM(J27:J34) -> #N/A | K35: =SUM(K27:K34) -> 1565.7399
G42: 5.4 | H42: Industry Process CH4 Emissions by Sector | J42: EPS 2021 | K42: EPA 2021
A43: CH4 | D43: cement and other nonmetallic minerals 239 | E43: Process Emissions before CCS | I43: cement and other carbonates | J43: =SUMIFS(EPS!L:L,EPS!D:D,A43,EPS!B:B,E43,EPS!C:C,D43) -> 0
A44: CH4 | B44: refined petroleum and coke 19 | C44: oil and gas extraction 06 | D44: energy pipelines and gas processing 352T353 | E44: Process Emissions before CCS | I44: natural gas and petroleum systems | J44: =SUM(SUMIFS(EPS!L:L,EPS!D:D,A44,EPS!B:B,E44,EPS!C:C,D44),SUMIFS(EPS!L:L,EPS!D:D,A44,EPS!B:B,E44,EPS!C:C,C44),SUMIFS(EPS!L:L,EPS!D:D,A44,EPS!B:B,E44,EPS!C:C,B44)) -> 0 | K44: =SUMIFS('Table 3-1'!C:C,'Table 3-1'!D:D,"process",'Table 3-1'!F:F,A44,'Table 3-1'!E:E,C44) -> 208.96919
A45: CH4 | D45: iron and steel 241 | E45: Process Emissions before CCS | I45: iron and steel | J45: =SUMIFS(EPS!L:L,EPS!D:D,A45,EPS!B:B,E45,EPS!C:C,D45) -> 0
A46: CH4 | D46: chemicals 20 | E46: Process Emissions before CCS | I46: chemicals | J46: =SUMIFS(EPS!L:L,EPS!D:D,A46,EPS!B:B,E46,EPS!C:C,D46) -> 0 | K46: ='Table 4-1'!C25 -> +
A47: CH4 | D47: coal mining 05 | E47: Process Emissions before CCS | I47: coal mining | J47: =SUMIFS(EPS!L:L,EPS!D:D,A47,EPS!B:B,E47,EPS!C:C,D47) -> 0 | K47: =SUMIFS('Table 3-1'!C:C,'Table 3-1'!D:D,"process",'Table 3-1'!F:F,A47,'Table 3-1'!E:E,D47) -> 51.56631
A48: CH4 | D48: water and waste 36T39 | E48: Process Emissions before CCS | I48: waste management | J48: =SUMIFS(EPS!L:L,EPS!D:D,A48,EPS!B:B,E48,EPS!C:C,D48) -> 0 | K48: ='Table 7-1'!C4 -> 143.20296
A49: CH4 | D49: agriculture and forestry 01T03 | E49: Process Emissions before CCS | I49: agriculture | J49: =SUMIFS(EPS!L:L,EPS!D:D,A49,EPS!B:B,E49,EPS!C:C,D49) -> 0 | K49: ='Table 5-1'!C7 -> 271.5682
A50: CH4 | D50: other | E50: Process Emissions before CCS | I50: other industries | J50: =SUMIFS(EPS!L:L,EPS!D:D,A50,EPS!B:B,E50)-SUM(J43:J49) -> 0
I51: Total process | J51: =SUM(J43:J50) -> 0 | K51: =SUM(K43:K50) -> 675.30666

Sheet 6. Total
G1: Total
G2: MMTCO2e
A5: EPS Sub 4 | B5: EPS Sub 3 | C5: EPS Sub 2 | D5: EPS Sub 1 | E5: EPS Variable | F5: EPA Table
G7: 6.1 | H7: Total Economy-wide Greenhouse Gas Emissions by Sector
J8: EPS 2021 | K8: EPA 2021 | L8: EIA 2021 | M8: EPA - EPS Difference
D9: transportation sector | E9: Output Total CO2e Emissions by Sector | I9: Transportation Sector | J9: ='1. Transportation'!K12 -> 1733.8957 | K9: =SUM('1. Transportation'!L9:L11) -> 1723.2452 | L9: ='1. Transportation'!M12 -> 1741.377 | M9: =K9-J9 -> -10.650468
D10: electricity sector | E10: Output Total CO2e Emissions by Sector | I10: Electricity Sector | J10: ='2. Electricity'!K12 -> 1611.746 | K10: =SUM('2. Electricity'!L9:L11) -> 1445.0188 | L10: ='2. Electricity'!M35 -> 1568.859 | M10: =K10-J10 -> -166.72721
D11: LULUCF sector | E11: Output Total CO2e Emissions by Sector | I11: LULUCF Sector | J11: =SUMIFS(EPS!$L:$L,EPS!$B:$B,'6. Total'!E11,EPS!$C:$C,'6. Total'!D11) -> #N/A | K11: ='Table 6-1'!C42 -> -939.9 | M11: =K11-J11 -> #N/A
D12: geoengineering sector | E12: Output Total CO2e Emissions by Sector | I12: Geoengineering sector | J12: =SUMIFS(EPS!$L:$L,EPS!$B:$B,'6. Total'!E12,EPS!$C:$C,'6. Total'!D12) -> #N/A | M12: =K12-J12 -> #N/A
E13: Process Emissions after CCS | I13: Industry Process | J13: =SUMIFS(EPS!$L:$L,EPS!$B:$B,'6. Total'!E13)-SUM(J15:J16) -> #N/A | K13: =SUM('5. Industry Process'!K9:K12)-K15-K16 -> 816.5083 | M13: =K13-J13 -> #N/A | N13: *discrepancy from ethanol
D14: industry sector | E14: Output Total CO2e Emissions by Sector | I14: Industry Energy | J14: ='3. Industry Energy'!M13 -> #N/A | K14: =SUM('3. Industry Energy'!N10:N12) -> 867.36615 | L14: ='3. Industry Energy'!O13 -> 975.411 | M14: =K14-J14 -> #N/A
D15: agriculture and forestry 01T03 | E15: Process Emissions after CCS | I15: Agriculture Process | J15: =SUMIFS(EPS!$L:$L,EPS!$B:$B,'6. Total'!E15,EPS!C:C,'6. Total'!D15) -> #N/A | K15: ='5. Industry Process'!K33 -> 595.39797 | M15: =K15-J15 -> #N/A
D16: water and waste 36T39 | E16: Process Emissions after CCS | I16: Waste Process | J16: =SUMIFS(EPS!$L:$L,EPS!$B:$B,'6. Total'!E16,EPS!C:C,'6. Total'!D16) -> #N/A | K16: ='5. Industry Process'!K32 -> 165.84952 | M16: =K16-J16 -> #N/A
E17: Output Buildings Sector CO2e Emissions | I17: Buildings | J17: ='4. Buildings'!L12+'4. Buildings'!L29 -> #N/A | K17: =SUM('4. Buildings'!M9:M11,'4. Buildings'!M26:M28) -> 557.98497 | L17: =SUM('4. Buildings'!N12,'4. Buildings'!N29) -> 570.164 | M17: =K17-J17 -> #N/A
E18: Output Total CO2e Emissions by Sector[district heat and hydrogen sector] | I18: District Heat and Hydrogen | J18: =INDEX(NoSettings!C:C,MATCH(E18,NoSettings!A:A,0)) -> #N/A | M18: =K18-J18 -> #N/A
J19: =SUM(J13,J14,J15,J16,J9,J10,J17,J18,J11) -> #N/A | K19: =SUM(K9:K17) -> 5231.4709 | L19: =SUM(L9:L17) -> 4855.811 | M19: =K19-J19 -> #N/A
J20: *we should be ~53 MMT higher from
J21: ethanol refining
J23: **the EPA column does not include emissions from US terriroties,
J24: since those are not apportioned by sector in the Inventory
G33: 6.2 | H33: Total CH4 Emissions
J34: EPS 2021 | K34: EPA 2021
I35: Transportation Sector | J35: ='1. Transportation'!K10 -> 2.0116845 | K35: ='1. Transportation'!L10 -> 2.5398312
I36: Electricity Sector | J36: ='2. Electricity'!K10 -> 1.8685541 | K36: ='2. Electricity'!L10 -> 1.5057991
I37: District Heat Sector
C38: CH4 | D38: LULUCF sector | E38: Total Pollutant Emissions by Sector | I38: LULUCF Sector | J38: =SUMIFS(EPS!L:L,EPS!B:B,E38,EPS!C:C,D38,EPS!D:D,C38) -> #N/A | K38: ='Table 6-1'!C40 -> 5.9
I39: Geoengineering sector
I40: Industry Process | J40: ='5. Industry Process'!J10 -> #N/A | K40: ='5. Industry Process'!K10 -> 675.30666
I41: Industry Energy | J41: ='3. Industry Energy'!M11 -> #N/A | K41: ='3. Industry Energy'!N11 -> 1.4973585
I42: Agriculture
I43: Waste
I44: Buildings
J45: =SUM(J35:J44) -> #N/A | K45: =SUM(K35:K44) -> 686.74964
K46: =K45-J45 -> #N/A
G47: 6.3 | H47: Total N2O
J48: EPS 2021 | K48: EPA 2021
I49: Transportation Sector | J49: ='1. Transportation'!K11 -> 11.32663 | K49: ='1. Transportation'!L11 -> 16.183964
I50: Electricity Sector | J50: ='2. Electricity'!K11 -> 17.593559 | K50: ='2. Electricity'!L11 -> 16.910483
I51: District Heat Sector
C52: N2O | D52: LULUCF sector | E52: Total Pollutant Emissions by Sector | I52: LULUCF Sector | J52: =SUMIFS(EPS!L:L,EPS!B:B,E52,EPS!C:C,D52,EPS!D:D,C52) -> #N/A | K52: ='Table 6-1'!C41 -> -1000.5
I53: Geoengineering sector
I54: Industry Process | J54: ='5. Industry Process'!J11 -> #N/A | K54: ='5. Industry Process'!K11 -> 355.64667
I55: Industry Energy | J55: ='3. Industry Energy'!M12 -> #N/A | K55: ='3. Industry Energy'!N12 -> 1.9174828
I56: Agriculture
I57: Waste
I58: Buildings
J59: =SUM(J49:J58) -> #N/A | K59: =SUM(K49:K58) -> -609.8414

Sheet 7. Particulates
G1: Total Pollutant Emissions by Sector
G2: metric tons pollutant
A6: EPS Sub 4 | B6: EPS Sub 3 | C6: EPS Sub 2 | D6: EPS Sub 1 | E6: EPS Variable | F6: EPA Table
G8: 7.1
J9: EPS 2021 | K9: EPA 2020
C10: NOx | D10: transportation sector | E10: Total Pollutant Emissions by Sector | I10: Transportation Sector | J10: =SUMIFS(EPS!$J:$J,EPS!$D:$D,'7. Particulates'!C10,EPS!$C:$C,'7. Particulates'!D10,EPS!$B:$B,'7. Particulates'!E10)/10^6 -> #N/A | K10: =SUMIFS('2020 EPA Data'!$D:$D,'2020 EPA Data'!$G:$G,C10,'2020 EPA Data'!$F:$F,I10)/metricton_to_shortton -> 2840387
C11: NOx | D11: electricity sector | E11: Total Pollutant Emissions by Sector | I11: Electricity Sector | J11: =SUMIFS(EPS!$J:$J,EPS!$D:$D,'7. Particulates'!C11,EPS!$C:$C,'7. Particulates'!D11,EPS!$B:$B,'7. Particulates'!E11)/10^6 -> #N/A | K11: =SUMIFS('2020 EPA Data'!$D:$D,'2020 EPA Data'!$G:$G,C11,'2020 EPA Data'!$F:$F,I11)/metricton_to_shortton -> 762145.86
C12: NOx | D12: residential buildings sector | E12: Total Pollutant Emissions by Sector | I12: Residential Buildings Sector | J12: =SUMIFS(EPS!$J:$J,EPS!$D:$D,'7. Particulates'!C12,EPS!$C:$C,'7. Particulates'!D12,EPS!$B:$B,'7. Particulates'!E12)/10^6 -> #N/A | K12: =SUMIFS('2020 EPA Data'!$D:$D,'2020 EPA Data'!$G:$G,C12,'2020 EPA Data'!$F:$F,I12)/metricton_to_shortton -> 299876.62
C13: NOx | D13: commercial buildings sector | E13: Total Pollutant Emissions by Sector | I13: Commercial Buildings Sector | J13: =SUMIFS(EPS!$J:$J,EPS!$D:$D,'7. Particulates'!C13,EPS!$C:$C,'7. Particulates'!D13,EPS!$B:$B,'7. Particulates'!E13)/10^6 -> #N/A | K13: =SUMIFS('2020 EPA Data'!$D:$D,'2020 EPA Data'!$G:$G,C13,'2020 EPA Data'!$F:$F,I13)/metricton_to_shortton -> 192228.14
C14: NOx | D14: industry sector | E14: Total Pollutant Emissions by Sector | I14: Industry | J14: =SUMIFS(EPS!$J:$J,EPS!$D:$D,'7. Particulates'!C14,EPS!$C:$C,'7. Particulates'!D14,EPS!$B:$B,'7. Particulates'!E14)/10^6 -> #N/A | K14: =SUMIFS('2020 EPA Data'!$D:$D,'2020 EPA Data'!$G:$G,C14,'2020 EPA Data'!$F:$F,"*"&I14&"*")/metricton_to_shortton -> 1875963.2
C15: NOx | I15: Nonroad | J15: =SUMIFS(EPS!$J:$J,EPS!$D:$D,'7. Particulates'!C15,EPS!$C:$C,'7. Particulates'!D15,EPS!$B:$B,'7. Particulates'!E15)/10^6 -> 0 | K15: =SUMIFS('2020 EPA Data'!$D:$D,'2020 EPA Data'!$G:$G,C15,'2020 EPA Data'!$F:$F,I15)/metricton_to_shortton*INDEX(GWP!$C$2:$C$13,MATCH(C15,GWP!$B$2:$B$13,0)) -> 0
C16: NOx | D16: district heat and hydrogen sector | E16: Total Pollutant Emissions by Sector | I16: District Heat Sector | J16: =SUMIFS(EPS!$J:$J,EPS!$D:$D,'7. Particulates'!C16,EPS!$C:$C,'7. Particulates'!D16,EPS!$B:$B,'7. Particulates'!E16)/10^6 -> #N/A | K16: =SUMIFS('2020 EPA Data'!$D:$D,'2020 EPA Data'!$G:$G,C16,'2020 EPA Data'!$F:$F,I16)/metricton_to_shortton*INDEX(GWP!$C$2:$C$13,MATCH(C16,GWP!$B$2:$B$13,0)) -> 0
C17: NOx | D17: LULUCF sector | E17: Total Pollutant Emissions by Sector | I17: LULUCF Sector | J17: =SUMIFS(EPS!$J:$J,EPS!$D:$D,'7. Particulates'!C17,EPS!$C:$C,'7. Particulates'!D17,EPS!$B:$B,'7. Particulates'!E17)/10^6 -> #N/A | K17: =SUMIFS('2020 EPA Data'!$D:$D,'2020 EPA Data'!$G:$G,C17,'2020 EPA Data'!$F:$F,I17)/metricton_to_shortton*INDEX(GWP!$C$2:$C$13,MATCH(C17,GWP!$B$2:$B$13,0)) -> 0
C18: NOx | D18: geoengineering sector | E18: Total Pollutant Emissions by Sector | I18: Geoengineering Sector | J18: =SUMIFS(EPS!$J:$J,EPS!$D:$D,'7. Particulates'!C18,EPS!$C:$C,'7. Particulates'!D18,EPS!$B:$B,'7. Particulates'!E18)/10^6 -> #N/A | K18: =SUMIFS('2020 EPA Data'!$D:$D,'2020 EPA Data'!$G:$G,C18,'2020 EPA Data'!$F:$F,I18)/metricton_to_shortton*INDEX(GWP!$C$2:$C$13,MATCH(C18,GWP!$B$2:$B$13,0)) -> 0
C19: NOx | I19: Other-EPA | J19: =SUMIFS(EPS!$J:$J,EPS!$D:$D,'7. Particulates'!C19,EPS!$C:$C,'7. Particulates'!D19,EPS!$B:$B,'7. Particulates'!E19)/10^6 -> 0 | K19: =SUMIFS('2020 EPA Data'!$D:$D,'2020 EPA Data'!$G:$G,C19,'2020 EPA Data'!$F:$F,I19)/metricton_to_shortton -> 2116542.5
I20: Total | J20: =SUM(J10:J19) -> #N/A | K20: =SUM(K10:K16) -> 5970600.8
G29: 7.2
J30: EPS 2021 | K30: EPA 2020
C31: SOx | D31: transportation sector | E31: Total Pollutant Emissions by Sector | I31: Transportation Sector | J31: =SUMIFS(EPS!$J:$J,EPS!$D:$D,'7. Particulates'!C31,EPS!$C:$C,'7. Particulates'!D31,EPS!$B:$B,'7. Particulates'!E31)/10^6 -> #N/A | K31: =SUMIFS('2020 EPA Data'!$D:$D,'2020 EPA Data'!$G:$G,C31,'2020 EPA Data'!$F:$F,I31)/metricton_to_shortton -> 20906.097
C32: SOx | D32: electricity sector | E32: Total Pollutant Emissions by Sector | I32: Electricity Sector | J32: =SUMIFS(EPS!$J:$J,EPS!$D:$D,'7. Particulates'!C32,EPS!$C:$C,'7. Particulates'!D32,EPS!$B:$B,'7. Particulates'!E32)/10^6 -> #N/A | K32: =SUMIFS('2020 EPA Data'!$D:$D,'2020 EPA Data'!$G:$G,C32,'2020 EPA Data'!$F:$F,I32)/metricton_to_shortton -> 758009.09
C33: SOx | D33: residential buildings sector | E33: Total Pollutant Emissions by Sector | I33: Residential Buildings Sector | J33: =SUMIFS(EPS!$J:$J,EPS!$D:$D,'7. Particulates'!C33,EPS!$C:$C,'7. Particulates'!D33,EPS!$B:$B,'7. Particulates'!E33)/10^6 -> #N/A | K33: =SUMIFS('2020 EPA Data'!$D:$D,'2020 EPA Data'!$G:$G,C33,'2020 EPA Data'!$F:$F,I33)/metricton_to_shortton -> 13103.392
C34: SOx | D34: commercial buildings sector | E34: Total Pollutant Emissions by Sector | I34: Commercial Buildings Sector | J34: =SUMIFS(EPS!$J:$J,EPS!$D:$D,'7. Particulates'!C34,EPS!$C:$C,'7. Particulates'!D34,EPS!$B:$B,'7. Particulates'!E34)/10^6 -> #N/A | K34: =SUMIFS('2020 EPA Data'!$D:$D,'2020 EPA Data'!$G:$G,C34,'2020 EPA Data'!$F:$F,I34)/metricton_to_shortton -> 12396.694
C35: SOx | D35: industry sector | E35: Total Pollutant Emissions by Sector | I35: Industry | J35: =SUMIFS(EPS!$J:$J,EPS!$D:$D,'7. Particulates'!C35,EPS!$C:$C,'7. Particulates'!D35,EPS!$B:$B,'7. Particulates'!E35)/10^6 -> #N/A | K35: =SUMIFS('2020 EPA Data'!$D:$D,'2020 EPA Data'!$G:$G,C35,'2020 EPA Data'!$F:$F,"*"&I35&"*")/metricton_to_shortton -> 663082.98
C36: SOx | I36: Nonroad | J36: =SUMIFS(EPS!$J:$J,EPS!$D:$D,'7. Particulates'!C36,EPS!$C:$C,'7. Particulates'!D36,EPS!$B:$B,'7. Particulates'!E36)/10^6 -> 0 | K36: =SUMIFS('2020 EPA Data'!$D:$D,'2020 EPA Data'!$G:$G,C36,'2020 EPA Data'!$F:$F,I36)/metricton_to_shortton*INDEX(GWP!$C$2:$C$13,MATCH(C36,GWP!$B$2:$B$13,0)) -> 0
C37: SOx | D37: district heat and hydrogen sector | E37: Total Pollutant Emissions by Sector | I37: District Heat Sector | J37: =SUMIFS(EPS!$J:$J,EPS!$D:$D,'7. Particulates'!C37,EPS!$C:$C,'7. Particulates'!D37,EPS!$B:$B,'7. Particulates'!E37)/10^6 -> #N/A | K37: =SUMIFS('2020 EPA Data'!$D:$D,'2020 EPA Data'!$G:$G,C37,'2020 EPA Data'!$F:$F,I37)/metricton_to_shortton*INDEX(GWP!$C$2:$C$13,MATCH(C37,GWP!$B$2:$B$13,0)) -> 0
C38: SOx | D38: LULUCF sector | E38: Total Pollutant Emissions by Sector | I38: LULUCF Sector | J38: =SUMIFS(EPS!$J:$J,EPS!$D:$D,'7. Particulates'!C38,EPS!$C:$C,'7. Particulates'!D38,EPS!$B:$B,'7. Particulates'!E38)/10^6 -> #N/A | K38: =SUMIFS('2020 EPA Data'!$D:$D,'2020 EPA Data'!$G:$G,C38,'2020 EPA Data'!$F:$F,I38)/metricton_to_shortton*INDEX(GWP!$C$2:$C$13,MATCH(C38,GWP!$B$2:$B$13,0)) -> 0
C39: SOx | D39: geoengineering sector | E39: Total Pollutant Emissions by Sector | I39: Geoengineering Sector | J39: =SUMIFS(EPS!$J:$J,EPS!$D:$D,'7. Particulates'!C39,EPS!$C:$C,'7. Particulates'!D39,EPS!$B:$B,'7. Particulates'!E39)/10^6 -> #N/A | K39: =SUMIFS('2020 EPA Data'!$D:$D,'2020 EPA Data'!$G:$G,C39,'2020 EPA Data'!$F:$F,I39)/metricton_to_shortton*INDEX(GWP!$C$2:$C$13,MATCH(C39,GWP!$B$2:$B$13,0)) -> 0
C40: SOx | I40: Other-EPA | J40: =SUMIFS(EPS!$J:$J,EPS!$D:$D,'7. Particulates'!C40,EPS!$C:$C,'7. Particulates'!D40,EPS!$B:$B,'7. Particulates'!E40)/10^6 -> 0 | K40: =SUMIFS('2020 EPA Data'!$D:$D,'2020 EPA Data'!$G:$G,C40,'2020 EPA Data'!$F:$F,I40)/metricton_to_shortton -> 202975.57
I41: Total | J41: =SUM(J31:J40) -> #N/A | K41: =SUM(K31:K40) -> 1670473.8
G50: 7.3
J51: EPS 2021 | K51: EPA 2020
C52: PM25 | D52: transportation sector | E52: Total Pollutant Emissions by Sector | I52: Transportation Sector | J52: =SUMIFS(EPS!$J:$J,EPS!$D:$D,'7. Particulates'!C52,EPS!$C:$C,'7. Particulates'!D52,EPS!$B:$B,'7. Particulates'!E52)/10^6 -> #N/A | K52: =SUMIFS('2020 EPA Data'!$D:$D,'2020 EPA Data'!$G:$G,C52,'2020 EPA Data'!$F:$F,I52)/metricton_to_shortton -> 93376.636
C53: PM25 | D53: electricity sector | E53: Total Pollutant Emissions by Sector | I53: Electricity Sector | J53: =SUMIFS(EPS!$J:$J,EPS!$D:$D,'7. Particulates'!C53,EPS!$C:$C,'7. Particulates'!D53,EPS!$B:$B,'7. Particulates'!E53)/10^6 -> #N/A | K53: =SUMIFS('2020 EPA Data'!$D:$D,'2020 EPA Data'!$G:$G,C53,'2020 EPA Data'!$F:$F,I53)/metricton_to_shortton -> 77467.319
C54: PM25 | D54: residential buildings sector | E54: Total Pollutant Emissions by Sector | I54: Residential Buildings Sector | J54: =SUMIFS(EPS!$J:$J,EPS!$D:$D,'7. Particulates'!C54,EPS!$C:$C,'7. Particulates'!D54,EPS!$B:$B,'7. Particulates'!E54)/10^6 -> #N/A | K54: =SUMIFS('2020 EPA Data'!$D:$D,'2020 EPA Data'!$G:$G,C54,'2020 EPA Data'!$F:$F,I54)/metricton_to_shortton -> 445198.72
C55: PM25 | D55: commercial buildings sector | E55: Total Pollutant Emissions by Sector | I55: Commercial Buildings Sector | J55: =SUMIFS(EPS!$J:$J,EPS!$D:$D,'7. Particulates'!C55,EPS!$C:$C,'7. Particulates'!D55,EPS!$B:$B,'7. Particulates'!E55)/10^6 -> #N/A | K55: =SUMIFS('2020 EPA Data'!$D:$D,'2020 EPA Data'!$G:$G,C55,'2020 EPA Data'!$F:$F,I55)/metricton_to_shortton -> 191830.79
C56: PM25 | D56: industry sector | E56: Total Pollutant Emissions by Sector | I56: Industry | J56: =SUMIFS(EPS!$J:$J,EPS!$D:$D,'7. Particulates'!C56,EPS!$C:$C,'7. Particulates'!D56,EPS!$B:$B,'7. Particulates'!E56)/10^6 -> #N/A | K56: =SUMIFS('2020 EPA Data'!$D:$D,'2020 EPA Data'!$G:$G,C56,'2020 EPA Data'!$F:$F,"*"&I56&"*")/metricton_to_shortton -> 654635.27
C57: PM25 | I57: Nonroad | J57: =SUMIFS(EPS!$J:$J,EPS!$D:$D,'7. Particulates'!C57,EPS!$C:$C,'7. Particulates'!D57,EPS!$B:$B,'7. Particulates'!E57)/10^6 -> 0 | K57: =SUMIFS('2020 EPA Data'!$D:$D,'2020 EPA Data'!$G:$G,C57,'2020 EPA Data'!$F:$F,I57)/metricton_to_shortton*INDEX(GWP!$C$2:$C$13,MATCH(C57,GWP!$B$2:$B$13,0)) -> 0
C58: PM25 | D58: district heat and hydrogen sector | E58: Total Pollutant Emissions by Sector | I58: District Heat Sector | J58: =SUMIFS(EPS!$J:$J,EPS!$D:$D,'7. Particulates'!C58,EPS!$C:$C,'7. Particulates'!D58,EPS!$B:$B,'7. Particulates'!E58)/10^6 -> #N/A | K58: =SUMIFS('2020 EPA Data'!$D:$D,'2020 EPA Data'!$G:$G,C58,'2020 EPA Data'!$F:$F,I58)/metricton_to_shortton*INDEX(GWP!$C$2:$C$13,MATCH(C58,GWP!$B$2:$B$13,0)) -> 0
C59: PM25 | D59: LULUCF sector | E59: Total Pollutant Emissions by Sector | I59: LULUCF Sector | J59: =SUMIFS(EPS!$J:$J,EPS!$D:$D,'7. Particulates'!C59,EPS!$C:$C,'7. Particulates'!D59,EPS!$B:$B,'7. Particulates'!E59)/10^6 -> #N/A | K59: =SUMIFS('2020 EPA Data'!$D:$D,'2020 EPA Data'!$G:$G,C59,'2020 EPA Data'!$F:$F,I59)/metricton_to_shortton*INDEX(GWP!$C$2:$C$13,MATCH(C59,GWP!$B$2:$B$13,0)) -> 0
C60: PM25 | D60: geoengineering sector | E60: Total Pollutant Emissions by Sector | I60: Geoengineering Sector | J60: =SUMIFS(EPS!$J:$J,EPS!$D:$D,'7. Particulates'!C60,EPS!$C:$C,'7. Particulates'!D60,EPS!$B:$B,'7. Particulates'!E60)/10^6 -> #N/A | K60: =SUMIFS('2020 EPA Data'!$D:$D,'2020 EPA Data'!$G:$G,C60,'2020 EPA Data'!$F:$F,I60)/metricton_to_shortton*INDEX(GWP!$C$2:$C$13,MATCH(C60,GWP!$B$2:$B$13,0)) -> 0
C61: PM25 | I61: Other-EPA | J61: =SUMIFS(EPS!$J:$J,EPS!$D:$D,'7. Particulates'!C61,EPS!$C:$C,'7. Particulates'!D61,EPS!$B:$B,'7. Particulates'!E61)/10^6 -> 0 | K61: =SUMIFS('2020 EPA Data'!$D:$D,'2020 EPA Data'!$G:$G,C61,'2020 EPA Data'!$F:$F,I61)/metricton_to_shortton -> 3818253.5
I62: Total | J62: =SUM(J52:J61) -> #N/A | K62: =SUM(K52:K61) -> 5280762.2
G69: 7.4
J70: EPS 2021 | K70: EPA 2020
C71: BC | D71: transportation sector | E71: Total Pollutant Emissions by Sector | I71: Transportation Sector | J71: =SUMIFS(EPS!$J:$J,EPS!$D:$D,'7. Particulates'!C71,EPS!$C:$C,'7. Particulates'!D71,EPS!$B:$B,'7. Particulates'!E71)/10^6 -> #N/A | K71: =SUMIFS('2020 EPA Data'!$D:$D,'2020 EPA Data'!$G:$G,C71,'2020 EPA Data'!$F:$F,I71)/metricton_to_shortton -> 43692.791
C72: BC | D72: electricity sector | E72: Total Pollutant Emissions by Sector | I72: Electricity Sector | J72: =SUMIFS(EPS!$J:$J,EPS!$D:$D,'7. Particulates'!C72,EPS!$C:$C,'7. Particulates'!D72,EPS!$B:$B,'7. Particulates'!E72)/10^6 -> #N/A | K72: =SUMIFS('2020 EPA Data'!$D:$D,'2020 EPA Data'!$G:$G,C72,'2020 EPA Data'!$F:$F,I72)/metricton_to_shortton -> 4659.3064
C73: BC | D73: residential buildings sector | E73: Total Pollutant Emissions by Sector | I73: Residential Buildings Sector | J73: =SUMIFS(EPS!$J:$J,EPS!$D:$D,'7. Particulates'!C73,EPS!$C:$C,'7. Particulates'!D73,EPS!$B:$B,'7. Particulates'!E73)/10^6 -> #N/A | K73: =SUMIFS('2020 EPA Data'!$D:$D,'2020 EPA Data'!$G:$G,C73,'2020 EPA Data'!$F:$F,I73)/metricton_to_shortton -> 24924.023
C74: BC | D74: commercial buildings sector | E74: Total Pollutant Emissions by Sector | I74: Commercial Buildings Sector | J74: =SUMIFS(EPS!$J:$J,EPS!$D:$D,'7. Particulates'!C74,EPS!$C:$C,'7. Particulates'!D74,EPS!$B:$B,'7. Particulates'!E74)/10^6 -> #N/A | K74: =SUMIFS('2020 EPA Data'!$D:$D,'2020 EPA Data'!$G:$G,C74,'2020 EPA Data'!$F:$F,I74)/metricton_to_shortton -> 6658.7439
C75: BC | D75: industry sector | E75: Total Pollutant Emissions by Sector | I75: Industry | J75: =SUMIFS(EPS!$J:$J,EPS!$D:$D,'7. Particulates'!C75,EPS!$C:$C,'7. Particulates'!D75,EPS!$B:$B,'7. Particulates'!E75)/10^6 -> #N/A | K75: =SUMIFS('2020 EPA Data'!$D:$D,'2020 EPA Data'!$G:$G,C75,'2020 EPA Data'!$F:$F,"*"&I75&"*")/metricton_to_shortton -> 35762.172
C76: BC | I76: Nonroad | J76: =SUMIFS(EPS!$J:$J,EPS!$D:$D,'7. Particulates'!C76,EPS!$C:$C,'7. Particulates'!D76,EPS!$B:$B,'7. Particulates'!E76)/10^6 -> 0 | K76: =SUMIFS('2020 EPA Data'!$D:$D,'2020 EPA Data'!$G:$G,C76,'2020 EPA Data'!$F:$F,I76)/metricton_to_shortton*INDEX(GWP!$C$2:$C$13,MATCH(C76,GWP!$B$2:$B$13,0)) -> 0
C77: BC | D77: district heat and hydrogen sector | E77: Total Pollutant Emissions by Sector | I77: District Heat Sector | J77: =SUMIFS(EPS!$J:$J,EPS!$D:$D,'7. Particulates'!C77,EPS!$C:$C,'7. Particulates'!D77,EPS!$B:$B,'7. Particulates'!E77)/10^6 -> #N/A | K77: =SUMIFS('2020 EPA Data'!$D:$D,'2020 EPA Data'!$G:$G,C77,'2020 EPA Data'!$F:$F,I77)/metricton_to_shortton*INDEX(GWP!$C$2:$C$13,MATCH(C77,GWP!$B$2:$B$13,0)) -> 0
C78: BC | D78: LULUCF sector | E78: Total Pollutant Emissions by Sector | I78: LULUCF Sector | J78: =SUMIFS(EPS!$J:$J,EPS!$D:$D,'7. Particulates'!C78,EPS!$C:$C,'7. Particulates'!D78,EPS!$B:$B,'7. Particulates'!E78)/10^6 -> #N/A | K78: =SUMIFS('2020 EPA Data'!$D:$D,'2020 EPA Data'!$G:$G,C78,'2020 EPA Data'!$F:$F,I78)/metricton_to_shortton*INDEX(GWP!$C$2:$C$13,MATCH(C78,GWP!$B$2:$B$13,0)) -> 0
C79: BC | D79: geoengineering sector | E79: Total Pollutant Emissions by Sector | I79: Geoengineering Sector | J79: =SUMIFS(EPS!$J:$J,EPS!$D:$D,'7. Particulates'!C79,EPS!$C:$C,'7. Particulates'!D79,EPS!$B:$B,'7. Particulates'!E79)/10^6 -> #N/A | K79: =SUMIFS('2020 EPA Data'!$D:$D,'2020 EPA Data'!$G:$G,C79,'2020 EPA Data'!$F:$F,I79)/metricton_to_shortton*INDEX(GWP!$C$2:$C$13,MATCH(C79,GWP!$B$2:$B$13,0)) -> 0
C80: BC | I80: Other-EPA | J80: =SUMIFS(EPS!$J:$J,EPS!$D:$D,'7. Particulates'!C80,EPS!$C:$C,'7. Particulates'!D80,EPS!$B:$B,'7. Particulates'!E80)/10^6 -> 0 | K80: =SUMIFS('2020 EPA Data'!$D:$D,'2020 EPA Data'!$G:$G,C80,'2020 EPA Data'!$F:$F,I80)/metricton_to_shortton -> 223569.59
I81: Total | J81: =SUM(J71:J80) -> #N/A | K81: =SUM(K71:K80) -> 339266.63
G84: 7.5
J85: EPS 2021 | K85: EPA 2020
C86: OC | D86: transportation sector | E86: Total Pollutant Emissions by Sector | I86: Transportation Sector | J86: =SUMIFS(EPS!$J:$J,EPS!$D:$D,'7. Particulates'!C86,EPS!$C:$C,'7. Particulates'!D86,EPS!$B:$B,'7. Particulates'!E86)/10^6 -> #N/A | K86: =SUMIFS('2020 EPA Data'!$D:$D,'2020 EPA Data'!$G:$G,C86,'2020 EPA Data'!$F:$F,I86)/metricton_to_shortton -> 23322.84
C87: OC | D87: electricity sector | E87: Total Pollutant Emissions by Sector | I87: Electricity Sector | J87: =SUMIFS(EPS!$J:$J,EPS!$D:$D,'7. Particulates'!C87,EPS!$C:$C,'7. Particulates'!D87,EPS!$B:$B,'7. Particulates'!E87)/10^6 -> #N/A | K87: =SUMIFS('2020 EPA Data'!$D:$D,'2020 EPA Data'!$G:$G,C87,'2020 EPA Data'!$F:$F,I87)/metricton_to_shortton -> 16215.947
C88: OC | D88: residential buildings sector | E88: Total Pollutant Emissions by Sector | I88: Residential Buildings Sector | J88: =SUMIFS(EPS!$J:$J,EPS!$D:$D,'7. Particulates'!C88,EPS!$C:$C,'7. Particulates'!D88,EPS!$B:$B,'7. Particulates'!E88)/10^6 -> #N/A | K88: =SUMIFS('2020 EPA Data'!$D:$D,'2020 EPA Data'!$G:$G,C88,'2020 EPA Data'!$F:$F,I88)/metricton_to_shortton -> 234162.8
C89: OC | D89: commercial buildings sector | E89: Total Pollutant Emissions by Sector | I89: Commercial Buildings Sector | J89: =SUMIFS(EPS!$J:$J,EPS!$D:$D,'7. Particulates'!C89,EPS!$C:$C,'7. Particulates'!D89,EPS!$B:$B,'7. Particulates'!E89)/10^6 -> #N/A | K89: =SUMIFS('2020 EPA Data'!$D:$D,'2020 EPA Data'!$G:$G,C89,'2020 EPA Data'!$F:$F,I89)/metricton_to_shortton -> 119025.5
C90: OC | D90: industry sector | E90: Total Pollutant Emissions by Sector | I90: Industry | J90: =SUMIFS(EPS!$J:$J,EPS!$D:$D,'7. Particulates'!C90,EPS!$C:$C,'7. Particulates'!D90,EPS!$B:$B,'7. Particulates'!E90)/10^6 -> #N/A | K90: =SUMIFS('2020 EPA Data'!$D:$D,'2020 EPA Data'!$G:$G,C90,'2020 EPA Data'!$F:$F,"*"&I90&"*")/metricton_to_shortton -> 185456
C91: OC | I91: Nonroad | J91: =SUMIFS(EPS!$J:$J,EPS!$D:$D,'7. Particulates'!C91,EPS!$C:$C,'7. Particulates'!D91,EPS!$B:$B,'7. Particulates'!E91)/10^6 -> 0 | K91: =SUMIFS('2020 EPA Data'!$D:$D,'2020 EPA Data'!$G:$G,C91,'2020 EPA Data'!$F:$F,I91)/metricton_to_shortton*INDEX(GWP!$C$2:$C$13,MATCH(C91,GWP!$B$2:$B$13,0)) -> 0
C92: OC | D92: district heat and hydrogen sector | E92: Total Pollutant Emissions by Sector | I92: District Heat Sector | J92: =SUMIFS(EPS!$J:$J,EPS!$D:$D,'7. Particulates'!C92,EPS!$C:$C,'7. Particulates'!D92,EPS!$B:$B,'7. Particulates'!E92)/10^6 -> #N/A | K92: =SUMIFS('2020 EPA Data'!$D:$D,'2020 EPA Data'!$G:$G,C92,'2020 EPA Data'!$F:$F,I92)/metricton_to_shortton*INDEX(GWP!$C$2:$C$13,MATCH(C92,GWP!$B$2:$B$13,0)) -> 0
C93: OC | D93: LULUCF sector | E93: Total Pollutant Emissions by Sector | I93: LULUCF Sector | J93: =SUMIFS(EPS!$J:$J,EPS!$D:$D,'7. Particulates'!C93,EPS!$C:$C,'7. Particulates'!D93,EPS!$B:$B,'7. Particulates'!E93)/10^6 -> #N/A | K93: =SUMIFS('2020 EPA Data'!$D:$D,'2020 EPA Data'!$G:$G,C93,'2020 EPA Data'!$F:$F,I93)/metricton_to_shortton*INDEX(GWP!$C$2:$C$13,MATCH(C93,GWP!$B$2:$B$13,0)) -> 0
C94: OC | D94: geoengineering sector | E94: Total Pollutant Emissions by Sector | I94: Geoengineering Sector | J94: =SUMIFS(EPS!$J:$J,EPS!$D:$D,'7. Particulates'!C94,EPS!$C:$C,'7. Particulates'!D94,EPS!$B:$B,'7. Particulates'!E94)/10^6 -> #N/A | K94: =SUMIFS('2020 EPA Data'!$D:$D,'2020 EPA Data'!$G:$G,C94,'2020 EPA Data'!$F:$F,I94)/metricton_to_shortton*INDEX(GWP!$C$2:$C$13,MATCH(C94,GWP!$B$2:$B$13,0)) -> 0
C95: OC | I95: Other-EPA | J95: =SUMIFS(EPS!$J:$J,EPS!$D:$D,'7. Particulates'!C95,EPS!$C:$C,'7. Particulates'!D95,EPS!$B:$B,'7. Particulates'!E95)/10^6 -> 0 | K95: =SUMIFS('2020 EPA Data'!$D:$D,'2020 EPA Data'!$G:$G,C95,'2020 EPA Data'!$F:$F,I95)/metricton_to_shortton -> 1329276.7
I96: Total | J96: =SUM(J86:J95) -> #N/A | K96: =SUM(K86:K95) -> 1907459.8
G100: 7.6
J101: EPS 2021 | K101: EPA 2020
C102: VOC | D102: transportation sector | E102: Total Pollutant Emissions by Sector | I102: Transportation Sector | J102: =SUMIFS(EPS!$J:$J,EPS!$D:$D,'7. Particulates'!C102,EPS!$C:$C,'7. Particulates'!D102,EPS!$B:$B,'7. Particulates'!E102)/10^6 -> #N/A | K102: =SUMIFS('2020 EPA Data'!$D:$D,'2020 EPA Data'!$G:$G,C102,'2020 EPA Data'!$F:$F,I102)/metricton_to_shortton -> 939634.95
C103: VOC | D103: electricity sector | E103: Total Pollutant Emissions by Sector | I103: Electricity Sector | J103: =SUMIFS(EPS!$J:$J,EPS!$D:$D,'7. Particulates'!C103,EPS!$C:$C,'7. Particulates'!D103,EPS!$B:$B,'7. Particulates'!E103)/10^6 -> #N/A | K103: =SUMIFS('2020 EPA Data'!$D:$D,'2020 EPA Data'!$G:$G,C103,'2020 EPA Data'!$F:$F,I103)/metricton_to_shortton -> 25915.577
C104: VOC | D104: residential buildings sector | E104: Total Pollutant Emissions by Sector | I104: Residential Buildings Sector | J104: =SUMIFS(EPS!$J:$J,EPS!$D:$D,'7. Particulates'!C104,EPS!$C:$C,'7. Particulates'!D104,EPS!$B:$B,'7. Particulates'!E104)/10^6 -> #N/A | K104: =SUMIFS('2020 EPA Data'!$D:$D,'2020 EPA Data'!$G:$G,C104,'2020 EPA Data'!$F:$F,I104)/metricton_to_shortton -> 430545.85
C105: VOC | D105: commercial buildings sector | E105: Total Pollutant Emissions by Sector | I105: Commercial Buildings Sector | J105: =SUMIFS(EPS!$J:$J,EPS!$D:$D,'7. Particulates'!C105,EPS!$C:$C,'7. Particulates'!D105,EPS!$B:$B,'7. Particulates'!E105)/10^6 -> #N/A | K105: =SUMIFS('2020 EPA Data'!$D:$D,'2020 EPA Data'!$G:$G,C105,'2020 EPA Data'!$F:$F,I105)/metricton_to_shortton -> 40084.913
C106: VOC | D106: industry sector | E106: Total Pollutant Emissions by Sector | I106: Industry | J106: =SUMIFS(EPS!$J:$J,EPS!$D:$D,'7. Particulates'!C106,EPS!$C:$C,'7. Particulates'!D106,EPS!$B:$B,'7. Particulates'!E106)/10^6 -> #N/A | K106: =SUMIFS('2020 EPA Data'!$D:$D,'2020 EPA Data'!$G:$G,C106,'2020 EPA Data'!$F:$F,"*"&I106&"*")/metricton_to_shortton -> 4341385.8
C107: VOC | I107: Nonroad | J107: =SUMIFS(EPS!$J:$J,EPS!$D:$D,'7. Particulates'!C107,EPS!$C:$C,'7. Particulates'!D107,EPS!$B:$B,'7. Particulates'!E107)/10^6 -> 0 | K107: =SUMIFS('2020 EPA Data'!$D:$D,'2020 EPA Data'!$G:$G,C107,'2020 EPA Data'!$F:$F,I107)/metricton_to_shortton*INDEX(GWP!$C$2:$C$13,MATCH(C107,GWP!$B$2:$B$13,0)) -> 0
C108: VOC | D108: district heat and hydrogen sector | E108: Total Pollutant Emissions by Sector | I108: District Heat Sector | J108: =SUMIFS(EPS!$J:$J,EPS!$D:$D,'7. Particulates'!C108,EPS!$C:$C,'7. Particulates'!D108,EPS!$B:$B,'7. Particulates'!E108)/10^6 -> #N/A | K108: =SUMIFS('2020 EPA Data'!$D:$D,'2020 EPA Data'!$G:$G,C108,'2020 EPA Data'!$F:$F,I108)/metricton_to_shortton*INDEX(GWP!$C$2:$C$13,MATCH(C108,GWP!$B$2:$B$13,0)) -> 0
C109: VOC | D109: LULUCF sector | E109: Total Pollutant Emissions by Sector | I109: LULUCF Sector | J109: =SUMIFS(EPS!$J:$J,EPS!$D:$D,'7. Particulates'!C109,EPS!$C:$C,'7. Particulates'!D109,EPS!$B:$B,'7. Particulates'!E109)/10^6 -> #N/A | K109: =SUMIFS('2020 EPA Data'!$D:$D,'2020 EPA Data'!$G:$G,C109,'2020 EPA Data'!$F:$F,I109)/metricton_to_shortton*INDEX(GWP!$C$2:$C$13,MATCH(C109,GWP!$B$2:$B$13,0)) -> 0
C110: VOC | D110: geoengineering sector | E110: Total Pollutant Emissions by Sector | I110: Geoengineering Sector | J110: =SUMIFS(EPS!$J:$J,EPS!$D:$D,'7. Particulates'!C110,EPS!$C:$C,'7. Particulates'!D110,EPS!$B:$B,'7. Particulates'!E110)/10^6 -> #N/A | K110: =SUMIFS('2020 EPA Data'!$D:$D,'2020 EPA Data'!$G:$G,C110,'2020 EPA Data'!$F:$F,I110)/metricton_to_shortton*INDEX(GWP!$C$2:$C$13,MATCH(C110,GWP!$B$2:$B$13,0)) -> 0
C111: VOC | I111: Other-EPA | J111: =SUMIFS(EPS!$J:$J,EPS!$D:$D,'7. Particulates'!C111,EPS!$C:$C,'7. Particulates'!D111,EPS!$B:$B,'7. Particulates'!E111)/10^6 -> 0 | K111: =SUMIFS('2020 EPA Data'!$D:$D,'2020 EPA Data'!$G:$G,C111,'2020 EPA Data'!$F:$F,I111)/metricton_to_shortton -> 9343150.3
I112: Total | J112: =SUM(J102:J111) -> #N/A | K112: =SUM(K102:K111) -> 15120717
G119: 7.7
J120: EPS 2021 | K120: EPA 2020
C121: CO | D121: transportation sector | E121: Total Pollutant Emissions by Sector | I121: Transportation Sector | J121: =SUMIFS(EPS!$J:$J,EPS!$D:$D,'7. Particulates'!C121,EPS!$C:$C,'7. Particulates'!D121,EPS!$B:$B,'7. Particulates'!E121)/10^6 -> #N/A | K121: =SUMIFS('2020 EPA Data'!$D:$D,'2020 EPA Data'!$G:$G,C121,'2020 EPA Data'!$F:$F,I121)/metricton_to_shortton -> 13352487
C122: CO | D122: electricity sector | E122: Total Pollutant Emissions by Sector | I122: Electricity Sector | J122: =SUMIFS(EPS!$J:$J,EPS!$D:$D,'7. Particulates'!C122,EPS!$C:$C,'7. Particulates'!D122,EPS!$B:$B,'7. Particulates'!E122)/10^6 -> #N/A | K122: =SUMIFS('2020 EPA Data'!$D:$D,'2020 EPA Data'!$G:$G,C122,'2020 EPA Data'!$F:$F,I122)/metricton_to_shortton -> 361778.45
C123: CO | D123: residential buildings sector | E123: Total Pollutant Emissions by Sector | I123: Residential Buildings Sector | J123: =SUMIFS(EPS!$J:$J,EPS!$D:$D,'7. Particulates'!C123,EPS!$C:$C,'7. Particulates'!D123,EPS!$B:$B,'7. Particulates'!E123)/10^6 -> #N/A | K123: =SUMIFS('2020 EPA Data'!$D:$D,'2020 EPA Data'!$G:$G,C123,'2020 EPA Data'!$F:$F,I123)/metricton_to_shortton -> 2968044.4
C124: CO | D124: commercial buildings sector | E124: Total Pollutant Emissions by Sector | I124: Commercial Buildings Sector | J124: =SUMIFS(EPS!$J:$J,EPS!$D:$D,'7. Particulates'!C124,EPS!$C:$C,'7. Particulates'!D124,EPS!$B:$B,'7. Particulates'!E124)/10^6 -> #N/A | K124: =SUMIFS('2020 EPA Data'!$D:$D,'2020 EPA Data'!$G:$G,C124,'2020 EPA Data'!$F:$F,I124)/metricton_to_shortton -> 224643.7
C125: CO | D125: industry sector | E125: Total Pollutant Emissions by Sector | I125: Industry | J125: =SUMIFS(EPS!$J:$J,EPS!$D:$D,'7. Particulates'!C125,EPS!$C:$C,'7. Particulates'!D125,EPS!$B:$B,'7. Particulates'!E125)/10^6 -> #N/A | K125: =SUMIFS('2020 EPA Data'!$D:$D,'2020 EPA Data'!$G:$G,C125,'2020 EPA Data'!$F:$F,"*"&I125&"*")/metricton_to_shortton -> 3569852.4
C126: CO | I126: Nonroad | J126: =SUMIFS(EPS!$J:$J,EPS!$D:$D,'7. Particulates'!C126,EPS!$C:$C,'7. Particulates'!D126,EPS!$B:$B,'7. Particulates'!E126)/10^6 -> 0 | K126: =SUMIFS('2020 EPA Data'!$D:$D,'2020 EPA Data'!$G:$G,C126,'2020 EPA Data'!$F:$F,I126)/metricton_to_shortton*INDEX(GWP!$C$2:$C$13,MATCH(C126,GWP!$B$2:$B$13,0)) -> 0
C127: CO | D127: district heat and hydrogen sector | E127: Total Pollutant Emissions by Sector | I127: District Heat Sector | J127: =SUMIFS(EPS!$J:$J,EPS!$D:$D,'7. Particulates'!C127,EPS!$C:$C,'7. Particulates'!D127,EPS!$B:$B,'7. Particulates'!E127)/10^6 -> #N/A | K127: =SUMIFS('2020 EPA Data'!$D:$D,'2020 EPA Data'!$G:$G,C127,'2020 EPA Data'!$F:$F,I127)/metricton_to_shortton*INDEX(GWP!$C$2:$C$13,MATCH(C127,GWP!$B$2:$B$13,0)) -> 0
C128: CO | D128: LULUCF sector | E128: Total Pollutant Emissions by Sector | I128: LULUCF Sector | J128: =SUMIFS(EPS!$J:$J,EPS!$D:$D,'7. Particulates'!C128,EPS!$C:$C,'7. Particulates'!D128,EPS!$B:$B,'7. Particulates'!E128)/10^6 -> #N/A | K128: =SUMIFS('2020 EPA Data'!$D:$D,'2020 EPA Data'!$G:$G,C128,'2020 EPA Data'!$F:$F,I128)/metricton_to_shortton*INDEX(GWP!$C$2:$C$13,MATCH(C128,GWP!$B$2:$B$13,0)) -> 0
C129: CO | D129: geoengineering sector | E129: Total Pollutant Emissions by Sector | I129: Geoengineering Sector | J129: =SUMIFS(EPS!$J:$J,EPS!$D:$D,'7. Particulates'!C129,EPS!$C:$C,'7. Particulates'!D129,EPS!$B:$B,'7. Particulates'!E129)/10^6 -> #N/A | K129: =SUMIFS('2020 EPA Data'!$D:$D,'2020 EPA Data'!$G:$G,C129,'2020 EPA Data'!$F:$F,I129)/metricton_to_shortton*INDEX(GWP!$C$2:$C$13,MATCH(C129,GWP!$B$2:$B$13,0)) -> 0
C130: CO | I130: Other-EPA | J130: =SUMIFS(EPS!$J:$J,EPS!$D:$D,'7. Particulates'!C130,EPS!$C:$C,'7. Particulates'!D130,EPS!$B:$B,'7. Particulates'!E130)/10^6 -> 0 | K130: =SUMIFS('2020 EPA Data'!$D:$D,'2020 EPA Data'!$G:$G,C130,'2020 EPA Data'!$F:$F,I130)/metricton_to_shortton -> 39535357
I131: Total | J131: =SUM(J121:J130) -> #N/A | K131: =SUM(K121:K130) -> 60012163
G137: 7.8
J138: EPS 2021 | K138: EPA 2020
C139: PM10 | D139: transportation sector | E139: Total Pollutant Emissions by Sector | I139: Transportation Sector | J139: =SUMIFS(EPS!$J:$J,EPS!$D:$D,'7. Particulates'!C139,EPS!$C:$C,'7. Particulates'!D139,EPS!$B:$B,'7. Particulates'!E139)/10^6 -> #N/A | K139: =SUMIFS('2020 EPA Data'!$D:$D,'2020 EPA Data'!$G:$G,C139,'2020 EPA Data'!$F:$F,I139)/metricton_to_shortton -> 195852.35
C140: PM10 | D140: electricity sector | E140: Total Pollutant Emissions by Sector | I140: Electricity Sector | J140: =SUMIFS(EPS!$J:$J,EPS!$D:$D,'7. Particulates'!C140,EPS!$C:$C,'7. Particulates'!D140,EPS!$B:$B,'7. Particulates'!E140)/10^6 -> #N/A | K140: =SUMIFS('2020 EPA Data'!$D:$D,'2020 EPA Data'!$G:$G,C140,'2020 EPA Data'!$F:$F,I140)/metricton_to_shortton -> 91268.336
C141: PM10 | D141: residential buildings sector | E141: Total Pollutant Emissions by Sector | I141: Residential Buildings Sector | J141: =SUMIFS(EPS!$J:$J,EPS!$D:$D,'7. Particulates'!C141,EPS!$C:$C,'7. Particulates'!D141,EPS!$B:$B,'7. Particulates'!E141)/10^6 -> #N/A | K141: =SUMIFS('2020 EPA Data'!$D:$D,'2020 EPA Data'!$G:$G,C141,'2020 EPA Data'!$F:$F,I141)/metricton_to_shortton -> 449161.31
C142: PM10 | D142: commercial buildings sector | E142: Total Pollutant Emissions by Sector | I142: Commercial Buildings Sector | J142: =SUMIFS(EPS!$J:$J,EPS!$D:$D,'7. Particulates'!C142,EPS!$C:$C,'7. Particulates'!D142,EPS!$B:$B,'7. Particulates'!E142)/10^6 -> #N/A | K142: =SUMIFS('2020 EPA Data'!$D:$D,'2020 EPA Data'!$G:$G,C142,'2020 EPA Data'!$F:$F,I142)/metricton_to_shortton -> 207873.47
...

Sheet EPS
A1: NoSettings Tag | B1: Variable Name | C1: Sub 1 | D1: Sub 2 | E1: Sub 3 | F1: Sub 4 | G1: Sector | H1: units | I1: Pollutant | J1: 2021 (g pollutant) | K1: GWP | L1: Value (MMTCO2e; MMT; MWh) | N1: =SUBTOTAL(9,L62:L1281)*million -> 5.7879197e+08
A2: Transportation Pollutant Emissions Disaggregated[LDVs,CO2,passenger,electricity tf] | B2: Transportation Pollutant Emissions Disaggregated | C2: LDVs | D2: CO2 | E2: passenger | F2: electricity tf | H2: =INDEX('Vensim Variables'!$B:$B,MATCH(EPS!$B2,'Vensim Variables'!$A:$A,0)) -> g pollutant | I2: =IF(OR(C2="CO2",C2="CH4",C2="N2O",C2="F gases",C2="VOC",C2="CO",C2="NOx",C2="PM10",C2="PM25",C2="SOx",C2="BC",C2="OC"),C2,IF(OR(D2="CO2",D2="CH4",D2="N2O",D2="F gases",D2="VOC",D2="CO",D2="NOx",D2="PM10",D2="PM25",D2="SOx",D2="BC",D2="OC"),D2,IF(OR(E2="CO2",E2="CH4",E2="N2O",E2="F gases",E2="VOC",E2="CO",E2="NOx",E2="PM10",E2="PM25",E2="SOx",E2="BC",E2="OC"),E2,"NA"))) -> CO2 | J2: =INDEX(NoSettings!$C:$C,MATCH(EPS!$A2,NoSettings!$A:$A,0)) -> 0 | K2: =INDEX(GWP!$C$2:$C$13,MATCH(EPS!I2,GWP!$B$2:$B$13,0)) -> 1 | L2: =IF(H2="g pollutant",K2*J2/10^12,IF(H2="MMTCO2e",J2,IF(H2="MWh",J2,0))) -> 0
A3: Transportation Pollutant Emissions Disaggregated[LDVs,CO2,passenger,natural gas tf] | B3: Transportation Pollutant Emissions Disaggregated | C3: LDVs | D3: CO2 | E3: passenger | F3: natural gas tf | H3: =INDEX('Vensim Variables'!$B:$B,MATCH(EPS!$B3,'Vensim Variables'!$A:$A,0)) -> g pollutant | I3: =IF(OR(C3="CO2",C3="CH4",C3="N2O",C3="F gases",C3="VOC",C3="CO",C3="NOx",C3="PM10",C3="PM25",C3="SOx",C3="BC",C3="OC"),C3,IF(OR(D3="CO2",D3="CH4",D3="N2O",D3="F gases",D3="VOC",D3="CO",D3="NOx",D3="PM10",D3="PM25",D3="SOx",D3="BC",D3="OC"),D3,IF(OR(E3="CO2",E3="CH4",E3="N2O",E3="F gases",E3="VOC",E3="CO",E3="NOx",E3="PM10",E3="PM25",E3="SOx",E3="BC",E3="OC"),E3,"NA"))) -> CO2 | J3: =INDEX(NoSettings!$C:$C,MATCH(EPS!$A3,NoSettings!$A:$A,0)) -> 53417600000 | K3: =INDEX(GWP!$C$2:$C$13,MATCH(EPS!I3,GWP!$B$2:$B$13,0)) -> 1 | L3: =IF(H3="g pollutant",K3*J3/10^12,IF(H3="MMTCO2e",J3,IF(H3="MWh",J3,0))) -> 0.0534176
A4: Transportation Pollutant Emissions Disaggregated[LDVs,CO2,passenger,petroleum gasoline tf] | B4: Transportation Pollutant Emissions Disaggregated | C4: LDVs | D4: CO2 | E4: passenger | F4: petroleum gasoline tf | H4: =INDEX('Vensim Variables'!$B:$B,MATCH(EPS!$B4,'Vensim Variables'!$A:$A,0)) -> g pollutant | I4: =IF(OR(C4="CO2",C4="CH4",C4="N2O",C4="F gases",C4="VOC",C4="CO",C4="NOx",C4="PM10",C4="PM25",C4="SOx",C4="BC",C4="OC"),C4,IF(OR(D4="CO2",D4="CH4",D4="N2O",D4="F gases",D4="VOC",D4="CO",D4="NOx",D4="PM10",D4="PM25",D4="SOx",D4="BC",D4="OC"),D4,IF(OR(E4="CO2",E4="CH4",E4="N2O",E4="F gases",E4="VOC",E4="CO",E4="NOx",E4="PM10",E4="PM25",E4="SOx",E4="BC",E4="OC"),E4,"NA"))) -> CO2 | J4: =INDEX(NoSettings!$C:$C,MATCH(EPS!$A4,NoSettings!$A:$A,0)) -> 968772000000000 | K4: =INDEX(GWP!$C$2:$C$13,MATCH(EPS!I4,GWP!$B$2:$B$13,0)) -> 1 | L4: =IF(H4="g pollutant",K4*J4/10^12,IF(H4="MMTCO2e",J4,IF(H4="MWh",J4,0))) -> 968.772
A5: Transportation Pollutant Emissions Disaggregated[LDVs,CO2,passenger,petroleum diesel tf] | B5: Transportation Pollutant Emissions Disaggregated | C5: LDVs | D5: CO2 | E5: passenger | F5: petroleum diesel tf | H5: =INDEX('Vensim Variables'!$B:$B,MATCH(EPS!$B5,'Vensim Variables'!$A:$A,0)) -> g pollutant | I5: =IF(OR(C5="CO2",C5="CH4",C5="N2O",C5="F gases",C5="VOC",C5="CO",C5="NOx",C5="PM10",C5="PM25",C5="SOx",C5="BC",C5="OC"),C5,IF(OR(D5="CO2",D5="CH4",D5="N2O",D5="F gases",D5="VOC",D5="CO",D5="NOx",D5="PM10",D5="PM25",D5="SOx",D5="BC",D5="OC"),D5,IF(OR(E5="CO2",E5="CH4",E5="N2O",E5="F gases",E5="VOC",E5="CO",E5="NOx",E5="PM10",E5="PM25",E5="SOx",E5="BC",E5="OC"),E5,"NA"))) -> CO2 | J5: =INDEX(NoSettings!$C:$C,MATCH(EPS!$A5,NoSettings!$A:$A,0)) -> 4619900000000 | K5: =INDEX(GWP!$C$2:$C$13,MATCH(EPS!I5,GWP!$B$2:$B$13,0)) -> 1 | L5: =IF(H5="g pollutant",K5*J5/10^12,IF(H5="MMTCO2e",J5,IF(H5="MWh",J5,0))) -> 4.6199
A6: Transportation Pollutant Emissions Disaggregated[LDVs,CO2,passenger,biofuel gasoline tf] | B6: Transportation Pollutant Emissions Disaggregated | C6: LDVs | D6: CO2 | E6: passenger | F6: biofuel gasoline tf | H6: =INDEX('Vensim Variables'!$B:$B,MATCH(EPS!$B6,'Vensim Variables'!$A:$A,0)) -> g pollutant | I6: =IF(OR(C6="CO2",C6="CH4",C6="N2O",C6="F gases",C6="VOC",C6="CO",C6="NOx",C6="PM10",C6="PM25",C6="SOx",C6="BC",C6="OC"),C6,IF(OR(D6="CO2",D6="CH4",D6="N2O",D6="F gases",D6="VOC",D6="CO",D6="NOx",D6="PM10",D6="PM25",D6="SOx",D6="BC",D6="OC"),D6,IF(OR(E6="CO2",E6="CH4",E6="N2O",E6="F gases",E6="VOC",E6="CO",E6="NOx",E6="PM10",E6="PM25",E6="SOx",E6="BC",E6="OC"),E6,"NA"))) -> CO2 | J6: =INDEX(NoSettings!$C:$C,MATCH(EPS!$A6,NoSettings!$A:$A,0)) -> 0 | K6: =INDEX(GWP!$C$2:$C$13,MATCH(EPS!I6,GWP!$B$2:$B$13,0)) -> 1 | L6: =IF(H6="g pollutant",K6*J6/10^12,IF(H6="MMTCO2e",J6,IF(H6="MWh",J6,0))) -> 0
A7: Transportation Pollutant Emissions Disaggregated[LDVs,CO2,passenger,biofuel diesel tf] | B7: Transportation Pollutant Emissions Disaggregated | C7: LDVs | D7: CO2 | E7: passenger | F7: biofuel diesel tf | H7: =INDEX('Vensim Variables'!$B:$B,MATCH(EPS!$B7,'Vensim Variables'!$A:$A,0)) -> g pollutant | I7: =IF(OR(C7="CO2",C7="CH4",C7="N2O",C7="F gases",C7="VOC",C7="CO",C7="NOx",C7="PM10",C7="PM25",C7="SOx",C7="BC",C7="OC"),C7,IF(OR(D7="CO2",D7="CH4",D7="N2O",D7="F gases",D7="VOC",D7="CO",D7="NOx",D7="PM10",D7="PM25",D7="SOx",D7="BC",D7="OC"),D7,IF(OR(E7="CO2",E7="CH4",E7="N2O",E7="F gases",E7="VOC",E7="CO",E7="NOx",E7="PM10",E7="PM25",E7="SOx",E7="BC",E7="OC"),E7,"NA"))) -> CO2 | J7: =INDEX(NoSettings!$C:$C,MATCH(EPS!$A7,NoSettings!$A:$A,0)) -> 0 | K7: =INDEX(GWP!$C$2:$C$13,MATCH(EPS!I7,GWP!$B$2:$B$13,0)) -> 1 | L7: =IF(H7="g pollutant",K7*J7/10^12,IF(H7="MMTCO2e",J7,IF(H7="MWh",J7,0))) -> 0
A8: Transportation Pollutant Emissions Disaggregated[LDVs,CO2,passenger,jet fuel tf] | B8: Transportation Pollutant Emissions Disaggregated | C8: LDVs | D8: CO2 | E8: passenger | F8: jet fuel tf | H8: =INDEX('Vensim Variables'!$B:$B,MATCH(EPS!$B8,'Vensim Variables'!$A:$A,0)) -> g pollutant | I8: =IF(OR(C8="CO2",C8="CH4",C8="N2O",C8="F gases",C8="VOC",C8="CO",C8="NOx",C8="PM10",C8="PM25",C8="SOx",C8="BC",C8="OC"),C8,IF(OR(D8="CO2",D8="CH4",D8="N2O",D8="F gases",D8="VOC",D8="CO",D8="NOx",D8="PM10",D8="PM25",D8="SOx",D8="BC",D8="OC"),D8,IF(OR(E8="CO2",E8="CH4",E8="N2O",E8="F gases",E8="VOC",E8="CO",E8="NOx",E8="PM10",E8="PM25",E8="SOx",E8="BC",E8="OC"),E8,"NA"))) -> CO2 | J8: =INDEX(NoSettings!$C:$C,MATCH(EPS!$A8,NoSettings!$A:$A,0)) -> 0 | K8: =INDEX(GWP!$C$2:$C$13,MATCH(EPS!I8,GWP!$B$2:$B$13,0)) -> 1 | L8: =IF(H8="g pollutant",K8*J8/10^12,IF(H8="MMTCO2e",J8,IF(H8="MWh",J8,0))) -> 0
A9: Transportation Pollutant Emissions Disaggregated[LDVs,CO2,passenger,heavy or residual fuel oil tf] | B9: Transportation Pollutant Emissions Disaggregated | C9: LDVs | D9: CO2 | E9: passenger | F9: heavy or residual fuel oil tf | H9: =INDEX('Vensim Variables'!$B:$B,MATCH(EPS!$B9,'Vensim Variables'!$A:$A,0)) -> g pollutant | I9: =IF(OR(C9="CO2",C9="CH4",C9="N2O",C9="F gases",C9="VOC",C9="CO",C9="NOx",C9="PM10",C9="PM25",C9="SOx",C9="BC",C9="OC"),C9,IF(OR(D9="CO2",D9="CH4",D9="N2O",D9="F gases",D9="VOC",D9="CO",D9="NOx",D9="PM10",D9="PM25",D9="SOx",D9="BC",D9="OC"),D9,IF(OR(E9="CO2",E9="CH4",E9="N2O",E9="F gases",E9="VOC",E9="CO",E9="NOx",E9="PM10",E9="PM25",E9="SOx",E9="BC",E9="OC"),E9,"NA"))) -> CO2 | J9: =INDEX(NoSettings!$C:$C,MATCH(EPS!$A9,NoSettings!$A:$A,0)) -> 0 | K9: =INDEX(GWP!$C$2:$C$13,MATCH(EPS!I9,GWP!$B$2:$B$13,0)) -> 1 | L9: =IF(H9="g pollutant",K9*J9/10^12,IF(H9="MMTCO2e",J9,IF(H9="MWh",J9,0))) -> 0
A10: Transportation Pollutant Emissions Disaggregated[LDVs,CO2,passenger,LPG propane or butane tf] | B10: Transportation Pollutant Emissions Disaggregated | C10: LDVs | D10: CO2 | E10: passenger | F10: LPG propane or butane tf | H10: =INDEX('Vensim Variables'!$B:$B,MATCH(EPS!$B10,'Vensim Variables'!$A:$A,0)) -> g pollutant | I10: =IF(OR(C10="CO2",C10="CH4",C10="N2O",C10="F gases",C10="VOC",C10="CO",C10="NOx",C10="PM10",C10="PM25",C10="SOx",C10="BC",C10="OC"),C10,IF(OR(D10="CO2",D10="CH4",D10="N2O",D10="F gases",D10="VOC",D10="CO",D10="NOx",D10="PM10",D10="PM25",D10="SOx",D10="BC",D10="OC"),D10,IF(OR(E10="CO2",E10="CH4",E10="N2O",E10="F gases",E10="VOC",E10="CO",E10="NOx",E10="PM10",E10="PM25",E10="SOx",E10="BC",E10="OC"),E10,"NA"))) -> CO2 | J10: =INDEX(NoSettings!$C:$C,MATCH(EPS!$A10,NoSettings!$A:$A,0)) -> 90425500000 | K10: =INDEX(GWP!$C$2:$C$13,MATCH(EPS!I10,GWP!$B$2:$B$13,0)) -> 1 | L10: =IF(H10="g pollutant",K10*J10/10^12,IF(H10="MMTCO2e",J10,IF(H10="MWh",J10,0))) -> 0.0904255
A11: Transportation Pollutant Emissions Disaggregated[LDVs,CO2,passenger,hydrogen tf] | B11: Transportation Pollutant Emissions Disaggregated | C11: LDVs | D11: CO2 | E11: passenger | F11: hydrogen tf | H11: =INDEX('Vensim Variables'!$B:$B,MATCH(EPS!$B11,'Vensim Variables'!$A:$A,0)) -> g pollutant | I11: =IF(OR(C11="CO2",C11="CH4",C11="N2O",C11="F gases",C11="VOC",C11="CO",C11="NOx",C11="PM10",C11="PM25",C11="SOx",C11="BC",C11="OC"),C11,IF(OR(D11="CO2",D11="CH4",D11="N2O",D11="F gases",D11="VOC",D11="CO",D11="NOx",D11="PM10",D11="PM25",D11="SOx",D11="BC",D11="OC"),D11,IF(OR(E11="CO2",E11="CH4",E11="N2O",E11="F gases",E11="VOC",E11="CO",E11="NOx",E11="PM10",E11="PM25",E11="SOx",E11="BC",E11="OC"),E11,"NA"))) -> CO2 | J11: =INDEX(NoSettings!$C:$C,MATCH(EPS!$A11,NoSettings!$A:$A,0)) -> 0 | K11: =INDEX(GWP!$C$2:$C$13,MATCH(EPS!I11,GWP!$B$2:$B$13,0)) -> 1 | L11: =IF(H11="g pollutant",K11*J11/10^12,IF(H11="MMTCO2e",J11,IF(H11="MWh",J11,0))) -> 0
A12: Transportation Pollutant Emissions Disaggregated[LDVs,CO2,freight,electricity tf] | B12: Transportation Pollutant Emissions Disaggregated | C12: LDVs | D12: CO2 | E12: freight | F12: electricity tf | H12: =INDEX('Vensim Variables'!$B:$B,MATCH(EPS!$B12,'Vensim Variables'!$A:$A,0)) -> g pollutant | I12: =IF(OR(C12="CO2",C12="CH4",C12="N2O",C12="F gases",C12="VOC",C12="CO",C12="NOx",C12="PM10",C12="PM25",C12="SOx",C12="BC",C12="OC"),C12,IF(OR(D12="CO2",D12="CH4",D12="N2O",D12="F gases",D12="VOC",D12="CO",D12="NOx",D12="PM10",D12="PM25",D12="SOx",D12="BC",D12="OC"),D12,IF(OR(E12="CO2",E12="CH4",E12="N2O",E12="F gases",E12="VOC",E12="CO",E12="NOx",E12="PM10",E12="PM25",E12="SOx",E12="BC",E12="OC"),E12,"NA"))) -> CO2 | J12: =INDEX(NoSettings!$C:$C,MATCH(EPS!$A12,NoSettings!$A:$A,0)) -> 0 | K12: =INDEX(GWP!$C$2:$C$13,MATCH(EPS!I12,GWP!$B$2:$B$13,0)) -> 1 | L12: =IF(H12="g pollutant",K12*J12/10^12,IF(H12="MMTCO2e",J12,IF(H12="MWh",J12,0))) -> 0
A13: Transportation Pollutant Emissions Disaggregated[LDVs,CO2,freight,natural gas tf] | B13: Transportation Pollutant Emissions Disaggregated | C13: LDVs | D13: CO2 | E13: freight | F13: natural gas tf | H13: =INDEX('Vensim Variables'!$B:$B,MATCH(EPS!$B13,'Vensim Variables'!$A:$A,0)) -> g pollutant | I13: =IF(OR(C13="CO2",C13="CH4",C13="N2O",C13="F gases",C13="VOC",C13="CO",C13="NOx",C13="PM10",C13="PM25",C13="SOx",C13="BC",C13="OC"),C13,IF(OR(D13="CO2",D13="CH4",D13="N2O",D13="F gases",D13="VOC",D13="CO",D13="NOx",D13="PM10",D13="PM25",D13="SOx",D13="BC",D13="OC"),D13,IF(OR(E13="CO2",E13="CH4",E13="N2O",E13="F gases",E13="VOC",E13="CO",E13="NOx",E13="PM10",E13="PM25",E13="SOx",E13="BC",E13="OC"),E13,"NA"))) -> CO2 | J13: =INDEX(NoSettings!$C:$C,MATCH(EPS!$A13,NoSettings!$A:$A,0)) -> 113334000000 | K13: =INDEX(GWP!$C$2:$C$13,MATCH(EPS!I13,GWP!$B$2:$B$13,0)) -> 1 | L13: =IF(H13="g pollutant",K13*J13/10^12,IF(H13="MMTCO2e",J13,IF(H13="MWh",J13,0))) -> 0.113334
... A1441: Transportation Pollutant Emissions Disaggregated[motorbikes,F gases,freight,hydrogen tf] | B1441: Transportation Pollutant Emissions Disaggregated | C1441: motorbikes | D1441: F gases | E1441: freight | F1441: hydrogen tf | H1441: =INDEX('Vensim Variables'!$B:$B,MATCH(EPS!$B1441,'Vensim Variables'!$A:$A,0)) -> g pollutant | I1441: =IF(OR(C1441="CO2",C1441="CH4",C1441="N2O",C1441="F gases",C1441="VOC",C1441="CO",C1441="NOx",C1441="PM10",C1441="PM25",C1441="SOx",C1441="BC",C1441="OC"),C1441,IF(OR(D1441="CO2",D1441="CH4",D1441="N2O",D1441="F gases",D1441="VOC",D1441="CO",D1441="NOx",D1441="PM10",D1441="PM25",D1441="SOx",D1441="BC",D1441="OC"),D1441,IF(OR(E1441="CO2",E1441="CH4",E1441="N2O",E1441="F gases",E1441="VOC",E1441="CO",E1441="NOx",E1441="PM10",E1441="PM25",E1441="SOx",E1441="BC",E1441="OC"),E1441,"NA"))) -> F gases | J1441: =INDEX(NoSettings!$C:$C,MATCH(EPS!$A1441,NoSettings!$A:$A,0)) -> 0 | K1441: =INDEX(GWP!$C$2:$C$13,MATCH(EPS!I1441,GWP!$B$2:$B$13,0)) -> 1 | L1441: =IF(H1441="g pollutant",K1441*J1441/10^12,IF(H1441="MMTCO2e",J1441,IF(H1441="MWh",J1441,0))) -> 0
A1442: Transportation Sector Pollutant Emissions[CO2] | B1442: Transportation Sector Pollutant Emissions | C1442: CO2 | H1442: =INDEX('Vensim Variables'!$B:$B,MATCH(EPS!$B1442,'Vensim Variables'!$A:$A,0)) -> g pollutant | I1442: =IF(OR(C1442="CO2",C1442="CH4",C1442="N2O",C1442="F gases",C1442="VOC",C1442="CO",C1442="NOx",C1442="PM10",C1442="PM25",C1442="SOx",C1442="BC",C1442="OC"),C1442,IF(OR(D1442="CO2",D1442="CH4",D1442="N2O",D1442="F gases",D1442="VOC",D1442="CO",D1442="NOx",D1442="PM10",D1442="PM25",D1442="SOx",D1442="BC",D1442="OC"),D1442,IF(OR(E1442="CO2",E1442="CH4",E1442="N2O",E1442="F gases",E1442="VOC",E1442="CO",E1442="NOx",E1442="PM10",E1442="PM25",E1442="SOx",E1442="BC",E1442="OC"),E1442,"NA"))) -> CO2 | J1442: =INDEX(NoSettings!$C:$C,MATCH(EPS!$A1442,NoSettings!$A:$A,0)) -> #N/A | K1442: =INDEX(GWP!$C$2:$C$13,MATCH(EPS!I1442,GWP!$B$2:$B$13,0)) -> 1 | L1442: =IF(H1442="g pollutant",K1442*J1442/10^12,IF(H1442="MMTCO2e",J1442,IF(H1442="MWh",J1442,0))) -> #N/A
A1443: Transportation Sector Pollutant Emissions[VOC] | B1443: Transportation Sector Pollutant Emissions | C1443: VOC | H1443: =INDEX('Vensim Variables'!$B:$B,MATCH(EPS!$B1443,'Vensim Variables'!$A:$A,0)) -> g pollutant | I1443: =IF(OR(C1443="CO2",C1443="CH4",C1443="N2O",C1443="F gases",C1443="VOC",C1443="CO",C1443="NOx",C1443="PM10",C1443="PM25",C1443="SOx",C1443="BC",C1443="OC"),C1443,IF(OR(D1443="CO2",D1443="CH4",D1443="N2O",D1443="F gases",D1443="VOC",D1443="CO",D1443="NOx",D1443="PM10",D1443="PM25",D1443="SOx",D1443="BC",D1443="OC"),D1443,IF(OR(E1443="CO2",E1443="CH4",E1443="N2O",E1443="F gases",E1443="VOC",E1443="CO",E1443="NOx",E1443="PM10",E1443="PM25",E1443="SOx",E1443="BC",E1443="OC"),E1443,"NA"))) -> VOC | J1443: =INDEX(NoSettings!$C:$C,MATCH(EPS!$A1443,NoSettings!$A:$A,0)) -> #N/A | K1443: =INDEX(GWP!$C$2:$C$13,MATCH(EPS!I1443,GWP!$B$2:$B$13,0)) -> 0 | L1443: =IF(H1443="g pollutant",K1443*J1443/10^12,IF(H1443="MMTCO2e",J1443,IF(H1443="MWh",J1443,0))) -> #N/A
A1444: Transportation Sector Pollutant Emissions[CO] | B1444: Transportation Sector Pollutant Emissions | C1444: CO | H1444: =INDEX('Vensim Variables'!$B:$B,MATCH(EPS!$B1444,'Vensim Variables'!$A:$A,0)) -> g pollutant | I1444: =IF(OR(C1444="CO2",C1444="CH4",C1444="N2O",C1444="F gases",C1444="VOC",C1444="CO",C1444="NOx",C1444="PM10",C1444="PM25",C1444="SOx",C1444="BC",C1444="OC"),C1444,IF(OR(D1444="CO2",D1444="CH4",D1444="N2O",D1444="F gases",D1444="VOC",D1444="CO",D1444="NOx",D1444="PM10",D1444="PM25",D1444="SOx",D1444="BC",D1444="OC"),D1444,IF(OR(E1444="CO2",E1444="CH4",E1444="N2O",E1444="F gases",E1444="VOC",E1444="CO",E1444="NOx",E1444="PM10",E1444="PM25",E1444="SOx",E1444="BC",E1444="OC"),E1444,"NA"))) -> CO | J1444: =INDEX(NoSettings!$C:$C,MATCH(EPS!$A1444,NoSettings!$A:$A,0)) -> #N/A | K1444: =INDEX(GWP!$C$2:$C$13,MATCH(EPS!I1444,GWP!$B$2:$B$13,0)) -> 0 | L1444: =IF(H1444="g pollutant",K1444*J1444/10^12,IF(H1444="MMTCO2e",J1444,IF(H1444="MWh",J1444,0))) -> #N/A
A1445: Transportation Sector Pollutant Emissions[NOx] | B1445: Transportation Sector Pollutant Emissions | C1445: NOx | H1445: =INDEX('Vensim Variables'!$B:$B,MATCH(EPS!$B1445,'Vensim Variables'!$A:$A,0)) -> g pollutant | I1445: =IF(OR(C1445="CO2",C1445="CH4",C1445="N2O",C1445="F gases",C1445="VOC",C1445="CO",C1445="NOx",C1445="PM10",C1445="PM25",C1445="SOx",C1445="BC",C1445="OC"),C1445,IF(OR(D1445="CO2",D1445="CH4",D1445="N2O",D1445="F gases",D1445="VOC",D1445="CO",D1445="NOx",D1445="PM10",D1445="PM25",D1445="SOx",D1445="BC",D1445="OC"),D1445,IF(OR(E1445="CO2",E1445="CH4",E1445="N2O",E1445="F gases",E1445="VOC",E1445="CO",E1445="NOx",E1445="PM10",E1445="PM25",E1445="SOx",E1445="BC",E1445="OC"),E1445,"NA"))) -> NOx | J1445: =INDEX(NoSettings!$C:$C,MATCH(EPS!$A1445,NoSettings!$A:$A,0)) -> #N/A | K1445: =INDEX(GWP!$C$2:$C$13,MATCH(EPS!I1445,GWP!$B$2:$B$13,0)) -> 0 | L1445: =IF(H1445="g pollutant",K1445*J1445/10^12,IF(H1445="MMTCO2e",J1445,IF(H1445="MWh",J1445,0))) -> #N/A
A1446: Transportation Sector Pollutant Emissions[PM10] | B1446: Transportation Sector Pollutant Emissions | C1446: PM10 | H1446: =INDEX('Vensim Variables'!$B:$B,MATCH(EPS!$B1446,'Vensim Variables'!$A:$A,0)) -> g pollutant | I1446: =IF(OR(C1446="CO2",C1446="CH4",C1446="N2O",C1446="F gases",C1446="VOC",C1446="CO",C1446="NOx",C1446="PM10",C1446="PM25",C1446="SOx",C1446="BC",C1446="OC"),C1446,IF(OR(D1446="CO2",D1446="CH4",D1446="N2O",D1446="F gases",D1446="VOC",D1446="CO",D1446="NOx",D1446="PM10",D1446="PM25",D1446="SOx",D1446="BC",D1446="OC"),D1446,IF(OR(E1446="CO2",E1446="CH4",E1446="N2O",E1446="F gases",E1446="VOC",E1446="CO",E1446="NOx",E1446="PM10",E1446="PM25",E1446="SOx",E1446="BC",E1446="OC"),E1446,"NA"))) -> PM10 | J1446: =INDEX(NoSettings!$C:$C,MATCH(EPS!$A1446,NoSettings!$A:$A,0)) -> #N/A | K1446: =INDEX(GWP!$C$2:$C$13,MATCH(EPS!I1446,GWP!$B$2:$B$13,0)) -> 0 | L1446: =IF(H1446="g pollutant",K1446*J1446/10^12,IF(H1446="MMTCO2e",J1446,IF(H1446="MWh",J1446,0))) -> #N/A
A1447: Transportation Sector Pollutant Emissions[PM25] | B1447: Transportation Sector Pollutant Emissions | C1447: PM25 | H1447: =INDEX('Vensim Variables'!$B:$B,MATCH(EPS!$B1447,'Vensim Variables'!$A:$A,0)) -> g pollutant | I1447: =IF(OR(C1447="CO2",C1447="CH4",C1447="N2O",C1447="F gases",C1447="VOC",C1447="CO",C1447="NOx",C1447="PM10",C1447="PM25",C1447="SOx",C1447="BC",C1447="OC"),C1447,IF(OR(D1447="CO2",D1447="CH4",D1447="N2O",D1447="F gases",D1447="VOC",D1447="CO",D1447="NOx",D1447="PM10",D1447="PM25",D1447="SOx",D1447="BC",D1447="OC"),D1447,IF(OR(E1447="CO2",E1447="CH4",E1447="N2O",E1447="F gases",E1447="VOC",E1447="CO",E1447="NOx",E1447="PM10",E1447="PM25",E1447="SOx",E1447="BC",E1447="OC"),E1447,"NA"))) -> PM25 | J1447: =INDEX(NoSettings!$C:$C,MATCH(EPS!$A1447,NoSettings!$A:$A,0)) -> #N/A | K1447: =INDEX(GWP!$C$2:$C$13,MATCH(EPS!I1447,GWP!$B$2:$B$13,0)) -> 0 | L1447: =IF(H1447="g pollutant",K1447*J1447/10^12,IF(H1447="MMTCO2e",J1447,IF(H1447="MWh",J1447,0))) -> #N/A
A1448: Transportation Sector Pollutant Emissions[SOx] | B1448: Transportation Sector Pollutant Emissions | C1448: SOx | H1448: =INDEX('Vensim Variables'!$B:$B,MATCH(EPS!$B1448,'Vensim Variables'!$A:$A,0)) -> g pollutant | I1448: =IF(OR(C1448="CO2",C1448="CH4",C1448="N2O",C1448="F gases",C1448="VOC",C1448="CO",C1448="NOx",C1448="PM10",C1448="PM25",C1448="SOx",C1448="BC",C1448="OC"),C1448,IF(OR(D1448="CO2",D1448="CH4",D1448="N2O",D1448="F gases",D1448="VOC",D1448="CO",D1448="NOx",D1448="PM10",D1448="PM25",D1448="SOx",D1448="BC",D1448="OC"),D1448,IF(OR(E1448="CO2",E1448="CH4",E1448="N2O",E1448="F gases",E1448="VOC",E1448="CO",E1448="NOx",E1448="PM10",E1448="PM25",E1448="SOx",E1448="BC",E1448="OC"),E1448,"NA"))) -> SOx | J1448: =INDEX(NoSettings!$C:$C,MATCH(EPS!$A1448,NoSettings!$A:$A,0)) -> #N/A | K1448: =INDEX(GWP!$C$2:$C$13,MATCH(EPS!I1448,GWP!$B$2:$B$13,0)) -> 0 | L1448: =IF(H1448="g pollutant",K1448*J1448/10^12,IF(H1448="MMTCO2e",J1448,IF(H1448="MWh",J1448,0))) -> #N/A
A1449: Transportation Sector Pollutant Emissions[BC] | B1449: Transportation Sector Pollutant Emissions | C1449: BC | H1449: =INDEX('Vensim Variables'!$B:$B,MATCH(EPS!$B1449,'Vensim Variables'!$A:$A,0)) -> g pollutant | I1449: =IF(OR(C1449="CO2",C1449="CH4",C1449="N2O",C1449="F gases",C1449="VOC",C1449="CO",C1449="NOx",C1449="PM10",C1449="PM25",C1449="SOx",C1449="BC",C1449="OC"),C1449,IF(OR(D1449="CO2",D1449="CH4",D1449="N2O",D1449="F gases",D1449="VOC",D1449="CO",D1449="NOx",D1449="PM10",D1449="PM25",D1449="SOx",D1449="BC",D1449="OC"),D1449,IF(OR(E1449="CO2",E1449="CH4",E1449="N2O",E1449="F gases",E1449="VOC",E1449="CO",E1449="NOx",E1449="PM10",E1449="PM25",E1449="SOx",E1449="BC",E1449="OC"),E1449,"NA"))) -> BC | J1449: =INDEX(NoSettings!$C:$C,MATCH(EPS!$A1449,NoSettings!$A:$A,0)) -> #N/A | K1449: =INDEX(GWP!$C$2:$C$13,MATCH(EPS!I1449,GWP!$B$2:$B$13,0)) -> 0 | L1449: =IF(H1449="g pollutant",K1449*J1449/10^12,IF(H1449="MMTCO2e",J1449,IF(H1449="MWh",J1449,0))) -> #N/A
A1450: Transportation Sector Pollutant Emissions[OC] | B1450: Transportation Sector Pollutant Emissions | C1450: OC | H1450: =INDEX('Vensim Variables'!$B:$B,MATCH(EPS!$B1450,'Vensim Variables'!$A:$A,0)) -> g pollutant | I1450: =IF(OR(C1450="CO2",C1450="CH4",C1450="N2O",C1450="F gases",C1450="VOC",C1450="CO",C1450="NOx",C1450="PM10",C1450="PM25",C1450="SOx",C1450="BC",C1450="OC"),C1450,IF(OR(D1450="CO2",D1450="CH4",D1450="N2O",D1450="F gases",D1450="VOC",D1450="CO",D1450="NOx",D1450="PM10",D1450="PM25",D1450="SOx",D1450="BC",D1450="OC"),D1450,IF(OR(E1450="CO2",E1450="CH4",E1450="N2O",E1450="F gases",E1450="VOC",E1450="CO",E1450="NOx",E1450="PM10",E1450="PM25",E1450="SOx",E1450="BC",E1450="OC"),E1450,"NA"))) -> OC | J1450: =INDEX(NoSettings!$C:$C,MATCH(EPS!$A1450,NoSettings!$A:$A,0)) -> #N/A | K1450: =INDEX(GWP!$C$2:$C$13,MATCH(EPS!I1450,GWP!$B$2:$B$13,0)) -> 0 | L1450: =IF(H1450="g pollutant",K1450*J1450/10^12,IF(H1450="MMTCO2e",J1450,IF(H1450="MWh",J1450,0))) -> #N/A
A1451: Transportation Sector Pollutant Emissions[CH4] | B1451: Transportation Sector Pollutant Emissions | C1451: CH4 | H1451: =INDEX('Vensim Variables'!$B:$B,MATCH(EPS!$B1451,'Vensim Variables'!$A:$A,0)) -> g pollutant | I1451: =IF(OR(C1451="CO2",C1451="CH4",C1451="N2O",C1451="F gases",C1451="VOC",C1451="CO",C1451="NOx",C1451="PM10",C1451="PM25",C1451="SOx",C1451="BC",C1451="OC"),C1451,IF(OR(D1451="CO2",D1451="CH4",D1451="N2O",D1451="F gases",D1451="VOC",D1451="CO",D1451="NOx",D1451="PM10",D1451="PM25",D1451="SOx",D1451="BC",D1451="OC"),D1451,IF(OR(E1451="CO2",E1451="CH4",E1451="N2O",E1451="F gases",E1451="VOC",E1451="CO",E1451="NOx",E1451="PM10",E1451="PM25",E1451="SOx",E1451="BC",E1451="OC"),E1451,"NA"))) -> CH4 | J1451: =INDEX(NoSettings!$C:$C,MATCH(EPS!$A1451,NoSettings!$A:$A,0)) -> #N/A | K1451: =INDEX(GWP!$C$2:$C$13,MATCH(EPS!I1451,GWP!$B$2:$B$13,0)) -> 28 | L1451: =IF(H1451="g pollutant",K1451*J1451/10^12,IF(H1451="MMTCO2e",J1451,IF(H1451="MWh",J1451,0))) -> #N/A
A1452: Transportation Sector Pollutant Emissions[N2O] | B1452: Transportation Sector Pollutant Emissions | C1452: N2O | H1452: =INDEX('Vensim Variables'!$B:$B,MATCH(EPS!$B1452,'Vensim Variables'!$A:$A,0)) -> g pollutant | I1452: =IF(OR(C1452="CO2",C1452="CH4",C1452="N2O",C1452="F gases",C1452="VOC",C1452="CO",C1452="NOx",C1452="PM10",C1452="PM25",C1452="SOx",C1452="BC",C1452="OC"),C1452,IF(OR(D1452="CO2",D1452="CH4",D1452="N2O",D1452="F gases",D1452="VOC",D1452="CO",D1452="NOx",D1452="PM10",D1452="PM25",D1452="SOx",D1452="BC",D1452="OC"),D1452,IF(OR(E1452="CO2",E1452="CH4",E1452="N2O",E1452="F gases",E1452="VOC",E1452="CO",E1452="NOx",E1452="PM10",E1452="PM25",E1452="SOx",E1452="BC",E1452="OC"),E1452,"NA"))) -> N2O | J1452: =INDEX(NoSettings!$C:$C,MATCH(EPS!$A1452,NoSettings!$A:$A,0)) -> #N/A | K1452: =INDEX(GWP!$C$2:$C$13,MATCH(EPS!I1452,GWP!$B$2:$B$13,0)) -> 265 | L1452: =IF(H1452="g pollutant",K1452*J1452/10^12,IF(H1452="MMTCO2e",J1452,IF(H1452="MWh",J1452,0))) -> #N/A
A1453: Transportation Sector Pollutant Emissions[F gases] | B1453: Transportation Sector Pollutant Emissions | C1453: F gases | H1453: =INDEX('Vensim Variables'!$B:$B,MATCH(EPS!$B1453,'Vensim Variables'!$A:$A,0)) -> g pollutant | I1453: =IF(OR(C1453="CO2",C1453="CH4",C1453="N2O",C1453="F gases",C1453="VOC",C1453="CO",C1453="NOx",C1453="PM10",C1453="PM25",C1453="SOx",C1453="BC",C1453="OC"),C1453,IF(OR(D1453="CO2",D1453="CH4",D1453="N2O",D1453="F gases",D1453="VOC",D1453="CO",D1453="NOx",D1453="PM10",D1453="PM25",D1453="SOx",D1453="BC",D1453="OC"),D1453,IF(OR(E1453="CO2",E1453="CH4",E1453="N2O",E1453="F gases",E1453="VOC",E1453="CO",E1453="NOx",E1453="PM10",E1453="PM25",E1453="SOx",E1453="BC",E1453="OC"),E1453,"NA"))) -> F gases | J1453: =INDEX(NoSettings!$C:$C,MATCH(EPS!$A1453,NoSettings!$A:$A,0)) -> #N/A | K1453: =INDEX(GWP!$C$2:$C$13,MATCH(EPS!I1453,GWP!$B$2:$B$13,0)) -> 1 | L1453: =IF(H1453="g pollutant",K1453*J1453/10^12,IF(H1453="MMTCO2e",J1453,IF(H1453="MWh",J1453,0))) -> #N/A
A1454: Electricity Sector Pollutant Emissions[CO2,hard coal es] | B1454: Electricity Sector Pollutant Emissions | C1454: CO2 | D1454: hard coal es | H1454: =INDEX('Vensim Variables'!$B:$B,MATCH(EPS!$B1454,'Vensim Variables'!$A:$A,0)) -> g pollutant | I1454: =IF(OR(C1454="CO2",C1454="CH4",C1454="N2O",C1454="F gases",C1454="VOC",C1454="CO",C1454="NOx",C1454="PM10",C1454="PM25",C1454="SOx",C1454="BC",C1454="OC"),C1454,IF(OR(D1454="CO2",D1454="CH4",D1454="N2O",D1454="F gases",D1454="VOC",D1454="CO",D1454="NOx",D1454="PM10",D1454="PM25",D1454="SOx",D1454="BC",D1454="OC"),D1454,IF(OR(E1454="CO2",E1454="CH4",E1454="N2O",E1454="F gases",E1454="VOC",E1454="CO",E1454="NOx",E1454="PM10",E1454="PM25",E1454="SOx",E1454="BC",E1454="OC"),E1454,"NA"))) -> CO2 | J1454: =INDEX(NoSettings!$C:$C,MATCH(EPS!$A1454,NoSettings!$A:$A,0)) -> 774520000000000 | K1454: =INDEX(GWP!$C$2:$C$13,MATCH(EPS!I1454,GWP!$B$2:$B$13,0)) -> 1 | L1454: =IF(H1454="g pollutant",K1454*J1454/10^12,IF(H1454="MMTCO2e",J1454,IF(H1454="MWh",J1454,0))) -> 774.52
A1455: Electricity Sector Pollutant Emissions[CO2,natural gas steam turbine es] | B1455: Electricity Sector Pollutant Emissions | C1455: CO2 | D1455: natural gas steam turbine es | H1455: =INDEX('Vensim Variables'!$B:$B,MATCH(EPS!$B1455,'Vensim Variables'!$A:$A,0)) -> g pollutant | I1455: =IF(OR(C1455="CO2",C1455="CH4",C1455="N2O",C1455="F gases",C1455="VOC",C1455="CO",C1455="NOx",C1455="PM10",C1455="PM25",C1455="SOx",C1455="BC",C1455="OC"),C1455,IF(OR(D1455="CO2",D1455="CH4",D1455="N2O",D1455="F gases",D1455="VOC",D1455="CO",D1455="NOx",D1455="PM10",D1455="PM25",D1455="SOx",D1455="BC",D1455="OC"),D1455,IF(OR(E1455="CO2",E1455="CH4",E1455="N2O",E1455="F gases",E1455="VOC",E1455="CO",E1455="NOx",E1455="PM10",E1455="PM25",E1455="SOx",E1455="BC",E1455="OC"),E1455,"NA"))) -> CO2 | J1455: =INDEX(NoSettings!$C:$C,MATCH(EPS!$A1455,NoSettings!$A:$A,0)) -> 47581300000000 | K1455: =INDEX(GWP!$C$2:$C$13,MATCH(EPS!I1455,GWP!$B$2:$B$13,0)) -> 1 | L1455: =IF(H1455="g pollutant",K1455*J1455/10^12,IF(H1455="MMTCO2e",J1455,IF(H1455="MWh",J1455,0))) -> 47.5813
A1456: Electricity Sector Pollutant Emissions[CO2,natural gas combined cycle es] | B1456: Electricity Sector Pollutant Emissions | C1456: CO2 | D1456: natural gas combined cycle es | H1456: =INDEX('Vensim Variables'!$B:$B,MATCH(EPS!$B1456,'Vensim Variables'!$A:$A,0)) -> g pollutant | I1456: =IF(OR(C1456="CO2",C1456="CH4",C1456="N2O",C1456="F gases",C1456="VOC",C1456="CO",C1456="NOx",C1456="PM10",C1456="PM25",C1456="SOx",C1456="BC",C1456="OC"),C1456,IF(OR(D1456="CO2",D1456="CH4",D1456="N2O",D1456="F gases",D1456="VOC",D1456="CO",D1456="NOx",D1456="PM10",D1456="PM25",D1456="SOx",D1456="BC",D1456="OC"),D1456,IF(OR(E1456="CO2",E1456="CH4",E1456="N2O",E1456="F gases",E1456="VOC",E1456="CO",E1456="NOx",E1456="PM10",E1456="PM25",E1456="SOx",E1456="BC",E1456="OC"),E1456,"NA"))) -> CO2 | J1456: =INDEX(NoSettings!$C:$C,MATCH(EPS!$A1456,NoSettings!$A:$A,0)) -> 692135000000000 | K1456: =INDEX(GWP!$C$2:$C$13,MATCH(EPS!I1456,GWP!$B$2:$B$13,0)) -> 1 | L1456: =IF(H1456="g pollutant",K1456*J1456/10^12,IF(H1456="MMTCO2e",J1456,IF(H1456="MWh",J1456,0))) -> 692.135
A1457: Electricity Sector Pollutant Emissions[CO2,nuclear es] | B1457: Electricity Sector Pollutant Emissions | C1457: CO2 | D1457: nuclear es | H1457: =INDEX('Vensim Variables'!$B:$B,MATCH(EPS!$B1457,'Vensim Variables'!$A:$A,0)) -> g pollutant | I1457: =IF(OR(C1457="CO2",C1457="CH4",C1457="N2O",C1457="F gases",C1457="VOC",C1457="CO",C1457="NOx",C1457="PM10",C1457="PM25",C1457="SOx",C1457="BC",C1457="OC"),C1457,IF(OR(D1457="CO2",D1457="CH4",D1457="N2O",D1457="F gases",D1457="VOC",D1457="CO",D1457="NOx",D1457="PM10",D1457="PM25",D1457="SOx",D1457="BC",D1457="OC"),D1457,IF(OR(E1457="CO2",E1457="CH4",E1457="N2O",E1457="F gases",E1457="VOC",E1457="CO",E1457="NOx",E1457="PM10",E1457="PM25",E1457="SOx",E1457="BC",E1457="OC"),E1457,"NA"))) -> CO2 | J1457: =INDEX(NoSettings!$C:$C,MATCH(EPS!$A1457,NoSettings!$A:$A,0)) -> 0 | K1457: =INDEX(GWP!$C$2:$C$13,MATCH(EPS!I1457,GWP!$B$2:$B$13,0)) -> 1 | L1457: =IF(H1457="g pollutant",K1457*J1457/10^12,IF(H1457="MMTCO2e",J1457,IF(H1457="MWh",J1457,0))) -> 0
A1458: Electricity Sector Pollutant Emissions[CO2,hydro es] | B1458: Electricity Sector Pollutant Emissions | C1458: CO2 | D1458: hydro es | H1458: =INDEX('Vensim Variables'!$B:$B,MATCH(EPS!$B1458,'Vensim Variables'!$A:$A,0)) -> g pollutant | I1458: =IF(OR(C1458="CO2",C1458="CH4",C1458="N2O",C1458="F gases",C1458="VOC",C1458="CO",C1458="NOx",C1458="PM10",C1458="PM25",C1458="SOx",C1458="BC",C1458="OC"),C1458,IF(OR(D1458="CO2",D1458="CH4",D1458="N2O",D1458="F gases",D1458="VOC",D1458="CO",D1458="NOx",D1458="PM10",D1458="PM25",D1458="SOx",D1458="BC",D1458="OC"),D1458,IF(OR(E1458="CO2",E1458="CH4",E1458="N2O",E1458="F gases",E1458="VOC",E1458="CO",E1458="NOx",E1458="PM10",E1458="PM25",E1458="SOx",E1458="BC",E1458="OC"),E1458,"NA"))) -> CO2 | J1458: =INDEX(NoSettings!$C:$C,MATCH(EPS!$A1458,NoSettings!$A:$A,0)) -> 0 | K1458: =INDEX(GWP!$C$2:$C$13,MATCH(EPS!I1458,GWP!$B$2:$B$13,0)) -> 1 | L1458: =IF(H1458="g pollutant",K1458*J1458/10^12,IF(H1458="MMTCO2e",J1458,IF(H1458="MWh",J1458,0))) -> 0
A1459: Electricity Sector Pollutant Emissions[CO2,onshore wind es] | B1459: Electricity Sector Pollutant Emissions | C1459: CO2 | D1459: onshore wind es | H1459: =INDEX('Vensim Variables'!$B:$B,MATCH(EPS!$B1459,'Vensim Variables'!$A:$A,0)) -> g pollutant | I1459: =IF(OR(C1459="CO2",C1459="CH4",C1459="N2O",C1459="F gases",C1459="VOC",C1459="CO",C1459="NOx",C1459="PM10",C1459="PM25",C1459="SOx",C1459="BC",C1459="OC"),C1459,IF(OR(D1459="CO2",D1459="CH4",D1459="N2O",D1459="F gases",D1459="VOC",D1459="CO",D1459="NOx",D1459="PM10",D1459="PM25",D1459="SOx",D1459="BC",D1459="OC"),D1459,IF(OR(E1459="CO2",E1459="CH4",E1459="N2O",E1459="F gases",E1459="VOC",E1459="CO",E1459="NOx",E1459="PM10",E1459="PM25",E1459="SOx",E1459="BC",E1459="OC"),E1459,"NA"))) -> CO2 | J1459: =INDEX(NoSettings!$C:$C,MATCH(EPS!$A1459,NoSettings!$A:$A,0)) -> 0 | K1459: =INDEX(GWP!$C$2:$C$13,MATCH(EPS!I1459,GWP!$B$2:$B$13,0)) -> 1 | L1459: =IF(H1459="g pollutant",K1459*J1459/10^12,IF(H1459="MMTCO2e",J1459,IF(H1459="MWh",J1459,0))) -> 0
A1460: Electricity Sector Pollutant Emissions[CO2,solar PV es] | B1460: Electricity Sector Pollutant Emissions | C1460: CO2 | D1460: solar PV es | H1460: =INDEX('Vensim Variables'!$B:$B,MATCH(EPS!$B1460,'Vensim Variables'!$A:$A,0)) -> g pollutant | I1460: =IF(OR(C1460="CO2",C1460="CH4",C1460="N2O",C1460="F gases",C1460="VOC",C1460="CO",C1460="NOx",C1460="PM10",C1460="PM25",C1460="SOx",C1460="BC",C1460="OC"),C1460,IF(OR(D1460="CO2",D1460="CH4",D1460="N2O",D1460="F gases",D1460="VOC",D1460="CO",D1460="NOx",D1460="PM10",D1460="PM25",D1460="SOx",D1460="BC",D1460="OC"),D1460,IF(OR(E1460="CO2",E1460="CH4",E1460="N2O",E1460="F gases",E1460="VOC",E1460="CO",E1460="NOx",E1460="PM10",E1460="PM25",E1460="SOx",E1460="BC",E1460="OC"),E1460,"NA"))) -> CO2 | J1460: =INDEX(NoSettings!$C:$C,MATCH(EPS!$A1460,NoSettings!$A:$A,0)) -> 0 | K1460: =INDEX(GWP!$C$2:$C$13,MATCH(EPS!I1460,GWP!$B$2:$B$13,0)) -> 1 | L1460: =IF(H1460="g pollutant",K1460*J1460/10^12,IF(H1460="MMTCO2e",J1460,IF(H1460="MWh",J1460,0))) -> 0
A1461: Electricity Sector Pollutant Emissions[CO2,solar thermal es] | B1461: Electricity Sector Pollutant Emissions | C1461: CO2 | D1461: solar thermal es | H1461: =INDEX('Vensim Variables'!$B:$B,MATCH(EPS!$B1461,'Vensim Variables'!$A:$A,0)) -> g pollutant | I1461: =IF(OR(C1461="CO2",C1461="CH4",C1461="N2O",C1461="F gases",C1461="VOC",C1461="CO",C1461="NOx",C1461="PM10",C1461="PM25",C1461="SOx",C1461="BC",C1461="OC"),C1461,IF(OR(D1461="CO2",D1461="CH4",D1461="N2O",D1461="F gases",D1461="VOC",D1461="CO",D1461="NOx",D1461="PM10",D1461="PM25",D1461="SOx",D1461="BC",D1461="OC"),D1461,IF(OR(E1461="CO2",E1461="CH4",E1461="N2O",E1461="F gases",E1461="VOC",E1461="CO",E1461="NOx",E1461="PM10",E1461="PM25",E1461="SOx",E1461="BC",E1461="OC"),E1461,"NA"))) -> CO2 | J1461: =INDEX(NoSettings!$C:$C,MATCH(EPS!$A1461,NoSettings!$A:$A,0)) -> 0 | K1461: =INDEX(GWP!$C$2:$C$13,MATCH(EPS!I1461,GWP!$B$2:$B$13,0)) -> 1 | L1461: =IF(H1461="g pollutant",K1461*J1461/10^12,IF(H1461="MMTCO2e",J1461,IF(H1461="MWh",J1461,0))) -> 0
A1462: Electricity Sector Pollutant Emissions[CO2,biomass es] | B1462: Electricity Sector Pollutant Emissions | C1462: CO2 | D1462: biomass es | H1462: =INDEX('Vensim Variables'!$B:$B,MATCH(EPS!$B1462,'Vensim Variables'!$A:$A,0)) -> g pollutant | I1462: =IF(OR(C1462="CO2",C1462="CH4",C1462="N2O",C1462="F gases",C1462="VOC",C1462="CO",C1462="NOx",C1462="PM10",C1462="PM25",C1462="SOx",C1462="BC",C1462="OC"),C1462,IF(OR(D1462="CO2",D1462="CH4",D1462="N2O",D1462="F gases",D1462="VOC",D1462="CO",D1462="NOx",D1462="PM10",D1462="PM25",D1462="SOx",D1462="BC",D1462="OC"),D1462,IF(OR(E1462="CO2",E1462="CH4",E1462="N2O",E1462="F gases",E1462="VOC",E1462="CO",E1462="NOx",E1462="PM10",E1462="PM25",E1462="SOx",E1462="BC",E1462="OC"),E1462,"NA"))) -> CO2 | J1462: =INDEX(NoSettings!$C:$C,MATCH(EPS!$A1462,NoSettings!$A:$A,0)) -> 0 | K1462: =INDEX(GWP!$C$2:$C$13,MATCH(EPS!I1462,GWP!$B$2:$B$13,0)) -> 1 | L1462: =IF(H1462="g pollutant",K1462*J1462/10^12,IF(H1462="MMTCO2e",J1462,IF(H1462="MWh",J1462,0))) -> 0
A1463: Electricity Sector Pollutant Emissions[CO2,geothermal es] | B1463: Electricity Sector Pollutant Emissions | C1463: CO2 | D1463: geothermal es | H1463: =INDEX('Vensim Variables'!$B:$B,MATCH(EPS!$B1463,'Vensim Variables'!$A:$A,0)) -> g pollutant | I1463: =IF(OR(C1463="CO2",C1463="CH4",C1463="N2O",C1463="F gases",C1463="VOC",C1463="CO",C1463="NOx",C1463="PM10",C1463="PM25",C1463="SOx",C1463="BC",C1463="OC"),C1463,IF(OR(D1463="CO2",D1463="CH4",D1463="N2O",D1463="F gases",D1463="VOC",D1463="CO",D1463="NOx",D1463="PM10",D1463="PM25",D1463="SOx",D1463="BC",D1463="OC"),D1463,IF(OR(E1463="CO2",E1463="CH4",E1463="N2O",E1463="F gases",E1463="VOC",E1463="CO",E1463="NOx",E1463="PM10",E1463="PM25",E1463="SOx",E1463="BC",E1463="OC"),E1463,"NA"))) -> CO2 | J1463: =INDEX(NoSettings!$C:$C,MATCH(EPS!$A1463,NoSettings!$A:$A,0)) -> 0 | K1463: =INDEX(GWP!$C$2:$C$13,MATCH(EPS!I1463,GWP!$B$2:$B$13,0)) -> 1 | L1463: =IF(H1463="g pollutant",K1463*J1463/10^12,IF(H1463="MMTCO2e",J1463,IF(H1463="MWh",J1463,0))) -> 0
A1464: Electricity Sector Pollutant Emissions[CO2,petroleum es] | B1464: Electricity Sector Pollutant Emissions | C1464: CO2 | D1464: petroleum es | H1464: =INDEX('Vensim Variables'!$B:$B,MATCH(EPS!$B1464,'Vensim Variables'!$A:$A,0)) -> g pollutant | I1464: =IF(OR(C1464="CO2",C1464="CH4",C1464="N2O",C1464="F gases",C1464="VOC",C1464="CO",C1464="NOx",C1464="PM10",C1464="PM25",C1464="SOx",C1464="BC",C1464="OC"),C1464,IF(OR(D1464="CO2",D1464="CH4",D1464="N2O",D1464="F gases",D1464="VOC",D1464="CO",D1464="NOx",D1464="PM10",D1464="PM25",D1464="SOx",D1464="BC",D1464="OC"),D1464,IF(OR(E1464="CO2",E1464="CH4",E1464="N2O",E1464="F gases",E1464="VOC",E1464="CO",E1464="NOx",E1464="PM10",E1464="PM25",E1464="SOx",E1464="BC",E1464="OC"),E1464,"NA"))) -> CO2 | J1464: =INDEX(NoSettings!$C:$C,MATCH(EPS!$A1464,NoSettings!$A:$A,0)) -> 2014110000000 | K1464: =INDEX(GWP!$C$2:$C$13,MATCH(EPS!I1464,GWP!$B$2:$B$13,0)) -> 1 | L1464: =IF(H1464="g pollutant",K1464*J1464/10^12,IF(H1464="MMTCO2e",J1464,IF(H1464="MWh",J1464,0))) -> 2.01411
A1465: Electricity Sector Pollutant Emissions[CO2,natural gas peaker es] | B1465: Electricity Sector Pollutant Emissions | C1465: CO2 | D1465: natural gas peaker es | H1465: =INDEX('Vensim Variables'!$B:$B,MATCH(EPS!$B1465,'Vensim Variables'!$A:$A,0)) -> g pollutant | I1465: =IF(OR(C1465="CO2",C1465="CH4",C1465="N2O",C1465="F gases",C1465="VOC",C1465="CO",C1465="NOx",C1465="PM10",C1465="PM25",C1465="SOx",C1465="BC",C1465="OC"),C1465,IF(OR(D1465="CO2",D1465="CH4",D1465="N2O",D1465="F gases",D1465="VOC",D1465="CO",D1465="NOx",D1465="PM10",D1465="PM25",D1465="SOx",D1465="BC",D1465="OC"),D1465,IF(OR(E1465="CO2",E1465="CH4",E1465="N2O",E1465="F gases",E1465="VOC",E1465="CO",E1465="NOx",E1465="PM10",E1465="PM25",E1465="SOx",E1465="BC",E1465="OC"),E1465,"NA"))) -> CO2 | J1465: =INDEX(NoSettings!$C:$C,MATCH(EPS!$A1465,NoSettings!$A:$A,0)) -> 45280700000000 | K1465: =INDEX(GWP!$C$2:$C$13,MATCH(EPS!I1465,GWP!$B$2:$B$13,0)) -> 1 | L1465: =IF(H1465="g pollutant",K1465*J1465/10^12,IF(H1465="MMTCO2e",J1465,IF(H1465="MWh",J1465,0))) -> 45.2807
... A2077: Process Emissions after CCS[construction 41T43,F gases] | B2077: Process Emissions after CCS | C2077: construction 41T43 | D2077: F gases | H2077: =INDEX('Vensim Variables'!$B:$B,MATCH(EPS!$B2077,'Vensim Variables'!$A:$A,0)) -> g pollutant | I2077: =IF(OR(C2077="CO2",C2077="CH4",C2077="N2O",C2077="F gases",C2077="VOC",C2077="CO",C2077="NOx",C2077="PM10",C2077="PM25",C2077="SOx",C2077="BC",C2077="OC"),C2077,IF(OR(D2077="CO2",D2077="CH4",D2077="N2O",D2077="F gases",D2077="VOC",D2077="CO",D2077="NOx",D2077="PM10",D2077="PM25",D2077="SOx",D2077="BC",D2077="OC"),D2077,IF(OR(E2077="CO2",E2077="CH4",E2077="N2O",E2077="F gases",E2077="VOC",E2077="CO",E2077="NOx",E2077="PM10",E2077="PM25",E2077="SOx",E2077="BC",E2077="OC"),E2077,"NA"))) -> F gases | J2077: =INDEX(NoSettings!$C:$C,MATCH(EPS!$A2077,NoSettings!$A:$A,0)) -> #N/A | K2077: =INDEX(GWP!$C$2:$C$13,MATCH(EPS!I2077,GWP!$B$2:$B$13,0)) -> 1 | L2077: =IF(H2077="g pollutant",K2077*J2077/10^12,IF(H2077="MMTCO2e",J2077,IF(H2077="MWh",J2077,0))) -> #N/A
A2078: Industrial Sector Energy Related Emissions after CCS[electricity if,agriculture and forestry 01T03,CO2] | B2078: Industrial Sector Energy Related Emissions after CCS | C2078: electricity if | D2078: agriculture and forestry 01T03 | E2078: CO2 | H2078: =INDEX('Vensim Variables'!$B:$B,MATCH(EPS!$B2078,'Vensim Variables'!$A:$A,0)) -> g pollutant | I2078: =IF(OR(C2078="CO2",C2078="CH4",C2078="N2O",C2078="F gases",C2078="VOC",C2078="CO",C2078="NOx",C2078="PM10",C2078="PM25",C2078="SOx",C2078="BC",C2078="OC"),C2078,IF(OR(D2078="CO2",D2078="CH4",D2078="N2O",D2078="F gases",D2078="VOC",D2078="CO",D2078="NOx",D2078="PM10",D2078="PM25",D2078="SOx",D2078="BC",D2078="OC"),D2078,IF(OR(E2078="CO2",E2078="CH4",E2078="N2O",E2078="F gases",E2078="VOC",E2078="CO",E2078="NOx",E2078="PM10",E2078="PM25",E2078="SOx",E2078="BC",E2078="OC"),E2078,"NA"))) -> CO2 | J2078: =INDEX(NoSettings!$C:$C,MATCH(EPS!$A2078,NoSettings!$A:$A,0)) -> #N/A | K2078: =INDEX(GWP!$C$2:$C$13,MATCH(EPS!I2078,GWP!$B$2:$B$13,0)) -> 1 | L2078: =IF(H2078="g pollutant",K2078*J2078/10^12,IF(H2078="MMTCO2e",J2078,IF(H2078="MWh",J2078,0))) -> #N/A
A2079: Industrial Sector Energy Related Emissions after CCS[electricity if,agriculture and forestry 01T03,VOC] | B2079: Industrial Sector Energy Related Emissions after CCS | C2079: electricity if | D2079: agriculture and forestry 01T03 | E2079: VOC | H2079: =INDEX('Vensim Variables'!$B:$B,MATCH(EPS!$B2079,'Vensim Variables'!$A:$A,0)) -> g pollutant | I2079: =IF(OR(C2079="CO2",C2079="CH4",C2079="N2O",C2079="F gases",C2079="VOC",C2079="CO",C2079="NOx",C2079="PM10",C2079="PM25",C2079="SOx",C2079="BC",C2079="OC"),C2079,IF(OR(D2079="CO2",D2079="CH4",D2079="N2O",D2079="F gases",D2079="VOC",D2079="CO",D2079="NOx",D2079="PM10",D2079="PM25",D2079="SOx",D2079="BC",D2079="OC"),D2079,IF(OR(E2079="CO2",E2079="CH4",E2079="N2O",E2079="F gases",E2079="VOC",E2079="CO",E2079="NOx",E2079="PM10",E2079="PM25",E2079="SOx",E2079="BC",E2079="OC"),E2079,"NA"))) -> VOC | J2079: =INDEX(NoSettings!$C:$C,MATCH(EPS!$A2079,NoSettings!$A:$A,0)) -> #N/A | K2079: =INDEX(GWP!$C$2:$C$13,MATCH(EPS!I2079,GWP!$B$2:$B$13,0)) -> 0 | L2079: =IF(H2079="g pollutant",K2079*J2079/10^12,IF(H2079="MMTCO2e",J2079,IF(H2079="MWh",J2079,0))) -> #N/A
A2080: Industrial Sector Energy Related Emissions after CCS[electricity if,agriculture and forestry 01T03,CO] | B2080: Industrial Sector Energy Related Emissions after CCS | C2080: electricity if | D2080: agriculture and forestry 01T03 | E2080: CO | H2080: =INDEX('Vensim Variables'!$B:$B,MATCH(EPS!$B2080,'Vensim Variables'!$A:$A,0)) -> g pollutant | I2080: =IF(OR(C2080="CO2",C2080="CH4",C2080="N2O",C2080="F gases",C2080="VOC",C2080="CO",C2080="NOx",C2080="PM10",C2080="PM25",C2080="SOx",C2080="BC",C2080="OC"),C2080,IF(OR(D2080="CO2",D2080="CH4",D2080="N2O",D2080="F gases",D2080="VOC",D2080="CO",D2080="NOx",D2080="PM10",D2080="PM25",D2080="SOx",D2080="BC",D2080="OC"),D2080,IF(OR(E2080="CO2",E2080="CH4",E2080="N2O",E2080="F gases",E2080="VOC",E2080="CO",E2080="NOx",E2080="PM10",E2080="PM25",E2080="SOx",E2080="BC",E2080="OC"),E2080,"NA"))) -> CO | J2080: =INDEX(NoSettings!$C:$C,MATCH(EPS!$A2080,NoSettings!$A:$A,0)) -> #N/A | K2080: =INDEX(GWP!$C$2:$C$13,MATCH(EPS!I2080,GWP!$B$2:$B$13,0)) -> 0 | L2080: =IF(H2080="g pollutant",K2080*J2080/10^12,IF(H2080="MMTCO2e",J2080,IF(H2080="MWh",J2080,0))) -> #N/A
A2081: Industrial Sector Energy Related Emissions after CCS[electricity if,agriculture and forestry 01T03,NOx] | B2081: Industrial Sector Energy Related Emissions after CCS | C2081: electricity if | D2081: agriculture and forestry 01T03 | E2081: NOx | H2081: =INDEX('Vensim Variables'!$B:$B,MATCH(EPS!$B2081,'Vensim Variables'!$A:$A,0)) -> g pollutant | I2081: =IF(OR(C2081="CO2",C2081="CH4",C2081="N2O",C2081="F gases",C2081="VOC",C2081="CO",C2081="NOx",C2081="PM10",C2081="PM25",C2081="SOx",C2081="BC",C2081="OC"),C2081,IF(OR(D2081="CO2",D2081="CH4",D2081="N2O",D2081="F gases",D2081="VOC",D2081="CO",D2081="NOx",D2081="PM10",D2081="PM25",D2081="SOx",D2081="BC",D2081="OC"),D2081,IF(OR(E2081="CO2",E2081="CH4",E2081="N2O",E2081="F gases",E2081="VOC",E2081="CO",E2081="NOx",E2081="PM10",E2081="PM25",E2081="SOx",E2081="BC",E2081="OC"),E2081,"NA"))) -> NOx | J2081: =INDEX(NoSettings!$C:$C,MATCH(EPS!$A2081,NoSettings!$A:$A,0)) -> #N/A | K2081: =INDEX(GWP!$C$2:$C$13,MATCH(EPS!I2081,GWP!$B$2:$B$13,0)) -> 0 | L2081: =IF(H2081="g pollutant",K2081*J2081/10^12,IF(H2081="MMTCO2e",J2081,IF(H2081="MWh",J2081,0))) -> #N/A
A2082: Industrial Sector Energy Related Emissions after CCS[electricity if,agriculture and forestry 01T03,PM10] | B2082: Industrial Sector Energy Related Emissions after CCS | C2082: electricity if | D2082: agriculture and forestry 01T03 | E2082: PM10 | H2082: =INDEX('Vensim Variables'!$B:$B,MATCH(EPS!$B2082,'Vensim Variables'!$A:$A,0)) -> g pollutant | I2082: =IF(OR(C2082="CO2",C2082="CH4",C2082="N2O",C2082="F gases",C2082="VOC",C2082="CO",C2082="NOx",C2082="PM10",C2082="PM25",C2082="SOx",C2082="BC",C2082="OC"),C2082,IF(OR(D2082="CO2",D2082="CH4",D2082="N2O",D2082="F gases",D2082="VOC",D2082="CO",D2082="NOx",D2082="PM10",D2082="PM25",D2082="SOx",D2082="BC",D2082="OC"),D2082,IF(OR(E2082="CO2",E2082="CH4",E2082="N2O",E2082="F gases",E2082="VOC",E2082="CO",E2082="NOx",E2082="PM10",E2082="PM25",E2082="SOx",E2082="BC",E2082="OC"),E2082,"NA"))) -> PM10 | J2082: =INDEX(NoSettings!$C:$C,MATCH(EPS!$A2082,NoSettings!$A:$A,0)) -> #N/A | K2082: =INDEX(GWP!$C$2:$C$13,MATCH(EPS!I2082,GWP!$B$2:$B$13,0)) -> 0 | L2082: =IF(H2082="g pollutant",K2082*J2082/10^12,IF(H2082="MMTCO2e",J2082,IF(H2082="MWh",J2082,0))) -> #N/A
A2083: Industrial Sector Energy Related Emissions after CCS[electricity if,agriculture and forestry 01T03,PM25] | B2083: Industrial Sector Energy Related Emissions after CCS | C2083: electricity if | D2083: agriculture and forestry 01T03 | E2083: PM25 | H2083: =INDEX('Vensim Variables'!$B:$B,MATCH(EPS!$B2083,'Vensim Variables'!$A:$A,0)) -> g pollutant | I2083: =IF(OR(C2083="CO2",C2083="CH4",C2083="N2O",C2083="F gases",C2083="VOC",C2083="CO",C2083="NOx",C2083="PM10",C2083="PM25",C2083="SOx",C2083="BC",C2083="OC"),C2083,IF(OR(D2083="CO2",D2083="CH4",D2083="N2O",D2083="F gases",D2083="VOC",D2083="CO",D2083="NOx",D2083="PM10",D2083="PM25",D2083="SOx",D2083="BC",D2083="OC"),D2083,IF(OR(E2083="CO2",E2083="CH4",E2083="N2O",E2083="F gases",E2083="VOC",E2083="CO",E2083="NOx",E2083="PM10",E2083="PM25",E2083="SOx",E2083="BC",E2083="OC"),E2083,"NA"))) -> PM25 | J2083: =INDEX(NoSettings!$C:$C,MATCH(EPS!$A2083,NoSettings!$A:$A,0)) -> #N/A | K2083: =INDEX(GWP!$C$2:$C$13,MATCH(EPS!I2083,GWP!$B$2:$B$13,0)) -> 0 | L2083: =IF(H2083="g pollutant",K2083*J2083/10^12,IF(H2083="MMTCO2e",J2083,IF(H2083="MWh",J2083,0))) -> #N/A
A2084: Industrial Sector Energy Related Emissions after CCS[electricity if,agriculture and forestry 01T03,SOx] | B2084: Industrial Sector Energy Related Emissions after CCS | C2084: electricity if | D2084: agriculture and forestry 01T03 | E2084: SOx | H2084: =INDEX('Vensim Variables'!$B:$B,MATCH(EPS!$B2084,'Vensim Variables'!$A:$A,0)) -> g pollutant | I2084: =IF(OR(C2084="CO2",C2084="CH4",C2084="N2O",C2084="F gases",C2084="VOC",C2084="CO",C2084="NOx",C2084="PM10",C2084="PM25",C2084="SOx",C2084="BC",C2084="OC"),C2084,IF(OR(D2084="CO2",D2084="CH4",D2084="N2O",D2084="F gases",D2084="VOC",D2084="CO",D2084="NOx",D2084="PM10",D2084="PM25",D2084="SOx",D2084="BC",D2084="OC"),D2084,IF(OR(E2084="CO2",E2084="CH4",E2084="N2O",E2084="F gases",E2084="VOC",E2084="CO",E2084="NOx",E2084="PM10",E2084="PM25",E2084="SOx",E2084="BC",E2084="OC"),E2084,"NA"))) -> SOx | J2084: =INDEX(NoSettings!$C:$C,MATCH(EPS!$A2084,NoSettings!$A:$A,0)) -> #N/A | K2084: =INDEX(GWP!$C$2:$C$13,MATCH(EPS!I2084,GWP!$B$2:$B$13,0)) -> 0 | L2084: =IF(H2084="g pollutant",K2084*J2084/10^12,IF(H2084="MMTCO2e",J2084,IF(H2084="MWh",J2084,0))) -> #N/A
A2085: Industrial Sector Energy Related Emissions after CCS[electricity if,agriculture and forestry 01T03,BC] | B2085: Industrial Sector Energy Related Emissions after CCS | C2085: electricity if | D2085: agriculture and forestry 01T03 | E2085: BC | H2085: =INDEX('Vensim Variables'!$B:$B,MATCH(EPS!$B2085,'Vensim Variables'!$A:$A,0)) -> g pollutant | I2085: =IF(OR(C2085="CO2",C2085="CH4",C2085="N2O",C2085="F gases",C2085="VOC",C2085="CO",C2085="NOx",C2085="PM10",C2085="PM25",C2085="SOx",C2085="BC",C2085="OC"),C2085,IF(OR(D2085="CO2",D2085="CH4",D2085="N2O",D2085="F gases",D2085="VOC",D2085="CO",D2085="NOx",D2085="PM10",D2085="PM25",D2085="SOx",D2085="BC",D2085="OC"),D2085,IF(OR(E2085="CO2",E2085="CH4",E2085="N2O",E2085="F gases",E2085="VOC",E2085="CO",E2085="NOx",E2085="PM10",E2085="PM25",E2085="SOx",E2085="BC",E2085="OC"),E2085,"NA"))) -> BC | J2085: =INDEX(NoSettings!$C:$C,MATCH(EPS!$A2085,NoSettings!$A:$A,0)) -> #N/A | K2085: =INDEX(GWP!$C$2:$C$13,MATCH(EPS!I2085,GWP!$B$2:$B$13,0)) -> 0 | L2085: =IF(H2085="g pollutant",K2085*J2085/10^12,IF(H2085="MMTCO2e",J2085,IF(H2085="MWh",J2085,0))) -> #N/A
A2086: Industrial Sector Energy Related Emissions after CCS[electricity if,agriculture and forestry 01T03,OC] | B2086: Industrial Sector Energy Related Emissions after CCS | C2086: electricity if | D2086: agriculture and forestry 01T03 | E2086: OC | H2086: =INDEX('Vensim Variables'!$B:$B,MATCH(EPS!$B2086,'Vensim Variables'!$A:$A,0)) -> g pollutant | I2086: =IF(OR(C2086="CO2",C2086="CH4",C2086="N2O",C2086="F gases",C2086="VOC",C2086="CO",C2086="NOx",C2086="PM10",C2086="PM25",C2086="SOx",C2086="BC",C2086="OC"),C2086,IF(OR(D2086="CO2",D2086="CH4",D2086="N2O",D2086="F gases",D2086="VOC",D2086="CO",D2086="NOx",D2086="PM10",D2086="PM25",D2086="SOx",D2086="BC",D2086="OC"),D2086,IF(OR(E2086="CO2",E2086="CH4",E2086="N2O",E2086="F gases",E2086="VOC",E2086="CO",E2086="NOx",E2086="PM10",E2086="PM25",E2086="SOx",E2086="BC",E2086="OC"),E2086,"NA"))) -> OC | J2086: =INDEX(NoSettings!$C:$C,MATCH(EPS!$A2086,NoSettings!$A:$A,0)) -> #N/A | K2086: =INDEX(GWP!$C$2:$C$13,MATCH(EPS!I2086,GWP!$B$2:$B$13,0)) -> 0 | L2086: =IF(H2086="g pollutant",K2086*J2086/10^12,IF(H2086="MMTCO2e",J2086,IF(H2086="MWh",J2086,0))) -> #N/A
A2087: Industrial Sector Energy Related Emissions after CCS[electricity if,agriculture and forestry 01T03,CH4] | B2087: Industrial Sector Energy Related Emissions after CCS | C2087: electricity if | D2087: agriculture and forestry 01T03 | E2087: CH4 | H2087: =INDEX('Vensim Variables'!$B:$B,MATCH(EPS!$B2087,'Vensim Variables'!$A:$A,0)) -> g pollutant | I2087: =IF(OR(C2087="CO2",C2087="CH4",C2087="N2O",C2087="F gases",C2087="VOC",C2087="CO",C2087="NOx",C2087="PM10",C2087="PM25",C2087="SOx",C2087="BC",C2087="OC"),C2087,IF(OR(D2087="CO2",D2087="CH4",D2087="N2O",D2087="F gases",D2087="VOC",D2087="CO",D2087="NOx",D2087="PM10",D2087="PM25",D2087="SOx",D2087="BC",D2087="OC"),D2087,IF(OR(E2087="CO2",E2087="CH4",E2087="N2O",E2087="F gases",E2087="VOC",E2087="CO",E2087="NOx",E2087="PM10",E2087="PM25",E2087="SOx",E2087="BC",E2087="OC"),E2087,"NA"))) -> CH4 | J2087: =INDEX(NoSettings!$C:$C,MATCH(EPS!$A2087,NoSettings!$A:$A,0)) -> #N/A | K2087: =INDEX(GWP!$C$2:$C$13,MATCH(EPS!I2087,GWP!$B$2:$B$13,0)) -> 28 | L2087: =IF(H2087="g pollutant",K2087*J2087/10^12,IF(H2087="MMTCO2e",J2087,IF(H2087="MWh",J2087,0))) -> #N/A
A2088: Industrial Sector Energy Related Emissions after CCS[electricity if,agriculture and forestry 01T03,N2O] | B2088: Industrial Sector Energy Related Emissions after CCS | C2088: electricity if | D2088: agriculture and forestry 01T03 | E2088: N2O | H2088: =INDEX('Vensim Variables'!$B:$B,MATCH(EPS!$B2088,'Vensim Variables'!$A:$A,0)) -> g pollutant | I2088: =IF(OR(C2088="CO2",C2088="CH4",C2088="N2O",C2088="F gases",C2088="VOC",C2088="CO",C2088="NOx",C2088="PM10",C2088="PM25",C2088="SOx",C2088="BC",C2088="OC"),C2088,IF(OR(D2088="CO2",D2088="CH4",D2088="N2O",D2088="F gases",D2088="VOC",D2088="CO",D2088="NOx",D2088="PM10",D2088="PM25",D2088="SOx",D2088="BC",D2088="OC"),D2088,IF(OR(E2088="CO2",E2088="CH4",E2088="N2O",E2088="F gases",E2088="VOC",E2088="CO",E2088="NOx",E2088="PM10",E2088="PM25",E2088="SOx",E2088="BC",E2088="OC"),E2088,"NA"))) -> N2O | J2088: =INDEX(NoSettings!$C:$C,MATCH(EPS!$A2088,NoSettings!$A:$A,0)) -> #N/A | K2088: =INDEX(GWP!$C$2:$C$13,MATCH(EPS!I2088,GWP!$B$2:$B$13,0)) -> 265 | L2088: =IF(H2088="g pollutant",K2088*J2088/10^12,IF(H2088="MMTCO2e",J2088,IF(H2088="MWh",J2088,0))) -> #N/A
A2089: Industrial Sector Energy Related Emissions after CCS[electricity if,agriculture and forestry 01T03,F gases] | B2089: Industrial Sector Energy Related Emissions after CCS | C2089: electricity if | D2089: agriculture and forestry 01T03 | E2089: F gases | H2089: =INDEX('Vensim Variables'!$B:$B,MATCH(EPS!$B2089,'Vensim Variables'!$A:$A,0)) -> g pollutant | I2089: =IF(OR(C2089="CO2",C2089="CH4",C2089="N2O",C2089="F gases",C2089="VOC",C2089="CO",C2089="NOx",C2089="PM10",C2089="PM25",C2089="SOx",C2089="BC",C2089="OC"),C2089,IF(OR(D2089="CO2",D2089="CH4",D2089="N2O",D2089="F gases",D2089="VOC",D2089="CO",D2089="NOx",D2089="PM10",D2089="PM25",D2089="SOx",D2089="BC",D2089="OC"),D2089,IF(OR(E2089="CO2",E2089="CH4",E2089="N2O",E2089="F gases",E2089="VOC",E2089="CO",E2089="NOx",E2089="PM10",E2089="PM25",E2089="SOx",E2089="BC",E2089="OC"),E2089,"NA"))) -> F gases | J2089: =INDEX(NoSettings!$C:$C,MATCH(EPS!$A2089,NoSettings!$A:$A,0)) -> #N/A | K2089: =INDEX(GWP!$C$2:$C$13,MATCH(EPS!I2089,GWP!$B$2:$B$13,0)) -> 1 | L2089: =IF(H2089="g pollutant",K2089*J2089/10^12,IF(H2089="MMTCO2e",J2089,IF(H2089="MWh",J2089,0))) -> #N/A
... A5077: Industrial Sector Energy Related Emissions after CCS[hydrogen if,construction 41T43,F gases] | B5077: Industrial Sector Energy Related Emissions after CCS | C5077: hydrogen if | D5077: construction 41T43 | E5077: F gases | H5077: =INDEX('Vensim Variables'!$B:$B,MATCH(EPS!$B5077,'Vensim Variables'!$A:$A,0)) -> g pollutant | I5077: =IF(OR(C5077="CO2",C5077="CH4",C5077="N2O",C5077="F gases",C5077="VOC",C5077="CO",C5077="NOx",C5077="PM10",C5077="PM25",C5077="SOx",C5077="BC",C5077="OC"),C5077,IF(OR(D5077="CO2",D5077="CH4",D5077="N2O",D5077="F gases",D5077="VOC",D5077="CO",D5077="NOx",D5077="PM10",D5077="PM25",D5077="SOx",D5077="BC",D5077="OC"),D5077,IF(OR(E5077="CO2",E5077="CH4",E5077="N2O",E5077="F gases",E5077="VOC",E5077="CO",E5077="NOx",E5077="PM10",E5077="PM25",E5077="SOx",E5077="BC",E5077="OC"),E5077,"NA"))) -> F gases | J5077: =INDEX(NoSettings!$C:$C,MATCH(EPS!$A5077,NoSettings!$A:$A,0)) -> #N/A | K5077: =INDEX(GWP!$C$2:$C$13,MATCH(EPS!I5077,GWP!$B$2:$B$13,0)) -> 1 | L5077: =IF(H5077="g pollutant",K5077*J5077/10^12,IF(H5077="MMTCO2e",J5077,IF(H5077="MWh",J5077,0))) -> #N/A
A5078: Industrial Sector Pollutant Emissions[agriculture and forestry 01T03,CO2] | B5078: Industrial Sector Pollutant Emissions | C5078: agriculture and forestry 01T03 | D5078: CO2 | H5078: =INDEX('Vensim Variables'!$B:$B,MATCH(EPS!$B5078,'Vensim Variables'!$A:$A,0)) -> g pollutant | I5078: =IF(OR(C5078="CO2",C5078="CH4",C5078="N2O",C5078="F gases",C5078="VOC",C5078="CO",C5078="NOx",C5078="PM10",C5078="PM25",C5078="SOx",C5078="BC",C5078="OC"),C5078,IF(OR(D5078="CO2",D5078="CH4",D5078="N2O",D5078="F gases",D5078="VOC",D5078="CO",D5078="NOx",D5078="PM10",D5078="PM25",D5078="SOx",D5078="BC",D5078="OC"),D5078,IF(OR(E5078="CO2",E5078="CH4",E5078="N2O",E5078="F gases",E5078="VOC",E5078="CO",E5078="NOx",E5078="PM10",E5078="PM25",E5078="SOx",E5078="BC",E5078="OC"),E5078,"NA"))) -> CO2 | J5078: =INDEX(NoSettings!$C:$C,MATCH(EPS!$A5078,NoSettings!$A:$A,0)) -> #N/A | K5078: =INDEX(GWP!$C$2:$C$13,MATCH(EPS!I5078,GWP!$B$2:$B$13,0)) -> 1 | L5078: =IF(H5078="g pollutant",K5078*J5078/10^12,IF(H5078="MMTCO2e",J5078,IF(H5078="MWh",J5078,0))) -> #N/A
A5079: Industrial Sector Pollutant Emissions[agriculture and forestry 01T03,VOC] | B5079: Industrial Sector Pollutant Emissions | C5079: agriculture and forestry 01T03 | D5079: VOC | H5079: =INDEX('Vensim Variables'!$B:$B,MATCH(EPS!$B5079,'Vensim Variables'!$A:$A,0)) -> g pollutant | I5079: =IF(OR(C5079="CO2",C5079="CH4",C5079="N2O",C5079="F gases",C5079="VOC",C5079="CO",C5079="NOx",C5079="PM10",C5079="PM25",C5079="SOx",C5079="BC",C5079="OC"),C5079,IF(OR(D5079="CO2",D5079="CH4",D5079="N2O",D5079="F gases",D5079="VOC",D5079="CO",D5079="NOx",D5079="PM10",D5079="PM25",D5079="SOx",D5079="BC",D5079="OC"),D5079,IF(OR(E5079="CO2",E5079="CH4",E5079="N2O",E5079="F gases",E5079="VOC",E5079="CO",E5079="NOx",E5079="PM10",E5079="PM25",E5079="SOx",E5079="BC",E5079="OC"),E5079,"NA"))) -> VOC | J5079: =INDEX(NoSettings!$C:$C,MATCH(EPS!$A5079,NoSettings!$A:$A,0)) -> #N/A | K5079: =INDEX(GWP!$C$2:$C$13,MATCH(EPS!I5079,GWP!$B$2:$B$13,0)) -> 0 | L5079: =IF(H5079="g pollutant",K5079*J5079/10^12,IF(H5079="MMTCO2e",J5079,IF(H5079="MWh",J5079,0))) -> #N/A
A5080: Industrial Sector Pollutant Emissions[agriculture and forestry 01T03,CO] | B5080: Industrial Sector Pollutant Emissions | C5080: agriculture and forestry 01T03 | D5080: CO | H5080: =INDEX('Vensim Variables'!$B:$B,MATCH(EPS!$B5080,'Vensim Variables'!$A:$A,0)) -> g pollutant | I5080: =IF(OR(C5080="CO2",C5080="CH4",C5080="N2O",C5080="F gases",C5080="VOC",C5080="CO",C5080="NOx",C5080="PM10",C5080="PM25",C5080="SOx",C5080="BC",C5080="OC"),C5080,IF(OR(D5080="CO2",D5080="CH4",D5080="N2O",D5080="F gases",D5080="VOC",D5080="CO",D5080="NOx",D5080="PM10",D5080="PM25",D5080="SOx",D5080="BC",D5080="OC"),D5080,IF(OR(E5080="CO2",E5080="CH4",E5080="N2O",E5080="F gases",E5080="VOC",E5080="CO",E5080="NOx",E5080="PM10",E5080="PM25",E5080="SOx",E5080="BC",E5080="OC"),E5080,"NA"))) -> CO | J5080: =INDEX(NoSettings!$C:$C,MATCH(EPS!$A5080,NoSettings!$A:$A,0)) -> #N/A | K5080: =INDEX(GWP!$C$2:$C$13,MATCH(EPS!I5080,GWP!$B$2:$B$13,0)) -> 0 | L5080: =IF(H5080="g pollutant",K5080*J5080/10^12,IF(H5080="MMTCO2e",J5080,IF(H5080="MWh",J5080,0))) -> #N/A
A5081: Industrial Sector Pollutant Emissions[agriculture and forestry 01T03,NOx] | B5081: Industrial Sector Pollutant Emissions | C5081: agriculture and forestry 01T03 | D5081: NOx | H5081: =INDEX('Vensim Variables'!$B:$B,MATCH(EPS!$B5081,'Vensim Variables'!$A:$A,0)) -> g pollutant | I5081: =IF(OR(C5081="CO2",C5081="CH4",C5081="N2O",C5081="F gases",C5081="VOC",C5081="CO",C5081="NOx",C5081="PM10",C5081="PM25",C5081="SOx",C5081="BC",C5081="OC"),C5081,IF(OR(D5081="CO2",D5081="CH4",D5081="N2O",D5081="F gases",D5081="VOC",D5081="CO",D5081="NOx",D5081="PM10",D5081="PM25",D5081="SOx",D5081="BC",D5081="OC"),D5081,IF(OR(E5081="CO2",E5081="CH4",E5081="N2O",E5081="F gases",E5081="VOC",E5081="CO",E5081="NOx",E5081="PM10",E5081="PM25",E5081="SOx",E5081="BC",E5081="OC"),E5081,"NA"))) -> NOx | J5081: =INDEX(NoSettings!$C:$C,MATCH(EPS!$A5081,NoSettings!$A:$A,0)) -> #N/A | K5081: =INDEX(GWP!$C$2:$C$13,MATCH(EPS!I5081,GWP!$B$2:$B$13,0)) -> 0 | L5081: =IF(H5081="g pollutant",K5081*J5081/10^12,IF(H5081="MMTCO2e",J5081,IF(H5081="MWh",J5081,0))) -> #N/A
A5082: Industrial Sector Pollutant Emissions[agriculture and forestry 01T03,PM10] | B5082: Industrial Sector Pollutant Emissions | C5082: agriculture and forestry 01T03 | D5082: PM10 | H5082: =INDEX('Vensim Variables'!$B:$B,MATCH(EPS!$B5082,'Vensim Variables'!$A:$A,0)) -> g pollutant | I5082: =IF(OR(C5082="CO2",C5082="CH4",C5082="N2O",C5082="F gases",C5082="VOC",C5082="CO",C5082="NOx",C5082="PM10",C5082="PM25",C5082="SOx",C5082="BC",C5082="OC"),C5082,IF(OR(D5082="CO2",D5082="CH4",D5082="N2O",D5082="F gases",D5082="VOC",D5082="CO",D5082="NOx",D5082="PM10",D5082="PM25",D5082="SOx",D5082="BC",D5082="OC"),D5082,IF(OR(E5082="CO2",E5082="CH4",E5082="N2O",E5082="F gases",E5082="VOC",E5082="CO",E5082="NOx",E5082="PM10",E5082="PM25",E5082="SOx",E5082="BC",E5082="OC"),E5082,"NA"))) -> PM10 | J5082: =INDEX(NoSettings!$C:$C,MATCH(EPS!$A5082,NoSettings!$A:$A,0)) -> #N/A | K5082: =INDEX(GWP!$C$2:$C$13,MATCH(EPS!I5082,GWP!$B$2:$B$13,0)) -> 0 | L5082: =IF(H5082="g pollutant",K5082*J5082/10^12,IF(H5082="MMTCO2e",J5082,IF(H5082="MWh",J5082,0))) -> #N/A
A5083: Industrial Sector Pollutant Emissions[agriculture and forestry 01T03,PM25] | B5083: Industrial Sector Pollutant Emissions | C5083: agriculture and forestry 01T03 | D5083: PM25 | H5083: =INDEX('Vensim Variables'!$B:$B,MATCH(EPS!$B5083,'Vensim Variables'!$A:$A,0)) -> g pollutant | I5083: =IF(OR(C5083="CO2",C5083="CH4",C5083="N2O",C5083="F gases",C5083="VOC",C5083="CO",C5083="NOx",C5083="PM10",C5083="PM25",C5083="SOx",C5083="BC",C5083="OC"),C5083,IF(OR(D5083="CO2",D5083="CH4",D5083="N2O",D5083="F gases",D5083="VOC",D5083="CO",D5083="NOx",D5083="PM10",D5083="PM25",D5083="SOx",D5083="BC",D5083="OC"),D5083,IF(OR(E5083="CO2",E5083="CH4",E5083="N2O",E5083="F gases",E5083="VOC",E5083="CO",E5083="NOx",E5083="PM10",E5083="PM25",E5083="SOx",E5083="BC",E5083="OC"),E5083,"NA"))) -> PM25 | J5083: =INDEX(NoSettings!$C:$C,MATCH(EPS!$A5083,NoSettings!$A:$A,0)) -> #N/A | K5083: =INDEX(GWP!$C$2:$C$13,MATCH(EPS!I5083,GWP!$B$2:$B$13,0)) -> 0 | L5083: =IF(H5083="g pollutant",K5083*J5083/10^12,IF(H5083="MMTCO2e",J5083,IF(H5083="MWh",J5083,0))) -> #N/A
A5084: Industrial Sector Pollutant Emissions[agriculture and forestry 01T03,SOx] | B5084: Industrial Sector Pollutant Emissions | C5084: agriculture and forestry 01T03 | D5084: SOx | H5084: =INDEX('Vensim Variables'!$B:$B,MATCH(EPS!$B5084,'Vensim Variables'!$A:$A,0)) -> g pollutant | I5084: =IF(OR(C5084="CO2",C5084="CH4",C5084="N2O",C5084="F gases",C5084="VOC",C5084="CO",C5084="NOx",C5084="PM10",C5084="PM25",C5084="SOx",C5084="BC",C5084="OC"),C5084,IF(OR(D5084="CO2",D5084="CH4",D5084="N2O",D5084="F gases",D5084="VOC",D5084="CO",D5084="NOx",D5084="PM10",D5084="PM25",D5084="SOx",D5084="BC",D5084="OC"),D5084,IF(OR(E5084="CO2",E5084="CH4",E5084="N2O",E5084="F gases",E5084="VOC",E5084="CO",E5084="NOx",E5084="PM10",E5084="PM25",E5084="SOx",E5084="BC",E5084="OC"),E5084,"NA"))) -> SOx | J5084: =INDEX(NoSettings!$C:$C,MATCH(EPS!$A5084,NoSettings!$A:$A,0)) -> #N/A | K5084: =INDEX(GWP!$C$2:$C$13,MATCH(EPS!I5084,GWP!$B$2:$B$13,0)) -> 0 | L5084: =IF(H5084="g pollutant",K5084*J5084/10^12,IF(H5084="MMTCO2e",J5084,IF(H5084="MWh",J5084,0))) -> #N/A
A5085: Industrial Sector Pollutant Emissions[agriculture and forestry 01T03,BC] | B5085: Industrial Sector Pollutant Emissions | C5085: agriculture and forestry 01T03 | D5085: BC | H5085: =INDEX('Vensim Variables'!$B:$B,MATCH(EPS!$B5085,'Vensim Variables'!$A:$A,0)) -> g pollutant | I5085: =IF(OR(C5085="CO2",C5085="CH4",C5085="N2O",C5085="F gases",C5085="VOC",C5085="CO",C5085="NOx",C5085="PM10",C5085="PM25",C5085="SOx",C5085="BC",C5085="OC"),C5085,IF(OR(D5085="CO2",D5085="CH4",D5085="N2O",D5085="F gases",D5085="VOC",D5085="CO",D5085="NOx",D5085="PM10",D5085="PM25",D5085="SOx",D5085="BC",D5085="OC"),D5085,IF(OR(E5085="CO2",E5085="CH4",E5085="N2O",E5085="F gases",E5085="VOC",E5085="CO",E5085="NOx",E5085="PM10",E5085="PM25",E5085="SOx",E5085="BC",E5085="OC"),E5085,"NA"))) -> BC | J5085: =INDEX(NoSettings!$C:$C,MATCH(EPS!$A5085,NoSettings!$A:$A,0)) -> #N/A | K5085: =INDEX(GWP!$C$2:$C$13,MATCH(EPS!I5085,GWP!$B$2:$B$13,0)) -> 0 | L5085: =IF(H5085="g pollutant",K5085*J5085/10^12,IF(H5085="MMTCO2e",J5085,IF(H5085="MWh",J5085,0))) -> #N/A
A5086: Industrial Sector Pollutant Emissions[agriculture and forestry 01T03,OC] | B5086: Industrial Sector Pollutant Emissions | C5086: agriculture and forestry 01T03 | D5086: OC | H5086: =INDEX('Vensim Variables'!$B:$B,MATCH(EPS!$B5086,'Vensim Variables'!$A:$A,0)) -> g pollutant | I5086: =IF(OR(C5086="CO2",C5086="CH4",C5086="N2O",C5086="F gases",C5086="VOC",C5086="CO",C5086="NOx",C5086="PM10",C5086="PM25",C5086="SOx",C5086="BC",C5086="OC"),C5086,IF(OR(D5086="CO2",D5086="CH4",D5086="N2O",D5086="F gases",D5086="VOC",D5086="CO",D5086="NOx",D5086="PM10",D5086="PM25",D5086="SOx",D5086="BC",D5086="OC"),D5086,IF(OR(E5086="CO2",E5086="CH4",E5086="N2O",E5086="F gases",E5086="VOC",E5086="CO",E5086="NOx",E5086="PM10",E5086="PM25",E5086="SOx",E5086="BC",E5086="OC"),E5086,"NA"))) -> OC | J5086: =INDEX(NoSettings!$C:$C,MATCH(EPS!$A5086,NoSettings!$A:$A,0)) -> #N/A | K5086: =INDEX(GWP!$C$2:$C$13,MATCH(EPS!I5086,GWP!$B$2:$B$13,0)) -> 0 | L5086: =IF(H5086="g pollutant",K5086*J5086/10^12,IF(H5086="MMTCO2e",J5086,IF(H5086="MWh",J5086,0))) -> #N/A
A5087: Industrial Sector Pollutant Emissions[agriculture and forestry 01T03,CH4] | B5087: Industrial Sector Pollutant Emissions | C5087: agriculture and forestry 01T03 | D5087: CH4 | H5087: =INDEX('Vensim Variables'!$B:$B,MATCH(EPS!$B5087,'Vensim Variables'!$A:$A,0)) -> g pollutant | I5087: =IF(OR(C5087="CO2",C5087="CH4",C5087="N2O",C5087="F gases",C5087="VOC",C5087="CO",C5087="NOx",C5087="PM10",C5087="PM25",C5087="SOx",C5087="BC",C5087="OC"),C5087,IF(OR(D5087="CO2",D5087="CH4",D5087="N2O",D5087="F gases",D5087="VOC",D5087="CO",D5087="NOx",D5087="PM10",D5087="PM25",D5087="SOx",D5087="BC",D5087="OC"),D5087,IF(OR(E5087="CO2",E5087="CH4",E5087="N2O",E5087="F gases",E5087="VOC",E5087="CO",E5087="NOx",E5087="PM10",E5087="PM25",E5087="SOx",E5087="BC",E5087="OC"),E5087,"NA"))) -> CH4 | J5087: =INDEX(NoSettings!$C:$C,MATCH(EPS!$A5087,NoSettings!$A:$A,0)) -> #N/A | K5087: =INDEX(GWP!$C$2:$C$13,MATCH(EPS!I5087,GWP!$B$2:$B$13,0)) -> 28 | L5087: =IF(H5087="g pollutant",K5087*J5087/10^12,IF(H5087="MMTCO2e",J5087,IF(H5087="MWh",J5087,0))) -> #N/A
A5088: Industrial Sector Pollutant Emissions[agriculture and forestry 01T03,N2O] | B5088: Industrial Sector Pollutant Emissions | C5088: agriculture and forestry 01T03 | D5088: N2O | H5088: =INDEX('Vensim Variables'!$B:$B,MATCH(EPS!$B5088,'Vensim Variables'!$A:$A,0)) -> g pollutant | I5088: =IF(OR(C5088="CO2",C5088="CH4",C5088="N2O",C5088="F gases",C5088="VOC",C5088="CO",C5088="NOx",C5088="PM10",C5088="PM25",C5088="SOx",C5088="BC",C5088="OC"),C5088,IF(OR(D5088="CO2",D5088="CH4",D5088="N2O",D5088="F gases",D5088="VOC",D5088="CO",D5088="NOx",D5088="PM10",D5088="PM25",D5088="SOx",D5088="BC",D5088="OC"),D5088,IF(OR(E5088="CO2",E5088="CH4",E5088="N2O",E5088="F gases",E5088="VOC",E5088="CO",E5088="NOx",E5088="PM10",E5088="PM25",E5088="SOx",E5088="BC",E5088="OC"),E5088,"NA"))) -> N2O | J5088: =INDEX(NoSettings!$C:$C,MATCH(EPS!$A5088,NoSettings!$A:$A,0)) -> #N/A | K5088: =INDEX(GWP!$C$2:$C$13,MATCH(EPS!I5088,GWP!$B$2:$B$13,0)) -> 265 | L5088: =IF(H5088="g pollutant",K5088*J5088/10^12,IF(H5088="MMTCO2e",J5088,IF(H5088="MWh",J5088,0))) -> #N/A
A5089: Industrial Sector Pollutant Emissions[agriculture and forestry 01T03,F gases] | B5089: Industrial Sector Pollutant Emissions | C5089: agriculture and forestry 01T03 | D5089: F gases | H5089: =INDEX('Vensim Variables'!$B:$B,MATCH(EPS!$B5089,'Vensim Variables'!$A:$A,0)) -> g pollutant | I5089: =IF(OR(C5089="CO2",C5089="CH4",C5089="N2O",C5089="F gases",C5089="VOC",C5089="CO",C5089="NOx",C5089="PM10",C5089="PM25",C5089="SOx",C5089="BC",C5089="OC"),C5089,IF(OR(D5089="CO2",D5089="CH4",D5089="N2O",D5089="F gases",D5089="VOC",D5089="CO",D5089="NOx",D5089="PM10",D5089="PM25",D5089="SOx",D5089="BC",D5089="OC"),D5089,IF(OR(E5089="CO2",E5089="CH4",E5089="N2O",E5089="F gases",E5089="VOC",E5089="CO",E5089="NOx",E5089="PM10",E5089="PM25",E5089="SOx",E5089="BC",E5089="OC"),E5089,"NA"))) -> F gases | J5089: =INDEX(NoSettings!$C:$C,MATCH(EPS!$A5089,NoSettings!$A:$A,0)) -> #N/A | K5089: =INDEX(GWP!$C$2:$C$13,MATCH(EPS!I5089,GWP!$B$2:$B$13,0)) -> 1 | L5089: =IF(H5089="g pollutant",K5089*J5089/10^12,IF(H5089="MMTCO2e",J5089,IF(H5089="MWh",J5089,0))) -> #N/A
... A5377: Industrial Sector Pollutant Emissions[construction 41T43,F gases] | B5377: Industrial Sector Pollutant Emissions | C5377: construction 41T43 | D5377: F gases | H5377: =INDEX('Vensim Variables'!$B:$B,MATCH(EPS!$B5377,'Vensim Variables'!$A:$A,0)) -> g pollutant | I5377: =IF(OR(C5377="CO2",C5377="CH4",C5377="N2O",C5377="F gases",C5377="VOC",C5377="CO",C5377="NOx",C5377="PM10",C5377="PM25",C5377="SOx",C5377="BC",C5377="OC"),C5377,IF(OR(D5377="CO2",D5377="CH4",D5377="N2O",D5377="F gases",D5377="VOC",D5377="CO",D5377="NOx",D5377="PM10",D5377="PM25",D5377="SOx",D5377="BC",D5377="OC"),D5377,IF(OR(E5377="CO2",E5377="CH4",E5377="N2O",E5377="F gases",E5377="VOC",E5377="CO",E5377="NOx",E5377="PM10",E5377="PM25",E5377="SOx",E5377="BC",E5377="OC"),E5377,"NA"))) -> F gases | J5377: =INDEX(NoSettings!$C:$C,MATCH(EPS!$A5377,NoSettings!$A:$A,0)) -> #N/A | K5377: =INDEX(GWP!$C$2:$C$13,MATCH(EPS!I5377,GWP!$B$2:$B$13,0)) -> 1 | L5377: =IF(H5377="g pollutant",K5377*J5377/10^12,IF(H5377="MMTCO2e",J5377,IF(H5377="MWh",J5377,0))) -> #N/A
A5378: Output Total CO2e Emissions by Sector[transportation sector] | B5378: Output Total CO2e Emissions by Sector | C5378: transportation sector | H5378: =INDEX('Vensim Variables'!$B:$B,MATCH(EPS!$B5378,'Vensim Variables'!$A:$A,0)) -> MMTCO2e | I5378: =IF(OR(C5378="CO2",C5378="CH4",C5378="N2O",C5378="F gases",C5378="VOC",C5378="CO",C5378="NOx",C5378="PM10",C5378="PM25",C5378="SOx",C5378="BC",C5378="OC"),C5378,IF(OR(D5378="CO2",D5378="CH4",D5378="N2O",D5378="F gases",D5378="VOC",D5378="CO",D5378="NOx",D5378="PM10",D5378="PM25",D5378="SOx",D5378="BC",D5378="OC"),D5378,IF(OR(E5378="CO2",E5378="CH4",E5378="N2O",E5378="F gases",E5378="VOC",E5378="CO",E5378="NOx",E5378="PM10",E5378="PM25",E5378="SOx",E5378="BC",E5378="OC"),E5378,"NA"))) -> NA | J5378: =INDEX(NoSettings!$C:$C,MATCH(EPS!$A5378,NoSettings!$A:$A,0)) -> #N/A | K5378: =INDEX(GWP!$C$2:$C$13,MATCH(EPS!I5378,GWP!$B$2:$B$13,0)) -> #N/A | L5378: =IF(H5378="g pollutant",K5378*J5378/10^12,IF(H5378="MMTCO2e",J5378,IF(H5378="MWh",J5378,0))) -> #N/A
A5379: Output Total CO2e Emissions by Sector[electricity sector] | B5379: Output Total CO2e Emissions by Sector | C5379: electricity sector | H5379: =INDEX('Vensim Variables'!$B:$B,MATCH(EPS!$B5379,'Vensim Variables'!$A:$A,0)) -> MMTCO2e | I5379: =IF(OR(C5379="CO2",C5379="CH4",C5379="N2O",C5379="F gases",C5379="VOC",C5379="CO",C5379="NOx",C5379="PM10",C5379="PM25",C5379="SOx",C5379="BC",C5379="OC"),C5379,IF(OR(D5379="CO2",D5379="CH4",D5379="N2O",D5379="F gases",D5379="VOC",D5379="CO",D5379="NOx",D5379="PM10",D5379="PM25",D5379="SOx",D5379="BC",D5379="OC"),D5379,IF(OR(E5379="CO2",E5379="CH4",E5379="N2O",E5379="F gases",E5379="VOC",E5379="CO",E5379="NOx",E5379="PM10",E5379="PM25",E5379="SOx",E5379="BC",E5379="OC"),E5379,"NA"))) -> NA | J5379: =INDEX(NoSettings!$C:$C,MATCH(EPS!$A5379,NoSettings!$A:$A,0)) -> #N/A | K5379: =INDEX(GWP!$C$2:$C$13,MATCH(EPS!I5379,GWP!$B$2:$B$13,0)) -> #N/A | L5379: =IF(H5379="g pollutant",K5379*J5379/10^12,IF(H5379="MMTCO2e",J5379,IF(H5379="MWh",J5379,0))) -> #N/A
A5380: Output Total CO2e Emissions by Sector[district heat and hydrogen sector] | B5380: Output Total CO2e Emissions by Sector | C5380: district heat and hydrogen sector | H5380: =INDEX('Vensim Variables'!$B:$B,MATCH(EPS!$B5380,'Vensim Variables'!$A:$A,0)) -> MMTCO2e | I5380: =IF(OR(C5380="CO2",C5380="CH4",C5380="N2O",C5380="F gases",C5380="VOC",C5380="CO",C5380="NOx",C5380="PM10",C5380="PM25",C5380="SOx",C5380="BC",C5380="OC"),C5380,IF(OR(D5380="CO2",D5380="CH4",D5380="N2O",D5380="F gases",D5380="VOC",D5380="CO",D5380="NOx",D5380="PM10",D5380="PM25",D5380="SOx",D5380="BC",D5380="OC"),D5380,IF(OR(E5380="CO2",E5380="CH4",E5380="N2O",E5380="F gases",E5380="VOC",E5380="CO",E5380="NOx",E5380="PM10",E5380="PM25",E5380="SOx",E5380="BC",E5380="OC"),E5380,"NA"))) -> NA | J5380: =INDEX(NoSettings!$C:$C,MATCH(EPS!$A5380,NoSettings!$A:$A,0)) -> #N/A | K5380: =INDEX(GWP!$C$2:$C$13,MATCH(EPS!I5380,GWP!$B$2:$B$13,0)) -> #N/A | L5380: =IF(H5380="g pollutant",K5380*J5380/10^12,IF(H5380="MMTCO2e",J5380,IF(H5380="MWh",J5380,0))) -> #N/A
A5381: Output Total CO2e Emissions by Sector[LULUCF sector] | B5381: Output Total CO2e Emissions by Sector | C5381: LULUCF sector | H5381: =INDEX('Vensim Variables'!$B:$B,MATCH(EPS!$B5381,'Vensim Variables'!$A:$A,0)) -> MMTCO2e | I5381: =IF(OR(C5381="CO2",C5381="CH4",C5381="N2O",C5381="F gases",C5381="VOC",C5381="CO",C5381="NOx",C5381="PM10",C5381="PM25",C5381="SOx",C5381="BC",C5381="OC"),C5381,IF(OR(D5381="CO2",D5381="CH4",D5381="N2O",D5381="F gases",D5381="VOC",D5381="CO",D5381="NOx",D5381="PM10",D5381="PM25",D5381="SOx",D5381="BC",D5381="OC"),D5381,IF(OR(E5381="CO2",E5381="CH4",E5381="N2O",E5381="F gases",E5381="VOC",E5381="CO",E5381="NOx",E5381="PM10",E5381="PM25",E5381="SOx",E5381="BC",E5381="OC"),E5381,"NA"))) -> NA | J5381: =INDEX(NoSettings!$C:$C,MATCH(EPS!$A5381,NoSettings!$A:$A,0)) -> #N/A | K5381: =INDEX(GWP!$C$2:$C$13,MATCH(EPS!I5381,GWP!$B$2:$B$13,0)) -> #N/A | L5381: =IF(H5381="g pollutant",K5381*J5381/10^12,IF(H5381="MMTCO2e",J5381,IF(H5381="MWh",J5381,0))) -> #N/A
A5382: Output Total CO2e Emissions by Sector[geoengineering sector] | B5382: Output Total CO2e Emissions by Sector | C5382: geoengineering sector | H5382: =INDEX('Vensim Variables'!$B:$B,MATCH(EPS!$B5382,'Vensim Variables'!$A:$A,0)) -> MMTCO2e | I5382: =IF(OR(C5382="CO2",C5382="CH4",C5382="N2O",C5382="F gases",C5382="VOC",C5382="CO",C5382="NOx",C5382="PM10",C5382="PM25",C5382="SOx",C5382="BC",C5382="OC"),C5382,IF(OR(D5382="CO2",D5382="CH4",D5382="N2O",D5382="F gases",D5382="VOC",D5382="CO",D5382="NOx",D5382="PM10",D5382="PM25",D5382="SOx",D5382="BC",D5382="OC"),D5382,IF(OR(E5382="CO2",E5382="CH4",E5382="N2O",E5382="F gases",E5382="VOC",E5382="CO",E5382="NOx",E5382="PM10",E5382="PM25",E5382="SOx",E5382="BC",E5382="OC"),E5382,"NA"))) -> NA | J5382: =INDEX(NoSettings!$C:$C,MATCH(EPS!$A5382,NoSettings!$A:$A,0)) -> #N/A | K5382: =INDEX(GWP!$C$2:$C$13,MATCH(EPS!I5382,GWP!$B$2:$B$13,0)) -> #N/A | L5382: =IF(H5382="g pollutant",K5382*J5382/10^12,IF(H5382="MMTCO2e",J5382,IF(H5382="MWh",J5382,0))) -> #N/A
A5383: Output Industry Sector Process Emissions in CO2e Excluding Ag and Waste | B5383: Output Industry Sector Process Emissions in CO2e Excluding Ag and Waste | H5383: =INDEX('Vensim Variables'!$B:$B,MATCH(EPS!$B5383,'Vensim Variables'!$A:$A,0)) -> MMTCO2e | I5383: =IF(OR(C5383="CO2",C5383="CH4",C5383="N2O",C5383="F gases",C5383="VOC",C5383="CO",C5383="NOx",C5383="PM10",C5383="PM25",C5383="SOx",C5383="BC",C5383="OC"),C5383,IF(OR(D5383="CO2",D5383="CH4",D5383="N2O",D5383="F gases",D5383="VOC",D5383="CO",D5383="NOx",D5383="PM10",D5383="PM25",D5383="SOx",D5383="BC",D5383="OC"),D5383,IF(OR(E5383="CO2",E5383="CH4",E5383="N2O",E5383="F gases",E5383="VOC",E5383="CO",E5383="NOx",E5383="PM10",E5383="PM25",E5383="SOx",E5383="BC",E5383="OC"),E5383,"NA"))) -> NA | J5383: =INDEX(NoSettings!$C:$C,MATCH(EPS!$A5383,NoSettings!$A:$A,0)) -> #N/A | K5383: =INDEX(GWP!$C$2:$C$13,MATCH(EPS!I5383,GWP!$B$2:$B$13,0)) -> #N/A | L5383: =IF(H5383="g pollutant",K5383*J5383/10^12,IF(H5383="MMTCO2e",J5383,IF(H5383="MWh",J5383,0))) -> #N/A
A5384: Output Industry Sector Energy Related CO2e Emissions Excluding Ag and Waste | B5384: Output Industry Sector Energy Related CO2e Emissions Excluding Ag and Waste | H5384: =INDEX('Vensim Variables'!$B:$B,MATCH(EPS!$B5384,'Vensim Variables'!$A:$A,0)) -> MMTCO2e | I5384: =IF(OR(C5384="CO2",C5384="CH4",C5384="N2O",C5384="F gases",C5384="VOC",C5384="CO",C5384="NOx",C5384="PM10",C5384="PM25",C5384="SOx",C5384="BC",C5384="OC"),C5384,IF(OR(D5384="CO2",D5384="CH4",D5384="N2O",D5384="F gases",D5384="VOC",D5384="CO",D5384="NOx",D5384="PM10",D5384="PM25",D5384="SOx",D5384="BC",D5384="OC"),D5384,IF(OR(E5384="CO2",E5384="CH4",E5384="N2O",E5384="F gases",E5384="VOC",E5384="CO",E5384="NOx",E5384="PM10",E5384="PM25",E5384="SOx",E5384="BC",E5384="OC"),E5384,"NA"))) -> NA | J5384: =INDEX(NoSettings!$C:$C,MATCH(EPS!$A5384,NoSettings!$A:$A,0)) -> #N/A | K5384: =INDEX(GWP!$C$2:$C$13,MATCH(EPS!I5384,GWP!$B$2:$B$13,0)) -> #N/A | L5384: =IF(H5384="g pollutant",K5384*J5384/10^12,IF(H5384="MMTCO2e",J5384,IF(H5384="MWh",J5384,0))) -> #N/A
A5385: Output Agriculture CO2e Emissions | B5385: Output Agriculture CO2e Emissions | H5385: =INDEX('Vensim Variables'!$B:$B,MATCH(EPS!$B5385,'Vensim Variables'!$A:$A,0)) -> MMTCO2e | I5385: =IF(OR(C5385="CO2",C5385="CH4",C5385="N2O",C5385="F gases",C5385="VOC",C5385="CO",C5385="NOx",C5385="PM10",C5385="PM25",C5385="SOx",C5385="BC",C5385="OC"),C5385,IF(OR(D5385="CO2",D5385="CH4",D5385="N2O",D5385="F gases",D5385="VOC",D5385="CO",D5385="NOx",D5385="PM10",D5385="PM25",D5385="SOx",D5385="BC",D5385="OC"),D5385,IF(OR(E5385="CO2",E5385="CH4",E5385="N2O",E5385="F gases",E5385="VOC",E5385="CO",E5385="NOx",E5385="PM10",E5385="PM25",E5385="SOx",E5385="BC",E5385="OC"),E5385,"NA"))) -> NA | J5385: =INDEX(NoSettings!$C:$C,MATCH(EPS!$A5385,NoSettings!$A:$A,0)) -> #N/A | K5385: =INDEX(GWP!$C$2:$C$13,MATCH(EPS!I5385,GWP!$B$2:$B$13,0)) -> #N/A | L5385: =IF(H5385="g pollutant",K5385*J5385/10^12,IF(H5385="MMTCO2e",J5385,IF(H5385="MWh",J5385,0))) -> #N/A
A5386: Output Waste Management CO2e Emissions | B5386: Output Waste Management CO2e Emissions | H5386: =INDEX('Vensim Variables'!$B:$B,MATCH(EPS!$B5386,'Vensim Variables'!$A:$A,0)) -> MMTCO2e | I5386: =IF(OR(C5386="CO2",C5386="CH4",C5386="N2O",C5386="F gases",C5386="VOC",C5386="CO",C5386="NOx",C5386="PM10",C5386="PM25",C5386="SOx",C5386="BC",C5386="OC"),C5386,IF(OR(D5386="CO2",D5386="CH4",D5386="N2O",D5386="F gases",D5386="VOC",D5386="CO",D5386="NOx",D5386="PM10",D5386="PM25",D5386="SOx",D5386="BC",D5386="OC"),D5386,IF(OR(E5386="CO2",E5386="CH4",E5386="N2O",E5386="F gases",E5386="VOC",E5386="CO",E5386="NOx",E5386="PM10",E5386="PM25",E5386="SOx",E5386="BC",E5386="OC"),E5386,"NA"))) -> NA | J5386: =INDEX(NoSettings!$C:$C,MATCH(EPS!$A5386,NoSettings!$A:$A,0)) -> #N/A | K5386: =INDEX(GWP!$C$2:$C$13,MATCH(EPS!I5386,GWP!$B$2:$B$13,0)) -> #N/A | L5386: =IF(H5386="g pollutant",K5386*J5386/10^12,IF(H5386="MMTCO2e",J5386,IF(H5386="MWh",J5386,0))) -> #N/A
A5387: Output Buildings Sector CO2e Emissions | B5387: Output Buildings Sector CO2e Emissions | H5387: =INDEX('Vensim Variables'!$B:$B,MATCH(EPS!$B5387,'Vensim Variables'!$A:$A,0)) -> MMTCO2e | I5387: =IF(OR(C5387="CO2",C5387="CH4",C5387="N2O",C5387="F gases",C5387="VOC",C5387="CO",C5387="NOx",C5387="PM10",C5387="PM25",C5387="SOx",C5387="BC",C5387="OC"),C5387,IF(OR(D5387="CO2",D5387="CH4",D5387="N2O",D5387="F gases",D5387="VOC",D5387="CO",D5387="NOx",D5387="PM10",D5387="PM25",D5387="SOx",D5387="BC",D5387="OC"),D5387,IF(OR(E5387="CO2",E5387="CH4",E5387="N2O",E5387="F gases",E5387="VOC",E5387="CO",E5387="NOx",E5387="PM10",E5387="PM25",E5387="SOx",E5387="BC",E5387="OC"),E5387,"NA"))) -> NA | J5387: =INDEX(NoSettings!$C:$C,MATCH(EPS!$A5387,NoSettings!$A:$A,0)) -> #N/A | K5387: =INDEX(GWP!$C$2:$C$13,MATCH(EPS!I5387,GWP!$B$2:$B$13,0)) -> #N/A | L5387: =IF(H5387="g pollutant",K5387*J5387/10^12,IF(H5387="MMTCO2e",J5387,IF(H5387="MWh",J5387,0))) -> #N/A
A5388: Electricity Generation by Type Including Distributed Generation[hard coal es] | B5388: Electricity Generation by Type Including Distributed Generation | C5388: hard coal es | H5388: =INDEX('Vensim Variables'!$B:$B,MATCH(EPS!$B5388,'Vensim Variables'!$A:$A,0)) -> MWh | I5388: =IF(OR(C5388="CO2",C5388="CH4",C5388="N2O",C5388="F gases",C5388="VOC",C5388="CO",C5388="NOx",C5388="PM10",C5388="PM25",C5388="SOx",C5388="BC",C5388="OC"),C5388,IF(OR(D5388="CO2",D5388="CH4",D5388="N2O",D5388="F gases",D5388="VOC",D5388="CO",D5388="NOx",D5388="PM10",D5388="PM25",D5388="SOx",D5388="BC",D5388="OC"),D5388,IF(OR(E5388="CO2",E5388="CH4",E5388="N2O",E5388="F gases",E5388="VOC",E5388="CO",E5388="NOx",E5388="PM10",E5388="PM25",E5388="SOx",E5388="BC",E5388="OC"),E5388,"NA"))) -> NA | J5388: =INDEX(NoSettings!$C:$C,MATCH(EPS!$A5388,NoSettings!$A:$A,0)) -> 756720000 | K5388: =INDEX(GWP!$C$2:$C$13,MATCH(EPS!I5388,GWP!$B$2:$B$13,0)) -> #N/A | L5388: =IF(H5388="g pollutant",K5388*J5388/10^12,IF(H5388="MMTCO2e",J5388,IF(H5388="MWh",J5388,0))) -> 756720000
A5389: Electricity Generation by Type Including Distributed Generation[natural gas steam turbine es] | B5389: Electricity Generation by Type Including Distributed Generation | C5389: natural gas steam turbine es | H5389: =INDEX('Vensim Variables'!$B:$B,MATCH(EPS!$B5389,'Vensim Variables'!$A:$A,0)) -> MWh | I5389: =IF(OR(C5389="CO2",C5389="CH4",C5389="N2O",C5389="F gases",C5389="VOC",C5389="CO",C5389="NOx",C5389="PM10",C5389="PM25",C5389="SOx",C5389="BC",C5389="OC"),C5389,IF(OR(D5389="CO2",D5389="CH4",D5389="N2O",D5389="F gases",D5389="VOC",D5389="CO",D5389="NOx",D5389="PM10",D5389="PM25",D5389="SOx",D5389="BC",D5389="OC"),D5389,IF(OR(E5389="CO2",E5389="CH4",E5389="N2O",E5389="F gases",E5389="VOC",E5389="CO",E5389="NOx",E5389="PM10",E5389="PM25",E5389="SOx",E5389="BC",E5389="OC"),E5389,"NA"))) -> NA | J5389: =INDEX(NoSettings!$C:$C,MATCH(EPS!$A5389,NoSettings!$A:$A,0)) -> 79390000 | K5389: =INDEX(GWP!$C$2:$C$13,MATCH(EPS!I5389,GWP!$B$2:$B$13,0)) -> #N/A | L5389: =IF(H5389="g pollutant",K5389*J5389/10^12,IF(H5389="MMTCO2e",J5389,IF(H5389="MWh",J5389,0))) -> 79390000
A5390: Electricity Generation by Type Including Distributed Generation[natural gas combined cycle es] | B5390: Electricity Generation by Type Including Distributed Generation | C5390: natural gas combined cycle es | H5390: =INDEX('Vensim Variables'!$B:$B,MATCH(EPS!$B5390,'Vensim Variables'!$A:$A,0)) -> MWh | I5390: =IF(OR(C5390="CO2",C5390="CH4",C5390="N2O",C5390="F gases",C5390="VOC",C5390="CO",C5390="NOx",C5390="PM10",C5390="PM25",C5390="SOx",C5390="BC",C5390="OC"),C5390,IF(OR(D5390="CO2",D5390="CH4",D5390="N2O",D5390="F gases",D5390="VOC",D5390="CO",D5390="NOx",D5390="PM10",D5390="PM25",D5390="SOx",D5390="BC",D5390="OC"),D5390,IF(OR(E5390="CO2",E5390="CH4",E5390="N2O",E5390="F gases",E5390="VOC",E5390="CO",E5390="NOx",E5390="PM10",E5390="PM25",E5390="SOx",E5390="BC",E5390="OC"),E5390,"NA"))) -> NA | J5390: =INDEX(NoSettings!$C:$C,MATCH(EPS!$A5390,NoSettings!$A:$A,0)) -> 1831760000 | K5390: =INDEX(GWP!$C$2:$C$13,MATCH(EPS!I5390,GWP!$B$2:$B$13,0)) -> #N/A | L5390: =IF(H5390="g pollutant",K5390*J5390/10^12,IF(H5390="MMTCO2e",J5390,IF(H5390="MWh",J5390,0))) -> 1831760000
A5391: Electricity Generation by Type Including Distributed Generation[nuclear es] | B5391: Electricity Generation by Type Including Distributed Generation | C5391: nuclear es | H5391: =INDEX('Vensim Variables'!$B:$B,MATCH(EPS!$B5391,'Vensim Variables'!$A:$A,0)) -> MWh | I5391: =IF(OR(C5391="CO2",C5391="CH4",C5391="N2O",C5391="F gases",C5391="VOC",C5391="CO",C5391="NOx",C5391="PM10",C5391="PM25",C5391="SOx",C5391="BC",C5391="OC"),C5391,IF(OR(D5391="CO2",D5391="CH4",D5391="N2O",D5391="F gases",D5391="VOC",D5391="CO",D5391="NOx",D5391="PM10",D5391="PM25",D5391="SOx",D5391="BC",D5391="OC"),D5391,IF(OR(E5391="CO2",E5391="CH4",E5391="N2O",E5391="F gases",E5391="VOC",E5391="CO",E5391="NOx",E5391="PM10",E5391="PM25",E5391="SOx",E5391="BC",E5391="OC"),E5391,"NA"))) -> NA | J5391: =INDEX(NoSettings!$C:$C,MATCH(EPS!$A5391,NoSettings!$A:$A,0)) -> 788710000 | K5391: =INDEX(GWP!$C$2:$C$13,MATCH(EPS!I5391,GWP!$B$2:$B$13,0)) -> #N/A | L5391: =IF(H5391="g pollutant",K5391*J5391/10^12,IF(H5391="MMTCO2e",J5391,IF(H5391="MWh",J5391,0))) -> 788710000
A5392: Electricity Generation by Type Including Distributed Generation[hydro es] | B5392: Electricity Generation by Type Including Distributed Generation | C5392: hydro es | H5392: =INDEX('Vensim Variables'!$B:$B,MATCH(EPS!$B5392,'Vensim Variables'!$A:$A,0)) -> MWh | I5392: =IF(OR(C5392="CO2",C5392="CH4",C5392="N2O",C5392="F gases",C5392="VOC",C5392="CO",C5392="NOx",C5392="PM10",C5392="PM25",C5392="SOx",C5392="BC",C5392="OC"),C5392,IF(OR(D5392="CO2",D5392="CH4",D5392="N2O",D5392="F gases",D5392="VOC",D5392="CO",D5392="NOx",D5392="PM10",D5392="PM25",D5392="SOx",D5392="BC",D5392="OC"),D5392,IF(OR(E5392="CO2",E5392="CH4",E5392="N2O",E5392="F gases",E5392="VOC",E5392="CO",E5392="NOx",E5392="PM10",E5392="PM25",E5392="SOx",E5392="BC",E5392="OC"),E5392,"NA"))) -> NA | J5392: =INDEX(NoSettings!$C:$C,MATCH(EPS!$A5392,NoSettings!$A:$A,0)) -> 210240000 | K5392: =INDEX(GWP!$C$2:$C$13,MATCH(EPS!I5392,GWP!$B$2:$B$13,0)) -> #N/A | L5392: =IF(H5392="g pollutant",K5392*J5392/10^12,IF(H5392="MMTCO2e",J5392,IF(H5392="MWh",J5392,0))) -> 210240000
A5393: Electricity Generation by Type Including Distributed Generation[onshore wind es] | B5393: Electricity Generation by Type Including Distributed Generation | C5393: onshore wind es | H5393: =INDEX('Vensim Variables'!$B:$B,MATCH(EPS!$B5393,'Vensim Variables'!$A:$A,0)) -> MWh | I5393: =IF(OR(C5393="CO2",C5393="CH4",C5393="N2O",C5393="F gases",C5393="VOC",C5393="CO",C5393="NOx",C5393="PM10",C5393="PM25",C5393="SOx",C5393="BC",C5393="OC"),C5393,IF(OR(D5393="CO2",D5393="CH4",D5393="N2O",D5393="F gases",D5393="VOC",D5393="CO",D5393="NOx",D5393="PM10",D5393="PM25",D5393="SOx",D5393="BC",D5393="OC"),D5393,IF(OR(E5393="CO2",E5393="CH4",E5393="N2O",E5393="F gases",E5393="VOC",E5393="CO",E5393="NOx",E5393="PM10",E5393="PM25",E5393="SOx",E5393="BC",E5393="OC"),E5393,"NA"))) -> NA | J5393: =INDEX(NoSettings!$C:$C,MATCH(EPS!$A5393,NoSettings!$A:$A,0)) -> 450225000 | K5393: =INDEX(GWP!$C$2:$C$13,MATCH(EPS!I5393,GWP!$B$2:$B$13,0)) -> #N/A | L5393: =IF(H5393="g pollutant",K5393*J5393/10^12,IF(H5393="MMTCO2e",J5393,IF(H5393="MWh",J5393,0))) -> 450225000
A5394: Electricity Generation by Type Including Distributed Generation[solar PV es] | B5394: Electricity Generation by Type Including Distributed Generation | C5394: solar PV es | H5394: =INDEX('Vensim Variables'!$B:$B,MATCH(EPS!$B5394,'Vensim Variables'!$A:$A,0)) -> MWh | I5394: =IF(OR(C5394="CO2",C5394="CH4",C5394="N2O",C5394="F gases",C5394="VOC",C5394="CO",C5394="NOx",C5394="PM10",C5394="PM25",C5394="SOx",C5394="BC",C5394="OC"),C5394,IF(OR(D5394="CO2",D5394="CH4",D5394="N2O",D5394="F gases",D5394="VOC",D5394="CO",D5394="NOx",D5394="PM10",D5394="PM25",D5394="SOx",D5394="BC",D5394="OC"),D5394,IF(OR(E5394="CO2",E5394="CH4",E5394="N2O",E5394="F gases",E5394="VOC",E5394="CO",E5394="NOx",E5394="PM10",E5394="PM25",E5394="SOx",E5394="BC",E5394="OC"),E5394,"NA"))) -> NA | J5394: =INDEX(NoSettings!$C:$C,MATCH(EPS!$A5394,NoSettings!$A:$A,0)) -> 282008000 | K5394: =INDEX(GWP!$C$2:$C$13,MATCH(EPS!I5394,GWP!$B$2:$B$13,0)) -> #N/A | L5394: =IF(H5394="g pollutant",K5394*J5394/10^12,IF(H5394="MMTCO2e",J5394,IF(H5394="MWh",J5394,0))) -> 282008000
A5395: Electricity Generation by Type Including Distributed Generation[solar thermal es] | B5395: Electricity Generation by Type Including Distributed Generation | C5395: solar thermal es | H5395: =INDEX('Vensim Variables'!$B:$B,MATCH(EPS!$B5395,'Vensim Variables'!$A:$A,0)) -> MWh | I5395: =IF(OR(C5395="CO2",C5395="CH4",C5395="N2O",C5395="F gases",C5395="VOC",C5395="CO",C5395="NOx",C5395="PM10",C5395="PM25",C5395="SOx",C5395="BC",C5395="OC"),C5395,IF(OR(D5395="CO2",D5395="CH4",D5395="N2O",D5395="F gases",D5395="VOC",D5395="CO",D5395="NOx",D5395="PM10",D5395="PM25",D5395="SOx",D5395="BC",D5395="OC"),D5395,IF(OR(E5395="CO2",E5395="CH4",E5395="N2O",E5395="F gases",E5395="VOC",E5395="CO",E5395="NOx",E5395="PM10",E5395="PM25",E5395="SOx",E5395="BC",E5395="OC"),E5395,"NA"))) -> NA | J5395: =INDEX(NoSettings!$C:$C,MATCH(EPS!$A5395,NoSettings!$A:$A,0)) -> 2600000 | K5395: =INDEX(GWP!$C$2:$C$13,MATCH(EPS!I5395,GWP!$B$2:$B$13,0)) -> #N/A | L5395: =IF(H5395="g pollutant",K5395*J5395/10^12,IF(H5395="MMTCO2e",J5395,IF(H5395="MWh",J5395,0))) -> 2600000
A5396: Electricity Generation by Type Including Distributed Generation[biomass es] | B5396: Electricity Generation by Type Including Distributed Generation | C5396: biomass es | H5396: =INDEX('Vensim Variables'!$B:$B,MATCH(EPS!$B5396,'Vensim Variables'!$A:$A,0)) -> MWh | I5396: =IF(OR(C5396="CO2",C5396="CH4",C5396="N2O",C5396="F gases",C5396="VOC",C5396="CO",C5396="NOx",C5396="PM10",C5396="PM25",C5396="SOx",C5396="BC",C5396="OC"),C5396,IF(OR(D5396="CO2",D5396="CH4",D5396="N2O",D5396="F gases",D5396="VOC",D5396="CO",D5396="NOx",D5396="PM10",D5396="PM25",D5396="SOx",D5396="BC",D5396="OC"),D5396,IF(OR(E5396="CO2",E5396="CH4",E5396="N2O",E5396="F gases",E5396="VOC",E5396="CO",E5396="NOx",E5396="PM10",E5396="PM25",E5396="SOx",E5396="BC",E5396="OC"),E5396,"NA"))) -> NA | J5396: =INDEX(NoSettings!$C:$C,MATCH(EPS!$A5396,NoSettings!$A:$A,0)) -> 21410000 | K5396: =INDEX(GWP!$C$2:$C$13,MATCH(EPS!I5396,GWP!$B$2:$B$13,0)) -> #N/A | L5396: =IF(H5396="g pollutant",K5396*J5396/10^12,IF(H5396="MMTCO2e",J5396,IF(H5396="MWh",J5396,0))) -> 21410000
A5397: Electricity Generation by Type Including Distributed Generation[geothermal es] | B5397: Electricity Generation by Type Including Distributed Generation | C5397: geothermal es | H5397: =INDEX('Vensim Variables'!$B:$B,MATCH(EPS!$B5397,'Vensim Variables'!$A:$A,0)) -> MWh | I5397: =IF(OR(C5397="CO2",C5397="CH4",C5397="N2O",C5397="F gases",C5397="VOC",C5397="CO",C5397="NOx",C5397="PM10",C5397="PM25",C5397="SOx",C5397="BC",C5397="OC"),C5397,IF(OR(D5397="CO2",D5397="CH4",D5397="N2O",D5397="F gases",D5397="VOC",D5397="CO",D5397="NOx",D5397="PM10",D5397="PM25",D5397="SOx",D5397="BC",D5397="OC"),D5397,IF(OR(E5397="CO2",E5397="CH4",E5397="N2O",E5397="F gases",E5397="VOC",E5397="CO",E5397="NOx",E5397="PM10",E5397="PM25",E5397="SOx",E5397="BC",E5397="OC"),E5397,"NA"))) -> NA | J5397: =INDEX(NoSettings!$C:$C,MATCH(EPS!$A5397,NoSettings!$A:$A,0)) -> 16390000 | K5397: =INDEX(GWP!$C$2:$C$13,MATCH(EPS!I5397,GWP!$B$2:$B$13,0)) -> #N/A | L5397: =IF(H5397="g pollutant",K5397*J5397/10^12,IF(H5397="MMTCO2e",J5397,IF(H5397="MWh",J5397,0))) -> 16390000
A5398: Electricity Generation by Type Including Distributed Generation[petroleum es] | B5398: Electricity Generation by Type Including Distributed Generation | C5398: petroleum es | H5398: =INDEX('Vensim Variables'!$B:$B,MATCH(EPS!$B5398,'Vensim Variables'!$A:$A,0)) -> MWh | I5398: =IF(OR(C5398="CO2",C5398="CH4",C5398="N2O",C5398="F gases",C5398="VOC",C5398="CO",C5398="NOx",C5398="PM10",C5398="PM25",C5398="SOx",C5398="BC",C5398="OC"),C5398,IF(OR(D5398="CO2",D5398="CH4",D5398="N2O",D5398="F gases",D5398="VOC",D5398="CO",D5398="NOx",D5398="PM10",D5398="PM25",D5398="SOx",D5398="BC",D5398="OC"),D5398,IF(OR(E5398="CO2",E5398="CH4",E5398="N2O",E5398="F gases",E5398="VOC",E5398="CO",E5398="NOx",E5398="PM10",E5398="PM25",E5398="SOx",E5398="BC",E5398="OC"),E5398,"NA"))) -> NA | J5398: =INDEX(NoSettings!$C:$C,MATCH(EPS!$A5398,NoSettings!$A:$A,0)) -> 2177250 | K5398: =INDEX(GWP!$C$2:$C$13,MATCH(EPS!I5398,GWP!$B$2:$B$13,0)) -> #N/A | L5398: =IF(H5398="g pollutant",K5398*J5398/10^12,IF(H5398="MMTCO2e",J5398,IF(H5398="MWh",J5398,0))) -> 2177250
A5399: Electricity Generation by Type Including Distributed Generation[natural gas peaker es] | B5399: Electricity Generation by Type Including Distributed Generation | C5399: natural gas peaker es | H5399: =INDEX('Vensim Variables'!$B:$B,MATCH(EPS!$B5399,'Vensim Variables'!$A:$A,0)) -> MWh | I5399: =IF(OR(C5399="CO2",C5399="CH4",C5399="N2O",C5399="F gases",C5399="VOC",C5399="CO",C5399="NOx",C5399="PM10",C5399="PM25",C5399="SOx",C5399="BC",C5399="OC"),C5399,IF(OR(D5399="CO2",D5399="CH4",D5399="N2O",D5399="F gases",D5399="VOC",D5399="CO",D5399="NOx",D5399="PM10",D5399="PM25",D5399="SOx",D5399="BC",D5399="OC"),D5399,IF(OR(E5399="CO2",E5399="CH4",E5399="N2O",E5399="F gases",E5399="VOC",E5399="CO",E5399="NOx",E5399="PM10",E5399="PM25",E5399="SOx",E5399="BC",E5399="OC"),E5399,"NA"))) -> NA | J5399: =INDEX(NoSettings!$C:$C,MATCH(EPS!$A5399,NoSettings!$A:$A,0)) -> 78400000 | K5399: =INDEX(GWP!$C$2:$C$13,MATCH(EPS!I5399,GWP!$B$2:$B$13,0)) -> #N/A | L5399: =IF(H5399="g pollutant",K5399*J5399/10^12,IF(H5399="MMTCO2e",J5399,IF(H5399="MWh",J5399,0))) -> 78400000
... A5411: Electricity Generation by Type Including Distributed Generation[hydrogen combined cycle es] | B5411: Electricity Generation by Type Including Distributed Generation | C5411: hydrogen combined cycle es | H5411: =INDEX('Vensim Variables'!$B:$B,MATCH(EPS!$B5411,'Vensim Variables'!$A:$A,0)) -> MWh | I5411: =IF(OR(C5411="CO2",C5411="CH4",C5411="N2O",C5411="F gases",C5411="VOC",C5411="CO",C5411="NOx",C5411="PM10",C5411="PM25",C5411="SOx",C5411="BC",C5411="OC"),C5411,IF(OR(D5411="CO2",D5411="CH4",D5411="N2O",D5411="F gases",D5411="VOC",D5411="CO",D5411="NOx",D5411="PM10",D5411="PM25",D5411="SOx",D5411="BC",D5411="OC"),D5411,IF(OR(E5411="CO2",E5411="CH4",E5411="N2O",E5411="F gases",E5411="VOC",E5411="CO",E5411="NOx",E5411="PM10",E5411="PM25",E5411="SOx",E5411="BC",E5411="OC"),E5411,"NA"))) -> NA | J5411: =INDEX(NoSettings!$C:$C,MATCH(EPS!$A5411,NoSettings!$A:$A,0)) -> 0 | K5411: =INDEX(GWP!$C$2:$C$13,MATCH(EPS!I5411,GWP!$B$2:$B$13,0)) -> #N/A | L5411: =IF(H5411="g pollutant",K5411*J5411/10^12,IF(H5411="MMTCO2e",J5411,IF(H5411="MWh",J5411,0))) -> 0
A5412: Total Pollutant Emissions by Sector[transportation sector,CO2] | B5412: Total Pollutant Emissions by Sector | C5412: transportation sector | D5412: CO2 | H5412: =INDEX('Vensim Variables'!$B:$B,MATCH(EPS!$B5412,'Vensim Variables'!$A:$A,0)) -> g pollutant | I5412: =IF(OR(C5412="CO2",C5412="CH4",C5412="N2O",C5412="F gases",C5412="VOC",C5412="CO",C5412="NOx",C5412="PM10",C5412="PM25",C5412="SOx",C5412="BC",C5412="OC"),C5412,IF(OR(D5412="CO2",D5412="CH4",D5412="N2O",D5412="F gases",D5412="VOC",D5412="CO",D5412="NOx",D5412="PM10",D5412="PM25",D5412="SOx",D5412="BC",D5412="OC"),D5412,IF(OR(E5412="CO2",E5412="CH4",E5412="N2O",E5412="F gases",E5412="VOC",E5412="CO",E5412="NOx",E5412="PM10",E5412="PM25",E5412="SOx",E5412="BC",E5412="OC"),E5412,"NA"))) -> CO2 | J5412: =INDEX(NoSettings!$C:$C,MATCH(EPS!$A5412,NoSettings!$A:$A,0)) -> #N/A | K5412: =INDEX(GWP!$C$2:$C$13,MATCH(EPS!I5412,GWP!$B$2:$B$13,0)) -> 1 | L5412: =IF(H5412="g pollutant",K5412*J5412/10^12,IF(H5412="MMTCO2e",J5412,IF(H5412="MWh",J5412,0))) -> #N/A
A5413: Total Pollutant Emissions by Sector[transportation sector,VOC] | B5413: Total Pollutant Emissions by Sector | C5413: transportation sector | D5413: VOC | H5413: =INDEX('Vensim Variables'!$B:$B,MATCH(EPS!$B5413,'Vensim Variables'!$A:$A,0)) -> g pollutant | I5413: =IF(OR(C5413="CO2",C5413="CH4",C5413="N2O",C5413="F gases",C5413="VOC",C5413="CO",C5413="NOx",C5413="PM10",C5413="PM25",C5413="SOx",C5413="BC",C5413="OC"),C5413,IF(OR(D5413="CO2",D5413="CH4",D5413="N2O",D5413="F gases",D5413="VOC",D5413="CO",D5413="NOx",D5413="PM10",D5413="PM25",D5413="SOx",D5413="BC",D5413="OC"),D5413,IF(OR(E5413="CO2",E5413="CH4",E5413="N2O",E5413="F gases",E5413="VOC",E5413="CO",E5413="NOx",E5413="PM10",E5413="PM25",E5413="SOx",E5413="BC",E5413="OC"),E5413,"NA"))) -> VOC | J5413: =INDEX(NoSettings!$C:$C,MATCH(EPS!$A5413,NoSettings!$A:$A,0)) -> #N/A | K5413: =INDEX(GWP!$C$2:$C$13,MATCH(EPS!I5413,GWP!$B$2:$B$13,0)) -> 0 | L5413: =IF(H5413="g pollutant",K5413*J5413/10^12,IF(H5413="MMTCO2e",J5413,IF(H5413="MWh",J5413,0))) -> #N/A
A5414: Total Pollutant Emissions by Sector[transportation sector,CO] | B5414: Total Pollutant Emissions by Sector | C5414: transportation sector | D5414: CO | H5414: =INDEX('Vensim Variables'!$B:$B,MATCH(EPS!$B5414,'Vensim Variables'!$A:$A,0)) -> g pollutant | I5414: =IF(OR(C5414="CO2",C5414="CH4",C5414="N2O",C5414="F gases",C5414="VOC",C5414="CO",C5414="NOx",C5414="PM10",C5414="PM25",C5414="SOx",C5414="BC",C5414="OC"),C5414,IF(OR(D5414="CO2",D5414="CH4",D5414="N2O",D5414="F gases",D5414="VOC",D5414="CO",D5414="NOx",D5414="PM10",D5414="PM25",D5414="SOx",D5414="BC",D5414="OC"),D5414,IF(OR(E5414="CO2",E5414="CH4",E5414="N2O",E5414="F gases",E5414="VOC",E5414="CO",E5414="NOx",E5414="PM10",E5414="PM25",E5414="SOx",E5414="BC",E5414="OC"),E5414,"NA"))) -> CO | J5414: =INDEX(NoSettings!$C:$C,MATCH(EPS!$A5414,NoSettings!$A:$A,0)) -> #N/A | K5414: =INDEX(GWP!$C$2:$C$13,MATCH(EPS!I5414,GWP!$B$2:$B$13,0)) -> 0 | L5414: =IF(H5414="g pollutant",K5414*J5414/10^12,IF(H5414="MMTCO2e",J5414,IF(H5414="MWh",J5414,0))) -> #N/A
A5415: Total Pollutant Emissions by Sector[transportation sector,NOx] | B5415: Total Pollutant Emissions by Sector | C5415: transportation sector | D5415: NOx | H5415: =INDEX('Vensim Variables'!$B:$B,MATCH(EPS!$B5415,'Vensim Variables'!$A:$A,0)) -> g pollutant | I5415: =IF(OR(C5415="CO2",C5415="CH4",C5415="N2O",C5415="F gases",C5415="VOC",C5415="CO",C5415="NOx",C5415="PM10",C5415="PM25",C5415="SOx",C5415="BC",C5415="OC"),C5415,IF(OR(D5415="CO2",D5415="CH4",D5415="N2O",D5415="F gases",D5415="VOC",D5415="CO",D5415="NOx",D5415="PM10",D5415="PM25",D5415="SOx",D5415="BC",D5415="OC"),D5415,IF(OR(E5415="CO2",E5415="CH4",E5415="N2O",E5415="F gases",E5415="VOC",E5415="CO",E5415="NOx",E5415="PM10",E5415="PM25",E5415="SOx",E5415="BC",E5415="OC"),E5415,"NA"))) -> NOx | J5415: =INDEX(NoSettings!$C:$C,MATCH(EPS!$A5415,NoSettings!$A:$A,0)) -> #N/A | K5415: =INDEX(GWP!$C$2:$C$13,MATCH(EPS!I5415,GWP!$B$2:$B$13,0)) -> 0 | L5415: =IF(H5415="g pollutant",K5415*J5415/10^12,IF(H5415="MMTCO2e",J5415,IF(H5415="MWh",J5415,0))) -> #N/A
A5416: Total Pollutant Emissions by Sector[transportation sector,PM10] | B5416: Total Pollutant Emissions by Sector | C5416: transportation sector | D5416: PM10 | H5416: =INDEX('Vensim Variables'!$B:$B,MATCH(EPS!$B5416,'Vensim Variables'!$A:$A,0)) -> g pollutant | I5416: =IF(OR(C5416="CO2",C5416="CH4",C5416="N2O",C5416="F gases",C5416="VOC",C5416="CO",C5416="NOx",C5416="PM10",C5416="PM25",C5416="SOx",C5416="BC",C5416="OC"),C5416,IF(OR(D5416="CO2",D5416="CH4",D5416="N2O",D5416="F gases",D5416="VOC",D5416="CO",D5416="NOx",D5416="PM10",D5416="PM25",D5416="SOx",D5416="BC",D5416="OC"),D5416,IF(OR(E5416="CO2",E5416="CH4",E5416="N2O",E5416="F gases",E5416="VOC",E5416="CO",E5416="NOx",E5416="PM10",E5416="PM25",E5416="SOx",E5416="BC",E5416="OC"),E5416,"NA"))) -> PM10 | J5416: =INDEX(NoSettings!$C:$C,MATCH(EPS!$A5416,NoSettings!$A:$A,0)) -> #N/A | K5416: =INDEX(GWP!$C$2:$C$13,MATCH(EPS!I5416,GWP!$B$2:$B$13,0)) -> 0 | L5416: =IF(H5416="g pollutant",K5416*J5416/10^12,IF(H5416="MMTCO2e",J5416,IF(H5416="MWh",J5416,0))) -> #N/A
A5417: Total Pollutant Emissions by Sector[transportation sector,PM25] | B5417: Total Pollutant Emissions by Sector | C5417: transportation sector | D5417: PM25 | H5417: =INDEX('Vensim Variables'!$B:$B,MATCH(EPS!$B5417,'Vensim Variables'!$A:$A,0)) -> g pollutant | I5417: =IF(OR(C5417="CO2",C5417="CH4",C5417="N2O",C5417="F gases",C5417="VOC",C5417="CO",C5417="NOx",C5417="PM10",C5417="PM25",C5417="SOx",C5417="BC",C5417="OC"),C5417,IF(OR(D5417="CO2",D5417="CH4",D5417="N2O",D5417="F gases",D5417="VOC",D5417="CO",D5417="NOx",D5417="PM10",D5417="PM25",D5417="SOx",D5417="BC",D5417="OC"),D5417,IF(OR(E5417="CO2",E5417="CH4",E5417="N2O",E5417="F gases",E5417="VOC",E5417="CO",E5417="NOx",E5417="PM10",E5417="PM25",E5417="SOx",E5417="BC",E5417="OC"),E5417,"NA"))) -> PM25 | J5417: =INDEX(NoSettings!$C:$C,MATCH(EPS!$A5417,NoSettings!$A:$A,0)) -> #N/A | K5417: =INDEX(GWP!$C$2:$C$13,MATCH(EPS!I5417,GWP!$B$2:$B$13,0)) -> 0 | L5417: =IF(H5417="g pollutant",K5417*J5417/10^12,IF(H5417="MMTCO2e",J5417,IF(H5417="MWh",J5417,0))) -> #N/A
A5418: Total Pollutant Emissions by Sector[transportation sector,SOx] | B5418: Total Pollutant Emissions by Sector | C5418: transportation sector | D5418: SOx | H5418: =INDEX('Vensim Variables'!$B:$B,MATCH(EPS!$B5418,'Vensim Variables'!$A:$A,0)) -> g pollutant | I5418: =IF(OR(C5418="CO2",C5418="CH4",C5418="N2O",C5418="F gases",C5418="VOC",C5418="CO",C5418="NOx",C5418="PM10",C5418="PM25",C5418="SOx",C5418="BC",C5418="OC"),C5418,IF(OR(D5418="CO2",D5418="CH4",D5418="N2O",D5418="F gases",D5418="VOC",D5418="CO",D5418="NOx",D5418="PM10",D5418="PM25",D5418="SOx",D5418="BC",D5418="OC"),D5418,IF(OR(E5418="CO2",E5418="CH4",E5418="N2O",E5418="F gases",E5418="VOC",E5418="CO",E5418="NOx",E5418="PM10",E5418="PM25",E5418="SOx",E5418="BC",E5418="OC"),E5418,"NA"))) -> SOx | J5418: =INDEX(NoSettings!$C:$C,MATCH(EPS!$A5418,NoSettings!$A:$A,0)) -> #N/A | K5418: =INDEX(GWP!$C$2:$C$13,MATCH(EPS!I5418,GWP!$B$2:$B$13,0)) -> 0 | L5418: =IF(H5418="g pollutant",K5418*J5418/10^12,IF(H5418="MMTCO2e",J5418,IF(H5418="MWh",J5418,0))) -> #N/A
A5419: Total Pollutant Emissions by Sector[transportation sector,BC] | B5419: Total Pollutant Emissions by Sector | C5419: transportation sector | D5419: BC | H5419: =INDEX('Vensim Variables'!$B:$B,MATCH(EPS!$B5419,'Vensim Variables'!$A:$A,0)) -> g pollutant | I5419: =IF(OR(C5419="CO2",C5419="CH4",C5419="N2O",C5419="F gases",C5419="VOC",C5419="CO",C5419="NOx",C5419="PM10",C5419="PM25",C5419="SOx",C5419="BC",C5419="OC"),C5419,IF(OR(D5419="CO2",D5419="CH4",D5419="N2O",D5419="F gases",D5419="VOC",D5419="CO",D5419="NOx",D5419="PM10",D5419="PM25",D5419="SOx",D5419="BC",D5419="OC"),D5419,IF(OR(E5419="CO2",E5419="CH4",E5419="N2O",E5419="F gases",E5419="VOC",E5419="CO",E5419="NOx",E5419="PM10",E5419="PM25",E5419="SOx",E5419="BC",E5419="OC"),E5419,"NA"))) -> BC | J5419: =INDEX(NoSettings!$C:$C,MATCH(EPS!$A5419,NoSettings!$A:$A,0)) -> #N/A | K5419: =INDEX(GWP!$C$2:$C$13,MATCH(EPS!I5419,GWP!$B$2:$B$13,0)) -> 0 | L5419: =IF(H5419="g pollutant",K5419*J5419/10^12,IF(H5419="MMTCO2e",J5419,IF(H5419="MWh",J5419,0))) -> #N/A
A5420: Total Pollutant Emissions by Sector[transportation sector,OC] | B5420: Total Pollutant Emissions by Sector | C5420: transportation sector | D5420: OC | H5420: =INDEX('Vensim Variables'!$B:$B,MATCH(EPS!$B5420,'Vensim Variables'!$A:$A,0)) -> g pollutant | I5420: =IF(OR(C5420="CO2",C5420="CH4",C5420="N2O",C5420="F gases",C5420="VOC",C5420="CO",C5420="NOx",C5420="PM10",C5420="PM25",C5420="SOx",C5420="BC",C5420="OC"),C5420,IF(OR(D5420="CO2",D5420="CH4",D5420="N2O",D5420="F gases",D5420="VOC",D5420="CO",D5420="NOx",D5420="PM10",D5420="PM25",D5420="SOx",D5420="BC",D5420="OC"),D5420,IF(OR(E5420="CO2",E5420="CH4",E5420="N2O",E5420="F gases",E5420="VOC",E5420="CO",E5420="NOx",E5420="PM10",E5420="PM25",E5420="SOx",E5420="BC",E5420="OC"),E5420,"NA"))) -> OC | J5420: =INDEX(NoSettings!$C:$C,MATCH(EPS!$A5420,NoSettings!$A:$A,0)) -> #N/A | K5420: =INDEX(GWP!$C$2:$C$13,MATCH(EPS!I5420,GWP!$B$2:$B$13,0)) -> 0 | L5420: =IF(H5420="g pollutant",K5420*J5420/10^12,IF(H5420="MMTCO2e",J5420,IF(H5420="MWh",J5420,0))) -> #N/A
A5421: Total Pollutant Emissions by Sector[transportation sector,CH4] | B5421: Total Pollutant Emissions by Sector | C5421: transportation sector | D5421: CH4 | H5421: =INDEX('Vensim Variables'!$B:$B,MATCH(EPS!$B5421,'Vensim Variables'!$A:$A,0)) -> g pollutant | I5421: =IF(OR(C5421="CO2",C5421="CH4",C5421="N2O",C5421="F gases",C5421="VOC",C5421="CO",C5421="NOx",C5421="PM10",C5421="PM25",C5421="SOx",C5421="BC",C5421="OC"),C5421,IF(OR(D5421="CO2",D5421="CH4",D5421="N2O",D5421="F gases",D5421="VOC",D5421="CO",D5421="NOx",D5421="PM10",D5421="PM25",D5421="SOx",D5421="BC",D5421="OC"),D5421,IF(OR(E5421="CO2",E5421="CH4",E5421="N2O",E5421="F gases",E5421="VOC",E5421="CO",E5421="NOx",E5421="PM10",E5421="PM25",E5421="SOx",E5421="BC",E5421="OC"),E5421,"NA"))) -> CH4 | J5421: =INDEX(NoSettings!$C:$C,MATCH(EPS!$A5421,NoSettings!$A:$A,0)) -> #N/A | K5421: =INDEX(GWP!$C$2:$C$13,MATCH(EPS!I5421,GWP!$B$2:$B$13,0)) -> 28 | L5421: =IF(H5421="g pollutant",K5421*J5421/10^12,IF(H5421="MMTCO2e",J5421,IF(H5421="MWh",J5421,0))) -> #N/A
A5422: Total Pollutant Emissions by Sector[transportation sector,N2O] | B5422: Total Pollutant Emissions by Sector | C5422: transportation sector | D5422: N2O | H5422: =INDEX('Vensim Variables'!$B:$B,MATCH(EPS!$B5422,'Vensim Variables'!$A:$A,0)) -> g pollutant | I5422: =IF(OR(C5422="CO2",C5422="CH4",C5422="N2O",C5422="F gases",C5422="VOC",C5422="CO",C5422="NOx",C5422="PM10",C5422="PM25",C5422="SOx",C5422="BC",C5422="OC"),C5422,IF(OR(D5422="CO2",D5422="CH4",D5422="N2O",D5422="F gases",D5422="VOC",D5422="CO",D5422="NOx",D5422="PM10",D5422="PM25",D5422="SOx",D5422="BC",D5422="OC"),D5422,IF(OR(E5422="CO2",E5422="CH4",E5422="N2O",E5422="F gases",E5422="VOC",E5422="CO",E5422="NOx",E5422="PM10",E5422="PM25",E5422="SOx",E5422="BC",E5422="OC"),E5422,"NA"))) -> N2O | J5422: =INDEX(NoSettings!$C:$C,MATCH(EPS!$A5422,NoSettings!$A:$A,0)) -> #N/A | K5422: =INDEX(GWP!$C$2:$C$13,MATCH(EPS!I5422,GWP!$B$2:$B$13,0)) -> 265 | L5422: =IF(H5422="g pollutant",K5422*J5422/10^12,IF(H5422="MMTCO2e",J5422,IF(H5422="MWh",J5422,0))) -> #N/A
A5423: Total Pollutant Emissions by Sector[transportation sector,F gases] | B5423: Total Pollutant Emissions by Sector | C5423: transportation sector | D5423: F gases | H5423: =INDEX('Vensim Variables'!$B:$B,MATCH(EPS!$B5423,'Vensim Variables'!$A:$A,0)) -> g pollutant | I5423: =IF(OR(C5423="CO2",C5423="CH4",C5423="N2O",C5423="F gases",C5423="VOC",C5423="CO",C5423="NOx",C5423="PM10",C5423="PM25",C5423="SOx",C5423="BC",C5423="OC"),C5423,IF(OR(D5423="CO2",D5423="CH4",D5423="N2O",D5423="F gases",D5423="VOC",D5423="CO",D5423="NOx",D5423="PM10",D5423="PM25",D5423="SOx",D5423="BC",D5423="OC"),D5423,IF(OR(E5423="CO2",E5423="CH4",E5423="N2O",E5423="F gases",E5423="VOC",E5423="CO",E5423="NOx",E5423="PM10",E5423="PM25",E5423="SOx",E5423="BC",E5423="OC"),E5423,"NA"))) -> F gases | J5423: =INDEX(NoSettings!$C:$C,MATCH(EPS!$A5423,NoSettings!$A:$A,0)) -> #N/A | K5423: =INDEX(GWP!$C$2:$C$13,MATCH(EPS!I5423,GWP!$B$2:$B$13,0)) -> 1 | L5423: =IF(H5423="g pollutant",K5423*J5423/10^12,IF(H5423="MMTCO2e",J5423,IF(H5423="MWh",J5423,0))) -> #N/A
...

Sheet GWP
A1: Time (Time) | B1: Pollutant | C1: GWP | D1: AR4 GWP | E1: AR5 GWP
A2: GWP by Pollutant | B2: CO2 | C2: =INDEX(D2:E2,MATCH(Overview!$B$29,GWP!$D$1:$E$1,0)) -> 1 | D2: 1 | E2: 1
A3: GWP by Pollutant | B3: VOC | C3: 0 | D3: 5 | E3: 5
A4: GWP by Pollutant | B4: CO | C4: 0 | D4: 1.8 | E4: 1.8
A5: GWP by Pollutant | B5: NOx | C5: 0 | D5: -8.2 | E5: -8.2
A6: GWP by Pollutant | B6: PM10 | C6: 0 | D6: 0 | E6: 0
A7: GWP by Pollutant | B7: PM25 | C7: 0 | D7: 0 | E7: 0
A8: GWP by Pollutant | B8: SOx | C8: 0 | D8: 0 | E8: 0
A9: GWP by Pollutant | B9: BC | C9: 0 | D9: 345 | E9: 345
A10: GWP by Pollutant | B10: OC | C10: 0 | D10: -46 | E10: -46
A11: GWP by Pollutant | B11: CH4 | C11: =INDEX(D11:E11,MATCH(Overview!$B$29,GWP!$D$1:$E$1,0)) -> 28 | D11: 25 | E11: 28
A12: GWP by Pollutant | B12: N2O | C12: =INDEX(D12:E12,MATCH(Overview!$B$29,GWP!$D$1:$E$1,0)) -> 265 | D12: 298 | E12: 265
A13: GWP by Pollutant | B13: F gases | C13: =INDEX(D13:E13,MATCH(Overview!$B$29,GWP!$D$1:$E$1,0)) -> 1 | D13: 1 | E13: 1

Sheet NoSettings
A1: Time | B1: NoSettings | C1: 2024 | D1: 2025 | E1: 2026 | F1: 2027 | G1: 2028 | H1: 2029 | I1: 2030 | J1: 2031 | K1: 2032 | L1: 2033 | M1: 2034 | N1: 2035 | O1: 2036 | P1: 2037 | Q1: 2038 | R1: 2039 | S1: 2040 | T1: 2041 | U1: 2042 | V1: 2043 | W1: 2044 | X1: 2045 | Y1: 2046 | Z1: 2047 | AA1: 2048 | AB1: 2049 | AC1: 2050
A2: BAU Cargo Dist Transported[LDVs,passenger] | B2: NoSettings | C2: 5033080000000 | D2: 5107630000000 | E2: 5149520000000 | F2: 5177180000000 | G2: 5197580000000 | H2: 5219870000000 | I2: 5244230000000 | J2: 5267350000000 | K2: 5279750000000 | L2: 5289290000000 | M2: 5297260000000 | N2: 5301330000000 | O2: 5309780000000 | P2: 5326640000000 | Q2: 5349100000000 | R2: 5371080000000 | S2: 5395120000000 | T2: 5418030000000 | U2: 5439810000000 | V2: 5459120000000 | W2: 5476660000000 | X2: 5491860000000 | Y2: 5507020000000 | Z2: 5525480000000 | AA2: 5546810000000 | AB2: 5569690000000 | AC2: 5594440000000
A3: BAU Cargo Dist Transported[LDVs,freight] | B3: NoSettings | C3: 235404000000 | D3: 235276000000 | E3: 234395000000 | F3: 233897000000 | G3: 233280000000 | H3: 233462000000 | I3: 234200000000 | J3: 234947000000 | K3: 235915000000 | L3: 236939000000 | M3: 238190000000 | N3: 239504000000 | O3: 240992000000 | P3: 242562000000 | Q3: 244150000000 | R3: 245680000000 | S3: 247410000000 | T3: 248998000000 | U3: 250579000000 | V3: 251910000000 | W3: 253215000000 | X3: 254703000000 | Y3: 256234000000 | Z3: 258320000000 | AA3: 260231000000 | AB3: 261922000000 | AC3: 263393000000
A4: BAU Cargo Dist Transported[HDVs,passenger] | B4: NoSettings | C4: 382343000000 | D4: 394082000000 | E4: 401586000000 | F4: 406362000000 | G4: 409848000000 | H4: 412376000000 | I4: 414157000000 | J4: 415157000000 | K4: 415655000000 | L4: 415941000000 | M4: 416240000000 | N4: 416284000000 | O4: 416193000000 | P4: 416073000000 | Q4: 415709000000 | R4: 415230000000 | S4: 414622000000 | T4: 413899000000 | U4: 413050000000 | V4: 412159000000 | W4: 411161000000 | X4: 410152000000 | Y4: 409019000000 | Z4: 407820000000 | AA4: 406630000000 | AB4: 405442000000 | AC4: 404367000000
A5: BAU Cargo Dist Transported[HDVs,freight] | B5: NoSettings | C5: 3174200000000 | D5: 3252010000000 | E5: 3309140000000 | F5: 3362890000000 | G5: 3401350000000 | H5: 3436510000000 | I5: 3468370000000 | J5: 3491960000000 | K5: 3514050000000 | L5: 3531480000000 | M5: 3550940000000 | N5: 3569640000000 | O5: 3592750000000 | P5: 3618460000000 | Q5: 3644180000000 | R5: 3665330000000 | S5: 3686990000000 | T5: 3707060000000 | U5: 3727160000000 | V5: 3743730000000 | W5: 3757170000000 | X5: 3771440000000 | Y5: 3782350000000 | Z5: 3806580000000 | AA5: 3831750000000 | AB5: 3854470000000 | AC5: 3871810000000
A6: BAU Cargo Dist Transported[aircraft,passenger] | B6: NoSettings | C6: 798901000000 | D6: 806457000000 | E6: 826467000000 | F6: 845062000000 | G6: 860502000000 | H6: 877191000000 | I6: 892491000000 | J6: 905210000000 | K6: 919889000000 | L6: 935575000000 | M6: 950686000000 | N6: 967305000000 | O6: 984233000000 | P6: 1002220000000 | Q6: 1021530000000 | R6: 1040880000000 | S6: 1060260000000 | T6: 1079300000000 | U6: 1099930000000 | V6: 1120130000000 | W6: 1139000000000 | X6: 1157510000000 | Y6: 1175710000000 | Z6: 1197010000000 | AA6: 1219740000000 | AB6: 1241520000000 | AC6: 1263020000000
A7: BAU Cargo Dist Transported[aircraft,freight] | B7: NoSettings | C7: 51333800000 | D7: 51819300000 | E7: 53105100000 | F7: 54299900000 | G7: 55292000000 | H7: 56364400000 | I7: 57347400000 | J7: 58164700000 | K7: 59107900000 | L7: 60115800000 | M7: 61086800000 | N7: 62154600000 | O7: 63242400000 | P7: 64397900000 | Q7: 65639000000 | R7: 66882500000 | S7: 68127500000 | T7: 69351100000 | U7: 70676800000 | V7: 71974700000 | W7: 73186800000 | X7: 74376100000 | Y7: 75545500000 | Z7: 76914700000 | AA7: 78374800000 | AB7: 79774700000 | AC7: 81155900000
A8: BAU Cargo Dist Transported[rail,passenger] | B8: NoSettings | C8: 16564900000 | D8: 18418200000 | E8: 19837200000 | F8: 20926100000 | G8: 21775800000 | H8: 22507100000 | I8: 23113900000 | J8: 23590000000 | K8: 23980800000 | L8: 24301600000 | M8: 24617800000 | N8: 24871200000 | O8: 25114100000 | P8: 25376400000 | Q8: 25650800000 | R8: 25895500000 | S8: 26124100000 | T8: 26326900000 | U8: 26518600000 | V8: 26704000000 | W8: 26853600000 | X8: 27012800000 | Y8: 27134000000 | Z8: 27277800000 | AA8: 27456600000 | AB8: 27635900000 | AC8: 27875700000
A9: BAU Cargo Dist Transported[rail,freight] | B9: NoSettings | C9: 1464730000000 | D9: 1498450000000 | E9: 1462250000000 | F9: 1413610000000 | G9: 1413990000000 | H9: 1410440000000 | I9: 1369620000000 | J9: 1370060000000 | K9: 1305700000000 | L9: 1312100000000 | M9: 1299740000000 | N9: 1300310000000 | O9: 1305640000000 | P9: 1312280000000 | Q9: 1330170000000 | R9: 1321860000000 | S9: 1328220000000 | T9: 1330180000000 | U9: 1337230000000 | V9: 1345090000000 | W9: 1349650000000 | X9: 1354440000000 | Y9: 1355570000000 | Z9: 1370240000000 | AA9: 1382410000000 | AB9: 1392580000000 | AC9: 1397090000000
A10: BAU Cargo Dist Transported[ships,passenger] | B10: NoSettings | C10: 2569250000 | D10: 2549940000 | E10: 2540130000 | F10: 2530000000 | G10: 2514050000 | H10: 2500930000 | I10: 2484450000 | J10: 2463560000 | K10: 2446900000 | L10: 2431850000 | M10: 2416380000 | N10: 2403780000 | O10: 2391830000 | P10: 2381750000 | Q10: 2372440000 | R10: 2362580000 | S10: 2352930000 | T10: 2342940000 | U10: 2334240000 | V10: 2324840000 | W10: 2313790000 | X10: 2302060000 | Y10: 2289690000 | Z10: 2280660000 | AA10: 2272380000 | AB10: 2262900000 | AC10: 2253050000
A11: BAU Cargo Dist Transported[ships,freight] | B11: NoSettings | C11: 2441710000000 | D11: 2399530000000 | E11: 2430970000000 | F11: 2477760000000 | G11: 2517530000000 | H11: 2560050000000 | I11: 2602100000000 | J11: 2640940000000 | K11: 2682410000000 | L11: 2723930000000 | M11: 2767410000000 | N11: 2803810000000 | O11: 2835670000000 | P11: 2867350000000 | Q11: 2896560000000 | R11: 2925920000000 | S11: 2953540000000 | T11: 2980900000000 | U11: 3008820000000 | V11: 3036410000000 | W11: 3063320000000 | X11: 3089560000000 | Y11: 3113470000000 | Z11: 3143230000000 | AA11: 3176380000000 | AB11: 3208820000000 | AC11: 3240050000000
A12: BAU Cargo Dist Transported[motorbikes,passenger] | B12: NoSettings | C12: 117250000000 | D12: 114466000000 | E12: 110748000000 | F12: 106408000000 | G12: 101958000000 | H12: 97544200000 | I12: 93398100000 | J12: 89399300000 | K12: 85579400000 | L12: 81897300000 | M12: 79067600000 | N12: 76056500000 | O12: 73077700000 | P12: 70674600000 | Q12: 68766800000 | R12: 66977500000 | S12: 65390800000 | T12: 64115200000 | U12: 62907300000 | V12: 61907000000 | W12: 60921800000 | X12: 60108200000 | Y12: 59348400000 | Z12: 58880100000 | AA12: 58188600000 | AB12: 57552600000 | AC12: 57141500000
... A8670: Transportation Sector Fuel Used[motorbikes,freight,hydrogen vehicle,hydrogen tf] | B8670: NoSettings | C8670: 0 | D8670: 0 | E8670: 0 | F8670: 0 | G8670: 0 | H8670: 0 | I8670: 0 | J8670: 0 | K8670: 0 | L8670: 0 | M8670: 0 | N8670: 0 | O8670: 0 | P8670: 0 | Q8670: 0 | R8670: 0 | S8670: 0 | T8670: 0 | U8670: 0 | V8670: 0 | W8670: 0 | X8670: 0 | Y8670: 0 | Z8670: 0 | AA8670: 0 | AB8670: 0 | AC8670: 0

Sheet Sheet1
A1: Time
A2: Transportation Pollutant Emissions Disaggregated[LDVs,CO2,passenger,electricity tf] | B2: Transportation Pollutant Emissions Disaggregated | C2: LDVs | D2: CO2 | E2: passenger | F2: electricity tf
A3: Transportation Pollutant Emissions Disaggregated[LDVs,CO2,passenger,natural gas tf] | B3: Transportation Pollutant Emissions Disaggregated | C3: LDVs | D3: CO2 | E3: passenger | F3: natural gas tf
A4: Transportation Pollutant Emissions Disaggregated[LDVs,CO2,passenger,petroleum gasoline tf] | B4: Transportation Pollutant Emissions Disaggregated | C4: LDVs | D4: CO2 | E4: passenger | F4: petroleum gasoline tf
A5: Transportation Pollutant Emissions Disaggregated[LDVs,CO2,passenger,petroleum diesel tf] | B5: Transportation Pollutant Emissions Disaggregated | C5: LDVs | D5: CO2 | E5: passenger | F5: petroleum diesel tf
A6: Transportation Pollutant Emissions Disaggregated[LDVs,CO2,passenger,biofuel gasoline tf] | B6: Transportation Pollutant Emissions Disaggregated | C6: LDVs | D6: CO2 | E6: passenger | F6: biofuel gasoline tf
A7: Transportation Pollutant Emissions Disaggregated[LDVs,CO2,passenger,biofuel diesel tf] | B7: Transportation Pollutant Emissions Disaggregated | C7: LDVs | D7: CO2 | E7: passenger | F7: biofuel diesel tf
A8: Transportation Pollutant Emissions Disaggregated[LDVs,CO2,passenger,jet fuel tf] | B8: Transportation Pollutant Emissions Disaggregated | C8: LDVs | D8: CO2 | E8: passenger | F8: jet fuel tf
A9: Transportation Pollutant Emissions Disaggregated[LDVs,CO2,passenger,heavy or residual fuel oil tf] | B9: Transportation Pollutant Emissions Disaggregated | C9: LDVs | D9: CO2 | E9: passenger | F9: heavy or residual fuel oil tf
A10: Transportation Pollutant Emissions Disaggregated[LDVs,CO2,passenger,LPG propane or butane tf] | B10: Transportation Pollutant Emissions Disaggregated | C10: LDVs | D10: CO2 | E10: passenger | F10: LPG propane or butane tf
A11: Transportation Pollutant Emissions Disaggregated[LDVs,CO2,passenger,hydrogen tf] | B11: Transportation Pollutant Emissions Disaggregated | C11: LDVs | D11: CO2 | E11: passenger | F11: hydrogen tf
A12: Transportation Pollutant Emissions Disaggregated[LDVs,CO2,freight,electricity tf] | B12: Transportation Pollutant Emissions Disaggregated | C12: LDVs | D12: CO2 | E12: freight | F12: electricity tf
A13: Transportation Pollutant Emissions Disaggregated[LDVs,CO2,freight,natural gas tf] | B13: Transportation Pollutant Emissions Disaggregated | C13: LDVs | D13: CO2 | E13: freight | F13: natural gas tf
... A1441: Transportation Pollutant Emissions Disaggregated[motorbikes,F gases,freight,hydrogen tf] | B1441: Transportation Pollutant Emissions Disaggregated | C1441: motorbikes | D1441: F gases | E1441: freight | F1441: hydrogen tf
A1442: Transportation Sector Pollutant Emissions[CO2] | B1442: Transportation Sector Pollutant Emissions | C1442: CO2
A1443: Transportation Sector Pollutant Emissions[VOC] | B1443: Transportation Sector Pollutant Emissions | C1443: VOC
A1444: Transportation Sector Pollutant Emissions[CO] | B1444: Transportation Sector Pollutant Emissions | C1444: CO
A1445: Transportation Sector Pollutant Emissions[NOx] | B1445: Transportation Sector Pollutant Emissions | C1445: NOx
A1446: Transportation Sector Pollutant Emissions[PM10] | B1446: Transportation Sector Pollutant Emissions | C1446: PM10
A1447: Transportation Sector Pollutant Emissions[PM25] | B1447: Transportation Sector Pollutant Emissions | C1447: PM25
A1448: Transportation Sector Pollutant Emissions[SOx] | B1448: Transportation Sector Pollutant Emissions | C1448: SOx
A1449: Transportation Sector Pollutant Emissions[BC] | B1449: Transportation Sector Pollutant Emissions | C1449: BC
A1450: Transportation Sector Pollutant Emissions[OC] | B1450: Transportation Sector Pollutant Emissions | C1450: OC
A1451: Transportation Sector Pollutant Emissions[CH4] | B1451: Transportation Sector Pollutant Emissions | C1451: CH4
A1452: Transportation Sector Pollutant Emissions[N2O] | B1452: Transportation Sector Pollutant Emissions | C1452: N2O
A1453: Transportation Sector Pollutant Emissions[F gases] | B1453: Transportation Sector Pollutant Emissions | C1453: F gases
A1454: Electricity Sector Pollutant Emissions[CO2,hard coal es] | B1454: Electricity Sector Pollutant Emissions | C1454: CO2 | D1454: hard coal es
A1455: Electricity Sector Pollutant Emissions[CO2,natural gas nonpeaker es] | B1455: Electricity Sector Pollutant Emissions | C1455: CO2 | D1455: natural gas nonpeaker es
A1456: Electricity Sector Pollutant Emissions[CO2,nuclear es] | B1456: Electricity Sector Pollutant Emissions | C1456: CO2 | D1456: nuclear es
A1457: Electricity Sector Pollutant Emissions[CO2,hydro es] | B1457: Electricity Sector Pollutant Emissions | C1457: CO2 | D1457: hydro es
A1458: Electricity Sector Pollutant Emissions[CO2,onshore wind es] | B1458: Electricity Sector Pollutant Emissions | C1458: CO2 | D1458: onshore wind es
A1459: Electricity Sector Pollutant Emissions[CO2,solar PV es] | B1459: Electricity Sector Pollutant Emissions | C1459: CO2 | D1459: solar PV es
A1460: Electricity Sector Pollutant Emissions[CO2,solar thermal es] | B1460: Electricity Sector Pollutant Emissions | C1460: CO2 | D1460: solar thermal es
A1461: Electricity Sector Pollutant Emissions[CO2,biomass es] | B1461: Electricity Sector Pollutant Emissions | C1461: CO2 | D1461: biomass es
A1462: Electricity Sector Pollutant Emissions[CO2,geothermal es] | B1462: Electricity Sector Pollutant Emissions | C1462: CO2 | D1462: geothermal es
A1463: Electricity Sector Pollutant Emissions[CO2,petroleum es] | B1463: Electricity Sector Pollutant Emissions | C1463: CO2 | D1463: petroleum es
A1464: Electricity Sector Pollutant Emissions[CO2,natural gas peaker es] | B1464: Electricity Sector Pollutant Emissions | C1464: CO2 | D1464: natural gas peaker es
A1465: Electricity Sector Pollutant Emissions[CO2,lignite es] | B1465: Electricity Sector Pollutant Emissions | C1465: CO2 | D1465: lignite es
... A1981: Process Emissions before CCS[construction 41T43,F gases] | B1981: Process Emissions before CCS | C1981: construction 41T43 | D1981: F gases
A1982: Industrial Energy Related Emissions Excluding Fuels to Power CCS[electricity if,agriculture and forestry 01T03,CO2] | B1982: Industrial Energy Related Emissions Excluding Fuels to Power CCS | C1982: electricity if | D1982: agriculture and forestry 01T03 | E1982: CO2
A1983: Industrial Energy Related Emissions Excluding Fuels to Power CCS[electricity if,agriculture and forestry 01T03,VOC] | B1983: Industrial Energy Related Emissions Excluding Fuels to Power CCS | C1983: electricity if | D1983: agriculture and forestry 01T03 | E1983: VOC
A1984: Industrial Energy Related Emissions Excluding Fuels to Power CCS[electricity if,agriculture and forestry 01T03,CO] | B1984: Industrial Energy Related Emissions Excluding Fuels to Power CCS | C1984: electricity if | D1984: agriculture and forestry 01T03 | E1984: CO
A1985: Industrial Energy Related Emissions Excluding Fuels to Power CCS[electricity if,agriculture and forestry 01T03,NOx] | B1985: Industrial Energy Related Emissions Excluding Fuels to Power CCS | C1985: electricity if | D1985: agriculture and forestry 01T03 | E1985: NOx
A1986: Industrial Energy Related Emissions Excluding Fuels to Power CCS[electricity if,agriculture and forestry 01T03,PM10] | B1986: Industrial Energy Related Emissions Excluding Fuels to Power CCS | C1986: electricity if | D1986: agriculture and forestry 01T03 | E1986: PM10
A1987: Industrial Energy Related Emissions Excluding Fuels to Power CCS[electricity if,agriculture and forestry 01T03,PM25] | B1987: Industrial Energy Related Emissions Excluding Fuels to Power CCS | C1987: electricity if | D1987: agriculture and forestry 01T03 | E1987: PM25
A1988: Industrial Energy Related Emissions Excluding Fuels to Power CCS[electricity if,agriculture and forestry 01T03,SOx] | B1988: Industrial Energy Related Emissions Excluding Fuels to Power CCS | C1988: electricity if | D1988: agriculture and forestry 01T03 | E1988: SOx
A1989: Industrial Energy Related Emissions Excluding Fuels to Power CCS[electricity if,agriculture and forestry 01T03,BC] | B1989: Industrial Energy Related Emissions Excluding Fuels to Power CCS | C1989: electricity if | D1989: agriculture and forestry 01T03 | E1989: BC
A1990: Industrial Energy Related Emissions Excluding Fuels to Power CCS[electricity if,agriculture and forestry 01T03,OC] | B1990: Industrial Energy Related Emissions Excluding Fuels to Power CCS | C1990: electricity if | D1990: agriculture and forestry 01T03 | E1990: OC
A1991: Industrial Energy Related Emissions Excluding Fuels to Power CCS[electricity if,agriculture and forestry 01T03,CH4] | B1991: Industrial Energy Related Emissions Excluding Fuels to Power CCS | C1991: electricity if | D1991: agriculture and forestry 01T03 | E1991: CH4
A1992: Industrial Energy Related Emissions Excluding Fuels to Power CCS[electricity if,agriculture and forestry 01T03,N2O] | B1992: Industrial Energy Related Emissions Excluding Fuels to Power CCS | C1992: electricity if | D1992: agriculture and forestry 01T03 | E1992: N2O
A1993: Industrial Energy Related Emissions Excluding Fuels to Power CCS[electricity if,agriculture and forestry 01T03,F gases] | B1993: Industrial Energy Related Emissions Excluding Fuels to Power CCS | C1993: electricity if | D1993: agriculture and forestry 01T03 | E1993: F gases
... A4981: Industrial Energy Related Emissions Excluding Fuels to Power CCS[hydrogen if,construction 41T43,F gases] | B4981: Industrial Energy Related Emissions Excluding Fuels to Power CCS | C4981: hydrogen if | D4981: construction 41T43 | E4981: F gases
A4982: Industrial Sector Pollutant Emissions[agriculture and forestry 01T03,CO2] | B4982: Industrial Sector Pollutant Emissions | C4982: agriculture and forestry 01T03 | D4982: CO2
A4983: Industrial Sector Pollutant Emissions[agriculture and forestry 01T03,VOC] | B4983: Industrial Sector Pollutant Emissions | C4983: agriculture and forestry 01T03 | D4983: VOC
A4984: Industrial Sector Pollutant Emissions[agriculture and forestry 01T03,CO] | B4984: Industrial Sector Pollutant Emissions | C4984: agriculture and forestry 01T03 | D4984: CO
A4985: Industrial Sector Pollutant Emissions[agriculture and forestry 01T03,NOx] | B4985: Industrial Sector Pollutant Emissions | C4985: agriculture and forestry 01T03 | D4985: NOx
A4986: Industrial Sector Pollutant Emissions[agriculture and forestry 01T03,PM10] | B4986: Industrial Sector Pollutant Emissions | C4986: agriculture and forestry 01T03 | D4986: PM10
A4987: Industrial Sector Pollutant Emissions[agriculture and forestry 01T03,PM25] | B4987: Industrial Sector Pollutant Emissions | C4987: agriculture and forestry 01T03 | D4987: PM25
A4988: Industrial Sector Pollutant Emissions[agriculture and forestry 01T03,SOx] | B4988: Industrial Sector Pollutant Emissions | C4988: agriculture and forestry 01T03 | D4988: SOx
A4989: Industrial Sector Pollutant Emissions[agriculture and forestry 01T03,BC] | B4989: Industrial Sector Pollutant Emissions | C4989: agriculture and forestry 01T03 | D4989: BC
A4990: Industrial Sector Pollutant Emissions[agriculture and forestry 01T03,OC] | B4990: Industrial Sector Pollutant Emissions | C4990: agriculture and forestry 01T03 | D4990: OC
A4991: Industrial Sector Pollutant Emissions[agriculture and forestry 01T03,CH4] | B4991: Industrial Sector Pollutant Emissions | C4991: agriculture and forestry 01T03 | D4991: CH4
A4992: Industrial Sector Pollutant Emissions[agriculture and forestry 01T03,N2O] | B4992: Industrial Sector Pollutant Emissions | C4992: agriculture and forestry 01T03 | D4992: N2O
A4993: Industrial Sector Pollutant Emissions[agriculture and forestry 01T03,F gases] | B4993: Industrial Sector Pollutant Emissions | C4993: agriculture and forestry 01T03 | D4993: F gases
... A5281: Industrial Sector Pollutant Emissions[construction 41T43,F gases] | B5281: Industrial Sector Pollutant Emissions | C5281: construction 41T43 | D5281: F gases
A5282: Output Total CO2e Emissions by Sector[transportation sector] | B5282: Output Total CO2e Emissions by Sector | C5282: transportation sector
A5283: Output Total CO2e Emissions by Sector[electricity sector] | B5283: Output Total CO2e Emissions by Sector | C5283: electricity sector
A5284: Output Total CO2e Emissions by Sector[district heat and hydrogen sector] | B5284: Output Total CO2e Emissions by Sector | C5284: district heat and hydrogen sector
A5285: Output Total CO2e Emissions by Sector[LULUCF sector] | B5285: Output Total CO2e Emissions by Sector | C5285: LULUCF sector
A5286: Output Total CO2e Emissions by Sector[geoengineering sector] | B5286: Output Total CO2e Emissions by Sector | C5286: geoengineering sector
A5287: Output Industry Sector Process Emissions in CO2e Excluding Ag and Waste | B5287: Output Industry Sector Process Emissions in CO2e Excluding Ag and Waste
A5288: Output Industry Sector Energy Related CO2e Emissions Excluding Ag and Waste | B5288: Output Industry Sector Energy Related CO2e Emissions Excluding Ag and Waste
A5289: Output Agriculture CO2e Emissions | B5289: Output Agriculture CO2e Emissions
A5290: Output Waste Management CO2e Emissions | B5290: Output Waste Management CO2e Emissions
A5291: Output Buildings Sector CO2e Emissions | B5291: Output Buildings Sector CO2e Emissions
A5292: Electricity Generation by Type Including Distributed Generation[hard coal es] | B5292: Electricity Generation by Type Including Distributed Generation | C5292: hard coal es
A5293: Electricity Generation by Type Including Distributed Generation[natural gas nonpeaker es] | B5293: Electricity Generation by Type Including Distributed Generation | C5293: natural gas nonpeaker es
A5294: Electricity Generation by Type Including Distributed Generation[nuclear es] | B5294: Electricity Generation by Type Including Distributed Generation | C5294: nuclear es
A5295: Electricity Generation by Type Including Distributed Generation[hydro es] | B5295: Electricity Generation by Type Including Distributed Generation | C5295: hydro es
A5296: Electricity Generation by Type Including Distributed Generation[onshore wind es] | B5296: Electricity Generation by Type Including Distributed Generation | C5296: onshore wind es
A5297: Electricity Generation by Type Including Distributed Generation[solar PV es] | B5297: Electricity Generation by Type Including Distributed Generation | C5297: solar PV es
A5298: Electricity Generation by Type Including Distributed Generation[solar thermal es] | B5298: Electricity Generation by Type Including Distributed Generation | C5298: solar thermal es
A5299: Electricity Generation by Type Including Distributed Generation[biomass es] | B5299: Electricity Generation by Type Including Distributed Generation | C5299: biomass es
A5300: Electricity Generation by Type Including Distributed Generation[geothermal es] | B5300: Electricity Generation by Type Including Distributed Generation | C5300: geothermal es
A5301: Electricity Generation by Type Including Distributed Generation[petroleum es] | B5301: Electricity Generation by Type Including Distributed Generation | C5301: petroleum es
A5302: Electricity Generation by Type Including Distributed Generation[natural gas peaker es] | B5302: Electricity Generation by Type Including Distributed Generation | C5302: natural gas peaker es
A5303: Electricity Generation by Type Including Distributed Generation[lignite es] | B5303: Electricity Generation by Type Including Distributed Generation | C5303: lignite es
... A5307: Electricity Generation by Type Including Distributed Generation[municipal solid waste es] | B5307: Electricity Generation by Type Including Distributed Generation | C5307: municipal solid waste es
A5308: Total Pollutant Emissions by Sector[transportation sector,CO2] | B5308: Total Pollutant Emissions by Sector | C5308: transportation sector | D5308: CO2
A5309: Total Pollutant Emissions by Sector[transportation sector,VOC] | B5309: Total Pollutant Emissions by Sector | C5309: transportation sector | D5309: VOC
A5310: Total Pollutant Emissions by Sector[transportation sector,CO] | B5310: Total Pollutant Emissions by Sector | C5310: transportation sector | D5310: CO
A5311: Total Pollutant Emissions by Sector[transportation sector,NOx] | B5311: Total Pollutant Emissions by Sector | C5311: transportation sector | D5311: NOx
A5312: Total Pollutant Emissions by Sector[transportation sector,PM10] | B5312: Total Pollutant Emissions by Sector | C5312: transportation sector | D5312: PM10
A5313: Total Pollutant Emissions by Sector[transportation sector,PM25] | B5313: Total Pollutant Emissions by Sector | C5313: transportation sector | D5313: PM25
A5314: Total Pollutant Emissions by Sector[transportation sector,SOx] | B5314: Total Pollutant Emissions by Sector | C5314: transportation sector | D5314: SOx
A5315: Total Pollutant Emissions by Sector[transportation sector,BC] | B5315: Total Pollutant Emissions by Sector | C5315: transportation sector | D5315: BC
A5316: Total Pollutant Emissions by Sector[transportation sector,OC] | B5316: Total Pollutant Emissions by Sector | C5316: transportation sector | D5316: OC
A5317: Total Pollutant Emissions by Sector[transportation sector,CH4] | B5317: Total Pollutant Emissions by Sector | C5317: transportation sector | D5317: CH4
A5318: Total Pollutant Emissions by Sector[transportation sector,N2O] | B5318: Total Pollutant Emissions by Sector | C5318: transportation sector | D5318: N2O
A5319: Total Pollutant Emissions by Sector[transportation sector,F gases] | B5319: Total Pollutant Emissions by Sector | C5319: transportation sector | D5319: F gases
...

Sheet Vensim Variables
A1: Variables | B1: Units | C1: Sector
A2: Transportation Pollutant Emissions Disaggregated | B2: g pollutant
A3: Transportation Sector Pollutant Emissions | B3: g pollutant
A4: Electricity Sector Pollutant Emissions | B4: g pollutant
A5: Buildings Sector Pollutant Emissions | B5: g pollutant
A6: Process Emissions after CCS | B6: g pollutant
A7: Industrial Sector Energy Related Emissions after CCS | B7: g pollutant
A8: Industrial Sector Pollutant Emissions | B8: g pollutant
A9: Output Total CO2e Emissions by Sector[transportation sector] | B9: MMTCO2e
A10: Output Total CO2e Emissions by Sector[electricity sector] | B10: MMTCO2e
A11: Output Total CO2e Emissions by Sector[district heat and hydrogen sector] | B11: MMTCO2e
A12: Output Total CO2e Emissions by Sector[LULUCF sector] | B12: MMTCO2e
A13: Output Total CO2e Emissions by Sector[geoengineering sector] | B13: MMTCO2e
... A22: Output Total CO2e Emissions by Sector | B22: MMTCO2e

Sheet EPA_GHG

Sheet Table 3-1
A1: Table 3-1: CO2, CH4, and N2O Emissions from Energy (MMT CO2 Eq.) | E1: =SUM(C13:C14,C25,C27,C29) -> 269.92235
B3: Gas/Source | C3: 2023 | D3: Process vs. other | E3: Industrial sector | F3: gas
B4: CO2 | C4: 4742.3359
B5: Fossil Fuel Combustion | C5: 4559.3792 | D5: included in sector tabs | F5: CO2 | H5: Energy | I5: =SUM(C5,C15,C28,C31,C35,C36,C37) -> 4619.2588 | J5: =SUM('6. Total'!K9,'6. Total'!K10,'6. Total'!K17,'6. Total'!K14) -> 4593.6151
B6: Transportation | C6: 1776.4505 | D6: included in sector tabs | F6: CO2 | H6: Process | I6: =SUM(C12,C13,C14,C16,C25,C26,C27,C29,C30)+'Table 4-1'!C58 -> 812.56186 | J6: ='6. Total'!K13 -> 816.5083
B7: Electricity Generation | C7: 1414.1775 | D7: included in sector tabs | F7: CO2 | H7: Total | I7: =SUM(I5:I6) -> 5431.8207 | J7: =SUM(5173.3,381.6) -> 5554.9
B8: Industrial | C8: 792.61967 | D8: included in sector tabs | F8: CO2
B9: Residential | C9: 307.07737 | D9: included in sector tabs | F9: CO2
B10: Commercial | C10: 244.16078 | D10: included in sector tabs | F10: CO2
B11: U.S. Territories | C11: 24.893367 | D11: Not included | F11: CO2
B12: Non-Energy Use of Fuels | C12: 107.06948 | F12: CO2
B13: Natural Gas Systems | C13: 37.681565 | D13: process | E13: oil and gas extraction 06 | F13: CO2
B14: Petroleum Systems | C14: 23.271596 | D14: process | E14: oil and gas extraction 06 | F14: CO2
B15: Incineration of Waste | C15: 12.425005 | F15: CO2
B16: Coal Mining | C16: 2.4037187 | D16: process | E16: coal mining 05 | F16: CO2
B17: CO2 Transport, Injection, and Geological and Storage | C17: 0.097643205
B18: Abandoned Oil and Gas Wells | C18: 0.007757168 | D18: process | F18: CO2
B19: Biomass-Wood a | C19: 187.68968 | D19: Not included | F19: CO2
B20: International Bunker Fuels b | C20: 96.159803 | D20: Not included | F20: CO2
B21: Biofuels-Ethanol a | C21: 80.708082 | D21: Not included | F21: CO2
B22: Biofuels-Biodiesel a | C22: 18.184651 | D22: Not included | F22: CO2
B23: Biomass-MSW a | C23: 13.935685 | D23: Not included | F23: CO2
B24: CH4 | C24: 271.85366
B25: Natural Gas Systems | C25: 162.44598 | D25: process | E25: oil and gas extraction 06 | F25: CH4
B26: Coal Mining | C26: 45.430056 | D26: process | E26: coal mining 05 | F26: CH4
B27: Petroleum Systems | C27: 38.028099 | D27: process | E27: oil and gas extraction 06 | F27: CH4
B28: Stationary Combustion | C28: 8.776103 | D28: included in sector tabs | F28: CH4
B29: Abandoned Oil and Gas Wells | C29: 8.4951084 | D29: process | E29: oil and gas extraction 06 | F29: CH4
B30: Abandoned Underground Coal Mines | C30: 6.1362542 | D30: process | E30: coal mining 05 | F30: CH4
B31: Mobile Combustion | C31: 2.5419145 | D31: included in sector tabs | F31: CH4
B32: Incineration of Waste | C32: 0.000138299 | F32: CH4
B33: International Bunker Fuels b | C33: 0.082633123 | D33: Not included | F33: CH4
B34: N2O | C34: 36.166811
B35: Stationary Combustion | C35: 19.564306 | D35: included in sector tabs | F35: N2O
B36: Mobile Combustion | C36: 16.245076 | D36: included in sector tabs | F36: N2O
B37: Incineration of Waste | C37: 0.32721731 | F37: N2O
B38: Petroleum Systems | C38: 0.008165215 | D38: process | E38: natural gas and petroleum systems | F38: N2O
B39: Natural Gas Systems | C39: 0.022045884 | F39: N2O
B40: International Bunker Fuels b | C40: 0.7548416 | D40: Not included | F40: N2O
B41: Total | C41: 5050.3564
B42: Note: Totals may not sum due to independent rounding.
B43: + Does not exceed 0.05 MMT CO2 Eq.
B44: a Emissions from Wood Biomass, Ethanol, and Biodiesel Consumption are not included specifically in summing Energy sector totals. Net carbon fluxes from changes in biogenic carbon reservoirs are accounted for in the estimates for LULUCF.
B45: b Emissions from International Bunker Fuels are not included in totals. These values are presented for informational purposes only, in line with the 2006 IPCC Guidelines and UNFCCC reporting obligations.

Sheet Table 3-7
A1: Table 3-7: CO2 Emissions from Stationary Fossil Fuel Combustion (MMT CO2 Eq.)
B3: Sector/Fuel Type | C3: 2023
B4: Electric Power | C4: 1414.1775
B5: Coal | C5: 694.55699
B6: Natural Gas | C6: 704.54465
B7: Fuel Oil | C7: 14.708588
B8: Geothermal | C8: 0.36724082
B9: Industrial | C9: 792.61967
B10: Coal | C10: 36.484927
B11: Natural Gas | C11: 514.79147
B12: Fuel Oil | C12: 241.34327
