Workbook

Sheet About
A1: Web App Data
A3: This spreadsheet contains data that is used to populate the web application interface
A4: for the Energy Policy Simulator. The data in other tabs in this spreadsheet are used
A5: to establish the policy levers, lever bounds, descriptive text for pop-over
A6: panels, output graphs, and reference scenarios available in the web app.
A8: A live version of the web application interface powered by a copy of this model
A9: can be found at:
A10: https://www.energypolicy.solutions
A12: You are unlikely to need to use or change the contents of this spreadsheet, unless
A13: you are adapting the Energy Policy Simulator to a new country and desire
A14: a web application interface customized for your country-specific model version.
A16: Checks for Policy ID Number Validity
A17: Max policy ID number in use | B17: 3306
A18: Lowest duplicate ID number | B18: {=IF(MIN(IF(COUNTIF(PolicyLevers!$H$2:$H$3291,PolicyLevers!$H$2:$H$3291)>1,PolicyLevers!$H$2:$H$3291, ""))=0,"No duplicate ID numbers",MIN(IF(COUNTIF(PolicyLevers!$H$2:$H$3291,PolicyLevers!$H$2:$H$3291)>1,PolicyLevers!$H$2:$H$3291, "")))} -> No duplicate ID numbers
A19: Row of first policy missing a valid ID number | B19: {=IF(MIN(IF((NOT(ISNUMBER(PolicyLevers!$H$2:$H$3291)))*(ISTEXT(PolicyLevers!$I$2:$I$3291)),ROW(PolicyLevers!$H$2:$H$3291)))=0,"No missing ID numbers",MIN(IF((NOT(ISNUMBER(PolicyLevers!$H$2:$H$3291)))*(ISTEXT(PolicyLevers!$I$2:$I$3291)),ROW(PolicyLevers!$H$2:$H$3291))))} -> No missing ID numbers
A21: Customizing Policy Levers
A22: Define most policy properties on the "Policy Characteristics" tab.
A23: Specify the subscripted elements of each policy and which are enabled/disabled on the "PolicyLevers" tab.
A24: On the PolicyLevers tab, only manually edit the cells under the green column headers. Simply extend the
A25: existing formulas up or down to fill cells under the red headers on that tab.
A27: Notes on Meaning of Blank Cells on the Policy Characteristics Tab
A28: Leave the "Policy Schedule Subscript" cell blank to deny the ability to edit the implementation
A29: schedule for a lever. This should generally only be done for levers that do not use an
A30: implementation schedule: the toggle to Non-BAU Mandated Capacity Construction
A31: (which has its own schedule built into its input data) and the Nuclear Lifetime Extension
A32: (which simply delays retirements that would occur in the BAU Retirements input data).
A34: Leave the "Policy Group" cell blank to exclude a lever from wedge diagrams and abatement cost curves.
... A59: are ignored. The web app will look for an equals sign in Units to choose the selector input control.

Sheet Policy Characteristics
A1: This tab contains information about each policy that does not vary by subscripted element of that policy.
A2: It matches policies to the listing in the "PolicyLevers" tab using the "Vensim Variable Name" column.
A3: Sector | B3: Short Name | C3: Vensim Variable Name | D3: Policy Group | E3: Policy Schedule Subscript | F3: Min Slider Value | G3: Max Slider Value | H3: Slider Step Size | I3: Units | J3: Text for Pop-Over Panel Description | K3: URL for "How the model handles this policy" links | L3: URL for "How to design this policy well" links | M3: Source for Guidance Text (if any) | N3: Source for Max Slider Value (if any)
A4: Transportation | B4: Conventional Pollutant Standards | C4: Percentage Reduction of Separately Regulated Pollutants | D4: Conventional Pollutant Standard | E4: trans reduce regulated pollutants | F4: 0 | G4: 1 | H4: 0.02 | I4: % reduction in emissions | J4: **Description:** This policy represents strengthening standards for the selected pollutant(s) emitted by the selected vehicle type(s). Conventional pollutants' most important, harmful impacts are on human health rather than on climate change. The following descriptions detail the different vehicle types: // **Passenger cars and SUVs:** most light-duty road vehicles // **Light and Medium Commercial Trucks:** commercial trucks carrying freight, not passengers // **Buses:** including school, transit, and intercity buses // **Heavy Duty Trucks:** all other heavy road vehicles (mostly freight trucks) // **Commercial passenger flights:** this is not general aviation // **Commercial freight flights:** this includes all other commercial flights, and is not general aviation // **Passenger rail:** intercity, transit, and commuter rail // **Freight rail:** all other rail // **Recreational boats:** not commercial passenger ferries // **Cargo ships:** commercial ships carrying freight // **Passenger motorbikes:** registered motorcycles // **Guidance for setting values:** In the United States, since 1997, the 24-hour national ambient air quality standard (NAAQS) for PM2.5, the most harmful type of particulate for human health, declined from 65 µg/m^3 to 35 µg/m^3, a reduction of 46%. | K4: transportation-sector-main.html#conv-pol-stds | L4: conventional-pollutant-standards.html
A5: Transportation | B5: Electric Vehicle Charger Deployment | C5: Percentage Increase in EV Chargers | D5: EV Charger Deployment | E5: trans EV charger deployment | F5: -1 | G5: 3 | H5: 0.1 | I5: % change | J5: **Description:** This policy increases the deployment of EV charging stations, including DC Fast and Level 2 charging stations. A negative value decreases chargers relative to the Current Policies scenario. // **Guidance for setting values:** This policy increases vehicle deployment by lowering the perceived charging availability penalty for EVs, insofar as it increases the ratio of EV chargers to gasoline pumps. In the United States, we find the charging availability penalty already reaches zero by roughly 2030. Beyond that point, this policy lever will have no additional effect on EV deployment. | L5: ev-charger-deployment.html | M5: Number of EV chargers: https://evadoption.com/ev-charging-stations-statistics/ Number of gas stations: U.S. Census, Statistics of U.S. Businesses, https://www.census.gov/data/tables/2016/econ/susb/2016-susb-annual.html Pumps per station: https://247wallst.com/economy/2014/05/22/why-are-there-115000-or-150000-gas-stations-in-america/
A6: Transportation | B6: Electric Vehicle Range | C6: Reduce EV Range Anxiety | D6: EV Range & Charging Time | E6: trans reduce EV range anxiety | F6: 0 | G6: 1 | H6: 0.02 | I6: % reduction in concern | J6: **Description:** This policy specifies a percentage reduction in vehicle buyers' aversion to electric vehicles due to concerns over the vehicles' range (how far the EV can travel on a charge). A 100% setting implies consumers are no more concerned about EV range and charging time than they are about range and fueling time of gasoline vehicles. It does not imply that range is infinite. This policy only affects passenger cars and SUVs (most light-duty road vehicles). // **Guidance for setting values:** U.S. model year 2017 all-electric (not hybrid) vehicles had ranges from 58 to 335 miles (median 114 miles). | L6: reduce-range-anxiety-charging-time.html | M6: Ranges: https://www.energy.gov/eere/vehicles/articles/fotw-1010-january-1-2018-all-electric-light-vehicle-ranges-can-exceed-those Charging Times: https://www.chargepoint.com/files/Quick_Guide_to_Fast_Charging.pdf
A7: Transportation | B7: Passenger Vehicle Subsidy | C7: Additional Passenger Vehicle Subsidy | D7: Vehicle Subsidy | E7: trans psgr subsidy | F7: -45000 | G7: 50000 | H7: 100 | I7: $ / vehicle | J7: **Description:** This policy specifies the dollar amount offered as a subsidy to the purchaser of a new passenger vehicle. This is in addition to subsidies that exist in the BAU case. A negative value implies a tax or removal of subsidies. // **Guidance for setting values:** The U.S. currently offers a federal tax credit for up to $7,500 for qualifying clean passenger light-duty vehicles as part of the Inflation Reduction Act. This tax credit is included in the BAU scenario as an estimated average credit for new vehicles, accounting for the fact many vehicles will not be eligible starting in 2025 due to requirements for critical minerals sourcing. The BAU also includes the weighted average state-level credit offered for vehicles in the U.S. on top of the federal tax credits. | K7: transportation-sector-main.html#ev-subsidy | L7: ev-subsidy.html | M7: https://www.fueleconomy.gov/feg/taxevb.shtml plus Chevrolet and Tesla websites
A8: Transportation | B8: Freight Vehicle Subsidy | C8: Additional Freight Vehicle Subsidy | D8: Vehicle Subsidy | E8: trans frgt subsidy | F8: -45000 | G8: 50000 | H8: 100 | I8: $ / vehicle | J8: **Description:** This policy specifies the dollar amount offered as a subsidy to the purchaser of a new freight vehicle. This is in addition to subsidies that exist in the BAU case. A negative value implies a tax or removal of subsidies. // **Guidance for setting values:** The U.S. currently offers a federal tax credit for up to $40,500 for qualifying clean commercial vehicles, which is incorporated in the BAU. | K8: transportation-sector-main.html#ev-subsidy | L8: ev-subsidy.html
A9: Transportation | B9: Feebate | C9: LDVs Feebate Rate | D9: Feebate | E9: trans LDVs feebate | F9: 0 | G9: 1 | H9: 0.02 | I9: % of global best practice rate | J9: **Description:** This policy implements a fee on sales of inefficient cars and SUVs (light-duty road vehicles; LDVs) that is rebated to buyers of efficient LDVs. The feebate policy is revenue-neutral, as the pivot point (the efficiency level that incurs neither a rebate nor a fee) is set such that the total of all fees equals the total of all rebates. // **Guidance for setting values:** The feebate is set as a fraction of the global best practice feebate rate. The global best practice feebate rate is $2000 per (hundredth gal/mile), which equates to a $2000 fee on an LDV that gets 20 mpg if the pivot point is 25 mpg. (To see this: 20 mpg is 0.04 gpm. 25 mpg is 0.05 gpm. The difference is -.01 gpm. So in order to levy a $2000 fee on the 20 mpg car when the pivot point is 25 mpg, we need a rate of $2000/.01 gpm.) | K9: transportation-sector-main.html#feebate | L9: feebate.html | M9: Greene et al., 2005, "Feebates, rebates and gas-guzzler taxes: a study of incentives for increased fuel economy", Energy Policy, 33(6), 757-775, http://cta.ornl.gov/cta/Publications/Reports/FeebateEnergyPolicy_FINAL.pdf. | N9: John German and Dan Meszler, 2010, "Best Practices for Feebate Program Design and Implementation", ICCT, http://www.theicct.org/sites/default/files/publications/ICCT_feebates_may2010.pdf, Table 2
A10: Transportation | B10: Fuel Economy Standard | C10: Percentage Additional Improvement of Fuel Economy Std | D10: Vehicle Fuel Economy Standards | E10: trans fuel economy standards | F10: -0.25 | G10: =ROUND(MaxBoundCalculations!B88,1) -> 1 | H10: 0.01 | I10: % change in miles/gal | J10: **Description:** This policy specifies a percentage improvement in fuel economy (distance traveled on the same quantity of fuel with the same cargo or passenger loading) due to fuel economy standards for newly sold vehicles of the selected type(s) with fossil fuel-burning engines. A negative value implies a decrease in fuel economy. The following descriptions detail the different vehicle types: // **Passenger cars and SUVs:** most light-duty road vehicles // **Light and Medium Commercial Trucks:** commercial trucks carrying freight, not passengers // **Buses:** including school, transit, and intercity buses // **Heavy Duty Trucks:** all other heavy road vehicles (mostly freight trucks) // **Commercial passenger flights:** this is not general aviation // **Commercial freight flights:** this includes all other commercial flights, and is not general aviation // **Passenger rail:** intercity, transit, and commuter rail // **Freight rail:** all other rail // **Recreational boats:** not commercial passenger ferries // **Cargo ships:** commercial ships carrying freight // **Passenger motorbikes:** registered motorcycles // **Guidance for setting values:** // **Passenger cars and SUVs:** U.S. combined fuel economy standards for cars and light trucks were 34.6 mpg in 2020 and are scheduled to rise to 38.3 mpg through 2026, then remain constant. The National Research Council's estimated future average fuel economy is roughly 74 mpg for a midrange scenario and 94 mpg for an optimistic scenario. // **Light and Medium Commercial Trucks:** U.S. fuel economy standards for heavy-duty vehicles vary by vehicle characteristics, but proposed standards for vocational vehicles (the category that includes buses) would reduce GHG emissions by 24% for 2027 model year vehicles relative to the 2018 model year, then remain constant. Extrapolating this trend to 2050 would be an 85% improvement relative to 2018, compared to a 40% improvement relative to 2018 in the BAU case. This could be represented by a policy lever setting of 45%. // **Heavy Duty Trucks:** U.S. fuel economy standards for heavy-duty vehicles vary by vehicle characteristics, but proposed standards for combination tractor-trailers (which are responsible for roughly 60% of HDV emissions) would reduce GHG emissions by 25% for 2027 model year trucks relative to the 2018 model year, then remain constant. Extrapolating this trend to 2050 would be an 96% improvement relative to 2018, compared to a 40% improvement relative to 2018 in the BAU case. This could be represented by a policy lever setting of 56%. // **Commercial passenger flights:** The U.S. currently does not have fuel economy standards for aircraft. In the absence of standards, new passenger aircraft fuel economy is projected to improve roughly 17% from 2018-2050 in the BAU case. // **Commercial freight flights:** The U.S. currently does not have fuel economy standards for aircraft. In the absence of standards, new freight aircraft fuel economy is projected to improve roughly 50% from 2018-2050 in the BAU case. // **Passenger rail:** The U.S. currently does not have fuel economy standards for trains. In the absence of standards, new passenger train fuel economy is not projected to change significantly from 2018-2050 in the BAU case. // **Freight rail:** The U.S. currently does not have fuel economy standards for trains. In the absence of standards, new freight train fuel economy is projected to improve roughly 23% from 2018-2050 in the BAU case. // **Recreational boats:** The U.S. currently does not have fuel economy standards for recreational boats. In the absence of standards, new passenger boat fuel economy is not projected to change significantly from 2018-2050 in the BAU case. // **Cargo ships:** The U.S. currently does not have fuel economy standards for ships. In the absence of standards, new freight ship fuel economy is projected to improve roughly 21% from 2018-2050 in the BAU case. however, the ICCT suggests in-use CO2 intensity of freight ships could fall by roughly 50% by 2040, corresponding to a 100% improvement in fuel economy. // **Passenger motorbikes:** The U.S. currently does not have fuel economy standards for motorbikes. In the absence of standards, new motorbike fuel economy is not projected to change significantly from 2018-2050 in the BAU case. | K10: transportation-sector-main.html#fuel-econ-std | L10: fuel-economy-standard.html | M10: U. S. EPA, 2012, "Fact Sheet: EPA and NHTSA Set Standards to Reduce Greenhouse Gases and Improve Fuel Economy for Model Years 2017-2025 Cars and Light Trucks", https://nepis.epa.gov/Exe/ZyNET.exe/P100EZ7C.txt?ZyActionD=ZyDocument&Client=EPA&Index=2011%20Thru%202015&Docs=&Query=&Time=&EndTime=&SearchMethod=1&TocRestrict=n&Toc=&TocEntry=&QField=&QFieldYear=&QFieldMonth=&QFieldDay=&UseQField=&IntQFieldOp=0&ExtQFieldOp=0&XmlQuery=&File=D%3A%5CZYFILES%5CINDEX%20DATA%5C11THRU15%5CTXT%5C00000005%5CP100EZ7C.txt&User=ANONYMOUS&Password=anonymous&SortMethod=h%7C-&MaximumDocuments=1&FuzzyDegree=0&ImageQuality=r75g8/r75g8/x150y150g16/i425&Display=hpfr&DefSeekPage=x&SearchBack=ZyActionL&Back=ZyActionS&BackDesc=Results%20page&MaximumPages=1&ZyEntry=4, Table 1, Row 4. U.S. EPA, 2015, "EPA and NHTSA Propose Standards to Reduce Greenhouse Gas Emissions and Improve Fuel Efficiency of Medium- and Heavy-Duty Vehicles for Model Year 2018 and Beyond", https://nepis.epa.gov/Exe/ZyNET.exe/P100P7NL.txt?ZyActionD=ZyDocument&Client=EPA&Index=2016%20Thru%202020&Docs=&Query=&Time=&EndTime=&SearchMethod=1&TocRestrict=n&Toc=&TocEntry=&QField=&QFieldYear=&QFieldMonth=&QFieldDay=&UseQField=&IntQFieldOp=0&ExtQFieldOp=0&XmlQuery=&File=D%3A%5CZYFILES%5CINDEX%20DATA%5C16THRU20%5CTXT%5C00000002%5CP100P7NL.txt&User=ANONYMOUS&Password=anonymous&SortMethod=h%7C-&MaximumDocuments=1&FuzzyDegree=0&ImageQuality=r75g8/r75g8/x150y150g16/i425&Display=hpfr&DefSeekPage=x&SearchBack=ZyActionL&Back=ZyActionS&BackDesc=Results%20page&MaximumPages=1&ZyEntry=3, Page 3. https://theicct.org/sites/default/files/publications/ICCT_ShipEfficiency_20130723.pdf Others calculated from model input data. | N10: National Research Council, 2013, "Transitions to Alternative Vehicles and Fuels", https://www.nap.edu/catalog/18264/transitions-to-alternative-vehicles-and-fuels, Table 2.9, Fuel economy test mpg. U.S. DoE, 2013, "Potential for Energy Efficiency Improvement Beyond the Light-Duty-Vehicle Sector," http://www.nrel.gov/docs/fy13osti/55637.pdf, Table 2.2 and Section 3.4.5, Paragraph 1 David McCollum, Gregory Gould, and Davide Greene, 2009, "Greenhouse Gas Emissions from Aviation and Marine Transportation: Mitigation Potential and Policies", Pew Center on Global Climate Change, http://www.c2es.org/docUploads/aviation-and-marine-report-2009.pdf, Table 4 https://theicct.org/sites/default/files/publications/ICCT_ShipEfficiency_20130723.pdf
A11: Transportation | B11: Low Carbon Fuel Standard | C11: Additional LCFS Percentage | D11: Low Carbon Fuel Standard | E11: trans LCFS | F11: 0 | G11: 1 | H11: 0.01 | I11: % reduction in carbon emissions | J11: **Description:** This policy specifies the percentage reduction in carbon emissions from the transportation sector that must be achieved via fuel switching. By default, this policy applies to all non-aviation vehicle types. If the lever Non-BAU LCFS-Qualifying Vehicles is enabled, this policy only applies to aviation and represents the use of sustainable aviation fuels. The value set in this lever is in addition to BAU requirements. // **Guidance for setting values:** The U.S. National Renewable Fuel Standard equates to a BAU LCFS of 2.2% - 4.6% (varying by year). California adopted an LCFS that requires a 10% reduction in carbon intensity of the transportation fuel pool by 2020. | K11: transportation-sector-main.html#lcfs | L11: low-carbon-fuel-standard.html | M11: https://www.arb.ca.gov/fuels/lcfs/background/basics.htm
A12: Transportation | B12: Non-BAU LCFS-Qualifying Vehicles | C12: Boolean Use Non BAU LCFS Vehicle Types | D12: Low Carbon Fuel Standard | E12: trans LCFS vehicles | F12: 0 | G12: 1 | H12: 1 | I12: on/off | J12: **Description:** This lever changes which vehicles qualify under the low carbon fuel standard. With the lever off, LCFS-qualifying vehicles include all vehicle types except aircraft. With the lever on, only aircraft qualify. | K12: transportation-sector-main.html#lcfs | L12: low-carbon-fuel-standard.html | M12: https://www.arb.ca.gov/fuels/lcfs/background/basics.htm
A13: Transportation | B13: Mode Shifting | C13: Percent of Travel Demand Shifted to Other Modes or Eliminated | D13: Mode Shifting | E13: trans mode shifting | F13: 0 | G13: =-ROUND(MaxBoundCalculations!$B$206,2) -> 0.33 | H13: 0.01 | I13: % of trips shifted | J13: **Description:** This policy represents a set of measures aimed at reducing demand for passenger or freight transportation in the selected vehicle type(s). **Passenger car and SUV** trips may be shifted to other travel modes, such as buses, rail, walking, biking, or eliminated through technology such as videoconferencing. Example measures include improved public transit systems, more walking and bike paths, zoning for higher density along transit corridors, zoning for mixed-use developments, roadway and congestion pricing, and increased parking fees. **Commercial passenger and freight flight** trips may be shifted to inter-city rail or eliminated using technology such as videoconferencing. **Heavy Heavy Duty Truck** trips can be reduced through improved logistics that avoids backhauls and transporting empty shipping containers. The following descriptions detail the different vehicle types: // **Passenger cars and SUVs:** most light-duty road vehicles // **Heavy Duty Trucks:** all other heavy road vehicles (mostly freight trucks) // **Commercial passenger flights:** this is not general aviation // **Guidance for setting values:** // **Passenger cars and SUVs:** The International Energy Agency's BLUE Shifts scenario (from the 2009 report "Transport, Energy, and CO2: Moving Toward Sustainability") includes a 26% reduction in usage of cars and SUVs in OECD countries by 2050 relative to a BAU case. // **Commercial passenger flights:** The International Energy Agency's BLUE Shifts scenario (from the 2009 report "Transport, Energy, and CO2: Moving Toward Sustainability") includes a 30% reduction in usage of aircraft in OECD countries by 2050 relative to a BAU case. // **Heavy Duty Trucks:** The U.S. Federal Highway Administration reports that approximately 25% of mileage for trucks larger than pickups/minivans/other light vans are for empty backhauls and empty shipping containers. | K13: transportation-sector-main.html#tdm | L13: transportation-demand-management.html | M13: International Energy Agency, 2009, "Transport, Energy and CO2: Moving toward Sustainability", http://www.iea.org/publications/freepublications/publication/transport2009.pdf "Freight Facts and Figures", 2013, https://ops.fhwa.dot.gov/freight/freight_analysis/nat_freight_stats/docs/13factsfigures/pdfs/fff2013_highres.pdf
A14: Transportation | B14: Federal Zero-Emission Vehicle Sales Standard | C14: Additional Minimum Required ZEV Sales Percentage for Model Region | D14: ZEV Sales Standard | E14: trans ZEV minimum | F14: -1 | G14: 1 | H14: 0.01 | I14: % of new vehicles sold | J14: **Description:** This policy requires a specified percentage of newly sold vehicles of the selected type(s) to consist of zero-emission vehicles. If that percentage would already be achieved through BAU sales plus the effects of other policies, such as an EV subsidy, this policy has no effect. Manufactures may meet a sales standard through techniques such as more heavily marketing electric vehicles, lowering the price of electric vehicles, or raising the price of non-electric vehicles. A negative setting for this lever implies a decrease in ZEV sales requirements relative to the Current Policies scenario. The following descriptions detail the different vehicle types: // **Passenger Cars and SUVs:** most light-duty road vehicles //**Light and Medium Freight Trucks:** commercial trucks carrying freight, not passengers // **Buses:** including school, transit, and intercity buses // **Heavy Duty Trucks:** all other heavy road vehicles (mostly freight trucks) // **Passenger Motorbikes:** registered motorcycles // **Guidance for setting values:** // This lever should only reflect federal U.S. ZEV requirements, not state level requirements like Advanced Clean Cars or Advanced Clean Trucks. Those requirements are captured elsewhere. //**Passenger Cars and SUVs:** In 2024, EPA passed tailpipe regulations for passenger LDVs that they project will result in 68% ZEV sales by 2032. // **Light and Medium Commercial and Heavy Duty Trucks:** Today, the share of electric freight trucks is very low, but electrification is particularly promising for certain types of trucks, such as those used to make deliveries within cities, those involved in port operations, garbage trucks, and others with frequent starts and stops. EPA tailpipe regulations will require a steadily increasing share of vehicle sales to be ZEVs through 2032. // **Buses:** Electric bus manufacturer Proterra believes all new transit bus sales could be electric as early as 2030, but transit buses make up roughly 15% of the bus fleet. // **Passenger motorbikes:** Though electric motorcycles and scooters are popular in Europe and Asia, where motorbikes are commonly used for urban transportation and commuting, electric motorbikes are not yet a significant presence in the U.S., where motorbikes are mostly used for recreation. | K14: transportation-sector-main.html#ev-mandate | L14: ev-mandate.html | M14: https://autoalliance.org/energy-environment/state-electric-vehicle-mandate/ https://www.cnbc.com/2019/08/26/colorado-joins-california-in-requiring-automakers-to-sell-more-evs.html https://www.consumerreports.org/hybrids-evs/california-says-new-cars-sold-in-the-state-must-be-zero-emissions-by-2035/ https://www.greentechmedia.com/articles/read/electric-buses-are-going-to-dominate statistics from FoVObE variable https://www.prnewswire.com/news-releases/electric-boats-and-ships-2017-2027-300561222.html
A15: Transportation | B15: Non-BAU ZEV-Qualifying Vehicles | C15: Boolean Use Non BAU ZEV Qualifying Vehicle Definitions | D15: ZEV Sales Standard | E15: trans non BAU ZEV vehicle definitions | F15: 0 | G15: 1 | H15: 1 | I15: on/off | J15: **Description:** This lever changes which vehicles qualify under the ZEV standard. With the lever off, ZEV-qualifying vehicles include battery electric vehicles, plugin hybrid vehicles, and hydrogen-fueled vehicles. With the lever on, only battery electric vehicles and hydrogen-fueled vehicles qualify.
A16: Transportation | B16: Subsidy for Vehicle Battery Production | C16: Additional Subsidy for Vehicle Battery Production | D16: Vehicle Battery Production Subsidy | E16: trans battery subsidy | F16: -50 | G16: 50 | H16: 1 | I16: $/kWh | J16: **Description:** This policy specifies a dollar per kilowatt-hour subsidy for production of vehicle batteries, additional to any BAU subsidies. The subsidy will only be applied to the fraction of vehicle batteries produced domestically. A negative value implies removing chargers relative to the Current Policies scenario. // **Guidance for setting values:** The Inflation Reduction Act includes a $35/kWh tax credit for battery cells and a $10/kWh tax credit for assembly for onroad vehicles, which are included in the BAU case.
A17: Transportation | B17: Non-BAU State-Level Zero-Emission Vehicle Sales Standard | C17: Boolean Use Non BAU Minimum Required ZEV Sales Percentage by Subregion | D17: ZEV Sales Standard | E17: trans non BAU ZEV minimum | F17: 0 | G17: 1 | H17: 1 | I17: on/off | J17: **Description:** This policy applies alternate assumptions for state level minimum ZEV requirements (specified through an input data file). In the United States model, this tests reversing state Advanced Clean Cars and Advanced Clean Trucks requirements starting in 2025.
A18: Buildings and Appliances | B18: Building Component Electrification | C18: Fraction of New Bldg Components Shifted to Other Fuels | D18: Building Component Electrification | E18: bldgs new component fuel shifting | F18: 0 | G18: 1 | H18: 0.01 | I18: % of newly sold non-electric building components | J18: **Description:** This policy replaces the specified fraction of newly sold non-electric building components of the selected type(s) in buildings of the selected type(s) with electricity-using components. // **Guidance for setting values:** // **Urban Residential Heating:** // In the BAU case, in the United States, the share of electricity among fuels used for heating in urban, residential buildings will stay roughly constant at 12% through 2050. // **Urban Residential Appliances:** In the BAU case, in the United States, the share of electricity among fuels used by appliances in urban, residential buildings will remain constant at roughly 51% through 2050. // **Urban Residential Other Components:** In the BAU case, in the United States, the share of electricity among fuels used by other components in urban, residential buildings will rise from 87% to 90% through 2050. // **Rural Residential Heating:** In the BAU case, in the United States, the share of electricity among fuels used for heating in rural, residential buildings will stay roughly constant at 12% through 2050. // **Rural Residential Appliances:** In the BAU case, in the United States, the share of electricity among fuels used by appliances in rural, residential buildings will remain constant at roughly 51% through 2050. // **Rural Residential Other Components:** In the BAU case, in the United States, the share of electricity among fuels used by other components in urban, residential buildings will rise from 87% to 90% through 2050. // **Commercial Heating:** In the BAU case, in the United States, the share of electricity among fuels used for heating in commercial buildings will stay roughly constant at 4% through 2050. // **Commercial Appliances:** In the BAU case, in the United States, the share of electricity among fuels used by appliances in commercial buildings will fall from 42% to 39% through 2050. // **Commercial Other Components:** In the BAU case, in the United States, the share of electricity among fuels used by other components in commercial buildings will increase from 67% to 72% through 2050. | K18: buildings-sector-main.html#component-elec | L18: building-component-electrification.html | M18: EIA AEO
A19: Buildings and Appliances | B19: Building Energy Efficiency Standards | C19: Reduction in E Use Allowed by Component Eff Std | D19: Building Energy Efficiency Standards | E19: bldgs efficiency standards | F19: 0 | G19: 0.75 | H19: 0.01 | I19: % reduction in energy use | J19: **Description:** This policy tightens energy efficiency standards for the selected component(s) in the selected building type(s). The policy only applies to newly sold components each year (whether for new buildings or replacement of old components of existing buildings). // **Guidance for setting values:** In "Assessment of Electricity Savings in the U.S. Achievable through New Appliance/Equipment Efficiency Standards and Building Efficiency Codes, 2010-2025" (2011), the Edison Foundation considered a 30% reduction in whole-building energy use (moderate case) and 40-45% (aggressive case) relative to BAU from 2010 to 2025. | K19: buildings-sector-main.html#eff-stds | L19: building-energy-efficiency-standards.html | M19: Edison Foundation, 2011, "Assessment of Electricity Savings in the U.S. Achievable through New Appliance/Equipment Efficiency Standards and Building Efficiency Codes (2010 - 2025)", http://www.edisonfoundation.net/iei/Documents/IEE_CodesandStandardsAssessment_2010-2025_UPDATE.pdf, Page B-2, Table B-1. | N19: Itron, 2007, "ASSESSMENT OF LONG-TERM ELECTRIC ENERGY EFFICIENCY POTENTIAL IN CALIFORNIA’S RESIDENTIAL SECTOR," http://www.energy.ca.gov/2007publications/CEC-500-2007-002/CEC-500-2007-002.PDF, p.33, Table 5-1
A20: Buildings and Appliances | B20: Contractor Training | C20: Boolean Improved Contractor Edu and Training | D20: Contractor Training | E20: bldgs contractor training | F20: 0 | G20: 1 | H20: 1 | I20: on/off | J20: **Description:** This policy represents a program to train contractors in energy-efficient products and installation practices. This covers activities such as air sealing, building framing, and choice and application of insulation. This policy affects newly sold building envelope components, which reduce the energy use of heating, cooling, and ventilation systems in buildings by 3.7% (based on a 2006 study from the Energy Center of Wisconsin). | K20: buildings-sector-main.html#contractor-ed | L20: contractor-training.html
A21: Buildings and Appliances | B21: Distributed Solar Carve-Out | C21: Min Fraction of Total Elec Demand to be Met by Distributed Solar PV | D21: Distributed Solar Promotion | E21: bldgs min fraction distributed solar | F21: 0 | G21: =ROUND(MaxBoundCalculations!B172,2) -> 0.24 | H21: 0.005 | I21: minimum % elec from solar | J21: **Description:** This policy requires at least the specified percentage of total retail electricity demand to be generated by residential and commercial buildings' distributed solar systems (typically rooftop PV). // **Guidance for setting values:** Colorado has established a 3% carve-out for 2020 (though it includes non-solar on-site sources). | K21: buildings-sector-main.html#solar-carve-out | L21: solar-carve-out.html | M21: MASSACHUSETTS: http://www.mass.gov/eea/energy-utilities-clean-tech/renewable-energy/solar/rps-solar-carve-out/current-status-of-the-rps-solar-carve-out-program.html COLORADO: http://www.seia.org/research-resources/rps-solar-carve-out-colorado | N21: RMI, 2011, "Reinventing Fire Electricity Sector Methodology," http://www.rmi.org/cms/Download.aspx?id=10765&file=Reinventing+Fire+Electricity+Sector+Methodology.pdf&title=Reinventing+Fire+Electricity+Sector+Methodology, Page 11, 2050 Generation by Case
A22: Buildings and Appliances | B22: Distributed Solar Subsidy | C22: Additional Perc Subsidy for Distributed Solar PV Capacity | D22: Distributed Solar Promotion | E22: bldgs distributed solar subsidy | F22: 0 | G22: 0.5 | H22: 0.01 | I22: % of PV system cost | J22: **Description:** This policy causes the government to reimburse building owners for an additional percentage of the cost of new distributed solar PV capacity that is installed on or around buildings. // **Guidance for setting values:** The Inflation Reduction Act includes a 30% tax credit for residential solar through 2032, phased down to 0% by 2035 (already incorporated in the business-as-usual case). | K22: buildings-sector-main.html#distributed-solar-subsidy | L22: distributed-solar-subsidy.html | M22: Department of Energy. Business Energy Investment Tax Credit (ITC). http://energy.gov/savings/business-energy-investment-tax-credit-itc
A23: Buildings and Appliances | B23: Distributed Solar Capacity Requirement | C23: Min Required Rooftop Solar Capacity | D23: Distributed Solar Promotion | E23: bldgs min req rooftop solar | F23: 0 | G23: 600000 | H23: 5000 | I23: MW | J23: **Description:** This policy requires at least the specified capacity of distributed solar be built by the model. // **Guidance for setting values:** We estimate the maximum rooftop solar potential in the U.S. at 385 GW for commercial buildings, 595 GW for urban residential buildings, and 135 GW for rural residential buildings.
A24: Buildings and Appliances | B24: Non BAU Distributed Solar Capacity | C24: Boolean Use Non BAU Distributed Solar Capacity | D24: Distributed Solar Promotion | E24: bldgs non BAU dist solar | F24: 0 | G24: 1 | H24: 1 | I24: on/off | J24: **Description:** This policy adds or subtracts an amount of distributed solar according to an alternate input data file. For the U.S., this file is configured to remove the amount of incremental distributed solar deployment expected from the Inflation Reduction Act. //
A25: Buildings and Appliances | B25: Improved Labeling | C25: Boolean Improved Device Labeling | D25: Improved Labeling | E25: bldgs device labeling | F25: 0 | G25: 1 | H25: 1 | I25: on/off | J25: **Description:** This policy represents a program requiring newly sold heating systems, cooling and ventilation systems, and appliances to feature prominent, well-designed labels highlighting their energy efficiencies. The policy reduces energy consumption of newly sold building components of these types by 10%. | K25: buildings-sector-main.html#device-labeling | L25: improved-labeling.html | M25: none
A26: Buildings and Appliances | B26: Retrofit Existing Buildings | C26: Share of Preexisting Buildings Subject to Retrofitting | D26: Increased Retrofitting | E26: bldgs retrofitting | F26: 0 | G26: 0.5 | H26: 0.01 | I26: % of existing buildings | J26: **Description:** This policy retrofits the specified percentage of buildings to more efficient heating, cooling, and envelope components. // **Guidance for setting values:** Without additional policy, by 2050, roughly 90% of the preexisting residential buildings and 85% of commercial buildings will survive without major renovations. This policy renovates them more quickly than they would have otherwise, improving the efficiency of building stock. A policy value of 100% causes all preexisting buildings to be renovated along the schedule specified by the user. If required by 2050, for example, this policy would induce retrofits of the 90% of residential buildings and 85% of commercial buildings not overhauled in the model baseline. A value of 50% in 2050 would renovate 45% of preexisting residential and 42.5% of preexisting commercial buildings, and so forth. | K26: buildings-sector-main.html#retrofitting | L26: increased-retrofitting.html | M26: Calculated from model data; see the relevant variable(s) in the InputData folder for source information.
A27: Buildings and Appliances | B27: Rebate for Efficient Products | C27: Boolean Rebate Program for Efficient Components | D27: Rebate for Efficient Products | E27: bldgs rebate | F27: 0 | G27: 1 | H27: 1 | I27: on/off | J27: **Description:** This policy represents a modest rebate paid to customers who purchase energy-efficient building equipment of the selected type(s). Typical rebate amounts represented by this policy are $50-100 for a clothes washer and $25-50 for a dishwasher or refrigerator. | K27: buildings-sector-main.html#rebate | L27: rebate-for-efficient-products.html
A28: Electricity Supply | B28: Restrict New Power Plants | C28: Boolean Ban New Power Plants | D28: Restrict New Power Plants | E28: elec ban new power plants | F28: 0 | G28: 1 | H28: 1 | I28: on/off | J28: **Description:** This policy prevents new capacity of the selected type(s) from being built or deployed. | K28: electricity-sector-main.html#ban | L28: ban-new-capacity.html
A29: Electricity Supply | B29: Restrict New Power Plant Retrofits | C29: Boolean Ban New Power Plant Retrofits | D29: Restrict New Power Plant Retrofits | E29: elec ban new power plant retrofits | F29: 0 | G29: 1 | H29: 1 | I29: on/off | J29: **Description:** This policy prevents new capacity of the selected CCS plant type(s) from being built to replace existing non-CCS plants.
A30: Electricity Supply | B30: Electricity CCS Subsidy | C30: Additional Subsidy for Elec CCS | D30: Electricity CCS Subsidy | E30: elec CCS subsidy | F30: -100 | G30: 100 | H30: 1 | I30: $ / metric ton CO2e | J30: **Description:** This policy provides a dollar per metric ton CO2e subsidy, additional to any BAU subsidies. // **Guidance for setting values:** The 45Q tax credits provide $85 per metric ton CO2e stored, which is included in the BAU case.
A31: Electricity Supply | B31: CCS Transport and Storage Subsidy | C31: Perc Subsidy for Electricity Sector CCS Transport and Storage Costs | D31: CCS Transport and Storage Subsidy | E31: elec CCS tport storage subsidy | F31: 0 | G31: 1 | H31: 0.01 | I31: % of unsubsidized cost | J31: **Description:** This policy allows the government to cover the cost of CO2 transportation and storage. // **Guidance for setting values:** The BAU cost for CCS transportation and storage is around $29 per tonne. A setting of 100% would cover the full cost.
A32: Electricity Supply | B32: Clean Electricity Standard | C32: Clean Electricity Standard | D32: Clean Electricity Standard | E32: elec clean electricity standards | F32: 0 | G32: 1 | H32: 0.01 | I32: % of electricity generation | J32: **Description:** This policy specifies the fraction of electricity generation that must come from qualifying carbon-free sources (wind, solar, biomass, nuclear, hydro, and geothermal) in 2050. This policy has no effect until the user-set value exceeds the existing fraction of carbon-free electricity and any carbon-free electricity standards which have been enacted at the state level, which in total reaches 47% in 2050 as a generation-weighted national average. By default, the implementation schedule is set to start at roughly 42% in 2024, matching the BAU share of clean electricity in that year. If you set this policy to a value less than 100%, you should be sure to adjust the 2023 implementation schedule value accordingly. For example, if your chosen lever setting is 80%, the fraction of policy achieved in 2024 should be 42% * 80% (or 33.6%), and the fraction of policy achieved in 2050 should be 100%. Also note that the model incorporates a cap on the CES credit price. If the CES credit price hits this $/MWh amount in a given year, the model will not deploy any additional CES qualifying resources. You can change the maximum CES credit price in the Clean Electricity Standard Alternative Compliance Payment lever. // **Guidance for setting values:** Multiple states have set 100% clean energy or renewable energy laws or goals, including California, Hawaii, New Jersey, New York, Washington, New Mexico, Maine, Wisconsin, Minnesota, Nevada, and Washington DC. The earliest 100% target is Washington DC by 2032, with other states pledging to reach 100% clean or renewable energy by 2040-2050. At very high CES values, the associated policy costs are highly uncertain and should be complemented with other modeling. | K32: electricity-sector-main.html#ces | L32: clean-energy-standard.html | M32: White House, 2015, "Fact Sheet: President Obama to Announce Historic Carbon Pollution Standards for Power Plants", https://www.whitehouse.gov/the-press-office/2015/08/03/fact-sheet-president-obama-announce-historic-carbon-pollution-standards.
A33: Electricity Supply | B33: Renewable Portfolio Standard | C33: Renewable Portfolio Std Percentage | D33: Renewable Portfolio Standard | E33: elec renewable portfolio standards | F33: 0 | G33: 1 | H33: 0.01 | I33: % of electricity generation | J33: **Description:** This policy specifies the fraction of electricity generation that must come from qualifying renewable sources (wind, solar, hydro, geothermal, and hydrogen) in 2050. This policy has no effect until the user-set value exceeds the existing fraction of renewable electricity and any renewable electricity standards which have been enacted at the state level. Also note that the model incorporates a cap on the RPS credit price. If the RPS credit price hits this $/MWh amount in a given year, the model will not deploy any additional RPS qualifying resources. You can change the maximum RPS credit price in the Clean Electricity Standard Alternative Compliance Payment lever. // **Guidance for setting values:** Multiple states have set 100% clean energy or renewable energy laws or goals, including California, Hawaii, New Jersey, New York, Washington, New Mexico, Maine, Wisconsin, Minnesota, Nevada, and Washington DC. The earliest 100% target is Washington DC by 2032, with other states pledging to reach 100% clean or renewable energy by 2040-2050. At very high CES values, the associated policy costs are highly uncertain and should be complemented with other modeling.
A34: Electricity Supply | B34: Clean Electricity Standard Foresight | C34: BESHFoFRV Boolean Electricity Suppliers Have Foresight of Future RPS Values | F34: 0 | G34: 1 | H34: 1 | I34: on/off | J34: **Description:** This setting indicates whether electricity suppliers have foresight of future-year CES values (both BAU case values and any values set by the user in the CES policy lever). With foresight, electricity suppliers will build some CES-qualifying resources in earlier years than would be strictly necessary to meet the CES requirement in those years if it allows them to approach a higher, future-year CES target more gradually, lessening the need to build power plants abruptly if the CES rises more steeply in the future.
A35: Electricity Supply | B35: Lift the Clean Electricity Standard Alternative Compliance Payment | C35: Boolean Use Non BAU RPS Alternative Compliance Payment | D35: Clean Electricity Standard | E35: elec non BAU RACP | F35: 0 | G35: 1 | H35: 1 | I35: on/off | J35: **Description:** The BAU scenario includes a CES alternative compliance payment of roughly 180 $/MWh, meaning the model will not deploy any additional CES qualifying resources above this price in an attempt to meet the CES. Enabling this policy lifts this cap, meaning there is no price constraint on new resources.
A36: Electricity Supply | B36: Change Electricity Exports | C36: Percent Change in Electricity Exports | D36: Electricity Imports and Exports | E36: elec change exports | F36: -0.5 | G36: 1 | H36: 0.02 | I36: % change in exports | J36: **Description:** This policy increases or decreases the amount of electricity exported from the United States to Canada and Mexico. It does not cause the construction or removal of transmission lines linking these countries. // **Guidance for setting values:** From 2010-2014, electricity exports declined by 30%. | K36: electricity-sector-main.html#elec-exports | L36: electricity-imports-exports.html | M36: Energy Information Administation. 2016. Electric Power Annual. Table 2.13.
A37: Electricity Supply | B37: Change Electricity Imports | C37: Percent Change in Electricity Imports | D37: Electricity Imports and Exports | E37: elec change imports | F37: -0.5 | G37: 1 | H37: 0.02 | I37: % change in imports | J37: **Description:** This policy increases or decreases the amount of electricity imported to the United States from Canada and Mexico. It does not cause the construction or removal of transmission lines linking these countries. // **Guidance for setting values:** From 2010-2014, electricity imports grew by 48%. | K37: electricity-sector-main.html#elec-imports | L37: electricity-imports-exports.html | M37: Energy Information Administation. 2016. Electric Power Annual. Table 2.13.
A38: Electricity Supply | B38: Non BAU Guaranteed Dispatch | C38: Boolean Use Non BAU Guaranteed Dispatch Settings | D38: Non BAU Guaranteed Dispatch | E38: elec non BAU guaranteed dispatch | F38: 0 | G38: 1 | H38: 1 | I38: on/off
A39: Electricity Supply | B39: Decrease Cost of Capital | C39: Percentage Decrease in Cost of Capital for Power Plants | D39: Decrease Electricity Sector Cost of Capital | E39: elec power plant cost of capital | F39: 0 | G39: 1 | H39: 1 | I39: % decrease | J39: **Description:** This policy decreases the cost of capital for new power plant investments, making the specified plant type more attractive to deploy. // **Guidance for setting values:** The BAU cost of capital for all plant types is calculated as 7.4%, based on data from Lazard. | M39: https://www.lazard.com/media/451905/lazards-levelized-cost-of-energy-version-150-vf.pdf
A40: Electricity Supply | B40: Demand Response | C40: Fraction of Additional Demand Response Potential Achieved | D40: Demand Response | E40: elec demand response | F40: 0 | G40: 1 | H40: 0.01 | I40: % of potential achieved | J40: **Description:** This policy represents regulations that cause more demand response (DR) capacity to be added to the electric grid. Demand response provides flexibility that allows for the integration of more wind and solar PV, if the electricity system is flexibility-constrained. Demand response can be load-shedding (demand is reduced in the worst hours without adding demand in other hours) or load-shifting (demand is reduced in the worst hours and added in other hours). The type of demand response modeled here is load-shedding, which is by far the most common type of demand response that exists today. // **Guidance for setting values:** A 100% setting provides for an additional 390 GW of demand response capacity in 2050 (on top of a BAU quantity of 59 GW). | K40: electricity-sector-main.html#dr | L40: demand-response.html | M40: Calculated from model data; see the relevant variable(s) in the InputData folder for source information.
A41: Electricity Supply | B41: Early Retirement of Power Plants | C41: Annual Additional Capacity Retired due to Early Retirement Policy | D41: Early Retirement of Power Plants | E41: elec early retirement | F41: 0 | G41: 25000 | H41: 500 | I41: MW/year | J41: **Description:** This policy causes the specified quantity of otherwise non-retiring capacity of the selected type(s) to be retired each year. | K41: electricity-sector-main.html#early-ret | L41: early-retirement-of-power-plants.html | M41: Energy Information Administration, 2014, "Annual Energy Outlook 2014", http://www.eia.gov/oiaf/aeo/tablebrowser/#release=AEO2014&subject=6-AEO2014&table=9-AEO2014&region=0-0&cases=hccstom-d012314a,ref2014-d102413a, Table Browser. Select Electric Power Sector, Electricity Generating Capacity (and check Reference and Accelerated coal retirements scenarios). | N41: The Brattle Group, 2012, "Potential Coal Plant Retirements: 2012 Update," http://greatlakeslegalfoundation.org/wwcms/wp-content/uploads/documents/regulatory/TrainWreck/12Oct15_BrattleStudy.pdf, Page 8, Table 4
A42: Electricity Supply | B42: Minimum Annual Grid Battery Additions | C42: Minimum Additional Grid Batteries Deployed | D42: Grid Battery Construction | E42: elec min grid battery additions | F42: 0 | G42: 500000 | H42: 1000 | I42: MWh/year | J42: **Description:** This policy requires the specified quantity of new diurnal battery capacity to be deployed each year. The value is specified in MW*hr of batteries. By default, the EPS assumes diurnal batteries discharge over four hours, so 10 GW*hr of battery corresponds to 2.5 GW of capacity. // **Guidance for setting values:** In 2024, the U.S. had between 20 and 30 GW of total installed grid battery storage. Projections for 2030 range from 80 to 150 GW of total installed capacity.
A43: Electricity Supply | B43: Non BAU Capacity Retirement Schedule | C43: Boolean Use Non BAU Capacity Retirement Schedule | D43: Non BAU Capacity Retirement Schedule | F43: 0 | G43: 1 | H43: 1 | I43: on/off | J43: **Description:** The EPS calculates economc capacity additions and retirements in each year. In addition, it incorporates any announced retirements through input data files. This policy uses an alternate input data file specifying planned retirement schedules for existing capacity of the selected type(s). // **Guidance for setting values:** The Current Policies scenario includes all expected coal retirements resulting from EPA's Clean Air Act Section 111 regulations for power plants, as well as from other regulations and legislation like the Inflation Reduction Act. Turning this lever on removes the effect of those federal policies, resulting in fewer coal retirements.
A44: Electricity Supply | B44: Non BAU Mandated Capacity Construction | C44: Boolean Use Non BAU Mandated Capacity Construction Schedule | D44: Non BAU Mandated Capacity Construction | F44: 0 | G44: 1 | H44: 1 | I44: on/off | J44: **Description:** The business-as-usual case includes all capacity currently under construction (data provided by the U.S. Energy Information Administration). This policy uses an alternate set of planned capacity additions. // **Guidance for setting values:** // **Solar PV and Onshore Wind:** This policy lever includes all capacity currently under construction or planned but not yet under construction. // **Offshore Wind:** When used in the context of the NDC scenario, this policy results in roughly 30 GW of offshore wind by 2030 and 220 of offshore wind by 2050.
A45: Electricity Supply | B45: Non BAU Mandated Capacity CCUS Retrofits | C45: Boolean Use Non BAU Mandated Capacity Retrofit Schedule | D45: Non BAU Mandated Capacity CCUS Retrofits | F45: 0 | G45: 1 | H45: 1 | I45: on/off | J45: **Description:** The business-as-usual case includes all planned CCUS retrofits (as modeled by the EPA for its latest Clean Air Act Section 111 regulations for power plants). Turning this policy lever on assumes those retrofits do not happen.
A46: Electricity Supply | B46: Non BAU RPS Qualifying Resources | C46: Boolean Use Non BAU RPS Qualifying Resource Definitions | D46: Non BAU RPS Qualifying Resources | E46: elec non BAU RPS qualifying resources | F46: 0 | G46: 1 | H46: 1 | I46: on/off
A47: Electricity Supply | B47: Change in Expected Power Plant Capacity Factor | C47: Percentage Reduction in Plant Downtime | D47: Reduce Plant Downtime | E47: elec reduce plant downtime | F47: -0.3 | G47: 0.6 | H47: 0.01 | I47: % reduction in downtime | J47: **Description:** This policy specifies the change in capacity factor (time spent generating power) for new natural gas combined cycle plants. This policy changes these plants' expected capacity factors, but it does not force them to be dispatched if it would be uneconomical to do so. A negative value implies a decrease in capacity factor relative to the Current Policies scenario. // **Guidance for setting values:** // **Natural Gas Combined Cycle:** As part of EPA's Clean Air Act Section 111 regulations for new power plants, natural gas combined cycle plants that operate more than 40 percent of the time must capture 90 percent of on-site emissions by 2032. This would effectively block new natural gas plants without CCS (which are tracked as a separate power plant type in the model). Therefore, we adjust the expected capacity factor for new combined cycle plants so that they would run at a maximum capacity factor of 40 percent starting in 2032. | K47: electricity-sector-main.html#red-downtime | L47: reduce-downtime.html | M47: E&E Publishing. The Clean Power Plan - A Summary. http://www.eenews.net/interactive/clean_power_plan/fact_sheets/rule National Renewable Energy Laboratory. United States (48 Contiguous States) Potential Wind Capacity Cumulative Area vs. Gross Capacity Factor. http://apps2.eere.energy.gov/wind/windexchange/pdfs/wind_maps/us_contiguous_wind_potential_chart.pdf See the discussion of multi-junction solar cells on Wikipedia at https://en.wikipedia.org/wiki/Multi-junction_solar_cell. Also NREL has a useful chart at http://www.nrel.gov/ncpv/images/efficiency_chart.jpg.
A48: Electricity Supply | B48: Reduce Soft Costs | C48: Percent Reduction in Soft Costs of Capacity Construction | D48: Reduce Soft Costs | E48: elec reduce soft costs | F48: 0 | G48: 0.9 | H48: 0.01 | I48: % reduction in soft costs | J48: **Description:** This policy specifies a reduction in soft costs (costs for things other than capital equipment) for new plants of the selected type(s), such as the costs of permitting, financing, project management, assembly, etc. // **Guidance for setting values:** Costs of permitting and financing can be reduced by streamlining permitting processes, but some soft costs (such as labor) may be difficult to reduce via policy. A value of 50% would be an aggressive soft cost reduction. | K48: endogenous-learning.html#red-soft-costs | L48: reduce-soft-costs.html
A49: Electricity Supply | B49: Reduce Transmission & Distribution Losses | C49: Percentage TnD Losses Avoided | D49: Reduce T&D Losses | E49: elec avoid TND loss | F49: 0 | G49: 0.4 | H49: 0.01 | I49: % of losses avoided | J49: **Description:** This policy specifies the reduction in transmission and distribution losses that will be achieved by 2050. // **Guidance for setting values:** The U.S. has transmission and distribution losses of about 6%. Germany, Japan, Finland, and the Netherlands have T&D losses of around 4%. Therefore, a 33% policy setting would cause the U.S. to match these countries' current level of T&D losses by 2050. | K49: electricity-sector-main.html#red-tnd-losses | L49: reduce-tnd-losses.html | M49: The World Bank. Electric power transmission and distribution losses (% of output). http://data.worldbank.org/indicator/EG.ELC.LOSS.ZS
A50: Electricity Supply | B50: Subsidy for Capacity Construction | C50: Perc Subsidy for Elec Capacity Construction | D50: Subsidy for Capacity Construction | E50: elec capacity construction subsidy | F50: 0 | G50: 0.95 | H50: 0.01 | I50: % of construction cost | J50: **Description:** This policy is a subsidy paid by the government to electricity suppliers per unit of new capacity constructed. This only applies to utilities, not distributed systems (such as rooftop solar). // **Guidance for setting values:** The U.S. provides clean electricity tax credits as part of the Inflation Reduction Act (IRA). Tax credits are claimed as either the Investment Tax Credit (per unit capacity) or Production Tax Credit (per unit electricity generation), depending on the plant type. The BAU assumes IRA tax credits will begin phasing out after the year 2036, when electricity sector emissions reach the target of 25% below 2022 levels. // **Nuclear:** The U.S. Federal Government has guaranteed billions of dollars of loans for the construction new nuclear plants and has funded billions of dollars of nuclear technology R&D. The construction of two new reactors at the Vogtle power plant, the only recently built nuclear energy project under construction in the U.S., received $12 billion in loan guarantees as of March 2019. (Loan guarantees are not equivalent to subsidies dollar-for-dollar, but they lower the cost of construction by enabling the plant to access cheaper financing.) // **Solar Thermal:** We assume IRA tax credits of 41.6%, based on assumptions on which share of new plants qualify for various bonus credits. // **Biomass:** The U.S. Federal Government has collectively guaranteed billions of dollars of loans for the construction new biomass plants. (Loan guarantees are not equivalent to subsidies dollar-for-dollar, but they lower the cost of construction by enabling the plant to access cheaper financing.) // **Geothermal:** We assume IRA tax credits of 41.6%, based on assumptions on which share of new plants qualify for various bonus credits. // **Offshore Wind:** We assume IRA tax credits of 41.6%, based on assumptions on which share of new plants qualify for various bonus credits. | K50: electricity-sector-main.html#subsidies | M50: https://www.energy.gov/articles/secretary-perry-announces-financial-close-additional-loan-guarantees-during-trip-vogtle https://www.energysage.com/solar/cost-benefit/solar-investment-tax-credit/ http://biomassmagazine.com/articles/8185/usda-loan-guarantees-support-3-biomass-power-plants
A51: Electricity Supply | B51: Subsidy for Electricity Production | C51: Subsidy for Elec Production by Fuel | D51: Subsidy for Electricity Production | E51: elec generation subsidy | F51: 0 | G51: 60 | H51: 1 | I51: =UnitControlCenter!$B$57 -> $/MWh | J51: **Description:** This policy is a subsidy paid by the government to suppliers of electricity per unit of electricity generated from the selected plant type(s). // **Guidance for setting values:** The U.S. provides clean electricity tax credits as part of the Inflation Reduction Act (IRA). Tax credits are claimed as either the Investment Tax Credit (per unit capacity) or Production Tax Credit (per unit electricity generation), depending on the plant type. The BAU assumes IRA tax credits will begin phasing out after the year 2036, when electricity sector emissions reach the target of 25% below 2022 levels. // Also note that the Energy Policy Simulator chooses which new power plants to build based on lifetime plant costs, and the PTC is only available for the first 10 years of a project. // **Nuclear:** We assume roughly $10/MWh worth of incentives for nuclear in our BAU as part of the IRA and the Infrastructure Investment and Jobs Act. // **Onshore Wind:** We assume IRA tax credits of roughly $32 per MWh, based on assumptions on which share of new plants qualify for various bonus credits. // **Solar PV:** We assume IRA tax credits of roughly $31, based on assumptions on which share of new plants qualify for various bonus credits. | K51: electricity-sector-main.html#subsidies | L51: subsidy-for-electricity-production.html | M51: PRODUCTION TAX CREDIT: Database of State Incentives for Renewables & Efficiency, 2013, "Renewable Energy Production Tax Credit (PTC)", http://dsireusa.org/incentives/incentive.cfm?Incentive_Code=US13F. STATE-LEVEL INCENTIVES: Energy Information Administration, 2013, "Feed-In Tariffs and similar programs", http://www.eia.gov/electricity/policies/provider_programs.cfm.
A52: Electricity Supply | B52: Use EVs for Grid Balancing | C52: Share of EVs Used for Grid Balancing | D52: EVs for Grid Balancing | E52: elec use EVs for grid balancing | F52: 0 | G52: 1 | H52: 0.01 | I52: % of EVs used | J52: **Description:** This policy increases the share of EVs that are used to assist in grid balancing on an average day. This means the EV is connected to the grid during the hours when demand-shifting would be helpful (hours of net peak load) and can pause its charging or, ideally, can partially discharge its battery during these hours to help provide electricity to the grid. // **Guidance for setting values:** Today, EVs generally are not used to help with grid balancing, and EVs and chargers may not have the capability to send electricity in the reverse direction to supply the grid (and have suitable safety cut-off systems to prevent energizing the grid when utilities intentionally shut it down to do repairs and maintenance). Automatically changing the hours when an EV charges (but not discharging to support the grid) is technologically easier but provides less support to the grid.
A53: Electricity Supply | B53: Subsidy for Grid Battery Production | C53: Additional Subsidy for Grid Battery Production | D53: Grid Battery Subsidy | E53: elec battery production subsidy | F53: -100 | G53: 100 | H53: 1 | I53: $/kWh | J53: **Description:** This policy provides a subsidy in units of dollars per kilowatt-hour of battery capacity produced by manufacturers, additional to any BAU subsidies. A negative value implies a tax or removal of subsidies. // **Guidance for setting values:** The BAU case has a $45/kWh production credit provided to manufacturers reflecting the Inflation Reduction Act's 45X tax credit.
A54: Electricity Supply | B54: Subsidy for Grid Battery Capacity | C54: Additional Percent Subsidy per Unit Grid Battery Capacity Deployed | D54: Grid Battery Subsidy | E54: elec battery construction subsidy | F54: -1 | G54: 1 | H54: 0.01 | I54: % of capital costs | J54: **Description:** This policy subsidizes a percentage of grid battery capacity costs, additional to any BAU capacity construction subsidies. A negative value implies a tax or removal of subsidies. // **Guidance for setting values:** We assume IRA tax credits of 41.6%, based on assumptions on which share of new projects qualify for various bonus credits.
A55: Industry | B55: Buy In-Region Products | C55: Fraction of Imported Industrial Outputs Shifted to In Region Suppliers | D55: Buy In-Region Products | E55: indst buy in region outputs | F55: 0 | G55: 0.5 | H55: 0.01 | I55: % of imports shifted | J55: **Description:** This policy increases the extent to which the selected industry's products are supplied by producers within the modeled region. // **Guidance for setting values:** The lever specifies the percentage of imported products (in the BAU case) that are shifted to domestic suppliers (in the policy case). For example, suppose buyers within the modeled region purchase 60% of their road vehicles from domestic automakers and 40% from automakers outside the modeled region. If this policy lever is applied to the "Road Vehicles" industry with a 50% setting, buyers will obtain 80% of their road vehicles from domestic automakers and 20% from automakers outside the modeled region. // **Implementation Note:** This policy reduces imports. In reality, other regions might retaliate by restricting their own purchases of goods produced by the modeled region. However, the EPS only considers policies within the modeled region, so the Buy In-Region Products policy does not affect export levels (i.e., other countries/regions are assumed not to retaliate).
A56: Industry | B56: Carbon Capture and Sequestration | C56: Industry Sector Minimum Fraction of CCS Achieved | D56: Industry CCS | E56: indst CCS | F56: 0 | G56: 1 | H56: 0.01 | I56: % of CO2 captured | J56: **Description:** This policy specifies the minimum fraction of CO2 emissions from industry that is required to be captured and stored. // **Guidance for setting values:** Very few CCS-equipped industrial facilities exist today, so in a scenario where industry does not transition to clean energy, a value over 20% is likely very optimistic. However, in scenarios in which industry mostly or entirely transitions to clean energy (i.e. due to other policies, such as industrial fuel switching and industrial energy efficiency), CCS settings as high as 100% (to capture the small amount of residual CO2 emissions, such as process CO2 from the cement industry) may be very feasible. Capture of process-related emissions is typically more economical, especially in particular industries, because of higher concentration CO2 streams than those from a boiler, for example. | K56: ccs.html#ccs | L56: carbon-capture-and-sequestration.html
A57: Industry | B57: Non BAU Industry CCS Subsidy | C57: Boolean Use Non BAU Industry CCS Subsidies | D57: Industry CCS | E57: indst non BAU CCS subsidy | F57: 0 | G57: 1 | H57: 1 | I57: on/off | J57: **Description:** This policy allows users to model the emissions and cash flow impact of a non-BAU industry CCS subsidy. For the United States, this lever is set up to test the impacts of removing all CCS subsidies flowing to industry in the BAU scenario. // **Guidance for setting values:** The United States currently offers 45Q tax credits through 2032 for CCS. Enabling this lever will remove those credits and the amount of CO2 sequestration they are estimated to incentivize. | K57: ccs.html#ccs | L57: carbon-capture-and-sequestration.html
A58: Industry | B58: CCS Transport and Storage Subsidy | C58: Perc Subsidy for Industry Sector CCS Transport and Storage Costs | D58: CCS Transport and Storage Subsidy | E58: indst CCS tport storage subsidy | F58: 0 | G58: 1 | H58: 0.01 | I58: % of unsubsidized cost | J58: **Description:** This policy allows the government to cover the cost of CO2 transportation and storage. // **Guidance for setting values:** The BAU cost for CCS transportation and storage is around $29 per tonne. A setting of 100% would cover the full cost.
A59: Industry | B59: Non BAU Industry CCS Subsidy | C59: Boolean Use Non BAU Industry CCS Subsidies | D59: Industry CCS | E59: indst non BAU CCS | F59: 0 | G59: 1 | H59: 1 | I59: on/off | J59: **Description:** This policy allows users to model the emissions and cash flow impacts of a non-BAU industry CCS subsidy. For the United States, this lever is set up to test the impacts of removing all CCS subsidies flowing to industry from the Current Policies scenario. // **Guidance for setting values:** The United States currently offers 45Q tax credits through 2032 for CCS. Enabling this lever will remove those credits and the amount of CO2 sequestration they are estimated to incentivize. | K59: ccs.html#ccs | L59: carbon-capture-and-sequestration.html
A60: Industry | B60: Cement Clinker Substitution | C60: Fraction of Cement Measures Achieved | D60: Cement Clinker Substitution | E60: indst cement measures | F60: 0 | G60: 1 | H60: 0.01 | I60: % of potential achieved | J60: **Description:** This policy reduces CO2 emissions from the cement industry by substituting other inputs, such as fly ash, for a portion of the clinker in cement. // **Guidance for setting values:** If this policy is fully implemented, the share of clinker in cement is reduced to 60%. | K60: industry-ag-main.html#clinker | L60: cement-clinker-substitution.html | M60: International Energy Agency and Cement Sustainability Initiative. 2018. Technology Roadmap: Low-Carbon Transition in the Cement Industry. p41. http://www.iea.org/publications/freepublications/publication/TechnologyRoadmapLowCarbonTransitionintheCementIndustry.pdf
A61: Industry | B61: Cement Kiln Fuel Shift | C61: Fraction of Fossil Kiln Energy Shifted | D61: Cement Kiln Fuel Shift | E61: indst cement kiln fuel shift | F61: 0 | G61: 1 | H61: 0.01 | I61: % of fossil kiln fuel shifted | J61: **Description:** This policy replaces part of the fossil fuel burned in cement kilns (coal, petroleum coke, natural gas) with other fuels, taking the same share of each fossil fuel. In this region's data the shifted heat goes to alternative fuels: tire-derived fuel, engineered fuels made from municipal and commercial waste, waste oils and solvents, and biomass residues. Total kiln energy per ton of clinker is unchanged. Alternative fuels in the US are mostly fossil-derived (about 80 percent by energy), so the emissions benefit depends on their biogenic share. // **Guidance for setting values:** The EU cement industry already gets 50-60% of kiln heat from alternative fuels, India targets 20-25% by 2030, and the GCCA 2050 roadmap reaches 43%. The lever is the share of fossil kiln fuel replaced, so a target T for a fleet that already gets a share A of its kiln heat from alternative fuels maps to (T - A) / (1 - A). | K61: industry-ag-main.html#cement | L61: cement-kiln-fuel-shift.html | M61: Global Cement and Concrete Association. 2021. Concrete Future: The GCCA 2050 Cement and Concrete Industry Roadmap for Net Zero Concrete (alternative-fuel share path). NITI Aayog. 2024-2025 thermal substitution rate target for Indian cement. | N61: Upper bound 1 (all fossil kiln energy shifted); the EU already gets 50-60 percent of kiln heat from alternative fuels.
A62: Industry | B62: Cement Pathway Capital Subsidy | C62: Perc Subsidy for Cement Pathway Capital Cost | D62: Cement Pathway Capital Subsidy | E62: indst cement pathway capital subsidy | F62: 0 | G62: 1 | H62: 0.01 | I62: % of capital cost | J62: **Description:** This policy pays part of the capital cost of new clinker production capacity on the selected cement production pathway (kiln plus any carbon capture equipment), lowering the cost investors compare when they choose which kind of kiln to build. It adds to any subsidy the region already provides. The subsidized share is paid by government; the plant's own capital spending is booked in full. // **Guidance for setting values:** Capital grants for low-carbon cement plants have typically covered 20-50% of project cost (EU Innovation Fund grants of roughly 20-40%, Canada's 50% tax credit for capture equipment, the cancelled US DOE demonstration awards at 25-50%). A value of 1 means government pays the entire capital cost. | K62: industry-ag-main.html#cement | L62: cement-pathway-capital-subsidy.html | M62: European Commission. Innovation Fund large-scale project awards for cement (GeZero, Aalborg, Kujawy), 2022-2025. Government of Canada. Investment Tax Credit for Carbon Capture, Utilization and Storage, 2022.
A63: Industry | B63: Cement Pathway Mandate | C63: Minimum Share of New Clinker Capacity by Pathway | D63: Cement Pathway Mandate | E63: indst cement pathway mandate | F63: 0 | G63: 1 | H63: 0.01 | I63: % of new clinker capacity | J63: **Description:** This policy requires that at least the chosen share of each year's new clinker production capacity be built on the selected cement production pathway. Mandated shares are filled first and the remaining capacity is allocated by cost, so the mandate acts as a floor; it can pull a pathway into the market before it would be chosen on cost alone. If the mandated shares across pathways add up to more than 100%, they are scaled down proportionally. // **Guidance for setting values:** Represents new-line standards (China's benchmark rule for new kilns), low-carbon procurement shares (the EU's proposed 5% public-concrete share from 2029, the First Movers Coalition's 10% near-zero pledge for 2030) and state near-zero procurement programs. A value of 1 on one pathway means every new kiln is built on that pathway. | K63: industry-ag-main.html#cement | L63: cement-pathway-mandate.html | M63: European Commission. 2026. Proposal for an Industrial Accelerator Act (low-carbon public procurement share). World Economic Forum. First Movers Coalition cement and concrete commitment, 2023.
A64: Industry | B64: Cement Carbon Price Output-Based Allocation | C64: Fraction of Cement Carbon Price Rebated by Output Based Allocation | D64: Cement Carbon Price Allocation | E64: indst cement carbon price allocation | F64: 0 | G64: 1 | H64: 0.01 | I64: % of carbon-price bill rebated against output | J64: **Description:** This policy hands part of the cement industry's carbon-price bill back in proportion to the clinker it produces, measured against a benchmark intensity (the CABI input). Every cement emissions trading system works this way (free allowances in the EU, California, Korea and Canada; intensity-based allocation in China): producers still pay the full carbon price on each extra tonne of CO2, so the incentive to choose cleaner kilns is unchanged, but the average cost they pass on to buyers is only the carbon price on emissions above the benchmark. The rebate is paid by government and reduces the carbon cost passed through to cement buyers. // **Guidance for setting values:** 1 rebates the benchmark allocation in full, as the EU did before 2026 and California does today; the EU share falls from 0.975 in 2026 to 0.515 in 2030 and 0 in 2034 as the carbon border adjustment phases in. The companion setting Marginal Carbon Price Factor for Cement (1 by default, 0.15 for China's coefficient rule) controls how much of the carbon price acts on producers' choices. | K64: industry-ag-main.html#cement | L64: cement-carbon-price-allocation.html | M64: European Commission. 2026. Implementing Regulation (EU) 2026/1412 (grey clinker benchmark). Directive (EU) 2023/959, recital 46 (free-allocation phase-out). California Air Resources Board. 2026. Cap-and-Invest Final Regulation Order, Tables 8-1 and 9-2.
A65: Industry | B65: Cement Marginal Carbon Price Factor | C65: Marginal Carbon Price Factor for Cement | D65: Cement Carbon Price Allocation | F65: 0 | G65: 1 | H65: 0.05 | I65: share of carbon price acting on the margin | J65: **Description:** This setting is the share of the carbon price that cement producers weigh when choosing between kiln technologies and deciding whether to overhaul or replace a kiln. It is 1 for a carbon tax and for benchmark-based allocation systems, where every marginal tonne of CO2 pays the full price. China's national emissions trading system instead adjusts each plant's allocation by 0.15 times its intensity deviation from the sector balance value (capped at plus or minus 3 percent), so only about 15 percent of the allowance price reaches the intensity margin. // **Guidance for setting values:** Leave at 1 unless modelling China's rule, where 0.15 applies. The carbon tax actually paid, and the output-based allocation rebate, are unchanged by this setting. | K65: industry-ag-main.html#cement | L65: cement-carbon-price-allocation.html | M65: Ministry of Ecology and Environment of China. 2026. Allowance total and allocation plan for the power, steel, cement and aluminium sectors, section 3(2).
A66: Industry | B66: Cement Kiln Performance Standard | C66: Fraction of Below Standard Clinker Capacity Forced to Decide Each Year | D66: Cement Kiln Performance Standard | E66: indst cement kiln standard | F66: 0 | G66: 1 | H66: 0.01 | I66: % of below-standard kilns forced to decide each year | J66: **Description:** This policy makes the oldest, least efficient kilns (wet, long-dry and preheater-only kilns, about 9 percent of U.S. capacity, the CSBS input) face their overhaul-or-retire decision early rather than at the end of their normal campaign. China's clinker energy benchmark and baseline rule (below-baseline kilns had to upgrade or close by the end of 2025) and India's PAT intensity targets work this way. Forced kilns go through the same economic comparison as kilns reaching a campaign end: overhaul for another campaign or retire and be replaced through the new-kiln choice. The companion policy Percent Improvement in Overhauled Kiln Energy Intensity sets how much better an overhauled kiln burns. // **Guidance for setting values:** 1 forces every remaining below-standard kiln to decide each year once the policy is fully implemented (a hard deadline); 0.2 spreads the decisions over about five years. | K66: industry-ag-main.html#cement | L66: cement-kiln-performance-standard.html | M66: National Development and Reform Commission of China. 2023. Benchmark and baseline energy-efficiency levels for key industrial sectors (2023 edition). Portland Cement Association. 2023. Environmental Product Declaration (kiln technology shares).
A67: Industry | B67: Cement Overhauled Kiln Efficiency | C67: Percent Improvement in Overhauled Kiln Energy Intensity | D67: Cement Kiln Performance Standard | E67: indst cement overhaul efficiency | F67: 0 | G67: 0.3 | H67: 0.01 | I67: % reduction in kiln energy per ton | J67: **Description:** This policy requires that when an existing kiln is overhauled for another campaign it is also modernised, cutting its fuel use per tonne of clinker by the chosen share. By default an overhaul rebuilds a kiln at its old efficiency. The improvement applies to the share of the start-year fleet that has been overhauled since the start year, whether the overhaul was forced by the kiln performance standard or came at a normal campaign end. // **Guidance for setting values:** Rebuilding a long-dry kiln with a preheater and precalciner saves about 28 percent of its fuel; adding a precalciner to a preheater kiln saves about 10 percent; wet-to-dry conversions save 45 to 50 percent. 0.1 to 0.2 is a reasonable fleet-average value for a modernisation requirement. | K67: industry-ag-main.html#cement | L67: cement-kiln-performance-standard.html | M67: Lawrence Berkeley National Laboratory. 2008. Energy Efficiency Improvement and Cost Saving Opportunities for Cement Making (LBNL-54036). | N67: Upper bound 0.3: a long-dry kiln rebuilt as a precalciner kiln saves about 28 percent of its fuel.
A68: Industry | B68: Cement Capacity Replacement Rule | C68: Additional Clinker Capacity Retired per Unit of New Capacity | D68: Cement Capacity Replacement Rule | E68: indst cement capacity swap | F68: 0 | G68: 1 | H68: 0.05 | I68: tons retired per ton built | J68: **Description:** This policy requires that old kiln capacity be retired whenever new capacity is built, beyond the retirements the market makes on its own: the setting is the extra tonnes of start-year capacity closed for each tonne of new clinker capacity. China's capacity replacement rules require 1.5 to 2 tonnes closed per tonne built. The retirements come out of the surviving start-year fleet in proportion to each pathway's capacity, one year after the new capacity is built, and the fleet rebuilds through the ordinary new-kiln choice if demand needs it. // **Guidance for setting values:** 0.5 corresponds to China's 1.5-to-1 rule and 1 to its 2-to-1 rule for key air-quality regions. The policy bites only in markets that are building; in a slack market with spare kilns it mostly tightens utilisation. | K68: industry-ag-main.html#cement | L68: cement-capacity-replacement.html | M68: Ministry of Industry and Information Technology of China. 2024. Cement and glass industry capacity replacement implementation measures (2024 edition). | N68: Upper bound 1 (China's 2-to-1 rule).
A69: Industry | B69: Cement Carbon Contract for Difference | C69: Cement CCfD Strike Price | D69: Cement Carbon Contract for Difference | E69: indst cement CCfD | F69: 0 | G69: 300 | H69: 5 | I69: =UnitControlCenter!$B$56 -> $/metric ton CO2e | J69: **Description:** This policy offers new low-carbon cement kilns a carbon contract for difference: a guaranteed price per tonne of CO2 avoided relative to a conventional kiln, paid for a fixed contract term (15 years by default). Each year the contracted kiln receives the strike price less the carbon price it already faces (and less any per-tonne capture credit it already gets) on every tonne it avoids; a contract keeps the strike price it signed at for its whole term, and a two-sided contract (the share is set in the CCTS input file) pays the difference back when the carbon price exceeds the strike. Germany's Klimaschutzvertraege, the Netherlands' SDE++ and the Danish and UK industrial carbon-capture contracts work this way. Investors count the expected payments against the cost of a new kiln, so the lever pulls the CCS, electric and alternative-chemistry pathways forward. // **Guidance for setting values:** Denmark's 2026 cement capture contract pays about 117 euros per tonne captured (roughly 95 2012-dollars); German bids are capped at 550-600 euros per tonne. With no carbon price in place the contract is simply a payment per tonne avoided. Enter 0 to turn the programme off. | K69: industry-ag-main.html#cement | L69: cement-carbon-contract-for-difference.html | M69: Richstein, J.C. and K. Neuhoff. 2022. Carbon contracts-for-difference: how to de-risk innovative investments for a low-carbon industry transition. iScience 25(8). Bundesministerium fuer Wirtschaft und Klimaschutz. 2024. Foerderrichtlinie Klimaschutzvertraege. Cementir Holding. 2026. Aalborg Portland CCS agreement with the Danish Energy Agency. | N69: Upper bound 300 USD per tonne: German round-1 bids ran up to 600 euros per tonne, with average funding well below 200.
A70: Industry | B70: Cement CCfD Contract Length | C70: Cement CCfD Contract Length | D70: Cement Carbon Contract for Difference | F70: 5 | G70: 20 | H70: 1 | I70: years | J70: **Description:** Years a cement carbon contract for difference pays after the kiln is built. // **Guidance for setting values:** 15 years in Germany, the Netherlands and Denmark; the UK uses 10 years plus up to 5 one-year extensions. | K70: industry-ag-main.html#cement | L70: cement-carbon-contract-for-difference.html | M70: See the Cement Carbon Contract for Difference lever.
A71: Industry | B71: Low-Carbon Cement Procurement | C71: Fraction of Cement Demand Purchased under Low Carbon Procurement | D71: Low-Carbon Cement Procurement | E71: indst cement procurement | F71: 0 | G71: 1 | H71: 0.01 | I71: % of cement demand bought as low-carbon | J71: **Description:** This policy commits buyers to purchase a share of the region's cement as low-carbon cement, defined as cement at or below the LCPT share of last year's fleet-average CO2 intensity (0.817 for the US: the GSA best-20-percent limit over the industry-average cement declaration). It represents Buy Clean rules for public construction and private advance market commitments. The committed volume is served first with blended cement such as limestone calcined clay cement (LC3), as far as supplementary material supply allows, then by existing low-carbon kilns; any shortfall is built as new low-carbon kilns ahead of the ordinary cost-driven choice, split among the qualifying kiln types by cost, which also opens the market for kiln types that are not yet commercial. Buyers pay the cost premium over conventional cement; the Share of Low Carbon Cement Premium Paid by Government setting splits it between government (public procurement) and private buyers (an advance market commitment). // **Guidance for setting values:** Public works take about half of US cement, so a Buy Clean rule covering all public purchases is about 0.5 and a federal-only rule much less; First Movers Coalition members commit to 10 percent of their own purchases by 2030, a small share of national demand. | K71: industry-ag-main.html#cement | L71: cement-low-carbon-procurement.html | M71: U.S. General Services Administration. 2023. IRA Low Embodied Carbon Material Requirements. Portland Cement Association. 2021. Public-sector share of cement consumption. World Economic Forum. 2024. First Movers Coalition Cement and Concrete Procurement Guide.
A72: Industry | B72: Procurement Premium Paid by Government | C72: Share of Low Carbon Cement Premium Paid by Government | D72: Low-Carbon Cement Procurement | F72: 0 | G72: 1 | H72: 0.05 | I72: % of premium | J72: **Description:** The share of the low-carbon cement premium that government pays under the procurement policy. 1 is public Buy Clean procurement; 0 is a private advance market commitment, where the buyers absorb the premium (treated as a transfer among businesses and not booked as a government cash flow). // **Guidance for setting values:** Set to the public share of the committed purchases. | K72: industry-ag-main.html#cement | L72: cement-low-carbon-procurement.html | M72: See the Low-Carbon Cement Procurement lever.
A73: Industry | B73: Low-Carbon Cement Production Tax Credit | C73: Low Carbon Cement Production Tax Credit | D73: Low-Carbon Cement Production Tax Credit | E73: indst cement production credit | F73: 0 | G73: 100 | H73: 1 | I73: =UnitControlCenter!$B$56 -> $/metric ton CO2e | J73: **Description:** This policy pays a credit per tonne of cement produced by kilns whose direct CO2 per tonne is at or below the LCCT share of last year's fleet-average CO2 intensity (40 percent below by default, so the CCS and alternative-chemistry pathways qualify and the electric kiln, which keeps the calcination CO2, does not), for a fixed term after the kiln is built (10 years by default). It is the cement analogue of the production tax credits with intensity tiers in federal law (45V, 45Z) and of New Mexico's 2026 proposal for low-carbon industrial products. Investors count the credit against the cost of a new kiln, so it pulls the qualifying pathways forward. // **Guidance for setting values:** New Mexico's proposal paid 85 dollars per tonne of CO2 avoided, about 25 dollars per tonne of cement for a kiln 40 percent below the benchmark; the cost gap between conventional and CCS or electric clinker is 50 to 80 dollars per tonne in the model's US inputs. | K73: industry-ag-main.html#cement | L73: cement-production-tax-credit.html | M73: New Mexico Legislature. 2026. House Bill 153, Industrial Carbon Reduction Act. Congressional Research Service. 2024. The Clean Fuel Production Credit (45Z). | N73: Upper bound 100 USD per tonne, above the model's conventional-to-clean cost gap.
A74: Industry | B74: Cement Credit Duration | C74: Low Carbon Cement Credit Duration | D74: Low-Carbon Cement Production Tax Credit | F74: 1 | G74: 20 | H74: 1 | I74: years | J74: **Description:** Years a new kiln earns the low-carbon cement production tax credit after it is built. // **Guidance for setting values:** US production credits typically run 10 years; 45Q runs 12. | K74: industry-ag-main.html#cement | L74: cement-production-tax-credit.html | M74: See the Low-Carbon Cement Production Tax Credit lever.
A75: Industry | B75: Cement Pollution Border Fee | C75: Cement Border Fee Rate | D75: Cement Pollution Border Fee | E75: indst cement border fee | F75: 0 | G75: 200 | H75: 5 | I75: =UnitControlCenter!$B$56 -> $/metric ton CO2e | J75: **Description:** This policy charges a fee per tonne of CO2 embodied in imported cement and clinker. By default the fee applies only to the import's intensity above the domestic fleet's (the Clean Competition Act design); with the full-intensity setting on it applies to the whole embodied intensity (the EU carbon border adjustment design). The fee raises the delivered price of imports, so the import share of cement demand falls (with an Armington-type elasticity, adjusting over a few years) and production, energy use and emissions shift in-region; the revenue goes to government and the change in emissions abroad is reported separately. // **Guidance for setting values:** The Clean Competition Act charges 60 dollars per tonne of CO2 in 2026, rising with inflation plus 6 points a year; the EU CBAM charges the ETS price (about 75-85 euros). Because imported cement from the main US suppliers is only slightly more carbon-intensive than US cement, a fee on the intensity gap is small; a full-intensity fee at 60 dollars adds roughly 50 dollars to an 80-dollar tonne. | K75: industry-ag-main.html#cement | L75: cement-pollution-border-fee.html | M75: U.S. Senate. 2025. Clean Competition Act, S. 3523. European Commission. 2023. Regulation (EU) 2023/956 establishing a carbon border adjustment mechanism. Fowlie, M., M. Reguant and S.P. Ryan. 2016. Market-based emissions regulation and industry dynamics. Journal of Political Economy 124(1). | N75: Upper bound 200 USD per tonne, above any proposed border fee.
A76: Industry | B76: Border Fee on Full Import Intensity | C76: Cement Border Fee Charges Full Import Intensity | D76: Cement Pollution Border Fee | F76: 0 | G76: 1 | H76: 1 | I76: on/off | J76: **Description:** When on, the cement border fee is charged on the import's whole embodied CO2 (EU CBAM style). When off, only on the excess over the domestic fleet's intensity (Clean Competition Act style). // **Guidance for setting values:** Off by default. | K76: industry-ag-main.html#cement | L76: cement-pollution-border-fee.html | M76: See the Cement Pollution Border Fee lever.
A77: Industry | B77: Cement Carbon-Intensity Standard | C77: Cement CO2 Intensity Standard | D77: Cement Carbon-Intensity Standard | E77: indst cement intensity standard | F77: 0 | G77: 1 | H77: 0.01 | I77: % below start-year intensity | J77: **Description:** This policy caps the direct CO2 per tonne of cement produced in the region, as a reduction below the start-year fleet. California's SB 596 requires a 40 percent cut from 2019 by 2035 and net zero by 2045. The fleet complies in cost order each year: first by substituting supplementary cementitious materials for clinker up to the SCM supply limit, then by requiring a share of new kilns to be low-carbon, split among the qualifying kiln types by cost. The costs land in the existing capital, operating and clinker-substitution chains; no credit market is modelled. // **Guidance for setting values:** 0.4 on a schedule reaching full implementation in 2035 reproduces SB 596's interim target. Because kilns turn over slowly, steep targets can exceed what new builds alone can deliver in a year; the model then builds every new kiln low-carbon and reports the remaining gap. | K77: industry-ag-main.html#cement | L77: cement-carbon-intensity-standard.html | M77: California Legislature. 2021. Senate Bill 596 (Becker). California Air Resources Board. 2025. Draft Net-Zero Emissions Strategy for the Cement Sector.
A78: Industry | B78: Clean Industrial Heat PTC | C78: Subsidy for Clean Industrial Heat Production | D78: Clean Industrial Heat PTC | E78: indst clean heat PTC | F78: 0 | G78: 20 | H78: 1 | I78: $ / million BTU | J78: **Description:** This policy pays industrial firms that utilize heat in industrial processes from a designated set of "clean" energy sources, such as electricity, hydrogen, and biomass. // **Guidance for setting values:** Clean heat PTC rates under discussion in the United States in 2024 were around $10 per million BTU. This is equivalent to roughly 40% of the average cost of electricity for industrial electricity buyers. Higher PTC values have been considered for higher-temperature processes.
A79: Industry | B79: Clean Industrial Heat ITC | C79: Perc Subsidy for Clean Industrial Heat Equipment | D79: Clean Industrial Heat ITC | E79: indst clean heat ITC | F79: 0 | G79: 0.95 | H79: 0.01 | I79: % of equipment cost | J79: **Description:** This policy is a subsidy paid by the government to industrial producers to cover the cost of heating equipment powered by "clean" energy sources, such as electricity, hydrogen, and biomass. // **Guidance for setting values:** Up-front capital costs make up a small share of the total cost of ownership of industrial equipment -- approximately 90% is fuel costs over the lifetime of the equipment. For this reason, investment subsidies need to be substantial to make significant impact. The cost differential varies by industry and by temperature, with high-temperature heat applications (e.g., electric arc furnaces) having more significant cost differentials vs fossil-fueled equivalents than low-temperature heat applications like heat pumps.
A80: Industry | B80: Decrease Cost of Capital | C80: Perc Decrease in Cost of Capital for Clean Industrial Equipment | D80: Decrease Clean Industrial Equipment Cost of Capital | E80: indst eqpt cost of capital | F80: 0 | G80: 0.5 | H80: 0.01 | I80: % decrease | J80: **Description:** This policy decreases the cost of capital for new clean industrial equipment investments, making the specified equipment types more attractive to deploy. // **Guidance for setting values:** The BAU real cost of capital varies by subsector with values between 3 and 7%, based on data from NYU. Setting a value of 100% is the equivalent of offering a government-subsidized, interest-free loan that indexes to inflation. | M80: https://www.lazard.com/media/451905/lazards-levelized-cost-of-energy-version-150-vf.pdf
A81: Industry | B81: Early Retirement of Equipment | C81: Minimum Share of Start Year Industrial Equipment Retired | D81: Equipment Early Retirement | E81: indst eqpt early retirement | F81: 0 | G81: 1 | H81: 0.01 | I81: % of start year equipment | J81: **Description:** This policy accelerates the retirement of aging industrial equipment that were installed before the model's start year, allowing for replacement with more energy-efficient, often electrically powered equipment. **Guidance for setting values:** Industrial equipment often have long lifetimes sometimes exceeding 40 years, so fossil fueled equipment installed before the model run can still be online by the end of the run. We assume a 40-year average lifetime for industrial heating equipment like boilers and furnaces, such that ~12% of preexisting equipment (installed during or before 2020) will be retired by 2025 and ~71% by 2050. We assume a 26-year average lifetime for non-heating equipment like chillers, motors, and electrolyzers, such that ~19% of preexisting equipment (installed during or before 2020) will be retired by 2025 and ~93% by 2050. | K81: industry-ag-main.html#eff-stds | L81: industry-energy-efficiency-standards.html
A82: Industry | B82: Energy Efficiency Standards for Electrical Eqpt | C82: Perc Improvement in Eqpt Efficiency Stds Above BAU for Electricity | D82: Industry Energy Efficiency | E82: indst elec efficiency stds | F82: 0 | G82: 0.25 | H82: 0.01 | I82: % reduction in energy use | J82: **Description:** This policy reduces fuel consumption by the selected industry by increasing the efficiency of newly sold, electrically powered industrial equipment through stronger standards. // **Guidance for setting values:** In 2016, the U.S. Department of Energy developed an industrial energy efficiency potential analysis that suggests the US could double its annual rate of improvement rate through 2030. Extended through 2050, this equates to a maximum potential improvement of 17% by 2050 relative to BAU. The DOE study's value refers to sector-wide energy efficiency, not specifically for new equipment. To achieve a 17% improvement sector-wide by 2050, a setting for this lever several times higher would be needed, due to industrial equipment capital stock turnover time. | K82: industry-ag-main.html#eff-stds | L82: industry-energy-efficiency-standards.html | M82: U.S. DOE, 2016, Industrial Energy Efficiency Potential Analysis, https://energy.gov/sites/prod/files/2017/04/f34/energy-savings-by-state-industrial-methodology.pdf | N82: U.S. DOE, 2016, Industrial Energy Efficiency Potential Analysis, https://energy.gov/sites/prod/files/2017/04/f34/energy-savings-by-state-industrial-methodology.pdf
A83: Industry | B83: Energy Efficiency Standards for Other Eqpt | C83: Perc Improvement in Eqpt Efficiency Stds Above BAU for Combustible Fuels | D83: Industry Energy Efficiency | E83: indst fuel efficiency stds | F83: 0 | G83: 0.25 | H83: 0.01 | I83: % reduction in energy use | J83: **Description:** This policy reduces fuel consumption by the selected industry by increasing the efficiency of newly sold industrial equipment powered by combustible fuels through stronger standards. // **Guidance for setting values:** In 2016, the U.S. Department of Energy developed an industrial energy efficiency potential analysis that suggests the US could double its annual rate of improvement rate through 2030. Extended through 2050, this equates to a maximum potential improvement of 17% by 2050 relative to BAU. The DOE study's value refers to sector-wide energy efficiency, not specifically for new equipment. To achieve a 17% improvement sector-wide by 2050, a setting for this lever several times higher would be needed, due to industrial equipment capital stock turnover time. | K83: industry-ag-main.html#eff-stds | L83: industry-energy-efficiency-standards.html | M83: U.S. DOE, 2016, Industrial Energy Efficiency Potential Analysis, https://energy.gov/sites/prod/files/2017/04/f34/energy-savings-by-state-industrial-methodology.pdf | N83: U.S. DOE, 2016, Industrial Energy Efficiency Potential Analysis, https://energy.gov/sites/prod/files/2017/04/f34/energy-savings-by-state-industrial-methodology.pdf
A84: Industry | B84: Industry Process Efficiency | C84: Percentage Improvement in Industrial Process Efficiency above BAU | D84: Industry Energy Efficiency | E84: indst process efficiency | F84: 0 | G84: 0.25 | H84: 0.01 | I84: % reduction in energy use | J84: **Description:** This policy reduces fuel consumption by the selected industry by increasing the efficiency of industrial processes. // **Guidance for setting values:** In 2016, the U.S. Department of Energy developed an industrial energy efficiency potential analysis that suggests the US could double its annual rate of improvement rate through 2030. Extended through 2050, this equates to a maximum potential improvement of 17% by 2050 relative to BAU. The DOE study's value refers to sector-wide energy efficiency, not specifically for new equipment. To achieve a 17% improvement sector-wide by 2050, a setting for this lever several times higher would be needed, due to industrial equipment capital stock turnover time. | K84: industry-ag-main.html#eff-stds | L84: industry-energy-efficiency-standards.html | M84: U.S. DOE, 2016, Industrial Energy Efficiency Potential Analysis, https://energy.gov/sites/prod/files/2017/04/f34/energy-savings-by-state-industrial-methodology.pdf | N84: U.S. DOE, 2016, Industrial Energy Efficiency Potential Analysis, https://energy.gov/sites/prod/files/2017/04/f34/energy-savings-by-state-industrial-methodology.pdf
A85: Industry | B85: Electrification | C85: Fraction of Eligible Industrial Energy Use Shifted to Electricity | D85: Electrification | E85: indst shift to electricity | F85: 0 | G85: 1 | H85: 0.01 | I85: % of fuel shifted | J85: **Description:** This policy reduces greenhouse gas emissions from the selected industry by switching the fuels used by newly sold industrial equipment to electricity. Only fuel consumed for energy, not fuel used as a chemical feedstock, is affected by this policy. Biomass and purchased heat (steam) are also unaffected. // **Guidance for setting values:** Over 90% of manufacturers' thermal fuels (excluding feedstocks) are used to generate process heat, including to fuel boilers. Generally, boilers/steam and low-temperature non-boiler heat are easier to electrify than higher-temperature heat. For U.S. manufacturing industries, 21% of heat demand is at low tempratures (below 165°C), 40% is at medium temperatures (165-400°C), and the remainder is at high temperatures (above 400°C). | K85: industry-ag-main.html#fuel-switching | L85: industry-elec-and-hydrogen.html
A86: Industry | B86: F-Gas Substitution | C86: Fraction of F Gas Substitution Achieved | D86: F-gas Measures | E86: indst f gas substitution | F86: 0 | G86: 1 | H86: 0.01 | I86: % of potential achieved | J86: **Description:** This policy reduces emissions of high-GWP, fluorinated gases (F-gases) from the industry sector by substituting less-harmful chemicals. // **Guidance for setting values:** The production and consumption of f-gases are limited in the U.S. by the American Innovation and Manufacturing (AIM) Act, which is incorporated in the BAU. Therefore, the U.S. model reflects limited additional abatement potential. If this policy is fully implemented, F-gas emissions in 2050 are reduced by 27%. | K86: industry-ag-main.html#avoid-f-gases | L86: avoid-f-gases.html | M86: Calculated from model data; see the relevant variable(s) in the InputData folder for source information.
A87: Industry | B87: F-Gas Destruction | C87: Fraction of F Gas Destruction Achieved | D87: F-gas Measures | E87: indst f gas destruction | F87: 0 | G87: 1 | H87: 0.01 | I87: % of potential achieved | J87: **Description:** This policy reduces emissions of high-GWP, fluorinated gases (F-gases) from the industry sector by destroying F-gases created as byproducts during the creation of desired products. // **Guidance for setting values:** The production and consumption of f-gases are limited in the U.S. by the American Innovation and Manufacturing (AIM) Act, which is incorporated in the BAU. Therefore, the U.S. model reflects limited additional abatement potential. If this policy is fully implemented, F-gas emissions in 2050 are reduced by 1%. | K87: industry-ag-main.html#avoid-f-gases | L87: avoid-f-gases.html
A88: Industry | B88: F-Gas Recovery | C88: Fraction of F Gas Recovery Achieved | D88: F-gas Measures | E88: indst f gas recovery | F88: 0 | G88: 1 | H88: 0.01 | I88: % of potential achieved | J88: **Description:** This policy reduces emissions of high-GWP, fluorinated gases (F-gases) by recovering F-gases from equipment at the end of its service life and destroying or recycling those F-gases. // **Guidance for setting values:** The production and consumption of f-gases are limited in the U.S. by the American Innovation and Manufacturing (AIM) Act, which is incorporated in the BAU. Therefore, the U.S. model reflects limited additional abatement potential. If this policy is fully implemented, F-gas emissions in 2050 are reduced by 2%. | K88: industry-ag-main.html#avoid-f-gases | L88: avoid-f-gases.html
A89: Industry | B89: F-Gas Eqpt. Maintenance & Retrofits | C89: Fraction of F Gas Inspct Maint Retrofit Achieved | D89: F-gas Measures | E89: indst f gas inspct maint retrofit | F89: 0 | G89: 1 | H89: 0.01 | I89: % of potential achieved | J89: **Description:** This policy reduces emissions of high-GWP, fluorinated gases (F-gases) from the industry sector by reducing leakage and losses through improved inspections, maintenance, and retrofitting of equipment. // **Guidance for setting values:** The production and consumption of f-gases are limited in the U.S. by the American Innovation and Manufacturing (AIM) Act, which is incorporated in the BAU. Therefore, the U.S. model reflects limited additional abatement potential. If this policy is fully implemented, F-gas emissions in 2050 are reduced by less than 1%. | K89: industry-ag-main.html#avoid-f-gases | L89: avoid-f-gases.html
A90: Industry | B90: Feedstock Shifting | C90: Fraction of Feedstock Shifted | D90: Feedstock Shifting | E90: indst feedstock shifting | F90: 0 | G90: 1 | H90: 0.01 | I90: % of potential achieved | J90: **Description:** This policy shifts the use of fossil-fuel feedstocks to hydrogen. The shifted feedstock is met with ordinary hydrogen unless the Required Green or Low Carbon Share of Hydrogen Demand levers, or hydrogen prices, make it green or low carbon. Those requirements apply to all of a sector's hydrogen use, not only the shifted feedstock. // **Guidance for setting values (Chemicals):** Approximately 52 percent of natural gas consumed as a chemical feedstock globally goes to producing ammonia and methanol. These pathways can be replaced with green electrolytic hydrogen to eliminate process emissions associated with production. // **Guidance for setting values (Iron & Steel):** Coal is the most significant feedstock used in the steel industry, largely for reducing iron ore in blast furnaces. A transition from the traditional steelmaking route (blast furnace-basic oxygen furnace) to alternatives (like hydrogen-based direct reduced iron with electric arc furnaces) can be represented by pairing this lever with electrification of industrial heat.
A91: Industry | B91: Alternative Fuel Shifting | C91: Fraction of Eligible Industrial Energy Use Shifted to Alternate Fuel | D91: Alternate Fuel Shifting | E91: indst shift to alt fuel | F91: 0 | G91: 1 | H91: 0.01 | I91: % of fuel shifted | J91: **Description:** This policy reduces greenhouse gas emissions from the selected industry by switching the fuels used by newly sold industrial equipment to hydrogen combustion. Only fuel consumed for energy, not fuel used as a chemical feedstock, is affected by this policy. Purchased heat (steam) is unaffected. // **Guidance for setting values:** Over 90% of manufacturers' thermal fuels (excluding feedstocks) are used to generate process heat, including to fuel boilers. Generally, hydrogen combustion is reserved for high-temperature heat, since it is often simpler and more efficient to directly electrify heat at lower temperatures. For U.S. manufacturing industries, 21% of heat demand is at low tempratures (below 165°C), 40% is at medium temperatures (165-400°C), and the remainder is at high temperatures (above 400°C). | K91: industry-ag-main.html#fuel-switching | L91: industry-elec-and-hydrogen.html
A92: Industry | B92: Material Efficiency, Longevity, & Re-Use | C92: Percent Reduction in Nonenergy Nonagriculture Industry Product Demand | D92: Material Efficiency, Longevity, & Re-Use | E92: indst reduce nonenergy product demand | F92: 0 | G92: 1 | H92: 0.01 | I92: % demand reduction | J92: **Description:** // **Cement and Iron & Steel:** This policy reduces demand for the selected materials through techniques such as material-efficient building codes (using modern designs that require less material per unit floor area), requirements for greater building and infrastructure longevity, greater re-use and re-purposing of buildings (rather than tearing down and building new), etc. // **Guidance for setting values:** In "Sustainable Materials Without the Hot Air: Making Buildings, Vehicles and Products Efficiently and with Less New Material," Allwood and Cullen estimate that concrete use could be reduced by up to 40% using optimized molds, and concrete building longevity could be more than doubled to 200 years. Together, these measures might reduce concrete demand by up to 70%, if demand for building floorspace reaches steady state. They estimate that steel use could be reduced by 30% by optimizing designs and controlling the loads they experience during installation and use. If the lifetime of steel products could be doubled, the resulting material reduction could be up to 65%, if sales reach steady state. // **Water and Waste:** This policy reduces demand for water treatment and waste management services through techniques such as water conservation, reduction in disposable packaging, requirements for greater product longevity, greater repair and re-use of products, and increased recycling and composting. // **Guidance for setting values:** The majority of energy use and emissions from the water and waste sector are a result of water treatment, not solid waste management. The USDA reports that agriculture accounts for 80% of U.S. water consumption, and the U.S. EPA reports that "as much as 50 percent of the water we use outdoors is lost due to wind, evaporation, and runoff caused by inefficient irrigation methods and systems." Non-agriculture uses, including lawn irrigation and in-home use, may be able to achieve similar savings through improved practices and fixtures. | L92: material-efficiency-longevity-reuse.html | M92: Allwood and Cullen, "Sustainable Materials Without the Hot Air: Making Buildings, Vehicles and Products Efficiently and with Less New Material" Allwood and Cullen, "Sustainable Materials With Both Eyes Open" - page 185, http://www.withbotheyesopen.com/read.php?c=12 USDA Irrigation & Water Use: https://www.ers.usda.gov/topics/farm-practices-management/irrigation-water-use.aspx and EPA WaterSense Statistics and Facts: https://www.epa.gov/watersense/statistics-and-facts
A93: Industry | B93: Methane Capture | C93: Fraction of Methane Capture Opportunities Achieved | D93: Methane Capture and Destruction | E93: indst methane capture | F93: 0 | G93: 1 | H93: 0.01 | I93: % of potential achieved | J93: **Description:** This policy reduces methane emissions from the selected industry by increasing the capture of methane that is currently being released into the atmosphere (for example, stopping leaks from wellheads, pipes, coal mines, landfills, etc.). **Guidance for setting values:** The U.S. has standards for new and existing equipment covering the oil and gas production and energy pipelines and gas processing industries in the EPS, which are reflected in the BAU. The rules for existing equipment are together expected to reduce emissions by 119 MMT CO2e by the year 2039. | K93: industry-ag-main.html#methane-capture | L93: methane-capture.html
A94: Industry | B94: Methane Destruction | C94: Fraction of Methane Destruction Opportunities Achieved | D94: Methane Capture and Destruction | E94: indst methane destruction | F94: 0 | G94: 1 | H94: 0.01 | I94: % of potential achieved | J94: **Description:** This policy reduces methane emissions from the selected industry by increasing the burning of methane that is currently being released into the atmosphere (i.e. flaring instead of venting/leaking). **Guidance for setting values:** The U.S. has standards for new and existing equipment covering the oil and gas production and energy pipelines and gas processing industries in the EPS, which are reflected in the BAU. The rules for existing equipment are together expected to reduce emissions by 119 MMT CO2e by the year 2039. | K94: industry-ag-main.html#methane-destr | L94: methane-destruction.html
A95: Industry | B95: N2O Abatement | C95: Fraction of N2O Abatement Achieved | D95: N2O Abatement | E95: indst N2O abatement | F95: 0 | G95: 1 | H95: 0.01 | I95: % of potential achieved | J95: **Description:** This policy reduces nitrous oxide (N2O) process emissions from the chemicals industry (primarily from the production of nitric acid and adipic acid) by destroying the N2O rather than venting it to the atmosphere. //
A96: Industry | B96: Non BAU Increase in Process Emissions | C96: Boolean Use Non BAU Process Emissions Additions | D96: Process Emissions Increases | E96: non BAU indst process emissions | F96: 0 | G96: 1 | H96: 1 | I96: on/off | J96: **Description:** This policy lever tests increases in industrial process emissions relative to the Current Policies scenario according to schedules set via model input data. // **Guidance for setting values:** //**Methane capture and destruction:** The EPA has set standards for oil and gas methane emissions for new and existing equipment, which are projected to save 130 MMT CO2e annually by 2029. This lever repeals those standards. // **Cropland, rice, and livestock measures:** The Inflation Reduction Act includes billions of dollars in financial support for lower-emissions agricultural practices. This lever removes that financial support and the projected emissions reductions from those programs.
A97: Industry | B97: Non BAU Increase in Process Emissions | C97: Boolean Use Non BAU Process Emissions Additions | D97: Process Emissions Increases | E97: non BAU indst process emissions | F97: 0 | G97: 1 | H97: 1 | I97: on/off | J97: **Description:** This policy lever tests increases in industrial process emissions relative to the Current Policies scenario according to schedules set via model input data. The following descriptions explain what scenarios this lever is set up to test: // **Guidance for setting values:** //**Methane capture and destruction:** The EPA has set standards for oil and gas methane emissions for new and existing equipment, which are projected to save 130 MMT CO2e annually by 2029. This lever repeals those standards. // **Cropland, rice, and livestock measures:** The Inflation Reduction Act includes billions in financial support for clean agricultural practices. This lever removes that financial support and the projected emissions reductions from those programs.
A98: Industry | B98: Waste Heat Recovery | C98: Perc of Waste Heat Recovery Potential Achieved | D98: Industry Energy Efficiency | E98: indst waste heat recovery | F98: 0 | G98: 1 | H98: 0.01 | I98: ^% of potential achieved | J98: **Description:** This policy reduces fuel consumption by the selected industry by capturing waste heat from industrial processes. // **Guidance for setting values:** The potential for waste heat varies by industry. We use EU industry data which finds usable waste heat potential (as a share of primary energy consumptions) ranging from 0.5% for the mining & quarrying industry to 9.1% for the iron & steel sector. | K98: industry-ag-main.html#eff-stds | L98: industry-energy-efficiency-standards.html | M98: Bianchi et al., 2019, Estimating the waste heat recovery in the European Union Industry, https://link.springer.com/article/10.1007/s40974-019-00132-7
A99: Industry | B99: Reduce Fossil Fuel Exports | C99: Percent Reduction in Fossil Fuel Exports | D99: Percent Reduction in Fossil Fuel Exports | E99: indst reduce fossil fuel exports | F99: 0 | G99: 1 | H99: 0.01 | I99: % reduction in exports | J99: **Description:** This policy reduces production of the selected fuel type(s) for export. This lever may represent a reduction in fuel demand by actors outside the modeled region (i.e., not caused by domestic policy) or a conscious policy within the modeled region to transition its economy away from dependence on fossil fuel exports. // **Guidance for setting values:** Today, exports represent 15% of U.S. hard coal production, 22% of natural gas production, 8% of petroleum gasoline production, 28% of petroleum diesel production, 11% of jet fuel and kerosene production, 29% of crude oil production, 74% of heavy and residual fuel oil production, and 56% of LPG, propane, and butane production. | L99: reduce-fuel-exports.html | M99: Calculated from model data; see the relevant variable(s) in the InputData folder for source information.
A100: Agriculture, Land Use, and Forestry | B100: Afforestation and Reforestation | C100: Fraction of Afforestation and Reforestation Achieved | D100: Afforestation and Reforestation | E100: land afforestation and reforestation | F100: -3 | G100: 1 | H100: 0.01 | I100: % of potential achieved | J100: **Description:** This policy increases the sequestration of CO2 by planting forests. Planted forests are assumed to be managed with best practices and are not used for timber harvesting. A negative values implies less sequestration compared to the Current Policies scenario. // **Guidance for setting values:** The potential for this policy lever is sourced from EPA's 2024 Forestry and Agriculture Sector Mitigation Analysis, which evaluates various carbon price scenarios across both the forestry and agriculture sectors and considers land use competition. At the maximum level of $100 per ton, the afforestation and reforestation potential is roughly 175 MMT CO2e in 2050. | K100: lulucf.html#aff-ref | L100: afforestation-and-reforestation.html | M100: Calculated from model data; see the relevant variable(s) in the InputData folder for source information. | N100: Ross W. Gorte, 2009, "U.S. Tree Planting for Carbon Sequestration," Congressional Research Service, https://www.fas.org/sgp/crs/misc/R40562.pdf, p.3, paragraph 1
...

Sheet PolicyLevers
A1: Sector | B1: Short Name | C1: Vensim Variable Name | D1: Subscript 1 Value | E1: Subscript 2 Value | F1: Subscript 1 Display Name | G1: Subscript 2 Display Name | H1: Policy ID Number | I1: Include in Web App | J1: Policy Group | K1: Policy Schedule Subscript | L1: Min Slider Value | M1: Max Slider Value | N1: Slider Step Size | O1: Units | P1: Text for Pop-Over Panel Description | Q1: URL for "How the model handles this policy" links | R1: URL for "How to design this policy well" links
A2: =IF(ISBLANK(INDEX('Policy Characteristics'!A:A,MATCH($C2,'Policy Characteristics'!$C:$C,0))),"",INDEX('Policy Characteristics'!A:A,MATCH($C2,'Policy Characteristics'!$C:$C,0))) -> Transportation | B2: =IF(ISBLANK(INDEX('Policy Characteristics'!B:B,MATCH($C2,'Policy Characteristics'!$C:$C,0))),"",INDEX('Policy Characteristics'!B:B,MATCH($C2,'Policy Characteristics'!$C:$C,0))) -> Conventional Pollutant Standards | C2: Percentage Reduction of Separately Regulated Pollutants | D2: LDVs | E2: VOC | F2: Passenger cars, SUVs, Light and Medium Commercial Trucks | G2: VOCs | H2: 1 | I2: Yes | J2: =IF(ISBLANK(INDEX('Policy Characteristics'!D:D,MATCH($C2,'Policy Characteristics'!$C:$C,0))),"",INDEX('Policy Characteristics'!D:D,MATCH($C2,'Policy Characteristics'!$C:$C,0))) -> Conventional Pollutant Standard | K2: =IF(ISBLANK(INDEX('Policy Characteristics'!E:E,MATCH($C2,'Policy Characteristics'!$C:$C,0))),"",INDEX('Policy Characteristics'!E:E,MATCH($C2,'Policy Characteristics'!$C:$C,0))) -> trans reduce regulated pollutants | L2: =IF(ISBLANK(INDEX('Policy Characteristics'!F:F,MATCH($C2,'Policy Characteristics'!$C:$C,0))),"",INDEX('Policy Characteristics'!F:F,MATCH($C2,'Policy Characteristics'!$C:$C,0))) -> 0 | M2: =IF(ISBLANK(INDEX('Policy Characteristics'!G:G,MATCH($C2,'Policy Characteristics'!$C:$C,0))),"",INDEX('Policy Characteristics'!G:G,MATCH($C2,'Policy Characteristics'!$C:$C,0))) -> 1 | N2: =IF(ISBLANK(INDEX('Policy Characteristics'!H:H,MATCH($C2,'Policy Characteristics'!$C:$C,0))),"",INDEX('Policy Characteristics'!H:H,MATCH($C2,'Policy Characteristics'!$C:$C,0))) -> 0.02 | O2: =IF(ISBLANK(INDEX('Policy Characteristics'!I:I,MATCH($C2,'Policy Characteristics'!$C:$C,0))),"",INDEX('Policy Characteristics'!I:I,MATCH($C2,'Policy Characteristics'!$C:$C,0))) -> % reduction in emissions | P2: =IF(ISBLANK(INDEX('Policy Characteristics'!J:J,MATCH($C2,'Policy Characteristics'!$C:$C,0))),"",INDEX('Policy Characteristics'!J:J,MATCH($C2,'Policy Characteristics'!$C:$C,0))) -> **Description:** This policy represents strengthening standards for the selected pollutant(s) emitted by the selected vehicle type(s). Conventional pollutants' most important, harmful impacts are on human health rather than on climate change. The following descriptions detail the different vehicle types: // **Passenger cars and SUVs:** most light-duty road vehicles // **Light and Medium Commercial Trucks:** commercial trucks carrying freight, not passengers // **Buses:** including school, transit, and intercity buses // **Heavy Duty Trucks:** all other heavy road vehicles (mostly freight trucks) // **Commercial passenger flights:** this is not general aviation // **Commercial freight flights:** this includes all other commercial flights, and is not general aviation // **Passenger rail:** intercity, transit, and commuter rail // **Freight rail:** all other rail // **Recreational boats:** not commercial passenger ferries // **Cargo ships:** commercial ships carrying freight // **Passenger motorbikes:** registered motorcycles // **Guidance for setting values:** In the United States, since 1997, the 24-hour national ambient air quality standard (NAAQS) for PM2.5, the most harmful type of particulate for human health, declined from 65 µg/m^3 to 35 µg/m^3, a reduction of 46%. | Q2: =IF(ISBLANK(INDEX('Policy Characteristics'!K:K,MATCH($C2,'Policy Characteristics'!$C:$C,0))),"",INDEX('Policy Characteristics'!K:K,MATCH($C2,'Policy Characteristics'!$C:$C,0))) -> transportation-sector-main.html#conv-pol-stds | R2: =IF(ISBLANK(INDEX('Policy Characteristics'!L:L,MATCH($C2,'Policy Characteristics'!$C:$C,0))),"",INDEX('Policy Characteristics'!L:L,MATCH($C2,'Policy Characteristics'!$C:$C,0))) -> conventional-pollutant-standards.html
A3: =IF(ISBLANK(INDEX('Policy Characteristics'!A:A,MATCH($C3,'Policy Characteristics'!$C:$C,0))),"",INDEX('Policy Characteristics'!A:A,MATCH($C3,'Policy Characteristics'!$C:$C,0))) -> Transportation | B3: =IF(ISBLANK(INDEX('Policy Characteristics'!B:B,MATCH($C3,'Policy Characteristics'!$C:$C,0))),"",INDEX('Policy Characteristics'!B:B,MATCH($C3,'Policy Characteristics'!$C:$C,0))) -> Conventional Pollutant Standards | C3: =C$2 -> Percentage Reduction of Separately Regulated Pollutants | D3: LDVs | E3: CO | F3: Passenger cars, SUVs, Light and Medium Commercial Trucks | G3: CO | H3: =H2+1 -> 2 | I3: Yes | J3: =IF(ISBLANK(INDEX('Policy Characteristics'!D:D,MATCH($C3,'Policy Characteristics'!$C:$C,0))),"",INDEX('Policy Characteristics'!D:D,MATCH($C3,'Policy Characteristics'!$C:$C,0))) -> Conventional Pollutant Standard | K3: =IF(ISBLANK(INDEX('Policy Characteristics'!E:E,MATCH($C3,'Policy Characteristics'!$C:$C,0))),"",INDEX('Policy Characteristics'!E:E,MATCH($C3,'Policy Characteristics'!$C:$C,0))) -> trans reduce regulated pollutants | L3: =IF(ISBLANK(INDEX('Policy Characteristics'!F:F,MATCH($C3,'Policy Characteristics'!$C:$C,0))),"",INDEX('Policy Characteristics'!F:F,MATCH($C3,'Policy Characteristics'!$C:$C,0))) -> 0 | M3: =IF(ISBLANK(INDEX('Policy Characteristics'!G:G,MATCH($C3,'Policy Characteristics'!$C:$C,0))),"",INDEX('Policy Characteristics'!G:G,MATCH($C3,'Policy Characteristics'!$C:$C,0))) -> 1 | N3: =IF(ISBLANK(INDEX('Policy Characteristics'!H:H,MATCH($C3,'Policy Characteristics'!$C:$C,0))),"",INDEX('Policy Characteristics'!H:H,MATCH($C3,'Policy Characteristics'!$C:$C,0))) -> 0.02 | O3: =IF(ISBLANK(INDEX('Policy Characteristics'!I:I,MATCH($C3,'Policy Characteristics'!$C:$C,0))),"",INDEX('Policy Characteristics'!I:I,MATCH($C3,'Policy Characteristics'!$C:$C,0))) -> % reduction in emissions | P3: =IF(ISBLANK(INDEX('Policy Characteristics'!J:J,MATCH($C3,'Policy Characteristics'!$C:$C,0))),"",INDEX('Policy Characteristics'!J:J,MATCH($C3,'Policy Characteristics'!$C:$C,0))) -> **Description:** This policy represents strengthening standards for the selected pollutant(s) emitted by the selected vehicle type(s). Conventional pollutants' most important, harmful impacts are on human health rather than on climate change. The following descriptions detail the different vehicle types: // **Passenger cars and SUVs:** most light-duty road vehicles // **Light and Medium Commercial Trucks:** commercial trucks carrying freight, not passengers // **Buses:** including school, transit, and intercity buses // **Heavy Duty Trucks:** all other heavy road vehicles (mostly freight trucks) // **Commercial passenger flights:** this is not general aviation // **Commercial freight flights:** this includes all other commercial flights, and is not general aviation // **Passenger rail:** intercity, transit, and commuter rail // **Freight rail:** all other rail // **Recreational boats:** not commercial passenger ferries // **Cargo ships:** commercial ships carrying freight // **Passenger motorbikes:** registered motorcycles // **Guidance for setting values:** In the United States, since 1997, the 24-hour national ambient air quality standard (NAAQS) for PM2.5, the most harmful type of particulate for human health, declined from 65 µg/m^3 to 35 µg/m^3, a reduction of 46%. | Q3: =IF(ISBLANK(INDEX('Policy Characteristics'!K:K,MATCH($C3,'Policy Characteristics'!$C:$C,0))),"",INDEX('Policy Characteristics'!K:K,MATCH($C3,'Policy Characteristics'!$C:$C,0))) -> transportation-sector-main.html#conv-pol-stds | R3: =IF(ISBLANK(INDEX('Policy Characteristics'!L:L,MATCH($C3,'Policy Characteristics'!$C:$C,0))),"",INDEX('Policy Characteristics'!L:L,MATCH($C3,'Policy Characteristics'!$C:$C,0))) -> conventional-pollutant-standards.html
A4: =IF(ISBLANK(INDEX('Policy Characteristics'!A:A,MATCH($C4,'Policy Characteristics'!$C:$C,0))),"",INDEX('Policy Characteristics'!A:A,MATCH($C4,'Policy Characteristics'!$C:$C,0))) -> Transportation | B4: =IF(ISBLANK(INDEX('Policy Characteristics'!B:B,MATCH($C4,'Policy Characteristics'!$C:$C,0))),"",INDEX('Policy Characteristics'!B:B,MATCH($C4,'Policy Characteristics'!$C:$C,0))) -> Conventional Pollutant Standards | C4: =C$2 -> Percentage Reduction of Separately Regulated Pollutants | D4: LDVs | E4: NOx | F4: Passenger cars, SUVs, Light and Medium Commercial Trucks | G4: NOx | H4: =H3+1 -> 3 | I4: Yes | J4: =IF(ISBLANK(INDEX('Policy Characteristics'!D:D,MATCH($C4,'Policy Characteristics'!$C:$C,0))),"",INDEX('Policy Characteristics'!D:D,MATCH($C4,'Policy Characteristics'!$C:$C,0))) -> Conventional Pollutant Standard | K4: =IF(ISBLANK(INDEX('Policy Characteristics'!E:E,MATCH($C4,'Policy Characteristics'!$C:$C,0))),"",INDEX('Policy Characteristics'!E:E,MATCH($C4,'Policy Characteristics'!$C:$C,0))) -> trans reduce regulated pollutants | L4: =IF(ISBLANK(INDEX('Policy Characteristics'!F:F,MATCH($C4,'Policy Characteristics'!$C:$C,0))),"",INDEX('Policy Characteristics'!F:F,MATCH($C4,'Policy Characteristics'!$C:$C,0))) -> 0 | M4: =IF(ISBLANK(INDEX('Policy Characteristics'!G:G,MATCH($C4,'Policy Characteristics'!$C:$C,0))),"",INDEX('Policy Characteristics'!G:G,MATCH($C4,'Policy Characteristics'!$C:$C,0))) -> 1 | N4: =IF(ISBLANK(INDEX('Policy Characteristics'!H:H,MATCH($C4,'Policy Characteristics'!$C:$C,0))),"",INDEX('Policy Characteristics'!H:H,MATCH($C4,'Policy Characteristics'!$C:$C,0))) -> 0.02 | O4: =IF(ISBLANK(INDEX('Policy Characteristics'!I:I,MATCH($C4,'Policy Characteristics'!$C:$C,0))),"",INDEX('Policy Characteristics'!I:I,MATCH($C4,'Policy Characteristics'!$C:$C,0))) -> % reduction in emissions | P4: =IF(ISBLANK(INDEX('Policy Characteristics'!J:J,MATCH($C4,'Policy Characteristics'!$C:$C,0))),"",INDEX('Policy Characteristics'!J:J,MATCH($C4,'Policy Characteristics'!$C:$C,0))) -> **Description:** This policy represents strengthening standards for the selected pollutant(s) emitted by the selected vehicle type(s). Conventional pollutants' most important, harmful impacts are on human health rather than on climate change. The following descriptions detail the different vehicle types: // **Passenger cars and SUVs:** most light-duty road vehicles // **Light and Medium Commercial Trucks:** commercial trucks carrying freight, not passengers // **Buses:** including school, transit, and intercity buses // **Heavy Duty Trucks:** all other heavy road vehicles (mostly freight trucks) // **Commercial passenger flights:** this is not general aviation // **Commercial freight flights:** this includes all other commercial flights, and is not general aviation // **Passenger rail:** intercity, transit, and commuter rail // **Freight rail:** all other rail // **Recreational boats:** not commercial passenger ferries // **Cargo ships:** commercial ships carrying freight // **Passenger motorbikes:** registered motorcycles // **Guidance for setting values:** In the United States, since 1997, the 24-hour national ambient air quality standard (NAAQS) for PM2.5, the most harmful type of particulate for human health, declined from 65 µg/m^3 to 35 µg/m^3, a reduction of 46%. | Q4: =IF(ISBLANK(INDEX('Policy Characteristics'!K:K,MATCH($C4,'Policy Characteristics'!$C:$C,0))),"",INDEX('Policy Characteristics'!K:K,MATCH($C4,'Policy Characteristics'!$C:$C,0))) -> transportation-sector-main.html#conv-pol-stds | R4: =IF(ISBLANK(INDEX('Policy Characteristics'!L:L,MATCH($C4,'Policy Characteristics'!$C:$C,0))),"",INDEX('Policy Characteristics'!L:L,MATCH($C4,'Policy Characteristics'!$C:$C,0))) -> conventional-pollutant-standards.html
A5: =IF(ISBLANK(INDEX('Policy Characteristics'!A:A,MATCH($C5,'Policy Characteristics'!$C:$C,0))),"",INDEX('Policy Characteristics'!A:A,MATCH($C5,'Policy Characteristics'!$C:$C,0))) -> Transportation | B5: =IF(ISBLANK(INDEX('Policy Characteristics'!B:B,MATCH($C5,'Policy Characteristics'!$C:$C,0))),"",INDEX('Policy Characteristics'!B:B,MATCH($C5,'Policy Characteristics'!$C:$C,0))) -> Conventional Pollutant Standards | C5: =C$2 -> Percentage Reduction of Separately Regulated Pollutants | D5: LDVs | E5: PM10 | F5: Passenger cars, SUVs, Light and Medium Commercial Trucks | G5: PM10 | H5: =H4+1 -> 4 | I5: Yes | J5: =IF(ISBLANK(INDEX('Policy Characteristics'!D:D,MATCH($C5,'Policy Characteristics'!$C:$C,0))),"",INDEX('Policy Characteristics'!D:D,MATCH($C5,'Policy Characteristics'!$C:$C,0))) -> Conventional Pollutant Standard | K5: =IF(ISBLANK(INDEX('Policy Characteristics'!E:E,MATCH($C5,'Policy Characteristics'!$C:$C,0))),"",INDEX('Policy Characteristics'!E:E,MATCH($C5,'Policy Characteristics'!$C:$C,0))) -> trans reduce regulated pollutants | L5: =IF(ISBLANK(INDEX('Policy Characteristics'!F:F,MATCH($C5,'Policy Characteristics'!$C:$C,0))),"",INDEX('Policy Characteristics'!F:F,MATCH($C5,'Policy Characteristics'!$C:$C,0))) -> 0 | M5: =IF(ISBLANK(INDEX('Policy Characteristics'!G:G,MATCH($C5,'Policy Characteristics'!$C:$C,0))),"",INDEX('Policy Characteristics'!G:G,MATCH($C5,'Policy Characteristics'!$C:$C,0))) -> 1 | N5: =IF(ISBLANK(INDEX('Policy Characteristics'!H:H,MATCH($C5,'Policy Characteristics'!$C:$C,0))),"",INDEX('Policy Characteristics'!H:H,MATCH($C5,'Policy Characteristics'!$C:$C,0))) -> 0.02 | O5: =IF(ISBLANK(INDEX('Policy Characteristics'!I:I,MATCH($C5,'Policy Characteristics'!$C:$C,0))),"",INDEX('Policy Characteristics'!I:I,MATCH($C5,'Policy Characteristics'!$C:$C,0))) -> % reduction in emissions | P5: =IF(ISBLANK(INDEX('Policy Characteristics'!J:J,MATCH($C5,'Policy Characteristics'!$C:$C,0))),"",INDEX('Policy Characteristics'!J:J,MATCH($C5,'Policy Characteristics'!$C:$C,0))) -> **Description:** This policy represents strengthening standards for the selected pollutant(s) emitted by the selected vehicle type(s). Conventional pollutants' most important, harmful impacts are on human health rather than on climate change. The following descriptions detail the different vehicle types: // **Passenger cars and SUVs:** most light-duty road vehicles // **Light and Medium Commercial Trucks:** commercial trucks carrying freight, not passengers // **Buses:** including school, transit, and intercity buses // **Heavy Duty Trucks:** all other heavy road vehicles (mostly freight trucks) // **Commercial passenger flights:** this is not general aviation // **Commercial freight flights:** this includes all other commercial flights, and is not general aviation // **Passenger rail:** intercity, transit, and commuter rail // **Freight rail:** all other rail // **Recreational boats:** not commercial passenger ferries // **Cargo ships:** commercial ships carrying freight // **Passenger motorbikes:** registered motorcycles // **Guidance for setting values:** In the United States, since 1997, the 24-hour national ambient air quality standard (NAAQS) for PM2.5, the most harmful type of particulate for human health, declined from 65 µg/m^3 to 35 µg/m^3, a reduction of 46%. | Q5: =IF(ISBLANK(INDEX('Policy Characteristics'!K:K,MATCH($C5,'Policy Characteristics'!$C:$C,0))),"",INDEX('Policy Characteristics'!K:K,MATCH($C5,'Policy Characteristics'!$C:$C,0))) -> transportation-sector-main.html#conv-pol-stds | R5: =IF(ISBLANK(INDEX('Policy Characteristics'!L:L,MATCH($C5,'Policy Characteristics'!$C:$C,0))),"",INDEX('Policy Characteristics'!L:L,MATCH($C5,'Policy Characteristics'!$C:$C,0))) -> conventional-pollutant-standards.html
A6: =IF(ISBLANK(INDEX('Policy Characteristics'!A:A,MATCH($C6,'Policy Characteristics'!$C:$C,0))),"",INDEX('Policy Characteristics'!A:A,MATCH($C6,'Policy Characteristics'!$C:$C,0))) -> Transportation | B6: =IF(ISBLANK(INDEX('Policy Characteristics'!B:B,MATCH($C6,'Policy Characteristics'!$C:$C,0))),"",INDEX('Policy Characteristics'!B:B,MATCH($C6,'Policy Characteristics'!$C:$C,0))) -> Conventional Pollutant Standards | C6: =C$2 -> Percentage Reduction of Separately Regulated Pollutants | D6: LDVs | E6: PM25 | F6: Passenger cars, SUVs, Light and Medium Commercial Trucks | G6: PM2.5 | H6: =H5+1 -> 5 | I6: Yes | J6: =IF(ISBLANK(INDEX('Policy Characteristics'!D:D,MATCH($C6,'Policy Characteristics'!$C:$C,0))),"",INDEX('Policy Characteristics'!D:D,MATCH($C6,'Policy Characteristics'!$C:$C,0))) -> Conventional Pollutant Standard | K6: =IF(ISBLANK(INDEX('Policy Characteristics'!E:E,MATCH($C6,'Policy Characteristics'!$C:$C,0))),"",INDEX('Policy Characteristics'!E:E,MATCH($C6,'Policy Characteristics'!$C:$C,0))) -> trans reduce regulated pollutants | L6: =IF(ISBLANK(INDEX('Policy Characteristics'!F:F,MATCH($C6,'Policy Characteristics'!$C:$C,0))),"",INDEX('Policy Characteristics'!F:F,MATCH($C6,'Policy Characteristics'!$C:$C,0))) -> 0 | M6: =IF(ISBLANK(INDEX('Policy Characteristics'!G:G,MATCH($C6,'Policy Characteristics'!$C:$C,0))),"",INDEX('Policy Characteristics'!G:G,MATCH($C6,'Policy Characteristics'!$C:$C,0))) -> 1 | N6: =IF(ISBLANK(INDEX('Policy Characteristics'!H:H,MATCH($C6,'Policy Characteristics'!$C:$C,0))),"",INDEX('Policy Characteristics'!H:H,MATCH($C6,'Policy Characteristics'!$C:$C,0))) -> 0.02 | O6: =IF(ISBLANK(INDEX('Policy Characteristics'!I:I,MATCH($C6,'Policy Characteristics'!$C:$C,0))),"",INDEX('Policy Characteristics'!I:I,MATCH($C6,'Policy Characteristics'!$C:$C,0))) -> % reduction in emissions | P6: =IF(ISBLANK(INDEX('Policy Characteristics'!J:J,MATCH($C6,'Policy Characteristics'!$C:$C,0))),"",INDEX('Policy Characteristics'!J:J,MATCH($C6,'Policy Characteristics'!$C:$C,0))) -> **Description:** This policy represents strengthening standards for the selected pollutant(s) emitted by the selected vehicle type(s). Conventional pollutants' most important, harmful impacts are on human health rather than on climate change. The following descriptions detail the different vehicle types: // **Passenger cars and SUVs:** most light-duty road vehicles // **Light and Medium Commercial Trucks:** commercial trucks carrying freight, not passengers // **Buses:** including school, transit, and intercity buses // **Heavy Duty Trucks:** all other heavy road vehicles (mostly freight trucks) // **Commercial passenger flights:** this is not general aviation // **Commercial freight flights:** this includes all other commercial flights, and is not general aviation // **Passenger rail:** intercity, transit, and commuter rail // **Freight rail:** all other rail // **Recreational boats:** not commercial passenger ferries // **Cargo ships:** commercial ships carrying freight // **Passenger motorbikes:** registered motorcycles // **Guidance for setting values:** In the United States, since 1997, the 24-hour national ambient air quality standard (NAAQS) for PM2.5, the most harmful type of particulate for human health, declined from 65 µg/m^3 to 35 µg/m^3, a reduction of 46%. | Q6: =IF(ISBLANK(INDEX('Policy Characteristics'!K:K,MATCH($C6,'Policy Characteristics'!$C:$C,0))),"",INDEX('Policy Characteristics'!K:K,MATCH($C6,'Policy Characteristics'!$C:$C,0))) -> transportation-sector-main.html#conv-pol-stds | R6: =IF(ISBLANK(INDEX('Policy Characteristics'!L:L,MATCH($C6,'Policy Characteristics'!$C:$C,0))),"",INDEX('Policy Characteristics'!L:L,MATCH($C6,'Policy Characteristics'!$C:$C,0))) -> conventional-pollutant-standards.html
A7: =IF(ISBLANK(INDEX('Policy Characteristics'!A:A,MATCH($C7,'Policy Characteristics'!$C:$C,0))),"",INDEX('Policy Characteristics'!A:A,MATCH($C7,'Policy Characteristics'!$C:$C,0))) -> Transportation | B7: =IF(ISBLANK(INDEX('Policy Characteristics'!B:B,MATCH($C7,'Policy Characteristics'!$C:$C,0))),"",INDEX('Policy Characteristics'!B:B,MATCH($C7,'Policy Characteristics'!$C:$C,0))) -> Conventional Pollutant Standards | C7: =C$2 -> Percentage Reduction of Separately Regulated Pollutants | D7: LDVs | E7: SOx | F7: Passenger cars, SUVs, Light and Medium Commercial Trucks | G7: SOx | H7: =H6+1 -> 6 | I7: Yes | J7: =IF(ISBLANK(INDEX('Policy Characteristics'!D:D,MATCH($C7,'Policy Characteristics'!$C:$C,0))),"",INDEX('Policy Characteristics'!D:D,MATCH($C7,'Policy Characteristics'!$C:$C,0))) -> Conventional Pollutant Standard | K7: =IF(ISBLANK(INDEX('Policy Characteristics'!E:E,MATCH($C7,'Policy Characteristics'!$C:$C,0))),"",INDEX('Policy Characteristics'!E:E,MATCH($C7,'Policy Characteristics'!$C:$C,0))) -> trans reduce regulated pollutants | L7: =IF(ISBLANK(INDEX('Policy Characteristics'!F:F,MATCH($C7,'Policy Characteristics'!$C:$C,0))),"",INDEX('Policy Characteristics'!F:F,MATCH($C7,'Policy Characteristics'!$C:$C,0))) -> 0 | M7: =IF(ISBLANK(INDEX('Policy Characteristics'!G:G,MATCH($C7,'Policy Characteristics'!$C:$C,0))),"",INDEX('Policy Characteristics'!G:G,MATCH($C7,'Policy Characteristics'!$C:$C,0))) -> 1 | N7: =IF(ISBLANK(INDEX('Policy Characteristics'!H:H,MATCH($C7,'Policy Characteristics'!$C:$C,0))),"",INDEX('Policy Characteristics'!H:H,MATCH($C7,'Policy Characteristics'!$C:$C,0))) -> 0.02 | O7: =IF(ISBLANK(INDEX('Policy Characteristics'!I:I,MATCH($C7,'Policy Characteristics'!$C:$C,0))),"",INDEX('Policy Characteristics'!I:I,MATCH($C7,'Policy Characteristics'!$C:$C,0))) -> % reduction in emissions | P7: =IF(ISBLANK(INDEX('Policy Characteristics'!J:J,MATCH($C7,'Policy Characteristics'!$C:$C,0))),"",INDEX('Policy Characteristics'!J:J,MATCH($C7,'Policy Characteristics'!$C:$C,0))) -> **Description:** This policy represents strengthening standards for the selected pollutant(s) emitted by the selected vehicle type(s). Conventional pollutants' most important, harmful impacts are on human health rather than on climate change. The following descriptions detail the different vehicle types: // **Passenger cars and SUVs:** most light-duty road vehicles // **Light and Medium Commercial Trucks:** commercial trucks carrying freight, not passengers // **Buses:** including school, transit, and intercity buses // **Heavy Duty Trucks:** all other heavy road vehicles (mostly freight trucks) // **Commercial passenger flights:** this is not general aviation // **Commercial freight flights:** this includes all other commercial flights, and is not general aviation // **Passenger rail:** intercity, transit, and commuter rail // **Freight rail:** all other rail // **Recreational boats:** not commercial passenger ferries // **Cargo ships:** commercial ships carrying freight // **Passenger motorbikes:** registered motorcycles // **Guidance for setting values:** In the United States, since 1997, the 24-hour national ambient air quality standard (NAAQS) for PM2.5, the most harmful type of particulate for human health, declined from 65 µg/m^3 to 35 µg/m^3, a reduction of 46%. | Q7: =IF(ISBLANK(INDEX('Policy Characteristics'!K:K,MATCH($C7,'Policy Characteristics'!$C:$C,0))),"",INDEX('Policy Characteristics'!K:K,MATCH($C7,'Policy Characteristics'!$C:$C,0))) -> transportation-sector-main.html#conv-pol-stds | R7: =IF(ISBLANK(INDEX('Policy Characteristics'!L:L,MATCH($C7,'Policy Characteristics'!$C:$C,0))),"",INDEX('Policy Characteristics'!L:L,MATCH($C7,'Policy Characteristics'!$C:$C,0))) -> conventional-pollutant-standards.html
A8: =IF(ISBLANK(INDEX('Policy Characteristics'!A:A,MATCH($C8,'Policy Characteristics'!$C:$C,0))),"",INDEX('Policy Characteristics'!A:A,MATCH($C8,'Policy Characteristics'!$C:$C,0))) -> Transportation | B8: =IF(ISBLANK(INDEX('Policy Characteristics'!B:B,MATCH($C8,'Policy Characteristics'!$C:$C,0))),"",INDEX('Policy Characteristics'!B:B,MATCH($C8,'Policy Characteristics'!$C:$C,0))) -> Conventional Pollutant Standards | C8: =C$2 -> Percentage Reduction of Separately Regulated Pollutants | D8: LDVs | E8: BC | F8: Passenger cars, SUVs, Light and Medium Commercial Trucks | G8: BC | H8: =H7+1 -> 7 | I8: Yes | J8: =IF(ISBLANK(INDEX('Policy Characteristics'!D:D,MATCH($C8,'Policy Characteristics'!$C:$C,0))),"",INDEX('Policy Characteristics'!D:D,MATCH($C8,'Policy Characteristics'!$C:$C,0))) -> Conventional Pollutant Standard | K8: =IF(ISBLANK(INDEX('Policy Characteristics'!E:E,MATCH($C8,'Policy Characteristics'!$C:$C,0))),"",INDEX('Policy Characteristics'!E:E,MATCH($C8,'Policy Characteristics'!$C:$C,0))) -> trans reduce regulated pollutants | L8: =IF(ISBLANK(INDEX('Policy Characteristics'!F:F,MATCH($C8,'Policy Characteristics'!$C:$C,0))),"",INDEX('Policy Characteristics'!F:F,MATCH($C8,'Policy Characteristics'!$C:$C,0))) -> 0 | M8: =IF(ISBLANK(INDEX('Policy Characteristics'!G:G,MATCH($C8,'Policy Characteristics'!$C:$C,0))),"",INDEX('Policy Characteristics'!G:G,MATCH($C8,'Policy Characteristics'!$C:$C,0))) -> 1 | N8: =IF(ISBLANK(INDEX('Policy Characteristics'!H:H,MATCH($C8,'Policy Characteristics'!$C:$C,0))),"",INDEX('Policy Characteristics'!H:H,MATCH($C8,'Policy Characteristics'!$C:$C,0))) -> 0.02 | O8: =IF(ISBLANK(INDEX('Policy Characteristics'!I:I,MATCH($C8,'Policy Characteristics'!$C:$C,0))),"",INDEX('Policy Characteristics'!I:I,MATCH($C8,'Policy Characteristics'!$C:$C,0))) -> % reduction in emissions | P8: =IF(ISBLANK(INDEX('Policy Characteristics'!J:J,MATCH($C8,'Policy Characteristics'!$C:$C,0))),"",INDEX('Policy Characteristics'!J:J,MATCH($C8,'Policy Characteristics'!$C:$C,0))) -> **Description:** This policy represents strengthening standards for the selected pollutant(s) emitted by the selected vehicle type(s). Conventional pollutants' most important, harmful impacts are on human health rather than on climate change. The following descriptions detail the different vehicle types: // **Passenger cars and SUVs:** most light-duty road vehicles // **Light and Medium Commercial Trucks:** commercial trucks carrying freight, not passengers // **Buses:** including school, transit, and intercity buses // **Heavy Duty Trucks:** all other heavy road vehicles (mostly freight trucks) // **Commercial passenger flights:** this is not general aviation // **Commercial freight flights:** this includes all other commercial flights, and is not general aviation // **Passenger rail:** intercity, transit, and commuter rail // **Freight rail:** all other rail // **Recreational boats:** not commercial passenger ferries // **Cargo ships:** commercial ships carrying freight // **Passenger motorbikes:** registered motorcycles // **Guidance for setting values:** In the United States, since 1997, the 24-hour national ambient air quality standard (NAAQS) for PM2.5, the most harmful type of particulate for human health, declined from 65 µg/m^3 to 35 µg/m^3, a reduction of 46%. | Q8: =IF(ISBLANK(INDEX('Policy Characteristics'!K:K,MATCH($C8,'Policy Characteristics'!$C:$C,0))),"",INDEX('Policy Characteristics'!K:K,MATCH($C8,'Policy Characteristics'!$C:$C,0))) -> transportation-sector-main.html#conv-pol-stds | R8: =IF(ISBLANK(INDEX('Policy Characteristics'!L:L,MATCH($C8,'Policy Characteristics'!$C:$C,0))),"",INDEX('Policy Characteristics'!L:L,MATCH($C8,'Policy Characteristics'!$C:$C,0))) -> conventional-pollutant-standards.html
A9: =IF(ISBLANK(INDEX('Policy Characteristics'!A:A,MATCH($C9,'Policy Characteristics'!$C:$C,0))),"",INDEX('Policy Characteristics'!A:A,MATCH($C9,'Policy Characteristics'!$C:$C,0))) -> Transportation | B9: =IF(ISBLANK(INDEX('Policy Characteristics'!B:B,MATCH($C9,'Policy Characteristics'!$C:$C,0))),"",INDEX('Policy Characteristics'!B:B,MATCH($C9,'Policy Characteristics'!$C:$C,0))) -> Conventional Pollutant Standards | C9: =C$2 -> Percentage Reduction of Separately Regulated Pollutants | D9: LDVs | E9: OC | F9: Passenger cars, SUVs, Light and Medium Commercial Trucks | G9: OC | H9: =H8+1 -> 8 | I9: Yes | J9: =IF(ISBLANK(INDEX('Policy Characteristics'!D:D,MATCH($C9,'Policy Characteristics'!$C:$C,0))),"",INDEX('Policy Characteristics'!D:D,MATCH($C9,'Policy Characteristics'!$C:$C,0))) -> Conventional Pollutant Standard | K9: =IF(ISBLANK(INDEX('Policy Characteristics'!E:E,MATCH($C9,'Policy Characteristics'!$C:$C,0))),"",INDEX('Policy Characteristics'!E:E,MATCH($C9,'Policy Characteristics'!$C:$C,0))) -> trans reduce regulated pollutants | L9: =IF(ISBLANK(INDEX('Policy Characteristics'!F:F,MATCH($C9,'Policy Characteristics'!$C:$C,0))),"",INDEX('Policy Characteristics'!F:F,MATCH($C9,'Policy Characteristics'!$C:$C,0))) -> 0 | M9: =IF(ISBLANK(INDEX('Policy Characteristics'!G:G,MATCH($C9,'Policy Characteristics'!$C:$C,0))),"",INDEX('Policy Characteristics'!G:G,MATCH($C9,'Policy Characteristics'!$C:$C,0))) -> 1 | N9: =IF(ISBLANK(INDEX('Policy Characteristics'!H:H,MATCH($C9,'Policy Characteristics'!$C:$C,0))),"",INDEX('Policy Characteristics'!H:H,MATCH($C9,'Policy Characteristics'!$C:$C,0))) -> 0.02 | O9: =IF(ISBLANK(INDEX('Policy Characteristics'!I:I,MATCH($C9,'Policy Characteristics'!$C:$C,0))),"",INDEX('Policy Characteristics'!I:I,MATCH($C9,'Policy Characteristics'!$C:$C,0))) -> % reduction in emissions | P9: =IF(ISBLANK(INDEX('Policy Characteristics'!J:J,MATCH($C9,'Policy Characteristics'!$C:$C,0))),"",INDEX('Policy Characteristics'!J:J,MATCH($C9,'Policy Characteristics'!$C:$C,0))) -> **Description:** This policy represents strengthening standards for the selected pollutant(s) emitted by the selected vehicle type(s). Conventional pollutants' most important, harmful impacts are on human health rather than on climate change. The following descriptions detail the different vehicle types: // **Passenger cars and SUVs:** most light-duty road vehicles // **Light and Medium Commercial Trucks:** commercial trucks carrying freight, not passengers // **Buses:** including school, transit, and intercity buses // **Heavy Duty Trucks:** all other heavy road vehicles (mostly freight trucks) // **Commercial passenger flights:** this is not general aviation // **Commercial freight flights:** this includes all other commercial flights, and is not general aviation // **Passenger rail:** intercity, transit, and commuter rail // **Freight rail:** all other rail // **Recreational boats:** not commercial passenger ferries // **Cargo ships:** commercial ships carrying freight // **Passenger motorbikes:** registered motorcycles // **Guidance for setting values:** In the United States, since 1997, the 24-hour national ambient air quality standard (NAAQS) for PM2.5, the most harmful type of particulate for human health, declined from 65 µg/m^3 to 35 µg/m^3, a reduction of 46%. | Q9: =IF(ISBLANK(INDEX('Policy Characteristics'!K:K,MATCH($C9,'Policy Characteristics'!$C:$C,0))),"",INDEX('Policy Characteristics'!K:K,MATCH($C9,'Policy Characteristics'!$C:$C,0))) -> transportation-sector-main.html#conv-pol-stds | R9: =IF(ISBLANK(INDEX('Policy Characteristics'!L:L,MATCH($C9,'Policy Characteristics'!$C:$C,0))),"",INDEX('Policy Characteristics'!L:L,MATCH($C9,'Policy Characteristics'!$C:$C,0))) -> conventional-pollutant-standards.html
A10: =IF(ISBLANK(INDEX('Policy Characteristics'!A:A,MATCH($C10,'Policy Characteristics'!$C:$C,0))),"",INDEX('Policy Characteristics'!A:A,MATCH($C10,'Policy Characteristics'!$C:$C,0))) -> Transportation | B10: =IF(ISBLANK(INDEX('Policy Characteristics'!B:B,MATCH($C10,'Policy Characteristics'!$C:$C,0))),"",INDEX('Policy Characteristics'!B:B,MATCH($C10,'Policy Characteristics'!$C:$C,0))) -> Conventional Pollutant Standards | C10: =C$2 -> Percentage Reduction of Separately Regulated Pollutants | D10: LDVs | E10: CH4 | F10: Passenger cars, SUVs, Light and Medium Commercial Trucks | G10: CH4 | H10: =H9+1 -> 9 | I10: No | J10: =IF(ISBLANK(INDEX('Policy Characteristics'!D:D,MATCH($C10,'Policy Characteristics'!$C:$C,0))),"",INDEX('Policy Characteristics'!D:D,MATCH($C10,'Policy Characteristics'!$C:$C,0))) -> Conventional Pollutant Standard | K10: =IF(ISBLANK(INDEX('Policy Characteristics'!E:E,MATCH($C10,'Policy Characteristics'!$C:$C,0))),"",INDEX('Policy Characteristics'!E:E,MATCH($C10,'Policy Characteristics'!$C:$C,0))) -> trans reduce regulated pollutants | L10: =IF(ISBLANK(INDEX('Policy Characteristics'!F:F,MATCH($C10,'Policy Characteristics'!$C:$C,0))),"",INDEX('Policy Characteristics'!F:F,MATCH($C10,'Policy Characteristics'!$C:$C,0))) -> 0 | M10: =IF(ISBLANK(INDEX('Policy Characteristics'!G:G,MATCH($C10,'Policy Characteristics'!$C:$C,0))),"",INDEX('Policy Characteristics'!G:G,MATCH($C10,'Policy Characteristics'!$C:$C,0))) -> 1 | N10: =IF(ISBLANK(INDEX('Policy Characteristics'!H:H,MATCH($C10,'Policy Characteristics'!$C:$C,0))),"",INDEX('Policy Characteristics'!H:H,MATCH($C10,'Policy Characteristics'!$C:$C,0))) -> 0.02 | O10: =IF(ISBLANK(INDEX('Policy Characteristics'!I:I,MATCH($C10,'Policy Characteristics'!$C:$C,0))),"",INDEX('Policy Characteristics'!I:I,MATCH($C10,'Policy Characteristics'!$C:$C,0))) -> % reduction in emissions | P10: =IF(ISBLANK(INDEX('Policy Characteristics'!J:J,MATCH($C10,'Policy Characteristics'!$C:$C,0))),"",INDEX('Policy Characteristics'!J:J,MATCH($C10,'Policy Characteristics'!$C:$C,0))) -> **Description:** This policy represents strengthening standards for the selected pollutant(s) emitted by the selected vehicle type(s). Conventional pollutants' most important, harmful impacts are on human health rather than on climate change. The following descriptions detail the different vehicle types: // **Passenger cars and SUVs:** most light-duty road vehicles // **Light and Medium Commercial Trucks:** commercial trucks carrying freight, not passengers // **Buses:** including school, transit, and intercity buses // **Heavy Duty Trucks:** all other heavy road vehicles (mostly freight trucks) // **Commercial passenger flights:** this is not general aviation // **Commercial freight flights:** this includes all other commercial flights, and is not general aviation // **Passenger rail:** intercity, transit, and commuter rail // **Freight rail:** all other rail // **Recreational boats:** not commercial passenger ferries // **Cargo ships:** commercial ships carrying freight // **Passenger motorbikes:** registered motorcycles // **Guidance for setting values:** In the United States, since 1997, the 24-hour national ambient air quality standard (NAAQS) for PM2.5, the most harmful type of particulate for human health, declined from 65 µg/m^3 to 35 µg/m^3, a reduction of 46%. | Q10: =IF(ISBLANK(INDEX('Policy Characteristics'!K:K,MATCH($C10,'Policy Characteristics'!$C:$C,0))),"",INDEX('Policy Characteristics'!K:K,MATCH($C10,'Policy Characteristics'!$C:$C,0))) -> transportation-sector-main.html#conv-pol-stds | R10: =IF(ISBLANK(INDEX('Policy Characteristics'!L:L,MATCH($C10,'Policy Characteristics'!$C:$C,0))),"",INDEX('Policy Characteristics'!L:L,MATCH($C10,'Policy Characteristics'!$C:$C,0))) -> conventional-pollutant-standards.html
A11: =IF(ISBLANK(INDEX('Policy Characteristics'!A:A,MATCH($C11,'Policy Characteristics'!$C:$C,0))),"",INDEX('Policy Characteristics'!A:A,MATCH($C11,'Policy Characteristics'!$C:$C,0))) -> Transportation | B11: =IF(ISBLANK(INDEX('Policy Characteristics'!B:B,MATCH($C11,'Policy Characteristics'!$C:$C,0))),"",INDEX('Policy Characteristics'!B:B,MATCH($C11,'Policy Characteristics'!$C:$C,0))) -> Conventional Pollutant Standards | C11: =C$2 -> Percentage Reduction of Separately Regulated Pollutants | D11: LDVs | E11: N2O | F11: Passenger cars, SUVs, Light and Medium Commercial Trucks | G11: N2O | H11: =H10+1 -> 10 | I11: No | J11: =IF(ISBLANK(INDEX('Policy Characteristics'!D:D,MATCH($C11,'Policy Characteristics'!$C:$C,0))),"",INDEX('Policy Characteristics'!D:D,MATCH($C11,'Policy Characteristics'!$C:$C,0))) -> Conventional Pollutant Standard | K11: =IF(ISBLANK(INDEX('Policy Characteristics'!E:E,MATCH($C11,'Policy Characteristics'!$C:$C,0))),"",INDEX('Policy Characteristics'!E:E,MATCH($C11,'Policy Characteristics'!$C:$C,0))) -> trans reduce regulated pollutants | L11: =IF(ISBLANK(INDEX('Policy Characteristics'!F:F,MATCH($C11,'Policy Characteristics'!$C:$C,0))),"",INDEX('Policy Characteristics'!F:F,MATCH($C11,'Policy Characteristics'!$C:$C,0))) -> 0 | M11: =IF(ISBLANK(INDEX('Policy Characteristics'!G:G,MATCH($C11,'Policy Characteristics'!$C:$C,0))),"",INDEX('Policy Characteristics'!G:G,MATCH($C11,'Policy Characteristics'!$C:$C,0))) -> 1 | N11: =IF(ISBLANK(INDEX('Policy Characteristics'!H:H,MATCH($C11,'Policy Characteristics'!$C:$C,0))),"",INDEX('Policy Characteristics'!H:H,MATCH($C11,'Policy Characteristics'!$C:$C,0))) -> 0.02 | O11: =IF(ISBLANK(INDEX('Policy Characteristics'!I:I,MATCH($C11,'Policy Characteristics'!$C:$C,0))),"",INDEX('Policy Characteristics'!I:I,MATCH($C11,'Policy Characteristics'!$C:$C,0))) -> % reduction in emissions | P11: =IF(ISBLANK(INDEX('Policy Characteristics'!J:J,MATCH($C11,'Policy Characteristics'!$C:$C,0))),"",INDEX('Policy Characteristics'!J:J,MATCH($C11,'Policy Characteristics'!$C:$C,0))) -> **Description:** This policy represents strengthening standards for the selected pollutant(s) emitted by the selected vehicle type(s). Conventional pollutants' most important, harmful impacts are on human health rather than on climate change. The following descriptions detail the different vehicle types: // **Passenger cars and SUVs:** most light-duty road vehicles // **Light and Medium Commercial Trucks:** commercial trucks carrying freight, not passengers // **Buses:** including school, transit, and intercity buses // **Heavy Duty Trucks:** all other heavy road vehicles (mostly freight trucks) // **Commercial passenger flights:** this is not general aviation // **Commercial freight flights:** this includes all other commercial flights, and is not general aviation // **Passenger rail:** intercity, transit, and commuter rail // **Freight rail:** all other rail // **Recreational boats:** not commercial passenger ferries // **Cargo ships:** commercial ships carrying freight // **Passenger motorbikes:** registered motorcycles // **Guidance for setting values:** In the United States, since 1997, the 24-hour national ambient air quality standard (NAAQS) for PM2.5, the most harmful type of particulate for human health, declined from 65 µg/m^3 to 35 µg/m^3, a reduction of 46%. | Q11: =IF(ISBLANK(INDEX('Policy Characteristics'!K:K,MATCH($C11,'Policy Characteristics'!$C:$C,0))),"",INDEX('Policy Characteristics'!K:K,MATCH($C11,'Policy Characteristics'!$C:$C,0))) -> transportation-sector-main.html#conv-pol-stds | R11: =IF(ISBLANK(INDEX('Policy Characteristics'!L:L,MATCH($C11,'Policy Characteristics'!$C:$C,0))),"",INDEX('Policy Characteristics'!L:L,MATCH($C11,'Policy Characteristics'!$C:$C,0))) -> conventional-pollutant-standards.html
A12: =IF(ISBLANK(INDEX('Policy Characteristics'!A:A,MATCH($C12,'Policy Characteristics'!$C:$C,0))),"",INDEX('Policy Characteristics'!A:A,MATCH($C12,'Policy Characteristics'!$C:$C,0))) -> Transportation | B12: =IF(ISBLANK(INDEX('Policy Characteristics'!B:B,MATCH($C12,'Policy Characteristics'!$C:$C,0))),"",INDEX('Policy Characteristics'!B:B,MATCH($C12,'Policy Characteristics'!$C:$C,0))) -> Conventional Pollutant Standards | C12: =C$2 -> Percentage Reduction of Separately Regulated Pollutants | D12: HDVs | E12: VOC | F12: Buses and Heavy Duty Trucks | G12: VOCs | H12: =H11+1 -> 11 | I12: Yes | J12: =IF(ISBLANK(INDEX('Policy Characteristics'!D:D,MATCH($C12,'Policy Characteristics'!$C:$C,0))),"",INDEX('Policy Characteristics'!D:D,MATCH($C12,'Policy Characteristics'!$C:$C,0))) -> Conventional Pollutant Standard | K12: =IF(ISBLANK(INDEX('Policy Characteristics'!E:E,MATCH($C12,'Policy Characteristics'!$C:$C,0))),"",INDEX('Policy Characteristics'!E:E,MATCH($C12,'Policy Characteristics'!$C:$C,0))) -> trans reduce regulated pollutants | L12: =IF(ISBLANK(INDEX('Policy Characteristics'!F:F,MATCH($C12,'Policy Characteristics'!$C:$C,0))),"",INDEX('Policy Characteristics'!F:F,MATCH($C12,'Policy Characteristics'!$C:$C,0))) -> 0 | M12: =IF(ISBLANK(INDEX('Policy Characteristics'!G:G,MATCH($C12,'Policy Characteristics'!$C:$C,0))),"",INDEX('Policy Characteristics'!G:G,MATCH($C12,'Policy Characteristics'!$C:$C,0))) -> 1 | N12: =IF(ISBLANK(INDEX('Policy Characteristics'!H:H,MATCH($C12,'Policy Characteristics'!$C:$C,0))),"",INDEX('Policy Characteristics'!H:H,MATCH($C12,'Policy Characteristics'!$C:$C,0))) -> 0.02 | O12: =IF(ISBLANK(INDEX('Policy Characteristics'!I:I,MATCH($C12,'Policy Characteristics'!$C:$C,0))),"",INDEX('Policy Characteristics'!I:I,MATCH($C12,'Policy Characteristics'!$C:$C,0))) -> % reduction in emissions | P12: =IF(ISBLANK(INDEX('Policy Characteristics'!J:J,MATCH($C12,'Policy Characteristics'!$C:$C,0))),"",INDEX('Policy Characteristics'!J:J,MATCH($C12,'Policy Characteristics'!$C:$C,0))) -> **Description:** This policy represents strengthening standards for the selected pollutant(s) emitted by the selected vehicle type(s). Conventional pollutants' most important, harmful impacts are on human health rather than on climate change. The following descriptions detail the different vehicle types: // **Passenger cars and SUVs:** most light-duty road vehicles // **Light and Medium Commercial Trucks:** commercial trucks carrying freight, not passengers // **Buses:** including school, transit, and intercity buses // **Heavy Duty Trucks:** all other heavy road vehicles (mostly freight trucks) // **Commercial passenger flights:** this is not general aviation // **Commercial freight flights:** this includes all other commercial flights, and is not general aviation // **Passenger rail:** intercity, transit, and commuter rail // **Freight rail:** all other rail // **Recreational boats:** not commercial passenger ferries // **Cargo ships:** commercial ships carrying freight // **Passenger motorbikes:** registered motorcycles // **Guidance for setting values:** In the United States, since 1997, the 24-hour national ambient air quality standard (NAAQS) for PM2.5, the most harmful type of particulate for human health, declined from 65 µg/m^3 to 35 µg/m^3, a reduction of 46%. | Q12: =IF(ISBLANK(INDEX('Policy Characteristics'!K:K,MATCH($C12,'Policy Characteristics'!$C:$C,0))),"",INDEX('Policy Characteristics'!K:K,MATCH($C12,'Policy Characteristics'!$C:$C,0))) -> transportation-sector-main.html#conv-pol-stds | R12: =IF(ISBLANK(INDEX('Policy Characteristics'!L:L,MATCH($C12,'Policy Characteristics'!$C:$C,0))),"",INDEX('Policy Characteristics'!L:L,MATCH($C12,'Policy Characteristics'!$C:$C,0))) -> conventional-pollutant-standards.html
A13: =IF(ISBLANK(INDEX('Policy Characteristics'!A:A,MATCH($C13,'Policy Characteristics'!$C:$C,0))),"",INDEX('Policy Characteristics'!A:A,MATCH($C13,'Policy Characteristics'!$C:$C,0))) -> Transportation | B13: =IF(ISBLANK(INDEX('Policy Characteristics'!B:B,MATCH($C13,'Policy Characteristics'!$C:$C,0))),"",INDEX('Policy Characteristics'!B:B,MATCH($C13,'Policy Characteristics'!$C:$C,0))) -> Conventional Pollutant Standards | C13: =C$2 -> Percentage Reduction of Separately Regulated Pollutants | D13: HDVs | E13: CO | F13: Buses and Heavy Duty Trucks | G13: CO | H13: =H12+1 -> 12 | I13: Yes | J13: =IF(ISBLANK(INDEX('Policy Characteristics'!D:D,MATCH($C13,'Policy Characteristics'!$C:$C,0))),"",INDEX('Policy Characteristics'!D:D,MATCH($C13,'Policy Characteristics'!$C:$C,0))) -> Conventional Pollutant Standard | K13: =IF(ISBLANK(INDEX('Policy Characteristics'!E:E,MATCH($C13,'Policy Characteristics'!$C:$C,0))),"",INDEX('Policy Characteristics'!E:E,MATCH($C13,'Policy Characteristics'!$C:$C,0))) -> trans reduce regulated pollutants | L13: =IF(ISBLANK(INDEX('Policy Characteristics'!F:F,MATCH($C13,'Policy Characteristics'!$C:$C,0))),"",INDEX('Policy Characteristics'!F:F,MATCH($C13,'Policy Characteristics'!$C:$C,0))) -> 0 | M13: =IF(ISBLANK(INDEX('Policy Characteristics'!G:G,MATCH($C13,'Policy Characteristics'!$C:$C,0))),"",INDEX('Policy Characteristics'!G:G,MATCH($C13,'Policy Characteristics'!$C:$C,0))) -> 1 | N13: =IF(ISBLANK(INDEX('Policy Characteristics'!H:H,MATCH($C13,'Policy Characteristics'!$C:$C,0))),"",INDEX('Policy Characteristics'!H:H,MATCH($C13,'Policy Characteristics'!$C:$C,0))) -> 0.02 | O13: =IF(ISBLANK(INDEX('Policy Characteristics'!I:I,MATCH($C13,'Policy Characteristics'!$C:$C,0))),"",INDEX('Policy Characteristics'!I:I,MATCH($C13,'Policy Characteristics'!$C:$C,0))) -> % reduction in emissions | P13: =IF(ISBLANK(INDEX('Policy Characteristics'!J:J,MATCH($C13,'Policy Characteristics'!$C:$C,0))),"",INDEX('Policy Characteristics'!J:J,MATCH($C13,'Policy Characteristics'!$C:$C,0))) -> **Description:** This policy represents strengthening standards for the selected pollutant(s) emitted by the selected vehicle type(s). Conventional pollutants' most important, harmful impacts are on human health rather than on climate change. The following descriptions detail the different vehicle types: // **Passenger cars and SUVs:** most light-duty road vehicles // **Light and Medium Commercial Trucks:** commercial trucks carrying freight, not passengers // **Buses:** including school, transit, and intercity buses // **Heavy Duty Trucks:** all other heavy road vehicles (mostly freight trucks) // **Commercial passenger flights:** this is not general aviation // **Commercial freight flights:** this includes all other commercial flights, and is not general aviation // **Passenger rail:** intercity, transit, and commuter rail // **Freight rail:** all other rail // **Recreational boats:** not commercial passenger ferries // **Cargo ships:** commercial ships carrying freight // **Passenger motorbikes:** registered motorcycles // **Guidance for setting values:** In the United States, since 1997, the 24-hour national ambient air quality standard (NAAQS) for PM2.5, the most harmful type of particulate for human health, declined from 65 µg/m^3 to 35 µg/m^3, a reduction of 46%. | Q13: =IF(ISBLANK(INDEX('Policy Characteristics'!K:K,MATCH($C13,'Policy Characteristics'!$C:$C,0))),"",INDEX('Policy Characteristics'!K:K,MATCH($C13,'Policy Characteristics'!$C:$C,0))) -> transportation-sector-main.html#conv-pol-stds | R13: =IF(ISBLANK(INDEX('Policy Characteristics'!L:L,MATCH($C13,'Policy Characteristics'!$C:$C,0))),"",INDEX('Policy Characteristics'!L:L,MATCH($C13,'Policy Characteristics'!$C:$C,0))) -> conventional-pollutant-standards.html
A14: =IF(ISBLANK(INDEX('Policy Characteristics'!A:A,MATCH($C14,'Policy Characteristics'!$C:$C,0))),"",INDEX('Policy Characteristics'!A:A,MATCH($C14,'Policy Characteristics'!$C:$C,0))) -> Transportation | B14: =IF(ISBLANK(INDEX('Policy Characteristics'!B:B,MATCH($C14,'Policy Characteristics'!$C:$C,0))),"",INDEX('Policy Characteristics'!B:B,MATCH($C14,'Policy Characteristics'!$C:$C,0))) -> Conventional Pollutant Standards | C14: =C$2 -> Percentage Reduction of Separately Regulated Pollutants | D14: HDVs | E14: NOx | F14: Buses and Heavy Duty Trucks | G14: NOx | H14: =H13+1 -> 13 | I14: Yes | J14: =IF(ISBLANK(INDEX('Policy Characteristics'!D:D,MATCH($C14,'Policy Characteristics'!$C:$C,0))),"",INDEX('Policy Characteristics'!D:D,MATCH($C14,'Policy Characteristics'!$C:$C,0))) -> Conventional Pollutant Standard | K14: =IF(ISBLANK(INDEX('Policy Characteristics'!E:E,MATCH($C14,'Policy Characteristics'!$C:$C,0))),"",INDEX('Policy Characteristics'!E:E,MATCH($C14,'Policy Characteristics'!$C:$C,0))) -> trans reduce regulated pollutants | L14: =IF(ISBLANK(INDEX('Policy Characteristics'!F:F,MATCH($C14,'Policy Characteristics'!$C:$C,0))),"",INDEX('Policy Characteristics'!F:F,MATCH($C14,'Policy Characteristics'!$C:$C,0))) -> 0 | M14: =IF(ISBLANK(INDEX('Policy Characteristics'!G:G,MATCH($C14,'Policy Characteristics'!$C:$C,0))),"",INDEX('Policy Characteristics'!G:G,MATCH($C14,'Policy Characteristics'!$C:$C,0))) -> 1 | N14: =IF(ISBLANK(INDEX('Policy Characteristics'!H:H,MATCH($C14,'Policy Characteristics'!$C:$C,0))),"",INDEX('Policy Characteristics'!H:H,MATCH($C14,'Policy Characteristics'!$C:$C,0))) -> 0.02 | O14: =IF(ISBLANK(INDEX('Policy Characteristics'!I:I,MATCH($C14,'Policy Characteristics'!$C:$C,0))),"",INDEX('Policy Characteristics'!I:I,MATCH($C14,'Policy Characteristics'!$C:$C,0))) -> % reduction in emissions | P14: =IF(ISBLANK(INDEX('Policy Characteristics'!J:J,MATCH($C14,'Policy Characteristics'!$C:$C,0))),"",INDEX('Policy Characteristics'!J:J,MATCH($C14,'Policy Characteristics'!$C:$C,0))) -> **Description:** This policy represents strengthening standards for the selected pollutant(s) emitted by the selected vehicle type(s). Conventional pollutants' most important, harmful impacts are on human health rather than on climate change. The following descriptions detail the different vehicle types: // **Passenger cars and SUVs:** most light-duty road vehicles // **Light and Medium Commercial Trucks:** commercial trucks carrying freight, not passengers // **Buses:** including school, transit, and intercity buses // **Heavy Duty Trucks:** all other heavy road vehicles (mostly freight trucks) // **Commercial passenger flights:** this is not general aviation // **Commercial freight flights:** this includes all other commercial flights, and is not general aviation // **Passenger rail:** intercity, transit, and commuter rail // **Freight rail:** all other rail // **Recreational boats:** not commercial passenger ferries // **Cargo ships:** commercial ships carrying freight // **Passenger motorbikes:** registered motorcycles // **Guidance for setting values:** In the United States, since 1997, the 24-hour national ambient air quality standard (NAAQS) for PM2.5, the most harmful type of particulate for human health, declined from 65 µg/m^3 to 35 µg/m^3, a reduction of 46%. | Q14: =IF(ISBLANK(INDEX('Policy Characteristics'!K:K,MATCH($C14,'Policy Characteristics'!$C:$C,0))),"",INDEX('Policy Characteristics'!K:K,MATCH($C14,'Policy Characteristics'!$C:$C,0))) -> transportation-sector-main.html#conv-pol-stds | R14: =IF(ISBLANK(INDEX('Policy Characteristics'!L:L,MATCH($C14,'Policy Characteristics'!$C:$C,0))),"",INDEX('Policy Characteristics'!L:L,MATCH($C14,'Policy Characteristics'!$C:$C,0))) -> conventional-pollutant-standards.html
... A61: =IF(ISBLANK(INDEX('Policy Characteristics'!A:A,MATCH($C61,'Policy Characteristics'!$C:$C,0))),"",INDEX('Policy Characteristics'!A:A,MATCH($C61,'Policy Characteristics'!$C:$C,0))) -> Transportation | B61: =IF(ISBLANK(INDEX('Policy Characteristics'!B:B,MATCH($C61,'Policy Characteristics'!$C:$C,0))),"",INDEX('Policy Characteristics'!B:B,MATCH($C61,'Policy Characteristics'!$C:$C,0))) -> Conventional Pollutant Standards | C61: =C$2 -> Percentage Reduction of Separately Regulated Pollutants | D61: motorbikes | E61: N2O | F61: Passenger motorbikes | G61: N2O | H61: =H60+1 -> 60 | I61: No | J61: =IF(ISBLANK(INDEX('Policy Characteristics'!D:D,MATCH($C61,'Policy Characteristics'!$C:$C,0))),"",INDEX('Policy Characteristics'!D:D,MATCH($C61,'Policy Characteristics'!$C:$C,0))) -> Conventional Pollutant Standard | K61: =IF(ISBLANK(INDEX('Policy Characteristics'!E:E,MATCH($C61,'Policy Characteristics'!$C:$C,0))),"",INDEX('Policy Characteristics'!E:E,MATCH($C61,'Policy Characteristics'!$C:$C,0))) -> trans reduce regulated pollutants | L61: =IF(ISBLANK(INDEX('Policy Characteristics'!F:F,MATCH($C61,'Policy Characteristics'!$C:$C,0))),"",INDEX('Policy Characteristics'!F:F,MATCH($C61,'Policy Characteristics'!$C:$C,0))) -> 0 | M61: =IF(ISBLANK(INDEX('Policy Characteristics'!G:G,MATCH($C61,'Policy Characteristics'!$C:$C,0))),"",INDEX('Policy Characteristics'!G:G,MATCH($C61,'Policy Characteristics'!$C:$C,0))) -> 1 | N61: =IF(ISBLANK(INDEX('Policy Characteristics'!H:H,MATCH($C61,'Policy Characteristics'!$C:$C,0))),"",INDEX('Policy Characteristics'!H:H,MATCH($C61,'Policy Characteristics'!$C:$C,0))) -> 0.02 | O61: =IF(ISBLANK(INDEX('Policy Characteristics'!I:I,MATCH($C61,'Policy Characteristics'!$C:$C,0))),"",INDEX('Policy Characteristics'!I:I,MATCH($C61,'Policy Characteristics'!$C:$C,0))) -> % reduction in emissions | P61: =IF(ISBLANK(INDEX('Policy Characteristics'!J:J,MATCH($C61,'Policy Characteristics'!$C:$C,0))),"",INDEX('Policy Characteristics'!J:J,MATCH($C61,'Policy Characteristics'!$C:$C,0))) -> **Description:** This policy represents strengthening standards for the selected pollutant(s) emitted by the selected vehicle type(s). Conventional pollutants' most important, harmful impacts are on human health rather than on climate change. The following descriptions detail the different vehicle types: // **Passenger cars and SUVs:** most light-duty road vehicles // **Light and Medium Commercial Trucks:** commercial trucks carrying freight, not passengers // **Buses:** including school, transit, and intercity buses // **Heavy Duty Trucks:** all other heavy road vehicles (mostly freight trucks) // **Commercial passenger flights:** this is not general aviation // **Commercial freight flights:** this includes all other commercial flights, and is not general aviation // **Passenger rail:** intercity, transit, and commuter rail // **Freight rail:** all other rail // **Recreational boats:** not commercial passenger ferries // **Cargo ships:** commercial ships carrying freight // **Passenger motorbikes:** registered motorcycles // **Guidance for setting values:** In the United States, since 1997, the 24-hour national ambient air quality standard (NAAQS) for PM2.5, the most harmful type of particulate for human health, declined from 65 µg/m^3 to 35 µg/m^3, a reduction of 46%. | Q61: =IF(ISBLANK(INDEX('Policy Characteristics'!K:K,MATCH($C61,'Policy Characteristics'!$C:$C,0))),"",INDEX('Policy Characteristics'!K:K,MATCH($C61,'Policy Characteristics'!$C:$C,0))) -> transportation-sector-main.html#conv-pol-stds | R61: =IF(ISBLANK(INDEX('Policy Characteristics'!L:L,MATCH($C61,'Policy Characteristics'!$C:$C,0))),"",INDEX('Policy Characteristics'!L:L,MATCH($C61,'Policy Characteristics'!$C:$C,0))) -> conventional-pollutant-standards.html
A62: =IF(ISBLANK(INDEX('Policy Characteristics'!A:A,MATCH($C62,'Policy Characteristics'!$C:$C,0))),"",INDEX('Policy Characteristics'!A:A,MATCH($C62,'Policy Characteristics'!$C:$C,0))) -> Transportation | B62: =IF(ISBLANK(INDEX('Policy Characteristics'!B:B,MATCH($C62,'Policy Characteristics'!$C:$C,0))),"",INDEX('Policy Characteristics'!B:B,MATCH($C62,'Policy Characteristics'!$C:$C,0))) -> Electric Vehicle Charger Deployment | C62: Percentage Increase in EV Chargers | H62: =H61+1 -> 61 | I62: Yes | J62: =IF(ISBLANK(INDEX('Policy Characteristics'!D:D,MATCH($C62,'Policy Characteristics'!$C:$C,0))),"",INDEX('Policy Characteristics'!D:D,MATCH($C62,'Policy Characteristics'!$C:$C,0))) -> EV Charger Deployment | K62: =IF(ISBLANK(INDEX('Policy Characteristics'!E:E,MATCH($C62,'Policy Characteristics'!$C:$C,0))),"",INDEX('Policy Characteristics'!E:E,MATCH($C62,'Policy Characteristics'!$C:$C,0))) -> trans EV charger deployment | L62: =IF(ISBLANK(INDEX('Policy Characteristics'!F:F,MATCH($C62,'Policy Characteristics'!$C:$C,0))),"",INDEX('Policy Characteristics'!F:F,MATCH($C62,'Policy Characteristics'!$C:$C,0))) -> -1 | M62: =IF(ISBLANK(INDEX('Policy Characteristics'!G:G,MATCH($C62,'Policy Characteristics'!$C:$C,0))),"",INDEX('Policy Characteristics'!G:G,MATCH($C62,'Policy Characteristics'!$C:$C,0))) -> 3 | N62: =IF(ISBLANK(INDEX('Policy Characteristics'!H:H,MATCH($C62,'Policy Characteristics'!$C:$C,0))),"",INDEX('Policy Characteristics'!H:H,MATCH($C62,'Policy Characteristics'!$C:$C,0))) -> 0.1 | O62: =IF(ISBLANK(INDEX('Policy Characteristics'!I:I,MATCH($C62,'Policy Characteristics'!$C:$C,0))),"",INDEX('Policy Characteristics'!I:I,MATCH($C62,'Policy Characteristics'!$C:$C,0))) -> % change | P62: =IF(ISBLANK(INDEX('Policy Characteristics'!J:J,MATCH($C62,'Policy Characteristics'!$C:$C,0))),"",INDEX('Policy Characteristics'!J:J,MATCH($C62,'Policy Characteristics'!$C:$C,0))) -> **Description:** This policy increases the deployment of EV charging stations, including DC Fast and Level 2 charging stations. A negative value decreases chargers relative to the Current Policies scenario. // **Guidance for setting values:** This policy increases vehicle deployment by lowering the perceived charging availability penalty for EVs, insofar as it increases the ratio of EV chargers to gasoline pumps. In the United States, we find the charging availability penalty already reaches zero by roughly 2030. Beyond that point, this policy lever will have no additional effect on EV deployment. | Q62: =IF(ISBLANK(INDEX('Policy Characteristics'!K:K,MATCH($C62,'Policy Characteristics'!$C:$C,0))),"",INDEX('Policy Characteristics'!K:K,MATCH($C62,'Policy Characteristics'!$C:$C,0))) | R62: =IF(ISBLANK(INDEX('Policy Characteristics'!L:L,MATCH($C62,'Policy Characteristics'!$C:$C,0))),"",INDEX('Policy Characteristics'!L:L,MATCH($C62,'Policy Characteristics'!$C:$C,0))) -> ev-charger-deployment.html
A63: =IF(ISBLANK(INDEX('Policy Characteristics'!A:A,MATCH($C63,'Policy Characteristics'!$C:$C,0))),"",INDEX('Policy Characteristics'!A:A,MATCH($C63,'Policy Characteristics'!$C:$C,0))) -> Transportation | B63: =IF(ISBLANK(INDEX('Policy Characteristics'!B:B,MATCH($C63,'Policy Characteristics'!$C:$C,0))),"",INDEX('Policy Characteristics'!B:B,MATCH($C63,'Policy Characteristics'!$C:$C,0))) -> Passenger Vehicle Subsidy | C63: Additional Passenger Vehicle Subsidy | D63: LDVs | E63: battery electric vehicle | F63: Cars and SUVs | G63: Battery electric vehicle | H63: =H62+1 -> 62 | I63: Yes | J63: =IF(ISBLANK(INDEX('Policy Characteristics'!D:D,MATCH($C63,'Policy Characteristics'!$C:$C,0))),"",INDEX('Policy Characteristics'!D:D,MATCH($C63,'Policy Characteristics'!$C:$C,0))) -> Vehicle Subsidy | K63: =IF(ISBLANK(INDEX('Policy Characteristics'!E:E,MATCH($C63,'Policy Characteristics'!$C:$C,0))),"",INDEX('Policy Characteristics'!E:E,MATCH($C63,'Policy Characteristics'!$C:$C,0))) -> trans psgr subsidy | L63: =IF(ISBLANK(INDEX('Policy Characteristics'!F:F,MATCH($C63,'Policy Characteristics'!$C:$C,0))),"",INDEX('Policy Characteristics'!F:F,MATCH($C63,'Policy Characteristics'!$C:$C,0))) -> -45000 | M63: =IF(ISBLANK(INDEX('Policy Characteristics'!G:G,MATCH($C63,'Policy Characteristics'!$C:$C,0))),"",INDEX('Policy Characteristics'!G:G,MATCH($C63,'Policy Characteristics'!$C:$C,0))) -> 50000 | N63: =IF(ISBLANK(INDEX('Policy Characteristics'!H:H,MATCH($C63,'Policy Characteristics'!$C:$C,0))),"",INDEX('Policy Characteristics'!H:H,MATCH($C63,'Policy Characteristics'!$C:$C,0))) -> 100 | O63: =IF(ISBLANK(INDEX('Policy Characteristics'!I:I,MATCH($C63,'Policy Characteristics'!$C:$C,0))),"",INDEX('Policy Characteristics'!I:I,MATCH($C63,'Policy Characteristics'!$C:$C,0))) -> $ / vehicle | P63: =IF(ISBLANK(INDEX('Policy Characteristics'!J:J,MATCH($C63,'Policy Characteristics'!$C:$C,0))),"",INDEX('Policy Characteristics'!J:J,MATCH($C63,'Policy Characteristics'!$C:$C,0))) -> **Description:** This policy specifies the dollar amount offered as a subsidy to the purchaser of a new passenger vehicle. This is in addition to subsidies that exist in the BAU case. A negative value implies a tax or removal of subsidies. // **Guidance for setting values:** The U.S. currently offers a federal tax credit for up to $7,500 for qualifying clean passenger light-duty vehicles as part of the Inflation Reduction Act. This tax credit is included in the BAU scenario as an estimated average credit for new vehicles, accounting for the fact many vehicles will not be eligible starting in 2025 due to requirements for critical minerals sourcing. The BAU also includes the weighted average state-level credit offered for vehicles in the U.S. on top of the federal tax credits. | Q63: =IF(ISBLANK(INDEX('Policy Characteristics'!K:K,MATCH($C63,'Policy Characteristics'!$C:$C,0))),"",INDEX('Policy Characteristics'!K:K,MATCH($C63,'Policy Characteristics'!$C:$C,0))) -> transportation-sector-main.html#ev-subsidy | R63: =IF(ISBLANK(INDEX('Policy Characteristics'!L:L,MATCH($C63,'Policy Characteristics'!$C:$C,0))),"",INDEX('Policy Characteristics'!L:L,MATCH($C63,'Policy Characteristics'!$C:$C,0))) -> ev-subsidy.html
A64: =IF(ISBLANK(INDEX('Policy Characteristics'!A:A,MATCH($C64,'Policy Characteristics'!$C:$C,0))),"",INDEX('Policy Characteristics'!A:A,MATCH($C64,'Policy Characteristics'!$C:$C,0))) -> Transportation | B64: =IF(ISBLANK(INDEX('Policy Characteristics'!B:B,MATCH($C64,'Policy Characteristics'!$C:$C,0))),"",INDEX('Policy Characteristics'!B:B,MATCH($C64,'Policy Characteristics'!$C:$C,0))) -> Passenger Vehicle Subsidy | C64: =C$63 -> Additional Passenger Vehicle Subsidy | D64: LDVs | E64: natural gas vehicle | F64: Cars and SUVs | G64: Natural gas vehicle | H64: =H63+1 -> 63 | I64: No | J64: =IF(ISBLANK(INDEX('Policy Characteristics'!D:D,MATCH($C64,'Policy Characteristics'!$C:$C,0))),"",INDEX('Policy Characteristics'!D:D,MATCH($C64,'Policy Characteristics'!$C:$C,0))) -> Vehicle Subsidy | K64: =IF(ISBLANK(INDEX('Policy Characteristics'!E:E,MATCH($C64,'Policy Characteristics'!$C:$C,0))),"",INDEX('Policy Characteristics'!E:E,MATCH($C64,'Policy Characteristics'!$C:$C,0))) -> trans psgr subsidy | L64: =IF(ISBLANK(INDEX('Policy Characteristics'!F:F,MATCH($C64,'Policy Characteristics'!$C:$C,0))),"",INDEX('Policy Characteristics'!F:F,MATCH($C64,'Policy Characteristics'!$C:$C,0))) -> -45000 | M64: =IF(ISBLANK(INDEX('Policy Characteristics'!G:G,MATCH($C64,'Policy Characteristics'!$C:$C,0))),"",INDEX('Policy Characteristics'!G:G,MATCH($C64,'Policy Characteristics'!$C:$C,0))) -> 50000 | N64: =IF(ISBLANK(INDEX('Policy Characteristics'!H:H,MATCH($C64,'Policy Characteristics'!$C:$C,0))),"",INDEX('Policy Characteristics'!H:H,MATCH($C64,'Policy Characteristics'!$C:$C,0))) -> 100 | O64: =IF(ISBLANK(INDEX('Policy Characteristics'!I:I,MATCH($C64,'Policy Characteristics'!$C:$C,0))),"",INDEX('Policy Characteristics'!I:I,MATCH($C64,'Policy Characteristics'!$C:$C,0))) -> $ / vehicle | P64: =IF(ISBLANK(INDEX('Policy Characteristics'!J:J,MATCH($C64,'Policy Characteristics'!$C:$C,0))),"",INDEX('Policy Characteristics'!J:J,MATCH($C64,'Policy Characteristics'!$C:$C,0))) -> **Description:** This policy specifies the dollar amount offered as a subsidy to the purchaser of a new passenger vehicle. This is in addition to subsidies that exist in the BAU case. A negative value implies a tax or removal of subsidies. // **Guidance for setting values:** The U.S. currently offers a federal tax credit for up to $7,500 for qualifying clean passenger light-duty vehicles as part of the Inflation Reduction Act. This tax credit is included in the BAU scenario as an estimated average credit for new vehicles, accounting for the fact many vehicles will not be eligible starting in 2025 due to requirements for critical minerals sourcing. The BAU also includes the weighted average state-level credit offered for vehicles in the U.S. on top of the federal tax credits. | Q64: =IF(ISBLANK(INDEX('Policy Characteristics'!K:K,MATCH($C64,'Policy Characteristics'!$C:$C,0))),"",INDEX('Policy Characteristics'!K:K,MATCH($C64,'Policy Characteristics'!$C:$C,0))) -> transportation-sector-main.html#ev-subsidy | R64: =IF(ISBLANK(INDEX('Policy Characteristics'!L:L,MATCH($C64,'Policy Characteristics'!$C:$C,0))),"",INDEX('Policy Characteristics'!L:L,MATCH($C64,'Policy Characteristics'!$C:$C,0))) -> ev-subsidy.html
A65: =IF(ISBLANK(INDEX('Policy Characteristics'!A:A,MATCH($C65,'Policy Characteristics'!$C:$C,0))),"",INDEX('Policy Characteristics'!A:A,MATCH($C65,'Policy Characteristics'!$C:$C,0))) -> Transportation | B65: =IF(ISBLANK(INDEX('Policy Characteristics'!B:B,MATCH($C65,'Policy Characteristics'!$C:$C,0))),"",INDEX('Policy Characteristics'!B:B,MATCH($C65,'Policy Characteristics'!$C:$C,0))) -> Passenger Vehicle Subsidy | C65: =C$63 -> Additional Passenger Vehicle Subsidy | D65: LDVs | E65: gasoline vehicle | F65: Cars and SUVs | G65: Gasoline vehicle | H65: =H64+1 -> 64 | I65: No | J65: =IF(ISBLANK(INDEX('Policy Characteristics'!D:D,MATCH($C65,'Policy Characteristics'!$C:$C,0))),"",INDEX('Policy Characteristics'!D:D,MATCH($C65,'Policy Characteristics'!$C:$C,0))) -> Vehicle Subsidy | K65: =IF(ISBLANK(INDEX('Policy Characteristics'!E:E,MATCH($C65,'Policy Characteristics'!$C:$C,0))),"",INDEX('Policy Characteristics'!E:E,MATCH($C65,'Policy Characteristics'!$C:$C,0))) -> trans psgr subsidy | L65: =IF(ISBLANK(INDEX('Policy Characteristics'!F:F,MATCH($C65,'Policy Characteristics'!$C:$C,0))),"",INDEX('Policy Characteristics'!F:F,MATCH($C65,'Policy Characteristics'!$C:$C,0))) -> -45000 | M65: =IF(ISBLANK(INDEX('Policy Characteristics'!G:G,MATCH($C65,'Policy Characteristics'!$C:$C,0))),"",INDEX('Policy Characteristics'!G:G,MATCH($C65,'Policy Characteristics'!$C:$C,0))) -> 50000 | N65: =IF(ISBLANK(INDEX('Policy Characteristics'!H:H,MATCH($C65,'Policy Characteristics'!$C:$C,0))),"",INDEX('Policy Characteristics'!H:H,MATCH($C65,'Policy Characteristics'!$C:$C,0))) -> 100 | O65: =IF(ISBLANK(INDEX('Policy Characteristics'!I:I,MATCH($C65,'Policy Characteristics'!$C:$C,0))),"",INDEX('Policy Characteristics'!I:I,MATCH($C65,'Policy Characteristics'!$C:$C,0))) -> $ / vehicle | P65: =IF(ISBLANK(INDEX('Policy Characteristics'!J:J,MATCH($C65,'Policy Characteristics'!$C:$C,0))),"",INDEX('Policy Characteristics'!J:J,MATCH($C65,'Policy Characteristics'!$C:$C,0))) -> **Description:** This policy specifies the dollar amount offered as a subsidy to the purchaser of a new passenger vehicle. This is in addition to subsidies that exist in the BAU case. A negative value implies a tax or removal of subsidies. // **Guidance for setting values:** The U.S. currently offers a federal tax credit for up to $7,500 for qualifying clean passenger light-duty vehicles as part of the Inflation Reduction Act. This tax credit is included in the BAU scenario as an estimated average credit for new vehicles, accounting for the fact many vehicles will not be eligible starting in 2025 due to requirements for critical minerals sourcing. The BAU also includes the weighted average state-level credit offered for vehicles in the U.S. on top of the federal tax credits. | Q65: =IF(ISBLANK(INDEX('Policy Characteristics'!K:K,MATCH($C65,'Policy Characteristics'!$C:$C,0))),"",INDEX('Policy Characteristics'!K:K,MATCH($C65,'Policy Characteristics'!$C:$C,0))) -> transportation-sector-main.html#ev-subsidy | R65: =IF(ISBLANK(INDEX('Policy Characteristics'!L:L,MATCH($C65,'Policy Characteristics'!$C:$C,0))),"",INDEX('Policy Characteristics'!L:L,MATCH($C65,'Policy Characteristics'!$C:$C,0))) -> ev-subsidy.html
A66: =IF(ISBLANK(INDEX('Policy Characteristics'!A:A,MATCH($C66,'Policy Characteristics'!$C:$C,0))),"",INDEX('Policy Characteristics'!A:A,MATCH($C66,'Policy Characteristics'!$C:$C,0))) -> Transportation | B66: =IF(ISBLANK(INDEX('Policy Characteristics'!B:B,MATCH($C66,'Policy Characteristics'!$C:$C,0))),"",INDEX('Policy Characteristics'!B:B,MATCH($C66,'Policy Characteristics'!$C:$C,0))) -> Passenger Vehicle Subsidy | C66: =C$63 -> Additional Passenger Vehicle Subsidy | D66: LDVs | E66: diesel vehicle | F66: Cars and SUVs | G66: Diesel vehicle | H66: =H65+1 -> 65 | I66: No | J66: =IF(ISBLANK(INDEX('Policy Characteristics'!D:D,MATCH($C66,'Policy Characteristics'!$C:$C,0))),"",INDEX('Policy Characteristics'!D:D,MATCH($C66,'Policy Characteristics'!$C:$C,0))) -> Vehicle Subsidy | K66: =IF(ISBLANK(INDEX('Policy Characteristics'!E:E,MATCH($C66,'Policy Characteristics'!$C:$C,0))),"",INDEX('Policy Characteristics'!E:E,MATCH($C66,'Policy Characteristics'!$C:$C,0))) -> trans psgr subsidy | L66: =IF(ISBLANK(INDEX('Policy Characteristics'!F:F,MATCH($C66,'Policy Characteristics'!$C:$C,0))),"",INDEX('Policy Characteristics'!F:F,MATCH($C66,'Policy Characteristics'!$C:$C,0))) -> -45000 | M66: =IF(ISBLANK(INDEX('Policy Characteristics'!G:G,MATCH($C66,'Policy Characteristics'!$C:$C,0))),"",INDEX('Policy Characteristics'!G:G,MATCH($C66,'Policy Characteristics'!$C:$C,0))) -> 50000 | N66: =IF(ISBLANK(INDEX('Policy Characteristics'!H:H,MATCH($C66,'Policy Characteristics'!$C:$C,0))),"",INDEX('Policy Characteristics'!H:H,MATCH($C66,'Policy Characteristics'!$C:$C,0))) -> 100 | O66: =IF(ISBLANK(INDEX('Policy Characteristics'!I:I,MATCH($C66,'Policy Characteristics'!$C:$C,0))),"",INDEX('Policy Characteristics'!I:I,MATCH($C66,'Policy Characteristics'!$C:$C,0))) -> $ / vehicle | P66: =IF(ISBLANK(INDEX('Policy Characteristics'!J:J,MATCH($C66,'Policy Characteristics'!$C:$C,0))),"",INDEX('Policy Characteristics'!J:J,MATCH($C66,'Policy Characteristics'!$C:$C,0))) -> **Description:** This policy specifies the dollar amount offered as a subsidy to the purchaser of a new passenger vehicle. This is in addition to subsidies that exist in the BAU case. A negative value implies a tax or removal of subsidies. // **Guidance for setting values:** The U.S. currently offers a federal tax credit for up to $7,500 for qualifying clean passenger light-duty vehicles as part of the Inflation Reduction Act. This tax credit is included in the BAU scenario as an estimated average credit for new vehicles, accounting for the fact many vehicles will not be eligible starting in 2025 due to requirements for critical minerals sourcing. The BAU also includes the weighted average state-level credit offered for vehicles in the U.S. on top of the federal tax credits. | Q66: =IF(ISBLANK(INDEX('Policy Characteristics'!K:K,MATCH($C66,'Policy Characteristics'!$C:$C,0))),"",INDEX('Policy Characteristics'!K:K,MATCH($C66,'Policy Characteristics'!$C:$C,0))) -> transportation-sector-main.html#ev-subsidy | R66: =IF(ISBLANK(INDEX('Policy Characteristics'!L:L,MATCH($C66,'Policy Characteristics'!$C:$C,0))),"",INDEX('Policy Characteristics'!L:L,MATCH($C66,'Policy Characteristics'!$C:$C,0))) -> ev-subsidy.html
A67: =IF(ISBLANK(INDEX('Policy Characteristics'!A:A,MATCH($C67,'Policy Characteristics'!$C:$C,0))),"",INDEX('Policy Characteristics'!A:A,MATCH($C67,'Policy Characteristics'!$C:$C,0))) -> Transportation | B67: =IF(ISBLANK(INDEX('Policy Characteristics'!B:B,MATCH($C67,'Policy Characteristics'!$C:$C,0))),"",INDEX('Policy Characteristics'!B:B,MATCH($C67,'Policy Characteristics'!$C:$C,0))) -> Passenger Vehicle Subsidy | C67: =C$63 -> Additional Passenger Vehicle Subsidy | D67: LDVs | E67: plugin hybrid vehicle | F67: Cars and SUVs | G67: Plugin hybrid vehicle | H67: =H66+1 -> 66 | I67: Yes | J67: =IF(ISBLANK(INDEX('Policy Characteristics'!D:D,MATCH($C67,'Policy Characteristics'!$C:$C,0))),"",INDEX('Policy Characteristics'!D:D,MATCH($C67,'Policy Characteristics'!$C:$C,0))) -> Vehicle Subsidy | K67: =IF(ISBLANK(INDEX('Policy Characteristics'!E:E,MATCH($C67,'Policy Characteristics'!$C:$C,0))),"",INDEX('Policy Characteristics'!E:E,MATCH($C67,'Policy Characteristics'!$C:$C,0))) -> trans psgr subsidy | L67: =IF(ISBLANK(INDEX('Policy Characteristics'!F:F,MATCH($C67,'Policy Characteristics'!$C:$C,0))),"",INDEX('Policy Characteristics'!F:F,MATCH($C67,'Policy Characteristics'!$C:$C,0))) -> -45000 | M67: =IF(ISBLANK(INDEX('Policy Characteristics'!G:G,MATCH($C67,'Policy Characteristics'!$C:$C,0))),"",INDEX('Policy Characteristics'!G:G,MATCH($C67,'Policy Characteristics'!$C:$C,0))) -> 50000 | N67: =IF(ISBLANK(INDEX('Policy Characteristics'!H:H,MATCH($C67,'Policy Characteristics'!$C:$C,0))),"",INDEX('Policy Characteristics'!H:H,MATCH($C67,'Policy Characteristics'!$C:$C,0))) -> 100 | O67: =IF(ISBLANK(INDEX('Policy Characteristics'!I:I,MATCH($C67,'Policy Characteristics'!$C:$C,0))),"",INDEX('Policy Characteristics'!I:I,MATCH($C67,'Policy Characteristics'!$C:$C,0))) -> $ / vehicle | P67: =IF(ISBLANK(INDEX('Policy Characteristics'!J:J,MATCH($C67,'Policy Characteristics'!$C:$C,0))),"",INDEX('Policy Characteristics'!J:J,MATCH($C67,'Policy Characteristics'!$C:$C,0))) -> **Description:** This policy specifies the dollar amount offered as a subsidy to the purchaser of a new passenger vehicle. This is in addition to subsidies that exist in the BAU case. A negative value implies a tax or removal of subsidies. // **Guidance for setting values:** The U.S. currently offers a federal tax credit for up to $7,500 for qualifying clean passenger light-duty vehicles as part of the Inflation Reduction Act. This tax credit is included in the BAU scenario as an estimated average credit for new vehicles, accounting for the fact many vehicles will not be eligible starting in 2025 due to requirements for critical minerals sourcing. The BAU also includes the weighted average state-level credit offered for vehicles in the U.S. on top of the federal tax credits. | Q67: =IF(ISBLANK(INDEX('Policy Characteristics'!K:K,MATCH($C67,'Policy Characteristics'!$C:$C,0))),"",INDEX('Policy Characteristics'!K:K,MATCH($C67,'Policy Characteristics'!$C:$C,0))) -> transportation-sector-main.html#ev-subsidy | R67: =IF(ISBLANK(INDEX('Policy Characteristics'!L:L,MATCH($C67,'Policy Characteristics'!$C:$C,0))),"",INDEX('Policy Characteristics'!L:L,MATCH($C67,'Policy Characteristics'!$C:$C,0))) -> ev-subsidy.html
A68: =IF(ISBLANK(INDEX('Policy Characteristics'!A:A,MATCH($C68,'Policy Characteristics'!$C:$C,0))),"",INDEX('Policy Characteristics'!A:A,MATCH($C68,'Policy Characteristics'!$C:$C,0))) -> Transportation | B68: =IF(ISBLANK(INDEX('Policy Characteristics'!B:B,MATCH($C68,'Policy Characteristics'!$C:$C,0))),"",INDEX('Policy Characteristics'!B:B,MATCH($C68,'Policy Characteristics'!$C:$C,0))) -> Passenger Vehicle Subsidy | C68: =C$63 -> Additional Passenger Vehicle Subsidy | D68: LDVs | E68: LPG vehicle | F68: Cars and SUVs | G68: LPG vehicle | H68: =H67+1 -> 67 | I68: No | J68: =IF(ISBLANK(INDEX('Policy Characteristics'!D:D,MATCH($C68,'Policy Characteristics'!$C:$C,0))),"",INDEX('Policy Characteristics'!D:D,MATCH($C68,'Policy Characteristics'!$C:$C,0))) -> Vehicle Subsidy | K68: =IF(ISBLANK(INDEX('Policy Characteristics'!E:E,MATCH($C68,'Policy Characteristics'!$C:$C,0))),"",INDEX('Policy Characteristics'!E:E,MATCH($C68,'Policy Characteristics'!$C:$C,0))) -> trans psgr subsidy | L68: =IF(ISBLANK(INDEX('Policy Characteristics'!F:F,MATCH($C68,'Policy Characteristics'!$C:$C,0))),"",INDEX('Policy Characteristics'!F:F,MATCH($C68,'Policy Characteristics'!$C:$C,0))) -> -45000 | M68: =IF(ISBLANK(INDEX('Policy Characteristics'!G:G,MATCH($C68,'Policy Characteristics'!$C:$C,0))),"",INDEX('Policy Characteristics'!G:G,MATCH($C68,'Policy Characteristics'!$C:$C,0))) -> 50000 | N68: =IF(ISBLANK(INDEX('Policy Characteristics'!H:H,MATCH($C68,'Policy Characteristics'!$C:$C,0))),"",INDEX('Policy Characteristics'!H:H,MATCH($C68,'Policy Characteristics'!$C:$C,0))) -> 100 | O68: =IF(ISBLANK(INDEX('Policy Characteristics'!I:I,MATCH($C68,'Policy Characteristics'!$C:$C,0))),"",INDEX('Policy Characteristics'!I:I,MATCH($C68,'Policy Characteristics'!$C:$C,0))) -> $ / vehicle | P68: =IF(ISBLANK(INDEX('Policy Characteristics'!J:J,MATCH($C68,'Policy Characteristics'!$C:$C,0))),"",INDEX('Policy Characteristics'!J:J,MATCH($C68,'Policy Characteristics'!$C:$C,0))) -> **Description:** This policy specifies the dollar amount offered as a subsidy to the purchaser of a new passenger vehicle. This is in addition to subsidies that exist in the BAU case. A negative value implies a tax or removal of subsidies. // **Guidance for setting values:** The U.S. currently offers a federal tax credit for up to $7,500 for qualifying clean passenger light-duty vehicles as part of the Inflation Reduction Act. This tax credit is included in the BAU scenario as an estimated average credit for new vehicles, accounting for the fact many vehicles will not be eligible starting in 2025 due to requirements for critical minerals sourcing. The BAU also includes the weighted average state-level credit offered for vehicles in the U.S. on top of the federal tax credits. | Q68: =IF(ISBLANK(INDEX('Policy Characteristics'!K:K,MATCH($C68,'Policy Characteristics'!$C:$C,0))),"",INDEX('Policy Characteristics'!K:K,MATCH($C68,'Policy Characteristics'!$C:$C,0))) -> transportation-sector-main.html#ev-subsidy | R68: =IF(ISBLANK(INDEX('Policy Characteristics'!L:L,MATCH($C68,'Policy Characteristics'!$C:$C,0))),"",INDEX('Policy Characteristics'!L:L,MATCH($C68,'Policy Characteristics'!$C:$C,0))) -> ev-subsidy.html
A69: =IF(ISBLANK(INDEX('Policy Characteristics'!A:A,MATCH($C69,'Policy Characteristics'!$C:$C,0))),"",INDEX('Policy Characteristics'!A:A,MATCH($C69,'Policy Characteristics'!$C:$C,0))) -> Transportation | B69: =IF(ISBLANK(INDEX('Policy Characteristics'!B:B,MATCH($C69,'Policy Characteristics'!$C:$C,0))),"",INDEX('Policy Characteristics'!B:B,MATCH($C69,'Policy Characteristics'!$C:$C,0))) -> Passenger Vehicle Subsidy | C69: =C$63 -> Additional Passenger Vehicle Subsidy | D69: LDVs | E69: hydrogen vehicle | F69: Cars and SUVs | G69: Hydrogen vehicle | H69: =H68+1 -> 68 | I69: Yes | J69: =IF(ISBLANK(INDEX('Policy Characteristics'!D:D,MATCH($C69,'Policy Characteristics'!$C:$C,0))),"",INDEX('Policy Characteristics'!D:D,MATCH($C69,'Policy Characteristics'!$C:$C,0))) -> Vehicle Subsidy | K69: =IF(ISBLANK(INDEX('Policy Characteristics'!E:E,MATCH($C69,'Policy Characteristics'!$C:$C,0))),"",INDEX('Policy Characteristics'!E:E,MATCH($C69,'Policy Characteristics'!$C:$C,0))) -> trans psgr subsidy | L69: =IF(ISBLANK(INDEX('Policy Characteristics'!F:F,MATCH($C69,'Policy Characteristics'!$C:$C,0))),"",INDEX('Policy Characteristics'!F:F,MATCH($C69,'Policy Characteristics'!$C:$C,0))) -> -45000 | M69: =IF(ISBLANK(INDEX('Policy Characteristics'!G:G,MATCH($C69,'Policy Characteristics'!$C:$C,0))),"",INDEX('Policy Characteristics'!G:G,MATCH($C69,'Policy Characteristics'!$C:$C,0))) -> 50000 | N69: =IF(ISBLANK(INDEX('Policy Characteristics'!H:H,MATCH($C69,'Policy Characteristics'!$C:$C,0))),"",INDEX('Policy Characteristics'!H:H,MATCH($C69,'Policy Characteristics'!$C:$C,0))) -> 100 | O69: =IF(ISBLANK(INDEX('Policy Characteristics'!I:I,MATCH($C69,'Policy Characteristics'!$C:$C,0))),"",INDEX('Policy Characteristics'!I:I,MATCH($C69,'Policy Characteristics'!$C:$C,0))) -> $ / vehicle | P69: =IF(ISBLANK(INDEX('Policy Characteristics'!J:J,MATCH($C69,'Policy Characteristics'!$C:$C,0))),"",INDEX('Policy Characteristics'!J:J,MATCH($C69,'Policy Characteristics'!$C:$C,0))) -> **Description:** This policy specifies the dollar amount offered as a subsidy to the purchaser of a new passenger vehicle. This is in addition to subsidies that exist in the BAU case. A negative value implies a tax or removal of subsidies. // **Guidance for setting values:** The U.S. currently offers a federal tax credit for up to $7,500 for qualifying clean passenger light-duty vehicles as part of the Inflation Reduction Act. This tax credit is included in the BAU scenario as an estimated average credit for new vehicles, accounting for the fact many vehicles will not be eligible starting in 2025 due to requirements for critical minerals sourcing. The BAU also includes the weighted average state-level credit offered for vehicles in the U.S. on top of the federal tax credits. | Q69: =IF(ISBLANK(INDEX('Policy Characteristics'!K:K,MATCH($C69,'Policy Characteristics'!$C:$C,0))),"",INDEX('Policy Characteristics'!K:K,MATCH($C69,'Policy Characteristics'!$C:$C,0))) -> transportation-sector-main.html#ev-subsidy | R69: =IF(ISBLANK(INDEX('Policy Characteristics'!L:L,MATCH($C69,'Policy Characteristics'!$C:$C,0))),"",INDEX('Policy Characteristics'!L:L,MATCH($C69,'Policy Characteristics'!$C:$C,0))) -> ev-subsidy.html
A70: =IF(ISBLANK(INDEX('Policy Characteristics'!A:A,MATCH($C70,'Policy Characteristics'!$C:$C,0))),"",INDEX('Policy Characteristics'!A:A,MATCH($C70,'Policy Characteristics'!$C:$C,0))) -> Transportation | B70: =IF(ISBLANK(INDEX('Policy Characteristics'!B:B,MATCH($C70,'Policy Characteristics'!$C:$C,0))),"",INDEX('Policy Characteristics'!B:B,MATCH($C70,'Policy Characteristics'!$C:$C,0))) -> Passenger Vehicle Subsidy | C70: =C$63 -> Additional Passenger Vehicle Subsidy | D70: HDVs | E70: battery electric vehicle | F70: Buses | G70: Battery electric vehicle | H70: =H69+1 -> 69 | I70: Yes | J70: =IF(ISBLANK(INDEX('Policy Characteristics'!D:D,MATCH($C70,'Policy Characteristics'!$C:$C,0))),"",INDEX('Policy Characteristics'!D:D,MATCH($C70,'Policy Characteristics'!$C:$C,0))) -> Vehicle Subsidy | K70: =IF(ISBLANK(INDEX('Policy Characteristics'!E:E,MATCH($C70,'Policy Characteristics'!$C:$C,0))),"",INDEX('Policy Characteristics'!E:E,MATCH($C70,'Policy Characteristics'!$C:$C,0))) -> trans psgr subsidy | L70: =IF(ISBLANK(INDEX('Policy Characteristics'!F:F,MATCH($C70,'Policy Characteristics'!$C:$C,0))),"",INDEX('Policy Characteristics'!F:F,MATCH($C70,'Policy Characteristics'!$C:$C,0))) -> -45000 | M70: =IF(ISBLANK(INDEX('Policy Characteristics'!G:G,MATCH($C70,'Policy Characteristics'!$C:$C,0))),"",INDEX('Policy Characteristics'!G:G,MATCH($C70,'Policy Characteristics'!$C:$C,0))) -> 50000 | N70: =IF(ISBLANK(INDEX('Policy Characteristics'!H:H,MATCH($C70,'Policy Characteristics'!$C:$C,0))),"",INDEX('Policy Characteristics'!H:H,MATCH($C70,'Policy Characteristics'!$C:$C,0))) -> 100 | O70: =IF(ISBLANK(INDEX('Policy Characteristics'!I:I,MATCH($C70,'Policy Characteristics'!$C:$C,0))),"",INDEX('Policy Characteristics'!I:I,MATCH($C70,'Policy Characteristics'!$C:$C,0))) -> $ / vehicle | P70: =IF(ISBLANK(INDEX('Policy Characteristics'!J:J,MATCH($C70,'Policy Characteristics'!$C:$C,0))),"",INDEX('Policy Characteristics'!J:J,MATCH($C70,'Policy Characteristics'!$C:$C,0))) -> **Description:** This policy specifies the dollar amount offered as a subsidy to the purchaser of a new passenger vehicle. This is in addition to subsidies that exist in the BAU case. A negative value implies a tax or removal of subsidies. // **Guidance for setting values:** The U.S. currently offers a federal tax credit for up to $7,500 for qualifying clean passenger light-duty vehicles as part of the Inflation Reduction Act. This tax credit is included in the BAU scenario as an estimated average credit for new vehicles, accounting for the fact many vehicles will not be eligible starting in 2025 due to requirements for critical minerals sourcing. The BAU also includes the weighted average state-level credit offered for vehicles in the U.S. on top of the federal tax credits. | Q70: =IF(ISBLANK(INDEX('Policy Characteristics'!K:K,MATCH($C70,'Policy Characteristics'!$C:$C,0))),"",INDEX('Policy Characteristics'!K:K,MATCH($C70,'Policy Characteristics'!$C:$C,0))) -> transportation-sector-main.html#ev-subsidy | R70: =IF(ISBLANK(INDEX('Policy Characteristics'!L:L,MATCH($C70,'Policy Characteristics'!$C:$C,0))),"",INDEX('Policy Characteristics'!L:L,MATCH($C70,'Policy Characteristics'!$C:$C,0))) -> ev-subsidy.html
