Workbook

Sheet About
A1: CNBEIR Cement New Build Energy Intensity Ratio
A3: Sources: | B3: Best-available and fleet-typical kiln energy
B4: U.S. Department of Energy, Advanced Manufacturing Office
B5: Bandwidth Study on Energy Use and Potential Energy Savings Opportunities in U.S. Cement Manufacturing
B6: 2017
B7: https://www.energy.gov/eere/amo/articles/bandwidth-study-energy-use-and-potential-energy-savings-opportunities-us-cement
B8: Best-practice dry-process pyroprocessing energy of about 2.9 GJ per metric ton of clinker, against a current fleet-typical value of 1,554 Btu per pound, which is about 3.43 million BTU per metric ton (the same fleet value used in the CEIbPaF file). Both are typed into the 'Derivation' tab. We read the figures from the study's summary tables and press coverage, not from the underlying workbook.
B10: Cross-check on the best-available figure
B11: International Energy Agency
B12: Technology Roadmap: Low-Carbon Transition in the Cement Industry
B13: 2018
B14: https://www.iea.org/reports/technology-roadmap-low-carbon-transition-in-the-cement-industry
B15: Benchmarks for the best dry kilns with preheater and precalciner put thermal energy at roughly 2.9-3.0 GJ per metric ton of clinker, in line with the DOE figure. It is a report-level cross-check and does not enter the calculation. The roadmap also treats kiln thermal efficiency as already near its practical limit, which supports holding the ratio flat over time.
A18: Notes:
A19: Purpose and layout | B19: This file gives, for each cement production pathway, the energy use of newly built kilns as a fraction of the existing fleet's energy use (a ratio of 1.0 means no improvement). The EPS cement module applies it only to capacity built during the model run: the fleet's energy intensity per ton of clinker falls as new best-available kilns replace old ones, in the business-as-usual and policy cases alike. It also scales the fuel cost per ton for new builds, which feeds the investment choice among pathways. The tabs run from inputs to output. 'Derivation' holds the DOE figures, the arithmetic, and the judgment values for the electric kiln and alternative chemistry. 'Checks' tests that each ratio sits between 0.5 and 1.0. The 'CNBEIR' tab reads from 'Derivation' by formula, repeats each pathway's value across 2021-2050, and is what gets exported to CNBEIR.csv.
A20: Dry kiln with precalciner | B20: The ratio is the best-available energy intensity over the fleet-typical intensity. We convert the DOE best-practice figure from 2.9 GJ to 2.75 million BTU per metric ton of clinker (dividing by 1.05506 GJ per million BTU) and divide by the fleet-typical 3.426 million BTU per metric ton. The result is 0.8023. In plain terms, a new best-practice kiln uses about 20% less thermal energy per ton of clinker than the current U.S. average.
A21: Dry kiln with CCS | B21: The CCS pathway uses the same 0.802 as the dry kiln with precalciner. Its energy row in the CEIbPaF file covers the kiln only, so the same best-available credit applies to all of it. The capture unit's energy is booked by the CCS sector, and it is not discounted here.
A22: Electric kiln and alternative chemistry cement | B22: Both are held at 1.0, with no efficiency credit. Their energy values in the CEIbPaF file are already forward-looking estimates for new technology, and no existing fleet exists to compare against, so a further discount would count the same gain twice. This is our own judgment, not a sourced figure.
A23: Held flat over time | B23: Each ratio is the same in every year from 2021 to 2050, because the roadmaps treat best-practice dry-kiln thermal efficiency as already close to its limit. The flat path is our judgment, not a year-by-year projection.
A24: Electric kiln with CCS | B24: The electric kiln with CCS is the electric kiln with a capture unit on its nearly pure CO2 stream, so it uses the electric kiln's value here (same kiln). Its capture is added through CCF (95 percent of calcination CO2 captured) and the CDSC capture inputs.

Sheet Derivation
A1: CNBEIR derivation by Cement Production Pathway
A3: Dry kiln with precalciner
A4: BAT thermal energy intensity (GJ/metric ton clinker, DOE Bandwidth Study) | B4: 2.9
A5: Fleet-typical thermal energy intensity (Btu/lb clinker, DOE Bandwidth Study) | B5: 1554
A6: Unit conversion factor (lb per metric ton) | B6: 2204.62
A7: Fleet-typical thermal energy intensity (MMBtu/metric ton; matches CEIbPaF convention) | B7: =B5*B6/1000000 -> 3.4259795
A8: Precalciner CNBEIR = BAT (GJ/t, converted to MMBtu at 1.05506 GJ per MMBtu) / fleet-typical (MMBtu/t) | B8: =B4/1.05506/B7 -> 0.80229869
A9: Precalciner CNBEIR (value used) | B9: =(B8) -> 0.80229869
A11: Dry kiln with CCS: equals the dry kiln (the CEIbPaF CCS row is kiln only; capture energy is booked by the CCS sector)
A12: CEIbPaF precalciner pathway fuel total (BTU/metric ton clinker) | B12: 4020000
A13: CEIbPaF CCS pathway fuel total (BTU/metric ton clinker) | B13: 6270000
A14: CCS amine-regeneration/compression adder = CCS total - precalciner total | B14: =B13-B12 -> 2250000
A15: Precalciner CNBEIR applied to the kiln-thermal component | B15: =B9 -> 0.80229869
A16: BAT credit on the amine adder (1.0 = no discount; process energy, not kiln pyroprocessing) | B16: 1
A17: CCS CNBEIR = precalciner value (the CEIbPaF CCS row is kiln only) | B17: =B9 -> 0.80229869
A18: CCS CNBEIR (value used) | B18: =(B17) -> 0.80229869
A20: Electric kiln
A21: CNBEIR = 1.0 (EI judgment: CEIbPaF value already a forward-looking new-technology estimate, no legacy fleet to benchmark against) | B21: 1
A23: Alternative chemistry cement
A24: CNBEIR = 1.0 (EI judgment: CEIbPaF value already a forward-looking new-technology estimate, no legacy fleet to benchmark against) | B24: 1
A26: Held flat 2021-2050 for all four pathways (see About notes). The BAT figure is converted from GJ to MMBtu before dividing.

Sheet Checks
A1: Checks
A3: dry kiln with precalciner: 0.5 <= value <= 1.0 | B3: =IF(AND(MIN(CNBEIR!B2:AE2)>=0.5,MAX(CNBEIR!B2:AE2)<=1),"PASS","FAIL") -> PASS
A4: dry kiln with CCS: 0.5 <= value <= 1.0 | B4: =IF(AND(MIN(CNBEIR!B3:AE3)>=0.5,MAX(CNBEIR!B3:AE3)<=1),"PASS","FAIL") -> PASS
A5: electric kiln: 0.5 <= value <= 1.0 | B5: =IF(AND(MIN(CNBEIR!B4:AE4)>=0.5,MAX(CNBEIR!B4:AE4)<=1),"PASS","FAIL") -> PASS
A6: alternative chemistry cement: 0.5 <= value <= 1.0 | B6: =IF(AND(MIN(CNBEIR!B6:AE6)>=0.5,MAX(CNBEIR!B6:AE6)<=1),"PASS","FAIL") -> PASS

Sheet CNBEIR
A1: Unit: dimensionless | B1: 2021 | C1: 2022 | D1: 2023 | E1: 2024 | F1: 2025 | G1: 2026 | H1: 2027 | I1: 2028 | J1: 2029 | K1: 2030 | L1: 2031 | M1: 2032 | N1: 2033 | O1: 2034 | P1: 2035 | Q1: 2036 | R1: 2037 | S1: 2038 | T1: 2039 | U1: 2040 | V1: 2041 | W1: 2042 | X1: 2043 | Y1: 2044 | Z1: 2045 | AA1: 2046 | AB1: 2047 | AC1: 2048 | AD1: 2049 | AE1: 2050
A2: dry kiln with precalciner | B2: =Derivation!$B$9 -> 0.80229869 | C2: =Derivation!$B$9 -> 0.80229869 | D2: =Derivation!$B$9 -> 0.80229869 | E2: =Derivation!$B$9 -> 0.80229869 | F2: =Derivation!$B$9 -> 0.80229869 | G2: =Derivation!$B$9 -> 0.80229869 | H2: =Derivation!$B$9 -> 0.80229869 | I2: =Derivation!$B$9 -> 0.80229869 | ... AE2: =Derivation!$B$9 -> 0.80229869
A3: dry kiln with CCS | B3: =Derivation!$B$18 -> 0.80229869 | C3: =Derivation!$B$18 -> 0.80229869 | D3: =Derivation!$B$18 -> 0.80229869 | E3: =Derivation!$B$18 -> 0.80229869 | F3: =Derivation!$B$18 -> 0.80229869 | G3: =Derivation!$B$18 -> 0.80229869 | H3: =Derivation!$B$18 -> 0.80229869 | I3: =Derivation!$B$18 -> 0.80229869 | ... AE3: =Derivation!$B$18 -> 0.80229869
A4: electric kiln | B4: =Derivation!$B$21 -> 1 | C4: =Derivation!$B$21 -> 1 | D4: =Derivation!$B$21 -> 1 | E4: =Derivation!$B$21 -> 1 | F4: =Derivation!$B$21 -> 1 | G4: =Derivation!$B$21 -> 1 | H4: =Derivation!$B$21 -> 1 | I4: =Derivation!$B$21 -> 1 | ... AE4: =Derivation!$B$21 -> 1
A5: electric kiln with CCS | B5: =B4 -> 1 | C5: =C4 -> 1 | D5: =D4 -> 1 | E5: =E4 -> 1 | F5: =F4 -> 1 | G5: =G4 -> 1 | H5: =H4 -> 1 | I5: =I4 -> 1 | ... AE5: =AE4 -> 1
A6: alternative chemistry cement | B6: =Derivation!$B$24 -> 1 | C6: =Derivation!$B$24 -> 1 | D6: =Derivation!$B$24 -> 1 | E6: =Derivation!$B$24 -> 1 | F6: =Derivation!$B$24 -> 1 | G6: =Derivation!$B$24 -> 1 | H6: =Derivation!$B$24 -> 1 | I6: =Derivation!$B$24 -> 1 | ... AE6: =Derivation!$B$24 -> 1
