Workbook

Sheet About
A1: BCPCS BAU Cement Pathway Capital Subsidy
A3: Sources: | B3: U.S. federal capital support for low-carbon cement plants
B4: Canary Media
B5: Trump cut funding for clean industry projects (U.S. DOE Office of Clean Energy Demonstrations award terminations)
B6: 2025
B7: https://www.canarymedia.com/articles/clean-industry/trump-cut-funding-oced
B8: Reports the May 30, 2025 termination of 24 Office of Clean Energy Demonstrations awards, including the Industrial Demonstrations Program cement awards (Heidelberg Materials Mitchell, National Cement Lebec, Brimstone, Sublime Systems), which would have paid part of the capital cost of those plants. With them cancelled, no U.S. federal program pays a share of cement plant capital, so the U.S. values are zero. Per-ton support for captured CO2 (the 45Q credit) is not a capital subsidy and enters the model through the industry CCS subsidy instead.
B10: Example of a capital subsidy other regions may need to enter
B11: Government of Canada (summarized by Leyton)
B12: Clean technology tax credits: federal budget 2025, what is new (Investment Tax Credit for Carbon Capture, Utilization and Storage)
B13: 2025
B14: https://leyton.com/ca/en/insights/articles/clean-technology-tax-credits-federal-budget-2025-whats-new/
B15: Canada credits 50 percent of the cost of carbon capture equipment and 37.5 percent of transport, storage and use equipment, with full rates extended to the end of 2035 in Budget 2025 (the legislative status of the extension should be checked). A credit on capture equipment only covers part of a CCS cement plant, so convert it to a share of the whole pathway capital cost before entering it (see Notes). Secondary source; not used for the U.S. values.
A18: Notes:
A19: Purpose and layout | B19: BCPCS is the share of the capital cost of new clinker production capacity that government already pays, by production pathway and year, under policies in place before any new policy. It lowers the capital cost investors weigh when they choose which kind of kiln to build, in both the business-as-usual and policy cases, and the model books the payments as government spending. The cement pathway capital subsidy policy adds to it (the two together are capped at the whole cost). Edit the 'Subsidy Rates' tab; the 'BCPCS' tab is exported to BCPCS.csv.
A20: U.S. values | B20: Zero for every pathway and year: the federal cement demonstration awards were cancelled in 2025 and no other program pays a share of cement plant capital.
A21: Entering a credit that covers only part of the plant | B21: The model's pathway capital cost includes the kiln and, for the CCS pathway, the capture equipment. A credit that covers only the capture equipment should be entered as the credit rate times the capture equipment's share of the CCS pathway's capital cost. With the U.S. cost inputs, capture equipment is a little under 40 percent of the CCS pathway's greenfield capital, so a 50 percent capture-equipment credit is about 0.2.
A22: Other regions | B22: Enter grants or investment tax credits that are in force and open to cement plants (for example EU Innovation Fund grants for named projects, or Canada's carbon capture credit), and end them in the year the program closes.
A23: Electric kiln with CCS | B23: The electric kiln with CCS is the electric kiln with a capture unit on its nearly pure CO2 stream, so it uses the electric kiln's value here (same kiln). Its capture is added through CCF (95 percent of calcination CO2 captured) and the CDSC capture inputs.

Sheet Subsidy Rates
A1: BAU share of pathway capital cost paid by government (edit here)
A2: Fraction of the capital cost of new clinker capacity (kiln plus any capture equipment) paid under policies already in place, by pathway and year, between 0 and 1.
A3: Pathway | B3: 2021 | C3: 2022 | D3: 2023 | E3: 2024 | F3: 2025 | G3: 2026 | H3: 2027 | I3: 2028 | J3: 2029 | K3: 2030 | L3: 2031 | M3: 2032 | N3: 2033 | O3: 2034 | P3: 2035 | Q3: 2036 | R3: 2037 | S3: 2038 | T3: 2039 | U3: 2040 | V3: 2041 | W3: 2042 | X3: 2043 | Y3: 2044 | Z3: 2045 | AA3: 2046 | AB3: 2047 | AC3: 2048 | AD3: 2049 | AE3: 2050
A4: dry kiln with precalciner | B4: 0 | C4: 0 | D4: 0 | E4: 0 | F4: 0 | G4: 0 | H4: 0 | I4: 0 | J4: 0 | K4: 0 | L4: 0 | M4: 0 | N4: 0 | O4: 0 | P4: 0 | Q4: 0 | R4: 0 | S4: 0 | T4: 0 | U4: 0 | V4: 0 | W4: 0 | X4: 0 | Y4: 0 | Z4: 0 | AA4: 0 | AB4: 0 | AC4: 0 | AD4: 0 | AE4: 0
A5: dry kiln with CCS | B5: 0 | C5: 0 | D5: 0 | E5: 0 | F5: 0 | G5: 0 | H5: 0 | I5: 0 | J5: 0 | K5: 0 | L5: 0 | M5: 0 | N5: 0 | O5: 0 | P5: 0 | Q5: 0 | R5: 0 | S5: 0 | T5: 0 | U5: 0 | V5: 0 | W5: 0 | X5: 0 | Y5: 0 | Z5: 0 | AA5: 0 | AB5: 0 | AC5: 0 | AD5: 0 | AE5: 0
A6: electric kiln | B6: 0 | C6: 0 | D6: 0 | E6: 0 | F6: 0 | G6: 0 | H6: 0 | I6: 0 | J6: 0 | K6: 0 | L6: 0 | M6: 0 | N6: 0 | O6: 0 | P6: 0 | Q6: 0 | R6: 0 | S6: 0 | T6: 0 | U6: 0 | V6: 0 | W6: 0 | X6: 0 | Y6: 0 | Z6: 0 | AA6: 0 | AB6: 0 | AC6: 0 | AD6: 0 | AE6: 0
A7: alternative chemistry cement | B7: 0 | C7: 0 | D7: 0 | E7: 0 | F7: 0 | G7: 0 | H7: 0 | I7: 0 | J7: 0 | K7: 0 | L7: 0 | M7: 0 | N7: 0 | O7: 0 | P7: 0 | Q7: 0 | R7: 0 | S7: 0 | T7: 0 | U7: 0 | V7: 0 | W7: 0 | X7: 0 | Y7: 0 | Z7: 0 | AA7: 0 | AB7: 0 | AC7: 0 | AD7: 0 | AE7: 0

Sheet Checks
A1: Live checks
A2: Check | B2: Value | C2: Result
A3: Values below 0 or above 1 (count) | B3: =COUNTIF('Subsidy Rates'!B4:AE7,"<0")+COUNTIF('Subsidy Rates'!B4:AE7,">1") -> 0 | C3: =IF(B3=0,"PASS","FAIL") -> PASS

Sheet BCPCS
A1: Unit: dimensionless | B1: 2021 | C1: 2022 | D1: 2023 | E1: 2024 | F1: 2025 | G1: 2026 | H1: 2027 | I1: 2028 | J1: 2029 | K1: 2030 | L1: 2031 | M1: 2032 | N1: 2033 | O1: 2034 | P1: 2035 | Q1: 2036 | R1: 2037 | S1: 2038 | T1: 2039 | U1: 2040 | V1: 2041 | W1: 2042 | X1: 2043 | Y1: 2044 | Z1: 2045 | AA1: 2046 | AB1: 2047 | AC1: 2048 | AD1: 2049 | AE1: 2050
A2: ='Subsidy Rates'!A4 -> dry kiln with precalciner | B2: ='Subsidy Rates'!B4 -> 0 | C2: ='Subsidy Rates'!C4 -> 0 | D2: ='Subsidy Rates'!D4 -> 0 | E2: ='Subsidy Rates'!E4 -> 0 | F2: ='Subsidy Rates'!F4 -> 0 | G2: ='Subsidy Rates'!G4 -> 0 | H2: ='Subsidy Rates'!H4 -> 0 | ... AE2: ='Subsidy Rates'!AE4 -> 0
A3: ='Subsidy Rates'!A5 -> dry kiln with CCS | B3: ='Subsidy Rates'!B5 -> 0 | C3: ='Subsidy Rates'!C5 -> 0 | D3: ='Subsidy Rates'!D5 -> 0 | E3: ='Subsidy Rates'!E5 -> 0 | F3: ='Subsidy Rates'!F5 -> 0 | G3: ='Subsidy Rates'!G5 -> 0 | H3: ='Subsidy Rates'!H5 -> 0 | ... AE3: ='Subsidy Rates'!AE5 -> 0
A4: ='Subsidy Rates'!A6 -> electric kiln | B4: ='Subsidy Rates'!B6 -> 0 | C4: ='Subsidy Rates'!C6 -> 0 | D4: ='Subsidy Rates'!D6 -> 0 | E4: ='Subsidy Rates'!E6 -> 0 | F4: ='Subsidy Rates'!F6 -> 0 | G4: ='Subsidy Rates'!G6 -> 0 | H4: ='Subsidy Rates'!H6 -> 0 | ... AE4: ='Subsidy Rates'!AE6 -> 0
A5: electric kiln with CCS | B5: =B4 -> 0 | C5: =C4 -> 0 | D5: =D4 -> 0 | E5: =E4 -> 0 | F5: =F4 -> 0 | G5: =G4 -> 0 | H5: =H4 -> 0 | I5: =I4 -> 0 | ... AE5: =AE4 -> 0
A6: ='Subsidy Rates'!A7 -> alternative chemistry cement | B6: ='Subsidy Rates'!B7 -> 0 | C6: ='Subsidy Rates'!C7 -> 0 | D6: ='Subsidy Rates'!D7 -> 0 | E6: ='Subsidy Rates'!E7 -> 0 | F6: ='Subsidy Rates'!F7 -> 0 | G6: ='Subsidy Rates'!G7 -> 0 | H6: ='Subsidy Rates'!H7 -> 0 | ... AE6: ='Subsidy Rates'!AE7 -> 0
