Workbook
Name a: #REF!
Name a: #REF!
Name AsphaltStore: [1]Control!$D$50
Name base.year: #REF!
Name BaseYear: 2018
Name BTV11_15: #REF!
Name BTV11_15: #REF!
Name BVT17_15: #REF!
Name BVT17_15: #REF!
Name CAAGR_tolerance: 200
Name CH4_to_CO2e: '[2]Cross-Page Data'!$C$12
Name CH4GWP: #REF!
Name CO2_T4_APS: #REF!
Name CO2_T4_APS: #REF!
Name CO2_T4_NZE: #REF!
Name CO2_T4_NZE: #REF!
Name CO2_T4_STEPS: #REF!
Name CO2_T4_STEPS: #REF!
Name CO2_T5_APS: #REF!
Name CO2_T5_APS: #REF!
Name CO2_T5_CPS: #REF!
Name CO2_T5_CPS: #REF!
Name CO2_T5_NZE: #REF!
Name CO2_T5_NZE: #REF!
Name CO2_T5_STEPS: #REF!
Name CO2_T5_STEPS: #REF!
Name coal.past: #REF!
Name COAL_PRODUCTION: #REF!
Name COAL_PRODUCTION: #REF!
Name Coal_trade: #REF!
Name Coal_trade: #REF!
Name coaldemand: #REF!
Name coaldemand: #REF!
Name CokeCoalStore: [1]Control!$D$63
Name Constants.Density.Diesel: #REF!
Name Constants.Density.Ethanol: #REF!
Name Constants.Density.JetFuel: #REF!
Name Constants.Density.MotorSpirit: #REF!
Name ConsumeBlock1: '[1]Default State Energy Data Table'!$A$6:$AM$67
Name Conversion.to.average.power: #REF!
Name Conversion.water.L: #REF!
Name Conversion.water.units: #REF!
Name Conversions.Area.m2: #REF!
Name Conversions.Area.Units: #REF!
Name Conversions.Energy.Joules: #REF!
Name Conversions.Energy.Units: #REF!
Name Conversions.Money.GBP: #REF!
Name Conversions.Money.Units: #REF!
Name Conversions.Power.Units: #REF!
Name Conversions.Power.Watts: #REF!
Name Cost.Capital.Scenario: #REF!
Name Cost.Finance.Scenario: #REF!
Name Cost.Fuel.Scenario: #REF!
Name Cost.Infrastructure.Scenario: #REF!
Name cpi_2010to2012: #REF!
Name cpi_2010to2012: #REF!
Name cpi_2013to2012: #REF!
Name cpi_2013to2012: #REF!
Name cpi_2014to2012: #REF!
Name cpi_2014to2012: #REF!

Sheet About
A1: IECCpUAEU Industrial Equipment Capital Cost per Unit Annual Energy Use
A2: Check the heat pump capex against other sources (kWth vs kWheat?)
A3: Sources: | B3: Industrial heat pumps cost per unit heat delivered | D3: Electric and gas-fired ovens
B4: Zühlsdorf, B., Andersen, M. P., Tammone, C. et.al. | D4: DOE (EERE)
B5: 2025 | D5: 2016
B6: Industrial High-Temperature Heat Pumps. Task 1 – Technologies: Yearly Report 2025 | D6: Energy Savings Potential and RD&D Opportunities for Commercial Building Appliances (2015 Update)
B7: https://heatpumpingtechnologies.org/project68/task1/ | D7: https://www.energy.gov/sites/prod/files/2016/06/f32/DOE-BTO%20Comml%20Appl%20Report%20-%20Full%20Report_0.pdf
B8: Page 16, Figure 1-4
D9: Natural gas-fired distillation columns
B10: Industrial heat pumps capacity factor | D10: DOE (OSTI)
B11: Copeland (formerly Emerson Climate Technologies) | D11: 2013
B12: 2011 | D12: Distributive Distillation Enabled by Microchannel Process Technology
B13: Industrial Heat Pumps | D13: https://www.osti.gov/servlets/purl/1077001
B14: https://media.copeland.com/1da81099-2c21-4ce5-8096-b16d0037b111/VILTER%20Heat%20Pump%20White%20Paper.pdf
B15: Page 6-8. Capacity factor is based on the average annual operating hours across the four examples, assuming each operates at full capacity.
B17: Three fossil fuel type industrial boiler costs | D17: Hydrogen boiler capital cost price ratio
B18: IRENA | D18: E3
B19: 2016 | D19: "Achieving Carbon Neutrality in California (Revised Report): 2045 Abatement Cost Estimates"
B20: Remap Technology and Performance Assumptions (for year 2030) | D20: 2020
B21: https://www.irena.org/-/media/Irena/Files/REmap/IRENA_REmap_2030_technology_cost.xlsx | D21: https://ww2.arb.ca.gov/sites/default/files/2020-09/e3_cn_draft_report_supp_data_aug2020.xlsx
B23: NOT USED - Included for reference/comparison - natural gas boiler costs | D23: Electrochemical
B24: State of Michigan | D24: Data from the DOE's Pathways to Commercial Liftoff: Clean Hydrogen , 2023, p.13, p.88
B25: 2003
B26: Miscellaneous Industrial Costs | D26: China capex numbers provided by:
B27: https://www.michigan.gov/-/media/Project/Websites/treasury/VOL/Vol236UIP12MiscellaneousIndustrialCosts.pdf?rev=b2a14a143c11493e8d0a30587afaa282 | D27: Wang et al., 2023. "The multi-scenario projection of cost reduction in hydrogen production by proton exchange membrane (PEM) water electrolysis in the near future (2020–2060) of China." Fuel, Vol. 354
B28: Page 1
B30: NOT USED - Included for reference/comparison - natural gas boiler costs | D30: Natural gas-fired chillers
B31: National Renewable Energy Laboratory | D31: EnergistX
B32: 2017 | D32: undated
B33: Electrification Futures Study | D33: 500 Ton Natural Gas-Fired Absorption Chiller replacement of Aged Centrifugal Electric Chiller
B34: https://docs.nrel.gov/docs/fy18osti/70485.pdf | D34: https://enrgistx.com/natural-gas-fired-chillers/
B35: Page 64, Table 17
B37: Nonboiler High Temp | D37: Electric chillers
B38: Electric Example (EAF) References: | D38: Florida Power & Light
B39: Capex costs per ton: | D39: undated
B40: Deutsches Institut für Wirtschaftsforschung | D40: Water-Cooled Chillers
B41: 2024 | D41: https://www.fpl.com/content/dam/fplgp/us/en/business/save/programs/pdf/water-cooled-chillers-primer.pdf
B42: "Revisiting Investment Costs for Green Steel: Capital Expenditures, Firm Level Impacts, and Policy Implications"
B43: https://www.diw.de/documents/publikationen/73/diw_01.c.901039.de/dp2082.pdf
B45: Energy expenditure/output:
B46: Paeng & Azimi
B47: 2024
B48: "Technoeconomic Analysis of the Electrorefining Process for Copper and Carbon Removal from Scrap Steel for Green Steelmaking"
B49: Industrial & Chemical Engineering Research
B50: https://pubs.acs.org/doi/10.1021/acs.iecr.4c02665
B52: Annual production capacity:
B53: Energy Transitions Commission
B54: 44621
B55: "Unlocking the first wave of breakthrough steel investments in France"
B56: https://www.energy-transitions.org/wp-content/uploads/2023/03/Unlocking-the-First-Wave-of-Breakthrough-Steel-Investments-in-France-March-2022.pdf
B58: Coal Example (Cement Kiln) References:
B59: Vattenfall & Cementa (Heidelberg Cement Group)
B60: 2018
B61: CemZero
B63: China Ruibin Information Network
B64: 2024
B65: "How much does it cost to build a rotary kiln with a daily output of 600 tons"
B66: http://www.jixiemuye.com/en/business-2/article-364.html
B68: Europe cement kiln reference:
B69: Edoardo De Lena et al.
B70: 2019
B71: Techno-economic analysis of calcium looping processes for low CO2 emission cement plants
B72: https://www.researchgate.net/publication/330875028_Techno-economic_analysis_of_calcium_looping_processes_for_low_CO_2_emission_cement_plants
B73: Table 8, "Capex, Europ/ton clinker" row
B76: Natural Gas Example (NG Glass Melting Furnace) References:
B77: Glass Technology Services Ltd.
B78: 38231
B79: "A Study of the Balance Between Furnace Operating Parameters and Recycled Glass in Melting Furnaces."
B80: https:/www.glass-ts.com/site/assets/files/1015/2004_-_a_study_of_the_balance_between_furnace_operating_parameters_and_recycled_glass_in_glass_melting_furnaces.pdf
B82: Machine Drive
B83: Global CO2 Initiative at Uniiversity of Michigan
B84: Assess CCUS Capital Equipment Cost Database
B85: Information on a diesel engine and various electric motors and drives (Rows 144-155)
B87: with additional data derived from their primary source:
B88: Donald R. Woods
B89: 2007
B90: Appendix D of Rules of Thumb in Engineering
B92: Operating hours, and percentage of motors in a given horsepower bin for calculating weighted averages based on energy distribution,
B93: were obtained from the U.S. Industrial Electric Motor Systems Market Opportunities Assessment (2002).
B94: The recent assessment did not have data disaggregated in the appropriate way to provide more recent values.
B95: U.S. Industrial Electric Motor Systems Market Opportunities Assessment (2002)
B97: Nonboiler Med/High Temp - Electric Resistance Heater Example References:
B98: Mayer, P., Baader, F.J., et al. (ETH Zürich)
B99: 2025
B100: "Transition pathways to electrified chemical production within sector-coupled national energy systems"
B101: https://arxiv.org/pdf/2503.02008
B102: Supplementary Table: resistance-heater CAPEX 238 k€/MW (= €238/kW), attributed to Baumgärtner et al. Used for the 200-500 °C and 500-1000 °C electricity cells.
A111: Energy content:
A112: 138490 | B112: BTU/gal diesel
A113: https://afdc.energy.gov/fuels/properties
A114: 3412.14 | B114: BTU/kWh
A117: 0.78452102 | B117: 2022 to 2012 USD
A118: 0.84730413 | B118: 2021 to 2012 USD
A120: CPI-U annual average (BLS, 1982-84=100), and multiplier to 2012 USD
A121: Year | B121: CPI-U | C121: Mult to 2012
A122: 2004 | B122: 188.9 | C122: =$B$123/B122 -> 1.2154262
A123: 2012 | B123: 229.594 | C123: =$B$123/B123 -> 1
A124: 2013 | B124: 232.957 | C124: =$B$123/B124 -> 0.98556386
A125: 2015 | B125: 237.017 | C125: =$B$123/B125 -> 0.96868157
A126: 2016 | B126: 240.007 | C126: =$B$123/B126 -> 0.95661377
...

Sheet cpi
A1: Historical Consumer Price Index for All Urban Consumers (CPI-U): U.S. city average, all items, index
A2: averages — Continued
A3: [1982-84=100, unless otherwise noted]
A4: Year | B4: Semiannual averages | D4: Annual avg. | E4: Percent change from previous | G4: Multiply by to get 2012 Dollars
B5: 1st half | C5: 2nd half | E5: Dec. | F5: Annual avg.
A6: 1968............................................................................. . | B6: – | C6: – | D6: 34.8 | E6: 4.7 | F6: 4.2
A7: 1969............................................................................. . | B7: – | C7: – | D7: 36.7 | E7: 6.2 | F7: 5.5
A8: 1970............................................................................. . | B8: – | C8: – | D8: 38.8 | E8: 5.6 | F8: 5.7
A9: 1971............................................................................. . | B9: – | C9: – | D9: 40.5 | E9: 3.3 | F9: 4.4
A10: 1972............................................................................. . | B10: – | C10: – | D10: 41.8 | E10: 3.4 | F10: 3.2
A11: 1973............................................................................. . | B11: – | C11: – | D11: 44.4 | E11: 8.7 | F11: 6.2
A12: 1974............................................................................. . | B12: – | C12: – | D12: 49.3 | E12: 12.3 | F12: 11
A13: 1975............................................................................. . | B13: – | C13: – | D13: 53.8 | E13: 6.9 | F13: 9.1
A14: 1976............................................................................. . | B14: – | C14: – | D14: 56.9 | E14: 4.9 | F14: 5.8
A15: 1977............................................................................. . | B15: – | C15: – | D15: 60.6 | E15: 6.7 | F15: 6.5
A16: 1978............................................................................. . | B16: – | C16: – | D16: 65.2 | E16: 9 | F16: 7.6
A17: 1979............................................................................. . | B17: – | C17: – | D17: 72.6 | E17: 13.3 | F17: 11.3
... A21: 1983............................................................................. . | B21: – | C21: – | D21: 99.6 | E21: 3.8 | F21: 3.2
A22: 1984............................................................................. . | B22: 102.9 | C22: 104.9 | D22: 103.9 | E22: 3.9 | F22: 4.3
A23: 1985............................................................................. . | B23: 106.6 | C23: 108.5 | D23: 107.6 | E23: 3.8 | F23: 3.6
A24: 1986............................................................................. . | B24: 109.1 | C24: 110.1 | D24: 109.6 | E24: 1.1 | F24: 1.9
A25: 1987............................................................................. . | B25: 112.4 | C25: 114.9 | D25: 113.6 | E25: 4.4 | F25: 3.6
A26: 1988............................................................................. . | B26: 116.8 | C26: 119.7 | D26: 118.3 | E26: 4.4 | F26: 4.1
A27: 1989............................................................................. . | B27: 122.7 | C27: 125.3 | D27: 124 | E27: 4.6 | F27: 4.8
A28: 1990............................................................................. . | B28: 128.7 | C28: 132.6 | D28: 130.7 | E28: 6.1 | F28: 5.4 | G28: =$D$50/D28 -> 1.7566488
A29: 1991............................................................................. . | B29: 135.2 | C29: 137.2 | D29: 136.2 | E29: 3.1 | F29: 4.2 | G29: =$D$50/D29 -> 1.6857122
A30: 1992............................................................................. . | B30: 139.2 | C30: 141.4 | D30: 140.3 | E30: 2.9 | F30: 3 | G30: =$D$50/D30 -> 1.6364505
A31: 1993............................................................................. . | B31: 143.7 | C31: 145.3 | D31: 144.5 | E31: 2.7 | F31: 3 | G31: =$D$50/D31 -> 1.5888858
A32: 1994............................................................................. . | B32: 147.2 | C32: 149.3 | D32: 148.2 | E32: 2.7 | F32: 2.6 | G32: =$D$50/D32 -> 1.5492173
A33: 1995............................................................................. . | B33: 151.5 | C33: 153.2 | D33: 152.4 | E33: 2.5 | F33: 2.8 | G33: =$D$50/D33 -> 1.5065223
A34: 1996............................................................................. . | B34: 155.8 | C34: 157.9 | D34: 156.9 | E34: 3.3 | F34: 3 | G34: =$D$50/D34 -> 1.4633142
A35: 1997............................................................................. . | B35: 159.9 | C35: 161.2 | D35: 160.5 | E35: 1.7 | F35: 2.3 | G35: =$D$50/D35 -> 1.4304922
A36: 1998............................................................................. . | B36: 162.3 | C36: 163.7 | D36: 163 | E36: 1.6 | F36: 1.6 | G36: =$D$50/D36 -> 1.4085521
A37: 1999............................................................................. . | B37: 165.4 | C37: 167.8 | D37: 166.6 | E37: 2.7 | F37: 2.2 | G37: =$D$50/D37 -> 1.3781152
A38: 2000............................................................................. . | B38: 170.8 | C38: 173.6 | D38: 172.2 | E38: 3.4 | F38: 3.4 | G38: =$D$50/D38 -> 1.3332985
A39: 2001............................................................................. . | B39: 176.6 | C39: 177.5 | D39: 177.1 | E39: 1.6 | F39: 2.8 | G39: =$D$50/D39 -> 1.2964088
... A60: 2022............................................................................. . | B60: 288.347 | C60: 296.963 | D60: 292.655 | E60: 6.5 | F60: 8 | G60: =$D$50/D60 -> 0.78452102
A61: 2023............................................................................. . | B61: 302.408 | C61: 306.996 | D61: 304.702 | G61: =$D$50/D61 -> 0.75350342
A62: 2024............................................................................. . | B62: 312.145 | C62: 315.233 | D62: 313.689 | G62: =$D$50/D62 -> 0.73191601
A63: 2025............................................................................. . | B63: 320.13 | C63: 324.16 | D63: 321.962 | G63: =$D$50/D63 -> 0.713109

Sheet Boilers & Heat Pumps
A1: Industrial heat pumps
A2: For electricity in the "boilers" end use, we use industrial heat pumps rather than electric boilers because industrial heat pumps
A3: are more efficient and are therefore recommended over electrical boilers wherever practical.
A5: Metric | B5: Value | C5: Unit
A6: Per-kW CAPEX | B6: 600 | C6: 2024€/kW | D6: € / power draw
A7: Currency adj. EUR to USD 2024 | B7: 1.0822 | C7: 2024$/2024€
A8: Per-kW CAPEX | B8: =B6*B7 -> 649.32 | C8: 2024$/kW
A9: Annual hours | B9: 8760 | C9: hrs/yr
A10: Capacity factor | B10: =AVERAGE(5944,2503,6257,6257)/B9 -> 0.59820205 | C10: %
A11: Per-kWh/yr CAPEX | B11: =B8/(B9*B10) -> 0.12391012 | C11: 2024$/(kWh/yr) | D11: $ / electricity consumption each year
A13: Conversion factor | B13: 3412.14 | C13: BTU/kWh
A15: Per-BTU/yr CAPEX | B15: =B11/B13 -> 3.6314489e-05 | C15: 2024$/(BTU/yr) | D15: $ / electricity consumption (in BTU of electricity) each year
D16: FLAGGED — see note on B6: this assertion appears to be incorrect. The source figure is per kW of heat output, so a COP conversion IS required.
A19: Industrial fossil fuel boilers
B20: Reference capacity (kW) | C20: Overnight capital cost (USD/kW) — IRENA REmap 2030 (see About rows 17-21) | D20: Boiler cost ($) | E20: Conversion efficiency | F20: Annual Energy Input (BTU) | G20: Cost per annual energy input (2015$/(BTU/yr)) | H20: Cost per annual energy input (2024$/(BTU/yr))
A21: coal (steam boiler) | B21: 2000 | C21: 300 | D21: =B21*C21 -> 600000 | E21: 0.903 | F21: =$B$29/E21 -> 3.9902767e+10 | G21: =D21/F21 -> 1.5036551e-05 | H21: =G21*$B$30 -> 1.9888846e-05
A22: petroleum products (steam boiler) | B22: 2000 | C22: 200 | D22: =B22*C22 -> 400000 | E22: 0.892 | F22: =$B$29/E22 -> 4.0394841e+10 | G22: =D22/F22 -> 9.9022545e-06 | H22: =G22*$B$30 -> 1.3097712e-05
A23: natural gas (steam boiler) | B23: 2000 | C23: 100 | D23: =B23*C23 -> 200000 | E23: 0.857 | F23: =$B$29/E23 -> 4.2044572e+10 | G23: =D23/F23 -> 4.7568566e-06 | H23: =G23*$B$30 -> 6.2918942e-06
B25: Value | C25: Unit
A26: Annual operating hours | B26: 5280 | C26: hours / year
A27: Annual heat output | B27: =B21*B26 -> 10560000 | C27: kWh
A28: Conversion factor | B28: 3412.14 | C28: BTU/kWh
A29: Annual heat output | B29: =B27*B28 -> 36032198400 | C29: BTU
A30: 2015 to 2024 inflation adj. | B30: 1.3227 | C30: dmnl
A32: Hydrogen boiler
A34: The ARB document suggests that a hydrogen boiler under a "conservative" scenario would cost
A35: 50% more than a natural gas boiler.
A37: =H23*1.5 -> 9.4378413e-06 | B37: 2024$/(BTU/yr)
A40: NOT USED - State of Michigan 2003 reference for natural gas boiler costs
A42: Using a 400-horsepower boiler as our example:
A44: water tube boiler | B44: 80375 | C44: 2003 USD
A45: fire tube boiler | B45: 91475 | C45: 2003 USD
A46: average cost | B46: =AVERAGE(B44:B45) -> 85925 | C46: 2003 USD
A48: 2003 to 2024 inflation adj. | B48: 1.7042 | C48: dmnl
A50: average cost (inflation adjusted) | B50: =B46*B48 -> 146433.38 | C50: 2024 USD
A52: boiler horsepower | B52: 400
A53: kW / boiler horsepower | B53: 9.8095 | C53: Unit conversion ref: | D53: https://www.unitconverters.net/power/horsepower-boiler-to-kilowatt.htm
A54: kW | B54: =B52*B53 -> 3923.8
A56: Annual operating hours: | B56: 5280
A58: annual energy consumption | B58: =B54*B56 -> 20717664 | C58: kWh/year
A59: Conversion factor | B59: 3412.14 | C59: BTU/kWh
A60: annual energy consumption | B60: =B58*B59 -> 7.069157e+10 | C60: BTU/year
A62: Capital cost per BTU energy consumption
A63: =B50/B60 -> 2.0714406e-06 | B63: 2024$/(BTU/yr)
A66: NOT USED - NREL 2017 reference for natural gas boiler costs
A68: boiler cost | B68: 87540 | C68: 2016 USD | D68: NREL's report was published in 2017. We assume the currency figures are given in 2016 USD, which would have been the latest year for which inflation data were available when the NREL report was published.
A69: 2016 to 2024 inflation adj. | B69: 1.3062 | C69: dmnl
A70: boiler cost | B70: =B68*B69 -> 114344.75 | C70: 2024 USD
A72: boiler horsepower | B72: 100
A73: kW / boiler horsepower | B73: 9.8095 | C73: Unit conversion ref: | D73: https://www.unitconverters.net/power/horsepower-boiler-to-kilowatt.htm
A74: kW | B74: =B72*B73 -> 980.95
A76: Annual operating hours: | B76: 5280
A78: annual energy consumption | B78: =B74*B76 -> 5179416
A79: Conversion factor | B79: 3412.14
A80: annual energy consumption | B80: =B78*B79 -> 1.7672893e+10
A82: Capital cost per BTU energy consumption
A83: =B70/B80 -> 6.4700641e-06 | B83: 2024$/(BTU/yr)

Sheet Cooling
A1: Natural Gas-Fired Chillers
A3: Based on a 500-ton natural gas-fired absorption chiller
A5: Capital cost | B5: 307500 | C5: $
A6: Operating hours | B6: 4000 | C6: hours/yr
A8: Natural gas charges | B8: 75863 | C8: $
A9: Electricity charges (for pumps) | B9: 6226 | C9: $
A11: Natural gas rate | B11: 0.45 | C11: $/therm
A12: Electricity rate | B12: 0.15 | C12: $/kWh
A14: NG use | B14: =B8/B11 -> 168584.44 | C14: therms
A15: Electricity use | B15: =B9/B12 -> 41506.667 | C15: kWh
A17: Conversion factor | B17: 100000 | C17: BTU/therm
A18: Conversion factor | B18: 3412.14 | C18: BTU/kWh
A20: NG use | B20: =B14*B17 -> 1.6858444e+10 | C20: BTU
A21: Electricity use | B21: =B15*B18 -> 1.4162656e+08 | C21: BTU
A23: The vast majority of the energy use is natural gas. But we don't want to disregard the
A24: cost of the electricity used to power the pumps. So we sum it with natural gas.
A26: Energy use (over 99% natural gas) | B26: =SUM(B20:B21) -> 1.7000071e+10 | C26: BTU
A27: Cost per BTU consumed | B27: =B5/B26 -> 1.808816e-05 | C27: $/(BTU/yr)
A29: Electric Chiller
A31: Centrifugal chillers >400 tons
A32: Low-end capital cost | B32: 200 | C32: $/ton
A33: High-end capital cost | B33: 500 | C33: $/ton
A34: Average capital cost | B34: =AVERAGE(B32:B33) -> 350 | C34: $/ton
A36: Capacity of reference chiller | B36: 500 | C36: tons | D36: Assumed to be the same as the NG-fired chiller above
A38: Capital cost of electric chiller | B38: =B34*B36 -> 175000 | C38: $
A41: Energy intensity of centrifugal chiller 300 - 600 tons capacity | B41: 0.576 | C41: kW/ton
A42: Power of centrifugal chiller 300 - 600 tons capacity | B42: =B41*B36 -> 288 | C42: kW
A44: Operating hours | B44: =B6 -> 4000 | C44: hours/yr | D44: Assumed to be the same as the NG-fired chiller above
A46: Electricity use | B46: =B42*B44 -> 1152000 | C46: kWh
A47: Electricity use | B47: =B46*B18 -> 3930785280 | C47: BTU
A49: Cost per BTU consumed | B49: =B38/B47 -> 4.4520366e-05 | C49: $/(BTU/yr)

Sheet NB Medium Temp
A1: Commercial Ovens (used as our model for medium-temperature, non-boiler industrial heating equipment)
A3: Commercial Oven Installed Base by Equipment Type | C3: p. 42, table 2-8
A4: Oven Type | B4: Installed Base
A5: deck | B5: 492000
A6: convection (1/2) | B6: 135000
A7: convection (full) | B7: 474000
A8: combiantion | B8: 70000
A9: rotary rack | B9: 22000
A10: rorary | B10: 18000
A11: cook & hold | B11: 216000
A12: conveyor | B12: 51000
A13: dough proofer | B13: 125000
A15: Commercial oven capital cost breakdown by oven type | C15: p. 44, table 2-10
A16: Oven Type | B16: Average Cost
A17: deck | B17: 13400
A18: convection | B18: 5300
A19: proofer | B19: 13600
A21: Commercial oven use characteristics | E21: p. 45, table 2-11
A22: Fuel Type | B22: Operating Hrs/Yr | C22: Capacity (btu/hr) | D22: Capacity (kW)
A23: electric | B23: 4380 | D23: 15
A24: gas | B24: 4380 | C24: 56000
A27: Adjustment to Operating Hours per Year
A28: The operating hours per year reported in the table above are for commercial ovens.
A29: We would expect an industrial facility to operate more hours per year than a commercial bakery.
A30: For this reason, and for consistency across different industrial equipment categories in this spreadsheet,
A31: we use the number of operating hours per year from the "Boilers" tab to also represent the operating hours
A32: per year for medium-temperature industrial heating equipment.
A33: Operating hours per year: | B33: ='Boilers & Heat Pumps'!B56 -> 5280
A36: Conversion factor | B36: 3412.14 | C36: BTU/kWh
A38: Calculated energy use by fuel type
A39: Fuel Type | B39: Energy Use (btu/yr) | C39: Weighted avg CapEx | D39: CapEx/(BTU/yr)
A40: electric | B40: =$B$33*D23*B36 -> 270241488 | C40: =($B$17*$B$5+$B$18*SUM($B$6:$B$7)+$B$19*$B$13)/SUM($B$5:$B$7,$B$13) -> 9396.8189 | D40: =C40/B40 -> 3.4771933e-05
A41: gas | B41: =$B$33*C24 -> 295680000 | C41: =($B$17*$B$5+$B$18*SUM($B$6:$B$7)+$B$19*$B$13)/SUM($B$5:$B$7,$B$13) -> 9396.8189 | D41: =C41/B41 -> 3.1780367e-05
A50: For reference, not used in calculations above:
A51: Commercial oven installed base by fuel type | D51: p. 43, table 2-9
A52: Fuel type | B52: installed base | C52: Percent
A53: electric | B53: 722000 | C53: =B53/SUM($B$53:$B$54) -> 0.45012469
A54: gas | B54: 882000 | C54: =B54/SUM($B$53:$B$54) -> 0.54987531
A56: FOSSIL 200-500 °C: BOILER / DIRECT-FIRED DUTY BLEND (July 2026)
A57: Mirrors the T1 duty split in the efficiency workbooks: 55% of 200-500 °C heat is boiler-served steam, 45% direct-fired. Previously this band used a single direct-fired (oven) figure for every fossil fuel, so coal, petroleum and gas were all identical in Summary row 4 despite very different boiler costs. Boiler share source: McMillan et al. 2016 (NREL/TP-6A50-66743 / INL/EXT-16-39680) — steam boilers + CHP ≈ 70% of heat loads across the 14 most energy-intensive industries, chemicals ~40% via steam loops, pulp & paper ~70% steam; offset because ~45% of US process heat is below 200 °C and steam systems top out near 250-300 °C. Suggested range 45-65%.
A58: Fuel | B58: Boiler CAPEX $/(BTU/yr) | C58: Direct-fired CAPEX $/(BTU/yr) | D58: Blended $/(BTU/yr) | E58: vs current flat figure
A59: hard coal | B59: ='Boilers & Heat Pumps'!H21 -> 1.9888846e-05 | C59: =$D$41*$B$64 -> 4.153692e-05 | D59: =$B$63*B59+(1-$B$63)*C59 -> 2.963048e-05 | E59: =D59/$D$41-1 -> -0.067648291
A60: petroleum products | B60: ='Boilers & Heat Pumps'!H22 -> 1.3097712e-05 | C60: =$D$41*$B$64 -> 4.153692e-05 | D60: =$B$63*B60+(1-$B$63)*C60 -> 2.5895356e-05 | E60: =D60/$D$41-1 -> -0.18517758
A61: natural gas | B61: ='Boilers & Heat Pumps'!H23 -> 6.2918942e-06 | C61: =$D$41*$B$64 -> 4.153692e-05 | D61: =$B$63*B61+(1-$B$63)*C61 -> 2.2152156e-05 | E61: =D61/$D$41-1 -> -0.30296098
A63: Boiler-served share of 200-500 °C heat | B63: 0.55
A64: Commercial-oven escalation, 2016 → 2024 USD | B64: =cpi!D62/cpi!D54 -> 1.3069994
A65: SOURCE VIABILITY — read before relying on the blend above
A66: NOTE 1 (resolved) — the boiler CAPEX inputs ARE sourced: IRENA, REmap Technology and Performance Assumptions for 2030 (2016), https://www.irena.org/-/media/Irena/Files/REmap/IRENA_REmap_2030_technology_cost.xlsx — recorded on the About tab rows 17-21, which is where this workbook keeps its references. Overnight costs 300 / 200 / 100 USD per kW for coal / petroleum / gas ('Boilers & Heat Pumps' C21:C23, 2015 USD). Viable and appropriate: a published international-agency dataset on the same vintage as the file's 2015 dollar basis. Danish Energy Agency cross-check (tabs now in this workbook) broadly supports it but is not identical: '6.1 Boiler, gas and oil' = 0.09 M€/MW ≈ 97 2024$/kW against the file's ~132 2024$/kW for gas (good agreement); '6.3 Boiler, coal' = 0.565 M€/MW ≈ 611 2024$/kW against the file's ~397 (DEA ~55% higher); and DEA prices oil the same as gas whereas IRENA prices oil at twice gas. Read the IRENA values as central with DEA marking the upper end for coal — a Danish-versus-global cost-basis difference, not an error in either.
A67: FLAG 2 — the direct-fired component is a COMMERCIAL BAKERY OVEN. D41 is built from installed-base-weighted commercial oven costs (deck, convection, proofer) at 4,380 operating hours — rows 1-26 above. Note that the ELECTRIC side of this band was already migrated off this same proxy (Summary!B4's note: 'Replaces the commercial-oven figure', now an industrial resistance heater), so the fossil side is the only place the commercial-oven proxy still survives. It very likely understates industrial direct-fired equipment at 200-500 °C (fired heaters, process dryers, kilns). DEA sheet '7.1 Direct firing Natural Gas' (0.0176 M€/MW ≈ 19 2024$/kW) is NOT a substitute: DEA's direct-firing sheets cover the firing system only, excluding the process vessel (see their note F on sheet 7.3), so using it would understate by roughly an order of magnitude. A genuine industrial oven/dryer or fired-heater CAPEX is still needed.
A68: STATUS: blend built and arithmetic verified, NOT yet wired into Summary. Summary!C4, D4, E4, F4 (and the crude/HFO/LPG rows that copy them) still all point at the single flat figure D41 = 3.178E-05. Wiring D59:D61 through would differentiate the fuels correctly and reduce this band's fossil CAPEX by 21% (coal), 32% (petroleum) and 44% (natural gas). The boiler side is now confirmed sourced (NOTE 1); the remaining weakness is the commercial-oven direct-fired proxy (FLAG 2), which affects 45% of the blend.

Sheet NB High Temp
A1: Electric Arc Furnace (Electric nonboiler high temp example)
I2: Source
A3: CapEx costs: | F3: =254*1.04 -> 264.16 | G3: $/tonne | I3: DIW Berlin 2024
A4: Energy expenditure/output: | F4: 450 | G4: kWh/tonne | I4: Paeng & Azimi 2024
A5: Annual production capacity: | F5: 800000 | G5: tonnes/year | I5: Energy Transitions Commission
A7: Annual energy consumption/year (kWh): | F7: =F4*F5 -> 360000000 | G7: kWh/year
A8: Annual energy consumption/year (mmBTU): | F8: =F7*0.003412 -> 1228320 | G8: mmBTU/year
A9: CapEx costs per annual yield: | F9: =F3*F5 -> 2.11328e+08 | G9: $/year
A10: $/BTU/year | F10: =F9/(F8*10^6) -> 0.00017204637 | G10: $/BTU/year | I10: Note: since the CapEx here scales with tonnes capacity, the final cost per unit capacity isn't affected by the annual production capacity figure above.
A12: 130-180 tonnes per hour essentially means | E12: =8760*155 -> 1357800 | F12: tonnes/year.
A14: Coal-fueled cement kiln
A16: Cement plant (whole plant) capital cost per unit capacity | F16: 170 | G16: $/ton cement annual production capacity
F17: =F16/F23 -> 26.356589 | G17: $/(GJ/yr)
F18: =F17/277.778 -> 0.094883645 | G18: $/(kWh/yr)
F19: =F18/3412 -> 2.7808806e-05 | G19: $/(BTU/yr) | I19: Not used because it is the whole plant, not just the kiln. Kiln-only data are just below.
A21: Kiln capital cost | F21: 36000000 | G21: RMB | I21: China Ruibin Information Network article
A22: Kiln capital cost | F22: =F21*0.14 -> 5040000 | G22: $
A23: Energy expenditure/output | F23: =AVERAGE(5.1,7.8) -> 6.45 | G23: GJ/tonne | I23: Average for rotary kiln, CemZero study
A24: Annual hours of operation: | F24: 8000 | G24: hours/year | I24: CemZero study
A25: Daily production capacity | F25: 600 | G25: tons/day | I25: China Ruibin Information Network article
F26: =F23*F25 -> 3870 | G26: GJ/day
F27: =F26*(F24/24) -> 1290000 | G27: GJ/year
A28: Annual energy consumption/year (kWh): | F28: =F27*277.778 -> 3.5833362e+08 | G28: kWh/year | I28: includes conversion factor for GJ to kWh (1:277.778)
A29: Annual energy consumption/year (mmBTU): | F29: =F28*0.003412 -> 1222634.3 | G29: mmBTU/year
A30: $/BTU/year | F30: =(F21*0.14)/(F29*10^6) -> 4.1222465e-06 | G30: $/BTU/year | I30: includes RMB to USD conversion (1:0.14)
A32: Since these are Chinese prices, we double-checked using prices from Europe. They come out about the same:
A34: CapEx of cement kiln witout CCS | F34: 21.08 | G34: 2014 euros / ton clinker (annual capacity) | I34: https://www.researchgate.net/publication/330875028_Techno-economic_analysis_of_calcium_looping_processes_for_low_CO_2_emission_cement_plants
A35: Average share of clinker in cement (global average) | F35: 0.76 | G35: % | I35: https://www.wri.org/insights/lower-carbon-blended-cement#:~:text=U.S.%20cement%20produces%20more%20emissions,is%20between%200.64%20and%200.76.
A36: CapEx of cement kiln witout CCS | F36: =F34*F35 -> 16.0208 | G36: 2014 euros / ton cement (annual capacity)
F37: 1.3284 | G37: 2014 USD / 2014 euro
F38: =F36*F37 -> 21.282031 | G38: 2014 USD / ton cement (annual capacity)
F39: 1.32 | G39: 2024 USD / 2014 USD
F40: =F38*F39 -> 28.092281 | G40: 2024 USD / ton cement (annual capacity)
F41: =F40/F23 -> 4.3553923 | G41: 2024 USD / (GJ/yr)
F42: 277.778 | G42: kWh / GJ
F43: =F41/F42 -> 0.0156794 | G43: USD / (kWh/yr)
F44: 3412.14 | G44: BTU / kWh
F45: =F43/F44 -> 4.5951807e-06 | G45: USD / (BTU/yr)
A47: Natural Gas-fueled Glass Melting Furnace (NG nonboiler high temp example)
A49: Furnace capital cost | F49: 6000000 | G49: ₤ | I49: Glass Technology Services Ltd.
A50: Output rate | F50: 300 | G50: tonnes glass/day | I50: Glass Technology Services Ltd.
A51: Annual hours of operation (operates continuously): | F51: 8760 | G51: hrs/year | I51: Glass Technology Services Ltd.
A52: Energy expenditure/output | F52: 1100 | G52: kWh/tonne | I52: Glass Technology Services Ltd.
A54: Annual energy consumption/year (kWh): | F54: =(F3*365)*F52 -> 1.0606024e+08 | G54: kWh/year
A55: Annual energy consumption/year (mmBTU): | F55: =F54*0.003412 -> 361877.54 | G55: mmBTU/year
A56: $/BTU/year | F56: =(F49*1.25)/(F55*10^6) -> 2.0725243e-05 | G56: $/BTU/year
A58: Hydrogen-DR Plant (does not include EAF) (hydrogen high temp example)
A60: CapEx costs: | F60: =574-184 -> 390 | G60: €/ton
A61: Energy expenditure/output: | F61: 3500 | G61: kWh/ton | I61: Rechberger et al. 2020
A62: Annual production capacity: | F62: 1500000 | G62: tons/year | I62: Vogl et al. 2018
A64: Annual energy consumption/year (kWh): | F64: =F61*F62 -> 5250000000 | G64: kWh/year
A65: Annual energy consumption/year (mmBTU): | F65: =F64*0.003412 -> 17913000 | G65: mmBTU/year
A66: CapEx costs per annual yield: | F66: =F60*F62 -> 585000000 | G66: $/year
A67: $/BTU/year | F67: =F66/(F65*10^6) -> 3.2657846e-05 | G67: $/BTU/year
A70: Electric Resistance Heater (electric non-arc example for medium/high-temp process heat, ~200-1000 C)
A71: CAPEX | F71: 238 | G71: k€/MW (= €/kW) | I71: arXiv:2503.02008, Suppl. Table (Baumgärtner et al.)
A72: EUR to USD 2024 | F72: ='Boilers & Heat Pumps'!B7 -> 1.0822 | G72: 2024$/2024€
A73: CAPEX | F73: =F71*F72 -> 257.5636 | G73: 2024$/kW
A74: Annual full-load hours | F74: ='Boilers & Heat Pumps'!B9*'Boilers & Heat Pumps'!B10 -> 5240.25 | G74: hrs/yr (8760 × capacity factor) | I74: Uses same utilization as other electrified heating in this workbook (Boilers tab)
A75: Per-kWh/yr CAPEX | F75: =F73/F74 -> 0.049151014 | G75: 2024$/(kWh/yr)
A76: Conversion factor | F76: ='Boilers & Heat Pumps'!B13 -> 3412.14 | G76: BTU/kWh
A77: Per-BTU/yr CAPEX | F77: =F75/F76 -> 1.4404747e-05 | G77: 2024$/(BTU/yr)
A80: ELECTRIC TECHNOLOGY-BLEND CAPEX, 200-1000 °C (July 2026) — mirrors the technology mix in the efficiency workbooks
A81: All CAPEX below is per kW of ELECTRICAL INPUT capacity, consistent with this workbook's construction: $/kW ÷ annual full-load hours ÷ BTU per kWh = $/(BTU of electricity per year). The efficiency revision in the start-year and minimum-UEF files therefore needs NO manual adjustment here — the EPS multiplies this by annual energy use, which already rose with the revised unit energy factors, so total equipment cost scales correctly.
A83: Technology | B83: CAPEX | C83: Unit | D83: Share, 200-500 °C | E83: Share, 500-1000 °C | F83: Source
A84: Electric boiler (electrode / resistance, steam) | B84: =175*(About!$C$133/About!$C$130)*$F$72 -> 232.37381 | C84: 2024$/kW-electric | D84: 0.55 | E84: 0 | F84: Agora Energiewende (2019) mean €175/kW — 'Agora' tab row 95; DEA '5.1b' retained as low bound
A85: Electric resistance heater / oven / furnace | B85: =F73 -> 257.5636 | C85: 2024$/kW-electric | D85: 0.3 | E85: 0.55 | F85: Reinert et al. 2025 (arXiv:2503.02008) Suppl. Table, from Baumgärtner et al.: 238 k€/MW — already in row 71 above
A86: Induction heating / melting (incl. power supply) | B86: =B103 -> 365.3899 | C86: 2024$/kW-electric | D86: 0.05 | E86: 0.4 | F86: EPRI 1987 (and EPRI Table B-46) — derivation at rows 98-104
A87: Electric infrared (emitters + controls) | B87: =Other!E3/Other!E4 -> 157.81889 | C87: 2024$/kW-electric | D87: 0.1 | E87: 0.05 | F87: Existing workbook figure — 'Other'!E3/E4 (industrial IR vendor quote)
A88: Share check (must equal 100%) | D88: =SUM(D84:D87) -> 1 | E88: =SUM(E84:E87) -> 1
A89: Cross-check — DEA direct electric firing (alternative to the resistance-heater figure in B85) | B89: =0.07*1000*$F$72 -> 75.754 | C89: 2024$/kW-electric (low-end bound)
A90: Blended CAPEX, 200-500 °C | B90: =SUMPRODUCT($B$84:$B$87,D84:D87) -> 239.12606 | C90: 2024$/kW-electric
A91: Blended CAPEX, 500-1000 °C | B91: =SUMPRODUCT($B$84:$B$87,E84:E87) -> 295.70689 | C91: 2024$/kW-electric
A93: Blended per-BTU/yr CAPEX, 200-500 °C | B93: =B90/$F$74/$F$76 -> 1.3373592e-05 | C93: 2024$/(BTU/yr)
A94: Blended per-BTU/yr CAPEX, 500-1000 °C | B94: =B91/$F$74/$F$76 -> 1.6537985e-05 | C94: 2024$/(BTU/yr)
A96: STATUS: scaffold complete and arithmetic verified; NOT yet wired into the Summary tab. Summary!B4 and B5 still point at the flat resistance-heater figure (F77 = 1.440E-05). Wire B93 and B94 through only after the electric-boiler, induction and infrared CAPEX values are sourced — leaving them blank would silently understate the blend. Note also that Summary!B4 and B5 are currently IDENTICAL, which is no longer consistent with the two different technology mixes.
A98: Induction heating/melting CAPEX derivation (EPRI 1987, deflated) — feeds B86
A99: Capital cost per furnace (1987 USD) | B99: 600000
A100: Annual electricity consumption per furnace (kWh/yr) | B100: 12000000
A101: CAPEX per annual kWh (1987 USD) | B101: =B99/B100 -> 0.05
A102: CAPEX per annual kWh (2024 USD) — CENTRAL, treating the figure as 2011 USD | B102: =B101*About!$C$132/About!$C$130 -> 0.069727571
A103: Equivalent CAPEX per kW-electric (2024 USD, at this workbook's full-load hours) | B103: =B102*$F$74 -> 365.3899
A104: Modern market cross-check (not used): new 1-tonne induction melters quote roughly $25,000-50,000 from Chinese manufacturers, typically paired with a 500-750 kW supply — very roughly $40-100/kW. Western OEM systems (Inductotherm, Ajax Tocco, Pillar) are commonly cited at 2-4x that once installation, cooling and harmonics mitigation are included, i.e. ~$80-400/kW, but that multiplier is anecdotal rather than published. This suggests the EPRI-derived figure sits at or above the top of today's market — unsurprising, since 1987 induction supplies were motor-generator/thyristor sets, whereas modern solid-state IGBT supplies are substantially cheaper in real terms. EPRI is retained as central because it is the only published, citable US figure and matches this workbook's sourcing standard; treat the modern range as the low-end sensitivity.
A105: Upper bound — same figure read as 1987 USD (not used) | B105: =B101*About!$C$131/About!$C$130*$F$74 -> 723.50739 | C105: 2024$/kW-electric (upper bound)
A106: SCALE AND INSTALLATION JUDGMENTS (decided July 2026, analyst's call): representative duties of 20 MW for the 500-1000 °C fired heater and 50 MW for the >1000 °C reheat furnace, and a bare-module factor of 2.2 throughout. Rationale — refinery and petrochemical fired heaters commonly run 10-50 MW and the 500-1000 °C band also contains smaller chemical, food and dryer duty, so 20 MW is a fair central; steel reheat furnaces run 20-100 MW, so 50 MW is central for that band and correctly places reheat at a lower unit cost than the smaller fired heater. The 2.2 bare-module factor is Turton's own value for fired heaters in carbon steel at near-atmospheric pressure, and is required because every other exemplar in this workbook is an installed rather than purchased cost. SENSITIVITY: duty spans roughly 2x on these curves and the bare-module factor spans 2.0-2.5, so the combined uncertainty on both Turton-derived exemplars is roughly 3x. They drive the 500-1000 °C gas figure and about two-thirds of the >1000 °C blend.
A107: GAS FIRED HEATER, 500-1000 °C (Turton et al.) — replaces the glass-furnace proxy for this band
A108: Exemplar selected: NON-REACTIVE FIRED HEATER from the Turton purchased-cost chart (see 'Turton' tab). This is the correct duty for the 500-1000 °C band, which the efficiency workbooks show is dominated by chemicals and refining fired heaters (process fluid heated without reaction) plus metal reheat. The chart's Reformer and Pyrolysis Furnace curves are reactive high-temperature units (steam reforming ~800-900 °C, steam cracking ~850 °C) and sit in the >1000 °C population instead; its Steam Boiler and Hot Water Heater curves are boiler duty already covered on the 'Boilers & Heat Pumps' tab.
A109: Representative duty | B109: 20000 | C109: kW duty
A110: Purchased cost per unit duty, read from chart at that duty | B110: 70 | C110: 2001$/kW duty (purchased)
A111: CEPCI escalation, Sept 2001 to 2024 | B111: =800/397 -> 2.0151134
A112: Bare-module (installation) factor | B112: 2.2
A113: Installed cost per unit duty | B113: =B110*B111*B112 -> 310.32746 | C113: 2024$/kW duty (installed)
A114: Delivered efficiency, 500-1000 °C — coal / petroleum / natural gas | B114: 0.5027 | C114: 0.5529 | D114: 0.5781
A115: Installed cost per unit fuel input — coal / petroleum / natural gas | B115: =$B$113/B114 -> 617.32138 | C115: =$B$113/$C$114 -> 561.2723 | D115: =$B$113/D114 -> 536.80584
A116: Annual operating hours | B116: 8760 | C116: hrs/yr
A117: Fired heater CAPEX per annual fuel BTU, 500-1000 °C — coal / petroleum / natural gas | B117: =B115/$B$116/$F$76 -> 2.0652868e-05 | C117: =$C$115/$B$116/$F$76 -> 1.8777712e-05 | D117: =D115/$B$116/$F$76 -> 1.7959171e-05
A118: Cross-check: gas value versus the glass-furnace figure it replaces | B118: =D117/F56-1 -> -0.13346392
A120: REHEAT / METAL-HEATING FURNACE, >1000 °C (Turton, non-reactive fired heater read at reheat scale)
A121: PROXY, documented: the Turton chart's lower panel is titled 'Furnace' and its Non-Reactive Fired Heater curve is therefore a fired-furnace cost, not a fluid-heater-only cost. Read at steel reheat scale it stands in for reheat, annealing and metal-melting furnaces. Its Reformer and Pyrolysis Furnace curves are NOT used: in this model's temperature profile, chemicals and refining have zero heat above 1000 °C, so reactive chemical furnaces do not appear in this band. SOURCE SEARCH CLOSED (July 2026): LBNL-4779E, 'Energy Efficiency Improvement and Cost Saving Opportunities for the U.S. Iron and Steel Industry' (Worrell et al.), was checked and does NOT contain a whole-furnace capital cost — it reports retrofit measure costs only (turbulators $10-15 per boiler tube, ladle heaters $70,000, Tundish heater-dryer $45,000, EAF transformer retrofit $1.1M) and discusses walking-beam furnaces only qualitatively. Retrofit measure costs are not substitutable for equipment capital cost, so the Turton proxy is retained.
A122: Representative duty | B122: 50000 | C122: kW duty
...

Sheet Machine Drive
A1: Electric Motors
A2: Equipment CapEx cost derived from the AssessCCUS's Capital Equipment Cost Database's equation, based on data from Woods 2007 (see sources in About):
A3: Equipment cost = minimum equipment cost * (desired equipment scale value / minimum equipment scale value)scaling factor * (current CEPCI / listed CEPCI); 2024 CEPCI is ~800
A4: To derive Annual BTU, motor operating hours are based on the equivalent horsepower (HP) bin from the U.S. Industrial Electric Motor Systems Market Opportunities Assessment (2002). kWh are converted to mmBTU with a conversion factor of 0.003412, then multiplied by annual operating hours.
A5: Bins represented in the data by horsepower (HP) are 1-5, 6-20, 21-50,101-200,1000+. Not represented are 51-100 (12.7% of motor energy use), 201-500 (15.8%), 501-1000 (13.4%). Weighted averages thus take % of motor energy use in a given HP bin and divide by the remaining 58.1%. Weighted averages also average the energy values within a bin (e.g., averaging $/BTU/yr across all equipment in the 101-200 HP bin).
A6: The example gas diesel engine is assumed to be in operation the simple average annual operating hours (5267) of other motors/machine drives.
B8: Equipment Name | C8: Scaling Unit | D8: Min Scale | E8: Max Scale | F8: Min Cost | G8: Max Cost | H8: Scaling Factor | I8: CEPCI | J8: kW (scale average) | L8: equiv. HP | N8: Capital Cost (USD) | P8: Annual Operating Hrs | R8: % Distr. by Energy Use of Motor HP Category | T8: Annual energy use (MMbtu) | W8: $/BTU/yr
B9: Electric motor: induction, squirrel cage, 3 phase, AC, TEFC, 1800 rpm excluding starter, gearing | C9: kW | D9: 0.3 | E9: 1500 | F9: 43.754184 | G9: 512727.48 | H9: 1.1 | I9: 1000 | J9: =AVERAGE(D9,E9) -> 750.15 | L9: =J9*1.34102 -> 1005.9662 | N9: =F9*(((D9+E9)/2)/D9)^H9*(800/I9) -> 191398.76 | P9: 7436 | R9: =0.157/0.581 -> 0.27022375 | T9: =J9*0.003412*P9 -> 19032.53 | W9: =N9/(T9*10^6) -> 1.0056402e-05
B10: Electric motor: induction, wound rotor, 3 phase, AC, open drip proof, 1800 rpm, excluding starter | C10: kW | D10: 8 | E10: 150 | F10: 1455.1963 | G10: 22223.515 | H10: 0.93 | I10: 1000 | J10: =AVERAGE(D10,E10) -> 79 | L10: =J10*1.34102 -> 105.94058 | N10: =F10*(((D10+E10)/2)/D10)^H10*(800/I10) -> 9793.3452 | P10: 4174 | R10: =0.144/0.581 -> 0.24784854 | T10: =J10*0.003412*P10 -> 1125.0934 | W10: =N10/(T10*10^6) -> 8.7044735e-06
B11: Electric motor: synchronous, AC open drip proof, 1800 rpm excluding gears | C11: kW | D11: 350 | E11: 7000 | F11: 64088.852 | G11: 1137028.3 | H11: 0.96 | I11: 1000 | J11: =AVERAGE(D11,E11) -> 3675 | L11: =J11*1.34102 -> 4928.2485 | N11: =F11*(((D11+E11)/2)/D11)^H11*(800/I11) -> 490020.45 | P11: 7436 | R11: =0.157/0.581 -> 0.27022375 | T11: =J11*0.003412*P11 -> 93240.748 | W11: =N11/(T11*10^6) -> 5.2554325e-06
B12: Electric motor: synchronous, open drip proof, AC, 1200 rpm excluding gears | C12: kW | D12: 500 | E12: 7000 | F12: 77307.967 | G12: 655523.04 | H12: 0.81 | I12: 1000 | J12: =AVERAGE(D12,E12) -> 3750 | L12: =J12*1.34102 -> 5028.825 | N12: =F12*(((D12+E12)/2)/D12)^H12*(800/I12) -> 316310.69 | P12: 7436 | R12: =0.157/0.581 -> 0.27022375 | T12: =J12*0.003412*P12 -> 95143.62 | W12: =N12/(T12*10^6) -> 3.3245601e-06
B13: Electric motor: gear reduced TEFC, 1800 rpm plus gear reducer to give fixed output rpm | C13: kW | D13: 0.35 | E13: 1.8 | F13: 1297.2737 | G13: 1800 | H13: 0.2 | I13: 1000 | J13: =AVERAGE(D13,E13) -> 1.075 | L13: =J13*1.34102 -> 1.4415965 | N13: =F13*(((D13+E13)/2)/D13)^H13*(800/I13) -> 1298.9418 | P13: 2745 | R13: =0.048/0.581 -> 0.082616179 | T13: =J13*0.003412*P13 -> 10.068385 | W13: =N13/(T13*10^6) -> 0.00012901192
B14: Electric motor: gear reduced TEFC, 1800 rpm plus gear reducer to give fixed output rpm | C14: kW | D14: 1.8 | E14: 15 | F14: 1800 | G14: 5537.407 | H14: 0.53 | I14: 1000 | J14: =AVERAGE(D14,E14) -> 8.4 | L14: =J14*1.34102 -> 11.264568 | N14: =F14*(((D14+E14)/2)/D14)^H14*(800/I14) -> 3257.8875 | P14: 3391 | R14: =0.104/0.581 -> 0.17900172 | T14: =J14*0.003412*P14 -> 97.188773 | W14: =N14/(T14*10^6) -> 3.3521233e-05
B15: Electric motor: variable speed TEFC, 1800 rpm plus V-belt unit for speed control 2/1 to 5/1 at 3480, 520 and 30 rpm | C15: kW (at 1800 rpm) | D15: 0.35 | E15: 7.5 | F15: 3198.2717 | G15: 22051.65 | H15: 0.63 | I15: 1000 | J15: =AVERAGE(D15,E15) -> 3.925 | L15: =J15*1.34102 -> 5.2635035 | N15: =F15*(((D15+E15)/2)/D15)^H15*(800/I15) -> 11731.714 | P15: 2745 | R15: =0.048/0.581 -> 0.082616179 | T15: =J15*0.003412*P15 -> 36.761315 | W15: =N15/(T15*10^6) -> 0.00031913206
B16: Drive: gear unit, general, single, double, triple reduction on concentric, offset or vertical right angle drives, excluding lubrication system and motor | C16: kW (w/ reduction ratio) | D16: 3 | E16: 50 | F16: 1691.6843 | G16: 6000 | H16: 0.45 | I16: 1000 | J16: =AVERAGE(D16,E16) -> 26.5 | L16: =J16*1.34102 -> 35.53703 | N16: =F16*(((D16+E16)/2)/D16)^H16*(800/I16) -> 3607.1598 | P16: 3530 | R16: =0.127/0.581 -> 0.21858864 | T16: =J16*0.003412*P16 -> 319.17554 | W16: =N16/(T16*10^6) -> 1.1301492e-05
B17: Drive: gear unit, general, single, double, triple reduction on concentric, offset or vertical right angle drives, excluding lubrication system and motor (large) | C17: kW (w/ reduction ratio) | D17: 50 | E17: 1500 | F17: 6000 | G17: 76911.661 | H17: 0.75 | I17: 1000 | J17: =AVERAGE(D17,E17) -> 775 | L17: =J17*1.34102 -> 1039.2905 | N17: =F17*(((D17+E17)/2)/D17)^H17*(800/I17) -> 37496.438 | P17: 7436 | R17: =0.157/0.581 -> 0.27022375 | T17: =J17*0.003412*P17 -> 19663.015 | W17: =N17/(T17*10^6) -> 1.9069526e-06
B18: Drive: gear unit, medium duty, single reduction 20/1 to 50/1 excluding lubrication system and motor (large) | C18: kW (w/ reduction ratio) | D18: 3 | E18: 180 | F18: 580.86364 | G18: 5300 | H18: 0.54 | I18: 1000 | J18: =AVERAGE(D18,E18) -> 91.5 | L18: =J18*1.34102 -> 122.70333 | N18: =F18*(((D18+E18)/2)/D18)^H18*(800/I18) -> 2942.2942 | P18: 4174 | R18: =0.144/0.581 -> 0.24784854 | T18: =J18*0.003412*P18 -> 1303.1145 | W18: =N18/(T18*10^6) -> 2.2578939e-06
B19: Drive: gear unit, medium duty, single reduction 20/1 to 50/1 excluding lubrication system and motor (large) | C19: kW (w/ reduction ratio) | D19: 180 | E19: 1500 | F19: 5300 | G19: 297736.1 | H19: 1.9 | I19: 1000 | J19: =AVERAGE(D19,E19) -> 840 | L19: =J19*1.34102 -> 1126.4568 | N19: =F19*(((D19+E19)/2)/D19)^H19*(800/I19) -> 79155.071 | P19: 7436 | R19: =0.157/0.581 -> 0.27022375 | T19: =J19*0.003412*P19 -> 21312.171 | W19: =N19/(T19*10^6) -> 3.7140783e-06
B21: Simple Average for electric motors/drive units: | T21: =AVERAGE(T9:T19) -> 22843.953 | W21: =AVERAGE(W9:W19) -> 4.8016955e-05
B22: Weighted Average (by distribution of energy use) for electric motors/drive units (see below for breakdown): | T22: =SUMPRODUCT(F24:F28, I24:I28) -> 13814.302 | W22: =SUMPRODUCT(F24:F28, N24:N28) -> 2.9652198e-05
C23: Representative Horsepower Bin | F23: % Distr. by Energy Use Per HP Bin | I23: Average Annual Energy Use by HP Bin (MMbtu) | N23: $/BTU/yr
C24: 1-5 | F24: =0.048/0.581 -> 0.082616179 | I24: =((T13+T15)/2) -> 23.41485 | N24: =((W13+W15)/2) -> 0.00022407199
C25: 6-20 | F25: =0.104/0.581 -> 0.17900172 | I25: =T14 -> 97.188773 | N25: =W14 -> 3.3521233e-05
C26: 21-50 | F26: =0.127/0.581 -> 0.21858864 | I26: =T16 -> 319.17554 | N26: =W16 -> 1.1301492e-05
C27: 101-200 | F27: =0.144/0.581 -> 0.24784854 | I27: =((T10+T18)/2) -> 1214.1039 | N27: =((W10+W18)/2) -> 5.4811837e-06
C28: 1000+ | F28: =0.157/0.581 -> 0.27022375 | I28: =((T9+T11+T12+T17+T19)/5) -> 49678.417 | N28: =((W9+W11+W12+W17+W19)/5) -> 4.851485e-06
A31: Gas Diesel Engine
G32: Source
B33: Capital expenditures | D33: 502 | E33: $/kW | G33: Rockefeller Foundation: Electrifying Economies: Detailed Cost Models and Benchmarks
B34: Representative engine bhp | D34: 250 | E34: bhp | G34: EPA General Conformity Training Modules: Appendix A Sample Emissions Calculations
B35: Representative engine kW | D35: =D34/1.341 -> 186.42804 | E35: kW
B36: Representative annual operating hours | D36: 2080 | E36: hrs/year | G36: EPA General Conformity Training Modules: Appendix A Sample Emissions Calculations
B37: Annual energy consumed (MMbtu) | D37: =D35*0.003412*D36 -> 1323.0723 | E37: Mmbtu
B38: $/BTU | D38: =(D33*D35)/(D37*10^6) -> 7.0734512e-05 | E38: $/BTU

Sheet Electrochemical
A1: Hydrogen Electrolyzers
A2: Based on DoE "Pathways to Commercial Liftoff: Clean Hydrogen" p.13 CAPEX costs
A3: China capex costs based on Wang et al. 2023
A5: Alkaline Water Electrolysis
A6: Capital expenditures (U.S./Western markets) | D6: =AVERAGE(760,1000) -> 880 | E6: $/kW
A7: Capital expenditures (China): | D7: =AVERAGE(373.1,597) -> 485.05 | E7: $/kW
A9: Proton Exchange Membrane Electrolyzer
A11: Capital expenditures (U.S./Western markets): | D11: =AVERAGE(975,1200) -> 1087.5 | E11: $/kW
A12: Capital expenditures (China): | D12: =AVERAGE(1492.5,2238.8) -> 1865.65 | E12: $/kW
A14: DOE Electrolyzer Capacity Example Case (p.88):
A15: Average size | D15: 1.5 | E15: GW/yr
A16: Average total operating capacity (first 3 years) | D16: 70 | E16: %
A18: Capex for AWE electrolyzer at 1.5 GW capacity (US): | G18: =(D6)*(1.5*1000000) -> 1320000000
A19: Energy use in kWh/year: | G19: =(1.5*1000000)*(0.7*8760) -> 9198000000
A20: Energy use in BTU/year | G20: =G19*3412 -> 31383576000000
A21: $/BTU/yr (US) | G21: =G18/G20 -> 4.2060216e-05
A22: $/BTU/yr (China) | G22: =(D7*(1.5*1000000))/G20 -> 2.3183305e-05
A24: Capex for PEM electrolyzer at 1.5 GW capacity (US): | G24: =(D11)*(1.5*1000000) -> 1631250000
A25: Energy use in kWh/year: | G25: =(1.5*1000000)*(0.7*8760) -> 9198000000
A26: Energy use in BTU/year | G26: =G25*3412 -> 31383576000000
A27: $/BTU/yr (US) | G27: =G24/G26 -> 5.1977824e-05
A28: $/BTU/yr (China) | G28: =(D12*(1.5*1000000))/G26 -> 8.9170049e-05
A30: DOE report cites potential penetrance of PEM of 25% of the U.S. market by 2030
A32: U.S. Weighted CapEx/BTU/yr: | G32: =(G21*0.75)+(G27*0.25) -> 4.4539618e-05
A33: DOE projected capex cost reduction by 2030: | G33: =G32*0.6 -> 2.6723771e-05
A35: China Data with US Weighted CapEx/BTU/yr: | G35: =(G22*0.75)+(G28*0.25) -> 3.9679991e-05

Sheet Lighting
A1: https://www.bulkofficesupply.com/Categories/Janitorial-and-Facility-Supplies/Lighting/Light-Bulbs.aspx?srsltid=AfmBOorWkgJMp4H4zdZKPjbhWJ39KPaQWfcg1JIX1YpF1EunQjEtuY1Z | P1: lightstoreusa.com
C3: incand | D3: LED | E3: LED | F3: LED | G3: LED | H3: LED | I3: LED | J3: LED | K3: fluorescent | L3: fluorescent | M3: fluorescent | N3: CFL | O3: CFL | P3: HID | Q3: HID | R3: HID | S3: HID | T3: HID
C4: bulb | D4: parabolic | E4: reflector | F4: parabolic | G4: parabolic | H4: bulb | I4: tube | J4: tube | K4: twin tube | L4: tube | M4: tube | N4: bulb | O4: bulb | P4: bulb | Q4: bulb | R4: bulb | S4: floodlight | T4: floodlight
C5: Satco A15 Appliance Light Bulb | D5: Satco 6.5W PAR 20/FL 3000K LED Bulb | E5: Satco 7.5W BR30 3000K LED Bulb | F5: Satco 12W PAR 30/LN/FL 3000K LED Bulb | G5: Satco 15W PAR38 3000K LED Bulb | H5: Satco 10W A19 LED 5000K Light Bulbs | I5: Satco 40W T8 4000K LED Tube Light | J5: Satco 11 Watt LED T8 Bulb | K5: Satco 13W GX23 Pin-Based 2700K Compact Fluorescent Bulb | L5: Satco 54W T5 3500K Fluorescent Tube | M5: Satco Flourescent Light Bulbs 32W 6/box | N5: Satco 23W T2 2700K Spiral CFL Bulb | O5: Satco 23W T2 2700K Spiral CFL Bulb | P5: Plusrite 1035 | Q5: M47 BT37 Mogul | R5: Plusrite 1056 | S5: Plusrite 1061 | T5: PLUSRITE Par 38
B6: $ | C6: 1.3 | D6: 5.15 | E6: 7.48 | F6: 8.3 | G6: 11.84 | H6: =12.98/4 -> 3.245 | I6: =124.94/10 -> 12.494 | J6: =172.75/25 -> 6.91 | K6: =5.21 -> 5.21 | L6: =206.09/40 -> 5.15225 | M6: =28.85/6 -> 4.8083333 | N6: =16.57/3 -> 5.5233333 | O6: =198.86/12/3 -> 5.5238889 | P6: 15.99 | Q6: 27.95 | R6: 39.95 | S6: 17 | T6: 12 | W6: $
B7: W | C7: 40 | D7: 6.5 | E7: 7.5 | F7: 12 | G7: 15 | H7: 10 | I7: 40 | J7: 11 | K7: 13 | L7: 54 | M7: 32 | N7: 23 | O7: 23 | P7: 100 | Q7: 1000 | R7: 1000 | S7: 70 | T7: 100
B8: lm | C8: 225 | D8: 520 | E8: 650 | F8: 1000 | G8: 1200 | H8: 800 | I8: 5500 | J8: 1800 | K8: 800 | L8: 5000 | M8: 3050 | N8: 1600 | O8: 1600 | P8: 8500 | Q8: 110000
B9: hr life | C9: 2500 | D9: 25000 | E9: 25000 | F9: 25000 | G9: 25000 | H9: 15000 | I9: 50000 | J9: 50000 | K9: 12000 | L9: 24000 | M9: 24000 | N9: 12000 | O9: 12000 | P9: 15000 | Q9: 10000 | R9: 5000 | S9: 6000
B10: W equiv. incandesc. | D10: 50 | E10: 65 | F10: 75 | G10: 90 | H10: 60 | I10: 59 | J10: ? | N10: 100 | O10: 100
C11: =C6/C7 -> 0.0325 | D11: =D6/D7 -> 0.79230769 | E11: =E6/E7 -> 0.99733333 | F11: =F6/F7 -> 0.69166667 | G11: =G6/G7 -> 0.78933333 | H11: =H6/H7 -> 0.3245 | I11: =I6/I7 -> 0.31235 | J11: =J6/J7 -> 0.62818182 | ... T11: =T6/T7 -> 0.12
H13: https://www.mordorintelligence.com/industry-reports/industrial-lighting-market
C14: $ | D14: lifetime | E14: BTU/yr | F14: W | H14: Industrial lighting market
B15: incand | C15: =AVERAGEIFS($C$6:$T$6,$C$3:$T$3,$B15) -> 1.3 | D15: =AVERAGEIFS($C$9:$T$9,$C$3:$T$3,$B15) -> 2500 | E15: =AVERAGEIFS($C$7:$T$7,$C$3:$T$3,$B15)*$O$19/1000*$O$21 -> 377565.42 | F15: =AVERAGEIFS($C$7:$T$7,$C$3:$T$3,$B15) -> 40 | H15: LED | I15: 0.652 | J15: =I15*D16 -> 20025.714 | K15: =I15*E16 -> 89677.181 | L15: =C16*I15 -> 5.161884 | M15: =I15*F16 -> 9.5005714
B16: LED | C16: =AVERAGEIFS($C$6:$T$6,$C$3:$T$3,$B16) -> 7.917 | D16: =AVERAGEIFS($C$9:$T$9,$C$3:$T$3,$B16) -> 30714.286 | E16: =AVERAGEIFS($C$7:$T$7,$C$3:$T$3,$B16)*$O$19/1000*$O$21 -> 137541.69 | F16: =AVERAGEIFS($C$7:$T$7,$C$3:$T$3,$B16) -> 14.571429 | H16: Fluorescent | I16: 0.1365 | J16: =I16*D17 -> 2730 | K16: =I16*E17 -> 42518.586 | L16: =I16*C17 -> 0.69026154 | M16: =I16*F17 -> 4.5045 | O16: assumed lighting lifetime (IESD)
B17: fluorescent | C17: =AVERAGEIFS($C$6:$T$6,$C$3:$T$3,$B17) -> 5.0568611 | D17: =AVERAGEIFS($C$9:$T$9,$C$3:$T$3,$B17) -> 20000 | E17: =AVERAGEIFS($C$7:$T$7,$C$3:$T$3,$B17)*$O$19/1000*$O$21 -> 311491.47 | F17: =AVERAGEIFS($C$7:$T$7,$C$3:$T$3,$B17) -> 33 | H17: HID fixtures | I17: 0.2005 | J17: =I17*D19 -> 1804.5 | K17: =I17*E19 -> 859216.19 | L17: =I17*C19 -> 4.526889 | M17: =I17*F19 -> 91.027 | O17: 9 | P17: years
B18: CFL | C18: =AVERAGEIFS($C$6:$T$6,$C$3:$T$3,$B18) -> 5.5236111 | D18: =AVERAGEIFS($C$9:$T$9,$C$3:$T$3,$B18) -> 12000 | E18: =AVERAGEIFS($C$7:$T$7,$C$3:$T$3,$B18)*$O$19/1000*$O$21 -> 217100.12 | F18: =AVERAGEIFS($C$7:$T$7,$C$3:$T$3,$B18) -> 23 | H18: OLED | I18: 0.011 | J18: =I18*D16 -> 337.85714 | K18: =I18*E16 -> 1512.9586 | L18: =I18*C16 -> 0.087087 | M18: =I18*F16 -> 0.16028571
B19: HID | C19: =AVERAGEIFS($C$6:$T$6,$C$3:$T$3,$B19) -> 22.578 | D19: =AVERAGEIFS($C$9:$T$9,$C$3:$T$3,$B19) -> 9000 | E19: =AVERAGEIFS($C$7:$T$7,$C$3:$T$3,$B19)*$O$19/1000*$O$21 -> 4285367.5 | F19: =AVERAGEIFS($C$7:$T$7,$C$3:$T$3,$B19) -> 454 | J19: =SUM(J15:J18) -> 24898.071 | K19: =SUM(K15:K18) -> 992924.92 | L19: =SUM(L15:L18) -> 10.466122 | M19: =SUM(M15:M18) -> 105.19236 | O19: =J19/9 -> 2766.4524 | P19: hours/yr use
J20: hour life | K20: BTU/yr | L20: $ | M20: W
O21: 3412 | P21: BTU/kWh
O23: =L19/K19 -> 1.0540698e-05 | P23: $/(BTU/yr)
B24: Lighting is generally electric. Other fuels can be used to power a generator to power lighting.
B25: So we apply an efficiency loss for using a generator to power lighting.
B27: =0.35 -> 0.35 | C27: generator efficiency
B28: =O23*B27 -> 3.6892443e-06 | C28: lightbulb contribution to cost
B31: And must account for the cost of a generator:
B32: Generac | C32: Westinghouse Wgen 5300c | D32: Westinghouse Wgen7500c | E32: Westinghouse WGen9500c | F32: WEN DF5600X | G32: DuroMax XP13000HX | H32: Firman Tri Fuel
A33: $ | B33: 3579 | C33: 649 | D33: 849 | E33: 926 | F33: 399.99 | G33: 1299 | H33: 999 | I33: =AVERAGE(Lighting!B33:H33) -> 1242.9986 | J33: avg $
A34: W | B34: 10000 | C34: 5300 | D34: 7500 | E34: 9500 | F34: 5600 | G34: 13000 | H34: =AVERAGE(10000,8000) -> 9000 | I34: =AVERAGE(Lighting!B34:H34) -> 8557.1429 | J34: avg watts
B35: =B33/B34 -> 0.3579 | C35: =C33/C34 -> 0.12245283 | D35: =D33/D34 -> 0.1132 | E35: =E33/E34 -> 0.097473684 | F35: =F33/F34 -> 0.071426786 | G35: =G33/G34 -> 0.099923077 | H35: =H33/H34 -> 0.111
I37: =I33*M19/I34 -> 15.280094 | J37: $ | K37: generator upfront cost per lightbulb powered
I38: =I37/K19*B27 -> 5.3861404e-06 | K38: generator contribution to cost
I39: =I38+B28 -> 9.0753847e-06 | K39: total cost per BTU

Sheet Other
A1: Electric example (Infrared Heater for Processed Foods)
A3: CapEx costs: | E3: =2758*1.03 -> 2840.74 | F3: USD | H3: Industrial infrared heater vendor
A4: Capacity: | E4: 18 | F4: kW | H4: Shadow Industrial Infrared model
A5: Annual operating hours: | E5: =18*365 -> 6570 | F5: hours/year | H5: Based on 16-20 hour operation of food processing plants
A7: Annual energy consumption/year (kWh): | E7: =E4*E5 -> 118260 | F7: kWh/year
A8: Annual energy consumption/year (mmBTU): | E8: =E7*0.003412 -> 403.50312 | F8: mmBTU/year
A9: $/BTU/year | E9: =E3/(E8*10^6) -> 7.0401934e-06 | F9: $/BTU/year
A12: Natural Gas-Fired Distillation Columns
A14: Based on a methanol/water separation column.
A16: Capital cost - low | B16: 862500 | C16: $
A17: Capital cost - high | B17: 1500000 | C17: $
A18: Capital cost - mean | B18: =AVERAGE(B16,B17) -> 1181250 | C18: $
A20: Operating hours | B20: 8760 | C20: hours/year
A21: Capacity | B21: 6051100 | C21: Btu/hour
A23: Annual fuel use | B23: =B20*B21 -> 53007636000 | C23: Btu/year
A24: Capital cost | B24: =B18/B23 -> 2.2284525e-05 | C24: $/Btu/year
A28: Remaining "Other Processes" cells use natural gas distillation column values modified by the ratios of capital costs for
A29: boilers using each fuel type to boilers using natural gas.

Sheet Other (mobile)
A1: Ag tractors
A2: 0.57060049 | B2: PIFURfE for ag tractors (other processes)
A3: =4000/15 -> 266.66667 | B3: Assumed annual usage (hours)
A5: =AVERAGE(O29,H39,H83) -> 0.00082719018 | B5: Diesel tractor price $/BTU
A6: =AVERAGE(O30,H40,H82) -> 0.0031381977 | B6: Electric tractor price $/BTU
A9: from https://environmentaldevices.com/wp-content/uploads/2023/09/Impacts-of-electrifying-agricultural-tractors.pdf
C28: Capital costs | D28: Tank capacity (gal) | E28: Battery capacity (kWh) | F28: Runtime/tank (hr) | G28: Energy content/tank | H28: E Intensity (BTU/hr) | I28: Annual usage (hr) | M28: price ($) | N28: annual E | O28: $/BTU
B29: DT #1 | C29: 17000 | D29: 7.1 | F29: 9.5 | G29: =D29*About!$A$112 -> 983279 | H29: =G29/F29 -> 103503.05 | I29: 250 | L29: Diesel | M29: =AVERAGE(C29:C31)*About!A117 -> 21966.589 | N29: =AVERAGE(H29:H31)*A3 -> 27574616 | O29: =M29/N29 -> 0.00079662355
B30: DT #2 | C30: 17000 | D30: 7.1 | F30: 10 | G30: =D30*About!$A$112 -> 983279 | H30: =G30/F30 -> 98327.9 | I30: 250 | L30: Electric | M30: =C32*About!A117 -> 43148.656 | N30: =N29*(1-A2) -> 11840527 | O30: =M30/N30 -> 0.0036441501
B31: DT #3 | C31: 50000 | D31: 18 | F31: 23 | G31: =D31*About!$A$112 -> 2492820 | H31: =G31/F31 -> 108383.48 | I31: 250
B32: eT | C32: 55000 | E32: 24 | F32: 16 | G32: =E32*About!$A$114 -> 81891.36 | I32: 250
C33: =C32/AVERAGE(C29:C31) -> 1.9642857
E34: =E32/38.1 -> 0.62992126
A36: from https://www.cadeogroup.com/wp-content/uploads/2022/04/PNW-Tractor-Electrification-Study.pdf
C38: Energy reservoir (kWh) | D38: hours/year | E38: price | F38: E intensity (BTU/hr) | G38: Annual BTUs | H38: $/BTU
B39: diesel | C39: 2940 | D39: 545 | E39: =37500 -> 37500 | F39: =AVERAGE(60400,120900,214300) -> 131866.67 | G39: =F39*$A$3 -> 35164444 | H39: =E39*About!$A$118/G39 -> 0.00090358046
B40: battery | C40: 113 | D40: 995 | E40: =AVERAGE(58000,74999) -> 66499.5 | F40: =F39*(1-A2) -> 56623.482 | G40: =F40*$A$3 -> 15099595 | H40: =E40*About!$A$118/G40 -> 0.0037315769
F41: ^assuming equal distribution of tasks
A53: from https://pub.epsilon.slu.se/id/document/20368600
C54: % energy consumption (bev vs diesel)
B55: example 1 | C55: 0.54 | E55: ** costs in table 3
B56: example 2 | C56: 0.52
A58: from https://static1.squarespace.com/static/5eab584a296dca09a66e85a6/t/627946f6c12c786debe434c7/1652115191705/TCO_report_May%2B2022.pdf
C81: capital cost | D81: operating hours/yr | E81: Annual energy (gal) | F81: Annual energy (kWh) | G81: Annual BTU | H81: $/BTU
B82: e-tractor | C82: 28398 | D82: 250 | G82: =G83*(1-A2) -> 11801531 | H82: =C82*About!$A$118/G82 -> 0.0020388662
B83: IC | C83: 25345 | D83: 250 | E83: =AVERAGE(144,228.1) -> 186.05 | G83: =E83*About!A112*A3/D83 -> 27483802 | H83: =C83*About!$A$118/G83 -> 0.00078136653

Sheet Summary
A1: Unit: $/(BTU/yr) - dollars of capital cost for equipment per BTU consumed annually by that equipment | B1: electricity if | C1: hard coal if | D1: natural gas if | E1: biomass if | F1: petroleum diesel if | G1: heat if | H1: crude oil if | I1: heavy or residual fuel oil if | J1: LPG propane or butane if | K1: hydrogen if
A2: heat below 100 °C | B2: =B3 -> 3.6314489e-05 | C2: =C3 -> 1.9888846e-05 | D2: =D3 -> 6.2918942e-06 | E2: =E3 -> 1.9888846e-05 | F2: =F3 -> 1.3097712e-05 | G2: 0 | H2: =H3 -> 1.3097712e-05 | I2: =I3 -> 1.3097712e-05 | J2: =J3 -> 1.3097712e-05 | K2: =K3 -> 9.4378413e-06
A3: heat 100 to 200 °C | B3: ='Boilers & Heat Pumps'!B15 -> 3.6314489e-05 | C3: ='Boilers & Heat Pumps'!$H$21 -> 1.9888846e-05 | D3: ='Boilers & Heat Pumps'!$H$23 -> 6.2918942e-06 | E3: =C3 -> 1.9888846e-05 | F3: ='Boilers & Heat Pumps'!$H$22 -> 1.3097712e-05 | G3: 0 | H3: =F3 -> 1.3097712e-05 | I3: =F3 -> 1.3097712e-05 | J3: =F3 -> 1.3097712e-05 | K3: ='Boilers & Heat Pumps'!A37 -> 9.4378413e-06
A4: heat 200 to 500 °C | B4: ='NB High Temp'!B93 -> 1.3373592e-05 | C4: ='NB Medium Temp'!D59 -> 2.963048e-05 | D4: ='NB Medium Temp'!D61 -> 2.2152156e-05 | E4: =C4 -> 2.963048e-05 | F4: ='NB Medium Temp'!D60 -> 2.5895356e-05 | G4: 0 | H4: =F4 -> 2.5895356e-05 | I4: =F4 -> 2.5895356e-05 | J4: =D4 -> 2.2152156e-05 | K4: =D4*(K3/D3) -> 3.3228234e-05
A5: heat 500 to 1000 °C | B5: ='NB High Temp'!B94 -> 1.6537985e-05 | C5: ='NB High Temp'!B117 -> 2.0652868e-05 | D5: ='NB High Temp'!D117 -> 1.7959171e-05 | E5: =C5 -> 2.0652868e-05 | F5: ='NB High Temp'!C117 -> 1.8777712e-05 | G5: 0 | H5: =F5 -> 1.8777712e-05 | I5: =F5 -> 1.8777712e-05 | J5: =D5 -> 1.7959171e-05 | K5: ='NB High Temp'!F67 -> 3.2657846e-05
A6: heat above 1000 °C | B6: ='NB High Temp'!F10 -> 0.00017204637 | C6: ='NB High Temp'!E140 -> 4.8979618e-06 | D6: ='NB High Temp'!E141 -> 1.4075502e-05 | E6: =C6 -> 4.8979618e-06 | F6: ='NB High Temp'!E142 -> 1.3887716e-05 | G6: 0 | H6: =F6 -> 1.3887716e-05 | I6: =F6 -> 1.3887716e-05 | J6: =D6 -> 1.4075502e-05 | K6: ='NB High Temp'!F67 -> 3.2657846e-05
A7: cooling | B7: =Cooling!$B$49 -> 4.4520366e-05 | C7: =$D$7 -> 1.808816e-05 | D7: =Cooling!$B$27 -> 1.808816e-05 | E7: =$D$7 -> 1.808816e-05 | F7: =$D$7 -> 1.808816e-05 | G7: 0 | H7: =$D$7 -> 1.808816e-05 | I7: =$D$7 -> 1.808816e-05 | J7: =$D$7 -> 1.808816e-05 | K7: =$D$7*(K3/D3) -> 2.713224e-05
A8: machine drive | B8: ='Machine Drive'!$W$22 -> 2.9652198e-05 | C8: =$F$8 -> 7.0734512e-05 | D8: =$F$8 -> 7.0734512e-05 | E8: =$F$8 -> 7.0734512e-05 | F8: ='Machine Drive'!D38 -> 7.0734512e-05 | G8: 0 | H8: =$F$8 -> 7.0734512e-05 | I8: =$F$8 -> 7.0734512e-05 | J8: =$F$8 -> 7.0734512e-05 | K8: =$F$8 -> 7.0734512e-05
A9: other processes | B9: =Other!E9 -> 7.0401934e-06 | C9: =C4 -> 2.963048e-05 | D9: =Other!B24 -> 2.2284525e-05 | E9: =C9 -> 2.963048e-05 | F9: =F4 -> 2.5895356e-05 | G9: 0 | H9: =F9 -> 2.5895356e-05 | I9: =F9 -> 2.5895356e-05 | J9: =F9 -> 2.5895356e-05 | K9: =D9*(K3/D3) -> 3.3426788e-05
A10: facility HVAC | B10: =B2 -> 3.6314489e-05 | C10: =C2 -> 1.9888846e-05 | D10: =D2 -> 6.2918942e-06 | E10: =E2 -> 1.9888846e-05 | F10: =F2 -> 1.3097712e-05 | G10: 0 | H10: =H2 -> 1.3097712e-05 | I10: =I2 -> 1.3097712e-05 | J10: =J2 -> 1.3097712e-05 | K10: =K2 -> 9.4378413e-06
A11: facility lighting | B11: =Lighting!O23 -> 1.0540698e-05 | C11: =$F$11 -> 9.0753847e-06 | D11: =$F$11 -> 9.0753847e-06 | E11: =$F$11 -> 9.0753847e-06 | F11: =Lighting!I39 -> 9.0753847e-06 | G11: 0 | H11: =$F$11 -> 9.0753847e-06 | I11: =$F$11 -> 9.0753847e-06 | J11: =$F$11 -> 9.0753847e-06 | K11: =$F$11 -> 9.0753847e-06
A12: other nonprocess | B12: =AVERAGE(B2:B11) -> 4.0265487e-05 | C12: =AVERAGE(C2:C11) -> 2.4237638e-05 | D12: =AVERAGE(D2:D11) -> 1.9324509e-05 | E12: =AVERAGE(E2:E11) -> 2.4237638e-05 | F12: =AVERAGE(F2:F11) -> 2.2164733e-05 | G12: 0 | H12: =AVERAGE(H2:H11) -> 2.2164733e-05 | I12: =AVERAGE(I2:I11) -> 2.2164733e-05 | J12: =AVERAGE(J2:J11) -> 2.1727338e-05 | K12: =AVERAGE(K2:K11) -> 2.6722637e-05
A13: Green cells are known explicitly. Orange cells are assumptions based on similar fuel types.
A14: Gray cells are not applicable, either because the energy is already in the form of heat or because the equipmen type cannot use that fuel type.
A42: The data on electric arc furnaces (our model for electric high-temp heat) has been double-checked and seem solid, and there are few other good examples of
A43: fully commercialized, electrified, high-temperature heating equipment. For instance, cement kilns burn coal and steam crackers use natural gas. Other electrical furnaces
A44: exist (like induction furnaces), but electric arc furnaces are likely the most common type and are likely the best choice to use as our model equipment type for high-temp
A45: electrified industrial heating equipment. So we do not consider them to be an outlier - i.e., the higher cost is justified.

Sheet IECCpUAEU
A1: Unit: $/(BTU/yr) in 2012 USD - capital cost per BTU consumed annually, deflated to 2012 USD via CPI-U (see About) | B1: electricity if | C1: hard coal if | D1: natural gas if | E1: biomass if | F1: petroleum diesel if | G1: heat if | H1: crude oil if | I1: heavy or residual fuel oil if | J1: LPG propane or butane if | K1: hydrogen if
A2: heat below 100 °C | B2: =Summary!B2*About!$C$130 -> 2.6579155e-05 | C2: =Summary!C2*About!$C$130 -> 1.4556965e-05 | D2: =Summary!D2*About!$C$130 -> 4.6051381e-06 | E2: =Summary!E2*About!$C$130 -> 1.4556965e-05 | F2: =Summary!F2*About!$C$130 -> 9.5864251e-06 | G2: =Summary!G2*About!$C$130 -> 0 | H2: =Summary!H2*About!$C$130 -> 9.5864251e-06 | I2: =Summary!I2*About!$C$130 -> 9.5864251e-06 | ... K2: =Summary!K2*About!$C$130 -> 6.9077071e-06
A3: heat 100 to 200 °C | B3: =Summary!B3*About!$C$130 -> 2.6579155e-05 | C3: =Summary!C3*About!$C$130 -> 1.4556965e-05 | D3: =Summary!D3*About!$C$130 -> 4.6051381e-06 | E3: =Summary!E3*About!$C$130 -> 1.4556965e-05 | F3: =Summary!F3*About!$C$130 -> 9.5864251e-06 | G3: =Summary!G3*About!$C$130 -> 0 | H3: =Summary!H3*About!$C$130 -> 9.5864251e-06 | I3: =Summary!I3*About!$C$130 -> 9.5864251e-06 | ... K3: =Summary!K3*About!$C$130 -> 6.9077071e-06
A4: heat 200 to 500 °C | B4: =Summary!B4*About!$C$130 -> 9.7883458e-06 | C4: =Summary!C4*About!$C$130 -> 2.1687022e-05 | D4: =Summary!D4*About!$C$130 -> 1.6213517e-05 | E4: =Summary!E4*About!$C$130 -> 2.1687022e-05 | F4: =Summary!F4*About!$C$130 -> 1.8953225e-05 | G4: =Summary!G4*About!$C$126 -> 0 | H4: =Summary!H4*About!$C$130 -> 1.8953225e-05 | I4: =Summary!I4*About!$C$130 -> 1.8953225e-05 | J4: =Summary!J4*About!$C$130 -> 1.6213517e-05 | K4: =Summary!K4*About!$C$130 -> 2.4320276e-05
A5: heat 500 to 1000 °C | B5: =Summary!B5*About!$C$130 -> 1.2104416e-05 | C5: =Summary!C5*About!$C$130 -> 1.5116165e-05 | D5: =Summary!D5*About!$C$130 -> 1.3144605e-05 | E5: =Summary!E5*About!$C$130 -> 1.5116165e-05 | F5: =Summary!F5*About!$C$130 -> 1.3743708e-05 | G5: =Summary!G5*About!$C$130 -> 0 | H5: =Summary!H5*About!$C$130 -> 1.3743708e-05 | I5: =Summary!I5*About!$C$130 -> 1.3743708e-05 | J5: =Summary!J5*About!$C$130 -> 1.3144605e-05 | K5: =Summary!K5*About!$C$127 -> 2.8971124e-05
A6: heat above 1000 °C | B6: =Summary!B6*About!$C$130 -> 0.00012592349 | C6: =Summary!C6*About!$C$130 -> 3.5848966e-06 | D6: =Summary!D6*About!$C$130 -> 1.0302085e-05 | E6: =Summary!E6*About!$C$130 -> 3.5848966e-06 | F6: =Summary!F6*About!$C$130 -> 1.0164641e-05 | G6: =Summary!G6*About!$C$130 -> 0 | H6: =Summary!H6*About!$C$130 -> 1.0164641e-05 | I6: =Summary!I6*About!$C$130 -> 1.0164641e-05 | J6: =Summary!J6*About!$C$130 -> 1.0302085e-05 | K6: =Summary!K6*About!$C$127 -> 2.8971124e-05
A7: cooling | B7: =Summary!B7*About!$C$130 -> 3.2585169e-05 | C7: =Summary!C7*About!$C$130 -> 1.3239014e-05 | D7: =Summary!D7*About!$C$130 -> 1.3239014e-05 | E7: =Summary!E7*About!$C$130 -> 1.3239014e-05 | F7: =Summary!F7*About!$C$130 -> 1.3239014e-05 | G7: =Summary!G7*About!$C$130 -> 0 | H7: =Summary!H7*About!$C$130 -> 1.3239014e-05 | I7: =Summary!I7*About!$C$130 -> 1.3239014e-05 | ... K7: =Summary!K7*About!$C$130 -> 1.985852e-05
A8: machine drive | B8: =Summary!B8*About!$C$130 -> 2.1702918e-05 | C8: =Summary!C8*About!$C$130 -> 5.1771721e-05 | D8: =Summary!D8*About!$C$130 -> 5.1771721e-05 | E8: =Summary!E8*About!$C$130 -> 5.1771721e-05 | F8: =Summary!F8*About!$C$130 -> 5.1771721e-05 | G8: =Summary!G8*About!$C$130 -> 0 | H8: =Summary!H8*About!$C$130 -> 5.1771721e-05 | I8: =Summary!I8*About!$C$130 -> 5.1771721e-05 | ... K8: =Summary!K8*About!$C$130 -> 5.1771721e-05
A9: other processes | B9: =Summary!B9*About!$C$130 -> 5.1528302e-06 | C9: =Summary!C9*About!$C$126 -> 2.8344925e-05 | D9: =Summary!D9*About!$C$124 -> 2.1962823e-05 | E9: =Summary!E9*About!$C$126 -> 2.8344925e-05 | F9: =Summary!F9*About!$C$126 -> 2.4771854e-05 | G9: =Summary!G9*About!$C$130 -> 0 | H9: =Summary!H9*About!$C$126 -> 2.4771854e-05 | I9: =Summary!I9*About!$C$126 -> 2.4771854e-05 | J9: =Summary!J9*About!$C$126 -> 2.4771854e-05 | K9: =Summary!K9*About!$C$124 -> 3.2944234e-05
A10: facility HVAC | B10: =Summary!B10*About!$C$130 -> 2.6579155e-05 | C10: =Summary!C10*About!$C$130 -> 1.4556965e-05 | D10: =Summary!D10*About!$C$130 -> 4.6051381e-06 | E10: =Summary!E10*About!$C$130 -> 1.4556965e-05 | F10: =Summary!F10*About!$C$130 -> 9.5864251e-06 | G10: =Summary!G10*About!$C$130 -> 0 | H10: =Summary!H10*About!$C$130 -> 9.5864251e-06 | I10: =Summary!I10*About!$C$130 -> 9.5864251e-06 | ... K10: =Summary!K10*About!$C$130 -> 6.9077071e-06
A11: facility lighting | B11: =Summary!B11*About!$C$130 -> 7.7149055e-06 | C11: =Summary!C11*About!$C$130 -> 6.6424193e-06 | D11: =Summary!D11*About!$C$130 -> 6.6424193e-06 | E11: =Summary!E11*About!$C$130 -> 6.6424193e-06 | F11: =Summary!F11*About!$C$130 -> 6.6424193e-06 | G11: =Summary!G11*About!$C$130 -> 0 | H11: =Summary!H11*About!$C$130 -> 6.6424193e-06 | I11: =Summary!I11*About!$C$130 -> 6.6424193e-06 | ... K11: =Summary!K11*About!$C$130 -> 6.6424193e-06
A12: other nonprocess | B12: =AVERAGE(B2:B11) -> 2.9470954e-05 | C12: =AVERAGE(C2:C11) -> 1.8405706e-05 | D12: =AVERAGE(D2:D11) -> 1.470916e-05 | E12: =AVERAGE(E2:E11) -> 1.8405706e-05 | F12: =AVERAGE(F2:F11) -> 1.6804586e-05 | G12: =AVERAGE(G2:G11) -> 0 | H12: =AVERAGE(H2:H11) -> 1.6804586e-05 | I12: =AVERAGE(I2:I11) -> 1.6804586e-05 | ... K12: =AVERAGE(K2:K11) -> 2.1420254e-05

Sheet IECCpUAEU-mobile
A1: Unit: $/(BTU/yr) in 2012 USD - capital cost per BTU consumed annually, deflated to 2012 USD via CPI-U (see About)
A2: electricity if | B2: ='Other (mobile)'!A6 -> 0.0031381977
A3: hard coal if | B3: =B6 -> 0.00082719018
A4: natural gas if | B4: =B6 -> 0.00082719018
A5: biomass if | B5: =B6 -> 0.00082719018
A6: petroleum diesel if | B6: ='Other (mobile)'!A5 -> 0.00082719018
A7: heat if | B7: 0
A8: crude oil if | B8: =B6 -> 0.00082719018
A9: heavy or residual fuel oil if | B9: =B6 -> 0.00082719018
A10: LPG propane or butane if | B10: =B6 -> 0.00082719018
A11: hydrogen if | B11: =B6 -> 0.00082719018

Sheet 1.1 Traditional heat pump
A1: Technology | C1: Heat pump, up to 60 °C, Temp lift = 40 K
A2: year | C2: 2025 | D2: 2030 | E2: 2035 | F2: 2040 | G2: 2050 | H2: 2025 | I2: 2025 | J2: 2050 | K2: 2050 | L2: Note | M2: Ref
A3: est | C3: ctrl | D3: ctrl | E3: ctrl | F3: ctrl | G3: ctrl | H3: lower | I3: upper | J3: lower | K3: upper | L3: - | M3: -
A4: cat | B4: par
A5: Energy/technical data
B6: Heat generation capacity for one unit [MW] | C6: 3 | D6: 3 | E6: 3 | F6: 3 | G6: 3 | H6: 0.5 | I6: 5 | J6: 0.5 | K6: 5 | L6: A | M6: [1, 2]
B7: Total efficiency, net [%], nominel load | C7: 5.33 | D7: =C7*1.03 -> 5.4899 | E7: 5.55 | F7: =D7*1.02 -> 5.599698 | G7: =F7*1.01 -> 5.655695 | H7: =C7 -> 5.33 | I7: =C7*1.05 -> 5.5965 | J7: =G7*0.97 -> 5.4860241 | K7: =G7*1.02 -> 5.7688089 | L7: B | M7: [1, 3]
B8: Total efficiency, net [%], annual average | C8: =C7-5% -> 5.28 | D8: =D7-5% -> 5.4399 | E8: =E7-5% -> 5.5 | F8: =F7-5% -> 5.549698 | G8: =G7-5% -> 5.605695 | H8: =H7-5% -> 5.28 | I8: =I7-5% -> 5.5465 | J8: =J7-5% -> 5.4360241 | K8: =K7-5% -> 5.7188089 | L8: B,C
B9: Auxiliary electricity consumption [% of heat gen] | C9: 0.01 | D9: 0.01 | E9: 0.01 | F9: 0.01 | G9: 0.01 | H9: 0.01 | I9: 0.04 | J9: 0.01 | K9: 0.04 | M9: 2
B10: Forced outage [%] | C10: 0 | D10: 0 | E10: 0 | F10: 0 | G10: 0 | H10: 0 | I10: 0.01 | J10: 0 | K10: 0.01 | L10: D | M10: 2
B11: Planned outage [weeks per year] | C11: 1 | D11: 1 | E11: 1 | F11: 1 | G11: 1 | H11: 0.5 | I11: 2 | J11: 0.5 | K11: 2 | M11: 2
B12: Technical lifetime [years] | C12: 25 | D12: 25 | E12: 25 | F12: 25 | G12: 25 | H12: 15 | I12: 40 | J12: 15 | K12: 40 | M12: 2
B13: Construction time [years] | C13: 0.5 | D13: 0.5 | E13: 0.5 | F13: 0.5 | G13: 0.5 | H13: 0.3 | I13: 1 | J13: 0.3 | K13: 1 | M13: 2
A14: Regulation Ability
B15: Minimum load [% of full load] | C15: 0.25 | D15: 0.25 | E15: 0.25 | F15: 0.25 | G15: 0.25 | H15: 0.1 | I15: 0.5 | J15: 0.1 | K15: 0.5 | M15: 2
B16: Warm start-up time [hours] | C16: 0.1 | D16: 0.1 | E16: 0.1 | F16: 0.1 | G16: 0.1 | H16: 0.1 | I16: 0.2 | J16: 0.1 | K16: 0.2 | M16: 2
B17: Cold start-up time [hours] | C17: 1 | D17: 1 | E17: 1 | F17: 1 | G17: 1 | H17: 0.2 | I17: 1 | J17: 0.2 | K17: 1 | M17: 2
A18: Financial data
B19: Nominal investment [M€/MW] | C19: 0.95 | D19: 0.94 | E19: 0.91 | F19: 0.91 | G19: 0.89 | H19: 0.91 | I19: 0.95 | J19: 0.88 | K19: 0.95 | M19: 2
B20: - of which equipment [%] | C20: 0.4 | D20: 0.4 | E20: 0.4 | F20: 0.4 | G20: 0.4 | L20: E | M20: 2
B21: - of which installation and other costs [%] | C21: 0.6 | D21: 0.6 | E21: 0.6 | F21: 0.6 | G21: 0.6 | L21: F | M21: 2
B22: Fixed O&M [€/MJ/s/year] | C22: 2127 | D22: 2095 | E22: 2032 | F22: 2032 | G22: 2001 | H22: 2032 | I22: 2127 | J22: 1970 | K22: 2127 | M22: 2
B23: Variable O&M [€/MWh] | C23: 3.07 | D23: 3.02 | E23: 2.93 | F23: 2.93 | G23: 2.89 | H23: 2.93 | I23: 3.07 | J23: 2.84 | K23: 3.07 | M23: 2
A24: Technology-specific data
B25: Indirect investments cost [M€/MW] | C25: =C19*0.2 -> 0.19 | D25: =D19*0.2 -> 0.188 | E25: =E19*0.2 -> 0.182 | F25: =F19*0.2 -> 0.182 | G25: =G19*0.2 -> 0.178 | L25: H
B26: Non energy gains [M€/MW] | C26: - | D26: - | E26: - | F26: - | G26: -
B27: Startup cost [€/MW/startup] | C27: 10 | D27: 10 | E27: 10 | F27: 10 | G27: 10
B28: Temperature heat source supply [°C] | C28: 30 | D28: 30 | E28: 30 | F28: 30 | G28: 30 | L28: I
B29: Temperature heat source return [°C] | C29: 20 | D29: 20 | E29: 20 | F29: 20 | G29: 20 | L29: I
B30: - Total efficiency, net [%], nominel load. Based on a temperature lift of 50 K, 70°C max | C30: 4.52 | D30: 4.6 | E30: 4.65 | F30: 4.7 | G30: 4.74 | H30: 4.47 | I30: 4.69 | J30: 4.6 | K30: 4.84 | L30: G
B31: - Total efficiency, net [%], nominel load. Based on a temperature lift of 60 K, 80°C max | C31: 3.95 | D31: 4 | E31: 4.04 | F31: 4.08 | G31: 4.12 | H31: 3.88 | I31: 4.07 | J31: 3.99 | K31: 4.2 | L31: G
B32: Cooling generation capacity for one unit [MW] | C32: - | D32: - | E32: - | F32: - | G32: -
A35: Notes:
A36: A | B36: 0,5-5 MW
A37: B | B37: Estimated based on cases presented in [3]
A38: C | B38: Based on lost produktion during startup/shutdown
A39: D | B39: May vary depending on heat source availability
A40: E | B40: Very individual, can vary ÷ 20 %
A41: F | B41: Very individual, can vary + 20 %
A42: G | B42: Based on the old technology catalogue on process heat from 2020.
A43: H | B43: Going from current implementation to potential
A44: I | B44: Uses waste heat
A46: References:
A47: 1 | B47: Viegand Maagøe, 2019.
A48: 2 | B48: Danish Enegy Agency, Technology Data - Energy Plants for Electricity and District heating generation, 2025
A49: 3 | B49: EHPA, Large Scale heat pumps in Europe, 2019

Sheet 1.2 heat_cool hp 80 C 75 K 
A1: Technology | C1: Combined heating and cooling heat pump, up to 80 °C, Temp lift = 75 K
A2: year | C2: 2025 | D2: 2030 | E2: 2035 | F2: 2040 | G2: 2050 | H2: 2025 | I2: 2025 | J2: 2050 | K2: 2050 | L2: Note | M2: Ref
A3: est | C3: ctrl | D3: ctrl | E3: ctrl | F3: ctrl | G3: ctrl | H3: lower | I3: upper | J3: lower | K3: upper | L3: - | M3: -
A4: cat | B4: par
A5: Energy/technical data
B6: Heat generation capacity for one unit [MW] | C6: 3 | D6: 3 | E6: 3 | F6: 3 | G6: 3 | H6: 0.5 | I6: 5 | J6: 0.5 | K6: 5 | L6: A | M6: [1, 2]
B7: Total efficiency, net [%], nominel load | C7: 3.35 | D7: 3.43 | E7: 3.48 | F7: =D7*1.02 -> 3.4986 | G7: =F7*1.01 -> 3.533586 | H7: 3.33 | I7: =C7*1.05 -> 3.5175 | J7: =G7*0.97 -> 3.4275784 | K7: =G7*1.02 -> 3.6042577 | L7: B | M7: [1, 3]
B8: Total efficiency, net [%], annual average | C8: =C7-5% -> 3.3 | D8: =D7-5% -> 3.38 | E8: =E7-5% -> 3.43 | F8: =F7-5% -> 3.4486 | G8: =G7-5% -> 3.483586 | H8: =H7-5% -> 3.28 | I8: =I7-5% -> 3.4675 | J8: =J7-5% -> 3.3775784 | K8: =K7-5% -> 3.5542577 | L8: B,C
B9: Auxiliary electricity consumption [% of heat gen] | C9: 0.01 | D9: 0.01 | E9: 0.01 | F9: 0.01 | G9: 0.01 | H9: 0.01 | I9: 0.04 | J9: 0.01 | K9: 0.04 | M9: 2
B10: Forced outage [%] | C10: 0 | D10: 0 | E10: 0 | F10: 0 | G10: 0 | H10: 0 | I10: 0.01 | J10: 0 | K10: 0.01 | L10: D | M10: 2
B11: Planned outage [weeks per year] | C11: 1 | D11: 1 | E11: 1 | F11: 1 | G11: 1 | H11: 0.5 | I11: 2 | J11: 0.5 | K11: 2 | M11: 2
B12: Technical lifetime [years] | C12: 25 | D12: 25 | E12: 25 | F12: 25 | G12: 25 | H12: 15 | I12: 40 | J12: 15 | K12: 40 | M12: 2
B13: Construction time [years] | C13: 0.5 | D13: 0.5 | E13: 0.5 | F13: 0.5 | G13: 0.5 | H13: 0.3 | I13: 1 | J13: 0.3 | K13: 1 | M13: 2
A14: Regulation Ability
B15: Minimum load [% of full load] | C15: 0.25 | D15: 0.25 | E15: 0.25 | F15: 0.25 | G15: 0.25 | H15: 0.1 | I15: 0.5 | J15: 0.1 | K15: 0.5 | M15: 2
B16: Warm start-up time [hours] | C16: 0.1 | D16: 0.1 | E16: 0.1 | F16: 0.1 | G16: 0.1 | H16: 0.1 | I16: 0.2 | J16: 0.1 | K16: 0.2 | M16: 2
B17: Cold start-up time [hours] | C17: 1 | D17: 1 | E17: 1 | F17: 1 | G17: 1 | H17: 0.2 | I17: 1 | J17: 0.2 | K17: 1 | M17: 2
A18: Financial data
B19: Nominal investment [M€/MW] | C19: 0.95 | D19: 0.94 | E19: 0.91 | F19: 0.91 | G19: 0.89 | H19: 0.91 | I19: 0.95 | J19: 0.88 | K19: 0.95 | M19: 2
B20: - of which equipment [%] | C20: 0.4 | D20: 0.4 | E20: 0.4 | F20: 0.4 | G20: 0.4 | L20: E | M20: 2
B21: - of which installation and other costs [%] | C21: 0.6 | D21: 0.6 | E21: 0.6 | F21: 0.6 | G21: 0.6 | L21: F | M21: 2
B22: Fixed O&M [€/MJ/s/year] | C22: 2127 | D22: 2095 | E22: 2032 | F22: 2032 | G22: 2001 | H22: 2032 | I22: 2127 | J22: 1970 | K22: 2127 | M22: 2
B23: Variable O&M [€/MWh] | C23: 3.07 | D23: 3.02 | E23: 2.93 | F23: 2.93 | G23: 2.89 | H23: 2.93 | I23: 3.07 | J23: 2.84 | K23: 3.07 | M23: 2
A24: Technology-specific data
B25: Indirect investments cost [M€/MW] | C25: =C19*0.2 -> 0.19 | D25: =D19*0.2 -> 0.188 | E25: =E19*0.2 -> 0.182 | F25: =F19*0.2 -> 0.182 | G25: =G19*0.2 -> 0.178 | L25: H
B26: Non energy gains [M€/MW] | C26: - | D26: - | E26: - | F26: - | G26: -
B27: Startup cost [€/MW/startup] | C27: 10 | D27: 10 | E27: 10 | F27: 10 | G27: 10
B28: Temperature heat source supply [°C] | C28: 15 | D28: 15 | E28: 15 | F28: 15 | G28: 15 | L28: I
B29: Temperature heat source return [°C] | C29: 5 | D29: 5 | E29: 5 | F29: 5 | G29: 5 | L29: I
B30: Cooling generation capacity for one unit [MW] | C30: =C6-C6/(C7/100) -> -86.552239 | D30: =D6-D6/(D7/100) -> -84.463557 | E30: =E6-E6/(E7/100) -> -83.206897 | F30: =F6-F6/(F7/100) -> -82.748585 | G30: =G6-G6/(G7/100) -> -81.899589
A33: Notes:
A34: A | B34: 0,5-5 MW
A35: B | B35: Estimated based on cases presented in [3]
A36: C | B36: Based on lost produktion during startup/shutdown
A37: D | B37: May vary depending on heat source availability
A38: E | B38: Very individual, can vary ÷ 20 %
A39: F | B39: Very individual, can vary + 20 %
A40: G | B40: Based on the old technology catalogue on process heat from 2020.
A41: H | B41: Going from current implementation to potential
A42: I | B42: Uses waste heat
A44: References
A45: 1 | B45: Viegand Maagøe, 2019.
A46: 2 | B46: Danish Enegy Agency, Technology Data - Energy Plants for Electricity and District heating generation, 2025
A47: 3 | B47: EHPA, Large Scale heat pumps in Europe, 2019

Sheet 2.a High temp. hp Up to 125C
A1: Technology | C1: High-temperature heat pumps up to 125 °C
A2: year | C2: 2025 | D2: 2030 | E2: 2035 | F2: 2040 | G2: 2050 | H2: 2025 | I2: 2025 | J2: 2050 | K2: 2050 | L2: Note | M2: Ref
A3: est | C3: ctrl | D3: ctrl | E3: ctrl | F3: ctrl | G3: ctrl | H3: lower | I3: upper | J3: lower | K3: upper | L3: - | M3: -
A4: cat | B4: par
A5: Energy/technical data
B6: Heat generation capacity for one unit [MW] | C6: 2 | D6: 2 | E6: 3 | F6: 3 | G6: 3 | H6: 0.3 | I6: 25 | J6: 0.2 | K6: 50 | L6: B | M6: 4
B7: Total efficiency, net [%], nominel load. Based on a temperature lift of 65 K | C7: 2.75 | D7: 2.85 | E7: 2.9 | F7: 2.95 | G7: 3 | H7: 2.25 | I7: 4 | J7: 2.5 | K7: 4.5 | L7: C, H | M7: 1
B8: Total efficiency, net [%], annual average | C8: 2.7 | D8: 2.8 | E8: 2.85 | F8: 2.9 | G8: 2.95 | H8: 2.2 | I8: 3.95 | J8: 2.45 | K8: 4.45
B9: Auxiliary electricity consumption [% of heat gen] | C9: 0.02 | D9: 0.02 | E9: 0.02 | F9: 0.02 | G9: 0.02 | H9: 0.01 | I9: 0.07 | J9: 0.01 | K9: 0.07 | M9: 1
B10: Forced outage [days] | C10: 0 | D10: 0 | E10: 0 | F10: 0 | G10: 0 | H10: 0 | I10: 1 | J10: 0 | K10: 1 | M10: 4
B11: Planned outage [weeks per year] | C11: 0.5 | D11: 0.5 | E11: 0.5 | F11: 0.5 | G11: 0.5 | H11: 0 | I11: 1 | J11: 0 | K11: 1 | M11: 4
B12: Technical lifetime [years] | C12: 20 | D12: 20 | E12: 20 | F12: 20 | G12: 20 | H12: 15 | I12: 30 | J12: 15 | K12: 30 | L12: D | M12: 4
B13: Construction time [years] | C13: 0.6 | D13: 0.5 | E13: 0.4 | F13: 0.4 | G13: 0.4 | H13: 0.4 | I13: 0.8 | J13: 0.2 | K13: 0.8 | L13: E | M13: 4
B14: Space requirement [1000 m2/MW_e] | C14: 0.02 | D14: 0.02 | E14: 0.02 | F14: 0.02 | G14: 0.02 | H14: 0.01 | I14: 0.04 | J14: 0.01 | K14: 0.04
A15: Regulation ability
B16: Primary regulation (of full load, per 30 seconds) [] | C16: 0.05 | D16: 0.07 | E16: 0.08 | F16: 0.09 | G16: 0.1 | H16: 0.02 | I16: 0.1 | J16: 0.05 | K16: 0.2
B17: Secondary regulation (of full load, per minute) [] | C17: 0.1 | D17: 0.14 | E17: 0.16 | F17: 0.18 | G17: 0.2 | H17: 0.04 | I17: 0.2 | J17: 0.1 | K17: 0.4
B18: Minimum load (of full load) [] | C18: 0.25 | D18: 0.25 | E18: 0.25 | F18: 0.25 | G18: 0.25 | H18: 0.1 | I18: 0.5 | J18: 0.1 | K18: 0.5 | L18: F | M18: 4
B19: Warm start-up time [hours] | C19: 0.25 | D19: 0.25 | E19: 0.25 | F19: 0.25 | G19: 0.25 | H19: 0.1 | I19: 0.5 | J19: 0.1 | K19: 0.25 | M19: 4
B20: Cold start-up time [hours] | C20: 1 | D20: 1 | E20: 1 | F20: 1 | G20: 1 | H20: 0.5 | I20: 1.5 | J20: 0.5 | K20: 1.5 | M20: 4
A21: Financial data
B22: Nominal investment (*total) [MEUR/MW] | C22: 1.2 | D22: 1.15 | E22: 1.1 | F22: 1.05 | G22: 1 | H22: 0.9 | I22: 1.5 | J22: 0.7 | K22: 1.3 | L22: G | M22: [1, 4]
B23: - of which equipment [%] | C23: 0.4 | D23: 0.4 | E23: 0.4 | F23: 0.4 | G23: 0.4 | H23: 0.25 | I23: 0.6 | J23: 0.25 | K23: 0.7 | L23: A | M23: 1
B24: - of which installation [%] | C24: 0.6 | D24: 0.6 | E24: 0.6 | F24: 0.6 | G24: 0.6 | H24: 0.4 | I24: 0.75 | J24: 0.3 | K24: 0.75 | L24: A | M24: 3
B25: Fixed O&M [EUR/MW_y] | C25: 2494 | D25: 2456 | E25: 2382 | F25: 2382 | G25: 2345 | M25: 2
B26: Variable O&M [EUR/MWh] | C26: 3.6 | D26: 3.54 | E26: 3.43 | F26: 3.43 | G26: 3.39 | M26: 2
A27: Technology-specific data
B28: Technology dependent
B29: Indirect investment cost [M€/MW] | C29: 0.23 | D29: 0.23 | E29: 0.23 | F29: 0.23 | G29: 0.23 | L29: I
B30: - Steam generation decreases COP [%-point] | C30: -0.15 | D30: -0.1 | E30: -0.05 | F30: -0.05 | G30: -0.05 | H30: -0.05 | I30: -0.2 | J30: -0.05 | K30: -0.15 | M30: [1, 4]
B31: - Steam generation increases equipment cost by [MEUR/MW] | C31: 0.2 | D31: 0.15 | E31: 0.1 | F31: 0.1 | G31: 0.1 | H31: 0.05 | I31: 0.3 | J31: 0.05 | K31: 0.2 | M31: [1, 4]
B32: - Additional equipment cost for temperature lift above 75 K [MEUR/MW] | C32: =MROUND(C22*C23*0.3,0.05) -> 0.15 | D32: =MROUND(D22*D23*0.3,0.05) -> 0.15 | E32: =MROUND(E22*E23*0.3,0.05) -> 0.15 | F32: =MROUND(F22*F23*0.3,0.05) -> 0.15 | G32: =MROUND(G22*G23*0.3,0.05) -> 0.1 | H32: =MROUND(H22*H23*0.3,0.05) -> 0.05 | I32: =MROUND(I22*I23*0.3,0.05) -> 0.25 | J32: =MROUND(J22*J23*0.3,0.05) -> 0.05 | K32: =MROUND(K22*K23*0.3,0.05) -> 0.25 | M32: [1, 4]
B33: - Total efficiency, net [%], nominel load. Based on a temperature lift of 40 K | C33: 4.45 | D33: 4.65 | E33: 4.7 | F33: 4.8 | G33: 4.9 | H33: 3.65 | I33: 6.5 | J33: 4.05 | K33: 7.3 | M33: [1, 4]
B34: - Total efficiency, net [%], nominel load. Based on a temperature lift of 80 K | C34: 2.4 | D34: 2.45 | E34: 2.5 | F34: 2.55 | G34: 2.6 | H34: 2 | I34: 3.4 | J34: 2.2 | K34: 3.8 | M34: [1, 4]
B35: - Total efficiency, net [%], nominel load. Based on a temperature lift of 100 K | C35: 2.05 | D35: 2.1 | E35: 2.15 | F35: 2.2 | G35: 2.2 | H35: 1.7 | I35: 2.85 | J35: 1.9 | K35: 3.2 | M35: [1, 4]
A38: Notes:
A39: A | B39: Depends on production infrastructure. If HTHP replaces another HTHP, there will be lower investment in new installation
A40: B | B40: Unit sizes vary a lot and depends on production infrastructure. Lower capacities for specific production processes and higher capacities for central hot water supply
A41: C | B41: Efficiency depends on temperature lift of HTHP. High temperature lift reduces COP.
A42: D | B42: Both depends on lifetime of parts and new technology with higher efficiencies leading to replacement of existing systems
A43: E | B43: Expected to be lower in future when serial production is gaining traction
A44: F | B44: HTHPs are frequency controlled but typically a higher minimum load means smaller losses in COP
A45: G | B45: Expected to be lower in future due to serial production and better integration knowledge
A46: H | B46: Efficiency depends on technology of HTHP and production processes
A47: I | B47: Relevant when needing to install new hot water piping instead of existing steam piping. Assumed similar to gas boiler.
A49: References:
A50: 1 | B50: Danish Technological Institute
A51: 2 | B51: Danish Enegy Agency, Technology Data - Energy Plants for Electricity and District heating generation, 2025
A52: 3 | B52: Viegand Maagøe
A53: 4 | B53: Annex 58
A54: 5 | B54: Fraunhofer ISI, "Direct electrification of industrial process heat. An assessment of technologies, potentials and future prospects for the EU. Study on behalf of Agora Industry", 2024

Sheet 2.b High temp. hp Up to 150
A1: Technology | C1: High-temperature heat pumps up to 150 °C
A2: year | C2: 2025 | D2: 2030 | E2: 2035 | F2: 2040 | G2: 2050 | H2: 2025 | I2: 2025 | J2: 2050 | K2: 2050 | L2: Note | M2: Ref
A3: est | C3: ctrl | D3: ctrl | E3: ctrl | F3: ctrl | G3: ctrl | H3: lower | I3: upper | J3: lower | K3: upper | L3: - | M3: -
A4: cat | B4: par
A5: Energy/technical data
B6: Heat generation capacity for one unit [MW] | C6: 2 | D6: 2 | E6: 3 | F6: 3 | G6: 3 | H6: 0.5 | I6: 80 | J6: 0.5 | K6: 100 | L6: B | M6: 4
B7: Total efficiency, net [%], nominel load. Based on a temperature lift of 65 K | C7: 2.75 | D7: 2.85 | E7: 2.9 | F7: 2.95 | G7: 3 | H7: 2.25 | I7: 4 | J7: 2.5 | K7: 4.5 | L7: C, H | M7: 1
B8: Total efficiency, net [%], annual average | C8: 2.7 | D8: 2.8 | E8: 2.85 | F8: 2.9 | G8: 2.95 | H8: 2.2 | I8: 3.95 | J8: 2.45 | K8: 4.45
B9: Auxiliary electricity consumption [% of heat gen] | C9: 0.02 | D9: 0.02 | E9: 0.02 | F9: 0.02 | G9: 0.02 | H9: 0.01 | I9: 0.07 | J9: 0.01 | K9: 0.07 | M9: 1
B10: Forced outage [days] | C10: 0 | D10: 0 | E10: 0 | F10: 0 | G10: 0 | H10: 0 | I10: 1 | J10: 0 | K10: 1 | M10: 4
B11: Planned outage [weeks per year] | C11: 0.5 | D11: 0.5 | E11: 0.5 | F11: 0.5 | G11: 0.5 | H11: 0 | I11: 1 | J11: 0 | K11: 1 | M11: 4
B12: Technical lifetime [years] | C12: 20 | D12: 20 | E12: 20 | F12: 20 | G12: 20 | H12: 15 | I12: 30 | J12: 15 | K12: 30 | L12: D | M12: 4
B13: Construction time [years] | C13: 0.6 | D13: 0.5 | E13: 0.4 | F13: 0.4 | G13: 0.4 | H13: 0.4 | I13: 0.8 | J13: 0.2 | K13: 0.8 | L13: E | M13: 4
B14: Space requirement [1000 m2/MW_e] | C14: 0.03 | D14: 0.03 | E14: 0.03 | F14: 0.03 | G14: 0.03 | H14: 0.02 | I14: 0.06 | J14: 0.01 | K14: 0.05
A15: Regulation ability
B16: Primary regulation (of full load, per 30 seconds) [] | C16: 0.05 | D16: 0.07 | E16: 0.08 | F16: 0.09 | G16: 0.1 | H16: 0.02 | I16: 0.1 | J16: 0.05 | K16: 0.2
B17: Secondary regulation (of full load, per minute) [] | C17: 0.1 | D17: 0.14 | E17: 0.16 | F17: 0.18 | G17: 0.2 | H17: 0.04 | I17: 0.2 | J17: 0.1 | K17: 0.4
B18: Minimum load (of full load) [] | C18: 0.25 | D18: 0.25 | E18: 0.25 | F18: 0.25 | G18: 0.25 | H18: 0.1 | I18: 0.5 | J18: 0.1 | K18: 0.5 | L18: F | M18: 4
B19: Warm start-up time [hours] | C19: 0.25 | D19: 0.25 | E19: 0.25 | F19: 0.25 | G19: 0.25 | H19: 0.1 | I19: 0.5 | J19: 0.1 | K19: 0.25 | M19: 4
B20: Cold start-up time [hours] | C20: 1 | D20: 1 | E20: 1 | F20: 1 | G20: 1 | H20: 0.5 | I20: 1.5 | J20: 0.5 | K20: 1.5 | M20: 4
A21: Financial data
B22: Nominal investment (*total) [MEUR/MW] | C22: 1.55 | D22: 1.5 | E22: 1.45 | F22: 1.4 | G22: 1.35 | H22: 1.25 | I22: 1.8 | J22: 1.1 | K22: 1.65 | L22: G
B23: - of which equipment [%] | C23: 0.4 | D23: 0.4 | E23: 0.4 | F23: 0.4 | G23: 0.4 | H23: 0.25 | I23: 0.6 | J23: 0.25 | K23: 0.7 | L23: A | M23: 1
B24: - of which installation [%] | C24: 0.6 | D24: 0.6 | E24: 0.6 | F24: 0.6 | G24: 0.6 | H24: 0.4 | I24: 0.75 | J24: 0.3 | K24: 0.75 | L24: A | M24: 3
B25: Fixed O&M [EUR/MW_y], from last update in 2019 | C25: 2494 | D25: 2456 | E25: 2382 | F25: 2382 | G25: 2345 | M25: 2
B26: Variable O&M [EUR/MWh], from last update in 2019 | C26: 3.6 | D26: 3.54 | E26: 3.43 | F26: 3.43 | G26: 3.39 | M26: 1
A27: Technology-specific data
B28: Technology dependent
B29: Indirect investment cost [M€/MW] | C29: 0.23 | D29: 0.23 | E29: 0.23 | F29: 0.23 | G29: 0.23 | L29: I
B30: - Steam generation decreases COP [%-point] | C30: -0.15 | D30: -0.1 | E30: -0.05 | F30: -0.05 | G30: -0.05 | H30: -0.05 | I30: -0.2 | J30: -0.05 | K30: -0.15 | M30: [1, 4]
B31: - Steam generation increases equipment cost by [MEUR/MW] | C31: 0.2 | D31: 0.15 | E31: 0.1 | F31: 0.1 | G31: 0.1 | H31: 0.05 | I31: 0.3 | J31: 0.05 | K31: 0.2 | M31: [1, 4]
B32: - Additional equipment cost for temperature lift above 75 K [MEUR/MW] | C32: =MROUND(C22*C23*0.3,0.05) -> 0.2 | D32: =MROUND(D22*D23*0.3,0.05) -> 0.2 | E32: =MROUND(E22*E23*0.3,0.05) -> 0.15 | F32: =MROUND(F22*F23*0.3,0.05) -> 0.15 | G32: =MROUND(G22*G23*0.3,0.05) -> 0.15 | H32: =MROUND(H22*H23*0.3,0.05) -> 0.1 | I32: =MROUND(I22*I23*0.3,0.05) -> 0.3 | J32: =MROUND(J22*J23*0.3,0.05) -> 0.1 | K32: =MROUND(K22*K23*0.3,0.05) -> 0.35 | M32: [1, 4]
B33: - Total efficiency, net [%], nominel load. Based on a temperature lift of 40 K | C33: 4.45 | D33: 4.65 | E33: 4.7 | F33: 4.8 | G33: 4.9 | H33: 3.65 | I33: 6.5 | J33: 4.05 | K33: 7.3 | M33: [1, 4]
B34: - Total efficiency, net [%], nominel load. Based on a temperature lift of 80 K | C34: 2.4 | D34: 2.45 | E34: 2.5 | F34: 2.55 | G34: 2.6 | H34: 2 | I34: 3.4 | J34: 2.2 | K34: 3.8 | M34: [1, 4]
B35: - Total efficiency, net [%], nominel load. Based on a temperature lift of 100 K | C35: 2.05 | D35: 2.1 | E35: 2.15 | F35: 2.2 | G35: 2.2 | H35: 1.7 | I35: 2.85 | J35: 1.9 | K35: 3.2 | M35: [1, 4]
A38: Notes:
A39: A | B39: Depends on production infrastructure. If HTHP replaces another HTHP, there will be lower investment in new installation
A40: B | B40: Unit sizes vary a lot and depends on production infrastructure. Lower capacities for specific production processes and higher capacities for central hot water supply
A41: C | B41: Efficiency depends on temperature lift of HTHP. High temperature lift reduces COP.
A42: D | B42: Both depends on lifetime of parts and new technology with higher efficiencies leading to replacement of existing systems
A43: E | B43: Expected to be lower in future when serial production is gaining traction
A44: F | B44: HTHPs are frequency controlled but typically a higher minimum load means smaller losses in COP
A45: G | B45: Expected to be lower in future due to serial production and better integration knowledge
A46: H | B46: Efficiency depends on technology of HTHP and production processes
A47: I | B47: Relevant when needing to install new hot water piping instead of existing steam piping. Assumed similar to gas boiler.
A49: References:
A50: 1 | B50: Danish Technological Institute
A51: 2 | B51: Jensen, J., Elmegaard, B., and Markussen, W. Industrial heat pumps for high temperature process applications.: A numerical study of the ammonia-water hybrid absorption-compression heat pump. PhD thesis. ,2016
A52: 3 | B52: Viegand Maagøe
A53: 4 | B53: Annex 58

Sheet 4 MVR 5 K
A1: Technology | C1: Mechanical vapor recompression
A2: year | C2: 2025 | D2: 2030 | E2: 2035 | F2: 2040 | G2: 2050 | H2: 2025 | I2: 2025 | J2: 2050 | K2: 2050 | L2: Note | M2: Ref
A3: est | C3: ctrl | D3: ctrl | E3: ctrl | F3: ctrl | G3: ctrl | H3: lower | I3: upper | J3: lower | K3: upper | L3: - | M3: -
A4: cat | B4: par
A5: Energy/technical data
B6: Heat generation capacity for one unit [MW] | C6: 20 | D6: 20 | E6: 20 | F6: 20 | G6: 20 | H6: 5 | I6: 50 | J6: 5 | K6: 50 | L6: A | M6: 1
B7: Total efficiency, net [%], nominel load | C7: 12.6 | D7: 13.2 | E7: 13.5 | F7: 13.8 | G7: 14.3 | H7: 10 | I7: 15.12 | J7: 10.56 | K7: 17.16 | L7: B | M7: 1
B8: Total efficiency, net [%], annual average | C8: =C7-50% -> 12.1 | D8: =D7-50% -> 12.7 | E8: =E7-50% -> 13 | F8: =F7-50% -> 13.3 | G8: =G7-50% -> 13.8 | H8: =H7-50% -> 9.5 | I8: =I7-50% -> 14.62 | J8: =J7-50% -> 10.06 | K8: =K7-50% -> 16.66
B9: Auxiliary electricity consumption [% of heat gen] | C9: 0.01 | D9: 0.01 | E9: 0.01 | F9: 0.01 | G9: 0.01 | H9: 0 | I9: 0.02 | J9: 0 | K9: 0.02 | M9: 3
B10: Forced outage [%] | C10: 0 | D10: 0 | E10: 0 | F10: 0 | G10: 0 | H10: 0 | I10: 0.01 | J10: 0 | K10: 0.01 | M10: 2
B11: Planned outage [weeks per year] | C11: 0.5 | D11: 0.5 | E11: 0.5 | F11: 0.5 | G11: 0.5 | H11: 0 | I11: 1 | J11: 0 | K11: 1 | M11: 2
B12: Technical lifetime [years] | C12: 25 | D12: 25 | E12: 25 | F12: 25 | G12: 25 | H12: 15 | I12: 35 | J12: 15 | K12: 35 | M12: [1, 2]
B13: Construction time [years] | C13: 0.1 | D13: 0.1 | E13: 0.1 | F13: 0.1 | G13: 0.1 | H13: 0.05 | I13: 0.2 | J13: 0.05 | K13: 0.2 | M13: [1, 3]
A14: Regulation Ability
B15: Minimum load [% of full load] | C15: 0.15 | D15: 0.15 | E15: 0.15 | F15: 0.15 | G15: 0.15 | M15: 4
B16: Warm start-up time [hours] | C16: 0.5 | D16: 0.5 | E16: 0.5 | F16: 0.5 | G16: 0.5 | M16: 3
B17: Cold start-up time [hours] | C17: 1 | D17: 1 | E17: 1 | F17: 1 | G17: 1 | M17: 3
A18: Financial data
B19: Nominal investment [M€/MW] | C19: 0.41 | D19: 0.39 | E19: 0.39 | F19: 0.38 | G19: 0.36 | M19: [1, 5]
B20: - of which equipment [%] | C20: 0.6 | D20: 0.6 | E20: 0.6 | F20: 0.6 | G20: 0.6 | M20: [1, 5]
B21: - of which installation [%] | C21: 0.4 | D21: 0.4 | E21: 0.4 | F21: 0.4 | G21: 0.4 | M21: [1, 5]
B22: Fixed O&M [€/MJ/s/year] | C22: 2345 | D22: 2345 | E22: 2345 | F22: 2345 | G22: 2345 | M22: 2
B23: Variable O&M [€/MWh] | C23: 2.1 | D23: 2 | E23: 2 | F23: 2 | G23: 1.9 | M23: 2
A26: Notes:
A27: A | B27: 5-50 MW
A28: B | B28: Assumed temperature lift of 5 K (saturation temperatur)
A30: References:
A31: 1 | B31: Viegand Maagøe, MVR, 2018
A32: 2 | B32: Technological data for energi plants (Compressions Heat Pumps for DH), Energistyrelsen, 2017
A33: 3 | B33: Viegand Maagøe, 2019
A34: 4 | B34: EPCON, EVAPORATION TECHNOLOGY, 2019
A35: 5 | B35: EPCON investment cost offer, 2017.

Sheet 5.1a Electric boiler steam
A1: Technology | C1: Electric boiler, 0,4-0,69 kV, steam, 1-12 bar
A2: year | C2: 2025 | D2: 2030 | E2: 2035 | F2: 2040 | G2: 2050 | H2: 2025 | I2: 2025 | J2: 2050 | K2: 2050 | L2: Note | M2: Ref
A3: est | C3: ctrl | D3: ctrl | E3: ctrl | F3: ctrl | G3: ctrl | H3: lower | I3: upper | J3: lower | K3: upper | L3: - | M3: -
A4: cat | B4: par
A5: Energy/technical data
B6: Heat generation capacity for one unit [MW] | C6: 2 | D6: 2 | E6: 2 | F6: 2 | G6: 2 | H6: 1 | I6: 5 | J6: 1 | K6: 5 | L6: A
B7: Total efficiency, net [%], nominel load | C7: 0.99 | D7: 0.99 | E7: 0.99 | F7: 0.99 | G7: 0.99 | H7: 0.98 | I7: 1 | J7: 0.98 | K7: 1 | M7: [1, 2]
B8: Total efficiency, net [%], annual average | C8: 0.99 | D8: 0.99 | E8: 0.99 | F8: 0.99 | G8: 0.99 | H8: 0.98 | I8: 0.99 | J8: 0.98 | K8: 0.99 | M8: [1, 2]
B9: Auxiliary electricity consumption [% of heat gen] | C9: 0.005 | D9: 0.005 | E9: 0.005 | F9: 0.005 | G9: 0.005 | H9: 0.001 | I9: 0.005 | J9: 0.001 | K9: 0.005 | M9: [1, 2]
B10: Forced outage [%] | C10: 0.01 | D10: 0.01 | E10: 0.01 | F10: 0.01 | G10: 0.01 | H10: 0.005 | I10: 0.01 | J10: 0.005 | K10: 0.01 | M10: [1, 2]
B11: Planned outage [weeks per year] | C11: 0.2 | D11: 0.2 | E11: 0.2 | F11: 0.2 | G11: 0.2 | H11: 0.2 | I11: 0.2 | J11: 0.2 | K11: 0.2 | M11: 2
B12: Technical lifetime [years] | C12: 25 | D12: 25 | E12: 25 | F12: 25 | G12: 25 | H12: 20 | I12: 25 | J12: 20 | K12: 25 | M12: 2
B13: Construction time [years] | C13: 0.5 | D13: 0.5 | E13: 0.5 | F13: 0.5 | G13: 0.5 | H13: 0.5 | I13: 1 | J13: 0.5 | K13: 1 | M13: 1
A14: Regulation Ability
B15: Minimum load [% of full load] | C15: 0.02 | D15: 0.02 | E15: 0.02 | F15: 0.02 | G15: 0.02 | M15: 2
B16: Warm start-up time [hours] | C16: 0.03 | D16: 0.03 | E16: 0.03 | F16: 0.03 | G16: 0.03 | M16: 2
B17: Cold start-up time [hours] | C17: 0.17 | D17: 0.17 | E17: 0.17 | F17: 0.17 | G17: 0.17 | M17: 2
A18: Financial data
B19: Nominal investment [M€/MW] | C19: 0.25 | D19: 0.22 | E19: 0.22 | F19: 0.22 | G19: 0.22 | L19: B,C | M19: [1, 2, 4]
B20: - of which equipment [%] | C20: 0.75 | D20: 0.75 | E20: 0.75 | F20: 0.75 | G20: 0.75 | M20: [2, 4]
B21: - of which installation [%] | C21: 0.25 | D21: 0.25 | E21: 0.25 | F21: 0.25 | G21: 0.25 | M21: [2, 4]
B22: Fixed O&M [€/MJ/s/year] | C22: 1442 | D22: 1375 | E22: 1341 | F22: 1307 | G22: 1240 | M22: [2, 3, 4]
B23: Variable O&M [€/MWh] | C23: 0.674 | D23: 0.642 | E23: 0.627 | F23: 0.611 | G23: 0.578 | M23: [2, 3, 4]
A24: Technology-specific data
B25: Additional investments cost for 12-16 bar boilers [M€/MW] | C25: 0.064 | D25: 0.057 | E25: 0.057 | F25: 0.057 | G25: 0.057
A28: Notes:
A29: A | B29: 1-5 MW
A30: B | B30: Electrode boilers at low voltage typically needs a transformer from distribution grid. Costs for the transformer are included in the equipment costs.
A31: C | B31: Investment cost is slightly higher than for a hot water boiler.
A33: References:
A34: 1 | B34: Danish Enegy Agency, Technology Data - Energy Plants for Electricity and District heating generation, 2022
A35: 2 | B35: AS:scan, Personal communication, 2022
A36: 3 | B36: Tjæreborg Industri, Personal communication, 2022
A37: 4 | B37: Nordheat, Personal communication, 2022

Sheet 5.1b Electric boiler steam
A1: Technology | C1: Electric boiler, 10 kV, steam, 1-12 bar
A2: year | C2: 2025 | D2: 2030 | E2: 2035 | F2: 2040 | G2: 2050 | H2: 2025 | I2: 2025 | J2: 2050 | K2: 2050 | L2: Note | M2: Ref
A3: est | C3: ctrl | D3: ctrl | E3: ctrl | F3: ctrl | G3: ctrl | H3: lower | I3: upper | J3: lower | K3: upper | L3: - | M3: -
A4: cat | B4: par
A5: Energy/technical data
B6: Heat generation capacity for one unit [MW] | C6: 15 | D6: 15 | E6: 15 | F6: 15 | G6: 15 | H6: 5 | I6: 60 | J6: 5 | K6: 60 | L6: A
B7: Total efficiency, net [%], nominel load | C7: 0.99 | D7: 0.99 | E7: 0.99 | F7: 0.99 | G7: 0.99 | H7: 0.98 | I7: 1 | J7: 0.98 | K7: 1 | M7: [1, 2]
B8: Total efficiency, net [%], annual average | C8: 0.99 | D8: 0.99 | E8: 0.99 | F8: 0.99 | G8: 0.99 | H8: 0.98 | I8: 0.99 | J8: 0.98 | K8: 0.99 | M8: [1, 2]
B9: Auxiliary electricity consumption [% of heat gen] | C9: 0.005 | D9: 0.005 | E9: 0.005 | F9: 0.005 | G9: 0.005 | H9: 0.001 | I9: 0.005 | J9: 0.001 | K9: 0.005 | M9: [1, 2]
B10: Forced outage [%] | C10: 0.01 | D10: 0.01 | E10: 0.01 | F10: 0.01 | G10: 0.01 | H10: 0.005 | I10: 0.01 | J10: 0.005 | K10: 0.01 | M10: [1, 2]
B11: Planned outage [weeks per year] | C11: 0.2 | D11: 0.2 | E11: 0.2 | F11: 0.2 | G11: 0.2 | H11: 0.2 | I11: 0.2 | J11: 0.2 | K11: 0.2 | M11: 2
B12: Technical lifetime [years] | C12: 25 | D12: 25 | E12: 25 | F12: 25 | G12: 25 | H12: 20 | I12: 25 | J12: 20 | K12: 25 | M12: 2
B13: Construction time [years] | C13: 0.5 | D13: 0.5 | E13: 0.5 | F13: 0.5 | G13: 0.5 | H13: 0.5 | I13: 1 | J13: 0.5 | K13: 1 | M13: 1
A14: Regulation Ability
B15: Minimum load [% of full load] | C15: 0.02 | D15: 0.02 | E15: 0.02 | F15: 0.02 | G15: 0.02 | M15: 2
B16: Warm start-up time [hours] | C16: 0.03 | D16: 0.03 | E16: 0.03 | F16: 0.03 | G16: 0.03 | M16: 2
B17: Cold start-up time [hours] | C17: 0.17 | D17: 0.17 | E17: 0.17 | F17: 0.17 | G17: 0.17 | M17: 2
A18: Financial data
B19: Nominal investment [M€/MW] | C19: 0.11 | D19: 0.1 | E19: 0.1 | F19: 0.1 | G19: 0.1 | L19: B,C | M19: [1, 2, 4]
B20: - of which equipment [%] | C20: 0.85 | D20: 0.85 | E20: 0.85 | F20: 0.85 | G20: 0.85 | M20: 2
B21: - of which installation [%] | C21: 0.15 | D21: 0.15 | E21: 0.15 | F21: 0.15 | G21: 0.15 | M21: 2
B22: Fixed O&M [€/MJ/s/year] | C22: 1298 | D22: 1237 | E22: 1208 | F22: 1177 | G22: 1116 | M22: [2, 3, 4]
B23: Variable O&M [€/MWh] | C23: 0.61 | D23: 0.58 | E23: 0.56 | F23: 0.55 | G23: 0.52 | M23: [2, 3, 4]
A24: Technology-specific data
B25: Additional investments cost for 12-16 bar boilers [M€/MW] | C25: 0.021 | D25: 0.018 | E25: 0.018 | F25: 0.018 | G25: 0.018
A28: Notes:
A29: A | B29: 5-60 MW
A30: B | B30: Electrode boilers at medium-high voltage are directly connected to the distribution grid. Costs for the distribution board are included in the equipment costs.
A31: C | B31: Investment cost is slightly higher than for a hot water boiler.
A33: References:
A34: 1 | B34: Danish Enegy Agency, Technology Data - Energy Plants for Electricity and District heating generation, 2022
A35: 2 | B35: AS:scan, Personal communication, 2022
A36: 3 | B36: Tjæreborg Industri, Personal communication, 2022
A37: 4 | B37: Nordheat, Personal communication, 2022

Sheet 5.2a Electric boiler hot wate
A1: Technology | C1: Electric boiler, 0,4-0,69 kV, hot water, 1-12 bar
A2: year | C2: 2025 | D2: 2030 | E2: 2035 | F2: 2040 | G2: 2050 | H2: 2025 | I2: 2025 | J2: 2050 | K2: 2050 | L2: Note | M2: Ref
A3: est | C3: ctrl | D3: ctrl | E3: ctrl | F3: ctrl | G3: ctrl | H3: lower | I3: upper | J3: lower | K3: upper | L3: - | M3: -
A4: cat | B4: par
A5: Energy/technical data
B6: Heat generation capacity for one unit [MW] | C6: 2 | D6: 2 | E6: 2 | F6: 2 | G6: 2 | H6: 1 | I6: 5 | J6: 1 | K6: 5 | L6: A
B7: Total efficiency, net [%], nominel load | C7: 0.99 | D7: 0.99 | E7: 0.99 | F7: 0.99 | G7: 0.99 | H7: 0.98 | I7: 1 | J7: 0.98 | K7: 1 | M7: [1, 2]
B8: Total efficiency, net [%], annual average | C8: 0.99 | D8: 0.99 | E8: 0.99 | F8: 0.99 | G8: 0.99 | H8: 0.98 | I8: 0.99 | J8: 0.98 | K8: 0.99 | M8: [1, 2]
B9: Auxiliary electricity consumption [% of heat gen] | C9: 0.005 | D9: 0.005 | E9: 0.005 | F9: 0.005 | G9: 0.005 | H9: 0.001 | I9: 0.005 | J9: 0.001 | K9: 0.005 | M9: [1, 2]
B10: Forced outage [%] | C10: 0.01 | D10: 0.01 | E10: 0.01 | F10: 0.01 | G10: 0.01 | H10: 0.005 | I10: 0.01 | J10: 0.005 | K10: 0.01 | M10: [1, 2]
B11: Planned outage [weeks per year] | C11: 0.2 | D11: 0.2 | E11: 0.2 | F11: 0.2 | G11: 0.2 | H11: 0.2 | I11: 0.2 | J11: 0.2 | K11: 0.2 | M11: 1
B12: Technical lifetime [years] | C12: 25 | D12: 25 | E12: 25 | F12: 25 | G12: 25 | H12: 20 | I12: 25 | J12: 20 | K12: 25 | M12: 2
B13: Construction time [years] | C13: 0.5 | D13: 0.5 | E13: 0.5 | F13: 0.5 | G13: 0.5 | H13: 0.5 | I13: 1 | J13: 0.5 | K13: 1 | M13: 1
A14: Regulation Ability
B15: Minimum load [% of full load] | C15: 0.05 | D15: 0.05 | E15: 0.05 | F15: 0.05 | G15: 0.05 | M15: 1
B16: Warm start-up time [hours] | C16: 0.008 | D16: 0.008 | E16: 0.008 | F16: 0.008 | G16: 0.008 | M16: 1
B17: Cold start-up time [hours] | C17: 0.08 | D17: 0.08 | E17: 0.08 | F17: 0.08 | G17: 0.08 | M17: 1
A18: Financial data
B19: Nominal investment [M€/MW] | C19: 0.202 | D19: 0.187 | E19: 0.187 | F19: 0.187 | G19: 0.187 | L19: B,C | M19: [1, 2, 4]
B20: - of which equipment [%] | C20: 0.75 | D20: 0.75 | E20: 0.75 | F20: 0.75 | G20: 0.75 | M20: 2
B21: - of which installation [%] | C21: 0.25 | D21: 0.25 | E21: 0.25 | F21: 0.25 | G21: 0.25 | M21: 2
B22: Fixed O&M [€/MJ/s/year] | C22: 1254 | D22: 1196 | E22: 1166 | F22: 1137 | G22: 1079 | M22: 1
B23: Variable O&M [€/MWh] | C23: 0.59 | D23: 0.56 | E23: 0.54 | F23: 0.53 | G23: 0.5 | M23: [2, 3, 4]
A24: Technology-specific data
B25: Indirect investments cost [M€/MW] | C25: =C19*0.5 -> 0.101 | D25: =D19*0.5 -> 0.0935 | E25: =E19*0.5 -> 0.0935 | F25: =F19*0.5 -> 0.0935 | G25: =G19*0.5 -> 0.0935 | L25: D
B26: Additional investments cost for 12-16 bar boilers [M€/MW] | C26: 0.057 | D26: 0.049 | E26: 0.049 | F26: 0.049 | G26: 0.049
A29: Notes:
A30: A | B30: 1-5 MW
A31: B | B31: Electrode boilers at low voltage typically needs a transformer from distribution grid. Costs for the transformer are included in the equipment costs.
A32: C | B32: Investment cost is slightly lower than for a steam boiler.
A33: D | B33: Going from current implementation to potential
A35: References:
A36: 1 | B36: Danish Enegy Agency, Technology Data - Energy Plants for Electricity and District heating generation, 2022
A37: 2 | B37: AS:scan, Personal communication, 2022
A38: 3 | B38: Tjæreborg Industri, Personal communication, 2019
A39: 4 | B39: Nordheat, Personal communication, 2022

Sheet 5.2b Electric boiler hot wate
A1: Technology | C1: Electric boiler,10 kV, hot water, 1-12 bar
A2: year | C2: 2025 | D2: 2030 | E2: 2035 | F2: 2040 | G2: 2050 | H2: 2025 | I2: 2025 | J2: 2050 | K2: 2050 | L2: Note | M2: Ref
A3: est | C3: ctrl | D3: ctrl | E3: ctrl | F3: ctrl | G3: ctrl | H3: lower | I3: upper | J3: lower | K3: upper | L3: - | M3: -
A4: cat | B4: par
A5: Energy/technical data
B6: Heat generation capacity for one unit [MW] | C6: 15 | D6: 15 | E6: 15 | F6: 15 | G6: 15 | H6: 5 | I6: 60 | J6: 5 | K6: 60 | L6: A
B7: Total efficiency, net [%], nominel load | C7: 0.99 | D7: 0.99 | E7: 0.99 | F7: 0.99 | G7: 0.99 | H7: 0.98 | I7: 1 | J7: 0.98 | K7: 1 | M7: [1, 2]
B8: Total efficiency, net [%], annual average | C8: 0.99 | D8: 0.99 | E8: 0.99 | F8: 0.99 | G8: 0.99 | H8: 0.98 | I8: 0.99 | J8: 0.98 | K8: 0.99 | M8: [1, 2]
B9: Auxiliary electricity consumption [% of heat gen] | C9: 0.005 | D9: 0.005 | E9: 0.005 | F9: 0.005 | G9: 0.005 | H9: 0.001 | I9: 0.005 | J9: 0.001 | K9: 0.005 | M9: [1, 2]
B10: Forced outage [%] | C10: 0.01 | D10: 0.01 | E10: 0.01 | F10: 0.01 | G10: 0.01 | H10: 0.005 | I10: 0.01 | J10: 0.005 | K10: 0.01 | M10: [1, 2]
B11: Planned outage [weeks per year] | C11: 0.2 | D11: 0.2 | E11: 0.2 | F11: 0.2 | G11: 0.2 | H11: 0.2 | I11: 0.2 | J11: 0.2 | K11: 0.2 | M11: 1
B12: Technical lifetime [years] | C12: 25 | D12: 25 | E12: 25 | F12: 25 | G12: 25 | H12: 20 | I12: 25 | J12: 20 | K12: 25 | M12: 2
B13: Construction time [years] | C13: 0.5 | D13: 0.5 | E13: 0.5 | F13: 0.5 | G13: 0.5 | H13: 0.5 | I13: 1 | J13: 0.5 | K13: 1 | M13: 1
A14: Regulation Ability
B15: Minimum load [% of full load] | C15: 0.05 | D15: 0.05 | E15: 0.05 | F15: 0.05 | G15: 0.05 | M15: 1
B16: Warm start-up time [hours] | C16: 0.008 | D16: 0.008 | E16: 0.008 | F16: 0.008 | G16: 0.008 | M16: 1
B17: Cold start-up time [hours] | C17: 0.08 | D17: 0.08 | E17: 0.08 | F17: 0.08 | G17: 0.08 | M17: 1
A18: Financial data
B19: Nominal investment [M€/MW] | C19: 0.089 | D19: 0.084 | E19: 0.084 | F19: 0.084 | G19: 0.084 | L19: B,C | M19: [1, 2, 4]
B20: - of which equipment [%] | C20: 0.85 | D20: 0.85 | E20: 0.85 | F20: 0.85 | G20: 0.85 | M20: 2
B21: - of which installation [%] | C21: 0.15 | D21: 0.15 | E21: 0.15 | F21: 0.15 | G21: 0.15 | M21: 2
B22: Fixed O&M [€/MJ/s/year] | C22: 1103 | D22: 1076 | E22: 1050 | F22: 1023 | G22: 971 | M22: [1, 2, 4]
B23: Variable O&M [€/MWh] | C23: 0.53 | D23: 0.5 | E23: 0.49 | F23: 0.48 | G23: 0.45 | M23: [2, 3, 4]
A24: Technology-specific data
B25: Indirect investments cost [M€/MW] | C25: =C19/2 -> 0.0445 | D25: =D19/2 -> 0.042 | E25: =E19/2 -> 0.042 | F25: =F19/2 -> 0.042 | G25: =G19/2 -> 0.042 | L25: D
B26: Additional investments cost for 12-16 bar boilers [M€/MW] | C26: 0.018 | D26: 0.016 | E26: 0.016 | F26: 0.016 | G26: 0.016
A29: Notes:
A30: A | B30: 5-60 MW
A31: B | B31: Electrode boilers at medium-high voltage are directly connected to the distribution grid. Costs for the distribution board are included in the equipment costs.
A32: C | B32: Investment cost is slightly lower than for a steam boiler.
A33: D | B33: Going from current implementation to potential
A35: References:
A36: 1 | B36: Danish Enegy Agency, Technology Data - Energy Plants for Electricity and District heating generation, 2022
A37: 2 | B37: AS:scan, Personal communication, 2022
A38: 3 | B38: Tjæreborg Industri, Personal communication, 2022
A39: 4 | B39: Nordheat, Personal communication, 2022

Sheet 6.1 Boiler, gas and oil
A1: Technology | C1: Boiler, gas and oil
A2: year | C2: 2025 | D2: 2030 | E2: 2035 | F2: 2040 | G2: 2050 | H2: 2025 | I2: 2025 | J2: 2050 | K2: 2050 | L2: Note | M2: Ref
A3: est | C3: ctrl | D3: ctrl | E3: ctrl | F3: ctrl | G3: ctrl | H3: lower | I3: upper | J3: lower | K3: upper | L3: - | M3: -
A4: cat | B4: par
A5: Energy/technical data
B6: Heat generation capacity for one unit [MW] | C6: 5 | D6: 5 | E6: 5 | F6: 5 | G6: 5 | H6: 0.5 | I6: 50 | J6: 0.5 | K6: 50 | M6: [1, 2, 3, 6]
B7: Total efficiency, net [%], nominel load | C7: 0.94 | D7: 0.94 | E7: 0.94 | F7: 0.94 | G7: 0.94 | H7: 0.92 | I7: 0.95 | J7: 0.92 | K7: 0.95 | L7: A, B, E | M7: [1, 4, 6]
B8: Total efficiency, net [%], annual average | C8: 0.939 | D8: 0.939 | E8: 0.939 | F8: 0.939 | G8: 0.939 | H8: 0.919 | I8: 0.949 | J8: 0.919 | K8: 0.949 | L8: A, B, D | M8: [1, 4]
B9: Auxiliary electricity consumption [% of heat gen] | C9: 0.0015 | D9: 0.0015 | E9: 0.0015 | F9: 0.0015 | G9: 0.0015 | H9: 0 | I9: 0.0015 | J9: 0 | K9: 0.0015 | M9: [1, 2]
B10: Forced outage [%] | C10: 0.01 | D10: 0.01 | E10: 0.01 | F10: 0.01 | G10: 0.01 | H10: 0 | I10: 0.02 | J10: 0 | K10: 0.02 | M10: 1
B11: Planned outage [weeks per year] | C11: 0.5 | D11: 0.5 | E11: 0.5 | F11: 0.5 | G11: 0.5 | H11: 0.3 | I11: 0.6 | J11: 0.3 | K11: 0.6 | M11: [1, 2]
B12: Technical lifetime [years] | C12: 25 | D12: 25 | E12: 25 | F12: 25 | G12: 25 | H12: 25 | J12: 25 | M12: 1
B13: Construction time [years] | C13: 0.2 | D13: 0.2 | E13: 0.2 | F13: 0.2 | G13: 0.2 | H13: 0.02 | I13: 0.7 | J13: 0.02 | K13: 0.7 | M13: [1, 2]
B14: Space requirement [1000 m2/MW_e] | C14: 0.008 | D14: 0.008 | E14: 0.008 | F14: 0.008 | G14: 0.008 | H14: 0.007 | I14: 0.01 | J14: 0.007 | K14: 0.01 | M14: [2, 3]
A15: Regulation ability
B16: Primary regulation (of full load, per 30 seconds) [%] | C16: 0.15 | D16: 0.15 | E16: 0.15 | F16: 0.15 | G16: 0.15 | H16: 0.035 | I16: 0.3 | L16: H | M16: [1, 2, 6]
B17: Secondary regulation (of full load, per minute) [%] | C17: 0.3 | D17: 0.3 | E17: 0.3 | F17: 0.3 | G17: 0.3 | H17: 0.07 | I17: 0.6 | L17: H | M17: [1, 2, 6]
B18: Minimum load (of full load) [%] | C18: 0.15 | D18: 0.15 | E18: 0.15 | F18: 0.15 | G18: 0.15 | H18: 0.1 | I18: 0.2 | M18: [1, 2, 6]
B19: Warm start-up time [hours] | C19: 0.06 | D19: 0.06 | E19: 0.06 | F19: 0.06 | G19: 0.06 | H19: 0.025 | I19: 0.2 | M19: [1, 2, 6]
B20: Cold start-up time [hours] | C20: 0.5 | D20: 0.5 | E20: 0.5 | F20: 0.5 | G20: 0.5 | H20: 0.3 | I20: 1 | M20: [1, 2, 6]
A21: Financial data
B22: Nominal investment (*total) [MEUR/MW] | C22: 0.09 | D22: 0.09 | E22: 0.09 | F22: 0.09 | G22: 0.09 | L22: C, B | M22: [1, 2, 6]
B23: - of which equipment [%] | C23: 0.66 | D23: 0.66 | E23: 0.66 | F23: 0.66 | G23: 0.66 | M23: [1, 2]
B24: - of which installation [%] | C24: 0.34 | D24: 0.34 | E24: 0.34 | F24: 0.34 | G24: 0.34 | M24: [1, 2]
B25: Fixed O&M [EUR/MW_y] | C25: 2000 | D25: 2000 | E25: 2000 | F25: 2000 | G25: 2000 | M25: [1, 2]
B26: Variable O&M [EUR/MWh] | C26: 1.23 | D26: 1.23 | E26: 1.23 | F26: 1.23 | G26: 1.23 | M26: 1
A27: Technology-specific data
B28: Indirect investment cost [M€/MW] | C28: 0.23 | D28: 0.23 | E28: 0.23 | F28: 0.23 | G28: 0.23 | L28: J | M28: 2
B29: Technology dependent
B30: - Adding flue gas condenser (after economiser) increases efficiency by [%-point] (gas only) | C30: 0.06 | D30: 0.06 | E30: 0.06 | F30: 0.06 | G30: 0.06 | L30: I, E | M30: [1, 2, 5]
B31: - Adding flue gas condenser (after economiser) increases nominal investment by [%] (gas only) | C31: 0.1 | D31: 0.1 | E31: 0.1 | F31: 0.1 | G31: 0.1 | L31: I | M31: 2
B32: - Hot water boiler instead of steam boiler increases efficiency by [%-point] | C32: 0.01 | D32: 0.01 | E32: 0.01 | F32: 0.01 | G32: 0.01 | L32: F
B33: - Hot water boiler instead of steam boiler reduces nominal investment by [%] | C33: 0.3 | D33: 0.3 | E33: 0.3 | F33: 0.3 | G33: 0.3 | L33: G | M33: [2, 3]
A36: Notes:
A37: A | B37: Effeciency for unit with economiser (but not flue gas condenser) installed.
A38: B | B38: Values for steam boiler (see technology-specific data for differences with hot water boiler)
A39: C | B39: Prices include boiler, firing equipment, pumps, economiser, water-treatment system, chimney and installation.
A40: D | B40: Assuming 10 starts a year.
A41: E | B41: For condensing boilers, efficiencies above 100% are possible, since the standard efficiency calculation using the lower heating value (LHV) as denominator.
A42: F | B42: 1 %-point higher for hot water boiler, due to assumed lower flue gas temperature. If no flue gas condenser and economiser is used, the increase will be higher.
A43: G | B43: Hot water boiler is generally operating at lower pressure levels, so pressure vessel is cheaper. Water treatment system not necessary for hot water boiler.
A44: H | B44: Assumes warm operation.
A45: I | B45: Flue gas condenser not possible for oil boilers as its combustion products contain pollutants which would heavily corrode the heat exchanger surfaces if condensed.
A46: J | B46: Relevant for hot water boiler when needing to install new hot water piping instead of existing steam piping.
A48: References:
A49: 1 | B49: Danish Energy Agency, Energy Plants for Electricity and District heating generation, 2016 (updated 2025) ."44 Natural Gas DH Only"
A50: 2 | B50: Bosch Industrial, Personal correspondence & product catalogue, 2025
A51: 3 | B51: Viessmann, Personal correspondence & product catalogue, 2025
A52: 4 | B52: Vakklianainen, Esa. Steam Generation from Biomass. 2017. (Chapter 3, Boiler processes)
A53: 5 | B53: Chen, Q., Finney, K., Li, H., Zhang, X., Zhou, J., Sharifi, V., Swithenbank, J. Condensing boiler applications in the process industry. Applied Energy, 89, 30-36, 2012
A54: 6 | B54: Danstoker, Personal correspondence & product catalogue, 2025

Sheet 6.2 Boiler, biomass
A1: Technology | C1: Boiler, biomass
A2: year | C2: 2025 | D2: 2030 | E2: 2035 | F2: 2040 | G2: 2050 | H2: 2025 | I2: 2025 | J2: 2050 | K2: 2050 | L2: Note | M2: Ref
A3: est | C3: ctrl | D3: ctrl | E3: ctrl | F3: ctrl | G3: ctrl | H3: lower | I3: upper | J3: lower | K3: upper | L3: - | M3: -
A4: cat | B4: par
A5: Energy/technical data
B6: Heat generation capacity for one unit [MW] | C6: 6.5 | D6: 6.5 | E6: 6.5 | F6: 6.5 | G6: 6.5 | H6: 0.3 | I6: 50 | J6: 0.3 | K6: 50 | M6: [1, 4, 5]
B7: Total efficiency, net [%], nominel load | C7: 0.89 | D7: 0.89 | E7: 0.89 | F7: 0.89 | G7: 0.89 | H7: 0.87 | I7: 0.91 | J7: 0.87 | K7: 0.91 | L7: A, B | M7: 2
B8: Total efficiency, net [%], annual average | C8: 0.889 | D8: 0.889 | E8: 0.889 | F8: 0.889 | G8: 0.889 | H8: 0.869 | I8: 0.909 | J8: 0.869 | K8: 0.909 | L8: A, B, D | M8: 2
B9: Auxiliary electricity consumption [% of heat gen] | C9: 0.02 | D9: 0.02 | E9: 0.02 | F9: 0.02 | G9: 0.02 | H9: 0.02 | I9: 0.02 | J9: 0.02 | K9: 0.02 | M9: 1
B10: Forced outage [%] | C10: 0.03 | D10: 0.03 | E10: 0.03 | F10: 0.03 | G10: 0.03 | H10: 0.03 | I10: 0.03 | J10: 0.03 | K10: 0.03 | M10: 1
B11: Planned outage [weeks per year] | C11: 2 | D11: 2 | E11: 2 | F11: 2 | G11: 2 | H11: 1.7 | I11: 2.3 | J11: 1.5 | K11: 2.5 | M11: 1
B12: Technical lifetime [years] | C12: 25 | D12: 25 | E12: 25 | F12: 25 | G12: 25 | H12: 20 | I12: 35 | J12: 20 | K12: 35 | M12: 1
B13: Construction time [years] | C13: 1 | D13: 1 | E13: 1 | F13: 1 | G13: 1 | H13: 0.5 | I13: 1.5 | J13: 0.5 | K13: 1.5 | M13: 1
B14: Space requirement [1000 m2/MW_e] | C14: 0.2 | D14: 0.2 | E14: 0.2 | F14: 0.2 | G14: 0.2 | H14: 0.14 | I14: 0.25 | J14: 0.12 | K14: 0.27 | M14: 1
A15: Regulation ability
B16: Primary regulation (of full load, per 30 seconds) [%]
B17: Secondary regulation (of full load, per minute) [%] | C17: 0.1 | D17: 0.1 | E17: 0.1 | F17: 0.1 | G17: 0.1 | M17: 1
B18: Minimum load (of full load) [%] | C18: 0.2 | D18: 0.2 | E18: 0.2 | F18: 0.2 | G18: 0.2 | M18: 1
B19: Warm start-up time [hours] | C19: 0.25 | D19: 0.25 | E19: 0.25 | F19: 0.25 | G19: 0.25 | M19: 1
B20: Cold start-up time [hours] | C20: 0.5 | D20: 0.5 | E20: 0.5 | F20: 0.5 | G20: 0.5 | M20: 1
A21: Financial data
B22: Nominal investment (*total) [MEUR/MW] | C22: 0.87840721 | D22: 0.82891948 | E22: 0.8072686 | F22: 0.78561772 | G22: 0.74231596 | M22: 1
B23: - of which equipment [%] | C23: 0.6 | D23: 0.6 | E23: 0.6 | F23: 0.6 | G23: 0.6 | M23: 1
B24: - of which installation [%] | C24: 0.4 | D24: 0.4 | E24: 0.4 | F24: 0.4 | G24: 0.4 | M24: 1
B25: Fixed O&M [EUR/MW_y] | C25: 39500 | D25: 38700 | E25: 37900 | F25: 37100 | G25: 35600 | M25: 1
B26: Variable O&M [EUR/MWh] | C26: 1.45 | D26: 1.45 | E26: 1.45 | F26: 1.45 | G26: 1.45 | L26: C, H | M26: 1
A27: Technology-specific data
B28: Indirect investment cost [M€/MW] | C28: 0.23 | D28: 0.23 | E28: 0.23 | F28: 0.23 | G28: 0.23 | L28: K, J
B29: Technology dependent
B30: - Using wood chips, and adding flue gas condenser (after economiser) increases efficiency by [%-point] | C30: 0.25 | D30: 0.25 | E30: 0.25 | F30: 0.25 | G30: 0.25 | L30: F, E | M30: [1, 3]
B31: - Using wood pellets, and adding flue gas condenser (after economiser) increases efficiency by [%-point] | C31: 0.12 | D31: 0.12 | E31: 0.12 | F31: 0.12 | G31: 0.12 | L31: E, I | M31: [1, 3]
B32: - Hot water boiler instead of steam boiler increases efficiency by [%-point] | C32: 0.01 | D32: 0.01 | E32: 0.01 | F32: 0.01 | G32: 0.01 | L32: G
B33: - Wood pellets (instead of wood chips) reduces Variable O&M by [%] | C33: 0.5 | D33: 0.5 | E33: 0.5 | F33: 0.5 | G33: 0.5 | M33: 1
A36: Notes:
A37: A | B37: Effeciency for unit with economiser (but not flue gas condenser) installed.
A38: B | B38: Values for steam boiler (see technology-specific data for differences with hot water boiler)
A39: C | B39: Values for wood chips (see technology-specific data for differences with wood pellets)
A40: D | B40: Assuming 10 starts a year.
A41: E | B41: For condensing boilers, efficiencies above 100% are possible, since the standard efficiency calculation using the lower heating value (LHV) as denominator.
A42: F | B42: Large increase in efficiency using flue gas condensen because of large water content in wood chips.
A43: G | B43: 1 %-point higher for hot water boiler, due to assumed lower flue gas temperature
A44: H | B44: Variable O&M cost includes consumables (for FGT etc.), disposal of residues, small share of staff-cost and maintenance cost
A45: I | B45: Wood pellets have lower water content than wood chips, and therefore the advantage of using flue gas condensation is smaller.
A46: J | B46: Assumed similar to gas and oil boiler.
A47: K | B47: Relevant for hot water boiler when needing to install new hot water piping instead of existing steam piping.
A49: References:
A50: 1 | B50: Danish Energy Agency, Energy Plants for Electricity and District heating generation, 2016 (updated 2025) ." 09a Wood Chips HOP (heat-only plant), small" and "09b Wood Pellets HOP"
A51: 2 | B51: Vakklianainen, Esa. Steam Generation from Biomass. 2017. (Chapter 3, Boiler processes)
A52: 3 | B52: Chen, Q., Finney, K., Li, H., Zhang, X., Zhou, J., Sharifi, V., Swithenbank, J. Condensing boiler applications in the process industry. Applied Energy, 89, 30-36, 2012
A53: 4 | B53: Tjæreborg Industri, Referenceliste for fasbrændselsanlæg (Reference list for solid fuel plants), 2024
A54: 5 | B54: Danstoker product catalogue, 2025

Sheet 6.3 Boiler, coal
A1: Technology | C1: Boiler, coal
A2: year | C2: 2025 | D2: 2030 | E2: 2035 | F2: 2040 | G2: 2050 | H2: 2025 | I2: 2025 | J2: 2050 | K2: 2050 | L2: Note | M2: Ref
A3: est | C3: ctrl | D3: ctrl | E3: ctrl | F3: ctrl | G3: ctrl | H3: lower | I3: upper | J3: lower | K3: upper | L3: - | M3: -
A4: cat | B4: par
A5: Energy/technical data
B6: Heat generation capacity for one unit [MW] | C6: 5 | D6: 5 | E6: 5 | F6: 5 | G6: 5 | H6: 1.6 | I6: 50 | J6: 1.6 | K6: 50 | M6: [3, 4]
B7: Total efficiency, net [%], nominel load | C7: 0.9 | D7: 0.9 | E7: 0.9 | F7: 0.9 | G7: 0.9 | H7: 0.88 | I7: 0.92 | J7: 0.88 | K7: 0.92 | L7: A, B, C | M7: 2
B8: Total efficiency, net [%], annual average | C8: 0.899 | D8: 0.899 | E8: 0.899 | F8: 0.899 | G8: 0.899 | H8: 0.879 | I8: 0.919 | J8: 0.879 | K8: 0.919 | L8: A, B, C, D | M8: 2
B9: Auxiliary electricity consumption [% of heat gen] | C9: 0.02 | D9: 0.02 | E9: 0.02 | F9: 0.02 | G9: 0.02 | H9: 0.02 | I9: 0.02 | J9: 0.02 | K9: 0.02 | L9: F | M9: 1
B10: Forced outage [%] | C10: 0.03 | D10: 0.03 | E10: 0.03 | F10: 0.03 | G10: 0.03 | H10: 0.03 | I10: 0.03 | J10: 0.03 | K10: 0.03 | L10: F | M10: 1
B11: Planned outage [weeks per year] | C11: 2 | D11: 2 | E11: 2 | F11: 2 | G11: 2 | H11: 1.7 | I11: 2.3 | J11: 1.5 | K11: 2.5 | L11: F | M11: 1
B12: Technical lifetime [years] | C12: 25 | D12: 25 | E12: 25 | F12: 25 | G12: 25 | H12: 20 | I12: 35 | J12: 20 | K12: 35 | L12: E, F | M12: 1
B13: Construction time [years] | C13: 1 | D13: 1 | E13: 1 | F13: 1 | G13: 1 | H13: 0.5 | I13: 1.5 | J13: 0.5 | K13: 1.5 | L13: F | M13: 1
B14: Space requirement [1000 m2/MW_e] | C14: 0.2 | D14: 0.2 | E14: 0.2 | F14: 0.2 | G14: 0.2 | H14: 0.14 | I14: 0.25 | J14: 0.12 | K14: 0.27 | L14: F | M14: 1
A15: Regulation ability
B16: Primary regulation (of full load, per 30 seconds) [%]
B17: Secondary regulation (of full load, per minute) [%] | C17: 0.1 | D17: 0.1 | E17: 0.1 | F17: 0.1 | G17: 0.1 | L17: F | M17: 1
B18: Minimum load (of full load) [%] | C18: 0.15 | D18: 0.15 | E18: 0.15 | F18: 0.15 | G18: 0.15 | L18: E | M18: 1
B19: Warm start-up time [hours] | C19: 0.25 | D19: 0.25 | E19: 0.25 | F19: 0.25 | G19: 0.25 | L19: F | M19: 1
B20: Cold start-up time [hours] | C20: 0.5 | D20: 0.5 | E20: 0.5 | F20: 0.5 | G20: 0.5 | L20: F | M20: 1
A21: Financial data
B22: Nominal investment (*total) [MEUR/MW] | C22: 0.565 | D22: 0.545 | E22: 0.533 | F22: 0.521 | G22: 0.515 | L22: F, H | M22: 1
B23: - of which equipment [%] | C23: 0.6 | D23: 0.6 | E23: 0.6 | F23: 0.6 | G23: 0.6 | M23: 1
B24: - of which installation [%] | C24: 0.4 | D24: 0.4 | E24: 0.4 | F24: 0.4 | G24: 0.4 | M24: 1
B25: Fixed O&M [EUR/MW_y] | C25: 40000 | D25: 39500 | E25: 39000 | F25: 38500 | G25: 37500 | L25: E, F | M25: 1
B26: Variable O&M [EUR/MWh] | C26: 1.45 | D26: 1.45 | E26: 1.45 | F26: 1.45 | G26: 1.45 | L26: F | M26: 1
A27: Technology-specific data
B28: Indirect investment cost [M€/MW] | C28: 0.23 | D28: 0.23 | E28: 0.23 | F28: 0.23 | G28: 0.23 | L28: I, J
B29: Technology dependent
B30: - Hot water boiler instead of steam boiler increases efficiency by [%-point] | C30: 0.01 | D30: 0.01 | E30: 0.01 | F30: 0.01 | G30: 0.01 | L30: G
A33: Notes:
A34: A | B34: Effeciency for unit with economiser (but not flue gas condenser) installed.
A35: B | B35: Values for steam boiler (see technology-specific data for differences with hot water boiler)
A36: C | B36: Flue gas condenser not possible for coal boiler, since no water vapor is present in flue gas.
A37: D | B37: Assuming 10 starts a year.
A38: E | B38: Values estimated based on "01 Coal CHP" from ref. 1.
A39: F | B39: Values estimated based on "09b Wood Pellets HOP"/"09a Wood Chips HOP, small" from ref. 1 (since they are solid fuels, and often the same boiler can used either biomass or coal)
A40: G | B40: 1 %-point higher for hot water boiler, due to assumed lower flue gas temperature
A41: H | B41: Viegand Maagøe A/S experience
A42: I | B42: Relevant for hot water boiler when needing to install new hot water piping instead of existing steam piping.
A43: J | B43: Assumed similar to gas and oil boiler.
A45: References:
A46: 1 | B46: Danish Energy Agency, Energy Plants for Electricity and District heating generation, 2016 (updated 2025).
A47: 2 | B47: Vakklianainen, Esa. Steam Generation from Biomass. 2017. (Chapter 3, Boiler processes)
A48: 3 | B48: Tjæreborg Industri, Referenceliste for fasbrændselsanlæg (Reference list for solid fuel plants), 2024
A49: 4 | B49: Danstoker product catalogue, 2025

Sheet 7.1 Direct firing Natural Gas
A1: Technology | C1: Direct firing, Natural gas
A2: year | C2: 2025 | D2: 2030 | E2: 2035 | F2: 2040 | G2: 2050 | H2: 2025 | I2: 2025 | J2: 2050 | K2: 2050 | L2: Note | M2: Ref
A3: est | C3: ctrl | D3: ctrl | E3: ctrl | F3: ctrl | G3: ctrl | H3: lower | I3: upper | J3: lower | K3: upper | L3: - | M3: -
A4: cat | B4: par
A5: Energy/technical data
B6: Heat generation capacity for one unit [MW] | C6: 2.5 | D6: 2.5 | E6: 2.5 | F6: 2.5 | G6: 2.5 | H6: 1 | I6: 10 | J6: 1 | K6: 10 | M6: 2
B7: Total efficiency, net [%], nominel load | C7: 1 | D7: 1 | E7: 1 | F7: 1 | G7: 1 | H7: 1 | I7: 1 | J7: 1 | K7: 1 | L7: A | M7: 2
B8: Total efficiency, net [%], annual average | C8: 1 | D8: 1 | E8: 1 | F8: 1 | G8: 1 | H8: 1 | I8: 1 | J8: 1 | K8: 1 | L8: A | M8: 2
B9: Auxiliary electricity consumption [% of heat gen] | C9: 0.0025 | D9: 0.0025 | E9: 0.0025 | F9: 0.0025 | G9: 0.0025 | H9: 0.001 | I9: 0.01 | J9: 0.001 | K9: 0.01 | M9: [8, 9]
B10: Forced outage [%] | C10: 0.0025 | D10: 0.0025 | E10: 0.0025 | F10: 0.0025 | G10: 0.0025 | H10: 0 | I10: 0.005 | J10: 0 | K10: 0.005 | M10: 2
B11: Planned outage [weeks per year] | C11: 0.5 | D11: 0.5 | E11: 0.5 | F11: 0.5 | G11: 0.5 | H11: 0 | I11: 1 | J11: 0 | K11: 1 | M11: 2
B12: Technical lifetime [years] | C12: 15 | D12: 15 | E12: 15 | F12: 15 | G12: 15 | H12: 10 | I12: 20 | J12: 10 | K12: 20 | M12: 4
B13: Construction time [years] | C13: 0.01 | D13: 0.01 | E13: 0.01 | F13: 0.01 | G13: 0.01 | H13: 0.01 | I13: 0.04 | J13: 0.01 | K13: 0.04 | M13: 2
A14: Regulation Ability
B15: Minimum load [% of full load] | C15: 0.1 | D15: 0.1 | E15: 0.1 | F15: 0.1 | G15: 0.1 | M15: 6
B16: Warm start-up time [hours] | C16: 0.01 | D16: 0.01 | E16: 0.01 | F16: 0.01 | G16: 0.01 | M16: 2
B17: Cold start-up time [hours] | C17: 0.01 | D17: 0.01 | E17: 0.01 | F17: 0.01 | G17: 0.01 | M17: 2
A18: Environment
B19: SO2 [g per GJ fuel] | C19: 0.3 | D19: 0.3 | E19: 0.3 | F19: 0.3 | G19: 0.3 | M19: 1
B20: PM2.5 [g per GJ fuel] | C20: 0.1 | D20: 0.1 | E20: 0.1 | F20: 0.1 | G20: 0.1 | M20: 1
B21: NOX [g per GJ fuel] | C21: 9 | D21: 7 | E21: 7 | F21: 6 | G21: 6 | M21: 1
B22: CH4 [g per GJ fuel] | C22: 3 | D22: 2 | E22: 2 | F22: 2 | G22: 2 | M22: 1
B23: N2O [g per GJ fuel] | C23: 1 | D23: 1 | E23: 1 | F23: 1 | G23: 1 | M23: 1
A24: Financial data
B25: Nominal investment [M€/MW] | C25: 0.0176 | D25: 0.0176 | E25: 0.0176 | F25: 0.0176 | G25: 0.0176 | L25: B | M25: [4, 7]
B26: - of which equipment [%] | C26: 0.66666667 | D26: 0.66666667 | E26: 0.66666667 | F26: 0.66666667 | G26: 0.66666667 | M26: 7
B27: - of which installation [%] | C27: 0.33333333 | D27: 0.33333333 | E27: 0.33333333 | F27: 0.33333333 | G27: 0.33333333 | M27: 7
B28: Fixed O&M [€/MJ/s/year] | C28: 213 | D28: 208 | E28: 205 | F28: 202 | G28: 181 | L28: C | M28: [2, 1]
B29: Variable O&M [€/MWh] | C29: 0.117 | D29: 0.105 | E29: 0.105 | F29: 0.105 | G29: 0.105 | L29: C | M29: 1
A30: Technology-specific data
B31: Indirect investments cost [M€/MW] | C31: - | D31: - | E31: - | F31: - | G31: - | L31: E | M31: -
A34: Notes:
A35: A | B35: The efficiency of the burner is set equal to the lower heating value, the process will determine how well the flue gas is utilised, and thus the final efficiency.
A36: B | B36: Unit price is based on Miton Megatherms 2.5 MW burner, installed price assessed by Viegand Maagøe. The assessment is an experience based guess as no concrete data was retrieved.
A37: C | B37: Assumed to be equal to 10% of the boiler O&M from [1].
A38: D | B38: The cost of auxiliary electricity consumption is calculated using the following electricity prices in €/MWh: 2020: 73, 2030: 75, 2040: 76, 2050: 76. Includes transport tarif
A39: E | B39: The indirect costs will be too strong a function of the process to put into a single value across all industries.
A41: References:
A42: 1 | B42: Danish Energy Agency, Technology Data Generation of Electricity and District Heating, August 2016 - Updated November 2019
A43: 2 | B43: Viegand Maagøe, Direct Firing, 2018
A44: 3 | B44: Danish Energy Agency, Forudsætninger for samfundsøkonomiske analyser på energiområdet, 2016
A45: 4 | B45: Milton Megatherm, Correspondance 2019
A46: 5 | B46: IOGP, The potential for CCS and CCU in Europe, REPORT TO THE THIRTY SECOND MEETING OF THE EUROPEAN GAS REGULATORY FORUM 5-6 JUNE 2019
A47: 6 | B47: Eclipse, Vortometric Burner Series Datasheet 128-3, 20/2/2015
A48: 7 | B48: Viegand Maagøe assessment, 2019
A49: 8 | B49: Eclipse, Eclipse AirHeat Burners Datasheet 115-11, 30/9/2010
A50: 9 | B50: Eclipse, Eclipse RatioAir Burners Datasheet 135, 21/10/2010

Sheet Agora
C3: Plant-specific data
C5: Note: This sheet lists the central sources for deriving the default values for the specific quantities used for the technologies under consideration. The reference value is the thermal production of one MWh.
C7: Natural gas steam boiler
D10: Source | E10: Unit | F10: Value | H10: Default calculated value | I10: Comment
C12: Energy usage
C13: Natural gas | D13: Calculation based on MHPS (2019) | E13: MWh/MWhth | F13: =F17/F16 -> 1.0526316 | H13: =F13 -> 1.0526316
C15: Perfomance
C16: Heat output | D16: MHPS | E16: MWth | F16: 6.7 | H16: =F16 -> 6.7
C17: Fuel consumption | D17: Calculation based on MHPS (2019) | E17: MWth | F17: =F16/(F18/100) -> 7.0526316 | H17: =F17 -> 7.0526316
C18: Efficiency | D18: MHPS | E18: % | F18: 95 | H18: =F18 -> 95
C21: Costs
C22: Full load hours | E22: h | F22: 2000 | H22: =F22 -> 2000
C23: Capex | D23: MHPS (2019) | E23: €/a | F23: 1566700 | H23: =F23 -> 1566700 | I23: 15% Capex
E24: €/kW | F24: =F23/F16/1000 -> 233.83582 | H24: =F24 -> 233.83582
C25: Opex
C26: fix
C27: maintenance costs | D27: MHPS (2019) | E27: €/MWhth (3% CAPEX) | F27: =0.03*$F$24*1000/'[7]Reference technology'!$F$22 -> 3.5075373 | H27: =F27 -> 3.5075373
C28: staff | D28: MHPS (2019) | E28: €/a (2% CAPEX) | F28: =0.02*$F$24*1000/'[7]Reference technology'!$F$22 -> 2.3383582 | H28: =F28 -> 2.3383582
C29: maintenance costs and stuff | E29: €/MWhth | F29: =SUM(F27:F28) -> 5.8458955 | H29: =F29 -> 5.8458955
C32: Natural gas CHP
D34: Source | E34: Unit | F34: Value | H34: Default calculated value | I34: Comment
C36: Perfomance
C37: Fuel consumption
D38: Konstantin P. (2017) | E38: MWth | G38: 430
D39: Calculation based on Ramboll (2020) | E39: MWth | F39: =(F42+F41)/(F49/100) -> 228.57143 | H39: =F39 -> 228.57143
C40: Electricity output
D41: Ramboll (2020) | E41: MW | F41: 80 | G41: 850 | H41: =F41 -> 80
C42: Heat output | D42: Ramboll (2020) | E42: MW | F42: =F41/F52 -> 114.28571 | G42: 430 | H42: =F42 -> 114.28571
C44: Specific natural gas consumption
C45: Natural gas | D45: Calculation based on Ramboll (2020) | E45: MWh/MWhth | G45: =(F39*'[7]Reference technology'!G55)/(F42*'[7]Reference technology'!G55) -> 2 | H45: =G45 -> 2
C47: Performance indicators
C48: Efficiency
C49: CHP total | D49: Ramboll (2020) | F49: 85 | G49: 0.9 | H49: =F49 -> 85
C50: Electric | D50: Ramboll (2020) | E50: % | F50: 35 | G50: 0.62 | H50: =F50 -> 35
C51: Thermal | D51: Ramboll (2020) | E51: % | F51: 50 | G51: 0.3 | H51: =F51 -> 50
C52: Electricity ratio | D52: Ramboll (2020) | E52: kWel/kWth | F52: 0.7 | G52: 2.1 | H52: =F52 -> 0.7 | I52: Ratio of the electricity generated by extracted heat in relation to the amount of extracted heat
C54: Costs
C55: Full usage hours | G55: 6000 | H55: =G55 -> 6000
C56: Capex
C57: FOB 400MW | D57: Konstantin P.(2017) | E57: €/KW | F57: =500*0.77 -> 385 | G57: =600*0.77 -> 462
C58: FOB 200MW | D58: Konstantin P.(2017) | E58: €/KW | F58: =600*0.77 -> 462 | G58: =700*0.77 -> 539
C59: FOB 100MW | D59: Konstantin P.(2017) | E59: €/KW | F59: =700*0.77 -> 539 | G59: =800*0.77 -> 616
C60: Transport | D60: Konstantin P.(2017) | E60: % | G60: 5 | I60: Surcharge on FOB
C61: Component | D61: Konstantin P.(2017) | E61: % | G61: 10 | I61: Surcharge on FOB
C62: Miscellaneous | D62: Konstantin P.(2017) | E62: % | G62: 30 | I62: Surcharge on FOB
C63: specific total | D63: Ramboll (2020) | E63: €/kW | G63: 900 | H63: =G63 -> 900
C64: Opex | E64: €/MWh or €/MW
C65: fix | E65: €/MWh or €/MW | G65: =G63*1000*0.02/'[7]Reference technology'!G55 -> 3 | H65: =G65 -> 3 | I65: approx. 2% of the total investment sum
C71: Plant-specific data
C73: Note: This sheet lists the central sources for deriving the default values for the specific quantities used for the technologies under consideration. The reference value is the thermal production of one MWh.
C75: Electric boiler
D78: Source | E78: Unit | F78: Range - low | G78: Range - high | H78: Default calculated value | I78: comment
C80: Energy usage
C81: Electricity | D81: Agora (2019) | E81: MWhel/MWhth | F81: =100/F83 -> 1.010101 | G81: =100/G83 -> 1.010101 | H81: =G81 -> 1.010101
C83: Utilization extent | D83: Agora (2019) | E83: % | F83: 99 | G83: 99 | H83: =G83 -> 99
D84: AGFW (2020) | E84: % | F84: 99 | G84: 99
C85: Perfomance
C86: Thermal | D86: AGFW (2020) | E86: MW | F86: 10 | G86: 40 | H86: =G86 -> 40
C87: Steam parameters
C88: Pressure | D88: Agora (2019) | E88: bar | G88: 30
D89: FFE | E89: bar | G89: 30 | I89: without super heater
C90: Temperature | D90: Agora (2019) | E90: °C | G90: 230
D91: FFE | E91: °C | G91: 240
D92: Agora (2019) | E92: °C | F92: >230 | G92: 400 | I92: can be reached by downstream electric flow heaters
C94: Costs
C95: Capex | D95: Agora (2019) | E95: €/kW | F95: 100 | G95: 250 | H95: =AVERAGE(F95:G95) -> 175 | I95: Average range
C96: Integration factor for system integration costs | H96: 1.5 | I96: Estimated surcharge to take the additional costs into account for system integration and grid connection
C97: resulting CAPEX taking the integration factor into account | H97: =H95*H96 -> 262.5 | I97: Default value times integration factor for system integration
D98: FFE | E98: €/kWel | F98: 100 | G98: 200
C99: additional grid connection for new systems | D99: Agora (2019) | E99: €/kWel | F99: =25000/1000 -> 25 | G99: =150000/1000 -> 150
D100: FFE | E100: €/kWel | F100: 25 | G100: 150
C101: Opex
C102: fix | D102: Agora (2019)/AGFW (2020) | E102: % | F102: 1 | G102: 2 | H102: =G102 -> 2 | I102: 2% Capex/year
C108: Plant-specific data
C110: Note: This sheet lists the central sources for deriving the default values for the specific quantities used for the technologies under consideration. The reference value is the thermal production of one MWh.
C112: High temperature heat pump (HT-WP) 80-100°C
D115: Source | E115: Unit | F115: Range - low | G115: Range - high | H115: Default calculated value | I115: comment
C117: Energy usage
C118: Electricity | D118: Pieper et al (2018) | E118: MWhel/MWhth | G118: =H123/G121 -> 0.27027027 | H118: =G118 -> 0.27027027
D119: EHPA (2019) | E119: MWhel/MWhth | G119: =G124/G122 -> 0.21276596
C120: Perfomance
C121: Heat output Qab | D121: Pieper et al (2018) | E121: MWth | G121: 1.3 | H121: =G121 -> 1.3
D122: EHPA (2019) | E122: MWth | G122: 9.02 | I122: 2 x 4510kw
C123: Electrical input power Pel | D123: Pieper et al (2018) | E123: MWel | G123: =G121/G134 -> 0.35135135 | H123: =G121/IF([7]Results!E138="",IF([7]Results!E134="",G134,[7]Results!E134),[7]Results!E138) -> 0.35135135 | I123: (Compressor)
D124: EHPA (2019) | E124: MWel | G124: =G122/G136 -> 1.9191489
C125: Process parameters
C126: Source temperature | D126: Pieper et al (2018) | E126: °C | G126: 30 | H126: =G126 -> 30
D127: Arpagaus (2019) | E127: °C | G127: 45 | I127: Practical example Ochsner
D128: EHPA (2019) | E128: °C | G128: 39
D129: AGFW (2020) | E129: °C | F129: 14 | G129: 50 | I129: typical range industrial waste heat
C130: Sink temperature | D130: Pieper et al (2018) | E130: °C | G130: 85 | H130: =G130 -> 85
D131: Arpagaus (2019) | E131: °C | G131: 90
D132: EHPA (2019) | E132: °C | G132: 83
D133: Dehli (2020)/IER 2017 | E133: °C | F133: 65 | G133: 110 | I133: max for new synthetic refrigerants and high-pressure compressors -> prospectively 130 °C/ 160 supercritical
C134: COP | D134: Pieper et al (2018) | E134: - | G134: 3.7 | H134: =G134 -> 3.7 | I134: =Qab/Pel
D135: Arpagaus (2019) | E135: - | G135: 4
D136: EPHA (2019) | E136: - | G136: 4.7
D137: VDE (2015) | E137: - | F137: 2.4 | G137: 7 | I137: Range dependent on temperature lift
D138: Dehli (2020) | F138: 2.4 | G138: 5.3
C140: Costs
...

Sheet Turton

Sheet 7.2 Direct firing Solid Fuels
A1: Technology | C1: Direct firing, Solid fuels
A2: year | C2: 2025 | D2: 2030 | E2: 2035 | F2: 2040 | G2: 2050 | H2: 2025 | I2: 2025 | J2: 2050 | K2: 2050 | L2: Note | M2: Ref
A3: est | C3: ctrl | D3: ctrl | E3: ctrl | F3: ctrl | G3: ctrl | H3: lower | I3: upper | J3: lower | K3: upper | L3: - | M3: -
A4: cat | B4: par
A5: Energy/technical data
B6: Heat generation capacity for one unit [MW] | C6: 10 | D6: 10 | E6: 10 | F6: 10 | G6: 10 | H6: 10 | I6: 10 | J6: 10 | K6: 10
B7: Total efficiency, net [%], nominel load | C7: 1 | D7: 1 | E7: 1 | F7: 1 | G7: 1 | H7: 1 | I7: 1 | J7: 1 | K7: 1 | L7: A | M7: 2
B8: Total efficiency, net [%], annual average | C8: 1 | D8: 1 | E8: 1 | F8: 1 | G8: 1 | H8: 1 | I8: 1 | J8: 1 | K8: 1 | L8: A | M8: 2
B9: Auxiliary electricity consumption [% of heat gen] | C9: 0.0025 | D9: 0.0025 | E9: 0.0025 | F9: 0.0025 | G9: 0.0025 | H9: 0.001 | I9: 0.01 | J9: 0.001 | K9: 0.01 | L9: B | M9: [8, 9]
B10: Forced outage [%] | C10: 0.0025 | D10: 0.0025 | E10: 0.0025 | F10: 0.0025 | G10: 0.0025 | H10: 0 | I10: 0.005 | J10: 0 | K10: 0.005 | M10: 2
B11: Planned outage [weeks per year] | C11: 3.5 | D11: 3.5 | E11: 3.5 | F11: 3.5 | G11: 3.5 | H11: 2 | I11: 5 | J11: 2 | K11: 5 | M11: 4
B12: Technical lifetime [years] | C12: 15 | D12: 15 | E12: 15 | F12: 15 | G12: 15 | H12: 10 | I12: 20 | J12: 10 | K12: 20 | M12: [2, 4]
B13: Construction time [years] | C13: 0.01 | D13: 0.01 | E13: 0.01 | F13: 0.01 | G13: 0.01 | H13: 0.001 | I13: 0.015 | J13: 0.001 | K13: 0.015 | L13: I | M13: [2, 4]
A14: Regulation Ability
B15: Minimum load [% of full load] | C15: 0.1 | D15: 0.1 | E15: 0.1 | F15: 0.1 | G15: 0.1 | M15: 6
B16: Warm start-up time [hours] | C16: 0.01 | D16: 0.01 | E16: 0.01 | F16: 0.01 | G16: 0.01 | L16: F | M16: 2
B17: Cold start-up time [hours] | C17: 0.01 | D17: 0.01 | E17: 0.01 | F17: 0.01 | G17: 0.01 | L17: F | M17: 2
A18: Environment
B19: SO2 [g per GJ fuel] | L19: D
B20: PM2.5 [g per GJ fuel] | L20: D
B21: NOX [g per GJ fuel] | L21: D
B22: CH4 [g per GJ fuel] | L22: D
B23: N2O [g per GJ fuel] | L23: D
A24: Financial data
B25: Nominal investment [M€/MW] | C25: 0.258 | D25: 0.258 | E25: 0.258 | F25: 0.258 | G25: 0.258 | L25: E, G, H | M25: [4, 7]
B26: - of which equipment [%] | C26: 0.66666667 | D26: 0.66666667 | E26: 0.66666667 | F26: 0.66666667 | G26: 0.66666667 | M26: 7
B27: - of which installation [%] | C27: 0.33333333 | D27: 0.33333333 | E27: 0.33333333 | F27: 0.33333333 | G27: 0.33333333 | M27: 7
B28: Fixed O&M [€/MJ/s/year] | C28: 3986 | D28: 3869 | E28: 3810 | F28: 3751 | G28: 3634 | L28: C | M28: [2, 1]
B29: Variable O&M [€/MWh] | C29: 0.167 | D29: 0.167 | E29: 0.167 | F29: 0.167 | G29: 0.167 | L29: C | M29: [2, 7]
A30: Technology-specific data
B31: Indirect investments cost [M€/MW] | C31: - | D31: - | E31: - | F31: - | G31: - | L31: J
A34: Notes:
A35: A | B35: The efficiency of the burner is set equal to the lower heating value, the process will determine how well the flue gas is utilised, and thus the final efficiency.
A36: B | B36: Auxilliary consumption based on gas burner as the fan power is comparable. Electricity for fuel feed systems are not included.
A37: C | B37: Assumed to be equal to 10% of the coal boiler O&M from [1]. With gaseous or liquid fuels the O&M will be lower.
A38: D | B38: Depends on the solid fuel mix used
A39: E | B39: Unit price from FLSmidth, installed price and auxilliary equipment assessed by Viegand Maagøe. The assessment is an experience based guess as no concrete data was retrieved.
A40: F | B40: The burner itself can start up quickly. However, in e.g. Cement industry the process equipment will limit the startup time to between 8 (warm) and 72 (cold) hours.
A41: G | B41: Capacity increase in multifuel burners comes with an attractive economy of scale. Going up 10 times in size will correspond toa 150% increase in pricing .
A42: H | B42: Auxilliary systems for solid fuels has been included, these correspond to a large part of the investment and will be a function of the chosen fuel.
A43: I | B43: Corresponds to a burner change, establishing a feed system has a longer construction period.
A44: J | B44: The indirect costs will be too strong a function of the process to put into a single value across all industries.
A46: References:
A47: 1 | B47: Danish Energy Agency, Technology Data Generation of Electricity and District Heating, August 2016 - Updated November 2019
A48: 2 | B48: Viegand Maagøe, Direct Firing, 2018
A49: 3 | B49: Danish Energy Agency, Forudsætninger for samfundsøkonomiske analyser på energiområdet, 2016
A50: 4 | B50: FLSmidth - Burner & PLM for HOTDISC, Correspondance 2019
A51: 5 | B51: IOGP, The potential for CCS and CCU in Europe, REPORT TO THE THIRTY SECOND MEETING OF THE EUROPEAN GAS REGULATORY FORUM 5-6 JUNE 2019
A52: 6 | B52: FCT International Burners, Correspondance 2019.
A53: 7 | B53: Viegand Maagøe assessment, 2019
A54: 8 | B54: Eclipse, Eclipse AirHeat Burners Datasheet 115-11, 30/9/2010
A55: 9 | B55: Eclipse, Eclipse RatioAir Burners Datasheet 135, 21/10/2010

Sheet 7.3 Direct electric firing
A1: Technology | C1: Direct electric heating
A2: year | C2: 2025 | D2: 2030 | E2: 2035 | F2: 2040 | G2: 2050 | H2: 2025 | I2: 2025 | J2: 2050 | K2: 2050 | L2: Note | M2: Ref
A3: est | C3: ctrl | D3: ctrl | E3: ctrl | F3: ctrl | G3: ctrl | H3: lower | I3: upper | J3: lower | K3: upper | L3: - | M3: -
A4: cat | B4: par
A5: Energy/technical data
B6: Heat generation capacity for one unit [MW] | C6: 5 | D6: 5 | E6: 5 | F6: 5 | G6: 5 | H6: 1 | I6: 10 | J6: 1 | K6: 10 | M6: [1, 2]
B7: Total efficiency, net [%], nominel load | C7: 1 | D7: 1 | E7: 1 | F7: 1 | G7: 1 | H7: 1 | I7: 1 | J7: 1 | K7: 1 | L7: A | M7: [3, 4]
B8: Total efficiency, net [%], annual average | C8: 1 | D8: 1 | E8: 1 | F8: 1 | G8: 1 | H8: 1 | I8: 1 | J8: 1 | K8: 1 | L8: A | M8: [3, 4]
B9: Auxiliary electricity consumption [% of heat gen] | C9: 0.0025 | D9: 0.0025 | E9: 0.0025 | F9: 0.0025 | G9: 0.0025 | H9: 0.001 | I9: 0.01 | J9: 0.001 | K9: 0.01 | L9: B | M9: [6, 7]
B10: Forced outage [days] | C10: 0 | D10: 0 | E10: 0 | F10: 0 | G10: 0 | H10: 0 | I10: 0.5 | J10: 0 | K10: 0.5 | L10: C | M10: 1
B11: Planned outage [weeks per year] | C11: 0 | D11: 0 | E11: 0 | F11: 0 | G11: 0 | H11: 0 | I11: 1 | J11: 0 | K11: 1 | L11: C | M11: 1
B12: Technical lifetime [years] | C12: 20 | D12: 20 | E12: 20 | F12: 20 | G12: 20 | M12: 8
B13: Construction time [years] | C13: 0.04 | D13: 0.04 | E13: 0.04 | F13: 0.04 | G13: 0.04 | M13: 1
B14: Space requirement [1000 m2/MW_e] | C14: =(1/80)/1000*1000 -> 0.0125 | D14: =(1/200)/1000*1000 -> 0.005 | E14: =(1/1000)/1000*1000 -> 0.001 | F14: =(1/1000)/1000*1000 -> 0.001 | G14: =(1/1000)/1000*1000 -> 0.001 | M14: 5
A15: Regulation ability
B16: Primary regulation (of full load, per 30 seconds) [%] | C16: 1 | D16: 1 | E16: 1 | F16: 1 | G16: 1 | L16: G | M16: 11
B17: Secondary regulation (of full load, per minute) [%] | C17: 1 | D17: 1 | E17: 1 | F17: 1 | G17: 1 | L17: G | M17: 11
B18: Minimum load [% of full load] | C18: 0.15 | D18: 0.15 | E18: 0.15 | F18: 0.15 | G18: 0.15 | L18: D | M18: 8
B19: Warm start-up time [hours] | C19: 0.01 | D19: 0.01 | E19: 0.01 | F19: 0.01 | G19: 0.01 | M19: [5, 9]
B20: Cold start-up time [hours] | C20: 0.01 | D20: 0.01 | E20: 0.01 | F20: 0.01 | G20: 0.01 | M20: [5, 9]
A21: Financial data
B22: Nominal investment (*total) [MEUR/MW] , from last update in 2019 | C22: 0.07 | D22: 0.07 | E22: 0.07 | F22: 0.07 | G22: 0.07 | L22: E, H | M22: [9, 10]
B23: - of which equipment [%] | C23: 0.66666667 | D23: 0.66666667 | E23: 0.66666667 | F23: 0.66666667 | G23: 0.66666667 | M23: 9
B24: - of which installation [%] | C24: 0.33333333 | D24: 0.33333333 | E24: 0.33333333 | F24: 0.33333333 | G24: 0.33333333 | M24: 9
B25: Fixed O&M [EUR/MW_y] | C25: 0 | D25: 0 | E25: 0 | F25: 0 | G25: 0 | L25: C | M25: 5
B26: Variable O&M [EUR/MWh] | C26: 0.235 | D26: 0.235 | E26: 0.235 | F26: 0.235 | G26: 0.235 | L26: C
A27: Technology-specific data
B28: Indirect investments cost [M€ per MW] | C28: - | D28: - | E28: - | F28: - | G28: - | L28: F
B29: Non energy gains [M€ per MW] | C29: - | D29: - | E29: - | F29: - | G29: - | L29: F
B30: Startup cost [€/MW/startup] | C30: - | D30: - | E30: - | F30: - | G30: - | L30: F
B31: Temperature heat supply, maximum [°C] | C31: 1800 | D31: 2000 | E31: 2000 | F31: 2000 | G31: 2000 | M31: [4, 5]
A34: Notes:
A35: A | B35: Transformer electricity losses are not included, and the efficiency will thus be 100%.
A36: B | B36: Auxilliary consumption estimation based on conventional industrial systems like gas burner/boilers as the fan power is comparable.
A37: C | B37: Units are composed of multiple heating elements, each unit is installed with backup elements that can be enabled if some of the elements fail, resulting in minimal downtime and O&M during the lifetime of the equipment.
A38: D | B38: The regulation is dependant on the flow conditions and the subsequent surface temperature, the chosen value is an average.
A39: E | B39: Unit price from San Electro Heat, installed price assessed by Viegand Maagøe. The assessment is an experience based guess as no concrete data was retrieved.
A40: F | B40: The indirect costs will be too strong a function of the process to put into a single value across all industries. This includes site updgrades to facilitate the installation of direct firing systems.
A41: G | B41: The electric heating element is able to adjust capacity almost instantly. The surrounding process equipment will be the limiting factor.
A42: H | B42: The cost has been corrected for inflation.
A44: References:
A45: 1 | B45: SAN Electro Heat A/S , Correspondance 2019
A46: 2 | B46: DTU, "Electrification of processes and technologies for Danish Industry: Elforsk project 350-038", 2021
A47: 3 | B47: Viegand Maagøe, Direct Firing, 2018
A48: 4 | B48: Renewable Thermal Collaborative, "Electrification Action Plan", 2024
A49: 5 | B49: Fraunhofer ISI, "Direct electrification of industrial process heat. An assessment of technologies, potentials and future prospects for the EU. Study on behalf of Agora Industry", 2024
A50: 6 | B50: Eclipse, Eclipse AirHeat Burners Datasheet 115-11, 30/9/2010
A51: 7 | B51: Eclipse, Eclipse RatioAir Burners Datasheet 135, 21/10/2010
A52: 8 | B52: Ashabi et al., "Assessing power-to-heat technologies for industrial electrification: A multi-criteria decision analysis approach", 2025
A53: 9 | B53: TNO, Technology factsheet Electric Industrial Boiler, 2018
A54: 10 | B54: Viegand Maagøe assessment, 2019
A55: 11 | B55: Energy Efficiency and Conservation Authority - New Zealand government, "Electrode and ElectricResistance Steam Generatorsand Hot Water Heaters for low carbon process heating", 2019

Sheet indst-BPFUbIP
B1: Fuel Type | C1: electricity if | D1: electricity if | E1: electricity if | F1: electricity if | G1: electricity if | H1: electricity if | I1: electricity if | J1: electricity if | L1: heavy or residual fuel oil if | M1: heavy or residual fuel oil if | N1: heavy or residual fuel oil if | O1: heavy or residual fuel oil if | P1: heavy or residual fuel oil if | Q1: heavy or residual fuel oil if | R1: heavy or residual fuel oil if | S1: heavy or residual fuel oil if | U1: petroleum diesel if | V1: petroleum diesel if | W1: petroleum diesel if | X1: petroleum diesel if | Y1: petroleum diesel if | Z1: petroleum diesel if | AA1: petroleum diesel if | AB1: petroleum diesel if | AD1: natural gas if | AE1: natural gas if | AF1: natural gas if | AG1: natural gas if | AH1: natural gas if | AI1: natural gas if | AJ1: natural gas if | AK1: natural gas if | AM1: LPG propane or butane if | AN1: LPG propane or butane if | AO1: LPG propane or butane if | AP1: LPG propane or butane if | AQ1: LPG propane or butane if | AR1: LPG propane or butane if | AS1: LPG propane or butane if | AT1: LPG propane or butane if | AV1: hard coal if | AW1: hard coal if | AX1: hard coal if | AY1: hard coal if | AZ1: hard coal if | BA1: hard coal if | BB1: hard coal if | BC1: hard coal if | BE1: biomass if | BF1: biomass if | BG1: biomass if | BH1: biomass if | BI1: biomass if | BJ1: biomass if
B2: MECS Row Adder | C2: 4 | D2: 8 | E2: 9 | F2: 10 | G2: 11 | H2: 12 | L2: 4 | M2: 8 | N2: 9 | O2: 10 | P2: 11 | Q2: 12 | U2: 4 | V2: 8 | W2: 9 | X2: 10 | Y2: 11 | Z2: 12 | AD2: 4 | AE2: 8 | AF2: 9 | AG2: 10 | AH2: 11 | AI2: 12 | AM2: 4 | AN2: 8 | AO2: 9 | AP2: 10 | AQ2: 11 | AR2: 12 | AV2: 4 | AW2: 8 | AX2: 9 | AY2: 10 | AZ2: 11 | BA2: 12
A3: MECS/Non-MECS | B3: Industry Category | C3: Boilers | D3: Nonboiler heat | E3: Cooling | F3: Machine Drive | G3: Other process | H3: Facility HVAC | I3: Facility Lighting | J3: Other Nonprocess | L3: Boilers | M3: Nonboiler heat | N3: Cooling | O3: Machine Drive | P3: Other process | Q3: Facility HVAC | R3: Facility Lighting | S3: Other Nonprocess | U3: Boilers | V3: Nonboiler heat | W3: Cooling | X3: Machine Drive | Y3: Other process | Z3: Facility HVAC | AA3: Facility Lighting | AB3: Other Nonprocess | AD3: Boilers | AE3: Nonboiler heat | AF3: Cooling | AG3: Machine Drive | AH3: Other process | AI3: Facility HVAC | AJ3: Facility Lighting | AK3: Other Nonprocess | AM3: Boilers | AN3: Nonboiler heat | AO3: Cooling | AP3: Machine Drive | AQ3: Other process | AR3: Facility HVAC | AS3: Facility Lighting | AT3: Other Nonprocess | AV3: Boilers | AW3: Nonboiler heat | AX3: Cooling | AY3: Machine Drive | AZ3: Other process | BA3: Facility HVAC | BB3: Facility Lighting | BC3: Other Nonprocess | BE3: Boilers | BF3: Nonboiler heat | BG3: Cooling | BH3: Machine Drive | BI3: Other process | BJ3: Facility HVAC | BK3: Facility Lighting | BL3: Other Nonprocess | BN3: Notes
A4: uses non-MECS EIA table | B4: agriculture and forestry 01T03 | C4: 0.1 | D4: 32.67638 | E4: 11.53284 | F4: 94.36766 | H4: 63.43062 | I4: 48.0535 | J4: 0.1 | L4: 0.1 | U4: 19.14465 | V4: 19.14465 | Z4: 19.14465 | AB4: 533.56405 | AD4: 22.13025 | AE4: 43.8605 | AG4: 20.942 | AI4: 21.93025 | AK4: 3.872 | AM4: 15.01475 | AN4: 30.0295 | AP4: 1.494 | AR4: 30.0295 | AT4: 6.197 | BE4: 48.2 | BF4: 154.173 | BN4: Buildings is assumed to be heating for barns and greenhouses, which is process heating, not non-process heating, when it is for animals or plants in agriculture. IRR = irrigation, which is assumed to be machine drive (for pumps). Also, we count municipal solid waste (which is not broken out as an industrial fuel in the EPS) as biomass.
A5: uses non-MECS EIA table | B5: coal mining 05 | F5: 14.583 | H5: 4.861 | I5: 4.861 | AB5: 57.363 | AI5: 13.858 | BN5: Electricity and diesel use are assumed to be machine drive (mining equipment, elevators, pumps, etc.) Natural gas is assumed to provide process heat.
A6: uses non-MECS EIA table | B6: oil and gas extraction 06 | F6: 76.2342 | H6: 25.4114 | I6: 25.4114 | O6: 9.46 | AB6: 169.648 | AD6: 101.6 | AE6: 271.515 | AW6: 0.16 | BF6: 8.601 | BN6: Electricity and diesel use are assumed to be machine drive (mining equipment, elevators, pumps, etc.) Other fuels are assumed to provide process heat.
A7: uses non-MECS EIA table | B7: other mining and quarrying 07T08 | F7: 66.2286 | H7: 22.0762 | I7: 22.0762 | AB7: 124.519 | AD7: 10.7 | AE7: 195.634 | AV7: 6.6 | AW7: 3.082 | BN7: Electricity and diesel use are assumed to be machine drive (mining equipment, elevators, pumps, etc.) Other fuels are assumed to provide process heat.
A8: MECS | B8: food beverage and tobacco 10T12 | C8: 11 | D8: 14 | E8: 85 | F8: 140 | G8: 7 | H8: 28 | I8: 19 | J8: 17 | L8: 0 | M8: 0 | N8: 0 | O8: 0 | P8: 0 | Q8: 0 | R8: 0 | S8: 0 | U8: 4 | V8: 0 | W8: 0.75 | X8: 0.75 | Y8: 0 | Z8: 0 | AA8: 0 | AB8: 8.5 | AD8: 533 | AE8: 219 | AF8: 15 | AG8: 24 | AH8: 15 | AI8: 72 | AJ8: 0 | AK8: 39 | AM8: 3 | AN8: 3 | AO8: 0 | AP8: 0 | AQ8: 0 | AR8: 0 | AS8: 0 | AT8: 2 | AV8: 47 | AW8: 6 | AX8: 0 | AY8: 1 | AZ8: 0 | BA8: 0 | BB8: 0 | BC8: 40 | BE8: 73.3
A9: MECS | B9: textiles apparel and leather 13T15 | C9: 1 | D9: 2 | E9: 2 | F9: 24 | G9: 0 | H9: 8 | I9: 2 | J9: 2 | L9: 0 | M9: 0 | N9: 0 | O9: 0 | P9: 0 | Q9: 0 | R9: 0 | S9: 0 | U9: 0 | V9: 0 | W9: 0 | X9: 0 | Y9: 0 | Z9: 0 | AA9: 0 | AB9: 0 | AD9: 13 | AE9: 14 | AF9: 0 | AG9: 1 | AH9: 0 | AI9: 4 | AJ9: 0 | AK9: 2 | AM9: 0 | AN9: 0 | AO9: 0 | AP9: 0 | AQ9: 0 | AR9: 0 | AS9: 0 | AT9: 0 | AV9: 0 | AW9: 0 | AX9: 0 | AY9: 0 | AZ9: 0 | BA9: 0 | BB9: 0 | BC9: 0
A10: MECS | B10: wood products 16 | C10: 2 | D10: 6 | E10: 1 | F10: 47 | G10: 2 | H10: 4 | I10: 4 | J10: 2 | L10: 0 | M10: 0 | N10: 0 | O10: 0 | P10: 0 | Q10: 0 | R10: 0 | S10: 0 | U10: 1 | V10: 1 | W10: 0 | X10: 1 | Y10: 0 | Z10: 0 | AA10: 0 | AB10: 7 | AD10: 17 | AE10: 50 | AF10: 0 | AG10: 2 | AH10: 2 | AI10: 7 | AJ10: 0 | AK10: 1 | AM10: 0 | AN10: 0 | AO10: 0 | AP10: 0 | AQ10: 0 | AR10: 0 | AS10: 0 | AT10: 2 | AV10: 0 | AW10: 0 | AX10: 0 | AY10: 0 | AZ10: 0 | BA10: 0 | BB10: 0 | BC10: 0 | BE10: 470.5
A11: MECS | B11: pulp paper and printing 17T18 | C11: 4 | D11: 8 | E11: 7 | F11: 142 | G11: 3 | H11: 15 | I11: 13 | J11: 15 | L11: 7 | M11: 0 | N11: 0 | O11: 0 | P11: 0 | Q11: 0 | R11: 0 | S11: 0 | U11: 2 | V11: 0 | W11: 0 | X11: 0 | Y11: 0 | Z11: 0 | AA11: 0 | AB11: 2 | AD11: 411 | AE11: 153 | AF11: 2 | AG11: 24 | AH11: 3 | AI11: 27 | AJ11: 0 | AK11: 16 | AM11: 0 | AN11: 0 | AO11: 0 | AP11: 0 | AQ11: 0 | AR11: 0 | AS11: 0 | AT11: 2 | AV11: 32 | AW11: 0 | AX11: 0 | AY11: 0 | AZ11: 0 | BA11: 0 | BB11: 0 | BC11: 0 | BE11: 491.33 | BF11: 491.33 | BN11: For biomass, we assume energy use is split evenly between boilers and non-boiler process heating (such as drying).
A12: MECS | B12: refined petroleum and coke 19 | C12: 0 | D12: 0 | E12: 7 | F12: 142 | G12: 5 | H12: 3 | I12: 3 | J12: 1 | L12: 0 | M12: 2 | N12: 0 | O12: 0 | P12: 0 | Q12: 0 | R12: 0 | S12: 0 | U12: 0 | V12: 1 | W12: 0 | X12: 2 | Y12: 0 | Z12: 0 | AA12: 0 | AB12: 2 | AD12: 348 | AE12: 623 | AF12: 6 | AG12: 15 | AH12: 56 | AI12: 5 | AJ12: 0 | AK12: 43 | AM12: 5 | AN12: 22 | AO12: 0 | AP12: 0 | AQ12: 0 | AR12: 0 | AS12: 0 | AT12: 0 | AV12: 0 | AW12: 0 | AX12: 0 | AY12: 0 | AZ12: 0 | BA12: 0 | BB12: 0 | BC12: 0
A13: MECS | B13: chemicals 20 | C13: 14 | D13: 21 | E13: 43 | F13: 278 | G13: 56 | H13: 40 | I13: 19 | J13: 41 | L13: 0 | M13: 0 | N13: 0 | O13: 0 | P13: 0 | Q13: 0 | R13: 0 | S13: 0 | U13: 3 | V13: 0 | W13: 0 | X13: 1 | Y13: 1 | Z13: 0 | AA13: 0 | AB13: 2 | AD13: 1440 | AE13: 771 | AF13: 11 | AG13: 126 | AH13: 152 | AI13: 60 | AJ13: 0 | AK13: 25 | AM13: 3 | AN13: 7 | AO13: 0 | AP13: 0 | AQ13: 3 | AR13: 0 | AS13: 0 | AT13: 2 | AV13: 17 | AW13: 2 | AX13: 0 | AY13: 0 | AZ13: 7 | BA13: 0 | BB13: 0 | BC13: 36
A14: MECS | B14: rubber and plastic products 22 | C14: 8 | D14: 21 | E14: 24 | F14: 114 | G14: 5 | H14: 32 | I14: 22 | J14: 15 | L14: 0 | M14: 0 | N14: 0 | O14: 0 | P14: 0 | Q14: 0 | R14: 0 | S14: 0 | U14: 0 | V14: 0 | W14: 0 | X14: 0 | Y14: 0 | Z14: 0 | AA14: 0 | AB14: 0 | AD14: 43 | AE14: 27 | AF14: 0 | AG14: 7 | AH14: 3 | AI14: 24 | AJ14: 0 | AK14: 2 | AM14: 0 | AN14: 0 | AO14: 0 | AP14: 2 | AQ14: 0 | AR14: 0 | AS14: 0 | AT14: 2 | AV14: 0 | AW14: 0 | AX14: 0 | AY14: 0 | AZ14: 0 | BA14: 0 | BB14: 0 | BC14: 0
A15: MECS | B15: glass and glass products 231 | C15: 0 | D15: 19 | E15: 5 | F15: 15 | G15: 2 | H15: 4 | I15: 2 | J15: 0 | L15: 0 | M15: 0 | N15: 0 | O15: 0 | P15: 0 | Q15: 0 | R15: 0 | S15: 0 | U15: 0 | V15: 0 | W15: 0 | X15: 0 | Y15: 0 | Z15: 0 | AA15: 0 | AB15: 0 | AD15: 3 | AE15: 117 | AF15: 2 | AG15: 6 | AH15: 0 | AI15: 9 | AJ15: 0 | AK15: 1 | AM15: 0 | AN15: 0 | AO15: 0 | AP15: 0 | AQ15: 0 | AR15: 0 | AS15: 0 | AT15: 0 | AV15: 0 | AW15: 0 | AX15: 0 | AY15: 0 | AZ15: 0 | BA15: 0 | BB15: 0 | BC15: 0
A16: MECS | B16: cement and other nonmetallic minerals 239 | C16: 0 | D16: 7 | E16: 2 | F16: 44 | G16: 3 | H16: 1 | I16: 1 | J16: 0 | L16: 0 | M16: 0 | N16: 0 | O16: 0 | P16: 0 | Q16: 0 | R16: 0 | S16: 0 | U16: 0 | V16: 1 | W16: 0 | X16: 0 | Y16: 0 | Z16: 0 | AA16: 0 | AB16: 3 | AD16: 3 | AE16: 192 | AF16: 1 | AG16: 9 | AH16: 1 | AI16: 4 | AJ16: 0 | AK16: 4 | AM16: 0 | AN16: 0 | AO16: 0 | AP16: 0 | AQ16: 0 | AR16: 0 | AS16: 0 | AT16: 0 | AV16: 0 | AW16: 176 | AX16: 0 | AY16: 2 | AZ16: 0 | BA16: 0 | BB16: 0 | BC16: 0 | BF16: 43.452
A17: MECS | B17: iron and steel 241 | C17: 1 | D17: 63 | E17: 4 | F17: 97.619718 | G17: 32.380282 | H17: 10 | I17: 8 | J17: 4 | L17: 0 | M17: 0 | N17: 0 | O17: 0 | P17: 0 | Q17: 0 | R17: 0 | S17: 2 | U17: 0 | V17: 0 | W17: 0 | X17: 0 | Y17: 0 | Z17: 0 | AA17: 0 | AB17: 5 | AD17: 52 | AE17: 324 | AF17: 3 | AG17: 6 | AH17: 27 | AI17: 26 | AJ17: 0 | AK17: 4 | AM17: 0 | AN17: 0 | AO17: 0 | AP17: 0 | AQ17: 0 | AR17: 0 | AS17: 0 | AT17: 0 | AV17: 2 | AW17: 5 | AX17: 0 | AY17: 0 | AZ17: 9 | BA17: 0 | BB17: 0 | BC17: 1
A18: MECS | B18: other metals 242 | C18: 0 | D18: 25 | E18: 4 | F18: 50.473684 | G18: 54.526316 | H18: 6 | I18: 5 | J18: 2 | L18: 0 | M18: 0 | N18: 0 | O18: 0 | P18: 0 | Q18: 0 | R18: 0 | S18: 0 | U18: 0 | V18: 0 | W18: 0 | X18: 0 | Y18: 0 | Z18: 0 | AA18: 0 | AB18: 1 | AD18: 33 | AE18: 200 | AF18: 0 | AG18: 15 | AH18: 6 | AI18: 19 | AJ18: 0 | AK18: 3 | AM18: 1 | AN18: 1 | AO18: 0 | AP18: 0 | AQ18: 0 | AR18: 0 | AS18: 0 | AT18: 1 | AV18: 0 | AW18: 0 | AX18: 0 | AY18: 0 | AZ18: 0 | BA18: 0 | BB18: 0 | BC18: 0
A19: MECS | B19: metal products except machinery and vehicles 25 | C19: 1 | D19: 22 | E19: 3 | F19: 66 | G19: 9 | H19: 20 | I19: 12 | J19: 10 | L19: 0 | M19: 0 | N19: 0 | O19: 0 | P19: 0 | Q19: 0 | R19: 0 | S19: 0 | U19: 0 | V19: 0 | W19: 0 | X19: 0 | Y19: 0 | Z19: 0 | AA19: 0 | AB19: 2 | AD19: 51 | AE19: 175 | AF19: 0 | AG19: 3 | AH19: 2 | AI19: 40 | AJ19: 0 | AK19: 4 | AM19: 0 | AN19: 0 | AO19: 0 | AP19: 1 | AQ19: 0 | AR19: 1 | AS19: 0 | AT19: 2 | AV19: 0 | AW19: 0 | AX19: 0 | AY19: 0 | AZ19: 0 | BA19: 0 | BB19: 0 | BC19: 0
A20: MECS | B20: computers and electronics 26 | C20: 1 | D20: 5 | E20: 12 | F20: 20 | G20: 21 | H20: 21 | I20: 7 | J20: 7 | L20: 0 | M20: 0 | N20: 0 | O20: 0 | P20: 0 | Q20: 0 | R20: 0 | S20: 0 | U20: 0 | V20: 0 | W20: 0 | X20: 0 | Y20: 0 | Z20: 0 | AA20: 0 | AB20: 0 | AD20: 8 | AE20: 5 | AF20: 0 | AG20: 2 | AH20: 1 | AI20: 13 | AJ20: 0 | AK20: 3 | AM20: 0 | AN20: 0 | AO20: 0 | AP20: 0 | AQ20: 0 | AR20: 0 | AS20: 0 | AT20: 0 | AV20: 0 | AW20: 0 | AX20: 0 | AY20: 0 | AZ20: 0 | BA20: 0 | BB20: 0 | BC20: 0
A21: MECS | B21: appliances and electrical equipment 27 | C21: 0 | D21: 5 | E21: 1 | F21: 15 | G21: 4 | H21: 7 | I21: 3 | J21: 4 | L21: 0 | M21: 0 | N21: 0 | O21: 0 | P21: 0 | Q21: 0 | R21: 0 | S21: 0 | U21: 0 | V21: 0 | W21: 0 | X21: 0 | Y21: 0 | Z21: 0 | AA21: 0 | AB21: 0 | AD21: 5 | AE21: 16 | AF21: 0 | AG21: 2 | AH21: 1 | AI21: 10 | AJ21: 0 | AK21: 3 | AM21: 0 | AN21: 0 | AO21: 0 | AP21: 0 | AQ21: 0 | AR21: 0 | AS21: 0 | AT21: 0 | AV21: 0 | AW21: 0 | AX21: 0 | AY21: 0 | AZ21: 0 | BA21: 0 | BB21: 0 | BC21: 0
A22: MECS | B22: other machinery 28 | C22: 0 | D22: 4 | E22: 3 | F22: 31 | G22: 3 | H22: 15 | I22: 7 | J22: 12 | L22: 0 | M22: 0 | N22: 0 | O22: 0 | P22: 0 | Q22: 0 | R22: 0 | S22: 0 | U22: 0 | V22: 0 | W22: 0 | X22: 0 | Y22: 3 | Z22: 0 | AA22: 0 | AB22: 0 | AD22: 5 | AE22: 20 | AF22: 1 | AG22: 3 | AH22: 1 | AI22: 25 | AJ22: 0 | AK22: 5 | AM22: 0 | AN22: 2 | AO22: 0 | AP22: 0 | AQ22: 0 | AR22: 1 | AS22: 0 | AT22: 1 | AV22: 0 | AW22: 0 | AX22: 0 | AY22: 0 | AZ22: 0 | BA22: 0 | BB22: 0 | BC22: 0
A23: MECS | B23: road vehicles 29 | C23: 1 | D23: 1 | E23: 2 | F23: 13 | G23: 1 | H23: 6 | I23: 2 | J23: 1 | L23: 0 | M23: 0 | N23: 0 | O23: 0 | P23: 0 | Q23: 0 | R23: 0 | S23: 0 | U23: 0 | V23: 0 | W23: 0 | X23: 0 | Y23: 0 | Z23: 0 | AA23: 0 | AB23: 0 | AD23: 4 | AE23: 24 | AF23: 0 | AG23: 0 | AH23: 1 | AI23: 10 | AJ23: 0 | AK23: 1 | AM23: 0 | AN23: 0 | AO23: 0 | AP23: 0 | AQ23: 0 | AR23: 0 | AS23: 0 | AT23: 0 | AV23: 0 | AW23: 0 | AX23: 0 | AY23: 0 | AZ23: 0 | BA23: 0 | BB23: 0 | BC23: 0
A24: MECS | B24: nonroad vehicles 30 | C24: 0 | D24: 4 | E24: 3 | F24: 9 | G24: 1 | H24: 8 | I24: 5 | J24: 1 | L24: 0 | M24: 0 | N24: 0 | O24: 0 | P24: 0 | Q24: 0 | R24: 0 | S24: 0 | U24: 0 | V24: 0 | W24: 0 | X24: 0 | Y24: 0 | Z24: 0 | AA24: 0 | AB24: 0 | AD24: 9 | AE24: 6 | AF24: 0 | AG24: 0 | AH24: 1 | AI24: 9 | AJ24: 0 | AK24: 2 | AM24: 0 | AN24: 0 | AO24: 0 | AP24: 0 | AQ24: 0 | AR24: 0 | AS24: 0 | AT24: 0 | AV24: 0 | AW24: 0 | AX24: 0 | AY24: 0 | AZ24: 0 | BA24: 0 | BB24: 0 | BC24: 0
A25: MECS | B25: other manufacturing 31T33 | C25: 0 | D25: 1 | E25: 5 | F25: 24 | G25: 2 | H25: 17 | I25: 9.3333333 | J25: 5.6666667 | L25: 0 | M25: 0 | N25: 0 | O25: 0 | P25: 0 | Q25: 0 | R25: 0 | S25: 0 | U25: 0 | V25: 0 | W25: 0 | X25: 0 | Y25: 0 | Z25: 0 | AA25: 0 | AB25: 0 | AD25: 4 | AE25: 14 | AF25: 0 | AG25: 0 | AH25: 0 | AI25: 16 | AJ25: 0 | AK25: 2 | AM25: 0 | AN25: 0 | AO25: 0 | AP25: 0 | AQ25: 0 | AR25: 0 | AS25: 0 | AT25: 0 | AV25: 0 | AW25: 0 | AX25: 0 | AY25: 0 | AZ25: 0 | BA25: 0 | BB25: 0 | BC25: 0 | BE25: 22.6
A26: see notes below | B26: energy pipelines and gas processing 352T353 | F26: 1 | O26: 1 | X26: 1 | AG26: 1 | AP26: 1 | AY26: 1 | BH26: 1 | BN26: The energy here is assumed to be largely pipelines, not natural gas processing. Energy use is dominated by pumps to move fluid, which is machine drive.
A27: see notes below | B27: water and waste 36T39 | F27: 1 | L27: 1 | U27: 1 | AD27: 1 | AM27: 1 | AV27: 1 | BE27: 1 | BN27: See notes below on this sheet.
A28: uses non-MECS EIA table | B28: construction 41T43 | F28: 156.1992 | H28: 52.0664 | I28: 52.0664 | AB28: 591.685 | AE28: 217.392 | AT28: 20.682 | BN28: Electricity and diesel use are assumed to be machine drive (construction equipment). Other fuels are assumed to provide process heat.
A30: Note on MECS Rows / Categories
A31: In cases where the EPS industry category is the sum of several MECS categories, we just take the most representative and/or largest MECS category, | AB31: Note: "other nonprocess" covers several categories, as you can see in Table 5.2: in MECS, it sums
A32: which simplifies the formulas greatly and shouldn't meaningfully affect the results, as all we care about here are the percentages of energy use by industrial process, | AB32: onsite transportation, facility support, and onsite electricity generation (e.g., generators).
A33: not the total quantities of energy use.
AB34: For non-manufacturing industries, the biggest contributor is mobile equipment like agricultural
A35: Note on Excluded Energy Uses | AB35: tractors, offroad construction equipment and mobile mining equipment. The file indst/PoONEUTiMEbIC
A36: Nonprocess uses (building HVAC, on-site vehicles like farm vehicles and forklifts) are omitted. | AB36: defines the share of other nonprocess equipment is mobile equipment. This is important because
A37: Heating barns and greenhouses to grow animals and plants is considered a process use, not a non-process use, even though it is heating of buildings. | AB37: both the technologies and policies for decarbonizing as well as the costs of these sources are quite
AB38: different from stationary equipment.
A39: Note on Water and Waste Industry
A40: Solid waste is dominated by vehicles (waste hauling trucks), which are considered nonprocess uses and are excluded.
A41: Water treatment is mostly electricity, but fossil fuels are sometimes used for multi-effect distillation and flash distillation,
A42: both of which involve boiling water. Since the fuel is being used to boil water, we categorize it as "boilers," even if the
A43: equipment involved may not techically be a "boiler."
A44: See Figure 8 on page 28 of the IEA Water-Energy Nexus report (2016) and the "Thermal" explanation on page 36, at:
A45: https://iea.blob.core.windows.net/assets/e4a7e1a5-b6ed-4f36-911f-b0111e49aab9/WorldEnergyOutlook2016ExcerptWaterEnergyNexus.pdf
A46: We arbitrarily assign "1" to boilers and "0" to other rows to achieve a 100% value for boilers.
A47: For electricity, energy use is dominated by pumping and water transfer, which is machine drive, and even treatment steps use electricity for machine drive.

Sheet indst heat consumption
D2: Temperature mapping | I2: Share of all energy for heat at various temp bands
B3: Industry Category | C3: Share of all industry boiler/nonboiler heat | D3: < 100°C | E3: 100-200°C | F3: 200-500°C | G3: 500-1000°C | H3: > 1000°C | I3: < 100°C | J3: 100-200°C | K3: 200-500°C | L3: 500-1000°C | M3: > 1000°C | N3: QTR PH loss share (Ref 36)
B4: agriculture and forestry 01T03 | C4: 0.041094089 | D4: 1 | E4: 0 | F4: 0 | G4: 0 | H4: 0 | I4: =$C4*D4/SUMPRODUCT($C$4:$C$28,D$4:D$28) -> 0.18630249 | J4: =$C4*E4/SUMPRODUCT($C$4:$C$28,E$4:E$28) -> 0 | K4: =$C4*F4/SUMPRODUCT($C$4:$C$28,F$4:F$28) -> 0 | L4: =$C4*G4/SUMPRODUCT($C$4:$C$28,G$4:G$28) -> 0 | M4: =$C4*H4/SUMPRODUCT($C$4:$C$28,H$4:H$28) -> 0 | N4: 0.39
B5: coal mining 05 | C5: 0 | D5: 1 | E5: 0 | F5: 0 | G5: 0 | H5: 0 | I5: =$C5*D5/SUMPRODUCT($C$4:$C$28,D$4:D$28) -> 0 | J5: =$C5*E5/SUMPRODUCT($C$4:$C$28,E$4:E$28) -> 0 | K5: =$C5*F5/SUMPRODUCT($C$4:$C$28,F$4:F$28) -> 0 | L5: =$C5*G5/SUMPRODUCT($C$4:$C$28,G$4:G$28) -> 0 | M5: =$C5*H5/SUMPRODUCT($C$4:$C$28,H$4:H$28) -> 0 | N5: 0.39
B6: oil and gas extraction 06 | C6: 0.040805825 | D6: 0.076923077 | E6: 0.25213675 | F6: 0.53205128 | G6: 0.13888889 | H6: 0 | I6: =$C6*D6/SUMPRODUCT($C$4:$C$28,D$4:D$28) -> 0.014230433 | J6: =$C6*E6/SUMPRODUCT($C$4:$C$28,E$4:E$28) -> 0.054733821 | K6: =$C6*F6/SUMPRODUCT($C$4:$C$28,F$4:F$28) -> 0.05537122 | L6: =$C6*G6/SUMPRODUCT($C$4:$C$28,G$4:G$28) -> 0.07021543 | M6: =$C6*H6/SUMPRODUCT($C$4:$C$28,H$4:H$28) -> 0 | N6: 0.18
B7: other mining and quarrying 07T08 | C7: 0.023082653 | D7: 1 | E7: 0 | F7: 0 | G7: 0 | H7: 0 | I7: =$C7*D7/SUMPRODUCT($C$4:$C$28,D$4:D$28) -> 0.10464658 | J7: =$C7*E7/SUMPRODUCT($C$4:$C$28,E$4:E$28) -> 0 | K7: =$C7*F7/SUMPRODUCT($C$4:$C$28,F$4:F$28) -> 0 | L7: =$C7*G7/SUMPRODUCT($C$4:$C$28,G$4:G$28) -> 0 | M7: =$C7*H7/SUMPRODUCT($C$4:$C$28,H$4:H$28) -> 0 | N7: 0.39
B8: food beverage and tobacco 10T12 | C8: 0.097591785 | D8: 0.23333333 | E8: 0.25555556 | F8: 0.51111111 | G8: 0 | H8: 0 | I8: =$C8*D8/SUMPRODUCT($C$4:$C$28,D$4:D$28) -> 0.10323557 | J8: =$C8*E8/SUMPRODUCT($C$4:$C$28,E$4:E$28) -> 0.13267712 | K8: =$C8*F8/SUMPRODUCT($C$4:$C$28,F$4:F$28) -> 0.12721462 | L8: =$C8*G8/SUMPRODUCT($C$4:$C$28,G$4:G$28) -> 0 | M8: =$C8*H8/SUMPRODUCT($C$4:$C$28,H$4:H$28) -> 0 | N8: 0.56
B9: textiles apparel and leather 13T15 | C9: 0.0032056866 | D9: 0.47272727 | E9: 0.17575758 | F9: 0.35151515 | G9: 0 | H9: 0 | I9: =$C9*D9/SUMPRODUCT($C$4:$C$28,D$4:D$28) -> 0.0068702259 | J9: =$C9*E9/SUMPRODUCT($C$4:$C$28,E$4:E$28) -> 0.0029973162 | K9: =$C9*F9/SUMPRODUCT($C$4:$C$28,F$4:F$28) -> 0.0028739125 | L9: =$C9*G9/SUMPRODUCT($C$4:$C$28,G$4:G$28) -> 0 | M9: =$C9*H9/SUMPRODUCT($C$4:$C$28,H$4:H$28) -> 0 | N9: 0.56
B10: wood products 16 | C10: 0.05850378 | D10: 0.11764706 | E10: 0.29411765 | F10: 0.58823529 | G10: 0 | H10: 0 | I10: =$C10*D10/SUMPRODUCT($C$4:$C$28,D$4:D$28) -> 0.031203571 | J10: =$C10*E10/SUMPRODUCT($C$4:$C$28,E$4:E$28) -> 0.091538218 | K10: =$C10*F10/SUMPRODUCT($C$4:$C$28,F$4:F$28) -> 0.087769462 | L10: =$C10*G10/SUMPRODUCT($C$4:$C$28,G$4:G$28) -> 0 | M10: =$C10*H10/SUMPRODUCT($C$4:$C$28,H$4:H$28) -> 0 | N10: 0.72
B11: pulp paper and printing 17T18 | C11: 0.17093362 | D11: 0.34666667 | E11: 0.20444444 | F11: 0.41555556 | G11: 0.033333333 | H11: 0 | I11: =$C11*D11/SUMPRODUCT($C$4:$C$28,D$4:D$28) -> 0.26864507 | J11: =$C11*E11/SUMPRODUCT($C$4:$C$28,E$4:E$28) -> 0.18590893 | K11: =$C11*F11/SUMPRODUCT($C$4:$C$28,F$4:F$28) -> 0.18116113 | L11: =$C11*G11/SUMPRODUCT($C$4:$C$28,G$4:G$28) -> 0.070590966 | M11: =$C11*H11/SUMPRODUCT($C$4:$C$28,H$4:H$28) -> 0 | N11: 0.72
B12: refined petroleum and coke 19 | C12: 0.10696308 | D12: 0.076923077 | E12: 0.25213675 | F12: 0.53205128 | G12: 0.13888889 | H12: 0 | I12: =$C12*D12/SUMPRODUCT($C$4:$C$28,D$4:D$28) -> 0.037301803 | J12: =$C12*E12/SUMPRODUCT($C$4:$C$28,E$4:E$28) -> 0.14347211 | K12: =$C12*F12/SUMPRODUCT($C$4:$C$28,F$4:F$28) -> 0.1451429 | L12: =$C12*G12/SUMPRODUCT($C$4:$C$28,G$4:G$28) -> 0.18405358 | M12: =$C12*H12/SUMPRODUCT($C$4:$C$28,H$4:H$28) -> 0 | N12: 0.18
B13: chemicals 20 | C13: 0.24341847 | D13: 0.076923077 | E13: 0.25213675 | F13: 0.53205128 | G13: 0.13888889 | H13: 0 | I13: =$C13*D13/SUMPRODUCT($C$4:$C$28,D$4:D$28) -> 0.084888619 | J13: =$C13*E13/SUMPRODUCT($C$4:$C$28,E$4:E$28) -> 0.32650296 | K13: =$C13*F13/SUMPRODUCT($C$4:$C$28,F$4:F$28) -> 0.33030523 | L13: =$C13*G13/SUMPRODUCT($C$4:$C$28,G$4:G$28) -> 0.4188552 | M13: =$C13*H13/SUMPRODUCT($C$4:$C$28,H$4:H$28) -> 0 | N13: 0.23
B14: rubber and plastic products 22 | C14: 0.010578766 | D14: 0.076923077 | E14: 0.25213675 | F14: 0.53205128 | G14: 0.13888889 | H14: 0 | I14: =$C14*D14/SUMPRODUCT($C$4:$C$28,D$4:D$28) -> 0.0036891893 | J14: =$C14*E14/SUMPRODUCT($C$4:$C$28,E$4:E$28) -> 0.014189549 | K14: =$C14*F14/SUMPRODUCT($C$4:$C$28,F$4:F$28) -> 0.014354793 | L14: =$C14*G14/SUMPRODUCT($C$4:$C$28,G$4:G$28) -> 0.018203101 | M14: =$C14*H14/SUMPRODUCT($C$4:$C$28,H$4:H$28) -> 0 | N14: 0.23
B15: glass and glass products 231 | C15: 0.014853014 | D15: 0 | E15: 0 | F15: 0.012820513 | G15: 0.064102564 | H15: 0.92307692 | I15: =$C15*D15/SUMPRODUCT($C$4:$C$28,D$4:D$28) -> 0 | J15: =$C15*E15/SUMPRODUCT($C$4:$C$28,E$4:E$28) -> 0 | K15: =$C15*F15/SUMPRODUCT($C$4:$C$28,F$4:F$28) -> 0.00048565564 | L15: =$C15*G15/SUMPRODUCT($C$4:$C$28,G$4:G$28) -> 0.011795949 | M15: =$C15*H15/SUMPRODUCT($C$4:$C$28,H$4:H$28) -> 0.11556765 | N15: 0.55
... B28: construction 41T43 | C28: 0.023229687 | D28: 1 | E28: 0 | F28: 0 | G28: 0 | H28: 0 | I28: =$C28*D28/SUMPRODUCT($C$4:$C$28,D$4:D$28) -> 0.10531316 | J28: =$C28*E28/SUMPRODUCT($C$4:$C$28,E$4:E$28) -> 0 | K28: =$C28*F28/SUMPRODUCT($C$4:$C$28,F$4:F$28) -> 0 | L28: =$C28*G28/SUMPRODUCT($C$4:$C$28,G$4:G$28) -> 0 | M28: =$C28*H28/SUMPRODUCT($C$4:$C$28,H$4:H$28) -> 0 | N28: 0.39
C29: * from indst/BPFUbIP file
