Workbook
Name Eno_TM: #REF!
Name Eno_Tons: #REF!
Name Sum_T2: #REF!
Name Sum_TTM: #REF!
Name ti_tbl_50: #REF!
Name ti_tbl_69: #REF!
Name TitleRegion1.f2.y3.5: #REF!
Name TitleRegion1.f3.n4.5: #REF!
Name TitleRegion2.e6.y15.5: #REF!
Name TitleRegion2.e8.n17.5: #REF!
Name TitleRegion3.c19.y51.5: #REF!
Name TitleRegion3.c24.n53.5: #REF!
Name TitleRegion4.e54.y63.5: #REF!
Name TitleRegion4.e57.n66.5: #REF!
Name TitleRegion5.d68.y124.5: #REF!
Name TitleRegion5.d73.n129.5: #REF!

Sheet About
A1: AVLo Average Vehicle Loading
A3: Sources: | B3: passenger LDVs | D3: Bus and rail ridership recovery (loading paths)
B4: U.S. Federal Highway Administration | D4: U.S. Energy Information Administration
B5: 2009 | D5: National Energy Modeling System, AEO 2026 public release, input/tdm/trnldvx.xlsx (TBCOVID, TMCOVID, TRCOVID, CRCOVID and their coefficients; TBPMTHIST, TRRPMHIST, CRRPMHIST) and tran.f
B6: 2009 National Household Travel Survey | D6: 2026
B7: http://nhts.ornl.gov/2009/pub/stt.pdf | D7: https://github.com/EIAgov/NEMS/tree/AEO2026-Public-Release/input/tdm
B8: Page 33, Table 16 | D8: Pasted on tabs 'NEMS bus covid' and 'NEMS rail covid'. NEMS projects transit, intercity and school bus travel and transit and commuter rail travel with recovery terms that fade through the 2030s; the ratio of the recovery factor in each year to its 2024 value is the loading multiplier. Use only for the post-2020 recovery, not as a general ridership forecast.
B10: freight HDVs | D10: Rail passengers per car-mile (check on the start-year value)
B11: U.S. DOT FHA Office of Freight Management and Operations | D11: Federal Transit Administration, National Transit Database
B12: 2008 | D12: NTD Annual Data, Service Data and Operating Expenses by Mode, Time Series 2.1
B13: Major Freight Corridors | D13: 2025
B14: http://ops.fhwa.dot.gov/freight/freight_analysis/freight_story/major.htm | D14: https://data.transportation.gov/Public-Transit/2024-NTD-Annual-Data-Service-Data-and-Operating-Exp/npsm-38gk
B15: Second bullet point on webpage (and Fig. 8 image caption) | D15: Passenger-miles over car revenue miles across the rail modes: 27.6 in 2019, 19.1 in 2024, with car-miles back to 97% of 2019. Supports treating the recovery as riders per car. The start-year loading itself comes from the NTD agency tables pasted here.
B17: Passenger HDVs, both types of aircraft, freigt rail, freight ships, passenger motorbikes
B18: U.S. Bureau of Transportation Statistics
B19: 2016
B20: National Transportation Statistics (most recently updated tables updated in October 2016)
B21: http://www.rita.dot.gov/bts/sites/rita.dot.gov.bts/files/publications/national_transportation_statistics/index.html#appendix_d
B22: Appendix D - Modal Profiles
B23: Air Carrier Profile
B24: Bus Profile
B25: Transit Profile
B26: Rail Profile
B27: Water Transport Profile
B28: Automobile Profile
B30: passenger ships
B31: U.S. Coast Guard
B32: 2013
B33: National Recreational Boating Survey 2012
B34: http://www.uscgboating.org/library/recreational-boating-servey/2012survey%20report.pdf
B35: Page 63, Table 40
B37: Rail-passenger data
B38: National Transit Database Tables
B39: American Public Transportation Association
B40: 2020
B41: https://www.apta.com/research-technical-resources/transit-statistics/ntd-data-tables/
A44: Notes:
A45: What this file is | B45: Average load per vehicle: passengers per vehicle for passenger types and tons per vehicle for freight types, in the start year (SYAVLo) and along the model run (AVLo). With the fleet and the miles per vehicle it converts AEO's passenger-miles and ton-miles into vehicles. The values are constant over time except where the notes below say otherwise; the 'bus loading' and 'rail loading' tabs hold the two paths that change. The dark-blue tabs are exported.
A46: Passenger LDVs | B46: 1.67 passengers per vehicle from the 2009 National Household Travel Survey, constant.
A47: Buses | B47: Distance-weighted passengers per bus from the BTS bus profile for the start year, then rising with NEMS's recovery terms for transit, intercity and school bus travel, weighted by their 2019 passenger-miles: about 10% higher by 2035. NEMS treats the return of bus ridership after 2020 as more riders on the existing fleet; carrying it in loading keeps the model from turning that recovery into bus purchases that no sales statistic shows.
A48: Passenger and freight aircraft | B48: Distance-weighted passengers per aircraft, and tons per freight aircraft, from the BTS air carrier profile, constant.
A49: Passenger rail | B49: Passenger-miles per car-mile from the NTD agency tables, 15.3 in the start year, then rising with NEMS's transit-rail and commuter-rail recovery terms weighted by 2019 passenger-miles: about 37% higher by 2030 and 48% by 2050. NTD shows passengers per car-mile a third below 2019 while car-miles are back near 2019, so most of AEO's rail passenger-mile growth is riders returning to existing cars; putting it in loading keeps the model from buying cars for it.
A50: Recreational boats (passenger ships) | B50: 1, because the distance file carries hours of use per boat rather than passenger-miles.
A51: Motorbikes | B51: Distance-weighted passengers per motorcycle from the BTS profile, constant.
A52: Freight LDVs (class 2b-6) | B52: 1 ton per truck, an assumption; no survey reports the average load of commercial light trucks. Any error here is absorbed in the miles per truck, which is derived from the same travel statistic.
A53: Heavy trucks (class 7-8) | B53: 16 tons per truck from FHWA's freight corridor analysis, constant.
A54: Freight rail and freight ships | B54: Tons per locomotive and per vessel from the BTS rail and water profiles. For ships this is cargo capacity rather than the actual load; the miles per vessel is derived from the same ton-mile statistic, so the product is right even if the split between loading and distance is approximate. The BTS rail figures are taken as train-car-miles rather than locomotive-miles, judged from their scale.

Sheet BTS NTS Modal Profile Data
A1: Passenger aircraft and freight aircraft | B1: 2006
A2: Aircraft revenue-miles (thousands), total certified | B2: 8218378
A3: Revenue passenger-miles (thousands), total certified | B3: 810106273
A4: Revenue ton-miles of freight (thousands), total certified | B4: 39719513
A5: total aircraft stock (U.S., 2014, EIA AEO 2016, Table 49) | B5: 7880
A6: cargo aircraft stock (U.S., 2014, EIA AEO 2016, Table 49) | B6: 907
A7: share of aircraft-miles devoted to freight | B7: =B6/B5 -> 0.11510152 | C7: Assumes passenger and freight aircraft fly similar numbers of miles per year
A8: Distance-weighted avg. passengers / aircraft | B8: =B3/(B2*(1-B7)) -> 111.39416
A9: Distance-weighted avg. freight tons / aircraft | B9: =B4/(B2*B7) -> 41.989116
A11: Passenger HDVs (buses) | B11: 2014
A12: Vehicle-miles, all buses (millions) | B12: 15999
A13: Passenger-miles, all buses (millions) | B13: 339117
A14: Distance-weighted avg. passengers/bus | B14: =B13/B12 -> 21.196137
A16: Freight Rail | B16: 2009
A17: Train mileage, freight (thousands) | B17: 436235
A18: Revenue ton-miles of freight (millions) | B18: 1532214
A19: Distance-weighted avg. freight tons/train | B19: =B18*10^3/B17 -> 3512.3592 | C19: This is per train, not per rail car. Rail car mileage is also available in the source document, should it be needed.
A21: Passenger Rail
A22: Assumption - train cars per locomotive | B22: 10
A23: Intercity (Amtrak) | B23: 2009
A24: Amtrak passenger train-miles (millions) | B24: 38
A25: Amtrak revenue passenger-miles (millions) | B25: 5914
A26: Distance-weighted avg. passengers/Amtrak train | B26: =B25/B24 -> 155.63158
A27: Transit | B27: 2009
A28: passenger-miles, heavy rail (millions) | B28: 16805
A29: passenger-miles, light rail (millions) | B29: 2196
A30: passenger-miles, commuter rail (millions) | B30: 11129
A31: vehicle-miles, heavy rail (millions) | B31: 685
A32: vehicle-miles, light rail (millions) | B32: 90
A33: vehicle-miles, commuter rail (millions) | B33: 337
A34: Distance-weighted avg. passengers/heavy rail vehicle | B34: =B28/B31 -> 24.532847
A35: Distance-weighted avg. passengers/light rail vehicle | B35: =B29/B32 -> 24.4
A36: Distance-weighted avg. passengers/commuter rail vehicle | B36: =B30/B33 -> 33.023739
A37: passenger-mile-weighted distance-weighted avg. passengers/vehicle | B37: =(B26*B25+B34*B28+B35*B29+B36*B30)/SUM(B25,B28:B30)*B22 -> 486.56732
A39: Freight Ships | B39: 2005
A40: number of self-propelled dry cargo barges | B40: 2967
A41: number of self-propelled tankers | B41: 100
A42: number of non-self-propelled dry cargo barges | B42: 27876 | C42: We include non-self-propelled vessels in our weighted average, because our freight ship vehicle count includes
A43: number of non-self-propelled tankers | B43: 4151 | C43: pusher ships (tugs / towboats) that propel these vessels, and we want their average capacity to be factored in,
C44: so the towboats are properly represented.
A45: total cargo capacity of all self-propelled dry cargo barges (short tons) | B45: 6614973
A46: total cargo capacity of all self-propelled tankers (short tons) | B46: 5727512
A47: total cargo capacity of all non-self-propelled dry cargo barges (short tons) | B47: 44777151
A48: total cargo capacity of all non-self-propelled tankers (short tons) | B48: 12172542
A50: average cargo capacity per self-propelled dry cargo barge | B50: =B45/B40 -> 2229.5157
A51: average cargo capacity per self-propelled tanker | B51: =B46/B41 -> 57275.12
A52: average cargo capacity per non-self-propelled dry cargo barge | B52: =B47/B42 -> 1606.2976
A53: average cargo capacity per non-self-propelled tanker | B53: =B48/B43 -> 2932.436
A55: weighted average cargo capacity (short tons) | B55: =SUMPRODUCT(B40:B43,B50:B53)/SUM(B40:B43) -> 1974.4736
A57: Passenger motorbikes | B57: 2007
A58: vehicle-miles, total (millions) | B58: 13611
A59: passenger-miles, total (millions) | B59: 17287
A60: distance-weighted avg. passengers/motorbike | B60: =B59/B58 -> 1.2700757
A62: Passenger LDVs | B62: 2007
A63: vehicle-miles, passenger car, total (millions) | B63: 1670994
A64: passenger-miles, passenger car, total (millions) | B64: 2640170
A65: distance-weighted avg. passengers/LDV | B65: =B64/B63 -> 1.5799997 | C65: Not currently used, but could be used instead of the figure from the National Household Travel Survey if desired.

Sheet Annual Service Data_rail only
A1: Agency | B1: City | C1: State | D1: Legacy NTD ID | E1: NTD ID | F1: Organization Type | G1: NTD Reporter Type | H1: Primary UZA Population | I1: Agency VOMS | J1: Mode | K1: Type of Service | L1: Mode VOMS | M1: Mode VOMS Questionable | N1: Max Trains in Operation | O1: Max Trains in Operation Questionable | P1: Average Speed (mi/hr) | Q1: Average Speed (mi/hr) Questionable | R1: Average Passenger Trip Length (mi) | S1: Average Passenger Trip Length (mi) Questionable | T1: Passengers per Hour | U1: Passengers per Hour Questionable | V1: Scheduled Vehicle Revenue Miles | W1: Scheduled Vehicle Revenue Miles Questionable | X1: Vehicle Miles | Y1: Vehicle Miles Questionable | Z1: Vehicle Revenue Miles | AA1: Vehicle Revenue Miles Questionable | AB1: Deadhead Miles | AC1: Deadhead Miles Questionable | AD1: Vehicle Hours | AE1: Vehicle Hours Questionable | AF1: Vehicle Revenue Hours | AG1: Vehicle Revenue Hours Questionable | AH1: Deadhead Hours | AI1: Deadhead Hours Questionable | AJ1: Train Miles | AK1: Train Miles Questionable | AL1: Train Revenue Miles | AM1: Train Revenue Miles Questionable | AN1: Train Hours | AO1: Train Hours Questionable | AP1: Train Revenue Hours | AQ1: Train Revenue Hours Questionable | AR1: Unlinked Passenger Trips | AS1: Unlinked Passenger Trips Questionable | AT1: Passenger Miles | AU1: Passenger Miles Questionable | AV1: Directional Route Miles | AW1: Directional Route Miles Questionable | AX1: Any data questionable
A2: MTA New York City Transit | B2: Brooklyn | C2: NY | D2: 2008 | E2: 20008 | F2: Subsidiary Unit of a Transit Agency, Reporting Separately | G2: Full Reporter | H2: 18351295 | I2: 10427 | J2: HR | K2: DO | L2: 5413 | N2: 527 | P2: 18.2156 | R2: 4.2032 | T2: 62.4037 | V2: 376401985 | X2: 334949157 | Z2: 324782077 | AB2: 10167080 | AD2: 18782357 | AF2: 17829918 | AH2: 952439 | AJ2: 36770774 | AL2: 35625281 | AN2: 2060234 | AP2: 1955760 | AR2: 1112653405 | AT2: 4676670633 | AV2: 493.68 | AX2: No
A3: New Jersey Transit Corporation | B3: Newark | C3: NJ | D3: 2080 | E3: 20080 | F3: Other Publicly-Owned or Privately Chartered Corporation | G3: Full Reporter | H3: 18351295 | I3: 3646 | J3: LR | K3: PT | L3: 42 | N3: 20 | P3: 16.5765 | R3: 3.7544 | T3: 104.7091 | V3: 1809860 | X3: 1929113 | Z3: 1893039 | AB3: 36074 | AD3: 115699 | AF3: 114200 | AH3: 1499 | AJ3: 1096779 | AL3: 1076347 | AN3: 64689 | AP3: 63804 | AR3: 11957780 | AT3: 44894834 | AV3: 34.08 | AX3: No
A4: New Jersey Transit Corporation | B4: Newark | C4: NJ | D4: 2080 | E4: 20080 | F4: Other Publicly-Owned or Privately Chartered Corporation | G4: Full Reporter | H4: 18351295 | I4: 3646 | J4: LR | K4: DO | L4: 15 | N4: 15 | P4: 9.3913 | R4: 2.2517 | T4: 88.6621 | V4: 458806 | X4: 481308 | Z4: 470004 | AB4: 11304 | AD4: 55608 | AF4: 50047 | AH4: 5561 | AJ4: 481308 | AL4: 470004 | AN4: 55608 | AP4: 50047 | AR4: 4437270 | AT4: 9991369 | AV4: 12.42 | AX4: No
A5: New Jersey Transit Corporation | B5: Newark | C5: NJ | D5: 2080 | E5: 20080 | F5: Other Publicly-Owned or Privately Chartered Corporation | G5: Full Reporter | H5: 18351295 | I5: 3646 | J5: CR | K5: DO | L5: 904 | N5: 105 | P5: 32.758 | R5: 22.0101 | T5: 40.0147 | V5: 54847772 | X5: 57155030 | Z5: 54301350 | AB5: 2853680 | AD5: 1953118 | AF5: 1657653 | AH5: 295465 | AJ5: 8422625 | AL5: 7942892 | AN5: 287491 | AP5: 248272 | AR5: 66330426 | AT5: 1459936301 | AV5: 920.4 | AX5: No
A6: Los Angeles County Metropolitan Transportation Authority, dba: Metro | B6: Los Angeles | C6: CA | D6: 9154 | E6: 90154 | F6: Independent Public Agency or Authority of Transit Service | G6: Full Reporter | H6: 12150996 | I6: 3482 | J6: LR | K6: DO | L6: 203 | N6: 74 | P6: 20.558 | R6: 7.5713 | T6: 55.704 | V6: 15592469 | X6: 16090545 | Z6: 15536688 | AB6: 553857 | AD6: 792734 | AF6: 755749 | AH6: 36985 | AJ6: 6384468 | AL6: 6156417 | AN6: 309440 | AP6: 294220 | AR6: 42098255 | AT6: 318737668 | AV6: 171.92 | AX6: No
A7: Los Angeles County Metropolitan Transportation Authority, dba: Metro | B7: Los Angeles | C7: CA | D7: 9154 | E7: 90154 | F7: Independent Public Agency or Authority of Transit Service | G7: Full Reporter | H7: 12150996 | I7: 3482 | J7: HR | K7: DO | L7: 68 | N7: 13 | P7: 21.8993 | R7: 4.8392 | T7: 108.4073 | V7: 6821561 | X7: 6973555 | Z7: 6801301 | AB7: 172254 | AD7: 327668 | AF7: 310572 | AH7: 17096 | AJ7: 1383514 | AL7: 1350454 | AN7: 66480 | AP7: 63158 | AR7: 33668265 | AT7: 162927528 | AV7: 31.9 | AX7: No
A8: Washington Metropolitan Area Transit Authority | B8: Washington | C8: DC | D8: 3030 | E8: 30030 | F8: Independent Public Agency or Authority of Transit Service | G8: Full Reporter | H8: 4586770 | I8: 3304 | J8: HR | K8: DO | L8: 998 | N8: 129 | P8: 23.3386 | R8: 5.6487 | T8: 51.0164 | V8: 81860566 | X8: 82234530 | Z8: 79847615 | AB8: 2386915 | AD8: 3524685 | AF8: 3421264 | AH8: 103421 | AJ8: 11770449 | AL8: 11432619 | AN8: 505929 | AP8: 489793 | AR8: 174540714 | AT8: 985922295 | AV8: 234.2 | AX8: No
A9: Chicago Transit Authority | B9: Chicago | C9: IL | D9: 5066 | E9: 50066 | F9: Independent Public Agency or Authority of Transit Service | G9: Full Reporter | H9: 8608208 | I9: 2703 | J9: HR | K9: DO | L9: 1148 | N9: 158 | P9: 18.0276 | R9: 6.3144 | S9: W | T9: 19.7235 | V9: 82996946 | X9: 70519745 | Z9: 69510641 | AB9: 1009104 | AD9: 4177041 | AF9: 3855798 | AH9: 321243 | AJ9: 10533049 | AL9: 10388783 | AN9: 631507 | AP9: 582079 | AR9: 76049871 | AT9: 480210760 | AU9: W | AV9: 207.84 | AX9: Yes
A10: Massachusetts Bay Transportation Authority | B10: Boston | C10: MA | D10: 1003 | E10: 10003 | F10: Independent Public Agency or Authority of Transit Service | G10: Full Reporter | H10: 4181019 | I10: 2428 | J10: LR | K10: DO | L10: 154 | N10: 86 | P10: 7.3029 | R10: 2.3538 | T10: 57.7745 | V10: 5714964 | X10: 5260506 | Z10: 5241369 | AB10: 19137 | AD10: 726323 | AF10: 717709 | AH10: 8614 | AI10: Q | AJ10: 2876932 | AL10: 2870560 | AN10: 321018 | AP10: 315916 | AR10: 41465243 | AT10: 97602251 | AV10: 51 | AX10: Yes
A11: Massachusetts Bay Transportation Authority | B11: Boston | C11: MA | D11: 1003 | E11: 10003 | F11: Independent Public Agency or Authority of Transit Service | G11: Full Reporter | H11: 4181019 | I11: 2428 | J11: HR | K11: DO | L11: 338 | N11: 56 | P11: 16.7071 | R11: 3.5198 | T11: 87.0464 | V11: 23317516 | X11: 22746421 | Z11: 22203578 | AB11: 542843 | AD11: 1393950 | AF11: 1328990 | AH11: 64960 | AJ11: 3791070 | AL11: 3700596 | AN11: 253575 | AP11: 242748 | AR11: 115683733 | AT11: 407181618 | AV11: 76.3 | AX11: No
A12: Massachusetts Bay Transportation Authority | B12: Boston | C12: MA | D12: 1003 | E12: 10003 | F12: Independent Public Agency or Authority of Transit Service | G12: Full Reporter | H12: 4181019 | I12: 2428 | J12: CR | K12: PT | L12: 436 | N12: 67 | P12: 29.7292 | R12: 20.751 | T12: 33.01 | V12: 22195183 | X12: 22810502 | Z12: 22300695 | AB12: 509807 | AD12: 768699 | AF12: 750128 | AH12: 18571 | AJ12: 4189947 | AL12: 4093393 | AN12: 141215 | AP12: 137738 | AR12: 24761705 | AT12: 513830968 | AV12: 776.08 | AX12: No
A13: Southeastern Pennsylvania Transportation Authority | B13: Philadelphia | C13: PA | D13: 3019 | E13: 30019 | F13: Independent Public Agency or Authority of Transit Service | G13: Full Reporter | H13: 5441567 | I13: 2406 | J13: HR | K13: DO | L13: 286 | N13: 61 | P13: 17.0971 | R13: 4.4254 | S13: W | T13: 75.5141 | U13: W | V13: 16431036 | X13: 16168711 | Z13: 16089713 | AB13: 78998 | AD13: 945947 | AF13: 941080 | AH13: 4867 | AJ13: 3121305 | AL13: 3101700 | AN13: 182557 | AP13: 181391 | AR13: 71064786 | AS13: W | AT13: 314489396 | AU13: W | AV13: 74.9 | AX13: Yes
A14: Southeastern Pennsylvania Transportation Authority | B14: Philadelphia | C14: PA | D14: 3019 | E14: 30019 | F14: Independent Public Agency or Authority of Transit Service | G14: Full Reporter | H14: 5441567 | I14: 2406 | J14: CR | K14: DO | L14: 357 | N14: 84 | P14: 19.6909 | R14: 13.4494 | S14: W | T14: 29.7939 | U14: W | V14: 16896038 | X14: 17498310 | Z14: 16621821 | AB14: 876489 | AD14: 882766 | AF14: 844136 | AH14: 38630 | AJ14: 4453116 | AL14: 4225898 | AN14: 224140 | AP14: 214329 | AR14: 25150117 | AS14: W | AT14: 338253606 | AU14: W | AV14: 446.94 | AX14: Yes
A15: Metropolitan Transit Authority of Harris County, Texas, dba: Metro | B15: Houston | C15: TX | D15: 6008 | E15: 60008 | F15: Independent Public Agency or Authority of Transit Service | G15: Full Reporter | H15: 4944332 | I15: 2157 | J15: LR | K15: DO | L15: 56 | N15: 29 | P15: 12.1474 | R15: 2.9095 | T15: 48.3795 | V15: 3257209 | X15: 3247125 | Z15: 3236011 | AB15: 11114 | AD15: 268268 | AF15: 266396 | AH15: 1872 | AJ15: 1940638 | AL15: 1929524 | AN15: 176143 | AP15: 174271 | AR15: 12888105 | AT15: 37497523 | AV15: 43.59 | AX15: No
A16: Maryland Transit Administration | B16: Baltimore | C16: MD | D16: 3034 | E16: 30034 | F16: State Government Unit or Department of Transportation | G16: Full Reporter | H16: 2203663 | I16: 1888 | J16: LR | K16: DO | L16: 38 | N16: 18 | P16: 19.6769 | R16: 5.7128 | S16: W | T16: 35.3738 | V16: 2774375 | X16: 2676810 | Z16: 2588105 | AB16: 88705 | AD16: 138492 | AF16: 131530 | AH16: 6962 | AJ16: 1046361 | AL16: 1044905 | AN16: 58730 | AP16: 58193 | AR16: 4652718 | AT16: 26579844 | AU16: W | AV16: 57.6 | AX16: Yes
A17: Maryland Transit Administration | B17: Baltimore | C17: MD | D17: 3034 | E17: 30034 | F17: State Government Unit or Department of Transportation | G17: Full Reporter | H17: 2203663 | I17: 1888 | J17: HR | K17: DO | L17: 54 | N17: 9 | P17: 26.0926 | R17: 4.7674 | S17: W | T17: 36.698 | V17: 4289979 | X17: 4659371 | Z17: 4169492 | AB17: 489879 | AD17: 180401 | AF17: 159796 | AH17: 20605 | AJ17: 845652 | AL17: 734915 | AN17: 32887 | AP17: 28462 | AR17: 5864191 | AT17: 27957087 | AU17: W | AV17: 29.4 | AX17: Yes
A18: Maryland Transit Administration | B18: Baltimore | C18: MD | D18: 3034 | E18: 30034 | F18: State Government Unit or Department of Transportation | G18: Full Reporter | H18: 2203663 | I18: 1888 | J18: CR | K18: PT | L18: 149 | N18: 28 | P18: 38.3283 | R18: 29.5846 | S18: W | T18: 45.7479 | V18: 6001808 | X18: 5996542 | Z18: 5596811 | AB18: 399731 | AD18: 155174 | AF18: 146023 | AH18: 9151 | AJ18: 1094365 | AL18: 1036558 | AN18: 30902 | AP18: 28513 | AR18: 6680248 | AT18: 197632189 | AU18: W | AV18: 400.4 | AX18: Yes
A19: County of Miami-Dade, dba: Transportation & Public Work | B19: Miami | C19: FL | D19: 4034 | E19: 40034 | F19: City, County or Local Government Unit or Department of Transportation | G19: Full Reporter | H19: 5502379 | I19: 1452 | J19: HR | K19: DO | L19: 76 | N19: 18 | P19: 21.7622 | R19: 7.3831 | S19: W | T19: 35.9601 | V19: 7212362 | X19: 7598157 | Z19: 7178627 | AB19: 419530 | AD19: 362201 | AF19: 329867 | AH19: 32334 | AJ19: 1899556 | AL19: 1794673 | AN19: 90549 | AP19: 82465 | AR19: 11862059 | AT19: 87578321 | AU19: W | AV19: 49.84 | AX19: Yes
A20: Denver Regional Transportation District | B20: Denver | C20: CO | D20: 8006 | E20: 80006 | F20: Independent Public Agency or Authority of Transit Service | G20: Full Reporter | H20: 2374203 | I20: 1431 | J20: LR | K20: DO | L20: 156 | N20: 41 | P20: 17.2002 | R20: 6.9673 | T20: 19.8586 | V20: 9004264 | X20: 9327859 | Z20: 9063803 | AB20: 264056 | AD20: 590892 | AF20: 526960 | AH20: 63932 | AJ20: 3900081 | AL20: 3745938 | AN20: 267096 | AP20: 226007 | AR20: 10464678 | AT20: 72910951 | AV20: 119.78 | AX20: No
A21: Denver Regional Transportation District | B21: Denver | C21: CO | D21: 8006 | E21: 80006 | F21: Independent Public Agency or Authority of Transit Service | G21: Full Reporter | H21: 2374203 | I21: 1431 | J21: CR | K21: PT | L21: 44 | N21: 12 | P21: 27.5631 | R21: 11.5166 | T21: 21.7837 | V21: 6222945 | X21: 6197643 | Z21: 6048702 | AB21: 148941 | AD21: 228257 | AF21: 219449 | AH21: 8808 | AJ21: 2010537 | AL21: 1917204 | AN21: 74540 | AP21: 70293 | AR21: 4780402 | AT21: 55053882 | AV21: 72.76 | AX21: No
A22: Denver Regional Transportation District | B22: Denver | C22: CO | D22: 8006 | E22: 80006 | F22: Independent Public Agency or Authority of Transit Service | G22: Full Reporter | H22: 2374203 | I22: 1431 | J22: CR | K22: DO | L22: 8 | N22: 3 | P22: 20.4842 | R22: 8.6131 | T22: 18.0161 | V22: 203262 | X22: 223786 | Z22: 197570 | AB22: 26216 | AD22: 12511 | AF22: 9645 | AH22: 2866 | AJ22: 115030 | AL22: 98743 | AN22: 6243 | AP22: 4937 | AR22: 173765 | AT22: 1496661 | AV22: 26.32 | AX22: No
A23: Metro-North Commuter Railroad Company, dba: MTA Metro-North Railroad | B23: New York | C23: NY | D23: 2078 | E23: 20078 | F23: Subsidiary Unit of a Transit Agency, Reporting Separately | G23: Full Reporter | H23: 18351295 | I23: 1133 | J23: CR | K23: DO | L23: 1122 | N23: 135 | P23: 31.2997 | R23: 22.8524 | S23: W | T23: 18.8824 | V23: 47488237 | X23: 53139671 | Z23: 48719168 | AB23: 4420503 | AD23: 1709469 | AF23: 1556539 | AH23: 152930 | AJ23: 7201726 | AL23: 6564652 | AN23: 225218 | AP23: 203440 | AR23: 29391259 | AT23: 671661254 | AU23: W | AV23: 545.74 | AX23: Yes
A24: Dallas Area Rapid Transit | B24: Dallas | C24: TX | D24: 6056 | E24: 60056 | F24: Independent Public Agency or Authority of Transit Service | G24: Full Reporter | H24: 5121892 | I24: 1082 | J24: LR | K24: DO | L24: 117 | N24: 44 | P24: 20.5101 | R24: 8.1822 | T24: 41.7424 | V24: 9953657 | X24: 9937246 | Z24: 9866803 | AB24: 70443 | AD24: 486886 | AF24: 481071 | AH24: 5815 | AJ24: 5348975 | AL24: 5310292 | AN24: 261692 | AP24: 258495 | AR24: 20081036 | AT24: 164306746 | AV24: 182.44 | AX24: No
A25: Dallas Area Rapid Transit | B25: Dallas | C25: TX | D25: 6056 | E25: 60056 | F25: Independent Public Agency or Authority of Transit Service | G25: Full Reporter | H25: 5121892 | I25: 1082 | J25: CR | K25: PT | L25: 23 | N25: 3 | P25: 22.474 | R25: 17.3008 | T25: 20.2524 | V25: 1390207 | X25: 1437340 | Z25: 1404961 | AB25: 32379 | AD25: 63773 | AF25: 62515 | AH25: 1258 | AJ25: 506768 | AL25: 495677 | AN25: 22535 | AP25: 22090 | AR25: 1266076 | AT25: 21904126 | AV25: 72.3 | AX25: No
A26: Utah Transit Authority | B26: Salt Lake City | C26: UT | D26: 8001 | E26: 80001 | F26: Independent Public Agency or Authority of Transit Service | G26: Full Reporter | H26: 1021243 | I26: 1081 | J26: LR | K26: DO | L26: 89 | N26: 22 | P26: 17.1928 | R26: 4.7437 | T26: 23.1914 | V26: 6112222 | X26: 6204641 | Z26: 6114108 | AB26: 90533 | AD26: 367255 | AF26: 355621 | AH26: 11634 | AJ26: 2255583 | AL26: 2223959 | AN26: 136213 | AP26: 131989 | AR26: 8247364 | AT26: 39122864 | AV26: 93.91 | AX26: No
A27: Utah Transit Authority | B27: Salt Lake City | C27: UT | D27: 8001 | E27: 80001 | F27: Independent Public Agency or Authority of Transit Service | G27: Full Reporter | H27: 1021243 | I27: 1081 | J27: CR | K27: DO | L27: 50 | N27: 9 | P27: 32.4736 | R27: 25.6439 | T27: 16.2748 | V27: 4053946 | X27: 4051779 | Z27: 4039581 | AB27: 12198 | AD27: 128674 | AF27: 124396 | AH27: 4278 | AJ27: 1067699 | AL27: 1064546 | AN27: 33846 | AP27: 32741 | AR27: 2024524 | AT27: 51916777 | AV27: 174.46 | AX27: No
A28: Northeast Illinois Regional Commuter Railroad Corporation, dba: Metra | B28: Chicago | C28: IL | D28: 5118 | E28: 50118 | F28: Independent Public Agency or Authority of Transit Service | G28: Full Reporter | H28: 8608208 | I28: 1066 | J28: CR | K28: PT | L28: 527 | N28: 40 | P28: 30.9325 | R28: 21.7125 | T28: 18.9791 | V28: 16284231 | X28: 16302662 | Z28: 15388572 | AB28: 914090 | AD28: 520340 | AF28: 497488 | AH28: 22852 | AJ28: 2394714 | AL28: 2258067 | AN28: 76862 | AP28: 73504 | AR28: 9441882 | AT28: 205006670 | AV28: 399.6 | AX28: No
A29: Northeast Illinois Regional Commuter Railroad Corporation, dba: Metra | B29: Chicago | C29: IL | D29: 5118 | E29: 50118 | F29: Independent Public Agency or Authority of Transit Service | G29: Full Reporter | H29: 8608208 | I29: 1066 | J29: CR | K29: DO | L29: 539 | N29: 53 | P29: 29.0824 | R29: 21.1725 | T29: 13.8796 | V29: 16028080 | X29: 15585872 | Z29: 15273179 | AB29: 312693 | AD29: 535954 | AF29: 525169 | AH29: 10785 | AJ29: 2545102 | AL29: 2494601 | AN29: 89035 | AP29: 87312 | AR29: 7289149 | AT29: 154329520 | AV29: 575.4 | AX29: No
A30: MTA Long Island Rail Road | B30: Jamaica | C30: NY | D30: 2100 | E30: 20100 | F30: Subsidiary Unit of a Transit Agency, Reporting Separately | G30: Full Reporter | H30: 18351295 | I30: 1022 | J30: CR | K30: DO | L30: 1022 | N30: 107 | P30: 29.2123 | R30: 28.2692 | S30: W | T30: 20.566 | U30: W | V30: 61301708 | X30: 68469245 | Z30: 61766650 | AB30: 6702595 | AD30: 2305899 | AF30: 2114409 | AH30: 191490 | AJ30: 7765181 | AL30: 6968685 | AN30: 266731 | AP30: 199752 | AR30: 43484907 | AS30: W | AT30: 1229284540 | AU30: W | AV30: 638.2 | AX30: Yes
A31: City and County of San Francisco, dba: San Francisco Municipal Transportation Agency (MUNI) | B31: San Francisco | C31: CA | D31: 9015 | E31: 90015 | F31: City, County or Local Government Unit or Department of Transportation | G31: Full Reporter | H31: 3281212 | I31: 996 | J31: LR | K31: DO | L31: 149 | N31: 141 | P31: 9.497 | R31: 2.7421 | T31: 76.5848 | V31: 4944335 | X31: 4660934 | Z31: 4640244 | AB31: 20690 | AD31: 491748 | AF31: 488601 | AH31: 3147 | AJ31: 3097363 | AL31: 3084167 | AN31: 326422 | AP31: 324323 | AR31: 37419416 | AT31: 102607757 | AV31: 64.4 | AX31: No
A32: Tri-County Metropolitan Transportation District of Oregon, dba: TriMet | B32: Portland | C32: OR | D32: 8 | E32: 8 | F32: Independent Public Agency or Authority of Transit Service | G32: Full Reporter | H32: 1849898 | I32: 982 | J32: LR | K32: DO | L32: 116 | N32: 55 | P32: 14.1369 | R32: 5.2552 | T32: 48.3924 | V32: 8977599 | X32: 8981104 | Z32: 8864217 | AB32: 116887 | AD32: 636882 | AF32: 627025 | AH32: 9857 | AJ32: 4501055 | AL32: 4442373 | AN32: 319090 | AP32: 314140 | AR32: 30343267 | AT32: 159458488 | AV32: 118.91 | AX32: No
A33: Metropolitan Atlanta Rapid Transit Authority | B33: Atlanta | C33: GA | D33: 4022 | E33: 40022 | F33: Independent Public Agency or Authority of Transit Service | G33: Full Reporter | H33: 4515419 | I33: 943 | J33: HR | K33: DO | L33: 212 | N33: 39 | P33: 26.494 | R33: 7.2762 | T33: 58.7473 | V33: 20499724 | X33: 21145309 | Z33: 20430752 | AB33: 714557 | AD33: 794602 | AF33: 771146 | AH33: 23456 | AJ33: 3715370 | AL33: 3628801 | AN33: 143614 | AP33: 139086 | AR33: 45302714 | AT33: 329631085 | AV33: 96.06 | AX33: No
A34: Port Authority of Allegheny County | B34: Pittsburgh | C34: PA | D34: 3022 | E34: 30022 | F34: Independent Public Agency or Authority of Transit Service | G34: Full Reporter | H34: 1733853 | I34: 930 | J34: LR | K34: DO | L34: 58 | N34: 29 | P34: 12.9097 | R34: 4.0318 | T34: 37.5305 | V34: 2027777 | X34: 1999310 | Z34: 1916792 | AB34: 82518 | AD34: 155486 | AF34: 148477 | AH34: 7009 | AJ34: 1497766 | AL34: 1442245 | AN34: 116738 | AP34: 112071 | AR34: 5572417 | AT34: 22466673 | AV34: 49.64 | AX34: No
A35: San Diego Metropolitan Transit System | B35: San Diego | C35: CA | D35: 9026 | E35: 90026 | F35: Independent Public Agency or Authority of Transit Service | G35: Full Reporter | H35: 2956746 | I35: 906 | J35: LR | K35: DO | L35: 103 | N35: 35 | P35: 18.1208 | R35: 6.0708 | T35: 62.966 | V35: 9662505 | X35: 9410942 | Z35: 9210076 | AB35: 200866 | AD35: 527144 | AF35: 508259 | AH35: 18885 | AJ35: 3279625 | AL35: 3207856 | AN35: 183992 | AP35: 177429 | AR35: 32003027 | AT35: 194284885 | AV35: 108.4 | AX35: No
A36: Metro Transit, dba: Metro Transit | B36: Minneapolis | C36: MN | D36: 5027 | E36: 50027 | F36: Subsidiary Unit of a Transit Agency, Reporting Separately | G36: Full Reporter | H36: 2650890 | I36: 823 | J36: LR | K36: DO | L36: 76 | N36: 23 | P36: 11.9859 | R36: 3.9724 | S36: W | T36: 30.4653 | V36: 4237895 | X36: 4129925 | Z36: 4034814 | AB36: 95111 | AD36: 354913 | AF36: 336629 | AH36: 18284 | AJ36: 1500026 | AL36: 1436691 | AN36: 125192 | AP36: 118274 | AR36: 10255520 | AT36: 40738989 | AU36: W | AV36: 44.26 | AX36: Yes
A37: Metro Transit, dba: Metro Transit | B37: Minneapolis | C37: MN | D37: 5027 | E37: 50027 | F37: Subsidiary Unit of a Transit Agency, Reporting Separately | G37: Full Reporter | H37: 2650890 | I37: 823 | J37: CR | K37: PT | L37: 20 | N37: 4 | P37: 43.769 | R37: 24.7025 | S37: W | T37: 26.3444 | V37: 253487 | X37: 256360 | Z37: 253291 | AB37: 3069 | AD37: 6199 | AF37: 5787 | AH37: 412 | AJ37: 64139 | AL37: 63372 | AN37: 1552 | AP37: 1448 | AR37: 152455 | AT37: 3766017 | AU37: W | AV37: 77.9 | AX37: Yes
A38: Santa Clara Valley Transportation Authority | B38: San Jose | C38: CA | D38: 9013 | E38: 90013 | F38: Independent Public Agency or Authority of Transit Service | G38: Full Reporter | H38: 1664496 | I38: 635 | J38: LR | K38: DO | L38: 61 | N38: 29 | P38: 14.6876 | R38: 5.3386 | T38: 31.9576 | V38: 3049391 | X38: 3045104 | Z38: 2886997 | AB38: 158107 | AD38: 208938 | AF38: 196560 | AH38: 12378 | AJ38: 1824324 | AL38: 1733696 | AN38: 131172 | AP38: 123509 | AR38: 6281578 | AT38: 33535077 | AV38: 80.96 | AX38: No
A39: San Francisco Bay Area Rapid Transit District | B39: Oakland | C39: CA | D39: 9003 | E39: 90003 | F39: Independent Public Agency or Authority of Transit Service | G39: Full Reporter | H39: 3281212 | I39: 616 | J39: HR | K39: DO | L39: 599 | N39: 56 | P39: 34.8299 | Q39: W | R39: 13.963 | T39: 44.2609 | U39: W | V39: 69597595 | X39: 72050709 | Z39: 69799195 | AB39: 2251514 | AD39: 2377255 | AF39: 2004002 | AG39: W | AH39: 373253 | AJ39: 8255518 | AL39: 7973519 | AN39: 277276 | AP39: 229211 | AR39: 88698878 | AT39: 1238506222 | AV39: 239.42 | AX39: Yes
A40: Bi-State Development Agency of the Missouri-Illinois Metropolitan District, dba: St. Louis Metro | B40: Saint Louis | C40: MO | D40: 7006 | E40: 70006 | F40: Independent Public Agency or Authority of Transit Service | G40: Full Reporter | H40: 2150706 | I40: 493 | J40: LR | K40: DO | L40: 50 | N40: 25 | P40: 23.1905 | R40: 6.749 | T40: 41.7394 | V40: 5954691 | X40: 5905439 | Z40: 5839491 | AB40: 65948 | AD40: 256119 | AF40: 251805 | AH40: 4314 | AJ40: 2952712 | AL40: 2919745 | AN40: 128060 | AP40: 125902 | AR40: 10510179 | AT40: 70933375 | AV40: 91.06 | AX40: No
A41: The Greater Cleveland Regional Transit Authority | B41: Cleveland | C41: OH | D41: 5015 | E41: 50015 | F41: Independent Public Agency or Authority of Transit Service | G41: Full Reporter | H41: 1780673 | I41: 418 | J41: LR | K41: DO | L41: 6 | N41: 6 | P41: 14.0802 | R41: 3.5057 | S41: W | T41: 14.4611 | V41: 559327 | X41: 577077 | Z41: 573726 | AB41: 3351 | AD41: 41389 | AF41: 40747 | AH41: 642 | AJ41: 562513 | AL41: 559161 | AN41: 40336 | AP41: 39693 | AR41: 589245 | AT41: 2065735 | AU41: W | AV41: 30.38 | AX41: Yes
A42: The Greater Cleveland Regional Transit Authority | B42: Cleveland | C42: OH | D42: 5015 | E42: 50015 | F42: Independent Public Agency or Authority of Transit Service | G42: Full Reporter | H42: 1780673 | I42: 418 | J42: HR | K42: DO | L42: 16 | N42: 8 | P42: 19.0147 | R42: 6.9599 | S42: W | T42: 20.6055 | V42: 2472057 | X42: 2440418 | Z42: 2434523 | AB42: 5895 | AD42: 129302 | AF42: 128034 | AH42: 1268 | AJ42: 1238321 | AL42: 1235375 | AN42: 65610 | AP42: 64976 | AR42: 2638201 | AT42: 18361515 | AU42: W | AV42: 38.08 | AX42: Yes
A43: Transportation District Commission of Hampton Roads, dba: Hampton Roads Transit | B43: Hampton | C43: VA | D43: 3083 | E43: 30083 | F43: Independent Public Agency or Authority of Transit Service | G43: Full Reporter | H43: 1439666 | I43: 417 | J43: LR | K43: DO | L43: 6 | N43: 6 | P43: 13.2671 | R43: 3.2272 | T43: 40.309 | V43: 344336 | X43: 344847 | Z43: 343618 | AB43: 1229 | AD43: 26101 | AF43: 25900 | AH43: 201 | AJ43: 344847 | AL43: 343618 | AN43: 26101 | AP43: 25900 | AR43: 1044002 | AT43: 3369249 | AV43: 14.8 | AX43: No
A44: City of Charlotte North Carolina, dba: Charlotte Area Transit System | B44: Charlotte | C44: NC | D44: 4008 | E44: 40008 | F44: City, County or Local Government Unit or Department of Transportation | G44: Full Reporter | H44: 1249442 | I44: 409 | J44: LR | K44: DO | L44: 36 | N44: 16 | P44: 16.1408 | R44: 5.183 | T44: 55.5262 | V44: 2178959 | X44: 2267166 | Z44: 2110955 | AB44: 156211 | AD44: 138754 | AF44: 130784 | AH44: 7970 | AJ44: 1141671 | AL44: 1059265 | AN44: 69828 | AP44: 65622 | AR44: 7261944 | AT44: 37638865 | AV44: 37.3 | AX44: No
A45: Central Puget Sound Regional Transit Authority, dba: Sound Transit | B45: Seattle | C45: WA | D45: 40 | E45: 40 | F45: Independent Public Agency or Authority of Transit Service | G45: Full Reporter | H45: 3059393 | I45: 381 | J45: LR | K45: DO | L45: 48 | N45: 17 | P45: 18.259 | R45: 6.303 | T45: 35.3672 | V45: 3994837 | X45: 4168064 | Z45: 4078592 | AB45: 89472 | AD45: 233843 | AF45: 223374 | AH45: 10469 | AJ45: 1165448 | AL45: 1140397 | AN45: 65104 | AP45: 61879 | AR45: 7900122 | AT45: 49794569 | AV45: 40.4 | AX45: No
A46: Central Puget Sound Regional Transit Authority, dba: Sound Transit | B46: Seattle | C46: WA | D46: 40 | E46: 40 | F46: Independent Public Agency or Authority of Transit Service | G46: Full Reporter | H46: 3059393 | I46: 381 | J46: CR | K46: PT | L46: 70 | N46: 23 | P46: 30.1167 | R46: 25.1925 | T46: 24.971 | V46: 1617729 | X46: 1562310 | Z46: 1526737 | AB46: 35573 | AD46: 54020 | AF46: 50694 | AH46: 3326 | AJ46: 250453 | AL46: 244746 | AN46: 8818 | AP46: 8281 | AR46: 1265882 | AT46: 31890678 | AV46: 163.84 | AX46: No
A47: Niagara Frontier Transportation Authority | B47: Buffalo | C47: NY | D47: 2004 | E47: 20004 | F47: Independent Public Agency or Authority of Transit Service | G47: Full Reporter | H47: 935906 | I47: 359 | J47: LR | K47: DO | L47: 23 | N47: 7 | P47: 11.1447 | R47: 2.6665 | T47: 48.6101 | V47: 962940 | X47: 984827 | Z47: 968353 | AB47: 16474 | AD47: 91599 | AF47: 86889 | AH47: 4710 | AJ47: 347313 | AL47: 341503 | AN47: 32115 | AP47: 30462 | AR47: 4223681 | AT47: 11262397 | AV47: 12.4 | AX47: No
A48: Sacramento Regional Transit District, dba: Sacramento RT | B48: Sacramento | C48: CA | D48: 9019 | E48: 90019 | F48: Independent Public Agency or Authority of Transit Service | G48: Full Reporter | H48: 1723634 | I48: 331 | J48: LR | K48: DO | L48: 69 | N48: 18 | P48: 17.4438 | R48: 5.9108 | T48: 43.4332 | V48: 3637080 | X48: 3765256 | Z48: 3610107 | AB48: 155149 | AD48: 213385 | AF48: 206957 | AH48: 6428 | AJ48: 1757466 | AL48: 1710343 | AN48: 101083 | AP48: 98064 | AR48: 8988806 | AT48: 53131252 | AV48: 84.92 | AX48: No
A49: Fort Worth Transportation Authority, dba: Trinity Metro | B49: Fort Worth | C49: TX | D49: 6007 | E49: 60007 | F49: Independent Public Agency or Authority of Transit Service | G49: Full Reporter | H49: 5121892 | I49: 312 | J49: CR | K49: PT | L49: 20 | N49: 5 | P49: 19.5091 | R49: 15.8208 | S49: Q | T49: 2.8579 | U49: Q | V49: 2417541 | X49: 2349671 | Z49: 2320998 | AB49: 28673 | AD49: 120510 | AF49: 118970 | AH49: 1540 | AJ49: 587418 | AL49: 580250 | AM49: Q | AN49: 30128 | AP49: 29743 | AQ49: Q | AR49: 340008 | AS49: Q | AT49: 5379214 | AU49: Q | AV49: 52.34 | AX49: Yes
A50: Port Authority Trans-Hudson Corporation | B50: New York | C50: NJ | D50: 2098 | E50: 20098 | F50: Independent Public Agency or Authority of Transit Service | G50: Full Reporter | H50: 18351295 | I50: 310 | J50: HR | K50: DO | L50: 304 | N50: 33 | P50: 13.6246 | R50: 5.0684 | T50: 31.7035 | V50: 12823047 | X50: 13103345 | Z50: 12744198 | AB50: 359147 | AD50: 954091 | AF50: 935379 | AH50: 18712 | AJ50: 1753804 | AL50: 1705415 | AN50: 129406 | AP50: 126903 | AR50: 29654770 | AT50: 150302485 | AV50: 28.6 | AX50: No
A51: North County Transit District | B51: Oceanside | C51: CA | D51: 9030 | E51: 90030 | F51: Independent Public Agency or Authority of Transit Service | G51: Full Reporter | H51: 2956746 | I51: 205 | J51: CR | K51: PT | L51: 24 | N51: 4 | P51: 31.6775 | R51: 26.4412 | T51: 25.2045 | V51: 1181583 | X51: 1254334 | Z51: 1186577 | AB51: 67757 | AD51: 42212 | AF51: 37458 | AH51: 4754 | AJ51: 243076 | AL51: 230008 | AN51: 7881 | AP51: 7305 | AR51: 944109 | AT51: 24963395 | AV51: 82.2 | AX51: No
A52: Southern California Regional Rail Authority, dba: Metrolink | B52: Los Angeles | C52: CA | D52: 9151 | E52: 90151 | F52: Independent Public Agency or Authority of Transit Service | G52: Full Reporter | H52: 12150996 | I52: 195 | J52: CR | K52: PT | L52: 195 | N52: 40 | P52: 36.3401 | R52: 34.3582 | S52: W | T52: 26.0574 | U52: W | V52: 13061501 | X52: 13618637 | Z52: 13049429 | AB52: 569208 | AD52: 387165 | AF52: 359092 | AH52: 28073 | AJ52: 2786037 | AL52: 2674879 | AN52: 80963 | AP52: 73871 | AR52: 9357013 | AS52: W | AT52: 321490316 | AU52: W | AV52: 826.8 | AX52: Yes
A53: Peninsula Corridor Joint Powers Board, dba: Caltrain | B53: San Carlos | C53: CA | D53: 9134 | E53: 90134 | F53: Independent Public Agency or Authority of Transit Service | G53: Full Reporter | H53: 3281212 | I53: 141 | J53: CR | K53: PT | L53: 111 | N53: 20 | P53: 32.3387 | R53: 22.0776 | T53: 68.2619 | V53: 6469218 | X53: 6644705 | Z53: 6486852 | AB53: 157853 | AD53: 216487 | AF53: 200591 | AH53: 15896 | AJ53: 1179829 | AL53: 1151035 | AN53: 38509 | AP53: 35662 | AR53: 13692716 | AT53: 302302869 | AV53: 153.68 | AX53: No
A54: Virginia Railway Express | B54: Alexandria | C54: VA | D54: 3073 | E54: 30073 | F54: Independent Public Agency or Authority of Transit Service | G54: Full Reporter | H54: 4586770 | I54: 99 | J54: CR | K54: PT | L54: 99 | N54: 32 | P54: 30.8269 | R54: 30.3917 | T54: 46.2879 | V54: 2148620 | X54: 2234620 | Z54: 2146074 | AB54: 88546 | AD54: 76838 | AF54: 69617 | AH54: 7221 | AJ54: 333795 | AL54: 320541 | AN54: 11411 | AP54: 10330 | AR54: 3222428 | AT54: 97935058 | AV54: 173.62 | AX54: No
A55: Port Authority Transit Corporation | B55: Lindenwold | C55: NJ | D55: 2075 | E55: 20075 | F55: Independent Public Agency or Authority of Transit Service | G55: Full Reporter | H55: 5441567 | I55: 78 | J55: HR | K55: DO | L55: 78 | N55: 11 | P55: 31.0718 | R55: 8.5806 | T55: 27.4235 | V55: 5618718 | X55: 4662890 | Z55: 4474868 | AB55: 188022 | AD55: 154306 | AF55: 144017 | AH55: 10289 | AJ55: 899973 | AL55: 836001 | AN55: 31034 | AP55: 28828 | AR55: 3949450 | AT55: 33888694 | AV55: 31.5 | AX55: No
A56: Northern Indiana Commuter Transportation District | B56: Chesterton | C56: IN | D56: 5104 | E56: 50104 | F56: Independent Public Agency or Authority of Transit Service | G56: Full Reporter | H56: 8608208 | I56: 70 | J56: CR | K56: DO | L56: 70 | N56: 17 | P56: 34.7689 | R56: 33 | T56: 8.8186 | V56: 4013838 | X56: 3988838 | Z56: 3923145 | AB56: 65693 | AD56: 114811 | AF56: 112835 | AH56: 1976 | AJ56: 739801 | AL56: 724288 | AN56: 21331 | AP56: 20981 | AR56: 995049 | AT56: 32836617 | AV56: 179.8 | AX56: No
A57: South Florida Regional Transportation Authority, dba: TRI-Rail | B57: Pompano Beach | C57: FL | D57: 4077 | E57: 40077 | F57: Independent Public Agency or Authority of Transit Service | G57: Full Reporter | H57: 5502379 | I57: 65 | J57: CR | K57: PT | L57: 43 | N57: 10 | P57: 27.9588 | R57: 27.1649 | T57: 31.1711 | V57: 3327000 | X57: 3379135 | Z57: 3159070 | AB57: 220065 | AD57: 125765 | AF57: 112990 | AH57: 12775 | AJ57: 1016844 | AL57: 958905 | AN57: 37346 | AP57: 33681 | AR57: 3522017 | AT57: 95675095 | AV57: 142.24 | AX57: No
A58: Rio Metro Regional Transit District | B58: Albuquerque | C58: NM | D58: 6111 | E58: 60111 | F58: Independent Public Agency or Authority of Transit Service | G58: Full Reporter | H58: 741318 | I58: 58 | J58: CR | K58: PT | L58: 25 | N58: 7 | P58: 37.3762 | R58: 46.6062 | T58: 20.3422 | V58: 949106 | X58: 965030 | Z58: 948235 | AB58: 16795 | AD58: 26411 | AF58: 25370 | AH58: 1041 | AJ58: 350454 | AL58: 318879 | AN58: 8899 | AP58: 8580 | AR58: 516082 | AT58: 24052625 | AV58: 193.1 | AX58: No
A59: Alternativa de Transporte Integrado -ATI | B59: San Juan | C59: PR | D59: 4094 | E59: 40094 | F59: State Government Unit or Department of Transportation | G59: Full Reporter | H59: 2148346 | I59: 54 | J59: HR | K59: PT | L59: 32 | N59: 8 | P59: 18.2421 | R59: 4.7439 | T59: 48.9513 | V59: 1280494 | X59: 1388955 | Z59: 1315913 | AB59: 73042 | AD59: 75239 | AF59: 72136 | AH59: 3103 | AJ59: 434149 | AL59: 411208 | AN59: 23224 | AP59: 22380 | AR59: 3531150 | AT59: 16751299 | AV59: 20.62 | AX59: No
A60: Regional Transportation Authority | B60: Madison | C60: TN | D60: 4159 | E60: 40159 | F60: Independent Public Agency or Authority of Transit Service | G60: Full Reporter | H60: 969587 | I60: 46 | J60: CR | K60: PT | L60: 8 | N60: 2 | P60: 27.2001 | R60: 15.8946 | T60: 31.5783 | V60: 185032 | X60: 208873 | Z60: 184417 | AB60: 24456 | AD60: 9329 | AF60: 6780 | AH60: 2549 | AJ60: 80763 | AL60: 75873 | AN60: 3127 | AP60: 2616 | AR60: 214101 | AT60: 3403059 | AV60: 62.8 | AX60: No
A61: Staten Island Rapid Transit Operating Authority, dba: MTA Staten Island Railway | B61: Staten Island | C61: NY | D61: 2099 | E61: 20099 | F61: Subsidiary Unit of a Transit Agency, Reporting Separately | G61: Full Reporter | H61: 18351295 | I61: 44 | J61: HR | K61: DO | L61: 44 | N61: 11 | P61: 14.9787 | R61: 6.2369 | T61: 20.2651 | V61: 2119585 | X61: 2255067 | Z61: 2005981 | AB61: 249086 | AD61: 144198 | AF61: 133922 | AH61: 10276 | AJ61: 563767 | AL61: 501496 | AN61: 36049 | AP61: 33480 | AR61: 2713941 | AT61: 16926538 | AV61: 28.6 | AX61: No
A62: Connecticut Department of Transportation | B62: Newington | C62: CT | D62: 1102 | E62: 10102 | F62: State Government Unit or Department of Transportation | G62: Full Reporter | H62: 924859 | I62: 43 | J62: CR | K62: PT | L62: 28 | N62: 5 | P62: 41.5304 | R62: 26.9747 | T62: 14.137 | V62: 1532134 | X62: 1717047 | Z62: 1403229 | AB62: 313818 | AD62: 40817 | AF62: 33788 | AH62: 7029 | AJ62: 501997 | AL62: 418641 | AN62: 11906 | AP62: 9943 | AR62: 477660 | AT62: 12884750 | AV62: 101.2 | AX62: No
A63: Valley Metro Rail, Inc. | B63: Phoenix | C63: AZ | D63: 9209 | E63: 90209 | F63: Other Publicly-Owned or Privately Chartered Corporation | G63: Full Reporter | H63: 3629114 | I63: 38 | J63: LR | K63: PT | L63: 38 | N63: 17 | P63: 15.7327 | R63: 7.0599 | T63: 59.3261 | V63: 3379368 | X63: 3435184 | Z63: 3401452 | AB63: 33732 | AD63: 220467 | AF63: 216203 | AH63: 4264 | AJ63: 1639416 | AL63: 1623906 | AN63: 105253 | AP63: 103186 | AR63: 12826471 | AT63: 90553779 | AV63: 54.48 | AX63: No
A64: Altamont Corridor Express | B64: Stockton | C64: CA | D64: 9182 | E64: 90182 | F64: Independent Public Agency or Authority of Transit Service | G64: Full Reporter | H64: 370583 | I64: 35 | J64: CR | K64: PT | L64: 35 | N64: 7 | P64: 39.3647 | R64: 43.7104 | T64: 41.437 | V64: 1050950 | X64: 1050950 | Z64: 1008877 | AB64: 42073 | AD64: 31545 | AF64: 25629 | AH64: 5916 | AJ64: 168072 | AL64: 158131 | AN64: 4801 | AP64: 4126 | AR64: 1061990 | AT64: 46419957 | AV64: 172 | AX64: No
... A67: Pennsylvania Department of Transportation | B67: Harrisburg | C67: PA | D67: 3057 | E67: 30057 | F67: State Government Unit or Department of Transportation | G67: Full Reporter | H67: 5441567 | I67: 20 | J67: CR | K67: PT | L67: 20 | N67: 2 | P67: 56.7263 | R67: 86.2939 | T67: 20.1547 | V67: 2195188 | X67: 1628329 | Z67: 1628329 | AB67: 0 | AD67: 28705 | AF67: 28705 | AH67: 0 | AJ67: 325666 | AL67: 325666 | AN67: 5741 | AP67: 5741 | AR67: 578541 | AT67: 49924566 | AV67: 144.4 | AX67: No
A68: Sonoma-Marin Area Rail Transit District | B68: Petaluma | C68: CA | E68: 90299 | F68: Independent Public Agency or Authority of Transit Service | G68: Full Reporter | H68: 308231 | I68: 12 | J68: CR | K68: DO | L68: 12 | N68: 4 | P68: 28.3315 | R68: 23.8338 | T68: 19.56 | V68: 857003 | X68: 833350 | Z68: 821415 | AB68: 11935 | AD68: 30370 | AF68: 28993 | AH68: 1377 | AJ68: 389580 | AL68: 384000 | AN68: 14198 | AP68: 13554 | AR68: 567103 | AT68: 13516234 | AV68: 90.1 | AX68: No
N71: =SUM(N2:N68) -> 2748

Sheet Fuel and Energy_rail only
A1: Agency | B1: City | C1: State | D1: Legacy NTD ID | E1: NTD ID | F1: Organization Type | G1: Primary UZA Population | H1: Agency VOMS | I1: Mode | J1: TOS | K1: Mode VOMS | L1: Fuel/Energy Used: | M1: Diesel (gal) | N1: Diesel (gal) Questionable | O1: Gasoline (gal) | P1: Gasoline (gal) Questionable | Q1: Liquefied Petroleum Gas (gal equivalent) | R1: Liquefied Petroleum Gas (gal equivalent) Questionable | S1: Compressed Natural Gas (gal equivalent) | T1: Compressed Natural Gas (gal equivalent) Questionable | U1: Bio-Diesel (gal) | V1: Bio-Diesel (gal) Questionable | W1: Other Fuel (gal/gal equivalent) | X1: Other Fuel (gal/gal equivalent) Questionable | Y1: Electric Propulsion (kwh) | Z1: Electric Propulsion (kwh) Questionable | AA1: Electric Battery (kwh) | AB1: Electric Battery (kwh) Questionable | AC1: Miles Traveled by Vehicles Fueled by: | AD1: Diesel | AE1: Diesel Questionable | AF1: Gasoline | AG1: Gasoline Questionable | AH1: Liquefied Petroleum Gas | AI1: Liquefied Petroleum Gas Questionable | AJ1: Compressed Natural Gas | AK1: Compressed Natural Gas Questionable | AL1: Other Fuel | AM1: Other Fuel Questionable | AN1: Electric Propulsion | AO1: Electric Propulsion Questionable | AP1: Electric Battery | AQ1: Electric Battery Questionable | AR1: Miles per Gallon/KwH: | AS1: Diesel (mpg) | AT1: Diesel (mpg) Questionable | AU1: Gasoline (mpg) | AV1: Gasoline (mpg) Questionable | AW1: Liquefied Petroleum Gas (mpg) | AX1: Liquefied Petroleum Gas (mpg) Questionable | AY1: Compressed Natural Gas (mpg) | AZ1: Compressed Natural Gas (mpg) Questionable | BA1: Other Fuel (mpg) | BB1: Other Fuel (mpg) Questionable | BC1: Electric Propulsion (mi/kwh) | BD1: Electric Propulsion (mi/kwh) Questionable | BE1: Electric Battery (mi/kwh) | BF1: Electric Battery (mi/kwh) Questionable | BG1: Any data questionable?
A2: MTA New York City Transit | B2: Brooklyn | C2: NY | D2: 2008 | E2: 20008 | F2: Subsidiary Unit of a Transit Agency, Reporting Separately | G2: 18351295 | H2: 10427 | I2: HR | J2: DO | K2: 5413 | M2: 0 | O2: 0 | Q2: 0 | S2: 0 | U2: 0 | W2: 0 | Y2: 1596235000 | AA2: 0 | AD2: 0 | AF2: 0 | AH2: 0 | AJ2: 0 | AL2: 0 | AN2: 335497633 | AP2: 0 | BC2: 0.2102 | BG2: No
A3: New Jersey Transit Corporation | B3: Newark | C3: NJ | D3: 2080 | E3: 20080 | F3: Other Publicly-Owned or Privately Chartered Corporation | G3: 18351295 | H3: 3646 | I3: CR | J3: DO | K3: 904 | M3: 13166567 | O3: 0 | Q3: 0 | S3: 0 | U3: 0 | W3: 0 | Y3: 359673989 | AA3: 0 | AD3: 2485889 | AF3: 0 | AH3: 0 | AJ3: 0 | AL3: 1663636 | AN3: 8381067 | AP3: 0 | AS3: 0.1888 | BC3: 0.0233 | BG3: No
A4: New Jersey Transit Corporation | B4: Newark | C4: NJ | D4: 2080 | E4: 20080 | F4: Other Publicly-Owned or Privately Chartered Corporation | G4: 18351295 | H4: 3646 | I4: LR | J4: PT | K4: 42 | M4: 0 | O4: 0 | Q4: 0 | S4: 0 | U4: 0 | W4: 0 | Y4: 27163871 | AA4: 0 | AD4: 0 | AF4: 0 | AH4: 0 | AJ4: 0 | AL4: 0 | AN4: 2073346 | AP4: 0 | BC4: 0.0763 | BG4: No
A5: New Jersey Transit Corporation | B5: Newark | C5: NJ | D5: 2080 | E5: 20080 | F5: Other Publicly-Owned or Privately Chartered Corporation | G5: 18351295 | H5: 3646 | I5: LR | J5: DO | K5: 15 | M5: 0 | O5: 0 | Q5: 0 | S5: 0 | U5: 0 | W5: 0 | Y5: 6694675 | AA5: 0 | AD5: 0 | AF5: 0 | AH5: 0 | AJ5: 0 | AL5: 0 | AN5: 492775 | AP5: 0 | BC5: 0.0736 | BG5: No
A6: Los Angeles County Metropolitan Transportation Authority, dba: Metro | B6: Los Angeles | C6: CA | D6: 9154 | E6: 90154 | F6: Independent Public Agency or Authority of Transit Service | G6: 12150996 | H6: 3482 | I6: HR | J6: DO | K6: 68 | M6: 0 | O6: 0 | Q6: 0 | S6: 0 | U6: 0 | W6: 0 | Y6: 82163176 | AA6: 0 | AD6: 0 | AF6: 0 | AH6: 0 | AJ6: 0 | AL6: 0 | AN6: 6909214 | AP6: 0 | BC6: 0.0841 | BG6: No
A7: Los Angeles County Metropolitan Transportation Authority, dba: Metro | B7: Los Angeles | C7: CA | D7: 9154 | E7: 90154 | F7: Independent Public Agency or Authority of Transit Service | G7: 12150996 | H7: 3482 | I7: LR | J7: DO | K7: 203 | M7: 0 | O7: 0 | Q7: 0 | S7: 0 | U7: 0 | W7: 0 | Y7: 144995154 | AA7: 0 | AD7: 0 | AF7: 0 | AH7: 0 | AJ7: 0 | AL7: 0 | AN7: 16469107 | AP7: 0 | BC7: 0.1136 | BG7: No
A8: Washington Metropolitan Area Transit Authority | B8: Washington | C8: DC | D8: 3030 | E8: 30030 | F8: Independent Public Agency or Authority of Transit Service | G8: 4586770 | H8: 3304 | I8: HR | J8: DO | K8: 998 | M8: 0 | O8: 0 | Q8: 0 | S8: 0 | U8: 0 | W8: 0 | Y8: 576455528 | AA8: 0 | AD8: 0 | AF8: 0 | AH8: 0 | AJ8: 0 | AL8: 0 | AN8: 64920984 | AP8: 0 | BC8: 0.1126 | BG8: No
A9: Chicago Transit Authority | B9: Chicago | C9: IL | D9: 5066 | E9: 50066 | F9: Independent Public Agency or Authority of Transit Service | G9: 8608208 | H9: 2703 | I9: HR | J9: DO | K9: 1148 | M9: 0 | O9: 0 | Q9: 0 | S9: 0 | U9: 0 | W9: 0 | Y9: 366545522 | AA9: 0 | AD9: 0 | AF9: 0 | AH9: 0 | AJ9: 0 | AL9: 0 | AN9: 63157258 | AP9: 0 | BC9: 0.1723 | BG9: No
A10: Massachusetts Bay Transportation Authority | B10: Boston | C10: MA | D10: 1003 | E10: 10003 | F10: Independent Public Agency or Authority of Transit Service | G10: 4181019 | H10: 2428 | I10: CR | J10: PT | K10: 436 | M10: 13360985 | O10: 0 | Q10: 0 | S10: 0 | U10: 0 | W10: 0 | Y10: 0 | AA10: 0 | AD10: 4339139 | AF10: 0 | AH10: 0 | AJ10: 0 | AL10: 0 | AN10: 0 | AP10: 0 | AS10: 0.3248 | BG10: No
A11: Massachusetts Bay Transportation Authority | B11: Boston | C11: MA | D11: 1003 | E11: 10003 | F11: Independent Public Agency or Authority of Transit Service | G11: 4181019 | H11: 2428 | I11: HR | J11: DO | K11: 338 | M11: 0 | O11: 0 | Q11: 0 | S11: 0 | U11: 0 | W11: 0 | Y11: 178406868 | AA11: 0 | AD11: 0 | AF11: 0 | AH11: 0 | AJ11: 0 | AL11: 0 | AN11: 22078161 | AP11: 0 | BC11: 0.1238 | BG11: No
A12: Massachusetts Bay Transportation Authority | B12: Boston | C12: MA | D12: 1003 | E12: 10003 | F12: Independent Public Agency or Authority of Transit Service | G12: 4181019 | H12: 2428 | I12: LR | J12: DO | K12: 154 | M12: 0 | O12: 0 | Q12: 0 | S12: 0 | U12: 0 | W12: 0 | Y12: 46803331 | AA12: 0 | AD12: 0 | AF12: 0 | AH12: 0 | AJ12: 0 | AL12: 0 | AN12: 5523588 | AP12: 0 | BC12: 0.118 | BG12: No
A13: Southeastern Pennsylvania Transportation Authority | B13: Philadelphia | C13: PA | D13: 3019 | E13: 30019 | F13: Independent Public Agency or Authority of Transit Service | G13: 5441567 | H13: 2406 | I13: CR | J13: DO | K13: 357 | M13: 0 | O13: 0 | Q13: 0 | S13: 0 | U13: 0 | W13: 0 | Y13: 190958248 | AA13: 0 | AD13: 0 | AF13: 0 | AH13: 0 | AJ13: 0 | AL13: 0 | AN13: 15598066 | AP13: 0 | BC13: 0.0817 | BG13: No
A14: Southeastern Pennsylvania Transportation Authority | B14: Philadelphia | C14: PA | D14: 3019 | E14: 30019 | F14: Independent Public Agency or Authority of Transit Service | G14: 5441567 | H14: 2406 | I14: HR | J14: DO | K14: 286 | M14: 0 | O14: 0 | Q14: 0 | S14: 0 | U14: 0 | W14: 0 | Y14: 125067726 | AA14: 0 | AD14: 0 | AF14: 0 | AH14: 0 | AJ14: 0 | AL14: 0 | AN14: 14000061 | AP14: 0 | BC14: 0.1119 | BG14: No
A15: Metropolitan Transit Authority of Harris County, Texas, dba: Metro | B15: Houston | C15: TX | D15: 6008 | E15: 60008 | F15: Independent Public Agency or Authority of Transit Service | G15: 4944332 | H15: 2157 | I15: LR | J15: DO | K15: 56 | M15: 0 | O15: 0 | Q15: 0 | S15: 0 | U15: 0 | W15: 0 | Y15: 20764234 | AA15: 0 | AD15: 0 | AF15: 0 | AH15: 0 | AJ15: 0 | AL15: 0 | AN15: 3420524 | AP15: 0 | BC15: 0.1647 | BG15: No
A16: Maryland Transit Administration | B16: Baltimore | C16: MD | D16: 3034 | E16: 30034 | F16: State Government Unit or Department of Transportation | G16: 2203663 | H16: 1888 | I16: HR | J16: DO | K16: 54 | M16: 0 | O16: 0 | Q16: 0 | S16: 0 | U16: 0 | W16: 0 | Y16: 44465246 | AA16: 0 | AD16: 0 | AF16: 0 | AH16: 0 | AJ16: 0 | AL16: 0 | AN16: 0 | AP16: 0 | BC16: 0 | BG16: No
A17: Maryland Transit Administration | B17: Baltimore | C17: MD | D17: 3034 | E17: 30034 | F17: State Government Unit or Department of Transportation | G17: 2203663 | H17: 1888 | I17: LR | J17: DO | K17: 38 | M17: 0 | O17: 0 | Q17: 0 | S17: 0 | U17: 0 | W17: 0 | Y17: 25044315 | AA17: 0 | AD17: 0 | AF17: 0 | AH17: 0 | AJ17: 0 | AL17: 0 | AN17: 2679810 | AP17: 0 | BC17: 0.107 | BG17: No
A18: Maryland Transit Administration | B18: Baltimore | C18: MD | D18: 3034 | E18: 30034 | F18: State Government Unit or Department of Transportation | G18: 2203663 | H18: 1888 | I18: CR | J18: PT | K18: 149 | M18: 3709703 | O18: 0 | Q18: 0 | S18: 0 | U18: 0 | W18: 0 | Y18: 21715405 | AA18: 0 | AD18: 764117 | AF18: 0 | AH18: 0 | AJ18: 0 | AL18: 0 | AN18: 163832 | AP18: 0 | AS18: 0.206 | BC18: 0.0075 | BG18: No
A19: County of Miami-Dade, dba: Transportation & Public Work | B19: Miami | C19: FL | D19: 4034 | E19: 40034 | F19: City, County or Local Government Unit or Department of Transportation | G19: 5502379 | H19: 1452 | I19: HR | J19: DO | K19: 76 | M19: 0 | O19: 0 | Q19: 0 | S19: 0 | U19: 0 | W19: 0 | Y19: 66954261 | AA19: 0 | AD19: 0 | AF19: 0 | AH19: 0 | AJ19: 0 | AL19: 0 | AN19: 559892 | AP19: 0 | BC19: 0.0084 | BG19: No
A20: Denver Regional Transportation District | B20: Denver | C20: CO | D20: 8006 | E20: 80006 | F20: Independent Public Agency or Authority of Transit Service | G20: 2374203 | H20: 1431 | I20: CR | J20: DO | K20: 8 | M20: 0 | O20: 0 | Q20: 0 | S20: 0 | U20: 0 | W20: 0 | Y20: 688983 | AA20: 0 | AD20: 0 | AF20: 0 | AH20: 0 | AJ20: 0 | AL20: 0 | AN20: 0 | AP20: 0 | BC20: 0 | BG20: No
A21: Denver Regional Transportation District | B21: Denver | C21: CO | D21: 8006 | E21: 80006 | F21: Independent Public Agency or Authority of Transit Service | G21: 2374203 | H21: 1431 | I21: CR | J21: PT | K21: 44 | M21: 0 | O21: 0 | Q21: 0 | S21: 0 | U21: 0 | W21: 0 | Y21: 40149051 | AA21: 0 | AD21: 0 | AF21: 0 | AH21: 0 | AJ21: 0 | AL21: 0 | AN21: 6311542 | AP21: 0 | BC21: 0.1572 | BG21: No
A22: Denver Regional Transportation District | B22: Denver | C22: CO | D22: 8006 | E22: 80006 | F22: Independent Public Agency or Authority of Transit Service | G22: 2374203 | H22: 1431 | I22: LR | J22: DO | K22: 156 | M22: 0 | O22: 0 | Q22: 0 | S22: 0 | U22: 0 | W22: 0 | Y22: 60630772 | AA22: 0 | AD22: 0 | AF22: 0 | AH22: 0 | AJ22: 0 | AL22: 0 | AN22: 9327859 | AP22: 0 | BC22: 0.1538 | BG22: No
A23: Metro-North Commuter Railroad Company, dba: MTA Metro-North Railroad | B23: New York | C23: NY | D23: 2078 | E23: 20078 | F23: Subsidiary Unit of a Transit Agency, Reporting Separately | G23: 18351295 | H23: 1133 | I23: CR | J23: DO | K23: 1122 | M23: 5697351 | O23: 0 | Q23: 0 | S23: 0 | U23: 0 | W23: 0 | Y23: 367362724 | AA23: 0 | AD23: 0 | AF23: 0 | AH23: 0 | AJ23: 0 | AL23: 2002432 | AN23: 40070882 | AP23: 0 | AS23: 0 | BC23: 0.1091 | BG23: No
A24: Dallas Area Rapid Transit | B24: Dallas | C24: TX | D24: 6056 | E24: 60056 | F24: Independent Public Agency or Authority of Transit Service | G24: 5121892 | H24: 1082 | I24: CR | J24: PT | K24: 23 | M24: 1375987 | O24: 0 | Q24: 0 | S24: 0 | U24: 0 | W24: 0 | Y24: 0 | AA24: 0 | AD24: 460806 | AF24: 0 | AH24: 0 | AJ24: 0 | AL24: 0 | AN24: 0 | AP24: 0 | AS24: 0.3349 | BG24: No
A25: Dallas Area Rapid Transit | B25: Dallas | C25: TX | D25: 6056 | E25: 60056 | F25: Independent Public Agency or Authority of Transit Service | G25: 5121892 | H25: 1082 | I25: LR | J25: DO | K25: 117 | M25: 0 | O25: 0 | Q25: 0 | S25: 0 | U25: 0 | W25: 0 | Y25: 116183770 | AA25: 0 | AD25: 0 | AF25: 0 | AH25: 0 | AJ25: 0 | AL25: 0 | AN25: 9894309 | AP25: 0 | BC25: 0.0852 | BG25: No
A26: Utah Transit Authority | B26: Salt Lake City | C26: UT | D26: 8001 | E26: 80001 | F26: Independent Public Agency or Authority of Transit Service | G26: 1021243 | H26: 1081 | I26: LR | J26: DO | K26: 89 | M26: 0 | O26: 0 | Q26: 0 | S26: 0 | U26: 0 | W26: 0 | Y26: 39602347 | AA26: 0 | AD26: 0 | AF26: 0 | AH26: 0 | AJ26: 0 | AL26: 0 | AN26: 6307169 | AP26: 0 | BC26: 0.1593 | BG26: No
A27: Utah Transit Authority | B27: Salt Lake City | C27: UT | D27: 8001 | E27: 80001 | F27: Independent Public Agency or Authority of Transit Service | G27: 1021243 | H27: 1081 | I27: CR | J27: DO | K27: 50 | M27: 1921417 | O27: 0 | Q27: 0 | S27: 0 | U27: 0 | W27: 0 | Y27: 0 | AA27: 0 | AD27: 850933 | AF27: 0 | AH27: 0 | AJ27: 0 | AL27: 0 | AN27: 0 | AP27: 0 | AS27: 0.4429 | BG27: No
A28: Northeast Illinois Regional Commuter Railroad Corporation, dba: Metra | B28: Chicago | C28: IL | D28: 5118 | E28: 50118 | F28: Independent Public Agency or Authority of Transit Service | G28: 8608208 | H28: 1066 | I28: CR | J28: DO | K28: 539 | M28: 18100043 | O28: 0 | Q28: 0 | S28: 0 | U28: 0 | W28: 0 | Y28: 56262281 | AA28: 0 | AD28: 5202961 | AF28: 0 | AH28: 0 | AJ28: 0 | AL28: 0 | AN28: 3759786 | AP28: 0 | AS28: 0.2875 | BC28: 0.0668 | BG28: No
A29: Northeast Illinois Regional Commuter Railroad Corporation, dba: Metra | B29: Chicago | C29: IL | D29: 5118 | E29: 50118 | F29: Independent Public Agency or Authority of Transit Service | G29: 8608208 | H29: 1066 | I29: CR | J29: PT | K29: 527 | M29: 18100043 | O29: 0 | Q29: 0 | S29: 0 | U29: 0 | W29: 0 | Y29: 0 | AA29: 0 | AD29: 0 | AF29: 0 | AH29: 0 | AJ29: 0 | AL29: 0 | AN29: 0 | AP29: 0 | AS29: 0 | BG29: No
A30: MTA Long Island Rail Road | B30: Jamaica | C30: NY | D30: 2100 | E30: 20100 | F30: Subsidiary Unit of a Transit Agency, Reporting Separately | G30: 18351295 | H30: 1022 | I30: CR | J30: DO | K30: 1022 | M30: 7034074 | O30: 0 | Q30: 0 | S30: 0 | U30: 0 | W30: 0 | Y30: 471350200 | AA30: 0 | AD30: 757533 | AF30: 0 | AH30: 0 | AJ30: 0 | AL30: 757533 | AN30: 54919600 | AP30: 0 | AS30: 0.1077 | BC30: 0.1165 | BG30: No
A31: City and County of San Francisco, dba: San Francisco Municipal Transportation Agency (MUNI) | B31: San Francisco | C31: CA | D31: 9015 | E31: 90015 | F31: City, County or Local Government Unit or Department of Transportation | G31: 3281212 | H31: 996 | I31: LR | J31: DO | K31: 149 | M31: 0 | O31: 0 | Q31: 0 | S31: 0 | U31: 0 | W31: 0 | Y31: 51453351 | AA31: 0 | AD31: 0 | AF31: 0 | AH31: 0 | AJ31: 0 | AL31: 0 | AN31: 5286597 | AP31: 0 | BC31: 0.1027 | BG31: No
A32: Tri-County Metropolitan Transportation District of Oregon, dba: TriMet | B32: Portland | C32: OR | D32: 8 | E32: 8 | F32: Independent Public Agency or Authority of Transit Service | G32: 1849898 | H32: 982 | I32: LR | J32: DO | K32: 116 | M32: 0 | O32: 0 | Q32: 0 | S32: 0 | U32: 0 | W32: 0 | Y32: 54389715 | AA32: 0 | AD32: 0 | AF32: 0 | AH32: 0 | AJ32: 0 | AL32: 0 | AN32: 9045741 | AP32: 0 | BC32: 0.1663 | BG32: No
A33: Metropolitan Atlanta Rapid Transit Authority | B33: Atlanta | C33: GA | D33: 4022 | E33: 40022 | F33: Independent Public Agency or Authority of Transit Service | G33: 4515419 | H33: 943 | I33: HR | J33: DO | K33: 212 | M33: 0 | O33: 0 | Q33: 0 | S33: 0 | U33: 0 | W33: 0 | Y33: 83566447 | AA33: 0 | AD33: 0 | AF33: 0 | AH33: 0 | AJ33: 0 | AL33: 0 | AN33: 19692749 | AP33: 0 | BC33: 0.2357 | BG33: No
A34: Port Authority of Allegheny County | B34: Pittsburgh | C34: PA | D34: 3022 | E34: 30022 | F34: Independent Public Agency or Authority of Transit Service | G34: 1733853 | H34: 930 | I34: LR | J34: DO | K34: 58 | M34: 0 | O34: 0 | Q34: 0 | S34: 0 | U34: 0 | W34: 0 | Y34: 30547053 | AA34: 0 | AD34: 0 | AF34: 0 | AH34: 0 | AJ34: 0 | AL34: 0 | AN34: 2154526 | AP34: 0 | BC34: 0.0705 | BG34: No
A35: San Diego Metropolitan Transit System | B35: San Diego | C35: CA | D35: 9026 | E35: 90026 | F35: Independent Public Agency or Authority of Transit Service | G35: 2956746 | H35: 906 | I35: LR | J35: DO | K35: 103 | M35: 0 | O35: 0 | Q35: 0 | S35: 0 | U35: 0 | W35: 0 | Y35: 52502166 | AA35: 0 | AD35: 0 | AF35: 0 | AH35: 0 | AJ35: 0 | AL35: 0 | AN35: 9579691 | AP35: 0 | BC35: 0.1825 | BG35: No
A36: Metro Transit, dba: Metro Transit | B36: Minneapolis | C36: MN | D36: 5027 | E36: 50027 | F36: Subsidiary Unit of a Transit Agency, Reporting Separately | G36: 2650890 | H36: 823 | I36: LR | J36: DO | K36: 76 | M36: 0 | O36: 0 | Q36: 0 | S36: 0 | U36: 0 | W36: 0 | Y36: 31871652 | AA36: 0 | AD36: 0 | AF36: 0 | AH36: 0 | AJ36: 0 | AL36: 0 | AN36: 4153269 | AP36: 0 | BC36: 0.1303 | BG36: No
A37: Metro Transit, dba: Metro Transit | B37: Minneapolis | C37: MN | D37: 5027 | E37: 50027 | F37: Subsidiary Unit of a Transit Agency, Reporting Separately | G37: 2650890 | H37: 823 | I37: CR | J37: PT | K37: 20 | M37: 213780 | O37: 0 | Q37: 0 | S37: 0 | U37: 0 | W37: 0 | Y37: 0 | AA37: 0 | AD37: 63438 | AF37: 0 | AH37: 0 | AJ37: 0 | AL37: 0 | AN37: 0 | AP37: 0 | AS37: 0.2967 | BG37: No
A38: Santa Clara Valley Transportation Authority | B38: San Jose | C38: CA | D38: 9013 | E38: 90013 | F38: Independent Public Agency or Authority of Transit Service | G38: 1664496 | H38: 635 | I38: LR | J38: DO | K38: 61 | M38: 0 | O38: 0 | Q38: 0 | S38: 0 | U38: 0 | W38: 0 | Y38: 22062611 | AA38: 0 | AD38: 0 | AF38: 0 | AH38: 0 | AJ38: 0 | AL38: 0 | AN38: 3093884 | AP38: 0 | BC38: 0.1402 | BG38: No
A39: San Francisco Bay Area Rapid Transit District | B39: Oakland | C39: CA | D39: 9003 | E39: 90003 | F39: Independent Public Agency or Authority of Transit Service | G39: 3281212 | H39: 616 | I39: HR | J39: DO | K39: 599 | M39: 0 | O39: 0 | Q39: 0 | S39: 0 | U39: 0 | W39: 0 | Y39: 298200780 | AA39: 0 | AD39: 0 | AF39: 0 | AH39: 0 | AJ39: 0 | AL39: 0 | AN39: 61097126 | AP39: 0 | BC39: 0.2049 | BG39: No
A40: Bi-State Development Agency of the Missouri-Illinois Metropolitan District, dba: St. Louis Metro | B40: Saint Louis | C40: MO | D40: 7006 | E40: 70006 | F40: Independent Public Agency or Authority of Transit Service | G40: 2150706 | H40: 493 | I40: LR | J40: DO | K40: 50 | M40: 0 | O40: 0 | Q40: 0 | S40: 0 | U40: 0 | W40: 0 | Y40: 36496148 | AA40: 0 | AD40: 0 | AF40: 0 | AH40: 0 | AJ40: 0 | AL40: 0 | AN40: 5934378 | AP40: 0 | BC40: 0.1626 | BG40: No
A41: The Greater Cleveland Regional Transit Authority | B41: Cleveland | C41: OH | D41: 5015 | E41: 50015 | F41: Independent Public Agency or Authority of Transit Service | G41: 1780673 | H41: 418 | I41: LR | J41: DO | K41: 6 | M41: 0 | O41: 0 | Q41: 0 | S41: 0 | U41: 0 | W41: 0 | Y41: 11321758 | AA41: 0 | AD41: 0 | AF41: 0 | AH41: 0 | AJ41: 0 | AL41: 0 | AN41: 625941 | AP41: 0 | BC41: 0.0553 | BG41: No
A42: The Greater Cleveland Regional Transit Authority | B42: Cleveland | C42: OH | D42: 5015 | E42: 50015 | F42: Independent Public Agency or Authority of Transit Service | G42: 1780673 | H42: 418 | I42: HR | J42: DO | K42: 16 | M42: 0 | O42: 0 | Q42: 0 | S42: 0 | U42: 0 | W42: 0 | Y42: 20768378 | AA42: 0 | AD42: 0 | AF42: 0 | AH42: 0 | AJ42: 0 | AL42: 0 | AN42: 2295631 | AP42: 0 | BC42: 0.1105 | BG42: No
A43: Transportation District Commission of Hampton Roads, dba: Hampton Roads Transit | B43: Hampton | C43: VA | D43: 3083 | E43: 30083 | F43: Independent Public Agency or Authority of Transit Service | G43: 1439666 | H43: 417 | I43: LR | J43: DO | K43: 6 | M43: 0 | O43: 0 | Q43: 0 | S43: 0 | U43: 0 | W43: 0 | Y43: 3318000 | AA43: 0 | AD43: 0 | AF43: 0 | AH43: 0 | AJ43: 0 | AL43: 0 | AN43: 345837 | AP43: 0 | BC43: 0.1042 | BG43: No
A44: City of Charlotte North Carolina, dba: Charlotte Area Transit System | B44: Charlotte | C44: NC | D44: 4008 | E44: 40008 | F44: City, County or Local Government Unit or Department of Transportation | G44: 1249442 | H44: 409 | I44: LR | J44: DO | K44: 36 | M44: 0 | O44: 0 | Q44: 0 | S44: 0 | U44: 0 | W44: 0 | Y44: 16786660 | AA44: 0 | AD44: 0 | AF44: 0 | AH44: 0 | AJ44: 0 | AL44: 0 | AN44: 2267804 | AP44: 0 | BC44: 0.1351 | BG44: No
A45: Central Puget Sound Regional Transit Authority, dba: Sound Transit | B45: Seattle | C45: WA | D45: 40 | E45: 40 | F45: Independent Public Agency or Authority of Transit Service | G45: 3059393 | H45: 381 | I45: CR | J45: PT | K45: 70 | M45: 625305 | O45: 0 | Q45: 0 | S45: 0 | U45: 0 | W45: 0 | Y45: 0 | AA45: 0 | AD45: 335545 | AF45: 0 | AH45: 0 | AJ45: 0 | AL45: 0 | AN45: 0 | AP45: 0 | AS45: 0.5366 | BG45: No
A46: Central Puget Sound Regional Transit Authority, dba: Sound Transit | B46: Seattle | C46: WA | D46: 40 | E46: 40 | F46: Independent Public Agency or Authority of Transit Service | G46: 3059393 | H46: 381 | I46: LR | J46: DO | K46: 48 | M46: 0 | O46: 0 | Q46: 0 | S46: 0 | U46: 0 | W46: 0 | Y46: 20355203 | AA46: 0 | AD46: 0 | AF46: 0 | AH46: 0 | AJ46: 0 | AL46: 0 | AN46: 4232555 | AP46: 0 | BC46: 0.2079 | BG46: No
A47: Niagara Frontier Transportation Authority | B47: Buffalo | C47: NY | D47: 2004 | E47: 20004 | F47: Independent Public Agency or Authority of Transit Service | G47: 935906 | H47: 359 | I47: LR | J47: DO | K47: 23 | M47: 0 | O47: 0 | Q47: 0 | S47: 0 | U47: 0 | W47: 0 | Y47: 7920559 | AA47: 0 | AD47: 0 | AF47: 0 | AH47: 0 | AJ47: 0 | AL47: 0 | AN47: 990450 | AP47: 0 | BC47: 0.125 | BG47: No
A48: Sacramento Regional Transit District, dba: Sacramento RT | B48: Sacramento | C48: CA | D48: 9019 | E48: 90019 | F48: Independent Public Agency or Authority of Transit Service | G48: 1723634 | H48: 331 | I48: LR | J48: DO | K48: 69 | M48: 0 | O48: 0 | Q48: 0 | S48: 0 | U48: 0 | W48: 0 | Y48: 30089655 | AA48: 0 | AD48: 0 | AF48: 0 | AH48: 0 | AJ48: 0 | AL48: 0 | AN48: 3768892 | AP48: 0 | BC48: 0.1253 | BG48: No
A49: Fort Worth Transportation Authority, dba: Trinity Metro | B49: Fort Worth | C49: TX | D49: 6007 | E49: 60007 | F49: Independent Public Agency or Authority of Transit Service | G49: 5121892 | H49: 312 | I49: CR | J49: PT | K49: 20 | M49: 442412 | O49: 0 | Q49: 0 | S49: 0 | U49: 0 | W49: 0 | Y49: 0 | AA49: 0 | AD49: 2349673 | AF49: 0 | AH49: 0 | AJ49: 0 | AL49: 0 | AN49: 0 | AP49: 0 | AS49: 5.3111 | BG49: No
A50: Port Authority Trans-Hudson Corporation | B50: New York | C50: NJ | D50: 2098 | E50: 20098 | F50: Independent Public Agency or Authority of Transit Service | G50: 18351295 | H50: 310 | I50: HR | J50: DO | K50: 304 | M50: 0 | O50: 0 | Q50: 0 | S50: 0 | U50: 0 | W50: 0 | Y50: 93567629 | AA50: 0 | AD50: 0 | AF50: 0 | AH50: 0 | AJ50: 0 | AL50: 0 | AN50: 13256385 | AP50: 0 | BC50: 0.1417 | BG50: No
A51: North County Transit District | B51: Oceanside | C51: CA | D51: 9030 | E51: 90030 | F51: Independent Public Agency or Authority of Transit Service | G51: 2956746 | H51: 205 | I51: CR | J51: PT | K51: 24 | M51: 766773 | O51: 0 | Q51: 0 | S51: 0 | U51: 0 | W51: 0 | Y51: 0 | AA51: 0 | AD51: 253519 | AF51: 0 | AH51: 0 | AJ51: 0 | AL51: 0 | AN51: 0 | AP51: 0 | AS51: 0.3306 | BG51: No
A52: Southern California Regional Rail Authority, dba: Metrolink | B52: Los Angeles | C52: CA | D52: 9151 | E52: 90151 | F52: Independent Public Agency or Authority of Transit Service | G52: 12150996 | H52: 195 | I52: CR | J52: PT | K52: 195 | M52: 8293151 | O52: 0 | Q52: 0 | S52: 0 | U52: 0 | W52: 0 | Y52: 0 | AA52: 0 | AD52: 2539026 | AF52: 0 | AH52: 0 | AJ52: 0 | AL52: 0 | AN52: 0 | AP52: 0 | AS52: 0.3062 | BG52: No
A53: Peninsula Corridor Joint Powers Board, dba: Caltrain | B53: San Carlos | C53: CA | D53: 9134 | E53: 90134 | F53: Independent Public Agency or Authority of Transit Service | G53: 3281212 | H53: 141 | I53: CR | J53: PT | K53: 111 | M53: 3805923 | O53: 0 | Q53: 0 | S53: 0 | U53: 0 | W53: 0 | Y53: 0 | AA53: 0 | AD53: 1179829 | AF53: 0 | AH53: 0 | AJ53: 0 | AL53: 0 | AN53: 0 | AP53: 0 | AS53: 0.31 | BG53: No
A54: Virginia Railway Express | B54: Alexandria | C54: VA | D54: 3073 | E54: 30073 | F54: Independent Public Agency or Authority of Transit Service | G54: 4586770 | H54: 99 | I54: CR | J54: PT | K54: 99 | M54: 1430638 | O54: 0 | Q54: 0 | S54: 0 | U54: 0 | W54: 0 | Y54: 0 | AA54: 0 | AD54: 333956 | AF54: 0 | AH54: 0 | AJ54: 0 | AL54: 0 | AN54: 0 | AP54: 0 | AS54: 0.2334 | BG54: No
A55: Port Authority Transit Corporation | B55: Lindenwold | C55: NJ | D55: 2075 | E55: 20075 | F55: Independent Public Agency or Authority of Transit Service | G55: 5441567 | H55: 78 | I55: HR | J55: DO | K55: 78 | M55: 0 | O55: 0 | Q55: 0 | S55: 0 | U55: 0 | W55: 0 | Y55: 32179173 | AA55: 0 | AD55: 0 | AF55: 0 | AH55: 0 | AJ55: 0 | AL55: 0 | AN55: 4661254 | AP55: 0 | BC55: 0.1449 | BG55: No
A56: Northern Indiana Commuter Transportation District | B56: Chesterton | C56: IN | D56: 5104 | E56: 50104 | F56: Independent Public Agency or Authority of Transit Service | G56: 8608208 | H56: 70 | I56: CR | J56: DO | K56: 70 | M56: 0 | O56: 0 | Q56: 0 | S56: 0 | U56: 0 | W56: 0 | Y56: 18158000 | AA56: 0 | AD56: 0 | AF56: 0 | AH56: 0 | AJ56: 0 | AL56: 0 | AN56: 3510093 | AP56: 0 | BC56: 0.1933 | BG56: No
A57: South Florida Regional Transportation Authority, dba: TRI-Rail | B57: Pompano Beach | C57: FL | D57: 4077 | E57: 40077 | F57: Independent Public Agency or Authority of Transit Service | G57: 5502379 | H57: 65 | I57: CR | J57: PT | K57: 43 | M57: 2838234 | O57: 0 | Q57: 0 | S57: 0 | U57: 0 | W57: 0 | Y57: 0 | AA57: 0 | AD57: 1018267 | AF57: 0 | AH57: 0 | AJ57: 0 | AL57: 0 | AN57: 0 | AP57: 0 | AS57: 0.3588 | BG57: No
A58: Rio Metro Regional Transit District | B58: Albuquerque | C58: NM | D58: 6111 | E58: 60111 | F58: Independent Public Agency or Authority of Transit Service | G58: 741318 | H58: 58 | I58: CR | J58: PT | K58: 25 | M58: 0 | O58: 0 | Q58: 0 | S58: 0 | U58: 792273 | W58: 0 | Y58: 0 | AA58: 0 | AD58: 350453 | AF58: 0 | AH58: 0 | AJ58: 0 | AL58: 0 | AN58: 0 | AP58: 0 | BG58: No
A59: Alternativa de Transporte Integrado -ATI | B59: San Juan | C59: PR | D59: 4094 | E59: 40094 | F59: State Government Unit or Department of Transportation | G59: 2148346 | H59: 54 | I59: HR | J59: PT | K59: 32 | M59: 0 | O59: 0 | Q59: 0 | S59: 0 | U59: 0 | W59: 0 | Y59: 4009792 | AA59: 0 | AD59: 0 | AF59: 0 | AH59: 0 | AJ59: 0 | AL59: 0 | AN59: 1432878 | AP59: 0 | BC59: 0.3573 | BG59: No
A60: Regional Transportation Authority | B60: Madison | C60: TN | D60: 4159 | E60: 40159 | F60: Independent Public Agency or Authority of Transit Service | G60: 969587 | H60: 46 | I60: CR | J60: PT | K60: 8 | M60: 195054 | O60: 0 | Q60: 0 | S60: 0 | U60: 0 | W60: 0 | Y60: 0 | AA60: 0 | AD60: 71832 | AF60: 0 | AH60: 0 | AJ60: 0 | AL60: 0 | AN60: 0 | AP60: 0 | AS60: 0.3683 | BG60: No
A61: Staten Island Rapid Transit Operating Authority, dba: MTA Staten Island Railway | B61: Staten Island | C61: NY | D61: 2099 | E61: 20099 | F61: Subsidiary Unit of a Transit Agency, Reporting Separately | G61: 18351295 | H61: 44 | I61: HR | J61: DO | K61: 44 | M61: 0 | O61: 0 | Q61: 0 | S61: 0 | U61: 0 | W61: 0 | Y61: 27982542 | AA61: 0 | AD61: 0 | AF61: 0 | AH61: 0 | AJ61: 0 | AL61: 0 | AN61: 2267541 | AP61: 0 | BC61: 0.081 | BG61: No
A62: Connecticut Department of Transportation | B62: Newington | C62: CT | D62: 1102 | E62: 10102 | F62: State Government Unit or Department of Transportation | G62: 924859 | H62: 43 | I62: CR | J62: PT | K62: 28 | M62: 1678569 | O62: 0 | Q62: 0 | S62: 0 | U62: 0 | W62: 0 | Y62: 0 | AA62: 0 | AD62: 724004 | AF62: 0 | AH62: 0 | AJ62: 0 | AL62: 0 | AN62: 0 | AP62: 0 | AS62: 0.4313 | BG62: No
A63: Valley Metro Rail, Inc. | B63: Phoenix | C63: AZ | D63: 9209 | E63: 90209 | F63: Other Publicly-Owned or Privately Chartered Corporation | G63: 3629114 | H63: 38 | I63: LR | J63: PT | K63: 38 | M63: 0 | O63: 0 | Q63: 0 | S63: 0 | U63: 0 | W63: 0 | Y63: 23474521 | AA63: 0 | AD63: 0 | AF63: 0 | AH63: 0 | AJ63: 0 | AL63: 0 | AN63: 3452467 | AP63: 0 | BC63: 0.1471 | BG63: No
A64: Altamont Corridor Express | B64: Stockton | C64: CA | D64: 9182 | E64: 90182 | F64: Independent Public Agency or Authority of Transit Service | G64: 370583 | H64: 35 | I64: CR | J64: PT | K64: 35 | M64: 514210 | O64: 0 | Q64: 0 | S64: 0 | U64: 0 | W64: 0 | Y64: 0 | AA64: 0 | AD64: 130583 | AF64: 0 | AH64: 0 | AJ64: 0 | AL64: 0 | AN64: 0 | AP64: 0 | AS64: 0.2539 | BG64: No
A65: Central Florida Commuter Rail, dba: SunRail | B65: Tallahassee | C65: FL | D65: 4232 | E65: 40232 | F65: State Government Unit or Department of Transportation | G65: 1510516 | H65: 25 | I65: CR | J65: PT | K65: 25 | M65: 810032 | O65: 0 | Q65: 0 | S65: 0 | U65: 0 | W65: 0 | Y65: 0 | AA65: 0 | AD65: 486222 | AF65: 0 | AH65: 0 | AJ65: 0 | AL65: 0 | AN65: 0 | AP65: 0 | AS65: 0.6003 | BG65: No
A66: Northern New England Passenger Rail Authority | B66: Portland | C66: ME | D66: 1115 | E66: 10115 | F66: Independent Public Agency or Authority of Transit Service | G66: 203914 | H66: 21 | I66: CR | J66: PT | K66: 21 | M66: 628302 | O66: 0 | Q66: 0 | S66: 0 | U66: 0 | W66: 0 | Y66: 0 | AA66: 0 | AD66: 0 | AF66: 0 | AH66: 0 | AJ66: 0 | AL66: 0 | AN66: 0 | AP66: 0 | AS66: 0 | BG66: No
A67: Pennsylvania Department of Transportation | B67: Harrisburg | C67: PA | D67: 3057 | E67: 30057 | F67: State Government Unit or Department of Transportation | G67: 5441567 | H67: 20 | I67: CR | J67: PT | K67: 20 | M67: 0 | O67: 0 | Q67: 0 | S67: 0 | U67: 0 | W67: 0 | Y67: 27325354 | AA67: 0 | AD67: 0 | AF67: 0 | AH67: 0 | AJ67: 0 | AL67: 0 | AN67: 0 | AP67: 0 | BC67: 0 | BG67: No
A68: Sonoma-Marin Area Rail Transit District | B68: Petaluma | C68: CA | E68: 90299 | F68: Independent Public Agency or Authority of Transit Service | G68: 308231 | H68: 12 | I68: CR | J68: DO | K68: 12 | M68: 286520 | O68: 0 | Q68: 0 | S68: 0 | U68: 0 | W68: 0 | Y68: 0 | AA68: 0 | AD68: 931897 | AF68: 0 | AH68: 0 | AJ68: 0 | AL68: 0 | AN68: 0 | AP68: 0 | AS68: 3.2525 | BG68: No
M70: =SUM(M1:M68) -> 104995073 | N70: =SUM(N1:N68) -> 0 | O70: =SUM(O1:O68) -> 0 | P70: =SUM(P1:P68) -> 0 | Q70: =SUM(Q1:Q68) -> 0 | R70: =SUM(R1:R68) -> 0 | S70: =SUM(S1:S68) -> 0 | T70: =SUM(T1:T68) -> 0 | ... AB70: =SUM(AB1:AB68) -> 0

Sheet NEMS bus covid
A1: NEMS AEO2026 Public Release, input/tdm/trnldvx.xlsx (https://github.com/EIAgov/NEMS/tree/AEO2026-Public-Release), named ranges TBCOVID (transit bus COVID travel impact by census division), TB_COEF (transit bus per-capita travel equation: constant, ln GDP per capita, ln fuel price, COVID term), TMCOVID (COVID travel impact, row 1 intercity bus, row 2 school bus; travel x (1 - TMCOVID)), TBPMTHIST (transit bus passenger-miles, millions), TMODINIT (intercity and school bus passenger-miles, millions). Used by tran.f lines ~8251-8309. Pasted 2026-10-13.
A3: year | C3: 1995 | D3: 1996 | E3: 1997 | F3: 1998 | G3: 1999 | H3: 2000 | I3: 2001 | J3: 2002 | K3: 2003 | L3: 2004 | M3: 2005 | N3: 2006 | O3: 2007 | P3: 2008 | Q3: 2009 | R3: 2010 | S3: 2011 | T3: 2012 | U3: 2013 | V3: 2014 | W3: 2015 | X3: 2016 | Y3: 2017 | Z3: 2018 | AA3: 2019 | AB3: 2020 | AC3: 2021 | AD3: 2022 | AE3: 2023 | AF3: 2024 | AG3: 2025 | AH3: 2026 | AI3: 2027 | AJ3: 2028 | AK3: 2029 | AL3: 2030 | AM3: 2031 | AN3: 2032 | AO3: 2033 | AP3: 2034 | AQ3: 2035 | AR3: 2036 | AS3: 2037 | AT3: 2038 | AU3: 2039 | AV3: 2040 | AW3: 2041 | AX3: 2042 | AY3: 2043 | AZ3: 2044 | BA3: 2045 | BB3: 2046 | BC3: 2047 | BD3: 2048 | BE3: 2049 | BF3: 2050
A4: TBCOVID by census division 1-9
A5: division 1 | C5: 0 | D5: 0 | E5: 0 | F5: 0 | G5: 0 | H5: 0 | I5: 0 | J5: 0 | K5: 0 | L5: 0 | M5: 0 | N5: 0 | O5: 0 | P5: 0 | Q5: 0 | R5: 0 | S5: 0 | T5: 0 | U5: 0 | V5: 0 | W5: 0 | X5: 0 | Y5: 0 | Z5: 0 | AA5: 0 | AB5: 1 | AC5: 4.0396062 | AD5: 2.9204162 | AE5: 2.1026997 | AF5: 1.4718898 | AG5: 1.0303228 | AH5: 0.72122598 | AI5: 0.50485819 | AJ5: 0.35340073 | AK5: 0.24738051 | AL5: 0.22264246 | AM5: 0.22264246 | AN5: 0.22264246 | AO5: 0.22264246 | AP5: 0.22264246 | AQ5: 0.22264246 | AR5: 0.22264246 | AS5: 0.22264246 | AT5: 0.22264246 | AU5: 0.22264246 | AV5: 0.22264246 | AW5: 0.22264246 | AX5: 0.22264246 | AY5: 0.22264246 | AZ5: 0.22264246 | BA5: 0.22264246 | BB5: 0.22264246 | BC5: 0.22264246 | BD5: 0.22264246 | BE5: 0.22264246 | BF5: 0.22264246
A6: division 2 | C6: 0 | D6: 0 | E6: 0 | F6: 0 | G6: 0 | H6: 0 | I6: 0 | J6: 0 | K6: 0 | L6: 0 | M6: 0 | N6: 0 | O6: 0 | P6: 0 | Q6: 0 | R6: 0 | S6: 0 | T6: 0 | U6: 0 | V6: 0 | W6: 0 | X6: 0 | Y6: 0 | Z6: 0 | AA6: 0 | AB6: 1 | AC6: 1.5197439 | AD6: 1.1232421 | AE6: 0.83119915 | AF6: 0.61508737 | AG6: 0.45516465 | AH6: 0.33682184 | AI6: 0.24924816 | AJ6: 0.18444364 | AK6: 0.13648829 | AL6: 0.10100134 | AM6: 0.07474099 | AN6: 0.055308333 | AO6: 0.040928166 | AP6: 0.030286843 | AQ6: 0.022412264 | AR6: 0.022412264 | AS6: 0.022412264 | AT6: 0.022412264 | AU6: 0.022412264 | AV6: 0.022412264 | AW6: 0.022412264 | AX6: 0.022412264 | AY6: 0.022412264 | AZ6: 0.022412264 | BA6: 0.022412264 | BB6: 0.022412264 | BC6: 0.022412264 | BD6: 0.022412264 | BE6: 0.022412264 | BF6: 0.022412264
A7: division 3 | C7: 0 | D7: 0 | E7: 0 | F7: 0 | G7: 0 | H7: 0 | I7: 0 | J7: 0 | K7: 0 | L7: 0 | M7: 0 | N7: 0 | O7: 0 | P7: 0 | Q7: 0 | R7: 0 | S7: 0 | T7: 0 | U7: 0 | V7: 0 | W7: 0 | X7: 0 | Y7: 0 | Z7: 0 | AA7: 0 | AB7: 1 | AC7: 1.3174377 | AD7: 1.1367371 | AE7: 0.90938967 | AF7: 0.72751174 | AG7: 0.58200939 | AH7: 0.46560751 | AI7: 0.37248601 | AJ7: 0.29798881 | AK7: 0.23839105 | AL7: 0.19071284 | AM7: 0.15257027 | AN7: 0.15257027 | AO7: 0.15257027 | AP7: 0.15257027 | AQ7: 0.15257027 | AR7: 0.15257027 | AS7: 0.15257027 | AT7: 0.15257027 | AU7: 0.15257027 | AV7: 0.15257027 | AW7: 0.15257027 | AX7: 0.15257027 | AY7: 0.15257027 | AZ7: 0.15257027 | BA7: 0.15257027 | BB7: 0.15257027 | BC7: 0.15257027 | BD7: 0.15257027 | BE7: 0.15257027 | BF7: 0.15257027
A8: division 4 | C8: 0 | D8: 0 | E8: 0 | F8: 0 | G8: 0 | H8: 0 | I8: 0 | J8: 0 | K8: 0 | L8: 0 | M8: 0 | N8: 0 | O8: 0 | P8: 0 | Q8: 0 | R8: 0 | S8: 0 | T8: 0 | U8: 0 | V8: 0 | W8: 0 | X8: 0 | Y8: 0 | Z8: 0 | AA8: 0 | AB8: 1 | AC8: 1.4683414 | AD8: 1.2768418 | AE8: 0.95763137 | AF8: 0.71822353 | AG8: 0.53866764 | AH8: 0.40400073 | AI8: 0.30300055 | AJ8: 0.22725041 | AK8: 0.17043781 | AL8: 0.12782836 | AM8: 0.095871268 | AN8: 0.076697014 | AO8: 0.076697014 | AP8: 0.076697014 | AQ8: 0.076697014 | AR8: 0.076697014 | AS8: 0.076697014 | AT8: 0.076697014 | AU8: 0.076697014 | AV8: 0.076697014 | AW8: 0.076697014 | AX8: 0.076697014 | AY8: 0.076697014 | AZ8: 0.076697014 | BA8: 0.076697014 | BB8: 0.076697014 | BC8: 0.076697014 | BD8: 0.076697014 | BE8: 0.076697014 | BF8: 0.076697014
A9: division 5 | C9: 0 | D9: 0 | E9: 0 | F9: 0 | G9: 0 | H9: 0 | I9: 0 | J9: 0 | K9: 0 | L9: 0 | M9: 0 | N9: 0 | O9: 0 | P9: 0 | Q9: 0 | R9: 0 | S9: 0 | T9: 0 | U9: 0 | V9: 0 | W9: 0 | X9: 0 | Y9: 0 | Z9: 0 | AA9: 0 | AB9: 0 | AC9: 1 | AD9: 1.9577247 | AE9: 1.5661798 | AF9: 1.2529438 | AG9: 1.002355 | AH9: 0.80188404 | AI9: 0.64150723 | AJ9: 0.51320578 | AK9: 0.41056463 | AL9: 0.3284517 | AM9: 0.3284517 | AN9: 0.3284517 | AO9: 0.3284517 | AP9: 0.3284517 | AQ9: 0.3284517 | AR9: 0.3284517 | AS9: 0.3284517 | AT9: 0.3284517 | AU9: 0.3284517 | AV9: 0.3284517 | AW9: 0.3284517 | AX9: 0.3284517 | AY9: 0.3284517 | AZ9: 0.3284517 | BA9: 0.3284517 | BB9: 0.3284517 | BC9: 0.3284517 | BD9: 0.3284517 | BE9: 0.3284517 | BF9: 0.3284517
A10: division 6 | C10: 0 | D10: 0 | E10: 0 | F10: 0 | G10: 0 | H10: 0 | I10: 0 | J10: 0 | K10: 0 | L10: 0 | M10: 0 | N10: 0 | O10: 0 | P10: 0 | Q10: 0 | R10: 0 | S10: 0 | T10: 0 | U10: 0 | V10: 0 | W10: 0 | X10: 0 | Y10: 0 | Z10: 0 | AA10: 0 | AB10: 0 | AC10: 1 | AD10: 0.86392038 | AE10: 0.6911363 | AF10: 0.55290904 | AG10: 0.44232723 | AH10: 0.35386179 | AI10: 0.28308943 | AJ10: 0.22647154 | AK10: 0.18117724 | AL10: 0.14494179 | AM10: 0.11595343 | AN10: 0.092762745 | AO10: 0.074210196 | AP10: 0.059368156 | AQ10: 0.047494525 | AR10: 0.03799562 | AS10: 0.030396496 | AT10: 0.024317197 | AU10: 0.019453758 | AV10: 0.015563006 | AW10: 0.012450405 | AX10: 0.0099603238 | AY10: 0.0079682591 | AZ10: 0.0063746073 | BA10: 0.0050996858 | BB10: 0.0040797486 | BC10: 0.0032637989 | BD10: 0.0026110391 | BE10: 0.0020888313 | BF10: 0.001671065
A11: division 7 | C11: 0 | D11: 0 | E11: 0 | F11: 0 | G11: 0 | H11: 0 | I11: 0 | J11: 0 | K11: 0 | L11: 0 | M11: 0 | N11: 0 | O11: 0 | P11: 0 | Q11: 0 | R11: 0 | S11: 0 | T11: 0 | U11: 0 | V11: 0 | W11: 0 | X11: 0 | Y11: 0 | Z11: 0 | AA11: 0 | AB11: 1 | AC11: 1.7977121 | AD11: 1.2583985 | AE11: 0.88087894 | AF11: 0.61661526 | AG11: 0.43163068 | AH11: 0.30214148 | AI11: 0.21149903 | AJ11: 0.14804932 | AK11: 0.10363453 | AL11: 0.072544168 | AM11: 0.050780918 | AN11: 0.035546643 | AO11: 0.02488265 | AP11: 0.017417855 | AQ11: 0.012192498 | AR11: 0.0085347489 | AS11: 0.0059743242 | AT11: 0.0041820269 | AU11: 0.0029274189 | AV11: 0.0020491932 | AW11: 0.0014344352 | AX11: 0.0010041047 | AY11: 0.00070287327 | AZ11: 0.00049201129 | BA11: 0.0003444079 | BB11: 0.00024108553 | BC11: 0.00016875987 | BD11: 0.00011813191 | BE11: 8.2692337e-05 | BF11: 5.7884636e-05
A12: division 8 | C12: 0 | D12: 0 | E12: 0 | F12: 0 | G12: 0 | H12: 0 | I12: 0 | J12: 0 | K12: 0 | L12: 0 | M12: 0 | N12: 0 | O12: 0 | P12: 0 | Q12: 0 | R12: 0 | S12: 0 | T12: 0 | U12: 0 | V12: 0 | W12: 0 | X12: 0 | Y12: 0 | Z12: 0 | AA12: 0 | AB12: 1 | AC12: 1.6147929 | AD12: 1.6022153 | AE12: 1.4419938 | AF12: 1.2977944 | AG12: 1.1680149 | AH12: 1.0512134 | AI12: 0.9460921 | AJ12: 0.85148289 | AK12: 0.7663346 | AL12: 0.68970114 | AM12: 0.62073103 | AN12: 0.55865792 | AO12: 0.50279213 | AP12: 0.45251292 | AQ12: 0.40726163 | AR12: 0.36653546 | AS12: 0.32988192 | AT12: 0.29689373 | AU12: 0.26720435 | AV12: 0.24048392 | AW12: 0.21643553 | AX12: 0.19479197 | AY12: 0.17531278 | AZ12: 0.1577815 | BA12: 0.14200335 | BB12: 0.12780301 | BC12: 0.11502271 | BD12: 0.10352044 | BE12: 0.093168397 | BF12: 0.083851557
A13: division 9 | C13: 0 | D13: 0 | E13: 0 | F13: 0 | G13: 0 | H13: 0 | I13: 0 | J13: 0 | K13: 0 | L13: 0 | M13: 0 | N13: 0 | O13: 0 | P13: 0 | Q13: 0 | R13: 0 | S13: 0 | T13: 0 | U13: 0 | V13: 0 | W13: 0 | X13: 0 | Y13: 0 | Z13: 0 | AA13: 0 | AB13: 1 | AC13: 1.8453548 | AD13: 1.1072129 | AE13: 0.66432773 | AF13: 0.39859664 | AG13: 0.23915798 | AH13: 0.14349479 | AI13: 0.086096874 | AJ13: 0.051658124 | AK13: 0.030994875 | AL13: 0.018596925 | AM13: 0.011158155 | AN13: 0.0066948929 | AO13: 0.0040169357 | AP13: 0.0024101614 | AQ13: 0.0014460969 | AR13: 0.00086765812 | AS13: 0.00052059487 | AT13: 0.00031235692 | AU13: 0.00018741415 | AV13: 0.00011244849 | AW13: 6.7469095e-05 | AX13: 4.0481457e-05 | AY13: 2.4288874e-05 | AZ13: 1.4573325e-05 | BA13: 8.7439948e-06 | BB13: 5.2463969e-06 | BC13: 3.1478381e-06 | BD13: 1.8887029e-06 | BE13: 1.1332217e-06 | BF13: 6.7993303e-07
A15: TB_COEF: constant, coef_gdp, coef_gas$, coef_covid
A16: division 1 | C16: 6.4027272 | D16: -0.40654413 | E16: -0.055296965 | F16: -0.15733188
A17: division 2 | C17: 8.0014128 | D17: -0.5652336 | E17: 0.10057339 | F17: -0.46804
A18: division 3 | C18: 9.3255679 | D18: -1.1359051 | E18: 0.12604253 | F18: -0.55667274
A19: division 4 | C19: 7.8984032 | D19: -0.91441821 | E19: 0.22004322 | F19: -0.54171648
A20: division 5 | C20: 8.2771762 | D20: -0.93472316 | E20: 0.43061969 | F20: -0.36375801
A21: division 6 | C21: 8.0085129 | D21: -1.117727 | E21: 0.31404727 | F21: -0.76837242
A22: division 7 | C22: 12.275457 | D22: -1.8252327 | E22: -0.010353338 | F22: -0.37611963
A23: division 8 | C23: 7.5401025 | D23: -0.70482232 | E23: 0.27390595 | F23: -0.38060221
A24: division 9 | C24: 14.556576 | D24: -2.229671 | E24: 0.36901086 | F24: -0.50091348
A26: TMCOVID (row 27 intercity, row 28 school)
A27: intercity | C27: 0 | D27: 0 | E27: 0 | F27: 0 | G27: 0 | H27: 0 | I27: 0 | J27: 0 | K27: 0 | L27: 0 | M27: 0 | N27: 0 | O27: 0 | P27: 0 | Q27: 0 | R27: 0 | S27: 0 | T27: 0 | U27: 0 | V27: 0 | W27: 0 | X27: 0 | Y27: 0 | Z27: 0 | AA27: 0 | AB27: 1 | AC27: 0.3 | AD27: 0.225 | AE27: 0.16875 | AF27: 0.1265625 | AG27: 0.094921875 | AH27: 0.071191406 | AI27: 0.053393554 | AJ27: 0.040045166 | AK27: 0.030033874 | AL27: 0.022525406 | AM27: 0.016894054 | AN27: 0.012670541 | AO27: 0.009502875 | AP27: 0.00712725 | AQ27: 0.00534525 | AR27: 0.004009125 | AS27: 0.00300675 | AT27: 0.00225525 | AU27: 0.00169125 | AV27: 0.001268625 | AW27: 0.000951375 | AX27: 0.000713625 | AY27: 0.000535125 | AZ27: 0.00040125 | BA27: 0.000301125 | BB27: 0.00022575 | BC27: 0.0001695 | BD27: 0.000127125 | BE27: 9.525e-05 | BF27: 7.125e-05
A28: school | C28: 0 | D28: 0 | E28: 0 | F28: 0 | G28: 0 | H28: 0 | I28: 0 | J28: 0 | K28: 0 | L28: 0 | M28: 0 | N28: 0 | O28: 0 | P28: 0 | Q28: 0 | R28: 0 | S28: 0 | T28: 0 | U28: 0 | V28: 0 | W28: 0 | X28: 0 | Y28: 0 | Z28: 0 | AA28: 0 | AB28: 1 | AC28: 0.26 | AD28: 0.104 | AE28: 0.0416 | AF28: 0.01664 | AG28: 0.006656 | AH28: 0.0026624 | AI28: 0.00106496 | AJ28: 0.000425984 | AK28: 0.000170391 | AL28: 6.8159e-05 | AM28: 2.726295e-05 | AN28: 1.090505e-05 | AO28: 4.3615e-06 | AP28: 1.742e-06 | AQ28: 6.955e-07 | AR28: 2.7885e-07 | AS28: 1.118e-07 | AT28: 4.4655e-08 | AU28: 1.7875e-08 | AV28: 7.15e-09 | AW28: 2.86e-09 | AX28: 1.144e-09 | AY28: 4.576e-10 | AZ28: 1.8265e-10 | BA28: 7.345e-11 | BB28: 2.925e-11 | BC28: 1.17e-11 | BD28: 4.6865e-12 | BE28: 1.872e-12 | BF28: 7.475e-13
A30: TBPMTHIST transit passenger-miles (millions) by division, 2023 (last history year), used as regional weights
A31: division 1 | B31: 596.36686
A32: division 2 | B32: 4165.8427
A33: division 3 | B33: 1393.9205
A34: division 4 | B34: 419.70064
A35: division 5 | B35: 2200.8583
A36: division 6 | B36: 158.75235
A37: division 7 | B37: 1026.3166
A38: division 8 | B38: 851.67792
A39: division 9 | B39: 3672.3086
A41: TMODINIT 2019 passenger-miles (millions), pre-COVID weights
A42: intercity 2019 | B42: 95540.938
A43: school 2019 | B43: 86255.422
A44: transit 2019 | B44: 20633.235

Sheet NEMS rail covid
A1: NEMS AEO2026 Public Release, input/tdm/trnldvx.xlsx (sheet trnldv): TRCOVID, CRCOVID, TR_COEF, CR_COEF, TRRPMHIST, CRRPMHIST. Read 2026-10-14.
A3: year | C3: 1995 | D3: 1996 | E3: 1997 | F3: 1998 | G3: 1999 | H3: 2000 | I3: 2001 | J3: 2002 | K3: 2003 | L3: 2004 | M3: 2005 | N3: 2006 | O3: 2007 | P3: 2008 | Q3: 2009 | R3: 2010 | S3: 2011 | T3: 2012 | U3: 2013 | V3: 2014 | W3: 2015 | X3: 2016 | Y3: 2017 | Z3: 2018 | AA3: 2019 | AB3: 2020 | AC3: 2021 | AD3: 2022 | AE3: 2023 | AF3: 2024 | AG3: 2025 | AH3: 2026 | AI3: 2027 | AJ3: 2028 | AK3: 2029 | AL3: 2030 | AM3: 2031 | AN3: 2032 | AO3: 2033 | AP3: 2034 | AQ3: 2035 | AR3: 2036 | AS3: 2037 | AT3: 2038 | AU3: 2039 | AV3: 2040 | AW3: 2041 | AX3: 2042 | AY3: 2043 | AZ3: 2044 | BA3: 2045 | BB3: 2046 | BC3: 2047 | BD3: 2048 | BE3: 2049 | BF3: 2050
A4: TRCOVID (transit rail) by census division 1-9
A5: division 1 | C5: 0 | D5: 0 | E5: 0 | F5: 0 | G5: 0 | H5: 0 | I5: 0 | J5: 0 | K5: 0 | L5: 0 | M5: 0 | N5: 0 | O5: 0 | P5: 0 | Q5: 0 | R5: 0 | S5: 0 | T5: 0 | U5: 0 | V5: 0 | W5: 0 | X5: 0 | Y5: 0 | Z5: 0 | AA5: 0 | AB5: 1 | AC5: 3.0269114 | AD5: 2.1364078 | AE5: 1.5078863 | AF5: 1.064273 | AG5: 0.75116873 | AH5: 0.5301783 | AI5: 0.37420225 | AJ5: 0.26411365 | AK5: 0.18641261 | AL5: 0.13157087 | AM5: 0.092863315 | AN5: 0.06554335 | AO5: 0.046260794 | AP5: 0.032651078 | AQ5: 0.023045279 | AR5: 0.016265463 | AS5: 0.011480237 | AT5: 0.0081028037 | AU5: 0.0057189956 | AV5: 0.0040364931 | AW5: 0.0028489752 | AX5: 0.0020108196 | AY5: 0.0014192456 | AZ5: 0.00100171 | BA5: 0.00070701146 | BB5: 0.0004990119 | BC5: 0.00035220486 | BD5: 0.00024858779 | BE5: 0.00017545439 | BF5: 0.00012383651
A6: division 2 | C6: 0 | D6: 0 | E6: 0 | F6: 0 | G6: 0 | H6: 0 | I6: 0 | J6: 0 | K6: 0 | L6: 0 | M6: 0 | N6: 0 | O6: 0 | P6: 0 | Q6: 0 | R6: 0 | S6: 0 | T6: 0 | U6: 0 | V6: 0 | W6: 0 | X6: 0 | Y6: 0 | Z6: 0 | AA6: 0 | AB6: 1 | AC6: 0.88670917 | AD6: 0.65633699 | AE6: 0.48581683 | AF6: 0.3595988 | AG6: 0.26617295 | AH6: 0.19701968 | AI6: 0.14583282 | AJ6: 0.10794461 | AK6: 0.079899974 | AL6: 0.059141498 | AM6: 0.043776194 | AN6: 0.032402885 | AO6: 0.023984427 | AP6: 0.017753134 | AQ6: 0.013140767 | AR6: 0.0097267196 | AS6: 0.0071996615 | AT6: 0.0053291477 | AU6: 0.0039446042 | AV6: 0.0029197732 | AW6: 0.0021611992 | AX6: 0.0015997071 | AY6: 0.0011840939 | AZ6: 0.00087645946 | BA6: 0.00064875021 | BB6: 0.00048020115 | BC6: 0.00035544211 | BD6: 0.00026309619 | BE6: 0.00019474227 | BF6: 0.0001441471
A7: division 3 | C7: 0 | D7: 0 | E7: 0 | F7: 0 | G7: 0 | H7: 0 | I7: 0 | J7: 0 | K7: 0 | L7: 0 | M7: 0 | N7: 0 | O7: 0 | P7: 0 | Q7: 0 | R7: 0 | S7: 0 | T7: 0 | U7: 0 | V7: 0 | W7: 0 | X7: 0 | Y7: 0 | Z7: 0 | AA7: 0 | AB7: 1 | AC7: 0.99406759 | AD7: 0.88133228 | AE7: 0.70506582 | AF7: 0.56405266 | AG7: 0.45124213 | AH7: 0.3609937 | AI7: 0.28879496 | AJ7: 0.23103597 | AK7: 0.18482878 | AL7: 0.14786302 | AM7: 0.11829042 | AN7: 0.094632333 | AO7: 0.075705866 | AP7: 0.060564693 | AQ7: 0.048451754 | AR7: 0.038761404 | AS7: 0.031009123 | AT7: 0.024807298 | AU7: 0.019845839 | AV7: 0.015876671 | AW7: 0.012701337 | AX7: 0.010161069 | AY7: 0.0081288555 | AZ7: 0.0065030844 | BA7: 0.0052024675 | BB7: 0.004161974 | BC7: 0.0033295792 | BD7: 0.0026636634 | BE7: 0.0021309307 | BF7: 0.0017047446
A8: division 4 | C8: 0 | D8: 0 | E8: 0 | F8: 0 | G8: 0 | H8: 0 | I8: 0 | J8: 0 | K8: 0 | L8: 0 | M8: 0 | N8: 0 | O8: 0 | P8: 0 | Q8: 0 | R8: 0 | S8: 0 | T8: 0 | U8: 0 | V8: 0 | W8: 0 | X8: 0 | Y8: 0 | Z8: 0 | AA8: 0 | AB8: 1 | AC8: 1.5066569 | AD8: 1.3377048 | AE8: 1.1876985 | AF8: 1.0545135 | AG8: 0.9362634 | AH8: 0.83127356 | AI8: 0.73805698 | AJ8: 0.65529343 | AK8: 0.58181075 | AL8: 0.51656819 | AM8: 0.45864175 | AN8: 0.407211 | AO8: 0.36154756 | AP8: 0.32100467 | AQ8: 0.28500815 | AR8: 0.25304817 | AS8: 0.22467209 | AT8: 0.19947802 | AU8: 0.17710914 | AV8: 0.15724864 | AW8: 0.13961524 | AX8: 0.12395919 | AY8: 0.11005877 | AZ8: 0.097717102 | BA8: 0.086759393 | BB8: 0.077030448 | BC8: 0.068392479 | BD8: 0.060723147 | BE8: 0.053913831 | BF8: 0.047868092
A9: division 5 | C9: 0 | D9: 0 | E9: 0 | F9: 0 | G9: 0 | H9: 0 | I9: 0 | J9: 0 | K9: 0 | L9: 0 | M9: 0 | N9: 0 | O9: 0 | P9: 0 | Q9: 0 | R9: 0 | S9: 0 | T9: 0 | U9: 0 | V9: 0 | W9: 0 | X9: 0 | Y9: 0 | Z9: 0 | AA9: 0 | AB9: 1 | AC9: 3.6398355 | AD9: 3.0440167 | AE9: 2.5457298 | AF9: 2.1290094 | AG9: 1.7805036 | AH9: 1.4890461 | AI9: 1.2452983 | AJ9: 1.0414506 | AK9: 0.87097151 | AL9: 0.7283988 | AM9: 0.60916438 | AN9: 0.50944789 | AO9: 0.42605439 | AP9: 0.35631189 | AQ9: 0.29798582 | AR9: 0.24920736 | AS9: 0.20841364 | AT9: 0.1742976 | AU9: 0.14576615 | AV9: 0.12190512 | AW9: 0.10195 | AX9: 0.08526141 | AY9: 0.071304639 | AZ9: 0.059632505 | BA9: 0.049871029 | BB9: 0.041707447 | BC9: 0.034880193 | BD9: 0.029170519 | BE9: 0.024395483 | BF9: 0.020402092
A10: division 6 | C10: 0 | D10: 0 | E10: 0 | F10: 0 | G10: 0 | H10: 0 | I10: 0 | J10: 0 | K10: 0 | L10: 0 | M10: 0 | N10: 0 | O10: 0 | P10: 0 | Q10: 0 | R10: 0 | S10: 0 | T10: 0 | U10: 0 | V10: 0 | W10: 0 | X10: 0 | Y10: 0 | Z10: 0 | AA10: 0 | AB10: 0 | AC10: 0 | AD10: 0 | AE10: 0 | AF10: 0 | AG10: 0 | AH10: 0 | AI10: 0 | AJ10: 0 | AK10: 0 | AL10: 0 | AM10: 0 | AN10: 0 | AO10: 0 | AP10: 0 | AQ10: 0 | AR10: 0 | AS10: 0 | AT10: 0 | AU10: 0 | AV10: 0 | AW10: 0 | AX10: 0 | AY10: 0 | AZ10: 0 | BA10: 0 | BB10: 0 | BC10: 0 | BD10: 0 | BE10: 0 | BF10: 0
A11: division 7 | C11: 0 | D11: 0 | E11: 0 | F11: 0 | G11: 0 | H11: 0 | I11: 0 | J11: 0 | K11: 0 | L11: 0 | M11: 0 | N11: 0 | O11: 0 | P11: 0 | Q11: 0 | R11: 0 | S11: 0 | T11: 0 | U11: 0 | V11: 0 | W11: 0 | X11: 0 | Y11: 0 | Z11: 0 | AA11: 0 | AB11: 1 | AC11: 1.9645841 | AD11: 1.5716673 | AE11: 1.2573338 | AF11: 1.005867 | AG11: 0.80469364 | AH11: 0.64375491 | AI11: 0.51500393 | AJ11: 0.41200314 | AK11: 0.32960251 | AL11: 0.26368201 | AM11: 0.21094561 | AN11: 0.16875649 | AO11: 0.13500519 | AP11: 0.10800415 | AQ11: 0.086403321 | AR11: 0.069122657 | AS11: 0.055298126 | AT11: 0.0442385 | AU11: 0.0353908 | AV11: 0.02831264 | AW11: 0.022650112 | AX11: 0.01812009 | AY11: 0.014496072 | AZ11: 0.011596857 | BA11: 0.009277486 | BB11: 0.0074219888 | BC11: 0.005937591 | BD11: 0.0047500728 | BE11: 0.0038000583 | BF11: 0.0030400466
A12: division 8 | C12: 0 | D12: 0 | E12: 0 | F12: 0 | G12: 0 | H12: 0 | I12: 0 | J12: 0 | K12: 0 | L12: 0 | M12: 0 | N12: 0 | O12: 0 | P12: 0 | Q12: 0 | R12: 0 | S12: 0 | T12: 0 | U12: 0 | V12: 0 | W12: 0 | X12: 0 | Y12: 0 | Z12: 0 | AA12: 0 | AB12: 1 | AC12: 1.3855395 | AD12: 1.1084316 | AE12: 1.0973473 | AF12: 0.87787781 | AG12: 0.70230225 | AH12: 0.5618418 | AI12: 0.44947344 | AJ12: 0.35957875 | AK12: 0.287663 | AL12: 0.2301304 | AM12: 0.18410432 | AN12: 0.14728346 | AO12: 0.11782676 | AP12: 0.094261412 | AQ12: 0.07540913 | AR12: 0.060327304 | AS12: 0.048261843 | AT12: 0.038609474 | AU12: 0.030887579 | AV12: 0.024710064 | AW12: 0.019768051 | AX12: 0.015814441 | AY12: 0.012651553 | AZ12: 0.010121242 | BA12: 0.0080969936 | BB12: 0.0064775949 | BC12: 0.0051820759 | BD12: 0.0041456607 | BE12: 0.0033165286 | BF12: 0.0026532229
A13: division 9 | C13: 0 | D13: 0 | E13: 0 | F13: 0 | G13: 0 | H13: 0 | I13: 0 | J13: 0 | K13: 0 | L13: 0 | M13: 0 | N13: 0 | O13: 0 | P13: 0 | Q13: 0 | R13: 0 | S13: 0 | T13: 0 | U13: 0 | V13: 0 | W13: 0 | X13: 0 | Y13: 0 | Z13: 0 | AA13: 0 | AB13: 1 | AC13: 2.5148347 | AD13: 1.6346426 | AE13: 1.0625177 | AF13: 0.69063649 | AG13: 0.44891372 | AH13: 0.29179392 | AI13: 0.18966605 | AJ13: 0.12328293 | AK13: 0.080133904 | AL13: 0.052087038 | AM13: 0.033856575 | AN13: 0.022006773 | AO13: 0.014304403 | AP13: 0.0092978618 | AQ13: 0.0060436102 | AR13: 0.0039283466 | AS13: 0.0025534253 | AT13: 0.0016597264 | AU13: 0.0010788222 | AV13: 0.00070123442 | AW13: 0.00045580237 | AX13: 0.00029627154 | AY13: 0.0001925765 | AZ13: 0.00012517473 | BA13: 8.1363572e-05 | BB13: 5.2886322e-05 | BC13: 3.4376109e-05 | BD13: 2.2344471e-05 | BE13: 1.4523906e-05 | BF13: 9.440539e-06
A15: CRCOVID (commuter rail) by census division 1-9
A16: division 1 | C16: 0 | D16: 0 | E16: 0 | F16: 0 | G16: 0 | H16: 0 | I16: 0 | J16: 0 | K16: 0 | L16: 0 | M16: 0 | N16: 0 | O16: 0 | P16: 0 | Q16: 0 | R16: 0 | S16: 0 | T16: 0 | U16: 0 | V16: 0 | W16: 0 | X16: 0 | Y16: 0 | Z16: 0 | AA16: 0 | AB16: 1 | AC16: 4.6405435 | AD16: 2.7843261 | AE16: 1.9490283 | AF16: 1.169417 | AG16: 0.70165018 | AH16: 0.42099011 | AI16: 0.25259406 | AJ16: 0.15155644 | AK16: 0.090933863 | AL16: 0.054560318 | AM16: 0.032736191 | AN16: 0.019641714 | AO16: 0.011785029 | AP16: 0.0070710172 | AQ16: 0.0042426103 | AR16: 0.0025455662 | AS16: 0.0015273397 | AT16: 0.00091640383 | AU16: 0.0005498423 | AV16: 0.00032990538 | AW16: 0.00019794323 | AX16: 0.00011876594 | AY16: 7.1259562e-05 | AZ16: 4.2755737e-05 | BA16: 2.5653442e-05 | BB16: 1.5392065e-05 | BC16: 9.2352392e-06 | BD16: 5.5411435e-06 | BE16: 3.3246861e-06 | BF16: 1.9948117e-06
A17: division 2 | C17: 0 | D17: 0 | E17: 0 | F17: 0 | G17: 0 | H17: 0 | I17: 0 | J17: 0 | K17: 0 | L17: 0 | M17: 0 | N17: 0 | O17: 0 | P17: 0 | Q17: 0 | R17: 0 | S17: 0 | T17: 0 | U17: 0 | V17: 0 | W17: 0 | X17: 0 | Y17: 0 | Z17: 0 | AA17: 0 | AB17: 1 | AC17: 1.2381507 | AD17: 0.86670551 | AE17: 0.60669386 | AF17: 0.4246857 | AG17: 0.29727999 | AH17: 0.20809599 | AI17: 0.1456672 | AJ17: 0.10196704 | AK17: 0.071376926 | AL17: 0.049963848 | AM17: 0.034974694 | AN17: 0.024482285 | AO17: 0.0171376 | AP17: 0.01199632 | AQ17: 0.0083974239 | AR17: 0.0058781967 | AS17: 0.0041147377 | AT17: 0.0028803164 | AU17: 0.0020162215 | AV17: 0.001411355 | AW17: 0.00098794853 | AX17: 0.00069156397 | AY17: 0.00048409478 | AZ17: 0.00033886634 | BA17: 0.00023720644 | BB17: 0.00016604451 | BC17: 0.00011623116 | BD17: 8.1361809e-05 | BE17: 5.6953267e-05 | BF17: 3.9867287e-05
A18: division 3 | C18: 0 | D18: 0 | E18: 0 | F18: 0 | G18: 0 | H18: 0 | I18: 0 | J18: 0 | K18: 0 | L18: 0 | M18: 0 | N18: 0 | O18: 0 | P18: 0 | Q18: 0 | R18: 0 | S18: 0 | T18: 0 | U18: 0 | V18: 0 | W18: 0 | X18: 0 | Y18: 0 | Z18: 0 | AA18: 0 | AB18: 1 | AC18: 1.0611965 | AD18: 0.86099479 | AE18: 0.69856242 | AF18: 0.56677399 | AG18: 0.45984833 | AH18: 0.37309489 | AI18: 0.30270807 | AJ18: 0.24560019 | AK18: 0.19926609 | AL18: 0.16167322 | AM18: 0.1311725 | AN18: 0.10642594 | AO18: 0.086347977 | AP18: 0.07005786 | AQ18: 0.05684098 | AR18: 0.046117553 | AS18: 0.037417171 | AT18: 0.030358174 | AU18: 0.024630903 | AV18: 0.01998412 | AW18: 0.016213984 | AX18: 0.013155108 | AY18: 0.01067331 | AZ18: 0.0086597193 | BA18: 0.0070260059 | BB18: 0.0057005033 | BC18: 0.0046250656 | BD18: 0.0037525164 | BE18: 0.0030445793 | BF18: 0.0024701992
A19: division 4 | C19: 0 | D19: 0 | E19: 0 | F19: 0 | G19: 0 | H19: 0 | I19: 0 | J19: 0 | K19: 0 | L19: 0 | M19: 0 | N19: 0 | O19: 0 | P19: 0 | Q19: 0 | R19: 0 | S19: 0 | T19: 0 | U19: 0 | V19: 0 | W19: 0 | X19: 0 | Y19: 0 | Z19: 0 | AA19: 0 | AB19: 1 | AC19: 1.1807782 | AD19: 1.1404374 | AE19: 0.91234989 | AF19: 0.72987991 | AG19: 0.58390393 | AH19: 0.46712315 | AI19: 0.37369852 | AJ19: 0.29895881 | AK19: 0.23916705 | AL19: 0.19133364 | AM19: 0.15306691 | AN19: 0.12245353 | AO19: 0.097962824 | AP19: 0.078370259 | AQ19: 0.062696207 | AR19: 0.050156966 | AS19: 0.040125573 | AT19: 0.032100458 | AU19: 0.025680366 | AV19: 0.020544293 | AW19: 0.016435435 | AX19: 0.013148348 | AY19: 0.010518678 | AZ19: 0.0084149425 | BA19: 0.006731954 | BB19: 0.0053855632 | BC19: 0.0043084506 | BD19: 0.0034467604 | BE19: 0.0027574084 | BF19: 0.0022059267
A20: division 5 | C20: 0 | D20: 0 | E20: 0 | F20: 0 | G20: 0 | H20: 0 | I20: 0 | J20: 0 | K20: 0 | L20: 0 | M20: 0 | N20: 0 | O20: 0 | P20: 0 | Q20: 0 | R20: 0 | S20: 0 | T20: 0 | U20: 0 | V20: 0 | W20: 0 | X20: 0 | Y20: 0 | Z20: 0 | AA20: 0 | AB20: 0 | AC20: 1 | AD20: 0.75161287 | AE20: 0.56492191 | AF20: 0.42460258 | AG20: 0.31913677 | AH20: 0.2398673 | AI20: 0.18028735 | AJ20: 0.13550629 | AK20: 0.10184828 | AL20: 0.076550475 | AM20: 0.057536322 | AN20: 0.043245041 | AO20: 0.032503529 | AP20: 0.024430071 | AQ20: 0.018361956 | AR20: 0.013801082 | AS20: 0.010373071 | AT20: 0.0077965338 | AU20: 0.0058599752 | AV20: 0.0044044328 | AW20: 0.0033104284 | AX20: 0.0024881606 | AY20: 0.0018701335 | AZ20: 0.0014056164 | BA20: 0.0010564794 | BB20: 0.00079406352 | BC20: 0.00059682837 | BD20: 0.00044858388 | BE20: 0.00033716142 | BF20: 0.00025341486
A21: division 6 | C21: 0 | D21: 0 | E21: 0 | F21: 0 | G21: 0 | H21: 0 | I21: 0 | J21: 0 | K21: 0 | L21: 0 | M21: 0 | N21: 0 | O21: 0 | P21: 0 | Q21: 0 | R21: 0 | S21: 0 | T21: 0 | U21: 0 | V21: 0 | W21: 0 | X21: 0 | Y21: 0 | Z21: 0 | AA21: 0 | AB21: 0 | AC21: 1 | AD21: 0.78949062 | AE21: 0.62329544 | AF21: 0.4920859 | AG21: 0.38849721 | AH21: 0.3067149 | AI21: 0.24214854 | AJ21: 0.191174 | AK21: 0.15093008 | AL21: 0.11915788 | AM21: 0.09407403 | AN21: 0.074270564 | AO21: 0.058635914 | AP21: 0.046292504 | AQ21: 0.036547498 | AR21: 0.028853907 | AS21: 0.022779889 | AT21: 0.017984508 | AU21: 0.014198601 | AV21: 0.011209662 | AW21: 0.008849923 | AX21: 0.0069869312 | AY21: 0.0055161167 | AZ21: 0.0043549224 | BA21: 0.0034381704 | BB21: 0.0027144033 | BC21: 0.0021429959 | BD21: 0.0016918752 | BE21: 0.0013357196 | BF21: 0.0010545381
A22: division 7 | C22: 0 | D22: 0 | E22: 0 | F22: 0 | G22: 0 | H22: 0 | I22: 0 | J22: 0 | K22: 0 | L22: 0 | M22: 0 | N22: 0 | O22: 0 | P22: 0 | Q22: 0 | R22: 0 | S22: 0 | T22: 0 | U22: 0 | V22: 0 | W22: 0 | X22: 0 | Y22: 0 | Z22: 0 | AA22: 0 | AB22: 1 | AC22: 1.8448783 | AD22: 1.2343212 | AE22: 0.82582621 | AF22: 0.55252144 | AG22: 0.36966608 | AH22: 0.24732617 | AI22: 0.1654743 | AJ22: 0.11071106 | AK22: 0.07407156 | AL22: 0.049557794 | AM22: 0.033156787 | AN22: 0.022183645 | AO22: 0.014842033 | AP22: 0.0099301053 | AQ22: 0.0066437659 | AR22: 0.004445031 | AS22: 0.002973961 | AT22: 0.0019897373 | AU22: 0.0013312395 | AV22: 0.00089066971 | AW22: 0.00059590517 | AX22: 0.0003986921 | AY22: 0.00026674611 | AZ22: 0.00017846727 | BA22: 0.00011940405 | BB22: 7.9887626e-05 | BC22: 5.3449049e-05 | BD22: 3.5760243e-05 | BE22: 2.3925495e-05 | BF22: 1.6007422e-05
A23: division 8 | C23: 0 | D23: 0 | E23: 0 | F23: 0 | G23: 0 | H23: 0 | I23: 0 | J23: 0 | K23: 0 | L23: 0 | M23: 0 | N23: 0 | O23: 0 | P23: 0 | Q23: 0 | R23: 0 | S23: 0 | T23: 0 | U23: 0 | V23: 0 | W23: 0 | X23: 0 | Y23: 0 | Z23: 0 | AA23: 0 | AB23: 1 | AC23: 0.98659121 | AD23: 0.5980352 | AE23: 0.36250688 | AF23: 0.2197383 | AG23: 0.13319725 | AH23: 0.080739259 | AI23: 0.04894116 | AJ23: 0.029666326 | AK23: 0.017982633 | AL23: 0.010900408 | AM23: 0.0066074255 | AN23: 0.0040051776 | AO23: 0.0024277909 | AP23: 0.0014716373 | AQ23: 0.00089205225 | AR23: 0.00054072916 | AS23: 0.00032777007 | AT23: 0.00019868213 | AU23: 0.00012043378 | AV23: 7.3002513e-05 | AW23: 4.425143e-05 | AX23: 2.6823585e-05 | AY23: 1.6259468e-05 | AZ23: 9.8558894e-06 | BA23: 5.9742766e-06 | BB23: 3.6213861e-06 | BC23: 2.1951507e-06 | BD23: 1.3306194e-06 | BE23: 8.0657237e-07 | BF23: 4.8891442e-07
A24: division 9 | C24: 0 | D24: 0 | E24: 0 | F24: 0 | G24: 0 | H24: 0 | I24: 0 | J24: 0 | K24: 0 | L24: 0 | M24: 0 | N24: 0 | O24: 0 | P24: 0 | Q24: 0 | R24: 0 | S24: 0 | T24: 0 | U24: 0 | V24: 0 | W24: 0 | X24: 0 | Y24: 0 | Z24: 0 | AA24: 0 | AB24: 0 | AC24: 1 | AD24: 0.6802109 | AE24: 0.46268686 | AF24: 0.31472465 | AG24: 0.21407913 | AH24: 0.14561896 | AI24: 0.099051602 | AJ24: 0.067375979 | AK24: 0.045829875 | AL24: 0.03117398 | AM24: 0.021204881 | AN24: 0.014423791 | AO24: 0.0098112199 | AP24: 0.0066736987 | AQ24: 0.0045395225 | AR24: 0.0030878327 | AS24: 0.0021003774 | AT24: 0.0014286996 | AU24: 0.00097181705 | AV24: 0.00066104055 | AW24: 0.00044964698 | AX24: 0.00030585478 | AY24: 0.00020804575 | AZ24: 0.00014151499 | BA24: 9.6260036e-05 | BB24: 6.5477125e-05 | BC24: 4.4538254e-05 | BD24: 3.0295406e-05 | BE24: 2.0607265e-05 | BF24: 1.4017286e-05
A26: coef_covid: TR_COEF (col B) and CR_COEF (col C) by division; NEMS tran.f: RPM per capita = exp(const + coef_gdp ln(GDP/cap) + coef_gas$ ln(fuel price) + coef_covid x COVID)
A27: division 1 | B27: -0.47309768 | C27: -0.30454805
A28: division 2 | B28: -0.72554702 | C28: -0.77770615
A29: division 3 | B29: -1.0186085 | C29: -1.3926806
A30: division 4 | B30: -0.64946015 | C30: -1.8867331
A31: division 5 | B31: -0.42539261 | C31: -1.6374921
A32: division 6 | B32: 0 | C32: -2.1055466
A33: division 7 | B33: -0.3934408 | C33: -0.44329701
A34: division 8 | B34: -0.73483982 | C34: -0.69365108
A35: division 9 | B35: -0.60770397 | C35: -2.0078063
A37: 2019 passenger-miles (millions), pre-COVID weights: TRRPMHIST (col B) and CRRPMHIST (col C) by division
A38: division 1 | B38: 709.7654 | C38: 713.8704
A39: division 2 | B39: 11571.46 | C39: 8574.089
A40: division 3 | B40: 1423.633 | C40: 1473.524
A41: division 4 | B41: 189.568 | C41: 18.9656
A42: division 5 | B42: 2022.191 | C42: 550.1987
A43: division 6 | B43: 0 | C43: 4.544152
A44: division 7 | B44: 279.3334 | C44: 41.9403
A45: division 8 | B45: 370.284 | C45: 290.4281
A46: division 9 | B46: 3266.956 | C46: 1063.919
A47: totals | B47: =SUM(B38:B46) -> 19833.191 | C47: =SUM(C38:C46) -> 12731.479

Sheet rail loading
A1: Passenger-rail loading path: NEMS projects transit- and commuter-rail travel with COVID-recovery terms; NTD shows passengers per car-mile at 19.1 in 2024 against 27.6 in 2019 with car-miles back to 97% of 2019. The recovery is treated as riders per car, as for buses, so it lands in loading, not vehicles.
A3: year | C3: ='NEMS rail covid'!C3 -> 1995 | D3: ='NEMS rail covid'!D3 -> 1996 | E3: ='NEMS rail covid'!E3 -> 1997 | F3: ='NEMS rail covid'!F3 -> 1998 | G3: ='NEMS rail covid'!G3 -> 1999 | H3: ='NEMS rail covid'!H3 -> 2000 | I3: ='NEMS rail covid'!I3 -> 2001 | J3: ='NEMS rail covid'!J3 -> 2002 | ... BF3: ='NEMS rail covid'!BF3 -> 2050
A4: R transit rail = sum_r w_r exp(coef_covid_r x TRCOVID_r) / sum_r w_r | C4: =SUMPRODUCT('NEMS rail covid'!$B$38:$B$46,EXP('NEMS rail covid'!$B$27:$B$35*'NEMS rail covid'!C5:C13))/'NEMS rail covid'!$B$47 -> 1 | D4: =SUMPRODUCT('NEMS rail covid'!$B$38:$B$46,EXP('NEMS rail covid'!$B$27:$B$35*'NEMS rail covid'!D5:D13))/'NEMS rail covid'!$B$47 -> 1 | E4: =SUMPRODUCT('NEMS rail covid'!$B$38:$B$46,EXP('NEMS rail covid'!$B$27:$B$35*'NEMS rail covid'!E5:E13))/'NEMS rail covid'!$B$47 -> 1 | F4: =SUMPRODUCT('NEMS rail covid'!$B$38:$B$46,EXP('NEMS rail covid'!$B$27:$B$35*'NEMS rail covid'!F5:F13))/'NEMS rail covid'!$B$47 -> 1 | G4: =SUMPRODUCT('NEMS rail covid'!$B$38:$B$46,EXP('NEMS rail covid'!$B$27:$B$35*'NEMS rail covid'!G5:G13))/'NEMS rail covid'!$B$47 -> 1 | H4: =SUMPRODUCT('NEMS rail covid'!$B$38:$B$46,EXP('NEMS rail covid'!$B$27:$B$35*'NEMS rail covid'!H5:H13))/'NEMS rail covid'!$B$47 -> 1 | I4: =SUMPRODUCT('NEMS rail covid'!$B$38:$B$46,EXP('NEMS rail covid'!$B$27:$B$35*'NEMS rail covid'!I5:I13))/'NEMS rail covid'!$B$47 -> 1 | J4: =SUMPRODUCT('NEMS rail covid'!$B$38:$B$46,EXP('NEMS rail covid'!$B$27:$B$35*'NEMS rail covid'!J5:J13))/'NEMS rail covid'!$B$47 -> 1 | ... BF4: =SUMPRODUCT('NEMS rail covid'!$B$38:$B$46,EXP('NEMS rail covid'!$B$27:$B$35*'NEMS rail covid'!BF5:BF13))/'NEMS rail covid'!$B$47 -> 0.99858456
A5: R commuter rail = sum_r w_r exp(coef_covid_r x CRCOVID_r) / sum_r w_r | C5: =SUMPRODUCT('NEMS rail covid'!$C$38:$C$46,EXP('NEMS rail covid'!$C$27:$C$35*'NEMS rail covid'!C16:C24))/'NEMS rail covid'!$C$47 -> 1 | D5: =SUMPRODUCT('NEMS rail covid'!$C$38:$C$46,EXP('NEMS rail covid'!$C$27:$C$35*'NEMS rail covid'!D16:D24))/'NEMS rail covid'!$C$47 -> 1 | E5: =SUMPRODUCT('NEMS rail covid'!$C$38:$C$46,EXP('NEMS rail covid'!$C$27:$C$35*'NEMS rail covid'!E16:E24))/'NEMS rail covid'!$C$47 -> 1 | F5: =SUMPRODUCT('NEMS rail covid'!$C$38:$C$46,EXP('NEMS rail covid'!$C$27:$C$35*'NEMS rail covid'!F16:F24))/'NEMS rail covid'!$C$47 -> 1 | G5: =SUMPRODUCT('NEMS rail covid'!$C$38:$C$46,EXP('NEMS rail covid'!$C$27:$C$35*'NEMS rail covid'!G16:G24))/'NEMS rail covid'!$C$47 -> 1 | H5: =SUMPRODUCT('NEMS rail covid'!$C$38:$C$46,EXP('NEMS rail covid'!$C$27:$C$35*'NEMS rail covid'!H16:H24))/'NEMS rail covid'!$C$47 -> 1 | I5: =SUMPRODUCT('NEMS rail covid'!$C$38:$C$46,EXP('NEMS rail covid'!$C$27:$C$35*'NEMS rail covid'!I16:I24))/'NEMS rail covid'!$C$47 -> 1 | J5: =SUMPRODUCT('NEMS rail covid'!$C$38:$C$46,EXP('NEMS rail covid'!$C$27:$C$35*'NEMS rail covid'!J16:J24))/'NEMS rail covid'!$C$47 -> 1 | ... BF5: =SUMPRODUCT('NEMS rail covid'!$C$38:$C$46,EXP('NEMS rail covid'!$C$27:$C$35*'NEMS rail covid'!BF16:BF24))/'NEMS rail covid'!$C$47 -> 0.99955432
A6: R weighted by 2019 passenger-miles (transit, commuter) | C6: =('NEMS rail covid'!$B$47*C4+'NEMS rail covid'!$C$47*C5)/('NEMS rail covid'!$B$47+'NEMS rail covid'!$C$47) -> 1 | D6: =('NEMS rail covid'!$B$47*D4+'NEMS rail covid'!$C$47*D5)/('NEMS rail covid'!$B$47+'NEMS rail covid'!$C$47) -> 1 | E6: =('NEMS rail covid'!$B$47*E4+'NEMS rail covid'!$C$47*E5)/('NEMS rail covid'!$B$47+'NEMS rail covid'!$C$47) -> 1 | F6: =('NEMS rail covid'!$B$47*F4+'NEMS rail covid'!$C$47*F5)/('NEMS rail covid'!$B$47+'NEMS rail covid'!$C$47) -> 1 | G6: =('NEMS rail covid'!$B$47*G4+'NEMS rail covid'!$C$47*G5)/('NEMS rail covid'!$B$47+'NEMS rail covid'!$C$47) -> 1 | H6: =('NEMS rail covid'!$B$47*H4+'NEMS rail covid'!$C$47*H5)/('NEMS rail covid'!$B$47+'NEMS rail covid'!$C$47) -> 1 | I6: =('NEMS rail covid'!$B$47*I4+'NEMS rail covid'!$C$47*I5)/('NEMS rail covid'!$B$47+'NEMS rail covid'!$C$47) -> 1 | J6: =('NEMS rail covid'!$B$47*J4+'NEMS rail covid'!$C$47*J5)/('NEMS rail covid'!$B$47+'NEMS rail covid'!$C$47) -> 1 | ... BF6: =('NEMS rail covid'!$B$47*BF4+'NEMS rail covid'!$C$47*BF5)/('NEMS rail covid'!$B$47+'NEMS rail covid'!$C$47) -> 0.99896369
A7: Loading multiplier = R(y) / R(2024) | C7: =C6/$AF$6 -> 1.4770342 | D7: =D6/$AF$6 -> 1.4770342 | E7: =E6/$AF$6 -> 1.4770342 | F7: =F6/$AF$6 -> 1.4770342 | G7: =G6/$AF$6 -> 1.4770342 | H7: =H6/$AF$6 -> 1.4770342 | I7: =I6/$AF$6 -> 1.4770342 | J7: =J6/$AF$6 -> 1.4770342 | ... BF7: =BF6/$AF$6 -> 1.4755036
A8: AVLo rail (passengers per car) = SYAVLo x multiplier, from 2025 | C8: =IF(C3<=2024,'SYAVLo-passengers'!$B$5,'SYAVLo-passengers'!$B$5*C7) -> 15.34784 | D8: =IF(D3<=2024,'SYAVLo-passengers'!$B$5,'SYAVLo-passengers'!$B$5*D7) -> 15.34784 | E8: =IF(E3<=2024,'SYAVLo-passengers'!$B$5,'SYAVLo-passengers'!$B$5*E7) -> 15.34784 | F8: =IF(F3<=2024,'SYAVLo-passengers'!$B$5,'SYAVLo-passengers'!$B$5*F7) -> 15.34784 | G8: =IF(G3<=2024,'SYAVLo-passengers'!$B$5,'SYAVLo-passengers'!$B$5*G7) -> 15.34784 | H8: =IF(H3<=2024,'SYAVLo-passengers'!$B$5,'SYAVLo-passengers'!$B$5*H7) -> 15.34784 | I8: =IF(I3<=2024,'SYAVLo-passengers'!$B$5,'SYAVLo-passengers'!$B$5*I7) -> 15.34784 | J8: =IF(J3<=2024,'SYAVLo-passengers'!$B$5,'SYAVLo-passengers'!$B$5*J7) -> 15.34784 | ... BF8: =IF(BF3<=2024,'SYAVLo-passengers'!$B$5,'SYAVLo-passengers'!$B$5*BF7) -> 22.645793

Sheet bus loading
A1: Bus loading path: NEMS projects bus travel with COVID-recovery terms; the recovery is treated as more riders per bus (loading), not as bus purchases. R is NEMS's recovery factor; the multiplier is R in each year over R in 2024.
A3: year | C3: ='NEMS bus covid'!C3 -> 1995 | D3: ='NEMS bus covid'!D3 -> 1996 | E3: ='NEMS bus covid'!E3 -> 1997 | F3: ='NEMS bus covid'!F3 -> 1998 | G3: ='NEMS bus covid'!G3 -> 1999 | H3: ='NEMS bus covid'!H3 -> 2000 | I3: ='NEMS bus covid'!I3 -> 2001 | J3: ='NEMS bus covid'!J3 -> 2002 | ... BF3: ='NEMS bus covid'!BF3 -> 2050
A4: R transit = sum_r w_r exp(coef_covid_r x TBCOVID_r) / sum_r w_r | C4: =SUMPRODUCT('NEMS bus covid'!$B$31:$B$39,EXP('NEMS bus covid'!$E$16:$E$24*'NEMS bus covid'!C5:C13))/SUM('NEMS bus covid'!$B$31:$B$39) -> 1 | D4: =SUMPRODUCT('NEMS bus covid'!$B$31:$B$39,EXP('NEMS bus covid'!$E$16:$E$24*'NEMS bus covid'!D5:D13))/SUM('NEMS bus covid'!$B$31:$B$39) -> 1 | E4: =SUMPRODUCT('NEMS bus covid'!$B$31:$B$39,EXP('NEMS bus covid'!$E$16:$E$24*'NEMS bus covid'!E5:E13))/SUM('NEMS bus covid'!$B$31:$B$39) -> 1 | F4: =SUMPRODUCT('NEMS bus covid'!$B$31:$B$39,EXP('NEMS bus covid'!$E$16:$E$24*'NEMS bus covid'!F5:F13))/SUM('NEMS bus covid'!$B$31:$B$39) -> 1 | G4: =SUMPRODUCT('NEMS bus covid'!$B$31:$B$39,EXP('NEMS bus covid'!$E$16:$E$24*'NEMS bus covid'!G5:G13))/SUM('NEMS bus covid'!$B$31:$B$39) -> 1 | H4: =SUMPRODUCT('NEMS bus covid'!$B$31:$B$39,EXP('NEMS bus covid'!$E$16:$E$24*'NEMS bus covid'!H5:H13))/SUM('NEMS bus covid'!$B$31:$B$39) -> 1 | I4: =SUMPRODUCT('NEMS bus covid'!$B$31:$B$39,EXP('NEMS bus covid'!$E$16:$E$24*'NEMS bus covid'!I5:I13))/SUM('NEMS bus covid'!$B$31:$B$39) -> 1 | J4: =SUMPRODUCT('NEMS bus covid'!$B$31:$B$39,EXP('NEMS bus covid'!$E$16:$E$24*'NEMS bus covid'!J5:J13))/SUM('NEMS bus covid'!$B$31:$B$39) -> 1 | ... BF4: =SUMPRODUCT('NEMS bus covid'!$B$31:$B$39,EXP('NEMS bus covid'!$E$16:$E$24*'NEMS bus covid'!BF5:BF13))/SUM('NEMS bus covid'!$B$31:$B$39) -> 1.0269614
A5: R intercity = 1 - TMCOVID intercity | C5: =1-'NEMS bus covid'!C27 -> 1 | D5: =1-'NEMS bus covid'!D27 -> 1 | E5: =1-'NEMS bus covid'!E27 -> 1 | F5: =1-'NEMS bus covid'!F27 -> 1 | G5: =1-'NEMS bus covid'!G27 -> 1 | H5: =1-'NEMS bus covid'!H27 -> 1 | I5: =1-'NEMS bus covid'!I27 -> 1 | J5: =1-'NEMS bus covid'!J27 -> 1 | ... BF5: =1-'NEMS bus covid'!BF27 -> 0.99992875
A6: R school = 1 - TMCOVID school | C6: =1-'NEMS bus covid'!C28 -> 1 | D6: =1-'NEMS bus covid'!D28 -> 1 | E6: =1-'NEMS bus covid'!E28 -> 1 | F6: =1-'NEMS bus covid'!F28 -> 1 | G6: =1-'NEMS bus covid'!G28 -> 1 | H6: =1-'NEMS bus covid'!H28 -> 1 | I6: =1-'NEMS bus covid'!I28 -> 1 | J6: =1-'NEMS bus covid'!J28 -> 1 | ... BF6: =1-'NEMS bus covid'!BF28 -> 1
A7: R weighted by 2019 passenger-miles (transit, intercity, school) | C7: =('NEMS bus covid'!$B$44*C4+'NEMS bus covid'!$B$42*C5+'NEMS bus covid'!$B$43*C6)/SUM('NEMS bus covid'!$B$42:$B$44) -> 1 | D7: =('NEMS bus covid'!$B$44*D4+'NEMS bus covid'!$B$42*D5+'NEMS bus covid'!$B$43*D6)/SUM('NEMS bus covid'!$B$42:$B$44) -> 1 | E7: =('NEMS bus covid'!$B$44*E4+'NEMS bus covid'!$B$42*E5+'NEMS bus covid'!$B$43*E6)/SUM('NEMS bus covid'!$B$42:$B$44) -> 1 | F7: =('NEMS bus covid'!$B$44*F4+'NEMS bus covid'!$B$42*F5+'NEMS bus covid'!$B$43*F6)/SUM('NEMS bus covid'!$B$42:$B$44) -> 1 | G7: =('NEMS bus covid'!$B$44*G4+'NEMS bus covid'!$B$42*G5+'NEMS bus covid'!$B$43*G6)/SUM('NEMS bus covid'!$B$42:$B$44) -> 1 | H7: =('NEMS bus covid'!$B$44*H4+'NEMS bus covid'!$B$42*H5+'NEMS bus covid'!$B$43*H6)/SUM('NEMS bus covid'!$B$42:$B$44) -> 1 | I7: =('NEMS bus covid'!$B$44*I4+'NEMS bus covid'!$B$42*I5+'NEMS bus covid'!$B$43*I6)/SUM('NEMS bus covid'!$B$42:$B$44) -> 1 | J7: =('NEMS bus covid'!$B$44*J4+'NEMS bus covid'!$B$42*J5+'NEMS bus covid'!$B$43*J6)/SUM('NEMS bus covid'!$B$42:$B$44) -> 1 | ... BF7: =('NEMS bus covid'!$B$44*BF4+'NEMS bus covid'!$B$42*BF5+'NEMS bus covid'!$B$43*BF6)/SUM('NEMS bus covid'!$B$42:$B$44) -> 1.0027145
A8: Loading multiplier = R(y) / R(2024) | C8: =C7/$AF$7 -> 1.0481517 | D8: =D7/$AF$7 -> 1.0481517 | E8: =E7/$AF$7 -> 1.0481517 | F8: =F7/$AF$7 -> 1.0481517 | G8: =G7/$AF$7 -> 1.0481517 | H8: =H7/$AF$7 -> 1.0481517 | I8: =I7/$AF$7 -> 1.0481517 | J8: =J7/$AF$7 -> 1.0481517 | ... BF8: =BF7/$AF$7 -> 1.0509969
A9: AVLo buses (passengers per bus) = SYAVLo x multiplier, from 2025 | C9: =IF(C3<=2024,'SYAVLo-passengers'!$B$3,'SYAVLo-passengers'!$B$3*C8) -> 21.196137 | D9: =IF(D3<=2024,'SYAVLo-passengers'!$B$3,'SYAVLo-passengers'!$B$3*D8) -> 21.196137 | E9: =IF(E3<=2024,'SYAVLo-passengers'!$B$3,'SYAVLo-passengers'!$B$3*E8) -> 21.196137 | F9: =IF(F3<=2024,'SYAVLo-passengers'!$B$3,'SYAVLo-passengers'!$B$3*F8) -> 21.196137 | G9: =IF(G3<=2024,'SYAVLo-passengers'!$B$3,'SYAVLo-passengers'!$B$3*G8) -> 21.196137 | H9: =IF(H3<=2024,'SYAVLo-passengers'!$B$3,'SYAVLo-passengers'!$B$3*H8) -> 21.196137 | I9: =IF(I3<=2024,'SYAVLo-passengers'!$B$3,'SYAVLo-passengers'!$B$3*I8) -> 21.196137 | J9: =IF(J3<=2024,'SYAVLo-passengers'!$B$3,'SYAVLo-passengers'!$B$3*J8) -> 21.196137 | ... BF9: =IF(BF3<=2024,'SYAVLo-passengers'!$B$3,'SYAVLo-passengers'!$B$3*BF8) -> 22.277075

Sheet psgr rail calcs
B2: btu/gallon diesel | C2: 138700
B3: btu/kwh | C3: 3412.14
B4: Mode | C4: Rail types | D4: HR | E4: CR | F4: LR
E6: Number of Vehicles and Miles | P6: Vehicle Fuel Use
H7: Miles Traveled by Vehicles Fueled by:
B8: State | C8: State | D8: subregion | E8: Max Trains in Operation | F8: Vehicle Miles | G8: Passenger Miles | H8: Diesel | I8: Electric Propulsion | J8: % of miles diesel | K8: % of miles electric | L8: calc AVLO | M8: calc BAADTVBT | N8: SYVBT-diesel | O8: SYVBT-electric | P8: Diesel (gal) | Q8: Bio-Diesel (gal) | R8: Electric Propulsion (kwh) | S8: diesel (btus) | T8: electric (btu) | U8: calc SYFAFE-diesel | V8: calc SYFAFE-electric
B9: Alabama | C9: AL | D9: subregion1 | E9: =SUMIFS('Annual Service Data_rail only'!N:N,'Annual Service Data_rail only'!C:C,C9) -> 0 | F9: =SUMIFS('Annual Service Data_rail only'!X:X,'Annual Service Data_rail only'!C:C,C9) -> 0 | G9: =SUMIFS('Annual Service Data_rail only'!AT:AT,'Annual Service Data_rail only'!C:C,C9) -> 0 | H9: =SUMIFS('Fuel and Energy_rail only'!AD:AD,'Fuel and Energy_rail only'!C:C,C9) -> 0 | I9: =SUMIFS('Fuel and Energy_rail only'!AN:AN,'Fuel and Energy_rail only'!C:C,C9) -> 0 | J9: =IFERROR(H9/SUM($H9:$I9),0) -> 0 | K9: =IFERROR(I9/SUM($H9:$I9),0) -> 0 | L9: =IFERROR(G9/F9,0) -> 0 | M9: =IFERROR(F9/E9,0) -> 0 | N9: =E9*J9 -> 0 | O9: =K9*E9 -> 0 | P9: =SUMIFS('Fuel and Energy_rail only'!M:M,'Fuel and Energy_rail only'!C:C,C9) -> 0 | Q9: =SUMIFS('Fuel and Energy_rail only'!U:U,'Fuel and Energy_rail only'!C:C,C9) -> 0 | R9: =SUMIFS('Fuel and Energy_rail only'!Y:Y,'Fuel and Energy_rail only'!C:C,C9) -> 0 | S9: =SUM(P9:Q9)*$C$2 -> 0 | T9: =R9*$C$3 -> 0 | U9: =IFERROR(($L9*$M9*N9)/S9,0) -> 0 | V9: =IFERROR(($L9*$M9*O9)/T9,0) -> 0
B10: Alaska | C10: AK | D10: subregion2 | E10: =SUMIFS('Annual Service Data_rail only'!N:N,'Annual Service Data_rail only'!C:C,C10) -> 0 | F10: =SUMIFS('Annual Service Data_rail only'!X:X,'Annual Service Data_rail only'!C:C,C10) -> 0 | G10: =SUMIFS('Annual Service Data_rail only'!AT:AT,'Annual Service Data_rail only'!C:C,C10) -> 0 | H10: =SUMIFS('Fuel and Energy_rail only'!AD:AD,'Fuel and Energy_rail only'!C:C,C10) -> 0 | I10: =SUMIFS('Fuel and Energy_rail only'!AN:AN,'Fuel and Energy_rail only'!C:C,C10) -> 0 | J10: =IFERROR(H10/SUM($H10:$I10),0) -> 0 | K10: =IFERROR(I10/SUM($H10:$I10),0) -> 0 | L10: =IFERROR(G10/F10,0) -> 0 | M10: =IFERROR(F10/E10,0) -> 0 | N10: =E10*J10 -> 0 | O10: =K10*E10 -> 0 | P10: =SUMIFS('Fuel and Energy_rail only'!M:M,'Fuel and Energy_rail only'!C:C,C10) -> 0 | Q10: =SUMIFS('Fuel and Energy_rail only'!U:U,'Fuel and Energy_rail only'!C:C,C10) -> 0 | R10: =SUMIFS('Fuel and Energy_rail only'!Y:Y,'Fuel and Energy_rail only'!C:C,C10) -> 0 | S10: =SUM(P10:Q10)*$C$2 -> 0 | T10: =R10*$C$3 -> 0 | U10: =IFERROR(($L10*$M10*N10)/S10,0) -> 0 | V10: =IFERROR(($L10*$M10*O10)/T10,0) -> 0
B11: Arizona | C11: AZ | D11: subregion3 | E11: =SUMIFS('Annual Service Data_rail only'!N:N,'Annual Service Data_rail only'!C:C,C11) -> 17 | F11: =SUMIFS('Annual Service Data_rail only'!X:X,'Annual Service Data_rail only'!C:C,C11) -> 3435184 | G11: =SUMIFS('Annual Service Data_rail only'!AT:AT,'Annual Service Data_rail only'!C:C,C11) -> 90553779 | H11: =SUMIFS('Fuel and Energy_rail only'!AD:AD,'Fuel and Energy_rail only'!C:C,C11) -> 0 | I11: =SUMIFS('Fuel and Energy_rail only'!AN:AN,'Fuel and Energy_rail only'!C:C,C11) -> 3452467 | J11: =IFERROR(H11/SUM($H11:$I11),0) -> 0 | K11: =IFERROR(I11/SUM($H11:$I11),0) -> 1 | L11: =IFERROR(G11/F11,0) -> 26.360678 | M11: =IFERROR(F11/E11,0) -> 202069.65 | N11: =E11*J11 -> 0 | O11: =K11*E11 -> 17 | P11: =SUMIFS('Fuel and Energy_rail only'!M:M,'Fuel and Energy_rail only'!C:C,C11) -> 0 | Q11: =SUMIFS('Fuel and Energy_rail only'!U:U,'Fuel and Energy_rail only'!C:C,C11) -> 0 | R11: =SUMIFS('Fuel and Energy_rail only'!Y:Y,'Fuel and Energy_rail only'!C:C,C11) -> 23474521 | S11: =SUM(P11:Q11)*$C$2 -> 0 | T11: =R11*$C$3 -> 8.0098352e+10 | U11: =IFERROR(($L11*$M11*N11)/S11,0) -> 0 | V11: =IFERROR(($L11*$M11*O11)/T11,0) -> 0.0011305324
B12: Arkansas | C12: AR | D12: subregion4 | E12: =SUMIFS('Annual Service Data_rail only'!N:N,'Annual Service Data_rail only'!C:C,C12) -> 0 | F12: =SUMIFS('Annual Service Data_rail only'!X:X,'Annual Service Data_rail only'!C:C,C12) -> 0 | G12: =SUMIFS('Annual Service Data_rail only'!AT:AT,'Annual Service Data_rail only'!C:C,C12) -> 0 | H12: =SUMIFS('Fuel and Energy_rail only'!AD:AD,'Fuel and Energy_rail only'!C:C,C12) -> 0 | I12: =SUMIFS('Fuel and Energy_rail only'!AN:AN,'Fuel and Energy_rail only'!C:C,C12) -> 0 | J12: =IFERROR(H12/SUM($H12:$I12),0) -> 0 | K12: =IFERROR(I12/SUM($H12:$I12),0) -> 0 | L12: =IFERROR(G12/F12,0) -> 0 | M12: =IFERROR(F12/E12,0) -> 0 | N12: =E12*J12 -> 0 | O12: =K12*E12 -> 0 | P12: =SUMIFS('Fuel and Energy_rail only'!M:M,'Fuel and Energy_rail only'!C:C,C12) -> 0 | Q12: =SUMIFS('Fuel and Energy_rail only'!U:U,'Fuel and Energy_rail only'!C:C,C12) -> 0 | R12: =SUMIFS('Fuel and Energy_rail only'!Y:Y,'Fuel and Energy_rail only'!C:C,C12) -> 0 | S12: =SUM(P12:Q12)*$C$2 -> 0 | T12: =R12*$C$3 -> 0 | U12: =IFERROR(($L12*$M12*N12)/S12,0) -> 0 | V12: =IFERROR(($L12*$M12*O12)/T12,0) -> 0
B13: California | C13: CA | D13: subregion5 | E13: =SUMIFS('Annual Service Data_rail only'!N:N,'Annual Service Data_rail only'!C:C,C13) -> 441 | F13: =SUMIFS('Annual Service Data_rail only'!X:X,'Annual Service Data_rail only'!C:C,C13) -> 139399021 | G13: =SUMIFS('Annual Service Data_rail only'!AT:AT,'Annual Service Data_rail only'!C:C,C13) -> 2812423160 | H13: =SUMIFS('Fuel and Energy_rail only'!AD:AD,'Fuel and Energy_rail only'!C:C,C13) -> 5034854 | I13: =SUMIFS('Fuel and Energy_rail only'!AN:AN,'Fuel and Energy_rail only'!C:C,C13) -> 106204511 | J13: =IFERROR(H13/SUM($H13:$I13),0) -> 0.045261441 | K13: =IFERROR(I13/SUM($H13:$I13),0) -> 0.95473856 | L13: =IFERROR(G13/F13,0) -> 20.175344 | M13: =IFERROR(F13/E13,0) -> 316097.55 | N13: =E13*J13 -> 19.960296 | O13: =K13*E13 -> 421.0397 | P13: =SUMIFS('Fuel and Energy_rail only'!M:M,'Fuel and Energy_rail only'!C:C,C13) -> 13666577 | Q13: =SUMIFS('Fuel and Energy_rail only'!U:U,'Fuel and Energy_rail only'!C:C,C13) -> 0 | R13: =SUMIFS('Fuel and Energy_rail only'!Y:Y,'Fuel and Energy_rail only'!C:C,C13) -> 681466893 | S13: =SUM(P13:Q13)*$C$2 -> 1895554229900 | T13: =R13*$C$3 -> 2.3252604e+12 | U13: =IFERROR(($L13*$M13*N13)/S13,0) -> 6.7154146e-05 | V13: =IFERROR(($L13*$M13*O13)/T13,0) -> 0.0011547648
B14: Colorado | C14: CO | D14: subregion6 | E14: =SUMIFS('Annual Service Data_rail only'!N:N,'Annual Service Data_rail only'!C:C,C14) -> 56 | F14: =SUMIFS('Annual Service Data_rail only'!X:X,'Annual Service Data_rail only'!C:C,C14) -> 15749288 | G14: =SUMIFS('Annual Service Data_rail only'!AT:AT,'Annual Service Data_rail only'!C:C,C14) -> 129461494 | H14: =SUMIFS('Fuel and Energy_rail only'!AD:AD,'Fuel and Energy_rail only'!C:C,C14) -> 0 | I14: =SUMIFS('Fuel and Energy_rail only'!AN:AN,'Fuel and Energy_rail only'!C:C,C14) -> 15639401 | J14: =IFERROR(H14/SUM($H14:$I14),0) -> 0 | K14: =IFERROR(I14/SUM($H14:$I14),0) -> 1 | L14: =IFERROR(G14/F14,0) -> 8.220149 | M14: =IFERROR(F14/E14,0) -> 281237.29 | N14: =E14*J14 -> 0 | O14: =K14*E14 -> 56 | P14: =SUMIFS('Fuel and Energy_rail only'!M:M,'Fuel and Energy_rail only'!C:C,C14) -> 0 | Q14: =SUMIFS('Fuel and Energy_rail only'!U:U,'Fuel and Energy_rail only'!C:C,C14) -> 0 | R14: =SUMIFS('Fuel and Energy_rail only'!Y:Y,'Fuel and Energy_rail only'!C:C,C14) -> 101468806 | S14: =SUM(P14:Q14)*$C$2 -> 0 | T14: =R14*$C$3 -> 3.4622577e+11 | U14: =IFERROR(($L14*$M14*N14)/S14,0) -> 0 | V14: =IFERROR(($L14*$M14*O14)/T14,0) -> 0.00037392218
B15: Connecticut | C15: CT | D15: subregion7 | E15: =SUMIFS('Annual Service Data_rail only'!N:N,'Annual Service Data_rail only'!C:C,C15) -> 5 | F15: =SUMIFS('Annual Service Data_rail only'!X:X,'Annual Service Data_rail only'!C:C,C15) -> 1717047 | G15: =SUMIFS('Annual Service Data_rail only'!AT:AT,'Annual Service Data_rail only'!C:C,C15) -> 12884750 | H15: =SUMIFS('Fuel and Energy_rail only'!AD:AD,'Fuel and Energy_rail only'!C:C,C15) -> 724004 | I15: =SUMIFS('Fuel and Energy_rail only'!AN:AN,'Fuel and Energy_rail only'!C:C,C15) -> 0 | J15: =IFERROR(H15/SUM($H15:$I15),0) -> 1 | K15: =IFERROR(I15/SUM($H15:$I15),0) -> 0 | L15: =IFERROR(G15/F15,0) -> 7.5040171 | M15: =IFERROR(F15/E15,0) -> 343409.4 | N15: =E15*J15 -> 5 | O15: =K15*E15 -> 0 | P15: =SUMIFS('Fuel and Energy_rail only'!M:M,'Fuel and Energy_rail only'!C:C,C15) -> 1678569 | Q15: =SUMIFS('Fuel and Energy_rail only'!U:U,'Fuel and Energy_rail only'!C:C,C15) -> 0 | R15: =SUMIFS('Fuel and Energy_rail only'!Y:Y,'Fuel and Energy_rail only'!C:C,C15) -> 0 | S15: =SUM(P15:Q15)*$C$2 -> 232817520300 | T15: =R15*$C$3 -> 0 | U15: =IFERROR(($L15*$M15*N15)/S15,0) -> 5.5342699e-05 | V15: =IFERROR(($L15*$M15*O15)/T15,0) -> 0
B16: Delaware | C16: DE | D16: subregion8 | E16: =SUMIFS('Annual Service Data_rail only'!N:N,'Annual Service Data_rail only'!C:C,C16) -> 0 | F16: =SUMIFS('Annual Service Data_rail only'!X:X,'Annual Service Data_rail only'!C:C,C16) -> 0 | G16: =SUMIFS('Annual Service Data_rail only'!AT:AT,'Annual Service Data_rail only'!C:C,C16) -> 0 | H16: =SUMIFS('Fuel and Energy_rail only'!AD:AD,'Fuel and Energy_rail only'!C:C,C16) -> 0 | I16: =SUMIFS('Fuel and Energy_rail only'!AN:AN,'Fuel and Energy_rail only'!C:C,C16) -> 0 | J16: =IFERROR(H16/SUM($H16:$I16),0) -> 0 | K16: =IFERROR(I16/SUM($H16:$I16),0) -> 0 | L16: =IFERROR(G16/F16,0) -> 0 | M16: =IFERROR(F16/E16,0) -> 0 | N16: =E16*J16 -> 0 | O16: =K16*E16 -> 0 | P16: =SUMIFS('Fuel and Energy_rail only'!M:M,'Fuel and Energy_rail only'!C:C,C16) -> 0 | Q16: =SUMIFS('Fuel and Energy_rail only'!U:U,'Fuel and Energy_rail only'!C:C,C16) -> 0 | R16: =SUMIFS('Fuel and Energy_rail only'!Y:Y,'Fuel and Energy_rail only'!C:C,C16) -> 0 | S16: =SUM(P16:Q16)*$C$2 -> 0 | T16: =R16*$C$3 -> 0 | U16: =IFERROR(($L16*$M16*N16)/S16,0) -> 0 | V16: =IFERROR(($L16*$M16*O16)/T16,0) -> 0
B17: DC | C17: DC | D17: NA | E17: =SUMIFS('Annual Service Data_rail only'!N:N,'Annual Service Data_rail only'!C:C,C17) -> 129 | F17: =SUMIFS('Annual Service Data_rail only'!X:X,'Annual Service Data_rail only'!C:C,C17) -> 82234530 | G17: =SUMIFS('Annual Service Data_rail only'!AT:AT,'Annual Service Data_rail only'!C:C,C17) -> 985922295 | H17: =SUMIFS('Fuel and Energy_rail only'!AD:AD,'Fuel and Energy_rail only'!C:C,C17) -> 0 | I17: =SUMIFS('Fuel and Energy_rail only'!AN:AN,'Fuel and Energy_rail only'!C:C,C17) -> 64920984 | J17: =IFERROR(H17/SUM($H17:$I17),0) -> 0 | K17: =IFERROR(I17/SUM($H17:$I17),0) -> 1 | L17: =IFERROR(G17/F17,0) -> 11.989152 | M17: =IFERROR(F17/E17,0) -> 637476.98 | N17: =E17*J17 -> 0 | O17: =K17*E17 -> 129 | P17: =SUMIFS('Fuel and Energy_rail only'!M:M,'Fuel and Energy_rail only'!C:C,C17) -> 0 | Q17: =SUMIFS('Fuel and Energy_rail only'!U:U,'Fuel and Energy_rail only'!C:C,C17) -> 0 | R17: =SUMIFS('Fuel and Energy_rail only'!Y:Y,'Fuel and Energy_rail only'!C:C,C17) -> 576455528 | S17: =SUM(P17:Q17)*$C$2 -> 0 | T17: =R17*$C$3 -> 1.966947e+12 | U17: =IFERROR(($L17*$M17*N17)/S17,0) -> 0 | V17: =IFERROR(($L17*$M17*O17)/T17,0) -> 0.00050124498
B18: Florida | C18: FL | D18: subregion9 | E18: =SUMIFS('Annual Service Data_rail only'!N:N,'Annual Service Data_rail only'!C:C,C18) -> 35 | F18: =SUMIFS('Annual Service Data_rail only'!X:X,'Annual Service Data_rail only'!C:C,C18) -> 11964512 | G18: =SUMIFS('Annual Service Data_rail only'!AT:AT,'Annual Service Data_rail only'!C:C,C18) -> 203966246 | H18: =SUMIFS('Fuel and Energy_rail only'!AD:AD,'Fuel and Energy_rail only'!C:C,C18) -> 1504489 | I18: =SUMIFS('Fuel and Energy_rail only'!AN:AN,'Fuel and Energy_rail only'!C:C,C18) -> 559892 | J18: =IFERROR(H18/SUM($H18:$I18),0) -> 0.72878456 | K18: =IFERROR(I18/SUM($H18:$I18),0) -> 0.27121544 | L18: =IFERROR(G18/F18,0) -> 17.047603 | M18: =IFERROR(F18/E18,0) -> 341843.2 | N18: =E18*J18 -> 25.50746 | O18: =K18*E18 -> 9.4925404 | P18: =SUMIFS('Fuel and Energy_rail only'!M:M,'Fuel and Energy_rail only'!C:C,C18) -> 3648266 | Q18: =SUMIFS('Fuel and Energy_rail only'!U:U,'Fuel and Energy_rail only'!C:C,C18) -> 0 | R18: =SUMIFS('Fuel and Energy_rail only'!Y:Y,'Fuel and Energy_rail only'!C:C,C18) -> 66954261 | S18: =SUM(P18:Q18)*$C$2 -> 506014494200 | T18: =R18*$C$3 -> 2.2845731e+11 | U18: =IFERROR(($L18*$M18*N18)/S18,0) -> 0.00029376125 | V18: =IFERROR(($L18*$M18*O18)/T18,0) -> 0.00024214062
B19: Georgia | C19: GA | D19: subregion10 | E19: =SUMIFS('Annual Service Data_rail only'!N:N,'Annual Service Data_rail only'!C:C,C19) -> 39 | F19: =SUMIFS('Annual Service Data_rail only'!X:X,'Annual Service Data_rail only'!C:C,C19) -> 21145309 | G19: =SUMIFS('Annual Service Data_rail only'!AT:AT,'Annual Service Data_rail only'!C:C,C19) -> 329631085 | H19: =SUMIFS('Fuel and Energy_rail only'!AD:AD,'Fuel and Energy_rail only'!C:C,C19) -> 0 | I19: =SUMIFS('Fuel and Energy_rail only'!AN:AN,'Fuel and Energy_rail only'!C:C,C19) -> 19692749 | J19: =IFERROR(H19/SUM($H19:$I19),0) -> 0 | K19: =IFERROR(I19/SUM($H19:$I19),0) -> 1 | L19: =IFERROR(G19/F19,0) -> 15.588852 | M19: =IFERROR(F19/E19,0) -> 542187.41 | N19: =E19*J19 -> 0 | O19: =K19*E19 -> 39 | P19: =SUMIFS('Fuel and Energy_rail only'!M:M,'Fuel and Energy_rail only'!C:C,C19) -> 0 | Q19: =SUMIFS('Fuel and Energy_rail only'!U:U,'Fuel and Energy_rail only'!C:C,C19) -> 0 | R19: =SUMIFS('Fuel and Energy_rail only'!Y:Y,'Fuel and Energy_rail only'!C:C,C19) -> 83566447 | S19: =SUM(P19:Q19)*$C$2 -> 0 | T19: =R19*$C$3 -> 2.8514042e+11 | U19: =IFERROR(($L19*$M19*N19)/S19,0) -> 0 | V19: =IFERROR(($L19*$M19*O19)/T19,0) -> 0.0011560307
B20: Hawaii | C20: HI | D20: subregion11 | E20: =SUMIFS('Annual Service Data_rail only'!N:N,'Annual Service Data_rail only'!C:C,C20) -> 0 | F20: =SUMIFS('Annual Service Data_rail only'!X:X,'Annual Service Data_rail only'!C:C,C20) -> 0 | G20: =SUMIFS('Annual Service Data_rail only'!AT:AT,'Annual Service Data_rail only'!C:C,C20) -> 0 | H20: =SUMIFS('Fuel and Energy_rail only'!AD:AD,'Fuel and Energy_rail only'!C:C,C20) -> 0 | I20: =SUMIFS('Fuel and Energy_rail only'!AN:AN,'Fuel and Energy_rail only'!C:C,C20) -> 0 | J20: =IFERROR(H20/SUM($H20:$I20),0) -> 0 | K20: =IFERROR(I20/SUM($H20:$I20),0) -> 0 | L20: =IFERROR(G20/F20,0) -> 0 | M20: =IFERROR(F20/E20,0) -> 0 | N20: =E20*J20 -> 0 | O20: =K20*E20 -> 0 | P20: =SUMIFS('Fuel and Energy_rail only'!M:M,'Fuel and Energy_rail only'!C:C,C20) -> 0 | Q20: =SUMIFS('Fuel and Energy_rail only'!U:U,'Fuel and Energy_rail only'!C:C,C20) -> 0 | R20: =SUMIFS('Fuel and Energy_rail only'!Y:Y,'Fuel and Energy_rail only'!C:C,C20) -> 0 | S20: =SUM(P20:Q20)*$C$2 -> 0 | T20: =R20*$C$3 -> 0 | U20: =IFERROR(($L20*$M20*N20)/S20,0) -> 0 | V20: =IFERROR(($L20*$M20*O20)/T20,0) -> 0
... B59: Wyoming | C59: WY | D59: subregion50 | E59: =SUMIFS('Annual Service Data_rail only'!N:N,'Annual Service Data_rail only'!C:C,C59) -> 0 | F59: =SUMIFS('Annual Service Data_rail only'!X:X,'Annual Service Data_rail only'!C:C,C59) -> 0 | G59: =SUMIFS('Annual Service Data_rail only'!AT:AT,'Annual Service Data_rail only'!C:C,C59) -> 0 | H59: =SUMIFS('Fuel and Energy_rail only'!AD:AD,'Fuel and Energy_rail only'!C:C,C59) -> 0 | I59: =SUMIFS('Fuel and Energy_rail only'!AN:AN,'Fuel and Energy_rail only'!C:C,C59) -> 0 | J59: =IFERROR(H59/SUM($H59:$I59),0) -> 0 | K59: =IFERROR(I59/SUM($H59:$I59),0) -> 0 | L59: =IFERROR(G59/F59,0) -> 0 | M59: =IFERROR(F59/E59,0) -> 0 | N59: =E59*J59 -> 0 | O59: =K59*E59 -> 0 | P59: =SUMIFS('Fuel and Energy_rail only'!M:M,'Fuel and Energy_rail only'!C:C,C59) -> 0 | Q59: =SUMIFS('Fuel and Energy_rail only'!U:U,'Fuel and Energy_rail only'!C:C,C59) -> 0 | R59: =SUMIFS('Fuel and Energy_rail only'!Y:Y,'Fuel and Energy_rail only'!C:C,C59) -> 0 | S59: =SUM(P59:Q59)*$C$2 -> 0 | T59: =R59*$C$3 -> 0 | U59: =IFERROR(($L59*$M59*N59)/S59,0) -> 0 | V59: =IFERROR(($L59*$M59*O59)/T59,0) -> 0
E61: =E8 -> Max Trains in Operation | F61: =F8 -> Vehicle Miles | G61: =G8 -> Passenger Miles | L61: =L8 -> calc AVLO | M61: =M8 -> calc BAADTVBT | N61: =N8 -> SYVBT-diesel | O61: =O8 -> SYVBT-electric | S61: =S8 -> diesel (btus) | T61: =T8 -> electric (btu) | U61: =U8 -> calc SYFAFE-diesel | V61: =V8 -> calc SYFAFE-electric
D62: totals | E62: =SUM(E9:E59) -> 2740 | F62: =SUM(F9:F59) -> 1083860350 | G62: =SUM(G9:G59) -> 16634915700 | L62: =IFERROR(G62/F62,0) -> 15.34784 | M62: =IFERROR(F62/E62,0) -> 395569.47 | N62: =SUM(N9:N59) -> 173.39396 | O62: =SUM(O9:O59) -> 2563.606 | S62: =SUM(S9:S59) -> 14672704890200 | T62: =SUM(T9:T59) -> 2.0563856e+13 | U62: =IFERROR(($L62*$M62*N62)/S62,0) -> 7.1745362e-05 | V62: =IFERROR(($L62*$M62*O62)/T62,0) -> 0.00075686214
D64: CHECK | E64: =E62/SUM(N62:O62) -> 1.0010961 | G64: =L62*M62*SUM(N62:O62)/G62 -> 0.99890511 | S64: =($L62*$M62*N62/U62)/S62 -> 1 | T64: =($L62*$M62*O62/V62)/T62 -> 1

Sheet SYAVLo-passengers
A1: Vehicle Loading (passengers) | B1: 2020
A2: LDVs | B2: 1.67
A3: HDVs | B3: ='BTS NTS Modal Profile Data'!B14 -> 21.196137
A4: aircraft | B4: ='BTS NTS Modal Profile Data'!B8 -> 111.39416
A5: rail | B5: ='psgr rail calcs'!L62 -> 15.34784
A6: ships | B6: 1
A7: motorbikes | B7: ='BTS NTS Modal Profile Data'!B60 -> 1.2700757

Sheet SYAVLo-freight
A1: Vehicle Loading (tons) | B1: 2020
A2: LDVs | B2: 1
A3: HDVs | B3: 16
A4: aircraft | B4: ='BTS NTS Modal Profile Data'!B9 -> 41.989116
A5: rail | B5: ='BTS NTS Modal Profile Data'!B19 -> 3512.3592
A6: ships | B6: ='BTS NTS Modal Profile Data'!B55 -> 1974.4736
A7: motorbikes | B7: 0

Sheet AVLo-passengers
A1: Vehicle Loading (passengers) | B1: 2021 | C1: 2022 | D1: 2023 | E1: 2024 | F1: 2025 | G1: 2026 | H1: 2027 | I1: 2028 | J1: 2029 | K1: 2030 | L1: 2031 | M1: 2032 | N1: 2033 | O1: 2034 | P1: 2035 | Q1: 2036 | R1: 2037 | S1: 2038 | T1: 2039 | U1: 2040 | V1: 2041 | W1: 2042 | X1: 2043 | Y1: 2044 | Z1: 2045 | AA1: 2046 | AB1: 2047 | AC1: 2048 | AD1: 2049 | AE1: 2050
A2: LDVs | B2: 1.67 | C2: =$B2 -> 1.67 | D2: =$B2 -> 1.67 | E2: =$B2 -> 1.67 | F2: =$B2 -> 1.67 | G2: =$B2 -> 1.67 | H2: =$B2 -> 1.67 | I2: =$B2 -> 1.67 | J2: =$B2 -> 1.67 | ... AE2: =$B2 -> 1.67
A3: HDVs | B3: ='bus loading'!AC9 -> 21.196137 | C3: ='bus loading'!AD9 -> 21.196137 | D3: ='bus loading'!AE9 -> 21.196137 | E3: ='bus loading'!AF9 -> 21.196137 | F3: ='bus loading'!AG9 -> 21.500479 | G3: ='bus loading'!AH9 -> 21.703092 | H3: ='bus loading'!AI9 -> 21.845122 | I3: ='bus loading'!AJ9 -> 21.947622 | ... AE3: ='bus loading'!BF9 -> 22.277075
A4: aircraft | B4: ='BTS NTS Modal Profile Data'!B8 -> 111.39416 | C4: =$B4 -> 111.39416 | D4: =$B4 -> 111.39416 | E4: =$B4 -> 111.39416 | F4: =$B4 -> 111.39416 | G4: =$B4 -> 111.39416 | H4: =$B4 -> 111.39416 | I4: =$B4 -> 111.39416 | J4: =$B4 -> 111.39416 | ... AE4: =$B4 -> 111.39416
A5: rail | B5: ='rail loading'!AC8 -> 15.34784 | C5: ='rail loading'!AD8 -> 15.34784 | D5: ='rail loading'!AE8 -> 15.34784 | E5: ='rail loading'!AF8 -> 15.34784 | F5: ='rail loading'!AG8 -> 16.973953 | G5: ='rail loading'!AH8 -> 18.263175 | H5: ='rail loading'!AI8 -> 19.265701 | I5: ='rail loading'!AJ8 -> 20.037161 | ... AE5: ='rail loading'!BF8 -> 22.645793
A6: ships | B6: 1 | C6: =$B6 -> 1 | D6: =$B6 -> 1 | E6: =$B6 -> 1 | F6: =$B6 -> 1 | G6: =$B6 -> 1 | H6: =$B6 -> 1 | I6: =$B6 -> 1 | J6: =$B6 -> 1 | ... AE6: =$B6 -> 1
A7: motorbikes | B7: ='BTS NTS Modal Profile Data'!B60 -> 1.2700757 | C7: =$B7 -> 1.2700757 | D7: =$B7 -> 1.2700757 | E7: =$B7 -> 1.2700757 | F7: =$B7 -> 1.2700757 | G7: =$B7 -> 1.2700757 | H7: =$B7 -> 1.2700757 | I7: =$B7 -> 1.2700757 | J7: =$B7 -> 1.2700757 | ... AE7: =$B7 -> 1.2700757

Sheet AVLo-freight
A1: Vehicle Loading (tons) | B1: 2021 | C1: 2022 | D1: 2023 | E1: 2024 | F1: 2025 | G1: 2026 | H1: 2027 | I1: 2028 | J1: 2029 | K1: 2030 | L1: 2031 | M1: 2032 | N1: 2033 | O1: 2034 | P1: 2035 | Q1: 2036 | R1: 2037 | S1: 2038 | T1: 2039 | U1: 2040 | V1: 2041 | W1: 2042 | X1: 2043 | Y1: 2044 | Z1: 2045 | AA1: 2046 | AB1: 2047 | AC1: 2048 | AD1: 2049 | AE1: 2050
A2: LDVs | B2: 1 | C2: =$B2 -> 1 | D2: =$B2 -> 1 | E2: =$B2 -> 1 | F2: =$B2 -> 1 | G2: =$B2 -> 1 | H2: =$B2 -> 1 | I2: =$B2 -> 1 | J2: =$B2 -> 1 | ... AE2: =$B2 -> 1
A3: HDVs | B3: 16 | C3: =$B3 -> 16 | D3: =$B3 -> 16 | E3: =$B3 -> 16 | F3: =$B3 -> 16 | G3: =$B3 -> 16 | H3: =$B3 -> 16 | I3: =$B3 -> 16 | J3: =$B3 -> 16 | ... AE3: =$B3 -> 16
A4: aircraft | B4: ='BTS NTS Modal Profile Data'!B9 -> 41.989116 | C4: =$B4 -> 41.989116 | D4: =$B4 -> 41.989116 | E4: =$B4 -> 41.989116 | F4: =$B4 -> 41.989116 | G4: =$B4 -> 41.989116 | H4: =$B4 -> 41.989116 | I4: =$B4 -> 41.989116 | J4: =$B4 -> 41.989116 | ... AE4: =$B4 -> 41.989116
A5: rail | B5: ='BTS NTS Modal Profile Data'!B19 -> 3512.3592 | C5: =$B5 -> 3512.3592 | D5: =$B5 -> 3512.3592 | E5: =$B5 -> 3512.3592 | F5: =$B5 -> 3512.3592 | G5: =$B5 -> 3512.3592 | H5: =$B5 -> 3512.3592 | I5: =$B5 -> 3512.3592 | J5: =$B5 -> 3512.3592 | ... AE5: =$B5 -> 3512.3592
A6: ships | B6: ='BTS NTS Modal Profile Data'!B55 -> 1974.4736 | C6: =$B6 -> 1974.4736 | D6: =$B6 -> 1974.4736 | E6: =$B6 -> 1974.4736 | F6: =$B6 -> 1974.4736 | G6: =$B6 -> 1974.4736 | H6: =$B6 -> 1974.4736 | I6: =$B6 -> 1974.4736 | J6: =$B6 -> 1974.4736 | ... AE6: =$B6 -> 1974.4736
A7: motorbikes | B7: 0 | C7: =$B7 -> 0 | D7: =$B7 -> 0 | E7: =$B7 -> 0 | F7: =$B7 -> 0 | G7: =$B7 -> 0 | H7: =$B7 -> 0 | I7: =$B7 -> 0 | J7: =$B7 -> 0 | ... AE7: =$B7 -> 0
