Workbook
Name CH4_to_CO2e: '[1]Cross-Page Data'!$C$12
Name cpi_2010to2012: #REF!
Name cpi_2013to2012: #REF!
Name cpi_2014to2012: #REF!
Name cpi_2016to2012: #REF!
Name gigwatts_to_megawatts: [3]About!$A$31
Name IQ_CH: 110000
Name IQ_CQ: 5000
Name IQ_CY: 10000
Name IQ_DAILY: 500000
Name IQ_FH: 100000
Name IQ_FQ: 500
Name IQ_FY: 1000
Name IQ_LTM: 2000
Name IQ_MONTH: 15000
Name IQ_NTM: 6000
Name IQ_WEEK: 50000
Name IQ_YTD: 3000
Name N2O_to_CO2e: '[1]Cross-Page Data'!$C$13
Name unit_conv: [4]About!$A$123

Sheet About
A1: WHRPbI Waste Heat Recovery Capital Costs
A4: Sources: | B4: Recovery Costs
B5: Kermeli et al.
B6: 2022
B7: Energy efficiency potentials in the EU industry: impacts of deep decarbonization technologies
B8: https://link.springer.com/article/10.1007/s12053-022-10071-8#Sec15
B9: Supplementary Information
A11: Notes:
A16: Conversions:
A17: 0.8458 | B17: 2021 EUR to 2021 USD
A18: 0.847 | B18: 2021 USD to 2012 USD
A19: 947817 | B19: GJ to BTU

Sheet Kermeli Data
A1: Calculations
A2: Data from Kermeli et al. (SM) | B2: https://link.springer.com/article/10.1007/s12053-022-10071-8#Sec10
A3: NPV =CF0 + CF1/(1+r)1 + CF2/(1+r)2 + … + CFn/(1+r)n
A4: r = hurdle rate = WACC + risk premium
A5: https://capitalgains.thediff.co/p/hurdle-rates
A7: Energy Savings & Cost of Measures from Kermeli et al.
A8: Product / Process | B8: Technology / Measure | C8: 2015 Diffusion | D8: 2030 Implementation | E8: 2050 Implementation | F8: Fuel Savings (GJ/t) | G8: Elec. Savings (GJ/t) | H8: H2 Savings (GJ/t) | I8: Investment (€/t) | J8: Technical lifetime (years) | K8: Annual O&M Costs (€/t)
A9: Primary aluminum | B9: PFPBa | C9: 0.9 | D9: 0.1 | E9: 0.1 | F9: 0 | G9: 2.8 | H9: 0 | I9: 2340 | J9: 20 | K9: 0
A10: Primary aluminum | B10: Optimization electrolysis controlc | C10: 0.55 | D10: 0.35 | E10: 0.45 | F10: 0 | G10: 3.6 | H10: 0 | I10: 188 | J10: 5 | K10: -65
A11: Primary aluminum | B11: Optimization cell designc | C11: 0.55 | D11: 0.35 | E11: 0.45 | F11: 0 | G11: 2.5 | H11: 0 | I11: 236 | J11: 6 | K11: 0
A12: Secondary aluminum | B12: Regenerative or recuperative burnerd | C12: 0.3 | D12: 0.25 | E12: 0.5 | F12: 2 | G12: 0 | H12: 0 | I12: 14 | J12: 20 | K12: 0.4
A13: Secondary aluminum | B13: New decoating equipmentd | C13: 0 | D13: 0.15 | E13: 0.6 | F13: 0.4 | G13: 0 | H13: 0 | I13: 40 | J13: 10 | K13: 40
A14: Aluminum foundries | B14: Improved process schedulinge | C14: 0.6 | D14: 0.39 | E14: 0.4 | F14: 1.8 | G14: 0 | H14: 0 | I14: 25 | J14: 20 | K14: 0
A15: Aluminum foundries | B15: Regenerative or recuperative burnere | C15: 0.5 | D15: 0.05 | E15: 0.3 | F15: 4.8 | G15: 0 | H15: 0 | I15: 10 | J15: 20 | K15: 0.7
A16: Aluminum foundries | B16: Liquid metal as feedstocke | C16: 0.05 | D16: 0.2 | E16: 0.45 | F16: 8.7 | G16: 0 | H16: 0 | I16: 25 | J16: 20 | K16: 0
A17: Coke oven | B17: Programmed heatinga | C17: 0.3 | D17: 0.5 | E17: 0.7 | F17: 0.2 | G17: 0 | H17: 0 | I17: 0.2 | J17: 10 | K17: 0
A18: Coke oven | B18: Variable speed drive on compressorsa | C18: 0.3 | D18: 0.5 | E18: 0.7 | F18: 0 | G18: 0 | H18: 0 | I18: 0.3 | J18: 15 | K18: 0
A19: Coke oven | B19: Coal moisture controla | C19: 0.3 | D19: 0.5 | E19: 0.7 | F19: 0.3 | G19: 0 | H19: 0 | I19: 6.5 | J19: 10 | K19: 0
A20: Pig iron | B20: Waste heat recovery blast furnace slagb | C20: 0 | D20: 0.43 | E20: 0.8 | F20: 0.4 | G20: 0 | H20: 0 | I20: 54.5 | J20: 20 | K20: 0
... A175: Soda ash | B175: High temperature heat pump | C175: 0 | D175: 0.04 | E175: 0.4 | F175: 11.2 | G175: -2.4 | H175: 0 | I175: 841 | J175: 15 | K175: 0

Sheet Calcs
H2: *assume 2021EUR/t
B3: Product / Process | C3: Technology / Measure | D3: Fuel Savings (GJ/t) | E3: Elec. Savings (GJ/t) | F3: Investment (€/t) | G3: Technical lifetime (years) | H3: Annual O&M Costs (€/t) | I3: €/energy savings | J3: 2012USD/BTU
B4: Secondary aluminum | C4: Regenerative or recuperative burnerd | D4: =SUMIFS('Kermeli Data'!F$9:F$114,'Kermeli Data'!$A$9:$A$114,Calcs!$B4,'Kermeli Data'!$B$9:$B$114,Calcs!$C4) -> 2 | E4: =SUMIFS('Kermeli Data'!G$9:G$114,'Kermeli Data'!$A$9:$A$114,Calcs!$B4,'Kermeli Data'!$B$9:$B$114,Calcs!$C4) -> 0 | F4: =SUMIFS('Kermeli Data'!I$9:I$114,'Kermeli Data'!$A$9:$A$114,Calcs!$B4,'Kermeli Data'!$B$9:$B$114,Calcs!$C4) -> 14 | G4: =SUMIFS('Kermeli Data'!J$9:J$114,'Kermeli Data'!$A$9:$A$114,Calcs!$B4,'Kermeli Data'!$B$9:$B$114,Calcs!$C4) -> 20 | H4: =SUMIFS('Kermeli Data'!K$9:K$114,'Kermeli Data'!$A$9:$A$114,Calcs!$B4,'Kermeli Data'!$B$9:$B$114,Calcs!$C4) -> 0.4 | I4: =F4/SUM(D4:E4) -> 7 | J4: =I4/About!$A$17*About!$A$18/About!$A$19 -> 7.3958701e-06
B5: Aluminum foundries | C5: Regenerative or recuperative burnere | D5: =SUMIFS('Kermeli Data'!F$9:F$114,'Kermeli Data'!$A$9:$A$114,Calcs!$B5,'Kermeli Data'!$B$9:$B$114,Calcs!$C5) -> 4.8 | E5: =SUMIFS('Kermeli Data'!G$9:G$114,'Kermeli Data'!$A$9:$A$114,Calcs!$B5,'Kermeli Data'!$B$9:$B$114,Calcs!$C5) -> 0 | F5: =SUMIFS('Kermeli Data'!I$9:I$114,'Kermeli Data'!$A$9:$A$114,Calcs!$B5,'Kermeli Data'!$B$9:$B$114,Calcs!$C5) -> 10 | G5: =SUMIFS('Kermeli Data'!J$9:J$114,'Kermeli Data'!$A$9:$A$114,Calcs!$B5,'Kermeli Data'!$B$9:$B$114,Calcs!$C5) -> 20 | H5: =SUMIFS('Kermeli Data'!K$9:K$114,'Kermeli Data'!$A$9:$A$114,Calcs!$B5,'Kermeli Data'!$B$9:$B$114,Calcs!$C5) -> 0.7 | I5: =F5/SUM(D5:E5) -> 2.0833333 | J5: =I5/About!$A$17*About!$A$18/About!$A$19 -> 2.2011518e-06
B6: Aluminum foundries | C6: Liquid metal as feedstocke | D6: =SUMIFS('Kermeli Data'!F$9:F$114,'Kermeli Data'!$A$9:$A$114,Calcs!$B6,'Kermeli Data'!$B$9:$B$114,Calcs!$C6) -> 8.7 | E6: =SUMIFS('Kermeli Data'!G$9:G$114,'Kermeli Data'!$A$9:$A$114,Calcs!$B6,'Kermeli Data'!$B$9:$B$114,Calcs!$C6) -> 0 | F6: =SUMIFS('Kermeli Data'!I$9:I$114,'Kermeli Data'!$A$9:$A$114,Calcs!$B6,'Kermeli Data'!$B$9:$B$114,Calcs!$C6) -> 25 | G6: =SUMIFS('Kermeli Data'!J$9:J$114,'Kermeli Data'!$A$9:$A$114,Calcs!$B6,'Kermeli Data'!$B$9:$B$114,Calcs!$C6) -> 20 | H6: =SUMIFS('Kermeli Data'!K$9:K$114,'Kermeli Data'!$A$9:$A$114,Calcs!$B6,'Kermeli Data'!$B$9:$B$114,Calcs!$C6) -> 0 | I6: =F6/SUM(D6:E6) -> 2.8735632 | J6: =I6/About!$A$17*About!$A$18/About!$A$19 -> 3.0360715e-06
B7: Pig iron | C7: Waste heat recovery blast furnace slagb | D7: =SUMIFS('Kermeli Data'!F$9:F$114,'Kermeli Data'!$A$9:$A$114,Calcs!$B7,'Kermeli Data'!$B$9:$B$114,Calcs!$C7) -> 0.4 | E7: =SUMIFS('Kermeli Data'!G$9:G$114,'Kermeli Data'!$A$9:$A$114,Calcs!$B7,'Kermeli Data'!$B$9:$B$114,Calcs!$C7) -> 0 | F7: =SUMIFS('Kermeli Data'!I$9:I$114,'Kermeli Data'!$A$9:$A$114,Calcs!$B7,'Kermeli Data'!$B$9:$B$114,Calcs!$C7) -> 54.5 | G7: =SUMIFS('Kermeli Data'!J$9:J$114,'Kermeli Data'!$A$9:$A$114,Calcs!$B7,'Kermeli Data'!$B$9:$B$114,Calcs!$C7) -> 20 | H7: =SUMIFS('Kermeli Data'!K$9:K$114,'Kermeli Data'!$A$9:$A$114,Calcs!$B7,'Kermeli Data'!$B$9:$B$114,Calcs!$C7) -> 0 | I7: =F7/SUM(D7:E7) -> 136.25 | J7: =I7/About!$A$17*About!$A$18/About!$A$19 -> 0.00014395533
B8: BF/BOF steel | C8: Recovery of BOF and sensible heatc | D8: =SUMIFS('Kermeli Data'!F$9:F$114,'Kermeli Data'!$A$9:$A$114,Calcs!$B8,'Kermeli Data'!$B$9:$B$114,Calcs!$C8) -> 0.6 | E8: =SUMIFS('Kermeli Data'!G$9:G$114,'Kermeli Data'!$A$9:$A$114,Calcs!$B8,'Kermeli Data'!$B$9:$B$114,Calcs!$C8) -> 0 | F8: =SUMIFS('Kermeli Data'!I$9:I$114,'Kermeli Data'!$A$9:$A$114,Calcs!$B8,'Kermeli Data'!$B$9:$B$114,Calcs!$C8) -> 25.6 | G8: =SUMIFS('Kermeli Data'!J$9:J$114,'Kermeli Data'!$A$9:$A$114,Calcs!$B8,'Kermeli Data'!$B$9:$B$114,Calcs!$C8) -> 10 | H8: =SUMIFS('Kermeli Data'!K$9:K$114,'Kermeli Data'!$A$9:$A$114,Calcs!$B8,'Kermeli Data'!$B$9:$B$114,Calcs!$C8) -> 0 | I8: =F8/SUM(D8:E8) -> 42.666667 | J8: =I8/About!$A$17*About!$A$18/About!$A$19 -> 4.5079589e-05
B9: BF/BOF steel | C9: Scrap preheatingc | D9: =SUMIFS('Kermeli Data'!F$9:F$114,'Kermeli Data'!$A$9:$A$114,Calcs!$B9,'Kermeli Data'!$B$9:$B$114,Calcs!$C9) -> 0.2 | E9: =SUMIFS('Kermeli Data'!G$9:G$114,'Kermeli Data'!$A$9:$A$114,Calcs!$B9,'Kermeli Data'!$B$9:$B$114,Calcs!$C9) -> 0.4 | F9: =SUMIFS('Kermeli Data'!I$9:I$114,'Kermeli Data'!$A$9:$A$114,Calcs!$B9,'Kermeli Data'!$B$9:$B$114,Calcs!$C9) -> 17.4 | G9: =SUMIFS('Kermeli Data'!J$9:J$114,'Kermeli Data'!$A$9:$A$114,Calcs!$B9,'Kermeli Data'!$B$9:$B$114,Calcs!$C9) -> 30 | H9: =SUMIFS('Kermeli Data'!K$9:K$114,'Kermeli Data'!$A$9:$A$114,Calcs!$B9,'Kermeli Data'!$B$9:$B$114,Calcs!$C9) -> 0 | I9: =F9/SUM(D9:E9) -> 29 | J9: =I9/About!$A$17*About!$A$18/About!$A$19 -> 3.0640033e-05
B10: Rolled steel | C10: Recuperative or regenerative burnerc | D10: =SUMIFS('Kermeli Data'!F$9:F$114,'Kermeli Data'!$A$9:$A$114,Calcs!$B10,'Kermeli Data'!$B$9:$B$114,Calcs!$C10) -> 0.6 | E10: =SUMIFS('Kermeli Data'!G$9:G$114,'Kermeli Data'!$A$9:$A$114,Calcs!$B10,'Kermeli Data'!$B$9:$B$114,Calcs!$C10) -> 0 | F10: =SUMIFS('Kermeli Data'!I$9:I$114,'Kermeli Data'!$A$9:$A$114,Calcs!$B10,'Kermeli Data'!$B$9:$B$114,Calcs!$C10) -> 2.9 | G10: =SUMIFS('Kermeli Data'!J$9:J$114,'Kermeli Data'!$A$9:$A$114,Calcs!$B10,'Kermeli Data'!$B$9:$B$114,Calcs!$C10) -> 10 | H10: =SUMIFS('Kermeli Data'!K$9:K$114,'Kermeli Data'!$A$9:$A$114,Calcs!$B10,'Kermeli Data'!$B$9:$B$114,Calcs!$C10) -> 0 | I10: =F10/SUM(D10:E10) -> 4.8333333 | J10: =I10/About!$A$17*About!$A$18/About!$A$19 -> 5.1066722e-06
B11: Container glass | C11: Batch/cullet preheatinga | D11: =SUMIFS('Kermeli Data'!F$9:F$114,'Kermeli Data'!$A$9:$A$114,Calcs!$B11,'Kermeli Data'!$B$9:$B$114,Calcs!$C11) -> 0.7 | E11: =SUMIFS('Kermeli Data'!G$9:G$114,'Kermeli Data'!$A$9:$A$114,Calcs!$B11,'Kermeli Data'!$B$9:$B$114,Calcs!$C11) -> 0 | F11: =SUMIFS('Kermeli Data'!I$9:I$114,'Kermeli Data'!$A$9:$A$114,Calcs!$B11,'Kermeli Data'!$B$9:$B$114,Calcs!$C11) -> 20 | G11: =SUMIFS('Kermeli Data'!J$9:J$114,'Kermeli Data'!$A$9:$A$114,Calcs!$B11,'Kermeli Data'!$B$9:$B$114,Calcs!$C11) -> 20 | H11: =SUMIFS('Kermeli Data'!K$9:K$114,'Kermeli Data'!$A$9:$A$114,Calcs!$B11,'Kermeli Data'!$B$9:$B$114,Calcs!$C11) -> 0 | I11: =F11/SUM(D11:E11) -> 28.571429 | J11: =I11/About!$A$17*About!$A$18/About!$A$19 -> 3.0187225e-05
B12: Flat glass | C12: Waste heat recoveryd | D12: =SUMIFS('Kermeli Data'!F$9:F$114,'Kermeli Data'!$A$9:$A$114,Calcs!$B12,'Kermeli Data'!$B$9:$B$114,Calcs!$C12) -> 0 | E12: =SUMIFS('Kermeli Data'!G$9:G$114,'Kermeli Data'!$A$9:$A$114,Calcs!$B12,'Kermeli Data'!$B$9:$B$114,Calcs!$C12) -> 0.3 | F12: =SUMIFS('Kermeli Data'!I$9:I$114,'Kermeli Data'!$A$9:$A$114,Calcs!$B12,'Kermeli Data'!$B$9:$B$114,Calcs!$C12) -> 10 | G12: =SUMIFS('Kermeli Data'!J$9:J$114,'Kermeli Data'!$A$9:$A$114,Calcs!$B12,'Kermeli Data'!$B$9:$B$114,Calcs!$C12) -> 20 | H12: =SUMIFS('Kermeli Data'!K$9:K$114,'Kermeli Data'!$A$9:$A$114,Calcs!$B12,'Kermeli Data'!$B$9:$B$114,Calcs!$C12) -> 0 | I12: =F12/SUM(D12:E12) -> 33.333333 | J12: =I12/About!$A$17*About!$A$18/About!$A$19 -> 3.5218429e-05
B13: Flat glass | C13: Batch/cullet preheatinge | D13: =SUMIFS('Kermeli Data'!F$9:F$114,'Kermeli Data'!$A$9:$A$114,Calcs!$B13,'Kermeli Data'!$B$9:$B$114,Calcs!$C13) -> 1.1 | E13: =SUMIFS('Kermeli Data'!G$9:G$114,'Kermeli Data'!$A$9:$A$114,Calcs!$B13,'Kermeli Data'!$B$9:$B$114,Calcs!$C13) -> 0 | F13: =SUMIFS('Kermeli Data'!I$9:I$114,'Kermeli Data'!$A$9:$A$114,Calcs!$B13,'Kermeli Data'!$B$9:$B$114,Calcs!$C13) -> 20 | G13: =SUMIFS('Kermeli Data'!J$9:J$114,'Kermeli Data'!$A$9:$A$114,Calcs!$B13,'Kermeli Data'!$B$9:$B$114,Calcs!$C13) -> 20 | H13: =SUMIFS('Kermeli Data'!K$9:K$114,'Kermeli Data'!$A$9:$A$114,Calcs!$B13,'Kermeli Data'!$B$9:$B$114,Calcs!$C13) -> 0 | I13: =F13/SUM(D13:E13) -> 18.181818 | J13: =I13/About!$A$17*About!$A$18/About!$A$19 -> 1.9210052e-05
B14: Mechanical pulp | C14: Heat recovery (TMP, GW)a | D14: =SUMIFS('Kermeli Data'!F$9:F$114,'Kermeli Data'!$A$9:$A$114,Calcs!$B14,'Kermeli Data'!$B$9:$B$114,Calcs!$C14) -> 3.5 | E14: =SUMIFS('Kermeli Data'!G$9:G$114,'Kermeli Data'!$A$9:$A$114,Calcs!$B14,'Kermeli Data'!$B$9:$B$114,Calcs!$C14) -> 0 | F14: =SUMIFS('Kermeli Data'!I$9:I$114,'Kermeli Data'!$A$9:$A$114,Calcs!$B14,'Kermeli Data'!$B$9:$B$114,Calcs!$C14) -> 41 | G14: =SUMIFS('Kermeli Data'!J$9:J$114,'Kermeli Data'!$A$9:$A$114,Calcs!$B14,'Kermeli Data'!$B$9:$B$114,Calcs!$C14) -> 20 | H14: =SUMIFS('Kermeli Data'!K$9:K$114,'Kermeli Data'!$A$9:$A$114,Calcs!$B14,'Kermeli Data'!$B$9:$B$114,Calcs!$C14) -> 0 | I14: =F14/SUM(D14:E14) -> 11.714286 | J14: =I14/About!$A$17*About!$A$18/About!$A$19 -> 1.2376762e-05
B15: Recovered fibre pulp | C15: Heat recovery from bleachingb | D15: 0.03 | E15: =SUMIFS('Kermeli Data'!G$9:G$114,'Kermeli Data'!$A$9:$A$114,Calcs!$B15,'Kermeli Data'!$B$9:$B$114,Calcs!$C15) -> 0 | F15: =SUMIFS('Kermeli Data'!I$9:I$114,'Kermeli Data'!$A$9:$A$114,Calcs!$B15,'Kermeli Data'!$B$9:$B$114,Calcs!$C15) -> 2 | G15: =SUMIFS('Kermeli Data'!J$9:J$114,'Kermeli Data'!$A$9:$A$114,Calcs!$B15,'Kermeli Data'!$B$9:$B$114,Calcs!$C15) -> 20 | H15: =SUMIFS('Kermeli Data'!K$9:K$114,'Kermeli Data'!$A$9:$A$114,Calcs!$B15,'Kermeli Data'!$B$9:$B$114,Calcs!$C15) -> 0 | I15: =F15/SUM(D15:E15) -> 66.666667 | J15: =I15/About!$A$17*About!$A$18/About!$A$19 -> 7.0436858e-05
B16: Tissue paper | C16: Heat recovery and integrationa | D16: =SUMIFS('Kermeli Data'!F$9:F$114,'Kermeli Data'!$A$9:$A$114,Calcs!$B16,'Kermeli Data'!$B$9:$B$114,Calcs!$C16) -> 0 | E16: =SUMIFS('Kermeli Data'!G$9:G$114,'Kermeli Data'!$A$9:$A$114,Calcs!$B16,'Kermeli Data'!$B$9:$B$114,Calcs!$C16) -> 1.1 | F16: =SUMIFS('Kermeli Data'!I$9:I$114,'Kermeli Data'!$A$9:$A$114,Calcs!$B16,'Kermeli Data'!$B$9:$B$114,Calcs!$C16) -> 16 | G16: =SUMIFS('Kermeli Data'!J$9:J$114,'Kermeli Data'!$A$9:$A$114,Calcs!$B16,'Kermeli Data'!$B$9:$B$114,Calcs!$C16) -> 20 | H16: =SUMIFS('Kermeli Data'!K$9:K$114,'Kermeli Data'!$A$9:$A$114,Calcs!$B16,'Kermeli Data'!$B$9:$B$114,Calcs!$C16) -> 0 | I16: =F16/SUM(D16:E16) -> 14.545455 | J16: =I16/About!$A$17*About!$A$18/About!$A$19 -> 1.5368042e-05
B17: Graphic paper | C17: Heat recovery and integrationa | D17: =SUMIFS('Kermeli Data'!F$9:F$114,'Kermeli Data'!$A$9:$A$114,Calcs!$B17,'Kermeli Data'!$B$9:$B$114,Calcs!$C17) -> 0 | E17: =SUMIFS('Kermeli Data'!G$9:G$114,'Kermeli Data'!$A$9:$A$114,Calcs!$B17,'Kermeli Data'!$B$9:$B$114,Calcs!$C17) -> 1.1 | F17: =SUMIFS('Kermeli Data'!I$9:I$114,'Kermeli Data'!$A$9:$A$114,Calcs!$B17,'Kermeli Data'!$B$9:$B$114,Calcs!$C17) -> 16 | G17: =SUMIFS('Kermeli Data'!J$9:J$114,'Kermeli Data'!$A$9:$A$114,Calcs!$B17,'Kermeli Data'!$B$9:$B$114,Calcs!$C17) -> 20 | H17: =SUMIFS('Kermeli Data'!K$9:K$114,'Kermeli Data'!$A$9:$A$114,Calcs!$B17,'Kermeli Data'!$B$9:$B$114,Calcs!$C17) -> 0 | I17: =F17/SUM(D17:E17) -> 14.545455 | J17: =I17/About!$A$17*About!$A$18/About!$A$19 -> 1.5368042e-05
B18: Board and packaging paper | C18: Heat recovery and integrationa | D18: =SUMIFS('Kermeli Data'!F$9:F$114,'Kermeli Data'!$A$9:$A$114,Calcs!$B18,'Kermeli Data'!$B$9:$B$114,Calcs!$C18) -> 0 | E18: =SUMIFS('Kermeli Data'!G$9:G$114,'Kermeli Data'!$A$9:$A$114,Calcs!$B18,'Kermeli Data'!$B$9:$B$114,Calcs!$C18) -> 1.1 | F18: =SUMIFS('Kermeli Data'!I$9:I$114,'Kermeli Data'!$A$9:$A$114,Calcs!$B18,'Kermeli Data'!$B$9:$B$114,Calcs!$C18) -> 16 | G18: =SUMIFS('Kermeli Data'!J$9:J$114,'Kermeli Data'!$A$9:$A$114,Calcs!$B18,'Kermeli Data'!$B$9:$B$114,Calcs!$C18) -> 20 | H18: =SUMIFS('Kermeli Data'!K$9:K$114,'Kermeli Data'!$A$9:$A$114,Calcs!$B18,'Kermeli Data'!$B$9:$B$114,Calcs!$C18) -> 0 | I18: =F18/SUM(D18:E18) -> 14.545455 | J18: =I18/About!$A$17*About!$A$18/About!$A$19 -> 1.5368042e-05
B19: Soda ash | C19: Heat integratione | D19: =SUMIFS('Kermeli Data'!F$9:F$114,'Kermeli Data'!$A$9:$A$114,Calcs!$B19,'Kermeli Data'!$B$9:$B$114,Calcs!$C19) -> 1 | E19: =SUMIFS('Kermeli Data'!G$9:G$114,'Kermeli Data'!$A$9:$A$114,Calcs!$B19,'Kermeli Data'!$B$9:$B$114,Calcs!$C19) -> 0 | F19: =SUMIFS('Kermeli Data'!I$9:I$114,'Kermeli Data'!$A$9:$A$114,Calcs!$B19,'Kermeli Data'!$B$9:$B$114,Calcs!$C19) -> 20 | G19: =SUMIFS('Kermeli Data'!J$9:J$114,'Kermeli Data'!$A$9:$A$114,Calcs!$B19,'Kermeli Data'!$B$9:$B$114,Calcs!$C19) -> 20 | H19: =SUMIFS('Kermeli Data'!K$9:K$114,'Kermeli Data'!$A$9:$A$114,Calcs!$B19,'Kermeli Data'!$B$9:$B$114,Calcs!$C19) -> 0 | I19: =F19/SUM(D19:E19) -> 20 | J19: =I19/About!$A$17*About!$A$18/About!$A$19 -> 2.1131057e-05
B20: Soda ash | C20: Usage of CHPe | D20: =SUMIFS('Kermeli Data'!F$9:F$114,'Kermeli Data'!$A$9:$A$114,Calcs!$B20,'Kermeli Data'!$B$9:$B$114,Calcs!$C20) -> 1.8 | E20: =SUMIFS('Kermeli Data'!G$9:G$114,'Kermeli Data'!$A$9:$A$114,Calcs!$B20,'Kermeli Data'!$B$9:$B$114,Calcs!$C20) -> 0 | F20: =SUMIFS('Kermeli Data'!I$9:I$114,'Kermeli Data'!$A$9:$A$114,Calcs!$B20,'Kermeli Data'!$B$9:$B$114,Calcs!$C20) -> 36 | G20: =SUMIFS('Kermeli Data'!J$9:J$114,'Kermeli Data'!$A$9:$A$114,Calcs!$B20,'Kermeli Data'!$B$9:$B$114,Calcs!$C20) -> 30 | H20: =SUMIFS('Kermeli Data'!K$9:K$114,'Kermeli Data'!$A$9:$A$114,Calcs!$B20,'Kermeli Data'!$B$9:$B$114,Calcs!$C20) -> 0 | I20: =F20/SUM(D20:E20) -> 20 | J20: =I20/About!$A$17*About!$A$18/About!$A$19 -> 2.1131057e-05
B21: Carbon black | C21: Usage of CHPe | D21: =SUMIFS('Kermeli Data'!F$9:F$114,'Kermeli Data'!$A$9:$A$114,Calcs!$B21,'Kermeli Data'!$B$9:$B$114,Calcs!$C21) -> 6.5 | E21: =SUMIFS('Kermeli Data'!G$9:G$114,'Kermeli Data'!$A$9:$A$114,Calcs!$B21,'Kermeli Data'!$B$9:$B$114,Calcs!$C21) -> 0 | F21: =SUMIFS('Kermeli Data'!I$9:I$114,'Kermeli Data'!$A$9:$A$114,Calcs!$B21,'Kermeli Data'!$B$9:$B$114,Calcs!$C21) -> 130 | G21: =SUMIFS('Kermeli Data'!J$9:J$114,'Kermeli Data'!$A$9:$A$114,Calcs!$B21,'Kermeli Data'!$B$9:$B$114,Calcs!$C21) -> 20 | H21: =SUMIFS('Kermeli Data'!K$9:K$114,'Kermeli Data'!$A$9:$A$114,Calcs!$B21,'Kermeli Data'!$B$9:$B$114,Calcs!$C21) -> 0 | I21: =F21/SUM(D21:E21) -> 20 | J21: =I21/About!$A$17*About!$A$18/About!$A$19 -> 2.1131057e-05
B22: Ammonia | C22: Indirect cooling of the ammonia synthesis reactorf | D22: =SUMIFS('Kermeli Data'!F$9:F$114,'Kermeli Data'!$A$9:$A$114,Calcs!$B22,'Kermeli Data'!$B$9:$B$114,Calcs!$C22) -> 0.6 | E22: =SUMIFS('Kermeli Data'!G$9:G$114,'Kermeli Data'!$A$9:$A$114,Calcs!$B22,'Kermeli Data'!$B$9:$B$114,Calcs!$C22) -> 0 | F22: =SUMIFS('Kermeli Data'!I$9:I$114,'Kermeli Data'!$A$9:$A$114,Calcs!$B22,'Kermeli Data'!$B$9:$B$114,Calcs!$C22) -> 7 | G22: =SUMIFS('Kermeli Data'!J$9:J$114,'Kermeli Data'!$A$9:$A$114,Calcs!$B22,'Kermeli Data'!$B$9:$B$114,Calcs!$C22) -> 20 | H22: =SUMIFS('Kermeli Data'!K$9:K$114,'Kermeli Data'!$A$9:$A$114,Calcs!$B22,'Kermeli Data'!$B$9:$B$114,Calcs!$C22) -> 0 | I22: =F22/SUM(D22:E22) -> 11.666667 | J22: =I22/About!$A$17*About!$A$18/About!$A$19 -> 1.232645e-05
B23: Ammonia | C23: Increasing the air preheat with waste heatf | D23: =SUMIFS('Kermeli Data'!F$9:F$114,'Kermeli Data'!$A$9:$A$114,Calcs!$B23,'Kermeli Data'!$B$9:$B$114,Calcs!$C23) -> 0.9 | E23: =SUMIFS('Kermeli Data'!G$9:G$114,'Kermeli Data'!$A$9:$A$114,Calcs!$B23,'Kermeli Data'!$B$9:$B$114,Calcs!$C23) -> 0 | F23: =SUMIFS('Kermeli Data'!I$9:I$114,'Kermeli Data'!$A$9:$A$114,Calcs!$B23,'Kermeli Data'!$B$9:$B$114,Calcs!$C23) -> 7 | G23: =SUMIFS('Kermeli Data'!J$9:J$114,'Kermeli Data'!$A$9:$A$114,Calcs!$B23,'Kermeli Data'!$B$9:$B$114,Calcs!$C23) -> 20 | H23: =SUMIFS('Kermeli Data'!K$9:K$114,'Kermeli Data'!$A$9:$A$114,Calcs!$B23,'Kermeli Data'!$B$9:$B$114,Calcs!$C23) -> 0 | I23: =F23/SUM(D23:E23) -> 7.7777778 | J23: =I23/About!$A$17*About!$A$18/About!$A$19 -> 8.2176335e-06
B24: Clinker | C24: Heat Recovery for Power Generation (ORC)d | D24: =SUMIFS('Kermeli Data'!F$9:F$114,'Kermeli Data'!$A$9:$A$114,Calcs!$B24,'Kermeli Data'!$B$9:$B$114,Calcs!$C24) -> 0 | E24: =0.054 -> 0.054 | F24: =20/2 -> 10 | G24: =SUMIFS('Kermeli Data'!J$9:J$114,'Kermeli Data'!$A$9:$A$114,Calcs!$B24,'Kermeli Data'!$B$9:$B$114,Calcs!$C24) -> 20 | H24: =SUMIFS('Kermeli Data'!K$9:K$114,'Kermeli Data'!$A$9:$A$114,Calcs!$B24,'Kermeli Data'!$B$9:$B$114,Calcs!$C24) -> 1 | I24: =F24/SUM(D24:E24) -> 185.18519 | J24: =I24/About!$A$17*About!$A$18/About!$A$19 -> 0.00019565794
E25: ^manual from source data | L25: =20000000/2000000 -> 10
H26: Average: | I26: =AVERAGE(I4:I24) -> 32.925734 | J26: =AVERAGE(J4:J24) -> 3.4787779e-05
H27: Standard Deviation: | I27: =STDEV(I4:I24) -> 45.666637 | J27: =STDEV(J4:J24) -> 4.8249217e-05

Sheet WHRCC
A1: $/BTU | B1: cost
A2: average | B2: =Calcs!J26 -> 3.4787779e-05
