Workbook
Name gal_per_barrel: [1]About!$A$63

Sheet About
A1: BFPIaE BAU Fuel Production
A2: BFPIaE BAU Fuel Imports
A3: BFPIaE BAU Fuel Exports
A5: Source: | B5: Petroleum-based fuels, biofuels
B6: U.S. Energy Information Administration
B7: 2025 (with annual data for 2024)
B8: Petroleum & Other Liquids: Supply and Disposition
B9: https://www.eia.gov/dnav/pet/pet_sum_snd_d_nus_mbbl_a_cur.htm
B10: Area: US, Period: Annual 2024
B12: Nuclear Fuel (Uranium) Production
B13: U.S. Energy Information Administration
B14: 2025
B15: Domestic Uranium Production Report - Annual
B16: https://www.eia.gov/uranium/production/annual/umine.php
B18: Nuclear Fuel (Uranium) Domestic Demand
B19: U.S. Energy Information Administration
B20: 2025
B21: Uranium Marketing Annual Report
B22: https://www.eia.gov/uranium/marketing/summarytable1a.php?
B24: Hard Coal, Lignite
B25: U.S. Energy Information Administration
B26: 2025
B27: Annual Coal Report and Browser Data
B28: https://www.eia.gov/coal/annual/pdf/tableES1.pdf
B29: https://www.eia.gov/coal/data/browser/
B30: https://www.eia.gov/coal/data/browser/#/topic/41?agg=0,2,1&rank=g&freq=A&start=2001&end=2024&ctype=map&ltype=pin&rtype=s&maptype=0&rse=0&pin=
B31: https://www.eia.gov/coal/data/browser/#/topic/39?agg=2,1,0&rank=ok&map=COAL.EXPORT_QTY.TOT-TOT-TOT.A&freq=A&start=2001&end=2024&ctype=map&ltype=pin&rtype=s&pin=&rse=0&maptype=0
B33: Biomass Production and Exports
B34: U.S. Energy Information Administration
B35: 2025
B36: Monthly Densified Biomass Fuel Report, December 2024
B37: https://www.eia.gov/biofuels/biomass/?year=2024&month=12#table_data
B38: Tables 2 and 8
B40: Natural Gas, Hydrogen, Time Series Scaling Factors
B41: U.S. Energy Information Administration
B42: 2026
B43: Annual Energy Outlook 2026
B44: https://www.eia.gov/outlooks/aeo/tables_ref.php
B45: Alternative Electricity and Transportation, Tables 1, 19
B47: Municipal Solid Waste
B48: National Academies of Sciences
B49: 2025
B50: Municipal Solid Waste Recycling in the United States: Analysis of Current and Alternative Approaches
B51: https://www.nationalacademies.org/read/27978/chapter/4
B52: Summary of Key Messages, first paragraph
B54: Unit Conversions for hard coal, natural gas, petroleum fuels, liquid biofuels
B55: Energy Information Administration
B56: 2023
B57: Annual Energy Outlook 2023
B58: https://www.eia.gov/outlooks/archive/aeo23/
B59: AEO2023 Table 69
B61: Unit Conversions for Lignite, Biomass, LPG, municipal solid waste, hydrogen
B62: Argonne National Laboratory
B63: 2019
B64: GREET1 2019
B65: https://greet.es.anl.gov/
B66: Tab "Fuel_Specs"
B68: Unit Conversion for Uranium (U3O8)
B69: TradeTech
B70: 2019
B71: Uranium Primer - Price & Unit Conversion Calculator & Table
B72: https://www.uranium.info/unit_conversion_table.php
A74: Notes
A76: Collect Export, Import, and Production Data for Each Fuel
A77: The consolidated data in this variable (production, imports, exports, and domestic use of each fuel)
A78: is used in the variable fuels/CiFIaEpUDFS. Therefore, even though this variable only outputs
A79: production and exports, you should also collect data on fuel imports. (Domestic use data
A80: can be calculated from production, imports, and exports. We ignore changes in fuel stocks,
A81: which should average to zero over multi-year timeframes.)
A83: Time Series
A84: This variable contains time series data.
A85: However, only data from the first year are used in variable fuels/CiFIaEpUDFS.
A86: In the future, fuels/CiFIaEpUDFS may be replaced with internal Vensim calculations,
A87: making those values sensitive to changes over time.
... A105: BAU run (calibration/steps/05-bfpiae/solve.py, two passes, max change 1.2% < 2%). Imports and exports tabs unchanged.

Sheet Petroleum and Biofuel Data
B1: Area: US | C1: Period: 2017 (Annual) | E1: Unit: Thousand Barrels
C2: Supply | I2: Disposition | M2: Ending Stocks
C3: Field Production | D3: Renewable Fuels & Oxygenate Plant Net Production | E3: Refinery & Blender Net Production | F3: Imports | G3: Net Receipts | H3: Adjust- ments | I3: Stock Change | J3: Refinery & Blender Net Inputs | K3: Exports | L3: Products Supplied
A4: =TRIM(B4) -> Crude Oil & Petroleum Products | B4: Crude Oil & Petroleum Products | C4: 4794078 | D4: 437131 | E4: 7408771 | F4: 3702640 | H4: 137262 | I4: -135002 | J4: 7003159 | K4: 2327156 | L4: 7284569 | M4: 1894570
A5: =TRIM(B5) -> Crude Oil | B5: Crude Oil | C5: 4083494 | D5: - - | E5: - - | F5: 2230000 | H5: 194916 | I5: -108241 | J5: 5529012 | K5: 1087638 | L5: 0 | M5: 1015102
A6: =TRIM(B6) -> Hydrocarbon Gas Liquids | B6: Hydrocarbon Gas Liquids | C6: 1970031 | D6: -7941 | E6: 225172 | F6: 63125 | H6: - - | I6: -40797 | J6: 198527 | K6: 848015 | L6: 1244642 | M6: 188360
A7: =TRIM(B7) -> Natural Gas Liquids | B7: Natural Gas Liquids | C7: 1970031 | D7: -7941 | E7: 120757 | F7: 57128 | H7: - - | I7: -40636 | J7: 198527 | K7: 848015 | L7: 1134069 | M7: 186272
A8: =TRIM(B8) -> Ethane | B8: Ethane | C8: 781560 | D8: - - | E8: 1505 | F8: - | H8: - - | I8: -9779 | K8: 147584 | L8: 645260 | M8: 59821
A9: =TRIM(B9) -> Propane | B9: Propane | C9: 632906 | D9: - - | E9: 101344 | F9: 41465 | H9: - - | I9: -8358 | K9: 477616 | L9: 306457 | M9: 62077
A10: =TRIM(B10) -> Normal Butane | B10: Normal Butane | C10: 180543 | D10: - | E10: 20998 | F10: 13237 | H10: - - | I10: -7626 | J10: 66056 | K10: 149693 | L10: 6655 | M10: 34017
A11: =TRIM(B11) -> Isobutane | B11: Isobutane | C11: 153863 | D11: - | E11: -3090 | F11: 2358 | H11: - - | I11: -2667 | J11: 71652 | K11: 1181 | L11: 82965 | M11: 9674
A12: =TRIM(B12) -> Natural Gasoline | B12: Natural Gasoline | C12: 221159 | D12: -7941 | F12: 68 | H12: - - | I12: -12206 | J12: 60819 | K12: 71941 | L12: 92732 | M12: 20683
A13: =TRIM(B13) -> Refinery Olefins | B13: Refinery Olefins | C13: - - | D13: - - | E13: 104415 | F13: 5997 | H13: - - | I13: -161 | J13: - - | K13: - - | L13: 110573 | M13: 2088
A14: =TRIM(B14) -> Ethylene | B14: Ethylene | C14: - - | D14: - - | E14: 277 | F14: - | H14: - - | I14: 0 | J14: - - | K14: - - | L14: 277 | M14: 0
A15: =TRIM(B15) -> Propylene | B15: Propylene | C15: - - | D15: - - | E15: 106126 | F15: 5243 | H15: - - | I15: -90 | J15: - - | K15: - - | L15: 111459 | M15: 1397
A16: =TRIM(B16) -> Normal Butylene | B16: Normal Butylene | C16: - - | D16: - - | E16: -2397 | F16: 2433 | H16: - - | I16: -1165 | J16: - - | K16: - - | L16: 1201 | M16: 1204
A17: =TRIM(B17) -> Isobutylene | B17: Isobutylene | C17: - - | D17: - - | E17: 286 | F17: - | H17: - - | I17: 6 | J17: - - | K17: - - | L17: 280 | M17: 30
A18: =TRIM(B18) -> Other Liquids | B18: Other Liquids | C18: - - | D18: 443737 | E18: - - | F18: 471784 | H18: 19117 | I18: 8685 | J18: 741289 | K18: 171592 | L18: 13072 | M18: 328230
A19: =TRIM(B19) -> Hydrogen/Oxygenates/Renewables/Other Hydrocarbons | B19: Hydrogen/Oxygenates/Renewables/Other Hydrocarbons | C19: - - | D19: 443788 | E19: - - | F19: 19778 | H19: 36824 | I19: 577 | J19: 439078 | K19: 60735 | L19: 0 | M19: 29585
A20: =TRIM(B20) -> Hydrogen | B20: Hydrogen | C20: - - | D20: - - | E20: - - | H20: 81091 | I20: - - | J20: 81091 | L20: 0 | M20: - -
A21: =TRIM(B21) -> Oxygenates (excl. Fuel Ethanol) | B21: Oxygenates (excl. Fuel Ethanol) | C21: - - | D21: 26360 | E21: - - | F21: 3835 | H21: -4811 | I21: -31 | J21: - | K21: 25415 | L21: 0 | M21: 1446
A22: =TRIM(B22) -> Renewable Fuels (incl. Fuel Ethanol) | B22: Renewable Fuels (incl. Fuel Ethanol) | C22: - - | D22: 417428 | E22: - - | F22: 15707 | H22: -39640 | I22: 578 | J22: 357597 | K22: 35320 | L22: 0 | M22: 28092
A23: =TRIM(B23) -> Fuel Ethanol | B23: Fuel Ethanol | C23: - - | D23: 379435 | E23: - - | F23: 1824 | H23: -9859 | I23: 3285 | J23: 335023 | K23: 33092 | L23: 0 | M23: 23043
A24: =TRIM(B24) -> Renewable Fuels Except Fuel Ethanol | B24: Renewable Fuels Except Fuel Ethanol | C24: - - | D24: 37993 | E24: - - | F24: 13883 | H24: -29781 | I24: -2707 | J24: 22574 | K24: 2228 | L24: 0 | M24: 5049
A25: =TRIM(B25) -> Other Hydrocarbons | B25: Other Hydrocarbons | C25: - - | D25: - - | E25: - - | F25: 236 | H25: 184 | I25: 30 | J25: 390 | L25: 0 | M25: 47
A26: =TRIM(B26) -> Unfinished Oils | B26: Unfinished Oils | C26: - - | D26: - - | E26: - - | F26: 231478 | H26: - - | I26: 6013 | J26: 129406 | K26: 82949 | L26: 13110 | M26: 86337
A27: =TRIM(B27) -> Motor Gasoline Blend. Comp. | B27: Motor Gasoline Blend. Comp. | C27: - - | D27: -51 | E27: - - | F27: 220528 | H27: -17707 | I27: 2089 | J27: 172773 | K27: 27908 | L27: 0 | M27: 212293
A28: =TRIM(B28) -> Reformulated | B28: Reformulated | C28: - - | D28: -3 | E28: - - | F28: 76948 | H28: 65150 | I28: 1299 | J28: 140697 | K28: 99 | L28: 0 | M28: 53447
A29: =TRIM(B29) -> Conventional | B29: Conventional | C29: - - | D29: -48 | E29: - - | F29: 143580 | H29: -82856 | I29: 790 | J29: 32076 | K29: 27810 | L29: 0 | M29: 158846
A30: =TRIM(B30) -> Aviation Gasoline Blend. Comp. | B30: Aviation Gasoline Blend. Comp. | C30: - - | D30: - - | E30: - - | F30: - | H30: - - | I30: 6 | J30: 32 | K30: - | L30: -38 | M30: 15
A31: =TRIM(B31) -> Finished Petroleum Products | B31: Finished Petroleum Products | C31: - - | D31: 1336 | E31: 7179380 | F31: 250759 | H31: 57659 | I31: -38269 | J31: - - | K31: 1220551 | L31: 6306852 | M31: 291859
A32: =TRIM(B32) -> Finished Motor Gasoline | B32: Finished Motor Gasoline | C32: - - | D32: 1336 | E32: 3633123 | F32: 11784 | H32: 27566 | I32: -3860 | J32: - - | K32: 273483 | L32: 3404186 | M32: 24523
A33: =TRIM(B33) -> Reformulated | B33: Reformulated | C33: - - | E33: 1187104 | F33: - | H33: -59342 | I33: -7 | J33: - - | K33: - | L33: 1127769 | M33: 40
A34: =TRIM(B34) -> Conventional | B34: Conventional | C34: - - | D34: 1336 | E34: 2446019 | F34: 11784 | H34: 86908 | I34: -3853 | J34: - - | K34: 273483 | L34: 2276417 | M34: 24483
A35: =TRIM(B35) -> Finished Aviation Gasoline | B35: Finished Aviation Gasoline | C35: - - | D35: - - | E35: 4032 | F35: 165 | H35: - - | I35: 47 | J35: - - | K35: - | L35: 4150 | M35: 1041
A36: =TRIM(B36) -> Kerosene-Type Jet Fuel | B36: Kerosene-Type Jet Fuel | C36: - - | D36: - - | E36: 621176 | F36: 58273 | H36: - - | I36: -1706 | J36: - - | K36: 67161 | L36: 613994 | M36: 41304
A37: =TRIM(B37) -> Kerosene | B37: Kerosene | C37: - - | D37: - - | E37: 2738 | F37: 1429 | H37: - - | I37: 10 | J37: - - | K37: 2267 | L37: 1890 | M37: 2138
A38: =TRIM(B38) -> Distillate Fuel Oil | B38: Distillate Fuel Oil | C38: - - | D38: - - | E38: 1833879 | F38: 54975 | H38: 30093 | I38: -20457 | J38: - - | K38: 504155 | L38: 1435249 | M38: 145638
A39: =TRIM(B39) -> 15 ppm Sulfur and Under | B39: 15 ppm Sulfur and Under | C39: - - | D39: - - | E39: 1713652 | F39: 37012 | H39: 30093 | I39: -16256 | J39: - - | K39: 423862 | L39: 1373151 | M39: 128016
A40: =TRIM(B40) -> Greater than 15 to 500 ppm Sulfur | B40: Greater than 15 to 500 ppm Sulfur | C40: - - | D40: - - | E40: 42167 | F40: 759 | H40: - | I40: -929 | J40: - - | K40: 41645 | L40: 2210 | M40: 7480
A41: =TRIM(B41) -> Greater than 500 ppm Sulfur | B41: Greater than 500 ppm Sulfur | C41: - - | D41: - - | E41: 78060 | F41: 17204 | H41: - - | I41: -3272 | J41: - - | K41: 38648 | L41: 59888 | M41: 10142
A42: =TRIM(B42) -> Residual Fuel Oil | B42: Residual Fuel Oil | C42: - - | D42: - - | E42: 155851 | F42: 69015 | H42: - - | I42: -12098 | J42: - - | K42: 112240 | L42: 124724 | M42: 29377
A43: =TRIM(B43) -> Less than 0.31% Sulfur | B43: Less than 0.31% Sulfur | C43: - - | D43: - - | E43: 18946 | F43: 4112 | H43: - - | I43: -2600 | J43: - - | K43: NA | L43: NA | M43: 1928
A44: =TRIM(B44) -> 0.31 to 1.00% Sulfur | B44: 0.31 to 1.00% Sulfur | C44: - - | D44: - - | E44: 19577 | F44: 7295 | H44: - - | I44: -1119 | J44: - - | K44: NA | L44: NA | M44: 6822
A45: =TRIM(B45) -> Greater than 1.00% Sulfur | B45: Greater than 1.00% Sulfur | C45: - - | D45: - - | E45: 117328 | F45: 57608 | H45: - - | I45: -8379 | J45: - - | K45: NA | L45: NA | M45: 20621
A46: =TRIM(B46) -> Petrochemical Feedstocks | B46: Petrochemical Feedstocks | C46: - - | D46: - - | E46: 112198 | F46: 15696 | H46: - - | I46: -357 | J46: - - | K46: - | L46: 128251 | M46: 2883
A47: =TRIM(B47) -> Naphtha for Petro. Feed. Use | B47: Naphtha for Petro. Feed. Use | C47: - - | D47: - - | E47: 71578 | F47: 11373 | H47: - - | I47: -162 | J47: - - | K47: - | L47: 83113 | M47: 1849
A48: =TRIM(B48) -> Other Oils for Petro. Feed. Use | B48: Other Oils for Petro. Feed. Use | C48: - - | D48: - - | E48: 40620 | F48: 4323 | H48: - - | I48: -195 | J48: - - | K48: - | L48: 45138 | M48: 1034
A49: =TRIM(B49) -> Special Naphthas | B49: Special Naphthas | C49: - - | D49: - - | E49: 13688 | F49: 5405 | H49: - - | I49: -26 | J49: - - | K49: - | L49: 19119 | M49: 1192
A50: =TRIM(B50) -> Lubricants | B50: Lubricants | C50: - - | D50: - - | E50: 64970 | F50: 14901 | H50: - - | I50: -347 | J50: - - | K50: 36215 | L50: 44003 | M50: 12021
A51: =TRIM(B51) -> Waxes | B51: Waxes | C51: - - | D51: - - | E51: 1774 | F51: 1724 | H51: - - | I51: 184 | J51: - - | K51: 1479 | L51: 1835 | M51: 855
A52: =TRIM(B52) -> Petroleum Coke | B52: Petroleum Coke | C52: - - | D52: - - | E52: 329170 | F52: 3662 | H52: - - | I52: 1536 | J52: - - | K52: 215873 | L52: 115423 | M52: 8519
A53: =TRIM(B53) -> Marketable | B53: Marketable | C53: - - | D53: - - | E53: 245213 | F53: 3662 | H53: - - | I53: 1536 | J53: - - | K53: 215873 | L53: 31466 | M53: 8519
A54: =TRIM(B54) -> Catalyst | B54: Catalyst | C54: - - | D54: - - | E54: 83957 | F54: - - | G54: - - | H54: - - | I54: - - | J54: - - | K54: - - | L54: 83957 | M54: - -
A55: =TRIM(B55) -> Asphalt and Road Oil | B55: Asphalt and Road Oil | C55: - - | D55: - - | E55: 120515 | F55: 13666 | H55: - - | I55: -1184 | J55: - - | K55: 7399 | L55: 127966 | M55: 21697
A56: =TRIM(B56) -> Still Gas | B56: Still Gas | C56: - - | D56: - - | E56: 251761 | F56: - - | G56: - - | H56: - - | I56: - - | J56: - - | K56: - - | L56: 251761 | M56: - -
A57: =TRIM(B57) -> Miscellaneous Products | B57: Miscellaneous Products | C57: - - | D57: - - | E57: 34505 | F57: 64 | H57: - - | I57: -11 | J57: - - | K57: 279 | L57: 34301 | M57: 671

Sheet Petroleum and Biofuels 
A2: #VALUE!
A4: #VALUE! | C4: Field Production | D4: Transfers to Crude Oil Supply | E4: Biofuels Plant Net Production | F4: Refinery & Blender Net Production | G4: Imports | H4: Net Receipts | I4: Adjust- ments | J4: Stock Change | K4: Refinery & Blender Net Inputs | L4: Exports | M4: Products Supplied
B5: Crude Oil & Petroleum Products | C5: 7420896 | D5: 0 | E5: 504680 | F5: 7146373 | G5: 3088150 | I5: 64054 | J5: 23607 | K5: 6791496 | L5: 3919330 | M5: 7489722 | N5: 1629709
B6: Crude Oil | C6: 4843858 | D6: 223927 | E6: - - | F6: - - | G6: 2411095 | I6: -16532 | J6: 25773 | K6: 5938479 | L6: 1498096 | M6: 0 | N6: 806948
B7: Hydrocarbon Gas Liquids | C7: 2577038 | D7: -176427 | E7: -8484 | F7: 212322 | G7: 64641 | I7: - - | J7: 2412 | K7: 237103 | L7: 1060250 | M7: 1369325 | N7: 225710
B8: Natural Gas Liquids | C8: 2577038 | D8: -176427 | E8: -8484 | F8: 122497 | G8: 58699 | I8: - - | J8: 1772 | K8: 237103 | L8: 1060250 | M8: 1274198 | N8: 223701
B9: Ethane | C9: 1049589 | E9: - - | F9: 3305 | G9: - | I9: - - | J9: 5808 | L9: 178192 | M9: 868894 | N9: 71604
B10: Propane | C10: 798376 | D10: -269 | E10: - - | F10: 99800 | G10: 39610 | I10: - - | J10: 1009 | L10: 646618 | M10: 289890 | N10: 80649
B11: Normal Butane | C11: 246951 | D11: -5230 | E11: -- | F11: 25022 | G11: 15813 | I11: - - | J11: -2765 | K11: 62427 | L11: 179465 | M11: 43429 | N11: 36191
B12: Isobutane | C12: 170999 | D12: -1998 | E12: -- | F12: -5630 | G12: 3233 | I12: - - | J12: 1530 | K12: 91853 | L12: 1235 | M12: 71986 | N12: 12235
B13: Natural Gasoline | C13: 311123 | D13: -168930 | E13: -8484 | G13: 43 | I13: - - | J13: -3810 | K13: 82823 | L13: 54739 | M13: 0 | N13: 23022
B14: Condensate and Scrubber Oil | C14: 54857 | D14: -54860 | I14: - - | J14: -3 | M14: 0 | N14: 28
B15: Refinery Olefins | C15: - - | E15: - - | F15: 89825 | G15: 5942 | I15: - - | J15: 640 | K15: - - | L15: - - | M15: 95127 | N15: 2009
B16: Ethylene | C16: - - | E16: - - | F16: -6109 | G16: - | I16: - - | J16: 0 | K16: - - | L16: - - | M16: -6109 | N16: 0
B17: Propylene | C17: - - | E17: - - | F17: 96276 | G17: 5442 | I17: - - | J17: 466 | K17: - - | L17: - - | M17: 101252 | N17: 1375
B18: Normal Butylene | C18: - - | E18: - - | F18: -693 | G18: 500 | I18: - - | J18: 124 | K18: - - | L18: - - | M18: -317 | N18: 573
B19: Isobutylene | C19: - - | E19: - - | F19: 351 | G19: 7 | I19: - - | J19: 50 | K19: - - | L19: - - | M19: 301 | N19: 61
B20: Other Liquids | C20: - - | D20: -47500 | E20: 510454 | F20: - - | G20: 390451 | I20: 72862 | J20: -5840 | K20: 615914 | L20: 196936 | M20: 119257 | N20: 333975
B21: Hydrogen/Oxygenates/Renewables/Other Hydrocarbons | C21: - - | E21: 510459 | F21: - - | G21: 22625 | I21: 69549 | J21: 1891 | K21: 430753 | L21: 50526 | M21: 119462 | N21: 35008
B22: Hydrogen | C22: - - | E22: - - | F22: - - | I22: 80466 | J22: - - | K22: 80466 | M22: 0 | N22: - -
B23: Oxygenates (excl. Fuel Ethanol) | C23: - - | E23: -- | F23: - - | G23: -- | I23: -- | J23: -- | K23: -- | L23: -- | M23: - | N23: --
B24: Biofuels (incl. Fuel Ethanol) | C24: - - | E24: 510459 | F24: - - | G24: 22625 | I24: -11037 | J24: 1889 | K24: 350169 | L24: 50526 | M24: 119462 | N24: 34993
B25: Fuel Ethanol | C25: - - | E25: 386316 | F25: - - | G25: - | I25: -11037 | J25: 920 | K25: 328136 | L25: 46223 | M25: 0 | N25: 24418
B26: Biofuels (excl. Fuel Ethanol) | C26: - - | E26: 124142 | F26: - - | G26: 22625 | I26: -- | J26: 969 | K26: 22033 | L26: 4303 | M26: 119462 | N26: 10575
B27: Biodiesel | C27: - - | E27: 39795 | F27: - - | G27: 10231 | I27: - | J27: -258 | K27: 16089 | L27: 4303 | M27: 29893 | N27: 3555
B28: Renewable Diesel Fuel | C28: - - | E28: 76054 | F28: - - | G28: 12394 | I28: - | J28: 1053 | K28: 4037 | L28: NA | M28: 83358 | N28: 6531
B29: Other Biofuels | C29: - - | E29: 8293 | F29: - - | G29: - | I29: - | J29: 174 | K29: 1907 | L29: NA | M29: 6211 | N29: 489
B30: Other Hydrocarbons | C30: - - | E30: - - | F30: - - | G30: - | I30: 120 | J30: 2 | K30: 118 | M30: 0 | N30: 15
B31: Unfinished Oils | C31: - - | D31: -47500 | E31: - - | F31: - - | G31: 163638 | I31: - - | J31: -7656 | K31: 5556 | L31: 118238 | M31: 0 | N31: 76522
B32: Motor Gasoline Blend. Comp. | C32: - - | E32: -5 | F32: - - | G32: 204188 | I32: 3314 | J32: -85 | K32: 179410 | L32: 28172 | M32: 0 | N32: 222405
B33: Reformulated | C33: - - | E33: -1 | F33: - - | G33: 56108 | I33: 132745 | J33: 1456 | K33: 187319 | L33: 77 | M33: 0 | N33: 51987
B34: Conventional | C34: - - | E34: -5 | F34: - - | G34: 148080 | I34: -129431 | J34: -1541 | K34: -7909 | L34: 28095 | M34: 0 | N34: 170417
B35: Aviation Gasoline Blend. Comp. | C35: - - | E35: - - | F35: - - | G35: - | I35: - - | J35: 10 | K35: 195 | L35: - | M35: -205 | N35: 40
B36: Finished Petroleum Products | C36: - - | E36: 2711 | F36: 6934051 | G36: 221963 | I36: 7724 | J36: 1262 | K36: - - | L36: 1164048 | M36: 6001139 | N36: 263076
B37: Finished Motor Gasoline | C37: - - | E37: 2423 | F37: 3520823 | G37: 39911 | I37: 7724 | J37: -2415 | K37: - - | L37: 291546 | M37: 3281750 | N37: 15812
B38: Reformulated | C38: - - | F38: 1112341 | G38: - | I38: -99601 | J38: -1 | K38: - - | L38: - | M38: 1012741 | N38: 21
B39: Conventional | C39: - - | E39: 2423 | F39: 2408482 | G39: 39911 | I39: 107325 | J39: -2414 | K39: - - | L39: 291546 | M39: 2269009 | N39: 15791
B40: Finished Aviation Gasoline | C40: - - | E40: - - | F40: 4448 | G40: 322 | I40: - - | J40: 259 | K40: - - | L40: - | M40: 4511 | N40: 1460
B41: Kerosene-Type Jet Fuel | C41: - - | E41: 303 | F41: 660696 | G41: 38442 | I41: - - | J41: 3934 | K41: - - | L41: 76907 | M41: 618600 | N41: 43711
B42: Kerosene | C42: - - | E42: -- | F42: 4539 | G42: 15 | I42: - - | J42: -157 | K42: - - | L42: 1953 | M42: 2758 | N42: 1781
B43: Distillate Fuel Oil | C43: - - | E43: -15 | F43: 1806606 | G43: 53868 | I43: -- | J43: -65 | K43: - - | L43: 472631 | M43: 1387893 | N43: 130421
B44: 15 ppm Sulfur and Under | C44: - - | E44: -14 | F44: 1744279 | G44: 52436 | I44: -- | J44: -1683 | K44: - - | L44: 413451 | M44: 1384933 | N44: 120526
B45: Greater than 15 to 500 ppm Sulfur | C45: - - | E45: 0 | F45: 35948 | G45: 428 | I45: -- | J45: 376 | K45: - - | L45: 33888 | M45: 2112 | N45: 2798
B46: Greater than 500 ppm Sulfur | C46: - - | E46: -- | F46: 26379 | G46: 1004 | I46: - - | J46: 1242 | K46: - - | L46: 25292 | M46: 849 | N46: 7097
B47: Residual Fuel Oil | C47: - - | D47: - - | E47: - - | F47: 115747 | G47: 40046 | I47: - - | J47: -1353 | K47: - - | L47: 50003 | M47: 107143 | N47: 22741
B48: Less than 0.31% Sulfur | C48: - - | D48: - - | E48: - - | F48: 15982 | G48: 2954 | I48: - - | J48: -337 | K48: - - | L48: NA | M48: NA | N48: 2105
B49: 0.31 to 1.00% Sulfur | C49: - - | D49: - - | E49: - - | F49: 31568 | G49: 5545 | I49: - - | J49: -166 | K49: - - | L49: NA | M49: NA | N49: 5549
B50: Greater than 1.00% Sulfur | C50: - - | D50: - - | E50: - - | F50: 68197 | G50: 31547 | I50: - - | J50: -850 | K50: - - | L50: NA | M50: NA | N50: 15087
B51: Petrochemical Feedstocks | C51: - - | D51: - - | E51: - - | F51: 73866 | G51: 4762 | I51: - - | J51: 7 | K51: - - | L51: 3638 | M51: 74983 | N51: 2624
B52: Naphtha for Petro. Feed. Use | C52: - - | D52: - - | E52: - - | F52: 45038 | G52: 3556 | I52: - - | J52: -23 | K52: - - | L52: - | M52: 48617 | N52: 1820
B53: Other Oils for Petro. Feed. Use | C53: - - | D53: - - | E53: - - | F53: 28828 | G53: 1206 | I53: - - | J53: 30 | K53: - - | L53: 3638 | M53: 26366 | N53: 804
B54: Special Naphthas | C54: - - | D54: - - | E54: - - | F54: 10700 | G54: 4203 | I54: - - | J54: 32 | K54: - - | L54: - | M54: 14871 | N54: 1161
B55: Lubricants | C55: - - | D55: - - | E55: - - | F55: 58879 | G55: 16113 | I55: - - | J55: 215 | K55: - - | L55: 45968 | M55: 28809 | N55: 12316
B56: Waxes | C56: - - | D56: - - | E56: - - | F56: 2159 | G56: 1359 | I56: - - | J56: -34 | K56: - - | L56: 1543 | M56: 2009 | N56: 622
B57: Petroleum Coke | C57: - - | D57: - - | E57: - - | F57: 287967 | G57: 2730 | I57: - - | J57: -979 | K57: - - | L57: 211131 | M57: 80545 | N57: 4943
B58: Marketable | C58: - - | D58: - - | E58: - - | F58: 217127 | G58: 2730 | I58: - - | J58: -979 | K58: - - | L58: 211131 | M58: 9705 | N58: 4943
B59: Catalyst | C59: - - | D59: - - | E59: - - | F59: 70840 | G59: - - | H59: - - | I59: - - | J59: - - | K59: - - | L59: - - | M59: 70840 | N59: - -
B60: Asphalt and Road Oil | C60: - - | D60: - - | E60: - - | F60: 123534 | G60: 20192 | I60: - - | J60: 1723 | K60: - - | L60: 8143 | M60: 133860 | N60: 24474
B61: Still Gas | C61: - - | D61: - - | E61: - - | F61: 233635 | G61: - - | H61: - - | I61: - - | J61: - - | K61: - - | L61: - - | M61: 233635 | N61: - -
B62: Miscellaneous Products | C62: - - | D62: - - | E62: - - | F62: 30452 | G62: - | I62: - - | J62: 94 | K62: - - | L62: 586 | M62: 29772 | N62: 1010

Sheet Biomass Data
A2: Table 8. Export sales and average price of densified biomass fuel, 2020
A3: Month | B3: Quantity (tons) | C3: Average Price (USD per ton)
A4: 1 | B4: 516492 | C4: 167.75
A5: 2 | B5: 749693 | C5: 163.39
A6: 3 | B6: 828225 | C6: 167.92
A7: 4 | B7: 714829 | C7: 164.43
A8: 5 | B8: 747809 | C8: 166.38
A9: 6 | B9: 734710 | C9: 159.44
A10: 7 | B10: 826189 | C10: 159.27
A11: 8 | B11: 739552 | C11: 169.81
A12: 9 | B12: 738479 | C12: 165.88
A13: 10 | B13: 757813 | C13: 166.42
A14: 11 | B14: 738409 | C14: 171.17
A15: 12 | B15: 779012 | C15: 172.44
A17: Total wood pellet production (Table 2)
A18: 13341865 | B18: tons
A20: Total wood pellet exports
A21: =SUM(B4:B15) -> 8871212 | B21: tons
A23: We don't have biomass import data from EIA. Imports are assumed to be negligible.
A25: Total wood pellet imports
A26: 0 | B26: tons

Sheet Uranium, Coal, MSW, Hydrogen
A1: Uranium
B2: Production | C2: Imports | D2: Exports | E2: Demand | F2: Unit
A3: 2024 | B3: =677/1000 -> 0.677 | C3: =E3-B3 -> 55.223 | D3: 0 | E3: 55.9 | F3: million pounds U3O8
A5: Hard Coal and Lignite
A6: 40.016958 | B6: million short tons of lignite produced in 2024 | F6: https://www.eia.gov/coal/annual/pdf/tableES1.pdf
A7: 512.54032 | B7: million short tons of coal produced (of all types) in 2024 | F7: https://www.eia.gov/coal/data/browser/
A8: 108.32638 | B8: million short tons of coal exported in 2024 | F8: https://www.eia.gov/coal/data/browser/#/topic/41?agg=0,2,1&rank=g&freq=A&start=2001&end=2024&ctype=map&ltype=pin&rtype=s&maptype=0&rse=0&pin=
A9: 1.997711 | B9: million short tons of coal imported in 2024 | F9: https://www.eia.gov/coal/data/browser/#/topic/39?agg=2,1,0&rank=ok&map=COAL.EXPORT_QTY.TOT-TOT-TOT.A&freq=A&start=2001&end=2024&ctype=map&ltype=pin&rtype=s&pin=&rse=0&maptype=0
A10: We assume that all imported and exported coal was hard coal, while all lignite produced was used domestically.
B12: Production | C12: Imports | D12: Exports | E12: Unit
A13: Hard Coal | B13: =A7*(1-A6/A7) -> 472.52337 | C13: =A9 -> 1.997711 | D13: =A8 -> 108.32638 | E13: million short tons
A14: Lignite | B14: =A6 -> 40.016958 | C14: 0 | D14: 0 | E14: million short tons
A16: Municipal Solid Waste
A17: MSW Tonnage Data for Year 2015
A18: 292 | B18: U.S. MSW generated (million tons)
A20: Although the U.S. exports waste to other countries,
A21: it is difficult to find statistics for waste exports other than plastic waste.
A22: (Plastic waste exports to other countries in 2018 were
A23: 1.07 million metric tons in 2018.) | D23: https://www.plasticpollutioncoalition.org/pft/2019/3/6/157000-shipping-containers-of-us-plastic-waste-exported-to-countries-with-poor-waste-management-in-2018
A26: In this model, we are only concerned about MSW that is burned as a
A27: fuel. We will assume that a negligible amount of exported waste
A28: is used as a fuel.
A30: Hydrogen
A31: =5.51+0.23 -> 5.74 | B31: million metric tons
A32: produced in 2024 (NOT including byproduct hydrogen)
A34: We assume none was imported or exported.

Sheet AEO Conversion Factors
B1: ref2023.d020623a | C1: 2022 | D1: 2023 | E1: 2024 | F1: 2025 | G1: 2026 | H1: 2027 | I1: 2028 | J1: 2029 | K1: 2030 | L1: 2031 | M1: 2032 | N1: 2033 | O1: 2034 | P1: 2035 | Q1: 2036 | R1: 2037 | S1: 2038 | T1: 2039 | U1: 2040 | V1: 2041 | W1: 2042 | X1: 2043 | Y1: 2044 | Z1: 2045 | AA1: 2046 | AB1: 2047 | AC1: 2048 | AD1: 2049 | AE1: 2050
C3: Report | D3: Annual Energy Outlook 2023
C4: Scenario | D4: ref2023 | G4: Reference
C5: Datekey | D5: d020623a
C6: Release Date | E6: March 2023
A10: CNV000:convert_cbob | B10: 68. Conversion Factors | AF10: Annual
A11: CNV000:convert_rbob | B11: (from physical units to million Btu) | AF11: Change
A12: CNV000:aa_PentanesPlus | AF12: 2022–2050
A13: CNV000:aa_OtherPetroleu | C13: 2022 | D13: 2023 | E13: 2024 | F13: 2025 | G13: 2026 | H13: 2027 | I13: 2028 | J13: 2029 | K13: 2030 | L13: 2031 | M13: 2032 | N13: 2033 | O13: 2034 | P13: 2035 | Q13: 2036 | R13: 2037 | S13: 2038 | T13: 2039 | U13: 2040 | V13: 2041 | W13: 2042 | X13: 2043 | Y13: 2044 | Z13: 2045 | AA13: 2046 | AB13: 2047 | AC13: 2048 | AD13: 2049 | AE13: 2050 | AF13: 2050
A14: CNV000:aa_PetrochemFeed | B14: Petroleum and Other Liquids
A15: CNV000:aa_PetroleumCoke | B15: (million Btu per barrel)
A16: CNV000:aa_ResidualFuel | B16: Asphalt and Road Oil | C16: 6.636 | D16: 6.636 | E16: 6.636 | F16: 6.636 | G16: 6.636 | H16: 6.636 | I16: 6.636 | J16: 6.636 | K16: 6.636 | L16: 6.636 | M16: 6.636 | N16: 6.636 | O16: 6.636 | P16: 6.636 | Q16: 6.636 | R16: 6.636 | S16: 6.636 | T16: 6.636 | U16: 6.636 | V16: 6.636 | W16: 6.636 | X16: 6.636 | Y16: 6.636 | Z16: 6.636 | AA16: 6.636 | AB16: 6.636 | AC16: 6.636 | AD16: 6.636 | AE16: 6.636 | AF16: 0
A17: CNV000:aa_StillGas | B17: Aviation Gasoline | C17: 5.048 | D17: 5.048 | E17: 5.048 | F17: 5.048 | G17: 5.048 | H17: 5.048 | I17: 5.048 | J17: 5.048 | K17: 5.048 | L17: 5.048 | M17: 5.048 | N17: 5.048 | O17: 5.048 | P17: 5.048 | Q17: 5.048 | R17: 5.048 | S17: 5.048 | T17: 5.048 | U17: 5.048 | V17: 5.048 | W17: 5.048 | X17: 5.048 | Y17: 5.048 | Z17: 5.048 | AA17: 5.048 | AB17: 5.048 | AC17: 5.048 | AD17: 5.048 | AE17: 5.048 | AF17: 0
A18: CNV000:aa_UnfinishOilIm | B18: Biodiesel | C18: 5.359 | D18: 5.359 | E18: 5.359 | F18: 5.359 | G18: 5.359 | H18: 5.359 | I18: 5.359 | J18: 5.359 | K18: 5.359 | L18: 5.359 | M18: 5.359 | N18: 5.359 | O18: 5.359 | P18: 5.359 | Q18: 5.359 | R18: 5.359 | S18: 5.359 | T18: 5.359 | U18: 5.359 | V18: 5.359 | W18: 5.359 | X18: 5.359 | Y18: 5.359 | Z18: 5.359 | AA18: 5.359 | AB18: 5.359 | AC18: 5.359 | AD18: 5.359 | AE18: 5.359 | AF18: 0
A19: CNV000:aa_TotalPetroleu | B19: Distillate Fuel Oil | C19: 5.825 | D19: 5.825 | E19: 5.825 | F19: 5.825 | G19: 5.825 | H19: 5.825 | I19: 5.825 | J19: 5.825 | K19: 5.825 | L19: 5.825 | M19: 5.825 | N19: 5.825 | O19: 5.825 | P19: 5.825 | Q19: 5.825 | R19: 5.825 | S19: 5.825 | T19: 5.825 | U19: 5.825 | V19: 5.825 | W19: 5.825 | X19: 5.825 | Y19: 5.825 | Z19: 5.825 | AA19: 5.825 | AB19: 5.825 | AC19: 5.825 | AD19: 5.825 | AE19: 5.825 | AF19: 0
A20: CNV000:aa_Imports | B20: Residential | C20: 5.775621 | D20: 5.775648 | E20: 5.776083 | F20: 5.776062 | G20: 5.776467 | H20: 5.777218 | I20: 5.776948 | J20: 5.776953 | K20: 5.776798 | L20: 5.776974 | M20: 5.776898 | N20: 5.77701 | O20: 5.776805 | P20: 5.776956 | Q20: 5.776839 | R20: 5.776862 | S20: 5.776748 | T20: 5.776711 | U20: 5.776654 | V20: 5.776614 | W20: 5.776632 | X20: 5.776631 | Y20: 5.776552 | Z20: 5.776594 | AA20: 5.776409 | AB20: 5.776283 | AC20: 5.77638 | AD20: 5.776386 | AE20: 5.776234 | AF20: 4e-06
A21: CNV000:aa_Exports | B21: Commercial | C21: 5.775621 | D21: 5.775648 | E21: 5.776083 | F21: 5.776062 | G21: 5.776467 | H21: 5.777218 | I21: 5.776948 | J21: 5.776953 | K21: 5.776798 | L21: 5.776974 | M21: 5.776898 | N21: 5.77701 | O21: 5.776805 | P21: 5.776956 | Q21: 5.776839 | R21: 5.776862 | S21: 5.776748 | T21: 5.776711 | U21: 5.776654 | V21: 5.776614 | W21: 5.776632 | X21: 5.776631 | Y21: 5.776552 | Z21: 5.776594 | AA21: 5.776409 | AB21: 5.776283 | AC21: 5.77638 | AD21: 5.776386 | AE21: 5.776234 | AF21: 4e-06
B22: Transportation | C22: 5.775621 | D22: 5.775648 | E22: 5.776083 | F22: 5.776062 | G22: 5.776467 | H22: 5.777218 | I22: 5.776948 | J22: 5.776953 | K22: 5.776798 | L22: 5.776974 | M22: 5.776898 | N22: 5.77701 | O22: 5.776805 | P22: 5.776956 | Q22: 5.776839 | R22: 5.776862 | S22: 5.776748 | T22: 5.776711 | U22: 5.776654 | V22: 5.776614 | W22: 5.776632 | X22: 5.776631 | Y22: 5.776552 | Z22: 5.776594 | AA22: 5.776409 | AB22: 5.776283 | AC22: 5.77638 | AD22: 5.776386 | AE22: 5.776234 | AF22: 4e-06
A23: CNV000:aa_CrudeOilProdu | B23: Industrial | C23: 5.775621 | D23: 5.775648 | E23: 5.776083 | F23: 5.776062 | G23: 5.776467 | H23: 5.777218 | I23: 5.776948 | J23: 5.776953 | K23: 5.776798 | L23: 5.776974 | M23: 5.776898 | N23: 5.77701 | O23: 5.776805 | P23: 5.776956 | Q23: 5.776839 | R23: 5.776862 | S23: 5.776748 | T23: 5.776711 | U23: 5.776654 | V23: 5.776614 | W23: 5.776632 | X23: 5.776631 | Y23: 5.776552 | Z23: 5.776594 | AA23: 5.776409 | AB23: 5.776283 | AC23: 5.77638 | AD23: 5.776386 | AE23: 5.776234 | AF23: 4e-06
A24: CNV000:aa_CrudeOilImpor | B24: Electric Power | C24: 5.775621 | D24: 5.775648 | E24: 5.776083 | F24: 5.776062 | G24: 5.776467 | H24: 5.777218 | I24: 5.776948 | J24: 5.776953 | K24: 5.776798 | L24: 5.776974 | M24: 5.776898 | N24: 5.77701 | O24: 5.776805 | P24: 5.776956 | Q24: 5.776839 | R24: 5.776862 | S24: 5.776748 | T24: 5.776711 | U24: 5.776654 | V24: 5.776614 | W24: 5.776632 | X24: 5.776631 | Y24: 5.776552 | Z24: 5.776594 | AA24: 5.776409 | AB24: 5.776283 | AC24: 5.77638 | AD24: 5.776386 | AE24: 5.776234 | AF24: 4e-06
A25: CNV000:aa_CrudeOilExpor | B25: Total Distillate | C25: 5.775621 | D25: 5.775648 | E25: 5.776083 | F25: 5.776062 | G25: 5.776467 | H25: 5.777218 | I25: 5.776948 | J25: 5.776953 | K25: 5.776799 | L25: 5.776974 | M25: 5.776899 | N25: 5.77701 | O25: 5.776805 | P25: 5.776956 | Q25: 5.776838 | R25: 5.776862 | S25: 5.776748 | T25: 5.776711 | U25: 5.776654 | V25: 5.776614 | W25: 5.776632 | X25: 5.776631 | Y25: 5.776552 | Z25: 5.776594 | AA25: 5.776409 | AB25: 5.776284 | AC25: 5.77638 | AD25: 5.776386 | AE25: 5.776234 | AF25: 4e-06
A26: CNV000:aa_NaturalGasPla | B26: Distillate Fuel Oil - Low Sulfur Diesel | C26: 5.817 | D26: 5.817 | E26: 5.817 | F26: 5.817 | G26: 5.817 | H26: 5.817 | I26: 5.817 | J26: 5.817 | K26: 5.817 | L26: 5.817 | M26: 5.817 | N26: 5.817 | O26: 5.817 | P26: 5.817 | Q26: 5.817 | R26: 5.817 | S26: 5.817 | T26: 5.817 | U26: 5.817 | V26: 5.817 | W26: 5.817 | X26: 5.817 | Y26: 5.817 | Z26: 5.817 | AA26: 5.817 | AB26: 5.817 | AC26: 5.817 | AD26: 5.817 | AE26: 5.817 | AF26: 0
B27: Distillate Fuel Oil - Ultra Low Sulfur Diesel | C27: 5.77 | D27: 5.77 | E27: 5.77 | F27: 5.77 | G27: 5.77 | H27: 5.77 | I27: 5.77 | J27: 5.77 | K27: 5.77 | L27: 5.77 | M27: 5.77 | N27: 5.77 | O27: 5.77 | P27: 5.77 | Q27: 5.77 | R27: 5.77 | S27: 5.77 | T27: 5.77 | U27: 5.77 | V27: 5.77 | W27: 5.77 | X27: 5.77 | Y27: 5.77 | Z27: 5.77 | AA27: 5.77 | AB27: 5.77 | AC27: 5.77 | AD27: 5.77 | AE27: 5.77 | AF27: 0
B28: Ethanol including denaturant | C28: 3.563 | D28: 3.563 | E28: 3.563 | F28: 3.563 | G28: 3.563 | H28: 3.563 | I28: 3.563 | J28: 3.563 | K28: 3.563 | L28: 3.563 | M28: 3.563 | N28: 3.563 | O28: 3.563 | P28: 3.563 | Q28: 3.563 | R28: 3.563 | S28: 3.563 | T28: 3.563 | U28: 3.563 | V28: 3.563 | W28: 3.563 | X28: 3.563 | Y28: 3.563 | Z28: 3.563 | AA28: 3.563 | AB28: 3.563 | AC28: 3.563 | AD28: 3.563 | AE28: 3.563 | AF28: 0
A29: CNV000:ba_Consumption | B29: E85 1/ | C29: 3.994413 | D29: 3.994413 | E29: 3.994413 | F29: 3.994413 | G29: 3.994413 | H29: 3.994413 | I29: 3.994413 | J29: 3.994413 | K29: 3.994413 | L29: 3.994413 | M29: 3.994413 | N29: 3.994413 | O29: 3.994413 | P29: 3.994413 | Q29: 3.994413 | R29: 3.994413 | S29: 3.994413 | T29: 3.994413 | U29: 3.994413 | V29: 3.994413 | W29: 3.994413 | X29: 3.994413 | Y29: 3.994413 | Z29: 3.994413 | AA29: 3.994413 | AB29: 3.994413 | AC29: 3.994413 | AD29: 3.994413 | AE29: 3.994413 | AF29: 0
A30: CNV000:ba_Utility | B30: Jet Fuel - Kerosene | C30: 5.67 | D30: 5.67 | E30: 5.67 | F30: 5.67 | G30: 5.67 | H30: 5.67 | I30: 5.67 | J30: 5.67 | K30: 5.67 | L30: 5.67 | M30: 5.67 | N30: 5.67 | O30: 5.67 | P30: 5.67 | Q30: 5.67 | R30: 5.67 | S30: 5.67 | T30: 5.67 | U30: 5.67 | V30: 5.67 | W30: 5.67 | X30: 5.67 | Y30: 5.67 | Z30: 5.67 | AA30: 5.67 | AB30: 5.67 | AC30: 5.67 | AD30: 5.67 | AE30: 5.67 | AF30: 0
A31: CNV000:ba_Nonutility | B31: Lubricants | C31: 6.065 | D31: 6.065 | E31: 6.065 | F31: 6.065 | G31: 6.065 | H31: 6.065 | I31: 6.065 | J31: 6.065 | K31: 6.065 | L31: 6.065 | M31: 6.065 | N31: 6.065 | O31: 6.065 | P31: 6.065 | Q31: 6.065 | R31: 6.065 | S31: 6.065 | T31: 6.065 | U31: 6.065 | V31: 6.065 | W31: 6.065 | X31: 6.065 | Y31: 6.065 | Z31: 6.065 | AA31: 6.065 | AB31: 6.065 | AC31: 6.065 | AD31: 6.065 | AE31: 6.065 | AF31: 0
A32: CNV000:ba_Production | B32: Motor Gasoline Average | C32: 5.051711 | D32: 5.050536 | E32: 5.049363 | F32: 5.048181 | G32: 5.046995 | H32: 5.045806 | I32: 5.044614 | J32: 5.043417 | K32: 5.042216 | L32: 5.041012 | M32: 5.039805 | N32: 5.038594 | O32: 5.037381 | P32: 5.036164 | Q32: 5.03513 | R32: 5.034097 | S32: 5.033101 | T32: 5.032113 | U32: 5.031125 | V32: 5.030226 | W32: 5.029317 | X32: 5.028415 | Y32: 5.02752 | Z32: 5.02663 | AA32: 5.025746 | AB32: 5.024862 | AC32: 5.023974 | AD32: 5.023084 | AE32: 5.0222 | AF32: -0.000209
A33: CNV000:ba_Imports | B33: Conventional Motor Gasoline | C33: 5.051239 | D33: 5.049952 | E33: 5.048665 | F33: 5.047375 | G33: 5.046085 | H33: 5.044794 | I33: 5.043502 | J33: 5.042209 | K33: 5.040914 | L33: 5.039618 | M33: 5.038322 | N33: 5.037026 | O33: 5.03573 | P33: 5.034434 | Q33: 5.033323 | R33: 5.032218 | S33: 5.03115 | T33: 5.030091 | U33: 5.029032 | V33: 5.028083 | W33: 5.027124 | X33: 5.026171 | Y33: 5.025226 | Z33: 5.024285 | AA33: 5.023351 | AB33: 5.022417 | AC33: 5.021479 | AD33: 5.020539 | AE33: 5.019606 | AF33: -0.000224
A34: CNV000:ba_Exports | B34: Reformulated Motor Gasoline | C34: 5.050956 | D34: 5.04961 | E34: 5.048264 | F34: 5.046918 | G34: 5.045574 | H34: 5.04423 | I34: 5.042888 | J34: 5.041545 | K34: 5.040203 | L34: 5.038862 | M34: 5.037521 | N34: 5.036182 | O34: 5.034844 | P34: 5.033506 | Q34: 5.032413 | R34: 5.031326 | S34: 5.030284 | T34: 5.029252 | U34: 5.028219 | V34: 5.027245 | W34: 5.026256 | X34: 5.025273 | Y34: 5.024298 | Z34: 5.023329 | AA34: 5.022367 | AB34: 5.021404 | AC34: 5.020434 | AD34: 5.019461 | AE34: 5.018494 | AF34: -0.00023
A35: CNV000:ba_CompressedNat | B35: Conventional before Blending | C35: 5.22228 | D35: 5.22228 | E35: 5.22228 | F35: 5.22228 | G35: 5.22228 | H35: 5.22228 | I35: 5.22228 | J35: 5.22228 | K35: 5.22228 | L35: 5.22228 | M35: 5.22228 | N35: 5.22228 | O35: 5.22228 | P35: 5.22228 | Q35: 5.22228 | R35: 5.22228 | S35: 5.22228 | T35: 5.22228 | U35: 5.22228 | V35: 5.22228 | W35: 5.22228 | X35: 5.22228 | Y35: 5.22228 | Z35: 5.22228 | AA35: 5.22228 | AB35: 5.22228 | AC35: 5.22228 | AD35: 5.22228 | AE35: 5.22228 | AF35: 0
B36: Reformulated before Blending | C36: 5.22228 | D36: 5.22228 | E36: 5.22228 | F36: 5.22228 | G36: 5.22228 | H36: 5.22228 | I36: 5.22228 | J36: 5.22228 | K36: 5.22228 | L36: 5.22228 | M36: 5.22228 | N36: 5.22228 | O36: 5.22228 | P36: 5.22228 | Q36: 5.22228 | R36: 5.22228 | S36: 5.22228 | T36: 5.22228 | U36: 5.22228 | V36: 5.22228 | W36: 5.22228 | X36: 5.22228 | Y36: 5.22228 | Z36: 5.22228 | AA36: 5.22228 | AB36: 5.22228 | AC36: 5.22228 | AD36: 5.22228 | AE36: 5.22228 | AF36: 0
B37: Natural Gasoline | C37: 4.638 | D37: 4.638 | E37: 4.638 | F37: 4.638 | G37: 4.638 | H37: 4.638 | I37: 4.638 | J37: 4.638 | K37: 4.638 | L37: 4.638 | M37: 4.638 | N37: 4.638 | O37: 4.638 | P37: 4.638 | Q37: 4.638 | R37: 4.638 | S37: 4.638 | T37: 4.638 | U37: 4.638 | V37: 4.638 | W37: 4.638 | X37: 4.638 | Y37: 4.638 | Z37: 4.638 | AA37: 4.638 | AB37: 4.638 | AC37: 4.638 | AD37: 4.638 | AE37: 4.638 | AF37: 0
A38: CNV000:ca_Production | B38: Other Petroleum | C38: 5.8 | D38: 5.8 | E38: 5.8 | F38: 5.8 | G38: 5.8 | H38: 5.8 | I38: 5.8 | J38: 5.8 | K38: 5.8 | L38: 5.8 | M38: 5.8 | N38: 5.8 | O38: 5.8 | P38: 5.8 | Q38: 5.8 | R38: 5.8 | S38: 5.8 | T38: 5.8 | U38: 5.8 | V38: 5.8 | W38: 5.8 | X38: 5.8 | Y38: 5.8 | Z38: 5.8 | AA38: 5.8 | AB38: 5.8 | AC38: 5.8 | AD38: 5.8 | AE38: 5.8 | AF38: 0
A39: CNV000:ca_EastoftheMiss | B39: Petrochemical Feedstocks | C39: 5.448283 | D39: 5.448283 | E39: 5.448283 | F39: 5.448283 | G39: 5.448283 | H39: 5.448283 | I39: 5.448283 | J39: 5.448283 | K39: 5.448283 | L39: 5.448283 | M39: 5.448283 | N39: 5.448283 | O39: 5.448283 | P39: 5.448283 | Q39: 5.448283 | R39: 5.448283 | S39: 5.448283 | T39: 5.448283 | U39: 5.448283 | V39: 5.448283 | W39: 5.448283 | X39: 5.448283 | Y39: 5.448283 | Z39: 5.448283 | AA39: 5.448283 | AB39: 5.448283 | AC39: 5.448283 | AD39: 5.448283 | AE39: 5.448283 | AF39: 0
A40: CNV000:ca_WestoftheMiss | B40: Petroleum Coke | C40: 6.287 | D40: 6.287 | E40: 6.287 | F40: 6.287 | G40: 6.287 | H40: 6.287 | I40: 6.287 | J40: 6.287 | K40: 6.287 | L40: 6.287 | M40: 6.287 | N40: 6.287 | O40: 6.287 | P40: 6.287 | Q40: 6.287 | R40: 6.287 | S40: 6.287 | T40: 6.287 | U40: 6.287 | V40: 6.287 | W40: 6.287 | X40: 6.287 | Y40: 6.287 | Z40: 6.287 | AA40: 6.287 | AB40: 6.287 | AC40: 6.287 | AD40: 6.287 | AE40: 6.287 | AF40: 0
A41: CNV000:ca_Consumption | B41: Residual Fuel | C41: 6.287 | D41: 6.287 | E41: 6.287 | F41: 6.287 | G41: 6.287 | H41: 6.287 | I41: 6.287 | J41: 6.287 | K41: 6.287 | L41: 6.287 | M41: 6.287 | N41: 6.287 | O41: 6.287 | P41: 6.287 | Q41: 6.287 | R41: 6.287 | S41: 6.287 | T41: 6.287 | U41: 6.287 | V41: 6.287 | W41: 6.287 | X41: 6.287 | Y41: 6.287 | Z41: 6.287 | AA41: 6.287 | AB41: 6.287 | AC41: 6.287 | AD41: 6.287 | AE41: 6.287 | AF41: 0
A42: CNV000:ca_Residentialan | B42: Still Gas | C42: 6.287 | D42: 6.287 | E42: 6.287 | F42: 6.287 | G42: 6.287 | H42: 6.287 | I42: 6.287 | J42: 6.287 | K42: 6.287 | L42: 6.287 | M42: 6.287 | N42: 6.287 | O42: 6.287 | P42: 6.287 | Q42: 6.287 | R42: 6.287 | S42: 6.287 | T42: 6.287 | U42: 6.287 | V42: 6.287 | W42: 6.287 | X42: 6.287 | Y42: 6.287 | Z42: 6.287 | AA42: 6.287 | AB42: 6.287 | AC42: 6.287 | AD42: 6.287 | AE42: 6.287 | AF42: 0
A43: CNV000:ca_Industrial | B43: Unfinished Oils | C43: 6.191736 | D43: 6.192239 | E43: 6.193067 | F43: 6.163516 | G43: 6.155307 | H43: 6.161367 | I43: 6.16242 | J43: 6.163478 | K43: 6.164545 | L43: 6.160776 | M43: 6.166696 | N43: 6.167782 | O43: 6.168875 | P43: 6.169975 | Q43: 6.171082 | R43: 6.172197 | S43: 6.173318 | T43: 6.174447 | U43: 6.175582 | V43: 6.176932 | W43: 6.178004 | X43: 6.179245 | Y43: 6.180129 | Z43: 6.181304 | AA43: 6.182486 | AB43: 6.183676 | AC43: 6.184874 | AD43: 6.18608 | AE43: 6.187586 | AF43: -2.4e-05
A44: CNV000:ca_Coking | B44: Total Petroleum Consumption | C44: 5.067464 | D44: 5.059147 | E44: 5.022825 | F44: 5.01719 | G44: 5.000348 | H44: 4.985026 | I44: 4.974782 | J44: 4.967464 | K44: 4.961115 | L44: 4.957813 | M44: 4.952669 | N44: 4.947966 | O44: 4.942125 | P44: 4.937525 | Q44: 4.932009 | R44: 4.929103 | S44: 4.927769 | T44: 4.92266 | U44: 4.920143 | V44: 4.916678 | W44: 4.910859 | X44: 4.90548 | Y44: 4.903147 | Z44: 4.901598 | AA44: 4.899264 | AB44: 4.896852 | AC44: 4.895994 | AD44: 4.893797 | AE44: 4.891023 | AF44: -0.001265
A45: CNV000:ca_ElectricPower | B45: Petroleum Product Imports | C45: 5.892745 | D45: 5.789976 | E45: 5.795176 | F45: 5.783333 | G45: 5.778988 | H45: 5.799472 | I45: 5.80944 | J45: 5.820918 | K45: 5.826458 | L45: 5.833271 | M45: 5.836474 | N45: 5.845973 | O45: 5.848357 | P45: 5.858846 | Q45: 5.855556 | R45: 5.857804 | S45: 5.858994 | T45: 5.86145 | U45: 5.860619 | V45: 5.859704 | W45: 5.858002 | X45: 5.856611 | Y45: 5.854544 | Z45: 5.854034 | AA45: 5.846951 | AB45: 5.844751 | AC45: 5.839046 | AD45: 5.836578 | AE45: 5.833464 | AF45: -0.000361
A46: CNV000:ca_Imports | B46: Petroleum Product Exports | C46: 5.045286 | D46: 5.103044 | E46: 5.064793 | F46: 5.065934 | G46: 5.095077 | H46: 5.175824 | I46: 5.22638 | J46: 5.263233 | K46: 5.273697 | L46: 5.297207 | M46: 5.295012 | N46: 5.294183 | O46: 5.284441 | P46: 5.28901 | Q46: 5.274773 | R46: 5.276637 | S46: 5.279346 | T46: 5.27027 | U46: 5.2766 | V46: 5.276398 | W46: 5.263596 | X46: 5.257178 | Y46: 5.254526 | Z46: 5.25268 | AA46: 5.250132 | AB46: 5.249116 | AC46: 5.250511 | AD46: 5.251673 | AE46: 5.252563 | AF46: 0.001439
A47: CNV000:ca_Exports | B47: Crude Oil
A48: CNV000:ca_CoaltoLiquids | B48: Production | C48: 5.694899 | D48: 5.687719 | E48: 5.684641 | F48: 5.685889 | G48: 5.685311 | H48: 5.685627 | I48: 5.691115 | J48: 5.691816 | K48: 5.692057 | L48: 5.691126 | M48: 5.689834 | N48: 5.688972 | O48: 5.687781 | P48: 5.686316 | Q48: 5.68428 | R48: 5.682676 | S48: 5.680431 | T48: 5.678968 | U48: 5.676489 | V48: 5.672715 | W48: 5.67099 | X48: 5.670876 | Y48: 5.671312 | Z48: 5.670749 | AA48: 5.669248 | AB48: 5.665374 | AC48: 5.668751 | AD48: 5.669958 | AE48: 5.66872 | AF48: -0.000165
A49: CNV000:ca_WasteCoal | B49: Imports | C49: 6.037077 | D49: 5.997051 | E49: 6.035549 | F49: 6.040228 | G49: 6.057789 | H49: 6.049477 | I49: 6.061068 | J49: 6.060353 | K49: 6.06164 | L49: 6.070837 | M49: 6.079952 | N49: 6.078108 | O49: 6.089023 | P49: 6.089758 | Q49: 6.089698 | R49: 6.099061 | S49: 6.098973 | T49: 6.099608 | U49: 6.101254 | V49: 6.098327 | W49: 6.097382 | X49: 6.101766 | Y49: 6.104531 | Z49: 6.105972 | AA49: 6.100702 | AB49: 6.100448 | AC49: 6.09999 | AD49: 6.100516 | AE49: 6.10035 | AF49: 0.000372
B50: Exports | C50: 5.572606 | D50: 5.597443 | E50: 5.595406 | F50: 5.595317 | G50: 5.595244 | H50: 5.595073 | I50: 5.594945 | J50: 5.594821 | K50: 5.594671 | L50: 5.594597 | M50: 5.594531 | N50: 5.59447 | O50: 5.594379 | P50: 5.594272 | Q50: 5.59422 | R50: 5.594141 | S50: 5.594086 | T50: 5.593991 | U50: 5.593964 | V50: 5.593852 | W50: 5.593757 | X50: 5.593641 | Y50: 5.593558 | Z50: 5.59345 | AA50: 5.593437 | AB50: 5.593347 | AC50: 5.594541 | AD50: 5.593982 | AE50: 5.593036 | AF50: 0.000131
B51: Natural Gas Plant Liquids | C51: 3.565097 | D51: 3.554502 | E51: 3.549132 | F51: 3.54179 | G51: 3.539737 | H51: 3.540236 | I51: 3.541674 | J51: 3.54206 | K51: 3.541894 | L51: 3.541105 | M51: 3.540758 | N51: 3.540197 | O51: 3.538921 | P51: 3.537422 | Q51: 3.537616 | R51: 3.538247 | S51: 3.537914 | T51: 3.537523 | U51: 3.53428 | V51: 3.532229 | W51: 3.52957 | X51: 3.528002 | Y51: 3.528308 | Z51: 3.528638 | AA51: 3.52914 | AB51: 3.529557 | AC51: 3.530749 | AD51: 3.531657 | AE51: 3.53116 | AF51: -0.000342
A53: CNV000:da_Electricity | B53: Natural Gas (thousand Btu per cubic foot)
A54: CNV000:fossil_hr_us | B54: Consumption | C54: 1.037 | D54: 1.037 | E54: 1.037 | F54: 1.037 | G54: 1.037 | H54: 1.037 | I54: 1.037 | J54: 1.037 | K54: 1.037 | L54: 1.037 | M54: 1.037 | N54: 1.037 | O54: 1.037 | P54: 1.037 | Q54: 1.037 | R54: 1.037 | S54: 1.037 | T54: 1.037 | U54: 1.037 | V54: 1.037 | W54: 1.037 | X54: 1.037 | Y54: 1.037 | Z54: 1.037 | AA54: 1.037 | AB54: 1.037 | AC54: 1.037 | AD54: 1.037 | AE54: 1.037 | AF54: 0
B55: Electric Power Sector 2/ | C55: 1.034 | D55: 1.034 | E55: 1.034 | F55: 1.034 | G55: 1.034 | H55: 1.034 | I55: 1.034 | J55: 1.034 | K55: 1.034 | L55: 1.034 | M55: 1.034 | N55: 1.034 | O55: 1.034 | P55: 1.034 | Q55: 1.034 | R55: 1.034 | S55: 1.034 | T55: 1.034 | U55: 1.034 | V55: 1.034 | W55: 1.034 | X55: 1.034 | Y55: 1.034 | Z55: 1.034 | AA55: 1.034 | AB55: 1.034 | AC55: 1.034 | AD55: 1.034 | AE55: 1.034 | AF55: 0
B56: End-use Sector | C56: 1.039 | D56: 1.039 | E56: 1.039 | F56: 1.039 | G56: 1.039 | H56: 1.039 | I56: 1.039 | J56: 1.039 | K56: 1.039 | L56: 1.039 | M56: 1.039 | N56: 1.039 | O56: 1.039 | P56: 1.039 | Q56: 1.039 | R56: 1.039 | S56: 1.039 | T56: 1.039 | U56: 1.039 | V56: 1.039 | W56: 1.039 | X56: 1.039 | Y56: 1.039 | Z56: 1.039 | AA56: 1.039 | AB56: 1.039 | AC56: 1.039 | AD56: 1.039 | AE56: 1.039 | AF56: 0
B57: Production | C57: 1.037 | D57: 1.037 | E57: 1.037 | F57: 1.037 | G57: 1.037 | H57: 1.037 | I57: 1.037 | J57: 1.037 | K57: 1.037 | L57: 1.037 | M57: 1.037 | N57: 1.037 | O57: 1.037 | P57: 1.037 | Q57: 1.037 | R57: 1.037 | S57: 1.037 | T57: 1.037 | U57: 1.037 | V57: 1.037 | W57: 1.037 | X57: 1.037 | Y57: 1.037 | Z57: 1.037 | AA57: 1.037 | AB57: 1.037 | AC57: 1.037 | AD57: 1.037 | AE57: 1.037 | AF57: 0
B58: Imports | C58: 1.025 | D58: 1.025 | E58: 1.025 | F58: 1.025 | G58: 1.025 | H58: 1.025 | I58: 1.025 | J58: 1.025 | K58: 1.025 | L58: 1.025 | M58: 1.025 | N58: 1.025 | O58: 1.025 | P58: 1.025 | Q58: 1.025 | R58: 1.025 | S58: 1.025 | T58: 1.025 | U58: 1.025 | V58: 1.025 | W58: 1.025 | X58: 1.025 | Y58: 1.025 | Z58: 1.025 | AA58: 1.025 | AB58: 1.025 | AC58: 1.025 | AD58: 1.025 | AE58: 1.025 | AF58: 0
B59: Exports | C59: 1.009 | D59: 1.009 | E59: 1.009 | F59: 1.009 | G59: 1.009 | H59: 1.009 | I59: 1.009 | J59: 1.009 | K59: 1.009 | L59: 1.009 | M59: 1.009 | N59: 1.009 | O59: 1.009 | P59: 1.009 | Q59: 1.009 | R59: 1.009 | S59: 1.009 | T59: 1.009 | U59: 1.009 | V59: 1.009 | W59: 1.009 | X59: 1.009 | Y59: 1.009 | Z59: 1.009 | AA59: 1.009 | AB59: 1.009 | AC59: 1.009 | AD59: 1.009 | AE59: 1.009 | AF59: 0
B60: Compressed/Liquefied Natural Gas | C60: 0.96 | D60: 0.96 | E60: 0.96 | F60: 0.96 | G60: 0.96 | H60: 0.96 | I60: 0.96 | J60: 0.96 | K60: 0.96 | L60: 0.96 | M60: 0.96 | N60: 0.96 | O60: 0.96 | P60: 0.96 | Q60: 0.96 | R60: 0.96 | S60: 0.96 | T60: 0.96 | U60: 0.96 | V60: 0.96 | W60: 0.96 | X60: 0.96 | Y60: 0.96 | Z60: 0.96 | AA60: 0.96 | AB60: 0.96 | AC60: 0.96 | AD60: 0.96 | AE60: 0.96 | AF60: 0
B62: Coal (million Btu per short ton)
B63: Production | C63: 20.414087 | D63: 20.306387 | E63: 20.561386 | F63: 20.682283 | G63: 21.026535 | H63: 21.446421 | I63: 21.618557 | J63: 21.391855 | K63: 21.480253 | L63: 21.504978 | M63: 21.517519 | N63: 21.584536 | O63: 21.490145 | P63: 21.426874 | Q63: 21.444807 | R63: 21.408159 | S63: 21.737587 | T63: 21.762627 | U63: 21.825102 | V63: 21.77272 | W63: 21.752516 | X63: 21.840578 | Y63: 21.903273 | Z63: 21.967976 | AA63: 22.008549 | AB63: 22.019365 | AC63: 21.979197 | AD63: 22.007912 | AE63: 21.97847 | AF63: 0.002641
B64: East of the Mississippi | C64: 25.150553 | D64: 25.16258 | E64: 25.277229 | F64: 25.196438 | G64: 25.173244 | H64: 25.253006 | I64: 25.375315 | J64: 25.881294 | K64: 25.949392 | L64: 25.919323 | M64: 25.917715 | N64: 26.122444 | O64: 26.104872 | P64: 26.092716 | Q64: 26.109541 | R64: 26.115759 | S64: 26.111366 | T64: 26.064837 | U64: 26.097258 | V64: 26.119198 | W64: 26.115305 | X64: 26.109867 | Y64: 26.134989 | Z64: 26.120363 | AA64: 26.130583 | AB64: 26.147619 | AC64: 26.167906 | AD64: 26.162901 | AE64: 26.183289 | AF64: 0.001438
B65: West of the Mississippi | C65: 17.359545 | D65: 17.333267 | E65: 17.469742 | F65: 17.421644 | G65: 17.439486 | H65: 17.491636 | I65: 17.459488 | J65: 17.634378 | K65: 17.574055 | L65: 17.584854 | M65: 17.592421 | N65: 17.594152 | O65: 17.563728 | P65: 17.529621 | Q65: 17.516928 | R65: 17.304117 | S65: 17.516291 | T65: 17.500505 | U65: 17.477858 | V65: 17.479235 | W65: 17.47102 | X65: 17.484035 | Y65: 17.490488 | Z65: 17.495975 | AA65: 17.492517 | AB65: 17.48987 | AC65: 17.478798 | AD65: 17.460386 | AE65: 17.475588 | AF65: 0.000238
B66: Consumption | C66: 19.658428 | D66: 19.54789 | E66: 19.530924 | F66: 19.656338 | G66: 20.110069 | H66: 20.51845 | I66: 20.575666 | J66: 20.0931 | K66: 19.986597 | L66: 20.045502 | M66: 20.072807 | N66: 20.139336 | O66: 20.012087 | P66: 19.954887 | Q66: 19.927517 | R66: 20.046503 | S66: 20.41361 | T66: 20.439775 | U66: 20.443367 | V66: 20.372391 | W66: 20.360712 | X66: 20.399227 | Y66: 20.438107 | Z66: 20.498695 | AA66: 20.521355 | AB66: 20.524982 | AC66: 20.513655 | AD66: 20.569065 | AE66: 20.506569 | AF66: 0.00151
B67: Commercial and Institutional | C67: 18.006001 | D67: 18.076195 | E67: 18.050531 | F67: 17.893633 | G67: 17.823393 | H67: 17.884933 | I67: 17.960043 | J67: 18.007738 | K67: 18.045809 | L67: 18.149769 | M67: 18.107817 | N67: 18.119068 | O67: 18.106014 | P67: 18.099829 | Q67: 18.068781 | R67: 17.983765 | S67: 17.92384 | T67: 17.901514 | U67: 17.88397 | V67: 17.863047 | W67: 17.841541 | X67: 17.809853 | Y67: 17.789932 | Z67: 17.759554 | AA67: 17.740721 | AB67: 17.717068 | AC67: 17.692871 | AD67: 17.692043 | AE67: 17.690735 | AF67: -0.000631
B68: Industrial 3/ | C68: 18.783617 | D68: 18.841715 | E68: 19.240131 | F68: 19.234219 | G68: 19.213202 | H68: 19.209591 | I68: 19.205172 | J68: 19.192945 | K68: 19.182035 | L68: 19.171402 | M68: 19.160555 | N68: 19.138552 | O68: 19.129539 | P68: 19.110559 | Q68: 19.098141 | R68: 19.08354 | S68: 19.066294 | T68: 19.059637 | U68: 19.057035 | V68: 19.053011 | W68: 19.047277 | X68: 19.039465 | Y68: 19.03443 | Z68: 19.027761 | AA68: 19.017918 | AB68: 19.012091 | AC68: 19.021603 | AD68: 19.003336 | AE68: 18.998146 | AF68: 0.000406
B69: Coking | C69: 28.414658 | D69: 28.420496 | E69: 28.564054 | F69: 28.563307 | G69: 28.564709 | H69: 28.561665 | I69: 28.424852 | J69: 28.42708 | K69: 28.424328 | L69: 28.424635 | M69: 28.425568 | N69: 28.425659 | O69: 28.423475 | P69: 28.424204 | Q69: 28.424822 | R69: 28.423916 | S69: 28.423409 | T69: 28.418621 | U69: 28.418154 | V69: 28.416595 | W69: 28.418688 | X69: 28.417397 | Y69: 28.418079 | Z69: 28.415937 | AA69: 28.41695 | AB69: 28.417501 | AC69: 28.414228 | AD69: 28.414782 | AE69: 28.414515 | AF69: 0
B70: Electric Power 2/ | C70: 19.261753 | D70: 19.094007 | E70: 19.073429 | F70: 19.172199 | G70: 19.601582 | H70: 19.981222 | I70: 19.951309 | J70: 19.245697 | K70: 19.029951 | L70: 19.089005 | M70: 19.111488 | N70: 19.224411 | O70: 19.066448 | P70: 19.00494 | Q70: 18.96826 | R70: 19.093117 | S70: 19.521412 | T70: 19.550014 | U70: 19.53932 | V70: 19.461977 | W70: 19.446018 | X70: 19.485048 | Y70: 19.506826 | Z70: 19.564098 | AA70: 19.57564 | AB70: 19.57551 | AC70: 19.545101 | AD70: 19.618681 | AE70: 19.498875 | AF70: 0.000437
B71: Imports | C71: 23.859665 | D71: 23.823355 | E71: 24.306349 | F71: 24.259813 | G71: 24.157303 | H71: 24.166779 | I71: 24.34152 | J71: 24.34701 | K71: 24.354691 | L71: 24.360081 | M71: 24.36758 | N71: 24.405735 | O71: 24.413681 | P71: 24.419716 | Q71: 24.42701 | R71: 24.434261 | S71: 24.42054 | T71: 24.426121 | U71: 24.427452 | V71: 24.428066 | W71: 24.430658 | X71: 24.43626 | Y71: 24.411711 | Z71: 24.416954 | AA71: 24.419678 | AB71: 24.413704 | AC71: 24.385359 | AD71: 24.329634 | AE71: 24.333668 | AF71: 0.000703
B72: Exports | C72: 25.334827 | D72: 25.104584 | E72: 25.440268 | F72: 25.260695 | G72: 24.183857 | H72: 24.143476 | I72: 24.205839 | J72: 24.216169 | K72: 24.54221 | L72: 24.411135 | M72: 24.344088 | N72: 24.484596 | O72: 24.493073 | P72: 24.428741 | Q72: 24.565546 | R72: 24.314209 | S72: 24.333239 | T72: 24.333513 | U72: 24.421448 | V72: 24.449455 | W72: 24.400551 | X72: 24.57086 | Y72: 24.596798 | Z72: 24.58979 | AA72: 24.643402 | AB72: 24.656141 | AC72: 24.537497 | AD72: 24.472775 | AE72: 24.429749 | AF72: -0.001298
B73: Coal to Liquids | C73: -- | D73: -- | E73: -- | F73: -- | G73: -- | H73: -- | I73: -- | J73: -- | K73: -- | L73: -- | M73: -- | N73: -- | O73: -- | P73: -- | Q73: -- | R73: -- | S73: -- | T73: -- | U73: -- | V73: -- | W73: -- | X73: -- | Y73: -- | Z73: -- | AA73: -- | AB73: -- | AC73: -- | AD73: -- | AE73: -- | AF73: -- | AG73: -- | AH73: -- | AI73: -- | AJ73: -- | AK73: -- | AL73: -- | AM73: -- | AN73: -- | AO73: -- | AP73: -- | AQ73: -- | AR73: -- | AS73: -- | AT73: -- | AU73: -- | AV73: -- | AW73: -- | AX73: -- | AY73: -- | AZ73: -- | BA73: --
B74: Waste Coal | C74: 12.525999 | D74: 12.526001 | E74: 12.525999 | F74: 12.526 | G74: 12.526001 | H74: 12.526 | I74: 12.526 | J74: 12.526001 | K74: 12.526001 | L74: 12.526 | M74: 12.526 | N74: 12.525999 | O74: 12.526 | P74: 12.526 | Q74: 12.526 | R74: 12.526 | S74: 12.526 | T74: 12.526 | U74: 12.526 | V74: 12.526 | W74: 12.525999 | X74: 12.526 | Y74: 12.525999 | Z74: 12.526 | AA74: 12.526001 | AB74: 12.526001 | AC74: 12.525999 | AD74: 12.526001 | AE74: 12.526 | AF74: 0
B76: Approximate Heat Rates and Heat Content
B77: (Btu per kilowatthour)
B78: Electricity Heat Content | C78: 3412 | D78: 3412 | E78: 3412 | F78: 3412 | G78: 3412 | H78: 3412 | I78: 3412 | J78: 3412 | K78: 3412 | L78: 3412 | M78: 3412 | N78: 3412 | O78: 3412 | P78: 3412 | Q78: 3412 | R78: 3412 | S78: 3412 | T78: 3412 | U78: 3412 | V78: 3412 | W78: 3412 | X78: 3412 | Y78: 3412 | Z78: 3412 | AA78: 3412 | AB78: 3412 | AC78: 3412 | AD78: 3412 | AE78: 3412 | AF78: 0
B79: Fossil Fuel Heat Rate | C79: 8704.7637 | D79: 8578.2412 | E79: 8637.2559 | F79: 8588.4531 | G79: 8512.0645 | H79: 8435.9893 | I79: 8346.5156 | J79: 8291.6826 | K79: 8261.0889 | L79: 8271.4092 | M79: 8287.583 | N79: 8311.3779 | O79: 8325.2793 | P79: 8337.6533 | Q79: 8327.502 | R79: 8296.8252 | S79: 8242.873 | T79: 8227.127 | U79: 8192.457 | V79: 8198.7402 | W79: 8188.8389 | X79: 8173.1421 | Y79: 8166.9146 | Z79: 8150.8018 | AA79: 8133.8296 | AB79: 8130.3311 | AC79: 8101.1709 | AD79: 8098.4907 | AE79: 8065.7134 | AF79: -0.002719
B80: 1/ E85 refers to a blend of 85 percent ethanol (renewable) and 15 percent motor gasoline (nonrenewable). To address cold starting issues,
B81: the percentage of ethanol varies seasonally. The annual average ethanol content of 74% is used for these projections.
B82: 2/ Includes all electricity-only and combined-heat-and-power plants that have a regulatory status.
B83: 3/ Includes combined-heat-and-power plants that have a non-regulatory status and small on-site generating systems.
B84: Btu = British Thermal Unit.
B85: - - = Not applicable.
B86: Data source: 2022: U.S. Energy Information Administration (EIA), Short-Term Energy Outlook, November 2022 and EIA,
B87: AEO2023 National Energy Modeling System run ref2023.d020623a. Projections: EIA, AEO2023 National Energy Modeling System run ref2023.d020623a.
A135: PPC001
A141: PPC001:ba_End-UserPrice
A142: PPC001:ba_FederalTaxes
A143: PPC001:ba_StateTaxes
A144: PPC001:Diesel_Tax_Allow
A145: PPC001:ba_DistributionC
A146: PPC001:ba_WholesalePric
A149: PPC001:ca_End-UserPrice
A150: PPC001:ca_FederalTaxes
A151: PPC001:ca_StateTaxes
A152: PPC001:MoGas_Tax_Allow
A153: PPC001:ca_DistributionC
... A158: PPC001:da_FederalTaxes
A159: PPC001:da_StateTaxes | AF159: Average

Sheet AEO 2026 Table 1
A1: Table 1. Total Energy Supply, Disposition, and Price Summary
A2: https://www.eia.gov/outlooks/aeo/data/browser/#/?id=1-AEO2026&region=0-0&cases=electrnp&start=2025&end=2050&f=A&sourcekey=0
A3: Thu Apr 23 2026 14:30:14 GMT-0700 (Pacific Daylight Time)
A4: Source: U.S. Energy Information Administration
B5: full name | C5: api key | D5: units | E5: 2025 | F5: 2026 | G5: 2027 | H5: 2028 | I5: 2029 | J5: 2030 | K5: 2031 | L5: 2032 | M5: 2033 | N5: 2034 | O5: 2035 | P5: 2036 | Q5: 2037 | R5: 2038 | S5: 2039 | T5: 2040 | U5: 2041 | V5: 2042 | W5: 2043 | X5: 2044 | Y5: 2045 | Z5: 2046 | AA5: 2047 | AB5: 2048 | AC5: 2049 | AD5: 2050 | AE5: Growth (2025-2050)
A6: Production
A7: Crude Oil and Lease Condensate | B7: Total Energy: Production: Crude Oil and Lease Condensate: Alternative Electricity and Transportation | C7: AEO.2026.ELECTRNP.SUP_PRD_TEN_NA_CLC_NA_USA_QBTU.A | D7: quads | E7: 28.09622 | F7: 27.83951 | G7: 27.93445 | H7: 27.987217 | I7: 27.814901 | J7: 28.041071 | K7: 28.029518 | L7: 27.882774 | M7: 27.414968 | N7: 27.162401 | O7: 26.851124 | P7: 26.72197 | Q7: 26.669319 | R7: 26.478785 | S7: 26.444294 | T7: 26.71266 | U7: 26.96909 | V7: 27.048578 | W7: 27.202837 | X7: 27.264698 | Y7: 27.201111 | Z7: 27.041689 | AA7: 26.884602 | AB7: 26.681749 | AC7: 26.394308 | AD7: 25.994829 | AE7: -0.003
A8: Natural Gas Plant Liquids | B8: Total Energy: Production: Natural Gas Plant Liquids: Alternative Electricity and Transportation | C8: AEO.2026.ELECTRNP.SUP_PRD_TEN_NA_NGP_NA_USA_QBTU.A | D8: quads | E8: 9.619033 | F8: 9.796805 | G8: 10.516297 | H8: 10.408414 | I8: 10.449044 | J8: 10.487188 | K8: 10.989504 | L8: 11.466014 | M8: 11.930082 | N8: 12.265282 | O8: 12.51648 | P8: 12.657268 | Q8: 12.87834 | R8: 13.124127 | S8: 13.329017 | T8: 13.664953 | U8: 13.958897 | V8: 14.123372 | W8: 14.198471 | X8: 14.139817 | Y8: 13.995239 | Z8: 13.875278 | AA8: 13.909235 | AB8: 14.003947 | AC8: 14.058703 | AD8: 14.029639 | AE8: 0.015
A9: Dry Natural Gas | B9: Total Energy: Production: Dry Natural Gas: Alternative Electricity and Transportation | C9: AEO.2026.ELECTRNP.SUP_PRD_TEN_NA_DNG_NA_USA_QBTU.A | D9: quads | E9: 40.570412 | F9: 40.294426 | G9: 39.723049 | H9: 40.499924 | I9: 40.887131 | J9: 42.027294 | K9: 43.181034 | L9: 44.25951 | M9: 45.101624 | N9: 46.168903 | O9: 46.66502 | P9: 47.017208 | Q9: 47.328976 | R9: 47.659122 | S9: 47.983776 | T9: 48.581455 | U9: 49.290066 | V9: 49.974457 | W9: 50.566368 | X9: 51.11755 | Y9: 51.666023 | Z9: 52.372948 | AA9: 52.807499 | AB9: 53.11705 | AC9: 53.229816 | AD9: 53.342106 | AE9: 0.011
A10: Coal | B10: Total Energy: Production: Coal: Alternative Electricity and Transportation | C10: AEO.2026.ELECTRNP.SUP_PRD_TEN_NA_CL_NA_USA_QBTU.A | D10: quads | E10: 10.763646 | F10: 10.497858 | G10: 10.141273 | H10: 9.522483 | I10: 9.294424 | J10: 9.39627 | K10: 8.459009 | L10: 8.232461 | M10: 8.093637 | N10: 7.82284 | O10: 7.805241 | P10: 7.667391 | Q10: 7.643977 | R10: 7.652178 | S10: 7.588447 | T10: 7.438392 | U10: 7.274271 | V10: 7.150982 | W10: 7.07684 | X10: 7.009675 | Y10: 6.930867 | Z10: 6.866632 | AA10: 6.879517 | AB10: 6.854223 | AC10: 6.756863 | AD10: 6.497005 | AE10: -0.02
A11: Nuclear / Uranium | B11: Total Energy: Production: Nuclear: Alternative Electricity and Transportation | C11: AEO.2026.ELECTRNP.SUP_PRD_TEN_NA_NUC_NA_USA_QBTU.A | D11: quads | E11: 8.187651 | F11: 8.372738 | G11: 8.321443 | H11: 8.357332 | I11: 8.366615 | J11: 8.373707 | K11: 8.373858 | L11: 8.373865 | M11: 8.373583 | N11: 8.373583 | O11: 8.373577 | P11: 8.373578 | Q11: 8.370988 | R11: 8.366815 | S11: 8.368925 | T11: 8.36346 | U11: 8.357713 | V11: 8.371456 | W11: 8.365458 | X11: 8.373578 | Y11: 8.373578 | Z11: 8.373578 | AA11: 8.373579 | AB11: 8.373578 | AC11: 8.373578 | AD11: 8.373294 | AE11: 0.001
A12: Conventional Hydroelectric Power | B12: Total Energy: Production: Hydropower: Alternative Electricity and Transportation | C12: AEO.2026.ELECTRNP.SUP_PRD_TEN_NA_HYD_CNV_USA_QBTU.A | D12: quads | E12: 0.833386 | F12: 0.893707 | G12: 0.914331 | H12: 0.933283 | I12: 0.938944 | J12: 0.939915 | K12: 0.940947 | L12: 0.940738 | M12: 0.941016 | N12: 0.941605 | O12: 0.941869 | P12: 0.941762 | Q12: 0.943859 | R12: 0.944092 | S12: 0.944029 | T12: 0.943578 | U12: 0.944099 | V12: 0.944191 | W12: 0.944182 | X12: 0.944196 | Y12: 0.94409 | Z12: 0.944285 | AA12: 0.944356 | AB12: 0.944565 | AC12: 0.944563 | AD12: 0.944374 | AE12: 0.005
A13: Biomass | B13: Total Energy: Production: Biomass: Alternative Electricity and Transportation | C13: AEO.2026.ELECTRNP.SUP_PRD_TEN_NA_BMS_NA_USA_QBTU.A | D13: quads | E13: 4.753613 | F13: 4.876166 | G13: 4.835322 | H13: 4.839541 | I13: 4.821688 | J13: 4.751903 | K13: 4.713766 | L13: 4.689816 | M13: 4.680038 | N13: 4.683924 | O13: 4.690135 | P13: 4.716203 | Q13: 4.726579 | R13: 4.744782 | S13: 4.771104 | T13: 4.799549 | U13: 4.804287 | V13: 4.839866 | W13: 4.852074 | X13: 4.868423 | Y13: 4.891001 | Z13: 4.910817 | AA13: 4.948695 | AB13: 4.997142 | AC13: 5.05494 | AD13: 5.273374 | AE13: 0.004
A14: Other Renewable Energy | B14: Total Energy: Production: Other Renewable Energy: Alternative Electricity and Transportation | C14: AEO.2026.ELECTRNP.SUP_PRD_TEN_NA_PRE_NA_USA_QBTU.A | D14: quads | E14: 2.880712 | F14: 3.166233 | G14: 3.747644 | H14: 4.126372 | I14: 4.342162 | J14: 4.504683 | K14: 4.661613 | L14: 4.761504 | M14: 4.886238 | N14: 5.063766 | O14: 5.264389 | P14: 5.470821 | Q14: 5.615872 | R14: 5.739579 | S14: 5.866665 | T14: 5.986307 | U14: 6.091763 | V14: 6.138132 | W14: 6.158761 | X14: 6.175585 | Y14: 6.190252 | Z14: 6.209311 | AA14: 6.233634 | AB14: 6.247483 | AC14: 6.276224 | AD14: 6.308211 | AE14: 0.032
A15: Other | B15: Total Energy: Production: Other: Alternative Electricity and Transportation | C15: AEO.2026.ELECTRNP.SUP_PRD_TEN_NA_OTH_NA_USA_QBTU.A | D15: quads | E15: 1.597606 | F15: 1.539008 | G15: 0.732086 | H15: 0.664054 | I15: 0.656211 | J15: 0.650822 | K15: 0.634452 | L15: 0.506509 | M15: 0.508553 | N15: 0.526544 | O15: 0.532123 | P15: 0.529193 | Q15: 0.542328 | R15: 0.546555 | S15: 0.548446 | T15: 0.543072 | U15: 0.542411 | V15: 0.539229 | W15: 0.542313 | X15: 0.558117 | Y15: 0.564131 | Z15: 0.563349 | AA15: 0.565125 | AB15: 0.56417 | AC15: 0.563789 | AD15: 0.56249 | AE15: -0.041
A16: Total | B16: Total Energy: Production: Total: Alternative Electricity and Transportation | C16: AEO.2026.ELECTRNP.SUP_PRD_TEN_NA_TOT_NA_USA_QBTU.A | D16: quads | E16: 107.30228 | F16: 107.27644 | G16: 106.86589 | H16: 107.33862 | I16: 107.57112 | J16: 109.17285 | K16: 109.9837 | L16: 111.11319 | M16: 111.92973 | N16: 113.00884 | O16: 113.63995 | P16: 114.09539 | Q16: 114.72024 | R16: 115.25603 | S16: 115.84471 | T16: 117.03342 | U16: 118.2326 | V16: 119.13027 | W16: 119.9073 | X16: 120.45164 | Y16: 120.7563 | Z16: 121.15789 | AA16: 121.54624 | AB16: 121.78391 | AC16: 121.65279 | AD16: 121.32533 | AE16: 0.005
A17: Imports
A18: Crude Oil | B18: Total Energy: Imports: Crude Oil: Alternative Electricity and Transportation | C18: AEO.2026.ELECTRNP.TRAD_IMP_TEN_NA_CR_NA_USA_QBTU.A | D18: quads | E18: 13.254901 | F18: 12.62451 | G18: 13.906896 | H18: 14.053762 | I18: 14.525437 | J18: 14.625464 | K18: 14.482899 | L18: 14.885132 | M18: 15.092349 | N18: 15.432104 | O18: 15.633177 | P18: 15.400255 | Q18: 15.42865 | R18: 15.850074 | S18: 15.792415 | T18: 15.533682 | U18: 15.173124 | V18: 14.999949 | W18: 14.883173 | X18: 14.798785 | Y18: 15.292476 | Z18: 15.863901 | AA18: 16.235161 | AB18: 16.110662 | AC18: 16.079632 | AD18: 16.61627 | AE18: 0.009
A19: Petroleum and Other Liquids | B19: Total Energy: Imports: Liquid Fuels: Alternative Electricity and Transportation | C19: AEO.2026.ELECTRNP.TRAD_IMP_TEN_NA_LFL_NA_USA_QBTU.A | D19: quads | E19: 3.506377 | F19: 3.419535 | G19: 3.574062 | H19: 3.492604 | I19: 3.409276 | J19: 3.386769 | K19: 3.340114 | L19: 3.288664 | M19: 3.248637 | N19: 3.199638 | O19: 3.165486 | P19: 3.146207 | Q19: 3.146906 | R19: 3.138245 | S19: 3.132051 | T19: 3.134073 | U19: 3.123925 | V19: 3.122812 | W19: 3.124113 | X19: 3.116613 | Y19: 3.142915 | Z19: 3.108672 | AA19: 3.098501 | AB19: 3.171854 | AC19: 3.170427 | AD19: 3.125792 | AE19: -0.005
A20: Natural Gas | B20: Total Energy: Imports: Natural Gas: Alternative Electricity and Transportation | C20: AEO.2026.ELECTRNP.TRAD_IMP_TEN_NA_NG_NA_USA_QBTU.A | D20: quads | E20: 3.256896 | F20: 3.391662 | G20: 3.244866 | H20: 2.953583 | I20: 2.832458 | J20: 2.97589 | K20: 2.959408 | L20: 2.754073 | M20: 2.516675 | N20: 2.360982 | O20: 2.385319 | P20: 2.451794 | Q20: 2.522372 | R20: 2.578678 | S20: 2.652019 | T20: 2.552771 | U20: 2.306502 | V20: 2.2828 | W20: 2.345492 | X20: 2.457237 | Y20: 2.509919 | Z20: 2.442209 | AA20: 2.537626 | AB20: 2.670558 | AC20: 2.810932 | AD20: 2.948299 | AE20: -0.004
A21: Other | B21: Total Energy: Imports: Other: Alternative Electricity and Transportation | C21: AEO.2026.ELECTRNP.TRAD_IMP_TEN_NA_OTH_NA_USA_QBTU.A | D21: quads | E21: 0.094426 | F21: 0.145997 | G21: 0.205067 | H21: 0.244731 | I21: 0.265442 | J21: 0.29067 | K21: 0.288673 | L21: 0.294341 | M21: 0.304539 | N21: 0.308912 | O21: 0.314078 | P21: 0.30591 | Q21: 0.304515 | R21: 0.303384 | S21: 0.30777 | T21: 0.303434 | U21: 0.303217 | V21: 0.290294 | W21: 0.279213 | X21: 0.274696 | Y21: 0.273568 | Z21: 0.264709 | AA21: 0.255194 | AB21: 0.24511 | AC21: 0.22992 | AD21: 0.220576 | AE21: 0.035
A22: Total | B22: Total Energy: Imports: Total: Alternative Electricity and Transportation | C22: AEO.2026.ELECTRNP.TRAD_IMP_TEN_NA_TOT_NA_USA_QBTU.A | D22: quads | E22: 20.112602 | F22: 19.581705 | G22: 20.930889 | H22: 20.74468 | I22: 21.032614 | J22: 21.278793 | K22: 21.071095 | L22: 21.22221 | M22: 21.162201 | N22: 21.301638 | O22: 21.49806 | P22: 21.304167 | Q22: 21.402443 | R22: 21.870382 | S22: 21.884254 | T22: 21.52396 | U22: 20.906769 | V22: 20.695856 | W22: 20.63199 | X22: 20.647331 | Y22: 21.218876 | Z22: 21.679491 | AA22: 22.126482 | AB22: 22.198185 | AC22: 22.290911 | AD22: 22.910936 | AE22: 0.005
A23: Exports
A24: Petroleum and Other Liquids | B24: Total Energy: Exports: Petroleum: Alternative Electricity and Transportation | C24: AEO.2026.ELECTRNP.TRAD_EXP_TEN_NA_PET_NA_USA_QBTU.A | D24: quads | E24: 20.076674 | F24: 19.914589 | G24: 21.616186 | H24: 21.639196 | I24: 22.136238 | J24: 22.429478 | K24: 23.03207 | L24: 23.705414 | M24: 24.135605 | N24: 24.560024 | O24: 24.835129 | P24: 24.702003 | Q24: 24.975132 | R24: 25.413769 | S24: 25.593113 | T24: 25.894386 | U24: 26.1339 | V24: 26.221857 | W24: 26.39142 | X24: 26.317417 | Y24: 26.584335 | Z24: 26.764486 | AA24: 26.981876 | AB24: 26.844584 | AC24: 26.65336 | AD24: 26.702797 | AE24: 0.011
A25: Natural Gas | B25: Total Energy: Exports: Natural Gas: Alternative Electricity and Transportation | C25: AEO.2026.ELECTRNP.TRAD_EXP_TEN_NA_NG_NA_USA_QBTU.A | D25: quads | E25: 8.975658 | F25: 9.088441 | G25: 9.822119 | H25: 10.434997 | I25: 10.937449 | J25: 12.260552 | K25: 12.868597 | L25: 13.509771 | M25: 13.987963 | N25: 14.747663 | O25: 15.282458 | P25: 15.722227 | Q25: 15.969494 | R25: 16.216171 | S25: 16.470881 | T25: 16.730671 | U25: 16.97636 | V25: 17.203733 | W25: 17.429588 | X25: 17.687986 | Y25: 17.89101 | Z25: 18.132946 | AA25: 18.363718 | AB25: 18.52001 | AC25: 18.519236 | AD25: 18.544718 | AE25: 0.029
A26: Coal | B26: Total Energy: Exports: Coal: Alternative Electricity and Transportation | C26: AEO.2026.ELECTRNP.TRAD_EXP_TEN_NA_CL_NA_USA_QBTU.A | D26: quads | E26: 2.463368 | F26: 2.559237 | G26: 2.735956 | H26: 2.849638 | I26: 2.751542 | J26: 2.886293 | K26: 2.907977 | L26: 3.081553 | M26: 3.111071 | N26: 3.103139 | O26: 3.1274 | P26: 3.06748 | Q26: 3.123805 | R26: 3.146678 | S26: 3.130178 | T26: 3.149433 | U26: 3.085596 | V26: 3.056049 | W26: 3.095218 | X26: 3.120324 | Y26: 3.108418 | Z26: 3.122652 | AA26: 3.11857 | AB26: 3.101774 | AC26: 3.112857 | AD26: 3.034203 | AE26: 0.008
A27: Total | B27: Total Energy: Exports: Total: Alternative Electricity and Transportation | C27: AEO.2026.ELECTRNP.TRAD_EXP_TEN_NA_TOT_NA_USA_QBTU.A | D27: quads | E27: 31.515699 | F27: 31.562267 | G27: 34.174259 | H27: 34.923828 | I27: 35.825226 | J27: 37.576321 | K27: 38.808643 | L27: 40.296738 | M27: 41.234638 | N27: 42.410824 | O27: 43.244987 | P27: 43.491711 | Q27: 44.068432 | R27: 44.776619 | S27: 45.194176 | T27: 45.77449 | U27: 46.195858 | V27: 46.48164 | W27: 46.916225 | X27: 47.125725 | Y27: 47.583763 | Z27: 48.020081 | AA27: 48.464165 | AB27: 48.466366 | AC27: 48.285454 | AD27: 48.281715 | AE27: 0.017
A28: Discrepancy | B28: Total Energy: Discrepancy: Alternative Electricity and Transportation | C28: AEO.2026.ELECTRNP.UNC_NA_TEN_NA_DESCR_NA_USA_QBTU.A | D28: quads | E28: 0.609568 | F28: -0.330133 | G28: -0.56411 | H28: -0.473511 | I28: -0.333321 | J28: 0.028347 | K28: -0.001419 | L28: -0.002094 | M28: -0.083462 | N28: -0.047085 | O28: -0.115166 | P28: -0.141689 | Q28: -0.128963 | R28: -0.042755 | S28: -0.078278 | T28: -0.053158 | U28: -0.099354 | V28: -0.012081 | W28: -0.081821 | X28: -0.072121 | Y28: -0.052273 | Z28: 0.023468 | AA28: -0.026619 | AB28: -0.023872 | AC28: -0.0513 | AD28: -0.034363 | AE28: - -
A29: Consumption
A30: Petroleum and Other Liquids | B30: Total Energy: Use: Liquid Fuels: Alternative Electricity and Transportation | C30: AEO.2026.ELECTRNP.CNSM_USE_TEN_NA_LFL_NA_USA_QBTU.A | D30: quads | E30: 37.415314 | F30: 37.39756 | G30: 37.429806 | H30: 37.393105 | I30: 37.092777 | J30: 36.903763 | K30: 36.673176 | L30: 36.545361 | M30: 36.386639 | N30: 36.327778 | O30: 36.269566 | P30: 36.183342 | Q30: 36.101166 | R30: 36.030628 | S30: 35.997036 | T30: 35.997505 | U30: 35.993946 | V30: 35.983074 | W30: 36.004101 | X30: 36.009083 | Y30: 36.05069 | Z30: 36.066441 | AA30: 36.141716 | AB30: 36.131622 | AC30: 36.106647 | AD30: 36.114407 | AE30: -0.001
A31: Natural Gas | B31: Total Energy: Use: Natural Gas: Alternative Electricity and Transportation | C31: AEO.2026.ELECTRNP.CNSM_USE_TEN_NA_NG_NA_USA_QBTU.A | D31: quads | E31: 34.309906 | F31: 34.343494 | G31: 32.823555 | H31: 32.58604 | I31: 32.265926 | J31: 32.059547 | K31: 32.53434 | L31: 32.775009 | M31: 32.883018 | N31: 33.030529 | O31: 32.972298 | P31: 32.965488 | Q31: 33.113277 | R31: 33.27256 | S31: 33.420219 | T31: 33.683891 | U31: 33.893101 | V31: 34.241695 | W31: 34.675434 | X31: 35.069263 | Y31: 35.454762 | Z31: 35.832901 | AA31: 36.141129 | AB31: 36.424366 | AC31: 36.691483 | AD31: 36.904549 | AE31: 0.003
A32: Coal | B32: Total Energy: Use: Coal: Alternative Electricity and Transportation | C32: AEO.2026.ELECTRNP.CNSM_USE_TEN_NA_CL_NA_USA_QBTU.A | D32: quads | E32: 8.312325 | F32: 7.978454 | G32: 7.41205 | H32: 6.680679 | I32: 6.548737 | J32: 6.516286 | K32: 5.549825 | L32: 5.152449 | M32: 4.980665 | N32: 4.715786 | O32: 4.682521 | P32: 4.603929 | Q32: 4.522728 | R32: 4.506305 | S32: 4.465453 | T32: 4.287592 | U32: 4.18628 | V32: 4.097344 | W32: 3.978774 | X32: 3.887891 | Y32: 3.823375 | Z32: 3.756142 | AA32: 3.769727 | AB32: 3.763525 | AC32: 3.644761 | AD32: 3.470035 | AE32: -0.034
A33: Nuclear / Uranium | B33: Total Energy: Use: Nuclear: Alternative Electricity and Transportation | C33: AEO.2026.ELECTRNP.CNSM_USE_TEN_NA_NUC_NA_USA_QBTU.A | D33: quads | E33: 8.187651 | F33: 8.372738 | G33: 8.321443 | H33: 8.357332 | I33: 8.366615 | J33: 8.373707 | K33: 8.373858 | L33: 8.373865 | M33: 8.373583 | N33: 8.373583 | O33: 8.373577 | P33: 8.373578 | Q33: 8.370988 | R33: 8.366815 | S33: 8.368925 | T33: 8.36346 | U33: 8.357713 | V33: 8.371456 | W33: 8.365458 | X33: 8.373578 | Y33: 8.373578 | Z33: 8.373578 | AA33: 8.373579 | AB33: 8.373578 | AC33: 8.373578 | AD33: 8.373294 | AE33: 0.001
A34: Conventional Hydroelectric Power | B34: Total Energy: Use: Hydropower: Alternative Electricity and Transportation | C34: AEO.2026.ELECTRNP.CNSM_USE_TEN_NA_HYD_CNV_USA_QBTU.A | D34: quads | E34: 0.833386 | F34: 0.893707 | G34: 0.914331 | H34: 0.933283 | I34: 0.938944 | J34: 0.939915 | K34: 0.940947 | L34: 0.940738 | M34: 0.941016 | N34: 0.941605 | O34: 0.941869 | P34: 0.941762 | Q34: 0.943859 | R34: 0.944092 | S34: 0.944029 | T34: 0.943578 | U34: 0.944099 | V34: 0.944191 | W34: 0.944182 | X34: 0.944196 | Y34: 0.94409 | Z34: 0.944285 | AA34: 0.944356 | AB34: 0.944565 | AC34: 0.944563 | AD34: 0.944374 | AE34: 0.005
A35: Biomass | B35: Total Energy: Use: Biomass: Alternative Electricity and Transportation | C35: AEO.2026.ELECTRNP.CNSM_USE_TEN_NA_BMS_NA_USA_QBTU.A | D35: quads | E35: 2.925746 | F35: 3.020187 | G35: 2.990986 | H35: 2.971073 | I35: 2.95593 | J35: 2.923736 | K35: 2.881742 | L35: 2.854099 | M35: 2.839809 | N35: 2.838316 | O35: 2.839848 | P35: 2.852271 | Q35: 2.857769 | R35: 2.873178 | S35: 2.891686 | T35: 2.908722 | U35: 2.907083 | V35: 2.920886 | W35: 2.925695 | X35: 2.93498 | Y35: 2.954176 | Z35: 2.969813 | AA35: 2.994902 | AB35: 3.023774 | AC35: 3.049063 | AD35: 3.256605 | AE35: 0.004
A36: Other Renewable Energy | B36: Total Energy: Use: Other Renewable Energy: Alternative Electricity and Transportation | C36: AEO.2026.ELECTRNP.CNSM_USE_TEN_NA_PRE_NA_USA_QBTU.A | D36: quads | E36: 2.880712 | F36: 3.166233 | G36: 3.747644 | H36: 4.126372 | I36: 4.342162 | J36: 4.504683 | K36: 4.661613 | L36: 4.761504 | M36: 4.886238 | N36: 5.063766 | O36: 5.264389 | P36: 5.470821 | Q36: 5.615872 | R36: 5.739579 | S36: 5.866665 | T36: 5.986307 | U36: 6.091763 | V36: 6.138132 | W36: 6.158761 | X36: 6.175585 | Y36: 6.190252 | Z36: 6.209311 | AA36: 6.233634 | AB36: 6.247483 | AC36: 6.276224 | AD36: 6.308211 | AE36: 0.032
A37: Other | B37: Total Energy: Use: Other: Alternative Electricity and Transportation | C37: AEO.2026.ELECTRNP.CNSM_USE_TEN_NA_OTH_NA_USA_QBTU.A | D37: quads | E37: 0.424569 | F37: 0.453636 | G37: 0.546819 | H37: 0.585096 | I37: 0.60074 | J37: 0.625341 | K37: 0.632063 | L37: 0.637733 | M37: 0.649799 | N37: 0.65537 | O37: 0.664124 | P37: 0.658336 | Q37: 0.657547 | R37: 0.659404 | S37: 0.659049 | T37: 0.664997 | U37: 0.668879 | V37: 0.659788 | W37: 0.652483 | X37: 0.650791 | Y37: 0.65276 | Z37: 0.641367 | AA37: 0.636121 | AB37: 0.630691 | AC37: 0.62323 | AD37: 0.617439 | AE37: 0.015
A38: Total | B38: Total Energy: Use: Total: Alternative Electricity and Transportation | C38: AEO.2026.ELECTRNP.CNSM_USE_TEN_NA_TOT_NA_USA_QBTU.A | D38: quads | E38: 95.289612 | F38: 95.626015 | G38: 94.18663 | H38: 93.63298 | I38: 93.111832 | J38: 92.846977 | K38: 92.247574 | L38: 92.040756 | M38: 91.940758 | N38: 91.946739 | O38: 92.008194 | P38: 92.049538 | Q38: 92.183212 | R38: 92.392555 | S38: 92.613068 | T38: 92.836052 | U38: 93.042862 | V38: 93.356567 | W38: 93.704887 | X38: 94.045372 | Y38: 94.443687 | Z38: 94.793831 | AA38: 95.235176 | AB38: 95.539604 | AC38: 95.709549 | AD38: 95.988907 | AE38: 0
A39: Prices (2025 dollars per unit)
A40: Brent Spot Price (dollars per barrel) | B40: Total Energy: Real Prices: Brent: Alternative Electricity and Transportation | C40: AEO.2026.ELECTRNP.PRCE_RLP_TEN_NA_BRN_NA_USA_Y13DLRPBBL.A | D40: 2025 $/b | E40: 68.758003 | F40: 53.451851 | G40: 58.008591 | H40: 62.476402 | I40: 65.409325 | J40: 65.158569 | K40: 68.833679 | L40: 69.83049 | M40: 71.635643 | N40: 73.592148 | O40: 74.762581 | P40: 76.158562 | Q40: 78.223351 | R40: 79.690277 | S40: 80.750778 | T40: 81.161491 | U40: 82.013199 | V40: 83.342216 | W40: 84.728607 | X40: 85.865303 | Y40: 87.667793 | Z40: 89.243423 | AA40: 90.481903 | AB40: 91.804817 | AC40: 92.957466 | AD40: 94.122032 | AE40: 0.013
A41: West Texas Intermediate Spot Price (dollars per barrel) | B41: Total Energy: Real Prices: West Texas Intermediate: Alternative Electricity and Transportation | C41: AEO.2026.ELECTRNP.PRCE_RLP_TEN_NA_WTI_NA_USA_Y13DLRPBBL.A | D41: 2025 $/b | E41: 65.148003 | F41: 49.889759 | G41: 55.470398 | H41: 59.830151 | I41: 63.597237 | J41: 64.582809 | K41: 67.595825 | L41: 67.820969 | M41: 69.813576 | N41: 70.421333 | O41: 71.756279 | P41: 73.095161 | Q41: 74.791466 | R41: 76.362282 | S41: 77.228645 | T41: 77.679909 | U41: 78.579803 | V41: 79.948219 | W41: 81.499611 | X41: 82.588013 | Y41: 84.446144 | Z41: 85.794556 | AA41: 86.725136 | AB41: 88.563858 | AC41: 90.687332 | AD41: 91.284042 | AE41: 0.014
A42: Natural Gas at Henry Hub (dollars per MMBtu) | B42: Total Energy: Real Prices: Gas Price at Henry Hub: Alternative Electricity and Transportation | C42: AEO.2026.ELECTRNP.PRCE_RLP_TEN_NA_HHP_NA_USA_Y13DLRPMMBTU.A | D42: 2025 $/MMBtu | E42: 3.467273 | F42: 3.723197 | G42: 3.580499 | H42: 3.696219 | I42: 3.812272 | J42: 4.410327 | K42: 4.764429 | L42: 4.950762 | M42: 5.0083 | N42: 5.048673 | O42: 5.174382 | P42: 5.272789 | Q42: 5.338483 | R42: 5.475314 | S42: 5.644838 | T42: 5.767788 | U42: 5.7693 | V42: 5.55141 | W42: 5.240263 | X42: 4.995708 | Y42: 4.8816 | Z42: 4.85912 | AA42: 4.859154 | AB42: 4.85418 | AC42: 4.816893 | AD42: 4.764984 | AE42: 0.013
A43: Coal | B43: Minemouth (dollars per ton) | C43: Total Energy: Real Prices: Coal at Minemouth: Alternative Electricity and Transportation | D43: AEO.2026.ELECTRNP.PRCE_RLP_TEN_NA_CMN_NA_USA_Y13DLRPTN.A | E43: 2025 $/ton | F43: 49.795895 | G43: 50.747353 | H43: 48.035725 | I43: 49.787979 | J43: 50.350109 | K43: 51.098656 | L43: 54.688625 | M43: 55.262581 | N43: 55.603317 | O43: 56.090031 | P43: 56.297741 | Q43: 56.275612 | R43: 57.449318 | S43: 57.694397 | T43: 57.39418 | U43: 58.235558 | V43: 58.040581 | W43: 58.814297 | X43: 59.63015 | Y43: 60.090992 | Z43: 60.419445 | AA43: 61.244205 | AB43: 61.476044 | AC43: 61.865074 | AD43: 63.074032 | AE43: 64.450996 | AF43: 0.01
A44: Coal | B44: Minemouth (dollars per MMBtu) | C44: Total Energy: Real Prices: Coal Minemouth: Alternative Electricity and Transportation | D44: AEO.2026.ELECTRNP.PRCE_RLP_TEN_NA_CMN_NA_USA_Y13DLRPMMBTU.A | E44: 2025 $/MMBtu | F44: 2.374021 | G44: 2.405669 | H44: 2.308535 | I44: 2.372168 | J44: 2.390277 | K44: 2.417656 | L44: 2.54295 | M44: 2.567319 | N44: 2.578565 | O44: 2.593685 | P44: 2.602098 | Q44: 2.59848 | R44: 2.62642 | S44: 2.631369 | T44: 2.612399 | U44: 2.637557 | V44: 2.629111 | W44: 2.646902 | X44: 2.670286 | Y44: 2.682195 | Z44: 2.691905 | AA44: 2.712268 | AB44: 2.71805 | AC44: 2.728911 | AD44: 2.762147 | AE44: 2.803862 | AF44: 0.007
A45: Coal | B45: Delivered (dollars per MMBtu) | C45: Total Energy: Real Prices: Delivered Coal: Alternative Electricity and Transportation | D45: AEO.2026.ELECTRNP.PRCE_RLP_TEN_NA_DCL_NA_USA_Y13DLRPMMBTU.A | E45: 2025 $/MMBtu | F45: 2.827939 | G45: 2.794977 | H45: 2.780039 | I45: 2.790127 | J45: 2.782977 | K45: 2.789943 | L45: 2.799445 | M45: 2.812125 | N45: 2.815971 | O45: 2.809738 | P45: 2.802893 | Q45: 2.794339 | R45: 2.826534 | S45: 2.822435 | T45: 2.826797 | U45: 2.840614 | V45: 2.8351 | W45: 2.833347 | X45: 2.843825 | Y45: 2.835527 | Z45: 2.844337 | AA45: 2.852956 | AB45: 2.853899 | AC45: 2.855855 | AD45: 2.884762 | AE45: 2.895509 | AF45: 0.001
A46: Electricity (cents per kilowatthour) | B46: Total Energy: Real Prices: Electricity: Alternative Electricity and Transportation | C46: AEO.2026.ELECTRNP.PRCE_RLP_TEN_NA_ELC_NA_USA_Y13CNTPKWH.A | D46: 2025 cents/kWh | E46: 13.537334 | F46: 13.475026 | G46: 13.066734 | H46: 12.770625 | I46: 12.869843 | J46: 13.016791 | K46: 13.150146 | L46: 13.221062 | M46: 13.304499 | N46: 13.386029 | O46: 13.426527 | P46: 13.45792 | Q46: 13.532384 | R46: 13.581625 | S46: 13.653389 | T46: 13.7295 | U46: 13.750996 | V46: 13.735488 | W46: 13.698519 | X46: 13.669256 | Y46: 13.594911 | Z46: 13.655286 | AA46: 13.708775 | AB46: 13.761915 | AC46: 13.780516 | AD46: 13.826503 | AE46: 0.001
A47: Prices (nominal dollars per unit)
A48: Brent Spot Price (dollars per barrel) | B48: Total Energy: Nominal Prices: Brent: Alternative Electricity and Transportation | C48: AEO.2026.ELECTRNP.PRCE_NOMP_TEN_NA_BRN_NA_USA_NDLRPBRL.A | D48: nom $/b | E48: 68.758003 | F48: 54.921001 | G48: 60.734013 | H48: 66.772827 | I48: 71.344742 | J48: 72.551765 | K48: 78.250099 | L48: 81.018799 | M48: 84.889984 | N48: 89.027458 | O48: 92.352303 | P48: 96.012344 | Q48: 100.54858 | R48: 104.44556 | S48: 107.88986 | T48: 110.55418 | U48: 113.85683 | V48: 117.87924 | W48: 122.06422 | X48: 125.96648 | Y48: 130.94331 | Z48: 135.71101 | AA48: 140.09273 | AB48: 144.74268 | AC48: 149.22105 | AD48: 153.79326 | AE48: 0.033
A49: West Texas Intermediate Spot Price (dollars per barrel) | B49: Total Energy: Nominal Prices: West Texas Intermediate: Alternative Electricity and Transportation | C49: AEO.2026.ELECTRNP.PRCE_NOMP_TEN_NA_WTI_NA_USA_NDLRPBRL.A | D49: nom $/b | E49: 65.148003 | F49: 51.261002 | G49: 58.076569 | H49: 63.944592 | I49: 69.368225 | J49: 71.910675 | K49: 76.842903 | L49: 78.687309 | M49: 82.730782 | N49: 85.191597 | O49: 88.638695 | P49: 92.150345 | Q49: 96.13723 | R49: 100.08374 | S49: 103.184 | T49: 105.81175 | U49: 109.09033 | V49: 113.07878 | W49: 117.41236 | X49: 121.15861 | Y49: 126.13135 | Z49: 130.46639 | AA49: 134.27614 | AB49: 139.63286 | AC49: 145.5769 | AD49: 149.15605 | AE49: 0.034
A50: Natural Gas at Henry Hub (dollars per MMBtu) | B50: Total Energy: Nominal Prices: Gas Price at Henry Hub: Alternative Electricity and Transportation | C50: AEO.2026.ELECTRNP.PRCE_NOMP_TEN_NA_HHP_NA_USA_NDLRPMBTU.A | D50: nom $/MMBtu | E50: 3.467273 | F50: 3.825531 | G50: 3.748722 | H50: 3.950404 | I50: 4.158208 | J50: 4.910743 | K50: 5.4162 | L50: 5.743978 | M50: 5.934958 | N50: 6.107588 | O50: 6.391781 | P50: 6.647353 | Q50: 6.862106 | R50: 7.176185 | S50: 7.54198 | T50: 7.856596 | U50: 8.009372 | V50: 7.851915 | W50: 7.54938 | X50: 7.328824 | Y50: 7.291308 | Z50: 7.389185 | AA50: 7.523407 | AB50: 7.653269 | AC50: 7.732374 | AD50: 7.785874 | AE50: 0.033
A51: Coal | B51: Minemouth (dollars per ton) | C51: Total Energy: Nominal Prices: Coal at Minemouth: Alternative Electricity and Transportation | D51: AEO.2026.ELECTRNP.PRCE_NOMP_TEN_NA_CAM_NA_USA_NDLRPTON.A | E51: nom $/ton | F51: 49.795895 | G51: 52.14217 | H51: 50.292587 | I51: 53.211834 | J51: 54.919014 | K51: 56.896545 | L51: 62.170002 | M51: 64.116798 | N51: 65.891289 | O51: 67.854424 | P51: 69.543159 | Q51: 70.946106 | R51: 73.845566 | S51: 75.616791 | T51: 76.683472 | U51: 79.325607 | V51: 80.576248 | W51: 83.186951 | X51: 85.906136 | Y51: 88.154938 | Z51: 90.244339 | AA51: 93.133064 | AB51: 95.183083 | AC51: 97.538628 | AD51: 101.25033 | AE51: 105.31145 | AF51: 0.03
A52: Coal | B52: Minemouth (dollars per MMBtu) | C52: Total Energy: Nominal Prices: Coal Minemouth: Alternative Electricity and Transportation | D52: AEO.2026.ELECTRNP.PRCE_NOMP_TEN_NA_CMN_NA_USA_NDLRPMBTU.A | E52: nom $/MMBtu | F52: 2.374021 | G52: 2.471791 | H52: 2.416997 | I52: 2.535299 | J52: 2.607178 | K52: 2.691975 | L52: 2.890825 | M52: 2.978657 | N52: 3.055662 | O52: 3.137688 | P52: 3.214306 | Q52: 3.275878 | R52: 3.37601 | S52: 3.448787 | T52: 3.490386 | U52: 3.59275 | V52: 3.649928 | W52: 3.743779 | X52: 3.846946 | Y52: 3.934845 | Z52: 4.020712 | AA52: 4.124502 | AB52: 4.208345 | AC52: 4.302496 | AD52: 4.433969 | AE52: 4.581446 | AF52: 0.027
A53: Coal | B53: Delivered (dollars per MMBtu) | C53: Total Energy: Nominal Prices: Delivered Coal: Alternative Electricity and Transportation | D53: AEO.2026.ELECTRNP.PRCE_NOMP_TEN_NA_DCL_NA_USA_NDLRPMBTU.A | E53: nom $/MMBtu | F53: 2.827939 | G53: 2.871799 | H53: 2.910653 | I53: 2.982 | J53: 3.035512 | K53: 3.106503 | L53: 3.182408 | M53: 3.262687 | N53: 3.336995 | O53: 3.399057 | P53: 3.462342 | Q53: 3.522796 | R53: 3.633237 | S53: 3.699206 | T53: 3.77684 | U53: 3.869344 | V53: 3.935897 | W53: 4.007486 | X53: 4.096954 | Y53: 4.159787 | Z53: 4.248389 | AA53: 4.338443 | AB53: 4.41868 | AC53: 4.50264 | AD53: 4.630798 | AE53: 4.731195 | AF53: 0.021
A54: Electricity (cents per kilowatthour) | B54: Total Energy: Nominal Prices: Electricity: Alternative Electricity and Transportation | C54: AEO.2026.ELECTRNP.PRCE_NOMP_TEN_NA_ELC_NA_USA_NCNTPKWH.A | D54: nom cents/kWh | E54: 13.537334 | F54: 13.845394 | G54: 13.680649 | H54: 13.648844 | I54: 14.037687 | J54: 14.493737 | K54: 14.94908 | L54: 15.339353 | M54: 15.766155 | N54: 16.193632 | O54: 16.585445 | P54: 16.966267 | Q54: 17.394577 | R54: 17.800671 | S54: 18.242083 | T54: 18.701649 | U54: 19.090155 | V54: 19.427477 | W54: 19.734762 | X54: 20.053129 | Y54: 20.305777 | Z54: 20.765371 | AA54: 21.225235 | AB54: 21.697515 | AC54: 22.121334 | AD54: 22.59219 | AE54: 0.021

Sheet AEO 2026 Table 19
A1: Table 19. Hydrogen Supply, Disposition, and Prices
A2: https://www.eia.gov/outlooks/aeo/data/browser/#/?id=23-AEO2026&cases=electrnp&sourcekey=0
A3: Thu Apr 23 2026 15:00:15 GMT-0700 (Pacific Daylight Time)
A4: Source: U.S. Energy Information Administration
B5: full name | C5: api key | D5: units | E5: 2025 | F5: 2026 | G5: 2027 | H5: 2028 | I5: 2029 | J5: 2030 | K5: 2031 | L5: 2032 | M5: 2033 | N5: 2034 | O5: 2035 | P5: 2036 | Q5: 2037 | R5: 2038 | S5: 2039 | T5: 2040 | U5: 2041 | V5: 2042 | W5: 2043 | X5: 2044 | Y5: 2045 | Z5: 2046 | AA5: 2047 | AB5: 2048 | AC5: 2049 | AD5: 2050 | AE5: Growth (2025-2050)
A6: Supply
A7: Production By Technology
A8: Steam Methane Reforming | B8: Hydrogen Market Projections: Production By Technology: Steam Methane Reforming: Alternative Electricity and Transportation | C8: AEO.2026.ELECTRNP.SUP_PRD_NA_NA_HDG_SMR_USA_MMMT.A | D8: MMmt | E8: 5.659547 | F8: 5.032887 | G8: 4.992723 | H8: 5.019737 | I8: 4.898739 | J8: 4.879333 | K8: 4.789099 | L8: 4.76969 | M8: 4.790712 | N8: 4.936659 | O8: 4.982401 | P8: 5.015864 | Q8: 5.455601 | R8: 5.675931 | S8: 5.713116 | T8: 5.70251 | U8: 5.952733 | V8: 5.961066 | W8: 6.009364 | X8: 6.154692 | Y8: 6.243866 | Z8: 6.274028 | AA8: 6.329513 | AB8: 6.35868 | AC8: 6.383008 | AD8: 6.407354 | AE8: 0.005
A9: Steam Methane Reforming with CCS | B9: Hydrogen Market Projections: Production By Technology: Steam Methane Reforming with CCS: Alternative Electricity and Transportation | C9: AEO.2026.ELECTRNP.SUP_PRD_NA_NA_HDG_SMRCCS_USA_MMMT.A | D9: MMmt | E9: 0.334852 | F9: 0.334852 | G9: 0.334852 | H9: 0.334852 | I9: 0.334852 | J9: 0.334852 | K9: 0.334852 | L9: 0.334852 | M9: 0.334852 | N9: 0.334852 | O9: 0.334852 | P9: 0.304762 | Q9: 0 | R9: 0 | S9: 0 | T9: 0 | U9: 0 | V9: 0 | W9: 0 | X9: 0 | Y9: 0 | Z9: 0 | AA9: 0 | AB9: 0 | AC9: 0 | AD9: 0 | AE9: -1
A10: Autothermal Reforming with CCS | B10: Hydrogen Market Projections: Production By Technology: Autothermal Reforming with CCS: Alternative Electricity and Transportation | C10: AEO.2026.ELECTRNP.SUP_PRD_NA_NA_HDG_ATRCCS_USA_MMMT.A | D10: MMmt | E10: 0 | F10: 0.170512 | G10: 0.170512 | H10: 0.170512 | I10: 0.401204 | J10: 0.401204 | K10: 0.401204 | L10: 0.401204 | M10: 0.401204 | N10: 0.401204 | O10: 0.401204 | P10: 0.401204 | Q10: 0.401204 | R10: 0.230692 | S10: 0.230692 | T10: 0.230692 | U10: 0 | V10: 0 | W10: 0 | X10: 0 | Y10: 0 | Z10: 0 | AA10: 0 | AB10: 0 | AC10: 0 | AD10: 0 | AE10: - -
A11: Electrolysis | B11: Hydrogen Market Projections: Production By Technology: Electrolysis: Alternative Electricity and Transportation | C11: AEO.2026.ELECTRNP.SUP_PRD_NA_NA_HDG_GRDELEC_USA_MMMT.A | D11: MMmt | E11: 4.2e-05 | F11: 0.01439 | G11: 0.016392 | H11: 0.009311 | I11: 0.0081 | J11: 0.010323 | K11: 0.004869 | L11: 0.001615 | M11: 0.00146 | N11: 0.001759 | O11: 0.002048 | P11: 0 | Q11: 0 | R11: 0 | S11: 0 | T11: 0 | U11: 0 | V11: 0 | W11: 0 | X11: 0 | Y11: 0 | Z11: 0 | AA11: 0 | AB11: 0 | AC11: 0 | AD11: 0 | AE11: -1
A12: Byproduct Hydrogen Supply to Market | B12: Hydrogen Market Projections: Byproduct hydrogen supply to market: Alternative Electricity and Transportation | C12: AEO.2026.ELECTRNP.SUP_PRD_NA_NA_HDG_BYPROD_USA_MMMT.A | D12: MMmt | E12: 2.02554 | F12: 2.063889 | G12: 2.087271 | H12: 2.077101 | I12: 2.043689 | J12: 2.044156 | K12: 2.0521 | L12: 2.054974 | M12: 2.070796 | N12: 2.080865 | O12: 2.10896 | P12: 2.128429 | Q12: 2.133964 | R12: 2.157028 | S12: 2.179477 | T12: 2.199941 | U12: 2.230414 | V12: 2.258515 | W12: 2.286566 | X12: 2.307555 | Y12: 2.330795 | Z12: 2.360232 | AA12: 2.391338 | AB12: 2.418861 | AC12: 2.438444 | AD12: 2.464948 | AE12: 0.008
A13: Total Hydrogen Supply | B13: Hydrogen Market Projections: Total Hydrogen Supply: Alternative Electricity and Transportation | C13: AEO.2026.ELECTRNP.SUP_NA_NA_NA_HDG_TOT_USA_MMMT.A | D13: MMmt | E13: 8.019981 | F13: 7.61653 | G13: 7.601751 | H13: 7.611512 | I13: 7.686584 | J13: 7.669868 | K13: 7.582125 | L13: 7.562335 | M13: 7.599025 | N13: 7.75534 | O13: 7.829465 | P13: 7.850259 | Q13: 7.990769 | R13: 8.063651 | S13: 8.123285 | T13: 8.133142 | U13: 8.183146 | V13: 8.219581 | W13: 8.295929 | X13: 8.462247 | Y13: 8.574661 | Z13: 8.63426 | AA13: 8.720851 | AB13: 8.777541 | AC13: 8.821452 | AD13: 8.872303 | AE13: 0.004
A14: Consumption | B14: Hydrogen Market Projections: Total Hydrogen Consumption: Alternative Electricity and Transportation | C14: AEO.2026.ELECTRNP.CNSM_NA_NA_NA_HDG_TOT_USA_MMMT.A | D14: MMmt | E14: 8.012987 | F14: 7.607544 | G14: 7.591349 | H14: 7.601383 | I14: 7.675807 | J14: 7.659146 | K14: 7.571351 | L14: 7.551171 | M14: 7.587768 | N14: 7.744197 | O14: 7.818182 | P14: 7.839029 | Q14: 7.979493 | R14: 8.052443 | S14: 8.111986 | T14: 8.121541 | U14: 8.17167 | V14: 8.208235 | W14: 8.284301 | X14: 8.450414 | Y14: 8.562716 | Z14: 8.622116 | AA14: 8.708749 | AB14: 8.765518 | AC14: 8.809484 | AD14: 8.860441 | AE14: 0.004
A15: Industrial feedstock | B15: Hydrogen Market Projections: Consumption: Industrial feedstocks: Alternative Electricity and Transportation | C15: AEO.2026.ELECTRNP.CNSM_NA_NA_NA_HDG_INDF_USA_MMMT.A | D15: MMmt | E15: 8.009887 | F15: 7.604562 | G15: 7.588504 | H15: 7.598682 | I15: 7.673244 | J15: 7.656733 | K15: 7.569081 | L15: 7.549054 | M15: 7.5858 | N15: 7.742378 | O15: 7.81651 | P15: 7.837502 | Q15: 7.978107 | R15: 8.051191 | S15: 8.110865 | T15: 8.120539 | U15: 8.17078 | V15: 8.207437 | W15: 8.283582 | X15: 8.449756 | Y15: 8.562127 | Z15: 8.621575 | AA15: 8.708242 | AB15: 8.765047 | AC15: 8.809 | AD15: 8.859974 | AE15: 0.004
A16: Bulk Chemicals | B16: Hydrogen Market Projections: Consumption: Industrial feedstocks: Bulk chemicals: Alternative Electricity and Transportation | C16: AEO.2026.ELECTRNP.CNSM_NA_NA_NA_HDG_BC_USA_MMMT.A | D16: MMmt | E16: 4.312861 | F16: 4.257381 | G16: 4.269811 | H16: 4.242913 | I16: 4.220734 | J16: 4.243922 | K16: 4.277688 | L16: 4.290828 | M16: 4.312197 | N16: 4.334578 | O16: 4.366941 | P16: 4.409552 | Q16: 4.452061 | R16: 4.493399 | S16: 4.538706 | T16: 4.588114 | U16: 4.642948 | V16: 4.702968 | W16: 4.755772 | X16: 4.803819 | Y16: 4.870983 | Z16: 4.935818 | AA16: 5.008786 | AB16: 5.07222 | AC16: 5.118502 | AD16: 5.178623 | AE16: 0.007
A17: Refinery | B17: Hydrogen Market Projections: Consumption: Industrial feedstocks: Refinery: Alternative Electricity and Transportation | C17: AEO.2026.ELECTRNP.CNSM_NA_NA_NA_HDG_REF_USA_MMMT.A | D17: MMmt | E17: 3.696665 | F17: 3.346764 | G17: 3.318238 | H17: 3.355242 | I17: 3.451893 | J17: 3.412094 | K17: 3.29056 | L17: 3.257257 | M17: 3.272487 | N17: 3.40652 | O17: 3.448085 | P17: 3.426255 | Q17: 3.524112 | R17: 3.5556 | S17: 3.56969 | T17: 3.529653 | U17: 3.524729 | V17: 3.501023 | W17: 3.523996 | X17: 3.641738 | Y17: 3.686538 | Z17: 3.680712 | AA17: 3.693948 | AB17: 3.686834 | AC17: 3.683995 | AD17: 3.674316 | AE17: 0
A18: Other Industrial | B18: Hydrogen Market Projections: Consumption: Industrial feedstocks: Other industrial: Alternative Electricity and Transportation | C18: AEO.2026.ELECTRNP.CNSM_NA_NA_NA_HDG_OTHIND_USA_MMMT.A | D18: MMmt | E18: 0.000361 | F18: 0.000417 | G18: 0.000455 | H18: 0.000528 | I18: 0.000617 | J18: 0.000717 | K18: 0.000833 | L18: 0.00097 | M18: 0.001116 | N18: 0.00128 | O18: 0.001483 | P18: 0.001695 | Q18: 0.001934 | R18: 0.002192 | S18: 0.002469 | T18: 0.002772 | U18: 0.003103 | V18: 0.003445 | W18: 0.003814 | X18: 0.004199 | Y18: 0.004606 | Z18: 0.005045 | AA18: 0.005508 | AB18: 0.005993 | AC18: 0.006503 | AD18: 0.007035 | AE18: 0.126
A19: Transportation | B19: Hydrogen Market Projections: Consumption: Transportation: Alternative Electricity and Transportation | C19: AEO.2026.ELECTRNP.CNSM_NA_NA_NA_HDG_TRAN_USA_MMMT.A | D19: MMmt | E19: 0.003101 | F19: 0.002982 | G19: 0.002845 | H19: 0.002701 | I19: 0.002563 | J19: 0.002413 | K19: 0.00227 | L19: 0.002117 | M19: 0.001968 | N19: 0.001819 | O19: 0.001671 | P19: 0.001528 | Q19: 0.001386 | R19: 0.001251 | S19: 0.001122 | T19: 0.001003 | U19: 0.000889 | V19: 0.000798 | W19: 0.000719 | X19: 0.000658 | Y19: 0.000589 | Z19: 0.000541 | AA19: 0.000507 | AB19: 0.000471 | AC19: 0.000448 | AD19: 0.000426 | AE19: -0.076
A20: Light-Duty Vehicles | B20: Hydrogen Market Projections: Consumption: Transportation: Light Duty Vehicles: Alternative Electricity and Transportation | C20: AEO.2026.ELECTRNP.CNSM_NA_NA_NA_HDG_TRANLDV_USA_MMMT.A | D20: MMmt | E20: 0.002852 | F20: 0.002735 | G20: 0.002599 | H20: 0.002455 | I20: 0.002318 | J20: 0.002169 | K20: 0.002027 | L20: 0.001878 | M20: 0.001731 | N20: 0.001587 | O20: 0.001444 | P20: 0.001304 | Q20: 0.001166 | R20: 0.001035 | S20: 0.000909 | T20: 0.000794 | U20: 0.000685 | V20: 0.000597 | W20: 0.000522 | X20: 0.000466 | Y20: 0.000401 | Z20: 0.000356 | AA20: 0.000325 | AB20: 0.000293 | AC20: 0.000273 | AD20: 0.000256 | AE20: -0.092
A21: Commercial Light Trucks | B21: Hydrogen Market Projections: Consumption: Transportation: Commercial Light Trucks: Alternative Electricity and Transportation | C21: AEO.2026.ELECTRNP.CNSM_NA_NA_NA_HDG_TRANCLT_USA_MMMT.A | D21: MMmt | E21: 0 | F21: 0 | G21: 0 | H21: 0 | I21: 0 | J21: 0 | K21: 0 | L21: 0 | M21: 0 | N21: 0 | O21: 0 | P21: 0 | Q21: 0 | R21: 0 | S21: 0 | T21: 0 | U21: 0 | V21: 0 | W21: 0 | X21: 0 | Y21: 0 | Z21: 0 | AA21: 0 | AB21: 0 | AC21: 0 | AD21: 0 | AE21: - -
A22: Freight Trucks | B22: Hydrogen Market Projections: Consumption: Transportation: Freight Trucks: Alternative Electricity and Transportation | C22: AEO.2026.ELECTRNP.CNSM_NA_NA_NA_HDG_TRANFT_USA_MMMT.A | D22: MMmt | E22: 0 | F22: 0 | G22: 0 | H22: 0 | I22: 0 | J22: 0 | K22: 0 | L22: 0 | M22: 0 | N22: 0 | O22: 0 | P22: 0 | Q22: 0 | R22: 0 | S22: 0 | T22: 0 | U22: 0 | V22: 0 | W22: 0 | X22: 0 | Y22: 0 | Z22: 0 | AA22: 0 | AB22: 0 | AC22: 0 | AD22: 0 | AE22: - -
A23: Bus Transportation | B23: Hydrogen Market Projections: Consumption: Transportation: Bus Transportation: Alternative Electricity and Transportation | C23: AEO.2026.ELECTRNP.CNSM_NA_NA_NA_HDG_TRANBT_USA_MMMT.A | D23: MMmt | E23: 0.000249 | F23: 0.000248 | G23: 0.000246 | H23: 0.000246 | I23: 0.000246 | J23: 0.000244 | K23: 0.000243 | L23: 0.000239 | M23: 0.000237 | N23: 0.000232 | O23: 0.000228 | P23: 0.000224 | Q23: 0.00022 | R23: 0.000217 | S23: 0.000212 | T23: 0.000209 | U23: 0.000205 | V23: 0.000201 | W23: 0.000197 | X23: 0.000193 | Y23: 0.000189 | Z23: 0.000185 | AA23: 0.000182 | AB23: 0.000178 | AC23: 0.000174 | AD23: 0.000171 | AE23: -0.015
A24: Electric Power | B24: Hydrogen Market Projections: Consumption: Electric: Alternative Electricity and Transportation | C24: AEO.2026.ELECTRNP.CNSM_NA_NA_NA_HDG_ELECPOWER_USA_MMMT.A | D24: MMmt | E24: 0 | F24: 0 | G24: 0 | H24: 0 | I24: 0 | J24: 0 | K24: 0 | L24: 0 | M24: 0 | N24: 0 | O24: 0 | P24: 0 | Q24: 0 | R24: 0 | S24: 0 | T24: 0 | U24: 0 | V24: 0 | W24: 0 | X24: 0 | Y24: 0 | Z24: 0 | AA24: 0 | AB24: 0 | AC24: 3.7e-05 | AD24: 4.1e-05 | AE24: - -
A25: Discrepancy | B25: Hydrogen Market Projections: Discrepancy: Alternative Electricity and Transportation | C25: AEO.2026.ELECTRNP.UNC_NA_NA_NA_HDG_NA_USA_MMMT.A | D25: MMmt | E25: 0.006994 | F25: 0.008986 | G25: 0.010403 | H25: 0.010129 | I25: 0.010777 | J25: 0.010723 | K25: 0.010774 | L25: 0.011164 | M25: 0.011257 | N25: 0.011143 | O25: 0.011283 | P25: 0.01123 | Q25: 0.011276 | R25: 0.011209 | S25: 0.011299 | T25: 0.011601 | U25: 0.011477 | V25: 0.011346 | W25: 0.011628 | X25: 0.011833 | Y25: 0.011945 | Z25: 0.012144 | AA25: 0.012102 | AB25: 0.012023 | AC25: 0.011968 | AD25: 0.011862 | AE25: 0.021
A26: Prices ($/MMBtu)
A27: Hydrogen average market spot price | B27: Hydrogen Market Projections: Average hydrogen market spot price: Alternative Electricity and Transportation | C27: AEO.2026.ELECTRNP.PRCE_HHP_NA_NA_HDG_NA_USA_Y13DLRPMMBTU.A | D27: 2025 $/MMBtu | E27: 9.060712 | F27: 9.448622 | G27: 9.442252 | H27: 9.578299 | I27: 9.660954 | J27: 10.354512 | K27: 10.63828 | L27: 10.782046 | M27: 10.856977 | N27: 10.885521 | O27: 10.817353 | P27: 10.987251 | Q27: 11.007936 | R27: 11.107589 | S27: 11.199713 | T27: 11.249643 | U27: 11.169209 | V27: 10.978045 | W27: 10.657317 | X27: 10.390149 | Y27: 10.252335 | Z27: 10.198344 | AA27: 10.207758 | AB27: 10.212843 | AC27: 10.180652 | AD27: 10.139825 | AE27: 0.005
A28: Delivered End-Use Prices ($/MMBtu)
A29: Industrial | B29: Hydrogen Market Projections: Delivered End-Use prices: Industrial: Alternative Electricity and Transportation | C29: AEO.2026.ELECTRNP.PRCE_NA_IDAL_NA_HDG_NA_USA_Y13DLRPMMBTU.A | D29: 2025 $/MMBtu | E29: 11.501233 | F29: 11.889143 | G29: 11.882795 | H29: 12.018814 | I29: 12.101516 | J29: 12.795125 | K29: 13.07889 | L29: 13.222679 | M29: 13.297702 | N29: 13.326265 | O29: 13.258114 | P29: 13.428031 | Q29: 13.448741 | R29: 13.548419 | S29: 13.640569 | T29: 13.690514 | U29: 13.610089 | V29: 13.418937 | W29: 13.098224 | X29: 12.831071 | Y29: 12.693266 | Z29: 12.639281 | AA29: 12.648698 | AB29: 12.653787 | AC29: 12.621601 | AD29: 12.580778 | AE29: 0.004
A30: Transportation | B30: Hydrogen Market Projections: Delivered End-Use prices: Transportation: Alternative Electricity and Transportation | C30: AEO.2026.ELECTRNP.PRCE_NA_TRN_NA_HDG_NA_USA_Y13DLRPMMBTU.A | D30: 2025 $/MMBtu | E30: 62.374836 | F30: 62.746746 | G30: 62.738457 | H30: 63.015266 | I30: 63.048782 | J30: 63.657555 | K30: 64.013809 | L30: 64.172546 | M30: 63.995075 | N30: 64.052963 | O30: 64.015572 | P30: 64.193886 | Q30: 64.200798 | R30: 64.280998 | S30: 64.31958 | T30: 64.383682 | U30: 64.349739 | V30: 64.173012 | W30: 63.824421 | X30: 63.489323 | Y30: 63.327377 | Z30: 63.308292 | AA30: 63.319298 | AB30: 63.316147 | AC30: 63.268272 | AD30: 63.212685 | AE30: 0.001
A31: Electric Power | B31: Hydrogen Market Projections: Delivered End-Use prices: Electric Power: Alternative Electricity and Transportation | C31: AEO.2026.ELECTRNP.PRCE_NA_ELEP_NA_HDG_NA_USA_Y13DLRPMMBTU.A | D31: 2025 $/MMBtu | E31: 11.501233 | F31: 11.889143 | G31: 11.882795 | H31: 12.018814 | I31: 12.101516 | J31: 12.795125 | K31: 13.07889 | L31: 13.222679 | M31: 13.297702 | N31: 13.326265 | O31: 13.258114 | P31: 13.428031 | Q31: 13.448741 | R31: 13.548419 | S31: 13.640569 | T31: 13.690514 | U31: 13.610089 | V31: 13.418937 | W31: 13.098224 | X31: 12.831071 | Y31: 12.693266 | Z31: 12.639281 | AA31: 12.648698 | AB31: 12.653787 | AC31: 12.621601 | AD31: 12.580778 | AE31: 0.004
A32: Production Capacity by Technology
A33: Steam Methane Reforming | B33: Hydrogen Market Projections: Production Capacity By Technology: Steam Methane Reforming: Alternative Electricity and Transportation | C33: AEO.2026.ELECTRNP.SUP_CAP_NA_NA_HDG_SMR_USA_MMMT.A | D33: MMmt | E33: 8.108752 | F33: 8.108752 | G33: 8.108752 | H33: 8.108752 | I33: 8.108752 | J33: 8.108752 | K33: 8.108752 | L33: 8.108752 | M33: 8.108752 | N33: 8.108752 | O33: 8.108752 | P33: 8.108752 | Q33: 8.108752 | R33: 8.108752 | S33: 8.108752 | T33: 8.108752 | U33: 8.108752 | V33: 8.108752 | W33: 8.108752 | X33: 8.108752 | Y33: 8.108752 | Z33: 8.108752 | AA33: 8.108752 | AB33: 8.108752 | AC33: 8.110478 | AD33: 8.115871 | AE33: 0
A34: Steam Methane Reforming with CCS | B34: Hydrogen Market Projections: Production Capacity By Technology: Steam Methane Reforming with CCS: Alternative Electricity and Transportation | C34: AEO.2026.ELECTRNP.SUP_CAP_NA_NA_HDG_SMRCCS_USA_MMMT.A | D34: MMmt | E34: 0.535454 | F34: 0.535454 | G34: 0.535454 | H34: 0.535454 | I34: 0.535454 | J34: 0.535454 | K34: 0.535454 | L34: 0.535454 | M34: 0.535454 | N34: 0.535454 | O34: 0.535454 | P34: 0.535454 | Q34: 0.535454 | R34: 0.535454 | S34: 0.535454 | T34: 0.535454 | U34: 0.535454 | V34: 0.535454 | W34: 0.535454 | X34: 0.535454 | Y34: 0.535454 | Z34: 0.535454 | AA34: 0.535454 | AB34: 0.535454 | AC34: 0.535454 | AD34: 0.535454 | AE34: 0
A35: Autothermal Reforming with CCS | B35: Hydrogen Market Projections: Production Capacity By Technology: Autothermal Reforming with CCS: Alternative Electricity and Transportation | C35: AEO.2026.ELECTRNP.SUP_CAP_NA_NA_HDG_ATRCCS_USA_MMMT.A | D35: MMmt | E35: 0 | F35: 0.170512 | G35: 0.170512 | H35: 0.170512 | I35: 0.401204 | J35: 0.401204 | K35: 0.401204 | L35: 0.401204 | M35: 0.401204 | N35: 0.401204 | O35: 0.401204 | P35: 0.401204 | Q35: 0.401204 | R35: 0.401204 | S35: 0.401204 | T35: 0.401204 | U35: 0.401204 | V35: 0.401204 | W35: 0.401204 | X35: 0.401204 | Y35: 0.401204 | Z35: 0.401204 | AA35: 0.401204 | AB35: 0.401204 | AC35: 0.401204 | AD35: 0.401204 | AE35: - -
A36: Electrolysis | B36: Hydrogen Market Projections: Production Capacity By Technology: Electrolysis: Alternative Electricity and Transportation | C36: AEO.2026.ELECTRNP.SUP_CAP_NA_NA_HDG_GRDELEC_USA_MMMT.A | D36: MMmt | E36: 0.011264 | F36: 0.074205 | G36: 0.090132 | H36: 0.090132 | I36: 0.090132 | J36: 0.090132 | K36: 0.090132 | L36: 0.090132 | M36: 0.090132 | N36: 0.090132 | O36: 0.090132 | P36: 0.090132 | Q36: 0.090132 | R36: 0.090132 | S36: 0.090132 | T36: 0.090132 | U36: 0.090132 | V36: 0.090132 | W36: 0.090132 | X36: 0.090132 | Y36: 0.090132 | Z36: 0.090132 | AA36: 0.090132 | AB36: 0.090132 | AC36: 0.090132 | AD36: 0.090132 | AE36: 0.087

Sheet GREET1 Fuel_Specs
A1: Specifications of Fuels, Global Warming Potentials of Greenhouse Gases, and Carbon and Sulfur Ratios of Pollutants
A2: 1) Specifications of Fuels
A3: Fuel | B3: Heating Value | E3: Density | F3: C ratio | G3: S ratio | H3: S ratio
B4: Calculation: LHV | C4: LHV | D4: HHV | F4: (% by wt) | G4: (ppm by wt) | H4: Actual ratio by wt | I4: LHV/HHV
A5: Use LHV or HHV in calculations? | B5: 1 | C5: 1 -- LHV; 2 -- HHV
A6: Liquid Fuels: | B6: Btu/gal | C6: Btu/gal | D6: Btu/gal | E6: grams/gal
A7: Crude oil | B7: 129670 | C7: 129670 | D7: 138350 | E7: 3205 | F7: 0.853 | G7: 16000 | H7: 0.016 | I7: 0.93726057
A8: Synthetic crude oil (SCO) | B8: 135084.91 | C8: 135084.91 | D8: 144475.84 | E8: 3266 | F8: 0.85562069 | G8: 1800 | H8: 0.0018 | I8: 0.935
A9: Bitumen | B9: 152370.9 | C9: 152370.9 | D9: 162963.53 | E9: 3839.6821 | F9: 0.83 | G9: 48000 | H9: 0.048 | I9: 0.935
A10: Dilbit (After Recovery) | B10: 152370.9 | C10: 152370.9 | D10: 162963.53 | E10: 3839.6821 | F10: 0.83 | G10: 48000 | H10: 0.048 | I10: 0.935
A11: Dilbit (Before Recovery) | B11: 145194.19 | C11: 145194.19 | D11: 155287.9 | E11: 3500.4775 | F11: 0.83245886 | G11: 37227.39 | H11: 0.03722739 | I11: 0.935
A12: Diluent | B12: 128448.53 | C12: 128448.53 | D12: 137378.1 | E12: 2709 | F12: 0.84059084 | G12: 1600 | H12: 0.0016 | I12: 0.935
A13: Shale Oil (Bakken) | B13: 125600.91 | C13: 125600.91 | D13: 134008.53 | E13: 3087.2372 | F13: 0.853 | G13: 16000 | H13: 0.016 | I13: 0.93726057
A14: Shale Oil (Eagle Ford) | B14: 122492.61 | C14: 122492.61 | D14: 130692.16 | E14: 2984.0427 | F14: 0.853 | G14: 16000 | H14: 0.016 | I14: 0.93726057
A15: Gasoline blendstock | B15: 116090 | C15: 116090 | D15: 124340 | E15: 2819 | F15: 0.863 | G15: 10 | H15: 1e-05 | I15: 0.93364967
A16: Gasoline | B16: 112193.52 | C16: 112193.52 | D16: 120438.62 | E16: 2835.562 | F16: 0.82778547 | G16: 9.0261788 | H16: 9.0261788e-06 | I16: 0.93154106
A17: CA gasoline | B17: 112193.52 | C17: 112193.52 | D17: 120438.62 | E17: 2835.562 | F17: 0.82778547 | G17: 9.0261788 | H17: 9.0261788e-06 | I17: 0.93154106
A18: High Octane Fuel (E25) | B18: 106150 | C18: 106150 | D18: 114387.5 | E18: 2861.25 | F18: 0.77775 | G18: 7.6425 | H18: 7.6425e-06 | I18: 0.92798601
... A20: U.S. conventional diesel | B20: 128450 | C20: 128450 | D20: 137380 | E20: 3167 | F20: 0.865 | G20: 200 | H20: 0.0002 | I20: 0.93499782
A21: CA diesel | B21: 129487.85 | C21: 129487.85 | D21: 138490 | E21: 3206 | F21: 0.871 | G21: 11 | H21: 1.1e-05
A22: Diesel for non-road engines | B22: 128450 | C22: 128450 | D22: 137380 | E22: 3167 | F22: 0.865 | G22: 11 | H22: 1.1e-05 | I22: 0.93499782
A23: Low-sulfur diesel | B23: 129487.85 | C23: 129487.85 | D23: 138490 | E23: 3206 | F23: 0.871 | G23: 11 | H23: 1.1e-05 | I23: 0.93499782
A24: Petroleum naphtha | B24: 116920 | C24: 116920 | D24: 125080 | E24: 2745 | F24: 0.85 | G24: 1 | H24: 1e-06 | I24: 0.93476175
A25: Low Octane Gasoline-Like Fuel (LOF) | B25: 118237.43 | C25: 118237.43 | D25: 126586.16 | E25: 2833.857 | F25: 0.85315639 | G25: 10 | H25: 1e-05 | I25: 0.93404711
A26: Conventional Jet Fuel | B26: 124307.03 | C26: 124307.03 | D26: 132948.69 | E26: 3035.8996 | F26: 0.862 | G26: 700 | H26: 0.0007 | I26: 0.93500004
A27: ULS Jet Fuel | B27: 123041.23 | C27: 123041.23 | D27: 131594.89 | E27: 2998.0455 | F27: 0.86 | G27: 11 | H27: 1.1e-05 | I27: 0.93500004
A28: NG-based FT naphtha | B28: 111520 | C28: 111520 | D28: 119740 | E28: 2651 | F28: 0.842 | G28: 0 | H28: 0 | I28: 0.93135126
A29: Residual oil | B29: 140352.52 | C29: 140352.52 | D29: 150110 | E29: 3752 | F29: 0.868 | G29: 5000 | H29: 0.005 | I29: 0.93499782
A30: Bunker fuel for ocean tanker | B30: 140352.52 | C30: 140352.52 | D30: 150110 | E30: 3752 | F30: 0.868 | G30: 27000 | H30: 0.027 | I30: 0.93499782
A31: Methanol | B31: 57250 | C31: 57250 | D31: 65200 | E31: 3006 | F31: 0.375 | G31: 0 | H31: 0 | I31: 0.87806748
A32: Ethanol | B32: 76330 | C32: 76330 | D32: 84530 | E32: 2988 | F32: 0.522 | G32: 0.57000011 | H32: 5.7000011e-07 | I32: 0.90299302
A33: Butanol | B33: 99837 | C33: 99837 | D33: 108458 | E33: 3065 | F33: 0.6486 | G33: 0 | H33: 0 | I33: 0.92051301
... A56: Propane | B56: 84250 | C56: 84250 | D56: 91420 | E56: 1920 | F56: 0.818 | G56: 0 | H56: 0 | I56: 0.92157077
A57: Natural gas liquids | B57: 83686.112 | C57: 83686.112 | D57: 90050 | E57: 2532 | G57: 0 | H57: 0 | I57: 0.9293294
A58: n-Hexane | B58: 105124.8 | C58: 105124.8 | D58: 112166.3 | E58: 2478.7 | F58: 0.836251 | G58: 0 | H58: 0 | I58: 0.93722268
A59: Gaseous Fuels (at 32F and 1atm): | B59: Btu/ft3 | C59: Btu/ft3 | D59: Btu/ft3 | E59: gms/ft3 | I59: LHV/HHV
A60: Natural gas | B60: 983 | C60: 983 | D60: 1089 | E60: 22 | F60: 0.724 | G60: 6 | H60: 6e-06 | I60: 0.90266299
A61: Pure Methane | B61: 962.18505 | C61: 962.18505 | D61: 1068.0254 | E61: 20.303179 | F61: 0.75 | G61: 0 | H61: 0 | I61: 0.9009009
A62: Gaseous hydrogen | B62: 290 | C62: 290 | D62: 343 | E62: 2.55 | F62: 0 | G62: 0 | H62: 0 | I62: 0.84548105
A63: Carbon Dioxide | E63: 55.97783 | F63: 0.27272727 | G63: 0 | H63: 0
A64: Still gas (in refineries) | B64: 1159.2737 | C64: 1159.2737 | D64: 1279.7381 | E64: 25.019852 | F64: 0.76981386 | G64: 6 | H64: 6e-06 | I64: 0.9058679
A65: Solid Fuels: | B65: Btu/ton | C65: Btu/ton | D65: Btu/ton | I65: LHV/HHV
A66: Coal Mix for Electricity Generation | B66: 19474169 | C66: 19474169 | D66: 20673610 | F66: 0.5857111 | G66: 10455.988 | H66: 0.010455988
A67: Bituminous coal | B67: 22639320 | C67: 22639320 | D67: 23633493 | F67: 0.612 | G67: 15352.093 | H67: 0.015352093 | I67: 0.95793373
A68: Subbituminous coal | B68: 16085444 | C68: 16085444 | D68: 17449320 | F68: 0.537 | G68: 3568.2537 | H68: 0.0035682537 | I68: 0.92183789
A69: Lignite coal | B69: 10805183 | C69: 10805183 | D69: 12992302 | F69: 0.491 | G69: 9064.2347 | H69: 0.0090642347 | I69: 0.83166038
A70: Synthetic coal | B70: 22639320 | C70: 22639320 | D70: 23633493 | F70: 0.8064205 | G70: 16142.739 | H70: 0.016142739 | I70: 0.95793373
A71: Waste coal | B71: 9945646.3 | C71: 9945646.3 | D71: 11958783 | F71: 0.32642858 | G71: 9064.2347 | H71: 0.0090642347 | I71: 0.83166038
A72: Pet Coke | B72: 26949429 | C72: 26949429 | D72: 28595925 | F72: 0.8667 | G72: 45137.714 | H72: 0.045137714 | I72: 0.94242199
A73: Tire Derived Fuel | B73: 26664354 | C73: 26664354 | D73: 28293434 | F73: 0.48798697 | G73: 45137.714 | H73: 0.045137714 | I73: 0.94242199
A74: Coking coal | B74: 24599422 | C74: 24599422 | D74: 25679670 | F74: 0.747 | G74: 11800 | H74: 0.0118 | I74: 0.95793373
A75: Catalyst Coke | B75: 28385750 | C75: 28385750 | D75: 30120000 | F75: 0.86413234 | G75: 45137.714 | H75: 0.045137714 | I75: 0.94242199
A76: Willow | B76: 15396000 | C76: 15396000 | D76: 16524000 | F76: 0.487 | G76: 500 | H76: 0.0005 | I76: 0.93173566
A77: Poplar | B77: 15929000 | C77: 15929000 | D77: 17062000 | F77: 0.501 | G77: 200 | H77: 0.0002 | I77: 0.93359512
A78: Switchgrass | B78: 14447000 | C78: 14447000 | D78: 15583000 | F78: 0.466 | G78: 1100 | H78: 0.0011 | I78: 0.92710004
... A82: Clean Pine | B82: 15929000 | C82: 15929000 | D82: 17062000 | F82: 0.501 | G82: 200 | H82: 0.0002 | I82: 0.93359512
A83: Yard trimming waste | B83: 15000000 | C83: 15000000 | F83: 0.478 | G83: 400 | H83: 0.0004
A84: Sugarcane straw | B84: 13454049 | C84: 13454049 | D84: 15774000 | F84: 0.5 | I84: 0.85292563
A85: Sugarcane bagasse | B85: 12381771 | C85: 12381771 | D85: 14062678 | F85: 0.463 | I85: 0.88047037
A86: Bio-char | B86: 18916911 | C86: 18916911 | D86: 18916911 | F86: 0.512 | G86: 0 | H86: 0 | I86: 1
A87: Grain sorghum bagasse | B87: 12781599 | C87: 12781599 | D87: 14131556 | F87: 0.3934 | G87: 0 | H87: 0 | I87: 0.90447216
A88: Sweet sorghum bagasse | B88: 14409931 | C88: 14409931 | D88: 15305245 | F88: 0.41985 | G88: 0 | H88: 0 | I88: 0.94150281
A89: Forage sorghum bagasse | B89: 14409931 | C89: 14409931 | D89: 15305245 | F89: 0.41985 | G89: 0 | H89: 0 | I89: 0.94150281
A90: Municipal solid waste (defined by EISA) | B90: 11209639 | C90: 11209639 | D90: 13583445 | F90: 0.49161518 | G90: 1765.2251 | H90: 0.0017652251 | I90: 0.82524272
A91: Convertible municipal solid waste | B91: 14155275 | C91: 14155275 | D91: 16144033 | F91: 0.5049151 | G91: 1787.3101 | H91: 0.0017873101 | I91: 0.87681159
A92: Asphalt | B92: 152370.9 | C92: 152370.9 | D92: 162963.53 | E92: 3839.6821 | F92: 0.83 | G92: 48000 | H92: 0.048 | I92: 0.935
A93: Lubricants | B93: 144230 | E93: 3785.411 | F93: 0.80800504 | G93: 3510
A95: 2) Global Warming Potentials of Greenhouse Gases: relative to CO2
A96: Metrics for Carbon Dioxide, Methane, Nitrous Oxide
A97: AR Edition/Type | B97: AR5/GWP | C97: AR5/GWP | D97: AR5/GWP | E97: AR5/GTP | F97: AR5/GTP | G97: AR4/GWP | H97: AR4/GWP | I97: AR3/GWP | J97: AR3/GWP | K97: AR2/GWP | L97: AR2/GWP | M97: AR1/GWP | N97: AR1/GWP
A98: Time Horizon (YR) | B98: 100 | C98: 100 | D98: 20 | E98: 100 | F98: 20 | G98: 100 | H98: 20 | I98: 100 | J98: 20 | K98: 100 | L98: 20 | M98: 100 | N98: 20
A99: CO2 | B99: 1 | C99: 1 | D99: 1 | E99: 1 | F99: 1 | G99: 1 | H99: 1 | I99: 1 | J99: 1 | K99: 1 | L99: 1 | M99: 1 | N99: 1
A100: CH4 | B100: 30 | C100: 30 | D100: 85 | E100: 6 | F100: 68 | G100: 25 | H100: 72 | I100: 23 | J100: 62 | K100: 21 | L100: 56 | M100: 21 | N100: 63
A101: N2O | B101: 265 | C101: 265 | D101: 264 | E101: 234 | F101: 277 | G101: 298 | H101: 289 | I101: 296 | J101: 275 | K101: 310 | L101: 280 | M101: 290 | N101: 270
A103: Metrics for Near Term Climate Forcers
A104: Type | B104: None | C104: None | D104: GWP | E104: GWP | F104: GTP | G104: GTP
A105: Time Horizon (YR) | B105: 100 | D105: 100 | E105: 20 | F105: 100 | G105: 20
A106: VOC | B106: 0 | C106: 0 | D106: 4.5 | E106: 14 | F106: 0.66 | G106: 7.5
A107: CO | B107: 0 | C107: 0 | D107: 2.65 | E107: 7.65 | F107: 0.42 | G107: 4.9
A108: NOx | B108: 0 | C108: 0 | D108: -11 | E108: 19 | F108: -2.9 | G108: -87
A109: BC | B109: 0 | C109: 0 | D109: 900 | E109: 3200 | F109: 130 | G109: 920
A110: OC | B110: 0 | C110: 0 | D110: -69 | E110: -240 | F110: -10 | G110: -71
A112: 3) Carbon and Sulfur Ratios of Pollutants
A113: Carbon ratio of VOC | B113: 0.85
A114: Carbon ratio of CO | B114: 0.42857143
A115: Carbon ratio of CH4 | B115: 0.75
A116: Carbon ratio of CO2 | B116: 0.27272727
A117: Sulfur ratio of SO2 | B117: 0.5
A119: 4) Regulated Sulfur Content in Gasoline Blendstock and Conventional Diesel over Time
B121: 10 | F121: 200 | J121: 11 | N121: 11 | R121: 27000 | V121: 1000
B122: 10 | F122: 200 | J122: 11 | N122: 11 | R122: 27000 | V122: 1000
B123: 5-year period | C123: Sulfur Content in Gasoline Blendstock (ppm) | D123: Relative Change (to yr 2010) | F123: 5-year period | G123: Sulfur Content in Conventional Diesel (ppm) | H123: Relative Change (to yr 2010) | J123: 5-year period | K123: Sulfur Content in California Diesel (ppm) | L123: Relative Change (to yr 2010) | N123: 5-year period | O123: Sulfur Content in non-Road Diesel (ppm) | P123: Relative Change (to yr 2010) | R123: 5-year period | S123: Sulfur Content in Residual Oil (ppm) | T123: Relative Change (to yr 2010) | V123: 5-year period | W123: Sulfur Content in Marine Disttillate (ppm) | X123: Relative Change (to yr 2010)
B124: 1990 | C124: 500 | D124: 19.607843 | F124: 1990 | G124: 600 | H124: 3 | J124: 1990 | K124: 350 | L124: 31.818182 | N124: 1990 | O124: 2283 | P124: 14.006135 | R124: 1990 | S124: 27000 | T124: 1 | V124: 1990 | W124: 2000 | X124: 1
B125: 1995 | C125: 340 | D125: 13.333333 | F125: 1995 | G125: 350 | H125: 1.75 | J125: 1995 | K125: 200 | L125: 18.181818 | N125: 1995 | O125: 2283 | P125: 14.006135 | R125: 1995 | S125: 27000 | T125: 1 | V125: 1995 | W125: 2000 | X125: 1
B126: 2000 | C126: 200 | D126: 7.8431373 | F126: 2000 | G126: 200 | H126: 1 | J126: 2000 | K126: 120 | L126: 10.909091 | N126: 2000 | O126: 2283 | P126: 14.006135 | R126: 2000 | S126: 27000 | T126: 1 | V126: 2000 | W126: 2000 | X126: 1
B127: 2005 | C127: 25.5 | D127: 1 | F127: 2005 | G127: 200 | H127: 1 | J127: 2005 | K127: 120 | L127: 10.909091 | N127: 2005 | O127: 2283 | P127: 14.006135 | R127: 2005 | S127: 27000 | T127: 1 | V127: 2005 | W127: 2000 | X127: 1
B128: 2010 | C128: 25.5 | D128: 1 | F128: 2010 | G128: 200 | H128: 1 | J128: 2010 | K128: 11 | L128: 1 | N128: 2010 | O128: 163 | P128: 1 | R128: 2010 | S128: 27000 | T128: 1 | V128: 2010 | W128: 2000 | X128: 1
B129: 2015 | C129: 25.5 | D129: 1 | F129: 2015 | G129: 200 | H129: 1 | J129: 2015 | K129: 11 | L129: 1 | N129: 2015 | O129: 11 | P129: 0.067484663 | R129: 2015 | S129: 27000 | T129: 1 | V129: 2015 | W129: 1000 | X129: 0.5
B130: 2017 | C130: 10 | D130: 0.39215686 | F130: 2020 | G130: 200 | H130: 1 | J130: 2020 | K130: 11 | L130: 1 | N130: 2020 | O130: 11 | P130: 0.067484663 | R130: 2020 | S130: 5000 | T130: 0.185 | V130: 2020 | W130: 1000 | X130: 0.5
B131: 2020 | C131: 10 | D131: 0.39215686
...

Sheet Start Year Data
A1: Fuel | B1: Production | C1: Imports | D1: Exports | E1: Domestic Use | F1: Unit | G1: Domestic use also includes change in domestic inventories, which should average to zero over multi-year timeframes.
A2: electricity (not used in this variable)
A3: hard coal | B3: ='Uranium, Coal, MSW, Hydrogen'!B13 -> 472.52337 | C3: ='Uranium, Coal, MSW, Hydrogen'!C13 -> 1.997711 | D3: ='Uranium, Coal, MSW, Hydrogen'!D13 -> 108.32638 | E3: =B3+C3-D3 -> 366.19469 | F3: million short tons
A4: natural gas | B4: ='AEO 2026 Table 1'!E9 -> 40.570412 | C4: ='AEO 2026 Table 1'!E20 -> 3.256896 | D4: ='AEO 2026 Table 1'!E25 -> 8.975658 | E4: =B4+C4-D4 -> 34.85165 | F4: quads
A5: uranium | B5: ='Uranium, Coal, MSW, Hydrogen'!B3 -> 0.677 | C5: ='Uranium, Coal, MSW, Hydrogen'!C3 -> 55.223 | D5: ='Uranium, Coal, MSW, Hydrogen'!D3 -> 0 | E5: =B5+C5-D5 -> 55.9 | F5: million pounds U3O8
A6: hydro (is not a fuel)
A7: wind (is not a fuel)
A8: solar (is not a fuel)
A9: biomass | B9: ='Biomass Data'!A18 -> 13341865 | C9: ='Biomass Data'!A26 -> 0 | D9: ='Biomass Data'!A21 -> 8871212 | E9: =B9+C9-D9 -> 4470653 | F9: short tons
A10: petroleum gasoline | B10: =SUM('Petroleum and Biofuels '!E37:F37) -> 3523246 | C10: ='Petroleum and Biofuels '!G37 -> 39911 | D10: ='Petroleum and Biofuels '!L37 -> 291546 | E10: =B10+C10-D10 -> 3271611 | F10: thousand barrels
A11: petroleum diesel | B11: =SUM('Petroleum and Biofuels '!E43:F43) -> 1806591 | C11: ='Petroleum and Biofuels '!G43 -> 53868 | D11: ='Petroleum and Biofuels '!L43 -> 472631 | E11: =B11+C11-D11 -> 1387828 | F11: thousand barrels
A12: biofuel gasoline | B12: =SUM('Petroleum and Biofuels '!E25:F25) -> 386316 | C12: =IF(ISNUMBER('Petroleum and Biofuels '!G25)=FALSE,0,'Petroleum and Biofuels '!G25) -> 0 | D12: ='Petroleum and Biofuels '!L25 -> 46223 | E12: =B12+C12-D12 -> 340093 | F12: thousand barrels
A13: biofuel diesel | B13: =SUM('Petroleum and Biofuels '!E26:F26) -> 124142 | C13: ='Petroleum and Biofuels '!G26 -> 22625 | D13: ='Petroleum and Biofuels '!L26 -> 4303 | E13: =B13+C13-D13 -> 142464 | F13: thousand barrels
A14: jet fuel or kerosene | B14: =SUM('Petroleum and Biofuels '!E41:F42) -> 665538 | C14: =SUM('Petroleum and Biofuels '!G41:G42) -> 38457 | D14: =SUM('Petroleum and Biofuels '!L41:L42) -> 78860 | E14: =B14+C14-D14 -> 625135 | F14: thousand barrels
A15: heat (not used in this variable)
A16: geothermal (is not a fuel)
A17: lignite | B17: ='Uranium, Coal, MSW, Hydrogen'!B14 -> 40.016958 | C17: ='Uranium, Coal, MSW, Hydrogen'!C14 -> 0 | D17: ='Uranium, Coal, MSW, Hydrogen'!D14 -> 0 | E17: =B17+C17-D17 -> 40.016958 | F17: million short tons
A18: crude oil | B18: ='Petroleum and Biofuels '!C6 -> 4843858 | C18: ='Petroleum and Biofuels '!G6 -> 2411095 | D18: ='Petroleum and Biofuels '!L6 -> 1498096 | E18: =B18+C18-D18 -> 5756857 | F18: thousand barrels
A19: heavy fuel oil | B19: =SUM('Petroleum and Biofuels '!C47:F47) -> 115747 | C19: ='Petroleum and Biofuels '!G47 -> 40046 | D19: ='Petroleum and Biofuels '!L47 -> 50003 | E19: =B19+C19-D19 -> 105790 | F19: thousand barrels
A20: LPG propane or butane | B20: =SUM('Petroleum and Biofuels '!C9:F11) -> 2217544 | C20: =SUM('Petroleum and Biofuels '!G9:G11) -> 55423 | D20: =SUM('Petroleum and Biofuels '!L9:L11) -> 1004275 | E20: =B20+C20-D20 -> 1268692 | F20: thousand barrels
A21: municipal solid waste | B21: ='Uranium, Coal, MSW, Hydrogen'!A18 -> 292 | C21: 0 | D21: 0 | E21: =B21+C21-D21 -> 292 | F21: million short tons
A22: hydrogen | B22: ='Uranium, Coal, MSW, Hydrogen'!A31 -> 5.74 | C22: 0 | D22: 0 | E22: =B22+C22-D22 -> 5.74 | F22: million metric tons
A24: Converted to BTU
A25: Fuel | B25: Production | C25: Imports | D25: Exports | E25: Domestic Use | F25: Unit | H25: Conversion Factors
A26: electricity (not used in this variable)
A27: hard coal | B27: =B3*$H27 -> 9.2890666e+15 | C27: =C3*$H27 -> 39271857858308 | D27: =D3*$H27 -> 2.1295264e+15 | E27: =E3*$H27 -> 7.198812e+15 | F27: BTU | H27: ='AEO Conversion Factors'!$C66*10^12 -> 19658428000000 | I27: BTU per | J27: million short tons
A28: natural gas | B28: =B4*$H28 -> 4.0570412e+16 | C28: =C4*$H28 -> 3.256896e+15 | D28: =D4*$H28 -> 8.975658e+15 | E28: =E4*$H28 -> 3.485165e+16 | F28: BTU | H28: =10^15 -> 1e+15 | I28: BTU per | J28: quad
A29: uranium | B29: =B5*$H29 -> 1.2186e+14 | C29: =C5*$H29 -> 9.94014e+15 | D29: =D5*$H29 -> 0 | E29: =E5*$H29 -> 1.0062e+16 | F29: BTU | H29: =10^6*1.8*10^8 -> 180000000000000 | I29: BTU per | J29: million pounds U3O8
A30: hydro (is not a fuel)
A31: wind (is not a fuel)
A32: solar (is not a fuel)
A33: biomass | B33: =B9*$H33 -> 238899434690000 | C33: =C9*$H33 -> 0 | D33: =D9*$H33 -> 158847922072000 | E33: =E9*$H33 -> 80051512618000 | F33: BTU | H33: ='GREET1 Fuel_Specs'!$D$81 -> 17906000 | I33: BTU per | J33: short ton
A34: petroleum gasoline | B34: =B10*$H34 -> 1.7798421e+16 | C34: =C10*$H34 -> 201618837721000 | D34: =D10*$H34 -> 1.4728061e+15 | E34: =E10*$H34 -> 1.6527233e+16 | F34: BTU | H34: ='AEO Conversion Factors'!$C32*10^9 -> 5051711000 | I34: BTU per | J34: thousand barrels
A35: petroleum diesel | B35: =B11*$H35 -> 1.0523393e+16 | C35: =C11*$H35 -> 313781100000000 | D35: =D11*$H35 -> 2.7530756e+15 | E35: =E11*$H35 -> 8.0840981e+15 | F35: BTU | H35: ='AEO Conversion Factors'!$C19*10^9 -> 5825000000 | I35: BTU per | J35: thousand barrels
A36: biofuel gasoline | B36: =B12*$H36 -> 1.5431057e+15 | C36: =C12*$H36 -> 0 | D36: =D12*$H36 -> 184633752099000 | E36: =E12*$H36 -> 1.3584719e+15 | F36: BTU | H36: ='AEO Conversion Factors'!$C29*10^9 -> 3994413000 | I36: BTU per | J36: thousand barrels
A37: biofuel diesel | B37: =B13*$H37 -> 665276978000000 | C37: =C13*$H37 -> 121247375000000 | D37: =D13*$H37 -> 23059777000000 | E37: =E13*$H37 -> 763464576000000 | F37: BTU | H37: ='AEO Conversion Factors'!$C18*10^9 -> 5359000000 | I37: BTU per | J37: thousand barrels
A38: jet fuel or kerosene | B38: =B14*$H38 -> 3.7736005e+15 | C38: =C14*$H38 -> 218051190000000 | D38: =D14*$H38 -> 447136200000000 | E38: =E14*$H38 -> 3.5445154e+15 | F38: BTU | H38: ='AEO Conversion Factors'!$C30*10^9 -> 5670000000 | I38: BTU per | J38: thousand barrels
A39: heat (not used in this variable)
A40: geothermal (is not a fuel)
A41: lignite | B41: =B17*$H41 -> 5.199124e+14 | C41: =C17*$H41 -> 0 | D41: =D17*$H41 -> 0 | E41: =E17*$H41 -> 5.199124e+14 | F41: BTU | H41: ='GREET1 Fuel_Specs'!$D$69*10^6 -> 1.2992302e+13 | I41: BTU per | J41: million short tons
A42: crude oil | B42: =B18*$H42 -> 2.7585282e+16 | C42: =C18*$H42 -> 1.3730943e+16 | D42: =D18*$H42 -> 8.5315054e+15 | E42: =E18*$H42 -> 3.2784719e+16 | F42: BTU | H42: ='AEO Conversion Factors'!C48*10^9 -> 5694899000 | I42: BTU per | J42: thousand barrels
A43: heavy fuel oil | B43: =B19*$H43 -> 727701389000000 | C43: =C19*$H43 -> 251769202000000 | D43: =D19*$H43 -> 314368861000000 | E43: =E19*$H43 -> 665101730000000 | F43: BTU | H43: ='AEO Conversion Factors'!$C41*10^9 -> 6287000000 | I43: BTU per | J43: thousand barrels
A44: LPG propane or butane | B44: =B20*$H44 -> 8.5136393e+15 | C44: =C20*$H44 -> 212781090060000 | D44: =D20*$H44 -> 3.8556327e+15 | E44: =E20*$H44 -> 4.8707877e+15 | F44: BTU | H44: ='GREET1 Fuel_Specs'!$D$36*10^3*42 -> 3839220000 | I44: BTU per | J44: thousand barrels
A45: municipal solid waste | B45: =B21*$H45 -> 3.9663658e+15 | C45: =C21*$H45 -> 0 | D45: =D21*$H45 -> 0 | E45: =E21*$H45 -> 3.9663658e+15 | F45: BTU | H45: ='GREET1 Fuel_Specs'!$D$90*10^6 -> 1.3583445e+13 | I45: BTU per | J45: million short tons
A46: hydrogen | B46: =B22*$H46 -> 772086274509804 | C46: =C22*$H46 -> 0 | D46: =D22*$H46 -> 0 | E46: =E22*$H46 -> 772086274509804 | F46: BTU | H46: ='GREET1 Fuel_Specs'!$D$62/'GREET1 Fuel_Specs'!$E$62*10^12 -> 1.345098e+14 | I46: BTU per | J46: million metric tons
H48: ='AEO Conversion Factors'!C48 -> 5.694899
H49: =10^9 -> 1000000000
H50: =H48*H49 -> 5694899000
H51: =H50/H42 -> 1

Sheet Time Series Scaling Factors
A1: Production Scaling Factors
B2: 2025 | C2: 2026 | D2: 2027 | E2: 2028 | F2: 2029 | G2: 2030 | H2: 2031 | I2: 2032 | J2: 2033 | K2: 2034 | L2: 2035 | M2: 2036 | N2: 2037 | O2: 2038 | P2: 2039 | Q2: 2040 | R2: 2041 | S2: 2042 | T2: 2043 | U2: 2044 | V2: 2045 | W2: 2046 | X2: 2047 | Y2: 2048 | Z2: 2049 | AA2: 2050
A3: electricity (not used in this variable) | B3: 0 | C3: 0 | D3: 0 | E3: 0 | F3: 0 | G3: 0 | H3: 0 | I3: 0 | J3: 0 | K3: 0 | L3: 0 | M3: 0 | N3: 0 | O3: 0 | P3: 0 | Q3: 0 | R3: 0 | S3: 0 | T3: 0 | U3: 0 | V3: 0 | W3: 0 | X3: 0 | Y3: 0 | Z3: 0 | AA3: 0
A4: hard coal | B4: ='AEO 2026 Table 1'!E$10/'AEO 2026 Table 1'!$E$10 -> 1 | C4: ='AEO 2026 Table 1'!F$10/'AEO 2026 Table 1'!$E$10 -> 0.97530688 | D4: ='AEO 2026 Table 1'!G$10/'AEO 2026 Table 1'!$E$10 -> 0.94217824 | E4: ='AEO 2026 Table 1'!H$10/'AEO 2026 Table 1'!$E$10 -> 0.88468935 | F4: ='AEO 2026 Table 1'!I$10/'AEO 2026 Table 1'!$E$10 -> 0.86350146 | G4: ='AEO 2026 Table 1'!J$10/'AEO 2026 Table 1'!$E$10 -> 0.87296349 | H4: ='AEO 2026 Table 1'!K$10/'AEO 2026 Table 1'!$E$10 -> 0.78588696 | I4: ='AEO 2026 Table 1'!L$10/'AEO 2026 Table 1'!$E$10 -> 0.76483944 | ... AA4: ='AEO 2026 Table 1'!AD$10/'AEO 2026 Table 1'!$E$10 -> 0.60360634
A5: natural gas | B5: ='AEO 2026 Table 1'!E9/'AEO 2026 Table 1'!$E$9 -> 1 | C5: ='AEO 2026 Table 1'!F9/'AEO 2026 Table 1'!$E$9 -> 0.99319736 | D5: ='AEO 2026 Table 1'!G9/'AEO 2026 Table 1'!$E$9 -> 0.97911377 | E5: ='AEO 2026 Table 1'!H9/'AEO 2026 Table 1'!$E$9 -> 0.99826258 | F5: ='AEO 2026 Table 1'!I9/'AEO 2026 Table 1'!$E$9 -> 1.0078066 | G5: ='AEO 2026 Table 1'!J9/'AEO 2026 Table 1'!$E$9 -> 1.03591 | H5: ='AEO 2026 Table 1'!K9/'AEO 2026 Table 1'!$E$9 -> 1.0643479 | I5: ='AEO 2026 Table 1'!L9/'AEO 2026 Table 1'!$E$9 -> 1.0909308 | ... AA5: ='AEO 2026 Table 1'!AD9/'AEO 2026 Table 1'!$E$9 -> 1.3148032
A6: uranium | B6: ='AEO 2026 Table 1'!E11/'AEO 2026 Table 1'!$E$11 -> 1 | C6: ='AEO 2026 Table 1'!F11/'AEO 2026 Table 1'!$E$11 -> 1.0226056 | D6: ='AEO 2026 Table 1'!G11/'AEO 2026 Table 1'!$E$11 -> 1.0163407 | E6: ='AEO 2026 Table 1'!H11/'AEO 2026 Table 1'!$E$11 -> 1.020724 | F6: ='AEO 2026 Table 1'!I11/'AEO 2026 Table 1'!$E$11 -> 1.0218578 | G6: ='AEO 2026 Table 1'!J11/'AEO 2026 Table 1'!$E$11 -> 1.022724 | H6: ='AEO 2026 Table 1'!K11/'AEO 2026 Table 1'!$E$11 -> 1.0227424 | I6: ='AEO 2026 Table 1'!L11/'AEO 2026 Table 1'!$E$11 -> 1.0227433 | ... AA6: ='AEO 2026 Table 1'!AD11/'AEO 2026 Table 1'!$E$11 -> 1.0226735
A7: hydro (is not a fuel) | B7: 0 | C7: 0 | D7: 0 | E7: 0 | F7: 0 | G7: 0 | H7: 0 | I7: 0 | J7: 0 | K7: 0 | L7: 0 | M7: 0 | N7: 0 | O7: 0 | P7: 0 | Q7: 0 | R7: 0 | S7: 0 | T7: 0 | U7: 0 | V7: 0 | W7: 0 | X7: 0 | Y7: 0 | Z7: 0 | AA7: 0
A8: wind (is not a fuel) | B8: 0 | C8: 0 | D8: 0 | E8: 0 | F8: 0 | G8: 0 | H8: 0 | I8: 0 | J8: 0 | K8: 0 | L8: 0 | M8: 0 | N8: 0 | O8: 0 | P8: 0 | Q8: 0 | R8: 0 | S8: 0 | T8: 0 | U8: 0 | V8: 0 | W8: 0 | X8: 0 | Y8: 0 | Z8: 0 | AA8: 0
A9: solar (is not a fuel) | B9: 0 | C9: 0 | D9: 0 | E9: 0 | F9: 0 | G9: 0 | H9: 0 | I9: 0 | J9: 0 | K9: 0 | L9: 0 | M9: 0 | N9: 0 | O9: 0 | P9: 0 | Q9: 0 | R9: 0 | S9: 0 | T9: 0 | U9: 0 | V9: 0 | W9: 0 | X9: 0 | Y9: 0 | Z9: 0 | AA9: 0
A10: biomass | B10: ='AEO 2026 Table 1'!E13/'AEO 2026 Table 1'!$E$13 -> 1 | C10: ='AEO 2026 Table 1'!F13/'AEO 2026 Table 1'!$E$13 -> 1.025781 | D10: ='AEO 2026 Table 1'!G13/'AEO 2026 Table 1'!$E$13 -> 1.0171888 | E10: ='AEO 2026 Table 1'!H13/'AEO 2026 Table 1'!$E$13 -> 1.0180764 | F10: ='AEO 2026 Table 1'!I13/'AEO 2026 Table 1'!$E$13 -> 1.0143207 | G10: ='AEO 2026 Table 1'!J13/'AEO 2026 Table 1'!$E$13 -> 0.99964027 | H10: ='AEO 2026 Table 1'!K13/'AEO 2026 Table 1'!$E$13 -> 0.99161753 | I10: ='AEO 2026 Table 1'!L13/'AEO 2026 Table 1'!$E$13 -> 0.98657926 | ... AA10: ='AEO 2026 Table 1'!AD13/'AEO 2026 Table 1'!$E$13 -> 1.1093402
A11: petroleum gasoline | B11: ='AEO 2026 Table 1'!E$7/'AEO 2026 Table 1'!$E$7 -> 1 | C11: ='AEO 2026 Table 1'!F$7/'AEO 2026 Table 1'!$E$7 -> 0.99086318 | D11: ='AEO 2026 Table 1'!G$7/'AEO 2026 Table 1'!$E$7 -> 0.99424229 | E11: ='AEO 2026 Table 1'!H$7/'AEO 2026 Table 1'!$E$7 -> 0.99612037 | F11: ='AEO 2026 Table 1'!I$7/'AEO 2026 Table 1'!$E$7 -> 0.9899873 | G11: ='AEO 2026 Table 1'!J$7/'AEO 2026 Table 1'!$E$7 -> 0.99803714 | H11: ='AEO 2026 Table 1'!K$7/'AEO 2026 Table 1'!$E$7 -> 0.99762594 | I11: ='AEO 2026 Table 1'!L$7/'AEO 2026 Table 1'!$E$7 -> 0.99240303 | ... AA11: ='AEO 2026 Table 1'!AD$7/'AEO 2026 Table 1'!$E$7 -> 0.92520734
A12: petroleum diesel | B12: ='AEO 2026 Table 1'!E$7/'AEO 2026 Table 1'!$E$7 -> 1 | C12: ='AEO 2026 Table 1'!F$7/'AEO 2026 Table 1'!$E$7 -> 0.99086318 | D12: ='AEO 2026 Table 1'!G$7/'AEO 2026 Table 1'!$E$7 -> 0.99424229 | E12: ='AEO 2026 Table 1'!H$7/'AEO 2026 Table 1'!$E$7 -> 0.99612037 | F12: ='AEO 2026 Table 1'!I$7/'AEO 2026 Table 1'!$E$7 -> 0.9899873 | G12: ='AEO 2026 Table 1'!J$7/'AEO 2026 Table 1'!$E$7 -> 0.99803714 | H12: ='AEO 2026 Table 1'!K$7/'AEO 2026 Table 1'!$E$7 -> 0.99762594 | I12: ='AEO 2026 Table 1'!L$7/'AEO 2026 Table 1'!$E$7 -> 0.99240303 | ... AA12: ='AEO 2026 Table 1'!AD$7/'AEO 2026 Table 1'!$E$7 -> 0.92520734
A13: biofuel gasoline | B13: ='AEO 2026 Table 1'!E$7/'AEO 2026 Table 1'!$E$7 -> 1 | C13: ='AEO 2026 Table 1'!F$7/'AEO 2026 Table 1'!$E$7 -> 0.99086318 | D13: ='AEO 2026 Table 1'!G$7/'AEO 2026 Table 1'!$E$7 -> 0.99424229 | E13: ='AEO 2026 Table 1'!H$7/'AEO 2026 Table 1'!$E$7 -> 0.99612037 | F13: ='AEO 2026 Table 1'!I$7/'AEO 2026 Table 1'!$E$7 -> 0.9899873 | G13: ='AEO 2026 Table 1'!J$7/'AEO 2026 Table 1'!$E$7 -> 0.99803714 | H13: ='AEO 2026 Table 1'!K$7/'AEO 2026 Table 1'!$E$7 -> 0.99762594 | I13: ='AEO 2026 Table 1'!L$7/'AEO 2026 Table 1'!$E$7 -> 0.99240303 | ... AA13: ='AEO 2026 Table 1'!AD$7/'AEO 2026 Table 1'!$E$7 -> 0.92520734
A14: biofuel diesel | B14: ='AEO 2026 Table 1'!E$7/'AEO 2026 Table 1'!$E$7 -> 1 | C14: ='AEO 2026 Table 1'!F$7/'AEO 2026 Table 1'!$E$7 -> 0.99086318 | D14: ='AEO 2026 Table 1'!G$7/'AEO 2026 Table 1'!$E$7 -> 0.99424229 | E14: ='AEO 2026 Table 1'!H$7/'AEO 2026 Table 1'!$E$7 -> 0.99612037 | F14: ='AEO 2026 Table 1'!I$7/'AEO 2026 Table 1'!$E$7 -> 0.9899873 | G14: ='AEO 2026 Table 1'!J$7/'AEO 2026 Table 1'!$E$7 -> 0.99803714 | H14: ='AEO 2026 Table 1'!K$7/'AEO 2026 Table 1'!$E$7 -> 0.99762594 | I14: ='AEO 2026 Table 1'!L$7/'AEO 2026 Table 1'!$E$7 -> 0.99240303 | ... AA14: ='AEO 2026 Table 1'!AD$7/'AEO 2026 Table 1'!$E$7 -> 0.92520734
A15: jet fuel or kerosene | B15: ='AEO 2026 Table 1'!E$7/'AEO 2026 Table 1'!$E$7 -> 1 | C15: ='AEO 2026 Table 1'!F$7/'AEO 2026 Table 1'!$E$7 -> 0.99086318 | D15: ='AEO 2026 Table 1'!G$7/'AEO 2026 Table 1'!$E$7 -> 0.99424229 | E15: ='AEO 2026 Table 1'!H$7/'AEO 2026 Table 1'!$E$7 -> 0.99612037 | F15: ='AEO 2026 Table 1'!I$7/'AEO 2026 Table 1'!$E$7 -> 0.9899873 | G15: ='AEO 2026 Table 1'!J$7/'AEO 2026 Table 1'!$E$7 -> 0.99803714 | H15: ='AEO 2026 Table 1'!K$7/'AEO 2026 Table 1'!$E$7 -> 0.99762594 | I15: ='AEO 2026 Table 1'!L$7/'AEO 2026 Table 1'!$E$7 -> 0.99240303 | ... AA15: ='AEO 2026 Table 1'!AD$7/'AEO 2026 Table 1'!$E$7 -> 0.92520734
A16: heat (not used in this variable) | B16: 0 | C16: 0 | D16: 0 | E16: 0 | F16: 0 | G16: 0 | H16: 0 | I16: 0 | J16: 0 | K16: 0 | L16: 0 | M16: 0 | N16: 0 | O16: 0 | P16: 0 | Q16: 0 | R16: 0 | S16: 0 | T16: 0 | U16: 0 | V16: 0 | W16: 0 | X16: 0 | Y16: 0 | Z16: 0 | AA16: 0
A17: geothermal (is not a fuel) | B17: 0 | C17: 0 | D17: 0 | E17: 0 | F17: 0 | G17: 0 | H17: 0 | I17: 0 | J17: 0 | K17: 0 | L17: 0 | M17: 0 | N17: 0 | O17: 0 | P17: 0 | Q17: 0 | R17: 0 | S17: 0 | T17: 0 | U17: 0 | V17: 0 | W17: 0 | X17: 0 | Y17: 0 | Z17: 0 | AA17: 0
A18: lignite | B18: ='AEO 2026 Table 1'!E$10/'AEO 2026 Table 1'!$E$10 -> 1 | C18: ='AEO 2026 Table 1'!F$10/'AEO 2026 Table 1'!$E$10 -> 0.97530688 | D18: ='AEO 2026 Table 1'!G$10/'AEO 2026 Table 1'!$E$10 -> 0.94217824 | E18: ='AEO 2026 Table 1'!H$10/'AEO 2026 Table 1'!$E$10 -> 0.88468935 | F18: ='AEO 2026 Table 1'!I$10/'AEO 2026 Table 1'!$E$10 -> 0.86350146 | G18: ='AEO 2026 Table 1'!J$10/'AEO 2026 Table 1'!$E$10 -> 0.87296349 | H18: ='AEO 2026 Table 1'!K$10/'AEO 2026 Table 1'!$E$10 -> 0.78588696 | I18: ='AEO 2026 Table 1'!L$10/'AEO 2026 Table 1'!$E$10 -> 0.76483944 | ... AA18: ='AEO 2026 Table 1'!AD$10/'AEO 2026 Table 1'!$E$10 -> 0.60360634
A19: crude oil | B19: ='AEO 2026 Table 1'!E$7/'AEO 2026 Table 1'!$E$7 -> 1 | C19: ='AEO 2026 Table 1'!F$7/'AEO 2026 Table 1'!$E$7 -> 0.99086318 | D19: ='AEO 2026 Table 1'!G$7/'AEO 2026 Table 1'!$E$7 -> 0.99424229 | E19: ='AEO 2026 Table 1'!H$7/'AEO 2026 Table 1'!$E$7 -> 0.99612037 | F19: ='AEO 2026 Table 1'!I$7/'AEO 2026 Table 1'!$E$7 -> 0.9899873 | G19: ='AEO 2026 Table 1'!J$7/'AEO 2026 Table 1'!$E$7 -> 0.99803714 | H19: ='AEO 2026 Table 1'!K$7/'AEO 2026 Table 1'!$E$7 -> 0.99762594 | I19: ='AEO 2026 Table 1'!L$7/'AEO 2026 Table 1'!$E$7 -> 0.99240303 | ... AA19: ='AEO 2026 Table 1'!AD$7/'AEO 2026 Table 1'!$E$7 -> 0.92520734
A20: heavy fuel oil | B20: ='AEO 2026 Table 1'!E$7/'AEO 2026 Table 1'!$E$7 -> 1 | C20: ='AEO 2026 Table 1'!F$7/'AEO 2026 Table 1'!$E$7 -> 0.99086318 | D20: ='AEO 2026 Table 1'!G$7/'AEO 2026 Table 1'!$E$7 -> 0.99424229 | E20: ='AEO 2026 Table 1'!H$7/'AEO 2026 Table 1'!$E$7 -> 0.99612037 | F20: ='AEO 2026 Table 1'!I$7/'AEO 2026 Table 1'!$E$7 -> 0.9899873 | G20: ='AEO 2026 Table 1'!J$7/'AEO 2026 Table 1'!$E$7 -> 0.99803714 | H20: ='AEO 2026 Table 1'!K$7/'AEO 2026 Table 1'!$E$7 -> 0.99762594 | I20: ='AEO 2026 Table 1'!L$7/'AEO 2026 Table 1'!$E$7 -> 0.99240303 | ... AA20: ='AEO 2026 Table 1'!AD$7/'AEO 2026 Table 1'!$E$7 -> 0.92520734
A21: LPG propane or butane | B21: ='AEO 2026 Table 1'!E8/'AEO 2026 Table 1'!$E$8 -> 1 | C21: ='AEO 2026 Table 1'!F8/'AEO 2026 Table 1'!$E$8 -> 1.0184813 | D21: ='AEO 2026 Table 1'!G8/'AEO 2026 Table 1'!$E$8 -> 1.0932801 | E21: ='AEO 2026 Table 1'!H8/'AEO 2026 Table 1'!$E$8 -> 1.0820645 | F21: ='AEO 2026 Table 1'!I8/'AEO 2026 Table 1'!$E$8 -> 1.0862884 | G21: ='AEO 2026 Table 1'!J8/'AEO 2026 Table 1'!$E$8 -> 1.0902539 | H21: ='AEO 2026 Table 1'!K8/'AEO 2026 Table 1'!$E$8 -> 1.1424749 | I21: ='AEO 2026 Table 1'!L8/'AEO 2026 Table 1'!$E$8 -> 1.1920132 | ... AA21: ='AEO 2026 Table 1'!AD8/'AEO 2026 Table 1'!$E$8 -> 1.458529
A22: municipal solid waste | B22: ='AEO 2026 Table 1'!E15/'AEO 2026 Table 1'!$E$15 -> 1 | C22: ='AEO 2026 Table 1'!F15/'AEO 2026 Table 1'!$E$15 -> 0.96332137 | D22: ='AEO 2026 Table 1'!G15/'AEO 2026 Table 1'!$E$15 -> 0.45823939 | E22: ='AEO 2026 Table 1'!H15/'AEO 2026 Table 1'!$E$15 -> 0.41565567 | F22: ='AEO 2026 Table 1'!I15/'AEO 2026 Table 1'!$E$15 -> 0.41074645 | G22: ='AEO 2026 Table 1'!J15/'AEO 2026 Table 1'!$E$15 -> 0.40737328 | H22: ='AEO 2026 Table 1'!K15/'AEO 2026 Table 1'!$E$15 -> 0.3971267 | I22: ='AEO 2026 Table 1'!L15/'AEO 2026 Table 1'!$E$15 -> 0.3170425 | ... AA22: ='AEO 2026 Table 1'!AD15/'AEO 2026 Table 1'!$E$15 -> 0.35208305
A23: hydrogen | B23: =SUM('AEO 2026 Table 19'!E8:E11)/SUM('AEO 2026 Table 19'!$E$8:$E$11) -> 1 | C23: =SUM('AEO 2026 Table 19'!F8:F11)/SUM('AEO 2026 Table 19'!$E$8:$E$11) -> 0.92629838 | D23: =SUM('AEO 2026 Table 19'!G8:G11)/SUM('AEO 2026 Table 19'!$E$8:$E$11) -> 0.91993215 | E23: =SUM('AEO 2026 Table 19'!H8:H11)/SUM('AEO 2026 Table 19'!$E$8:$E$11) -> 0.9232574 | F23: =SUM('AEO 2026 Table 19'!I8:I11)/SUM('AEO 2026 Table 19'!$E$8:$E$11) -> 0.94135467 | G23: =SUM('AEO 2026 Table 19'!J8:J11)/SUM('AEO 2026 Table 19'!$E$8:$E$11) -> 0.93848818 | H23: =SUM('AEO 2026 Table 19'!K8:K11)/SUM('AEO 2026 Table 19'!$E$8:$E$11) -> 0.92252539 | I23: =SUM('AEO 2026 Table 19'!L8:L11)/SUM('AEO 2026 Table 19'!$E$8:$E$11) -> 0.91874472 | ... AA23: =SUM('AEO 2026 Table 19'!AD8:AD11)/SUM('AEO 2026 Table 19'!$E$8:$E$11) -> 1.0688827
A26: Imports Scaling Factors
B27: =B2 -> 2025 | C27: =C2 -> 2026 | D27: =D2 -> 2027 | E27: =E2 -> 2028 | F27: =F2 -> 2029 | G27: =G2 -> 2030 | H27: =H2 -> 2031 | I27: =I2 -> 2032 | ... AA27: =AA2 -> 2050
A28: electricity (not used in this variable) | B28: 0 | C28: 0 | D28: 0 | E28: 0 | F28: 0 | G28: 0 | H28: 0 | I28: 0 | J28: 0 | K28: 0 | L28: 0 | M28: 0 | N28: 0 | O28: 0 | P28: 0 | Q28: 0 | R28: 0 | S28: 0 | T28: 0 | U28: 0 | V28: 0 | W28: 0 | X28: 0 | Y28: 0 | Z28: 0 | AA28: 0
A29: hard coal | B29: ='AEO 2026 Table 1'!E$21/'AEO 2026 Table 1'!$E$21 -> 1 | C29: ='AEO 2026 Table 1'!F$21/'AEO 2026 Table 1'!$E$21 -> 1.5461525 | D29: ='AEO 2026 Table 1'!G$21/'AEO 2026 Table 1'!$E$21 -> 2.1717218 | E29: ='AEO 2026 Table 1'!H$21/'AEO 2026 Table 1'!$E$21 -> 2.5917756 | F29: ='AEO 2026 Table 1'!I$21/'AEO 2026 Table 1'!$E$21 -> 2.8111113 | G29: ='AEO 2026 Table 1'!J$21/'AEO 2026 Table 1'!$E$21 -> 3.0782835 | H29: ='AEO 2026 Table 1'!K$21/'AEO 2026 Table 1'!$E$21 -> 3.0571347 | I29: ='AEO 2026 Table 1'!L$21/'AEO 2026 Table 1'!$E$21 -> 3.1171605 | ... AA29: ='AEO 2026 Table 1'!AD$21/'AEO 2026 Table 1'!$E$21 -> 2.3359668
A30: natural gas | B30: ='AEO 2026 Table 1'!E$20/'AEO 2026 Table 1'!$E$20 -> 1 | C30: ='AEO 2026 Table 1'!F$20/'AEO 2026 Table 1'!$E$20 -> 1.0413787 | D30: ='AEO 2026 Table 1'!G$20/'AEO 2026 Table 1'!$E$20 -> 0.9963063 | E30: ='AEO 2026 Table 1'!H$20/'AEO 2026 Table 1'!$E$20 -> 0.90687053 | F30: ='AEO 2026 Table 1'!I$20/'AEO 2026 Table 1'!$E$20 -> 0.86968021 | G30: ='AEO 2026 Table 1'!J$20/'AEO 2026 Table 1'!$E$20 -> 0.91371969 | H30: ='AEO 2026 Table 1'!K$20/'AEO 2026 Table 1'!$E$20 -> 0.90865904 | I30: ='AEO 2026 Table 1'!L$20/'AEO 2026 Table 1'!$E$20 -> 0.84561282 | ... AA30: ='AEO 2026 Table 1'!AD$20/'AEO 2026 Table 1'!$E$20 -> 0.90524813
A31: uranium | B31: 1 | C31: 1 | D31: 1 | E31: 1 | F31: 1 | G31: 1 | H31: 1 | I31: 1 | J31: 1 | K31: 1 | L31: 1 | M31: 1 | N31: 1 | O31: 1 | P31: 1 | Q31: 1 | R31: 1 | S31: 1 | T31: 1 | U31: 1 | V31: 1 | W31: 1 | X31: 1 | Y31: 1 | Z31: 1 | AA31: 1
A32: hydro (is not a fuel) | B32: 0 | C32: 0 | D32: 0 | E32: 0 | F32: 0 | G32: 0 | H32: 0 | I32: 0 | J32: 0 | K32: 0 | L32: 0 | M32: 0 | N32: 0 | O32: 0 | P32: 0 | Q32: 0 | R32: 0 | S32: 0 | T32: 0 | U32: 0 | V32: 0 | W32: 0 | X32: 0 | Y32: 0 | Z32: 0 | AA32: 0
A33: wind (is not a fuel) | B33: 0 | C33: 0 | D33: 0 | E33: 0 | F33: 0 | G33: 0 | H33: 0 | I33: 0 | J33: 0 | K33: 0 | L33: 0 | M33: 0 | N33: 0 | O33: 0 | P33: 0 | Q33: 0 | R33: 0 | S33: 0 | T33: 0 | U33: 0 | V33: 0 | W33: 0 | X33: 0 | Y33: 0 | Z33: 0 | AA33: 0
A34: solar (is not a fuel) | B34: 0 | C34: 0 | D34: 0 | E34: 0 | F34: 0 | G34: 0 | H34: 0 | I34: 0 | J34: 0 | K34: 0 | L34: 0 | M34: 0 | N34: 0 | O34: 0 | P34: 0 | Q34: 0 | R34: 0 | S34: 0 | T34: 0 | U34: 0 | V34: 0 | W34: 0 | X34: 0 | Y34: 0 | Z34: 0 | AA34: 0
A35: biomass | B35: 1 | C35: 1 | D35: 1 | E35: 1 | F35: 1 | G35: 1 | H35: 1 | I35: 1 | J35: 1 | K35: 1 | L35: 1 | M35: 1 | N35: 1 | O35: 1 | P35: 1 | Q35: 1 | R35: 1 | S35: 1 | T35: 1 | U35: 1 | V35: 1 | W35: 1 | X35: 1 | Y35: 1 | Z35: 1 | AA35: 1
A36: petroleum gasoline | B36: ='AEO 2026 Table 1'!E$19/'AEO 2026 Table 1'!$E$19 -> 1 | C36: ='AEO 2026 Table 1'!F$19/'AEO 2026 Table 1'!$E$19 -> 0.97523313 | D36: ='AEO 2026 Table 1'!G$19/'AEO 2026 Table 1'!$E$19 -> 1.0193034 | E36: ='AEO 2026 Table 1'!H$19/'AEO 2026 Table 1'!$E$19 -> 0.99607201 | F36: ='AEO 2026 Table 1'!I$19/'AEO 2026 Table 1'!$E$19 -> 0.97230731 | G36: ='AEO 2026 Table 1'!J$19/'AEO 2026 Table 1'!$E$19 -> 0.96588844 | H36: ='AEO 2026 Table 1'!K$19/'AEO 2026 Table 1'!$E$19 -> 0.95258268 | I36: ='AEO 2026 Table 1'!L$19/'AEO 2026 Table 1'!$E$19 -> 0.93790941 | ... AA36: ='AEO 2026 Table 1'!AD$19/'AEO 2026 Table 1'!$E$19 -> 0.89145919
A37: petroleum diesel | B37: ='AEO 2026 Table 1'!E$19/'AEO 2026 Table 1'!$E$19 -> 1 | C37: ='AEO 2026 Table 1'!F$19/'AEO 2026 Table 1'!$E$19 -> 0.97523313 | D37: ='AEO 2026 Table 1'!G$19/'AEO 2026 Table 1'!$E$19 -> 1.0193034 | E37: ='AEO 2026 Table 1'!H$19/'AEO 2026 Table 1'!$E$19 -> 0.99607201 | F37: ='AEO 2026 Table 1'!I$19/'AEO 2026 Table 1'!$E$19 -> 0.97230731 | G37: ='AEO 2026 Table 1'!J$19/'AEO 2026 Table 1'!$E$19 -> 0.96588844 | H37: ='AEO 2026 Table 1'!K$19/'AEO 2026 Table 1'!$E$19 -> 0.95258268 | I37: ='AEO 2026 Table 1'!L$19/'AEO 2026 Table 1'!$E$19 -> 0.93790941 | ... AA37: ='AEO 2026 Table 1'!AD$19/'AEO 2026 Table 1'!$E$19 -> 0.89145919
A38: biofuel gasoline | B38: ='AEO 2026 Table 1'!E$19/'AEO 2026 Table 1'!$E$19 -> 1 | C38: ='AEO 2026 Table 1'!F$19/'AEO 2026 Table 1'!$E$19 -> 0.97523313 | D38: ='AEO 2026 Table 1'!G$19/'AEO 2026 Table 1'!$E$19 -> 1.0193034 | E38: ='AEO 2026 Table 1'!H$19/'AEO 2026 Table 1'!$E$19 -> 0.99607201 | F38: ='AEO 2026 Table 1'!I$19/'AEO 2026 Table 1'!$E$19 -> 0.97230731 | G38: ='AEO 2026 Table 1'!J$19/'AEO 2026 Table 1'!$E$19 -> 0.96588844 | H38: ='AEO 2026 Table 1'!K$19/'AEO 2026 Table 1'!$E$19 -> 0.95258268 | I38: ='AEO 2026 Table 1'!L$19/'AEO 2026 Table 1'!$E$19 -> 0.93790941 | ... AA38: ='AEO 2026 Table 1'!AD$19/'AEO 2026 Table 1'!$E$19 -> 0.89145919
A39: biofuel diesel | B39: ='AEO 2026 Table 1'!E$19/'AEO 2026 Table 1'!$E$19 -> 1 | C39: ='AEO 2026 Table 1'!F$19/'AEO 2026 Table 1'!$E$19 -> 0.97523313 | D39: ='AEO 2026 Table 1'!G$19/'AEO 2026 Table 1'!$E$19 -> 1.0193034 | E39: ='AEO 2026 Table 1'!H$19/'AEO 2026 Table 1'!$E$19 -> 0.99607201 | F39: ='AEO 2026 Table 1'!I$19/'AEO 2026 Table 1'!$E$19 -> 0.97230731 | G39: ='AEO 2026 Table 1'!J$19/'AEO 2026 Table 1'!$E$19 -> 0.96588844 | H39: ='AEO 2026 Table 1'!K$19/'AEO 2026 Table 1'!$E$19 -> 0.95258268 | I39: ='AEO 2026 Table 1'!L$19/'AEO 2026 Table 1'!$E$19 -> 0.93790941 | ... AA39: ='AEO 2026 Table 1'!AD$19/'AEO 2026 Table 1'!$E$19 -> 0.89145919
A40: jet fuel or kerosene | B40: ='AEO 2026 Table 1'!E$19/'AEO 2026 Table 1'!$E$19 -> 1 | C40: ='AEO 2026 Table 1'!F$19/'AEO 2026 Table 1'!$E$19 -> 0.97523313 | D40: ='AEO 2026 Table 1'!G$19/'AEO 2026 Table 1'!$E$19 -> 1.0193034 | E40: ='AEO 2026 Table 1'!H$19/'AEO 2026 Table 1'!$E$19 -> 0.99607201 | F40: ='AEO 2026 Table 1'!I$19/'AEO 2026 Table 1'!$E$19 -> 0.97230731 | G40: ='AEO 2026 Table 1'!J$19/'AEO 2026 Table 1'!$E$19 -> 0.96588844 | H40: ='AEO 2026 Table 1'!K$19/'AEO 2026 Table 1'!$E$19 -> 0.95258268 | I40: ='AEO 2026 Table 1'!L$19/'AEO 2026 Table 1'!$E$19 -> 0.93790941 | ... AA40: ='AEO 2026 Table 1'!AD$19/'AEO 2026 Table 1'!$E$19 -> 0.89145919
A41: heat (not used in this variable) | B41: 0 | C41: 0 | D41: 0 | E41: 0 | F41: 0 | G41: 0 | H41: 0 | I41: 0 | J41: 0 | K41: 0 | L41: 0 | M41: 0 | N41: 0 | O41: 0 | P41: 0 | Q41: 0 | R41: 0 | S41: 0 | T41: 0 | U41: 0 | V41: 0 | W41: 0 | X41: 0 | Y41: 0 | Z41: 0 | AA41: 0
A42: geothermal (is not a fuel) | B42: 0 | C42: 0 | D42: 0 | E42: 0 | F42: 0 | G42: 0 | H42: 0 | I42: 0 | J42: 0 | K42: 0 | L42: 0 | M42: 0 | N42: 0 | O42: 0 | P42: 0 | Q42: 0 | R42: 0 | S42: 0 | T42: 0 | U42: 0 | V42: 0 | W42: 0 | X42: 0 | Y42: 0 | Z42: 0 | AA42: 0
A43: lignite | B43: ='AEO 2026 Table 1'!E$21/'AEO 2026 Table 1'!$E$21 -> 1 | C43: ='AEO 2026 Table 1'!F$21/'AEO 2026 Table 1'!$E$21 -> 1.5461525 | D43: ='AEO 2026 Table 1'!G$21/'AEO 2026 Table 1'!$E$21 -> 2.1717218 | E43: ='AEO 2026 Table 1'!H$21/'AEO 2026 Table 1'!$E$21 -> 2.5917756 | F43: ='AEO 2026 Table 1'!I$21/'AEO 2026 Table 1'!$E$21 -> 2.8111113 | G43: ='AEO 2026 Table 1'!J$21/'AEO 2026 Table 1'!$E$21 -> 3.0782835 | H43: ='AEO 2026 Table 1'!K$21/'AEO 2026 Table 1'!$E$21 -> 3.0571347 | I43: ='AEO 2026 Table 1'!L$21/'AEO 2026 Table 1'!$E$21 -> 3.1171605 | ... AA43: ='AEO 2026 Table 1'!AD$21/'AEO 2026 Table 1'!$E$21 -> 2.3359668
A44: crude oil | B44: ='AEO 2026 Table 1'!E$18/'AEO 2026 Table 1'!$E$18 -> 1 | C44: ='AEO 2026 Table 1'!F$18/'AEO 2026 Table 1'!$E$18 -> 0.95244091 | D44: ='AEO 2026 Table 1'!G$18/'AEO 2026 Table 1'!$E$18 -> 1.049189 | E44: ='AEO 2026 Table 1'!H$18/'AEO 2026 Table 1'!$E$18 -> 1.0602691 | F44: ='AEO 2026 Table 1'!I$18/'AEO 2026 Table 1'!$E$18 -> 1.0958541 | G44: ='AEO 2026 Table 1'!J$18/'AEO 2026 Table 1'!$E$18 -> 1.1034005 | H44: ='AEO 2026 Table 1'!K$18/'AEO 2026 Table 1'!$E$18 -> 1.0926448 | I44: ='AEO 2026 Table 1'!L$18/'AEO 2026 Table 1'!$E$18 -> 1.1229908 | ... AA44: ='AEO 2026 Table 1'!AD$18/'AEO 2026 Table 1'!$E$18 -> 1.2535944
A45: heavy fuel oil | B45: ='AEO 2026 Table 1'!E$19/'AEO 2026 Table 1'!$E$19 -> 1 | C45: ='AEO 2026 Table 1'!F$19/'AEO 2026 Table 1'!$E$19 -> 0.97523313 | D45: ='AEO 2026 Table 1'!G$19/'AEO 2026 Table 1'!$E$19 -> 1.0193034 | E45: ='AEO 2026 Table 1'!H$19/'AEO 2026 Table 1'!$E$19 -> 0.99607201 | F45: ='AEO 2026 Table 1'!I$19/'AEO 2026 Table 1'!$E$19 -> 0.97230731 | G45: ='AEO 2026 Table 1'!J$19/'AEO 2026 Table 1'!$E$19 -> 0.96588844 | H45: ='AEO 2026 Table 1'!K$19/'AEO 2026 Table 1'!$E$19 -> 0.95258268 | I45: ='AEO 2026 Table 1'!L$19/'AEO 2026 Table 1'!$E$19 -> 0.93790941 | ... AA45: ='AEO 2026 Table 1'!AD$19/'AEO 2026 Table 1'!$E$19 -> 0.89145919
A46: LPG propane or butane | B46: ='AEO 2026 Table 1'!E$19/'AEO 2026 Table 1'!$E$19 -> 1 | C46: ='AEO 2026 Table 1'!F$19/'AEO 2026 Table 1'!$E$19 -> 0.97523313 | D46: ='AEO 2026 Table 1'!G$19/'AEO 2026 Table 1'!$E$19 -> 1.0193034 | E46: ='AEO 2026 Table 1'!H$19/'AEO 2026 Table 1'!$E$19 -> 0.99607201 | F46: ='AEO 2026 Table 1'!I$19/'AEO 2026 Table 1'!$E$19 -> 0.97230731 | G46: ='AEO 2026 Table 1'!J$19/'AEO 2026 Table 1'!$E$19 -> 0.96588844 | H46: ='AEO 2026 Table 1'!K$19/'AEO 2026 Table 1'!$E$19 -> 0.95258268 | I46: ='AEO 2026 Table 1'!L$19/'AEO 2026 Table 1'!$E$19 -> 0.93790941 | ... AA46: ='AEO 2026 Table 1'!AD$19/'AEO 2026 Table 1'!$E$19 -> 0.89145919
A47: municipal solid waste | B47: 1 | C47: 1 | D47: 1 | E47: 1 | F47: 1 | G47: 1 | H47: 1 | I47: 1 | J47: 1 | K47: 1 | L47: 1 | M47: 1 | N47: 1 | O47: 1 | P47: 1 | Q47: 1 | R47: 1 | S47: 1 | T47: 1 | U47: 1 | V47: 1 | W47: 1 | X47: 1 | Y47: 1 | Z47: 1 | AA47: 1
A48: hydrogen | B48: 1 | C48: 1 | D48: 1 | E48: 1 | F48: 1 | G48: 1 | H48: 1 | I48: 1 | J48: 1 | K48: 1 | L48: 1 | M48: 1 | N48: 1 | O48: 1 | P48: 1 | Q48: 1 | R48: 1 | S48: 1 | T48: 1 | U48: 1 | V48: 1 | W48: 1 | X48: 1 | Y48: 1 | Z48: 1 | AA48: 1
A51: Exports Scaling Factors
B52: =B2 -> 2025 | C52: =C2 -> 2026 | D52: =D2 -> 2027 | E52: =E2 -> 2028 | F52: =F2 -> 2029 | G52: =G2 -> 2030 | H52: =H2 -> 2031 | I52: =I2 -> 2032 | ... AA52: =AA2 -> 2050
A53: electricity (not used in this variable) | B53: 0 | C53: 0 | D53: 0 | E53: 0 | F53: 0 | G53: 0 | H53: 0 | I53: 0 | J53: 0 | K53: 0 | L53: 0 | M53: 0 | N53: 0 | O53: 0 | P53: 0 | Q53: 0 | R53: 0 | S53: 0 | T53: 0 | U53: 0 | V53: 0 | W53: 0 | X53: 0 | Y53: 0 | Z53: 0 | AA53: 0
A54: hard coal | B54: ='AEO 2026 Table 1'!E$26/'AEO 2026 Table 1'!$E$26 -> 1 | C54: ='AEO 2026 Table 1'!F$26/'AEO 2026 Table 1'!$E$26 -> 1.0389179 | D54: ='AEO 2026 Table 1'!G$26/'AEO 2026 Table 1'!$E$26 -> 1.1106566 | E54: ='AEO 2026 Table 1'!H$26/'AEO 2026 Table 1'!$E$26 -> 1.1568056 | F54: ='AEO 2026 Table 1'!I$26/'AEO 2026 Table 1'!$E$26 -> 1.1169837 | G54: ='AEO 2026 Table 1'!J$26/'AEO 2026 Table 1'!$E$26 -> 1.1716857 | H54: ='AEO 2026 Table 1'!K$26/'AEO 2026 Table 1'!$E$26 -> 1.1804883 | I54: ='AEO 2026 Table 1'!L$26/'AEO 2026 Table 1'!$E$26 -> 1.2509511 | ... AA54: ='AEO 2026 Table 1'!AD$26/'AEO 2026 Table 1'!$E$26 -> 1.2317295
A55: natural gas | B55: ='AEO 2026 Table 1'!E$25/'AEO 2026 Table 1'!$E$25 -> 1 | C55: ='AEO 2026 Table 1'!F$25/'AEO 2026 Table 1'!$E$25 -> 1.0125654 | D55: ='AEO 2026 Table 1'!G$25/'AEO 2026 Table 1'!$E$25 -> 1.0943063 | E55: ='AEO 2026 Table 1'!H$25/'AEO 2026 Table 1'!$E$25 -> 1.1625885 | F55: ='AEO 2026 Table 1'!I$25/'AEO 2026 Table 1'!$E$25 -> 1.2185679 | G55: ='AEO 2026 Table 1'!J$25/'AEO 2026 Table 1'!$E$25 -> 1.3659781 | H55: ='AEO 2026 Table 1'!K$25/'AEO 2026 Table 1'!$E$25 -> 1.4337219 | I55: ='AEO 2026 Table 1'!L$25/'AEO 2026 Table 1'!$E$25 -> 1.5051566 | ... AA55: ='AEO 2026 Table 1'!AD$25/'AEO 2026 Table 1'!$E$25 -> 2.0661124
A56: uranium | B56: 1 | C56: 1 | D56: 1 | E56: 1 | F56: 1 | G56: 1 | H56: 1 | I56: 1 | J56: 1 | K56: 1 | L56: 1 | M56: 1 | N56: 1 | O56: 1 | P56: 1 | Q56: 1 | R56: 1 | S56: 1 | T56: 1 | U56: 1 | V56: 1 | W56: 1 | X56: 1 | Y56: 1 | Z56: 1 | AA56: 1
A57: hydro (is not a fuel) | B57: 0 | C57: 0 | D57: 0 | E57: 0 | F57: 0 | G57: 0 | H57: 0 | I57: 0 | J57: 0 | K57: 0 | L57: 0 | M57: 0 | N57: 0 | O57: 0 | P57: 0 | Q57: 0 | R57: 0 | S57: 0 | T57: 0 | U57: 0 | V57: 0 | W57: 0 | X57: 0 | Y57: 0 | Z57: 0 | AA57: 0
A58: wind (is not a fuel) | B58: 0 | C58: 0 | D58: 0 | E58: 0 | F58: 0 | G58: 0 | H58: 0 | I58: 0 | J58: 0 | K58: 0 | L58: 0 | M58: 0 | N58: 0 | O58: 0 | P58: 0 | Q58: 0 | R58: 0 | S58: 0 | T58: 0 | U58: 0 | V58: 0 | W58: 0 | X58: 0 | Y58: 0 | Z58: 0 | AA58: 0
A59: solar (is not a fuel) | B59: 0 | C59: 0 | D59: 0 | E59: 0 | F59: 0 | G59: 0 | H59: 0 | I59: 0 | J59: 0 | K59: 0 | L59: 0 | M59: 0 | N59: 0 | O59: 0 | P59: 0 | Q59: 0 | R59: 0 | S59: 0 | T59: 0 | U59: 0 | V59: 0 | W59: 0 | X59: 0 | Y59: 0 | Z59: 0 | AA59: 0
A60: biomass | B60: 1 | C60: 1 | D60: 1 | E60: 1 | F60: 1 | G60: 1 | H60: 1 | I60: 1 | J60: 1 | K60: 1 | L60: 1 | M60: 1 | N60: 1 | O60: 1 | P60: 1 | Q60: 1 | R60: 1 | S60: 1 | T60: 1 | U60: 1 | V60: 1 | W60: 1 | X60: 1 | Y60: 1 | Z60: 1 | AA60: 1
A61: petroleum gasoline | B61: ='AEO 2026 Table 1'!E$24/'AEO 2026 Table 1'!$E$24 -> 1 | C61: ='AEO 2026 Table 1'!F$24/'AEO 2026 Table 1'!$E$24 -> 0.9919267 | D61: ='AEO 2026 Table 1'!G$24/'AEO 2026 Table 1'!$E$24 -> 1.0766816 | E61: ='AEO 2026 Table 1'!H$24/'AEO 2026 Table 1'!$E$24 -> 1.0778277 | F61: ='AEO 2026 Table 1'!I$24/'AEO 2026 Table 1'!$E$24 -> 1.1025849 | G61: ='AEO 2026 Table 1'!J$24/'AEO 2026 Table 1'!$E$24 -> 1.1171909 | H61: ='AEO 2026 Table 1'!K$24/'AEO 2026 Table 1'!$E$24 -> 1.1472055 | I61: ='AEO 2026 Table 1'!L$24/'AEO 2026 Table 1'!$E$24 -> 1.1807441 | ... AA61: ='AEO 2026 Table 1'!AD$24/'AEO 2026 Table 1'!$E$24 -> 1.3300409
A62: petroleum diesel | B62: ='AEO 2026 Table 1'!E$24/'AEO 2026 Table 1'!$E$24 -> 1 | C62: ='AEO 2026 Table 1'!F$24/'AEO 2026 Table 1'!$E$24 -> 0.9919267 | D62: ='AEO 2026 Table 1'!G$24/'AEO 2026 Table 1'!$E$24 -> 1.0766816 | E62: ='AEO 2026 Table 1'!H$24/'AEO 2026 Table 1'!$E$24 -> 1.0778277 | F62: ='AEO 2026 Table 1'!I$24/'AEO 2026 Table 1'!$E$24 -> 1.1025849 | G62: ='AEO 2026 Table 1'!J$24/'AEO 2026 Table 1'!$E$24 -> 1.1171909 | H62: ='AEO 2026 Table 1'!K$24/'AEO 2026 Table 1'!$E$24 -> 1.1472055 | I62: ='AEO 2026 Table 1'!L$24/'AEO 2026 Table 1'!$E$24 -> 1.1807441 | ... AA62: ='AEO 2026 Table 1'!AD$24/'AEO 2026 Table 1'!$E$24 -> 1.3300409
A63: biofuel gasoline | B63: ='AEO 2026 Table 1'!E$24/'AEO 2026 Table 1'!$E$24 -> 1 | C63: ='AEO 2026 Table 1'!F$24/'AEO 2026 Table 1'!$E$24 -> 0.9919267 | D63: ='AEO 2026 Table 1'!G$24/'AEO 2026 Table 1'!$E$24 -> 1.0766816 | E63: ='AEO 2026 Table 1'!H$24/'AEO 2026 Table 1'!$E$24 -> 1.0778277 | F63: ='AEO 2026 Table 1'!I$24/'AEO 2026 Table 1'!$E$24 -> 1.1025849 | G63: ='AEO 2026 Table 1'!J$24/'AEO 2026 Table 1'!$E$24 -> 1.1171909 | H63: ='AEO 2026 Table 1'!K$24/'AEO 2026 Table 1'!$E$24 -> 1.1472055 | I63: ='AEO 2026 Table 1'!L$24/'AEO 2026 Table 1'!$E$24 -> 1.1807441 | ... AA63: ='AEO 2026 Table 1'!AD$24/'AEO 2026 Table 1'!$E$24 -> 1.3300409
A64: biofuel diesel | B64: ='AEO 2026 Table 1'!E$24/'AEO 2026 Table 1'!$E$24 -> 1 | C64: ='AEO 2026 Table 1'!F$24/'AEO 2026 Table 1'!$E$24 -> 0.9919267 | D64: ='AEO 2026 Table 1'!G$24/'AEO 2026 Table 1'!$E$24 -> 1.0766816 | E64: ='AEO 2026 Table 1'!H$24/'AEO 2026 Table 1'!$E$24 -> 1.0778277 | F64: ='AEO 2026 Table 1'!I$24/'AEO 2026 Table 1'!$E$24 -> 1.1025849 | G64: ='AEO 2026 Table 1'!J$24/'AEO 2026 Table 1'!$E$24 -> 1.1171909 | H64: ='AEO 2026 Table 1'!K$24/'AEO 2026 Table 1'!$E$24 -> 1.1472055 | I64: ='AEO 2026 Table 1'!L$24/'AEO 2026 Table 1'!$E$24 -> 1.1807441 | ... AA64: ='AEO 2026 Table 1'!AD$24/'AEO 2026 Table 1'!$E$24 -> 1.3300409
A65: jet fuel or kerosene | B65: ='AEO 2026 Table 1'!E$24/'AEO 2026 Table 1'!$E$24 -> 1 | C65: ='AEO 2026 Table 1'!F$24/'AEO 2026 Table 1'!$E$24 -> 0.9919267 | D65: ='AEO 2026 Table 1'!G$24/'AEO 2026 Table 1'!$E$24 -> 1.0766816 | E65: ='AEO 2026 Table 1'!H$24/'AEO 2026 Table 1'!$E$24 -> 1.0778277 | F65: ='AEO 2026 Table 1'!I$24/'AEO 2026 Table 1'!$E$24 -> 1.1025849 | G65: ='AEO 2026 Table 1'!J$24/'AEO 2026 Table 1'!$E$24 -> 1.1171909 | H65: ='AEO 2026 Table 1'!K$24/'AEO 2026 Table 1'!$E$24 -> 1.1472055 | I65: ='AEO 2026 Table 1'!L$24/'AEO 2026 Table 1'!$E$24 -> 1.1807441 | ... AA65: ='AEO 2026 Table 1'!AD$24/'AEO 2026 Table 1'!$E$24 -> 1.3300409
A66: heat (not used in this variable) | B66: 0 | C66: 0 | D66: 0 | E66: 0 | F66: 0 | G66: 0 | H66: 0 | I66: 0 | J66: 0 | K66: 0 | L66: 0 | M66: 0 | N66: 0 | O66: 0 | P66: 0 | Q66: 0 | R66: 0 | S66: 0 | T66: 0 | U66: 0 | V66: 0 | W66: 0 | X66: 0 | Y66: 0 | Z66: 0 | AA66: 0
A67: geothermal (is not a fuel) | B67: 0 | C67: 0 | D67: 0 | E67: 0 | F67: 0 | G67: 0 | H67: 0 | I67: 0 | J67: 0 | K67: 0 | L67: 0 | M67: 0 | N67: 0 | O67: 0 | P67: 0 | Q67: 0 | R67: 0 | S67: 0 | T67: 0 | U67: 0 | V67: 0 | W67: 0 | X67: 0 | Y67: 0 | Z67: 0 | AA67: 0
A68: lignite | B68: ='AEO 2026 Table 1'!E$26/'AEO 2026 Table 1'!$E$26 -> 1 | C68: ='AEO 2026 Table 1'!F$26/'AEO 2026 Table 1'!$E$26 -> 1.0389179 | D68: ='AEO 2026 Table 1'!G$26/'AEO 2026 Table 1'!$E$26 -> 1.1106566 | E68: ='AEO 2026 Table 1'!H$26/'AEO 2026 Table 1'!$E$26 -> 1.1568056 | F68: ='AEO 2026 Table 1'!I$26/'AEO 2026 Table 1'!$E$26 -> 1.1169837 | G68: ='AEO 2026 Table 1'!J$26/'AEO 2026 Table 1'!$E$26 -> 1.1716857 | H68: ='AEO 2026 Table 1'!K$26/'AEO 2026 Table 1'!$E$26 -> 1.1804883 | I68: ='AEO 2026 Table 1'!L$26/'AEO 2026 Table 1'!$E$26 -> 1.2509511 | ... AA68: ='AEO 2026 Table 1'!AD$26/'AEO 2026 Table 1'!$E$26 -> 1.2317295
A69: crude oil | B69: ='AEO 2026 Table 1'!E$24/'AEO 2026 Table 1'!$E$24 -> 1 | C69: ='AEO 2026 Table 1'!F$24/'AEO 2026 Table 1'!$E$24 -> 0.9919267 | D69: ='AEO 2026 Table 1'!G$24/'AEO 2026 Table 1'!$E$24 -> 1.0766816 | E69: ='AEO 2026 Table 1'!H$24/'AEO 2026 Table 1'!$E$24 -> 1.0778277 | F69: ='AEO 2026 Table 1'!I$24/'AEO 2026 Table 1'!$E$24 -> 1.1025849 | G69: ='AEO 2026 Table 1'!J$24/'AEO 2026 Table 1'!$E$24 -> 1.1171909 | H69: ='AEO 2026 Table 1'!K$24/'AEO 2026 Table 1'!$E$24 -> 1.1472055 | I69: ='AEO 2026 Table 1'!L$24/'AEO 2026 Table 1'!$E$24 -> 1.1807441 | ... AA69: ='AEO 2026 Table 1'!AD$24/'AEO 2026 Table 1'!$E$24 -> 1.3300409
A70: heavy fuel oil | B70: ='AEO 2026 Table 1'!E$24/'AEO 2026 Table 1'!$E$24 -> 1 | C70: ='AEO 2026 Table 1'!F$24/'AEO 2026 Table 1'!$E$24 -> 0.9919267 | D70: ='AEO 2026 Table 1'!G$24/'AEO 2026 Table 1'!$E$24 -> 1.0766816 | E70: ='AEO 2026 Table 1'!H$24/'AEO 2026 Table 1'!$E$24 -> 1.0778277 | F70: ='AEO 2026 Table 1'!I$24/'AEO 2026 Table 1'!$E$24 -> 1.1025849 | G70: ='AEO 2026 Table 1'!J$24/'AEO 2026 Table 1'!$E$24 -> 1.1171909 | H70: ='AEO 2026 Table 1'!K$24/'AEO 2026 Table 1'!$E$24 -> 1.1472055 | I70: ='AEO 2026 Table 1'!L$24/'AEO 2026 Table 1'!$E$24 -> 1.1807441 | ... AA70: ='AEO 2026 Table 1'!AD$24/'AEO 2026 Table 1'!$E$24 -> 1.3300409
A71: LPG propane or butane | B71: ='AEO 2026 Table 1'!E$24/'AEO 2026 Table 1'!$E$24 -> 1 | C71: ='AEO 2026 Table 1'!F$24/'AEO 2026 Table 1'!$E$24 -> 0.9919267 | D71: ='AEO 2026 Table 1'!G$24/'AEO 2026 Table 1'!$E$24 -> 1.0766816 | E71: ='AEO 2026 Table 1'!H$24/'AEO 2026 Table 1'!$E$24 -> 1.0778277 | F71: ='AEO 2026 Table 1'!I$24/'AEO 2026 Table 1'!$E$24 -> 1.1025849 | G71: ='AEO 2026 Table 1'!J$24/'AEO 2026 Table 1'!$E$24 -> 1.1171909 | H71: ='AEO 2026 Table 1'!K$24/'AEO 2026 Table 1'!$E$24 -> 1.1472055 | I71: ='AEO 2026 Table 1'!L$24/'AEO 2026 Table 1'!$E$24 -> 1.1807441 | ... AA71: ='AEO 2026 Table 1'!AD$24/'AEO 2026 Table 1'!$E$24 -> 1.3300409
A72: municipal solid waste | B72: 1 | C72: 1 | D72: 1 | E72: 1 | F72: 1 | G72: 1 | H72: 1 | I72: 1 | J72: 1 | K72: 1 | L72: 1 | M72: 1 | N72: 1 | O72: 1 | P72: 1 | Q72: 1 | R72: 1 | S72: 1 | T72: 1 | U72: 1 | V72: 1 | W72: 1 | X72: 1 | Y72: 1 | Z72: 1 | AA72: 1
A73: hydrogen | B73: 1 | C73: 1 | D73: 1 | E73: 1 | F73: 1 | G73: 1 | H73: 1 | I73: 1 | J73: 1 | K73: 1 | L73: 1 | M73: 1 | N73: 1 | O73: 1 | P73: 1 | Q73: 1 | R73: 1 | S73: 1 | T73: 1 | U73: 1 | V73: 1 | W73: 1 | X73: 1 | Y73: 1 | Z73: 1 | AA73: 1

Sheet Calibration
A1: Calibrated BAU fuel production (BFPIaE-production) for fuels whose production the model balances
A2: calibration/steps/05-bfpiae/solve.py two-filter rule: for fuels the model produces domestically, the balanced production from the BAU run replaces the AEO-scaled path so the input is consistent with modelled demand; loop run -> solve until the largest change in 'BAU Percent Change in Fuel Production from Calculated Fuel Demand' is within 2% (converged in two passes; see calibration/calibration-log.md). Fuels not listed keep the Start Year Data x Time Series Scaling Factors formulas in the output tab. Block 2 keeps the pre-calibration (AEO-scaled) values for comparison; block 3 is the ratio.
A4: CALIBRATED PRODUCTION USED IN THE OUTPUT TAB (BTU) | B4: 2025 | C4: 2026 | D4: 2027 | E4: 2028 | F4: 2029 | G4: 2030 | H4: 2031 | I4: 2032 | J4: 2033 | K4: 2034 | L4: 2035 | M4: 2036 | N4: 2037 | O4: 2038 | P4: 2039 | Q4: 2040 | R4: 2041 | S4: 2042 | T4: 2043 | U4: 2044 | V4: 2045 | W4: 2046 | X4: 2047 | Y4: 2048 | Z4: 2049 | AA4: 2050
A5: hard coal | B5: 1.04799e+16 | C5: 1.06788e+16 | D5: 1.01839e+16 | E5: 9.98409e+15 | F5: 9.72638e+15 | G5: 9.58461e+15 | H5: 9.3327e+15 | I5: 9.20152e+15 | J5: 9.05464e+15 | K5: 8.87726e+15 | L5: 8.69729e+15 | M5: 8.55962e+15 | N5: 8.401e+15 | O5: 8.01963e+15 | P5: 7.64829e+15 | Q5: 7.50213e+15 | R5: 7.35983e+15 | S5: 7.21548e+15 | T5: 7.06102e+15 | U5: 6.90054e+15 | V5: 6.65603e+15 | W5: 6.59687e+15 | X5: 6.45064e+15 | Y5: 6.35738e+15 | Z5: 6.2503e+15 | AA5: 6.10248e+15
A6: natural gas | B6: 4.02559e+16 | C6: 3.93077e+16 | D6: 3.9636e+16 | E6: 4.00058e+16 | F6: 4.00633e+16 | G6: 4.09295e+16 | H6: 4.1477e+16 | I6: 4.26306e+16 | J6: 4.35282e+16 | K6: 4.4492e+16 | L6: 4.4772e+16 | M6: 4.46882e+16 | N6: 4.4387e+16 | O6: 4.41782e+16 | P6: 4.4009e+16 | Q6: 4.41575e+16 | R6: 4.46017e+16 | S6: 4.49927e+16 | T6: 4.53008e+16 | U6: 4.56496e+16 | V6: 4.5917e+16 | W6: 4.62669e+16 | X6: 4.62888e+16 | Y6: 4.61087e+16 | Z6: 4.59025e+16 | AA6: 4.56889e+16
A7: petroleum gasoline | B7: 1.62789e+16 | C7: 1.61356e+16 | D7: 1.61235e+16 | E7: 1.59605e+16 | F7: 1.58372e+16 | G7: 1.5683e+16 | H7: 1.55359e+16 | I7: 1.53932e+16 | J7: 1.52006e+16 | K7: 1.50055e+16 | L7: 1.47734e+16 | M7: 1.45131e+16 | N7: 1.42719e+16 | O7: 1.40362e+16 | P7: 1.3767e+16 | Q7: 1.3488e+16 | R7: 1.31953e+16 | S7: 1.29323e+16 | T7: 1.26583e+16 | U7: 1.2358e+16 | V7: 1.20801e+16 | W7: 1.17996e+16 | X7: 1.15154e+16 | Y7: 1.1208e+16 | Z7: 1.091e+16 | AA7: 1.06482e+16
A8: petroleum diesel | B8: 1.20202e+16 | C8: 1.19648e+16 | D8: 1.22513e+16 | E8: 1.23122e+16 | F8: 1.2385e+16 | G8: 1.2481e+16 | H8: 1.25351e+16 | I8: 1.26178e+16 | J8: 1.26332e+16 | K8: 1.2656e+16 | L8: 1.2653e+16 | M8: 1.26001e+16 | N8: 1.25842e+16 | O8: 1.25925e+16 | P8: 1.25618e+16 | Q8: 1.25639e+16 | R8: 1.25458e+16 | S8: 1.2481e+16 | T8: 1.24261e+16 | U8: 1.23518e+16 | V8: 1.23449e+16 | W8: 1.23315e+16 | X8: 1.23244e+16 | Y8: 1.2255e+16 | Z8: 1.21821e+16 | AA8: 1.21471e+16
A9: jet fuel or kerosene | B9: 2.297e+15 | C9: 2.34188e+15 | D9: 2.3888e+15 | E9: 2.39257e+15 | F9: 2.41636e+15 | G9: 2.43932e+15 | H9: 2.46883e+15 | I9: 2.50814e+15 | J9: 2.5444e+15 | K9: 2.5848e+15 | L9: 2.62526e+15 | M9: 2.64299e+15 | N9: 2.66857e+15 | O9: 2.69776e+15 | P9: 2.7191e+15 | Q9: 2.74342e+15 | R9: 2.76463e+15 | S9: 2.7838e+15 | T9: 2.80669e+15 | U9: 2.82441e+15 | V9: 2.84788e+15 | W9: 2.87138e+15 | X9: 2.88827e+15 | Y9: 2.89194e+15 | Z9: 2.90305e+15 | AA9: 2.92255e+15
A10: lignite | B10: 291061000000000 | C10: 310291000000000 | D10: 303830000000000 | E10: 313770000000000 | F10: 300343000000000 | G10: 290715000000000 | H10: 285962000000000 | I10: 268040000000000 | J10: 262311000000000 | K10: 255140000000000 | L10: 241968000000000 | M10: 239771000000000 | N10: 230867000000000 | O10: 213300000000000 | P10: 204190000000000 | Q10: 198549000000000 | R10: 193348000000000 | S10: 184627000000000 | T10: 172050000000000 | U10: 160458000000000 | V10: 149801000000000 | W10: 145869000000000 | X10: 138144000000000 | Y10: 134030000000000 | Z10: 128211000000000 | AA10: 124186000000000
A11: LPG propane or butane | B11: 8.87707e+15 | C11: 8.73566e+15 | D11: 9.24656e+15 | E11: 9.35466e+15 | F11: 9.38295e+15 | G11: 9.43576e+15 | H11: 9.58625e+15 | I11: 9.74498e+15 | J11: 9.86751e+15 | K11: 9.9968e+15 | L11: 1.0103e+16 | M11: 1.01424e+16 | N11: 1.02461e+16 | O11: 1.03835e+16 | P11: 1.05018e+16 | Q11: 1.06338e+16 | R11: 1.07625e+16 | S11: 1.08743e+16 | T11: 1.09943e+16 | U11: 1.10697e+16 | V11: 1.12163e+16 | W11: 1.13502e+16 | X11: 1.14994e+16 | Y11: 1.15639e+16 | Z11: 1.15967e+16 | AA11: 1.17026e+16
A13: Pre-calibration production (AEO-scaled formulas, as committed before this calibration) | B13: 2025 | C13: 2026 | D13: 2027 | E13: 2028 | F13: 2029 | G13: 2030 | H13: 2031 | I13: 2032 | J13: 2033 | K13: 2034 | L13: 2035 | M13: 2036 | N13: 2037 | O13: 2038 | P13: 2039 | Q13: 2040 | R13: 2041 | S13: 2042 | T13: 2043 | U13: 2044 | V13: 2045 | W13: 2046 | X13: 2047 | Y13: 2048 | Z13: 2049 | AA13: 2050
A14: hard coal | B14: 9.28907e+15 | C14: 9.05969e+15 | D14: 8.75196e+15 | E14: 8.21794e+15 | F14: 8.02112e+15 | G14: 8.10902e+15 | H14: 7.30016e+15 | I14: 7.10464e+15 | J14: 6.98484e+15 | K14: 6.75114e+15 | L14: 6.73595e+15 | M14: 6.61699e+15 | N14: 6.59678e+15 | O14: 6.60386e+15 | P14: 6.54886e+15 | Q14: 6.41936e+15 | R14: 6.27772e+15 | S14: 6.17132e+15 | T14: 6.10734e+15 | U14: 6.04938e+15 | V14: 5.98136e+15 | W14: 5.92593e+15 | X14: 5.93705e+15 | Y14: 5.91522e+15 | Z14: 5.8312e+15 | AA14: 5.60694e+15
A15: natural gas | B15: 4.05704e+16 | C15: 4.02944e+16 | D15: 3.9723e+16 | E15: 4.04999e+16 | F15: 4.08871e+16 | G15: 4.20273e+16 | H15: 4.3181e+16 | I15: 4.42595e+16 | J15: 4.51016e+16 | K15: 4.61689e+16 | L15: 4.6665e+16 | M15: 4.70172e+16 | N15: 4.7329e+16 | O15: 4.76591e+16 | P15: 4.79838e+16 | Q15: 4.85815e+16 | R15: 4.92901e+16 | S15: 4.99745e+16 | T15: 5.05664e+16 | U15: 5.11176e+16 | V15: 5.1666e+16 | W15: 5.23729e+16 | X15: 5.28075e+16 | Y15: 5.31171e+16 | Z15: 5.32298e+16 | AA15: 5.33421e+16
A16: petroleum gasoline | B16: 1.77984e+16 | C16: 1.76358e+16 | D16: 1.76959e+16 | E16: 1.77294e+16 | F16: 1.76202e+16 | G16: 1.77635e+16 | H16: 1.77562e+16 | I16: 1.76632e+16 | J16: 1.73669e+16 | K16: 1.72069e+16 | L16: 1.70097e+16 | M16: 1.69279e+16 | N16: 1.68945e+16 | O16: 1.67738e+16 | P16: 1.6752e+16 | Q16: 1.6922e+16 | R16: 1.70844e+16 | S16: 1.71348e+16 | T16: 1.72325e+16 | U16: 1.72717e+16 | V16: 1.72314e+16 | W16: 1.71304e+16 | X16: 1.70309e+16 | Y16: 1.69024e+16 | Z16: 1.67203e+16 | AA16: 1.64672e+16
... A22: Calibrated / pre-calibration | B22: 2025 | C22: 2026 | D22: 2027 | E22: 2028 | F22: 2029 | G22: 2030 | H22: 2031 | I22: 2032 | J22: 2033 | K22: 2034 | L22: 2035 | M22: 2036 | N22: 2037 | O22: 2038 | P22: 2039 | Q22: 2040 | R22: 2041 | S22: 2042 | T22: 2043 | U22: 2044 | V22: 2045 | W22: 2046 | X22: 2047 | Y22: 2048 | Z22: 2049 | AA22: 2050
A23: hard coal | B23: =IFERROR(B5/B14,"") -> 1.1281969 | C23: =IFERROR(C5/C14,"") -> 1.1787158 | D23: =IFERROR(D5/D14,"") -> 1.1636136 | E23: =IFERROR(E5/E14,"") -> 1.214914 | F23: =IFERROR(F5/F14,"") -> 1.2125962 | G23: =IFERROR(G5/G14,"") -> 1.181969 | H23: =IFERROR(H5/H14,"") -> 1.278424 | I23: =IFERROR(I5/I14,"") -> 1.2951423 | ... AA23: =IFERROR(AA5/AA14,"") -> 1.0883798
A24: natural gas | B24: =IFERROR(B6/B15,"") -> 0.99224804 | C24: =IFERROR(C6/C15,"") -> 0.97551273 | D24: =IFERROR(D6/D15,"") -> 0.99780983 | E24: =IFERROR(E6/E15,"") -> 0.98779997 | F24: =IFERROR(F6/F15,"") -> 0.97985184 | G24: =IFERROR(G6/G15,"") -> 0.97387888 | H24: =IFERROR(H6/H15,"") -> 0.9605382 | I24: =IFERROR(I6/I15,"") -> 0.9631966 | ... AA24: =IFERROR(AA6/AA15,"") -> 0.85652608
A25: petroleum gasoline | B25: =IFERROR(B7/B16,"") -> 0.91462716 | C25: =IFERROR(C7/C16,"") -> 0.91493439 | D25: =IFERROR(D7/D16,"") -> 0.91114326 | E25: =IFERROR(E7/E16,"") -> 0.90022787 | F25: =IFERROR(F7/F16,"") -> 0.89880932 | G25: =IFERROR(G7/G16,"") -> 0.88287781 | H25: =IFERROR(H7/H16,"") -> 0.87495635 | I25: =IFERROR(I7/I16,"") -> 0.87148422 | ... AA25: =IFERROR(AA7/AA16,"") -> 0.64663088
A26: petroleum diesel | B26: =IFERROR(B8/B17,"") -> 1.1422354 | C26: =IFERROR(C8/C17,"") -> 1.1474605 | D26: =IFERROR(D8/D17,"") -> 1.1709389 | E26: =IFERROR(E8/E17,"") -> 1.1745369 | F26: =IFERROR(F8/F17,"") -> 1.1888078 | G26: =IFERROR(G8/G17,"") -> 1.1883611 | H26: =IFERROR(H8/H17,"") -> 1.194001 | I26: =IFERROR(I8/I17,"") -> 1.2082081 | ... AA26: =IFERROR(AA8/AA17,"") -> 1.2476069
A27: jet fuel or kerosene | B27: =IFERROR(B9/B18,"") -> 0.60870257 | C27: =IFERROR(C9/C18,"") -> 0.62631849 | D27: =IFERROR(D9/D18,"") -> 0.63669583 | E27: =IFERROR(E9/E18,"") -> 0.63649786 | F27: =IFERROR(F9/F18,"") -> 0.64680847 | G27: =IFERROR(G9/G18,"") -> 0.64768904 | H27: =IFERROR(H9/H18,"") -> 0.65579445 | I27: =IFERROR(I9/I18,"") -> 0.66974283 | ... AA27: =IFERROR(AA9/AA18,"") -> 0.83708068
A28: lignite | B28: =IFERROR(B10/B19,"") -> 0.55982743 | C28: =IFERROR(C10/C19,"") -> 0.61192449 | D28: =IFERROR(D10/D19,"") -> 0.6202511 | E28: =IFERROR(E10/E19,"") -> 0.68216653 | F28: =IFERROR(F10/F19,"") -> 0.66899732 | G28: =IFERROR(G10/G19,"") -> 0.64053188 | H28: =IFERROR(H10/H19,"") -> 0.69987175 | I28: =IFERROR(I10/I19,"") -> 0.6740601 | ... AA28: =IFERROR(AA10/AA19,"") -> 0.39572114
A29: LPG propane or butane | B29: =IFERROR(B11/B20,"") -> 1.042688 | C29: =IFERROR(C11/C20,"") -> 1.0074594 | D29: =IFERROR(D11/D20,"") -> 0.99342164 | E29: =IFERROR(E11/E20,"") -> 1.0154522 | F29: =IFERROR(F11/F20,"") -> 1.0145627 | G29: =IFERROR(G11/G20,"") -> 1.0165621 | H29: =IFERROR(H11/H20,"") -> 0.98556847 | I29: =IFERROR(I11/I20,"") -> 0.96024792 | ... AA29: =IFERROR(AA11/AA20,"") -> 0.94243561

Sheet BFPIaE-production
A1: Fuel (BTU) | B1: 2025 | C1: 2026 | D1: 2027 | E1: 2028 | F1: 2029 | G1: 2030 | H1: 2031 | I1: 2032 | J1: 2033 | K1: 2034 | L1: 2035 | M1: 2036 | N1: 2037 | O1: 2038 | P1: 2039 | Q1: 2040 | R1: 2041 | S1: 2042 | T1: 2043 | U1: 2044 | V1: 2045 | W1: 2046 | X1: 2047 | Y1: 2048 | Z1: 2049 | AA1: 2050
A2: electricity (not used in this variable) | B2: ='Start Year Data'!B26 -> 0 | C2: =$B2*'Time Series Scaling Factors'!C3 -> 0 | D2: =$B2*'Time Series Scaling Factors'!D3 -> 0 | E2: =$B2*'Time Series Scaling Factors'!E3 -> 0 | F2: =$B2*'Time Series Scaling Factors'!F3 -> 0 | G2: =$B2*'Time Series Scaling Factors'!G3 -> 0 | H2: =$B2*'Time Series Scaling Factors'!H3 -> 0 | I2: =$B2*'Time Series Scaling Factors'!I3 -> 0 | J2: =$B2*'Time Series Scaling Factors'!J3 -> 0 | ... AA2: =$B2*'Time Series Scaling Factors'!AA3 -> 0
A3: hard coal | B3: =Calibration!B5 -> 1.04799e+16 | C3: =Calibration!C5 -> 1.06788e+16 | D3: =Calibration!D5 -> 1.01839e+16 | E3: =Calibration!E5 -> 9.98409e+15 | F3: =Calibration!F5 -> 9.72638e+15 | G3: =Calibration!G5 -> 9.58461e+15 | H3: =Calibration!H5 -> 9.3327e+15 | I3: =Calibration!I5 -> 9.20152e+15 | ... AA3: =Calibration!AA5 -> 6.10248e+15
A4: natural gas | B4: =Calibration!B6 -> 4.02559e+16 | C4: =Calibration!C6 -> 3.93077e+16 | D4: =Calibration!D6 -> 3.9636e+16 | E4: =Calibration!E6 -> 4.00058e+16 | F4: =Calibration!F6 -> 4.00633e+16 | G4: =Calibration!G6 -> 4.09295e+16 | H4: =Calibration!H6 -> 4.1477e+16 | I4: =Calibration!I6 -> 4.26306e+16 | ... AA4: =Calibration!AA6 -> 4.56889e+16
A5: nuclear | B5: ='Start Year Data'!B29 -> 1.2186e+14 | C5: =$B5*'Time Series Scaling Factors'!C6 -> 1.2461472e+14 | D5: =$B5*'Time Series Scaling Factors'!D6 -> 1.2385128e+14 | E5: =$B5*'Time Series Scaling Factors'!E6 -> 1.2438543e+14 | F5: =$B5*'Time Series Scaling Factors'!F6 -> 1.2452359e+14 | G5: =$B5*'Time Series Scaling Factors'!G6 -> 1.2462914e+14 | H5: =$B5*'Time Series Scaling Factors'!H6 -> 1.2463139e+14 | I5: =$B5*'Time Series Scaling Factors'!I6 -> 1.246315e+14 | J5: =$B5*'Time Series Scaling Factors'!J6 -> 1.246273e+14 | ... AA5: =$B5*'Time Series Scaling Factors'!AA6 -> 1.24623e+14
A6: hydro (is not a fuel) | B6: ='Start Year Data'!B30 -> 0 | C6: =$B6*'Time Series Scaling Factors'!C7 -> 0 | D6: =$B6*'Time Series Scaling Factors'!D7 -> 0 | E6: =$B6*'Time Series Scaling Factors'!E7 -> 0 | F6: =$B6*'Time Series Scaling Factors'!F7 -> 0 | G6: =$B6*'Time Series Scaling Factors'!G7 -> 0 | H6: =$B6*'Time Series Scaling Factors'!H7 -> 0 | I6: =$B6*'Time Series Scaling Factors'!I7 -> 0 | J6: =$B6*'Time Series Scaling Factors'!J7 -> 0 | ... AA6: =$B6*'Time Series Scaling Factors'!AA7 -> 0
A7: wind (is not a fuel) | B7: ='Start Year Data'!B31 -> 0 | C7: =$B7*'Time Series Scaling Factors'!C8 -> 0 | D7: =$B7*'Time Series Scaling Factors'!D8 -> 0 | E7: =$B7*'Time Series Scaling Factors'!E8 -> 0 | F7: =$B7*'Time Series Scaling Factors'!F8 -> 0 | G7: =$B7*'Time Series Scaling Factors'!G8 -> 0 | H7: =$B7*'Time Series Scaling Factors'!H8 -> 0 | I7: =$B7*'Time Series Scaling Factors'!I8 -> 0 | J7: =$B7*'Time Series Scaling Factors'!J8 -> 0 | ... AA7: =$B7*'Time Series Scaling Factors'!AA8 -> 0
A8: solar (is not a fuel) | B8: ='Start Year Data'!B32 -> 0 | C8: =$B8*'Time Series Scaling Factors'!C9 -> 0 | D8: =$B8*'Time Series Scaling Factors'!D9 -> 0 | E8: =$B8*'Time Series Scaling Factors'!E9 -> 0 | F8: =$B8*'Time Series Scaling Factors'!F9 -> 0 | G8: =$B8*'Time Series Scaling Factors'!G9 -> 0 | H8: =$B8*'Time Series Scaling Factors'!H9 -> 0 | I8: =$B8*'Time Series Scaling Factors'!I9 -> 0 | J8: =$B8*'Time Series Scaling Factors'!J9 -> 0 | ... AA8: =$B8*'Time Series Scaling Factors'!AA9 -> 0
A9: biomass | B9: ='Start Year Data'!B33 -> 238899434690000 | C9: =$B9*'Time Series Scaling Factors'!C10 -> 2.4505851e+14 | D9: =$B9*'Time Series Scaling Factors'!D10 -> 2.4300583e+14 | E9: =$B9*'Time Series Scaling Factors'!E10 -> 2.4321787e+14 | F9: =$B9*'Time Series Scaling Factors'!F10 -> 242320638523068 | G9: =$B9*'Time Series Scaling Factors'!G10 -> 2.388135e+14 | H9: =$B9*'Time Series Scaling Factors'!H10 -> 236896868268608 | I9: =$B9*'Time Series Scaling Factors'!I10 -> 2.3569323e+14 | J9: =$B9*'Time Series Scaling Factors'!J10 -> 2.3520182e+14 | ... AA9: =$B9*'Time Series Scaling Factors'!AA10 -> 2.6502075e+14
A10: petroleum gasoline | B10: =Calibration!B7 -> 1.62789e+16 | C10: =Calibration!C7 -> 1.61356e+16 | D10: =Calibration!D7 -> 1.61235e+16 | E10: =Calibration!E7 -> 1.59605e+16 | F10: =Calibration!F7 -> 1.58372e+16 | G10: =Calibration!G7 -> 1.5683e+16 | H10: =Calibration!H7 -> 1.55359e+16 | I10: =Calibration!I7 -> 1.53932e+16 | ... AA10: =Calibration!AA7 -> 1.06482e+16
A11: petroleum diesel | B11: =Calibration!B8 -> 1.20202e+16 | C11: =Calibration!C8 -> 1.19648e+16 | D11: =Calibration!D8 -> 1.22513e+16 | E11: =Calibration!E8 -> 1.23122e+16 | F11: =Calibration!F8 -> 1.2385e+16 | G11: =Calibration!G8 -> 1.2481e+16 | H11: =Calibration!H8 -> 1.25351e+16 | I11: =Calibration!I8 -> 1.26178e+16 | ... AA11: =Calibration!AA8 -> 1.21471e+16
A12: biofuel gasoline | B12: ='Start Year Data'!B36 -> 1.5431057e+15 | C12: =$B12*'Time Series Scaling Factors'!C13 -> 1.5290066e+15 | D12: =$B12*'Time Series Scaling Factors'!D13 -> 1.5342209e+15 | E12: =$B12*'Time Series Scaling Factors'!E13 -> 1.537119e+15 | F12: =$B12*'Time Series Scaling Factors'!F13 -> 1.527655e+15 | G12: =$B12*'Time Series Scaling Factors'!G13 -> 1.5400767e+15 | H12: =$B12*'Time Series Scaling Factors'!H13 -> 1.5394422e+15 | I12: =$B12*'Time Series Scaling Factors'!I13 -> 1.5313827e+15 | J12: =$B12*'Time Series Scaling Factors'!J13 -> 1.5056898e+15 | ... AA12: =$B12*'Time Series Scaling Factors'!AA13 -> 1.4276927e+15
A13: biofuel diesel | B13: ='Start Year Data'!B37 -> 665276978000000 | C13: =$B13*'Time Series Scaling Factors'!C14 -> 6.5919846e+14 | D13: =$B13*'Time Series Scaling Factors'!D14 -> 6.614465e+14 | E13: =$B13*'Time Series Scaling Factors'!E14 -> 6.6269595e+14 | F13: =$B13*'Time Series Scaling Factors'!F14 -> 6.5861576e+14 | G13: =$B13*'Time Series Scaling Factors'!G14 -> 6.6397113e+14 | H13: =$B13*'Time Series Scaling Factors'!H14 -> 6.6369757e+14 | I13: =$B13*'Time Series Scaling Factors'!I14 -> 6.6022289e+14 | J13: =$B13*'Time Series Scaling Factors'!J14 -> 6.4914594e+14 | ... AA13: =$B13*'Time Series Scaling Factors'!AA14 -> 615519143882941
A14: jet fuel or kerosene | B14: =Calibration!B9 -> 2.297e+15 | C14: =Calibration!C9 -> 2.34188e+15 | D14: =Calibration!D9 -> 2.3888e+15 | E14: =Calibration!E9 -> 2.39257e+15 | F14: =Calibration!F9 -> 2.41636e+15 | G14: =Calibration!G9 -> 2.43932e+15 | H14: =Calibration!H9 -> 2.46883e+15 | I14: =Calibration!I9 -> 2.50814e+15 | ... AA14: =Calibration!AA9 -> 2.92255e+15
A15: heat (not used in this variable) | B15: ='Start Year Data'!B39 -> 0 | C15: =$B15*'Time Series Scaling Factors'!C16 -> 0 | D15: =$B15*'Time Series Scaling Factors'!D16 -> 0 | E15: =$B15*'Time Series Scaling Factors'!E16 -> 0 | F15: =$B15*'Time Series Scaling Factors'!F16 -> 0 | G15: =$B15*'Time Series Scaling Factors'!G16 -> 0 | H15: =$B15*'Time Series Scaling Factors'!H16 -> 0 | I15: =$B15*'Time Series Scaling Factors'!I16 -> 0 | J15: =$B15*'Time Series Scaling Factors'!J16 -> 0 | ... AA15: =$B15*'Time Series Scaling Factors'!AA16 -> 0
A16: geothermal (is not a fuel) | B16: ='Start Year Data'!B40 -> 0 | C16: =$B16*'Time Series Scaling Factors'!C17 -> 0 | D16: =$B16*'Time Series Scaling Factors'!D17 -> 0 | E16: =$B16*'Time Series Scaling Factors'!E17 -> 0 | F16: =$B16*'Time Series Scaling Factors'!F17 -> 0 | G16: =$B16*'Time Series Scaling Factors'!G17 -> 0 | H16: =$B16*'Time Series Scaling Factors'!H17 -> 0 | I16: =$B16*'Time Series Scaling Factors'!I17 -> 0 | J16: =$B16*'Time Series Scaling Factors'!J17 -> 0 | ... AA16: =$B16*'Time Series Scaling Factors'!AA17 -> 0
A17: lignite | B17: =Calibration!B10 -> 291061000000000 | C17: =Calibration!C10 -> 310291000000000 | D17: =Calibration!D10 -> 303830000000000 | E17: =Calibration!E10 -> 313770000000000 | F17: =Calibration!F10 -> 300343000000000 | G17: =Calibration!G10 -> 290715000000000 | H17: =Calibration!H10 -> 285962000000000 | I17: =Calibration!I10 -> 268040000000000 | ... AA17: =Calibration!AA10 -> 124186000000000
A18: crude oil | B18: ='Start Year Data'!B42 -> 2.7585282e+16 | C18: =$B18*'Time Series Scaling Factors'!C19 -> 2.733324e+16 | D18: =$B18*'Time Series Scaling Factors'!D19 -> 2.7426454e+16 | E18: =$B18*'Time Series Scaling Factors'!E19 -> 2.7478261e+16 | F18: =$B18*'Time Series Scaling Factors'!F19 -> 2.7309079e+16 | G18: =$B18*'Time Series Scaling Factors'!G19 -> 2.7531136e+16 | H18: =$B18*'Time Series Scaling Factors'!H19 -> 2.7519793e+16 | I18: =$B18*'Time Series Scaling Factors'!I19 -> 2.7375718e+16 | J18: =$B18*'Time Series Scaling Factors'!J19 -> 2.6916419e+16 | ... AA18: =$B18*'Time Series Scaling Factors'!AA19 -> 2.5522105e+16
A19: heavy fuel oil | B19: ='Start Year Data'!B43 -> 727701389000000 | C19: =$B19*'Time Series Scaling Factors'!C20 -> 7.2105252e+14 | D19: =$B19*'Time Series Scaling Factors'!D20 -> 7.2351149e+14 | E19: =$B19*'Time Series Scaling Factors'!E20 -> 7.2487818e+14 | F19: =$B19*'Time Series Scaling Factors'!F20 -> 7.2041513e+14 | G19: =$B19*'Time Series Scaling Factors'!G20 -> 726273011663050 | H19: =$B19*'Time Series Scaling Factors'!H20 -> 7.2597379e+14 | I19: =$B19*'Time Series Scaling Factors'!I20 -> 7.2217307e+14 | J19: =$B19*'Time Series Scaling Factors'!J20 -> 7.1005674e+14 | ... AA19: =$B19*'Time Series Scaling Factors'!AA20 -> 6.7327467e+14
A20: LPG propane or butane | B20: =Calibration!B11 -> 8.87707e+15 | C20: =Calibration!C11 -> 8.73566e+15 | D20: =Calibration!D11 -> 9.24656e+15 | E20: =Calibration!E11 -> 9.35466e+15 | F20: =Calibration!F11 -> 9.38295e+15 | G20: =Calibration!G11 -> 9.43576e+15 | H20: =Calibration!H11 -> 9.58625e+15 | I20: =Calibration!I11 -> 9.74498e+15 | ... AA20: =Calibration!AA11 -> 1.17026e+16
A21: municipal solid waste | B21: ='Start Year Data'!B45 -> 3.9663658e+15 | C21: =$B21*'Time Series Scaling Factors'!C22 -> 3.820885e+15 | D21: =$B21*'Time Series Scaling Factors'!D22 -> 1.8175451e+15 | E21: =$B21*'Time Series Scaling Factors'!E22 -> 1.6486425e+15 | F21: =$B21*'Time Series Scaling Factors'!F22 -> 1.6291707e+15 | G21: =$B21*'Time Series Scaling Factors'!G22 -> 1.6157915e+15 | H21: =$B21*'Time Series Scaling Factors'!H22 -> 1.5751498e+15 | I21: =$B21*'Time Series Scaling Factors'!I22 -> 1.2575065e+15 | J21: =$B21*'Time Series Scaling Factors'!J22 -> 1.2625812e+15 | ... AA21: =$B21*'Time Series Scaling Factors'!AA22 -> 1.3964902e+15
A22: hydrogen | B22: ='Start Year Data'!B46 -> 772086274509804 | C22: =$B22*'Time Series Scaling Factors'!C23 -> 7.1518227e+14 | D22: =$B22*'Time Series Scaling Factors'!D23 -> 7.1026699e+14 | E22: =$B22*'Time Series Scaling Factors'!E23 -> 7.1283436e+14 | F22: =$B22*'Time Series Scaling Factors'!F23 -> 726807016367331 | G22: =$B22*'Time Series Scaling Factors'!G23 -> 7.2459384e+14 | H22: =$B22*'Time Series Scaling Factors'!H23 -> 7.1226919e+14 | I22: =$B22*'Time Series Scaling Factors'!I23 -> 7.0935019e+14 | J22: =$B22*'Time Series Scaling Factors'!J23 -> 7.1203786e+14 | ... AA22: =$B22*'Time Series Scaling Factors'!AA23 -> 8.2526963e+14

Sheet BFPIaE-imports
A1: Fuel (BTU) | B1: 2025 | C1: 2026 | D1: 2027 | E1: 2028 | F1: 2029 | G1: 2030 | H1: 2031 | I1: 2032 | J1: 2033 | K1: 2034 | L1: 2035 | M1: 2036 | N1: 2037 | O1: 2038 | P1: 2039 | Q1: 2040 | R1: 2041 | S1: 2042 | T1: 2043 | U1: 2044 | V1: 2045 | W1: 2046 | X1: 2047 | Y1: 2048 | Z1: 2049 | AA1: 2050
A2: electricity (not used in this variable) | B2: ='Start Year Data'!C26 -> 0 | C2: =$B2*'Time Series Scaling Factors'!C28 -> 0 | D2: =$B2*'Time Series Scaling Factors'!D28 -> 0 | E2: =$B2*'Time Series Scaling Factors'!E28 -> 0 | F2: =$B2*'Time Series Scaling Factors'!F28 -> 0 | G2: =$B2*'Time Series Scaling Factors'!G28 -> 0 | H2: =$B2*'Time Series Scaling Factors'!H28 -> 0 | I2: =$B2*'Time Series Scaling Factors'!I28 -> 0 | J2: =$B2*'Time Series Scaling Factors'!J28 -> 0 | ... AA2: =$B2*'Time Series Scaling Factors'!AA28 -> 0
A3: hard coal | B3: ='Start Year Data'!C27 -> 39271857858308 | C3: =$B3*'Time Series Scaling Factors'!C29 -> 6.0720283e+13 | D3: =$B3*'Time Series Scaling Factors'!D29 -> 8.5287549e+13 | E3: =$B3*'Time Series Scaling Factors'!E29 -> 1.0178384e+14 | F3: =$B3*'Time Series Scaling Factors'!F29 -> 1.1039757e+14 | G3: =$B3*'Time Series Scaling Factors'!G29 -> 1.2088991e+14 | H3: =$B3*'Time Series Scaling Factors'!H29 -> 1.2005936e+14 | I3: =$B3*'Time Series Scaling Factors'!I29 -> 1.2241669e+14 | J3: =$B3*'Time Series Scaling Factors'!J29 -> 1.2665804e+14 | ... AA3: =$B3*'Time Series Scaling Factors'!AA29 -> 9.1737756e+13
A4: natural gas | B4: ='Start Year Data'!C28 -> 3.256896e+15 | C4: =$B4*'Time Series Scaling Factors'!C30 -> 3.391662e+15 | D4: =$B4*'Time Series Scaling Factors'!D30 -> 3.244866e+15 | E4: =$B4*'Time Series Scaling Factors'!E30 -> 2.953583e+15 | F4: =$B4*'Time Series Scaling Factors'!F30 -> 2.832458e+15 | G4: =$B4*'Time Series Scaling Factors'!G30 -> 2.97589e+15 | H4: =$B4*'Time Series Scaling Factors'!H30 -> 2.959408e+15 | I4: =$B4*'Time Series Scaling Factors'!I30 -> 2.754073e+15 | J4: =$B4*'Time Series Scaling Factors'!J30 -> 2.516675e+15 | ... AA4: =$B4*'Time Series Scaling Factors'!AA30 -> 2.948299e+15
A5: nuclear | B5: ='Start Year Data'!C29 -> 9.94014e+15 | C5: =$B5*'Time Series Scaling Factors'!C31 -> 9.94014e+15 | D5: =$B5*'Time Series Scaling Factors'!D31 -> 9.94014e+15 | E5: =$B5*'Time Series Scaling Factors'!E31 -> 9.94014e+15 | F5: =$B5*'Time Series Scaling Factors'!F31 -> 9.94014e+15 | G5: =$B5*'Time Series Scaling Factors'!G31 -> 9.94014e+15 | H5: =$B5*'Time Series Scaling Factors'!H31 -> 9.94014e+15 | I5: =$B5*'Time Series Scaling Factors'!I31 -> 9.94014e+15 | J5: =$B5*'Time Series Scaling Factors'!J31 -> 9.94014e+15 | ... AA5: =$B5*'Time Series Scaling Factors'!AA31 -> 9.94014e+15
A6: hydro (is not a fuel) | B6: ='Start Year Data'!C30 -> 0 | C6: =$B6*'Time Series Scaling Factors'!C32 -> 0 | D6: =$B6*'Time Series Scaling Factors'!D32 -> 0 | E6: =$B6*'Time Series Scaling Factors'!E32 -> 0 | F6: =$B6*'Time Series Scaling Factors'!F32 -> 0 | G6: =$B6*'Time Series Scaling Factors'!G32 -> 0 | H6: =$B6*'Time Series Scaling Factors'!H32 -> 0 | I6: =$B6*'Time Series Scaling Factors'!I32 -> 0 | J6: =$B6*'Time Series Scaling Factors'!J32 -> 0 | ... AA6: =$B6*'Time Series Scaling Factors'!AA32 -> 0
A7: wind (is not a fuel) | B7: ='Start Year Data'!C31 -> 0 | C7: =$B7*'Time Series Scaling Factors'!C33 -> 0 | D7: =$B7*'Time Series Scaling Factors'!D33 -> 0 | E7: =$B7*'Time Series Scaling Factors'!E33 -> 0 | F7: =$B7*'Time Series Scaling Factors'!F33 -> 0 | G7: =$B7*'Time Series Scaling Factors'!G33 -> 0 | H7: =$B7*'Time Series Scaling Factors'!H33 -> 0 | I7: =$B7*'Time Series Scaling Factors'!I33 -> 0 | J7: =$B7*'Time Series Scaling Factors'!J33 -> 0 | ... AA7: =$B7*'Time Series Scaling Factors'!AA33 -> 0
A8: solar (is not a fuel) | B8: ='Start Year Data'!C32 -> 0 | C8: =$B8*'Time Series Scaling Factors'!C34 -> 0 | D8: =$B8*'Time Series Scaling Factors'!D34 -> 0 | E8: =$B8*'Time Series Scaling Factors'!E34 -> 0 | F8: =$B8*'Time Series Scaling Factors'!F34 -> 0 | G8: =$B8*'Time Series Scaling Factors'!G34 -> 0 | H8: =$B8*'Time Series Scaling Factors'!H34 -> 0 | I8: =$B8*'Time Series Scaling Factors'!I34 -> 0 | J8: =$B8*'Time Series Scaling Factors'!J34 -> 0 | ... AA8: =$B8*'Time Series Scaling Factors'!AA34 -> 0
A9: biomass | B9: ='Start Year Data'!C33 -> 0 | C9: =$B9*'Time Series Scaling Factors'!C35 -> 0 | D9: =$B9*'Time Series Scaling Factors'!D35 -> 0 | E9: =$B9*'Time Series Scaling Factors'!E35 -> 0 | F9: =$B9*'Time Series Scaling Factors'!F35 -> 0 | G9: =$B9*'Time Series Scaling Factors'!G35 -> 0 | H9: =$B9*'Time Series Scaling Factors'!H35 -> 0 | I9: =$B9*'Time Series Scaling Factors'!I35 -> 0 | J9: =$B9*'Time Series Scaling Factors'!J35 -> 0 | ... AA9: =$B9*'Time Series Scaling Factors'!AA35 -> 0
A10: petroleum gasoline | B10: ='Start Year Data'!C34 -> 201618837721000 | C10: =$B10*'Time Series Scaling Factors'!C36 -> 1.9662537e+14 | D10: =$B10*'Time Series Scaling Factors'!D36 -> 2.0551077e+14 | E10: =$B10*'Time Series Scaling Factors'!E36 -> 200826881735682 | F10: =$B10*'Time Series Scaling Factors'!F36 -> 1.9603547e+14 | G10: =$B10*'Time Series Scaling Factors'!G36 -> 1.947413e+14 | H10: =$B10*'Time Series Scaling Factors'!H36 -> 1.9205861e+14 | I10: =$B10*'Time Series Scaling Factors'!I36 -> 1.8910021e+14 | J10: =$B10*'Time Series Scaling Factors'!J36 -> 1.8679863e+14 | ... AA10: =$B10*'Time Series Scaling Factors'!AA36 -> 1.7973497e+14
A11: petroleum diesel | B11: ='Start Year Data'!C35 -> 313781100000000 | C11: =$B11*'Time Series Scaling Factors'!C37 -> 3.0600972e+14 | D11: =$B11*'Time Series Scaling Factors'!D37 -> 3.1983814e+14 | E11: =$B11*'Time Series Scaling Factors'!E37 -> 3.1254857e+14 | F11: =$B11*'Time Series Scaling Factors'!F37 -> 3.0509166e+14 | G11: =$B11*'Time Series Scaling Factors'!G37 -> 3.0307754e+14 | H11: =$B11*'Time Series Scaling Factors'!H37 -> 2.9890244e+14 | I11: =$B11*'Time Series Scaling Factors'!I37 -> 2.9429825e+14 | J11: =$B11*'Time Series Scaling Factors'!J37 -> 2.9071628e+14 | ... AA11: =$B11*'Time Series Scaling Factors'!AA37 -> 2.7972305e+14
A12: biofuel gasoline | B12: ='Start Year Data'!C36 -> 0 | C12: =$B12*'Time Series Scaling Factors'!C38 -> 0 | D12: =$B12*'Time Series Scaling Factors'!D38 -> 0 | E12: =$B12*'Time Series Scaling Factors'!E38 -> 0 | F12: =$B12*'Time Series Scaling Factors'!F38 -> 0 | G12: =$B12*'Time Series Scaling Factors'!G38 -> 0 | H12: =$B12*'Time Series Scaling Factors'!H38 -> 0 | I12: =$B12*'Time Series Scaling Factors'!I38 -> 0 | J12: =$B12*'Time Series Scaling Factors'!J38 -> 0 | ... AA12: =$B12*'Time Series Scaling Factors'!AA38 -> 0
A13: biofuel diesel | B13: ='Start Year Data'!C37 -> 121247375000000 | C13: =$B13*'Time Series Scaling Factors'!C39 -> 1.1824446e+14 | D13: =$B13*'Time Series Scaling Factors'!D39 -> 1.2358786e+14 | E13: =$B13*'Time Series Scaling Factors'!E39 -> 1.2077112e+14 | F13: =$B13*'Time Series Scaling Factors'!F39 -> 1.1788971e+14 | G13: =$B13*'Time Series Scaling Factors'!G39 -> 1.1711144e+14 | H13: =$B13*'Time Series Scaling Factors'!H39 -> 1.1549815e+14 | I13: =$B13*'Time Series Scaling Factors'!I39 -> 1.1371905e+14 | J13: =$B13*'Time Series Scaling Factors'!J39 -> 1.1233496e+14 | ... AA13: =$B13*'Time Series Scaling Factors'!AA39 -> 1.0808709e+14
... A22: hydrogen | B22: ='Start Year Data'!C46 -> 0 | C22: =$B22*'Time Series Scaling Factors'!C48 -> 0 | D22: =$B22*'Time Series Scaling Factors'!D48 -> 0 | E22: =$B22*'Time Series Scaling Factors'!E48 -> 0 | F22: =$B22*'Time Series Scaling Factors'!F48 -> 0 | G22: =$B22*'Time Series Scaling Factors'!G48 -> 0 | H22: =$B22*'Time Series Scaling Factors'!H48 -> 0 | I22: =$B22*'Time Series Scaling Factors'!I48 -> 0 | J22: =$B22*'Time Series Scaling Factors'!J48 -> 0 | ... AA22: =$B22*'Time Series Scaling Factors'!AA48 -> 0

Sheet BFPIaE-exports
A1: Fuel (BTU) | B1: 2025 | C1: 2026 | D1: 2027 | E1: 2028 | F1: 2029 | G1: 2030 | H1: 2031 | I1: 2032 | J1: 2033 | K1: 2034 | L1: 2035 | M1: 2036 | N1: 2037 | O1: 2038 | P1: 2039 | Q1: 2040 | R1: 2041 | S1: 2042 | T1: 2043 | U1: 2044 | V1: 2045 | W1: 2046 | X1: 2047 | Y1: 2048 | Z1: 2049 | AA1: 2050
A2: electricity (not used in this variable) | B2: ='Start Year Data'!$D26 -> 0 | C2: =$B2*'Time Series Scaling Factors'!C53 -> 0 | D2: =$B2*'Time Series Scaling Factors'!D53 -> 0 | E2: =$B2*'Time Series Scaling Factors'!E53 -> 0 | F2: =$B2*'Time Series Scaling Factors'!F53 -> 0 | G2: =$B2*'Time Series Scaling Factors'!G53 -> 0 | H2: =$B2*'Time Series Scaling Factors'!H53 -> 0 | I2: =$B2*'Time Series Scaling Factors'!I53 -> 0 | J2: =$B2*'Time Series Scaling Factors'!J53 -> 0 | ... AA2: =$B2*'Time Series Scaling Factors'!AA53 -> 0
A3: hard coal | B3: ='Start Year Data'!$D$27 -> 2.1295264e+15 | C3: =$B3*'Time Series Scaling Factors'!C54 -> 2.212403e+15 | D3: =$B3*'Time Series Scaling Factors'!D54 -> 2.3651726e+15 | E3: =$B3*'Time Series Scaling Factors'!E54 -> 2.4634482e+15 | F3: =$B3*'Time Series Scaling Factors'!F54 -> 2.3786464e+15 | G3: =$B3*'Time Series Scaling Factors'!G54 -> 2.4951356e+15 | H3: =$B3*'Time Series Scaling Factors'!H54 -> 2.5138809e+15 | I3: =$B3*'Time Series Scaling Factors'!I54 -> 2.6639335e+15 | J3: =$B3*'Time Series Scaling Factors'!J54 -> 2.6894511e+15 | ... AA3: =$B3*'Time Series Scaling Factors'!AA54 -> 2.6230005e+15
A4: natural gas | B4: ='Start Year Data'!$D$28 -> 8.975658e+15 | C4: =$B4*'Time Series Scaling Factors'!C55 -> 9.088441e+15 | D4: =$B4*'Time Series Scaling Factors'!D55 -> 9.822119e+15 | E4: =$B4*'Time Series Scaling Factors'!E55 -> 1.0434997e+16 | F4: =$B4*'Time Series Scaling Factors'!F55 -> 1.0937449e+16 | G4: =$B4*'Time Series Scaling Factors'!G55 -> 1.2260552e+16 | H4: =$B4*'Time Series Scaling Factors'!H55 -> 1.2868597e+16 | I4: =$B4*'Time Series Scaling Factors'!I55 -> 1.3509771e+16 | J4: =$B4*'Time Series Scaling Factors'!J55 -> 1.3987963e+16 | ... AA4: =$B4*'Time Series Scaling Factors'!AA55 -> 1.8544718e+16
A5: nuclear | B5: ='Start Year Data'!$D$29 -> 0 | C5: =$B5*'Time Series Scaling Factors'!C56 -> 0 | D5: =$B5*'Time Series Scaling Factors'!D56 -> 0 | E5: =$B5*'Time Series Scaling Factors'!E56 -> 0 | F5: =$B5*'Time Series Scaling Factors'!F56 -> 0 | G5: =$B5*'Time Series Scaling Factors'!G56 -> 0 | H5: =$B5*'Time Series Scaling Factors'!H56 -> 0 | I5: =$B5*'Time Series Scaling Factors'!I56 -> 0 | J5: =$B5*'Time Series Scaling Factors'!J56 -> 0 | ... AA5: =$B5*'Time Series Scaling Factors'!AA56 -> 0
A6: hydro (is not a fuel) | B6: ='Start Year Data'!$D$30 -> 0 | C6: =$B6*'Time Series Scaling Factors'!C57 -> 0 | D6: =$B6*'Time Series Scaling Factors'!D57 -> 0 | E6: =$B6*'Time Series Scaling Factors'!E57 -> 0 | F6: =$B6*'Time Series Scaling Factors'!F57 -> 0 | G6: =$B6*'Time Series Scaling Factors'!G57 -> 0 | H6: =$B6*'Time Series Scaling Factors'!H57 -> 0 | I6: =$B6*'Time Series Scaling Factors'!I57 -> 0 | J6: =$B6*'Time Series Scaling Factors'!J57 -> 0 | ... AA6: =$B6*'Time Series Scaling Factors'!AA57 -> 0
A7: wind (is not a fuel) | B7: ='Start Year Data'!$D$31 -> 0 | C7: =$B7*'Time Series Scaling Factors'!C58 -> 0 | D7: =$B7*'Time Series Scaling Factors'!D58 -> 0 | E7: =$B7*'Time Series Scaling Factors'!E58 -> 0 | F7: =$B7*'Time Series Scaling Factors'!F58 -> 0 | G7: =$B7*'Time Series Scaling Factors'!G58 -> 0 | H7: =$B7*'Time Series Scaling Factors'!H58 -> 0 | I7: =$B7*'Time Series Scaling Factors'!I58 -> 0 | J7: =$B7*'Time Series Scaling Factors'!J58 -> 0 | ... AA7: =$B7*'Time Series Scaling Factors'!AA58 -> 0
A8: solar (is not a fuel) | B8: ='Start Year Data'!$D$32 -> 0 | C8: =$B8*'Time Series Scaling Factors'!C59 -> 0 | D8: =$B8*'Time Series Scaling Factors'!D59 -> 0 | E8: =$B8*'Time Series Scaling Factors'!E59 -> 0 | F8: =$B8*'Time Series Scaling Factors'!F59 -> 0 | G8: =$B8*'Time Series Scaling Factors'!G59 -> 0 | H8: =$B8*'Time Series Scaling Factors'!H59 -> 0 | I8: =$B8*'Time Series Scaling Factors'!I59 -> 0 | J8: =$B8*'Time Series Scaling Factors'!J59 -> 0 | ... AA8: =$B8*'Time Series Scaling Factors'!AA59 -> 0
A9: biomass | B9: ='Start Year Data'!$D$33 -> 158847922072000 | C9: =$B9*'Time Series Scaling Factors'!C60 -> 158847922072000 | D9: =$B9*'Time Series Scaling Factors'!D60 -> 158847922072000 | E9: =$B9*'Time Series Scaling Factors'!E60 -> 158847922072000 | F9: =$B9*'Time Series Scaling Factors'!F60 -> 158847922072000 | G9: =$B9*'Time Series Scaling Factors'!G60 -> 158847922072000 | H9: =$B9*'Time Series Scaling Factors'!H60 -> 158847922072000 | I9: =$B9*'Time Series Scaling Factors'!I60 -> 158847922072000 | J9: =$B9*'Time Series Scaling Factors'!J60 -> 158847922072000 | ... AA9: =$B9*'Time Series Scaling Factors'!AA60 -> 158847922072000
A10: petroleum gasoline | B10: ='Start Year Data'!$D$34 -> 1.4728061e+15 | C10: =$B10*'Time Series Scaling Factors'!C61 -> 1.4609157e+15 | D10: =$B10*'Time Series Scaling Factors'!D61 -> 1.5857433e+15 | E10: =$B10*'Time Series Scaling Factors'!E61 -> 1.5874313e+15 | F10: =$B10*'Time Series Scaling Factors'!F61 -> 1.6238938e+15 | G10: =$B10*'Time Series Scaling Factors'!G61 -> 1.6454056e+15 | H10: =$B10*'Time Series Scaling Factors'!H61 -> 1.6896112e+15 | I10: =$B10*'Time Series Scaling Factors'!I61 -> 1.7390071e+15 | J10: =$B10*'Time Series Scaling Factors'!J61 -> 1.7705655e+15 | ... AA10: =$B10*'Time Series Scaling Factors'!AA61 -> 1.9588924e+15
A11: petroleum diesel | B11: ='Start Year Data'!$D$35 -> 2.7530756e+15 | C11: =$B11*'Time Series Scaling Factors'!C62 -> 2.7308492e+15 | D11: =$B11*'Time Series Scaling Factors'!D62 -> 2.9641859e+15 | E11: =$B11*'Time Series Scaling Factors'!E62 -> 2.9673412e+15 | F11: =$B11*'Time Series Scaling Factors'!F62 -> 3.0354996e+15 | G11: =$B11*'Time Series Scaling Factors'!G62 -> 3.075711e+15 | H11: =$B11*'Time Series Scaling Factors'!H62 -> 3.1583433e+15 | I11: =$B11*'Time Series Scaling Factors'!I62 -> 3.2506777e+15 | J11: =$B11*'Time Series Scaling Factors'!J62 -> 3.309669e+15 | ... AA11: =$B11*'Time Series Scaling Factors'!AA62 -> 3.661703e+15
A12: biofuel gasoline | B12: ='Start Year Data'!$D$36 -> 184633752099000 | C12: =$B12*'Time Series Scaling Factors'!C63 -> 1.8314315e+14 | D12: =$B12*'Time Series Scaling Factors'!D63 -> 1.9879177e+14 | E12: =$B12*'Time Series Scaling Factors'!E63 -> 1.9900338e+14 | F12: =$B12*'Time Series Scaling Factors'!F63 -> 2.0357439e+14 | G12: =$B12*'Time Series Scaling Factors'!G63 -> 206271152321444 | H12: =$B12*'Time Series Scaling Factors'!H63 -> 2.1181285e+14 | I12: =$B12*'Time Series Scaling Factors'!I63 -> 2.1800521e+14 | J12: =$B12*'Time Series Scaling Factors'!J63 -> 2.2196143e+14 | ... AA12: =$B12*'Time Series Scaling Factors'!AA63 -> 2.4557044e+14
A13: biofuel diesel | B13: ='Start Year Data'!$D$37 -> 23059777000000 | C13: =$B13*'Time Series Scaling Factors'!C64 -> 2.2873609e+13 | D13: =$B13*'Time Series Scaling Factors'!D64 -> 2.4828038e+13 | E13: =$B13*'Time Series Scaling Factors'!E64 -> 2.4854467e+13 | F13: =$B13*'Time Series Scaling Factors'!F64 -> 2.5425362e+13 | G13: =$B13*'Time Series Scaling Factors'!G64 -> 2.5762174e+13 | H13: =$B13*'Time Series Scaling Factors'!H64 -> 2.6454302e+13 | I13: =$B13*'Time Series Scaling Factors'!I64 -> 2.7227695e+13 | J13: =$B13*'Time Series Scaling Factors'!J64 -> 2.7721806e+13 | ... AA13: =$B13*'Time Series Scaling Factors'!AA64 -> 3.0670446e+13
A14: jet fuel or kerosene | B14: ='Start Year Data'!$D$38 -> 447136200000000 | C14: =$B14*'Time Series Scaling Factors'!C65 -> 4.4352634e+14 | D14: =$B14*'Time Series Scaling Factors'!D65 -> 4.8142333e+14 | E14: =$B14*'Time Series Scaling Factors'!E65 -> 4.819358e+14 | F14: =$B14*'Time Series Scaling Factors'!F65 -> 4.9300563e+14 | G14: =$B14*'Time Series Scaling Factors'!G65 -> 4.995365e+14 | H14: =$B14*'Time Series Scaling Factors'!H65 -> 5.1295709e+14 | I14: =$B14*'Time Series Scaling Factors'!I65 -> 5.2795342e+14 | J14: =$B14*'Time Series Scaling Factors'!J65 -> 5.3753439e+14 | ... AA14: =$B14*'Time Series Scaling Factors'!AA65 -> 5.9470942e+14
A15: heat (energy carrier) | B15: ='Start Year Data'!$D$39 -> 0 | C15: =$B15*'Time Series Scaling Factors'!C66 -> 0 | D15: =$B15*'Time Series Scaling Factors'!D66 -> 0 | E15: =$B15*'Time Series Scaling Factors'!E66 -> 0 | F15: =$B15*'Time Series Scaling Factors'!F66 -> 0 | G15: =$B15*'Time Series Scaling Factors'!G66 -> 0 | H15: =$B15*'Time Series Scaling Factors'!H66 -> 0 | I15: =$B15*'Time Series Scaling Factors'!I66 -> 0 | J15: =$B15*'Time Series Scaling Factors'!J66 -> 0 | ... AA15: =$B15*'Time Series Scaling Factors'!AA66 -> 0
A16: geothermal (is not a fuel) | B16: ='Start Year Data'!$D$40 -> 0 | C16: =$B16*'Time Series Scaling Factors'!C67 -> 0 | D16: =$B16*'Time Series Scaling Factors'!D67 -> 0 | E16: =$B16*'Time Series Scaling Factors'!E67 -> 0 | F16: =$B16*'Time Series Scaling Factors'!F67 -> 0 | G16: =$B16*'Time Series Scaling Factors'!G67 -> 0 | H16: =$B16*'Time Series Scaling Factors'!H67 -> 0 | I16: =$B16*'Time Series Scaling Factors'!I67 -> 0 | J16: =$B16*'Time Series Scaling Factors'!J67 -> 0 | ... AA16: =$B16*'Time Series Scaling Factors'!AA67 -> 0
A17: lignite | B17: ='Start Year Data'!$D$41 -> 0 | C17: =$B17*'Time Series Scaling Factors'!C68 -> 0 | D17: =$B17*'Time Series Scaling Factors'!D68 -> 0 | E17: =$B17*'Time Series Scaling Factors'!E68 -> 0 | F17: =$B17*'Time Series Scaling Factors'!F68 -> 0 | G17: =$B17*'Time Series Scaling Factors'!G68 -> 0 | H17: =$B17*'Time Series Scaling Factors'!H68 -> 0 | I17: =$B17*'Time Series Scaling Factors'!I68 -> 0 | J17: =$B17*'Time Series Scaling Factors'!J68 -> 0 | ... AA17: =$B17*'Time Series Scaling Factors'!AA68 -> 0
A18: crude oil | B18: ='Start Year Data'!$D$42 -> 8.5315054e+15 | C18: =$B18*'Time Series Scaling Factors'!C69 -> 8.462628e+15 | D18: =$B18*'Time Series Scaling Factors'!D69 -> 9.1857151e+15 | E18: =$B18*'Time Series Scaling Factors'!E69 -> 9.1954931e+15 | F18: =$B18*'Time Series Scaling Factors'!F69 -> 9.4067092e+15 | G18: =$B18*'Time Series Scaling Factors'!G69 -> 9.5313204e+15 | H18: =$B18*'Time Series Scaling Factors'!H69 -> 9.7873896e+15 | I18: =$B18*'Time Series Scaling Factors'!I69 -> 1.0073525e+16 | J18: =$B18*'Time Series Scaling Factors'!J69 -> 1.0256333e+16 | ... AA18: =$B18*'Time Series Scaling Factors'!AA69 -> 1.1347251e+16
A19: heavy fuel oil | B19: ='Start Year Data'!$D$43 -> 314368861000000 | C19: =$B19*'Time Series Scaling Factors'!C70 -> 3.1183087e+14 | D19: =$B19*'Time Series Scaling Factors'!D70 -> 3.3847518e+14 | E19: =$B19*'Time Series Scaling Factors'!E70 -> 3.3883548e+14 | F19: =$B19*'Time Series Scaling Factors'!F70 -> 3.4661837e+14 | G19: =$B19*'Time Series Scaling Factors'!G70 -> 3.5121004e+14 | H19: =$B19*'Time Series Scaling Factors'!H70 -> 3.6064567e+14 | I19: =$B19*'Time Series Scaling Factors'!I70 -> 3.7118917e+14 | J19: =$B19*'Time Series Scaling Factors'!J70 -> 3.7792528e+14 | ... AA19: =$B19*'Time Series Scaling Factors'!AA70 -> 418123434110860
A20: LPG propane or butane | B20: ='Start Year Data'!$D$44 -> 3.8556327e+15 | C20: =$B20*'Time Series Scaling Factors'!C71 -> 3.824505e+15 | D20: =$B20*'Time Series Scaling Factors'!D71 -> 4.1512888e+15 | E20: =$B20*'Time Series Scaling Factors'!E71 -> 4.1557078e+15 | F20: =$B20*'Time Series Scaling Factors'!F71 -> 4.2511624e+15 | G20: =$B20*'Time Series Scaling Factors'!G71 -> 4.3074778e+15 | H20: =$B20*'Time Series Scaling Factors'!H71 -> 4.4232028e+15 | I20: =$B20*'Time Series Scaling Factors'!I71 -> 4.5525154e+15 | J20: =$B20*'Time Series Scaling Factors'!J71 -> 4.6351316e+15 | ... AA20: =$B20*'Time Series Scaling Factors'!AA71 -> 5.128149e+15
A21: municipal solid waste | B21: ='Start Year Data'!$D$45 -> 0 | C21: =$B21*'Time Series Scaling Factors'!C72 -> 0 | D21: =$B21*'Time Series Scaling Factors'!D72 -> 0 | E21: =$B21*'Time Series Scaling Factors'!E72 -> 0 | F21: =$B21*'Time Series Scaling Factors'!F72 -> 0 | G21: =$B21*'Time Series Scaling Factors'!G72 -> 0 | H21: =$B21*'Time Series Scaling Factors'!H72 -> 0 | I21: =$B21*'Time Series Scaling Factors'!I72 -> 0 | J21: =$B21*'Time Series Scaling Factors'!J72 -> 0 | ... AA21: =$B21*'Time Series Scaling Factors'!AA72 -> 0
A22: hydrogen | B22: ='Start Year Data'!$D$46 -> 0 | C22: =$B22*'Time Series Scaling Factors'!C73 -> 0 | D22: =$B22*'Time Series Scaling Factors'!D73 -> 0 | E22: =$B22*'Time Series Scaling Factors'!E73 -> 0 | F22: =$B22*'Time Series Scaling Factors'!F73 -> 0 | G22: =$B22*'Time Series Scaling Factors'!G73 -> 0 | H22: =$B22*'Time Series Scaling Factors'!H73 -> 0 | I22: =$B22*'Time Series Scaling Factors'!I73 -> 0 | J22: =$B22*'Time Series Scaling Factors'!J73 -> 0 | ... AA22: =$B22*'Time Series Scaling Factors'!AA73 -> 0
