Workbook

Sheet About
A1: SoBCaICbIC Share of Buildings Capital and Installation Costs by ISIC Code
A3: Sources: | B3: Building Sector Appliance and Equipment Costs and Efficiencies
B4: EIA
B5: 2018
B6: "Updated Buildings Sector Appliance and Equipment Costs and Efficiencies"
B7: https://www.eia.gov/analysis/studies/buildings/equipcosts/pdf/full.pdf
B10: Commercial Equipment Prevalence
B11: EIA
B12: 2016
B13: Table B39. Heating equipment, floorspace & Table42. Water-heating equipment, number of buildings and floorspace
B14: https://www.eia.gov/consumption/commercial/data/2012/#b38-b46
B17: Residential Equipment Prevelance
B18: U.S. Energy Information Administration
B19: 2026
B20: Annual Energy Outlook 2026
B21: Alternative electricity and transportation: Table 21
B22: https://www.eia.gov/outlooks/aeo/tables_side_xls.php
B25: ISIC Code Mapping
B26: United Nations
B27: 2008
B28: International Standard Industrial Classification of All Economic Activities Revision 4
B29: https://unstats.un.org/unsd/publication/seriesM/seriesm_4rev4e.pdf
B31: Markups on equipment (manufacturer, freight, wholesale and retail)
B32: U.S. Bureau of Economic Analysis
B33: 2017
B34: Margins, Before Redefinitions, Detail (input-output accounts), sheet "2017"
B35: https://apps.bea.gov/industry/release/xlsx/Margins_Before_Redefinitions_Detail.xlsx
B36: Rows for the nine equipment commodities used here are on the "BEA 2017 Margins" tab. Accessed October 2026.
A39: Notes:
A40: Note from "Updated Building Sector Appliance and Equipment Costs and Efficiencies."
A41: The Energy Independence and Security Act of 2007 prescribes standards for current 100 watt incandescent lamps
A42: as of January 1, 2012. Starting in 2012, 100-watt incandescent lamps will be replaced by halogen lamps.
A44: For commercial lighting - estimated cost averages based on selected commercial light fixtures assumed to be most common
A46: Cost averages from NEMS are across appliance type and years (2012-2050)
A48: Water heating, refrigeration, clothes washing/drying, cooking, and diswashing equipment are all assigned to appliances
A50: Other equipment includes primarily additional plug load equipment including computers and televisions
A52: 52-code expansion (2026-07-17):
A53: The output tabs produce the 52-code ISIC list. The derivation above is unchanged and live; output-tab formulas reference the derivation tabs
A54: directly, with the original header-label criteria written as literals (the derivation tabs still use the pre-split 42-code labels).
A56: Children of split parents multiply the parent's allocation by the factors on the 'Factors applied' tab (editable; defaults = BEA 2024 gross-
... A65: conditioning equipment is bought through contractors, while nearly all household appliances and electronics are bought directly.

Sheet Factors applied
A1: Child factors applied inline in the output-tab formulas (editable). Defaults = BEA 2024 output shares; semantic overrides and fuel reroutes noted per row.
A2: File | B2: Row context | C2: Child | D2: Parent | E2: Factor | F2: Rationale | G2: BEA 2024 output share
A3: SoBCaICbIC-commercial.csv | B3: Appliances | C3: ISIC 01 | D3: ISIC 01T03 | E3: 0.94299868 | F3: BEA 2024 output share (default) | G3: 0.94299868
A4: SoBCaICbIC-commercial.csv | B4: Appliances | C4: ISIC 02 | D4: ISIC 01T03 | E4: 0.041765731 | F4: BEA 2024 output share (default) | G4: 0.041765731
A5: SoBCaICbIC-commercial.csv | B5: Appliances | C5: ISIC 03 | D5: ISIC 01T03 | E5: 0.015235586 | F5: BEA 2024 output share (default) | G5: 0.015235586
A6: SoBCaICbIC-commercial.csv | B6: Appliances | C6: ISIC 07 | D6: ISIC 07T08 | E6: 0.43273688 | F6: BEA 2024 output share (default) | G6: 0.43273688
A7: SoBCaICbIC-commercial.csv | B7: Appliances | C7: ISIC 08 | D7: ISIC 07T08 | E7: 0.56726312 | F7: BEA 2024 output share (default) | G7: 0.56726312
A8: SoBCaICbIC-commercial.csv | B8: Appliances | C8: ISIC 301 | D8: ISIC 30 | E8: 0.11713687 | F8: BEA 2024 output share (default) | G8: 0.11713687
A9: SoBCaICbIC-commercial.csv | B9: Appliances | C9: ISIC 302T309 | D9: ISIC 30 | E9: 0.88286313 | F9: BEA 2024 output share (default) | G9: 0.88286313
A10: SoBCaICbIC-commercial.csv | B10: Appliances | C10: ISIC 49 | D10: ISIC 49T53 | E10: 0.45630816 | F10: BEA 2024 output share (default) | G10: 0.45630816
A11: SoBCaICbIC-commercial.csv | B11: Appliances | C11: ISIC 50 | D11: ISIC 49T53 | E11: 0.044370048 | F11: BEA 2024 output share (default) | G11: 0.044370048
A12: SoBCaICbIC-commercial.csv | B12: Appliances | C12: ISIC 51 | D12: ISIC 49T53 | E12: 0.18837505 | F12: BEA 2024 output share (default) | G12: 0.18837505
A13: SoBCaICbIC-commercial.csv | B13: Appliances | C13: ISIC 52 | D13: ISIC 49T53 | E13: 0.22286512 | F13: BEA 2024 output share (default) | G13: 0.22286512
A14: SoBCaICbIC-commercial.csv | B14: Appliances | C14: ISIC 53 | D14: ISIC 49T53 | E14: 0.088081621 | F14: BEA 2024 output share (default) | G14: 0.088081621
... A290: SoBCaICbIC-urbanresidential.csv | B290: Other | C290: ISIC 94T96 | D290: ISIC 90T96 | E290: 0.57837505 | F290: BEA 2024 output share (default) | G290: 0.57837505

Sheet source data>

Sheet OECD Mapping
A1: OECD Code | B1: ISIC Code
A2: D01T03: Agriculture, forestry and fishing | B2: ISIC 01T03
A3: D05: Coal mining | B3: ISIC 05
A4: D06: Oil and gas extraction | B4: ISIC 06
A5: D07T08: Mining and quarrying of non-energy producing products | B5: ISIC 07T08
A6: D09: Mining support service activities | B6: ISIC 09
A7: D10T12: Food products, beverages and tobacco | B7: ISIC 10T12
A8: D13T15: Textiles, wearing apparel, leather and related products | B8: ISIC 13T15
A9: D16: Wood and products of wood and cork | B9: ISIC 16
A10: D17T18: Paper products and printing | B10: ISIC 17T18
A11: D19: Coke and refined petroleum products | B11: ISIC 19
A12: D20: Chemicals | B12: ISIC 20
... A43: D97T98: Private households with employed persons | B43: ISIC 97T98

Sheet ISIC Code Mapping
B1: Heating | C1: Cooling | D1: Envelope | E1: Lighting | F1: Appliances | G1: Other
A2: Equipment | B2: ='OECD Mapping'!B22 -> ISIC 28 | C2: ='OECD Mapping'!B22 -> ISIC 28 | D2: ='OECD Mapping'!B29 -> ISIC 41T43 | E2: ='OECD Mapping'!B21 -> ISIC 27 | F2: ='OECD Mapping'!B21 -> ISIC 27 | G2: ='OECD Mapping'!B21 -> ISIC 27
A3: Installation | B3: ='OECD Mapping'!B29 -> ISIC 41T43 | C3: ='OECD Mapping'!B29 -> ISIC 41T43 | D3: ='OECD Mapping'!B29 -> ISIC 41T43 | E3: ='OECD Mapping'!B29 -> ISIC 41T43 | F3: ='OECD Mapping'!B29 -> ISIC 41T43 | G3: ='OECD Mapping'!B29 -> ISIC 41T43

Sheet Cost Summary New
A1: Costs of Residential Equipment - Weighted Calculation
B3: Equipment Type - Name from RECS | C3: Percent Equipment Costs (Copied from NEMS spreadsheet) | D3: Percent of Total Appliances w/ Cost Data | E3: Weighted Percent Equipment Cost | F3: Weighted Percent Labor Cost | H3: Source | I3: Calculations
A4: Main Space Heaters | D4: =SUM(D5:D13) -> 1 | E4: =SUM(E5:E13) -> 0.55028127 | F4: =1-E4 -> 0.44971873 | H4: https://www.eia.gov/analysis/studies/buildings/equipcosts/pdf/full.pdf | I4: "NEMS cost data_new"
A5: Main Space Heaters | B5: Electric Heat Pumps | C5: 0.74328168 | D5: ='Summary_Res Appliances'!G6 -> 0.15713894 | E5: =D5*C5 -> 0.11679849 | H5: https://www.eia.gov/analysis/studies/buildings/equipcosts/pdf/full.pdf | I5: "NEMS cost data_new"
A6: Main Space Heaters | B6: Electric Other | C6: 0.59090909 | D6: ='Summary_Res Appliances'!G7 -> 0.24672282 | E6: =D6*C6 -> 0.14579076 | H6: https://www.eia.gov/analysis/studies/buildings/equipcosts/pdf/full.pdf | I6: "NEMS cost data_new"
A7: Main Space Heaters | B7: Natural Gas Heat Pumps | D7: ='Summary_Res Appliances'!G8 -> 0 | E7: =D7*C7 -> 0 | H7: https://www.eia.gov/analysis/studies/buildings/equipcosts/pdf/full.pdf | I7: "NEMS cost data_new"
A8: Main Space Heaters | B8: Natural Gas Other | C8: 0.48259279 | D8: ='Summary_Res Appliances'!G9 -> 0.59613825 | E8: =D8*C8 -> 0.28769202 | H8: https://www.eia.gov/analysis/studies/buildings/equipcosts/pdf/full.pdf | I8: "NEMS cost data_new"
A9: Main Space Heaters | B9: Distillate Fuel Oil | D9: ='Summary_Res Appliances'!G10 -> 0 | E9: =D9*C9 -> 0 | H9: https://www.eia.gov/analysis/studies/buildings/equipcosts/pdf/full.pdf | I9: "NEMS cost data_new"
A10: Main Space Heaters | B10: Propane | D10: ='Summary_Res Appliances'!G11 -> 0 | E10: =D10*C10 -> 0 | H10: https://www.eia.gov/analysis/studies/buildings/equipcosts/pdf/full.pdf | I10: "NEMS cost data_new"
A11: Main Space Heaters | B11: Kerosene | D11: ='Summary_Res Appliances'!G12 -> 0 | E11: =D11*C11 -> 0 | H11: https://www.eia.gov/analysis/studies/buildings/equipcosts/pdf/full.pdf | I11: "NEMS cost data_new"
A12: Main Space Heaters | B12: Wood Stoves | D12: ='Summary_Res Appliances'!G13 -> 0 | E12: =D12*C12 -> 0 | H12: https://www.eia.gov/analysis/studies/buildings/equipcosts/pdf/full.pdf | I12: "NEMS cost data_new"
A13: Main Space Heaters | B13: Geothermal Heat Pumps | D13: ='Summary_Res Appliances'!G14 -> 0 | E13: =D13*C13 -> 0 | H13: https://www.eia.gov/analysis/studies/buildings/equipcosts/pdf/full.pdf | I13: "NEMS cost data_new"
A14: Space Cooling | D14: =SUM(D15:D19) -> 1 | E14: =SUM(E15:E19) -> 0.73624569 | F14: =1-E14 -> 0.26375431 | H14: https://www.eia.gov/analysis/studies/buildings/equipcosts/pdf/full.pdf | I14: "NEMS cost data_new"
A15: Space Cooling | B15: Electric Heat Pumps | C15: 0.74328168 | D15: ='Summary_Res Appliances'!G17 -> 0.12261684 | E15: =D15*C15 -> 0.091138851 | H15: https://www.eia.gov/analysis/studies/buildings/equipcosts/pdf/full.pdf | I15: "NEMS cost data_new"
A16: Space Cooling | B16: Natural Gas Heat Pumps | D16: ='Summary_Res Appliances'!G18 -> 0 | E16: =D16*C16 -> 0 | H16: https://www.eia.gov/analysis/studies/buildings/equipcosts/pdf/full.pdf | I16: "NEMS cost data_new"
A17: Space Cooling | B17: Geothermal Heat Pumps | D17: ='Summary_Res Appliances'!G19 -> 0 | E17: =D17*C17 -> 0 | H17: https://www.eia.gov/analysis/studies/buildings/equipcosts/pdf/full.pdf | I17: "NEMS cost data_new"
A18: Space Cooling | B18: Central Air Conditioners | C18: 0.66273252 | D18: ='Summary_Res Appliances'!G20 -> 0.57118911 | E18: =D18*C18 -> 0.3785456 | H18: https://www.eia.gov/analysis/studies/buildings/equipcosts/pdf/full.pdf | I18: "NEMS cost data_new"
A19: Space Cooling | B19: Room Air Conditioners | C19: 0.87056309 | D19: ='Summary_Res Appliances'!G21 -> 0.30619405 | E19: =D19*C19 -> 0.26656124 | H19: https://www.eia.gov/analysis/studies/buildings/equipcosts/pdf/full.pdf | I19: "NEMS cost data_new"
A20: Water Heaters | E20: =SUM(E21:E25) -> 0.55741274 | F20: =1-E20 -> 0.44258726 | H20: https://www.eia.gov/analysis/studies/buildings/equipcosts/pdf/full.pdf | I20: "NEMS cost data_new"
A21: Water Heaters | B21: Electric | C21: 0.56212605 | D21: ='Summary_Res Appliances'!G24 -> 0.48965433 | E21: =D21*C21 -> 0.27524746 | H21: https://www.eia.gov/analysis/studies/buildings/equipcosts/pdf/full.pdf | I21: "NEMS cost data_new"
A22: Water Heaters | B22: Natural Gas | C22: 0.55289052 | D22: ='Summary_Res Appliances'!G25 -> 0.51034567 | E22: =D22*C22 -> 0.28216528 | H22: https://www.eia.gov/analysis/studies/buildings/equipcosts/pdf/full.pdf | I22: "NEMS cost data_new"
A23: Water Heaters | B23: Distillate Fuel Oil | D23: ='Summary_Res Appliances'!G26 -> 0 | E23: =D23*C23 -> 0 | H23: https://www.eia.gov/analysis/studies/buildings/equipcosts/pdf/full.pdf | I23: "NEMS cost data_new"
A24: Water Heaters | B24: Propane | D24: ='Summary_Res Appliances'!G27 -> 0 | E24: =D24*C24 -> 0 | H24: https://www.eia.gov/analysis/studies/buildings/equipcosts/pdf/full.pdf | I24: "NEMS cost data_new"
A25: Water Heaters | B25: Solar Thermal | D25: ='Summary_Res Appliances'!G28 -> 0 | E25: =D25*C25 -> 0 | H25: https://www.eia.gov/analysis/studies/buildings/equipcosts/pdf/full.pdf | I25: "NEMS cost data_new"
A26: Cooking Equipment | E26: =SUM(E27:E30) -> 0.83324329 | F26: =1-E26 -> 0.16675671 | H26: https://www.eia.gov/analysis/studies/buildings/equipcosts/pdf/full.pdf | I26: "NEMS cost data_new"
A27: Cooking Equipment | B27: Electric | D27: ='Summary_Res Appliances'!G31 -> 0 | E27: =D27*C27 -> 0 | H27: https://www.eia.gov/analysis/studies/buildings/equipcosts/pdf/full.pdf | I27: "NEMS cost data_new"
A28: Cooking Equipment | B28: Natural Gas | C28: 0.83324329 | D28: ='Summary_Res Appliances'!G32 -> 1 | E28: =D28*C28 -> 0.83324329 | H28: https://www.eia.gov/analysis/studies/buildings/equipcosts/pdf/full.pdf | I28: "NEMS cost data_new"
A29: Cooking Equipment | B29: Natural Gas | C29: 0.70132633 | D29: ='Summary_Res Appliances'!G33 -> 0 | E29: =D29*C29 -> 0 | H29: https://www.eia.gov/analysis/studies/buildings/equipcosts/pdf/full.pdf | I29: "NEMS cost data_new"
A30: Cooking Equipment | B30: Propane | D30: ='Summary_Res Appliances'!G34 -> 0 | E30: =D30*C30 -> 0 | H30: https://www.eia.gov/analysis/studies/buildings/equipcosts/pdf/full.pdf | I30: "NEMS cost data_new"
A31: Clothes Dryers | E31: =SUM(E32:E33) -> 0.8046221 | F31: =1-E31 -> 0.1953779 | H31: https://www.eia.gov/analysis/studies/buildings/equipcosts/pdf/full.pdf | I31: "NEMS cost data_new"
A32: Clothes Dryers | B32: Electric | C32: 0.81320282 | D32: ='Summary_Res Appliances'!G36 -> 0.82299211 | E32: =D32*C32 -> 0.6692595 | H32: https://www.eia.gov/analysis/studies/buildings/equipcosts/pdf/full.pdf | I32: "NEMS cost data_new"
A33: Clothes Dryers | B33: Natural Gas | C33: 0.76472644 | D33: ='Summary_Res Appliances'!G37 -> 0.17700787 | E33: =D33*C33 -> 0.1353626 | H33: https://www.eia.gov/analysis/studies/buildings/equipcosts/pdf/full.pdf | I33: "NEMS cost data_new"
A34: Other Appliances | E34: =AVERAGE(C35:C38) -> 0.82212755 | F34: =1-E34 -> 0.17787245
A35: Appliances | C35: 1 | H35: https://www.eia.gov/analysis/studies/buildings/equipcosts/pdf/full.pdf | I35: "NEMS cost data_new"
A36: Appliances | C36: 0.6516356 | H36: https://www.eia.gov/analysis/studies/buildings/equipcosts/pdf/full.pdf | I36: "NEMS cost data_new"
A37: Appliances | C37: 0.81848666 | H37: https://www.eia.gov/analysis/studies/buildings/equipcosts/pdf/full.pdf | I37: "NEMS cost data_new"
A38: Appliances | C38: 0.81838794 | H38: https://www.eia.gov/analysis/studies/buildings/equipcosts/pdf/full.pdf | I38: "NEMS cost data_new"
A39: Lighting | C39: 1 | E39: =C39 -> 1 | F39: =1-E39 -> 0 | H39: https://www.eia.gov/analysis/studies/buildings/equipcosts/pdf/full.pdf | I39: "NEMS cost data_new"
A41: Appliances - Average total | E41: =AVERAGE(E31,E34,E26,E20) -> 0.75435142 | F41: =1-E41 -> 0.24564858
A43: Costs of Commercial Equipment - Weighted Calculation
C44: Percent Equipment Costs (Copied from NEMS spreadsheet) | D44: Percent of Total Appliances w/ Cost Data | E44: Weighted Percent Equipment Cost | F44: Weighted Percent Labor Cost | H44: Source | I44: Calculations
A45: Commercial Space Heating Total | E45: =SUM(E46,E54,E62) -> 0.7039875 | F45: =1-E45 -> 0.2960125 | H45: https://www.eia.gov/analysis/studies/buildings/equipcosts/pdf/full.pdf | I45: "NEMS cost data_new"
A46: Electricity | D46: ='Summary_Com Appliances'!E3 -> 0.34719121 | E46: =(AVERAGE(C48:C51)*D46) -> 0.28421351 | F46: =1-E46 -> 0.71578649 | H46: https://www.eia.gov/analysis/studies/buildings/equipcosts/pdf/full.pdf | I46: "NEMS cost data_new"
A47: Electricity | B47: Heat pumps | H47: https://www.eia.gov/analysis/studies/buildings/equipcosts/pdf/full.pdf | I47: "NEMS cost data_new"
A48: Electricity | B48: Furnaces | C48: ='COM_NEMS Cost'!D6 -> 0.82799025 | H48: https://www.eia.gov/analysis/studies/buildings/equipcosts/pdf/full.pdf | I48: "NEMS cost data_new"
A49: Electricity | B49: Indiv- idual space heaters | H49: https://www.eia.gov/analysis/studies/buildings/equipcosts/pdf/full.pdf | I49: "NEMS cost data_new"
A50: Electricity | B50: District heat | H50: https://www.eia.gov/analysis/studies/buildings/equipcosts/pdf/full.pdf | I50: "NEMS cost data_new"
A51: Electricity | B51: Boilers | C51: ='COM_NEMS Cost'!D7 -> 0.80922582 | H51: https://www.eia.gov/analysis/studies/buildings/equipcosts/pdf/full.pdf | I51: "NEMS cost data_new"
A52: Electricity | B52: Pack- aged heating units | H52: https://www.eia.gov/analysis/studies/buildings/equipcosts/pdf/full.pdf | I52: "NEMS cost data_new"
A53: Electricity | B53: Other | H53: https://www.eia.gov/analysis/studies/buildings/equipcosts/pdf/full.pdf | I53: "NEMS cost data_new"
A54: Natural gas | D54: ='Summary_Com Appliances'!E11 -> 0.62252036 | E54: =AVERAGE(C56:C59)*D54 -> 0.39721513 | F54: =1-E54 -> 0.60278487 | H54: https://www.eia.gov/analysis/studies/buildings/equipcosts/pdf/full.pdf | I54: "NEMS cost data_new"
A55: Natural gas | B55: Heat pumps | H55: https://www.eia.gov/analysis/studies/buildings/equipcosts/pdf/full.pdf | I55: "NEMS cost data_new"
A56: Natural gas | B56: Furnaces | C56: ='COM_NEMS Cost'!D4 -> 0.5405477 | H56: https://www.eia.gov/analysis/studies/buildings/equipcosts/pdf/full.pdf | I56: "NEMS cost data_new"
A57: Natural gas | B57: Indiv- idual space heaters | H57: https://www.eia.gov/analysis/studies/buildings/equipcosts/pdf/full.pdf | I57: "NEMS cost data_new"
A58: Natural gas | B58: District heat | H58: https://www.eia.gov/analysis/studies/buildings/equipcosts/pdf/full.pdf | I58: "NEMS cost data_new"
A59: Natural gas | B59: Boilers | C59: ='COM_NEMS Cost'!D8 -> 0.73560375 | H59: https://www.eia.gov/analysis/studies/buildings/equipcosts/pdf/full.pdf | I59: "NEMS cost data_new"
A60: Natural gas | B60: Pack- aged heating units | H60: https://www.eia.gov/analysis/studies/buildings/equipcosts/pdf/full.pdf | I60: "NEMS cost data_new"
A61: Natural gas | B61: Other | H61: https://www.eia.gov/analysis/studies/buildings/equipcosts/pdf/full.pdf | I61: "NEMS cost data_new"
A62: Fuel oil | D62: ='Summary_Com Appliances'!E19 -> 0.03028843 | E62: =AVERAGE(C64:C67)*D62 -> 0.022558859 | F62: =1-E62 -> 0.97744114 | H62: https://www.eia.gov/analysis/studies/buildings/equipcosts/pdf/full.pdf | I62: "NEMS cost data_new"
A63: Fuel oil | B63: Heat pumps | H63: https://www.eia.gov/analysis/studies/buildings/equipcosts/pdf/full.pdf | I63: "NEMS cost data_new"
A64: Fuel oil | B64: Furnaces | C64: ='COM_NEMS Cost'!D5 -> 0.71607519 | H64: https://www.eia.gov/analysis/studies/buildings/equipcosts/pdf/full.pdf | I64: "NEMS cost data_new"
A65: Fuel oil | B65: Indiv- idual space heaters | H65: https://www.eia.gov/analysis/studies/buildings/equipcosts/pdf/full.pdf | I65: "NEMS cost data_new"
A66: Fuel oil | B66: District heat | H66: https://www.eia.gov/analysis/studies/buildings/equipcosts/pdf/full.pdf | I66: "NEMS cost data_new"
A67: Fuel oil | B67: Boilers | C67: ='COM_NEMS Cost'!D9 -> 0.77352719 | H67: https://www.eia.gov/analysis/studies/buildings/equipcosts/pdf/full.pdf | I67: "NEMS cost data_new"
A68: Fuel oil | B68: Pack- aged heating units | H68: https://www.eia.gov/analysis/studies/buildings/equipcosts/pdf/full.pdf | I68: "NEMS cost data_new"
A69: Fuel oil | B69: Other | H69: https://www.eia.gov/analysis/studies/buildings/equipcosts/pdf/full.pdf | I69: "NEMS cost data_new"
A70: District heat | H70: https://www.eia.gov/analysis/studies/buildings/equipcosts/pdf/full.pdf | I70: "NEMS cost data_new"
A71: District heat | B71: Heat pumps | H71: https://www.eia.gov/analysis/studies/buildings/equipcosts/pdf/full.pdf | I71: "NEMS cost data_new"
A72: District heat | B72: Furnaces | H72: https://www.eia.gov/analysis/studies/buildings/equipcosts/pdf/full.pdf | I72: "NEMS cost data_new"
A73: District heat | B73: Indiv- idual space heaters | H73: https://www.eia.gov/analysis/studies/buildings/equipcosts/pdf/full.pdf | I73: "NEMS cost data_new"
A74: District heat | B74: District heat | H74: https://www.eia.gov/analysis/studies/buildings/equipcosts/pdf/full.pdf | I74: "NEMS cost data_new"
A75: District heat | B75: Boilers | H75: https://www.eia.gov/analysis/studies/buildings/equipcosts/pdf/full.pdf | I75: "NEMS cost data_new"
A76: District heat | B76: Pack- aged heating units | H76: https://www.eia.gov/analysis/studies/buildings/equipcosts/pdf/full.pdf | I76: "NEMS cost data_new"
A77: District heat | B77: Other | H77: https://www.eia.gov/analysis/studies/buildings/equipcosts/pdf/full.pdf | I77: "NEMS cost data_new"
A78: Propane | H78: https://www.eia.gov/analysis/studies/buildings/equipcosts/pdf/full.pdf | I78: "NEMS cost data_new"
A79: Propane | B79: Heat pumps | H79: https://www.eia.gov/analysis/studies/buildings/equipcosts/pdf/full.pdf | I79: "NEMS cost data_new"
A80: Propane | B80: Furnaces | H80: https://www.eia.gov/analysis/studies/buildings/equipcosts/pdf/full.pdf | I80: "NEMS cost data_new"
A81: Propane | B81: Indiv- idual space heaters | H81: https://www.eia.gov/analysis/studies/buildings/equipcosts/pdf/full.pdf | I81: "NEMS cost data_new"
A82: Propane | B82: District heat | H82: https://www.eia.gov/analysis/studies/buildings/equipcosts/pdf/full.pdf | I82: "NEMS cost data_new"
A83: Propane | B83: Boilers | H83: https://www.eia.gov/analysis/studies/buildings/equipcosts/pdf/full.pdf | I83: "NEMS cost data_new"
A84: Propane | B84: Pack- aged heating units | H84: https://www.eia.gov/analysis/studies/buildings/equipcosts/pdf/full.pdf | I84: "NEMS cost data_new"
A85: Propane | B85: Other | H85: https://www.eia.gov/analysis/studies/buildings/equipcosts/pdf/full.pdf | I85: "NEMS cost data_new"
H86: https://www.eia.gov/analysis/studies/buildings/equipcosts/pdf/full.pdf | I86: "NEMS cost data_new"
H87: https://www.eia.gov/analysis/studies/buildings/equipcosts/pdf/full.pdf | I87: "NEMS cost data_new"
A88: Water Heating Equipment | E88: =SUM(E89:E91) -> 0.75439887 | F88: =1-E88 -> 0.24560113 | H88: https://www.eia.gov/analysis/studies/buildings/equipcosts/pdf/full.pdf | I88: "NEMS cost data_new"
A89: Electricity | B89: Buildings with water heating | C89: ='COM_NEMS Cost'!D14 -> 0.76129032 | D89: ='Summary_Com Appliances'!E46 -> 0.50784544 | E89: =C89*D89 -> 0.38661782 | H89: https://www.eia.gov/analysis/studies/buildings/equipcosts/pdf/full.pdf | I89: "NEMS cost data_new"
A90: Natural gas | B90: Buildings with water heating | C90: ='COM_NEMS Cost'!D13 -> 0.74018277 | D90: ='Summary_Com Appliances'!E47 -> 0.46945563 | E90: =C90*D90 -> 0.34748297 | H90: https://www.eia.gov/analysis/studies/buildings/equipcosts/pdf/full.pdf | I90: "NEMS cost data_new"
A91: Fuel oil | B91: Buildings with water heating | C91: ='COM_NEMS Cost'!D16 -> 0.89423077 | D91: ='Summary_Com Appliances'!E48 -> 0.022698927 | E91: =C91*D91 -> 0.020298079 | H91: https://www.eia.gov/analysis/studies/buildings/equipcosts/pdf/full.pdf | I91: "NEMS cost data_new"
A92: District heat | B92: Buildings with water heating | H92: https://www.eia.gov/analysis/studies/buildings/equipcosts/pdf/full.pdf | I92: "NEMS cost data_new"
A93: Propane | B93: Buildings with water heating | H93: https://www.eia.gov/analysis/studies/buildings/equipcosts/pdf/full.pdf | I93: "NEMS cost data_new"
H94: https://www.eia.gov/analysis/studies/buildings/equipcosts/pdf/full.pdf | I94: "NEMS cost data_new"
A95: Commercial Cooling | E95: =AVERAGE(C96:C98) -> 0.57983011 | F95: =1-E95 -> 0.42016989 | H95: https://www.eia.gov/analysis/studies/buildings/equipcosts/pdf/full.pdf | I95: "NEMS cost data_new"
A96: Electricity | B96: Commercial Rooftop Air Conditioners | C96: ='COM_NEMS Cost'!D10 -> 0.70929577 | D96: NA | H96: https://www.eia.gov/analysis/studies/buildings/equipcosts/pdf/full.pdf | I96: "NEMS cost data_new"
A97: Electricity | B97: Commercial Rooftop Heat Pumps | C97: ='COM_NEMS Cost'!D11 -> 0.72239286 | D97: NA | H97: https://www.eia.gov/analysis/studies/buildings/equipcosts/pdf/full.pdf | I97: "NEMS cost data_new"
A98: Electricity | B98: Commercial Ground Source Heat Pumps | C98: ='COM_NEMS Cost'!D12 -> 0.30780169 | D98: NA | H98: https://www.eia.gov/analysis/studies/buildings/equipcosts/pdf/full.pdf | I98: "NEMS cost data_new"
H99: https://www.eia.gov/analysis/studies/buildings/equipcosts/pdf/full.pdf | I99: "NEMS cost data_new"
A100: Commercial Lighting | E100: =AVERAGE(C101:C103) -> 0.40766895 | F100: =1-E100 -> 0.59233105 | H100: https://www.eia.gov/analysis/studies/buildings/equipcosts/pdf/full.pdf | I100: "NEMS cost data_new"
A101: Commercial Lighting | B101: Commercial Lighting - CFL | C101: ='COM_NEMS Cost'!D17 -> 0.23418372 | D101: NA | H101: https://www.eia.gov/analysis/studies/buildings/equipcosts/pdf/full.pdf | I101: "NEMS cost data_new"
A102: Commercial Lighting | B102: Commercial Lighting - LED | C102: ='COM_NEMS Cost'!D18 -> 0.72691465 | D102: NA | H102: https://www.eia.gov/analysis/studies/buildings/equipcosts/pdf/full.pdf | I102: "NEMS cost data_new"
A103: Commercial Lighting | B103: Commercial Lighting - Halogen | C103: ='COM_NEMS Cost'!D19 -> 0.26190847 | D103: NA | H103: https://www.eia.gov/analysis/studies/buildings/equipcosts/pdf/full.pdf | I103: "NEMS cost data_new"
...

Sheet COM_NEMS Cost
A1: Hard Copied from: "Summary Commercial" tab on "NEMS cost data new.xlsx"
C3: Equipment Type | D3: Percent Equipment Costs
B4: Commercial Heating | C4: Commercial Gas Fired Furnaces | D4: 0.5405477
B5: Commercial Heating | C5: Commercial Oil-Fired Furnaces | D5: 0.71607519
B6: Commercial Heating | C6: Commercial Electric Resistance Heaters | D6: 0.82799025
B7: Commercial Heating | C7: Commercial Electric Boilers | D7: 0.80922582
B8: Commercial Heating | C8: Commercial Gas Fired Boilers | D8: 0.73560375
B9: Commercial Heating | C9: Commercial Oil-Fired Boilers | D9: 0.77352719
B10: Commercial Cooling | C10: Commercial Rooftop Air Conditioners | D10: 0.70929577
B11: Commercial Cooling | C11: Commercial Rooftop Heat Pumps | D11: 0.72239286
B12: Commercial Cooling | C12: Commercial Ground Source Heat Pumps | D12: 0.30780169
B13: Commercial Water Heating | C13: Commercial Gas-Fired Storage Water Heaters | D13: 0.74018277
B14: Commercial Water Heating | C14: Commercial Electric Resistance Storage Water Heaters | D14: 0.76129032
B15: Commercial Water Heating | C15: Commercial Heat Pump Water Heaters | D15: 0.92443572
... B19: Commercial Lighting | C19: Commercial Lighting - Halogen | D19: 0.26190847

Sheet calcs>

Sheet Summary_Com Appliances
A1: Commercial Appliance Prevalance
A2: Fuel | B2: Heating Equipment | C2: Total Floorspace (million square feet) | D2: Percent of Total Appliances | E2: Percent of Total Appliances w/ Cost Data | I2: Source
A3: Electricity | E3: =SUM(C4:C10)/E43 -> 0.34719121
A4: Electricity | B4: Heat pumps | C4: =IFERROR(INDEX(TableB39!$E$154:$K$159,MATCH('Summary_Com Appliances'!$A4,TableB39!$B$154:$B$159,0),MATCH('Summary_Com Appliances'!$B4,TableB39!$E$5:$K$5,0)),"") -> 7215 | D4: =IFERROR(C4/$D$43,"") -> 0.06080859 | I4: =About!$B$14 -> https://www.eia.gov/consumption/commercial/data/2012/#b38-b46
A5: Electricity | B5: Furnaces | C5: =IFERROR(INDEX(TableB39!$E$154:$K$159,MATCH('Summary_Com Appliances'!$A5,TableB39!$B$154:$B$159,0),MATCH('Summary_Com Appliances'!$B5,TableB39!$E$5:$K$5,0)),"") -> 2270 | D5: =IFERROR(C5/$D$43,"") -> 0.019131739 | I5: =About!$B$14 -> https://www.eia.gov/consumption/commercial/data/2012/#b38-b46
A6: Electricity | B6: Indiv- idual space heaters | C6: =IFERROR(INDEX(TableB39!$E$154:$K$159,MATCH('Summary_Com Appliances'!$A6,TableB39!$B$154:$B$159,0),MATCH('Summary_Com Appliances'!$B6,TableB39!$E$5:$K$5,0)),"") -> 6035 | D6: =IFERROR(C6/$D$43,"") -> 0.050863457 | I6: =About!$B$14 -> https://www.eia.gov/consumption/commercial/data/2012/#b38-b46
A7: Electricity | B7: District heat | C7: =IFERROR(INDEX(TableB39!$E$154:$K$159,MATCH('Summary_Com Appliances'!$A7,TableB39!$B$154:$B$159,0),MATCH('Summary_Com Appliances'!$B7,TableB39!$E$5:$K$5,0)),"") -> Q | D7: =IFERROR(C7/$D$43,"") | I7: =About!$B$14 -> https://www.eia.gov/consumption/commercial/data/2012/#b38-b46
A8: Electricity | B8: Boilers | C8: =IFERROR(INDEX(TableB39!$E$154:$K$159,MATCH('Summary_Com Appliances'!$A8,TableB39!$B$154:$B$159,0),MATCH('Summary_Com Appliances'!$B8,TableB39!$E$5:$K$5,0)),"") -> 2982 | D8: =IFERROR(C8/$D$43,"") -> 0.025132532 | I8: =About!$B$14 -> https://www.eia.gov/consumption/commercial/data/2012/#b38-b46
A9: Electricity | B9: Pack- aged heating units | C9: =IFERROR(INDEX(TableB39!$E$154:$K$159,MATCH('Summary_Com Appliances'!$A9,TableB39!$B$154:$B$159,0),MATCH('Summary_Com Appliances'!$B9,TableB39!$E$5:$K$5,0)),"") -> 18523 | D9: =IFERROR(C9/$D$43,"") -> 0.15611331 | I9: =About!$B$14 -> https://www.eia.gov/consumption/commercial/data/2012/#b38-b46
A10: Electricity | B10: Other | C10: =IFERROR(INDEX(TableB39!$E$154:$K$159,MATCH('Summary_Com Appliances'!$A10,TableB39!$B$154:$B$159,0),MATCH('Summary_Com Appliances'!$B10,TableB39!$E$5:$K$5,0)),"") -> 447 | D10: =IFERROR(C10/$D$43,"") -> 0.0037673513 | I10: =About!$B$14 -> https://www.eia.gov/consumption/commercial/data/2012/#b38-b46
A11: Natural gas | C11: =IFERROR(INDEX(TableB39!$E$154:$K$159,MATCH('Summary_Com Appliances'!$A11,TableB39!$B$154:$B$159,0),MATCH('Summary_Com Appliances'!$B11,TableB39!$E$5:$K$5,0)),"") | D11: =IFERROR(C11/$D$43,"") | E11: =SUM(C12:C18)/E43 -> 0.62252036 | I11: =About!$B$14 -> https://www.eia.gov/consumption/commercial/data/2012/#b38-b46
A12: Natural gas | B12: Heat pumps | C12: =IFERROR(INDEX(TableB39!$E$154:$K$159,MATCH('Summary_Com Appliances'!$A12,TableB39!$B$154:$B$159,0),MATCH('Summary_Com Appliances'!$B12,TableB39!$E$5:$K$5,0)),"") -> 3792 | D12: =IFERROR(C12/$D$43,"") -> 0.031959276 | I12: =About!$B$14 -> https://www.eia.gov/consumption/commercial/data/2012/#b38-b46
A13: Natural gas | B13: Furnaces | C13: =IFERROR(INDEX(TableB39!$E$154:$K$159,MATCH('Summary_Com Appliances'!$A13,TableB39!$B$154:$B$159,0),MATCH('Summary_Com Appliances'!$B13,TableB39!$E$5:$K$5,0)),"") -> 5778 | D13: =IFERROR(C13/$D$43,"") -> 0.04869744 | I13: =About!$B$14 -> https://www.eia.gov/consumption/commercial/data/2012/#b38-b46
A14: Natural gas | B14: Indiv- idual space heaters | C14: =IFERROR(INDEX(TableB39!$E$154:$K$159,MATCH('Summary_Com Appliances'!$A14,TableB39!$B$154:$B$159,0),MATCH('Summary_Com Appliances'!$B14,TableB39!$E$5:$K$5,0)),"") -> 11482 | D14: =IFERROR(C14/$D$43,"") -> 0.096771203 | I14: =About!$B$14 -> https://www.eia.gov/consumption/commercial/data/2012/#b38-b46
A15: Natural gas | B15: District heat | C15: =IFERROR(INDEX(TableB39!$E$154:$K$159,MATCH('Summary_Com Appliances'!$A15,TableB39!$B$154:$B$159,0),MATCH('Summary_Com Appliances'!$B15,TableB39!$E$5:$K$5,0)),"") -> Q | D15: =IFERROR(C15/$D$43,"") | I15: =About!$B$14 -> https://www.eia.gov/consumption/commercial/data/2012/#b38-b46
A16: Natural gas | B16: Boilers | C16: =IFERROR(INDEX(TableB39!$E$154:$K$159,MATCH('Summary_Com Appliances'!$A16,TableB39!$B$154:$B$159,0),MATCH('Summary_Com Appliances'!$B16,TableB39!$E$5:$K$5,0)),"") -> 17437 | D16: =IFERROR(C16/$D$43,"") -> 0.14696041 | I16: =About!$B$14 -> https://www.eia.gov/consumption/commercial/data/2012/#b38-b46
A17: Natural gas | B17: Pack- aged heating units | C17: =IFERROR(INDEX(TableB39!$E$154:$K$159,MATCH('Summary_Com Appliances'!$A17,TableB39!$B$154:$B$159,0),MATCH('Summary_Com Appliances'!$B17,TableB39!$E$5:$K$5,0)),"") -> 27826 | D17: =IFERROR(C17/$D$43,"") -> 0.23451973 | I17: =About!$B$14 -> https://www.eia.gov/consumption/commercial/data/2012/#b38-b46
A18: Natural gas | B18: Other | C18: =IFERROR(INDEX(TableB39!$E$154:$K$159,MATCH('Summary_Com Appliances'!$A18,TableB39!$B$154:$B$159,0),MATCH('Summary_Com Appliances'!$B18,TableB39!$E$5:$K$5,0)),"") -> 873 | D18: =IFERROR(C18/$D$43,"") -> 0.007357713 | I18: =About!$B$14 -> https://www.eia.gov/consumption/commercial/data/2012/#b38-b46
A19: Fuel oil | C19: =IFERROR(INDEX(TableB39!$E$154:$K$159,MATCH('Summary_Com Appliances'!$A19,TableB39!$B$154:$B$159,0),MATCH('Summary_Com Appliances'!$B19,TableB39!$E$5:$K$5,0)),"") | D19: =IFERROR(C19/$D$43,"") | E19: =SUM(C20:C26)/E43 -> 0.03028843 | I19: =About!$B$14 -> https://www.eia.gov/consumption/commercial/data/2012/#b38-b46
A20: Fuel oil | B20: Heat pumps | C20: =IFERROR(INDEX(TableB39!$E$154:$K$159,MATCH('Summary_Com Appliances'!$A20,TableB39!$B$154:$B$159,0),MATCH('Summary_Com Appliances'!$B20,TableB39!$E$5:$K$5,0)),"") -> Q | D20: =IFERROR(C20/$D$43,"") | I20: =About!$B$14 -> https://www.eia.gov/consumption/commercial/data/2012/#b38-b46
A21: Fuel oil | B21: Furnaces | C21: =IFERROR(INDEX(TableB39!$E$154:$K$159,MATCH('Summary_Com Appliances'!$A21,TableB39!$B$154:$B$159,0),MATCH('Summary_Com Appliances'!$B21,TableB39!$E$5:$K$5,0)),"") -> Q | D21: =IFERROR(C21/$D$43,"") | I21: =About!$B$14 -> https://www.eia.gov/consumption/commercial/data/2012/#b38-b46
A22: Fuel oil | B22: Indiv- idual space heaters | C22: =IFERROR(INDEX(TableB39!$E$154:$K$159,MATCH('Summary_Com Appliances'!$A22,TableB39!$B$154:$B$159,0),MATCH('Summary_Com Appliances'!$B22,TableB39!$E$5:$K$5,0)),"") -> 1008 | D22: =IFERROR(C22/$D$43,"") -> 0.0084955036 | I22: =About!$B$14 -> https://www.eia.gov/consumption/commercial/data/2012/#b38-b46
A23: Fuel oil | B23: District heat | C23: =IFERROR(INDEX(TableB39!$E$154:$K$159,MATCH('Summary_Com Appliances'!$A23,TableB39!$B$154:$B$159,0),MATCH('Summary_Com Appliances'!$B23,TableB39!$E$5:$K$5,0)),"") -> Q | D23: =IFERROR(C23/$D$43,"") | I23: =About!$B$14 -> https://www.eia.gov/consumption/commercial/data/2012/#b38-b46
A24: Fuel oil | B24: Boilers | C24: =IFERROR(INDEX(TableB39!$E$154:$K$159,MATCH('Summary_Com Appliances'!$A24,TableB39!$B$154:$B$159,0),MATCH('Summary_Com Appliances'!$B24,TableB39!$E$5:$K$5,0)),"") -> 1504 | D24: =IFERROR(C24/$D$43,"") -> 0.012675831 | I24: =About!$B$14 -> https://www.eia.gov/consumption/commercial/data/2012/#b38-b46
A25: Fuel oil | B25: Pack- aged heating units | C25: =IFERROR(INDEX(TableB39!$E$154:$K$159,MATCH('Summary_Com Appliances'!$A25,TableB39!$B$154:$B$159,0),MATCH('Summary_Com Appliances'!$B25,TableB39!$E$5:$K$5,0)),"") -> 757 | D25: =IFERROR(C25/$D$43,"") -> 0.0063800558 | I25: =About!$B$14 -> https://www.eia.gov/consumption/commercial/data/2012/#b38-b46
A26: Fuel oil | B26: Other | C26: =IFERROR(INDEX(TableB39!$E$154:$K$159,MATCH('Summary_Com Appliances'!$A26,TableB39!$B$154:$B$159,0),MATCH('Summary_Com Appliances'!$B26,TableB39!$E$5:$K$5,0)),"") -> Q | D26: =IFERROR(C26/$D$43,"") | I26: =About!$B$14 -> https://www.eia.gov/consumption/commercial/data/2012/#b38-b46
A27: District heat | C27: =IFERROR(INDEX(TableB39!$E$154:$K$159,MATCH('Summary_Com Appliances'!$A27,TableB39!$B$154:$B$159,0),MATCH('Summary_Com Appliances'!$B27,TableB39!$E$5:$K$5,0)),"") | D27: =IFERROR(C27/$D$43,"") | I27: =About!$B$14 -> https://www.eia.gov/consumption/commercial/data/2012/#b38-b46
A28: District heat | B28: Heat pumps | C28: =IFERROR(INDEX(TableB39!$E$154:$K$159,MATCH('Summary_Com Appliances'!$A28,TableB39!$B$154:$B$159,0),MATCH('Summary_Com Appliances'!$B28,TableB39!$E$5:$K$5,0)),"") -> 464 | D28: =IFERROR(C28/$D$43,"") -> 0.0039106287 | I28: =About!$B$14 -> https://www.eia.gov/consumption/commercial/data/2012/#b38-b46
A29: District heat | B29: Furnaces | C29: =IFERROR(INDEX(TableB39!$E$154:$K$159,MATCH('Summary_Com Appliances'!$A29,TableB39!$B$154:$B$159,0),MATCH('Summary_Com Appliances'!$B29,TableB39!$E$5:$K$5,0)),"") -> Q | D29: =IFERROR(C29/$D$43,"") | I29: =About!$B$14 -> https://www.eia.gov/consumption/commercial/data/2012/#b38-b46
A30: District heat | B30: Indiv- idual space heaters | C30: =IFERROR(INDEX(TableB39!$E$154:$K$159,MATCH('Summary_Com Appliances'!$A30,TableB39!$B$154:$B$159,0),MATCH('Summary_Com Appliances'!$B30,TableB39!$E$5:$K$5,0)),"") -> 1271 | D30: =IFERROR(C30/$D$43,"") -> 0.010712088 | I30: =About!$B$14 -> https://www.eia.gov/consumption/commercial/data/2012/#b38-b46
A31: District heat | B31: District heat | C31: =IFERROR(INDEX(TableB39!$E$154:$K$159,MATCH('Summary_Com Appliances'!$A31,TableB39!$B$154:$B$159,0),MATCH('Summary_Com Appliances'!$B31,TableB39!$E$5:$K$5,0)),"") -> 5797 | D31: =IFERROR(C31/$D$43,"") -> 0.048857574 | I31: =About!$B$14 -> https://www.eia.gov/consumption/commercial/data/2012/#b38-b46
A32: District heat | B32: Boilers | C32: =IFERROR(INDEX(TableB39!$E$154:$K$159,MATCH('Summary_Com Appliances'!$A32,TableB39!$B$154:$B$159,0),MATCH('Summary_Com Appliances'!$B32,TableB39!$E$5:$K$5,0)),"") -> Q | D32: =IFERROR(C32/$D$43,"") | I32: =About!$B$14 -> https://www.eia.gov/consumption/commercial/data/2012/#b38-b46
A33: District heat | B33: Pack- aged heating units | C33: =IFERROR(INDEX(TableB39!$E$154:$K$159,MATCH('Summary_Com Appliances'!$A33,TableB39!$B$154:$B$159,0),MATCH('Summary_Com Appliances'!$B33,TableB39!$E$5:$K$5,0)),"") -> 650 | D33: =IFERROR(C33/$D$43,"") -> 0.0054782513 | I33: =About!$B$14 -> https://www.eia.gov/consumption/commercial/data/2012/#b38-b46
A34: District heat | B34: Other | C34: =IFERROR(INDEX(TableB39!$E$154:$K$159,MATCH('Summary_Com Appliances'!$A34,TableB39!$B$154:$B$159,0),MATCH('Summary_Com Appliances'!$B34,TableB39!$E$5:$K$5,0)),"") -> Q | D34: =IFERROR(C34/$D$43,"") | I34: =About!$B$14 -> https://www.eia.gov/consumption/commercial/data/2012/#b38-b46
A35: Propane | C35: =IFERROR(INDEX(TableB39!$E$154:$K$159,MATCH('Summary_Com Appliances'!$A35,TableB39!$B$154:$B$159,0),MATCH('Summary_Com Appliances'!$B35,TableB39!$E$5:$K$5,0)),"") | D35: =IFERROR(C35/$D$43,"") | I35: =About!$B$14 -> https://www.eia.gov/consumption/commercial/data/2012/#b38-b46
A36: Propane | B36: Heat pumps | C36: =IFERROR(INDEX(TableB39!$E$154:$K$159,MATCH('Summary_Com Appliances'!$A36,TableB39!$B$154:$B$159,0),MATCH('Summary_Com Appliances'!$B36,TableB39!$E$5:$K$5,0)),"") -> Q | D36: =IFERROR(C36/$D$43,"") | I36: =About!$B$14 -> https://www.eia.gov/consumption/commercial/data/2012/#b38-b46
A37: Propane | B37: Furnaces | C37: =IFERROR(INDEX(TableB39!$E$154:$K$159,MATCH('Summary_Com Appliances'!$A37,TableB39!$B$154:$B$159,0),MATCH('Summary_Com Appliances'!$B37,TableB39!$E$5:$K$5,0)),"") -> 405 | D37: =IFERROR(C37/$D$43,"") -> 0.003413372 | I37: =About!$B$14 -> https://www.eia.gov/consumption/commercial/data/2012/#b38-b46
A38: Propane | B38: Indiv- idual space heaters | C38: =IFERROR(INDEX(TableB39!$E$154:$K$159,MATCH('Summary_Com Appliances'!$A38,TableB39!$B$154:$B$159,0),MATCH('Summary_Com Appliances'!$B38,TableB39!$E$5:$K$5,0)),"") -> 666 | D38: =IFERROR(C38/$D$43,"") -> 0.0056131006 | I38: =About!$B$14 -> https://www.eia.gov/consumption/commercial/data/2012/#b38-b46
A39: Propane | B39: District heat | C39: =IFERROR(INDEX(TableB39!$E$154:$K$159,MATCH('Summary_Com Appliances'!$A39,TableB39!$B$154:$B$159,0),MATCH('Summary_Com Appliances'!$B39,TableB39!$E$5:$K$5,0)),"") -> N | D39: =IFERROR(C39/$D$43,"") | I39: =About!$B$14 -> https://www.eia.gov/consumption/commercial/data/2012/#b38-b46
A40: Propane | B40: Boilers | C40: =IFERROR(INDEX(TableB39!$E$154:$K$159,MATCH('Summary_Com Appliances'!$A40,TableB39!$B$154:$B$159,0),MATCH('Summary_Com Appliances'!$B40,TableB39!$E$5:$K$5,0)),"") -> 276 | D40: =IFERROR(C40/$D$43,"") -> 0.0023261498 | I40: =About!$B$14 -> https://www.eia.gov/consumption/commercial/data/2012/#b38-b46
A41: Propane | B41: Pack- aged heating units | C41: =IFERROR(INDEX(TableB39!$E$154:$K$159,MATCH('Summary_Com Appliances'!$A41,TableB39!$B$154:$B$159,0),MATCH('Summary_Com Appliances'!$B41,TableB39!$E$5:$K$5,0)),"") -> 1193 | D41: =IFERROR(C41/$D$43,"") -> 0.010054698 | I41: =About!$B$14 -> https://www.eia.gov/consumption/commercial/data/2012/#b38-b46
A42: Propane | B42: Other | C42: =IFERROR(INDEX(TableB39!$E$154:$K$159,MATCH('Summary_Com Appliances'!$A42,TableB39!$B$154:$B$159,0),MATCH('Summary_Com Appliances'!$B42,TableB39!$E$5:$K$5,0)),"") -> Q | D42: =IFERROR(C42/$D$43,"") | I42: =About!$B$14 -> https://www.eia.gov/consumption/commercial/data/2012/#b38-b46
D43: =SUM(C4:C42) -> 118651 | E43: =SUM(C3:C26) -> 107929 | I43: =About!$B$14 -> https://www.eia.gov/consumption/commercial/data/2012/#b38-b46
A45: Fuel | B45: Water Heating Equipment | C45: Total Floorspace (million square feet)
A46: Electricity | B46: Buildings with water heating | C46: =IFERROR(INDEX(TableB42!$H$147:$H$151,MATCH('Summary_Com Appliances'!$A46,TableB42!$A$147:$A$151,0),MATCH('Summary_Com Appliances'!$B46,TableB42!$H$4,0)),"") -> 42755 | D46: =C46/$D$51 -> 0.47339866 | E46: =C46/$E$51 -> 0.50784544 | I46: =About!$B$14 -> https://www.eia.gov/consumption/commercial/data/2012/#b38-b46
A47: Natural gas | B47: Buildings with water heating | C47: =IFERROR(INDEX(TableB42!$H$147:$H$151,MATCH('Summary_Com Appliances'!$A47,TableB42!$A$147:$A$151,0),MATCH('Summary_Com Appliances'!$B47,TableB42!$H$4,0)),"") -> 39523 | D47: =C47/$D$51 -> 0.4376128 | E47: =C47/$E$51 -> 0.46945563 | I47: =About!$B$14 -> https://www.eia.gov/consumption/commercial/data/2012/#b38-b46
A48: Fuel oil | B48: Buildings with water heating | C48: =IFERROR(INDEX(TableB42!$H$147:$H$151,MATCH('Summary_Com Appliances'!$A48,TableB42!$A$147:$A$151,0),MATCH('Summary_Com Appliances'!$B48,TableB42!$H$4,0)),"") -> 1911 | D48: =C48/$D$51 -> 0.021159276 | E48: =C48/$E$51 -> 0.022698927 | I48: =About!$B$14 -> https://www.eia.gov/consumption/commercial/data/2012/#b38-b46
A49: District heat | B49: Buildings with water heating | C49: =IFERROR(INDEX(TableB42!$H$147:$H$151,MATCH('Summary_Com Appliances'!$A49,TableB42!$A$147:$A$151,0),MATCH('Summary_Com Appliances'!$B49,TableB42!$H$4,0)),"") -> 4551 | D49: =C49/$D$51 -> 0.050390301 | I49: =About!$B$14 -> https://www.eia.gov/consumption/commercial/data/2012/#b38-b46
A50: Propane | B50: Buildings with water heating | C50: =IFERROR(INDEX(TableB42!$H$147:$H$151,MATCH('Summary_Com Appliances'!$A50,TableB42!$A$147:$A$151,0),MATCH('Summary_Com Appliances'!$B50,TableB42!$H$4,0)),"") -> 1575 | D50: =C50/$D$51 -> 0.017438964 | I50: =About!$B$14 -> https://www.eia.gov/consumption/commercial/data/2012/#b38-b46
C51: =SUM(C46:C50)=SUM(TableB42!H147:H151) -> TRUE | D51: =SUM(C46:C50) -> 90315 | E51: =SUM(C46:C48) -> 84189

Sheet Summary_Res Appliances
A1: Residential Appliance Prevalance
F2: Calculation | G2: Calculation | I2: Source
B3: full name | C3: api key | D3: units | E3: 2025 | F3: Percent of Total Appliances | G3: Percent of Total Appliances w/ Cost Data
A4: Equipment Stock (million units) | I4: =About!$B$21 -> Alternative electricity and transportation: Table 21
A5: Main Space Heaters | I5: =About!$B$21 -> Alternative electricity and transportation: Table 21
A6: Electric Heat Pumps | B6: Residential Equipment: Equipment Stock: Main Space Heaters: Electric Heat Pumps: Alternative Electricity and Transportation | D6: millions | E6: =IFERROR(INDEX('AEO26 Table 21'!$E$6:$AD$92,MATCH($B6,'AEO26 Table 21'!$B$6:$B$92,0),MATCH($E$3,'AEO26 Table 21'!$E$5:$AD$5,0)),"") -> 17.311983 | F6: =E6/$E$15 -> 0.13854098 | G6: =E6/$G$15 -> 0.15713894 | I6: =About!$B$21 -> Alternative electricity and transportation: Table 21
A7: Electric Other | B7: Residential Equipment: Equipment Stock: Main Space Heaters: Electric Other: Alternative Electricity and Transportation | D7: millions | E7: =IFERROR(INDEX('AEO26 Table 21'!$E$6:$AD$92,MATCH($B7,'AEO26 Table 21'!$B$6:$B$92,0),MATCH($E$3,'AEO26 Table 21'!$E$5:$AD$5,0)),"") -> 27.181431 | F7: =E7/$E$15 -> 0.21752229 | G7: =E7/$G$15 -> 0.24672282 | I7: =About!$B$21 -> Alternative electricity and transportation: Table 21
A8: Natural Gas Heat Pumps | B8: Residential Equipment: Equipment Stock: Main Space Heaters: Natural Gas Heat Pumps: Alternative Electricity and Transportation | D8: millions | E8: =IFERROR(INDEX('AEO26 Table 21'!$E$6:$AD$92,MATCH($B8,'AEO26 Table 21'!$B$6:$B$92,0),MATCH($E$3,'AEO26 Table 21'!$E$5:$AD$5,0)),"") -> 1.353481 | F8: =E8/$E$15 -> 0.010831376 | I8: =About!$B$21 -> Alternative electricity and transportation: Table 21
A9: Natural Gas Other | B9: Residential Equipment: Equipment Stock: Main Space Heaters: Natural Gas Other: Alternative Electricity and Transportation | D9: millions | E9: =IFERROR(INDEX('AEO26 Table 21'!$E$6:$AD$92,MATCH($B9,'AEO26 Table 21'!$B$6:$B$92,0),MATCH($E$3,'AEO26 Table 21'!$E$5:$AD$5,0)),"") -> 65.676498 | F9: =E9/$E$15 -> 0.52558316 | G9: =E9/$G$15 -> 0.59613825 | I9: =About!$B$21 -> Alternative electricity and transportation: Table 21
A10: Distillate Fuel Oil | B10: Residential Equipment: Equipment Stock: Main Space Heaters: Distillate Fuel Oil: Alternative Electricity and Transportation | D10: millions | E10: =IFERROR(INDEX('AEO26 Table 21'!$E$6:$AD$92,MATCH($B10,'AEO26 Table 21'!$B$6:$B$92,0),MATCH($E$3,'AEO26 Table 21'!$E$5:$AD$5,0)),"") -> 4.673755 | F10: =E10/$E$15 -> 0.037402221 | I10: =About!$B$21 -> Alternative electricity and transportation: Table 21
A11: Propane | B11: Residential Equipment: Equipment Stock: Main Space Heaters: Propane: Alternative Electricity and Transportation | D11: millions | E11: =IFERROR(INDEX('AEO26 Table 21'!$E$6:$AD$92,MATCH($B11,'AEO26 Table 21'!$B$6:$B$92,0),MATCH($E$3,'AEO26 Table 21'!$E$5:$AD$5,0)),"") -> 5.239571 | F11: =E11/$E$15 -> 0.041930224 | I11: =About!$B$21 -> Alternative electricity and transportation: Table 21
A12: Kerosene | B12: Residential Equipment: Equipment Stock: Main Space Heaters: Kerosene: Alternative Electricity and Transportation | D12: millions | E12: =IFERROR(INDEX('AEO26 Table 21'!$E$6:$AD$92,MATCH($B12,'AEO26 Table 21'!$B$6:$B$92,0),MATCH($E$3,'AEO26 Table 21'!$E$5:$AD$5,0)),"") | F12: =E12/$E$15 -> #VALUE! | I12: =About!$B$21 -> Alternative electricity and transportation: Table 21
A13: Wood Stoves | B13: Residential Equipment: Equipment Stock: Main Space Heaters: Wood Stoves: Alternative Electricity and Transportation | D13: millions | E13: =IFERROR(INDEX('AEO26 Table 21'!$E$6:$AD$92,MATCH($B13,'AEO26 Table 21'!$B$6:$B$92,0),MATCH($E$3,'AEO26 Table 21'!$E$5:$AD$5,0)),"") -> 2.209099 | F13: =E13/$E$15 -> 0.01767855 | I13: =About!$B$21 -> Alternative electricity and transportation: Table 21
A14: Geothermal Heat Pumps | B14: Residential Equipment: Equipment Stock: Main Space Heaters: Geothermal Heat Pumps: Alternative Electricity and Transportation | D14: millions | E14: =IFERROR(INDEX('AEO26 Table 21'!$E$6:$AD$92,MATCH($B14,'AEO26 Table 21'!$B$6:$B$92,0),MATCH($E$3,'AEO26 Table 21'!$E$5:$AD$5,0)),"") -> 1.313477 | F14: =E14/$E$15 -> 0.010511239 | I14: =About!$B$21 -> Alternative electricity and transportation: Table 21
A15: Total | B15: Residential Equipment: Equipment Stock: Main Space Heaters: Total: Alternative Electricity and Transportation | D15: millions | E15: =IFERROR(INDEX('AEO26 Table 21'!$E$6:$AD$92,MATCH($B15,'AEO26 Table 21'!$B$6:$B$92,0),MATCH($E$3,'AEO26 Table 21'!$E$5:$AD$5,0)),"") -> 124.95929 | F15: =E15/$E$15 -> 1 | G15: =SUM(E6:E7,E9) -> 110.16991 | I15: =About!$B$21 -> Alternative electricity and transportation: Table 21
A16: Space Cooling (million units) | E16: =IFERROR(INDEX('AEO26 Table 21'!$E$6:$AD$92,MATCH($B16,'AEO26 Table 21'!$B$6:$B$92,0),MATCH($E$3,'AEO26 Table 21'!$E$5:$AD$5,0)),"") | I16: =About!$B$21 -> Alternative electricity and transportation: Table 21
A17: Electric Heat Pumps | B17: Residential Equipment: Equipment Stock: Space Cooling: Electric Heat Pumps: Alternative Electricity and Transportation | D17: millions | E17: =IFERROR(INDEX('AEO26 Table 21'!$E$6:$AD$92,MATCH($B17,'AEO26 Table 21'!$B$6:$B$92,0),MATCH($E$3,'AEO26 Table 21'!$E$5:$AD$5,0)),"") -> 17.311981 | F17: =E17/$E$22 -> 0.12034362 | G17: =E17/$G$22 -> 0.12261684 | I17: =About!$B$21 -> Alternative electricity and transportation: Table 21
A18: Natural Gas Heat Pumps | B18: Residential Equipment: Equipment Stock: Space Cooling: Natural Gas Heat Pumps: Alternative Electricity and Transportation | D18: millions | E18: =IFERROR(INDEX('AEO26 Table 21'!$E$6:$AD$92,MATCH($B18,'AEO26 Table 21'!$B$6:$B$92,0),MATCH($E$3,'AEO26 Table 21'!$E$5:$AD$5,0)),"") -> 1.353481 | F18: =E18/$E$22 -> 0.0094086748 | I18: =About!$B$21 -> Alternative electricity and transportation: Table 21
A19: Geothermal Heat Pumps | B19: Residential Equipment: Equipment Stock: Space Cooling: Geothermal Heat Pumps: Alternative Electricity and Transportation | D19: millions | E19: =IFERROR(INDEX('AEO26 Table 21'!$E$6:$AD$92,MATCH($B19,'AEO26 Table 21'!$B$6:$B$92,0),MATCH($E$3,'AEO26 Table 21'!$E$5:$AD$5,0)),"") -> 1.313476 | F19: =E19/$E$22 -> 0.0091305815 | I19: =About!$B$21 -> Alternative electricity and transportation: Table 21
A20: Central Air Conditioners | B20: Residential Equipment: Equipment Stock: Space Cooling: Central Air Conditioners: Alternative Electricity and Transportation | D20: millions | E20: =IFERROR(INDEX('AEO26 Table 21'!$E$6:$AD$92,MATCH($B20,'AEO26 Table 21'!$B$6:$B$92,0),MATCH($E$3,'AEO26 Table 21'!$E$5:$AD$5,0)),"") -> 80.644836 | F20: =E20/$E$22 -> 0.5605997 | G20: =E20/$G$22 -> 0.57118911 | I20: =About!$B$21 -> Alternative electricity and transportation: Table 21
A21: Room Air Conditioners | B21: Residential Equipment: Equipment Stock: Space Cooling: Room Air Conditioners: Alternative Electricity and Transportation | D21: millions | E21: =IFERROR(INDEX('AEO26 Table 21'!$E$6:$AD$92,MATCH($B21,'AEO26 Table 21'!$B$6:$B$92,0),MATCH($E$3,'AEO26 Table 21'!$E$5:$AD$5,0)),"") -> 43.230812 | F21: =E21/$E$22 -> 0.30051744 | G21: =E21/$G$22 -> 0.30619405 | I21: =About!$B$21 -> Alternative electricity and transportation: Table 21
A22: Total | B22: Residential Equipment: Equipment Stock: Space Cooling: Total: Alternative Electricity and Transportation | D22: millions | E22: =IFERROR(INDEX('AEO26 Table 21'!$E$6:$AD$92,MATCH($B22,'AEO26 Table 21'!$B$6:$B$92,0),MATCH($E$3,'AEO26 Table 21'!$E$5:$AD$5,0)),"") -> 143.85458 | F22: =E22/$E$22 -> 1 | G22: =SUM(E17,E20:E21) -> 141.18763 | I22: =About!$B$21 -> Alternative electricity and transportation: Table 21
A23: Water Heaters (million units) | E23: =IFERROR(INDEX('AEO26 Table 21'!$E$6:$AD$92,MATCH($B23,'AEO26 Table 21'!$B$6:$B$92,0),MATCH($E$3,'AEO26 Table 21'!$E$5:$AD$5,0)),"") | I23: =About!$B$21 -> Alternative electricity and transportation: Table 21
A24: Electric | B24: Residential Equipment: Equipment Stock: Water Heaters: Electric: Alternative Electricity and Transportation | D24: millions | E24: =IFERROR(INDEX('AEO26 Table 21'!$E$6:$AD$92,MATCH($B24,'AEO26 Table 21'!$B$6:$B$92,0),MATCH($E$3,'AEO26 Table 21'!$E$5:$AD$5,0)),"") -> 62.475159 | F24: =E24/$E$29 -> 0.45872439 | G24: =E24/$G$29 -> 0.48965433 | I24: =About!$B$21 -> Alternative electricity and transportation: Table 21
A25: Natural Gas | B25: Residential Equipment: Equipment Stock: Water Heaters: Natural Gas: Alternative Electricity and Transportation | D25: millions | E25: =IFERROR(INDEX('AEO26 Table 21'!$E$6:$AD$92,MATCH($B25,'AEO26 Table 21'!$B$6:$B$92,0),MATCH($E$3,'AEO26 Table 21'!$E$5:$AD$5,0)),"") -> 65.115173 | F25: =E25/$E$29 -> 0.47810871 | G25: =E25/$G$29 -> 0.51034567 | I25: =About!$B$21 -> Alternative electricity and transportation: Table 21
A26: Distillate Fuel Oil | B26: Residential Equipment: Equipment Stock: Water Heaters: Distillate Fuel Oil: Alternative Electricity and Transportation | D26: millions | E26: =IFERROR(INDEX('AEO26 Table 21'!$E$6:$AD$92,MATCH($B26,'AEO26 Table 21'!$B$6:$B$92,0),MATCH($E$3,'AEO26 Table 21'!$E$5:$AD$5,0)),"") -> 2.224999 | F26: =E26/$E$29 -> 0.016337074 | I26: =About!$B$21 -> Alternative electricity and transportation: Table 21
A27: Propane | B27: Residential Equipment: Equipment Stock: Water Heaters: Propane: Alternative Electricity and Transportation | D27: millions | E27: =IFERROR(INDEX('AEO26 Table 21'!$E$6:$AD$92,MATCH($B27,'AEO26 Table 21'!$B$6:$B$92,0),MATCH($E$3,'AEO26 Table 21'!$E$5:$AD$5,0)),"") -> 4.199949 | F27: =E27/$E$29 -> 0.030838161 | I27: =About!$B$21 -> Alternative electricity and transportation: Table 21
A28: Solar Thermal | B28: Residential Equipment: Equipment Stock: Water Heaters: Solar Thermal: Alternative Electricity and Transportation | D28: millions | E28: =IFERROR(INDEX('AEO26 Table 21'!$E$6:$AD$92,MATCH($B28,'AEO26 Table 21'!$B$6:$B$92,0),MATCH($E$3,'AEO26 Table 21'!$E$5:$AD$5,0)),"") -> 2.17795 | F28: =E28/$E$29 -> 0.015991616 | I28: =About!$B$21 -> Alternative electricity and transportation: Table 21
A29: Total | B29: Residential Equipment: Equipment Stock: Water Heaters: Total: Alternative Electricity and Transportation | D29: millions | E29: =IFERROR(INDEX('AEO26 Table 21'!$E$6:$AD$92,MATCH($B29,'AEO26 Table 21'!$B$6:$B$92,0),MATCH($E$3,'AEO26 Table 21'!$E$5:$AD$5,0)),"") -> 136.19324 | F29: =E29/$E$29 -> 1 | G29: =SUM(E24:E25) -> 127.59033 | I29: =About!$B$21 -> Alternative electricity and transportation: Table 21
A30: Cooking Equipment (million units) | E30: =IFERROR(INDEX('AEO26 Table 21'!$E$6:$AD$92,MATCH($B30,'AEO26 Table 21'!$B$6:$B$92,0),MATCH($E$3,'AEO26 Table 21'!$E$5:$AD$5,0)),"") | I30: =About!$B$21 -> Alternative electricity and transportation: Table 21
A31: Electric | B31: Residential Equipment: Equipment Stock: Cooking Equipment: Electric: Alternative Electricity and Transportation | D31: millions | E31: =IFERROR(INDEX('AEO26 Table 21'!$E$6:$AD$92,MATCH($B31,'AEO26 Table 21'!$B$6:$B$92,0),MATCH($E$3,'AEO26 Table 21'!$E$5:$AD$5,0)),"") -> 101.44487 | F31: =E31/$E$34 -> 0.62683938 | I31: =About!$B$21 -> Alternative electricity and transportation: Table 21
A32: Natural Gas | B32: Residential Equipment: Equipment Stock: Cooking Equipment: Natural Gas: Alternative Electricity and Transportation | D32: millions | E32: =IFERROR(INDEX('AEO26 Table 21'!$E$6:$AD$92,MATCH($B32,'AEO26 Table 21'!$B$6:$B$92,0),MATCH($E$3,'AEO26 Table 21'!$E$5:$AD$5,0)),"") -> 54.077557 | F32: =E32/$E$34 -> 0.33415137 | G32: 1 | I32: =About!$B$21 -> Alternative electricity and transportation: Table 21
A33: Propane | B33: Residential Equipment: Equipment Stock: Cooking Equipment: Propane: Alternative Electricity and Transportation | D33: millions | E33: =IFERROR(INDEX('AEO26 Table 21'!$E$6:$AD$92,MATCH($B33,'AEO26 Table 21'!$B$6:$B$92,0),MATCH($E$3,'AEO26 Table 21'!$E$5:$AD$5,0)),"") -> 6.313086 | F33: =E33/$E$34 -> 0.039009276 | I33: =About!$B$21 -> Alternative electricity and transportation: Table 21
A34: Total | B34: Residential Equipment: Equipment Stock: Cooking Equipment: Total: Alternative Electricity and Transportation | D34: millions | E34: =IFERROR(INDEX('AEO26 Table 21'!$E$6:$AD$92,MATCH($B34,'AEO26 Table 21'!$B$6:$B$92,0),MATCH($E$3,'AEO26 Table 21'!$E$5:$AD$5,0)),"") -> 161.83551 | F34: =E34/$E$34 -> 1 | I34: =About!$B$21 -> Alternative electricity and transportation: Table 21
A35: Clothes Dryers (million units) | E35: =IFERROR(INDEX('AEO26 Table 21'!$E$6:$AD$92,MATCH($B35,'AEO26 Table 21'!$B$6:$B$92,0),MATCH($E$3,'AEO26 Table 21'!$E$5:$AD$5,0)),"") | I35: =About!$B$21 -> Alternative electricity and transportation: Table 21
A36: Electric | B36: Residential Equipment: Equipment Stock: Clothes Dryers: Electric: Alternative Electricity and Transportation | D36: millions | E36: =IFERROR(INDEX('AEO26 Table 21'!$E$6:$AD$92,MATCH($B36,'AEO26 Table 21'!$B$6:$B$92,0),MATCH($E$3,'AEO26 Table 21'!$E$5:$AD$5,0)),"") -> 95.14431 | F36: =E36/$E$38 -> 0.82299211 | G36: =F36 -> 0.82299211 | I36: =About!$B$21 -> Alternative electricity and transportation: Table 21
A37: Natural Gas | B37: Residential Equipment: Equipment Stock: Clothes Dryers: Natural Gas: Alternative Electricity and Transportation | D37: millions | E37: =IFERROR(INDEX('AEO26 Table 21'!$E$6:$AD$92,MATCH($B37,'AEO26 Table 21'!$B$6:$B$92,0),MATCH($E$3,'AEO26 Table 21'!$E$5:$AD$5,0)),"") -> 20.463491 | F37: =E37/$E$38 -> 0.17700787 | G37: =F37 -> 0.17700787 | I37: =About!$B$21 -> Alternative electricity and transportation: Table 21
A38: Total | B38: Residential Equipment: Equipment Stock: Clothes Dryers: Total: Alternative Electricity and Transportation | D38: millions | E38: =IFERROR(INDEX('AEO26 Table 21'!$E$6:$AD$92,MATCH($B38,'AEO26 Table 21'!$B$6:$B$92,0),MATCH($E$3,'AEO26 Table 21'!$E$5:$AD$5,0)),"") -> 115.6078 | F38: =E38/$E$38 -> 1 | G38: =SUM(E36:E37) -> 115.6078 | I38: =About!$B$21 -> Alternative electricity and transportation: Table 21
A39: Other Appliances (million units) | E39: =IFERROR(INDEX('AEO26 Table 21'!$E$6:$AD$92,MATCH($B39,'AEO26 Table 21'!$B$6:$B$92,0),MATCH($E$3,'AEO26 Table 21'!$E$5:$AD$5,0)),"") | I39: =About!$B$21 -> Alternative electricity and transportation: Table 21
A40: Refrigerators | B40: Residential Equipment: Equipment Stock: Other Appliances: Refrigerators: Alternative Electricity and Transportation | D40: millions | E40: =IFERROR(INDEX('AEO26 Table 21'!$E$6:$AD$92,MATCH($B40,'AEO26 Table 21'!$B$6:$B$92,0),MATCH($E$3,'AEO26 Table 21'!$E$5:$AD$5,0)),"") -> 187.50732 | I40: =About!$B$21 -> Alternative electricity and transportation: Table 21
A41: Freezers | B41: Residential Equipment: Equipment Stock: Other Appliances: Freezers: Alternative Electricity and Transportation | D41: millions | E41: =IFERROR(INDEX('AEO26 Table 21'!$E$6:$AD$92,MATCH($B41,'AEO26 Table 21'!$B$6:$B$92,0),MATCH($E$3,'AEO26 Table 21'!$E$5:$AD$5,0)),"") -> 48.868607 | I41: =About!$B$21 -> Alternative electricity and transportation: Table 21

Sheet Cost Breakdowns
A1: Sector | C1: Percent of cost | F1: ISIC Mapping | G1: Notes
C2: Urban-Residential | D2: Rural-Residential | E2: Commercial
A3: Heating | B3: Equipment | C3: ='Cost Summary New'!E$4*'Margin Calcs'!$L$5 -> 0.25957515 | D3: ='Cost Summary New'!E$4*'Margin Calcs'!$L$5 -> 0.25957515 | E3: ='Cost Summary New'!E45*'Margin Calcs'!$L$6 -> 0.48014297 | F3: ='ISIC Code Mapping'!B2 -> ISIC 28 | H3: Equipment rows: the equipment part of the installed cost times the manufacturer's, markup or freight share on the Margin Calcs tab.
A4: Heating | B4: Equipment markup (wholesale and retail) | C4: ='Cost Summary New'!E$4*'Margin Calcs'!$N$5 -> 0.28309633 | D4: ='Cost Summary New'!E$4*'Margin Calcs'!$N$5 -> 0.28309633 | E4: ='Cost Summary New'!E45*'Margin Calcs'!$N$6 -> 0.21006812 | F4: ="ISIC 45T47" -> ISIC 45T47
A5: Heating | B5: Equipment freight | C5: ='Cost Summary New'!E$4*'Margin Calcs'!$M$5 -> 0.0076097929 | D5: ='Cost Summary New'!E$4*'Margin Calcs'!$M$5 -> 0.0076097929 | E5: ='Cost Summary New'!E45*'Margin Calcs'!$M$6 -> 0.013776419 | F5: ="ISIC 49" -> ISIC 49
A6: Heating | B6: Labor | C6: ='Cost Summary New'!F$4 -> 0.44971873 | D6: ='Cost Summary New'!F$4 -> 0.44971873 | E6: ='Cost Summary New'!F45 -> 0.2960125 | F6: ='ISIC Code Mapping'!B3 -> ISIC 41T43
A7: Cooling | B7: Equipment | C7: ='Cost Summary New'!$E$14*'Margin Calcs'!$L$7 -> 0.34719458 | D7: ='Cost Summary New'!$E$14*'Margin Calcs'!$L$7 -> 0.34719458 | E7: ='Cost Summary New'!E95*'Margin Calcs'!$L$8 -> 0.39823638 | F7: ='ISIC Code Mapping'!C2 -> ISIC 28
A8: Cooling | B8: Equipment markup (wholesale and retail) | C8: ='Cost Summary New'!$E$14*'Margin Calcs'!$N$7 -> 0.37896261 | D8: ='Cost Summary New'!$E$14*'Margin Calcs'!$N$7 -> 0.37896261 | E8: ='Cost Summary New'!E95*'Margin Calcs'!$N$8 -> 0.17019402 | F8: ="ISIC 45T47" -> ISIC 45T47
A9: Cooling | B9: Equipment freight | C9: ='Cost Summary New'!$E$14*'Margin Calcs'!$M$7 -> 0.010088498 | D9: ='Cost Summary New'!$E$14*'Margin Calcs'!$M$7 -> 0.010088498 | E9: ='Cost Summary New'!E95*'Margin Calcs'!$M$8 -> 0.011399713 | F9: ="ISIC 49" -> ISIC 49
A10: Cooling | B10: Labor | C10: ='Cost Summary New'!$F$14 -> 0.26375431 | D10: ='Cost Summary New'!$F$14 -> 0.26375431 | E10: ='Cost Summary New'!F95 -> 0.42016989 | F10: ='ISIC Code Mapping'!C3 -> ISIC 41T43
A11: Lighting | B11: Equipment | C11: ='Cost Summary New'!$E$39*'Margin Calcs'!$L$9 -> 0.39998511 | D11: ='Cost Summary New'!$E$39*'Margin Calcs'!$L$9 -> 0.39998511 | E11: ='Cost Summary New'!E100*'Margin Calcs'!$L$10 -> 0.28238604 | F11: ='ISIC Code Mapping'!E2 -> ISIC 27
A12: Lighting | B12: Equipment markup (wholesale and retail) | C12: ='Cost Summary New'!$E$39*'Margin Calcs'!$N$9 -> 0.55505099 | D12: ='Cost Summary New'!$E$39*'Margin Calcs'!$N$9 -> 0.55505099 | E12: ='Cost Summary New'!E100*'Margin Calcs'!$N$10 -> 0.091251813 | F12: ="ISIC 45T47" -> ISIC 45T47
A13: Lighting | B13: Equipment freight | C13: ='Cost Summary New'!$E$39*'Margin Calcs'!$M$9 -> 0.044963895 | D13: ='Cost Summary New'!$E$39*'Margin Calcs'!$M$9 -> 0.044963895 | E13: ='Cost Summary New'!E100*'Margin Calcs'!$M$10 -> 0.034031096 | F13: ="ISIC 49" -> ISIC 49
A14: Lighting | B14: Labor | C14: ='Cost Summary New'!$F$39 -> 0 | D14: ='Cost Summary New'!$F$39 -> 0 | E14: ='Cost Summary New'!F100 -> 0.59233105 | F14: ='ISIC Code Mapping'!E3 -> ISIC 41T43
A15: Appliances | B15: Equipment | C15: ='Cost Summary New'!$E$41*'Margin Calcs'!$L$11 -> 0.41594355 | D15: ='Cost Summary New'!$E$41*'Margin Calcs'!$L$11 -> 0.41594355 | E15: ='Cost Summary New'!E88*'Margin Calcs'!$L$12 -> 0.51313159 | F15: ='ISIC Code Mapping'!F2 -> ISIC 27
A16: Appliances | B16: Equipment markup (wholesale and retail) | C16: ='Cost Summary New'!$E$41*'Margin Calcs'!$N$11 -> 0.33246167 | D16: ='Cost Summary New'!$E$41*'Margin Calcs'!$N$11 -> 0.33246167 | E16: ='Cost Summary New'!E88*'Margin Calcs'!$N$12 -> 0.22708138 | F16: ="ISIC 45T47" -> ISIC 45T47
A17: Appliances | B17: Equipment freight | C17: ='Cost Summary New'!$E$41*'Margin Calcs'!$M$11 -> 0.0059461992 | D17: ='Cost Summary New'!$E$41*'Margin Calcs'!$M$11 -> 0.0059461992 | E17: ='Cost Summary New'!E88*'Margin Calcs'!$M$12 -> 0.0141859 | F17: ="ISIC 49" -> ISIC 49
A18: Appliances | B18: Labor | C18: ='Cost Summary New'!$F$41 -> 0.24564858 | D18: ='Cost Summary New'!$F$41 -> 0.24564858 | E18: ='Cost Summary New'!F88 -> 0.24560113 | F18: ='ISIC Code Mapping'!F3 -> ISIC 41T43
A19: Other | B19: Equipment | C19: ='Cost Summary New'!$E$41*'Margin Calcs'!$L$13 -> 0.39439857 | D19: ='Cost Summary New'!$E$41*'Margin Calcs'!$L$13 -> 0.39439857 | E19: ='Cost Summary New'!E88*'Margin Calcs'!$L$14 -> 0.51142569 | F19: ='ISIC Code Mapping'!G2 -> ISIC 27 | G19: Other uses the appliances cost breakdown
A20: Other | B20: Equipment markup (wholesale and retail) | C20: ='Cost Summary New'!$E$41*'Margin Calcs'!$N$13 -> 0.34557881 | D20: ='Cost Summary New'!$E$41*'Margin Calcs'!$N$13 -> 0.34557881 | E20: ='Cost Summary New'!E88*'Margin Calcs'!$N$14 -> 0.23490525 | F20: ="ISIC 45T47" -> ISIC 45T47
A21: Other | B21: Equipment freight | C21: ='Cost Summary New'!$E$41*'Margin Calcs'!$M$13 -> 0.014374046 | D21: ='Cost Summary New'!$E$41*'Margin Calcs'!$M$13 -> 0.014374046 | E21: ='Cost Summary New'!E88*'Margin Calcs'!$M$14 -> 0.0080679255 | F21: ="ISIC 49" -> ISIC 49
A22: Other | B22: Labor | C22: ='Cost Summary New'!$F$41 -> 0.24564858 | D22: ='Cost Summary New'!$F$41 -> 0.24564858 | E22: ='Cost Summary New'!F88 -> 0.24560113 | F22: ='ISIC Code Mapping'!G3 -> ISIC 41T43

Sheet TableB39
B1: Release date: April 2015 Revised date: May 2016
B2: Table B39. Heating equipment, floorspace, 2012
C3: Total floorspace (million square feet)
C4: All buildings | D4: Buildings with space heating | E4: Heating equipment (more than one may apply)
E5: Heat pumps | F5: Furnaces | G5: Indiv- idual space heaters | H5: District heat | I5: Boilers | J5: Pack- aged heating units | K5: Other
B6: All buildings | C6: 87093 | D6: 80078 | E6: 11846 | F6: 8654 | G6: 20766 | H6: 5925 | I6: 22443 | J6: 49188 | K6: 1574
B7: Building floorspace (square feet)
B8: 1,001 to 5,000 | C8: 8041 | D8: 6699 | E8: 868 | F8: 1091 | G8: 1747 | H8: Q | I8: 400 | J8: 3809 | K8: Q
B9: 5,001 to 10,000 | C9: 8900 | D9: 7590 | E9: 1038 | F9: 1416 | G9: 2025 | H9: Q | I9: 734 | J9: 4622 | K9: Q
B10: 10,001 to 25,000 | C10: 14105 | D10: 12744 | E10: 1477 | F10: 2233 | G10: 3115 | H10: Q | I10: 2008 | J10: 8246 | K10: Q
B11: 25,001 to 50,000 | C11: 11917 | D11: 10911 | E11: 1642 | F11: 1439 | G11: 3021 | H11: 213 | I11: 2707 | J11: 7237 | K11: Q
B12: 50,001 to 100,000 | C12: 13918 | D12: 13114 | E12: 2664 | F12: 1042 | G12: 2763 | H12: 704 | I12: 4938 | J12: 8489 | K12: 541
B13: 100,001 to 200,000 | C13: 12415 | D13: 11941 | E13: 1549 | F13: 683 | G13: 2915 | H13: 1313 | I13: 4258 | J13: 7569 | K13: Q
B14: 200,001 to 500,000 | C14: 10724 | D14: 10348 | E14: 1527 | F14: 466 | G14: 2970 | H14: 1553 | I14: 4970 | J14: 5991 | K14: Q
B15: Over 500,000 | C15: 7074 | D15: 6730 | E15: 1080 | F15: 284 | G15: 2211 | H15: 1974 | I15: 2430 | J15: 3225 | K15: Q
B16: Principal building activity
B17: Education | C17: 12239 | D17: 12099 | E17: 2209 | F17: 564 | G17: 1750 | H17: 1155 | I17: 6637 | J17: 6107 | K17: Q
B18: Food sales | C18: 1252 | D18: 1196 | E18: Q | F18: Q | G18: 336 | H18: N | I18: Q | J18: 944 | K18: Q
B19: Food service | C19: 1819 | D19: 1762 | E19: 146 | F19: 266 | G19: 256 | H19: Q | I19: 145 | J19: 1296 | K19: Q
B20: Health care | C20: 4155 | D20: 4109 | E20: 739 | F20: 258 | G20: 967 | H20: 671 | I20: 2285 | J20: 2085 | K20: Q
B21: Inpatient | C21: 2374 | D21: 2354 | E21: 506 | F21: 124 | G21: 501 | H21: 563 | I21: 1698 | J21: 1073 | K21: Q
B22: Outpatient | C22: 1781 | D22: 1754 | E22: 233 | F22: 133 | G22: 466 | H22: Q | I22: 588 | J22: 1012 | K22: N
B23: Lodging | C23: 5826 | D23: 5696 | E23: 1259 | F23: 638 | G23: 2168 | H23: 621 | I23: 2105 | J23: 2561 | K23: Q
B24: Mercantile | C24: 11330 | D24: 10794 | E24: 1419 | F24: 1423 | G24: 2568 | H24: Q | I24: 1138 | J24: 9434 | K24: 872
B25: Retail (other than mall) | C25: 5439 | D25: 5088 | E25: 441 | F25: 590 | G25: 1007 | H25: Q | I25: 312 | J25: 3964 | K25: Q
B26: Enclosed and strip malls | C26: 5890 | D26: 5706 | E26: 978 | F26: 832 | G26: 1561 | H26: Q | I26: 826 | J26: 5470 | K26: 860
B27: Office | C27: 15952 | D27: 15753 | E27: 2667 | F27: 1691 | G27: 3727 | H27: 1794 | I27: 4650 | J27: 8407 | K27: Q
B28: Public assembly | C28: 5559 | D28: 5323 | E28: 727 | F28: 582 | G28: 1560 | H28: 888 | I28: 1621 | J28: 3016 | K28: Q
B29: Public order and safety | C29: 1440 | D29: 1391 | E29: Q | F29: Q | G29: 253 | H29: Q | I29: 466 | J29: 601 | K29: Q
B30: Religious worship | C30: 4557 | D30: 4511 | E30: 581 | F30: 927 | G30: 859 | H30: N | I30: 1359 | J30: 2801 | K30: Q
B31: Service | C31: 4630 | D31: 4157 | E31: 356 | F31: 497 | G31: 1919 | H31: Q | I31: 433 | J31: 2498 | K31: Q
B32: Warehouse and storage | C32: 13077 | D32: 9987 | E32: 1138 | F32: 1294 | G32: 3480 | H32: Q | I32: 841 | J32: 7297 | K32: Q
B33: Other | C33: 2002 | D33: 1886 | E33: Q | F33: Q | G33: 737 | H33: Q | I33: 408 | J33: 1257 | K33: Q
B34: Vacant | C34: 3256 | D34: 1415 | E34: Q | F34: Q | G34: Q | H34: Q | I34: 296 | J34: 886 | K34: Q
B35: Year constructed
B36: Before 1920 | C36: 3983 | D36: 3583 | E36: 371 | F36: 524 | G36: 1442 | H36: 523 | I36: 1221 | J36: 1380 | K36: Q
B37: 1920 to 1945 | C37: 6025 | D37: 5527 | E37: 744 | F37: 393 | G37: 1717 | H37: 888 | I37: 2016 | J37: 2589 | K37: Q
B38: 1946 to 1959 | C38: 7381 | D38: 6895 | E38: 907 | F38: 685 | G38: 2277 | H38: 446 | I38: 2659 | J38: 3715 | K38: Q
B39: 1960 to 1969 | C39: 10362 | D39: 9730 | E39: 1295 | F39: 1168 | G39: 2586 | H39: 1002 | I39: 3506 | J39: 5670 | K39: Q
B40: 1970 to 1979 | C40: 10846 | D40: 10045 | E40: 1198 | F40: 1345 | G40: 2923 | H40: 930 | I40: 2763 | J40: 6156 | K40: Q
B41: 1980 to 1989 | C41: 15230 | D41: 13723 | E41: 2386 | F41: 1763 | G41: 3424 | H41: 446 | I41: 2973 | J41: 9037 | K41: Q
B42: 1990 to 1999 | C42: 13803 | D42: 12389 | E42: 2136 | F42: 1266 | G42: 2996 | H42: 642 | I42: 2970 | J42: 8544 | K42: 397
B43: 2000 to 2003 | C43: 7215 | D43: 6707 | E43: 808 | F43: 551 | G43: 1292 | H43: Q | I43: 1636 | J43: 4281 | K43: Q
B44: 2004 to 2007 | C44: 6524 | D44: 5972 | E44: 1174 | F44: 516 | G44: 1160 | H44: Q | I44: 1395 | J44: 4076 | K44: Q
B45: 2008 to 2012 | C45: 5723 | D45: 5505 | E45: 826 | F45: 442 | G45: 948 | H45: Q | I45: 1303 | J45: 3741 | K45: Q
B46: Census region and division
B47: Northeast | C47: 15534 | D47: 15053 | E47: 1397 | F47: 1244 | G47: 4918 | H47: 1981 | I47: 6447 | J47: 7186 | K47: Q
B48: New England | C48: 4302 | D48: 4090 | E48: 400 | F48: 323 | G48: 1529 | H48: Q | I48: 1823 | J48: 1769 | K48: Q
B49: Middle Atlantic | C49: 11232 | D49: 10963 | E49: 998 | F49: 922 | G49: 3389 | H49: 1628 | I49: 4624 | J49: 5417 | K49: Q
B50: Midwest | C50: 18919 | D50: 18055 | E50: 1068 | F50: 2511 | G50: 5735 | H50: 906 | I50: 6666 | J50: 10894 | K50: 370
B51: East North Central | C51: 12742 | D51: 12240 | E51: 632 | F51: 1756 | G51: 3668 | H51: 574 | I51: 5083 | J51: 7347 | K51: Q
B52: West North Central | C52: 6178 | D52: 5815 | E52: 436 | F52: 755 | G52: 2066 | H52: 332 | I52: 1583 | J52: 3547 | K52: Q
B53: South | C53: 34279 | D53: 30499 | E53: 6927 | F53: 3363 | G53: 6519 | H53: 2171 | I53: 5784 | J53: 20049 | K53: 550
B54: South Atlantic | C54: 17981 | D54: 15883 | E54: 4909 | F54: 1234 | G54: 3328 | H54: 1148 | I54: 3247 | J54: 10168 | K54: Q
B55: East South Central | C55: 4904 | D55: 4692 | E55: 844 | F55: 530 | G55: 1295 | H55: Q | I55: 1077 | J55: 3136 | K55: Q
B56: West South Central | C56: 11394 | D56: 9923 | E56: 1174 | F56: 1599 | G56: 1896 | H56: 637 | I56: 1460 | J56: 6745 | K56: Q
B57: West | C57: 18360 | D57: 16471 | E57: 2453 | F57: 1536 | G57: 3594 | H57: 867 | I57: 3545 | J57: 11059 | K57: 339
B58: Mountain | C58: 4981 | D58: 4704 | E58: 498 | F58: 554 | G58: 1197 | H58: 482 | I58: 1150 | J58: 2967 | K58: Q
B59: Pacific | C59: 13379 | D59: 11767 | E59: 1955 | F59: 983 | G59: 2397 | H59: 385 | I59: 2395 | J59: 8092 | K59: 242
B60: Climate region1
B61: Very cold/Cold | C61: 31898 | D61: 30469 | E61: 2150 | F61: 3558 | G61: 10128 | H61: 1926 | I61: 11556 | J61: 17640 | K61: 824
B62: Mixed-humid | C62: 27873 | D62: 26716 | E62: 6182 | F62: 3009 | G62: 6697 | H62: 3002 | I62: 7029 | J62: 15485 | K62: 487
B63: Mixed-dry/Hot-dry | C63: 12037 | D63: 10484 | E63: 1669 | F63: 995 | G63: 1703 | H63: Q | I63: 1777 | J63: 7351 | K63: Q
B64: Hot-humid | C64: 12831 | D64: 10090 | E64: 1387 | F64: 937 | G64: 1607 | H64: 362 | I64: 1499 | J64: 7217 | K64: Q
B65: Marine | C65: 2454 | D65: 2319 | E65: 458 | F65: Q | G65: 631 | H65: Q | I65: 581 | J65: 1495 | K65: Q
B66: Number of floors
B67: One | C67: 39809 | D67: 34513 | E67: 4642 | F67: 4356 | G67: 8857 | H67: Q | I67: 4257 | J67: 24999 | K67: 1127
B68: Two | C68: 20206 | D68: 19411 | E68: 2844 | F68: 2518 | G68: 4987 | H68: Q | I68: 5762 | J68: 13422 | K68: 297
B69: Three | C69: 8140 | D69: 7896 | E69: 1229 | F69: 857 | G69: 2150 | H69: 544 | I69: 3667 | J69: 3918 | K69: Q
B70: Four to nine | C70: 13535 | D70: 12992 | E70: 2089 | F70: 826 | G70: 3398 | H70: 2791 | I70: 6521 | J70: 5180 | K70: Q
B71: Ten or more | C71: 5404 | D71: 5265 | E71: 1041 | F71: Q | G71: 1374 | H71: 1900 | I71: 2236 | J71: 1669 | K71: Q
B72: Number of workers (main shift)
B73: Fewer than 5 | C73: 17751 | D73: 12931 | E73: 1366 | F73: 1921 | G73: 3710 | H73: Q | I73: 1908 | J73: 6967 | K73: Q
B74: 5 to 9 | C74: 8973 | D74: 8492 | E74: 1230 | F74: 1264 | G74: 2274 | H74: Q | I74: 982 | J74: 5320 | K74: Q
B75: 10 to 19 | C75: 9623 | D75: 8970 | E75: 1234 | F75: 1758 | G75: 2219 | H75: Q | I75: 1219 | J75: 6041 | K75: Q
B76: 20 to 49 | C76: 14514 | D76: 14126 | E76: 2268 | F76: 1678 | G76: 3752 | H76: 623 | I76: 3764 | J76: 9817 | K76: 448
B77: 50 to 99 | C77: 13476 | D77: 13184 | E77: 2409 | F77: 1278 | G77: 3323 | H77: 669 | I77: 4610 | J77: 9055 | K77: Q
B78: 100 to 249 | C78: 10941 | D78: 10805 | E78: 1490 | F78: 387 | G78: 2390 | H78: 1096 | I78: 4938 | J78: 6596 | K78: 422
B79: 250 or more | C79: 11815 | D79: 11570 | E79: 1849 | F79: 367 | G79: 3097 | H79: 3053 | I79: 5021 | J79: 5393 | K79: Q
B80: Weekly operating hours
B81: Fewer than 40 | C81: 8220 | D81: 5763 | E81: 617 | F81: 980 | G81: 1222 | H81: Q | I81: 1180 | J81: 3012 | K81: Q
B82: 40 to 48 | C82: 15828 | D82: 14867 | E82: 2230 | F82: 2020 | G82: 3696 | H82: 403 | I82: 3907 | J82: 8633 | K82: Q
B83: 49 to 60 | C83: 20529 | D83: 19365 | E83: 3183 | F83: 2268 | G83: 4971 | H83: 1099 | I83: 5496 | J83: 11950 | K83: Q
B84: 61 to 84 | C84: 15867 | D84: 15148 | E84: 2427 | F84: 1262 | G84: 3999 | H84: 828 | I84: 3993 | J84: 10640 | K84: 443
B85: 85 to 167 | C85: 9395 | D85: 8711 | E85: 724 | F85: 878 | G85: 2183 | H85: 631 | I85: 2266 | J85: 6372 | K85: 364
B86: Open continuously | C86: 17253 | D86: 16224 | E86: 2666 | F86: 1246 | G86: 4696 | H86: 2792 | I86: 5601 | J86: 8582 | K86: Q
B87: Ownership and occupancy
B88: Nongovernment owned | C88: 67550 | D88: 61341 | E88: 8500 | F88: 7472 | G88: 16206 | H88: 3119 | I88: 13405 | J88: 40336 | K88: 1316
B89: Owner occupied | C89: 30637 | D89: 28745 | E89: 3841 | F89: 3629 | G89: 7363 | H89: 1825 | I89: 6663 | J89: 17635 | K89: 214
B90: Leased to tenant(s) | C90: 26115 | D90: 23766 | E90: 3022 | F90: 2880 | G90: 6507 | H90: 730 | I90: 4091 | J90: 17239 | K90: 1021
B91: Owner occupied and leased | C91: 8873 | D91: 8328 | E91: 1597 | F91: 900 | G91: 2284 | H91: 557 | I91: 2590 | J91: 5102 | K91: Q
B92: Unoccupied | C92: 1925 | D92: 502 | E92: Q | F92: Q | G92: Q | H92: Q | I92: Q | J92: 360 | K92: Q
B93: Government owned | C93: 19543 | D93: 18736 | E93: 3346 | F93: 1182 | G93: 4561 | H93: 2807 | I93: 9038 | J93: 8852 | K93: Q
B94: Federal | C94: 1573 | D94: 1557 | E94: 212 | F94: Q | G94: 558 | H94: 697 | I94: 471 | J94: 495 | K94: Q
B95: State | C95: 5539 | D95: 5411 | E95: 636 | F95: 378 | G95: 1375 | H95: 1526 | I95: 2305 | J95: 2213 | K95: Q
B96: Local | C96: 12431 | D96: 11768 | E96: 2497 | F96: 753 | G96: 2628 | H96: 584 | I96: 6263 | J96: 6144 | K96: Q
B97: Party responsible for operation and maintenance of energy systems
B98: Building owner | C98: 73702 | D98: 67644 | E98: 10210 | F98: 7076 | G98: 17425 | H98: 5737 | I98: 20588 | J98: 39517 | K98: 1008
B99: Business owner or tenant | C99: 11309 | D99: 10534 | E99: 1240 | F99: 1325 | G99: 2895 | H99: Q | I99: 1363 | J99: 8598 | K99: 549
B100: Property management | C100: 1250 | D100: 1073 | E100: Q | F100: Q | G100: 227 | H100: Q | I100: 273 | J100: 652 | K100: Q
...

Sheet TableB44
A1: Release date: April 2015 Revised date: May 2016
A2: Table B44. Lighting equipment, floorspace, 2012
B3: Total floorspace (million square feet)
B4: All buildings | C4: Lit buildings | D4: Lighting equipment (more than one may apply)
D5: Incand- escent | E5: Standard fluor- escent | F5: Compact fluor- escent | G5: High-intensity dis- charge | H5: Halogen | I5: LED
A6: All buildings | B6: 87093 | C6: 83569 | D6: 38406 | E6: 80081 | F6: 53816 | G6: 23396 | H6: 28059 | I6: 22071
A7: Building floorspace (square feet)
A8: 1,001 to 5,000 | B8: 8041 | C8: 7130 | D8: 2453 | E8: 6466 | F8: 2815 | G8: 373 | H8: 944 | I8: 348
A9: 5,001 to 10,000 | B9: 8900 | C9: 8152 | D9: 2917 | E9: 7589 | F9: 3740 | G9: 736 | H9: 1487 | I9: 714
A10: 10,001 to 25,000 | B10: 14105 | C10: 13250 | D10: 4987 | E10: 12533 | F10: 6767 | G10: 2175 | H10: 2903 | I10: 1882
A11: 25,001 to 50,000 | B11: 11917 | C11: 11542 | D11: 4788 | E11: 11063 | F11: 6970 | G11: 2712 | H11: 3556 | I11: 2252
A12: 50,001 to 100,000 | B12: 13918 | C12: 13564 | D12: 6218 | E12: 13217 | F12: 9652 | G12: 3766 | H12: 4989 | I12: 3479
A13: 100,001 to 200,000 | B13: 12415 | C13: 12282 | D13: 6239 | E13: 11745 | F13: 9078 | G13: 4244 | H13: 4605 | I13: 3919
A14: 200,001 to 500,000 | B14: 10724 | C14: 10634 | D14: 6002 | E14: 10552 | F14: 8775 | G14: 4981 | H14: 5161 | I14: 4866
A15: Over 500,000 | B15: 7074 | C15: 7014 | D15: 4803 | E15: 6915 | F15: 6021 | G15: 4409 | H15: 4413 | I15: 4612
A16: Principal building activity
A17: Education | B17: 12239 | C17: 12239 | D17: 5004 | E17: 12180 | F17: 8559 | G17: 4376 | H17: 3069 | I17: 2135
A18: Food sales | B18: 1252 | C18: 1252 | D18: 443 | E18: 1232 | F18: 560 | G18: Q | H18: 271 | I18: 323
A19: Food service | B19: 1819 | C19: 1819 | D19: 924 | E19: 1671 | F19: 1177 | G19: 121 | H19: 496 | I19: 275
A20: Health care | B20: 4155 | C20: 4155 | D20: 2391 | E20: 4074 | F20: 3535 | G20: 1448 | H20: 1875 | I20: 2245
A21: Inpatient | B21: 2374 | C21: 2374 | D21: 1745 | E21: 2373 | F21: 2260 | G21: 1217 | H21: 1452 | I21: 1647
A22: Outpatient | B22: 1781 | C22: 1781 | D22: 646 | E22: 1701 | F22: 1275 | G22: 231 | H22: 423 | I22: 598
A23: Lodging | B23: 5826 | C23: 5817 | D23: 3585 | E23: 5409 | F23: 5258 | G23: 1848 | H23: 2696 | I23: 2024
A24: Mercantile | B24: 11330 | C24: 11320 | D24: 6646 | E24: 10714 | F24: 8053 | G24: 3959 | H24: 5925 | I24: 5118
A25: Retail (other than mall) | B25: 5439 | C25: 5430 | D25: 1671 | E25: 4864 | F25: 2712 | G25: 891 | H25: 1608 | I25: 1295
A26: Enclosed and strip malls | B26: 5890 | C26: 5890 | D26: 4975 | E26: 5850 | F26: 5341 | G26: 3069 | H26: 4317 | I26: 3824
A27: Office | B27: 15952 | C27: 15952 | D27: 7541 | E27: 15547 | F27: 11438 | G27: 3858 | H27: 5598 | I27: 5034
A28: Public assembly | B28: 5559 | C28: 5527 | D28: 3035 | E28: 5208 | F28: 4125 | G28: 1922 | H28: 2172 | I28: 1955
A29: Public order and safety | B29: 1440 | C29: 1414 | D29: 623 | E29: 1375 | F29: 1086 | G29: 404 | H29: 416 | I29: 360
A30: Religious worship | B30: 4557 | C30: 4557 | D30: 3015 | E30: 4293 | F30: 3187 | G30: 839 | H30: 1540 | I30: 902
A31: Service | B31: 4630 | C31: 4379 | D31: 1026 | E31: 4142 | F31: 1569 | G31: 980 | H31: 1024 | I31: Q
A32: Warehouse and storage | B32: 13077 | C32: 12079 | D32: 3094 | E32: 11280 | F32: 4040 | G32: 2934 | H32: 2438 | I32: 998
A33: Other | B33: 2002 | C33: 1930 | D33: 790 | E33: 1880 | F33: 783 | G33: 383 | H33: 344 | I33: 290
A34: Vacant | B34: 3256 | C34: 1128 | D34: 288 | E34: 1076 | F34: 445 | G34: Q | H34: Q | I34: Q
A35: Year constructed
A36: Before 1920 | B36: 3983 | C36: 3715 | D36: 2292 | E36: 3280 | F36: 2346 | G36: 763 | H36: 1208 | I36: 744
A37: 1920 to 1945 | B37: 6025 | C37: 5774 | D37: 2750 | E37: 5472 | F37: 3714 | G37: 1337 | H37: 1948 | I37: 1528
A38: 1946 to 1959 | B38: 7381 | C38: 7087 | D38: 3494 | E38: 6860 | F38: 4340 | G38: 1785 | H38: 2028 | I38: 1306
A39: 1960 to 1969 | B39: 10362 | C39: 10061 | D39: 4629 | E39: 9857 | F39: 6463 | G39: 2525 | H39: 2948 | I39: 2224
A40: 1970 to 1979 | B40: 10846 | C40: 10354 | D40: 5560 | E40: 9992 | F40: 6913 | G40: 3311 | H40: 3418 | I40: 2632
A41: 1980 to 1989 | B41: 15230 | C41: 14688 | D41: 6972 | E41: 14263 | F41: 9199 | G41: 4591 | H41: 5124 | I41: 4374
A42: 1990 to 1999 | B42: 13803 | C42: 12856 | D42: 5494 | E42: 12267 | F42: 8327 | G42: 4127 | H42: 4364 | I42: 3489
A43: 2000 to 2003 | B43: 7215 | C43: 7100 | D43: 2874 | E43: 6810 | F43: 4692 | G43: 2072 | H43: 2580 | I43: 1915
A44: 2004 to 2007 | B44: 6524 | C44: 6378 | D44: 2745 | E44: 6209 | F44: 4249 | G44: 1770 | H44: 2514 | I44: 2113
A45: 2008 to 2012 | B45: 5723 | C45: 5556 | D45: 1595 | E45: 5070 | F45: 3574 | G45: 1116 | H45: 1929 | I45: 1747
A46: Census region and division
A47: Northeast | B47: 15534 | C47: 15071 | D47: 7565 | E47: 14473 | F47: 10771 | G47: 4510 | H47: 5267 | I47: 4752
A48: New England | B48: 4302 | C48: 4062 | D48: 2046 | E48: 3771 | F48: 2886 | G48: 1161 | H48: 1494 | I48: 1363
A49: Middle Atlantic | B49: 11232 | C49: 11009 | D49: 5520 | E49: 10702 | F49: 7886 | G49: 3349 | H49: 3774 | I49: 3388
A50: Midwest | B50: 18919 | C50: 18190 | D50: 9038 | E50: 17514 | F50: 11841 | G50: 5357 | H50: 6169 | I50: 5148
A51: East North Central | B51: 12742 | C51: 12323 | D51: 6180 | E51: 11880 | F51: 8336 | G51: 4102 | H51: 4590 | I51: 3759
A52: West North Central | B52: 6178 | C52: 5867 | D52: 2858 | E52: 5634 | F52: 3505 | G52: 1255 | H52: 1578 | I52: 1389
A53: South | B53: 34279 | C53: 32621 | D53: 14581 | E53: 31363 | F53: 20042 | G53: 9347 | H53: 10970 | I53: 7559
A54: South Atlantic | B54: 17981 | C54: 17449 | D54: 7828 | E54: 16888 | F54: 10855 | G54: 5325 | H54: 6161 | I54: 4553
A55: East South Central | B55: 4904 | C55: 4726 | D55: 2468 | E55: 4573 | F55: 2923 | G55: 1182 | H55: 1349 | I55: 1232
A56: West South Central | B56: 11394 | C56: 10446 | D56: 4286 | E56: 9901 | F56: 6263 | G56: 2841 | H56: 3459 | I56: 1774
A57: West | B57: 18360 | C57: 17687 | D57: 7222 | E57: 16732 | F57: 11163 | G57: 4182 | H57: 5653 | I57: 4612
A58: Mountain | B58: 4981 | C58: 4677 | D58: 2253 | E58: 4529 | F58: 3007 | G58: 1314 | H58: 1663 | I58: 1513
A59: Pacific | B59: 13379 | C59: 13010 | D59: 4969 | E59: 12203 | F59: 8156 | G59: 2868 | H59: 3990 | I59: 3099
A60: Climate region1
A61: Very cold/Cold | B61: 31898 | C61: 30542 | D61: 14837 | E61: 29315 | F61: 20485 | G61: 8734 | H61: 10366 | I61: 9156
A62: Mixed-humid | B62: 27873 | C62: 27096 | D62: 13429 | E62: 26407 | F62: 17410 | G62: 8547 | H62: 9391 | I62: 6936
A63: Mixed-dry/Hot-dry | B63: 12037 | C63: 11670 | D63: 4139 | E63: 11018 | F63: 6692 | G63: 2661 | H63: 3257 | I63: 2514
A64: Hot-humid | B64: 12831 | C64: 11881 | D64: 4769 | E64: 11096 | F64: 7285 | G64: 3035 | H64: 4152 | I64: 2733
A65: Marine | B65: 2454 | C65: 2381 | D65: 1232 | E65: 2246 | F65: 1944 | G65: 420 | H65: 893 | I65: 732
A66: Number of floors
A67: One | B67: 39809 | C67: 37113 | D67: 13966 | E67: 34818 | F67: 18664 | G67: 8474 | H67: 9952 | I67: 6930
A68: Two | B68: 20206 | C68: 19726 | D68: 9208 | E68: 19068 | F68: 12629 | G68: 5326 | H68: 5781 | I68: 3905
A69: Three | B69: 8140 | C69: 8055 | D69: 3886 | E69: 7767 | F69: 5761 | G69: 2239 | H69: 2789 | I69: 1950
A70: Four to nine | B70: 13535 | C70: 13307 | D70: 7842 | E70: 13083 | F70: 11610 | G70: 4469 | H70: 6053 | I70: 5642
A71: Ten or more | B71: 5404 | C71: 5368 | D71: 3504 | E71: 5344 | F71: 5152 | G71: 2888 | H71: 3484 | I71: 3645
A72: Number of workers (main shift)
A73: Fewer than 5 | B73: 17751 | C73: 14286 | D73: 4834 | E73: 12622 | F73: 6162 | G73: 1664 | H73: 2418 | I73: 993
A74: 5 to 9 | B74: 8973 | C74: 8925 | D74: 3346 | E74: 8446 | F74: 4404 | G74: 1445 | H74: 1953 | I74: 902
A75: 10 to 19 | B75: 9623 | C75: 9614 | D75: 3753 | E75: 9292 | F75: 5181 | G75: 1673 | H75: 2355 | I75: 1360
A76: 20 to 49 | B76: 14514 | C76: 14512 | D76: 6370 | E76: 14195 | F76: 9078 | G76: 3603 | H76: 4800 | I76: 3548
A77: 50 to 99 | B77: 13476 | C77: 13476 | D77: 6902 | E77: 13040 | F77: 9597 | G77: 4563 | H77: 5243 | I77: 4223
A78: 100 to 249 | B78: 10941 | C78: 10941 | D78: 5568 | E78: 10782 | F78: 8461 | G78: 4441 | H78: 4227 | I78: 4231
A79: 250 or more | B79: 11815 | C79: 11815 | D79: 7633 | E79: 11704 | F79: 10933 | G79: 6007 | H79: 7062 | I79: 6814
A80: Weekly operating hours
A81: Fewer than 40 | B81: 8220 | C81: 5514 | D81: 2684 | E81: 5037 | F81: 2645 | G81: 754 | H81: 1073 | I81: 445
A82: 40 to 48 | B82: 15828 | C82: 15693 | D82: 6209 | E82: 15156 | F82: 7767 | G82: 3063 | H82: 3615 | I82: 1876
A83: 49 to 60 | B83: 20529 | C83: 20401 | D83: 7753 | E83: 19671 | F83: 12581 | G83: 5227 | H83: 5702 | I83: 4094
A84: 61 to 84 | B84: 15867 | C84: 15773 | D84: 8805 | E84: 15372 | F84: 11430 | G84: 5341 | H84: 6696 | I84: 6080
A85: 85 to 167 | B85: 9395 | C85: 9336 | D85: 4289 | E85: 8702 | F85: 6225 | G85: 2726 | H85: 3544 | I85: 2832
A86: Open continuously | B86: 17253 | C86: 16852 | D86: 8667 | E86: 16144 | F86: 13169 | G86: 6286 | H86: 7428 | I86: 6745
A87: Ownership and occupancy
A88: Nongovernment owned | B88: 67550 | C88: 64509 | D88: 29885 | E88: 61330 | F88: 40348 | G88: 16399 | H88: 22488 | I88: 17210
A89: Owner occupied | B89: 30637 | C89: 29949 | D89: 13181 | E89: 28109 | F89: 18432 | G89: 6238 | H89: 8652 | I89: 6135
A90: Leased to tenant(s) | B90: 26115 | C90: 25543 | D90: 11650 | E90: 24494 | F90: 15538 | G90: 6932 | H90: 9504 | I90: 7422
A91: Owner occupied and leased | B91: 8873 | C91: 8778 | D91: 5011 | E91: 8508 | F91: 6323 | G91: 3190 | H91: 4293 | I91: 3647
A92: Unoccupied | B92: 1925 | C92: 239 | D92: Q | E92: 219 | F92: Q | G92: Q | H92: Q | I92: Q
A93: Government owned | B93: 19543 | C93: 19060 | D93: 8522 | E93: 18751 | F93: 13469 | G93: 6998 | H93: 5571 | I93: 4862
A94: Federal | B94: 1573 | C94: 1573 | D94: 761 | E94: 1572 | F94: 1288 | G94: 804 | H94: 949 | I94: 798
A95: State | B95: 5539 | C95: 5412 | D95: 2581 | E95: 5320 | F95: 4009 | G95: 1955 | H95: 1716 | I95: 1480
A96: Local | B96: 12431 | C96: 12074 | D96: 5180 | E96: 11859 | F96: 8171 | G96: 4238 | H96: 2906 | I96: 2584
A97: Party responsible for operation and maintenance of energy systems
A98: Building owner | B98: 73702 | C98: 70469 | D98: 31846 | E98: 67399 | F98: 46163 | G98: 19310 | H98: 22602 | I98: 17924
A99: Business owner or tenant | B99: 11309 | C99: 11045 | D99: 5466 | E99: 10748 | F99: 6369 | G99: 3351 | H99: 4596 | I99: 3455
A100: Property management | B100: 1250 | C100: 1230 | D100: 681 | E100: 1127 | F100: 841 | G100: 462 | H100: 628 | I100: 502
...

Sheet TableB42
A1: Release date: April 2015 Revised date: May 2016
A2: Table B42. Water-heating equipment, number of buildings and floorspace, 2012
B3: Number of buildings (thousand) | G3: Total floorspace (million square feet)
B4: All buildings | C4: Buildings with water heating | D4: Type of water-heating equipment | G4: All buildings | H4: Buildings with water heating | I4: Type of water-heating equipment
D5: Central- ized system | E5: Distrib- uted system | F5: Both central- ized and distrib- uted systems | I5: Central- ized system | J5: Distrib- uted system | K5: Both central- ized and distrib- uted systems
A6: All buildings | B6: 5557 | C6: 4423 | D6: 3348 | E6: 690 | F6: 385 | G6: 87093 | H6: 79015 | I6: 47534 | J6: 12688 | K6: 18793
A7: Building floorspace (square feet)
A8: 1,001 to 5,000 | B8: 2777 | C8: 2032 | D8: 1653 | E8: 322 | F8: 57 | G8: 8041 | H8: 6102 | I8: 4906 | J8: 1011 | K8: 185
A9: 5,001 to 10,000 | B9: 1229 | C9: 992 | D9: 789 | E9: 120 | F9: 82 | G9: 8900 | H9: 7236 | I9: 5731 | J9: 890 | K9: 615
A10: 10,001 to 25,000 | B10: 884 | C10: 775 | D10: 538 | E10: 143 | F10: 93 | G10: 14105 | H10: 12401 | I10: 8549 | J10: 2318 | K10: 1534
A11: 25,001 to 50,000 | B11: 332 | C11: 307 | D11: 198 | E11: 57 | F11: 51 | G11: 11917 | H11: 11007 | I11: 7125 | J11: 1983 | K11: 1899
A12: 50,001 to 100,000 | B12: 199 | C12: 186 | D12: 103 | E12: 28 | F12: 55 | G12: 13918 | H12: 13063 | I12: 7181 | J12: 1904 | K12: 3978
A13: 100,001 to 200,000 | B13: 90 | C13: 86 | D13: 45 | E13: 13 | F13: 29 | G13: 12415 | H13: 11903 | I13: 6120 | J13: 1846 | K13: 3937
A14: 200,001 to 500,000 | B14: 38 | C14: 36 | D14: 17 | E14: 5 | F14: 14 | G14: 10724 | H14: 10351 | I14: 4924 | J14: 1516 | K14: 3911
A15: Over 500,000 | B15: 8 | C15: 8 | D15: 4 | E15: 1 | F15: 3 | G15: 7074 | H15: 6951 | I15: 2998 | J15: 1220 | K15: 2734
A16: Principal building activity
A17: Education | B17: 389 | C17: 332 | D17: 244 | E17: 51 | F17: 38 | G17: 12239 | H17: 11905 | I17: 7580 | J17: 1269 | K17: 3057
A18: Food sales | B18: 177 | C18: 177 | D18: 155 | E18: Q | F18: Q | G18: 1252 | H18: 1252 | I18: 883 | J18: Q | K18: Q
A19: Food service | B19: 380 | C19: 379 | D19: 307 | E19: 33 | F19: 39 | G19: 1819 | H19: 1817 | I19: 1449 | J19: 130 | K19: 237
A20: Health care | B20: 157 | C20: 156 | D20: 124 | E20: 22 | F20: 10 | G20: 4155 | H20: 4153 | I20: 2630 | J20: 449 | K20: 1074
A21: Inpatient | B21: 10 | C21: 10 | D21: 6 | E21: Q | F21: 2 | G21: 2374 | H21: 2374 | I21: 1419 | J21: Q | K21: 860
A22: Outpatient | B22: 147 | C22: 146 | D22: 118 | E22: 21 | F22: Q | G22: 1781 | H22: 1779 | I22: 1211 | J22: 354 | K22: Q
A23: Lodging | B23: 158 | C23: 158 | D23: 132 | E23: 7 | F23: 19 | G23: 5826 | H23: 5821 | I23: 4418 | J23: 369 | K23: 1034
A24: Mercantile | B24: 602 | C24: 531 | D24: 342 | E24: 90 | F24: 99 | G24: 11330 | H24: 10960 | I24: 4705 | J24: 1492 | K24: 4763
A25: Retail (other than mall) | B25: 438 | C25: 367 | D25: 270 | E25: 80 | F25: 17 | G25: 5439 | H25: 5070 | I25: 2932 | J25: 1013 | K25: 1125
A26: Enclosed and strip malls | B26: 164 | C26: 164 | D26: 72 | E26: 10 | F26: 82 | G26: 5890 | H26: 5890 | I26: 1773 | J26: 479 | K26: 3638
A27: Office | B27: 1012 | C27: 943 | D27: 713 | E27: 160 | F27: 71 | G27: 15952 | H27: 15663 | I27: 8724 | J27: 2934 | K27: 4006
A28: Public assembly | B28: 352 | C28: 317 | D28: 248 | E28: 41 | F28: 28 | G28: 5559 | H28: 5318 | I28: 3389 | J28: 514 | K28: 1415
A29: Public order and safety | B29: 84 | C29: 80 | D29: 72 | E29: Q | F29: Q | G29: 1440 | H29: 1341 | I29: 1139 | J29: Q | K29: Q
A30: Religious worship | B30: 412 | C30: 383 | D30: 290 | E30: 70 | F30: 23 | G30: 4557 | H30: 4337 | I30: 2850 | J30: 711 | K30: 776
A31: Service | B31: 619 | C31: 442 | D31: 347 | E31: 80 | F31: Q | G31: 4630 | H31: 3763 | I31: 2695 | J31: 669 | K31: Q
A32: Warehouse and storage | B32: 796 | C32: 370 | D32: 252 | E32: 93 | F32: 26 | G32: 13077 | H32: 10041 | I32: 5204 | J32: 3449 | K32: 1388
A33: Other | B33: 125 | C33: 98 | D33: 81 | E33: Q | F33: Q | G33: 2002 | H33: 1614 | I33: 1170 | J33: Q | K33: Q
A34: Vacant | B34: 296 | C34: 56 | D34: 44 | E34: Q | F34: Q | G34: 3256 | H34: 1031 | I34: 700 | J34: Q | K34: Q
A35: Year constructed
A36: Before 1920 | B36: 362 | C36: 286 | D36: 232 | E36: 39 | F36: 15 | G36: 3983 | H36: 3403 | I36: 2287 | J36: 526 | K36: 590
A37: 1920 to 1945 | B37: 488 | C37: 383 | D37: 288 | E37: 69 | F37: 26 | G37: 6025 | H37: 5299 | I37: 2918 | J37: 743 | K37: 1638
A38: 1946 to 1959 | B38: 599 | C38: 460 | D38: 356 | E38: 78 | F38: 26 | G38: 7381 | H38: 6410 | I38: 4305 | J38: 943 | K38: 1162
A39: 1960 to 1969 | B39: 639 | C39: 540 | D39: 427 | E39: 60 | F39: 53 | G39: 10362 | H39: 9699 | I39: 6252 | J39: 1005 | K39: 2442
A40: 1970 to 1979 | B40: 684 | C40: 577 | D40: 435 | E40: 87 | F40: 55 | G40: 10846 | H40: 10158 | I40: 6298 | J40: 1773 | K40: 2087
A41: 1980 to 1989 | B41: 915 | C41: 727 | D41: 527 | E41: 139 | F41: 61 | G41: 15230 | H41: 13831 | I41: 7338 | J41: 2888 | K41: 3605
A42: 1990 to 1999 | B42: 845 | C42: 631 | D42: 498 | E42: 86 | F42: 48 | G42: 13803 | H42: 12209 | I42: 7417 | J42: 1724 | K42: 3069
A43: 2000 to 2003 | B43: 375 | C43: 312 | D43: 235 | E43: 45 | F43: 32 | G43: 7215 | H43: 6889 | I43: 4098 | J43: 1145 | K43: 1646
A44: 2004 to 2007 | B44: 347 | C44: 275 | D44: 190 | E44: 47 | F44: 38 | G44: 6524 | H44: 5955 | I44: 3445 | J44: 1007 | K44: 1503
A45: 2008 to 2012 | B45: 303 | C45: 231 | D45: 161 | E45: 39 | F45: 30 | G45: 5723 | H45: 5162 | I45: 3176 | J45: 933 | K45: 1053
A46: Census region and division
A47: Northeast | B47: 805 | C47: 671 | D47: 493 | E47: 123 | F47: 56 | G47: 15534 | H47: 14633 | I47: 9128 | J47: 2383 | K47: 3122
A48: New England | B48: 302 | C48: 235 | D48: 166 | E48: 40 | F48: 30 | G48: 4302 | H48: 3915 | I48: 2487 | J48: 586 | K48: 843
A49: Middle Atlantic | B49: 504 | C49: 436 | D49: 327 | E49: 83 | F49: 26 | G49: 11232 | H49: 10718 | I49: 6641 | J49: 1797 | K49: 2279
A50: Midwest | B50: 1237 | C50: 1014 | D50: 806 | E50: 133 | F50: 76 | G50: 18919 | H50: 17592 | I50: 11316 | J50: 2335 | K50: 3942
A51: East North Central | B51: 735 | C51: 629 | D51: 490 | E51: 90 | F51: 49 | G51: 12742 | H51: 12082 | I51: 7606 | J51: 1671 | K51: 2804
A52: West North Central | B52: 502 | C52: 385 | D52: 316 | E52: 43 | F52: 27 | G52: 6178 | H52: 5510 | I52: 3710 | J52: 663 | K52: 1137
A53: South | B53: 2247 | C53: 1740 | D53: 1322 | E53: 264 | F53: 154 | G53: 34279 | H53: 30261 | I53: 17460 | J53: 4938 | K53: 7863
A54: South Atlantic | B54: 1091 | C54: 856 | D54: 617 | E54: 160 | F54: 79 | G54: 17981 | H54: 16144 | I54: 8889 | J54: 3030 | K54: 4226
A55: East South Central | B55: 370 | C55: 325 | D55: 268 | E55: 28 | F55: 29 | G55: 4904 | H55: 4598 | I55: 2745 | J55: 437 | K55: 1416
A56: West South Central | B56: 786 | C56: 560 | D56: 437 | E56: 76 | F56: 46 | G56: 11394 | H56: 9519 | I56: 5826 | J56: 1471 | K56: 2222
A57: West | B57: 1267 | C57: 997 | D57: 728 | E57: 170 | F57: 99 | G57: 18360 | H57: 16529 | I57: 9631 | J57: 3032 | K57: 3866
A58: Mountain | B58: 338 | C58: 260 | D58: 195 | E58: 36 | F58: 29 | G58: 4981 | H58: 4440 | I58: 2573 | J58: 699 | K58: 1168
A59: Pacific | B59: 929 | C59: 737 | D59: 533 | E59: 135 | F59: 69 | G59: 13379 | H59: 12089 | I59: 7058 | J59: 2333 | K59: 2698
A60: Climate region1
A61: Very cold/Cold | B61: 2031 | C61: 1639 | D61: 1261 | E61: 242 | F61: 136 | G61: 31898 | H61: 29567 | I61: 18894 | J61: 4184 | K61: 6489
A62: Mixed-humid | B62: 1743 | C62: 1445 | D62: 1120 | E62: 201 | F62: 124 | G62: 27873 | H62: 25772 | I62: 15231 | J62: 3619 | K62: 6922
A63: Mixed-dry/Hot-dry | B63: 837 | C63: 635 | D63: 457 | E63: 124 | F63: 54 | G63: 12037 | H63: 10585 | I63: 6259 | J63: 2221 | K63: 2105
A64: Hot-humid | B64: 799 | C64: 590 | D64: 431 | E64: 104 | F64: 55 | G64: 12831 | H64: 10837 | I64: 5983 | J64: 2298 | K64: 2556
A65: Marine | B65: 147 | C65: 113 | D65: 78 | E65: Q | F65: 16 | G65: 2454 | H65: 2255 | I65: 1168 | J65: 366 | K65: 721
A66: Number of floors
A67: One | B67: 3836 | C67: 2862 | D67: 2179 | E67: 451 | F67: 231 | G67: 39809 | H67: 33591 | I67: 20177 | J67: 6094 | K67: 7321
A68: Two | B68: 1158 | C68: 1039 | D68: 786 | E68: 156 | F68: 97 | G68: 20206 | H68: 19088 | I68: 11762 | J68: 3133 | K68: 4194
A69: Three | B69: 374 | C69: 344 | D69: 259 | E69: 58 | F69: 26 | G69: 8140 | H69: 7932 | I69: 5148 | J69: 1181 | K69: 1602
A70: Four to nine | B70: 177 | C70: 166 | D70: 118 | E70: 23 | F70: 26 | G70: 13535 | H70: 13141 | I70: 7998 | J70: 1646 | K70: 3497
A71: Ten or more | B71: 13 | C71: 12 | D71: 6 | E71: 2 | F71: 5 | G71: 5404 | H71: 5264 | I71: 2450 | J71: 635 | K71: 2179
A72: Number of workers (main shift)
A73: Fewer than 5 | B73: 2892 | C73: 1917 | D73: 1547 | E73: 292 | F73: 78 | G73: 17751 | H73: 11783 | I73: 8984 | J73: 1713 | K73: 1086
A74: 5 to 9 | B74: 1085 | C74: 977 | D74: 777 | E74: 140 | F74: 61 | G74: 8973 | H74: 8205 | I74: 6262 | J74: 1188 | K74: 755
A75: 10 to 19 | B75: 731 | C75: 700 | D75: 515 | E75: 118 | F75: 66 | G75: 9623 | H75: 9137 | I75: 6320 | J75: 1690 | K75: 1126
A76: 20 to 49 | B76: 513 | C76: 495 | D76: 319 | E76: 78 | F76: 98 | G76: 14514 | H76: 14097 | I76: 7957 | J76: 2282 | K76: 3859
A77: 50 to 99 | B77: 206 | C77: 203 | D77: 122 | E77: 36 | F77: 46 | G77: 13476 | H77: 13171 | I77: 7105 | J77: 2192 | K77: 3873
A78: 100 to 249 | B78: 93 | C78: 93 | D78: 51 | E78: 20 | F78: 23 | G78: 10941 | H78: 10912 | I78: 5614 | J78: 1893 | K78: 3404
A79: 250 or more | B79: 37 | C79: 37 | D79: 17 | E79: 6 | F79: 14 | G79: 11815 | H79: 11711 | I79: 5292 | J79: 1730 | K79: 4689
A80: Weekly operating hours
A81: Fewer than 40 | B81: 1149 | C81: 703 | D81: 575 | E81: 97 | F81: 31 | G81: 8220 | H81: 5137 | I81: 3777 | J81: 659 | K81: 701
A82: 40 to 48 | B82: 1346 | C82: 1107 | D82: 843 | E82: 193 | F82: 71 | G82: 15828 | H82: 14388 | I82: 9155 | J82: 2631 | K82: 2602
A83: 49 to 60 | B83: 1244 | C83: 1063 | D83: 789 | E83: 184 | F83: 89 | G83: 20529 | H83: 18878 | I83: 11623 | J83: 3487 | K83: 3768
A84: 61 to 84 | B84: 764 | C84: 676 | D84: 467 | E84: 111 | F84: 98 | G84: 15867 | H84: 15304 | I84: 7601 | J84: 2621 | K84: 5082
A85: 85 to 167 | B85: 479 | C85: 428 | D85: 315 | E85: 67 | F85: 46 | G85: 9395 | H85: 8937 | I85: 5247 | J85: 1470 | K85: 2220
A86: Open continuously | B86: 575 | C86: 447 | D86: 359 | E86: 38 | F86: 49 | G86: 17253 | H86: 16371 | I86: 10131 | J86: 1820 | K86: 4420
A87: Ownership and occupancy
A88: Nongovernment owned | B88: 4781 | C88: 3791 | D88: 2851 | E88: 617 | F88: 323 | G88: 67550 | H88: 60645 | I88: 35837 | J88: 11091 | K88: 13717
A89: Owner occupied | B89: 2466 | C89: 2048 | D89: 1634 | E89: 289 | F89: 125 | G89: 30637 | H89: 27869 | I89: 19154 | J89: 4090 | K89: 4626
A90: Leased to tenant(s) | B90: 1745 | C90: 1401 | D90: 1001 | E90: 251 | F90: 149 | G90: 26115 | H90: 23900 | I90: 12749 | J90: 4804 | K90: 6347
A91: Owner occupied and leased | B91: 349 | C91: 316 | D91: 195 | E91: 75 | F91: 46 | G91: 8873 | H91: 8544 | I91: 3698 | J91: 2181 | K91: 2665
A92: Unoccupied | B92: 221 | C92: 26 | D92: 21 | E92: Q | F92: Q | G92: 1925 | H92: 332 | I92: 237 | J92: Q | K92: Q
A93: Government owned | B93: 776 | C93: 632 | D93: 497 | E93: 72 | F93: 62 | G93: 19543 | H93: 18370 | I93: 11697 | J93: 1596 | K93: 5076
A94: Federal | B94: 33 | C94: 33 | D94: 29 | E94: Q | F94: 3 | G94: 1573 | H94: 1565 | I94: 837 | J94: Q | K94: 626
A95: State | B95: 185 | C95: 146 | D95: 106 | E95: 22 | F95: 19 | G95: 5539 | H95: 5270 | I95: 3188 | J95: 746 | K95: 1336
A96: Local | B96: 558 | C96: 452 | D96: 362 | E96: 50 | F96: 40 | G96: 12431 | H96: 11535 | I96: 7672 | J96: 749 | K96: 3115
A97: Party responsible for operation and maintenance of energy systems
A98: Building owner | B98: 4715 | C98: 3706 | D98: 2841 | E98: 580 | F98: 285 | G98: 73702 | H98: 66462 | I98: 41135 | J98: 10474 | K98: 14852
A99: Business owner or tenant | B99: 724 | C99: 617 | D99: 432 | E99: 98 | F99: 87 | G99: 11309 | H99: 10617 | I99: 5269 | J99: 1896 | K99: 3452
A100: Property management | B100: 54 | C100: 42 | D100: 29 | E100: Q | F100: 7 | G100: 1250 | H100: 1177 | I100: 600 | J100: Q | K100: 400
...

Sheet AEO26 Table 21
A1: Table 21. Residential Sector Equipment Stock and Efficiency, and Distributed Generation
A2: https://www.eia.gov/outlooks/aeo/data/browser/#/?id=30-AEO2026&cases=electrnp&sourcekey=0
A3: Thu Apr 23 2026 15:00:43 GMT-0700 (Pacific Daylight Time)
A4: Source: U.S. Energy Information Administration
B5: full name | C5: api key | D5: units | E5: 2025 | F5: 2026 | G5: 2027 | H5: 2028 | I5: 2029 | J5: 2030 | K5: 2031 | L5: 2032 | M5: 2033 | N5: 2034 | O5: 2035 | P5: 2036 | Q5: 2037 | R5: 2038 | S5: 2039 | T5: 2040 | U5: 2041 | V5: 2042 | W5: 2043 | X5: 2044 | Y5: 2045 | Z5: 2046 | AA5: 2047 | AB5: 2048 | AC5: 2049 | AD5: 2050 | AE5: Growth (2025-2050)
A6: Equipment Stock (million units)
A7: Main Space Heaters
A8: Electric Heat Pumps | B8: Residential Equipment: Equipment Stock: Main Space Heaters: Electric Heat Pumps: Alternative Electricity and Transportation | C8: AEO.2026.ELECTRNP.EQNR_STK_RESD_MSHR_EHP_NA_NA_MILL.A | D8: millions | E8: 17.311983 | F8: 17.749022 | G8: 18.189438 | H8: 18.620296 | I8: 19.048622 | J8: 19.472925 | K8: 19.896326 | L8: 20.319126 | M8: 20.735678 | N8: 21.139624 | O8: 21.534763 | P8: 21.918703 | Q8: 22.287914 | R8: 22.643486 | S8: 22.982574 | T8: 23.308935 | U8: 23.62145 | V8: 23.92503 | W8: 24.216194 | X8: 24.49782 | Y8: 24.778502 | Z8: 25.059135 | AA8: 25.339226 | AB8: 25.618916 | AC8: 25.898472 | AD8: 26.179152 | AE8: 1.7%
A9: Electric Other | B9: Residential Equipment: Equipment Stock: Main Space Heaters: Electric Other: Alternative Electricity and Transportation | C9: AEO.2026.ELECTRNP.EQNR_STK_RESD_MSHR_ELO_NA_NA_MILL.A | D9: millions | E9: 27.181431 | F9: 27.515512 | G9: 27.865957 | H9: 28.217012 | I9: 28.567572 | J9: 28.915745 | K9: 29.279917 | L9: 29.647375 | M9: 30.01017 | N9: 30.363132 | O9: 30.709728 | P9: 31.049109 | Q9: 31.363337 | R9: 31.661715 | S9: 31.943415 | T9: 32.213226 | U9: 32.469131 | V9: 32.713242 | W9: 32.952084 | X9: 33.19083 | Y9: 33.431499 | Z9: 33.672844 | AA9: 33.914619 | AB9: 34.156719 | AC9: 34.399776 | AD9: 34.644348 | AE9: 1.0%
A10: Natural Gas Heat Pumps | B10: Residential Equipment: Equipment Stock: Main Space Heaters: Natural Gas Heat Pumps: Alternative Electricity and Transportation | C10: AEO.2026.ELECTRNP.EQNR_STK_RESD_MSHR_NHU_NA_NA_MILL.A | D10: millions | E10: 1.353481 | F10: 1.362886 | G10: 1.372539 | H10: 1.381982 | I10: 1.391457 | J10: 1.401143 | K10: 1.411546 | L10: 1.422006 | M10: 1.432234 | N10: 1.442105 | O10: 1.451719 | P10: 1.461083 | Q10: 1.469427 | R10: 1.477178 | S10: 1.484383 | T10: 1.491171 | U10: 1.497475 | V10: 1.50339 | W10: 1.509154 | X10: 1.51497 | Y10: 1.520823 | Z10: 1.526682 | AA10: 1.532497 | AB10: 1.538285 | AC10: 1.544062 | AD10: 1.549853 | AE10: 0.5%
A11: Natural Gas Other | B11: Residential Equipment: Equipment Stock: Main Space Heaters: Natural Gas Other: Alternative Electricity and Transportation | C11: AEO.2026.ELECTRNP.EQNR_STK_RESD_MSHR_NGO_NA_NA_MILL.A | D11: millions | E11: 65.676498 | F11: 66.275078 | G11: 66.880844 | H11: 67.475456 | I11: 68.067947 | J11: 68.658012 | K11: 69.244476 | L11: 69.829483 | M11: 70.404747 | N11: 70.963165 | O11: 71.509583 | P11: 72.040466 | Q11: 72.550301 | R11: 73.040489 | S11: 73.507484 | T11: 73.955643 | U11: 74.382568 | V11: 74.796257 | W11: 75.194984 | X11: 75.582878 | Y11: 75.97184 | Z11: 76.362976 | AA11: 76.752701 | AB11: 77.141457 | AC11: 77.52977 | AD11: 77.919685 | AE11: 0.7%
A12: Distillate Fuel Oil | B12: Residential Equipment: Equipment Stock: Main Space Heaters: Distillate Fuel Oil: Alternative Electricity and Transportation | C12: AEO.2026.ELECTRNP.EQNR_STK_RESD_MSHR_DFO_NA_NA_MILL.A | D12: millions | E12: 4.673755 | F12: 4.64228 | G12: 4.610223 | H12: 4.578134 | I12: 4.546576 | J12: 4.515469 | K12: 4.483974 | L12: 4.453804 | M12: 4.424804 | N12: 4.397667 | O12: 4.372064 | P12: 4.347501 | Q12: 4.324221 | R12: 4.301682 | S12: 4.279857 | T12: 4.258628 | U12: 4.237717 | V12: 4.217582 | W12: 4.198093 | X12: 4.179298 | Y12: 4.161189 | Z12: 4.143591 | AA12: 4.125104 | AB12: 4.105833 | AC12: 4.085906 | AD12: 4.065665 | AE12: -0.6%
A13: Propane | B13: Residential Equipment: Equipment Stock: Main Space Heaters: Propane: Alternative Electricity and Transportation | C13: AEO.2026.ELECTRNP.EQNR_STK_RESD_MSHR_PROP_NA_NA_MILL.A | D13: millions | E13: 5.239571 | F13: 5.254901 | G13: 5.275189 | H13: 5.292929 | I13: 5.315268 | J13: 5.332719 | K13: 5.345144 | L13: 5.356366 | M13: 5.366018 | N13: 5.374754 | O13: 5.382975 | P13: 5.390388 | Q13: 5.397145 | R13: 5.402469 | S13: 5.406065 | T13: 5.409037 | U13: 5.411285 | V13: 5.41324 | W13: 5.41502 | X13: 5.416883 | Y13: 5.419633 | Z13: 5.423519 | AA13: 5.425779 | AB13: 5.426469 | AC13: 5.425906 | AD13: 5.424696 | AE13: 0.1%
A14: Wood Stoves | B14: Residential Equipment: Equipment Stock: Main Space Heaters: Wood Stoves: Alternative Electricity and Transportation | C14: AEO.2026.ELECTRNP.EQNR_STK_RESD_MSHR_WDS_NA_NA_MILL.A | D14: millions | E14: 2.209099 | F14: 2.206372 | G14: 2.204716 | H14: 2.202679 | I14: 2.200257 | J14: 2.196498 | K14: 2.192493 | L14: 2.188411 | M14: 2.183818 | N14: 2.179103 | O14: 2.174059 | P14: 2.168741 | Q14: 2.162688 | R14: 2.15609 | S14: 2.148804 | T14: 2.141142 | U14: 2.133082 | V14: 2.125569 | W14: 2.118644 | X14: 2.112358 | Y14: 2.106657 | Z14: 2.101425 | AA14: 2.096687 | AB14: 2.092404 | AC14: 2.088661 | AD14: 2.085513 | AE14: -0.2%
A15: Geothermal Heat Pumps | B15: Residential Equipment: Equipment Stock: Main Space Heaters: Geothermal Heat Pumps: Alternative Electricity and Transportation | C15: AEO.2026.ELECTRNP.EQNR_STK_RESD_MSHR_GEHP_NA_NA_MILL.A | D15: millions | E15: 1.313477 | F15: 1.323818 | G15: 1.335508 | H15: 1.347146 | I15: 1.358514 | J15: 1.368395 | K15: 1.378022 | L15: 1.387662 | M15: 1.397142 | N15: 1.406364 | O15: 1.415457 | P15: 1.424366 | Q15: 1.432796 | R15: 1.440846 | S15: 1.448364 | T15: 1.455673 | U15: 1.462747 | V15: 1.469619 | W15: 1.476322 | X15: 1.48297 | Y15: 1.489655 | Z15: 1.496316 | AA15: 1.502908 | AB15: 1.509388 | AC15: 1.515807 | AD15: 1.522205 | AE15: 0.6%
A16: Total | B16: Residential Equipment: Equipment Stock: Main Space Heaters: Total: Alternative Electricity and Transportation | C16: AEO.2026.ELECTRNP.EQNR_STK_RESD_MSHR_TOT_NA_NA_MILL.A | D16: millions | E16: 124.95929 | F16: 126.32986 | G16: 127.73442 | H16: 129.11565 | I16: 130.49623 | J16: 131.86092 | K16: 133.23189 | L16: 134.60423 | M16: 135.95462 | N16: 137.26592 | O16: 138.55035 | P16: 139.80035 | Q16: 140.98782 | R16: 142.12393 | S16: 143.20094 | T16: 144.23346 | U16: 145.21547 | V16: 146.16393 | W16: 147.08049 | X16: 147.978 | Y16: 148.87981 | Z16: 149.7865 | AA16: 150.68953 | AB16: 151.58948 | AC16: 152.48834 | AD16: 153.39111 | AE16: 0.8%
A17: Space Cooling (million units)
A18: Electric Heat Pumps | B18: Residential Equipment: Equipment Stock: Space Cooling: Electric Heat Pumps: Alternative Electricity and Transportation | C18: AEO.2026.ELECTRNP.EQNR_STK_RESD_SPC_EHP_NA_NA_MILL.A | D18: millions | E18: 17.311981 | F18: 17.749023 | G18: 18.189428 | H18: 18.620302 | I18: 19.048615 | J18: 19.472927 | K18: 19.89633 | L18: 20.319124 | M18: 20.735674 | N18: 21.139622 | O18: 21.534761 | P18: 21.918699 | Q18: 22.287916 | R18: 22.643476 | S18: 22.982578 | T18: 23.308931 | U18: 23.621456 | V18: 23.925043 | W18: 24.216196 | X18: 24.497822 | Y18: 24.778507 | Z18: 25.059124 | AA18: 25.339233 | AB18: 25.618923 | AC18: 25.898476 | AD18: 26.179153 | AE18: 1.7%
A19: Natural Gas Heat Pumps | B19: Residential Equipment: Equipment Stock: Space Cooling: Natural Gas Heat Pumps: Alternative Electricity and Transportation | C19: AEO.2026.ELECTRNP.EQNR_STK_RESD_SPC_NHU_NA_NA_MILL.A | D19: millions | E19: 1.353481 | F19: 1.362886 | G19: 1.372539 | H19: 1.381982 | I19: 1.391457 | J19: 1.401143 | K19: 1.411546 | L19: 1.422006 | M19: 1.432234 | N19: 1.442105 | O19: 1.45172 | P19: 1.461082 | Q19: 1.469427 | R19: 1.477178 | S19: 1.484383 | T19: 1.491172 | U19: 1.497475 | V19: 1.503389 | W19: 1.509155 | X19: 1.51497 | Y19: 1.520824 | Z19: 1.526682 | AA19: 1.532497 | AB19: 1.538285 | AC19: 1.544062 | AD19: 1.549853 | AE19: 0.5%
A20: Geothermal Heat Pumps | B20: Residential Equipment: Equipment Stock: Space Cooling: Geothermal Heat Pumps: Alternative Electricity and Transportation | C20: AEO.2026.ELECTRNP.EQNR_STK_RESD_SPC_GEHP_NA_NA_MILL.A | D20: millions | E20: 1.313476 | F20: 1.323818 | G20: 1.335508 | H20: 1.347146 | I20: 1.358514 | J20: 1.368396 | K20: 1.378022 | L20: 1.387662 | M20: 1.397142 | N20: 1.406364 | O20: 1.415457 | P20: 1.424366 | Q20: 1.432797 | R20: 1.440846 | S20: 1.448364 | T20: 1.455673 | U20: 1.462748 | V20: 1.469619 | W20: 1.476323 | X20: 1.482969 | Y20: 1.489655 | Z20: 1.496316 | AA20: 1.502908 | AB20: 1.509388 | AC20: 1.515807 | AD20: 1.522205 | AE20: 0.6%
A21: Central Air Conditioners | B21: Residential Equipment: Equipment Stock: Space Cooling: Central Air Conditioners: Alternative Electricity and Transportation | C21: AEO.2026.ELECTRNP.EQNR_STK_RESD_SPC_CAC_NA_NA_MILL.A | D21: millions | E21: 80.644836 | F21: 81.803375 | G21: 82.981056 | H21: 84.147583 | I21: 85.314003 | J21: 86.473328 | K21: 87.635994 | L21: 88.79895 | M21: 89.949646 | N21: 91.078987 | O21: 92.193398 | P21: 93.288849 | Q21: 94.35051 | R21: 95.384315 | S21: 96.3862 | T21: 97.36377 | U21: 98.313896 | V21: 99.24588 | W21: 100.16054 | X21: 101.06491 | Y21: 101.97162 | Z21: 102.88116 | AA21: 103.78892 | AB21: 104.69522 | AC21: 105.60106 | AD21: 106.50925 | AE21: 1.1%
A22: Room Air Conditioners | B22: Residential Equipment: Equipment Stock: Space Cooling: Room Air Conditioners: Alternative Electricity and Transportation | C22: AEO.2026.ELECTRNP.EQNR_STK_RESD_SPC_RAC_NA_NA_MILL.A | D22: millions | E22: 43.230812 | F22: 43.332207 | G22: 43.4426 | H22: 43.551468 | I22: 43.660194 | J22: 43.765266 | K22: 43.876236 | L22: 43.988445 | M22: 44.098244 | N22: 44.203854 | O22: 44.306885 | P22: 44.407001 | Q22: 44.495968 | R22: 44.577995 | S22: 44.652718 | T22: 44.722828 | U22: 44.787525 | V22: 44.848129 | W22: 44.906857 | X22: 44.966091 | Y22: 45.026669 | Z22: 45.088047 | AA22: 45.149471 | AB22: 45.210838 | AC22: 45.272564 | AD22: 45.335133 | AE22: 0.2%
A23: Total | B23: Residential Equipment: Equipment Stock: Space Cooling: Total: Alternative Electricity and Transportation | C23: AEO.2026.ELECTRNP.EQNR_STK_RESD_SPC_TOT_NA_NA_MILL.A | D23: millions | E23: 143.85458 | F23: 145.57132 | G23: 147.32114 | H23: 149.04849 | I23: 150.77278 | J23: 152.48105 | K23: 154.19812 | L23: 155.91618 | M23: 157.61295 | N23: 159.27094 | O23: 160.90222 | P23: 162.5 | Q23: 164.03662 | R23: 165.5238 | S23: 166.95425 | T23: 168.34238 | U23: 169.68311 | V23: 170.99206 | W23: 172.26907 | X23: 173.52676 | Y23: 174.78728 | Z23: 176.05133 | AA23: 177.31303 | AB23: 178.57266 | AC23: 179.83197 | AD23: 181.09558 | AE23: 0.9%
A24: Water Heaters (million units)
A25: Electric | B25: Residential Equipment: Equipment Stock: Water Heaters: Electric: Alternative Electricity and Transportation | C25: AEO.2026.ELECTRNP.EQNR_STK_RESD_WHT_ELE_NA_NA_MILL.A | D25: millions | E25: 62.475159 | F25: 63.120701 | G25: 63.779793 | H25: 64.43132 | I25: 65.353851 | J25: 66.246185 | K25: 67.135971 | L25: 68.015442 | M25: 68.872505 | N25: 69.689301 | O25: 70.473305 | P25: 71.249405 | Q25: 71.99559 | R25: 72.71917 | S25: 73.415535 | T25: 74.092468 | U25: 74.745132 | V25: 75.379486 | W25: 75.998474 | X25: 76.607582 | Y25: 77.218094 | Z25: 77.830139 | AA25: 78.438873 | AB25: 79.044281 | AC25: 79.647743 | AD25: 80.251228 | AE25: 1.0%
A26: Natural Gas | B26: Residential Equipment: Equipment Stock: Water Heaters: Natural Gas: Alternative Electricity and Transportation | C26: AEO.2026.ELECTRNP.EQNR_STK_RESD_WHT_NG_NA_NA_MILL.A | D26: millions | E26: 65.115173 | F26: 65.884171 | G26: 66.651428 | H26: 67.398285 | I26: 67.943634 | J26: 68.493774 | K26: 69.045731 | L26: 69.599312 | M26: 70.14283 | N26: 70.674828 | O26: 71.197998 | P26: 71.701553 | Q26: 72.178955 | R26: 72.633232 | S26: 73.061043 | T26: 73.467194 | U26: 73.849609 | V26: 74.217758 | W26: 74.569519 | X26: 74.911041 | Y26: 75.253555 | Z26: 75.597664 | AA26: 75.939888 | AB26: 76.280815 | AC26: 76.620628 | AD26: 76.962227 | AE26: 0.7%
A27: Distillate Fuel Oil | B27: Residential Equipment: Equipment Stock: Water Heaters: Distillate Fuel Oil: Alternative Electricity and Transportation | C27: AEO.2026.ELECTRNP.EQNR_STK_RESD_WHT_DFO_NA_NA_MILL.A | D27: millions | E27: 2.224999 | F27: 2.137243 | G27: 2.054813 | H27: 1.979005 | I27: 1.905996 | J27: 1.841834 | K27: 1.785774 | L27: 1.73822 | M27: 1.699196 | N27: 1.669075 | O27: 1.648035 | P27: 1.625744 | Q27: 1.602431 | R27: 1.578433 | S27: 1.553985 | T27: 1.529364 | U27: 1.50473 | V27: 1.480259 | W27: 1.4561 | X27: 1.432403 | Y27: 1.409256 | Z27: 1.386725 | AA27: 1.364848 | AB27: 1.343653 | AC27: 1.32317 | AD27: 1.303432 | AE27: -2.1%
A28: Propane | B28: Residential Equipment: Equipment Stock: Water Heaters: Propane: Alternative Electricity and Transportation | C28: AEO.2026.ELECTRNP.EQNR_STK_RESD_WHT_PROP_NA_NA_MILL.A | D28: millions | E28: 4.199949 | F28: 4.230966 | G28: 4.274209 | H28: 4.316001 | I28: 4.294023 | J28: 4.272385 | K28: 4.249826 | L28: 4.228853 | M28: 4.20994 | N28: 4.195131 | O28: 4.186061 | P28: 4.171363 | Q28: 4.151415 | R28: 4.126579 | S28: 4.096916 | T28: 4.06407 | U28: 4.028924 | V28: 3.992864 | W28: 3.956489 | X28: 3.92079 | Y28: 3.886379 | Z28: 3.853128 | AA28: 3.82083 | AB28: 3.789447 | AC28: 3.759233 | AD28: 3.730529 | AE28: -0.5%
A29: Solar Thermal | B29: Residential Equipment: Equipment Stock: Water Heaters: Solar Thermal: Alternative Electricity and Transportation | C29: AEO.2026.ELECTRNP.EQNR_STK_RESD_WHT_SLR_THERM_NA_MILL.A | D29: millions | E29: 2.17795 | F29: 2.185155 | G29: 2.197155 | H29: 2.208678 | I29: 2.211119 | J29: 2.213908 | K29: 2.216808 | L29: 2.219646 | M29: 2.22244 | N29: 2.225163 | O29: 2.227813 | P29: 2.230457 | Q29: 2.233098 | R29: 2.235716 | S29: 2.238299 | T29: 2.240829 | U29: 2.243291 | V29: 2.245664 | W29: 2.247927 | X29: 2.250247 | Y29: 2.252614 | Z29: 2.25503 | AA29: 2.257498 | AB29: 2.260012 | AC29: 2.262555 | AD29: 2.265137 | AE29: 0.2%
A30: Total | B30: Residential Equipment: Equipment Stock: Water Heaters: Total: Alternative Electricity and Transportation | C30: AEO.2026.ELECTRNP.EQNR_STK_RESD_WHT_TOT_NA_NA_MILL.A | D30: millions | E30: 136.19324 | F30: 137.55823 | G30: 138.9574 | H30: 140.33328 | I30: 141.70862 | J30: 143.06808 | K30: 144.43411 | L30: 145.80147 | M30: 147.14693 | N30: 148.45349 | O30: 149.73322 | P30: 150.97852 | Q30: 152.16148 | R30: 153.29312 | S30: 154.36577 | T30: 155.39392 | U30: 156.37169 | V30: 157.31602 | W30: 158.2285 | X30: 159.12205 | Y30: 160.0199 | Z30: 160.92268 | AA30: 161.82193 | AB30: 162.71822 | AC30: 163.61333 | AD30: 164.51256 | AE30: 0.8%
A31: Cooking Equipment (million units)
A32: Electric | B32: Residential Equipment: Equipment Stock: Cooking Equipment: Electric: Alternative Electricity and Transportation | C32: AEO.2026.ELECTRNP.EQNR_STK_RESD_CER_ELE_NA_NA_MILL.A | D32: millions | E32: 101.44487 | F32: 102.38022 | G32: 103.33312 | H32: 104.26102 | I32: 105.18269 | J32: 106.08801 | K32: 106.99604 | L32: 107.8981 | M32: 108.7757 | N32: 109.5956 | O32: 110.36458 | P32: 111.06873 | Q32: 111.6779 | R32: 112.26496 | S32: 112.84231 | T32: 113.4248 | U32: 114.01843 | V32: 114.64278 | W32: 115.23735 | X32: 115.81297 | Y32: 116.38593 | Z32: 116.9555 | AA32: 117.51417 | AB32: 118.06109 | AC32: 118.59642 | AD32: 119.12215 | AE32: 0.6%
A33: Natural Gas | B33: Residential Equipment: Equipment Stock: Cooking Equipment: Natural Gas: Alternative Electricity and Transportation | C33: AEO.2026.ELECTRNP.EQNR_STK_RESD_CER_NG_NA_NA_MILL.A | D33: millions | E33: 54.077557 | F33: 54.473881 | G33: 54.882652 | H33: 55.293209 | I33: 55.709217 | J33: 56.129211 | K33: 56.555218 | L33: 56.989883 | M33: 57.42915 | N33: 57.889847 | O33: 58.377193 | P33: 58.898079 | Q33: 59.454914 | R33: 59.983089 | S33: 60.462696 | T33: 60.892117 | U33: 61.25919 | V33: 61.560585 | W33: 61.861618 | X33: 62.164097 | Y33: 62.474186 | Z33: 62.793369 | AA33: 63.121021 | AB33: 63.458534 | AC33: 63.807617 | AD33: 64.171135 | AE33: 0.7%
A34: Propane | B34: Residential Equipment: Equipment Stock: Cooking Equipment: Propane: Alternative Electricity and Transportation | C34: AEO.2026.ELECTRNP.EQNR_STK_RESD_CER_PROP_NA_NA_MILL.A | D34: millions | E34: 6.313086 | F34: 6.337418 | G34: 6.366057 | H34: 6.394745 | I34: 6.4238 | J34: 6.449594 | K34: 6.473336 | L34: 6.495827 | M34: 6.516507 | N34: 6.534659 | O34: 6.550374 | P34: 6.563093 | Q34: 6.572578 | R34: 6.581728 | S34: 6.59024 | T34: 6.599422 | U34: 6.609622 | V34: 6.621453 | W34: 6.631668 | X34: 6.640575 | Y34: 6.648939 | Z34: 6.656644 | AA34: 6.663402 | AB34: 6.669089 | AC34: 6.673856 | AD34: 6.678013 | AE34: 0.2%
A35: Total | B35: Residential Equipment: Equipment Stock: Cooking Equipment: Total: Alternative Electricity and Transportation | C35: AEO.2026.ELECTRNP.EQNR_STK_RESD_CER_TOT_NA_NA_MILL.A | D35: millions | E35: 161.83551 | F35: 163.19151 | G35: 164.58182 | H35: 165.94897 | I35: 167.3157 | J35: 168.66682 | K35: 170.0246 | L35: 171.38382 | M35: 172.72136 | N35: 174.0201 | O35: 175.29215 | P35: 176.52989 | Q35: 177.70538 | R35: 178.82977 | S35: 179.89525 | T35: 180.91634 | U35: 181.88724 | V35: 182.82483 | W35: 183.73064 | X35: 184.61765 | Y35: 185.50906 | Z35: 186.40552 | AA35: 187.2986 | AB35: 188.1887 | AC35: 189.0779 | AD35: 189.9713 | AE35: 0.6%
A36: Clothes Dryers (million units)
A37: Electric | B37: Residential Equipment: Equipment Stock: Clothes Dryers: Electric: Alternative Electricity and Transportation | C37: AEO.2026.ELECTRNP.EQNR_STK_RESD_CDR_ELE_NA_NA_MILL.A | D37: millions | E37: 95.14431 | F37: 97.873146 | G37: 100.64809 | H37: 103.42568 | I37: 106.18952 | J37: 108.94067 | K37: 111.67255 | L37: 114.38489 | M37: 117.08183 | N37: 119.74558 | O37: 122.39014 | P37: 125.00532 | Q37: 127.57001 | R37: 130.09308 | S37: 132.56723 | T37: 135.00874 | U37: 137.42129 | V37: 139.78984 | W37: 142.1165 | X37: 144.41321 | Y37: 146.70485 | Z37: 148.99615 | AA37: 151.27672 | AB37: 153.54921 | AC37: 155.81747 | AD37: 158.08495 | AE37: 2.1%
A38: Natural Gas | B38: Residential Equipment: Equipment Stock: Clothes Dryers: Natural Gas: Alternative Electricity and Transportation | C38: AEO.2026.ELECTRNP.EQNR_STK_RESD_CDR_NG_NA_NA_MILL.A | D38: millions | E38: 20.463491 | F38: 20.786949 | G38: 21.119661 | H38: 21.460751 | I38: 21.814619 | J38: 22.183361 | K38: 22.569464 | L38: 22.975388 | M38: 23.374451 | N38: 23.767054 | O38: 24.153271 | P38: 24.532173 | Q38: 24.902653 | R38: 25.263342 | S38: 25.611776 | T38: 25.946064 | U38: 26.263985 | V38: 26.590998 | W38: 26.924614 | X38: 27.264744 | Y38: 27.613161 | Z38: 27.969189 | AA38: 28.330772 | AB38: 28.696926 | AC38: 29.066328 | AD38: 29.43947 | AE38: 1.5%
A39: Total | B39: Residential Equipment: Equipment Stock: Clothes Dryers: Total: Alternative Electricity and Transportation | C39: AEO.2026.ELECTRNP.EQNR_STK_RESD_CDR_TOT_NA_NA_MILL.A | D39: millions | E39: 115.6078 | F39: 118.66009 | G39: 121.76775 | H39: 124.88643 | I39: 128.00413 | J39: 131.12404 | K39: 134.242 | L39: 137.36028 | M39: 140.45628 | N39: 143.51263 | O39: 146.54341 | P39: 149.53749 | Q39: 152.47267 | R39: 155.35641 | S39: 158.179 | T39: 160.9548 | U39: 163.68527 | V39: 166.38084 | W39: 169.04111 | X39: 171.67795 | Y39: 174.31801 | Z39: 176.96535 | AA39: 179.60748 | AB39: 182.24614 | AC39: 184.8838 | AD39: 187.52441 | AE39: 2.0%
A40: Other Appliances (million units)
A41: Refrigerators | B41: Residential Equipment: Equipment Stock: Other Appliances: Refrigerators: Alternative Electricity and Transportation | C41: AEO.2026.ELECTRNP.EQNR_STK_RESD_OTAR_RFG_NA_NA_MILL.A | D41: millions | E41: 187.50732 | F41: 189.532 | G41: 191.5986 | H41: 193.63084 | I41: 195.66356 | J41: 197.67378 | K41: 199.67798 | L41: 201.68271 | M41: 203.65733 | N41: 205.57686 | O41: 207.45824 | P41: 209.28874 | Q41: 211.04334 | R41: 212.72853 | S41: 214.33122 | T41: 215.87019 | U41: 217.33749 | V41: 218.75925 | W41: 220.13121 | X41: 221.46959 | Y41: 222.81328 | Z41: 224.16486 | AA41: 225.51157 | AB41: 226.85414 | AC41: 228.19508 | AD41: 229.54213 | AE41: 0.8%
A42: Freezers | B42: Residential Equipment: Equipment Stock: Other Appliances: Freezers: Alternative Electricity and Transportation | C42: AEO.2026.ELECTRNP.EQNR_STK_RESD_OTAR_FRZ_NA_NA_MILL.A | D42: millions | E42: 48.868607 | F42: 49.328506 | G42: 49.801876 | H42: 50.26841 | I42: 50.734222 | J42: 51.187572 | K42: 51.631802 | L42: 52.075958 | M42: 52.514103 | N42: 52.940769 | O42: 53.359661 | P42: 53.767311 | Q42: 54.163525 | R42: 54.546295 | S42: 54.911201 | T42: 55.263004 | U42: 55.600151 | V42: 55.928661 | W42: 56.245289 | X42: 56.55265 | Y42: 56.861313 | Z42: 57.172104 | AA42: 57.481895 | AB42: 57.790634 | AC42: 58.099026 | AD42: 58.408916 | AE42: 0.7%
A43: Stock Average Equipment Efficiency
A44: Main Space Heaters
A45: Electric Heat Pumps (HSPF) | B45: Residential Equipment: Stock Average Efficiency: Main Space Heaters: Electric Heat Pumps: Alternative Electricity and Transportation | C45: AEO.2026.ELECTRNP.EFI_STK_RESD_SPHR_EHP_NA_NA_HSPF.A | D45: HSPF | E45: 8.494412 | F45: 8.614711 | G45: 8.735021 | H45: 8.858002 | I45: 8.971167 | J45: 9.075111 | K45: 9.169779 | L45: 9.255559 | M45: 9.332383 | N45: 9.401034 | O45: 9.461356 | P45: 9.51375 | Q45: 9.558479 | R45: 9.595476 | S45: 9.624993 | T45: 9.648189 | U45: 9.662559 | V45: 9.66715 | W45: 9.672118 | X45: 9.677267 | Y45: 9.682276 | Z45: 9.687083 | AA45: 9.69175 | AB45: 9.696254 | AC45: 9.700517 | AD45: 9.704503 | AE45: 0.5%
A46: Natural Gas Heat Pumps (GCOP) | B46: Residential Equipment: Stock Average Efficiency: Main Space Heaters: Natural Gas Heat Pumps: Alternative Electricity and Transportation | C46: AEO.2026.ELECTRNP.EFI_STK_RESD_SPHR_NHU_NA_NA_GCOP.A | D46: GCOP | E46: 1.3 | F46: 1.3 | G46: 1.3 | H46: 1.3 | I46: 1.3 | J46: 1.3 | K46: 1.3 | L46: 1.3 | M46: 1.3 | N46: 1.3 | O46: 1.3 | P46: 1.3 | Q46: 1.3 | R46: 1.3 | S46: 1.3 | T46: 1.3 | U46: 1.3 | V46: 1.3 | W46: 1.3 | X46: 1.3 | Y46: 1.3 | Z46: 1.3 | AA46: 1.3 | AB46: 1.3 | AC46: 1.3 | AD46: 1.3 | AE46: 0.0%
A47: Geothermal Heat Pumps (COP) | B47: Residential Equipment: Stock Average Efficiency: Main Space Heaters: Geothermal Heat Pumps: Alternative Electricity and Transportation | C47: AEO.2026.ELECTRNP.EFI_STK_RESD_SPHR_GEHP_NA_NA_COP.A | D47: COP | E47: 3.202069 | F47: 3.220859 | G47: 3.239262 | H47: 3.258008 | I47: 3.276937 | J47: 3.295919 | K47: 3.315187 | L47: 3.333605 | M47: 3.35116 | N47: 3.367886 | O47: 3.383748 | P47: 3.398742 | Q47: 3.412921 | R47: 3.426215 | S47: 3.438614 | T47: 3.450181 | U47: 3.460697 | V47: 3.470215 | W47: 3.478648 | X47: 3.486041 | Y47: 3.492233 | Z47: 3.497434 | AA47: 3.501589 | AB47: 3.504642 | AC47: 3.506805 | AD47: 3.507983 | AE47: 0.4%
A48: Natural Gas Furnace (AFUE) | B48: Residential Equipment: Stock Average Efficiency: Main Space Heaters: Natural Gas Furnace: Alternative Electricity and Transportation | C48: AEO.2026.ELECTRNP.EFI_STK_RESD_SPHR_NFR_NA_NA_AFUE.A | D48: AFUE | E48: 0.821949 | F48: 0.826215 | G48: 0.8304 | H48: 0.83462 | I48: 0.842838 | J48: 0.851978 | K48: 0.861225 | L48: 0.870013 | M48: 0.878359 | N48: 0.886196 | O48: 0.893502 | P48: 0.900356 | Q48: 0.906728 | R48: 0.912645 | S48: 0.918086 | T48: 0.923074 | U48: 0.927592 | V48: 0.931675 | W48: 0.935279 | X48: 0.938381 | Y48: 0.940932 | Z48: 0.942906 | AA48: 0.944887 | AB48: 0.946836 | AC48: 0.948715 | AD48: 0.950491 | AE48: 0.6%
A49: Distillate Furnace (AFUE) | B49: Residential Equipment: Stock Average Efficiency: Main Space Heaters: Distillate Furnace: Alternative Electricity and Transportation | C49: AEO.2026.ELECTRNP.EFI_STK_RESD_SPHR_DFR_NA_NA_AFUE.A | D49: AFUE | E49: 0.832116 | F49: 0.832644 | G49: 0.833143 | H49: 0.833627 | I49: 0.834101 | J49: 0.834582 | K49: 0.835062 | L49: 0.835526 | M49: 0.835963 | N49: 0.836377 | O49: 0.836758 | P49: 0.837116 | Q49: 0.837445 | R49: 0.83775 | S49: 0.838033 | T49: 0.838292 | U49: 0.838525 | V49: 0.838736 | W49: 0.83892 | X49: 0.839077 | Y49: 0.839199 | Z49: 0.839295 | AA49: 0.839398 | AB49: 0.839505 | AC49: 0.839618 | AD49: 0.839736 | AE49: 0.0%
A50: Space Cooling
A51: Electric Heat Pumps (SEER) | B51: Residential Equipment: Stock Average Efficiency: Space Cooling: Electric Heat Pumps: Alternative Electricity and Transportation | C51: AEO.2026.ELECTRNP.EFI_STK_RESD_SPC_EHP_NA_NA_SEER.A | D51: SEER | E51: 14.394477 | F51: 14.649236 | G51: 14.903358 | H51: 15.162802 | I51: 15.401136 | J51: 15.619678 | K51: 15.818392 | L51: 15.998156 | M51: 16.158895 | N51: 16.302317 | O51: 16.428106 | P51: 16.537176 | Q51: 16.630083 | R51: 16.706705 | S51: 16.767574 | T51: 16.818882 | U51: 16.85113 | V51: 16.862507 | W51: 16.874935 | X51: 16.887955 | Y51: 16.900826 | Z51: 16.913347 | AA51: 16.925617 | AB51: 16.937542 | AC51: 16.948915 | AD51: 16.959635 | AE51: 0.7%
A52: Natural Gas Heat Pumps (GCOP) | B52: Residential Equipment: Stock Average Efficiency: Space Cooling: Natural Gas Heat Pumps: Alternative Electricity and Transportation | C52: AEO.2026.ELECTRNP.EFI_STK_RESD_SPC_NHU_NA_NA_GCOP.A | D52: GCOP | E52: 0.629929 | F52: 0.636247 | G52: 0.642884 | H52: 0.649906 | I52: 0.65655 | J52: 0.662793 | K52: 0.668605 | L52: 0.673974 | M52: 0.678862 | N52: 0.683288 | O52: 0.687221 | P52: 0.690665 | Q52: 0.693611 | R52: 0.696038 | S52: 0.697942 | T52: 0.699288 | U52: 0.7 | V52: 0.7 | W52: 0.7 | X52: 0.7 | Y52: 0.7 | Z52: 0.7 | AA52: 0.7 | AB52: 0.7 | AC52: 0.7 | AD52: 0.7 | AE52: 0.4%
A53: Geothermal Heat Pumps (EER) | B53: Residential Equipment: Stock Average Efficiency: Space Cooling: Geothermal Heat Pumps: Alternative Electricity and Transportation | C53: AEO.2026.ELECTRNP.EFI_STK_RESD_SPC_GEHP_NA_NA_EER.A | D53: EER | E53: 14.018055 | F53: 14.153003 | G53: 14.285445 | H53: 14.420227 | I53: 14.556438 | J53: 14.693085 | K53: 14.831795 | L53: 14.964412 | M53: 15.090815 | N53: 15.211212 | O53: 15.325381 | P53: 15.433255 | Q53: 15.535234 | R53: 15.630803 | S53: 15.719887 | T53: 15.802962 | U53: 15.878443 | V53: 15.946691 | W53: 16.007122 | X53: 16.060036 | Y53: 16.104307 | Z53: 16.141459 | AA53: 16.171091 | AB53: 16.192818 | AC53: 16.208145 | AD53: 16.216425 | AE53: 0.6%
A54: Central Air Conditioners (SEER) | B54: Residential Equipment: Stock Average Efficiency: Space Cooling: Central Air Conditioners: Alternative Electricity and Transportation | C54: AEO.2026.ELECTRNP.EFI_STK_RESD_SPC_CAC_NA_NA_SEER.A | D54: SEER | E54: 13.182222 | F54: 13.332609 | G54: 13.483406 | H54: 13.636544 | I54: 13.779715 | J54: 13.925951 | K54: 14.060987 | L54: 14.184299 | M54: 14.295242 | N54: 14.394967 | O54: 14.482498 | P54: 14.557345 | Q54: 14.620028 | R54: 14.671937 | S54: 14.712533 | T54: 14.742565 | U54: 14.761471 | V54: 14.768062 | W54: 14.774351 | X54: 14.780355 | Y54: 14.786111 | Z54: 14.791622 | AA54: 14.796846 | AB54: 14.801774 | AC54: 14.806413 | AD54: 14.810778 | AE54: 0.5%
A55: Room Air Conditioners (EER) | B55: Residential Equipment: Stock Average Efficiency: Space Cooling: Room Air Conditioners: Alternative Electricity and Transportation | C55: AEO.2026.ELECTRNP.EFI_STK_RESD_SPC_RAC_NA_NA_EER.A | D55: EER | E55: 11.645765 | F55: 11.861027 | G55: 12.310933 | H55: 12.76936 | I55: 13.284547 | J55: 13.782188 | K55: 14.243883 | L55: 14.660746 | M55: 15.032824 | N55: 15.34953 | O55: 15.587445 | P55: 15.743828 | Q55: 15.817233 | R55: 15.875089 | S55: 15.918317 | T55: 15.94899 | U55: 15.969603 | V55: 15.982771 | W55: 15.990712 | X55: 15.995247 | Y55: 15.997692 | Z55: 15.998946 | AA55: 15.999543 | AB55: 15.999808 | AC55: 15.999928 | AD55: 15.999976 | AE55: 1.3%
A56: Water Heaters
A57: Electric (EF) | B57: Residential Equipment: Stock Average Efficiency: Water Heaters: Electric: Alternative Electricity and Transportation | C57: AEO.2026.ELECTRNP.EFI_STK_RESD_WHT_ELE_NA_NA_EF.A | D57: EF | E57: 1.149943 | F57: 1.174917 | G57: 1.19136 | H57: 1.209078 | I57: 1.322374 | J57: 1.415462 | K57: 1.513617 | L57: 1.607691 | M57: 1.697708 | N57: 1.782251 | O57: 1.860952 | P57: 1.933254 | Q57: 1.998485 | R57: 2.05664 | S57: 2.107246 | T57: 2.15043 | U57: 2.185891 | V57: 2.213363 | W57: 2.233032 | X57: 2.251643 | Y57: 2.26908 | Z57: 2.285292 | AA57: 2.300254 | AB57: 2.313976 | AC57: 2.326515 | AD57: 2.337879 | AE57: 2.9%
A58: Natural Gas (EF) | B58: Residential Equipment: Stock Average Efficiency: Water Heaters: Natural Gas: Alternative Electricity and Transportation | C58: AEO.2026.ELECTRNP.EFI_STK_RESD_WHT_NG_NA_NA_EF.A | D58: EF | E58: 0.613419 | F58: 0.616896 | G58: 0.619763 | H58: 0.622133 | I58: 0.628677 | J58: 0.634337 | K58: 0.639269 | L58: 0.643449 | M58: 0.646743 | N58: 0.649166 | O58: 0.650777 | P58: 0.652387 | Q58: 0.653966 | R58: 0.655499 | S58: 0.656969 | T58: 0.658368 | U58: 0.659685 | V58: 0.660917 | W58: 0.662059 | X58: 0.66311 | Y58: 0.664071 | Z58: 0.664942 | AA58: 0.665724 | AB58: 0.666422 | AC58: 0.667041 | AD58: 0.667586 | AE58: 0.3%
A59: Distillate Fuel Oil (EF) | B59: Residential Equipment: Stock Average Efficiency: Water Heaters: Distillate Fuel Oil: Alternative Electricity and Transportation | C59: AEO.2026.ELECTRNP.EFI_STK_RESD_WHT_DFO_NA_NA_EF.A | D59: EF | E59: 0.55984 | F59: 0.572169 | G59: 0.584079 | H59: 0.595341 | I59: 0.606766 | J59: 0.616869 | K59: 0.625585 | L59: 0.632601 | M59: 0.637676 | N59: 0.640564 | O59: 0.641109 | P59: 0.641668 | Q59: 0.642233 | R59: 0.642799 | S59: 0.643363 | T59: 0.643918 | U59: 0.644462 | V59: 0.64499 | W59: 0.6455 | X59: 0.645988 | Y59: 0.646453 | Z59: 0.646892 | AA59: 0.647304 | AB59: 0.647688 | AC59: 0.648044 | AD59: 0.648372 | AE59: 0.6%
A60: Propane (EF) | B60: Residential Equipment: Stock Average Efficiency: Water Heaters: Propane: Alternative Electricity and Transportation | C60: AEO.2026.ELECTRNP.EFI_STK_RESD_WHT_PROP_NA_NA_EF.A | D60: EF | E60: 0.621927 | F60: 0.625153 | G60: 0.627432 | H60: 0.629172 | I60: 0.634517 | J60: 0.63917 | K60: 0.643133 | L60: 0.646393 | M60: 0.648897 | N60: 0.650628 | O60: 0.651559 | P60: 0.652503 | Q60: 0.653445 | R60: 0.654375 | S60: 0.655284 | T60: 0.656167 | U60: 0.657018 | V60: 0.657833 | W60: 0.658609 | X60: 0.659341 | Y60: 0.660028 | Z60: 0.660665 | AA60: 0.661251 | AB60: 0.661785 | AC60: 0.662269 | AD60: 0.662704 | AE60: 0.3%
A61: Other Appliances (kilowatthours per year)
A62: Refrigerators | B62: Residential Equipment: Stock Average Efficiency: Other Appliances: Refrigerators: Alternative Electricity and Transportation | C62: AEO.2026.ELECTRNP.EFI_STK_RESD_OTAR_RFG_NA_NA_KWH.A | D62: kWh | E62: 596.52557 | F62: 587.68524 | G62: 578.72015 | H62: 569.70685 | I62: 561.1781 | J62: 548.50134 | K62: 536.2691 | L62: 524.46576 | M62: 513.08746 | N62: 502.1141 | O62: 491.57819 | P62: 481.78293 | Q62: 472.79703 | R62: 464.6543 | S62: 457.3656 | T62: 450.89535 | U62: 445.24484 | V62: 440.37363 | W62: 436.31903 | X62: 433.03894 | Y62: 430.56067 | Z62: 428.90656 | AA62: 428.04953 | AB62: 427.28192 | AC62: 426.60016 | AD62: 425.98859 | AE62: -1.3%
A63: Freezers | B63: Residential Equipment: Stock Average Efficiency: Other Appliances: Freezers: Alternative Electricity and Transportation | C63: AEO.2026.ELECTRNP.EFI_STK_RESD_OTAR_FRZ_NA_NA_KWH.A | D63: kWh | E63: 458.94305 | F63: 454.38635 | G63: 449.85458 | H63: 445.28195 | I63: 440.63297 | J63: 433.89246 | K63: 427.01755 | L63: 420.04758 | M63: 413.35657 | N63: 406.94708 | O63: 400.83316 | P63: 395.00174 | Q63: 389.43475 | R63: 384.16476 | S63: 379.21167 | T63: 374.55356 | U63: 370.24371 | V63: 366.24969 | W63: 362.59119 | X63: 359.25006 | Y63: 356.20798 | Z63: 353.52856 | AA63: 351.18509 | AB63: 349.2287 | AC63: 347.68655 | AD63: 346.5629 | AE63: -1.1%
A64: Building Shell Efficiency Index
A65: Space Heating
A66: Pre-2020 Homes | B66: Residential Equipment: Building Shell Efficiency Index: Space Heating: Pre-2020 Homes: Alternative Electricity and Transportation | C66: AEO.2026.ELECTRNP.EFI_BSE_RESD_SPH_OLD_NA_NA_Y15EQ1.A | D66: 2020=1.00 | E66: 0.956101 | F66: 0.950758 | G66: 0.945052 | H66: 0.938998 | I66: 0.932345 | J66: 0.925172 | K66: 0.917816 | L66: 0.910537 | M66: 0.90305 | N66: 0.895764 | O66: 0.888572 | P66: 0.881558 | Q66: 0.874511 | R66: 0.867545 | S66: 0.860613 | T66: 0.853716 | U66: 0.846866 | V66: 0.840177 | W66: 0.83362 | X66: 0.82715 | Y66: 0.82065 | Z66: 0.814016 | AA66: 0.807256 | AB66: 0.800451 | AC66: 0.793677 | AD66: 0.786926 | AE66: -0.8%
A67: New Construction | B67: Residential Equipment: Building Shell Efficiency Index: Space Heating: New Construction: Alternative Electricity and Transportation | C67: AEO.2026.ELECTRNP.EFI_BSE_RESD_SPH_NCO_NA_NA_Y15EQ1.A | D67: 2020=1.00 | E67: 0.789724 | F67: 0.865747 | G67: 0.901509 | H67: 0.900807 | I67: 0.898675 | J67: 0.902115 | K67: 0.908102 | L67: 0.90784 | M67: 0.906341 | N67: 0.904926 | O67: 0.90334 | P67: 0.902405 | Q67: 0.895033 | R67: 0.891202 | S67: 0.888339 | T67: 0.885432 | U67: 0.881966 | V67: 0.8786 | W67: 0.878308 | X67: 0.879787 | Y67: 0.879173 | Z67: 0.877908 | AA67: 0.876591 | AB67: 0.875545 | AC67: 0.874588 | AD67: 0.873561 | AE67: 0.4%
A68: All Homes | B68: Residential Equipment: Building Shell Efficiency Index: Space Heating: All Homes: Alternative Electricity and Transportation | C68: AEO.2026.ELECTRNP.EFI_BSE_RESD_SPH_AHM_NA_NA_Y15EQ1.A | D68: 2020=1.00 | E68: 0.9475 | F68: 0.94159 | G68: 0.935891 | H68: 0.930009 | I68: 0.923702 | J68: 0.91712 | K68: 0.910592 | L68: 0.904272 | M68: 0.897896 | N68: 0.891807 | O68: 0.885903 | P68: 0.880253 | Q68: 0.874602 | R68: 0.869078 | S68: 0.863643 | T68: 0.858293 | U68: 0.853028 | V68: 0.847936 | W68: 0.84301 | X68: 0.838226 | Y68: 0.83348 | Z68: 0.828688 | AA68: 0.823853 | AB68: 0.81904 | AC68: 0.814306 | AD68: 0.809646 | AE68: -0.6%
A69: Space Cooling
A70: Pre-2020 Homes | B70: Residential Equipment: Building Shell Efficiency Index: Space Cooling: Pre-2020 Homes: Alternative Electricity and Transportation | C70: AEO.2026.ELECTRNP.EFI_BSE_RESD_SPC_OLD_NA_NA_Y15EQ1.A | D70: 2020=1.00 | E70: 0.984865 | F70: 0.983098 | G70: 0.98113 | H70: 0.978977 | I70: 0.976576 | J70: 0.974012 | K70: 0.971383 | L70: 0.968805 | M70: 0.966197 | N70: 0.963654 | O70: 0.961119 | P70: 0.958638 | Q70: 0.956141 | R70: 0.953668 | S70: 0.951209 | T70: 0.94877 | U70: 0.946343 | V70: 0.94397 | W70: 0.941637 | X70: 0.939331 | Y70: 0.937013 | Z70: 0.934647 | AA70: 0.932236 | AB70: 0.929807 | AC70: 0.927389 | AD70: 0.924984 | AE70: -0.3%
A71: New Construction | B71: Residential Equipment: Building Shell Efficiency Index: Space Cooling: New Construction: Alternative Electricity and Transportation | C71: AEO.2026.ELECTRNP.EFI_BSE_RESD_SPC_NCO_NA_NA_Y15EQ1.A | D71: 2020=1.00 | E71: 0.978933 | F71: 1.006527 | G71: 1.023568 | H71: 1.023448 | I71: 1.022484 | J71: 1.022529 | K71: 1.026335 | L71: 1.026398 | M71: 1.025671 | N71: 1.025067 | O71: 1.024506 | P71: 1.024467 | Q71: 1.019954 | R71: 1.017898 | S71: 1.016372 | T71: 1.015388 | U71: 1.014135 | V71: 1.01255 | W71: 1.013225 | X71: 1.015143 | Y71: 1.015255 | Z71: 1.01481 | AA71: 1.014474 | AB71: 1.014172 | AC71: 1.014011 | AD71: 1.013783 | AE71: 0.1%
A72: All Homes | B72: Residential Equipment: Building Shell Efficiency Index: Space Cooling: All Homes: Alternative Electricity and Transportation | C72: AEO.2026.ELECTRNP.EFI_BSE_RESD_SPC_AHM_NA_NA_Y15EQ1.A | D72: 2020=1.00 | E72: 0.985082 | F72: 0.983628 | G72: 0.982187 | H72: 0.98059 | I72: 0.978785 | J72: 0.976858 | K72: 0.974941 | L72: 0.973101 | M72: 0.971248 | N72: 0.969462 | O72: 0.967695 | P72: 0.965988 | Q72: 0.964231 | R72: 0.962486 | S72: 0.960742 | T72: 0.959014 | U72: 0.95729 | V72: 0.955606 | W72: 0.953964 | X72: 0.952364 | Y72: 0.950769 | Z72: 0.949148 | AA72: 0.947501 | AB72: 0.945849 | AC72: 0.944219 | AD72: 0.942611 | AE72: -0.2%
A73: Distributed Generation and
A74: Combined Heat and Power
A75: Generating Capacity (gigawatts)
A76: Natural Gas Fuel Cells | B76: Residential: Combined Heat and Power: Generating Capacity: Fuel Cells: Alternative Electricity and Transportation | C76: AEO.2026.ELECTRNP.CAP_NA_COMM_CHP_FCL_NA_NA_MW.A | D76: GW | E76: 0.000505 | F76: 0.001105 | G76: 0.001689 | H76: 0.001702 | I76: 0.001715 | J76: 0.002529 | K76: 0.003616 | L76: 0.004737 | M76: 0.005609 | N76: 0.006702 | O76: 0.006715 | P76: 0.006728 | Q76: 0.006741 | R76: 0.006754 | S76: 0.006768 | T76: 0.006782 | U76: 0.006798 | V76: 0.006819 | W76: 0.006848 | X76: 0.006894 | Y76: 0.006973 | Z76: 0.007111 | AA76: 0.007249 | AB76: 0.007388 | AC76: 0.007528 | AD76: 0.007669 | AE76: 11.5%
A77: Solar Photovoltaic | B77: Residential: Combined Heat and Power: Generating Capacity: Solar Photovoltaic: Alternative Electricity and Transportation | C77: AEO.2026.ELECTRNP.CAP_NA_RESD_CHP_SLR_PHTVL_NA_MW.A | D77: GW | E77: 44.365597 | F77: 47.055515 | G77: 50.09021 | H77: 53.229542 | I77: 56.177746 | J77: 59.281429 | K77: 62.644226 | L77: 66.000397 | M77: 69.527916 | N77: 73.271034 | O77: 77.272438 | P77: 81.470436 | Q77: 85.978043 | R77: 90.700516 | S77: 95.678627 | T77: 100.83944 | U77: 106.21883 | V77: 111.75826 | W77: 117.47205 | X77: 123.40828 | Y77: 129.49213 | Z77: 135.76173 | AA77: 142.2249 | AB77: 148.97238 | AC77: 155.8443 | AD77: 162.96338 | AE77: 5.3%
A78: Wind | B78: Residential: Combined Heat and Power: Generating Capacity: Wind: Alternative Electricity and Transportation | C78: AEO.2026.ELECTRNP.CAP_NA_RESD_CHP_WND_NA_NA_MW.A | D78: GW | E78: 0.161232 | F78: 0.161366 | G78: 0.16153 | H78: 0.161692 | I78: 0.161954 | J78: 0.16241 | K78: 0.163239 | L78: 0.164534 | M78: 0.166535 | N78: 0.169296 | O78: 0.1726 | P78: 0.176311 | Q78: 0.180427 | R78: 0.184751 | S78: 0.189183 | T78: 0.193883 | U78: 0.199127 | V78: 0.204729 | W78: 0.210513 | X78: 0.21644 | Y78: 0.222562 | Z78: 0.229229 | AA78: 0.236147 | AB78: 0.244054 | AC78: 0.252049 | AD78: 0.260129 | AE78: 1.9%
A79: Total | B79: Residential: Combined Heat and Power: Generating Capacity: Total: Alternative Electricity and Transportation | C79: AEO.2026.ELECTRNP.CAP_NA_RESD_CHP_TOT_NA_NA_MW.A | D79: GW | E79: 44.527336 | F79: 47.217987 | G79: 50.253429 | H79: 53.392937 | I79: 56.341415 | J79: 59.446369 | K79: 62.811081 | L79: 66.16967 | M79: 69.700058 | N79: 73.447029 | O79: 77.451752 | P79: 81.653473 | Q79: 86.165215 | R79: 90.892021 | S79: 95.87458 | T79: 101.04011 | U79: 106.42476 | V79: 111.96981 | W79: 117.68941 | X79: 123.63161 | Y79: 129.72166 | Z79: 135.99808 | AA79: 142.46829 | AB79: 149.22382 | AC79: 156.10387 | AD79: 163.23119 | AE79: 5.3%
A80: Net Generation (billion kilowatthours)
A81: Natural Gas Fuel Cells | B81: Residential: Combined Heat and Power: Net Generation: Fuel Cells: Alternative Electricity and Transportation | C81: AEO.2026.ELECTRNP.GEN_NA_COMM_CHP_FCL_NA_NA_MILLKWH.A | D81: billion kWh | E81: 0.002002 | F81: 0.004375 | G81: 0.006688 | H81: 0.006739 | I81: 0.006791 | J81: 0.010015 | K81: 0.014319 | L81: 0.018757 | M81: 0.022213 | N81: 0.026542 | O81: 0.026593 | P81: 0.026644 | Q81: 0.026696 | R81: 0.026747 | S81: 0.026799 | T81: 0.026855 | U81: 0.026919 | V81: 0.027001 | W81: 0.027117 | X81: 0.027301 | Y81: 0.027612 | Z81: 0.028158 | AA81: 0.028707 | AB81: 0.029258 | AC81: 0.029812 | AD81: 0.030371 | AE81: 11.5%
A82: Solar Photovoltaic | B82: Residential: Combined Heat and Power: Net Generation: Solar Photovoltaic: Alternative Electricity and Transportation | C82: AEO.2026.ELECTRNP.GEN_NA_COMM_CHP_SLR_PHTVL_NA_MILLKWH.A | D82: billion kWh | E82: 65.763306 | F82: 69.514885 | G82: 73.749603 | H82: 78.117584 | I82: 82.188416 | J82: 86.464531 | K82: 91.093109 | L82: 95.701416 | M82: 100.53012 | N82: 105.64702 | O82: 111.10266 | P82: 116.81789 | Q82: 122.9398 | R82: 129.34982 | S82: 136.10321 | T82: 143.0936 | U82: 150.36011 | V82: 157.83048 | W82: 165.5316 | X82: 173.53079 | Y82: 181.7104 | Z82: 190.12964 | AA82: 198.79532 | AB82: 207.82278 | AC82: 216.99315 | AD82: 226.49281 | AE82: 5.1%
A83: Wind | B83: Residential: Combined Heat and Power: Net Generation: Wind: Alternative Electricity and Transportation | C83: AEO.2026.ELECTRNP.GEN_NA_COMM_CHP_WND_NA_NA_MILLKWH.A | D83: billion kWh | E83: 0.172274 | F83: 0.172428 | G83: 0.172616 | H83: 0.172802 | I83: 0.173103 | J83: 0.173625 | K83: 0.174572 | L83: 0.176045 | M83: 0.178308 | N83: 0.181417 | O83: 0.185126 | P83: 0.189283 | Q83: 0.193886 | R83: 0.198717 | S83: 0.203668 | T83: 0.208914 | U83: 0.214761 | V83: 0.221002 | W83: 0.227441 | X83: 0.234035 | Y83: 0.240839 | Z83: 0.248212 | AA83: 0.255867 | AB83: 0.264578 | AC83: 0.273387 | AD83: 0.282286 | AE83: 2.0%
A84: Total | B84: Residential: Combined Heat and Power: Net Generation: Total: Alternative Electricity and Transportation | C84: AEO.2026.ELECTRNP.GEN_NA_COMM_CHP_TOT_NA_NA_MILLKWH.A | D84: billion kWh | E84: 65.937576 | F84: 69.691681 | G84: 73.928909 | H84: 78.297127 | I84: 82.368309 | J84: 86.64817 | K84: 91.282005 | L84: 95.896217 | M84: 100.73064 | N84: 105.85498 | O84: 111.31438 | P84: 117.03381 | Q84: 123.16039 | R84: 129.57529 | S84: 136.33368 | T84: 143.32936 | U84: 150.60179 | V84: 158.07849 | W84: 165.78616 | X84: 173.79213 | Y84: 181.97887 | Z84: 190.40601 | AA84: 199.07988 | AB84: 208.11661 | AC84: 217.29636 | AD84: 226.80547 | AE84: 5.1%
A85: Disposition
A86: Sales to the Grid | B86: Residential: Combined Heat and Power: Net Generation: Sales to the Grid: Alternative Electricity and Transportation | C86: AEO.2026.ELECTRNP.GEN_NA_COMM_CHP_STG_NA_NA_MILLKWH.A | D86: billion kWh | E86: 11.67818 | F86: 12.194283 | G86: 12.947095 | H86: 13.733868 | I86: 14.398316 | J86: 15.122087 | K86: 15.963413 | L86: 16.765619 | M86: 17.624851 | N86: 18.541655 | O86: 19.535112 | P86: 20.570559 | Q86: 21.70586 | R86: 22.895941 | S86: 24.190172 | T86: 25.53442 | U86: 26.944834 | V86: 28.379297 | W86: 29.894018 | X86: 31.475761 | Y86: 33.075306 | Z86: 34.696655 | AA86: 36.351891 | AB86: 38.104988 | AC86: 39.860676 | AD86: 41.713696 | AE86: 5.2%
A87: Generation for Own Use | B87: Residential: Combined Heat and Power: Net Generation: Generation for Own Use: Alternative Electricity and Transportation | C87: AEO.2026.ELECTRNP.GEN_NA_COMM_CHP_GFO_NA_NA_MILLKWH.A | D87: billion kWh | E87: 54.259399 | F87: 57.497406 | G87: 60.981812 | H87: 64.563263 | I87: 67.970001 | J87: 71.526085 | K87: 75.318588 | L87: 79.1306 | M87: 83.105789 | N87: 87.313324 | O87: 91.779266 | P87: 96.463249 | Q87: 101.45452 | R87: 106.67935 | S87: 112.1435 | T87: 117.79494 | U87: 123.65695 | V87: 129.69917 | W87: 135.89214 | X87: 142.31638 | Y87: 148.90355 | Z87: 155.70935 | AA87: 162.72798 | AB87: 170.01164 | AC87: 177.43568 | AD87: 185.09177 | AE87: 5.0%
A88: Energy Input (trillion Btu)
A89: Natural Gas Fuel Cells | B89: Residential: Combined Heat and Power: Energy Input: Fuel Cells: Alternative Electricity and Transportation | C89: AEO.2026.ELECTRNP.CNSM_NA_COMM_CHP_FCL_NA_NA_TRLBTU.A | D89: trillion Btu | E89: 0.015282 | F89: 0.033397 | G89: 0.051051 | H89: 0.051444 | I89: 0.051837 | J89: 0.076448 | K89: 0.109298 | L89: 0.143174 | M89: 0.169559 | N89: 0.202596 | O89: 0.202989 | P89: 0.203382 | Q89: 0.203775 | R89: 0.204168 | S89: 0.204565 | T89: 0.20499 | U89: 0.20548 | V89: 0.206107 | W89: 0.206993 | X89: 0.208397 | Y89: 0.210771 | Z89: 0.214935 | AA89: 0.219124 | AB89: 0.22333 | AC89: 0.227564 | AD89: 0.231824 | AE89: 11.5%
A90: Solar Photovoltaic | B90: Residential: Combined Heat and Power: Energy Input: Solar Photovoltaic: Alternative Electricity and Transportation | C90: AEO.2026.ELECTRNP.CNSM_NA_COMM_CHP_SLR_PHTVL_NA_TRLBTU.A | D90: trillion Btu | E90: 224.38437 | F90: 237.18477 | G90: 251.63364 | H90: 266.5372 | I90: 280.42688 | J90: 295.01697 | K90: 310.80969 | L90: 326.5332 | M90: 343.00873 | N90: 360.46759 | O90: 379.08227 | P90: 398.58258 | Q90: 419.47064 | R90: 441.34155 | S90: 464.38412 | T90: 488.23529 | U90: 513.02869 | V90: 538.51746 | W90: 564.79382 | X90: 592.08698 | Y90: 619.99591 | Z90: 648.72229 | AA90: 678.28955 | AB90: 709.09131 | AC90: 740.38062 | AD90: 772.79346 | AE90: 5.1%
A91: Wind | B91: Residential: Combined Heat and Power: Energy Input: Wind: Alternative Electricity and Transportation | C91: AEO.2026.ELECTRNP.CNSM_NA_COMM_CHP_WND_NA_NA_TRLBTU.A | D91: trillion Btu | E91: 0.587799 | F91: 0.588324 | G91: 0.588965 | H91: 0.589601 | I91: 0.590628 | J91: 0.59241 | K91: 0.59564 | L91: 0.600666 | M91: 0.608387 | N91: 0.618995 | O91: 0.631648 | P91: 0.645833 | Q91: 0.661538 | R91: 0.678022 | S91: 0.694915 | T91: 0.712813 | U91: 0.732765 | V91: 0.754058 | W91: 0.77603 | X91: 0.798529 | Y91: 0.821743 | Z91: 0.846899 | AA91: 0.873017 | AB91: 0.90274 | AC91: 0.932795 | AD91: 0.963161 | AE91: 2.0%
A92: Total | B92: Residential: Combined Heat and Power: Energy Input: Total: Alternative Electricity and Transportation | C92: AEO.2026.ELECTRNP.CNSM_NA_COMM_CHP_TOT_NA_NA_TRLBTU.A | D92: trillion Btu | E92: 224.98744 | F92: 237.80649 | G92: 252.27365 | H92: 267.17825 | I92: 281.06937 | J92: 295.68582 | K92: 311.51462 | L92: 327.27707 | M92: 343.78668 | N92: 361.28918 | O92: 379.91693 | P92: 399.43179 | Q92: 420.33594 | R92: 442.22372 | S92: 465.2836 | T92: 489.15308 | U92: 513.96698 | V92: 539.4776 | W92: 565.77679 | X92: 593.09387 | Y92: 621.02838 | Z92: 649.78412 | AA92: 679.38171 | AB92: 710.21735 | AC92: 741.54096 | AD92: 773.9884 | AE92: 5.1%

Sheet BEA 2017 Margins
A1: Margins, Before Redefinitions, 2017
A2: [Millions of dollars]
A3: Bureau of Economic Analysis
E4: Producers' Value | F4: Transportation Costs | G4: Trade Margins | I4: Purchasers' Value
A5: Industry Code | B5: Industry Description | C5: Commodity Code | D5: Commodity Description | G5: Wholesale | H5: Retail | J5: Buyer group used in this file | K5: Bought through a contractor?
A6: 1111A0 | B6: Oilseed farming | C6: 1111A0 | D6: Oilseed farming | E6: 8332 | F6: 1105 | G6: 2723 | H6: 0 | I6: 12160
A7: 1111B0 | B7: Grain farming | C7: 333414 | D7: Heating equipment (except warm air furnaces) manufacturing | E7: 0 | F7: 0 | G7: 0 | H7: 0 | I7: 0 | J7: =IFERROR(VLOOKUP(A7&"",'BEA Buyer Groups'!$A$4:$C$500,3,FALSE),"Not used") -> Not used | K7: =IF(LEFT(A7,2)="23","Contractor","Direct") -> Direct
A8: 111900 | B8: Other crop farming | C8: 334111 | D8: Electronic computer manufacturing | E8: 56 | F8: 1 | G8: 16 | H8: 0 | I8: 72 | J8: =IFERROR(VLOOKUP(A8&"",'BEA Buyer Groups'!$A$4:$C$500,3,FALSE),"Not used") -> Not used | K8: =IF(LEFT(A8,2)="23","Contractor","Direct") -> Direct
A9: 112120 | B9: Dairy cattle and milk production | C9: 333414 | D9: Heating equipment (except warm air furnaces) manufacturing | E9: 0 | F9: 0 | G9: 0 | H9: 0 | I9: 0 | J9: =IFERROR(VLOOKUP(A9&"",'BEA Buyer Groups'!$A$4:$C$500,3,FALSE),"Not used") -> Not used | K9: =IF(LEFT(A9,2)="23","Contractor","Direct") -> Direct
A10: 112120 | B10: Dairy cattle and milk production | C10: 335110 | D10: Electric lamp bulb and part manufacturing | E10: 1 | F10: 0 | G10: 0 | H10: 0 | I10: 1 | J10: =IFERROR(VLOOKUP(A10&"",'BEA Buyer Groups'!$A$4:$C$500,3,FALSE),"Not used") -> Not used | K10: =IF(LEFT(A10,2)="23","Contractor","Direct") -> Direct
A11: 1121A0 | B11: Beef cattle ranching and farming, including feedlots and dual-purpose ranching and farming | C11: 335110 | D11: Electric lamp bulb and part manufacturing | E11: 0 | F11: 0 | G11: 0 | H11: 0 | I11: 0 | J11: =IFERROR(VLOOKUP(A11&"",'BEA Buyer Groups'!$A$4:$C$500,3,FALSE),"Not used") -> Not used | K11: =IF(LEFT(A11,2)="23","Contractor","Direct") -> Direct
A12: 114000 | B12: Fishing, hunting and trapping | C12: 335110 | D12: Electric lamp bulb and part manufacturing | E12: 1 | F12: 0 | G12: 0 | H12: 0 | I12: 1 | J12: =IFERROR(VLOOKUP(A12&"",'BEA Buyer Groups'!$A$4:$C$500,3,FALSE),"Not used") -> Not used | K12: =IF(LEFT(A12,2)="23","Contractor","Direct") -> Direct
A13: 114000 | B13: Fishing, hunting and trapping | C13: 335120 | D13: Lighting fixture manufacturing | E13: 54 | F13: 7 | G13: 17 | H13: 0 | I13: 78 | J13: =IFERROR(VLOOKUP(A13&"",'BEA Buyer Groups'!$A$4:$C$500,3,FALSE),"Not used") -> Not used | K13: =IF(LEFT(A13,2)="23","Contractor","Direct") -> Direct
A14: 211000 | B14: Oil and gas extraction | C14: 333318 | D14: Other commercial and service industry machinery manufacturing | E14: 50 | F14: 2 | G14: 25 | H14: 0 | I14: 76 | J14: =IFERROR(VLOOKUP(A14&"",'BEA Buyer Groups'!$A$4:$C$500,3,FALSE),"Not used") -> Not used | K14: =IF(LEFT(A14,2)="23","Contractor","Direct") -> Direct
A15: 211000 | B15: Oil and gas extraction | C15: 333415 | D15: Air conditioning, refrigeration, and warm air heating equipment manufacturing | E15: 7 | F15: 0 | G15: 3 | H15: 0 | I15: 11 | J15: =IFERROR(VLOOKUP(A15&"",'BEA Buyer Groups'!$A$4:$C$500,3,FALSE),"Not used") -> Not used | K15: =IF(LEFT(A15,2)="23","Contractor","Direct") -> Direct
A16: 211000 | B16: Oil and gas extraction | C16: 335120 | D16: Lighting fixture manufacturing | E16: 39 | F16: 5 | G16: 12 | H16: 0 | I16: 56 | J16: =IFERROR(VLOOKUP(A16&"",'BEA Buyer Groups'!$A$4:$C$500,3,FALSE),"Not used") -> Not used | K16: =IF(LEFT(A16,2)="23","Contractor","Direct") -> Direct
A17: 212100 | B17: Coal mining | C17: 333318 | D17: Other commercial and service industry machinery manufacturing | E17: 0 | F17: 0 | G17: 0 | H17: 0 | I17: 0 | J17: =IFERROR(VLOOKUP(A17&"",'BEA Buyer Groups'!$A$4:$C$500,3,FALSE),"Not used") -> Not used | K17: =IF(LEFT(A17,2)="23","Contractor","Direct") -> Direct
A18: 212100 | B18: Coal mining | C18: 335120 | D18: Lighting fixture manufacturing | E18: 18 | F18: 2 | G18: 6 | H18: 0 | I18: 26 | J18: =IFERROR(VLOOKUP(A18&"",'BEA Buyer Groups'!$A$4:$C$500,3,FALSE),"Not used") -> Not used | K18: =IF(LEFT(A18,2)="23","Contractor","Direct") -> Direct
... A1074: S00600 | B1074: Federal general government (nondefense) | C1074: 335110 | D1074: Electric lamp bulb and part manufacturing | E1074: 250 | F1074: 2 | G1074: 78 | H1074: 0 | I1074: 330 | J1074: =IFERROR(VLOOKUP(A1074&"",'BEA Buyer Groups'!$A$4:$C$500,3,FALSE),"Not used") -> Commercial | K1074: =IF(LEFT(A1074,2)="23","Contractor","Direct") -> Direct
A1076: Rows copied verbatim from BEA "Margins, Before Redefinitions, 2017" (detail, sheet 2017) for the nine equipment commodities this file uses, all buyers. Columns J and K are added for this file.

Sheet BEA Buyer Groups
A1: Which buyers count as residential or commercial building purchases. Edit column C to change the grouping; "Not used" rows are left out.
A3: BEA buyer code | B3: Buyer | C3: Group | D3: Why
A4: 230301 | B4: Nonresidential maintenance and repair | C4: Commercial | D4: Businesses and governments buying equipment for their buildings, directly or through nonresidential construction contractors
A5: 233210 | B5: Health care structures | C5: Commercial | D5: Businesses and governments buying equipment for their buildings, directly or through nonresidential construction contractors
A6: 233262 | B6: Educational and vocational structures | C6: Commercial | D6: Businesses and governments buying equipment for their buildings, directly or through nonresidential construction contractors
A7: 2332A0 | B7: Office and commercial structures | C7: Commercial | D7: Businesses and governments buying equipment for their buildings, directly or through nonresidential construction contractors
A8: 2332D0 | B8: Other nonresidential structures | C8: Commercial | D8: Businesses and governments buying equipment for their buildings, directly or through nonresidential construction contractors
A9: 423100 | B9: Motor vehicle and motor vehicle parts and supplies | C9: Commercial | D9: Businesses and governments buying equipment for their buildings, directly or through nonresidential construction contractors
A10: 423400 | B10: Professional and commercial equipment and supplies | C10: Commercial | D10: Businesses and governments buying equipment for their buildings, directly or through nonresidential construction contractors
A11: 423600 | B11: Household appliances and electrical and electronic goods | C11: Commercial | D11: Businesses and governments buying equipment for their buildings, directly or through nonresidential construction contractors
A12: 423800 | B12: Machinery, equipment, and supplies | C12: Commercial | D12: Businesses and governments buying equipment for their buildings, directly or through nonresidential construction contractors
A13: 423A00 | B13: Other durable goods merchant wholesalers | C13: Commercial | D13: Businesses and governments buying equipment for their buildings, directly or through nonresidential construction contractors
A14: 424200 | B14: Drugs and druggists' sundries | C14: Commercial | D14: Businesses and governments buying equipment for their buildings, directly or through nonresidential construction contractors
... A396: F02R00 | B396: Residential private fixed investment | C396: Residential | D396: Households, landlords, owner- and tenant-occupied housing, and residential construction contractors

Sheet Margin Calcs
A1: Markups on equipment: how much of the equipment price goes to the maker, to freight, and to wholesale and retail trade
A2: Each row adds up BEA's 2017 purchases of the listed commodities by one group of buyers. The three share columns (L-N) are what the Cost Breakdowns tab uses.
A4: Component | B4: Buyer group | C4: BEA commodity 1 | D4: BEA commodity 2 | E4: BEA commodity 3 | F4: Producers' value ($M) | G4: Freight ($M) | H4: Wholesale margin ($M) | I4: Retail margin ($M) | J4: Bought directly ($M purchasers value) | K4: Bought through contractors ($M purchasers value) | L4: MANUFACTURER'S SHARE | M4: FREIGHT SHARE (to ISIC 49) | N4: WHOLESALE + RETAIL SHARE (to ISIC 45T47) | O4: Share bought through contractors
A5: Heating | B5: Residential | C5: 333415 | D5: 333414 | F5: =IF($C5="",0,SUMIFS('BEA 2017 Margins'!$E$7:$E$1074,'BEA 2017 Margins'!$C$7:$C$1074,$C5,'BEA 2017 Margins'!$J$7:$J$1074,$B5))+IF($D5="",0,SUMIFS('BEA 2017 Margins'!$E$7:$E$1074,'BEA 2017 Margins'!$C$7:$C$1074,$D5,'BEA 2017 Margins'!$J$7:$J$1074,$B5))+IF($E5="",0,SUMIFS('BEA 2017 Margins'!$E$7:$E$1074,'BEA 2017 Margins'!$C$7:$C$1074,$E5,'BEA 2017 Margins'!$J$7:$J$1074,$B5)) -> 8630 | G5: =IF($C5="",0,SUMIFS('BEA 2017 Margins'!$F$7:$F$1074,'BEA 2017 Margins'!$C$7:$C$1074,$C5,'BEA 2017 Margins'!$J$7:$J$1074,$B5))+IF($D5="",0,SUMIFS('BEA 2017 Margins'!$F$7:$F$1074,'BEA 2017 Margins'!$C$7:$C$1074,$D5,'BEA 2017 Margins'!$J$7:$J$1074,$B5))+IF($E5="",0,SUMIFS('BEA 2017 Margins'!$F$7:$F$1074,'BEA 2017 Margins'!$C$7:$C$1074,$E5,'BEA 2017 Margins'!$J$7:$J$1074,$B5)) -> 253 | H5: =IF($C5="",0,SUMIFS('BEA 2017 Margins'!$G$7:$G$1074,'BEA 2017 Margins'!$C$7:$C$1074,$C5,'BEA 2017 Margins'!$J$7:$J$1074,$B5))+IF($D5="",0,SUMIFS('BEA 2017 Margins'!$G$7:$G$1074,'BEA 2017 Margins'!$C$7:$C$1074,$D5,'BEA 2017 Margins'!$J$7:$J$1074,$B5))+IF($E5="",0,SUMIFS('BEA 2017 Margins'!$G$7:$G$1074,'BEA 2017 Margins'!$C$7:$C$1074,$E5,'BEA 2017 Margins'!$J$7:$J$1074,$B5)) -> 2992 | I5: =IF($C5="",0,SUMIFS('BEA 2017 Margins'!$H$7:$H$1074,'BEA 2017 Margins'!$C$7:$C$1074,$C5,'BEA 2017 Margins'!$J$7:$J$1074,$B5))+IF($D5="",0,SUMIFS('BEA 2017 Margins'!$H$7:$H$1074,'BEA 2017 Margins'!$C$7:$C$1074,$D5,'BEA 2017 Margins'!$J$7:$J$1074,$B5))+IF($E5="",0,SUMIFS('BEA 2017 Margins'!$H$7:$H$1074,'BEA 2017 Margins'!$C$7:$C$1074,$E5,'BEA 2017 Margins'!$J$7:$J$1074,$B5)) -> 6420 | J5: =IF($C5="",0,SUMIFS('BEA 2017 Margins'!$I$7:$I$1074,'BEA 2017 Margins'!$C$7:$C$1074,$C5,'BEA 2017 Margins'!$J$7:$J$1074,$B5,'BEA 2017 Margins'!$K$7:$K$1074,"Direct"))+IF($D5="",0,SUMIFS('BEA 2017 Margins'!$I$7:$I$1074,'BEA 2017 Margins'!$C$7:$C$1074,$D5,'BEA 2017 Margins'!$J$7:$J$1074,$B5,'BEA 2017 Margins'!$K$7:$K$1074,"Direct"))+IF($E5="",0,SUMIFS('BEA 2017 Margins'!$I$7:$I$1074,'BEA 2017 Margins'!$C$7:$C$1074,$E5,'BEA 2017 Margins'!$J$7:$J$1074,$B5,'BEA 2017 Margins'!$K$7:$K$1074,"Direct")) -> 8170 | K5: =IF($C5="",0,SUMIFS('BEA 2017 Margins'!$I$7:$I$1074,'BEA 2017 Margins'!$C$7:$C$1074,$C5,'BEA 2017 Margins'!$J$7:$J$1074,$B5,'BEA 2017 Margins'!$K$7:$K$1074,"Contractor"))+IF($D5="",0,SUMIFS('BEA 2017 Margins'!$I$7:$I$1074,'BEA 2017 Margins'!$C$7:$C$1074,$D5,'BEA 2017 Margins'!$J$7:$J$1074,$B5,'BEA 2017 Margins'!$K$7:$K$1074,"Contractor"))+IF($E5="",0,SUMIFS('BEA 2017 Margins'!$I$7:$I$1074,'BEA 2017 Margins'!$C$7:$C$1074,$E5,'BEA 2017 Margins'!$J$7:$J$1074,$B5,'BEA 2017 Margins'!$K$7:$K$1074,"Contractor")) -> 10126 | L5: =F5/SUM(F5:I5) -> 0.47171358 | M5: =G5/SUM(F5:I5) -> 0.013828915 | N5: =(H5+I5)/SUM(F5:I5) -> 0.5144575 | O5: =K5/(J5+K5) -> 0.55345431
A6: Heating | B6: Commercial | C6: 333415 | D6: 333414 | F6: =IF($C6="",0,SUMIFS('BEA 2017 Margins'!$E$7:$E$1074,'BEA 2017 Margins'!$C$7:$C$1074,$C6,'BEA 2017 Margins'!$J$7:$J$1074,$B6))+IF($D6="",0,SUMIFS('BEA 2017 Margins'!$E$7:$E$1074,'BEA 2017 Margins'!$C$7:$C$1074,$D6,'BEA 2017 Margins'!$J$7:$J$1074,$B6))+IF($E6="",0,SUMIFS('BEA 2017 Margins'!$E$7:$E$1074,'BEA 2017 Margins'!$C$7:$C$1074,$E6,'BEA 2017 Margins'!$J$7:$J$1074,$B6)) -> 26941 | G6: =IF($C6="",0,SUMIFS('BEA 2017 Margins'!$F$7:$F$1074,'BEA 2017 Margins'!$C$7:$C$1074,$C6,'BEA 2017 Margins'!$J$7:$J$1074,$B6))+IF($D6="",0,SUMIFS('BEA 2017 Margins'!$F$7:$F$1074,'BEA 2017 Margins'!$C$7:$C$1074,$D6,'BEA 2017 Margins'!$J$7:$J$1074,$B6))+IF($E6="",0,SUMIFS('BEA 2017 Margins'!$F$7:$F$1074,'BEA 2017 Margins'!$C$7:$C$1074,$E6,'BEA 2017 Margins'!$J$7:$J$1074,$B6)) -> 773 | H6: =IF($C6="",0,SUMIFS('BEA 2017 Margins'!$G$7:$G$1074,'BEA 2017 Margins'!$C$7:$C$1074,$C6,'BEA 2017 Margins'!$J$7:$J$1074,$B6))+IF($D6="",0,SUMIFS('BEA 2017 Margins'!$G$7:$G$1074,'BEA 2017 Margins'!$C$7:$C$1074,$D6,'BEA 2017 Margins'!$J$7:$J$1074,$B6))+IF($E6="",0,SUMIFS('BEA 2017 Margins'!$G$7:$G$1074,'BEA 2017 Margins'!$C$7:$C$1074,$E6,'BEA 2017 Margins'!$J$7:$J$1074,$B6)) -> 9815 | I6: =IF($C6="",0,SUMIFS('BEA 2017 Margins'!$H$7:$H$1074,'BEA 2017 Margins'!$C$7:$C$1074,$C6,'BEA 2017 Margins'!$J$7:$J$1074,$B6))+IF($D6="",0,SUMIFS('BEA 2017 Margins'!$H$7:$H$1074,'BEA 2017 Margins'!$C$7:$C$1074,$D6,'BEA 2017 Margins'!$J$7:$J$1074,$B6))+IF($E6="",0,SUMIFS('BEA 2017 Margins'!$H$7:$H$1074,'BEA 2017 Margins'!$C$7:$C$1074,$E6,'BEA 2017 Margins'!$J$7:$J$1074,$B6)) -> 1972 | J6: =IF($C6="",0,SUMIFS('BEA 2017 Margins'!$I$7:$I$1074,'BEA 2017 Margins'!$C$7:$C$1074,$C6,'BEA 2017 Margins'!$J$7:$J$1074,$B6,'BEA 2017 Margins'!$K$7:$K$1074,"Direct"))+IF($D6="",0,SUMIFS('BEA 2017 Margins'!$I$7:$I$1074,'BEA 2017 Margins'!$C$7:$C$1074,$D6,'BEA 2017 Margins'!$J$7:$J$1074,$B6,'BEA 2017 Margins'!$K$7:$K$1074,"Direct"))+IF($E6="",0,SUMIFS('BEA 2017 Margins'!$I$7:$I$1074,'BEA 2017 Margins'!$C$7:$C$1074,$E6,'BEA 2017 Margins'!$J$7:$J$1074,$B6,'BEA 2017 Margins'!$K$7:$K$1074,"Direct")) -> 28192 | K6: =IF($C6="",0,SUMIFS('BEA 2017 Margins'!$I$7:$I$1074,'BEA 2017 Margins'!$C$7:$C$1074,$C6,'BEA 2017 Margins'!$J$7:$J$1074,$B6,'BEA 2017 Margins'!$K$7:$K$1074,"Contractor"))+IF($D6="",0,SUMIFS('BEA 2017 Margins'!$I$7:$I$1074,'BEA 2017 Margins'!$C$7:$C$1074,$D6,'BEA 2017 Margins'!$J$7:$J$1074,$B6,'BEA 2017 Margins'!$K$7:$K$1074,"Contractor"))+IF($E6="",0,SUMIFS('BEA 2017 Margins'!$I$7:$I$1074,'BEA 2017 Margins'!$C$7:$C$1074,$E6,'BEA 2017 Margins'!$J$7:$J$1074,$B6,'BEA 2017 Margins'!$K$7:$K$1074,"Contractor")) -> 11320 | L6: =F6/SUM(F6:I6) -> 0.68203337 | M6: =G6/SUM(F6:I6) -> 0.019569125 | N6: =(H6+I6)/SUM(F6:I6) -> 0.29839751 | O6: =K6/(J6+K6) -> 0.28649524
A7: Cooling | B7: Residential | C7: 333415 | F7: =IF($C7="",0,SUMIFS('BEA 2017 Margins'!$E$7:$E$1074,'BEA 2017 Margins'!$C$7:$C$1074,$C7,'BEA 2017 Margins'!$J$7:$J$1074,$B7))+IF($D7="",0,SUMIFS('BEA 2017 Margins'!$E$7:$E$1074,'BEA 2017 Margins'!$C$7:$C$1074,$D7,'BEA 2017 Margins'!$J$7:$J$1074,$B7))+IF($E7="",0,SUMIFS('BEA 2017 Margins'!$E$7:$E$1074,'BEA 2017 Margins'!$C$7:$C$1074,$E7,'BEA 2017 Margins'!$J$7:$J$1074,$B7)) -> 6470 | G7: =IF($C7="",0,SUMIFS('BEA 2017 Margins'!$F$7:$F$1074,'BEA 2017 Margins'!$C$7:$C$1074,$C7,'BEA 2017 Margins'!$J$7:$J$1074,$B7))+IF($D7="",0,SUMIFS('BEA 2017 Margins'!$F$7:$F$1074,'BEA 2017 Margins'!$C$7:$C$1074,$D7,'BEA 2017 Margins'!$J$7:$J$1074,$B7))+IF($E7="",0,SUMIFS('BEA 2017 Margins'!$F$7:$F$1074,'BEA 2017 Margins'!$C$7:$C$1074,$E7,'BEA 2017 Margins'!$J$7:$J$1074,$B7)) -> 188 | H7: =IF($C7="",0,SUMIFS('BEA 2017 Margins'!$G$7:$G$1074,'BEA 2017 Margins'!$C$7:$C$1074,$C7,'BEA 2017 Margins'!$J$7:$J$1074,$B7))+IF($D7="",0,SUMIFS('BEA 2017 Margins'!$G$7:$G$1074,'BEA 2017 Margins'!$C$7:$C$1074,$D7,'BEA 2017 Margins'!$J$7:$J$1074,$B7))+IF($E7="",0,SUMIFS('BEA 2017 Margins'!$G$7:$G$1074,'BEA 2017 Margins'!$C$7:$C$1074,$E7,'BEA 2017 Margins'!$J$7:$J$1074,$B7)) -> 2016 | I7: =IF($C7="",0,SUMIFS('BEA 2017 Margins'!$H$7:$H$1074,'BEA 2017 Margins'!$C$7:$C$1074,$C7,'BEA 2017 Margins'!$J$7:$J$1074,$B7))+IF($D7="",0,SUMIFS('BEA 2017 Margins'!$H$7:$H$1074,'BEA 2017 Margins'!$C$7:$C$1074,$D7,'BEA 2017 Margins'!$J$7:$J$1074,$B7))+IF($E7="",0,SUMIFS('BEA 2017 Margins'!$H$7:$H$1074,'BEA 2017 Margins'!$C$7:$C$1074,$E7,'BEA 2017 Margins'!$J$7:$J$1074,$B7)) -> 5046 | J7: =IF($C7="",0,SUMIFS('BEA 2017 Margins'!$I$7:$I$1074,'BEA 2017 Margins'!$C$7:$C$1074,$C7,'BEA 2017 Margins'!$J$7:$J$1074,$B7,'BEA 2017 Margins'!$K$7:$K$1074,"Direct"))+IF($D7="",0,SUMIFS('BEA 2017 Margins'!$I$7:$I$1074,'BEA 2017 Margins'!$C$7:$C$1074,$D7,'BEA 2017 Margins'!$J$7:$J$1074,$B7,'BEA 2017 Margins'!$K$7:$K$1074,"Direct"))+IF($E7="",0,SUMIFS('BEA 2017 Margins'!$I$7:$I$1074,'BEA 2017 Margins'!$C$7:$C$1074,$E7,'BEA 2017 Margins'!$J$7:$J$1074,$B7,'BEA 2017 Margins'!$K$7:$K$1074,"Direct")) -> 5642 | K7: =IF($C7="",0,SUMIFS('BEA 2017 Margins'!$I$7:$I$1074,'BEA 2017 Margins'!$C$7:$C$1074,$C7,'BEA 2017 Margins'!$J$7:$J$1074,$B7,'BEA 2017 Margins'!$K$7:$K$1074,"Contractor"))+IF($D7="",0,SUMIFS('BEA 2017 Margins'!$I$7:$I$1074,'BEA 2017 Margins'!$C$7:$C$1074,$D7,'BEA 2017 Margins'!$J$7:$J$1074,$B7,'BEA 2017 Margins'!$K$7:$K$1074,"Contractor"))+IF($E7="",0,SUMIFS('BEA 2017 Margins'!$I$7:$I$1074,'BEA 2017 Margins'!$C$7:$C$1074,$E7,'BEA 2017 Margins'!$J$7:$J$1074,$B7,'BEA 2017 Margins'!$K$7:$K$1074,"Contractor")) -> 8081 | L7: =F7/SUM(F7:I7) -> 0.47157434 | M7: =G7/SUM(F7:I7) -> 0.013702624 | N7: =(H7+I7)/SUM(F7:I7) -> 0.51472303 | O7: =K7/(J7+K7) -> 0.58886541
A8: Cooling | B8: Commercial | C8: 333415 | F8: =IF($C8="",0,SUMIFS('BEA 2017 Margins'!$E$7:$E$1074,'BEA 2017 Margins'!$C$7:$C$1074,$C8,'BEA 2017 Margins'!$J$7:$J$1074,$B8))+IF($D8="",0,SUMIFS('BEA 2017 Margins'!$E$7:$E$1074,'BEA 2017 Margins'!$C$7:$C$1074,$D8,'BEA 2017 Margins'!$J$7:$J$1074,$B8))+IF($E8="",0,SUMIFS('BEA 2017 Margins'!$E$7:$E$1074,'BEA 2017 Margins'!$C$7:$C$1074,$E8,'BEA 2017 Margins'!$J$7:$J$1074,$B8)) -> 24838 | G8: =IF($C8="",0,SUMIFS('BEA 2017 Margins'!$F$7:$F$1074,'BEA 2017 Margins'!$C$7:$C$1074,$C8,'BEA 2017 Margins'!$J$7:$J$1074,$B8))+IF($D8="",0,SUMIFS('BEA 2017 Margins'!$F$7:$F$1074,'BEA 2017 Margins'!$C$7:$C$1074,$D8,'BEA 2017 Margins'!$J$7:$J$1074,$B8))+IF($E8="",0,SUMIFS('BEA 2017 Margins'!$F$7:$F$1074,'BEA 2017 Margins'!$C$7:$C$1074,$E8,'BEA 2017 Margins'!$J$7:$J$1074,$B8)) -> 711 | H8: =IF($C8="",0,SUMIFS('BEA 2017 Margins'!$G$7:$G$1074,'BEA 2017 Margins'!$C$7:$C$1074,$C8,'BEA 2017 Margins'!$J$7:$J$1074,$B8))+IF($D8="",0,SUMIFS('BEA 2017 Margins'!$G$7:$G$1074,'BEA 2017 Margins'!$C$7:$C$1074,$D8,'BEA 2017 Margins'!$J$7:$J$1074,$B8))+IF($E8="",0,SUMIFS('BEA 2017 Margins'!$G$7:$G$1074,'BEA 2017 Margins'!$C$7:$C$1074,$E8,'BEA 2017 Margins'!$J$7:$J$1074,$B8)) -> 8866 | I8: =IF($C8="",0,SUMIFS('BEA 2017 Margins'!$H$7:$H$1074,'BEA 2017 Margins'!$C$7:$C$1074,$C8,'BEA 2017 Margins'!$J$7:$J$1074,$B8))+IF($D8="",0,SUMIFS('BEA 2017 Margins'!$H$7:$H$1074,'BEA 2017 Margins'!$C$7:$C$1074,$D8,'BEA 2017 Margins'!$J$7:$J$1074,$B8))+IF($E8="",0,SUMIFS('BEA 2017 Margins'!$H$7:$H$1074,'BEA 2017 Margins'!$C$7:$C$1074,$E8,'BEA 2017 Margins'!$J$7:$J$1074,$B8)) -> 1749 | J8: =IF($C8="",0,SUMIFS('BEA 2017 Margins'!$I$7:$I$1074,'BEA 2017 Margins'!$C$7:$C$1074,$C8,'BEA 2017 Margins'!$J$7:$J$1074,$B8,'BEA 2017 Margins'!$K$7:$K$1074,"Direct"))+IF($D8="",0,SUMIFS('BEA 2017 Margins'!$I$7:$I$1074,'BEA 2017 Margins'!$C$7:$C$1074,$D8,'BEA 2017 Margins'!$J$7:$J$1074,$B8,'BEA 2017 Margins'!$K$7:$K$1074,"Direct"))+IF($E8="",0,SUMIFS('BEA 2017 Margins'!$I$7:$I$1074,'BEA 2017 Margins'!$C$7:$C$1074,$E8,'BEA 2017 Margins'!$J$7:$J$1074,$B8,'BEA 2017 Margins'!$K$7:$K$1074,"Direct")) -> 27004 | K8: =IF($C8="",0,SUMIFS('BEA 2017 Margins'!$I$7:$I$1074,'BEA 2017 Margins'!$C$7:$C$1074,$C8,'BEA 2017 Margins'!$J$7:$J$1074,$B8,'BEA 2017 Margins'!$K$7:$K$1074,"Contractor"))+IF($D8="",0,SUMIFS('BEA 2017 Margins'!$I$7:$I$1074,'BEA 2017 Margins'!$C$7:$C$1074,$D8,'BEA 2017 Margins'!$J$7:$J$1074,$B8,'BEA 2017 Margins'!$K$7:$K$1074,"Contractor"))+IF($E8="",0,SUMIFS('BEA 2017 Margins'!$I$7:$I$1074,'BEA 2017 Margins'!$C$7:$C$1074,$E8,'BEA 2017 Margins'!$J$7:$J$1074,$B8,'BEA 2017 Margins'!$K$7:$K$1074,"Contractor")) -> 9172 | L8: =F8/SUM(F8:I8) -> 0.68681562 | M8: =G8/SUM(F8:I8) -> 0.019660436 | N8: =(H8+I8)/SUM(F8:I8) -> 0.29352395 | O8: =K8/(J8+K8) -> 0.25353826
A9: Lighting | B9: Residential | C9: 335110 | D9: 335120 | F9: =IF($C9="",0,SUMIFS('BEA 2017 Margins'!$E$7:$E$1074,'BEA 2017 Margins'!$C$7:$C$1074,$C9,'BEA 2017 Margins'!$J$7:$J$1074,$B9))+IF($D9="",0,SUMIFS('BEA 2017 Margins'!$E$7:$E$1074,'BEA 2017 Margins'!$C$7:$C$1074,$D9,'BEA 2017 Margins'!$J$7:$J$1074,$B9))+IF($E9="",0,SUMIFS('BEA 2017 Margins'!$E$7:$E$1074,'BEA 2017 Margins'!$C$7:$C$1074,$E9,'BEA 2017 Margins'!$J$7:$J$1074,$B9)) -> 5373 | G9: =IF($C9="",0,SUMIFS('BEA 2017 Margins'!$F$7:$F$1074,'BEA 2017 Margins'!$C$7:$C$1074,$C9,'BEA 2017 Margins'!$J$7:$J$1074,$B9))+IF($D9="",0,SUMIFS('BEA 2017 Margins'!$F$7:$F$1074,'BEA 2017 Margins'!$C$7:$C$1074,$D9,'BEA 2017 Margins'!$J$7:$J$1074,$B9))+IF($E9="",0,SUMIFS('BEA 2017 Margins'!$F$7:$F$1074,'BEA 2017 Margins'!$C$7:$C$1074,$E9,'BEA 2017 Margins'!$J$7:$J$1074,$B9)) -> 604 | H9: =IF($C9="",0,SUMIFS('BEA 2017 Margins'!$G$7:$G$1074,'BEA 2017 Margins'!$C$7:$C$1074,$C9,'BEA 2017 Margins'!$J$7:$J$1074,$B9))+IF($D9="",0,SUMIFS('BEA 2017 Margins'!$G$7:$G$1074,'BEA 2017 Margins'!$C$7:$C$1074,$D9,'BEA 2017 Margins'!$J$7:$J$1074,$B9))+IF($E9="",0,SUMIFS('BEA 2017 Margins'!$G$7:$G$1074,'BEA 2017 Margins'!$C$7:$C$1074,$E9,'BEA 2017 Margins'!$J$7:$J$1074,$B9)) -> 1687 | I9: =IF($C9="",0,SUMIFS('BEA 2017 Margins'!$H$7:$H$1074,'BEA 2017 Margins'!$C$7:$C$1074,$C9,'BEA 2017 Margins'!$J$7:$J$1074,$B9))+IF($D9="",0,SUMIFS('BEA 2017 Margins'!$H$7:$H$1074,'BEA 2017 Margins'!$C$7:$C$1074,$D9,'BEA 2017 Margins'!$J$7:$J$1074,$B9))+IF($E9="",0,SUMIFS('BEA 2017 Margins'!$H$7:$H$1074,'BEA 2017 Margins'!$C$7:$C$1074,$E9,'BEA 2017 Margins'!$J$7:$J$1074,$B9)) -> 5769 | J9: =IF($C9="",0,SUMIFS('BEA 2017 Margins'!$I$7:$I$1074,'BEA 2017 Margins'!$C$7:$C$1074,$C9,'BEA 2017 Margins'!$J$7:$J$1074,$B9,'BEA 2017 Margins'!$K$7:$K$1074,"Direct"))+IF($D9="",0,SUMIFS('BEA 2017 Margins'!$I$7:$I$1074,'BEA 2017 Margins'!$C$7:$C$1074,$D9,'BEA 2017 Margins'!$J$7:$J$1074,$B9,'BEA 2017 Margins'!$K$7:$K$1074,"Direct"))+IF($E9="",0,SUMIFS('BEA 2017 Margins'!$I$7:$I$1074,'BEA 2017 Margins'!$C$7:$C$1074,$E9,'BEA 2017 Margins'!$J$7:$J$1074,$B9,'BEA 2017 Margins'!$K$7:$K$1074,"Direct")) -> 8642 | K9: =IF($C9="",0,SUMIFS('BEA 2017 Margins'!$I$7:$I$1074,'BEA 2017 Margins'!$C$7:$C$1074,$C9,'BEA 2017 Margins'!$J$7:$J$1074,$B9,'BEA 2017 Margins'!$K$7:$K$1074,"Contractor"))+IF($D9="",0,SUMIFS('BEA 2017 Margins'!$I$7:$I$1074,'BEA 2017 Margins'!$C$7:$C$1074,$D9,'BEA 2017 Margins'!$J$7:$J$1074,$B9,'BEA 2017 Margins'!$K$7:$K$1074,"Contractor"))+IF($E9="",0,SUMIFS('BEA 2017 Margins'!$I$7:$I$1074,'BEA 2017 Margins'!$C$7:$C$1074,$E9,'BEA 2017 Margins'!$J$7:$J$1074,$B9,'BEA 2017 Margins'!$K$7:$K$1074,"Contractor")) -> 4790 | L9: =F9/SUM(F9:I9) -> 0.39998511 | M9: =G9/SUM(F9:I9) -> 0.044963895 | N9: =(H9+I9)/SUM(F9:I9) -> 0.55505099 | O9: =K9/(J9+K9) -> 0.35661108
A10: Lighting | B10: Commercial | C10: 335110 | D10: 335120 | F10: =IF($C10="",0,SUMIFS('BEA 2017 Margins'!$E$7:$E$1074,'BEA 2017 Margins'!$C$7:$C$1074,$C10,'BEA 2017 Margins'!$J$7:$J$1074,$B10))+IF($D10="",0,SUMIFS('BEA 2017 Margins'!$E$7:$E$1074,'BEA 2017 Margins'!$C$7:$C$1074,$D10,'BEA 2017 Margins'!$J$7:$J$1074,$B10))+IF($E10="",0,SUMIFS('BEA 2017 Margins'!$E$7:$E$1074,'BEA 2017 Margins'!$C$7:$C$1074,$E10,'BEA 2017 Margins'!$J$7:$J$1074,$B10)) -> 17243 | G10: =IF($C10="",0,SUMIFS('BEA 2017 Margins'!$F$7:$F$1074,'BEA 2017 Margins'!$C$7:$C$1074,$C10,'BEA 2017 Margins'!$J$7:$J$1074,$B10))+IF($D10="",0,SUMIFS('BEA 2017 Margins'!$F$7:$F$1074,'BEA 2017 Margins'!$C$7:$C$1074,$D10,'BEA 2017 Margins'!$J$7:$J$1074,$B10))+IF($E10="",0,SUMIFS('BEA 2017 Margins'!$F$7:$F$1074,'BEA 2017 Margins'!$C$7:$C$1074,$E10,'BEA 2017 Margins'!$J$7:$J$1074,$B10)) -> 2078 | H10: =IF($C10="",0,SUMIFS('BEA 2017 Margins'!$G$7:$G$1074,'BEA 2017 Margins'!$C$7:$C$1074,$C10,'BEA 2017 Margins'!$J$7:$J$1074,$B10))+IF($D10="",0,SUMIFS('BEA 2017 Margins'!$G$7:$G$1074,'BEA 2017 Margins'!$C$7:$C$1074,$D10,'BEA 2017 Margins'!$J$7:$J$1074,$B10))+IF($E10="",0,SUMIFS('BEA 2017 Margins'!$G$7:$G$1074,'BEA 2017 Margins'!$C$7:$C$1074,$E10,'BEA 2017 Margins'!$J$7:$J$1074,$B10)) -> 5408 | I10: =IF($C10="",0,SUMIFS('BEA 2017 Margins'!$H$7:$H$1074,'BEA 2017 Margins'!$C$7:$C$1074,$C10,'BEA 2017 Margins'!$J$7:$J$1074,$B10))+IF($D10="",0,SUMIFS('BEA 2017 Margins'!$H$7:$H$1074,'BEA 2017 Margins'!$C$7:$C$1074,$D10,'BEA 2017 Margins'!$J$7:$J$1074,$B10))+IF($E10="",0,SUMIFS('BEA 2017 Margins'!$H$7:$H$1074,'BEA 2017 Margins'!$C$7:$C$1074,$E10,'BEA 2017 Margins'!$J$7:$J$1074,$B10)) -> 164 | J10: =IF($C10="",0,SUMIFS('BEA 2017 Margins'!$I$7:$I$1074,'BEA 2017 Margins'!$C$7:$C$1074,$C10,'BEA 2017 Margins'!$J$7:$J$1074,$B10,'BEA 2017 Margins'!$K$7:$K$1074,"Direct"))+IF($D10="",0,SUMIFS('BEA 2017 Margins'!$I$7:$I$1074,'BEA 2017 Margins'!$C$7:$C$1074,$D10,'BEA 2017 Margins'!$J$7:$J$1074,$B10,'BEA 2017 Margins'!$K$7:$K$1074,"Direct"))+IF($E10="",0,SUMIFS('BEA 2017 Margins'!$I$7:$I$1074,'BEA 2017 Margins'!$C$7:$C$1074,$E10,'BEA 2017 Margins'!$J$7:$J$1074,$B10,'BEA 2017 Margins'!$K$7:$K$1074,"Direct")) -> 15658 | K10: =IF($C10="",0,SUMIFS('BEA 2017 Margins'!$I$7:$I$1074,'BEA 2017 Margins'!$C$7:$C$1074,$C10,'BEA 2017 Margins'!$J$7:$J$1074,$B10,'BEA 2017 Margins'!$K$7:$K$1074,"Contractor"))+IF($D10="",0,SUMIFS('BEA 2017 Margins'!$I$7:$I$1074,'BEA 2017 Margins'!$C$7:$C$1074,$D10,'BEA 2017 Margins'!$J$7:$J$1074,$B10,'BEA 2017 Margins'!$K$7:$K$1074,"Contractor"))+IF($E10="",0,SUMIFS('BEA 2017 Margins'!$I$7:$I$1074,'BEA 2017 Margins'!$C$7:$C$1074,$E10,'BEA 2017 Margins'!$J$7:$J$1074,$B10,'BEA 2017 Margins'!$K$7:$K$1074,"Contractor")) -> 9244 | L10: =F10/SUM(F10:I10) -> 0.69268469 | M10: =G10/SUM(F10:I10) -> 0.083477283 | N10: =(H10+I10)/SUM(F10:I10) -> 0.22383803 | O10: =K10/(J10+K10) -> 0.37121516
A11: Appliances | B11: Residential | C11: 335220 | F11: =IF($C11="",0,SUMIFS('BEA 2017 Margins'!$E$7:$E$1074,'BEA 2017 Margins'!$C$7:$C$1074,$C11,'BEA 2017 Margins'!$J$7:$J$1074,$B11))+IF($D11="",0,SUMIFS('BEA 2017 Margins'!$E$7:$E$1074,'BEA 2017 Margins'!$C$7:$C$1074,$D11,'BEA 2017 Margins'!$J$7:$J$1074,$B11))+IF($E11="",0,SUMIFS('BEA 2017 Margins'!$E$7:$E$1074,'BEA 2017 Margins'!$C$7:$C$1074,$E11,'BEA 2017 Margins'!$J$7:$J$1074,$B11)) -> 30079 | G11: =IF($C11="",0,SUMIFS('BEA 2017 Margins'!$F$7:$F$1074,'BEA 2017 Margins'!$C$7:$C$1074,$C11,'BEA 2017 Margins'!$J$7:$J$1074,$B11))+IF($D11="",0,SUMIFS('BEA 2017 Margins'!$F$7:$F$1074,'BEA 2017 Margins'!$C$7:$C$1074,$D11,'BEA 2017 Margins'!$J$7:$J$1074,$B11))+IF($E11="",0,SUMIFS('BEA 2017 Margins'!$F$7:$F$1074,'BEA 2017 Margins'!$C$7:$C$1074,$E11,'BEA 2017 Margins'!$J$7:$J$1074,$B11)) -> 430 | H11: =IF($C11="",0,SUMIFS('BEA 2017 Margins'!$G$7:$G$1074,'BEA 2017 Margins'!$C$7:$C$1074,$C11,'BEA 2017 Margins'!$J$7:$J$1074,$B11))+IF($D11="",0,SUMIFS('BEA 2017 Margins'!$G$7:$G$1074,'BEA 2017 Margins'!$C$7:$C$1074,$D11,'BEA 2017 Margins'!$J$7:$J$1074,$B11))+IF($E11="",0,SUMIFS('BEA 2017 Margins'!$G$7:$G$1074,'BEA 2017 Margins'!$C$7:$C$1074,$E11,'BEA 2017 Margins'!$J$7:$J$1074,$B11)) -> 10419 | I11: =IF($C11="",0,SUMIFS('BEA 2017 Margins'!$H$7:$H$1074,'BEA 2017 Margins'!$C$7:$C$1074,$C11,'BEA 2017 Margins'!$J$7:$J$1074,$B11))+IF($D11="",0,SUMIFS('BEA 2017 Margins'!$H$7:$H$1074,'BEA 2017 Margins'!$C$7:$C$1074,$D11,'BEA 2017 Margins'!$J$7:$J$1074,$B11))+IF($E11="",0,SUMIFS('BEA 2017 Margins'!$H$7:$H$1074,'BEA 2017 Margins'!$C$7:$C$1074,$E11,'BEA 2017 Margins'!$J$7:$J$1074,$B11)) -> 13623 | J11: =IF($C11="",0,SUMIFS('BEA 2017 Margins'!$I$7:$I$1074,'BEA 2017 Margins'!$C$7:$C$1074,$C11,'BEA 2017 Margins'!$J$7:$J$1074,$B11,'BEA 2017 Margins'!$K$7:$K$1074,"Direct"))+IF($D11="",0,SUMIFS('BEA 2017 Margins'!$I$7:$I$1074,'BEA 2017 Margins'!$C$7:$C$1074,$D11,'BEA 2017 Margins'!$J$7:$J$1074,$B11,'BEA 2017 Margins'!$K$7:$K$1074,"Direct"))+IF($E11="",0,SUMIFS('BEA 2017 Margins'!$I$7:$I$1074,'BEA 2017 Margins'!$C$7:$C$1074,$E11,'BEA 2017 Margins'!$J$7:$J$1074,$B11,'BEA 2017 Margins'!$K$7:$K$1074,"Direct")) -> 50276 | K11: =IF($C11="",0,SUMIFS('BEA 2017 Margins'!$I$7:$I$1074,'BEA 2017 Margins'!$C$7:$C$1074,$C11,'BEA 2017 Margins'!$J$7:$J$1074,$B11,'BEA 2017 Margins'!$K$7:$K$1074,"Contractor"))+IF($D11="",0,SUMIFS('BEA 2017 Margins'!$I$7:$I$1074,'BEA 2017 Margins'!$C$7:$C$1074,$D11,'BEA 2017 Margins'!$J$7:$J$1074,$B11,'BEA 2017 Margins'!$K$7:$K$1074,"Contractor"))+IF($E11="",0,SUMIFS('BEA 2017 Margins'!$I$7:$I$1074,'BEA 2017 Margins'!$C$7:$C$1074,$E11,'BEA 2017 Margins'!$J$7:$J$1074,$B11,'BEA 2017 Margins'!$K$7:$K$1074,"Contractor")) -> 4273 | L11: =F11/SUM(F11:I11) -> 0.55139228 | M11: =G11/SUM(F11:I11) -> 0.0078825319 | N11: =(H11+I11)/SUM(F11:I11) -> 0.44072519 | O11: =K11/(J11+K11) -> 0.078333242
A12: Appliances | B12: Commercial | C12: 335220 | D12: 333318 | F12: =IF($C12="",0,SUMIFS('BEA 2017 Margins'!$E$7:$E$1074,'BEA 2017 Margins'!$C$7:$C$1074,$C12,'BEA 2017 Margins'!$J$7:$J$1074,$B12))+IF($D12="",0,SUMIFS('BEA 2017 Margins'!$E$7:$E$1074,'BEA 2017 Margins'!$C$7:$C$1074,$D12,'BEA 2017 Margins'!$J$7:$J$1074,$B12))+IF($E12="",0,SUMIFS('BEA 2017 Margins'!$E$7:$E$1074,'BEA 2017 Margins'!$C$7:$C$1074,$E12,'BEA 2017 Margins'!$J$7:$J$1074,$B12)) -> 23982 | G12: =IF($C12="",0,SUMIFS('BEA 2017 Margins'!$F$7:$F$1074,'BEA 2017 Margins'!$C$7:$C$1074,$C12,'BEA 2017 Margins'!$J$7:$J$1074,$B12))+IF($D12="",0,SUMIFS('BEA 2017 Margins'!$F$7:$F$1074,'BEA 2017 Margins'!$C$7:$C$1074,$D12,'BEA 2017 Margins'!$J$7:$J$1074,$B12))+IF($E12="",0,SUMIFS('BEA 2017 Margins'!$F$7:$F$1074,'BEA 2017 Margins'!$C$7:$C$1074,$E12,'BEA 2017 Margins'!$J$7:$J$1074,$B12)) -> 663 | H12: =IF($C12="",0,SUMIFS('BEA 2017 Margins'!$G$7:$G$1074,'BEA 2017 Margins'!$C$7:$C$1074,$C12,'BEA 2017 Margins'!$J$7:$J$1074,$B12))+IF($D12="",0,SUMIFS('BEA 2017 Margins'!$G$7:$G$1074,'BEA 2017 Margins'!$C$7:$C$1074,$D12,'BEA 2017 Margins'!$J$7:$J$1074,$B12))+IF($E12="",0,SUMIFS('BEA 2017 Margins'!$G$7:$G$1074,'BEA 2017 Margins'!$C$7:$C$1074,$E12,'BEA 2017 Margins'!$J$7:$J$1074,$B12)) -> 8869 | I12: =IF($C12="",0,SUMIFS('BEA 2017 Margins'!$H$7:$H$1074,'BEA 2017 Margins'!$C$7:$C$1074,$C12,'BEA 2017 Margins'!$J$7:$J$1074,$B12))+IF($D12="",0,SUMIFS('BEA 2017 Margins'!$H$7:$H$1074,'BEA 2017 Margins'!$C$7:$C$1074,$D12,'BEA 2017 Margins'!$J$7:$J$1074,$B12))+IF($E12="",0,SUMIFS('BEA 2017 Margins'!$H$7:$H$1074,'BEA 2017 Margins'!$C$7:$C$1074,$E12,'BEA 2017 Margins'!$J$7:$J$1074,$B12)) -> 1744 | J12: =IF($C12="",0,SUMIFS('BEA 2017 Margins'!$I$7:$I$1074,'BEA 2017 Margins'!$C$7:$C$1074,$C12,'BEA 2017 Margins'!$J$7:$J$1074,$B12,'BEA 2017 Margins'!$K$7:$K$1074,"Direct"))+IF($D12="",0,SUMIFS('BEA 2017 Margins'!$I$7:$I$1074,'BEA 2017 Margins'!$C$7:$C$1074,$D12,'BEA 2017 Margins'!$J$7:$J$1074,$B12,'BEA 2017 Margins'!$K$7:$K$1074,"Direct"))+IF($E12="",0,SUMIFS('BEA 2017 Margins'!$I$7:$I$1074,'BEA 2017 Margins'!$C$7:$C$1074,$E12,'BEA 2017 Margins'!$J$7:$J$1074,$B12,'BEA 2017 Margins'!$K$7:$K$1074,"Direct")) -> 31110 | K12: =IF($C12="",0,SUMIFS('BEA 2017 Margins'!$I$7:$I$1074,'BEA 2017 Margins'!$C$7:$C$1074,$C12,'BEA 2017 Margins'!$J$7:$J$1074,$B12,'BEA 2017 Margins'!$K$7:$K$1074,"Contractor"))+IF($D12="",0,SUMIFS('BEA 2017 Margins'!$I$7:$I$1074,'BEA 2017 Margins'!$C$7:$C$1074,$D12,'BEA 2017 Margins'!$J$7:$J$1074,$B12,'BEA 2017 Margins'!$K$7:$K$1074,"Contractor"))+IF($E12="",0,SUMIFS('BEA 2017 Margins'!$I$7:$I$1074,'BEA 2017 Margins'!$C$7:$C$1074,$E12,'BEA 2017 Margins'!$J$7:$J$1074,$B12,'BEA 2017 Margins'!$K$7:$K$1074,"Contractor")) -> 4157 | L12: =F12/SUM(F12:I12) -> 0.68018606 | M12: =G12/SUM(F12:I12) -> 0.018804243 | N12: =(H12+I12)/SUM(F12:I12) -> 0.3010097 | O12: =K12/(J12+K12) -> 0.11787223
A13: Other | B13: Residential | C13: 334111 | D13: 334300 | E13: 335210 | F13: =IF($C13="",0,SUMIFS('BEA 2017 Margins'!$E$7:$E$1074,'BEA 2017 Margins'!$C$7:$C$1074,$C13,'BEA 2017 Margins'!$J$7:$J$1074,$B13))+IF($D13="",0,SUMIFS('BEA 2017 Margins'!$E$7:$E$1074,'BEA 2017 Margins'!$C$7:$C$1074,$D13,'BEA 2017 Margins'!$J$7:$J$1074,$B13))+IF($E13="",0,SUMIFS('BEA 2017 Margins'!$E$7:$E$1074,'BEA 2017 Margins'!$C$7:$C$1074,$E13,'BEA 2017 Margins'!$J$7:$J$1074,$B13)) -> 53093 | G13: =IF($C13="",0,SUMIFS('BEA 2017 Margins'!$F$7:$F$1074,'BEA 2017 Margins'!$C$7:$C$1074,$C13,'BEA 2017 Margins'!$J$7:$J$1074,$B13))+IF($D13="",0,SUMIFS('BEA 2017 Margins'!$F$7:$F$1074,'BEA 2017 Margins'!$C$7:$C$1074,$D13,'BEA 2017 Margins'!$J$7:$J$1074,$B13))+IF($E13="",0,SUMIFS('BEA 2017 Margins'!$F$7:$F$1074,'BEA 2017 Margins'!$C$7:$C$1074,$E13,'BEA 2017 Margins'!$J$7:$J$1074,$B13)) -> 1935 | H13: =IF($C13="",0,SUMIFS('BEA 2017 Margins'!$G$7:$G$1074,'BEA 2017 Margins'!$C$7:$C$1074,$C13,'BEA 2017 Margins'!$J$7:$J$1074,$B13))+IF($D13="",0,SUMIFS('BEA 2017 Margins'!$G$7:$G$1074,'BEA 2017 Margins'!$C$7:$C$1074,$D13,'BEA 2017 Margins'!$J$7:$J$1074,$B13))+IF($E13="",0,SUMIFS('BEA 2017 Margins'!$G$7:$G$1074,'BEA 2017 Margins'!$C$7:$C$1074,$E13,'BEA 2017 Margins'!$J$7:$J$1074,$B13)) -> 16984 | I13: =IF($C13="",0,SUMIFS('BEA 2017 Margins'!$H$7:$H$1074,'BEA 2017 Margins'!$C$7:$C$1074,$C13,'BEA 2017 Margins'!$J$7:$J$1074,$B13))+IF($D13="",0,SUMIFS('BEA 2017 Margins'!$H$7:$H$1074,'BEA 2017 Margins'!$C$7:$C$1074,$D13,'BEA 2017 Margins'!$J$7:$J$1074,$B13))+IF($E13="",0,SUMIFS('BEA 2017 Margins'!$H$7:$H$1074,'BEA 2017 Margins'!$C$7:$C$1074,$E13,'BEA 2017 Margins'!$J$7:$J$1074,$B13)) -> 29537 | J13: =IF($C13="",0,SUMIFS('BEA 2017 Margins'!$I$7:$I$1074,'BEA 2017 Margins'!$C$7:$C$1074,$C13,'BEA 2017 Margins'!$J$7:$J$1074,$B13,'BEA 2017 Margins'!$K$7:$K$1074,"Direct"))+IF($D13="",0,SUMIFS('BEA 2017 Margins'!$I$7:$I$1074,'BEA 2017 Margins'!$C$7:$C$1074,$D13,'BEA 2017 Margins'!$J$7:$J$1074,$B13,'BEA 2017 Margins'!$K$7:$K$1074,"Direct"))+IF($E13="",0,SUMIFS('BEA 2017 Margins'!$I$7:$I$1074,'BEA 2017 Margins'!$C$7:$C$1074,$E13,'BEA 2017 Margins'!$J$7:$J$1074,$B13,'BEA 2017 Margins'!$K$7:$K$1074,"Direct")) -> 99793 | K13: =IF($C13="",0,SUMIFS('BEA 2017 Margins'!$I$7:$I$1074,'BEA 2017 Margins'!$C$7:$C$1074,$C13,'BEA 2017 Margins'!$J$7:$J$1074,$B13,'BEA 2017 Margins'!$K$7:$K$1074,"Contractor"))+IF($D13="",0,SUMIFS('BEA 2017 Margins'!$I$7:$I$1074,'BEA 2017 Margins'!$C$7:$C$1074,$D13,'BEA 2017 Margins'!$J$7:$J$1074,$B13,'BEA 2017 Margins'!$K$7:$K$1074,"Contractor"))+IF($E13="",0,SUMIFS('BEA 2017 Margins'!$I$7:$I$1074,'BEA 2017 Margins'!$C$7:$C$1074,$E13,'BEA 2017 Margins'!$J$7:$J$1074,$B13,'BEA 2017 Margins'!$K$7:$K$1074,"Contractor")) -> 1752 | L13: =F13/SUM(F13:I13) -> 0.52283134 | M13: =G13/SUM(F13:I13) -> 0.019054841 | N13: =(H13+I13)/SUM(F13:I13) -> 0.45811382 | O13: =K13/(J13+K13) -> 0.017253434
A14: Other | B14: Commercial | C14: 334111 | D14: 334300 | E14: 335210 | F14: =IF($C14="",0,SUMIFS('BEA 2017 Margins'!$E$7:$E$1074,'BEA 2017 Margins'!$C$7:$C$1074,$C14,'BEA 2017 Margins'!$J$7:$J$1074,$B14))+IF($D14="",0,SUMIFS('BEA 2017 Margins'!$E$7:$E$1074,'BEA 2017 Margins'!$C$7:$C$1074,$D14,'BEA 2017 Margins'!$J$7:$J$1074,$B14))+IF($E14="",0,SUMIFS('BEA 2017 Margins'!$E$7:$E$1074,'BEA 2017 Margins'!$C$7:$C$1074,$E14,'BEA 2017 Margins'!$J$7:$J$1074,$B14)) -> 48113 | G14: =IF($C14="",0,SUMIFS('BEA 2017 Margins'!$F$7:$F$1074,'BEA 2017 Margins'!$C$7:$C$1074,$C14,'BEA 2017 Margins'!$J$7:$J$1074,$B14))+IF($D14="",0,SUMIFS('BEA 2017 Margins'!$F$7:$F$1074,'BEA 2017 Margins'!$C$7:$C$1074,$D14,'BEA 2017 Margins'!$J$7:$J$1074,$B14))+IF($E14="",0,SUMIFS('BEA 2017 Margins'!$F$7:$F$1074,'BEA 2017 Margins'!$C$7:$C$1074,$E14,'BEA 2017 Margins'!$J$7:$J$1074,$B14)) -> 759 | H14: =IF($C14="",0,SUMIFS('BEA 2017 Margins'!$G$7:$G$1074,'BEA 2017 Margins'!$C$7:$C$1074,$C14,'BEA 2017 Margins'!$J$7:$J$1074,$B14))+IF($D14="",0,SUMIFS('BEA 2017 Margins'!$G$7:$G$1074,'BEA 2017 Margins'!$C$7:$C$1074,$D14,'BEA 2017 Margins'!$J$7:$J$1074,$B14))+IF($E14="",0,SUMIFS('BEA 2017 Margins'!$G$7:$G$1074,'BEA 2017 Margins'!$C$7:$C$1074,$E14,'BEA 2017 Margins'!$J$7:$J$1074,$B14)) -> 13914 | I14: =IF($C14="",0,SUMIFS('BEA 2017 Margins'!$H$7:$H$1074,'BEA 2017 Margins'!$C$7:$C$1074,$C14,'BEA 2017 Margins'!$J$7:$J$1074,$B14))+IF($D14="",0,SUMIFS('BEA 2017 Margins'!$H$7:$H$1074,'BEA 2017 Margins'!$C$7:$C$1074,$D14,'BEA 2017 Margins'!$J$7:$J$1074,$B14))+IF($E14="",0,SUMIFS('BEA 2017 Margins'!$H$7:$H$1074,'BEA 2017 Margins'!$C$7:$C$1074,$E14,'BEA 2017 Margins'!$J$7:$J$1074,$B14)) -> 8185 | J14: =IF($C14="",0,SUMIFS('BEA 2017 Margins'!$I$7:$I$1074,'BEA 2017 Margins'!$C$7:$C$1074,$C14,'BEA 2017 Margins'!$J$7:$J$1074,$B14,'BEA 2017 Margins'!$K$7:$K$1074,"Direct"))+IF($D14="",0,SUMIFS('BEA 2017 Margins'!$I$7:$I$1074,'BEA 2017 Margins'!$C$7:$C$1074,$D14,'BEA 2017 Margins'!$J$7:$J$1074,$B14,'BEA 2017 Margins'!$K$7:$K$1074,"Direct"))+IF($E14="",0,SUMIFS('BEA 2017 Margins'!$I$7:$I$1074,'BEA 2017 Margins'!$C$7:$C$1074,$E14,'BEA 2017 Margins'!$J$7:$J$1074,$B14,'BEA 2017 Margins'!$K$7:$K$1074,"Direct")) -> 68820 | K14: =IF($C14="",0,SUMIFS('BEA 2017 Margins'!$I$7:$I$1074,'BEA 2017 Margins'!$C$7:$C$1074,$C14,'BEA 2017 Margins'!$J$7:$J$1074,$B14,'BEA 2017 Margins'!$K$7:$K$1074,"Contractor"))+IF($D14="",0,SUMIFS('BEA 2017 Margins'!$I$7:$I$1074,'BEA 2017 Margins'!$C$7:$C$1074,$D14,'BEA 2017 Margins'!$J$7:$J$1074,$B14,'BEA 2017 Margins'!$K$7:$K$1074,"Contractor"))+IF($E14="",0,SUMIFS('BEA 2017 Margins'!$I$7:$I$1074,'BEA 2017 Margins'!$C$7:$C$1074,$E14,'BEA 2017 Margins'!$J$7:$J$1074,$B14,'BEA 2017 Margins'!$K$7:$K$1074,"Contractor")) -> 2175 | L14: =F14/SUM(F14:I14) -> 0.67792479 | M14: =G14/SUM(F14:I14) -> 0.010694509 | N14: =(H14+I14)/SUM(F14:I14) -> 0.3113807 | O14: =K14/(J14+K14) -> 0.03063596
A16: BEA rounds each figure to the nearest million dollars; the shares divide by the sum of the four parts so they add to exactly 100%. Purchasers' value for imports and exports is left out because those buyers are not used.

Sheet Checks
A1: Validation checks
A3: Child-factor groups sum to 1 (per file/context/parent; rate-file reroutes excluded)
A4: SoBCaICbIC-commercial.csv | Appliances | ISIC 01T03 | B4: =('Factors applied'!$E$3+'Factors applied'!$E$4+'Factors applied'!$E$5) -> 1 | C4: =IF(ABS(B4-1)<0.000000001,"PASS","FAIL") -> PASS
A5: SoBCaICbIC-commercial.csv | Appliances | ISIC 07T08 | B5: =('Factors applied'!$E$6+'Factors applied'!$E$7) -> 1 | C5: =IF(ABS(B5-1)<0.000000001,"PASS","FAIL") -> PASS
A6: SoBCaICbIC-commercial.csv | Appliances | ISIC 30 | B6: =('Factors applied'!$E$8+'Factors applied'!$E$9) -> 1 | C6: =IF(ABS(B6-1)<0.000000001,"PASS","FAIL") -> PASS
A7: SoBCaICbIC-commercial.csv | Appliances | ISIC 49T53 | B7: =('Factors applied'!$E$10+'Factors applied'!$E$11+'Factors applied'!$E$12+'Factors applied'!$E$13+'Factors applied'!$E$14) -> 1 | C7: =IF(ABS(B7-1)<0.000000001,"PASS","FAIL") -> PASS
A8: SoBCaICbIC-commercial.csv | Appliances | ISIC 69T82 | B8: =('Factors applied'!$E$15+'Factors applied'!$E$16) -> 1 | C8: =IF(ABS(B8-1)<0.000000001,"PASS","FAIL") -> PASS
A9: SoBCaICbIC-commercial.csv | Appliances | ISIC 90T96 | B9: =('Factors applied'!$E$17+'Factors applied'!$E$18) -> 1 | C9: =IF(ABS(B9-1)<0.000000001,"PASS","FAIL") -> PASS
A10: SoBCaICbIC-commercial.csv | Cooling | ISIC 01T03 | B10: =('Factors applied'!$E$19+'Factors applied'!$E$20+'Factors applied'!$E$21) -> 1 | C10: =IF(ABS(B10-1)<0.000000001,"PASS","FAIL") -> PASS
A11: SoBCaICbIC-commercial.csv | Cooling | ISIC 07T08 | B11: =('Factors applied'!$E$22+'Factors applied'!$E$23) -> 1 | C11: =IF(ABS(B11-1)<0.000000001,"PASS","FAIL") -> PASS
A12: SoBCaICbIC-commercial.csv | Cooling | ISIC 30 | B12: =('Factors applied'!$E$24+'Factors applied'!$E$25) -> 1 | C12: =IF(ABS(B12-1)<0.000000001,"PASS","FAIL") -> PASS
A13: SoBCaICbIC-commercial.csv | Cooling | ISIC 49T53 | B13: =('Factors applied'!$E$26+'Factors applied'!$E$27+'Factors applied'!$E$28+'Factors applied'!$E$29+'Factors applied'!$E$30) -> 1 | C13: =IF(ABS(B13-1)<0.000000001,"PASS","FAIL") -> PASS
A14: SoBCaICbIC-commercial.csv | Cooling | ISIC 69T82 | B14: =('Factors applied'!$E$31+'Factors applied'!$E$32) -> 1 | C14: =IF(ABS(B14-1)<0.000000001,"PASS","FAIL") -> PASS
A15: SoBCaICbIC-commercial.csv | Cooling | ISIC 90T96 | B15: =('Factors applied'!$E$33+'Factors applied'!$E$34) -> 1 | C15: =IF(ABS(B15-1)<0.000000001,"PASS","FAIL") -> PASS
A16: SoBCaICbIC-commercial.csv | Envelope | ISIC 01T03 | B16: =('Factors applied'!$E$35+'Factors applied'!$E$36+'Factors applied'!$E$37) -> 1 | C16: =IF(ABS(B16-1)<0.000000001,"PASS","FAIL") -> PASS
A17: SoBCaICbIC-commercial.csv | Envelope | ISIC 07T08 | B17: =('Factors applied'!$E$38+'Factors applied'!$E$39) -> 1 | C17: =IF(ABS(B17-1)<0.000000001,"PASS","FAIL") -> PASS
A18: SoBCaICbIC-commercial.csv | Envelope | ISIC 30 | B18: =('Factors applied'!$E$40+'Factors applied'!$E$41) -> 1 | C18: =IF(ABS(B18-1)<0.000000001,"PASS","FAIL") -> PASS
A19: SoBCaICbIC-commercial.csv | Envelope | ISIC 49T53 | B19: =('Factors applied'!$E$42+'Factors applied'!$E$43+'Factors applied'!$E$44+'Factors applied'!$E$45+'Factors applied'!$E$46) -> 1 | C19: =IF(ABS(B19-1)<0.000000001,"PASS","FAIL") -> PASS
A20: SoBCaICbIC-commercial.csv | Envelope | ISIC 69T82 | B20: =('Factors applied'!$E$47+'Factors applied'!$E$48) -> 1 | C20: =IF(ABS(B20-1)<0.000000001,"PASS","FAIL") -> PASS
A21: SoBCaICbIC-commercial.csv | Envelope | ISIC 90T96 | B21: =('Factors applied'!$E$49+'Factors applied'!$E$50) -> 1 | C21: =IF(ABS(B21-1)<0.000000001,"PASS","FAIL") -> PASS
A22: SoBCaICbIC-commercial.csv | Heating | ISIC 01T03 | B22: =('Factors applied'!$E$51+'Factors applied'!$E$52+'Factors applied'!$E$53) -> 1 | C22: =IF(ABS(B22-1)<0.000000001,"PASS","FAIL") -> PASS
A23: SoBCaICbIC-commercial.csv | Heating | ISIC 07T08 | B23: =('Factors applied'!$E$54+'Factors applied'!$E$55) -> 1 | C23: =IF(ABS(B23-1)<0.000000001,"PASS","FAIL") -> PASS
A24: SoBCaICbIC-commercial.csv | Heating | ISIC 30 | B24: =('Factors applied'!$E$56+'Factors applied'!$E$57) -> 1 | C24: =IF(ABS(B24-1)<0.000000001,"PASS","FAIL") -> PASS
A25: SoBCaICbIC-commercial.csv | Heating | ISIC 49T53 | B25: =('Factors applied'!$E$58+'Factors applied'!$E$59+'Factors applied'!$E$60+'Factors applied'!$E$61+'Factors applied'!$E$62) -> 1 | C25: =IF(ABS(B25-1)<0.000000001,"PASS","FAIL") -> PASS
A26: SoBCaICbIC-commercial.csv | Heating | ISIC 69T82 | B26: =('Factors applied'!$E$63+'Factors applied'!$E$64) -> 1 | C26: =IF(ABS(B26-1)<0.000000001,"PASS","FAIL") -> PASS
A27: SoBCaICbIC-commercial.csv | Heating | ISIC 90T96 | B27: =('Factors applied'!$E$65+'Factors applied'!$E$66) -> 1 | C27: =IF(ABS(B27-1)<0.000000001,"PASS","FAIL") -> PASS
A28: SoBCaICbIC-commercial.csv | Lighting | ISIC 01T03 | B28: =('Factors applied'!$E$67+'Factors applied'!$E$68+'Factors applied'!$E$69) -> 1 | C28: =IF(ABS(B28-1)<0.000000001,"PASS","FAIL") -> PASS
A29: SoBCaICbIC-commercial.csv | Lighting | ISIC 07T08 | B29: =('Factors applied'!$E$70+'Factors applied'!$E$71) -> 1 | C29: =IF(ABS(B29-1)<0.000000001,"PASS","FAIL") -> PASS
A30: SoBCaICbIC-commercial.csv | Lighting | ISIC 30 | B30: =('Factors applied'!$E$72+'Factors applied'!$E$73) -> 1 | C30: =IF(ABS(B30-1)<0.000000001,"PASS","FAIL") -> PASS
A31: SoBCaICbIC-commercial.csv | Lighting | ISIC 49T53 | B31: =('Factors applied'!$E$74+'Factors applied'!$E$75+'Factors applied'!$E$76+'Factors applied'!$E$77+'Factors applied'!$E$78) -> 1 | C31: =IF(ABS(B31-1)<0.000000001,"PASS","FAIL") -> PASS
A32: SoBCaICbIC-commercial.csv | Lighting | ISIC 69T82 | B32: =('Factors applied'!$E$79+'Factors applied'!$E$80) -> 1 | C32: =IF(ABS(B32-1)<0.000000001,"PASS","FAIL") -> PASS
A33: SoBCaICbIC-commercial.csv | Lighting | ISIC 90T96 | B33: =('Factors applied'!$E$81+'Factors applied'!$E$82) -> 1 | C33: =IF(ABS(B33-1)<0.000000001,"PASS","FAIL") -> PASS
A34: SoBCaICbIC-commercial.csv | Other | ISIC 01T03 | B34: =('Factors applied'!$E$83+'Factors applied'!$E$84+'Factors applied'!$E$85) -> 1 | C34: =IF(ABS(B34-1)<0.000000001,"PASS","FAIL") -> PASS
A35: SoBCaICbIC-commercial.csv | Other | ISIC 07T08 | B35: =('Factors applied'!$E$86+'Factors applied'!$E$87) -> 1 | C35: =IF(ABS(B35-1)<0.000000001,"PASS","FAIL") -> PASS
A36: SoBCaICbIC-commercial.csv | Other | ISIC 30 | B36: =('Factors applied'!$E$88+'Factors applied'!$E$89) -> 1 | C36: =IF(ABS(B36-1)<0.000000001,"PASS","FAIL") -> PASS
A37: SoBCaICbIC-commercial.csv | Other | ISIC 49T53 | B37: =('Factors applied'!$E$90+'Factors applied'!$E$91+'Factors applied'!$E$92+'Factors applied'!$E$93+'Factors applied'!$E$94) -> 1 | C37: =IF(ABS(B37-1)<0.000000001,"PASS","FAIL") -> PASS
A38: SoBCaICbIC-commercial.csv | Other | ISIC 69T82 | B38: =('Factors applied'!$E$95+'Factors applied'!$E$96) -> 1 | C38: =IF(ABS(B38-1)<0.000000001,"PASS","FAIL") -> PASS
A39: SoBCaICbIC-commercial.csv | Other | ISIC 90T96 | B39: =('Factors applied'!$E$97+'Factors applied'!$E$98) -> 1 | C39: =IF(ABS(B39-1)<0.000000001,"PASS","FAIL") -> PASS
A40: SoBCaICbIC-ruralresidential.csv | Appliances | ISIC 01T03 | B40: =('Factors applied'!$E$99+'Factors applied'!$E$100+'Factors applied'!$E$101) -> 1 | C40: =IF(ABS(B40-1)<0.000000001,"PASS","FAIL") -> PASS
A41: SoBCaICbIC-ruralresidential.csv | Appliances | ISIC 07T08 | B41: =('Factors applied'!$E$102+'Factors applied'!$E$103) -> 1 | C41: =IF(ABS(B41-1)<0.000000001,"PASS","FAIL") -> PASS
A42: SoBCaICbIC-ruralresidential.csv | Appliances | ISIC 30 | B42: =('Factors applied'!$E$104+'Factors applied'!$E$105) -> 1 | C42: =IF(ABS(B42-1)<0.000000001,"PASS","FAIL") -> PASS
A43: SoBCaICbIC-ruralresidential.csv | Appliances | ISIC 49T53 | B43: =('Factors applied'!$E$106+'Factors applied'!$E$107+'Factors applied'!$E$108+'Factors applied'!$E$109+'Factors applied'!$E$110) -> 1 | C43: =IF(ABS(B43-1)<0.000000001,"PASS","FAIL") -> PASS
A44: SoBCaICbIC-ruralresidential.csv | Appliances | ISIC 69T82 | B44: =('Factors applied'!$E$111+'Factors applied'!$E$112) -> 1 | C44: =IF(ABS(B44-1)<0.000000001,"PASS","FAIL") -> PASS
A45: SoBCaICbIC-ruralresidential.csv | Appliances | ISIC 90T96 | B45: =('Factors applied'!$E$113+'Factors applied'!$E$114) -> 1 | C45: =IF(ABS(B45-1)<0.000000001,"PASS","FAIL") -> PASS
A46: SoBCaICbIC-ruralresidential.csv | Cooling | ISIC 01T03 | B46: =('Factors applied'!$E$115+'Factors applied'!$E$116+'Factors applied'!$E$117) -> 1 | C46: =IF(ABS(B46-1)<0.000000001,"PASS","FAIL") -> PASS
A47: SoBCaICbIC-ruralresidential.csv | Cooling | ISIC 07T08 | B47: =('Factors applied'!$E$118+'Factors applied'!$E$119) -> 1 | C47: =IF(ABS(B47-1)<0.000000001,"PASS","FAIL") -> PASS
A48: SoBCaICbIC-ruralresidential.csv | Cooling | ISIC 30 | B48: =('Factors applied'!$E$120+'Factors applied'!$E$121) -> 1 | C48: =IF(ABS(B48-1)<0.000000001,"PASS","FAIL") -> PASS
A49: SoBCaICbIC-ruralresidential.csv | Cooling | ISIC 49T53 | B49: =('Factors applied'!$E$122+'Factors applied'!$E$123+'Factors applied'!$E$124+'Factors applied'!$E$125+'Factors applied'!$E$126) -> 1 | C49: =IF(ABS(B49-1)<0.000000001,"PASS","FAIL") -> PASS
A50: SoBCaICbIC-ruralresidential.csv | Cooling | ISIC 69T82 | B50: =('Factors applied'!$E$127+'Factors applied'!$E$128) -> 1 | C50: =IF(ABS(B50-1)<0.000000001,"PASS","FAIL") -> PASS
A51: SoBCaICbIC-ruralresidential.csv | Cooling | ISIC 90T96 | B51: =('Factors applied'!$E$129+'Factors applied'!$E$130) -> 1 | C51: =IF(ABS(B51-1)<0.000000001,"PASS","FAIL") -> PASS
A52: SoBCaICbIC-ruralresidential.csv | Envelope | ISIC 01T03 | B52: =('Factors applied'!$E$131+'Factors applied'!$E$132+'Factors applied'!$E$133) -> 1 | C52: =IF(ABS(B52-1)<0.000000001,"PASS","FAIL") -> PASS
A53: SoBCaICbIC-ruralresidential.csv | Envelope | ISIC 07T08 | B53: =('Factors applied'!$E$134+'Factors applied'!$E$135) -> 1 | C53: =IF(ABS(B53-1)<0.000000001,"PASS","FAIL") -> PASS
A54: SoBCaICbIC-ruralresidential.csv | Envelope | ISIC 30 | B54: =('Factors applied'!$E$136+'Factors applied'!$E$137) -> 1 | C54: =IF(ABS(B54-1)<0.000000001,"PASS","FAIL") -> PASS
A55: SoBCaICbIC-ruralresidential.csv | Envelope | ISIC 49T53 | B55: =('Factors applied'!$E$138+'Factors applied'!$E$139+'Factors applied'!$E$140+'Factors applied'!$E$141+'Factors applied'!$E$142) -> 1 | C55: =IF(ABS(B55-1)<0.000000001,"PASS","FAIL") -> PASS
A56: SoBCaICbIC-ruralresidential.csv | Envelope | ISIC 69T82 | B56: =('Factors applied'!$E$143+'Factors applied'!$E$144) -> 1 | C56: =IF(ABS(B56-1)<0.000000001,"PASS","FAIL") -> PASS
A57: SoBCaICbIC-ruralresidential.csv | Envelope | ISIC 90T96 | B57: =('Factors applied'!$E$145+'Factors applied'!$E$146) -> 1 | C57: =IF(ABS(B57-1)<0.000000001,"PASS","FAIL") -> PASS
A58: SoBCaICbIC-ruralresidential.csv | Heating | ISIC 01T03 | B58: =('Factors applied'!$E$147+'Factors applied'!$E$148+'Factors applied'!$E$149) -> 1 | C58: =IF(ABS(B58-1)<0.000000001,"PASS","FAIL") -> PASS
A59: SoBCaICbIC-ruralresidential.csv | Heating | ISIC 07T08 | B59: =('Factors applied'!$E$150+'Factors applied'!$E$151) -> 1 | C59: =IF(ABS(B59-1)<0.000000001,"PASS","FAIL") -> PASS
A60: SoBCaICbIC-ruralresidential.csv | Heating | ISIC 30 | B60: =('Factors applied'!$E$152+'Factors applied'!$E$153) -> 1 | C60: =IF(ABS(B60-1)<0.000000001,"PASS","FAIL") -> PASS
A61: SoBCaICbIC-ruralresidential.csv | Heating | ISIC 49T53 | B61: =('Factors applied'!$E$154+'Factors applied'!$E$155+'Factors applied'!$E$156+'Factors applied'!$E$157+'Factors applied'!$E$158) -> 1 | C61: =IF(ABS(B61-1)<0.000000001,"PASS","FAIL") -> PASS
A62: SoBCaICbIC-ruralresidential.csv | Heating | ISIC 69T82 | B62: =('Factors applied'!$E$159+'Factors applied'!$E$160) -> 1 | C62: =IF(ABS(B62-1)<0.000000001,"PASS","FAIL") -> PASS
A63: SoBCaICbIC-ruralresidential.csv | Heating | ISIC 90T96 | B63: =('Factors applied'!$E$161+'Factors applied'!$E$162) -> 1 | C63: =IF(ABS(B63-1)<0.000000001,"PASS","FAIL") -> PASS
A64: SoBCaICbIC-ruralresidential.csv | Lighting | ISIC 01T03 | B64: =('Factors applied'!$E$163+'Factors applied'!$E$164+'Factors applied'!$E$165) -> 1 | C64: =IF(ABS(B64-1)<0.000000001,"PASS","FAIL") -> PASS
A65: SoBCaICbIC-ruralresidential.csv | Lighting | ISIC 07T08 | B65: =('Factors applied'!$E$166+'Factors applied'!$E$167) -> 1 | C65: =IF(ABS(B65-1)<0.000000001,"PASS","FAIL") -> PASS
A66: SoBCaICbIC-ruralresidential.csv | Lighting | ISIC 30 | B66: =('Factors applied'!$E$168+'Factors applied'!$E$169) -> 1 | C66: =IF(ABS(B66-1)<0.000000001,"PASS","FAIL") -> PASS
A67: SoBCaICbIC-ruralresidential.csv | Lighting | ISIC 49T53 | B67: =('Factors applied'!$E$170+'Factors applied'!$E$171+'Factors applied'!$E$172+'Factors applied'!$E$173+'Factors applied'!$E$174) -> 1 | C67: =IF(ABS(B67-1)<0.000000001,"PASS","FAIL") -> PASS
A68: SoBCaICbIC-ruralresidential.csv | Lighting | ISIC 69T82 | B68: =('Factors applied'!$E$175+'Factors applied'!$E$176) -> 1 | C68: =IF(ABS(B68-1)<0.000000001,"PASS","FAIL") -> PASS
A69: SoBCaICbIC-ruralresidential.csv | Lighting | ISIC 90T96 | B69: =('Factors applied'!$E$177+'Factors applied'!$E$178) -> 1 | C69: =IF(ABS(B69-1)<0.000000001,"PASS","FAIL") -> PASS
A70: SoBCaICbIC-ruralresidential.csv | Other | ISIC 01T03 | B70: =('Factors applied'!$E$179+'Factors applied'!$E$180+'Factors applied'!$E$181) -> 1 | C70: =IF(ABS(B70-1)<0.000000001,"PASS","FAIL") -> PASS
A71: SoBCaICbIC-ruralresidential.csv | Other | ISIC 07T08 | B71: =('Factors applied'!$E$182+'Factors applied'!$E$183) -> 1 | C71: =IF(ABS(B71-1)<0.000000001,"PASS","FAIL") -> PASS
A72: SoBCaICbIC-ruralresidential.csv | Other | ISIC 30 | B72: =('Factors applied'!$E$184+'Factors applied'!$E$185) -> 1 | C72: =IF(ABS(B72-1)<0.000000001,"PASS","FAIL") -> PASS
A73: SoBCaICbIC-ruralresidential.csv | Other | ISIC 49T53 | B73: =('Factors applied'!$E$186+'Factors applied'!$E$187+'Factors applied'!$E$188+'Factors applied'!$E$189+'Factors applied'!$E$190) -> 1 | C73: =IF(ABS(B73-1)<0.000000001,"PASS","FAIL") -> PASS
A74: SoBCaICbIC-ruralresidential.csv | Other | ISIC 69T82 | B74: =('Factors applied'!$E$191+'Factors applied'!$E$192) -> 1 | C74: =IF(ABS(B74-1)<0.000000001,"PASS","FAIL") -> PASS
A75: SoBCaICbIC-ruralresidential.csv | Other | ISIC 90T96 | B75: =('Factors applied'!$E$193+'Factors applied'!$E$194) -> 1 | C75: =IF(ABS(B75-1)<0.000000001,"PASS","FAIL") -> PASS
A76: SoBCaICbIC-urbanresidential.csv | Appliances | ISIC 01T03 | B76: =('Factors applied'!$E$195+'Factors applied'!$E$196+'Factors applied'!$E$197) -> 1 | C76: =IF(ABS(B76-1)<0.000000001,"PASS","FAIL") -> PASS
A77: SoBCaICbIC-urbanresidential.csv | Appliances | ISIC 07T08 | B77: =('Factors applied'!$E$198+'Factors applied'!$E$199) -> 1 | C77: =IF(ABS(B77-1)<0.000000001,"PASS","FAIL") -> PASS
A78: SoBCaICbIC-urbanresidential.csv | Appliances | ISIC 30 | B78: =('Factors applied'!$E$200+'Factors applied'!$E$201) -> 1 | C78: =IF(ABS(B78-1)<0.000000001,"PASS","FAIL") -> PASS
A79: SoBCaICbIC-urbanresidential.csv | Appliances | ISIC 49T53 | B79: =('Factors applied'!$E$202+'Factors applied'!$E$203+'Factors applied'!$E$204+'Factors applied'!$E$205+'Factors applied'!$E$206) -> 1 | C79: =IF(ABS(B79-1)<0.000000001,"PASS","FAIL") -> PASS
A80: SoBCaICbIC-urbanresidential.csv | Appliances | ISIC 69T82 | B80: =('Factors applied'!$E$207+'Factors applied'!$E$208) -> 1 | C80: =IF(ABS(B80-1)<0.000000001,"PASS","FAIL") -> PASS
A81: SoBCaICbIC-urbanresidential.csv | Appliances | ISIC 90T96 | B81: =('Factors applied'!$E$209+'Factors applied'!$E$210) -> 1 | C81: =IF(ABS(B81-1)<0.000000001,"PASS","FAIL") -> PASS
A82: SoBCaICbIC-urbanresidential.csv | Cooling | ISIC 01T03 | B82: =('Factors applied'!$E$211+'Factors applied'!$E$212+'Factors applied'!$E$213) -> 1 | C82: =IF(ABS(B82-1)<0.000000001,"PASS","FAIL") -> PASS
A83: SoBCaICbIC-urbanresidential.csv | Cooling | ISIC 07T08 | B83: =('Factors applied'!$E$214+'Factors applied'!$E$215) -> 1 | C83: =IF(ABS(B83-1)<0.000000001,"PASS","FAIL") -> PASS
A84: SoBCaICbIC-urbanresidential.csv | Cooling | ISIC 30 | B84: =('Factors applied'!$E$216+'Factors applied'!$E$217) -> 1 | C84: =IF(ABS(B84-1)<0.000000001,"PASS","FAIL") -> PASS
A85: SoBCaICbIC-urbanresidential.csv | Cooling | ISIC 49T53 | B85: =('Factors applied'!$E$218+'Factors applied'!$E$219+'Factors applied'!$E$220+'Factors applied'!$E$221+'Factors applied'!$E$222) -> 1 | C85: =IF(ABS(B85-1)<0.000000001,"PASS","FAIL") -> PASS
A86: SoBCaICbIC-urbanresidential.csv | Cooling | ISIC 69T82 | B86: =('Factors applied'!$E$223+'Factors applied'!$E$224) -> 1 | C86: =IF(ABS(B86-1)<0.000000001,"PASS","FAIL") -> PASS
A87: SoBCaICbIC-urbanresidential.csv | Cooling | ISIC 90T96 | B87: =('Factors applied'!$E$225+'Factors applied'!$E$226) -> 1 | C87: =IF(ABS(B87-1)<0.000000001,"PASS","FAIL") -> PASS
A88: SoBCaICbIC-urbanresidential.csv | Envelope | ISIC 01T03 | B88: =('Factors applied'!$E$227+'Factors applied'!$E$228+'Factors applied'!$E$229) -> 1 | C88: =IF(ABS(B88-1)<0.000000001,"PASS","FAIL") -> PASS
A89: SoBCaICbIC-urbanresidential.csv | Envelope | ISIC 07T08 | B89: =('Factors applied'!$E$230+'Factors applied'!$E$231) -> 1 | C89: =IF(ABS(B89-1)<0.000000001,"PASS","FAIL") -> PASS
A90: SoBCaICbIC-urbanresidential.csv | Envelope | ISIC 30 | B90: =('Factors applied'!$E$232+'Factors applied'!$E$233) -> 1 | C90: =IF(ABS(B90-1)<0.000000001,"PASS","FAIL") -> PASS
A91: SoBCaICbIC-urbanresidential.csv | Envelope | ISIC 49T53 | B91: =('Factors applied'!$E$234+'Factors applied'!$E$235+'Factors applied'!$E$236+'Factors applied'!$E$237+'Factors applied'!$E$238) -> 1 | C91: =IF(ABS(B91-1)<0.000000001,"PASS","FAIL") -> PASS
A92: SoBCaICbIC-urbanresidential.csv | Envelope | ISIC 69T82 | B92: =('Factors applied'!$E$239+'Factors applied'!$E$240) -> 1 | C92: =IF(ABS(B92-1)<0.000000001,"PASS","FAIL") -> PASS
A93: SoBCaICbIC-urbanresidential.csv | Envelope | ISIC 90T96 | B93: =('Factors applied'!$E$241+'Factors applied'!$E$242) -> 1 | C93: =IF(ABS(B93-1)<0.000000001,"PASS","FAIL") -> PASS
A94: SoBCaICbIC-urbanresidential.csv | Heating | ISIC 01T03 | B94: =('Factors applied'!$E$243+'Factors applied'!$E$244+'Factors applied'!$E$245) -> 1 | C94: =IF(ABS(B94-1)<0.000000001,"PASS","FAIL") -> PASS
A95: SoBCaICbIC-urbanresidential.csv | Heating | ISIC 07T08 | B95: =('Factors applied'!$E$246+'Factors applied'!$E$247) -> 1 | C95: =IF(ABS(B95-1)<0.000000001,"PASS","FAIL") -> PASS
A96: SoBCaICbIC-urbanresidential.csv | Heating | ISIC 30 | B96: =('Factors applied'!$E$248+'Factors applied'!$E$249) -> 1 | C96: =IF(ABS(B96-1)<0.000000001,"PASS","FAIL") -> PASS
A97: SoBCaICbIC-urbanresidential.csv | Heating | ISIC 49T53 | B97: =('Factors applied'!$E$250+'Factors applied'!$E$251+'Factors applied'!$E$252+'Factors applied'!$E$253+'Factors applied'!$E$254) -> 1 | C97: =IF(ABS(B97-1)<0.000000001,"PASS","FAIL") -> PASS
A98: SoBCaICbIC-urbanresidential.csv | Heating | ISIC 69T82 | B98: =('Factors applied'!$E$255+'Factors applied'!$E$256) -> 1 | C98: =IF(ABS(B98-1)<0.000000001,"PASS","FAIL") -> PASS
A99: SoBCaICbIC-urbanresidential.csv | Heating | ISIC 90T96 | B99: =('Factors applied'!$E$257+'Factors applied'!$E$258) -> 1 | C99: =IF(ABS(B99-1)<0.000000001,"PASS","FAIL") -> PASS
A100: SoBCaICbIC-urbanresidential.csv | Lighting | ISIC 01T03 | B100: =('Factors applied'!$E$259+'Factors applied'!$E$260+'Factors applied'!$E$261) -> 1 | C100: =IF(ABS(B100-1)<0.000000001,"PASS","FAIL") -> PASS
A101: SoBCaICbIC-urbanresidential.csv | Lighting | ISIC 07T08 | B101: =('Factors applied'!$E$262+'Factors applied'!$E$263) -> 1 | C101: =IF(ABS(B101-1)<0.000000001,"PASS","FAIL") -> PASS
...

Sheet SoBCaICbIC-urbanresidential
A1: Unit: dimensionless (%) | B1: ISIC 01 | C1: ISIC 02 | D1: ISIC 03 | E1: ISIC 05 | F1: ISIC 06 | G1: ISIC 07 | H1: ISIC 08 | I1: ISIC 09 | J1: ISIC 10T12 | K1: ISIC 13T15 | L1: ISIC 16 | M1: ISIC 17T18 | N1: ISIC 19 | O1: ISIC 20 | P1: ISIC 21 | Q1: ISIC 22 | R1: ISIC 231 | S1: ISIC 239 | T1: ISIC 241 | U1: ISIC 242 | V1: ISIC 25 | W1: ISIC 26 | X1: ISIC 27 | Y1: ISIC 28 | Z1: ISIC 29 | AA1: ISIC 301 | AB1: ISIC 302T309 | AC1: ISIC 31T33 | AD1: ISIC 351 | AE1: ISIC 352T353 | AF1: ISIC 36T39 | AG1: ISIC 41T43 | AH1: ISIC 45T47 | AI1: ISIC 49 | AJ1: ISIC 50 | AK1: ISIC 51 | AL1: ISIC 52 | AM1: ISIC 53 | AN1: ISIC 55T56 | AO1: ISIC 58T60 | AP1: ISIC 61 | AQ1: ISIC 62T63 | AR1: ISIC 64T66 | AS1: ISIC 68 | AT1: ISIC 69T75 | AU1: ISIC 77T82 | AV1: ISIC 84 | AW1: ISIC 85 | AX1: ISIC 86T88 | AY1: ISIC 90T93 | AZ1: ISIC 94T96 | BA1: ISIC 97T98
