Workbook
Name billion: About!$A$95
Name CH4GWP: #REF!
Name Eno_TM: '[1]1997 Table 1a Modified'!#REF!
Name Eno_TM: #REF!
Name Eno_TM: '[2]1997 Table 1a Modified'!#REF!
Name Eno_TM: '[2]1997 Table 1a Modified'!#REF!
Name Eno_TM: '[2]1997 Table 1a Modified'!#REF!
Name Eno_Tons: '[1]1997 Table 1a Modified'!#REF!
Name Eno_Tons: #REF!
Name Eno_Tons: '[2]1997 Table 1a Modified'!#REF!
Name Eno_Tons: '[2]1997 Table 1a Modified'!#REF!
Name Eno_Tons: '[2]1997 Table 1a Modified'!#REF!
Name EPS_data: #REF!
Name EPS_dates: #REF!
Name EPS_varnames: #REF!
Name GWPCH4: #REF!
Name GWPN2O: #REF!
Name N2OGWP: #REF!
Name NTS_YR: [3]About!$B$136
Name Sum_T2: '[1]1997 Table 1a Modified'!#REF!
Name Sum_T2: #REF!
Name Sum_T2: '[2]1997 Table 1a Modified'!#REF!
Name Sum_T2: '[2]1997 Table 1a Modified'!#REF!
Name Sum_T2: '[2]1997 Table 1a Modified'!#REF!
Name Sum_TTM: '[1]1997 Table 1a Modified'!#REF!
Name Sum_TTM: #REF!
Name Sum_TTM: '[2]1997 Table 1a Modified'!#REF!
Name Sum_TTM: '[2]1997 Table 1a Modified'!#REF!
Name Sum_TTM: '[2]1997 Table 1a Modified'!#REF!
Name ti_tbl_50: #REF!
Name ti_tbl_50: #REF!
Name ti_tbl_50: #REF!
Name ti_tbl_69: #REF!
Name ti_tbl_69: #REF!
Name ti_tbl_69: #REF!
Name TitleRegion1.f2.y3.5: #REF!
Name TitleRegion1.f3.n4.5: #REF!
Name TitleRegion2.e6.y15.5: #REF!
Name TitleRegion2.e8.n17.5: #REF!
Name TitleRegion3.c19.y51.5: #REF!
Name TitleRegion3.c24.n53.5: #REF!
Name TitleRegion4.e54.y63.5: #REF!
Name TitleRegion4.e57.n66.5: #REF!
Name TitleRegion5.d68.y124.5: #REF!
Name TitleRegion5.d73.n129.5: #REF!
Name trillion: About!$A$96

Sheet About
A1: SYFAFE Start Year Fleet Avg Fuel Economy
A3: Sources: | B3: See Notes section for which vehicle types use which sources
B4: EIA
B5: 2023, 2025, 2026
B6: Annual Energy Outlook 2023, 2025, 2026
B7: https://www.eia.gov/outlooks/aeo/tables_ref.cfm
B8: Tables 7, 25, 36, 37, 38, 40, 41, 43, 46, 47, 48, 49
B10: Bureau of Transportation Statistics
B11: 2018
B12: National Transportation Statistics
B13: https://www.bts.gov/content/us-passenger-miles
B14: Table 1-40
B16: U.S. Coast Guard
B17: 2013
B18: National Recreational Boating Survey 2012
B19: http://www.uscgboating.org/library/recreational-boating-servey/2012survey%20report.pdf
B20: Page 63, Table 40
B22: U.S. Department of Energy
B23: 2015
B24: Fuel Cells Fact Sheet
B25: https://www.energy.gov/sites/prod/files/2015/11/f27/fcto_fuel_cells_fact_sheet.pdf
B27: US EPA
B28: Inventory of U.S. Greenhouse Gas Emissions and Sinks: 1990-2021 and Annex
B29: 2023
B30: https://www.epa.gov/ghgemissions/inventory-us-greenhouse-gas-emissions-and-sinks-1990-2021
B32: Rail-passenger data
B33: National Transit Database Tables
B34: American Public Transportation Association
B35: 2020
B36: https://www.apta.com/research-technical-resources/transit-statistics/ntd-data-tables/
B40: Others as noted on "Calculations Etc" tab
A42: Notes
A43: This variable gives fleet-wide fuel economy in units of cargo distance per BTU.
A45: passenger LDVs, freight LDVs and HDVs
A46: Sources: AEO 37, 41, 43, 36, 49
A47: Vehicle distance traveled and energy consumption by vehicle technology is available for passenger LDVs, commercial light trucks and HDVs.
A48: We sum vehicle distance traveled by technology, divide by energy consumption of that technology, and multiply by the vehicle loading values used in the
A49: EPS to convert from miles/BTU to thing-miles/BTU. The AEO shows 0 energy consumption by battery electric and plug-in hybrid commercial freight
A50: trucks in 2019. Therefore, we use 2020 data for those two technologies.
A52: freight rail
A53: Sources: AEO 7
A54: Freight rail efficiency is available directly from AEO 7.
A56: passenger rail
... A93: calibration and how to perform it.
A95: =10^9 -> 1000000000
A96: =10^12 -> 1000000000000
A99: Start Year | B99: 2024

Sheet source data>

Sheet EPA_Table 3-13
A1: Table 3-13: CO2 Emissions from Fossil Fuel Combustion in Transportation End-Use Sector (MMT CO2 Eq.)
A3: Fuel/Vehicle Type | B3: 2020 | C3: 2021
A4: Gasolinea | B4: 937 | C4: 1029
A5: Passenger Cars | B5: 328 | C5: 361
A6: Light-Duty Trucks | B6: 566 | C6: 620
A7: Medium- and Heavy-Duty Trucksb | B7: 24 | C7: 27
A8: Buses | B8: 3 | C8: 3
A9: Motorcycles | B9: 7 | C9: 7
A10: Recreational Boatsc | B10: 10 | C10: 11
A11: Distillate Fuel Oil (Diesel)a | B11: 455 | C11: 488
A12: Passenger Cars | B12: 3 | C12: 3
A13: Light-Duty Trucks | B13: 30 | C13: 33
A14: Medium- and Heavy-Duty Trucksb | B14: 353 | C14: 380
... A50: Biofuels-Biodieselh | B50: 17.7 | C50: 16.1
A51: + Does not exceed 0.05 MMT CO2 Eq.
A52: a On-road fuel consumption data from FHWA Table MF-21 and MF-27 were used to determine total on-road use of motor gasoline and diesel fuel (FHWA 1996 through 2023). Ratios developed from MOVES3 output are used to apportion FHWA fuel consumption data to vehicle type and fuel type (see Annex 3.2 for information about the MOVES model).
A53: b Includes medium- and heavy-duty trucks over 8,500 lbs.
A54: c In 2014, EPA incorporated the NONROAD2008 model into the MOVES model framework. The current Inventory uses the Nonroad component of MOVES3 for years 1999 through 2021. See Annex 3.2 for information about the MOVES model.
A55: d Note that large year over year fluctuations in emission estimates partially reflect nature of data collection for these sources.
A56: e Official estimates exclude emissions from the combustion of both aviation and marine international bunker fuels; however, estimates of international bunker fuel-related emissions are presented for informational purposes.
A57: f Commercial aircraft, as modeled in FAA’s Aviation Environmental Design Tool (AEDT), consists of passenger aircraft, cargo, and other chartered flights.
A58: g Pipelines reflect CO2 emissions from natural gas-powered pipelines transporting natural gas.
A59: h Ethanol and biodiesel estimates are presented for informational purposes only. See Section 3.10 of this chapter and the estimates in Land Use, Land-Use Change, and Forestry (see Chapter 6), in line with IPCC methodological guidance and UNFCCC reporting obligations, for more information on ethanol and biodiesel.
A60: i Transportation sector natural gas and LPG consumption are based on data from EIA (2021b). Prior to the 1990 to 2015 Inventory, data from DOE TEDB were used to estimate each vehicle class’s share of the total natural gas and LPG consumption. Since TEDB does not include estimates for natural gas use by medium and heavy-duty trucks or LPG use by passenger cars, EIA Alternative Fuel Vehicle Data (Browning 2017) is now used to determine each vehicle class’s share of the total natural gas and LPG consumption. These changes were first incorporated in the 1990 to 2016 Inventory and apply to the 1990 to 2021 time period.
A61: j Includes emissions from rail electricity.
A62: k Electricity consumption by passenger cars, light-duty trucks (SUVs), and buses is based on plug-in electric vehicle sales and engine efficiency data, as outlined in Browning (2018a). In prior Inventory years, CO2 emissions from electric vehicle charging were allocated to the residential and commercial sectors. They are now allocated to the transportation sector. These changes apply to the 2010 through 2021 time period.
A63: Notes: This table does not include emissions from non-transportation mobile sources, such as agricultural equipment and construction/mining equipment; it also does not include emissions associated with electricity consumption by pipelines or lubricants used in transportation. In addition, this table does not include CO2 emissions from U.S. Territories, since these are covered in a separate chapter of the Inventory. Totals may not sum due to independent rounding.

Sheet AVLo-passengers
A1: Vehicle Loading (passengers) | B1: 2015 | C1: 2016
A2: LDVs | B2: 1.67 | C2: 1.67
A3: HDVs | B3: 21.196137 | C3: 21.196137
A4: aircraft | B4: 111.39416 | C4: 111.39416
A5: rail | B5: 486.56732 | C5: 486.56732
A6: ships | B6: 1 | C6: 1
A7: motorbikes | B7: 1.2700757 | C7: 1.2700757

Sheet AVLo-freight
A1: Vehicle Loading (tons) | B1: 2016 | C1: 2017
A2: LDVs | B2: 1 | C2: 1
A3: HDVs | B3: 16 | C3: 16
A4: aircraft | B4: 41.989116 | C4: 41.989116
A5: rail | B5: 3512.3592 | C5: 3512.3592
A6: ships | B6: 1974.4736 | C6: 1974.4736
A7: motorbikes | B7: 0 | C7: 0

Sheet PEI-TFPEI-HDVs
A1: Pollutant Emissions Intensity (g pollutant/BTU) | B1: electricity | C1: natural gas | D1: petroleum gasoline | E1: petroleum diesel | F1: biofuel gasoline | G1: biofuel diesel | H1: jet fuel | I1: heavy or residual fuel oil | J1: LPG propane or butane | K1: hydrogen
A2: CO2 | B2: 0 | C2: 0.052751938 | D2: 0.072920704 | E2: 0.074215992 | F2: 0 | G2: 0 | H2: 0 | I2: 0 | J2: 0.067030065 | K2: 0
A3: VOC | B3: 0 | C3: 2.0116527e-05 | D3: 4.9544716e-05 | E3: 1.7127887e-05 | F3: 4.9544716e-05 | G3: 1.7127887e-05 | H3: 0 | I3: 0 | J3: 1.8676185e-05 | K3: 0
A4: CO | B4: 0 | C4: 0.0011140698 | D4: 0.0010281419 | E4: 7.8217123e-05 | F4: 0.0010281419 | G4: 7.8217123e-05 | H4: 0 | I4: 0 | J4: 3.2062705e-05 | K4: 0
A5: NOx | B5: 0 | C5: 6.3097541e-05 | D5: 0.00010277642 | E5: 0.00024072356 | F5: 0.00010277642 | G5: 0.00024072356 | H5: 0 | I5: 0 | J5: 0.000157038 | K5: 0
A6: PM10 | B6: 0 | C6: 5.6883776e-06 | D6: 6.1477987e-06 | E6: 1.5480764e-05 | F6: 6.1477987e-06 | G6: 1.5480764e-05 | H6: 0 | I6: 0 | J6: 5.2810902e-07 | K6: 0
A7: PM25 | B7: 0 | C7: 2.7736291e-06 | D7: 2.2736172e-06 | E7: 9.8509839e-06 | F7: 2.2736172e-06 | G7: 9.8509839e-06 | H7: 0 | I7: 0 | J7: 2.5750375e-07 | K7: 0
A8: SOx | B8: 0 | C8: 0 | D8: 7.7296864e-07 | E8: 6.6613125e-07 | F8: 7.7296864e-07 | G8: 6.6613125e-07 | H8: 0 | I8: 0 | J8: 0 | K8: 0
A9: BC | B9: 0 | C9: 2.2005086e-07 | D9: 3.5502594e-07 | E9: 4.9362701e-06 | F9: 3.5502594e-07 | G9: 4.9362701e-06 | H9: 0 | I9: 0 | J9: 2.0429523e-08 | K9: 0
A10: OC | B10: 0 | C10: 3.9999294e-07 | D10: 1.0010432e-06 | E10: 2.6892846e-06 | F10: 1.0010432e-06 | G10: 2.6892846e-06 | H10: 0 | I10: 0 | J10: 3.7135347e-08 | K10: 0
A11: CH4 | B11: 0 | C11: 1e-06 | D11: 3e-06 | E11: 3e-06 | F11: 0 | G11: 0 | H11: 0 | I11: 0 | J11: 3e-06 | K11: 0
A12: N2O | B12: 0 | C12: 1e-07 | D12: 6e-07 | E12: 6e-07 | F12: 0 | G12: 0 | H12: 0 | I12: 0 | J12: 6e-07 | K12: 0
A13: F gases | B13: 0 | C13: 0 | D13: 0 | E13: 0 | F13: 0 | G13: 0 | H13: 0 | I13: 0 | J13: 0 | K13: 0

Sheet AEO 2023 7
B1: ref2023.d020623a | C1: 2022 | D1: 2023 | E1: 2024 | F1: 2025 | G1: 2026 | H1: 2027 | I1: 2028 | J1: 2029 | K1: 2030 | L1: 2031 | M1: 2032 | N1: 2033 | O1: 2034 | P1: 2035 | Q1: 2036 | R1: 2037 | S1: 2038 | T1: 2039 | U1: 2040 | V1: 2041 | W1: 2042 | X1: 2043 | Y1: 2044 | Z1: 2045 | AA1: 2046 | AB1: 2047 | AC1: 2048 | AD1: 2049 | AE1: 2050
C3: Report | D3: Annual Energy Outlook 2023
C4: Scenario | D4: ref2023 | G4: Reference
C5: Datekey | D5: d020623a
C6: Release Date | E6: March 2023
A10: TKI000 | B10: 7. Transportation Sector Key Indicators and Delivered Energy Consumption | AF10: Average
AF11: Annual
AF12: Change
B13: Key Indicators and Consumption | C13: 2022 | D13: 2023 | E13: 2024 | F13: 2025 | G13: 2026 | H13: 2027 | I13: 2028 | J13: 2029 | K13: 2030 | L13: 2031 | M13: 2032 | N13: 2033 | O13: 2034 | P13: 2035 | Q13: 2036 | R13: 2037 | S13: 2038 | T13: 2039 | U13: 2040 | V13: 2041 | W13: 2042 | X13: 2043 | Y13: 2044 | Z13: 2045 | AA13: 2046 | AB13: 2047 | AC13: 2048 | AD13: 2049 | AE13: 2050 | AF13: 2022–2050
B15: Key Indicators
B16: Travel Indicators
B17: (billion vehicle miles traveled)
A18: TKI000:ba_Light-DutyVeh | B18: Light-Duty Vehicles less than 8,501 pounds | C18: 2843.2981 | D18: 2901.3589 | E18: 2922.5066 | F18: 2933.3601 | G18: 2954.238 | H18: 2981.9343 | I18: 3007.5581 | J18: 3027.573 | K18: 3042.8433 | L18: 3055.7747 | M18: 3066.6516 | N18: 3082.3594 | O18: 3102.4182 | P18: 3120.7375 | Q18: 3135.6208 | R18: 3152.9177 | S18: 3172.4355 | T18: 3192.1006 | U18: 3214.563 | V18: 3237.5806 | W18: 3261.5847 | X18: 3284.8975 | Y18: 3309.0391 | Z18: 3334.7034 | AA18: 3364.5225 | AB18: 3396.5352 | AC18: 3429.5627 | AD18: 3463.0249 | AE18: 3499.543 | AF18: 0.007444
A19: TKI000:ba_CommercialLig | B19: Commercial Light Trucks 1/ | C19: 102.21495 | D19: 103.34346 | E19: 103.55378 | F19: 104.36999 | G19: 105.65627 | H19: 107.00255 | I19: 108.20406 | J19: 109.32984 | K19: 110.21457 | L19: 111.0637 | M19: 112.17591 | N19: 113.26731 | O19: 114.36133 | P19: 115.53986 | Q19: 116.6934 | R19: 117.93478 | S19: 119.26325 | T19: 120.51714 | U19: 121.9657 | V19: 123.54321 | W19: 125.05544 | X19: 126.4902 | Y19: 127.8319 | Z19: 129.14803 | AA19: 130.64792 | AB19: 132.25534 | AC19: 133.71924 | AD19: 135.16911 | AE19: 137.06503 | AF19: 0.010533
A20: TKI000:ba_FreightTrucks | B20: Freight Trucks greater than 10,000 pounds | C20: 321.95499 | D20: 320.72061 | E20: 321.15665 | F20: 324.03918 | G20: 328.45148 | H20: 332.31928 | I20: 335.87875 | J20: 338.621 | K20: 341.15326 | L20: 344.16229 | M20: 348.16583 | N20: 351.54123 | O20: 354.83011 | P20: 358.3447 | Q20: 361.39355 | R20: 364.92679 | S20: 368.38065 | T20: 371.81143 | U20: 375.58807 | V20: 379.58752 | W20: 383.51465 | X20: 387.20883 | Y20: 390.63339 | Z20: 393.83795 | AA20: 397.54263 | AB20: 401.35467 | AC20: 404.65982 | AD20: 408.22446 | AE20: 413.08252 | AF20: 0.008941
B21: (billion passenger miles traveled)
A22: TKI000:buspassmiles | B22: Bus Transportation | C22: 175.47365 | D22: 186.88329 | E22: 193.3692 | F22: 197.39229 | G22: 200.32752 | H22: 202.52968 | I22: 204.21141 | J22: 205.46838 | K22: 206.39357 | L22: 207.0294 | M22: 207.54085 | N22: 207.99565 | O22: 208.43976 | P22: 208.79684 | Q22: 209.10339 | R22: 209.37013 | S22: 209.49379 | T22: 209.54416 | U22: 209.54358 | V22: 209.49118 | W22: 209.41185 | X22: 209.25844 | Y22: 209.10913 | Z22: 208.93102 | AA22: 208.81189 | AB22: 208.60612 | AC22: 208.41769 | AD22: 208.19235 | AE22: 207.99593 | AF22: 0.006091
A23: TKI000:railpassmiles | B23: Passenger Rail | C23: 30.144947 | D23: 32.030231 | E23: 33.06411 | F23: 33.706196 | G23: 34.620327 | H23: 35.443916 | I23: 36.137474 | J23: 36.650322 | K23: 37.00806 | L23: 37.264553 | M23: 37.633518 | N23: 38.06789 | O23: 38.564194 | P23: 38.985653 | Q23: 39.398945 | R23: 39.809189 | S23: 40.237045 | T23: 40.652229 | U23: 41.127975 | V23: 41.567631 | W23: 42.019573 | X23: 42.40731 | Y23: 42.842342 | Z23: 43.266335 | AA23: 43.867863 | AB23: 44.361511 | AC23: 44.905075 | AD23: 45.395485 | AE23: 46.002594 | AF23: 0.01521
B24: (billion seat miles available)
A25: TKI000:ba_Air | B25: Air | C25: 1173.0347 | D25: 1318.6946 | E25: 1361.6111 | F25: 1371.6552 | G25: 1402.928 | H25: 1433.8398 | I25: 1461.4722 | J25: 1484.8291 | K25: 1504.2688 | L25: 1524.7269 | M25: 1552.2568 | N25: 1583.9248 | O25: 1615.3802 | P25: 1647.3462 | Q25: 1682.5896 | R25: 1721.0469 | S25: 1761.139 | T25: 1801.941 | U25: 1848.072 | V25: 1894.2041 | W25: 1941.463 | X25: 1990.3643 | Y25: 2038.4374 | Z25: 2085.6875 | AA25: 2134.0049 | AB25: 2185.897 | AC25: 2238.8362 | AD25: 2292.3555 | AE25: 2350.269 | AF25: 0.02513
B26: (billion ton miles traveled)
A27: TKI000:ba_Rail | B27: Rail | C27: 1620.4949 | D27: 1600.1008 | E27: 1666.9198 | F27: 1628.4084 | G27: 1561.4207 | H27: 1509.6494 | I27: 1489.7312 | J27: 1507.5151 | K27: 1500.1649 | L27: 1506.9524 | M27: 1522.1982 | N27: 1534.7394 | O27: 1543.2374 | P27: 1554.5907 | Q27: 1557.5254 | R27: 1562.4816 | S27: 1568.9661 | T27: 1568.3395 | U27: 1571.7775 | V27: 1585.6112 | W27: 1597.307 | X27: 1600.1909 | Y27: 1601.8328 | Z27: 1602.9988 | AA27: 1608.1294 | AB27: 1618.0824 | AC27: 1630.808 | AD27: 1636.8905 | AE27: 1649.4695 | AF27: 0.000633
A28: TKI000:ba_DomesticShipp | B28: Domestic Shipping | C28: 444.89887 | D28: 450.42761 | E28: 448.61005 | F28: 446.74628 | G28: 445.22772 | H28: 442.84778 | I28: 440.43005 | J28: 437.0246 | K28: 434.03641 | L28: 431.39212 | M28: 429.99737 | N28: 428.16068 | O28: 426.27862 | P28: 424.17816 | Q28: 421.71698 | R28: 419.81464 | S28: 417.56705 | T28: 415.80768 | U28: 414.04514 | V28: 412.52209 | W28: 411.24774 | X28: 409.97736 | Y28: 408.52225 | Z28: 406.63034 | AA28: 405.35852 | AB28: 403.86591 | AC28: 401.97906 | AD28: 400.55664 | AE28: 400.09833 | AF28: -0.003783
B30: Energy Efficiency Indicators
B31: (miles per gallon)
A32: TKI000:ca_AvgCAFEStand | B32: New Light-Duty Vehicle CAFE Standard 2/ | C32: 35.855949 | D32: 36.277985 | E32: 39.337013 | F32: 42.578201 | G32: 47.262627 | H32: 47.227249 | I32: 47.18121 | J32: 47.168774 | K32: 47.163849 | L32: 47.152081 | M32: 47.159279 | N32: 47.152672 | O32: 47.146118 | P32: 47.131687 | Q32: 47.138325 | R32: 47.119869 | S32: 47.100937 | T32: 47.084251 | U32: 47.059879 | V32: 47.032314 | W32: 47.004074 | X32: 46.960155 | Y32: 46.939564 | Z32: 46.91069 | AA32: 46.948238 | AB32: 46.913113 | AC32: 46.90683 | AD32: 46.880138 | AE32: 46.870857 | AF32: 0.009613
A33: TKI000:ca_CarCAFEStand | B33: New Car 2/ | C33: 45.004654 | D33: 45.471119 | E33: 49.460312 | F33: 53.789036 | G33: 59.791531 | H33: 59.80352 | I33: 59.817413 | J33: 59.819332 | K33: 59.821598 | L33: 59.822445 | M33: 59.827473 | N33: 59.828793 | O33: 59.83078 | P33: 59.83112 | Q33: 59.842136 | R33: 59.842136 | S33: 59.842136 | T33: 59.843197 | U33: 59.843197 | V33: 59.843231 | W33: 59.845177 | X33: 59.845177 | Y33: 59.848228 | Z33: 59.848228 | AA33: 59.867775 | AB33: 59.867775 | AC33: 59.867775 | AD33: 59.867775 | AE33: 59.867775 | AF33: 0.010244
A34: TKI000:ca_TwukCAFEStand | B34: New Light Truck 2/ | C34: 32.047302 | D34: 32.608868 | E34: 35.403008 | F34: 38.46349 | G34: 42.755749 | H34: 42.75658 | I34: 42.76173 | J34: 42.76173 | K34: 42.761841 | L34: 42.762085 | M34: 42.762169 | N34: 42.76236 | O34: 42.76239 | P34: 42.76252 | Q34: 42.762554 | R34: 42.762699 | S34: 42.762756 | T34: 42.762825 | U34: 42.762897 | V34: 42.762962 | W34: 42.763016 | X34: 42.763103 | Y34: 42.763103 | Z34: 42.763184 | AA34: 42.763184 | AB34: 42.763294 | AC34: 42.763294 | AD34: 42.763393 | AE34: 42.763393 | AF34: 0.010356
A35: TKI000:ca_NewVehCred | B35: Compliance New Light-Duty Vehicle 3/ | C35: 41.802036 | D35: 43.2672 | E35: 44.448151 | F35: 47.052715 | G35: 48.571758 | H35: 49.79253 | I35: 52.281479 | J35: 53.248959 | K35: 53.962006 | L35: 54.332035 | M35: 54.872646 | N35: 55.329353 | O35: 55.771633 | P35: 56.242725 | Q35: 56.632603 | R35: 56.856194 | S35: 57.030457 | T35: 57.310715 | U35: 57.240421 | V35: 57.306023 | W35: 57.371868 | X35: 57.326744 | Y35: 57.237999 | Z35: 57.125122 | AA35: 57.475964 | AB35: 57.327747 | AC35: 57.273457 | AD35: 57.524818 | AE35: 57.479156 | AF35: 0.011439
A36: TKI000:ca_NewCarCred | B36: New Car 3/ | C36: 56.582645 | D36: 58.322227 | E36: 59.783314 | F36: 64.222374 | G36: 65.997482 | H36: 68.148636 | I36: 72.759445 | J36: 74.876167 | K36: 76.446304 | L36: 77.157303 | M36: 78.145363 | N36: 78.735664 | O36: 79.269257 | P36: 79.864815 | Q36: 80.311752 | R36: 80.510567 | S36: 80.643074 | T36: 81.042244 | U36: 80.790894 | V36: 80.999863 | W36: 81.213394 | X36: 81.251564 | Y36: 81.126785 | Z36: 80.963654 | AA36: 81.962257 | AB36: 81.685669 | AC36: 81.57402 | AD36: 82.338425 | AE36: 82.243484 | AF36: 0.013446
A37: TKI000:ca_NewTwukCred | B37: New Light Truck 3/ | C37: 36.263931 | D37: 37.832123 | E37: 39.014805 | F37: 41.375153 | G37: 42.876762 | H37: 43.911583 | I37: 45.953789 | J37: 46.678478 | K37: 47.207012 | L37: 47.518375 | M37: 47.939487 | N37: 48.362621 | O37: 48.779861 | P37: 49.233047 | Q37: 49.585567 | R37: 49.838345 | S37: 50.048077 | T37: 50.325745 | U37: 50.338009 | V37: 50.426777 | W37: 50.517311 | X37: 50.542614 | Y37: 50.50412 | Z37: 50.459385 | AA37: 50.61805 | AB37: 50.565735 | AC37: 50.535652 | AD37: 50.739391 | AE37: 50.721836 | AF37: 0.012055
A38: TKI000:ca_TestedNewVeh | B38: Tested New Light-Duty Vehicle 4/ | C38: 37.621078 | D38: 38.382416 | E38: 39.075672 | F38: 40.794502 | G38: 41.684994 | H38: 42.387779 | I38: 43.992405 | J38: 44.482399 | K38: 44.828846 | L38: 45.012852 | M38: 45.295109 | N38: 45.54966 | O38: 45.800465 | P38: 46.072914 | Q38: 46.308186 | R38: 46.454895 | S38: 46.573441 | T38: 46.763412 | U38: 46.743324 | V38: 46.781216 | W38: 46.812752 | X38: 46.781078 | Y38: 46.720787 | Z38: 46.649311 | AA38: 46.812588 | AB38: 46.721981 | AC38: 46.686661 | AD38: 46.844208 | AE38: 46.809135 | AF38: 0.007835
A39: TKI000:ca_TestedNewCar | B39: New Car 4/ | C39: 49.658657 | D39: 50.63982 | E39: 51.418789 | F39: 54.041267 | G39: 54.808311 | H39: 55.812794 | I39: 58.414131 | J39: 59.295654 | K39: 59.885937 | L39: 60.128426 | M39: 60.482559 | N39: 60.696911 | O39: 60.896141 | P39: 61.139969 | Q39: 61.34211 | R39: 61.456459 | S39: 61.54549 | T39: 61.791069 | U39: 61.720493 | V39: 61.820892 | W39: 61.909645 | X39: 61.923454 | Y39: 61.848679 | Z39: 61.762375 | AA39: 62.120819 | AB39: 61.989952 | AC39: 61.932671 | AD39: 62.331699 | AE39: 62.272804 | AF39: 0.008117
A40: TKI000:ca_TestedNewTwuk | B40: New Light Truck 4/ | C40: 32.951321 | D40: 33.82571 | E40: 34.570251 | F40: 36.235542 | G40: 37.203815 | H40: 37.859802 | I40: 39.251301 | J40: 39.65464 | K40: 39.942871 | L40: 40.123779 | M40: 40.372108 | N40: 40.635685 | O40: 40.898228 | P40: 41.187042 | Q40: 41.415565 | R40: 41.589336 | S40: 41.735809 | T40: 41.930031 | U40: 41.954327 | V40: 42.014381 | W40: 42.070942 | X40: 42.089371 | Y40: 42.062252 | Z40: 42.034523 | AA40: 42.106945 | AB40: 42.074627 | AC40: 42.053329 | AD40: 42.192116 | AE40: 42.17543 | AF40: 0.008853
A41: TKI000:ca_OnRoadNewVeh | B41: On-Road New Light-Duty Vehicle 5/ | C41: 30.687853 | D41: 31.308468 | E41: 31.873775 | F41: 33.275242 | G41: 34.001518 | H41: 34.574638 | I41: 35.883228 | J41: 36.28281 | K41: 36.56535 | L41: 36.715401 | M41: 36.945652 | N41: 37.153278 | O41: 37.357868 | P41: 37.580082 | Q41: 37.772026 | R41: 37.891651 | S41: 37.988308 | T41: 38.143211 | U41: 38.126759 | V41: 38.157574 | W41: 38.183201 | X41: 38.157219 | Y41: 38.107975 | Z41: 38.049587 | AA41: 38.182838 | AB41: 38.108822 | AC41: 38.080002 | AD41: 38.208389 | AE41: 38.179749 | AF41: 0.007832
A42: TKI000:ca_OnRoadNewCar | B42: New Car 5/ | C42: 40.552002 | D42: 41.353237 | E42: 41.989353 | F42: 44.130909 | G42: 44.75729 | H42: 45.577564 | I42: 47.701855 | J42: 48.421719 | K42: 48.903755 | L42: 49.101772 | M42: 49.390965 | N42: 49.566006 | O42: 49.728703 | P42: 49.927814 | Q42: 50.092888 | R42: 50.186264 | S42: 50.258968 | T42: 50.459515 | U42: 50.401878 | V42: 50.483868 | W42: 50.556343 | X42: 50.567619 | Y42: 50.506557 | Z42: 50.436081 | AA42: 50.72879 | AB42: 50.621925 | AC42: 50.575146 | AD42: 50.901001 | AE42: 50.852905 | AF42: 0.008117
A43: TKI000:ca_OnRoadNewTwuk | B43: New Light Truck 5/ | C43: 26.867123 | D43: 27.580063 | E43: 28.18713 | F43: 29.544939 | G43: 30.334429 | H43: 30.869291 | I43: 32.00386 | J43: 32.332729 | K43: 32.567738 | L43: 32.715244 | M43: 32.917721 | N43: 33.132629 | O43: 33.346695 | P43: 33.582184 | Q43: 33.768513 | R43: 33.910198 | S43: 34.029625 | T43: 34.187984 | U43: 34.207794 | V43: 34.25676 | W43: 34.302879 | X43: 34.317905 | Y43: 34.295792 | Z43: 34.273186 | AA43: 34.332233 | AB43: 34.305882 | AC43: 34.288517 | AD43: 34.40168 | AE43: 34.388073 | AF43: 0.008853
... A47: TKI000:ca_FreightTruck | B47: Freight Truck | C47: 7.472406 | D47: 7.578529 | E47: 7.705323 | F47: 7.84859 | G47: 8.002383 | H47: 8.163677 | I47: 8.321285 | J47: 8.479755 | K47: 8.638294 | L47: 8.79593 | M47: 8.948549 | N47: 9.090997 | O47: 9.222516 | P47: 9.343068 | Q47: 9.453315 | R47: 9.553063 | S47: 9.643444 | T47: 9.72671 | U47: 9.804593 | V47: 9.877275 | W47: 9.942431 | X47: 10.001567 | Y47: 10.055841 | Z47: 10.108454 | AA47: 10.161228 | AB47: 10.213311 | AC47: 10.263764 | AD47: 10.314513 | AE47: 10.365861 | AF47: 0.011758
B48: (seat miles per gallon)
A49: TKI000:ca_Aircraft | B49: Aircraft | C49: 72.717087 | D49: 73.091972 | E49: 73.492531 | F49: 74.018456 | G49: 74.683121 | H49: 75.131767 | I49: 75.59214 | J49: 76.024017 | K49: 76.492363 | L49: 77.014214 | M49: 77.60096 | N49: 78.266678 | O49: 78.981506 | P49: 79.730591 | Q49: 80.48922 | R49: 81.260979 | S49: 82.048454 | T49: 82.814575 | U49: 83.594772 | V49: 84.382309 | W49: 85.171204 | X49: 85.974022 | Y49: 86.764038 | Z49: 87.549927 | AA49: 88.321091 | AB49: 89.091156 | AC49: 89.849762 | AD49: 90.593376 | AE49: 91.328148 | AF49: 0.008172
B50: (ton miles/thousand Btu)
A51: TKI000:ca_Rail | B51: Rail | C51: 3.36634 | D51: 3.369893 | E51: 3.37345 | F51: 3.37701 | G51: 3.380574 | H51: 3.384142 | I51: 3.387713 | J51: 3.391289 | K51: 3.394868 | L51: 3.398451 | M51: 3.402037 | N51: 3.405628 | O51: 3.409222 | P51: 3.41282 | Q51: 3.416422 | R51: 3.420027 | S51: 3.423637 | T51: 3.42725 | U51: 3.430867 | V51: 3.434488 | W51: 3.438113 | X51: 3.441741 | Y51: 3.445373 | Z51: 3.44901 | AA51: 3.452649 | AB51: 3.456293 | AC51: 3.459941 | AD51: 3.463593 | AE51: 3.467248 | AF51: 0.001055
A52: TKI000:ca_DomesticShipp | B52: Domestic Shipping | C52: 4.820226 | D52: 4.838966 | E52: 4.857779 | F52: 4.876665 | G52: 4.895624 | H52: 4.914657 | I52: 4.933764 | J52: 4.952945 | K52: 4.9722 | L52: 4.991531 | M52: 5.010937 | N52: 5.030418 | O52: 5.049975 | P52: 5.069608 | Q52: 5.089317 | R52: 5.109103 | S52: 5.128966 | T52: 5.148906 | U52: 5.168923 | V52: 5.189019 | W52: 5.209192 | X52: 5.229445 | Y52: 5.249775 | Z52: 5.270185 | AA52: 5.290674 | AB52: 5.311243 | AC52: 5.331892 | AD52: 5.352621 | AE52: 5.37343 | AF52: 0.003888
B54: Energy Use by Mode
B55: (quadrillion Btu)
A56: TKI000:da_Light-DutyVeh | B56: Light-Duty Vehicles | C56: 14.541973 | D56: 14.586114 | E56: 14.429692 | F56: 14.201925 | G56: 14.016909 | H56: 13.860763 | I56: 13.679087 | J56: 13.473832 | K56: 13.253083 | L56: 13.044086 | M56: 12.836978 | N56: 12.674039 | O56: 12.534656 | P56: 12.394664 | Q56: 12.251548 | R56: 12.130822 | S56: 12.028416 | T56: 11.933923 | U56: 11.864001 | V56: 11.805396 | W56: 11.762742 | X56: 11.733644 | Y56: 11.725387 | Z56: 11.735775 | AA56: 11.770763 | AB56: 11.824349 | AC56: 11.889715 | AD56: 11.96291 | AE56: 12.054455 | AF56: -0.006678
A57: TKI000:da_CommercialLig | B57: Commercial Light Trucks 1/ | C57: 0.951503 | D57: 0.942558 | E57: 0.92534 | F57: 0.912452 | G57: 0.903111 | H57: 0.894807 | I57: 0.888385 | J57: 0.882995 | K57: 0.877033 | L57: 0.872791 | M57: 0.871791 | N57: 0.871868 | O57: 0.873034 | P57: 0.875074 | Q57: 0.8775 | R57: 0.881023 | S57: 0.885541 | T57: 0.889796 | U57: 0.896146 | V57: 0.903924 | W57: 0.911921 | X57: 0.918675 | Y57: 0.924721 | Z57: 0.93183 | AA57: 0.93994 | AB57: 0.94995 | AC57: 0.95832 | AD57: 0.96721 | AE57: 0.978898 | AF57: 0.001014
A58: TKI000:da_BusTransporta | B58: Bus Transportation | C58: 0.212163 | D58: 0.222312 | E58: 0.226957 | F58: 0.228013 | G58: 0.228798 | H58: 0.229238 | I58: 0.229403 | J58: 0.229156 | K58: 0.228548 | L58: 0.227556 | M58: 0.22653 | N58: 0.226005 | O58: 0.225336 | P58: 0.224473 | Q58: 0.223496 | R58: 0.22194 | S58: 0.220576 | T58: 0.219099 | U58: 0.2175 | V58: 0.215784 | W58: 0.214032 | X58: 0.212017 | Y58: 0.210154 | Z58: 0.208215 | AA58: 0.206535 | AB58: 0.204463 | AC58: 0.20246 | AD58: 0.200282 | AE58: 0.198183 | AF58: -0.002432
A59: TKI000:da_FreightTrucks | B59: Freight Trucks | C59: 5.921126 | D59: 5.815005 | E59: 5.726179 | F59: 5.670887 | G59: 5.636415 | H59: 5.588956 | I59: 5.540693 | J59: 5.48039 | K59: 5.418849 | L59: 5.367491 | M59: 5.336062 | N59: 5.302126 | O59: 5.274123 | P59: 5.25631 | Q59: 5.237802 | R59: 5.232226 | S59: 5.230621 | T59: 5.23229 | U59: 5.241601 | V59: 5.256566 | W59: 5.274461 | X59: 5.292318 | Y59: 5.309026 | Z59: 5.323563 | AA59: 5.344643 | AB59: 5.367305 | AC59: 5.383854 | AD59: 5.403469 | AE59: 5.43954 | AF59: -0.003025
A60: TKI000:da_Rail,Passenge | B60: Rail, Passenger | C60: 0.043913 | D60: 0.045564 | E60: 0.046541 | F60: 0.047205 | G60: 0.0479 | H60: 0.048571 | I60: 0.049133 | J60: 0.049707 | K60: 0.05015 | L60: 0.050599 | M60: 0.05114 | N60: 0.051727 | O60: 0.052369 | P60: 0.052924 | Q60: 0.053457 | R60: 0.053973 | S60: 0.05451 | T60: 0.055034 | U60: 0.055627 | V60: 0.056181 | W60: 0.056754 | X60: 0.057258 | Y60: 0.057816 | Z60: 0.058367 | AA60: 0.059116 | AB60: 0.059751 | AC60: 0.060445 | AD60: 0.061081 | AE60: 0.061848 | AF60: 0.012306
A61: TKI000:da_Rail,Freight | B61: Rail, Freight | C61: 0.481382 | D61: 0.474822 | E61: 0.494129 | F61: 0.482204 | G61: 0.46188 | H61: 0.446095 | I61: 0.439745 | J61: 0.444526 | K61: 0.441892 | L61: 0.443423 | M61: 0.447437 | N61: 0.450648 | O61: 0.452666 | P61: 0.455515 | Q61: 0.455894 | R61: 0.456862 | S61: 0.458275 | T61: 0.457609 | U61: 0.458128 | V61: 0.461673 | W61: 0.464588 | X61: 0.464937 | Y61: 0.464923 | Z61: 0.464771 | AA61: 0.465767 | AB61: 0.468155 | AC61: 0.47134 | AD61: 0.472599 | AE61: 0.475729 | AF61: -0.000422
A62: TKI000:da_Shipping,Dome | B62: Shipping, Domestic | C62: 0.098239 | D62: 0.098921 | E62: 0.098115 | F62: 0.097346 | G62: 0.096686 | H62: 0.095823 | I62: 0.094965 | J62: 0.093891 | K62: 0.092919 | L62: 0.09203 | M62: 0.091401 | N62: 0.090674 | O62: 0.089934 | P62: 0.089169 | Q62: 0.088333 | R62: 0.087615 | S62: 0.086833 | T62: 0.086157 | U62: 0.085474 | V62: 0.084846 | W62: 0.084274 | X62: 0.083705 | Y62: 0.083103 | Z62: 0.082418 | AA62: 0.081856 | AB62: 0.081249 | AC62: 0.080573 | AD62: 0.07999 | AE62: 0.079593 | AF62: -0.007489
A63: TKI000:da_Shipping,Inte | B63: Shipping, International | C63: 0.935028 | D63: 0.88183 | E63: 0.877727 | F63: 0.878604 | G63: 0.87125 | H63: 0.868449 | I63: 0.862689 | J63: 0.859142 | K63: 0.856634 | L63: 0.857136 | M63: 0.857437 | N63: 0.858 | O63: 0.85776 | P63: 0.858218 | Q63: 0.857547 | R63: 0.857614 | S63: 0.857635 | T63: 0.85735 | U63: 0.857245 | V63: 0.857301 | W63: 0.85783 | X63: 0.85782 | Y63: 0.858048 | Z63: 0.858068 | AA63: 0.860633 | AB63: 0.860924 | AC63: 0.859834 | AD63: 0.859122 | AE63: 0.858095 | AF63: -0.003062
A64: TKI000:da_RecreationalB | B64: Recreational Boats | C64: 0.202837 | D64: 0.199163 | E64: 0.195805 | F64: 0.193737 | G64: 0.192813 | H64: 0.191897 | I64: 0.190734 | J64: 0.18921 | K64: 0.187404 | L64: 0.185677 | M64: 0.184467 | N64: 0.18361 | O64: 0.182778 | P64: 0.181998 | Q64: 0.18145 | R64: 0.181106 | S64: 0.180746 | T64: 0.180383 | U64: 0.180295 | V64: 0.180161 | W64: 0.179988 | X64: 0.179814 | Y64: 0.179557 | Z64: 0.179244 | AA64: 0.17895 | AB64: 0.178728 | AC64: 0.178491 | AD64: 0.178228 | AE64: 0.178156 | AF64: -0.004623
A65: TKI000:da_Air | B65: Air | C65: 2.802808 | D65: 3.008168 | E65: 3.051203 | F65: 3.057111 | G65: 3.095898 | H65: 3.134227 | I65: 3.164552 | J65: 3.187108 | K65: 3.202938 | L65: 3.218783 | M65: 3.243937 | N65: 3.270448 | O65: 3.294403 | P65: 3.322924 | Q65: 3.359825 | R65: 3.403895 | S65: 3.450172 | T65: 3.498488 | U65: 3.554644 | V65: 3.608403 | W65: 3.663098 | X65: 3.718625 | Y65: 3.77401 | Z65: 3.827919 | AA65: 3.880434 | AB65: 3.936738 | AC65: 3.993604 | AD65: 4.049651 | AE65: 4.112158 | AF65: 0.013784
A66: TKI000:da_MilitaryUse | B66: Military Use | C66: 0.430832 | D66: 0.433131 | E66: 0.433968 | F66: 0.434628 | G66: 0.435162 | H66: 0.435947 | I66: 0.436506 | J66: 0.436951 | K66: 0.437332 | L66: 0.437576 | M66: 0.437744 | N66: 0.437827 | O66: 0.437858 | P66: 0.437879 | Q66: 0.438004 | R66: 0.438203 | S66: 0.438412 | T66: 0.438631 | U66: 0.438858 | V66: 0.439093 | W66: 0.439335 | X66: 0.439584 | Y66: 0.439839 | Z66: 0.440099 | AA66: 0.440364 | AB66: 0.440633 | AC66: 0.440907 | AD66: 0.441184 | AE66: 0.441465 | AF66: 0.000871
A67: TKI000:da_Lubricants | B67: Lubricants | C67: 0.125945 | D67: 0.125925 | E67: 0.126012 | F67: 0.12605 | G67: 0.126114 | H67: 0.125984 | I67: 0.125853 | J67: 0.125755 | K67: 0.125652 | L67: 0.125546 | M67: 0.125439 | N67: 0.12533 | O67: 0.12525 | P67: 0.125225 | Q67: 0.125255 | R67: 0.125318 | S67: 0.125412 | T67: 0.125527 | U67: 0.125667 | V67: 0.125797 | W67: 0.125925 | X67: 0.126046 | Y67: 0.126166 | Z67: 0.12632 | AA67: 0.126492 | AB67: 0.126661 | AC67: 0.126811 | AD67: 0.126974 | AE67: 0.127159 | AF67: 0.000342
... A70: TKI000:da_Total | B70: Total | C70: 27.986006 | D70: 28.032028 | E70: 27.776655 | F70: 27.4657 | G70: 27.255045 | H70: 27.051918 | I70: 26.819283 | J70: 26.59227 | K70: 26.360722 | L70: 26.162958 | M70: 26.008129 | N70: 25.897749 | O70: 25.802094 | P70: 25.704212 | Q70: 25.598515 | R70: 25.533525 | S70: 25.493338 | T70: 25.449312 | U70: 25.46059 | V70: 25.485914 | W70: 25.531475 | X70: 25.583796 | Y70: 25.657438 | Z70: 25.744152 | AA70: 25.868387 | AB70: 26.019403 | AC70: 26.175444 | AD70: 26.332941 | AE70: 26.540415 | AF70: -0.001892
B72: (million barrels per day oil equivalent)
A73: TKI000:ea_Light-DutyVeh | B73: Light-Duty Vehicles | C73: 7.887402 | D73: 7.912227 | E73: 7.827434 | F73: 7.704175 | G73: 7.603646 | H73: 7.518498 | I73: 7.419035 | J73: 7.306525 | K73: 7.185357 | L73: 7.070691 | M73: 6.957016 | N73: 6.86728 | O73: 6.790267 | P73: 6.712955 | Q73: 6.633772 | R73: 6.566808 | S73: 6.509881 | T73: 6.457382 | U73: 6.418384 | V73: 6.385576 | W73: 6.361585 | X73: 6.345073 | Y73: 6.340106 | Z73: 6.345462 | AA73: 6.36419 | AB73: 6.393152 | AC73: 6.428598 | AD73: 6.468379 | AE73: 6.518199 | AF73: -0.006786
A74: TKI000:ea_CommercialLig | B74: Commercial Light Trucks 1/ | C74: 0.496809 | D74: 0.492193 | E74: 0.483314 | F74: 0.476842 | G74: 0.472221 | H74: 0.467932 | I74: 0.464712 | J74: 0.462053 | K74: 0.459111 | L74: 0.457084 | M74: 0.456754 | N74: 0.456989 | O74: 0.457814 | P74: 0.459091 | Q74: 0.460564 | R74: 0.462619 | S74: 0.465189 | T74: 0.467623 | U74: 0.471176 | V74: 0.475436 | W74: 0.479853 | X74: 0.483793 | Y74: 0.487354 | Z74: 0.491353 | AA74: 0.496003 | AB74: 0.501565 | AC74: 0.506491 | AD74: 0.511462 | AE74: 0.517981 | AF74: 0.001492
A75: TKI000:ea_BusTransporta | B75: Bus Transportation | C75: 0.105213 | D75: 0.110296 | E75: 0.11259 | F75: 0.113083 | G75: 0.113492 | H75: 0.113737 | I75: 0.113843 | J75: 0.113729 | K75: 0.113434 | L75: 0.112917 | M75: 0.112403 | N75: 0.112129 | O75: 0.111806 | P75: 0.111381 | Q75: 0.110915 | R75: 0.110151 | S75: 0.109477 | T75: 0.108762 | U75: 0.107969 | V75: 0.107129 | W75: 0.106288 | X75: 0.105307 | Y75: 0.104391 | Z75: 0.103434 | AA75: 0.102605 | AB75: 0.101578 | AC75: 0.100586 | AD75: 0.099507 | AE75: 0.09846 | AF75: -0.002366
A76: TKI000:ea_FreightTrucks | B76: Freight Trucks | C76: 2.850965 | D76: 2.800434 | E76: 2.758164 | F76: 2.732194 | G76: 2.716136 | H76: 2.693672 | I76: 2.671257 | J76: 2.642962 | K76: 2.614177 | L76: 2.590174 | M76: 2.575932 | N76: 2.560368 | O76: 2.547745 | P76: 2.539845 | Q76: 2.531643 | R76: 2.529634 | S76: 2.5295 | T76: 2.530971 | U76: 2.536117 | V76: 2.544034 | W76: 2.553331 | X76: 2.562598 | Y76: 2.571348 | Z76: 2.579022 | AA76: 2.589984 | AB76: 2.601707 | AC76: 2.610389 | AD76: 2.620612 | AE76: 2.638885 | AF76: -0.002757
A77: TKI000:ea_Rail,Passenge | B77: Rail, Passenger | C77: 0.020781 | D77: 0.021563 | E77: 0.022025 | F77: 0.02234 | G77: 0.022668 | H77: 0.022984 | I77: 0.023251 | J77: 0.023523 | K77: 0.023733 | L77: 0.023945 | M77: 0.024201 | N77: 0.024479 | O77: 0.024783 | P77: 0.025045 | Q77: 0.025298 | R77: 0.025542 | S77: 0.025796 | T77: 0.026044 | U77: 0.026325 | V77: 0.026587 | W77: 0.026858 | X77: 0.027097 | Y77: 0.027361 | Z77: 0.027622 | AA77: 0.027977 | AB77: 0.028278 | AC77: 0.028605 | AD77: 0.028906 | AE77: 0.02927 | AF77: 0.012308
A78: TKI000:ea_Rail,Freight | B78: Rail, Freight | C78: 0.228347 | D78: 0.225234 | E78: 0.234373 | F78: 0.228717 | G78: 0.21906 | H78: 0.211545 | I78: 0.208541 | J78: 0.210806 | K78: 0.209559 | L78: 0.210276 | M78: 0.212178 | N78: 0.213692 | O78: 0.21465 | P78: 0.215989 | Q78: 0.216165 | R78: 0.216616 | S78: 0.21728 | T78: 0.216956 | U78: 0.217194 | V78: 0.218865 | W78: 0.220234 | X78: 0.220387 | Y78: 0.22037 | Z78: 0.220283 | AA78: 0.220747 | AB78: 0.221866 | AC78: 0.223355 | AD78: 0.223935 | AE78: 0.225407 | AF78: -0.000463
A79: TKI000:ea_Shipping,Dome | B79: Shipping, Domestic | C79: 0.046527 | D79: 0.046853 | E79: 0.04647 | F79: 0.04611 | G79: 0.045796 | H79: 0.045385 | I79: 0.044983 | J79: 0.044476 | K79: 0.04402 | L79: 0.0436 | M79: 0.043306 | N79: 0.042963 | O79: 0.042617 | P79: 0.042256 | Q79: 0.041863 | R79: 0.041525 | S79: 0.041158 | T79: 0.04084 | U79: 0.040519 | V79: 0.040222 | W79: 0.03995 | X79: 0.039681 | Y79: 0.039395 | Z79: 0.03907 | AA79: 0.038805 | AB79: 0.038517 | AC79: 0.038196 | AD79: 0.037919 | AE79: 0.037732 | AF79: -0.007455
A80: TKI000:ea_Shipping,Inte | B80: Shipping, International | C80: 0.417032 | D80: 0.39771 | E80: 0.396229 | F80: 0.396613 | G80: 0.393975 | H80: 0.392997 | I80: 0.390956 | J80: 0.389709 | K80: 0.388847 | L80: 0.389075 | M80: 0.389247 | N80: 0.389507 | O80: 0.389481 | P80: 0.389698 | Q80: 0.389505 | R80: 0.389575 | S80: 0.389634 | T80: 0.389581 | U80: 0.389597 | V80: 0.38967 | W80: 0.389917 | X80: 0.389969 | Y80: 0.390113 | Z80: 0.390178 | AA80: 0.391183 | AB80: 0.391349 | AC80: 0.391006 | AD80: 0.3908 | AE80: 0.390489 | AF80: -0.002346
A81: TKI000:ea_RecreationalB | B81: Recreational Boats | C81: 0.110006 | D81: 0.108038 | E81: 0.106242 | F81: 0.105144 | G81: 0.104667 | H81: 0.104195 | I81: 0.103587 | J81: 0.102784 | K81: 0.101827 | L81: 0.100913 | M81: 0.100279 | N81: 0.099838 | O81: 0.099409 | P81: 0.099009 | Q81: 0.098731 | R81: 0.098564 | S81: 0.098387 | T81: 0.098209 | U81: 0.098181 | V81: 0.098125 | W81: 0.098049 | X81: 0.097971 | Y81: 0.097849 | Z81: 0.097695 | AA81: 0.097552 | AB81: 0.097448 | AC81: 0.097337 | AD81: 0.097211 | AE81: 0.097188 | AF81: -0.004415
A82: TKI000:ea_Air | B82: Air | C82: 1.355634 | D82: 1.454865 | E82: 1.475662 | F82: 1.478519 | G82: 1.497263 | H82: 1.515786 | I82: 1.530442 | J82: 1.541344 | K82: 1.548995 | L82: 1.556654 | M82: 1.568811 | N82: 1.581624 | O82: 1.593202 | P82: 1.606986 | Q82: 1.624819 | R82: 1.646116 | S82: 1.668479 | T82: 1.691828 | U82: 1.718965 | V82: 1.744943 | W82: 1.771373 | X82: 1.798206 | Y82: 1.82497 | Z82: 1.851021 | AA82: 1.876398 | AB82: 1.903606 | AC82: 1.931086 | AD82: 1.95817 | AE82: 1.988375 | AF82: 0.013774
A83: TKI000:ea_MilitaryUse | B83: Military Use | C83: 0.207325 | D83: 0.208431 | E83: 0.20883 | F83: 0.209148 | G83: 0.209402 | H83: 0.209774 | I83: 0.210045 | J83: 0.210259 | K83: 0.210443 | L83: 0.21056 | M83: 0.210641 | N83: 0.21068 | O83: 0.210697 | P83: 0.210706 | Q83: 0.210766 | R83: 0.210862 | S83: 0.210964 | T83: 0.211069 | U83: 0.211179 | V83: 0.211292 | W83: 0.211409 | X83: 0.211529 | Y83: 0.211652 | Z83: 0.211777 | AA83: 0.211906 | AB83: 0.212036 | AC83: 0.212167 | AD83: 0.2123 | AE83: 0.212437 | AF83: 0.00087
A84: TKI000:ea_Lubricants | B84: Lubricants | C84: 0.059492 | D84: 0.059483 | E84: 0.059524 | F84: 0.059542 | G84: 0.059572 | H84: 0.059511 | I84: 0.059449 | J84: 0.059403 | K84: 0.059354 | L84: 0.059304 | M84: 0.059253 | N84: 0.059202 | O84: 0.059164 | P84: 0.059152 | Q84: 0.059166 | R84: 0.059196 | S84: 0.05924 | T84: 0.059295 | U84: 0.059361 | V84: 0.059422 | W84: 0.059483 | X84: 0.05954 | Y84: 0.059597 | Z84: 0.059669 | AA84: 0.059751 | AB84: 0.05983 | AC84: 0.059901 | AD84: 0.059978 | AE84: 0.060066 | AF84: 0.000342
... A87: TKI000:ea_Total | B87: Total | C87: 14.370443 | D87: 14.403465 | E87: 14.271711 | F87: 14.108815 | G87: 13.997396 | H87: 13.890337 | I87: 13.767988 | J87: 13.645885 | K87: 13.520164 | L87: 13.411051 | M87: 13.323045 | N87: 13.25902 | O87: 13.203858 | P87: 13.147519 | Q87: 13.087383 | R87: 13.048246 | S87: 13.022289 | T87: 12.995312 | U87: 12.996621 | V87: 13.0055 | W87: 13.025239 | X87: 13.049395 | Y87: 13.085273 | Z87: 13.128707 | AA87: 13.19174 | AB87: 13.269163 | AC87: 13.350009 | AD87: 13.432016 | AE87: 13.539635 | AF87: -0.002125
B89: 1/ Commercial trucks have a 8,501 to 10,000 pound gross vehicle weight rating.
B90: 2/ CAFE standard based on projected new vehicle sales.
B91: 3/ Includes CAFE credits for alternative fueled vehicle sales and credit banking.
B92: 4/ U.S. Environmental Protection Agency rated miles per gallon.
B93: 5/ Tested new vehicle efficiency revised for on-road performance.
B94: 6/ Combined "on-the-road" estimate for all cars and light trucks.
B95: 7/ Fuel used in facilities that liquefy natural gas for export.
B96: CAFE = Corporate average fuel economy.
B97: Btu = British thermal unit.
B98: Note: Totals may not equal sum of components due to independent rounding.
B99: Data source: 2022: U.S. Energy Information Administration (EIA), Short-Term Energy Outlook, November 2022 and EIA, AEO2023
B100: AEO2023 National Energy Modeling System run ref2023.d020623a. Projections: EIA, AEO2023 National Energy Modeling System run ref2023.d020623a.

Sheet AEO 2023 35
E1: 2021 | F1: 2022 | G1: 2023 | H1: 2024 | I1: 2025 | J1: 2026 | K1: 2027 | L1: 2028 | M1: 2029 | N1: 2030 | O1: 2031 | P1: 2032 | Q1: 2033 | R1: 2034 | S1: 2035 | T1: 2036 | U1: 2037 | V1: 2038 | W1: 2039 | X1: 2040 | Y1: 2041 | Z1: 2042 | AA1: 2043 | AB1: 2044 | AC1: 2045 | AD1: 2046 | AE1: 2047 | AF1: 2048 | AG1: 2049 | AH1: 2050 | AI1: Growth (2022-2050)
A10: Table 35. Transportation Sector Energy Use by Mode and Type
A11: https://www.eia.gov/outlooks/aeo/data/browser/#/?id=45-AEO2023&cases=ref2023&sourcekey=0
A12: Thu Dec 11 2025 13:26:03 GMT-0800 (Pacific Standard Time)
A13: Source: U.S. Energy Information Administration
B14: full name | C14: api key | D14: units | E14: 2021 | F14: 2022 | G14: 2023 | H14: 2024 | I14: 2025 | J14: 2026 | K14: 2027 | L14: 2028 | M14: 2029 | N14: 2030 | O14: 2031 | P14: 2032 | Q14: 2033 | R14: 2034 | S14: 2035 | T14: 2036 | U14: 2037 | V14: 2038 | W14: 2039 | X14: 2040 | Y14: 2041 | Z14: 2042 | AA14: 2043 | AB14: 2044 | AC14: 2045 | AD14: 2046 | AE14: 2047 | AF14: 2048 | AG14: 2049 | AH14: 2050 | AI14: Growth (2022-2050)
A15: Energy Use by Mode
A16: Highway
A17: Light-Duty Vehicles | B17: Transportation Energy Use: Highway: Light-Duty Vehicles: Reference case | C17: AEO.2023.REF2023.CNSM_NA_TRN_HWY_LDV_NA_NA_TRLBTU.A | D17: trillion Btu | F17: 14541.974 | G17: 14586.115 | H17: 14429.693 | I17: 14201.927 | J17: 14016.909 | K17: 13860.764 | L17: 13679.089 | M17: 13473.833 | N17: 13253.084 | O17: 13044.087 | P17: 12836.979 | Q17: 12674.041 | R17: 12534.656 | S17: 12394.664 | T17: 12251.55 | U17: 12130.824 | V17: 12028.419 | W17: 11933.924 | X17: 11864.004 | Y17: 11805.398 | Z17: 11762.744 | AA17: 11733.646 | AB17: 11725.389 | AC17: 11735.777 | AD17: 11770.766 | AE17: 11824.353 | AF17: 11889.718 | AG17: 11962.912 | AH17: 12054.456 | AI17: -0.007
A18: Automobiles | B18: Transportation Energy Use: Highway: Light-Duty Vehicles: Automobiles: Reference case | C18: AEO.2023.REF2023.CNSM_NA_TRN_HWY_LDV_AUTO_NA_TRLBTU.A | D18: trillion Btu | F18: 5654.1606 | G18: 5526.6772 | H18: 5311.813 | I18: 5067.3223 | J18: 4838.1689 | K18: 4619.4316 | L18: 4397.4468 | M18: 4169.8599 | N18: 3944.7561 | O18: 3731.1753 | P18: 3530.8748 | Q18: 3355.2742 | R18: 3201.8225 | S18: 3058.1055 | T18: 2927.6711 | U18: 2817.0913 | V18: 2726.7456 | W18: 2648.3855 | X18: 2585.8064 | Y18: 2534.5078 | Z18: 2494.8418 | AA18: 2463.2471 | AB18: 2438.6992 | AC18: 2420.9849 | AD18: 2411.0181 | AE18: 2405.7183 | AF18: 2403.655 | AG18: 2402.5029 | AH18: 2405.8833 | AI18: -0.03
A19: Light Trucks | B19: Transportation Energy Use: Highway: Light-Duty Vehicles: Light Trucks: Reference case | C19: AEO.2023.REF2023.CNSM_NA_TRN_HWY_LDV_LTRT_NA_TRLBTU.A | D19: trillion Btu | F19: 8871.5508 | G19: 9043.541 | H19: 9102.6006 | I19: 9120.0283 | J19: 9164.8242 | K19: 9228.0459 | L19: 9268.9941 | M19: 9291.9814 | N19: 9296.9863 | O19: 9302.1855 | P19: 9295.9561 | Q19: 9309.126 | R19: 9323.6357 | S19: 9327.7764 | T19: 9315.4736 | U19: 9305.6484 | V19: 9293.8496 | W19: 9277.9414 | X19: 9270.7812 | Y19: 9263.6221 | Z19: 9260.7471 | AA19: 9263.335 | AB19: 9279.6943 | AC19: 9307.8467 | AD19: 9352.8291 | AE19: 9411.7305 | AF19: 9479.1641 | AG19: 9553.5127 | AH19: 9641.666 | AI19: 0.003
A20: Motorcycles | B20: Transportation Energy Use: Highway: Light-Duty Vehicles: Motorcycles: Reference case | C20: AEO.2023.REF2023.CNSM_NA_TRN_HWY_LDV_MCYCL_NA_TRLBTU.A | D20: trillion Btu | F20: 16.262892 | G20: 15.896933 | H20: 15.278913 | I20: 14.5757 | J20: 13.916059 | K20: 13.285933 | L20: 12.647085 | M20: 11.991311 | N20: 11.342273 | O20: 10.726049 | P20: 10.148347 | Q20: 9.640781 | R20: 9.197762 | S20: 8.782386 | T20: 8.404802 | U20: 8.084402 | V20: 7.823192 | W20: 7.596957 | X20: 7.416474 | Y20: 7.268723 | Z20: 7.155083 | AA20: 7.064892 | AB20: 6.994964 | AC20: 6.945127 | AD20: 6.917612 | AE20: 6.903515 | AF20: 6.898674 | AG20: 6.896451 | AH20: 6.90719 | AI20: -0.03
A21: Commercial Light Trucks | B21: Transportation Energy Use: Highway: Commercial Light Trucks: Reference case | C21: AEO.2023.REF2023.CNSM_NA_TRN_HWY_CML_NA_NA_TRLBTU.A | D21: trillion Btu | F21: 951.50293 | G21: 942.55829 | H21: 925.34027 | I21: 912.45172 | J21: 903.11078 | K21: 894.80676 | L21: 888.38452 | M21: 882.99542 | N21: 877.03253 | O21: 872.79089 | P21: 871.79065 | Q21: 871.86749 | R21: 873.03369 | S21: 875.07349 | T21: 877.49945 | U21: 881.02332 | V21: 885.54089 | W21: 889.79602 | X21: 896.14636 | Y21: 903.92444 | Z21: 911.92096 | AA21: 918.6748 | AB21: 924.72058 | AC21: 931.8302 | AD21: 939.93994 | AE21: 949.95038 | AF21: 958.32001 | AG21: 967.2102 | AH21: 978.89801 | AI21: 0.001
A22: Buses | B22: Transportation Energy Use: Highway: Buses: Reference case | C22: AEO.2023.REF2023.CNSM_NA_TRN_HWY_BUS_NA_NA_TRLBTU.A | D22: trillion Btu | F22: 212.16301 | G22: 222.31247 | H22: 226.95673 | I22: 228.01268 | J22: 228.79755 | K22: 229.23793 | L22: 229.40265 | M22: 229.15626 | N22: 228.54794 | O22: 227.55568 | P22: 226.52992 | Q22: 226.00464 | R22: 225.33565 | S22: 224.47317 | T22: 223.49628 | U22: 221.94028 | V22: 220.57585 | W22: 219.0985 | X22: 217.49985 | Y22: 215.78369 | Z22: 214.03241 | AA22: 212.01721 | AB22: 210.15359 | AC22: 208.21464 | AD22: 206.53474 | AE22: 204.46298 | AF22: 202.45996 | AG22: 200.28244 | AH22: 198.18263 | AI22: -0.002
A23: Transit | B23: Transportation Energy Use: Highway: Buses: Transit: Reference case | C23: AEO.2023.REF2023.CNSM_NA_TRN_HWY_BUS_TNST_NA_TRLBTU.A | D23: trillion Btu | F23: 92.212234 | G23: 95.83783 | H23: 98.320953 | I23: 98.870079 | J23: 99.844643 | K23: 100.61442 | L23: 101.24708 | M23: 101.61662 | N23: 101.72417 | O23: 101.53801 | P23: 101.31126 | Q23: 100.9764 | R23: 100.75687 | S23: 100.29507 | T23: 99.678467 | U23: 98.421806 | V23: 97.683716 | W23: 96.918678 | X23: 96.071007 | Y23: 95.130722 | Z23: 94.233086 | AA23: 93.123825 | AB23: 92.2043 | AC23: 91.250328 | AD23: 90.65873 | AE23: 89.694473 | AF23: 88.826485 | AG23: 87.819649 | AH23: 86.904648 | AI23: -0.002
A24: Intercity | B24: Transportation Energy Use: Highway: Buses: Intercity: Reference case | C24: AEO.2023.REF2023.CNSM_NA_TRN_HWY_BUS_ICYT_NA_TRLBTU.A | D24: trillion Btu | F24: 26.118862 | G24: 28.024412 | H24: 29.477226 | I24: 30.571621 | J24: 31.3964 | K24: 32.010113 | L24: 32.464531 | M24: 32.799759 | N24: 33.046234 | O24: 33.226051 | P24: 33.352478 | Q24: 33.43018 | R24: 33.466476 | S24: 33.46925 | T24: 33.44516 | U24: 33.397396 | V24: 33.349758 | W24: 33.294384 | X24: 33.234276 | Y24: 33.167286 | Z24: 33.096901 | AA24: 33.025082 | AB24: 32.951077 | AC24: 32.875145 | AD24: 32.799278 | AE24: 32.723492 | AF24: 32.646706 | AG24: 32.56945 | AH24: 32.494362 | AI24: 0.008
A25: School | B25: Transportation Energy Use: Highway: Buses: School: Reference case | C25: AEO.2023.REF2023.CNSM_NA_TRN_HWY_BUS_SCBU_NA_TRLBTU.A | D25: trillion Btu | F25: 93.831894 | G25: 98.450195 | H25: 99.158546 | I25: 98.571014 | J25: 97.556511 | K25: 96.613396 | L25: 95.691032 | M25: 94.739861 | N25: 93.77755 | O25: 92.791618 | P25: 91.866196 | Q25: 91.598053 | R25: 91.112289 | S25: 90.70887 | T25: 90.37265 | U25: 90.12104 | V25: 89.542336 | W25: 88.885452 | X25: 88.194603 | Y25: 87.485649 | Z25: 86.702446 | AA25: 85.868294 | AB25: 84.99823 | AC25: 84.089134 | AD25: 83.076744 | AE25: 82.045021 | AF25: 80.986786 | AG25: 79.893326 | AH25: 78.783607 | AI25: -0.006
A26: Freight Trucks | B26: Transportation Energy Use: Highway: Freight Trucks: Reference case | C26: AEO.2023.REF2023.CNSM_NA_TRN_HWY_FGHT_NA_NA_TRLBTU.A | D26: trillion Btu | F26: 5922.792 | G26: 5816.707 | H26: 5728.0947 | I26: 5673.0977 | J26: 5638.8965 | K26: 5591.7075 | L26: 5543.7109 | M26: 5483.6704 | N26: 5422.3882 | O26: 5371.3022 | P26: 5340.1582 | Q26: 5306.5054 | R26: 5278.7798 | S26: 5261.2461 | T26: 5243 | U26: 5237.6978 | V26: 5236.3613 | W26: 5238.3042 | X26: 5247.9146 | Y26: 5263.2085 | Z26: 5281.4546 | AA26: 5299.6816 | AB26: 5316.7661 | AC26: 5331.6992 | AD26: 5353.2002 | AE26: 5376.3174 | AF26: 5393.3188 | AG26: 5413.416 | AH26: 5450.0127 | AI26: -0.003
A27: Light Medium | B27: Transportation Energy Use: Highway: Freight Trucks: Light Medium: Reference case | C27: AEO.2023.REF2023.CNSM_NA_TRN_HWY_FGHT_LITEMED_NA_TRLBTU.A | D27: trillion Btu | F27: 745.82806 | G27: 731.17401 | H27: 720.99341 | I27: 716.52246 | J27: 715.17627 | K27: 711.7099 | L27: 708.54388 | M27: 705.98785 | N27: 706.4599 | O27: 710.45679 | P27: 717.79156 | Q27: 724.37231 | R27: 731.39038 | S27: 739.17932 | T27: 746.30853 | U27: 754.65619 | V27: 763.13739 | W27: 772.1521 | X27: 782.66339 | Y27: 794.23718 | Z27: 805.87262 | AA27: 817.30426 | AB27: 829.03217 | AC27: 841.80096 | AD27: 857.07477 | AE27: 873.44006 | AF27: 889.11859 | AG27: 905.95618 | AH27: 926.21399 | AI27: 0.008
A28: Medium | B28: Transportation Energy Use: Highway: Freight Trucks: Medium: Reference case | C28: AEO.2023.REF2023.CNSM_NA_TRN_HWY_FGHT_MD10T26KLB_NA_TRLBTU.A | D28: trillion Btu | F28: 969.69183 | G28: 947.22809 | H28: 929.37402 | I28: 917.57544 | J28: 910.67749 | K28: 903.25037 | L28: 897.46631 | M28: 890.09558 | N28: 882.57385 | O28: 876.55035 | P28: 874.65271 | Q28: 871.91071 | R28: 869.98096 | S28: 869.72485 | T28: 869.34759 | U28: 871.61865 | V28: 873.72833 | W28: 877.64197 | X28: 882.78259 | Y28: 889.237 | Z28: 896.04053 | AA28: 903.72443 | AB28: 911.77496 | AC28: 919.3786 | AD28: 928.10925 | AE28: 937.41211 | AF28: 945.94012 | AG28: 955.21368 | AH28: 967.38184 | AI28: 0
A29: Large (more than 26000 pounds) | B29: Transportation Energy Use: Highway: Freight Trucks: Large: Reference case | C29: AEO.2023.REF2023.#N/A.A | D29: trillion Btu | F29: 4207.2715 | G29: 4138.3047 | H29: 4077.7268 | I29: 4039 | J29: 4013.0432 | K29: 3976.7476 | L29: 3937.7007 | M29: 3887.5867 | N29: 3833.355 | O29: 3784.2954 | P29: 3747.7139 | Q29: 3710.2224 | R29: 3677.4087 | S29: 3652.342 | T29: 3627.3435 | U29: 3611.4229 | V29: 3599.4961 | W29: 3588.51 | X29: 3582.4688 | Y29: 3579.7341 | Z29: 3579.5413 | AA29: 3578.6533 | AB29: 3575.9597 | AC29: 3570.5195 | AD29: 3568.0156 | AE29: 3565.4651 | AF29: 3558.26 | AG29: 3552.2463 | AH29: 3556.4165 | AI29: -0.006
A30: Non-Highway
A31: Air | B31: Transportation Energy Use: Non-Highway: Air: Reference case | C31: AEO.2023.REF2023.CNSM_NA_TRN_AIR_NA_NA_NA_TRLBTU.A | D31: trillion Btu | F31: 2802.8074 | G31: 3008.168 | H31: 3051.2026 | I31: 3057.1106 | J31: 3095.8982 | K31: 3134.2271 | L31: 3164.5515 | M31: 3187.1079 | N31: 3202.9382 | O31: 3218.7827 | P31: 3243.9365 | Q31: 3270.4482 | R31: 3294.4031 | S31: 3322.9241 | T31: 3359.825 | U31: 3403.8945 | V31: 3450.1719 | W31: 3498.4883 | X31: 3554.6438 | Y31: 3608.4036 | Z31: 3663.0974 | AA31: 3718.6248 | AB31: 3774.01 | AC31: 3827.9189 | AD31: 3880.4333 | AE31: 3936.7383 | AF31: 3993.604 | AG31: 4049.6506 | AH31: 4112.1577 | AI31: 0.014
A32: General Aviation | B32: Transportation Energy Use: Non-Highway: Air: General Aviation: Reference case | C32: AEO.2023.REF2023.CNSM_NA_TRN_AIR_GAV_NA_NA_TRLBTU.A | D32: trillion Btu | F32: 154.82079 | G32: 164.58934 | H32: 166.63007 | I32: 166.90428 | J32: 168.74524 | K32: 170.56552 | L32: 172.0056 | M32: 173.07629 | N32: 173.82729 | O32: 174.57951 | P32: 175.77553 | Q32: 177.03632 | R32: 178.17583 | S32: 179.53285 | T32: 181.289 | U32: 183.38686 | V32: 185.59007 | W32: 187.89032 | X32: 190.56396 | Y32: 193.12366 | Z32: 195.72784 | AA32: 198.37164 | AB32: 201.00888 | AC32: 203.57585 | AD32: 206.07645 | AE32: 208.75748 | AF32: 211.46515 | AG32: 214.13402 | AH32: 217.1105 | AI32: 0.012
A33: Domestic Passenger | B33: Transportation Energy Use: Non-Highway: Air: Domestic Passenger: Reference case | C33: AEO.2023.REF2023.CNSM_NA_TRN_AIR_DAC_NA_NA_TRLBTU.A | D33: trillion Btu | F33: 1525.3719 | G33: 1568.4963 | H33: 1545.2438 | I33: 1539.9454 | J33: 1560.0005 | K33: 1578.9973 | L33: 1593.6608 | M33: 1603.7645 | N33: 1608.9692 | O33: 1613.8066 | P33: 1624.1025 | Q33: 1638.2094 | R33: 1651.6223 | S33: 1665.2513 | T33: 1681.9424 | U33: 1701.5503 | V33: 1722.4525 | W33: 1743.975 | X33: 1770.0122 | Y33: 1794.5861 | Z33: 1819.5831 | AA33: 1845.8711 | AB33: 1871.9424 | AC33: 1896.6277 | AD33: 1920.9094 | AE33: 1947.4875 | AF33: 1974.0907 | AG33: 2000.766 | AH33: 2030.3903 | AI33: 0.01
A34: International Passenger | B34: Transportation Energy Use: Non-Highway: Air: International Passenger: Reference case | C34: AEO.2023.REF2023.CNSM_NA_TRN_AIR_IAC_NA_NA_TRLBTU.A | D34: trillion Btu | F34: 586.70477 | G34: 755.09033 | H34: 825.08246 | I34: 835.10657 | J34: 847.74762 | K34: 860.41785 | L34: 870.67084 | M34: 878.74676 | N34: 885.43268 | O34: 892.21881 | P34: 901.3352 | Q34: 909.30804 | R34: 916.19775 | S34: 925.32129 | T34: 937.39001 | U34: 951.84992 | V34: 966.82947 | W34: 982.55957 | X34: 1000.3361 | Y34: 1017.5378 | Z34: 1035.0142 | AA34: 1052.2997 | AB34: 1069.5682 | AC34: 1086.702 | AD34: 1103.2957 | AE34: 1120.8325 | AF34: 1138.662 | AG34: 1156.0013 | AH34: 1175.4172 | AI34: 0.025
A35: Dedicated Freight | B35: Transportation Energy Use: Non-Highway: Air: Dedicated Freight: Reference case | C35: AEO.2023.REF2023.CNSM_NA_TRN_AIR_DFT_NA_NA_TRLBTU.A | D35: trillion Btu | F35: 535.90997 | G35: 519.99194 | H35: 514.24634 | I35: 515.1543 | J35: 519.40478 | K35: 524.24622 | L35: 528.21435 | M35: 531.52032 | N35: 534.70904 | O35: 538.17767 | P35: 542.72302 | Q35: 545.89441 | R35: 548.40717 | S35: 552.81854 | T35: 559.20331 | U35: 567.1073 | V35: 575.29974 | W35: 584.06348 | X35: 593.73175 | Y35: 603.15594 | Z35: 612.77222 | AA35: 622.08221 | AB35: 631.49048 | AC35: 641.01318 | AD35: 650.15185 | AE35: 659.66058 | AF35: 669.38611 | AG35: 678.74933 | AH35: 689.23981 | AI35: 0.009
A36: Water | B36: Transportation Energy Use: Non-Highway: Water: Reference case | C36: AEO.2023.REF2023.CNSM_NA_TRN_WTR_NA_NA_NA_TRLBTU.A | D36: trillion Btu | F36: 1236.1034 | G36: 1179.9142 | H36: 1171.6475 | I36: 1169.6875 | J36: 1160.7493 | K36: 1156.1696 | L36: 1148.3876 | M36: 1142.2429 | N36: 1136.957 | O36: 1134.8431 | P36: 1133.3051 | Q36: 1132.2845 | R36: 1130.4717 | S36: 1129.385 | T36: 1127.3304 | U36: 1126.3339 | V36: 1125.2139 | W36: 1123.8895 | X36: 1123.0144 | Y36: 1122.3082 | Z36: 1122.0916 | AA36: 1121.3387 | AB36: 1120.708 | AC36: 1119.7297 | AD36: 1121.4393 | AE36: 1120.9009 | AF36: 1118.8984 | AG36: 1117.3406 | AH36: 1115.843 | AI36: -0.004
A37: Freight | B37: Transportation Energy Use: Non-Highway: Water: Freight: Reference case | C37: AEO.2023.REF2023.CNSM_NA_TRN_WTR_FGT_NA_NA_TRLBTU.A | D37: trillion Btu | F37: 1033.2667 | G37: 980.75116 | H37: 975.84198 | I37: 975.9502 | J37: 967.93616 | K37: 964.27222 | L37: 957.65405 | M37: 953.03247 | N37: 949.55359 | O37: 949.16626 | P37: 948.83813 | Q37: 948.67444 | R37: 947.69421 | S37: 947.38678 | T37: 945.88025 | U37: 945.22846 | V37: 944.46802 | W37: 943.50647 | X37: 942.71899 | Y37: 942.1471 | Z37: 942.10346 | AA37: 941.52521 | AB37: 941.15137 | AC37: 940.48584 | AD37: 942.48962 | AE37: 942.17328 | AF37: 940.40753 | AG37: 939.11212 | AH37: 937.68744 | AI37: -0.003
A38: Domestic Shipping | B38: Transportation Energy Use: Non-Highway: Water: Freight: Domestic Shipping: Reference case | C38: AEO.2023.REF2023.CNSM_NA_TRN_WTR_DMT_NA_NA_TRLBTU.A | D38: trillion Btu | F38: 98.239021 | G38: 98.920753 | H38: 98.114662 | I38: 97.346069 | J38: 96.685867 | K38: 95.823471 | L38: 94.964699 | M38: 93.890503 | N38: 92.919189 | O38: 92.029816 | P38: 91.401108 | Q38: 90.674225 | R38: 89.934029 | S38: 89.168869 | T38: 88.333008 | U38: 87.614967 | V38: 86.833351 | W38: 86.156693 | X38: 85.473595 | Y38: 84.846123 | Z38: 84.273766 | AA38: 83.705399 | AB38: 83.103455 | AC38: 82.418205 | AD38: 81.856209 | AE38: 81.249023 | AF38: 80.57312 | AG38: 79.990395 | AH38: 79.59285 | AI38: -0.007
A39: International Shipping | B39: Transportation Energy Use: Non-Highway: Water: Freight: International Shipping: Reference case | C39: AEO.2023.REF2023.CNSM_NA_TRN_WTR_INTS_NA_NA_TRLBTU.A | D39: trillion Btu | F39: 935.02771 | G39: 881.83038 | H39: 877.7273 | I39: 878.60413 | J39: 871.25031 | K39: 868.44873 | L39: 862.68933 | M39: 859.14197 | N39: 856.6344 | O39: 857.13648 | P39: 857.43701 | Q39: 858.00024 | R39: 857.76019 | S39: 858.2179 | T39: 857.54724 | U39: 857.61346 | V39: 857.63464 | W39: 857.34979 | X39: 857.24542 | Y39: 857.30096 | Z39: 857.82971 | AA39: 857.81982 | AB39: 858.04791 | AC39: 858.06763 | AD39: 860.63342 | AE39: 860.92426 | AF39: 859.83441 | AG39: 859.1217 | AH39: 858.0946 | AI39: -0.003
A40: Recreational Boats | B40: Transportation Energy Use: Non-Highway: Water: Recreational Boats: Reference case | C40: AEO.2023.REF2023.CNSM_NA_TRN_WTR_RBT_NA_NA_TRLBTU.A | D40: trillion Btu | F40: 202.83664 | G40: 199.16296 | H40: 195.80548 | I40: 193.73721 | J40: 192.81314 | K40: 191.8974 | L40: 190.73351 | M40: 189.21046 | N40: 187.40353 | O40: 185.67694 | P40: 184.46689 | Q40: 183.61003 | R40: 182.77757 | S40: 181.99818 | T40: 181.45029 | U40: 181.10551 | V40: 180.74588 | W40: 180.38298 | X40: 180.29542 | Y40: 180.16119 | Z40: 179.98802 | AA40: 179.81351 | AB40: 179.55652 | AC40: 179.24385 | AD40: 178.94971 | AE40: 178.72766 | AF40: 178.49087 | AG40: 178.22836 | AH40: 178.15555 | AI40: -0.005
A41: Rail | B41: Transportation Energy Use: Non-Highway: Rail: Reference case | C41: AEO.2023.REF2023.CNSM_NA_TRN_RAIL_RAIL_NA_NA_TRLBTU.A | D41: trillion Btu | F41: 525.29517 | G41: 520.38635 | H41: 540.67011 | I41: 529.40961 | J41: 509.78037 | K41: 494.66577 | L41: 488.8783 | M41: 494.23297 | N41: 492.04196 | O41: 494.02197 | P41: 498.57672 | Q41: 502.37463 | R41: 505.03482 | S41: 508.43884 | T41: 509.35068 | U41: 510.83496 | V41: 512.78436 | W41: 512.64246 | X41: 513.75494 | Y41: 517.85437 | Z41: 521.3421 | AA41: 522.19409 | AB41: 522.73846 | AC41: 523.13727 | AD41: 524.88281 | AE41: 527.90674 | AF41: 531.78455 | AG41: 533.67975 | AH41: 537.57678 | AI41: 0.001
A42: Freight | B42: Transportation Energy Use: Non-Highway: Rail: Freight: Reference case | C42: AEO.2023.REF2023.CNSM_NA_TRN_RAIL_FGT_NA_NA_TRLBTU.A | D42: trillion Btu | F42: 481.38171 | G42: 474.82239 | H42: 494.12915 | I42: 482.20422 | J42: 461.88034 | K42: 446.09524 | L42: 439.74536 | M42: 444.5257 | N42: 441.89194 | O42: 443.42331 | P42: 447.43723 | Q42: 450.64798 | R42: 452.66559 | S42: 455.51504 | T42: 455.89371 | U42: 456.86227 | V42: 458.27463 | W42: 457.60877 | X42: 458.12836 | Y42: 461.67325 | Z42: 464.58835 | AA42: 464.93649 | AB42: 464.92282 | AC42: 464.77069 | AD42: 465.76679 | AE42: 468.15533 | AF42: 471.33984 | AG42: 472.59906 | AH42: 475.72867 | AI42: 0
... A51: Jet Fuel and Aviation Gasoline | B51: Transportation Energy Use: Military Use: Aviation: Reference case | C51: AEO.2023.REF2023.CNSM_NA_TRN_MLU_AVI_NA_NA_TRLBTU.A | D51: trillion Btu | F51: 334.44891 | G51: 336.23386 | H51: 336.88306 | I51: 337.39594 | J51: 337.81006 | K51: 338.4198 | L51: 338.85339 | M51: 339.19925 | N51: 339.4949 | O51: 339.68457 | P51: 339.81464 | Q51: 339.87894 | R51: 339.90338 | S51: 339.91986 | T51: 340.01639 | U51: 340.17093 | V51: 340.33325 | W51: 340.50293 | X51: 340.67941 | Y51: 340.86197 | Z51: 341.05005 | AA51: 341.24316 | AB51: 341.44086 | AC51: 341.64276 | AD51: 341.84848 | AE51: 342.05759 | AF51: 342.26984 | AG51: 342.48502 | AH51: 342.70288 | AI51: 0.001
A52: Residual Fuel Oil | B52: Transportation Energy Use: Military Use: Residual Fuel Oil: Reference case | C52: AEO.2023.REF2023.CNSM_NA_TRN_MLU_RFO_NA_NA_TRLBTU.A | D52: trillion Btu | F52: 0 | G52: 0 | H52: 0 | I52: 0 | J52: 0 | K52: 0 | L52: 0 | M52: 0 | N52: 0 | O52: 0 | P52: 0 | Q52: 0 | R52: 0 | S52: 0 | T52: 0 | U52: 0 | V52: 0 | W52: 0 | X52: 0 | Y52: 0 | Z52: 0 | AA52: 0 | AB52: 0 | AC52: 0 | AD52: 0 | AE52: 0 | AF52: 0 | AG52: 0 | AH52: 0 | AI52: - -
A53: Distillates and Diesel | B53: Transportation Energy Use: Military Use: Distillate Fuel Oil: Reference case | C53: AEO.2023.REF2023.CNSM_NA_TRN_MLU_DFO_NA_NA_TRLBTU.A | D53: trillion Btu | F53: 96.382973 | G53: 96.897369 | H53: 97.084457 | I53: 97.232269 | J53: 97.351608 | K53: 97.527321 | L53: 97.652275 | M53: 97.751961 | N53: 97.837143 | O53: 97.891815 | P53: 97.929291 | Q53: 97.947815 | R53: 97.954857 | S53: 97.959595 | T53: 97.987419 | U53: 98.031967 | V53: 98.078743 | W53: 98.12764 | X53: 98.178513 | Y53: 98.231117 | Z53: 98.285309 | AA53: 98.340965 | AB53: 98.397942 | AC53: 98.456131 | AD53: 98.515411 | AE53: 98.575668 | AF53: 98.636826 | AG53: 98.698837 | AH53: 98.761627 | AI53: 0.001
A54: Total | B54: Transportation Energy Use: Total: Reference case | C54: AEO.2023.REF2023.CNSM_NA_TRN_NA_TOT_NA_NA_TRLBTU.A | D54: trillion Btu | F54: 27655.148 | G54: 27655.762 | H54: 27394.568 | I54: 27059.129 | J54: 26811.27 | K54: 26577.496 | L54: 26318.691 | M54: 26067.979 | N54: 25786.289 | O54: 25538.402 | P54: 25332.225 | Q54: 25172.969 | R54: 25035.588 | S54: 24912.785 | T54: 24789.316 | U54: 24709.041 | V54: 24660.725 | W54: 24616.969 | X54: 24627.309 | Y54: 24654.197 | Z54: 24700.111 | AA54: 24752.801 | AB54: 24825.584 | AC54: 24913.93 | AD54: 25038.584 | AE54: 25190.057 | AF54: 25345.311 | AG54: 25504.531 | AH54: 25712.529 | AI54: -0.003
A55: Energy Use by Type
A56: Motor Gasoline excluding E85 | B56: Transportation Energy Use: Petroleum: Motor Gasoline: Reference case | C56: AEO.2023.REF2023.CNSM_NA_TRN_NA_PET_MGS_NA_TRLBTU.A | D56: trillion Btu | F56: 15874.355 | G56: 15889.633 | H56: 15703.889 | I56: 15449.35 | J56: 15240.682 | K56: 15053.521 | L56: 14839.349 | M56: 14597.918 | N56: 14338.503 | O56: 14096.112 | P56: 13861.302 | Q56: 13670.039 | R56: 13502.24 | S56: 13335.431 | T56: 13166.213 | U56: 13022.09 | V56: 12897.387 | W56: 12783.024 | X56: 12697.221 | Y56: 12626.134 | Z56: 12573.058 | AA56: 12533.43 | AB56: 12516.672 | AC56: 12520.883 | AD56: 12551.513 | AE56: 12603.282 | AF56: 12665.79 | AG56: 12737.466 | AH56: 12832.444 | AI56: -0.008
A57: E85 | B57: Transportation Energy Use: E85: Reference case | C57: AEO.2023.REF2023.CNSM_NA_TRN_NA_E85_NA_NA_TRLBTU.A | D57: trillion Btu | F57: 34.631935 | G57: 35.037319 | H57: 32.552341 | I57: 32.353249 | J57: 31.504307 | K57: 30.668486 | L57: 29.69116 | M57: 28.651995 | N57: 27.562658 | O57: 26.514359 | P57: 25.50803 | Q57: 24.634333 | R57: 23.871559 | S57: 23.224663 | T57: 22.621021 | U57: 22.23918 | V57: 22.006664 | W57: 21.907352 | X57: 21.950138 | Y57: 22.073862 | Z57: 22.260597 | AA57: 22.542372 | AB57: 22.813953 | AC57: 23.132349 | AD57: 23.431681 | AE57: 23.847071 | AF57: 24.21563 | AG57: 24.654547 | AH57: 25.077648 | AI57: -0.011
A58: Diesel | B58: Transportation Energy Use: Petroleum: Diesel: Reference case | C58: AEO.2023.REF2023.CNSM_NA_TRN_NA_PET_DSL_NA_TRLBTU.A | D58: trillion Btu | F58: 6710.395 | G58: 6706.5205 | H58: 6636.6934 | I58: 6567.0239 | J58: 6510.3555 | K58: 6449.8804 | L58: 6399.6875 | M58: 6345.397 | N58: 6280.8228 | O58: 6224.6582 | P58: 6188.4878 | Q58: 6150.8975 | R58: 6117.8203 | S58: 6092.3511 | T58: 6064.7573 | U58: 6047.6304 | V58: 6036.644 | W58: 6023.3477 | X58: 6019.6016 | Y58: 6021.7837 | Z58: 6024.8711 | AA58: 6025.457 | AB58: 6023.2671 | AC58: 6018.6934 | AD58: 6019.314 | AE58: 6021.1924 | AF58: 6019.1113 | AG58: 6015.7207 | AH58: 6030.272 | AI58: -0.004
A59: Jet Fuel (kerosene & naphtha) | B59: Transportation Energy Use: Petroleum: Jet Fuel: Reference case | C59: AEO.2023.REF2023.UNC_NA_TRN_NA_PET_JFL_NA_TRLBTU.A | D59: trillion Btu | F59: 3114.8347 | G59: 3321.9912 | H59: 3365.6841 | I59: 3372.1125 | J59: 3411.3206 | K59: 3450.2642 | L59: 3481.0264 | M59: 3503.9324 | N59: 3520.061 | O59: 3536.0977 | P59: 3561.3833 | Q59: 3587.9609 | R59: 3611.9419 | S59: 3640.4805 | T59: 3677.4785 | U59: 3721.7036 | V59: 3768.144 | W59: 3816.6306 | X59: 3872.9631 | Y59: 3926.9058 | Z59: 3981.7881 | AA59: 4037.5085 | AB59: 4093.0918 | AC59: 4147.2026 | AD59: 4199.9233 | AE59: 4256.437 | AF59: 4313.5156 | AG59: 4369.7773 | AH59: 4432.502 | AI59: 0.013
A60: Residual Fuel Oil | B60: Transportation Energy Use: Petroleum: Residual Fuel Oil: Reference case | C60: AEO.2023.REF2023.CNSM_NA_TRN_NA_PET_RFO_NA_TRLBTU.A | D60: trillion Btu | F60: 687.54108 | G60: 533.95758 | H60: 521.0669 | I60: 521.9704 | J60: 499.00574 | K60: 489.2088 | L60: 471.12759 | M60: 459.55618 | N60: 451.02731 | O60: 451.06888 | P60: 450.30673 | Q60: 450.39215 | R60: 448.21356 | S60: 448.02866 | T60: 444.74847 | U60: 443.62381 | V60: 442.39099 | W60: 440.1236 | X60: 438.39453 | Y60: 437.18234 | Z60: 437.22125 | AA60: 435.65289 | AB60: 434.69913 | AC60: 433.13565 | AD60: 438.8573 | AE60: 438.0972 | AF60: 433.31424 | AG60: 429.63794 | AH60: 424.94931 | AI60: -0.017
A61: Aviation Gasoline | B61: Transportation Energy Use: Petroleum: Aviation Gasoline: Reference case | C61: AEO.2023.REF2023.CNSM_NA_TRN_NA_PET_AVGA_NA_TRLBTU.A | D61: trillion Btu | F61: 22.421618 | G61: 22.410635 | H61: 22.401548 | I61: 22.394032 | J61: 22.387812 | K61: 22.382666 | L61: 22.378407 | M61: 22.374884 | N61: 22.371969 | O61: 22.369558 | P61: 22.367563 | Q61: 22.365911 | R61: 22.364546 | S61: 22.363417 | T61: 22.36248 | U61: 22.361708 | V61: 22.361067 | W61: 22.360538 | X61: 22.3601 | Y61: 22.359737 | Z61: 22.359438 | AA61: 22.35919 | AB61: 22.358984 | AC61: 22.358814 | AD61: 22.358673 | AE61: 22.358557 | AF61: 22.358461 | AG61: 22.358381 | AH61: 22.358315 | AI61: 0
A62: Propane | B62: Transportation Energy Use: Petroleum: Propane: Reference case | C62: AEO.2023.REF2023.CNSM_NA_TRN_NA_PET_PROP_NA_TRLBTU.A | D62: trillion Btu | F62: 11.141157 | G62: 11.729122 | H62: 11.853459 | I62: 12.01076 | J62: 12.154844 | K62: 12.287197 | L62: 12.139218 | M62: 12.24054 | N62: 12.351296 | O62: 12.459235 | P62: 12.585068 | Q62: 12.731653 | R62: 12.905529 | S62: 13.095903 | T62: 13.307463 | U62: 13.546154 | V62: 13.805359 | W62: 14.093753 | X62: 14.423079 | Y62: 14.799322 | Z62: 15.214664 | AA62: 15.662395 | AB62: 16.14922 | AC62: 16.675133 | AD62: 17.265896 | AE62: 17.89559 | AF62: 18.551962 | AG62: 19.225891 | AH62: 19.960386 | AI62: 0.021
A63: Lubricants | B63: Transportation Energy Use: Petroleum: Lubricants: Reference case | C63: AEO.2023.REF2023.CNSM_NA_TRN_NA_PET_LBC_NA_TRLBTU.A | D63: trillion Btu | F63: 125.94522 | G63: 125.92506 | H63: 126.01238 | I63: 126.04986 | J63: 126.11367 | K63: 125.98441 | L63: 125.853 | M63: 125.75523 | N63: 125.65207 | O63: 125.54579 | P63: 125.43918 | Q63: 125.33015 | R63: 125.25038 | S63: 125.22502 | T63: 125.25526 | U63: 125.31821 | V63: 125.4119 | W63: 125.52669 | X63: 125.66653 | Y63: 125.79737 | Z63: 125.92503 | AA63: 126.04557 | AB63: 126.16628 | AC63: 126.32028 | AD63: 126.49239 | AE63: 126.66081 | AF63: 126.81145 | AG63: 126.97429 | AH63: 127.15868 | AI63: 0
A64: Petroleum and Other Liquids Subtotal | B64: Transportation Energy Use: Petroleum Subtotal: Reference case | C64: AEO.2023.REF2023.CNSM_NA_TRN_NA_PET_NA_NA_TRLBTU.A | D64: trillion Btu | F64: 26581.266 | G64: 26647.203 | H64: 26420.152 | I64: 26103.268 | J64: 25853.523 | K64: 25634.197 | L64: 25381.252 | M64: 25095.826 | N64: 24778.352 | O64: 24494.822 | P64: 24247.379 | Q64: 24044.354 | R64: 23864.607 | S64: 23700.199 | T64: 23536.744 | U64: 23418.512 | V64: 23328.15 | W64: 23247.016 | X64: 23212.578 | Y64: 23197.035 | Z64: 23202.699 | AA64: 23218.656 | AB64: 23255.219 | AC64: 23308.402 | AD64: 23399.156 | AE64: 23509.773 | AF64: 23623.67 | AG64: 23745.816 | AH64: 23914.723 | AI64: -0.004
A65: Electricity | B65: Transportation Energy Use: Electricity: Reference case | C65: AEO.2023.REF2023.CNSM_NA_TRN_NA_ELC_NA_NA_TRLBTU.A | D65: trillion Btu | F65: 58.271488 | G65: 70.924744 | H65: 86.151306 | I65: 103.80544 | J65: 124.94299 | K65: 150.04829 | L65: 178.72939 | M65: 211.36607 | N65: 247.30803 | O65: 280.38351 | P65: 314.45035 | Q65: 348.6257 | R65: 383.96487 | S65: 418.87405 | T65: 452.58807 | U65: 485.43649 | V65: 517.22076 | W65: 547.37634 | X65: 575.67041 | Y65: 602.42621 | Z65: 627.3949 | AA65: 650.20367 | AB65: 671.55237 | AC65: 690.80652 | AD65: 710.45508 | AE65: 729.02063 | AF65: 747.0238 | AG65: 764.70154 | AH65: 781.67743 | AI65: 0.097
A66: Compressed/Liquefied Natural Gas | B66: Transportation Energy Use: Natural Gas: Reference case | C66: AEO.2023.REF2023.CNSM_NA_TRN_NA_NG_NA_NA_TRLBTU.A | D66: trillion Btu | F66: 107.76208 | G66: 114.84132 | H66: 124.74314 | I66: 122.40164 | J66: 133.70236 | K66: 135.6781 | L66: 140.85495 | M66: 144.49738 | N66: 145.72705 | O66: 146.36429 | P66: 147.34078 | Q66: 148.05913 | R66: 150.25818 | S66: 153.89322 | T66: 159.30589 | U66: 165.10998 | V66: 170.17973 | W66: 178.24515 | X66: 185.24722 | Y66: 193.94168 | Z66: 203.10612 | AA66: 214.17357 | AB66: 224.93594 | AC66: 236.52026 | AD66: 245.41003 | AE66: 259.84387 | AF66: 276.02594 | AG66: 292.71753 | AH66: 309.737 | AI66: 0.038
A67: Hydrogen | B67: Transportation Energy Use: Hydrogen: Reference case | C67: AEO.2023.REF2023.CNSM_NA_TRN_NA_HDG_NA_NA_TRLBTU.A | D67: trillion Btu | F67: 0.449255 | G67: 0.542217 | H67: 0.620706 | I67: 0.690218 | J67: 0.763191 | K67: 0.832262 | L67: 0.905294 | M67: 0.974009 | N67: 1.046211 | O67: 1.119019 | P67: 1.19111 | Q67: 1.262406 | R67: 1.334878 | S67: 1.405921 | T67: 1.472262 | U67: 1.536677 | V67: 1.594822 | W67: 1.646765 | X67: 1.689135 | Y67: 1.72306 | Z67: 1.754586 | AA67: 1.776198 | AB67: 1.792174 | AC67: 1.801144 | AD67: 1.81132 | AE67: 1.821694 | AF67: 1.828998 | AG67: 1.834284 | AH67: 1.8375 | AI67: 0.052
... A70: Total Consumption | B70: Transportation: Total Energy Use: Reference case | C70: AEO.2023.REF2023.CNSM_NA_TRN_NA_NA_NA_NA_TRLBTU.A | D70: trillion Btu | F70: 27986.004 | G70: 28032.025 | H70: 27776.652 | I70: 27465.699 | J70: 27255.043 | K70: 27051.914 | L70: 26819.279 | M70: 26592.268 | N70: 26360.719 | O70: 26162.953 | P70: 26008.129 | Q70: 25897.748 | R70: 25802.094 | S70: 25704.211 | T70: 25598.514 | U70: 25533.523 | V70: 25493.338 | W70: 25449.312 | X70: 25460.59 | Y70: 25485.91 | Z70: 25531.479 | AA70: 25584.162 | AB70: 25658.191 | AC70: 25745.092 | AD70: 25869.725 | AE70: 26020.955 | AF70: 26177.635 | AG70: 26335.311 | AH70: 26543.111 | AI70: -0.002

Sheet AEO 2023 36
B1: Table 36. Transportation Sector Energy Use by Fuel Type Within a Mode
B2: https://www.eia.gov/outlooks/aeo/data/browser/#/?id=46-AEO2023&cases=ref2023&sourcekey=0
B3: Thu Dec 11 2025 13:27:15 GMT-0800 (Pacific Standard Time)
B4: Source: U.S. Energy Information Administration
C5: full name | D5: api key | E5: units | F5: 2021 | G5: 2022 | H5: 2023 | I5: 2024 | J5: 2025 | K5: 2026 | L5: 2027 | M5: 2028 | N5: 2029 | O5: 2030 | P5: 2031 | Q5: 2032 | R5: 2033 | S5: 2034 | T5: 2035 | U5: 2036 | V5: 2037 | W5: 2038 | X5: 2039 | Y5: 2040 | Z5: 2041 | AA5: 2042 | AB5: 2043 | AC5: 2044 | AD5: 2045 | AE5: 2046 | AF5: 2047 | AG5: 2048 | AH5: 2049 | AI5: 2050 | AJ5: Growth (2022-2050) | AK5: Growth (2020-2050)
B6: Light-Duty Vehicle | C6: Transportation Energy Use: Light-Duty Vehicle: Total: Reference case | D6: AEO.2023.REF2023.CNSM_NA_TRN_LDTY_NA_NA_NA_TRLBTU.A | E6: trillion Btu | G6: 14541.973 | H6: 14586.113 | I6: 14429.691 | J6: 14201.925 | K6: 14016.908 | L6: 13860.762 | M6: 13679.086 | N6: 13473.831 | O6: 13253.083 | P6: 13044.085 | Q6: 12836.978 | R6: 12674.038 | S6: 12534.655 | T6: 12394.663 | U6: 12251.547 | V6: 12130.821 | W6: 12028.415 | X6: 11933.922 | Y6: 11864.001 | Z6: 11805.396 | AA6: 11762.741 | AB6: 11733.644 | AC6: 11725.386 | AD6: 11735.774 | AE6: 11770.763 | AF6: 11824.349 | AG6: 11889.715 | AH6: 11962.909 | AI6: 12054.454 | AJ6: -0.007 | AK6: 0
B7: Motor Gasoline excluding E85 | C7: Transportation Energy Use: Light-Duty Vehicle: Motor Gasoline: Reference case | D7: AEO.2023.REF2023.CNSM_NA_TRN_LDTY_MGS_NA_NA_TRLBTU.A | E7: trillion Btu | G7: 14415.272 | H7: 14443.936 | I7: 14272.424 | J7: 14024.321 | K7: 13815.495 | L7: 13632.25 | M7: 13419.692 | N7: 13179.96 | O7: 12922.15 | P7: 12678.574 | Q7: 12437.037 | R7: 12238.959 | S7: 12063.409 | T7: 11887.983 | U7: 11710.702 | V7: 11556.08 | W7: 11421.213 | X7: 11295.929 | Y7: 11196.766 | Z7: 11110.767 | AA7: 11042.225 | AB7: 10988.435 | AC7: 10958.348 | AD7: 10949.109 | AE7: 10963.974 | AF7: 10998.307 | AG7: 11045.134 | AH7: 11100.26 | AI7: 11174.06 | AJ7: -0.009 | AK7: -0.001
B8: E85 | C8: Transportation Energy Use: Light-Duty Vehicle: Ethanol: Reference case | D8: AEO.2023.REF2023.CNSM_NA_TRN_LDTY_ETH_NA_NA_TRLBTU.A | E8: trillion Btu | G8: 31.110834 | H8: 31.64006 | I8: 29.552767 | J8: 29.441513 | K8: 28.728485 | L8: 27.952177 | M8: 27.018059 | N8: 25.972713 | O8: 24.873795 | P8: 23.80064 | Q8: 22.75461 | R8: 21.823027 | S8: 20.987984 | T8: 20.244169 | U8: 19.537762 | V8: 19.024712 | W8: 18.648621 | X8: 18.39851 | Y8: 18.275644 | Z8: 18.222813 | AA8: 18.236134 | AB8: 18.340065 | AC8: 18.452595 | AD8: 18.609615 | AE8: 18.756809 | AF8: 19.004078 | AG8: 19.229309 | AH8: 19.515997 | AI8: 19.788425 | AJ8: -0.016 | AK8: 0.004
B9: Distillate Fuel Oil (diesel) | C9: Transportation Energy Use: Light-Duty Vehicle: Distillate Fuel Oil: Reference case | D9: AEO.2023.REF2023.CNSM_NA_TRN_LDTY_DFO_NA_NA_TRLBTU.A | E9: trillion Btu | G9: 61.460403 | H9: 64.69902 | I9: 67.503647 | J9: 70.684074 | K9: 74.503555 | L9: 77.63253 | M9: 81.324982 | N9: 84.520767 | O9: 86.959732 | P9: 89.758049 | Q9: 91.490158 | R9: 93.247543 | S9: 95.158997 | T9: 96.641708 | U9: 98.053238 | V9: 99.8647 | W9: 101.3619 | X9: 102.78562 | Y9: 104.47522 | Z9: 105.74961 | AA9: 107.32461 | AB9: 109.77927 | AC9: 110.92001 | AD9: 111.97984 | AE9: 113.44128 | AF9: 115.03706 | AG9: 116.75106 | AH9: 118.59347 | AI9: 120.69574 | AJ9: 0.024 | AK9: 0.025
B10: Compressed/Liquefied Natural Gas | C10: Transportation Energy Use: Light-Duty Vehicle: Natural Gas: Reference case | D10: AEO.2023.REF2023.CNSM_NA_TRN_LDTY_NG_NA_NA_TRLBTU.A | E10: trillion Btu | G10: 0.712888 | H10: 0.677668 | I10: 0.537752 | J10: 0.515005 | K10: 0.507019 | L10: 0.492443 | M10: 0.481839 | N10: 0.470472 | O10: 0.445942 | P10: 0.443445 | Q10: 0.437883 | R10: 0.433434 | S10: 0.431733 | T10: 0.430499 | U10: 0.427096 | V10: 0.424631 | W10: 0.426227 | X10: 0.378024 | Y10: 0.335326 | Z10: 0.340053 | AA10: 0.343781 | AB10: 0.346656 | AC10: 0.349313 | AD10: 0.351864 | AE10: 0.356448 | AF10: 0.36171 | AG10: 0.367786 | AH10: 0.374043 | AI10: 0.381082 | AJ10: -0.022 | AK10: -0.001
B11: Propane | C11: Transportation Energy Use: Light-Duty Vehicle: Propane: Reference case | D11: AEO.2023.REF2023.CNSM_NA_TRN_LDTY_PROP_NA_NA_TRLBTU.A | E11: trillion Btu | G11: 0.797388 | H11: 0.735487 | I11: 0.547456 | J11: 0.540668 | K11: 0.544193 | L11: 0.561282 | M11: 0.312092 | N11: 0.33014 | O11: 0.384077 | P11: 0.437626 | Q11: 0.489719 | R11: 0.540254 | S11: 0.590177 | T11: 0.638076 | U11: 0.684164 | V11: 0.72876 | W11: 0.771586 | X11: 0.812987 | Y11: 0.85285 | Z11: 0.891809 | AA11: 0.930713 | AB11: 0.968622 | AC11: 1.007558 | AD11: 1.048031 | AE11: 1.096531 | AF11: 1.150243 | AG11: 1.209162 | AH11: 1.271896 | AI11: 1.341161 | AJ11: 0.019 | AK11: -0.007
B12: Electricity | C12: Transportation Energy Use: Light-Duty Vehicle: Electricity: Reference case | D12: AEO.2023.REF2023.CNSM_NA_TRN_LDTY_ELC_NA_NA_TRLBTU.A | E12: trillion Btu | G12: 32.193668 | H12: 43.907116 | I12: 58.529484 | J12: 75.757942 | K12: 96.391159 | L12: 121.06613 | M12: 149.37682 | N12: 181.62849 | O12: 217.24832 | P12: 249.97737 | Q12: 283.60272 | R12: 317.79742 | S12: 352.76804 | T12: 387.34479 | U12: 420.6944 | V12: 453.18622 | W12: 484.42331 | X12: 513.9956 | Y12: 541.63086 | Z12: 567.72461 | AA12: 591.9502 | AB12: 614.02081 | AC12: 634.53888 | AD12: 652.89734 | AE12: 671.34821 | AF12: 688.6897 | AG12: 705.21576 | AH12: 721.08112 | AI12: 736.37286 | AJ12: 0.118 | AK12: 0.101
B13: Hydrogen | C13: Transportation Energy Use: Light-Duty Vehicle: Hydrogen: Reference case | D13: AEO.2023.REF2023.CNSM_NA_TRN_LDTY_HDG_NA_NA_TRLBTU.A | E13: trillion Btu | G13: 0.426139 | H13: 0.518183 | I13: 0.595767 | J13: 0.665118 | K13: 0.737872 | L13: 0.80678 | M13: 0.879698 | N13: 0.948358 | O13: 1.020552 | P13: 1.093446 | Q13: 1.165657 | R13: 1.237105 | S13: 1.309695 | T13: 1.380918 | U13: 1.447488 | V13: 1.512508 | W13: 1.570883 | X13: 1.623062 | Y13: 1.665691 | Z13: 1.699897 | AA13: 1.731693 | AB13: 1.753623 | AC13: 1.769871 | AD13: 1.779117 | AE13: 1.789497 | AF13: 1.800149 | AG13: 1.807713 | AH13: 1.813287 | AI13: 1.816777 | AJ13: 0.053 | AK13: 0.038
B14: Commercial Light Trucks | C14: Transportation Energy Use: Commercial Light Trucks: Total: Reference case | D14: AEO.2023.REF2023.CNSM_NA_TRN_CLTR_NA_NA_NA_TRLBTU.A | E14: trillion Btu | G14: 951.50281 | H14: 942.55829 | I14: 925.34039 | J14: 912.45154 | K14: 903.11096 | L14: 894.80664 | M14: 888.38452 | N14: 882.9956 | O14: 877.03247 | P14: 872.79089 | Q14: 871.79065 | R14: 871.86755 | S14: 873.03363 | T14: 875.07349 | U14: 877.49945 | V14: 881.02332 | W14: 885.54096 | X14: 889.79608 | Y14: 896.14636 | Z14: 903.92438 | AA14: 911.92645 | AB14: 919.0462 | AC14: 925.474 | AD14: 932.77234 | AE14: 941.2807 | AF14: 951.49884 | AG14: 960.51416 | AH14: 969.5788 | AI14: 981.5957 | AJ14: 0.001 | AK14: 0.009
B15: Motor Gasoline excluding E85 | C15: Transportation Energy Use: Commercial Light Trucks: Motor Gasoline: Reference case | D15: AEO.2023.REF2023.CNSM_NA_TRN_CLTR_MGS_NA_NA_TRLBTU.A | E15: trillion Btu | G15: 657.76746 | H15: 651.25983 | I15: 640.80762 | J15: 634.44543 | K15: 630.82428 | L15: 624.78125 | M15: 620.94763 | N15: 618.08075 | O15: 615.03595 | P15: 613.48315 | Q15: 614.07129 | R15: 615.42194 | S15: 617.64148 | T15: 620.38318 | U15: 623.32221 | V15: 627.02631 | W15: 631.23346 | X15: 635.20404 | Y15: 640.80859 | Z15: 646.77948 | AA15: 653.38257 | AB15: 659.03369 | AC15: 663.90283 | AD15: 669.03552 | AE15: 675.10999 | AF15: 682.46606 | AG15: 688.97082 | AH15: 695.63995 | AI15: 704.23315 | AJ15: 0.002 | AK15: 0.008
B16: E85 | C16: Transportation Energy Use: Commercial Light Trucks: E85: Reference case | D16: AEO.2023.REF2023.CNSM_NA_TRN_CLTR_E85_NA_NA_TRLBTU.A | E16: trillion Btu | G16: 3.51367 | H16: 3.389497 | I16: 2.991625 | J16: 2.903706 | K16: 2.76768 | L16: 2.708098 | M16: 2.664845 | N16: 2.671002 | O16: 2.68058 | P16: 2.705457 | Q16: 2.745193 | R16: 2.803118 | S16: 2.875419 | T16: 2.972388 | U16: 3.075218 | V16: 3.206507 | W16: 3.350161 | X16: 3.50104 | Y16: 3.666781 | Z16: 3.843432 | AA16: 4.016943 | AB16: 4.194909 | AC16: 4.354052 | AD16: 4.515519 | AE16: 4.667729 | AF16: 4.835943 | AG16: 4.97936 | AH16: 5.131686 | AI16: 5.282454 | AJ16: 0.015 | AK16: 0.047
B17: Distillate Fuel Oil (diesel) | C17: Transportation Energy Use: Commercial Light Trucks: Distillate Fuel Oil: Reference case | D17: AEO.2023.REF2023.CNSM_NA_TRN_CLTR_DFO_NA_NA_TRLBTU.A | E17: trillion Btu | G17: 289.12039 | H17: 286.82144 | I17: 280.46921 | J17: 274.07837 | K17: 268.54092 | L17: 266.37576 | M17: 263.84299 | N17: 261.31543 | O17: 258.40118 | P17: 255.69388 | Q17: 254.05814 | R17: 252.70514 | S17: 251.54263 | T17: 250.69047 | U17: 250.00555 | V17: 249.60524 | W17: 249.66022 | X17: 249.65735 | Y17: 250.07077 | Z17: 251.50558 | AA17: 252.50731 | AB17: 253.54639 | AC17: 254.6667 | AD17: 256.36206 | AE17: 258.3045 | AF17: 260.63464 | AG17: 262.62152 | AH17: 264.4642 | AI17: 267.30786 | AJ17: -0.003 | AK17: 0.008
... B19: Compressed/Liquefied Natural Gas | C19: Transportation Energy Use: Commercial Light Trucks: Natural Gas: Reference case | D19: AEO.2023.REF2023.CNSM_NA_TRN_CLTR_NG_NA_NA_TRLBTU.A | E19: trillion Btu | G19: 1.100109 | H19: 1.028096 | I19: 0.954857 | J19: 0.851628 | K19: 0.748517 | L19: 0.657968 | M19: 0.592555 | N19: 0.535011 | O19: 0.478159 | P19: 0.423993 | Q19: 0.376664 | R19: 0.335485 | S19: 0.300891 | T19: 0.271073 | U19: 0.243198 | V19: 0.217586 | W19: 0.194927 | X19: 0.176079 | Y19: 0.160581 | Z19: 0.146182 | AA19: 0.133464 | AB19: 0.121475 | AC19: 0.110383 | AD19: 0.099974 | AE19: 0.087947 | AF19: 0.07232 | AG19: 0.057146 | AH19: 0.045076 | AI19: 0.03417 | AJ19: -0.117 | AK19: -0.013
B20: Electricity | C20: Transportation Energy Use: Commercial Light Trucks: Electricity: Reference case | D20: AEO.2023.REF2023.CNSM_NA_TRN_CLTR_ELC_NA_NA_TRLBTU.A | E20: trillion Btu | G20: 0 | H20: 0 | I20: 0 | J20: 0 | K20: 0 | L20: 0 | M20: 0 | N20: 0 | O20: 0 | P20: 0 | Q20: 0 | R20: 0 | S20: 0 | T20: 0 | U20: 0 | V20: 0 | W20: 0 | X20: 0 | Y20: 0 | Z20: 0 | AA20: 0 | AB20: 0 | AC20: 0 | AD20: 0 | AE20: 0 | AF20: 0 | AG20: 0 | AH20: 0 | AI20: 0 | AJ20: - - | AK20: 0.115
B21: Hydrogen | C21: Transportation Energy Use: Commercial Light Trucks: Hydrogen: Reference case | D21: AEO.2023.REF2023.CNSM_NA_TRN_CLTR_HDG_NA_NA_TRLBTU.A | E21: trillion Btu | G21: 0 | H21: 0 | I21: 0 | J21: 0 | K21: 0 | L21: 0 | M21: 0 | N21: 0 | O21: 0 | P21: 0 | Q21: 0 | R21: 0 | S21: 0 | T21: 0 | U21: 0 | V21: 0 | W21: 0 | X21: 0 | Y21: 0 | Z21: 0 | AA21: 0 | AB21: 0 | AC21: 0 | AD21: 0 | AE21: 0 | AF21: 0 | AG21: 0 | AH21: 0 | AI21: 0 | AJ21: - - | AK21: - -
B22: Freight Trucks | C22: Transportation Energy Use: Freight Trucks: Total: Reference case | D22: AEO.2023.REF2023.CNSM_NA_TRN_FRTT_NA_NA_NA_TRLBTU.A | E22: trillion Btu | G22: 5922.791 | H22: 5816.7056 | I22: 5728.0952 | J22: 5673.0986 | K22: 5638.8965 | L22: 5591.7085 | M22: 5543.7119 | N22: 5483.6694 | O22: 5422.3887 | P22: 5371.3027 | Q22: 5340.1582 | R22: 5306.5049 | S22: 5278.7798 | T22: 5261.2471 | U22: 5242.999 | V22: 5237.6973 | W22: 5236.3618 | X22: 5238.3042 | Y22: 5247.9146 | Z22: 5263.2085 | AA22: 5281.4541 | AB22: 5299.6816 | AC22: 5316.7681 | AD22: 5331.7002 | AE22: 5353.1992 | AF22: 5376.3164 | AG22: 5393.3179 | AH22: 5413.417 | AI22: 5450.0122 | AJ22: -0.003 | AK22: 0.005
B23: Motor Gasoline | C23: Transportation Energy Use: Freight Trucks: Motor Gasoline: Reference case | D23: AEO.2023.REF2023.CNSM_NA_TRN_FRTT_MGS_NA_NA_TRLBTU.A | E23: trillion Btu | G23: 616.2052 | H23: 611.60089 | I23: 610.37268 | J23: 612.19367 | K23: 616.9259 | L23: 620.02863 | M23: 623.43561 | N23: 626.1109 | O23: 629.31873 | P23: 633.79578 | Q23: 641.25617 | R23: 647.76111 | S23: 654.28461 | T23: 661.13013 | U23: 667.05139 | V23: 674.55737 | W23: 681.19171 | X23: 688.82941 | Y23: 697.0672 | Z23: 706.54358 | AA23: 715.97064 | AB23: 725.08044 | AC23: 734.18097 | AD23: 743.18781 | AE23: 753.50971 | AF23: 764.21655 | AG23: 774.0188 | AH23: 784.56543 | AI23: 797.65808 | AJ23: 0.009 | AK23: 0.017
B24: Distillate Fuel Oil (diesel) | C24: Transportation Energy Use: Freight Trucks: Distillate Fuel Oil: Reference case | D24: AEO.2023.REF2023.CNSM_NA_TRN_FRTT_DFO_NA_NA_TRLBTU.A | E24: trillion Btu | G24: 5252.3306 | H24: 5150.2441 | I24: 5062.3154 | J24: 5004.9751 | K24: 4965.6987 | L24: 4915.5693 | M24: 4864.6592 | N24: 4802.8213 | O24: 4739.4141 | P24: 4684.7788 | Q24: 4646.6831 | R24: 4606.6587 | S24: 4572.083 | T24: 4546.9648 | U24: 4521.8164 | V24: 4507.6465 | W24: 4498.0513 | X24: 4490.4604 | Y24: 4489.5615 | Z24: 4492.7368 | AA24: 4498.6597 | AB24: 4504.667 | AC24: 4509.3804 | AD24: 4511.9082 | AE24: 4519.4395 | AF24: 4527.9907 | AG24: 4531.3125 | AH24: 4536.8086 | AI24: 4555.8003 | AJ24: -0.005 | AK24: 0.003
B25: Compressed/Liquefied Natural Gas | C25: Transportation Energy Use: Freight Trucks: Natural Gas: Reference case | D25: AEO.2023.REF2023.CNSM_NA_TRN_FRTT_NG_NA_NA_TRLBTU.A | E25: trillion Btu | G25: 51.344929 | H25: 51.773193 | I25: 51.965775 | J25: 52.061794 | K25: 52.003609 | L25: 51.453991 | M25: 50.587242 | N25: 49.35791 | O25: 47.935226 | P25: 46.656029 | Q25: 45.774757 | R25: 45.265823 | S25: 45.213749 | T25: 45.570152 | U25: 46.181812 | V25: 47.148071 | W25: 48.373516 | X25: 49.850357 | Y25: 51.657871 | Z25: 53.785 | AA25: 56.128628 | AB25: 58.653038 | AC25: 61.32283 | AD25: 64.089226 | AE25: 67.060806 | AF25: 70.195709 | AG25: 73.347763 | AH25: 76.647514 | AI25: 80.336479 | AJ25: 0.016 | AK25: 0.022
B26: Propane | C26: Transportation Energy Use: Freight Trucks: Propane: Reference case | D26: AEO.2023.REF2023.CNSM_NA_TRN_FRTT_LPG_NA_NA_TRLBTU.A | E26: trillion Btu | G26: 1.245265 | H26: 1.386178 | I26: 1.524881 | J26: 1.656008 | K26: 1.786266 | L26: 1.903707 | M26: 2.010578 | N26: 2.099689 | O26: 2.180499 | P26: 2.260465 | Q26: 2.347809 | R26: 2.440473 | S26: 2.541221 | T26: 2.644983 | U26: 2.752405 | V26: 2.87385 | W26: 3.004591 | X26: 3.149585 | Y26: 3.313908 | Z26: 3.500602 | AA26: 3.702072 | AB26: 3.917007 | AC26: 4.141416 | AD26: 4.376885 | AE26: 4.632447 | AF26: 4.901746 | AG26: 5.174631 | AH26: 5.447477 | AI26: 5.745036 | AJ26: 0.056 | AK26: 0.045
B27: E85 | C27: Transportation Energy Use: Freight Trucks: E85: Reference case | D27: AEO.2023.REF2023.CNSM_NA_TRN_FRTT_E85_NA_NA_TRLBTU.A | E27: trillion Btu | G27: 1.575329 | H27: 1.59209 | I27: 1.542675 | J27: 1.600683 | K27: 1.639342 | L27: 1.678971 | M27: 1.719318 | N27: 1.762707 | O27: 1.813895 | P27: 1.879181 | Q27: 1.95436 | R27: 2.033936 | S27: 2.113308 | T27: 2.196958 | U27: 2.268667 | V27: 2.353445 | W27: 2.433783 | X27: 2.515797 | Y27: 2.611985 | Z27: 2.71994 | AA27: 2.833077 | AB27: 2.961128 | AC27: 3.087059 | AD27: 3.218797 | AE27: 3.346063 | AF27: 3.488648 | AG27: 3.617473 | AH27: 3.75576 | AI27: 3.895148 | AJ27: 0.033 | AK27: 0.067
B28: Electricity | C28: Transportation Energy Use: Freight Trucks: Electricity: Reference case | D28: AEO.2023.REF2023.CNSM_NA_TRN_FRTT_ELC_NA_NA_TRLBTU.A | E28: trillion Btu | G28: 0.090132 | H28: 0.109146 | I28: 0.144005 | J28: 0.163405 | K28: 0.180895 | L28: 0.195757 | M28: 0.208274 | N28: 0.218016 | O28: 0.225574 | P28: 0.231714 | Q28: 0.236945 | R28: 0.240285 | S28: 0.242473 | T28: 0.244232 | U28: 0.245169 | V28: 0.246735 | W28: 0.249455 | X28: 0.25267 | Y28: 0.257144 | Z28: 0.263999 | AA28: 0.273114 | AB28: 0.282851 | AC28: 0.293846 | AD28: 0.306597 | AE28: 0.321782 | AF28: 0.338025 | AG28: 0.354865 | AH28: 0.372904 | AI28: 0.39289 | AJ28: 0.054 | AK28: 0.123
B29: Hydrogen | C29: Transportation Energy Use: Freight Trucks: Hydrogen: Reference case | D29: AEO.2023.REF2023.CNSM_NA_TRN_FRTT_HDG_NA_NA_TRLBTU.A | E29: trillion Btu | G29: 0 | H29: 0 | I29: 0.229727 | J29: 0.447252 | K29: 0.662312 | L29: 0.877515 | M29: 1.09125 | N29: 1.299036 | O29: 1.500679 | P29: 1.700765 | Q29: 1.904776 | R29: 2.104716 | S29: 2.301462 | T29: 2.495941 | U29: 2.683397 | V29: 2.871152 | W29: 3.057535 | X29: 3.245911 | Y29: 3.444844 | Z29: 3.658572 | AA29: 3.886771 | AB29: 4.120397 | AC29: 4.36127 | AD29: 4.612166 | AE29: 4.888996 | AF29: 5.184831 | AG29: 5.492115 | AH29: 5.819783 | AI29: 6.18408 | AJ29: - - | AK29: 0.134
B30: Freight Rail | C30: Transportation Energy Use: Freight Rail: Total: Reference case | D30: AEO.2023.REF2023.CNSM_NA_TRN_FRAIL_NA_NA_NA_TRLBTU.A | E30: trillion Btu | G30: 481.38171 | H30: 474.82239 | I30: 494.12915 | J30: 482.20422 | K30: 461.88034 | L30: 446.09524 | M30: 439.74536 | N30: 444.5257 | O30: 441.89194 | P30: 443.42331 | Q30: 447.43723 | R30: 450.64798 | S30: 452.66559 | T30: 455.51504 | U30: 455.89371 | V30: 456.86227 | W30: 458.27463 | X30: 457.60877 | Y30: 458.12836 | Z30: 461.67325 | AA30: 464.58835 | AB30: 464.93649 | AC30: 464.92282 | AD30: 464.77069 | AE30: 465.76679 | AF30: 468.15533 | AG30: 471.33984 | AH30: 472.59906 | AI30: 475.72867 | AJ30: 0 | AK30: 0.001
B31: Distillate Fuel Oil (diesel) | C31: Transportation Energy Use: Freight Rail: Distillate Fuel Oil: Reference case | D31: AEO.2023.REF2023.CNSM_NA_TRN_FRAIL_DFO_NA_NA_TRLBTU.A | E31: trillion Btu | G31: 480.86655 | H31: 473.79251 | I31: 492.51502 | J31: 480.10034 | K31: 459.17535 | L31: 442.59573 | M31: 435.20493 | N31: 438.61609 | O31: 434.49127 | P31: 434.25302 | Q31: 435.99301 | R31: 436.48691 | S31: 435.37204 | T31: 434.60773 | U31: 431.05429 | V31: 427.65039 | W31: 424.25372 | X31: 418.55365 | Y31: 413.58151 | Z31: 410.94678 | AA31: 407.33847 | AB31: 401.1214 | AC31: 394.29074 | AD31: 387.0668 | AE31: 380.52634 | AF31: 373.70102 | AG31: 367.60938 | AH31: 360.13336 | AI31: 354.19946 | AJ31: -0.011 | AK31: -0.017
B32: Residual Fuel Oil | C32: Transportation Energy Use: Freight Rail: Residual Fuel Oil: Reference case | D32: AEO.2023.REF2023.CNSM_NA_TRN_FRAIL_RFO_NA_NA_TRLBTU.A | E32: trillion Btu | G32: 0 | H32: 0 | I32: 0 | J32: 0 | K32: 0 | L32: 0 | M32: 0 | N32: 0 | O32: 0 | P32: 0 | Q32: 0 | R32: 0 | S32: 0 | T32: 0 | U32: 0 | V32: 0 | W32: 0 | X32: 0 | Y32: 0 | Z32: 0 | AA32: 0 | AB32: 0 | AC32: 0 | AD32: 0 | AE32: 0 | AF32: 0 | AG32: 0 | AH32: 0 | AI32: 0 | AJ32: - - | AK32: - -
B33: Compressed Natural Gas | C33: Transportation Energy Use: Freight Rail: CNG: Reference case | D33: AEO.2023.REF2023.CNSM_NA_TRN_FRAIL_CNG_NA_NA_TRLBTU.A | E33: trillion Btu | G33: 0 | H33: 0 | I33: 0 | J33: 0 | K33: 0 | L33: 0 | M33: 0 | N33: 0 | O33: 0 | P33: 0 | Q33: 0 | R33: 0 | S33: 0 | T33: 0 | U33: 0 | V33: 0 | W33: 0 | X33: 0 | Y33: 0 | Z33: 0 | AA33: 0 | AB33: 0 | AC33: 0 | AD33: 0 | AE33: 0 | AF33: 0 | AG33: 0 | AH33: 0 | AI33: 0 | AJ33: - - | AK33: - -
B34: Liquefied Natural Gas | C34: Transportation Energy Use: Freight Rail: LNG: Reference case | D34: AEO.2023.REF2023.CNSM_NA_TRN_FRAIL_LNG_NA_NA_TRLBTU.A | E34: trillion Btu | G34: 0.515163 | H34: 1.02989 | I34: 1.614129 | J34: 2.103867 | K34: 2.704991 | L34: 3.499511 | M34: 4.540437 | N34: 5.909603 | O34: 7.400651 | P34: 9.170284 | Q34: 11.444215 | R34: 14.161068 | S34: 17.293554 | T34: 20.907318 | U34: 24.839417 | V34: 29.211893 | W34: 34.020897 | X34: 39.055111 | Y34: 44.546833 | Z34: 50.726471 | AA34: 57.249889 | AB34: 63.815086 | AC34: 70.632088 | AD34: 77.703888 | AE34: 85.240448 | AF34: 94.45433 | AG34: 103.73048 | AH34: 112.46571 | AI34: 121.5292 | AJ34: 0.215 | AK34: 0.223
B35: Domestic Shipping | C35: Transportation Energy Use: Domestic Shipping: Total: Reference case | D35: AEO.2023.REF2023.CNSM_NA_TRN_DMT_NA_NA_NA_TRLBTU.A | E35: trillion Btu | G35: 98.239021 | H35: 98.920753 | I35: 98.114662 | J35: 97.346069 | K35: 96.685867 | L35: 95.823471 | M35: 94.964699 | N35: 93.890503 | O35: 92.919189 | P35: 92.029816 | Q35: 91.401108 | R35: 90.674225 | S35: 89.934029 | T35: 89.168869 | U35: 88.333008 | V35: 87.614967 | W35: 86.833351 | X35: 86.156693 | Y35: 85.473595 | Z35: 84.846123 | AA35: 84.273766 | AB35: 83.705399 | AC35: 83.103455 | AD35: 82.418205 | AE35: 81.856209 | AF35: 81.249023 | AG35: 80.57312 | AH35: 79.990395 | AI35: 79.59285 | AJ35: -0.007 | AK35: -0.014
B36: Distillate Fuel Oil (diesel) | C36: Transportation Energy Use: Domestic Shipping: Distillate Fuel Oil: Reference case | D36: AEO.2023.REF2023.CNSM_NA_TRN_DMT_DFO_NA_NA_TRLBTU.A | E36: trillion Btu | G36: 95.724983 | H36: 96.410873 | I36: 95.648369 | J36: 94.922401 | K36: 94.299675 | L36: 93.480141 | M36: 92.663536 | N36: 91.636002 | O36: 90.709732 | P36: 89.864052 | Q36: 89.27182 | R36: 88.583908 | S36: 87.881882 | T36: 87.15461 | U36: 86.355026 | V36: 85.672012 | W36: 84.929306 | X36: 84.29055 | Y36: 83.598648 | Z36: 82.885956 | AA36: 82.221779 | AB36: 81.555756 | AC36: 80.850998 | AD36: 80.05899 | AE36: 79.380051 | AF36: 78.650116 | AG36: 77.846336 | AH36: 77.124741 | AI36: 76.572762 | AJ36: -0.008 | AK36: -0.014
B37: Residual Oil | C37: Transportation Energy Use: Domestic Shipping: Residual Oil: Reference case | D37: AEO.2023.REF2023.CNSM_NA_TRN_DMT_RFO_NA_NA_TRLBTU.A | E37: trillion Btu | G37: 1.875904 | H37: 1.807883 | I37: 1.713682 | J37: 1.621937 | K37: 1.541314 | L37: 1.455168 | M37: 1.371278 | N37: 1.286325 | O37: 1.199985 | P37: 1.112551 | Q37: 1.031564 | R37: 0.948396 | S37: 0.868606 | T37: 0.791824 | U37: 0.725306 | V37: 0.65481 | W37: 0.575319 | X37: 0.49193 | Y37: 0.417902 | Z37: 0.414755 | AA37: 0.411875 | AB37: 0.409016 | AC37: 0.40599 | AD37: 0.402548 | AE37: 0.399741 | AF37: 0.396733 | AG37: 0.393356 | AH37: 0.390453 | AI37: 0.388505 | AJ37: -0.055 | AK37: -0.061
B38: Compressed Natural Gas | C38: Transportation Energy Use: Domestic Shipping: CNG: Reference case | D38: AEO.2023.REF2023.CNSM_NA_TRN_DMT_CNG_NA_NA_TRLBTU.A | E38: trillion Btu | G38: 0 | H38: 0 | I38: 0 | J38: 0 | K38: 0 | L38: 0 | M38: 0 | N38: 0 | O38: 0 | P38: 0 | Q38: 0 | R38: 0 | S38: 0 | T38: 0 | U38: 0 | V38: 0 | W38: 0 | X38: 0 | Y38: 0 | Z38: 0 | AA38: 0 | AB38: 0 | AC38: 0 | AD38: 0 | AE38: 0 | AF38: 0 | AG38: 0 | AH38: 0 | AI38: 0 | AJ38: - - | AK38: - -
B39: Liquefied Natural Gas | C39: Transportation Energy Use: Domestic Shipping: LNG: Reference case | D39: AEO.2023.REF2023.CNSM_NA_TRN_DMT_LNG_NA_NA_TRLBTU.A | E39: trillion Btu | G39: 0.638131 | H39: 0.702 | I39: 0.752607 | J39: 0.801725 | K39: 0.84488 | L39: 0.888157 | M39: 0.929884 | N39: 0.968181 | O39: 1.009477 | P39: 1.053212 | Q39: 1.097725 | R39: 1.141919 | S39: 1.183538 | T39: 1.222433 | U39: 1.252678 | V39: 1.288148 | W39: 1.328728 | X39: 1.374214 | Y39: 1.457046 | Z39: 1.54541 | AA39: 1.640115 | AB39: 1.740627 | AC39: 1.846467 | AD39: 1.956663 | AE39: 2.076418 | AF39: 2.202173 | AG39: 2.333424 | AH39: 2.475207 | AI39: 2.631587 | AJ39: 0.052 | AK39: 0.048
B40: International Shipping | C40: Transportation Energy Use: International Shipping: Total: Reference case | D40: AEO.2023.REF2023.CNSM_NA_TRN_INTS_NA_NA_NA_TRLBTU.A | E40: trillion Btu | G40: 935.02771 | H40: 881.83038 | I40: 877.7273 | J40: 878.60413 | K40: 871.25031 | L40: 868.44873 | M40: 862.68933 | N40: 859.14197 | O40: 856.6344 | P40: 857.13648 | Q40: 857.43701 | R40: 858.00024 | S40: 857.76019 | T40: 858.2179 | U40: 857.54724 | V40: 857.61346 | W40: 857.63464 | X40: 857.34979 | Y40: 857.24542 | Z40: 857.30096 | AA40: 857.82971 | AB40: 857.81982 | AC40: 858.04791 | AD40: 858.06763 | AE40: 860.63342 | AF40: 860.92426 | AG40: 859.83441 | AH40: 859.1217 | AI40: 858.0946 | AJ40: -0.003 | AK40: 0.002
B41: Distillate Fuel Oil (diesel) | C41: Transportation Energy Use: International Shipping: Distillate Fuel Oil: Reference case | D41: AEO.2023.REF2023.CNSM_NA_TRN_INTS_DFO_NA_NA_TRLBTU.A | E41: trillion Btu | G41: 222.93867 | H41: 318.21375 | I41: 318.50684 | J41: 321.42749 | K41: 326.40894 | L41: 331.7504 | M41: 339.13263 | N41: 343.65381 | O41: 348.44 | P41: 348.61185 | Q41: 349.93619 | R41: 351.71851 | S41: 354.40064 | T41: 355.177 | U41: 356.67023 | V41: 356.87671 | W41: 358.82895 | X41: 358.93921 | Y41: 360.5722 | Z41: 361.26196 | AA41: 361.28479 | AB41: 360.64624 | AC41: 360.38776 | AD41: 360.0556 | AE41: 358.46176 | AF41: 357.26376 | AG41: 357.07413 | AH41: 355.22809 | AI41: 354.51148 | AJ41: 0.017 | AK41: -0.01
B42: Residual Oil | C42: Transportation Energy Use: International Shipping: Residual Oil: Reference case | D42: AEO.2023.REF2023.CNSM_NA_TRN_INTS_RFO_NA_NA_TRLBTU.A | E42: trillion Btu | G42: 685.66516 | H42: 532.14972 | I42: 519.35321 | J42: 520.34845 | K42: 497.46442 | L42: 487.75363 | M42: 469.75632 | N42: 458.26987 | O42: 449.82733 | P42: 449.95633 | Q42: 449.27518 | R42: 449.44376 | S42: 447.34497 | T42: 447.23685 | U42: 444.02316 | V42: 442.96899 | W42: 441.81567 | X42: 439.63165 | Y42: 437.97662 | Z42: 436.76758 | AA42: 436.80939 | AB42: 435.24387 | AC42: 434.29315 | AD42: 432.73309 | AE42: 438.45755 | AF42: 437.70047 | AG42: 432.9209 | AH42: 429.2475 | AI42: 424.56079 | AJ42: -0.017 | AK42: 0.005
B43: Compressed Natural Gas | C43: Transportation Energy Use: International Shipping: CNG: Reference case | D43: AEO.2023.REF2023.CNSM_NA_TRN_INTS_CNG_NA_NA_TRLBTU.A | E43: trillion Btu | G43: 0 | H43: 0 | I43: 0 | J43: 0 | K43: 0 | L43: 0 | M43: 0 | N43: 0 | O43: 0 | P43: 0 | Q43: 0 | R43: 0 | S43: 0 | T43: 0 | U43: 0 | V43: 0 | W43: 0 | X43: 0 | Y43: 0 | Z43: 0 | AA43: 0 | AB43: 0 | AC43: 0 | AD43: 0 | AE43: 0 | AF43: 0 | AG43: 0 | AH43: 0 | AI43: 0 | AJ43: - - | AK43: - -
B44: Liquefied Natural Gas | C44: Transportation Energy Use: International Shipping: LNG: Reference case | D44: AEO.2023.REF2023.CNSM_NA_TRN_INTS_LNG_NA_NA_TRLBTU.A | E44: trillion Btu | G44: 26.423862 | H44: 31.466925 | I44: 39.867241 | J44: 36.82819 | K44: 47.376953 | L44: 48.944679 | M44: 53.800423 | N44: 57.218277 | O44: 58.367088 | P44: 58.568268 | Q44: 58.225639 | R44: 56.838043 | S44: 56.014595 | T44: 55.804081 | U44: 56.853912 | V44: 57.767784 | W44: 56.989986 | X44: 58.778946 | Y44: 58.696617 | Z44: 59.2714 | AA44: 59.735519 | AB44: 61.929657 | AC44: 63.367027 | AD44: 65.278946 | AE44: 63.714081 | AF44: 65.960022 | AG44: 69.839432 | AH44: 74.646149 | AI44: 79.022369 | AJ44: 0.04 | AK44: 0.061
B45: Air Transportation | C45: Transportation Energy Use: Air: Total: Reference case | D45: AEO.2023.REF2023.CNSM_NA_TRN_AIR_NA_NA_NA_TRLBTU.A | E45: trillion Btu | G45: 2802.8074 | H45: 3008.168 | I45: 3051.2026 | J45: 3057.1106 | K45: 3095.8982 | L45: 3134.2268 | M45: 3164.5515 | N45: 3187.1082 | O45: 3202.9382 | P45: 3218.7827 | Q45: 3243.9363 | R45: 3270.448 | S45: 3294.4031 | T45: 3322.9241 | U45: 3359.8247 | V45: 3403.8945 | W45: 3450.1719 | X45: 3498.4883 | Y45: 3554.6438 | Z45: 3608.4033 | AA45: 3663.0974 | AB45: 3718.6245 | AC45: 3774.0098 | AD45: 3827.9187 | AE45: 3880.4333 | AF45: 3936.738 | AG45: 3993.604 | AH45: 4049.6506 | AI45: 4112.1577 | AJ45: 0.014 | AK45: 0.026
B46: Jet Fuel | C46: Transportation Energy Use: Air: Jet Fuel: Reference case | D46: AEO.2023.REF2023.CNSM_NA_TRN_AIR_JFL_NA_NA_TRLBTU.A | E46: trillion Btu | G46: 2780.3857 | H46: 2985.7573 | I46: 3028.801 | J46: 3034.7166 | K46: 3073.5105 | L46: 3111.8442 | M46: 3142.1731 | N46: 3164.7332 | O46: 3180.5662 | P46: 3196.4131 | Q46: 3221.5686 | R46: 3248.082 | S46: 3272.0386 | T46: 3300.5605 | U46: 3337.4622 | V46: 3381.5327 | W46: 3427.8108 | X46: 3476.1277 | Y46: 3532.2837 | Z46: 3586.0437 | AA46: 3640.738 | AB46: 3696.2654 | AC46: 3751.6509 | AD46: 3805.5598 | AE46: 3858.0747 | AF46: 3914.3794 | AG46: 3971.2456 | AH46: 4027.2922 | AI46: 4089.7993 | AJ46: 0.014 | AK46: 0.027
B47: Aviation Gasoline | C47: Transportation Energy Use: Air: Aviation Gasoline: Reference case | D47: AEO.2023.REF2023.CNSM_NA_TRN_AIR_AVGA_NA_NA_TRLBTU.A | E47: trillion Btu | G47: 22.421618 | H47: 22.410635 | I47: 22.401548 | J47: 22.394032 | K47: 22.387812 | L47: 22.382666 | M47: 22.378407 | N47: 22.374884 | O47: 22.371969 | P47: 22.369558 | Q47: 22.367563 | R47: 22.365911 | S47: 22.364546 | T47: 22.363417 | U47: 22.36248 | V47: 22.361708 | W47: 22.361067 | X47: 22.360538 | Y47: 22.3601 | Z47: 22.359737 | AA47: 22.359438 | AB47: 22.35919 | AC47: 22.358984 | AD47: 22.358814 | AE47: 22.358673 | AF47: 22.358557 | AG47: 22.358461 | AH47: 22.358381 | AI47: 22.358315 | AJ47: 0 | AK47: 0
B48: Military Use | C48: Transportation Energy Use: Military: Total: Reference case | D48: AEO.2023.REF2023.CNSM_NA_TRN_MILT_NA_NA_NA_TRLBTU.A | E48: trillion Btu | G48: 430.83188 | H48: 433.13123 | I48: 433.96753 | J48: 434.6282 | K48: 435.16168 | L48: 435.94711 | M48: 436.50568 | N48: 436.9512 | O48: 437.33203 | P48: 437.57639 | Q48: 437.74393 | R48: 437.82675 | S48: 437.85825 | T48: 437.87946 | U48: 438.00381 | V48: 438.20288 | W48: 438.41199 | X48: 438.63055 | Y48: 438.85791 | Z48: 439.09308 | AA48: 439.33536 | AB48: 439.58414 | AC48: 439.83881 | AD48: 440.09888 | AE48: 440.36389 | AF48: 440.63324 | AG48: 440.90668 | AH48: 441.18384 | AI48: 441.46451 | AJ48: 0.001 | AK48: 0
B49: Jet Fuel and Aviation Gasoline | C49: Transportation Energy Use: Military: Jet Fuel: Reference case | D49: AEO.2023.REF2023.CNSM_NA_TRN_MILT_JFL_NA_NA_TRLBTU.A | E49: trillion Btu | G49: 334.44891 | H49: 336.23386 | I49: 336.88306 | J49: 337.39594 | K49: 337.81006 | L49: 338.4198 | M49: 338.85339 | N49: 339.19925 | O49: 339.4949 | P49: 339.68457 | Q49: 339.81464 | R49: 339.87894 | S49: 339.90338 | T49: 339.91986 | U49: 340.01639 | V49: 340.17093 | W49: 340.33325 | X49: 340.50293 | Y49: 340.67941 | Z49: 340.86197 | AA49: 341.05005 | AB49: 341.24316 | AC49: 341.44086 | AD49: 341.64276 | AE49: 341.84848 | AF49: 342.05759 | AG49: 342.26984 | AH49: 342.48502 | AI49: 342.70288 | AJ49: 0.001 | AK49: 0
B50: Residual Fuel Oil | C50: Transportation Energy Use: Military: Residual Fuel Oil: Reference case | D50: AEO.2023.REF2023.CNSM_NA_TRN_MILT_RFO_NA_NA_TRLBTU.A | E50: trillion Btu | G50: 0 | H50: 0 | I50: 0 | J50: 0 | K50: 0 | L50: 0 | M50: 0 | N50: 0 | O50: 0 | P50: 0 | Q50: 0 | R50: 0 | S50: 0 | T50: 0 | U50: 0 | V50: 0 | W50: 0 | X50: 0 | Y50: 0 | Z50: 0 | AA50: 0 | AB50: 0 | AC50: 0 | AD50: 0 | AE50: 0 | AF50: 0 | AG50: 0 | AH50: 0 | AI50: 0 | AJ50: - - | AK50: 0
B51: Distillates and Diesel | C51: Transportation Energy Use: Military: Distillate Fuel Oil: Reference case | D51: AEO.2023.REF2023.CNSM_NA_TRN_MILT_DFO_NA_NA_TRLBTU.A | E51: trillion Btu | G51: 96.382973 | H51: 96.897369 | I51: 97.084457 | J51: 97.232269 | K51: 97.351608 | L51: 97.527321 | M51: 97.652275 | N51: 97.751961 | O51: 97.837143 | P51: 97.891815 | Q51: 97.929291 | R51: 97.947815 | S51: 97.954857 | T51: 97.959595 | U51: 97.987419 | V51: 98.031967 | W51: 98.078743 | X51: 98.12764 | Y51: 98.178513 | Z51: 98.231117 | AA51: 98.285309 | AB51: 98.340965 | AC51: 98.397942 | AD51: 98.456131 | AE51: 98.515411 | AF51: 98.575668 | AG51: 98.636826 | AH51: 98.698837 | AI51: 98.761627 | AJ51: 0.001 | AK51: 0
B52: Bus Transportation | C52: Transportation Energy Use: Bus: Reference case | D52: AEO.2023.REF2023.CNSM_NA_TRN_BUS_NA_NA_NA_TRLBTU.A | E52: trillion Btu | G52: 210.97722 | H52: 220.80747 | I52: 225.1512 | J52: 225.93091 | K52: 226.44176 | L52: 226.74643 | M52: 226.78705 | N52: 226.39072 | O52: 225.62442 | P52: 224.46057 | Q52: 223.25034 | R52: 223.04596 | S52: 222.35724 | T52: 221.45557 | U52: 220.40602 | V52: 218.77556 | W52: 217.16113 | X52: 215.39122 | Y52: 213.4718 | Z52: 211.4082 | AA52: 209.23976 | AB52: 206.76431 | AC52: 204.38597 | AD52: 201.85864 | AE52: 199.42545 | AF52: 196.48846 | AG52: 193.40808 | AH52: 189.77907 | AI52: 186.44667 | AJ52: -0.004 | AK52: 0.019
B53: Transit Bus | C53: Transportation Energy Use: Bus: Transit Bus: Reference case | D53: AEO.2023.REF2023.CNSM_NA_TRN_TBUS_NA_NA_NA_TRLBTU.A | E53: trillion Btu | G53: 92.212234 | H53: 95.83783 | I53: 98.320953 | J53: 98.870079 | K53: 99.844643 | L53: 100.61442 | M53: 101.24708 | N53: 101.61662 | O53: 101.72417 | P53: 101.53801 | Q53: 101.31126 | R53: 100.9764 | S53: 100.75687 | T53: 100.29507 | U53: 99.678467 | V53: 98.421806 | W53: 97.683716 | X53: 96.918678 | Y53: 96.071007 | Z53: 95.130722 | AA53: 94.233086 | AB53: 93.123825 | AC53: 92.2043 | AD53: 91.250328 | AE53: 90.65873 | AF53: 89.694473 | AG53: 88.826485 | AH53: 87.819649 | AI53: 86.904648 | AJ53: -0.002 | AK53: 0.01
A54: gasoline vehicle | B54: Motor Gasoline | C54: Transportation Energy Use: Bus: Transit Bus: Motor Gasoline: Reference case | D54: AEO.2023.REF2023.CNSM_NA_TRN_TBUS_MGS_NA_NA_TRLBTU.A | E54: trillion Btu | G54: 12.007432 | H54: 12.465114 | I54: 12.775763 | J54: 12.835154 | K54: 12.958027 | L54: 13.056922 | M54: 13.141269 | N54: 13.190033 | O54: 13.202685 | P54: 13.177554 | Q54: 13.150479 | R54: 13.109433 | S54: 13.083599 | T54: 13.026247 | U54: 12.949903 | V54: 12.790073 | W54: 12.696983 | X54: 12.600635 | Y54: 12.493633 | Z54: 12.37418 | AA54: 12.260481 | AB54: 12.119045 | AC54: 12.002355 | AD54: 11.880788 | AE54: 11.80858 | AF54: 11.685587 | AG54: 11.575792 | AH54: 11.447132 | AI54: 11.331304 | AJ54: -0.002 | AK54: 0.011
A55: gasoline vehicle | B55: E85 | C55: Transportation Energy Use: Bus: Transit Bus: E85: Reference case | D55: AEO.2023.REF2023.CNSM_NA_TRN_TBUS_E85_NA_NA_TRLBTU.A | E55: trillion Btu | G55: 0.007432 | H55: 0.007763 | I55: 0.007949 | J55: 0.008029 | K55: 0.008141 | L55: 0.00821 | M55: 0.008257 | N55: 0.008279 | O55: 0.008283 | P55: 0.008261 | Q55: 0.008229 | R55: 0.008189 | S55: 0.008157 | T55: 0.008107 | U55: 0.008042 | V55: 0.007961 | W55: 0.007883 | X55: 0.007803 | Y55: 0.007713 | Z55: 0.007615 | AA55: 0.007521 | AB55: 0.007398 | AC55: 0.007307 | AD55: 0.007215 | AE55: 0.007143 | AF55: 0.00705 | AG55: 0.006961 | AH55: 0.006864 | AI55: 0.006769 | AJ55: -0.003 | AK55: 0.003
A56: diesel vehicle | B56: Distillate Fuel Oil (diesel) | C56: Transportation Energy Use: Bus: Transit Bus: Distillate Fuel Oil: Reference case | D56: AEO.2023.REF2023.CNSM_NA_TRN_TBUS_DFO_NA_NA_TRLBTU.A | E56: trillion Btu | G56: 52.012611 | H56: 54.015755 | I56: 55.245651 | J56: 55.522507 | K56: 56.047764 | L56: 56.442497 | M56: 56.754585 | N56: 56.903236 | O56: 56.888607 | P56: 56.712852 | Q56: 56.517418 | R56: 56.260185 | S56: 56.054283 | T56: 55.704571 | U56: 55.26152 | V56: 54.562843 | W56: 54.018444 | X56: 53.439865 | Y56: 52.799095 | Z56: 52.084652 | AA56: 51.363411 | AB56: 50.487484 | AC56: 49.676125 | AD56: 48.788139 | AE56: 48.012001 | AF56: 46.925766 | AG56: 45.703896 | AH56: 44.05574 | AI56: 42.693802 | AJ56: -0.007 | AK56: 0.005
A57: natural gas vehicle | B57: Compressed/Liquefied Natural Gas | C57: Transportation Energy Use: Bus: Transit Bus: Natural Gas: Reference case | D57: AEO.2023.REF2023.CNSM_NA_TRN_TBUS_NG_NA_NA_TRLBTU.A | E57: trillion Btu | G57: 26.102913 | H57: 27.152719 | I57: 27.997173 | J57: 28.156235 | K57: 28.412041 | L57: 28.617826 | M57: 28.781719 | N57: 28.881859 | O57: 28.919271 | P57: 28.863106 | Q57: 28.782406 | R57: 28.664639 | S57: 28.58287 | T57: 28.43108 | U57: 28.230478 | V57: 27.752499 | W57: 27.526546 | X57: 27.295059 | Y57: 27.037399 | Z57: 26.75387 | AA57: 26.484291 | AB57: 26.160324 | AC57: 25.88516 | AD57: 25.601519 | AE57: 25.421154 | AF57: 25.134628 | AG57: 24.876854 | AH57: 24.58086 | AI57: 24.309217 | AJ57: -0.003 | AK57: 0.01
A58: LPG vehicle | B58: Propane | C58: Transportation Energy Use: Bus: Transit Bus: Propane: Reference case | D58: AEO.2023.REF2023.CNSM_NA_TRN_TBUS_LPG_NA_NA_TRLBTU.A | E58: trillion Btu | G58: 1.475766 | H58: 1.532684 | I58: 1.572022 | J58: 1.578621 | K58: 1.595975 | L58: 1.609501 | M58: 1.620445 | N58: 1.627665 | O58: 1.630974 | P58: 1.629221 | Q58: 1.626818 | R58: 1.622336 | S58: 1.619639 | T58: 1.613038 | U58: 1.60452 | V58: 1.5851 | W58: 1.57385 | X58: 1.56229 | Y58: 1.549139 | Z58: 1.534283 | AA58: 1.520311 | AB58: 1.501987 | AC58: 1.487985 | AD58: 1.473216 | AE58: 1.465529 | AF58: 1.450458 | AG58: 1.437376 | AH58: 1.421625 | AI58: 1.407719 | AJ58: -0.002 | AK58: 0.016
A59: battery electric vehicle | B59: Electricity | C59: Transportation Energy Use: Bus: Transit Bus: Electricity: Reference case | D59: AEO.2023.REF2023.CNSM_NA_TRN_TBUS_ELC_NA_NA_TRLBTU.A | E59: trillion Btu | G59: 0.582963 | H59: 0.639772 | I59: 0.697459 | J59: 0.744435 | K59: 0.797369 | L59: 0.853976 | M59: 0.915217 | N59: 0.979902 | O59: 1.04869 | P59: 1.121444 | Q59: 1.200446 | R59: 1.286315 | S59: 1.38315 | T59: 1.48702 | U59: 1.599227 | V59: 1.699166 | W59: 1.836078 | X59: 1.989325 | Y59: 2.160585 | Z59: 2.35296 | AA59: 2.574177 | AB59: 2.82502 | AC59: 3.12307 | AD59: 3.477429 | AE59: 3.922498 | AF59: 4.469448 | AG59: 5.204321 | AH59: 6.286437 | AI59: 7.135109 | AJ59: 0.094 | AK59: 0.106
A60: hydrogen vehicle | B60: Hydrogen | C60: Transportation Energy Use: Bus: Transit Bus: Hydrogen: Reference case | D60: AEO.2023.REF2023.CNSM_NA_TRN_TBUS_HDG_NA_NA_TRLBTU.A | E60: trillion Btu | G60: 0.023117 | H60: 0.024035 | I60: 0.024939 | J60: 0.025099 | K60: 0.025319 | L60: 0.025482 | M60: 0.025596 | N60: 0.025651 | O60: 0.025658 | P60: 0.025573 | Q60: 0.025453 | R60: 0.025301 | S60: 0.025183 | T60: 0.025003 | U60: 0.024774 | V60: 0.024169 | W60: 0.023939 | X60: 0.023702 | Y60: 0.023444 | Z60: 0.023163 | AA60: 0.022893 | AB60: 0.022575 | AC60: 0.022303 | AD60: 0.022027 | AE60: 0.021823 | AF60: 0.021545 | AG60: 0.021284 | AH60: 0.020997 | AI60: 0.020723 | AJ60: -0.004 | AK60: 0.012
B61: Intercity Bus | C61: Transportation Energy Use: Bus: Intercity Bus: Reference case | D61: AEO.2023.REF2023.CNSM_NA_TRN_IBUS_NA_NA_NA_TRLBTU.A | E61: trillion Btu | G61: 26.118862 | H61: 28.024412 | I61: 29.477226 | J61: 30.571621 | K61: 31.3964 | L61: 32.010113 | M61: 32.464531 | N61: 32.799759 | O61: 33.046234 | P61: 33.226051 | Q61: 33.352478 | R61: 33.43018 | S61: 33.466476 | T61: 33.46925 | U61: 33.44516 | V61: 33.397396 | W61: 33.349758 | X61: 33.294384 | Y61: 33.234276 | Z61: 33.167286 | AA61: 33.096901 | AB61: 33.025082 | AC61: 32.951077 | AD61: 32.875145 | AE61: 32.799278 | AF61: 32.723492 | AG61: 32.646706 | AH61: 32.56945 | AI61: 32.494362 | AJ61: 0.008 | AK61: 0.022
A62: gasoline vehicle | B62: Motor Gasoline | C62: Transportation Energy Use: Bus: Intercity Bus: Motor Gasoline: Reference case | D62: AEO.2023.REF2023.CNSM_NA_TRN_IBUS_MGS_NA_NA_TRLBTU.A | E62: trillion Btu | G62: 0 | H62: 0 | I62: 0 | J62: 0 | K62: 0 | L62: 0 | M62: 0 | N62: 0 | O62: 0 | P62: 0 | Q62: 0 | R62: 0 | S62: 0 | T62: 0 | U62: 0 | V62: 0 | W62: 0 | X62: 0 | Y62: 0 | Z62: 0 | AA62: 0 | AB62: 0 | AC62: 0 | AD62: 0 | AE62: 0 | AF62: 0 | AG62: 0 | AH62: 0 | AI62: 0 | AJ62: - - | AK62: - -
A63: gasoline vehicle | B63: E85 | C63: Transportation Energy Use: Bus: Intercity Bus: E85: Reference case | D63: AEO.2023.REF2023.CNSM_NA_TRN_IBUS_E85_NA_NA_TRLBTU.A | E63: trillion Btu | G63: 0 | H63: 0 | I63: 0 | J63: 0 | K63: 0 | L63: 0 | M63: 0 | N63: 0 | O63: 0 | P63: 0 | Q63: 0 | R63: 0 | S63: 0 | T63: 0 | U63: 0 | V63: 0 | W63: 0 | X63: 0 | Y63: 0 | Z63: 0 | AA63: 0 | AB63: 0 | AC63: 0 | AD63: 0 | AE63: 0 | AF63: 0 | AG63: 0 | AH63: 0 | AI63: 0 | AJ63: - - | AK63: - -
A64: diesel vehicle | B64: Distillate Fuel Oil (diesel) | C64: Transportation Energy Use: Bus: Intercity Bus: Distillate Fuel Oil: Reference case | D64: AEO.2023.REF2023.CNSM_NA_TRN_IBUS_DFO_NA_NA_TRLBTU.A | E64: trillion Btu | G64: 26.118862 | H64: 28.024412 | I64: 29.477226 | J64: 30.571621 | K64: 31.3964 | L64: 32.010113 | M64: 32.464531 | N64: 32.799759 | O64: 33.046234 | P64: 33.226051 | Q64: 33.352478 | R64: 33.43018 | S64: 33.466476 | T64: 33.46925 | U64: 33.44516 | V64: 33.397396 | W64: 33.349758 | X64: 33.294384 | Y64: 33.234276 | Z64: 33.167286 | AA64: 33.096901 | AB64: 33.025082 | AC64: 32.951077 | AD64: 32.875145 | AE64: 32.799278 | AF64: 32.723492 | AG64: 32.646706 | AH64: 32.56945 | AI64: 32.494362 | AJ64: 0.008 | AK64: 0.022
A65: natural gas vehicle | B65: Compressed/Liquefied Natural Gas | C65: Transportation Energy Use: Bus: Intercity Bus: Natural Gas: Reference case | D65: AEO.2023.REF2023.CNSM_NA_TRN_IBUS_NG_NA_NA_TRLBTU.A | E65: trillion Btu | G65: 0 | H65: 0 | I65: 0 | J65: 0 | K65: 0 | L65: 0 | M65: 0 | N65: 0 | O65: 0 | P65: 0 | Q65: 0 | R65: 0 | S65: 0 | T65: 0 | U65: 0 | V65: 0 | W65: 0 | X65: 0 | Y65: 0 | Z65: 0 | AA65: 0 | AB65: 0 | AC65: 0 | AD65: 0 | AE65: 0 | AF65: 0 | AG65: 0 | AH65: 0 | AI65: 0 | AJ65: - - | AK65: - -
A66: LPG vehicle | B66: Propane | C66: Transportation Energy Use: Bus: Intercity Bus: Propane: Reference case | D66: AEO.2023.REF2023.CNSM_NA_TRN_IBUS_LPG_NA_NA_TRLBTU.A | E66: trillion Btu | G66: 0 | H66: 0 | I66: 0 | J66: 0 | K66: 0 | L66: 0 | M66: 0 | N66: 0 | O66: 0 | P66: 0 | Q66: 0 | R66: 0 | S66: 0 | T66: 0 | U66: 0 | V66: 0 | W66: 0 | X66: 0 | Y66: 0 | Z66: 0 | AA66: 0 | AB66: 0 | AC66: 0 | AD66: 0 | AE66: 0 | AF66: 0 | AG66: 0 | AH66: 0 | AI66: 0 | AJ66: - - | AK66: - -
A67: battery electric vehicle | B67: Electricity | C67: Transportation Energy Use: Bus: Intercity Bus: Electricity: Reference case | D67: AEO.2023.REF2023.CNSM_NA_TRN_IBUS_ELC_NA_NA_TRLBTU.A | E67: trillion Btu | G67: 0 | H67: 0 | I67: 0 | J67: 0 | K67: 0 | L67: 0 | M67: 0 | N67: 0 | O67: 0 | P67: 0 | Q67: 0 | R67: 0 | S67: 0 | T67: 0 | U67: 0 | V67: 0 | W67: 0 | X67: 0 | Y67: 0 | Z67: 0 | AA67: 0 | AB67: 0 | AC67: 0 | AD67: 0 | AE67: 0 | AF67: 0 | AG67: 0 | AH67: 0 | AI67: 0 | AJ67: - - | AK67: - -
A68: hydrogen vehicle | B68: Hydrogen | C68: Transportation Energy Use: Bus: Intercity Bus: Hydrogen: Reference case | D68: AEO.2023.REF2023.CNSM_NA_TRN_IBUS_HDG_NA_NA_TRLBTU.A | E68: trillion Btu | G68: 0 | H68: 0 | I68: 0 | J68: 0 | K68: 0 | L68: 0 | M68: 0 | N68: 0 | O68: 0 | P68: 0 | Q68: 0 | R68: 0 | S68: 0 | T68: 0 | U68: 0 | V68: 0 | W68: 0 | X68: 0 | Y68: 0 | Z68: 0 | AA68: 0 | AB68: 0 | AC68: 0 | AD68: 0 | AE68: 0 | AF68: 0 | AG68: 0 | AH68: 0 | AI68: 0 | AJ68: - - | AK68: - -
B69: School Bus | C69: Transportation Energy Use: Bus: School Bus: Reference case | D69: AEO.2023.REF2023.CNSM_NA_TRN_LSRC_NA_NA_NA_TRLBTU.A | E69: trillion Btu | G69: 93.831894 | H69: 98.450195 | I69: 99.158546 | J69: 98.571014 | K69: 97.556511 | L69: 96.613396 | M69: 95.691032 | N69: 94.739861 | O69: 93.77755 | P69: 92.791618 | Q69: 91.866196 | R69: 91.598053 | S69: 91.112289 | T69: 90.70887 | U69: 90.37265 | V69: 90.12104 | W69: 89.542336 | X69: 88.885452 | Y69: 88.194603 | Z69: 87.485649 | AA69: 86.702446 | AB69: 85.868294 | AC69: 84.99823 | AD69: 84.089134 | AE69: 83.076744 | AF69: 82.045021 | AG69: 80.986786 | AH69: 79.893326 | AI69: 78.783607 | AJ69: -0.006 | AK69: 0.033
A70: gasoline vehicle | B70: Motor Gasoline | C70: Transportation Energy Use: Bus: School Bus: Motor Gasoline: Reference case | D70: AEO.2023.REF2023.CNSM_NA_TRN_LSRC_MGS_NA_NA_TRLBTU.A | E70: trillion Btu | G70: 9.494101 | H70: 9.984732 | I70: 10.080206 | J70: 10.044081 | K70: 9.964186 | L70: 9.877207 | M70: 9.790693 | N70: 9.703547 | O70: 9.615687 | P70: 9.526428 | Q70: 9.443931 | R70: 9.376018 | S70: 9.31937 | T70: 9.272266 | U70: 9.234446 | V70: 9.206593 | W70: 9.15974 | X70: 9.107673 | Y70: 9.053213 | Z70: 8.997488 | AA70: 8.938418 | AB70: 8.875582 | AC70: 8.809856 | AD70: 8.741948 | AE70: 8.671112 | AF70: 8.599361 | AG70: 8.527375 | AH70: 8.454552 | AI70: 8.381558 | AJ70: -0.004 | AK70: 0.033
A71: gasoline vehicle | B71: E85 | C71: Transportation Energy Use: Bus: School Bus: E85: Reference case | D71: AEO.2023.REF2023.CNSM_NA_TRN_LSRC_E85_NA_NA_TRLBTU.A | E71: trillion Btu | G71: 0 | H71: 0 | I71: 0 | J71: 0 | K71: 0 | L71: 0 | M71: 0 | N71: 0 | O71: 0 | P71: 0 | Q71: 0 | R71: 0 | S71: 0 | T71: 0 | U71: 0 | V71: 0 | W71: 0 | X71: 0 | Y71: 0 | Z71: 0 | AA71: 0 | AB71: 0 | AC71: 0 | AD71: 0 | AE71: 0 | AF71: 0 | AG71: 0 | AH71: 0 | AI71: 0 | AJ71: - - | AK71: - -
A72: diesel vehicle | B72: Distillate Fuel Oil (diesel) | C72: Transportation Energy Use: Bus: School Bus: Distillate Fuel Oil: Reference case | D72: AEO.2023.REF2023.CNSM_NA_TRN_LSRC_DFO_NA_NA_TRLBTU.A | E72: trillion Btu | G72: 75.219894 | H72: 78.60582 | I72: 78.857498 | J72: 78.076454 | K72: 76.964111 | L72: 76.07975 | M72: 75.233322 | N72: 74.338867 | O72: 73.430573 | P72: 72.491913 | Q72: 71.594032 | R72: 71.837708 | S72: 71.512497 | T72: 71.239052 | U72: 70.989594 | V72: 70.790924 | W72: 70.163765 | X72: 69.442642 | Y72: 68.681885 | Z72: 67.900276 | AA72: 67.010056 | AB72: 66.063095 | AC72: 65.078491 | AD72: 64.041969 | AE72: 62.83419 | AF72: 61.60294 | AG72: 60.321541 | AH72: 58.979691 | AI72: 57.60738 | AJ72: -0.009 | AK72: 0.033
A73: natural gas vehicle | B73: Compressed/Liquefied Natural Gas | C73: Transportation Energy Use: Bus: School Bus: Natural Gas: Reference case | D73: AEO.2023.REF2023.CNSM_NA_TRN_LSRC_NG_NA_NA_TRLBTU.A | E73: trillion Btu | G73: 0.924086 | H73: 1.010828 | I73: 1.053611 | J73: 1.083197 | K73: 1.104337 | L73: 1.12353 | M73: 1.14085 | N73: 1.156073 | O73: 1.171249 | P73: 1.185954 | Q73: 1.20149 | R73: 1.218719 | S73: 1.237236 | T73: 1.256583 | U73: 1.277304 | V73: 1.299385 | W73: 1.318905 | X73: 1.337343 | Y73: 1.355548 | Z73: 1.373292 | AA73: 1.390433 | AB73: 1.4067 | AC73: 1.42267 | AD73: 1.438181 | AE73: 1.45274 | AF73: 1.462957 | AG73: 1.473053 | AH73: 1.482996 | AI73: 1.492894 | AJ73: 0.017 | AK73: 0.05
A74: LPG vehicle | B74: Propane | C74: Transportation Energy Use: Bus: School Bus: Propane: Reference case | D74: AEO.2023.REF2023.CNSM_NA_TRN_LSRC_LPG_NA_NA_TRLBTU.A | E74: trillion Btu | G74: 7.621545 | H74: 8.015407 | I74: 8.092051 | J74: 8.06305 | K74: 7.998913 | L74: 7.929089 | M74: 7.85964 | N74: 7.78968 | O74: 7.71915 | P74: 7.647495 | Q74: 7.581269 | R74: 7.526752 | S74: 7.481277 | T74: 7.443463 | U74: 7.413102 | V74: 7.390742 | W74: 7.353132 | X74: 7.311333 | Y74: 7.267616 | Z74: 7.22288 | AA74: 7.175461 | AB74: 7.125019 | AC74: 7.072256 | AD74: 7.017741 | AE74: 6.960877 | AF74: 6.903278 | AG74: 6.84549 | AH74: 6.78703 | AI74: 6.728433 | AJ74: -0.004 | AK74: 0.033
A75: battery electric vehicle | B75: Electricity | C75: Transportation Energy Use: Bus: School Bus: Electricity: Reference case | D75: AEO.2023.REF2023.CNSM_NA_TRN_LSRC_ELC_NA_NA_TRLBTU.A | E75: trillion Btu | G75: 0.572265 | H75: 0.833416 | I75: 1.075178 | J75: 1.30423 | K75: 1.524958 | L75: 1.603828 | M75: 1.66653 | N75: 1.751691 | O75: 1.8409 | P75: 1.939823 | Q75: 2.045474 | R75: 1.638865 | S75: 1.561909 | T75: 1.497497 | U75: 1.458207 | V75: 1.433402 | W75: 1.546791 | X75: 1.686464 | Y75: 1.836342 | Z75: 1.991712 | AA75: 2.188076 | AB75: 2.397905 | AC75: 2.614949 | AD75: 2.849298 | AE75: 3.157824 | AF75: 3.476489 | AG75: 3.819326 | AH75: 4.189054 | AI75: 4.573342 | AJ75: 0.077 | AK75: - -
A76: hydrogen vehicle | B76: Hydrogen | C76: Transportation Energy Use: Bus: School Bus: Hydrogen: Reference case | D76: AEO.2023.REF2023.CNSM_NA_TRN_LSRC_HDG_NA_NA_TRLBTU.A | E76: trillion Btu | G76: 0 | H76: 0 | I76: 0 | J76: 0 | K76: 0 | L76: 0 | M76: 0 | N76: 0 | O76: 0 | P76: 0 | Q76: 0 | R76: 0 | S76: 0 | T76: 0 | U76: 0 | V76: 0 | W76: 0 | X76: 0 | Y76: 0 | Z76: 0 | AA76: 0 | AB76: 0 | AC76: 0 | AD76: 0 | AE76: 0 | AF76: 0 | AG76: 0 | AH76: 0 | AI76: 0 | AJ76: - - | AK76: - -
B77: Rail Transportation | C77: Transportation Energy Use: Rail: Reference case | D77: AEO.2023.REF2023.CNSM_NA_TRN_RAIL_NA_NA_NA_TRLBTU.A | E77: trillion Btu | G77: 43.913422 | H77: 45.563988 | I77: 46.540951 | J77: 47.205399 | K77: 47.900013 | L77: 48.570526 | M77: 49.132919 | N77: 49.707283 | O77: 50.150032 | P77: 50.598679 | Q77: 51.1395 | R77: 51.726662 | S77: 52.369225 | T77: 52.923794 | U77: 53.456974 | V77: 53.972694 | W77: 54.509743 | X77: 55.033695 | Y77: 55.626583 | Z77: 56.181145 | AA77: 56.75378 | AB77: 57.257599 | AC77: 57.815628 | AD77: 58.366592 | AE77: 59.116035 | AF77: 59.751427 | AG77: 60.444683 | AH77: 61.080704 | AI77: 61.848125 | AJ77: 0.012 | AK77: 0.027
B78: Intercity Rail | C78: Transportation Energy Use: Rail: Intercity Rail: Reference case | D78: AEO.2023.REF2023.CNSM_NA_TRN_IRAIL_NA_NA_NA_TRLBTU.A | E78: trillion Btu | G78: 7.594637 | H78: 8.270811 | I78: 8.811752 | J78: 9.242524 | K78: 9.58907 | L78: 9.871216 | M78: 10.105147 | N78: 10.303372 | O78: 10.475068 | P78: 10.626024 | Q78: 10.758954 | R78: 10.875568 | S78: 10.979033 | T78: 11.071654 | U78: 11.154877 | V78: 11.229655 | W78: 11.304667 | X78: 11.377219 | Y78: 11.447278 | Z78: 11.515232 | AA78: 11.582256 | AB78: 11.648867 | AC78: 11.715138 | AD78: 11.781057 | AE78: 11.847012 | AF78: 11.912785 | AG78: 11.978335 | AH78: 12.043905 | AI78: 12.109465 | AJ78: 0.017 | AK78: 0.03
B79: Electricity | C79: Transportation Energy Use: Rail: Intercity Rail: Electricity: Reference case | D79: AEO.2023.REF2023.CNSM_NA_TRN_IRAIL_ELC_NA_NA_TRLBTU.A | E79: trillion Btu | G79: 0.923149 | H79: 1.00534 | I79: 1.071092 | J79: 1.123454 | K79: 1.165578 | L79: 1.199873 | M79: 1.228308 | N79: 1.252403 | O79: 1.273273 | P79: 1.291622 | Q79: 1.30778 | R79: 1.321955 | S79: 1.334531 | T79: 1.34579 | U79: 1.355906 | V79: 1.364995 | W79: 1.374113 | X79: 1.382932 | Y79: 1.391448 | Z79: 1.399708 | AA79: 1.407855 | AB79: 1.415952 | AC79: 1.424006 | AD79: 1.432019 | AE79: 1.440037 | AF79: 1.448031 | AG79: 1.455999 | AH79: 1.463969 | AI79: 1.471938 | AJ79: 0.017 | AK79: 0.03
B80: Diesel | C80: Transportation Energy Use: Rail: Intercity Rail: Diesel: Reference case | D80: AEO.2023.REF2023.CNSM_NA_TRN_IRAIL_DSL_NA_NA_TRLBTU.A | E80: trillion Btu | G80: 6.671488 | H80: 7.265471 | I80: 7.74066 | J80: 8.11907 | K80: 8.423492 | L80: 8.671343 | M80: 8.87684 | N80: 9.050969 | O80: 9.201796 | P80: 9.334402 | Q80: 9.451174 | R80: 9.553614 | S80: 9.644503 | T80: 9.725864 | U80: 9.798971 | V80: 9.86466 | W80: 9.930554 | X80: 9.994287 | Y80: 10.05583 | Z80: 10.115524 | AA80: 10.174401 | AB80: 10.232915 | AC80: 10.291132 | AD80: 10.349038 | AE80: 10.406975 | AF80: 10.464753 | AG80: 10.522336 | AH80: 10.579936 | AI80: 10.637527 | AJ80: 0.017 | AK80: 0.03
B81: Compressed Natural Gas | C81: Transportation Energy Use: Rail: Intercity Rail: CNG: Reference case | D81: AEO.2023.REF2023.CNSM_NA_TRN_IRAIL_CNG_NA_NA_TRLBTU.A | E81: trillion Btu | G81: 0 | H81: 0 | I81: 0 | J81: 0 | K81: 0 | L81: 0 | M81: 0 | N81: 0 | O81: 0 | P81: 0 | Q81: 0 | R81: 0 | S81: 0 | T81: 0 | U81: 0 | V81: 0 | W81: 0 | X81: 0 | Y81: 0 | Z81: 0 | AA81: 0 | AB81: 0 | AC81: 0 | AD81: 0 | AE81: 0 | AF81: 0 | AG81: 0 | AH81: 0 | AI81: 0 | AJ81: - - | AK81: - -
B82: Liquefied Natural Gas | C82: Transportation Energy Use: Rail: Intercity Rail: LNG: Reference case | D82: AEO.2023.REF2023.CNSM_NA_TRN_IRAIL_LNG_NA_NA_TRLBTU.A | E82: trillion Btu | G82: 0 | H82: 0 | I82: 0 | J82: 0 | K82: 0 | L82: 0 | M82: 0 | N82: 0 | O82: 0 | P82: 0 | Q82: 0 | R82: 0 | S82: 0 | T82: 0 | U82: 0 | V82: 0 | W82: 0 | X82: 0 | Y82: 0 | Z82: 0 | AA82: 0 | AB82: 0 | AC82: 0 | AD82: 0 | AE82: 0 | AF82: 0 | AG82: 0 | AH82: 0 | AI82: 0 | AJ82: - - | AK82: - -
B83: Transit Rail | C83: Transportation Energy Use: Rail: Transit Rail: Reference case | D83: AEO.2023.REF2023.CNSM_NA_TRN_TRAIL_NA_NA_NA_TRLBTU.A | E83: trillion Btu | G83: 17.032639 | H83: 17.333525 | I83: 17.471111 | J83: 17.514868 | K83: 17.667709 | L83: 17.921017 | M83: 18.139038 | N83: 18.293453 | O83: 18.389309 | P83: 18.446941 | Q83: 18.571213 | R83: 18.730658 | S83: 18.930088 | T83: 19.092125 | U83: 19.259436 | V83: 19.415512 | W83: 19.584526 | X83: 19.751869 | Y83: 19.950642 | Z83: 20.133373 | AA83: 20.32523 | AB83: 20.481424 | AC83: 20.667053 | AD83: 20.844881 | AE83: 21.123302 | AF83: 21.333515 | AG83: 21.575636 | AH83: 21.790667 | AI83: 22.070597 | AJ83: 0.009 | AK83: 0.026
B84: Electricity | C84: Transportation Energy Use: Rail: Transit Rail: Electricity: Reference case | D84: AEO.2023.REF2023.CNSM_NA_TRN_TRAIL_ELC_NA_NA_TRLBTU.A | E84: trillion Btu | G84: 17.032639 | H84: 17.333525 | I84: 17.471111 | J84: 17.514868 | K84: 17.667709 | L84: 17.921017 | M84: 18.139038 | N84: 18.293453 | O84: 18.389309 | P84: 18.446941 | Q84: 18.571213 | R84: 18.730658 | S84: 18.930088 | T84: 19.092125 | U84: 19.259436 | V84: 19.415512 | W84: 19.584526 | X84: 19.751869 | Y84: 19.950642 | Z84: 20.133373 | AA84: 20.32523 | AB84: 20.481424 | AC84: 20.667053 | AD84: 20.844881 | AE84: 21.123302 | AF84: 21.333515 | AG84: 21.575636 | AH84: 21.790667 | AI84: 22.070597 | AJ84: 0.009 | AK84: 0.026
B85: Commuter Rail | C85: Transportation Energy Use: Rail: Commuter Rail: Reference case | D85: AEO.2023.REF2023.CNSM_NA_TRN_CRAIL_NA_NA_NA_TRLBTU.A | E85: trillion Btu | G85: 19.286148 | H85: 19.959654 | I85: 20.258087 | J85: 20.448008 | K85: 20.643234 | L85: 20.778294 | M85: 20.888737 | N85: 21.11046 | O85: 21.285656 | P85: 21.525711 | Q85: 21.809334 | R85: 22.120438 | S85: 22.4601 | T85: 22.760014 | U85: 23.042664 | V85: 23.327526 | W85: 23.620548 | X85: 23.904606 | Y85: 24.228664 | Z85: 24.532539 | AA85: 24.846294 | AB85: 25.127308 | AC85: 25.433437 | AD85: 25.740656 | AE85: 26.145723 | AF85: 26.505127 | AG85: 26.890711 | AH85: 27.246132 | AI85: 27.668062 | AJ85: 0.013 | AK85: 0.025
B86: Electricity | C86: Transportation Energy Use: Rail: Commuter Rail: Electricity: Reference case | D86: AEO.2023.REF2023.CNSM_NA_TRN_CRAIL_ELC_NA_NA_TRLBTU.A | E86: trillion Btu | G86: 6.966804 | H86: 7.205571 | I86: 7.306987 | J86: 7.360508 | K86: 7.396221 | L86: 7.403453 | M86: 7.403485 | N86: 7.460123 | O86: 7.507533 | P86: 7.606305 | Q86: 7.72276 | R86: 7.850501 | S86: 7.987139 | T86: 8.106824 | U86: 8.220928 | V86: 8.337174 | W86: 8.455911 | X86: 8.570151 | Y86: 8.700564 | Z86: 8.823834 | AA86: 8.949368 | AB86: 9.06256 | AC86: 9.184396 | AD86: 9.305553 | AE86: 9.463213 | AF86: 9.603458 | AG86: 9.752829 | AH86: 9.890326 | AI86: 10.053587 | AJ86: 0.013 | AK86: 0.025
B87: Diesel | C87: Transportation Energy Use: Rail: Commuter Rail: Diesel: Reference case | D87: AEO.2023.REF2023.CNSM_NA_TRN_CRAIL_DSL_NA_NA_TRLBTU.A | E87: trillion Btu | G87: 12.319345 | H87: 12.754084 | I87: 12.951099 | J87: 13.0875 | K87: 13.247013 | L87: 13.37484 | M87: 13.48525 | N87: 13.650337 | O87: 13.778123 | P87: 13.919407 | Q87: 14.086574 | R87: 14.269936 | S87: 14.47296 | T87: 14.65319 | U87: 14.821736 | V87: 14.990353 | W87: 15.164637 | X87: 15.334455 | Y87: 15.528099 | Z87: 15.708706 | AA87: 15.896927 | AB87: 16.064747 | AC87: 16.249043 | AD87: 16.435102 | AE87: 16.68251 | AF87: 16.901669 | AG87: 17.137882 | AH87: 17.355804 | AI87: 17.614475 | AJ87: 0.013 | AK87: 0.026
B88: Compressed Natural Gas | C88: Transportation Energy Use: Rail: Commuter Rail: CNG: Reference case | D88: AEO.2023.REF2023.CNSM_NA_TRN_CRAIL_CNG_NA_NA_TRLBTU.A | E88: trillion Btu | G88: 0 | H88: 0 | I88: 0 | J88: 0 | K88: 0 | L88: 0 | M88: 0 | N88: 0 | O88: 0 | P88: 0 | Q88: 0 | R88: 0 | S88: 0 | T88: 0 | U88: 0 | V88: 0 | W88: 0 | X88: 0 | Y88: 0 | Z88: 0 | AA88: 0 | AB88: 0 | AC88: 0 | AD88: 0 | AE88: 0 | AF88: 0 | AG88: 0 | AH88: 0 | AI88: 0 | AJ88: - - | AK88: - -
B89: Liquefied Natural Gas | C89: Transportation Energy Use: Rail: Commuter Rail: LNG: Reference case | D89: AEO.2023.REF2023.CNSM_NA_TRN_CRAIL_LNG_NA_NA_TRLBTU.A | E89: trillion Btu | G89: 0 | H89: 0 | I89: 0 | J89: 0 | K89: 0 | L89: 0 | M89: 0 | N89: 0 | O89: 0 | P89: 0 | Q89: 0 | R89: 0 | S89: 0 | T89: 0 | U89: 0 | V89: 0 | W89: 0 | X89: 0 | Y89: 0 | Z89: 0 | AA89: 0 | AB89: 0 | AC89: 0 | AD89: 0 | AE89: 0 | AF89: 0 | AG89: 0 | AH89: 0 | AI89: 0 | AJ89: - - | AK89: - -
B90: Recreational Boats | C90: Transportation Energy Use: Recreation Boats: Reference case | D90: AEO.2023.REF2023.CNSM_NA_TRN_RCB_NA_NA_NA_TRLBTU.A | E90: trillion Btu | G90: 202.83664 | H90: 199.16296 | I90: 195.80548 | J90: 193.73721 | K90: 192.81314 | L90: 191.8974 | M90: 190.73351 | N90: 189.21046 | O90: 187.40353 | P90: 185.67694 | Q90: 184.46689 | R90: 183.61003 | S90: 182.77757 | T90: 181.99818 | U90: 181.45029 | V90: 181.10551 | W90: 180.74588 | X90: 180.38298 | Y90: 180.29542 | Z90: 180.16119 | AA90: 179.98802 | AB90: 179.81351 | AC90: 179.55652 | AD90: 179.24385 | AE90: 178.94971 | AF90: 178.72766 | AG90: 178.49087 | AH90: 178.22836 | AI90: 178.15555 | AJ90: -0.005 | AK90: -0.003
A91: gasoline vehicle | B91: Gasoline | C91: Transportation Energy Use: Recreation Boats: Motor Gasoline: Reference case | D91: AEO.2023.REF2023.CNSM_NA_TRN_RCB_GSL_NA_NA_TRLBTU.A | E91: trillion Btu | G91: 163.60873 | H91: 160.38701 | I91: 157.42775 | J91: 155.51083 | K91: 154.515 | L91: 153.52698 | M91: 152.34193 | N91: 150.87234 | O91: 149.17961 | P91: 147.55435 | Q91: 146.34232 | R91: 145.41208 | S91: 144.50224 | T91: 143.63538 | U91: 142.95183 | V91: 142.42835 | W91: 141.89296 | X91: 141.35481 | Y91: 141.03188 | Z91: 140.67157 | AA91: 140.28008 | AB91: 139.88684 | AC91: 139.42889 | AD91: 138.92732 | AE91: 138.43982 | AF91: 138.00766 | AG91: 137.5636 | AH91: 137.09927 | AI91: 136.78018 | AJ91: -0.006 | AK91: -0.005
A92: diesel vehicle | B92: Distillate Fuel Oil (diesel) | C92: Transportation Energy Use: Recreation Boats: Distillate Fuel Oil: Reference case | D92: AEO.2023.REF2023.CNSM_NA_TRN_RCB_DFO_NA_NA_TRLBTU.A | E92: trillion Btu | G92: 39.227898 | H92: 38.775948 | I92: 38.377731 | J92: 38.226379 | K92: 38.298149 | L92: 38.370419 | M92: 38.391571 | N92: 38.33812 | O92: 38.223915 | P92: 38.122589 | Q92: 38.124577 | R92: 38.197956 | S92: 38.275326 | T92: 38.362804 | U92: 38.498459 | V92: 38.677174 | W92: 38.852928 | X92: 39.028164 | Y92: 39.263546 | Z92: 39.489632 | AA92: 39.707951 | AB92: 39.926662 | AC92: 40.127632 | AD92: 40.316528 | AE92: 40.509892 | AF92: 40.720009 | AG92: 40.927284 | AH92: 41.129097 | AI92: 41.375362 | AJ92: 0.002 | AK92: 0.003
B93: Lubricants | C93: Transportation Energy Use: Lubricants: Reference case | D93: AEO.2023.REF2023.CNSM_NA_TRN_NA_LBC_NA_NA_TRLBTU.A | E93: trillion Btu | G93: 125.94522 | H93: 125.92506 | I93: 126.01238 | J93: 126.04986 | K93: 126.11367 | L93: 125.98441 | M93: 125.853 | N93: 125.75523 | O93: 125.65207 | P93: 125.54579 | Q93: 125.43918 | R93: 125.33015 | S93: 125.25038 | T93: 125.22502 | U93: 125.25526 | V93: 125.31821 | W93: 125.4119 | X93: 125.52669 | Y93: 125.66653 | Z93: 125.79737 | AA93: 125.92503 | AB93: 126.04557 | AC93: 126.16628 | AD93: 126.32028 | AE93: 126.49239 | AF93: 126.66081 | AG93: 126.81145 | AH93: 126.97429 | AI93: 127.15868 | AJ93: 0 | AK93: 0.001
B94: Pipeline Fuel Natural Gas | C94: Transportation Energy Use: Pipeline Fuel Natural Gas: Reference case | D94: AEO.2023.REF2023.CNSM_NA_TRN_PIPL_NG_NA_NA_TRLBTU.A | E94: trillion Btu | G94: 905.73224 | H94: 820.5426 | I94: 760.98248 | J94: 726.75244 | K94: 695.8501 | L94: 653.98541 | M94: 613.92792 | N94: 612.03296 | O94: 610.31641 | P94: 611.89654 | Q94: 617.76355 | R94: 626.28516 | S94: 630.76672 | T94: 633.4773 | U94: 634.00311 | V94: 632.9682 | W94: 637.83142 | X94: 636.66797 | Y94: 645.80701 | Z94: 652.42676 | AA94: 658.16638 | AB94: 660.99408 | AC94: 665.09454 | AD94: 669.20264 | AE94: 674.53369 | AF94: 682.13464 | AG94: 689.49054 | AH94: 691.88214 | AI94: 696.77728 | AJ94: -0.009 | AK94: 0.004
B95: Natural Gas Liquefaction for Export | C95: Transportation Energy Use: Natural Gas for Liquefaction: Reference case | D95: AEO.2023.REF2023.CNSM_NA_NMFG_LQFCT_DELE_NA_NA_TRLBTU.A | E95: trillion Btu | G95: 332.5231 | H95: 377.97052 | I95: 384.00461 | J95: 408.78293 | K95: 446.26065 | L95: 477.17264 | M95: 503.61008 | N95: 527.57086 | O95: 577.96906 | P95: 628.36725 | Q95: 680.00372 | R95: 729.16363 | S95: 771.16211 | T95: 796.36121 | U95: 814.39893 | V95: 829.96002 | W95: 838.35974 | X95: 838.35974 | Y95: 839.59802 | Z95: 838.35974 | AA95: 838.35974 | AB95: 838.35974 | AC95: 839.59802 | AD95: 838.35974 | AE95: 838.35974 | AF95: 838.35974 | AG95: 839.59802 | AH95: 838.35974 | AI95: 838.35974 | AJ95: 0.034 | AK95: 0.005
B96: Total Consumption | C96: Transportation Energy Use: Total Use: Reference case | D96: AEO.2023.REF2023.CNSM_NA_TRN_NA_NA_NA_NA_TRLBTU.A | E96: trillion Btu | G96: 27986.479 | H96: 28032.221 | I96: 27776.766 | J96: 27465.828 | K96: 27255.17 | L96: 27052.176 | M96: 26819.684 | N96: 26592.781 | O96: 26361.336 | P96: 26163.676 | Q96: 26008.943 | R96: 25899.168 | S96: 25803.771 | T96: 25706.131 | U96: 25600.619 | V96: 25535.832 | W96: 25495.666 | X96: 25451.617 | Y96: 25462.877 | Z96: 25488.182 | AA96: 25533.678 | AB96: 25586.275 | AC96: 25660.166 | AD96: 25746.871 | AE96: 25871.172 | AF96: 26021.988 | AG96: 26178.047 | AH96: 26334.756 | AI96: 26541.848 | AJ96: -0.002

Sheet AEO 2023 37
B1: Table 37. Light-Duty Vehicle Energy Consumption by Technology Type and Fuel Type
B2: https://www.eia.gov/outlooks/aeo/data/browser/#/?id=47-AEO2023&cases=ref2023&sourcekey=0
B3: Thu Dec 11 2025 13:39:49 GMT-0800 (Pacific Standard Time)
B4: Source: U.S. Energy Information Administration
C5: full name | D5: api key | E5: units | F5: 2021 | G5: 2022 | H5: 2023 | I5: 2024 | J5: 2025 | K5: 2026 | L5: 2027 | M5: 2028 | N5: 2029 | O5: 2030 | P5: 2031 | Q5: 2032 | R5: 2033 | S5: 2034 | T5: 2035 | U5: 2036 | V5: 2037 | W5: 2038 | X5: 2039 | Y5: 2040 | Z5: 2041 | AA5: 2042 | AB5: 2043 | AC5: 2044 | AD5: 2045 | AE5: 2046 | AF5: 2047 | AG5: 2048 | AH5: 2049 | AI5: 2050 | AJ5: Growth (2022-2050)
B6: Light-Duty Consumption by Technology Type
B7: Conventional Vehicles
A8: gasoline vehicle | B8: Gasoline ICE Vehicles | C8: Transportation Energy Use: Light-Duty Vehicles: Conventional: Gasoline: Reference case | D8: AEO.2023.REF2023.CNSM_NA_TRN_LDV_CNV_GIC_NA_TRLBTU.A | E8: trillion Btu | G8: 12881.066 | H8: 12908.202 | I8: 12756.777 | J8: 12537.511 | K8: 12357.115 | L8: 12199.979 | M8: 12016.358 | N8: 11807.21 | O8: 11580.357 | P8: 11365.739 | Q8: 11149.033 | R8: 10969.979 | S8: 10808.191 | T8: 10642.521 | U8: 10471.983 | V8: 10320.19 | W8: 10182.744 | X8: 10049.588 | Y8: 9935.6455 | Z8: 9837.9648 | AA8: 9757.4873 | AB8: 9689.8076 | AC8: 9646 | AD8: 9624.1328 | AE8: 9624.3623 | AF8: 9643.373 | AG8: 9674.415 | AH8: 9714.2891 | AI8: 9771.2861 | AJ8: -0.01
A9: diesel vehicle | B9: TDI Diesel ICE | C9: Transportation Energy Use: Light-Duty Vehicles: Conventional: TDI Diesel: Reference case | D9: AEO.2023.REF2023.CNSM_NA_TRN_LDV_CNV_TDS_NA_TRLBTU.A | E9: trillion Btu | G9: 61.460407 | H9: 64.69902 | I9: 67.503647 | J9: 70.684082 | K9: 74.503548 | L9: 77.63253 | M9: 81.324989 | N9: 84.520767 | O9: 86.959724 | P9: 89.758049 | Q9: 91.490173 | R9: 93.247543 | S9: 95.159004 | T9: 96.641716 | U9: 98.053253 | V9: 99.8647 | W9: 101.3619 | X9: 102.78561 | Y9: 104.4752 | Z9: 105.74961 | AA9: 107.32461 | AB9: 109.77927 | AC9: 110.92002 | AD9: 111.97982 | AE9: 113.44127 | AF9: 115.03707 | AG9: 116.75105 | AH9: 118.59347 | AI9: 120.69575 | AJ9: 0.024
B10: Total Conventional | C10: Transportation Energy Use: Light-Duty Vehicles: Conventional: Total: Reference case | D10: AEO.2023.REF2023.CNSM_NA_TRN_LDV_CNV_NA_NA_TRLBTU.A | E10: trillion Btu | G10: 12942.526 | H10: 12972.901 | I10: 12824.281 | J10: 12608.195 | K10: 12431.619 | L10: 12277.612 | M10: 12097.684 | N10: 11891.73 | O10: 11667.317 | P10: 11455.497 | Q10: 11240.523 | R10: 11063.227 | S10: 10903.351 | T10: 10739.163 | U10: 10570.037 | V10: 10420.055 | W10: 10284.106 | X10: 10152.373 | Y10: 10040.121 | Z10: 9943.7148 | AA10: 9864.8115 | AB10: 9799.5869 | AC10: 9756.9199 | AD10: 9736.1123 | AE10: 9737.8037 | AF10: 9758.4102 | AG10: 9791.166 | AH10: 9832.8828 | AI10: 9891.9814 | AJ10: -0.01
B11: Alternative-Fuel Vehicles
A12: gasoline vehicle | B12: Ethanol-Flex Fuel ICE | C12: Transportation Energy Use: Light-Duty Vehicles: Alternative-Fuel: Ethanol Flex: Reference case | D12: AEO.2023.REF2023.CNSM_NA_TRN_LDV_ALF1_ETHF_NA_TRLBTU.A | E12: trillion Btu | G12: 1339.1326 | H12: 1319.3763 | I12: 1275.7671 | J12: 1221.3973 | K12: 1167.0458 | L12: 1113.8267 | M12: 1058.1517 | N12: 1000.6174 | O12: 942.97351 | P12: 886.95709 | Q12: 834.95325 | R12: 788.07349 | S12: 746.06122 | T12: 707.77228 | U12: 673.77527 | V12: 645.22839 | W12: 622.27368 | X12: 604.38629 | Y12: 590.49341 | Z12: 578.73364 | AA12: 569.68555 | AB12: 562.43762 | AC12: 557.20813 | AD12: 552.74524 | AE12: 549.35913 | AF12: 547.08942 | AG12: 545.57074 | AH12: 544.521 | AI12: 544.48712 | AJ12: -0.032
A13: battery electric vehicle | B13: 100-Mile Electric Vehicle | C13: Transportation Energy Use: Light-Duty Vehicles: Alternative-Fuel: 100-Mile Electric Vehicle: Reference case | D13: AEO.2023.REF2023.#N/A.A | E13: trillion Btu | G13: 2.559272 | H13: 2.801123 | I13: 2.938387 | J13: 3.198433 | K13: 3.46944 | L13: 3.824871 | M13: 4.214181 | N13: 4.64197 | O13: 5.080826 | P13: 5.409801 | Q13: 5.757645 | R13: 6.129659 | S13: 6.536924 | T13: 6.985487 | U13: 7.481553 | V13: 8.004829 | W13: 8.592344 | X13: 9.199112 | Y13: 9.855124 | Z13: 10.55482 | AA13: 11.261348 | AB13: 12.093517 | AC13: 13.104404 | AD13: 13.828259 | AE13: 14.575327 | AF13: 15.333433 | AG13: 16.094807 | AH13: 16.875494 | AI13: 17.68449 | AJ13: 0.071
A14: battery electric vehicle | B14: 200-Mile Electric Vehicle | C14: Transportation Energy Use: Light-Duty Vehicles: Alternative-Fuel: 200-Mile Electric Vehicle: Reference case | D14: AEO.2023.REF2023.#N/A.A | E14: trillion Btu | G14: 4.23001 | H14: 5.338574 | I14: 7.581603 | J14: 9.787632 | K14: 12.592564 | L14: 16.132769 | M14: 20.282379 | N14: 25.35833 | O14: 31.289043 | P14: 36.80603 | Q14: 42.54187 | R14: 48.338242 | S14: 54.20961 | T14: 59.939297 | U14: 65.392517 | V14: 70.586815 | W14: 75.455902 | X14: 79.913757 | Y14: 83.872467 | Z14: 87.392548 | AA14: 90.522141 | AB14: 92.990646 | AC14: 95.30146 | AD14: 96.839081 | AE14: 98.250748 | AF14: 99.208252 | AG14: 99.851822 | AH14: 100.11125 | AI14: 100.09346 | AJ14: 0.12
A15: battery electric vehicle | B15: 300-Mile Electric Vehicle | C15: Transportation Energy Use: Light-Duty Vehicles: Alternative-Fuel: 300-Mile Electric Vehicle: Reference case | D15: AEO.2023.REF2023.#N/A.A | E15: trillion Btu | G15: 15.9704 | H15: 24.20409 | I15: 33.748886 | J15: 45.167313 | K15: 58.883274 | L15: 75.400421 | M15: 94.456154 | N15: 116.52211 | O15: 141.06322 | P15: 163.17174 | Q15: 185.98447 | R15: 209.30423 | S15: 233.2849 | T15: 257.06119 | U15: 280.19522 | V15: 302.78024 | W15: 324.57373 | X15: 345.21057 | Y15: 364.40649 | Z15: 382.57037 | AA15: 399.60388 | AB15: 415.15625 | AC15: 429.39673 | AD15: 442.784 | AE15: 456.38461 | AF15: 469.40271 | AG15: 482.0321 | AH15: 494.172 | AI15: 506.31152 | AJ15: 0.131
A16: plugin hybrid vehicle | B16: Plug-in 20 Gasoline Hybrid | C16: Transportation Energy Use: Light-Duty Vehicles: Alternative-Fuel: Plug-in 20 Gasoline Hybrid: Reference case | D16: AEO.2023.REF2023.CNSM_NA_TRN_LDV_ALF1_PI20GH_NA_TRLBTU.A | E16: trillion Btu | G16: 18.560482 | H16: 22.740395 | I16: 27.495119 | J16: 32.623177 | K16: 38.521145 | L16: 44.721348 | M16: 50.693836 | N16: 56.983059 | O16: 62.858303 | P16: 68.78035 | Q16: 74.37513 | R16: 79.731766 | S16: 85.03717 | T16: 90.026291 | U16: 94.311279 | V16: 98.472031 | W16: 102.10908 | X16: 105.42519 | Y16: 108.994 | Z16: 111.98223 | AA16: 114.74972 | AB16: 117.44008 | AC16: 119.75434 | AD16: 121.83944 | AE16: 123.95615 | AF16: 125.98113 | AG16: 127.9929 | AH16: 129.93436 | AI16: 132.0304 | AJ16: 0.073
A17: plugin hybrid vehicle | B17: Plug-in 50 Gasoline Hybrid | C17: Transportation Energy Use: Light-Duty Vehicles: Alternative-Fuel: Plug-in 50 Gasoline Hybrid: Reference case | D17: AEO.2023.REF2023.CNSM_NA_TRN_LDV_ALF1_PI50GH_NA_TRLBTU.A | E17: trillion Btu | G17: 6.073068 | H17: 7.22458 | I17: 9.104139 | J17: 11.706738 | K17: 15.01347 | L17: 18.922571 | M17: 23.104176 | N17: 27.733246 | O17: 32.733551 | P17: 37.850918 | Q17: 43.0508 | R17: 48.288136 | S17: 53.537937 | T17: 58.725227 | U17: 63.640675 | V17: 68.471672 | W17: 73.244919 | X17: 77.821266 | Y17: 82.422424 | Z17: 87.153137 | AA17: 91.386086 | AB17: 95.450897 | AC17: 99.383911 | AD17: 102.97137 | AE17: 106.46774 | AF17: 109.89616 | AG17: 113.09894 | AH17: 116.14382 | AI17: 119.04137 | AJ17: 0.112
A18: diesel vehicle | B18: Electric-Diesel Hybrid | C18: Transportation Energy Use: Light-Duty Vehicles: Alternative-Fuel: Electric-Diesel Hybrid: Reference case | D18: AEO.2023.REF2023.CNSM_NA_TRN_LDV_ALF1_EDH_NA_TRLBTU.A | E18: trillion Btu | G18: 0 | H18: 0 | I18: 0 | J18: 0 | K18: 0 | L18: 0 | M18: 0 | N18: 0 | O18: 0 | P18: 0 | Q18: 0 | R18: 0 | S18: 0 | T18: 0 | U18: 0 | V18: 0 | W18: 0 | X18: 0 | Y18: 0 | Z18: 0 | AA18: 0 | AB18: 0 | AC18: 0 | AD18: 0 | AE18: 0 | AF18: 0 | AG18: 0 | AH18: 0 | AI18: 0 | AJ18: - -
A19: gasoline vehicle | B19: Electric-Gasoline Hybrid | C19: Transportation Energy Use: Light-Duty Vehicles: Alternative-Fuel: Electric-Gasoline Hybrid: Reference case | D19: AEO.2023.REF2023.CNSM_NA_TRN_LDV_ALF1_EGH_NA_TRLBTU.A | E19: trillion Btu | G19: 209.8335 | H19: 228.33878 | I19: 245.96523 | J19: 266.85602 | K19: 286.55102 | L19: 306.89453 | M19: 327.11194 | N19: 346.66968 | O19: 365.93665 | P19: 385.50098 | Q19: 405.40732 | R19: 426.28775 | S19: 447.70267 | T19: 469.7746 | U19: 491.21402 | V19: 511.44318 | W19: 531.99805 | X19: 553.30676 | Y19: 577.32837 | Z19: 596.52765 | AA19: 613.70355 | AB19: 631.23663 | AC19: 646.83551 | AD19: 660.9419 | AE19: 675.99029 | AF19: 690.79431 | AG19: 705.40674 | AH19: 719.49921 | AI19: 733.77801 | AJ19: 0.046
A20: natural gas vehicle | B20: Natural Gas ICE | C20: Transportation Energy Use: Light-Duty Vehicles: Alternative-Fuel: Natural Gas ICE: Reference case | D20: AEO.2023.REF2023.CNSM_NA_TRN_LDV_ALF1_NGI_NA_TRLBTU.A | E20: trillion Btu | G20: 0.581258 | H20: 0.55293 | I20: 0.522262 | J20: 0.503062 | K20: 0.49137 | L20: 0.472963 | M20: 0.458756 | N20: 0.443704 | O20: 0.416023 | P20: 0.410545 | Q20: 0.402262 | R20: 0.395324 | S20: 0.391301 | T20: 0.387988 | U20: 0.382749 | V20: 0.378652 | W20: 0.378823 | X20: 0.329403 | Y20: 0.285635 | Z20: 0.289419 | AA20: 0.292288 | AB20: 0.294398 | AC20: 0.296296 | AD20: 0.298051 | AE20: 0.301542 | AF20: 0.305546 | AG20: 0.310221 | AH20: 0.315011 | AI20: 0.320412 | AJ20: -0.021
A21: natural gas vehicle | B21: Natural Gas Bi-fuel | C21: Transportation Energy Use: Light-Duty Vehicles: Alternative-Fuel: Natural Gas Bi-fuel: Reference case | D21: AEO.2023.REF2023.CNSM_NA_TRN_LDV_ALF1_NBF_NA_TRLBTU.A | E21: trillion Btu | G21: 0.191884 | H21: 0.182127 | I21: 0.024032 | J21: 0.019267 | K21: 0.024889 | L21: 0.030671 | M21: 0.036106 | N21: 0.041263 | O21: 0.045994 | P21: 0.050478 | Q21: 0.054582 | R21: 0.058343 | S21: 0.061862 | T21: 0.065025 | U21: 0.067828 | V21: 0.070328 | W21: 0.07252 | X21: 0.074398 | Y21: 0.076047 | Z21: 0.077498 | AA21: 0.078827 | AB21: 0.079999 | AC21: 0.081156 | AD21: 0.082353 | AE21: 0.083991 | AF21: 0.085869 | AG21: 0.08795 | AH21: 0.090122 | AI21: 0.092545 | AJ21: -0.026
A22: LPG vehicle | B22: Propane ICE | C22: Transportation Energy Use: Light-Duty Vehicles: Alternative-Fuel: Propane ICE: Reference case | D22: AEO.2023.REF2023.CNSM_NA_TRN_LDV_ALF1_PROP_NA_TRLBTU.A | E22: trillion Btu | G22: 0.533454 | H22: 0.505462 | I22: 0.489564 | J22: 0.491104 | K22: 0.498606 | L22: 0.518397 | M22: 0.270967 | N22: 0.325005 | O22: 0.378384 | P22: 0.431472 | Q22: 0.483158 | R22: 0.533378 | S22: 0.583001 | T22: 0.63062 | U22: 0.676329 | V22: 0.720717 | W22: 0.763431 | X22: 0.804592 | Y22: 0.844414 | Z22: 0.883361 | AA22: 0.922178 | AB22: 0.96007 | AC22: 0.998824 | AD22: 1.039229 | AE22: 1.087219 | AF22: 1.140783 | AG22: 1.199417 | AH22: 1.261919 | AI22: 1.330774 | AJ22: 0.033
A23: LPG vehicle | B23: Propane Bi-fuel | C23: Transportation Energy Use: Light-Duty Vehicles: Alternative-Fuel: Propane Bi-fuel: Reference case | D23: AEO.2023.REF2023.CNSM_NA_TRN_LDV_ALF1_PBF_NA_TRLBTU.A | E23: trillion Btu | G23: 0.578767 | H23: 0.526545 | I23: 0.125743 | J23: 0.110143 | K23: 0.098673 | L23: 0.091381 | M23: 0.087222 | N23: 0.010904 | O23: 0.012193 | P23: 0.013408 | Q23: 0.014499 | R23: 0.015486 | S23: 0.016387 | T23: 0.017177 | U23: 0.01785 | V23: 0.01843 | W23: 0.018912 | X23: 0.019301 | Y23: 0.019611 | Z23: 0.019856 | AA23: 0.020058 | AB23: 0.02021 | AC23: 0.020346 | AD23: 0.020489 | AE23: 0.02078 | AF23: 0.021123 | AG23: 0.021518 | AH23: 0.021944 | AI23: 0.022431 | AJ23: -0.11
A24: hydrogen vehicle | B24: Fuel Cell Methanol | C24: Transportation Energy Use: Light-Duty Vehicles: Alternative-Fuel: Fuel Cell Methanol: Reference case | D24: AEO.2023.REF2023.CNSM_NA_TRN_LDV_ALF1_FCLMTH_NA_TRLBTU.A | E24: trillion Btu | G24: 0 | H24: 0 | I24: 0 | J24: 0 | K24: 0 | L24: 0 | M24: 0 | N24: 0 | O24: 0 | P24: 0 | Q24: 0 | R24: 0 | S24: 0 | T24: 0 | U24: 0 | V24: 0 | W24: 0 | X24: 0 | Y24: 0 | Z24: 0 | AA24: 0 | AB24: 0 | AC24: 0 | AD24: 0 | AE24: 0 | AF24: 0 | AG24: 0 | AH24: 0 | AI24: 0 | AJ24: - -
A25: hydrogen vehicle | B25: Fuel Cell Hydrogen | C25: Transportation Energy Use: Light-Duty Vehicles: Alternative-Fuel: Fuel Cell Hydrogen: Reference case | D25: AEO.2023.REF2023.CNSM_NA_TRN_LDV_ALF1_FCH_NA_TRLBTU.A | E25: trillion Btu | G25: 0.426139 | H25: 0.518183 | I25: 0.595767 | J25: 0.665118 | K25: 0.737872 | L25: 0.80678 | M25: 0.879697 | N25: 0.948358 | O25: 1.020553 | P25: 1.093446 | Q25: 1.165657 | R25: 1.237105 | S25: 1.309695 | T25: 1.380918 | U25: 1.447488 | V25: 1.512507 | W25: 1.570883 | X25: 1.623062 | Y25: 1.665691 | Z25: 1.699897 | AA25: 1.731693 | AB25: 1.753623 | AC25: 1.769871 | AD25: 1.779117 | AE25: 1.789497 | AF25: 1.80015 | AG25: 1.807713 | AH25: 1.813287 | AI25: 1.816777 | AJ25: 0.053
B26: Total Alternative | C26: Transportation Energy Use: Light-Duty Vehicles: Alternative-Fuel: Total: Reference case | D26: AEO.2023.REF2023.CNSM_NA_TRN_LDV_ALF1_NA_NA_TRLBTU.A | E26: trillion Btu | G26: 1598.6709 | H26: 1612.3092 | I26: 1604.3578 | J26: 1592.5254 | K26: 1583.9281 | L26: 1581.6434 | M26: 1579.7472 | N26: 1580.2948 | O26: 1583.8082 | P26: 1586.4763 | Q26: 1594.1907 | R26: 1608.3928 | S26: 1628.7327 | T26: 1652.766 | U26: 1678.6028 | V26: 1707.6877 | W26: 1741.0524 | X26: 1778.1136 | Y26: 1820.2637 | Z26: 1857.8845 | AA26: 1893.9574 | AB26: 1929.9141 | AC26: 1964.151 | AD26: 1995.1686 | AE26: 2028.267 | AF26: 2061.0588 | AG26: 2093.4746 | AH26: 2124.7595 | AI26: 2157.0095 | AJ26: 0.011
B27: Total | C27: Transportation Energy Use: Light-Duty Vehicles: Total: Reference case | D27: AEO.2023.REF2023.CNSM_NA_TRN_LDV_NA_NA_NA_TRLBTU.A | E27: trillion Btu | G27: 14541.197 | H27: 14585.211 | I27: 14428.639 | J27: 14200.721 | K27: 14015.547 | L27: 13859.256 | M27: 13677.431 | N27: 13472.025 | O27: 13251.126 | P27: 13041.974 | Q27: 12834.714 | R27: 12671.619 | S27: 12532.083 | T27: 12391.929 | U27: 12248.64 | V27: 12127.742 | W27: 12025.159 | X27: 11930.486 | Y27: 11860.385 | Z27: 11801.6 | AA27: 11758.769 | AB27: 11729.501 | AC27: 11721.071 | AD27: 11731.281 | AE27: 11766.07 | AF27: 11819.469 | AG27: 11884.641 | AH27: 11957.643 | AI27: 12048.991 | AJ27: -0.007
B28: Light-Duty Consumption by Fuel Type
B29: Motor Gasoline | C29: Transportation Energy Use: Light-Duty Vehicle: Motor Gasoline: Reference case | D29: AEO.2023.REF2023.CNSM_NA_TRN_LDV_MGS_NA_NA_TRLBTU.A | E29: trillion Btu | G29: 14415.272 | H29: 14443.936 | I29: 14272.424 | J29: 14024.321 | K29: 13815.495 | L29: 13632.25 | M29: 13419.692 | N29: 13179.96 | O29: 12922.15 | P29: 12678.574 | Q29: 12437.037 | R29: 12238.959 | S29: 12063.409 | T29: 11887.983 | U29: 11710.702 | V29: 11556.08 | W29: 11421.213 | X29: 11295.929 | Y29: 11196.766 | Z29: 11110.767 | AA29: 11042.225 | AB29: 10988.435 | AC29: 10958.348 | AD29: 10949.109 | AE29: 10963.974 | AF29: 10998.307 | AG29: 11045.134 | AH29: 11100.26 | AI29: 11174.06 | AJ29: -0.009
B30: Distillate Fuel Oil (diesel) | C30: Transportation Energy Use: Light-Duty Vehicle: Distillate Fuel Oil: Reference case | D30: AEO.2023.REF2023.CNSM_NA_TRN_LDV_DFO_NA_NA_TRLBTU.A | E30: trillion Btu | G30: 61.460403 | H30: 64.69902 | I30: 67.503647 | J30: 70.684074 | K30: 74.503555 | L30: 77.63253 | M30: 81.324982 | N30: 84.520767 | O30: 86.959732 | P30: 89.758049 | Q30: 91.490158 | R30: 93.247543 | S30: 95.158997 | T30: 96.641708 | U30: 98.053238 | V30: 99.8647 | W30: 101.3619 | X30: 102.78562 | Y30: 104.47522 | Z30: 105.74961 | AA30: 107.32461 | AB30: 109.77927 | AC30: 110.92001 | AD30: 111.97984 | AE30: 113.44128 | AF30: 115.03706 | AG30: 116.75106 | AH30: 118.59347 | AI30: 120.69574 | AJ30: 0.024
B31: E85 | C31: Transportation Energy Use: Light-Duty Vehicle: Ethanol: Reference case | D31: AEO.2023.REF2023.CNSM_NA_TRN_LDV_ETH_NA_NA_TRLBTU.A | E31: trillion Btu | G31: 31.110834 | H31: 31.64006 | I31: 29.552767 | J31: 29.441513 | K31: 28.728485 | L31: 27.952177 | M31: 27.018059 | N31: 25.972713 | O31: 24.873795 | P31: 23.80064 | Q31: 22.75461 | R31: 21.823027 | S31: 20.987984 | T31: 20.244169 | U31: 19.537762 | V31: 19.024712 | W31: 18.648621 | X31: 18.39851 | Y31: 18.275644 | Z31: 18.222813 | AA31: 18.236134 | AB31: 18.340065 | AC31: 18.452595 | AD31: 18.609615 | AE31: 18.756809 | AF31: 19.004078 | AG31: 19.229309 | AH31: 19.515997 | AI31: 19.788425 | AJ31: -0.016
B32: Natural Gas | C32: Transportation Energy Use: Light-Duty Vehicle: Natural Gas: Reference case | D32: AEO.2023.REF2023.CNSM_NA_TRN_LDV_NG_NA_NA_TRLBTU.A | E32: trillion Btu | G32: 0.712888 | H32: 0.677668 | I32: 0.537752 | J32: 0.515005 | K32: 0.507019 | L32: 0.492443 | M32: 0.481839 | N32: 0.470472 | O32: 0.445942 | P32: 0.443445 | Q32: 0.437883 | R32: 0.433434 | S32: 0.431733 | T32: 0.430499 | U32: 0.427096 | V32: 0.424631 | W32: 0.426227 | X32: 0.378024 | Y32: 0.335326 | Z32: 0.340053 | AA32: 0.343781 | AB32: 0.346656 | AC32: 0.349313 | AD32: 0.351864 | AE32: 0.356448 | AF32: 0.36171 | AG32: 0.367786 | AH32: 0.374043 | AI32: 0.381082 | AJ32: -0.022
B33: Propane | C33: Transportation Energy Use: Light-Duty Vehicle: Propane: Reference case | D33: AEO.2023.REF2023.CNSM_NA_TRN_LDV_PROP_NA_NA_TRLBTU.A | E33: trillion Btu | G33: 0.797388 | H33: 0.735487 | I33: 0.547456 | J33: 0.540668 | K33: 0.544193 | L33: 0.561282 | M33: 0.312092 | N33: 0.33014 | O33: 0.384077 | P33: 0.437626 | Q33: 0.489719 | R33: 0.540254 | S33: 0.590177 | T33: 0.638076 | U33: 0.684164 | V33: 0.72876 | W33: 0.771586 | X33: 0.812987 | Y33: 0.85285 | Z33: 0.891809 | AA33: 0.930713 | AB33: 0.968622 | AC33: 1.007558 | AD33: 1.048031 | AE33: 1.096531 | AF33: 1.150243 | AG33: 1.209162 | AH33: 1.271896 | AI33: 1.341161 | AJ33: 0.019
B34: Electricity | C34: Transportation Energy Use: Light-Duty Vehicle: Electricity: Reference case | D34: AEO.2023.REF2023.CNSM_NA_TRN_LDV_ELC_NA_NA_TRLBTU.A | E34: trillion Btu | G34: 32.193668 | H34: 43.907116 | I34: 58.529484 | J34: 75.757942 | K34: 96.391159 | L34: 121.06613 | M34: 149.37682 | N34: 181.62849 | O34: 217.24832 | P34: 249.97737 | Q34: 283.60272 | R34: 317.79742 | S34: 352.76804 | T34: 387.34479 | U34: 420.6944 | V34: 453.18622 | W34: 484.42331 | X34: 513.9956 | Y34: 541.63086 | Z34: 567.72461 | AA34: 591.9502 | AB34: 614.02081 | AC34: 634.53888 | AD34: 652.89734 | AE34: 671.34821 | AF34: 688.6897 | AG34: 705.21576 | AH34: 721.08112 | AI34: 736.37286 | AJ34: 0.118
B35: Hydrogen | C35: Transportation Energy Use: Light-Duty Vehicle: Hydrogen: Reference case | D35: AEO.2023.REF2023.CNSM_NA_TRN_LDV_HDG_NA_NA_TRLBTU.A | E35: trillion Btu | G35: 0.426139 | H35: 0.518183 | I35: 0.595767 | J35: 0.665118 | K35: 0.737872 | L35: 0.80678 | M35: 0.879698 | N35: 0.948358 | O35: 1.020552 | P35: 1.093446 | Q35: 1.165657 | R35: 1.237105 | S35: 1.309695 | T35: 1.380918 | U35: 1.447488 | V35: 1.512508 | W35: 1.570883 | X35: 1.623062 | Y35: 1.665691 | Z35: 1.699897 | AA35: 1.731693 | AB35: 1.753623 | AC35: 1.769871 | AD35: 1.779117 | AE35: 1.789497 | AF35: 1.800149 | AG35: 1.807713 | AH35: 1.813287 | AI35: 1.816777 | AJ35: 0.053

Sheet AEO 2023 41
C1: ref2023.d020623a | D1: 2022 | E1: 2023 | F1: 2024 | G1: 2025 | H1: 2026 | I1: 2027 | J1: 2028 | K1: 2029 | L1: 2030 | M1: 2031 | N1: 2032 | O1: 2033 | P1: 2034 | Q1: 2035 | R1: 2036 | S1: 2037 | T1: 2038 | U1: 2039 | V1: 2040 | W1: 2041 | X1: 2042 | Y1: 2043 | Z1: 2044 | AA1: 2045 | AB1: 2046 | AC1: 2047 | AD1: 2048 | AE1: 2049 | AF1: 2050 | AH1: 2050
D3: Report | E3: Annual Energy Outlook 2023
D4: Scenario | E4: ref2023 | H4: Reference
D5: Datekey | E5: d020623a
D6: Release Date | F6: March 2023
A10: VMT000 | C10: 41. Light-Duty Vehicle Miles Traveled by Technology Type | AG10: Annual | AI10: Compound
C11: (billion miles, unless otherwise noted) | AG11: Change | AI11: Growth
AG12: 2022–2050 | AI12: 2020-2050
C13: Technology Type | D13: 2022 | E13: 2023 | F13: 2024 | G13: 2025 | H13: 2026 | I13: 2027 | J13: 2028 | K13: 2029 | L13: 2030 | M13: 2031 | N13: 2032 | O13: 2033 | P13: 2034 | Q13: 2035 | R13: 2036 | S13: 2037 | T13: 2038 | U13: 2039 | V13: 2040 | W13: 2041 | X13: 2042 | Y13: 2043 | Z13: 2044 | AA13: 2045 | AB13: 2046 | AC13: 2047 | AD13: 2048 | AE13: 2049 | AF13: 2050 | AG13: 2050 | AH13: 2050 | AI13: (percent)
C14: Conventional Vehicles 1/
A15: VMT000:aa_GasolineICEVe | B15: gasoline vehicle | C15: Gasoline ICE Vehicles | D15: 2496.2039 | E15: 2540.0024 | F15: 2549.3982 | G15: 2547.3508 | H15: 2552.2783 | I15: 2560.6907 | J15: 2564.7273 | K15: 2560.8389 | L15: 2550.1602 | M15: 2538.8882 | N15: 2524.3862 | O15: 2513.1665 | P15: 2504.7222 | Q15: 2494.2324 | R15: 2480.8706 | S15: 2469.8887 | T15: 2461.1475 | U15: 2452.8848 | V15: 2447.2812 | W15: 2444.3616 | X15: 2443.9963 | Y15: 2444.438 | Z15: 2447.4312 | AA15: 2453.5154 | AB15: 2463.1755 | AC15: 2475.7632 | AD15: 2489.9929 | AE15: 2505.4944 | AF15: 2524.0015 | AG15: 0.000396 | AH15: 2718.4993 | AI15: 0.005274
A16: VMT000:aa_TDIDieselICE | B16: diesel vehicle | C16: TDI Diesel ICE | D16: 14.31778 | E16: 15.188455 | F16: 15.940958 | G16: 16.851959 | H16: 17.929171 | I16: 18.841543 | J16: 19.926758 | K16: 20.916462 | L16: 21.721556 | M16: 22.431366 | N16: 23.062347 | O16: 23.693542 | P16: 24.359486 | Q16: 24.930275 | R16: 25.474934 | S16: 26.098764 | T16: 26.663237 | U16: 27.217226 | V16: 27.70447 | W16: 28.202288 | X16: 28.754858 | Y16: 29.295786 | Z16: 29.747328 | AA16: 30.164621 | AB16: 30.686481 | AC16: 31.215885 | AD16: 31.766838 | AE16: 32.350456 | AF16: 32.997715 | AG16: 0.030268 | AH16: 27.447765 | AI16: 0.028967
C18: Alternative-Fuel Vehicles 1/
A19: VMT000:ba_Ethanol-FlexF | B19: gasoline vehicle | C19: Ethanol-Flex Fuel ICE | D19: 240.3689 | E19: 238.55046 | F19: 232.37468 | G19: 224.28368 | H19: 216.2281 | I19: 208.32843 | J19: 199.95787 | K19: 191.11638 | L19: 182.13873 | M19: 173.4005 | N19: 165.27101 | O19: 158.03084 | P19: 151.60454 | Q19: 145.8215 | R19: 140.74507 | S19: 136.60683 | T19: 133.40529 | U19: 131.08212 | V19: 129.44026 | W19: 128.15411 | X19: 127.33864 | Y19: 126.74524 | Z19: 126.45383 | AA19: 126.34758 | AB19: 126.40852 | AC19: 126.64651 | AD19: 126.98559 | AE19: 127.42006 | AF19: 128.02672 | AG19: -0.022247 | AH19: 180.10965 | AI19: -0.006788
A20: VMT000:ba_100mileEV | B20: battery electric vehicle | C20: 100-Mile Electric Vehicle | D20: 1.293168 | E20: 1.329799 | F20: 1.261706 | G20: 1.225423 | H20: 1.166643 | I20: 1.133927 | J20: 1.106725 | K20: 1.08164 | L20: 1.050006 | M20: 0.947058 | N20: 0.844521 | O20: 0.748753 | P20: 0.660953 | Q20: 0.580422 | R20: 0.511285 | S20: 0.448466 | T20: 0.403803 | U20: 0.365459 | V20: 0.339309 | W20: 0.321891 | X20: 0.311214 | Y20: 0.306009 | Z20: 0.304403 | AA20: 0.30368 | AB20: 0.304971 | AC20: 0.306484 | AD20: 0.308283 | AE20: 0.310488 | AF20: 0.313438 | AG20: -0.049356 | AH20: 0.892446 | AI20: -0.032226
A21: VMT000:da_ElectricVehic | B21: battery electric vehicle | C21: 200-Mile Electric Vehicle | D21: 2.803167 | E21: 3.596449 | F21: 5.180786 | G21: 6.78617 | H21: 8.822824 | I21: 11.374497 | J21: 14.374306 | K21: 18.027864 | L21: 22.297363 | M21: 26.342045 | N21: 30.566568 | O21: 34.859005 | P21: 39.232258 | Q21: 43.545601 | R21: 47.706928 | S21: 51.714142 | T21: 55.526184 | U21: 59.077873 | V21: 62.303284 | W21: 65.235252 | X21: 67.875572 | Y21: 70.092789 | Z21: 72.005653 | AA21: 73.606461 | AB21: 75.12603 | AC21: 76.323387 | AD21: 77.293854 | AE21: 77.998962 | AF21: 78.512604 | AG21: 0.12639 | AH21: 57.014374 | AI21: 0.107132
A22: VMT000:ba_FuelCellGas | B22: battery electric vehicle | C22: 300-Mile Electric Vehicle | D22: 11.963635 | E22: 18.062939 | F22: 25.114439 | G22: 33.539726 | H22: 43.633289 | I22: 55.704681 | J22: 69.562294 | K22: 85.483986 | L22: 103.08805 | M22: 118.89004 | N22: 135.13141 | O22: 151.68396 | P22: 168.66231 | Q22: 185.45224 | R22: 201.75081 | S22: 217.62799 | T22: 232.92596 | U22: 247.38501 | V22: 260.81403 | W22: 273.48639 | X22: 285.35251 | Y22: 296.13873 | Z22: 306.02155 | AA22: 315.24387 | AB22: 324.74051 | AC22: 333.8277 | AD22: 342.65927 | AE22: 351.16562 | AF22: 359.69476 | AG22: 0.129245 | AH22: 171.20548 | AI22: 0.120617
A23: VMT000:da_PlugIn10 | B23: plugin hybrid vehicle | C23: Plug-in 20 Gasoline Hybrid | D23: 5.997003 | E23: 7.318346 | F23: 8.835059 | G23: 10.528111 | H23: 12.49413 | I23: 14.599579 | J23: 16.69804 | K23: 18.92646 | L23: 21.055801 | M23: 23.226791 | N23: 25.29916 | O23: 27.298203 | P23: 29.278225 | Q23: 31.138155 | R23: 32.752979 | S23: 34.304794 | T23: 35.688198 | U23: 36.946682 | V23: 38.25774 | W23: 39.401421 | X23: 40.467293 | Y23: 41.489872 | Z23: 42.389427 | AA23: 43.212708 | AB23: 44.039898 | AC23: 44.838875 | AD23: 45.620209 | AE23: 46.373375 | AF23: 47.175957 | AG23: 0.076446 | AH23: 23.364334 | AI23: 0.055695
A24: VMT000:ba_PlugIn40 | B24: plugin hybrid vehicle | C24: Plug-in 50 Gasoline Hybrid | D24: 2.950048 | E24: 3.4684 | F24: 4.308969 | G24: 5.503342 | H24: 7.034838 | I24: 8.853513 | J24: 10.827475 | K24: 13.016227 | L24: 15.405021 | M24: 17.866121 | N24: 20.373514 | O24: 22.905313 | P24: 25.445019 | Q24: 27.955698 | R24: 30.34293 | S24: 32.690796 | T24: 35.018063 | U24: 37.256523 | V24: 39.501953 | W24: 41.814838 | X24: 43.902096 | Y24: 45.872871 | Z24: 47.79282 | AA24: 49.569958 | AB24: 51.297363 | AC24: 52.964493 | AD24: 54.547184 | AE24: 56.045303 | AF24: 57.467575 | AG24: 0.111877 | AH24: 36.401176 | AI24: 0.091355
A25: VMT000:ca_ElectricDiesl | B25: diesel vehicle | C25: Electric-Diesel Hybrid | D25: 0 | E25: 0 | F25: 0 | G25: 0 | H25: 0 | I25: 0 | J25: 0 | K25: 0 | L25: 0 | M25: 0 | N25: 0 | O25: 0 | P25: 0 | Q25: 0 | R25: 0 | S25: 0 | T25: 0 | U25: 0 | V25: 0 | W25: 0 | X25: 0 | Y25: 0 | Z25: 0 | AA25: 0 | AB25: 0 | AC25: 0 | AD25: 0 | AE25: 0 | AF25: 0 | AG25: -- | AH25: 0 | AI25: --
A26: VMT000:ca_ElectricGaso | B26: gasoline vehicle | C26: Electric-Gasoline Hybrid | D26: 66.959084 | E26: 73.383095 | F26: 79.613281 | G26: 86.791557 | H26: 94.12468 | I26: 101.85257 | J26: 109.79015 | K26: 117.54632 | L26: 125.27403 | M26: 133.0958 | N26: 140.99568 | O26: 149.21825 | P26: 157.66312 | Q26: 166.2565 | R26: 174.60805 | S26: 182.64728 | T26: 190.73744 | U26: 198.93771 | V26: 207.9501 | W26: 215.61105 | X26: 222.57498 | Y26: 229.49191 | Z26: 235.85236 | AA26: 241.68681 | AB26: 247.6772 | AC26: 253.56854 | AD26: 259.29343 | AE26: 264.75613 | AF26: 270.22638 | AG26: 0.05109 | AH26: 229.25201 | AI26: 0.050493
A27: VMT000:ba_CompressedICE | B27: natural gas vehicle | C27: Natural Gas ICE | D27: 0.114899 | E27: 0.110576 | F27: 0.107853 | G27: 0.105383 | H27: 0.103343 | I27: 0.10154 | J27: 0.099687 | K27: 0.098166 | L27: 0.097297 | M27: 0.096393 | N27: 0.095671 | O27: 0.095227 | P27: 0.095168 | Q27: 0.095221 | R27: 0.095377 | S27: 0.095995 | T27: 0.096486 | U27: 0.096884 | V27: 0.097119 | W27: 0.097166 | X27: 0.097028 | Y27: 0.09674 | Z27: 0.096432 | AA27: 0.096127 | AB27: 0.095888 | AC27: 0.095823 | AD27: 0.095925 | AE27: 0.096124 | AF27: 0.096541 | AG27: -0.006198 | AH27: 0.212146 | AI27: -0.014596
A28: VMT000:ca_CompressedBi- | B28: natural gas vehicle | C28: Natural Gas Bi-fuel | D28: 0.024334 | E28: 0.023461 | F28: 0.023621 | G28: 0.023889 | H28: 0.024288 | I28: 0.024797 | J28: 0.025291 | K28: 0.025767 | L28: 0.026189 | M28: 0.026596 | N28: 0.026947 | O28: 0.027253 | P28: 0.027534 | Q28: 0.027757 | R28: 0.027917 | S28: 0.028034 | T28: 0.028101 | U28: 0.028116 | V28: 0.028097 | W28: 0.028052 | X28: 0.027996 | Y28: 0.02792 | Z28: 0.027856 | AA28: 0.027819 | AB28: 0.027786 | AC28: 0.027831 | AD28: 0.02794 | AE28: 0.0281 | AF28: 0.028343 | AG28: 0.005462 | AH28: 0.70318 | AI28: -0.004362
A29: VMT000:ca_LiquefiedPetr | B29: LPG vehicle | C29: Propane ICE | D29: 0.074514 | E29: 0.072763 | F29: 0.073984 | G29: 0.077732 | H29: 0.08447 | I29: 0.093717 | J29: 0.103895 | K29: 0.114743 | L29: 0.125697 | M29: 0.136789 | N29: 0.147746 | O29: 0.158563 | P29: 0.169416 | Q29: 0.179952 | R29: 0.190176 | S29: 0.200238 | T29: 0.21004 | U29: 0.219606 | V29: 0.228955 | W29: 0.238188 | X29: 0.247466 | Y29: 0.25657 | Z29: 0.265906 | AA29: 0.275669 | AB29: 0.286315 | AC29: 0.297736 | AD29: 0.310135 | AE29: 0.323438 | AF29: 0.338239 | AG29: 0.055513 | AH29: 0.359848 | AI29: 0.02045
A30: VMT000:da_LiquefiedPetr | B30: LPG vehicle | C30: Propane Bi-fuel | D30: 0.079431 | E30: 0.071473 | F30: 0.065703 | G30: 0.060731 | H30: 0.056873 | I30: 0.053929 | J30: 0.051277 | K30: 0.048889 | L30: 0.046631 | M30: 0.044505 | N30: 0.042486 | O30: 0.040574 | P30: 0.038765 | Q30: 0.037042 | R30: 0.035399 | S30: 0.033835 | T30: 0.032344 | U30: 0.03092 | V30: 0.029562 | W30: 0.02827 | X30: 0.027043 | Y30: 0.025875 | Z30: 0.024772 | AA30: 0.023735 | AB30: 0.022766 | AC30: 0.02187 | AD30: 0.021041 | AE30: 0.020275 | AF30: 0.019576 | AG30: -0.04879 | AH30: 0.310858 | AI30: -0.029047
A31: VMT000:da_FuelCellMeth | B31: hydrogen vehicle | C31: Fuel Cell Methanol | D31: 0 | E31: 0 | F31: 0 | G31: 0 | H31: 0 | I31: 0 | J31: 0 | K31: 0 | L31: 0 | M31: 0 | N31: 0 | O31: 0 | P31: 0 | Q31: 0 | R31: 0 | S31: 0 | T31: 0 | U31: 0 | V31: 0 | W31: 0 | X31: 0 | Y31: 0 | Z31: 0 | AA31: 0 | AB31: 0 | AC31: 0 | AD31: 0 | AE31: 0 | AF31: 0 | AG31: -- | AH31: 0 | AI31: --
A32: VMT000:da_FuelCellHydro | B32: hydrogen vehicle | C32: Fuel Cell Hydrogen | D32: 0.148194 | E32: 0.18033 | F32: 0.207392 | G32: 0.23166 | H32: 0.257087 | I32: 0.281222 | J32: 0.306958 | K32: 0.331216 | L32: 0.356784 | M32: 0.382604 | N32: 0.408205 | O32: 0.433574 | P32: 0.459385 | Q32: 0.484714 | R32: 0.508506 | S32: 0.531828 | T32: 0.552842 | U32: 0.571697 | V32: 0.587199 | W32: 0.599733 | X32: 0.611379 | Y32: 0.619509 | Z32: 0.625582 | AA32: 0.629156 | AB32: 0.633107 | AC32: 0.637117 | AD32: 0.640003 | AE32: 0.642185 | AF32: 0.643591 | AG32: 0.053848 | AH32: 0.298756 | AI32: 0.039478
C34: VMT Equation Components
A35: VMT000:ea_TotalVMT(bill | C35: Total VMT (billion miles) | D35: 2843.2981 | E35: 2901.3589 | F35: 2922.5066 | G35: 2933.3601 | H35: 2954.238 | I35: 2981.9343 | J35: 3007.5581 | K35: 3027.573 | L35: 3042.8433 | M35: 3055.7747 | N35: 3066.6516 | O35: 3082.3594 | P35: 3102.4182 | Q35: 3120.7375 | R35: 3135.6208 | S35: 3152.9177 | T35: 3172.4355 | U35: 3192.1006 | V35: 3214.563 | W35: 3237.5806 | X35: 3261.5847 | Y35: 3284.8975 | Z35: 3309.0391 | AA35: 3334.7034 | AB35: 3364.5225 | AC35: 3396.5352 | AD35: 3429.5627 | AE35: 3463.0249 | AF35: 3499.543 | AG35: 0.007444 | AH35: 3446.0715 | AI35: 0.009092
A36: VMT000:ea_VMT/DrivingPo | C36: VMT/Licensed Driver (thousand miles) | D36: 12.292728 | E36: 12.526435 | F36: 12.577197 | G36: 12.567465 | H36: 12.577917 | I36: 12.610725 | J36: 12.638391 | K36: 12.65343 | L36: 12.655709 | M36: 12.651836 | N36: 12.637545 | O36: 12.641304 | P36: 12.658344 | Q36: 12.676088 | R36: 12.692268 | S36: 12.71774 | T36: 12.749751 | U36: 12.786051 | V36: 12.831347 | W36: 12.882289 | X36: 12.938205 | Y36: 12.994745 | Z36: 13.055583 | AA36: 13.120469 | AB36: 13.200115 | AC36: 13.287262 | AD36: 13.378972 | AE36: 13.473079 | AF36: 13.577239 | AG36: 0.003556 | AH36: 12.87923 | AI36: 0.003057
A37: VMT000:ea_DrivingPopula | C37: Licensed Drivers (million) | D37: 231.29918 | E37: 231.61888 | F37: 232.36549 | G37: 233.40906 | H37: 234.87499 | I37: 236.46017 | J37: 237.97003 | K37: 239.26895 | L37: 240.43247 | M37: 241.52815 | N37: 242.66199 | O37: 243.83238 | P37: 245.08878 | Q37: 246.19089 | R37: 247.04968 | S37: 247.91493 | T37: 248.82333 | U37: 249.65492 | V37: 250.52422 | W37: 251.3203 | X37: 252.08943 | Y37: 252.78659 | Z37: 253.45778 | AA37: 254.16037 | AB37: 254.88583 | AC37: 255.62341 | AD37: 256.33978 | AE37: 257.03293 | AF37: 257.7507 | AG37: 0.003875 | AH37: 267.56815 | AI37: 0.006016
C39: Price Effects
A40: VMT000:fa_MotorGasoline | C40: Motor Gasoline Price (1987 $/million Btu) | D40: 13.600198 | E40: 12.754691 | F40: 12.439536 | G40: 11.600028 | H40: 11.469229 | I40: 11.407544 | J40: 11.409302 | K40: 11.435968 | L40: 11.46751 | M40: 11.460815 | N40: 11.517622 | O40: 11.553983 | P40: 11.599117 | Q40: 11.612701 | R40: 11.746193 | S40: 11.75865 | T40: 11.787958 | U40: 11.844007 | V40: 11.863857 | W40: 11.858942 | X40: 11.88617 | Y40: 11.836548 | Z40: 11.913117 | AA40: 11.933886 | AB40: 12.259571 | AC40: 12.259737 | AD40: 12.373319 | AE40: 12.389043 | AF40: 12.508653 | AG40: -0.002984 | AH40: 13.601268 | AI40: 0.017378
A41: VMT000:fa_FleetMilesper | C41: Household Stock Miles per Gallon | D41: 25.400711 | E41: 25.906796 | F41: 26.449829 | G41: 27.048653 | H41: 27.674738 | I41: 28.324505 | J41: 29.045471 | K41: 29.774456 | L41: 30.506573 | M41: 31.204981 | N41: 31.883957 | O41: 32.440662 | P41: 33.040554 | Q41: 33.627987 | R41: 34.193863 | S41: 34.758469 | T41: 35.326801 | U41: 35.911545 | V41: 36.466499 | W41: 37.008877 | X41: 37.505836 | Y41: 37.956326 | Z41: 38.285721 | AA41: 38.543011 | AB41: 38.790493 | AC41: 39.008453 | AD41: 39.202869 | AE41: 39.366676 | AF41: 39.502735 | AG41: 0.015896 | AH41: 32.361847 | AI41: 0.010179
A42: VMT000:fa_RealCostofDri | C42: Real Cost of Driving per Mile (1987 cents) | D42: 9.161829 | E42: 8.445475 | F42: 8.089037 | G42: 7.395504 | H42: 7.164747 | I42: 6.98038 | J42: 6.830608 | K42: 6.698566 | L42: 6.573293 | M42: 6.437982 | N42: 6.344121 | O42: 6.25063 | P42: 6.166095 | Q42: 6.06848 | R42: 6.038244 | S42: 5.952086 | T42: 5.880244 | U42: 5.825352 | V42: 5.760146 | W42: 5.688338 | X42: 5.638334 | Y42: 5.560752 | Z42: 5.55147 | AA42: 5.521921 | AB42: 5.638013 | AC42: 5.609405 | AD42: 5.637034 | AE42: 5.622787 | AF42: 5.659869 | AG42: -0.017054 | AH42: 6.892969 | AI42: 0.007178
A43: VMT000:fa_PointPriceEla | C43: Licensing Rate | D43: 0.849699 | E43: 0.844758 | F43: 0.840867 | G43: 0.838446 | H43: 0.837871 | I43: 0.837995 | J43: 0.838004 | K43: 0.837326 | L43: 0.83619 | M43: 0.834895 | N43: 0.833978 | O43: 0.833574 | P43: 0.833814 | Q43: 0.83386 | R43: 0.833424 | S43: 0.833365 | T43: 0.833234 | U43: 0.832891 | V43: 0.832753 | W43: 0.832451 | X43: 0.832077 | Y43: 0.831462 | Z43: 0.830767 | AA43: 0.83019 | AB43: 0.829682 | AC43: 0.829228 | AD43: 0.828727 | AE43: 0.82816 | AF43: 0.827683 | AG43: -0.000937 | AH43: 0.830692 | AI43: 7.3e-05
C45: 1/ Includes personal and fleet vehicles. Includes both cars and light trucks.
C46: VMT = Vehicle miles traveled.
C47: ICE = Internal combustion engine.
C48: Btu = British thermal units.
C49: TDI = Turbocharged direct injection
C50: - - = Not applicable.
C51: Data source: U.S. Energy Information Administration, AEO2023 National Energy Modeling System run ref2023.d020623a.
AG84: Average

Sheet AEO 2023 43
F1: 2021 | G1: 2022 | H1: 2023 | I1: 2024 | J1: 2025 | K1: 2026 | L1: 2027 | M1: 2028 | N1: 2029 | O1: 2030 | P1: 2031 | Q1: 2032 | R1: 2033 | S1: 2034 | T1: 2035 | U1: 2036 | V1: 2037 | W1: 2038 | X1: 2039 | Y1: 2040 | Z1: 2041 | AA1: 2042 | AB1: 2043 | AC1: 2044 | AD1: 2045 | AE1: 2046 | AF1: 2047 | AG1: 2048 | AH1: 2049 | AI1: 2050 | AJ1: Growth (2022-2050) | AL1: Growth (2019-2050)
B10: Table 43. Transportation Fleet Car and Truck Fuel Consumption by Type and Technology
B11: https://www.eia.gov/outlooks/aeo/data/browser/#/?id=53-AEO2023&cases=ref2023&sourcekey=0
B12: Thu Dec 11 2025 14:13:46 GMT-0800 (Pacific Standard Time)
B13: Source: U.S. Energy Information Administration
C14: full name | D14: api key | E14: units | F14: 2021 | G14: 2022 | H14: 2023 | I14: 2024 | J14: 2025 | K14: 2026 | L14: 2027 | M14: 2028 | N14: 2029 | O14: 2030 | P14: 2031 | Q14: 2032 | R14: 2033 | S14: 2034 | T14: 2035 | U14: 2036 | V14: 2037 | W14: 2038 | X14: 2039 | Y14: 2040 | Z14: 2041 | AA14: 2042 | AB14: 2043 | AC14: 2044 | AD14: 2045 | AE14: 2046 | AF14: 2047 | AG14: 2048 | AH14: 2049 | AI14: 2050 | AJ14: Growth (2022-2050) | AL14: Growth (2020-2050)
B15: Cars
B16: Conventional Cars
B17: Gasoline ICE Vehicles | C17: Fleet Vehicle Energy Use: Conventional Cars: Gasoline: Reference case | D17: AEO.2023.REF2023.CNSM_LDV_CNV_FLC_GSL_NA_NA_TRLBTU.A | E17: trillion Btu | G17: 216.06125 | H17: 202.9135 | I17: 191.10733 | J17: 179.43311 | K17: 168.36864 | L17: 158.00653 | M17: 149.33066 | N17: 140.68388 | O17: 134.1611 | P17: 127.85799 | Q17: 122.4565 | R17: 117.64224 | S17: 114.5518 | T17: 110.55763 | U17: 107.00807 | V17: 104.09293 | W17: 102.85469 | X17: 100.53545 | Y17: 98.836113 | Z17: 97.028748 | AA17: 94.866089 | AB17: 93.695923 | AC17: 91.912941 | AD17: 89.544693 | AE17: 87.944168 | AF17: 87.058197 | AG17: 86.250748 | AH17: 84.798187 | AI17: 84.145813 | AJ17: -0.033 | AL17: -0.009
B18: TDI Diesel ICE | C18: Fleet Vehicle Energy Use: Conventional Cars: TDI Diesel: Reference case | D18: AEO.2023.REF2023.CNSM_LDV_CNV_FLC_TDS_NA_NA_TRLBTU.A | E18: trillion Btu | G18: 0.413871 | H18: 0.361576 | I18: 0.309829 | J18: 0.265181 | K18: 0.22418 | L18: 0.188825 | M18: 0.159462 | N18: 0.131808 | O18: 0.113044 | P18: 0.089904 | Q18: 0.073531 | R18: 0.061947 | S18: 0.052716 | T18: 0.042709 | U18: 0.035432 | V18: 0.029818 | W18: 0.02649 | X18: 0.022981 | Y18: 0.020287 | Z18: 0.017553 | AA18: 0.01556 | AB18: 0.014064 | AC18: 0 | AD18: 0 | AE18: 0 | AF18: 0 | AG18: 0 | AH18: 0 | AI18: 0 | AJ18: - - | AL18: - -
B19: Total Conventional Cars | C19: Fleet Vehicle Energy Use: Conventional Cars: Total: Reference case | D19: AEO.2023.REF2023.CNSM_LDV_CNV_FLC_NA_NA_NA_TRLBTU.A | E19: trillion Btu | G19: 216.47511 | H19: 203.27507 | I19: 191.41716 | J19: 179.69829 | K19: 168.59282 | L19: 158.19536 | M19: 149.49013 | N19: 140.81569 | O19: 134.27414 | P19: 127.94789 | Q19: 122.53003 | R19: 117.70418 | S19: 114.60452 | T19: 110.60034 | U19: 107.0435 | V19: 104.12274 | W19: 102.88118 | X19: 100.55843 | Y19: 98.8564 | Z19: 97.046303 | AA19: 94.881645 | AB19: 93.709984 | AC19: 91.912941 | AD19: 89.544693 | AE19: 87.944168 | AF19: 87.058197 | AG19: 86.250748 | AH19: 84.798187 | AI19: 84.145813 | AJ19: -0.033 | AL19: -0.01
B20: Alternative-Fuel Cars
B21: Ethanol-Flex Fuel ICE | C21: Fleet Vehicle Energy Use: Alternative-Fuel Cars: Ethanol-Flex Fuel ICE: Reference case | D21: AEO.2023.REF2023.CNSM_LDV_ALF1_FLC_EFFI_NA_NA_TRLBTU.A | E21: trillion Btu | G21: 10.480461 | H21: 9.339098 | I21: 8.326321 | J21: 7.379097 | K21: 6.577947 | L21: 5.885735 | M21: 5.276652 | N21: 4.770383 | O21: 4.368061 | P21: 4.044937 | Q21: 3.792466 | R21: 3.594607 | S21: 3.463673 | T21: 3.349346 | U21: 3.264263 | V21: 3.200262 | W21: 3.180461 | X21: 3.134341 | Y21: 3.105323 | Z21: 3.072893 | AA21: 3.031026 | AB21: 3.01194 | AC21: 2.979381 | AD21: 2.940709 | AE21: 2.926165 | AF21: 2.925412 | AG21: 2.924571 | AH21: 2.904869 | AI21: 2.901273 | AJ21: -0.045 | AL21: -0.02
B22: 100-Mile Electric Vehicle | C22: Fleet Vehicle Energy Use: Alternative-Fuel Cars: 100-Mile Electric Vehicle: Reference case | D22: AEO.2023.REF2023.#N/A.A | E22: trillion Btu | G22: 0.150231 | H22: 0.155677 | I22: 0.162253 | J22: 0.167239 | K22: 0.170803 | L22: 0.174378 | M22: 0.178883 | N22: 0.183914 | O22: 0.189435 | P22: 0.195387 | Q22: 0.202451 | R22: 0.208928 | S22: 0.216712 | T22: 0.225808 | U22: 0.235789 | V22: 0.2462 | W22: 0.257053 | X22: 0.267747 | Y22: 0.278729 | Z22: 0.289051 | AA22: 0.299019 | AB22: 0.308472 | AC22: 0.317751 | AD22: 0.327821 | AE22: 0.339303 | AF22: 0.350303 | AG22: 0.361062 | AH22: 0.371853 | AI22: 0.38317 | AJ22: 0.034 | AL22: 0.031
B23: 200-Mile Electric Vehicle | C23: Fleet Vehicle Energy Use: Alternative-Fuel Cars: 200-Mile Electric Vehicle: Reference case | D23: AEO.2023.REF2023.#N/A.A | E23: trillion Btu | G23: 0.209457 | H23: 0.242884 | I23: 0.298059 | J23: 0.364701 | K23: 0.432926 | L23: 0.503313 | M23: 0.574033 | N23: 0.648205 | O23: 0.725444 | P23: 0.805029 | Q23: 0.887278 | R23: 0.970448 | S23: 1.056158 | T23: 1.145687 | U23: 1.24113 | V23: 1.338882 | W23: 1.438357 | X23: 1.53907 | Y23: 1.641113 | Z23: 1.740686 | AA23: 1.838436 | AB23: 1.93234 | AC23: 2.027029 | AD23: 2.126119 | AE23: 2.234841 | AF23: 2.340926 | AG23: 2.445624 | AH23: 2.549783 | AI23: 2.658384 | AJ23: 0.095 | AL23: 0.13
B24: 300-Mile Electric Vehicle | C24: Fleet Vehicle Energy Use: Alternative-Fuel Cars: 300-Mile Electric Vehicle: Reference case | D24: AEO.2023.REF2023.#N/A.A | E24: trillion Btu | G24: 0.550371 | H24: 0.648269 | I24: 0.756525 | J24: 0.871065 | K24: 0.977481 | L24: 1.080344 | M24: 1.178738 | N24: 1.276028 | O24: 1.371656 | P24: 1.465148 | Q24: 1.55807 | R24: 1.648828 | S24: 1.740313 | T24: 1.834678 | U24: 1.935023 | V24: 2.036239 | W24: 2.137901 | X24: 2.239863 | Y24: 2.342256 | Z24: 2.440363 | AA24: 2.535465 | AB24: 2.625218 | AC24: 2.715503 | AD24: 2.811472 | AE24: 2.919548 | AF24: 3.024014 | AG24: 3.126449 | AH24: 3.228807 | AI24: 3.336067 | AJ24: 0.066 | AL24: 0.07
B25: Plug-in 20 Gasoline Hybrid | C25: Fleet Vehicle Energy Use: Alternative-Fuel Cars: Plug-in 20 Gasoline Hybrid: Reference case | D25: AEO.2023.REF2023.CNSM_LDV_ALF1_FLC_PI20GH_NA_NA_TRLBTU.A | E25: trillion Btu | G25: 0.386329 | H25: 0.39309 | I25: 0.407523 | J25: 0.420666 | K25: 0.432347 | L25: 0.442696 | M25: 0.450198 | N25: 0.458008 | O25: 0.466522 | P25: 0.475876 | Q25: 0.486238 | R25: 0.497319 | S25: 0.509674 | T25: 0.523991 | U25: 0.540794 | V25: 0.559039 | W25: 0.578382 | X25: 0.598256 | Y25: 0.619031 | Z25: 0.639369 | AA25: 0.659435 | AB25: 0.678625 | AC25: 0.698127 | AD25: 0.718996 | AE25: 0.742586 | AF25: 0.76579 | AG25: 0.788487 | AH25: 0.810004 | AI25: 0.833037 | AJ25: 0.028 | AL25: 0.006
B26: Plug-in 50 Gasoline Hybrid | C26: Fleet Vehicle Energy Use: Alternative-Fuel Cars: Plug-in 50 Gasoline Hybrid: Reference case | D26: AEO.2023.REF2023.CNSM_LDV_ALF1_FLC_PI50GH_NA_NA_TRLBTU.A | E26: trillion Btu | G26: 0.142296 | H26: 0.14536 | I26: 0.152097 | J26: 0.159747 | K26: 0.167478 | L26: 0.175601 | M26: 0.183401 | N26: 0.192391 | O26: 0.202745 | P26: 0.214382 | Q26: 0.227351 | R26: 0.241294 | S26: 0.256446 | T26: 0.273004 | U26: 0.29123 | V26: 0.310325 | W26: 0.330047 | X26: 0.350062 | Y26: 0.370532 | Z26: 0.390592 | AA26: 0.410392 | AB26: 0.429528 | AC26: 0.448834 | AD26: 0.469132 | AE26: 0.491377 | AF26: 0.513273 | AG26: 0.534812 | AH26: 0.555787 | AI26: 0.577731 | AJ26: 0.051 | AL26: 0.029
B27: Electric-Diesel Hybrid | C27: Fleet Vehicle Energy Use: Alternative-Fuel Cars: Electric-Diesel Hybrid: Reference case | D27: AEO.2023.REF2023.CNSM_LDV_ALF1_FLC_EDH_NA_NA_TRLBTU.A | E27: trillion Btu | G27: 0 | H27: 0 | I27: 0 | J27: 0 | K27: 0 | L27: 0 | M27: 0 | N27: 0 | O27: 0 | P27: 0 | Q27: 0 | R27: 0 | S27: 0 | T27: 0 | U27: 0 | V27: 0 | W27: 0 | X27: 0 | Y27: 0 | Z27: 0 | AA27: 0 | AB27: 0 | AC27: 0 | AD27: 0 | AE27: 0 | AF27: 0 | AG27: 0 | AH27: 0 | AI27: 0 | AJ27: - - | AL27: - -
B28: Electric-Gasoline Hybrid | C28: Fleet Vehicle Energy Use: Alternative-Fuel Cars: Electric-Gasoline Hybrid: Reference case | D28: AEO.2023.REF2023.CNSM_LDV_ALF1_FLC_EGH_NA_NA_TRLBTU.A | E28: trillion Btu | G28: 5.879539 | H28: 5.738644 | I28: 5.603165 | J28: 5.429924 | K28: 5.292542 | L28: 5.15739 | M28: 5.025331 | N28: 4.929605 | O28: 4.874351 | P28: 4.848295 | Q28: 4.849487 | R28: 4.867949 | S28: 4.914701 | T28: 4.979584 | U28: 5.063626 | V28: 5.162593 | W28: 5.284299 | X28: 5.399176 | Y28: 5.525168 | Z28: 5.645712 | AA28: 5.759627 | AB28: 5.876257 | AC28: 5.988899 | AD28: 6.108795 | AE28: 6.252316 | AF28: 6.399149 | AG28: 6.545864 | AH28: 6.682308 | AI28: 6.836644 | AJ28: 0.005 | AL28: 0.019
B29: Natural Gas ICE | C29: Fleet Vehicle Energy Use: Alternative-Fuel Cars: Natural Gas ICE: Reference case | D29: AEO.2023.REF2023.CNSM_LDV_ALF1_FLC_NGI_NA_NA_TRLBTU.A | E29: trillion Btu | G29: 0.377738 | H29: 0.347667 | I29: 0.318573 | J29: 0.288045 | K29: 0.256492 | L29: 0.227241 | M29: 0.200066 | N29: 0.173455 | O29: 0.147637 | P29: 0.130939 | Q29: 0.112808 | R29: 0.097209 | S29: 0.085281 | T29: 0.074024 | U29: 0.06433 | V29: 0.057296 | W29: 0.053471 | X29: 0.048527 | Y29: 0 | Z29: 0 | AA29: 0 | AB29: 0 | AC29: 0 | AD29: 0 | AE29: 0 | AF29: 0 | AG29: 0 | AH29: 0 | AI29: 0 | AJ29: - - | AL29: -0.049
B30: Natural Gas Bi-fuel | C30: Fleet Vehicle Energy Use: Alternative-Fuel Cars: Natural Gas Bi-fuel: Reference case | D30: AEO.2023.REF2023.CNSM_LDV_ALF1_FLC_NBF_NA_NA_TRLBTU.A | E30: trillion Btu | G30: 0.013046 | H30: 0.01125 | I30: 0.010099 | J30: 0 | K30: 0 | L30: 0 | M30: 0 | N30: 0 | O30: 0 | P30: 0 | Q30: 0 | R30: 0 | S30: 0 | T30: 0 | U30: 0 | V30: 0 | W30: 0 | X30: 0 | Y30: 0 | Z30: 0 | AA30: 0 | AB30: 0 | AC30: 0 | AD30: 0 | AE30: 0 | AF30: 0 | AG30: 0 | AH30: 0 | AI30: 0 | AJ30: - - | AL30: -0.022
B31: Propane ICE | C31: Fleet Vehicle Energy Use: Alternative-Fuel Cars: Propane ICE: Reference case | D31: AEO.2023.REF2023.CNSM_LDV_ALF1_FLC_PROP_NA_NA_TRLBTU.A | E31: trillion Btu | G31: 0.082875 | H31: 0.070932 | I31: 0.060793 | J31: 0.052714 | K31: 0.046782 | L31: 0.042687 | M31: 0 | N31: 0 | O31: 0 | P31: 0 | Q31: 0 | R31: 0 | S31: 0 | T31: 0 | U31: 0 | V31: 0 | W31: 0 | X31: 0 | Y31: 0 | Z31: 0 | AA31: 0 | AB31: 0 | AC31: 0 | AD31: 0 | AE31: 0 | AF31: 0 | AG31: 0 | AH31: 0 | AI31: 0 | AJ31: - - | AL31: -0.008
B32: Propane Bi-fuel | C32: Fleet Vehicle Energy Use: Alternative-Fuel Cars: Propane Bi-fuel: Reference case | D32: AEO.2023.REF2023.CNSM_LDV_ALF1_FLC_PBF_NA_NA_TRLBTU.A | E32: trillion Btu | G32: 0.167751 | H32: 0.143226 | I32: 0.122224 | J32: 0.105211 | K32: 0.092229 | L32: 0.083367 | M32: 0.077726 | N32: 0 | O32: 0 | P32: 0 | Q32: 0 | R32: 0 | S32: 0 | T32: 0 | U32: 0 | V32: 0 | W32: 0 | X32: 0 | Y32: 0 | Z32: 0 | AA32: 0 | AB32: 0 | AC32: 0 | AD32: 0 | AE32: 0 | AF32: 0 | AG32: 0 | AH32: 0 | AI32: 0 | AJ32: - - | AL32: -0.007
B33: Fuel Cell Methanol | C33: Fleet Vehicle Energy Use: Alternative-Fuel Cars: Fuel Cell Methanol: Reference case | D33: AEO.2023.REF2023.CNSM_LDV_ALF1_FLC_FCLMTH_NA_NA_TRLBTU.A | E33: trillion Btu | G33: 0 | H33: 0 | I33: 0 | J33: 0 | K33: 0 | L33: 0 | M33: 0 | N33: 0 | O33: 0 | P33: 0 | Q33: 0 | R33: 0 | S33: 0 | T33: 0 | U33: 0 | V33: 0 | W33: 0 | X33: 0 | Y33: 0 | Z33: 0 | AA33: 0 | AB33: 0 | AC33: 0 | AD33: 0 | AE33: 0 | AF33: 0 | AG33: 0 | AH33: 0 | AI33: 0 | AJ33: - - | AL33: - -
B34: Fuel Cell Hydrogen | C34: Fleet Vehicle Energy Use: Alternative-Fuel Cars: Fuel Cell Hydrogen: Reference case | D34: AEO.2023.REF2023.CNSM_LDV_ALF1_FLC_FCH_NA_NA_TRLBTU.A | E34: trillion Btu | G34: 0.014403 | H34: 0.014289 | I34: 0.014946 | J34: 0.016136 | K34: 0.017772 | L34: 0.019704 | M34: 0.021841 | N34: 0.024252 | O34: 0.02688 | P34: 0.029724 | Q34: 0.032782 | R34: 0.035993 | S34: 0.039388 | T34: 0.042983 | U34: 0.046814 | V34: 0.050803 | W34: 0.054937 | X34: 0.059182 | Y34: 0.063514 | Z34: 0.067837 | AA34: 0.072143 | AB34: 0.076353 | AC34: 0.080558 | AD34: 0.084838 | AE34: 0.089361 | AF34: 0.093822 | AG34: 0.098271 | AH34: 0.102715 | AI34: 0.107226 | AJ34: 0.074 | AL34: 0.087
B35: Total Alternative Cars | C35: Fleet Vehicle Energy Use: Alternative-Fuel Cars: Total Alternative: Reference case | D35: AEO.2023.REF2023.CNSM_LDV_ALF1_FLC_NA_NA_NA_TRLBTU.A | E35: trillion Btu | G35: 18.454498 | H35: 17.250389 | I35: 16.232576 | J35: 15.254543 | K35: 14.464799 | L35: 13.792457 | M35: 13.166869 | N35: 12.656242 | O35: 12.372729 | P35: 12.209716 | Q35: 12.148932 | R35: 12.162574 | S35: 12.282345 | T35: 12.449106 | U35: 12.683 | V35: 12.961639 | W35: 13.314907 | X35: 13.636225 | Y35: 13.945666 | Z35: 14.286504 | AA35: 14.605542 | AB35: 14.938734 | AC35: 15.256081 | AD35: 15.587882 | AE35: 15.995499 | AF35: 16.412689 | AG35: 16.825138 | AH35: 17.206125 | AI35: 17.633532 | AJ35: -0.002 | AL35: 0.007
B36: Total Car Consumption | C36: Fleet Vehicle Energy Use: Total Cars: Reference case | D36: AEO.2023.REF2023.CNSM_LDV_FLEET_CAR_NA_NA_NA_TRLBTU.A | E36: trillion Btu | G36: 234.92961 | H36: 220.52545 | I36: 207.64973 | J36: 194.95283 | K36: 183.05762 | L36: 171.98781 | M36: 162.657 | N36: 153.47192 | O36: 146.64687 | P36: 140.15761 | Q36: 134.67896 | R36: 129.86676 | S36: 126.88687 | T36: 123.04945 | U36: 119.7265 | V36: 117.08438 | W36: 116.19609 | X36: 114.19465 | Y36: 112.80206 | Z36: 111.33281 | AA36: 109.48719 | AB36: 108.64872 | AC36: 107.16902 | AD36: 105.13258 | AE36: 103.93967 | AF36: 103.47089 | AG36: 103.07588 | AH36: 102.00431 | AI36: 101.77934 | AJ36: -0.029 | AL36: -0.008
B37: Light Trucks
B38: Conventional Light Trucks
B39: Gasoline ICE Vehicles | C39: Fleet Vehicle Energy Use: Conventional Light Trucks: Gasoline: Reference case | D39: AEO.2023.REF2023.CNSM_LDV_CNV_FLTR_GSL_NA_NA_TRLBTU.A | E39: trillion Btu | G39: 501.75183 | H39: 503.61713 | I39: 504.86755 | J39: 504.33365 | K39: 502.3031 | L39: 495.53616 | M39: 490.14276 | N39: 484.03726 | O39: 477.31152 | P39: 471.26633 | Q39: 464.98279 | R39: 456.71075 | S39: 454.35187 | T39: 451.81256 | U39: 446.86377 | V39: 443.61679 | W39: 440.89624 | X39: 437.76324 | Y39: 436.4787 | Z39: 435.17401 | AA39: 432.18591 | AB39: 431.62946 | AC39: 431.20193 | AD39: 428.54828 | AE39: 426.72995 | AF39: 425.77786 | AG39: 425.50494 | AH39: 424.65006 | AI39: 424.85764 | AJ39: -0.006 | AL39: -0.003
B40: TDI Diesel ICE | C40: Fleet Vehicle Energy Use: Conventional Light Trucks: TDI Diesel: Reference case | D40: AEO.2023.REF2023.CNSM_LDV_CNV_FLTR_TDS_NA_NA_TRLBTU.A | E40: trillion Btu | G40: 2.484018 | H40: 2.248934 | I40: 2.001443 | J40: 1.795542 | K40: 1.594673 | L40: 1.408485 | M40: 1.280047 | N40: 1.145545 | O40: 1.010979 | P40: 0.875686 | Q40: 0.757276 | R40: 0.63287 | S40: 0.54049 | T40: 0.449834 | U40: 0.373424 | V40: 0.307815 | W40: 0.255471 | X40: 0.209836 | Y40: 0.175591 | Z40: 0.14886 | AA40: 0.126199 | AB40: 0.109986 | AC40: 0.097024 | AD40: 0.08544 | AE40: 0.005575 | AF40: 0.005638 | AG40: 0.005687 | AH40: 0.005736 | AI40: 0.005797 | AJ40: -0.195 | AL40: 0.041
B41: Total Conventional Light Trucks | C41: Fleet Vehicle Energy Use: Conventional Light Trucks: Total: Reference case | D41: AEO.2023.REF2023.CNSM_LDV_CNV_FLTR_NA_NA_NA_TRLBTU.A | E41: trillion Btu | G41: 504.23584 | H41: 505.86606 | I41: 506.86899 | J41: 506.12918 | K41: 503.89777 | L41: 496.94464 | M41: 491.42282 | N41: 485.1828 | O41: 478.32251 | P41: 472.142 | Q41: 465.74005 | R41: 457.34363 | S41: 454.89236 | T41: 452.26239 | U41: 447.23718 | V41: 443.92459 | W41: 441.1517 | X41: 437.97308 | Y41: 436.6543 | Z41: 435.32288 | AA41: 432.3121 | AB41: 431.73944 | AC41: 431.29895 | AD41: 428.63373 | AE41: 426.73554 | AF41: 425.78351 | AG41: 425.51062 | AH41: 424.65579 | AI41: 424.86343 | AJ41: -0.006 | AL41: -0.002
B42: Alternative-Fuel Light Trucks
B43: Ethanol-Flex Fuel ICE | C43: Fleet Vehicle Energy Use: Alternative-Fuel Light Trucks: Ethanol-Flex Fuel ICE: Reference case | D43: AEO.2023.REF2023.CNSM_LDV_ALF1_FLTR_EFFI_NA_NA_TRLBTU.A | E43: trillion Btu | G43: 77.758781 | H43: 70.702797 | I43: 64.56916 | J43: 58.392281 | K43: 52.867081 | L43: 47.688961 | M43: 43.066307 | N43: 39.060745 | O43: 35.591724 | P43: 32.686638 | Q43: 30.181273 | R43: 27.918329 | S43: 26.471878 | T43: 25.25741 | U43: 24.151287 | V43: 23.380859 | W43: 22.818052 | X43: 22.313604 | Y43: 22.065504 | Z43: 21.856394 | AA43: 21.520844 | AB43: 21.437918 | AC43: 21.388447 | AD43: 21.119314 | AE43: 20.951746 | AF43: 20.870531 | AG43: 20.838223 | AH43: 20.751728 | AI43: 20.771072 | AJ43: -0.046 | AL43: -0.003
B44: 100-Mile Electric Vehicle | C44: Fleet Vehicle Energy Use: Alternative-Fuel Light Trucks: 100-Mile Electric Vehicle: Reference case | D44: AEO.2023.REF2023.#N/A.A | E44: trillion Btu | G44: 0.007213 | H44: 0.007115 | I44: 0.00705 | J44: 0.007079 | K44: 0.006964 | L44: 0.006225 | M44: 0.006222 | N44: 0.006205 | O44: 0.006167 | P44: 0.006113 | Q44: 0.00604 | R44: 0.005946 | S44: 0.00583 | T44: 0.005812 | U44: 0.00563 | V44: 0.004755 | W44: 0.004601 | X44: 0.004423 | Y44: 0.004227 | Z44: 0.004013 | AA44: 0.003787 | AB44: 0.003551 | AC44: 0.003308 | AD44: 0.00306 | AE44: 0.002822 | AF44: 0.002564 | AG44: 0.002305 | AH44: 0.002041 | AI44: 0.001777 | AJ44: -0.049 | AL44: - -
B45: 200-Mile Electric Vehicle | C45: Fleet Vehicle Energy Use: Alternative-Fuel Light Trucks: 200-Mile Electric Vehicle: Reference case | D45: AEO.2023.REF2023.#N/A.A | E45: trillion Btu | G45: 0.157907 | H45: 0.309263 | I45: 0.526982 | J45: 0.798223 | K45: 1.11458 | L45: 1.46172 | M45: 1.836559 | N45: 2.243148 | O45: 2.670595 | P45: 3.116636 | Q45: 3.577014 | R45: 4.049897 | S45: 4.539747 | T45: 5.053014 | U45: 5.586455 | V45: 6.138822 | W45: 6.711488 | X45: 7.300607 | Y45: 7.909584 | Z45: 8.528099 | AA45: 9.157216 | AB45: 9.797174 | AC45: 10.445819 | AD45: 11.116942 | AE45: 11.795783 | AF45: 12.487298 | AG45: 13.180316 | AH45: 13.890413 | AI45: 14.621585 | AJ45: 0.176 | AL45: 0.215
B46: 300-Mile Electric Vehicle | C46: Fleet Vehicle Energy Use: Alternative-Fuel Light Trucks: 300-Mile Electric Vehicle: Reference case | D46: AEO.2023.REF2023.#N/A.A | E46: trillion Btu | G46: 0.06813 | H46: 0.093171 | I46: 0.125104 | J46: 0.162371 | K46: 0.203087 | L46: 0.246397 | M46: 0.292222 | N46: 0.340935 | O46: 0.392119 | P46: 0.445542 | Q46: 0.499981 | R46: 0.555235 | S46: 0.611954 | T46: 0.671019 | U46: 0.732074 | V46: 0.795021 | W46: 0.860015 | X46: 0.926675 | Y46: 0.995405 | Z46: 1.065078 | AA46: 1.135914 | AB46: 1.207883 | AC46: 1.280732 | AD46: 1.356058 | AE46: 1.432175 | AF46: 1.509734 | AG46: 1.587452 | AH46: 1.667159 | AI46: 1.749228 | AJ46: 0.123 | AL46: 0.102
B47: Plug-in 20 Gasoline Hybrid | C47: Fleet Vehicle Energy Use: Alternative-Fuel Light Trucks: Plug-in 20 Gasoline Hybrid: Reference case | D47: AEO.2023.REF2023.CNSM_LDV_ALF1_FLTR_PI20GH_NA_NA_TRLBTU.A | E47: trillion Btu | G47: 0.736833 | H47: 0.755365 | I47: 0.777186 | J47: 0.876546 | K47: 0.973577 | L47: 1.065621 | M47: 1.14999 | N47: 1.231477 | O47: 1.308586 | P47: 1.381874 | Q47: 1.451041 | R47: 1.515952 | S47: 1.577906 | T47: 1.638222 | U47: 1.697212 | V47: 1.755401 | W47: 1.813574 | X47: 1.871447 | Y47: 1.930384 | Z47: 1.989441 | AA47: 2.049068 | AB47: 2.109643 | AC47: 2.171116 | AD47: 2.234781 | AE47: 2.299394 | AF47: 2.365882 | AG47: 2.432531 | AH47: 2.500198 | AI47: 2.570302 | AJ47: 0.046 | AL47: 0.069
B48: Plug-in 50 Gasoline Hybrid | C48: Fleet Vehicle Energy Use: Alternative-Fuel Light Trucks: Plug-in 50 Gasoline Hybrid: Reference case | D48: AEO.2023.REF2023.CNSM_LDV_ALF1_FLTR_PI50GH_NA_NA_TRLBTU.A | E48: trillion Btu | G48: 0.02835 | H48: 0.041937 | I48: 0.061585 | J48: 0.087241 | K48: 0.119358 | L48: 0.15621 | M48: 0.196858 | N48: 0.241861 | O48: 0.290423 | P48: 0.342297 | Q48: 0.396977 | R48: 0.454093 | S48: 0.513774 | T48: 0.576316 | U48: 0.641519 | V48: 0.709294 | W48: 0.77969 | X48: 0.852262 | Y48: 0.927325 | Z48: 1.00398 | AA48: 1.082246 | AB48: 1.162094 | AC48: 1.24325 | AD48: 1.326875 | AE48: 1.411644 | AF48: 1.49812 | AG48: 1.585271 | AH48: 1.674039 | AI48: 1.765017 | AJ48: 0.159 | AL48: 0.077
B49: Electric-Diesel Hybrid | C49: Fleet Vehicle Energy Use: Alternative-Fuel Light Trucks: Electric-Diesel Hybrid: Reference case | D49: AEO.2023.REF2023.CNSM_LDV_ALF1_FLTR_EDH_NA_NA_TRLBTU.A | E49: trillion Btu | G49: 0 | H49: 0 | I49: 0 | J49: 0 | K49: 0 | L49: 0 | M49: 0 | N49: 0 | O49: 0 | P49: 0 | Q49: 0 | R49: 0 | S49: 0 | T49: 0 | U49: 0 | V49: 0 | W49: 0 | X49: 0 | Y49: 0 | Z49: 0 | AA49: 0 | AB49: 0 | AC49: 0 | AD49: 0 | AE49: 0 | AF49: 0 | AG49: 0 | AH49: 0 | AI49: 0 | AJ49: - - | AL49: - -
B50: Electric-Gasoline Hybrid | C50: Fleet Vehicle Energy Use: Alternative-Fuel Light Trucks: Electric-Gasoline Hybrid: Reference case | D50: AEO.2023.REF2023.CNSM_LDV_ALF1_FLTR_EGH_NA_NA_TRLBTU.A | E50: trillion Btu | G50: 5.68154 | H50: 6.772939 | I50: 7.8264 | J50: 8.871678 | K50: 9.864345 | L50: 10.707438 | M50: 11.431044 | N50: 12.085834 | O50: 12.673258 | P50: 13.206234 | Q50: 13.686852 | R50: 14.115453 | S50: 14.526539 | T50: 14.914807 | U50: 15.279657 | V50: 15.632938 | W50: 15.982077 | X50: 16.321697 | Y50: 16.670664 | Z50: 17.015572 | AA50: 17.356346 | AB50: 17.706573 | AC50: 18.06147 | AD50: 18.431583 | AE50: 18.810234 | AF50: 19.204651 | AG50: 19.601482 | AH50: 20.001671 | AI50: 20.427528 | AJ50: 0.047 | AL50: 0.068
B51: Natural Gas ICE | C51: Fleet Vehicle Energy Use: Alternative-Fuel Light Trucks: Natural Gas ICE: Reference case | D51: AEO.2023.REF2023.CNSM_LDV_ALF1_FLTR_NGI_NA_NA_TRLBTU.A | E51: trillion Btu | G51: 0.190599 | H51: 0.177307 | I51: 0.154094 | J51: 0.143256 | K51: 0.139979 | L51: 0.127385 | M51: 0.118635 | N51: 0.109754 | O51: 0.089389 | P51: 0.083531 | Q51: 0.07795 | R51: 0.072657 | S51: 0.067701 | T51: 0.064348 | U51: 0.059003 | V51: 0.053484 | W51: 0.05031 | X51: 0 | Y51: 0 | Z51: 0 | AA51: 0 | AB51: 0 | AC51: 0 | AD51: 0 | AE51: 0 | AF51: 0 | AG51: 0 | AH51: 0 | AI51: 0 | AJ51: - - | AL51: -0.022
B52: Natural Gas Bi-fuel | C52: Fleet Vehicle Energy Use: Alternative-Fuel Light Trucks: Natural Gas Bi-fuel: Reference case | D52: AEO.2023.REF2023.CNSM_LDV_ALF1_FLTR_NBF_NA_NA_TRLBTU.A | E52: trillion Btu | G52: 0.174772 | H52: 0.162522 | I52: 0 | J52: 0 | K52: 0 | L52: 0 | M52: 0 | N52: 0 | O52: 0 | P52: 0 | Q52: 0 | R52: 0 | S52: 0 | T52: 0 | U52: 0 | V52: 0 | W52: 0 | X52: 0 | Y52: 0 | Z52: 0 | AA52: 0 | AB52: 0 | AC52: 0 | AD52: 0 | AE52: 0 | AF52: 0 | AG52: 0 | AH52: 0 | AI52: 0 | AJ52: - - | AL52: -0.003
B53: Propane ICE | C53: Fleet Vehicle Energy Use: Alternative-Fuel Light Trucks: Propane ICE: Reference case | D53: AEO.2023.REF2023.CNSM_LDV_ALF1_FLTR_PROP_NA_NA_TRLBTU.A | E53: trillion Btu | G53: 0.432597 | H53: 0.389215 | I53: 0.346855 | J53: 0.316062 | K53: 0.283891 | L53: 0.256976 | M53: 0 | N53: 0 | O53: 0 | P53: 0 | Q53: 0 | R53: 0 | S53: 0 | T53: 0 | U53: 0 | V53: 0 | W53: 0 | X53: 0 | Y53: 0 | Z53: 0 | AA53: 0 | AB53: 0 | AC53: 0 | AD53: 0 | AE53: 0 | AF53: 0 | AG53: 0 | AH53: 0 | AI53: 0 | AJ53: - - | AL53: -0.023
B54: Propane Bi-fuel | C54: Fleet Vehicle Energy Use: Alternative-Fuel Light Trucks: Propane Bi-fuel: Reference case | D54: AEO.2023.REF2023.CNSM_LDV_ALF1_FLTR_PBF_NA_NA_TRLBTU.A | E54: trillion Btu | G54: 0.409997 | H54: 0.381231 | I54: 0 | J54: 0 | K54: 0 | L54: 0 | M54: 0 | N54: 0 | O54: 0 | P54: 0 | Q54: 0 | R54: 0 | S54: 0 | T54: 0 | U54: 0 | V54: 0 | W54: 0 | X54: 0 | Y54: 0 | Z54: 0 | AA54: 0 | AB54: 0 | AC54: 0 | AD54: 0 | AE54: 0 | AF54: 0 | AG54: 0 | AH54: 0 | AI54: 0 | AJ54: - - | AL54: -0.044
B55: Fuel Cell Methanol | C55: Fleet Vehicle Energy Use: Alternative-Fuel Light Trucks: Fuel Cell Methanol: Reference case | D55: AEO.2023.REF2023.CNSM_LDV_ALF1_FLTR_FCLMTH_NA_NA_TRLBTU.A | E55: trillion Btu | G55: 0 | H55: 0 | I55: 0 | J55: 0 | K55: 0 | L55: 0 | M55: 0 | N55: 0 | O55: 0 | P55: 0 | Q55: 0 | R55: 0 | S55: 0 | T55: 0 | U55: 0 | V55: 0 | W55: 0 | X55: 0 | Y55: 0 | Z55: 0 | AA55: 0 | AB55: 0 | AC55: 0 | AD55: 0 | AE55: 0 | AF55: 0 | AG55: 0 | AH55: 0 | AI55: 0 | AJ55: - - | AL55: - -
B56: Fuel Cell Hydrogen | C56: Fleet Vehicle Energy Use: Alternative-Fuel Light Trucks: Fuel Cell Hydrogen: Reference case | D56: AEO.2023.REF2023.CNSM_LDV_ALF1_FLTR_FCH_NA_NA_TRLBTU.A | E56: trillion Btu | G56: 9.4e-05 | H56: 0.000286 | I56: 0.000586 | J56: 0.000997 | K56: 0.00151 | L56: 0.002119 | M56: 0.002817 | N56: 0.003605 | O56: 0.004468 | P56: 0.005401 | Q56: 0.006395 | R56: 0.007441 | S56: 0.008539 | T56: 0.00969 | U56: 0.010892 | V56: 0.012143 | W56: 0.013444 | X56: 0.01479 | Y56: 0.016183 | Z56: 0.017611 | AA56: 0.019073 | AB56: 0.020568 | AC56: 0.022091 | AD56: 0.023657 | AE56: 0.025248 | AF56: 0.026872 | AG56: 0.028514 | AH56: 0.030191 | AI56: 0.031908 | AJ56: 0.231 | AL56: 0.194
B57: Total Alternative Light Trucks | C57: Fleet Vehicle Energy Use: Alternative-Fuel Light Trucks: Total Alternative: Reference case | D57: AEO.2023.REF2023.CNSM_LDV_ALF1_FLTR_NA_NA_NA_TRLBTU.A | E57: trillion Btu | G57: 85.646805 | H57: 79.793159 | I57: 74.395004 | J57: 69.655739 | K57: 65.574371 | L57: 61.719051 | M57: 58.100651 | N57: 55.323563 | O57: 53.026733 | P57: 51.274261 | Q57: 49.883522 | R57: 48.695007 | S57: 48.323868 | T57: 48.190636 | U57: 48.163731 | V57: 48.482716 | W57: 49.033249 | X57: 49.605507 | Y57: 50.519279 | Z57: 51.48019 | AA57: 52.324493 | AB57: 53.445404 | AC57: 54.61623 | AD57: 55.612267 | AE57: 56.729046 | AF57: 57.965652 | AG57: 59.256092 | AH57: 60.517441 | AI57: 61.938416 | AJ57: -0.012 | AL57: 0.006
B58: Total Light Truck Consumption | C58: Fleet Vehicle Energy Use: Total Light Trucks: Reference case | D58: AEO.2023.REF2023.CNSM_LDV_FLEET_LTK_NA_NA_NA_TRLBTU.A | E58: trillion Btu | G58: 589.88263 | H58: 585.65924 | I58: 581.26398 | J58: 575.78491 | K58: 569.47217 | L58: 558.6637 | M58: 549.5235 | N58: 540.50635 | O58: 531.34924 | P58: 523.41626 | Q58: 515.6236 | R58: 506.03863 | S58: 503.21625 | T58: 500.45303 | U58: 495.40091 | V58: 492.40732 | W58: 490.18494 | X58: 487.57858 | Y58: 487.17358 | Z58: 486.80307 | AA58: 484.6366 | AB58: 485.18484 | AC58: 485.91519 | AD58: 484.246 | AE58: 483.46457 | AF58: 483.74915 | AG58: 484.76672 | AH58: 485.17322 | AI58: 486.80185 | AJ58: -0.007 | AL58: -0.001
B59: Total Fleet Vehicles | C59: Fleet Vehicle Energy Use: Total Fleet Vehicles: Reference case | D59: AEO.2023.REF2023.CNSM_LDV_FLEET_NA_NA_NA_NA_TRLBTU.A | E59: trillion Btu | G59: 824.81226 | H59: 806.18469 | I59: 788.9137 | J59: 770.73773 | K59: 752.52978 | L59: 730.65149 | M59: 712.18048 | N59: 693.97827 | O59: 677.99609 | P59: 663.57385 | Q59: 650.30255 | R59: 635.9054 | S59: 630.10315 | T59: 623.5025 | U59: 615.12744 | V59: 609.4917 | W59: 606.38104 | X59: 601.77325 | Y59: 599.97565 | Z59: 598.13586 | AA59: 594.12378 | AB59: 593.83356 | AC59: 593.08423 | AD59: 589.3786 | AE59: 587.40424 | AF59: 587.22003 | AG59: 587.84259 | AH59: 587.17755 | AI59: 588.58118 | AJ59: -0.012 | AL59: -0.003
B60: Commercial Light Trucks
A61: gasoline vehicle | B61: Motor Gasoline | C61: Fleet Vehicle Energy Use: Commercial Light Trucks: Gasoline: Reference case | D61: AEO.2023.REF2023.CNSM_LDV_TRN_CML_GSL_NA_NA_TRLBTU.A | E61: trillion Btu | G61: 510.03906 | H61: 513.23224 | I61: 514.50214 | J61: 516.66699 | K61: 520.87158 | L61: 519.23016 | M61: 518.84228 | N61: 517.39124 | O61: 515.60321 | P61: 514.84003 | Q61: 515.51892 | R61: 516.3894 | S61: 517.64654 | T61: 518.72296 | U61: 519.57184 | V61: 520.63886 | W61: 521.87012 | X61: 522.68402 | Y61: 524.88648 | Z61: 527.33356 | AA61: 530.56335 | AB61: 533.10168 | AC61: 535.1593 | AD61: 537.66614 | AE61: 541.15063 | AF61: 546.01294 | AG61: 550.45172 | AH61: 555.21411 | AI61: 561.63238 | AJ61: 0.003 | AL61: -0.025
A62: diesel vehicle | B62: Diesel | C62: Fleet Vehicle Energy Use: Commercial Light Trucks: TDI Diesel: Reference case | D62: AEO.2023.REF2023.CNSM_LDV_TRN_CML_TDS_NA_NA_TRLBTU.A | E62: trillion Btu | G62: 289.12042 | H62: 286.75845 | I62: 280.34622 | J62: 273.8996 | K62: 268.30765 | L62: 266.09418 | M62: 263.51706 | N62: 260.94449 | O62: 258.00409 | P62: 255.27026 | Q62: 253.60591 | R62: 252.22235 | S62: 251.02647 | T62: 250.13725 | U62: 249.41119 | V62: 248.96448 | W62: 248.9669 | X62: 248.90626 | Y62: 249.25397 | Z62: 250.6158 | AA62: 251.53905 | AB62: 252.49449 | AC62: 253.52728 | AD62: 255.13101 | AE62: 256.97702 | AF62: 259.20792 | AG62: 261.09692 | AH62: 262.84183 | AI62: 265.58344 | AJ62: -0.003 | AL62: 0.008
A63: LPG vehicle | B63: Propane | C63: Fleet Vehicle Energy Use: Commercial Light Trucks: Propane: Reference case | D63: AEO.2023.REF2023.CNSM_LDV_TRN_CML_PROP_NA_NA_TRLBTU.A | E63: trillion Btu | G63: 0.001192 | H63: 0.059367 | I63: 0.11705 | J63: 0.172413 | K63: 0.229498 | L63: 0.283619 | M63: 0.336463 | N63: 0.393365 | O63: 0.436597 | P63: 0.484428 | Q63: 0.539452 | R63: 0.601839 | S63: 0.673214 | T63: 0.756342 | U63: 0.853271 | V63: 0.967702 | W63: 1.102202 | X63: 1.257558 | Y63: 1.439565 | Z63: 1.649748 | AA63: 1.886108 | AB63: 2.14976 | AC63: 2.440006 | AD63: 2.759259 | AE63: 3.110511 | AF63: 3.489864 | AG63: 3.885303 | AH63: 4.297863 | AI63: 4.738037 | AJ63: 0.344 | AL63: 0.088
A64: natural gas vehicle | B64: Compressed/Liquefied Natural Gas | C64: Fleet Vehicle Energy Use: Commercial Light Trucks: CNG/LNG: Reference case | D64: AEO.2023.REF2023.CNSM_LDV_TRN_CML_NG_NA_NA_TRLBTU.A | E64: trillion Btu | G64: 1.100109 | H64: 1.028096 | I64: 0.954857 | J64: 0.851628 | K64: 0.748517 | L64: 0.657968 | M64: 0.592555 | N64: 0.535011 | O64: 0.478159 | P64: 0.423993 | Q64: 0.376664 | R64: 0.335485 | S64: 0.300891 | T64: 0.271073 | U64: 0.243198 | V64: 0.217586 | W64: 0.194927 | X64: 0.176079 | Y64: 0.160581 | Z64: 0.146182 | AA64: 0.133464 | AB64: 0.121475 | AC64: 0.110383 | AD64: 0.099974 | AE64: 0.087947 | AF64: 0.07232 | AG64: 0.057146 | AH64: 0.045076 | AI64: 0.03417 | AJ64: -0.117 | AL64: -0.013
A65: gasoline vehicle | B65: Ethanol-Flex Fuel | C65: Fleet Vehicle Energy Use: Commercial Light Trucks: Ethanol Flex: Reference case | D65: AEO.2023.REF2023.CNSM_LDV_TRN_CML_EFFI_NA_NA_TRLBTU.A | E65: trillion Btu | G65: 151.2421 | H65: 141.34045 | I65: 129.14581 | J65: 120.46179 | K65: 112.43228 | L65: 107.91116 | M65: 104.36762 | N65: 102.90226 | O65: 101.62165 | P65: 100.82185 | Q65: 100.73156 | R65: 101.22623 | S65: 102.21268 | T65: 103.91997 | U65: 106.05133 | V65: 108.74959 | W65: 111.78932 | X65: 115.00824 | Y65: 118.47511 | Z65: 122.06258 | AA65: 125.48125 | AB65: 128.27446 | AC65: 130.72479 | AD65: 133.17833 | AE65: 135.37009 | AF65: 137.66872 | AG65: 139.07935 | AH65: 140.81187 | AI65: 142.6514 | AJ65: -0.002 | AL65: 0.031
A66: battery electric vehicle | B66: Electric | C66: Fleet Vehicle Energy Use: Commercial Light Trucks: Electric: Reference case | D66: AEO.2023.REF2023.CNSM_LDV_TRN_CML_ELE_NA_NA_TRLBTU.A | E66: trillion Btu | G66: 0 | H66: 0 | I66: 0 | J66: 0 | K66: 0 | L66: 0 | M66: 0 | N66: 0 | O66: 0 | P66: 0 | Q66: 0 | R66: 0 | S66: 0 | T66: 0 | U66: 0 | V66: 0 | W66: 0 | X66: 0 | Y66: 0 | Z66: 0 | AA66: 0 | AB66: 0 | AC66: 0 | AD66: 0 | AE66: 0 | AF66: 0 | AG66: 0 | AH66: 0 | AI66: 0 | AJ66: - - | AL66: 0.115
A67: plugin hybrid vehicle | B67: Plug-in Gasoline Hybrid | C67: Fleet Vehicle Energy Use: Commercial Light Trucks: Plug-in Gasoline: Reference case | D67: AEO.2023.REF2023.CNSM_LDV_TRN_CML_EGH_NA_NA_TRLBTU.A | E67: trillion Btu | G67: 0 | H67: 0.062978 | I67: 0.122956 | J67: 0.178811 | K67: 0.233279 | L67: 0.28163 | M67: 0.325901 | N67: 0.370868 | O67: 0.397096 | P67: 0.423606 | Q67: 0.452219 | R67: 0.482781 | S67: 0.516136 | T67: 0.553246 | U67: 0.594358 | V67: 0.640736 | W67: 0.693285 | X67: 0.751108 | Y67: 0.816813 | Z67: 0.889812 | AA67: 0.968298 | AB67: 1.051889 | AC67: 1.139437 | AD67: 1.231045 | AE67: 1.327474 | AF67: 1.426723 | AG67: 1.52464 | AH67: 1.622346 | AI67: 1.724409 | AJ67: - - | AL67: 0.11
A68: plugin hybrid vehicle | B68: Plug-in Diesel Hybrid | C68: Fleet Vehicle Energy Use: Commercial Light Trucks: Plug-in Diesel: Reference case | D68: AEO.2023.REF2023.CNSM_LDV_TRN_CML_EDH_NA_NA_TRLBTU.A | E68: trillion Btu | G68: 0 | H68: 0.076647 | I68: 0.151202 | J68: 0.22044 | K68: 0.288016 | L68: 0.34804 | M68: 0.402573 | N68: 0.458179 | O68: 0.491732 | P68: 0.526732 | Q68: 0.565955 | R68: 0.609316 | S68: 0.65773 | T68: 0.712648 | U68: 0.774261 | V68: 0.844385 | W68: 0.924143 | X68: 1.012774 | Y68: 1.113816 | Z68: 1.226819 | AA68: 1.34934 | AB68: 1.481028 | AC68: 1.619354 | AD68: 1.764458 | AE68: 1.91617 | AF68: 2.071944 | AG68: 2.224892 | AH68: 2.377063 | AI68: 2.534203 | AJ68: - - | AL68: 0.115
A69: hydrogen vehicle | B69: Fuel Cell | C69: Fleet Vehicle Energy Use: Commercial Light Trucks: Fuel Cell: Reference case | D69: AEO.2023.REF2023.CNSM_LDV_TRN_CML_FUC_NA_NA_TRLBTU.A | E69: trillion Btu | G69: 0 | H69: 0 | I69: 0 | J69: 0 | K69: 0 | L69: 0 | M69: 0 | N69: 0 | O69: 0 | P69: 0 | Q69: 0 | R69: 0 | S69: 0 | T69: 0 | U69: 0 | V69: 0 | W69: 0 | X69: 0 | Y69: 0 | Z69: 0 | AA69: 0 | AB69: 0 | AC69: 0 | AD69: 0 | AE69: 0 | AF69: 0 | AG69: 0 | AH69: 0 | AI69: 0 | AJ69: - - | AL69: - -
B70: Total Commercial Light Trucks | C70: Fleet Vehicle Energy Use: Commercial Light Trucks: Total: Reference case | D70: AEO.2023.REF2023.CNSM_LDV_TRN_CML_NA_NA_NA_TRLBTU.A | E70: trillion Btu | G70: 951.50293 | H70: 942.55829 | I70: 925.34027 | J70: 912.45172 | K70: 903.11078 | L70: 894.80676 | M70: 888.38452 | N70: 882.99542 | O70: 877.03253 | P70: 872.79089 | Q70: 871.79065 | R70: 871.86749 | S70: 873.03369 | T70: 875.07349 | U70: 877.49945 | V70: 881.02332 | W70: 885.54089 | X70: 889.79602 | Y70: 896.14636 | Z70: 903.92444 | AA70: 911.92096 | AB70: 918.6748 | AC70: 924.72058 | AD70: 931.8302 | AE70: 939.93994 | AF70: 949.95038 | AG70: 958.32001 | AH70: 967.2102 | AI70: 978.89801 | AJ70: 0.001 | AL70: 0.009

Sheet AEO 2023 46
F1: 2021 | G1: 2022 | H1: 2023 | I1: 2024 | J1: 2025 | K1: 2026 | L1: 2027 | M1: 2028 | N1: 2029 | O1: 2030 | P1: 2031 | Q1: 2032 | R1: 2033 | S1: 2034 | T1: 2035 | U1: 2036 | V1: 2037 | W1: 2038 | X1: 2039 | Y1: 2040 | Z1: 2041 | AA1: 2042 | AB1: 2043 | AC1: 2044 | AD1: 2045 | AE1: 2046 | AF1: 2047 | AG1: 2048 | AH1: 2049 | AI1: 2050 | AJ1: Growth (2022-2050)
B10: Table 46. Transportation Fleet Car and Truck Vehicle Miles Traveled by Type and Technology
B11: https://www.eia.gov/outlooks/aeo/data/browser/#/?id=56-AEO2023&cases=ref2023&sourcekey=0
B12: Thu Dec 11 2025 14:20:56 GMT-0800 (Pacific Standard Time)
B13: Source: U.S. Energy Information Administration
C14: full name | D14: api key | E14: units | F14: 2021 | G14: 2022 | H14: 2023 | I14: 2024 | J14: 2025 | K14: 2026 | L14: 2027 | M14: 2028 | N14: 2029 | O14: 2030 | P14: 2031 | Q14: 2032 | R14: 2033 | S14: 2034 | T14: 2035 | U14: 2036 | V14: 2037 | W14: 2038 | X14: 2039 | Y14: 2040 | Z14: 2041 | AA14: 2042 | AB14: 2043 | AC14: 2044 | AD14: 2045 | AE14: 2046 | AF14: 2047 | AG14: 2048 | AH14: 2049 | AI14: 2050 | AJ14: Growth (2022-2050)
B15: Cars
B16: Conventional Cars
B17: Gasoline ICE Vehicles | C17: Fleet Vehicle Miles Traveled: Conventional Cars: Gasoline: Reference case | D17: AEO.2023.REF2023.ECI_VMT_CNV_FLC_GSL_NA_NA_BLNMLS.A | E17: billion miles | G17: 49.601604 | H17: 47.635735 | I17: 45.880428 | J17: 44.023563 | K17: 42.271244 | L17: 40.47142 | M17: 38.879578 | N17: 37.498188 | O17: 36.282726 | P17: 35.198715 | Q17: 34.24884 | R17: 33.389473 | S17: 32.649353 | T17: 32.037964 | U17: 31.56945 | V17: 31.164738 | W17: 30.803478 | X17: 30.475691 | Y17: 30.174114 | Z17: 29.852413 | AA17: 29.519142 | AB17: 29.156063 | AC17: 28.806911 | AD17: 28.505373 | AE17: 28.289747 | AF17: 28.052269 | AG17: 27.803013 | AH17: 27.557156 | AI17: 27.341675 | AJ17: -0.021
B18: TDI Diesel ICE | C18: Fleet Vehicle Miles Traveled: Conventional Cars: TDI Diesel: Reference case | D18: AEO.2023.REF2023.ECI_VMT_CNV_FLC_TDS_NA_NA_BLNMLS.A | E18: billion miles | G18: 0.111688 | H18: 0.096533 | I18: 0.083162 | J18: 0.071313 | K18: 0.060877 | L18: 0.051619 | M18: 0.043394 | N18: 0.036203 | O18: 0.030032 | P18: 0.024808 | Q18: 0.020457 | R18: 0.016912 | S18: 0.01408 | T18: 0.011855 | U18: 0.010115 | V18: 0.008753 | W18: 0.00769 | X18: 0.006846 | Y18: 0.006137 | Z18: 0.005519 | AA18: 0.004978 | AB18: 0.004498 | AC18: 0.00407 | AD18: 0.003685 | AE18: 0.003339 | AF18: 0.003028 | AG18: 0.002748 | AH18: 0.002497 | AI18: 0.00227 | AJ18: -0.13
