Workbook
Name lignite_multiplier: '[1]Hard Coal and Lig Multipliers'!$N$16
Name nonlignite_multiplier: '[1]Hard Coal and Lig Multipliers'!$N$17

Sheet About
A1: EIaE BAU Imported Electricity
A2: EIaE BAU Exported Electricity
A3: EIaE Imported Electricity Price
A4: EIaE BAU Exported Electricity Price
A6: Source: | B6: Quantity of Imports and Exports
B7: U.S. Energy Information Administration
B8: 2026
B9: Annual Energy Outlook 2026
B10: Alternative electricity and transportation: Table 10
B11: https://www.eia.gov/outlooks/aeo/tables_side_xls.php
B13: Canadian Electricity Generation by Type
B14: National Energy Board, Government of Canada
B15: 2021
B16: Canada's Energy Future 2021, Appendices
B17: https://apps.neb-one.gc.ca/ftrppndc/dflt.aspx?GoCTemplateCulture=en-CA
B18: Table "Electricity Generation," Reference Case, Canada
B20: Imported and Exported Electricity Prices
B21: U.S. Energy Information Administration
B22: 2026
B23: Annual Energy Outlook 2026
B24: Alternative electricity and transportation: Table 10
B25: https://www.eia.gov/outlooks/aeo/tables_side_xls.php
B27: Canada NG Generation by Turbine Type
B28: Statistics Canada
B29: 2022
B30: Electric power generation, monthly generation by type of electricity
B31: https://www150.statcan.gc.ca/t1/tbl1/en/tv.action?pid=2510001501&pickMembers%5B0%5D=1.1&pickMembers%5B1%5D=2.2&cubeTimeFrame.startMonth=01&cubeTimeFrame.startYear=2015&cubeTimeFrame.endMonth=12&cubeTimeFrame.endYear=2015&referencePeriods=20150101%2C20151201
B32: Data after 2015 does not break out turbine types, so we use data from 2015.
A34: Notes
A35: We need to know the mix of imported electricity types if we will be including
A36: pollutant emissions associated with imported electricity into the totals, which
A37: is managed by a control lever. If these emissions will not be included in the
A38: emissions totals, the breakdown is unimportant, and you may assign all
A39: imported electricity emissions to any one electricity source, if you prefer.
A41: Electricity exports are supplied by power plants in the modeled region and
A42: hence do not need their electricity source to be specified here.
A44: Since electricity imported to the U.S. comes overwhelmingly from Canada,
A45: we use Canada's electricity generation mix to approximate the mix
A46: of all imported electricity.
A48: All Canadian natural gas was assigned to the "natural gas nonpeaker" plant type
... A57: Conversion Factors
A58: 2.931e-07 | B58: MWh/BTU
A59: 0.88711067 | B59: 2012 USD/2020 USD
A60: 0.732 | B60: 2012 USD/2024 USD
A61: 0.713109 | B61: 2012 USD/2025 USD

Sheet Source Data>

Sheet AEO Table 10 2025
A1: Table 10. Electricity Trade
A2: https://www.eia.gov/outlooks/aeo/data/browser/#/?id=10-AEO2025&cases=highZTC&sourcekey=0
A3: Tue Dec 02 2025 13:19:25 GMT-0800 (Pacific Standard Time)
A4: Source: U.S. Energy Information Administration
B5: full name | C5: api key | D5: units | E5: 2023 | F5: 2024 | G5: 2025 | H5: 2026 | I5: 2027 | J5: 2028 | K5: 2029 | L5: 2030 | M5: 2031 | N5: 2032 | O5: 2033 | P5: 2034 | Q5: 2035 | R5: 2036 | S5: 2037 | T5: 2038 | U5: 2039 | V5: 2040 | W5: 2041 | X5: 2042 | Y5: 2043 | Z5: 2044 | AA5: 2045 | AB5: 2046 | AC5: 2047 | AD5: 2048 | AE5: 2049 | AF5: 2050 | AG5: Growth (2024-2050)
A6: Interregional Electricity Trade
A7: Gross Domestic Sales
A8: Firm Power | B8: Electricity Trade: Gross Domestic Sales: Firm Power: High Zero-Carbon Technology Cost | C8: AEO.2025.HIGHZTC.TRAD_FPW_ELEP_GDSE_SAL_NA_USA_BLNKWH.A | D8: BkWh | F8: 45.122738 | G8: 43.267342 | H8: 43.046135 | I8: 42.817745 | J8: 42.559059 | K8: 42.293133 | L8: 42.024811 | M8: 41.620968 | N8: 41.217125 | O8: 40.813286 | P8: 40.156345 | Q8: 39.466721 | R8: 38.769127 | S8: 37.904129 | T8: 37.069424 | U8: 36.021156 | V8: 34.9147 | W8: 33.94376 | X8: 32.853245 | Y8: 31.762728 | Z8: 31.010212 | AA8: 30.418716 | AB8: 29.843166 | AC8: 29.442196 | AD8: 29.041224 | AE8: 28.861069 | AF8: 28.741493 | AG8: -0.017
A9: Economy | B9: Electricity Trade: Gross Domestic Sales: Economy: High Zero-Carbon Technology Cost | C9: AEO.2025.HIGHZTC.TRAD_ECN_ELEP_GDSE_SAL_NA_USA_BLNKWH.A | D9: BkWh | F9: 249.34067 | G9: 237.90076 | H9: 224.18767 | I9: 252.91287 | J9: 276.10901 | K9: 290.98074 | L9: 319.57144 | M9: 301.05426 | N9: 347.96228 | O9: 365.80243 | P9: 385.14499 | Q9: 402.39383 | R9: 398.53207 | S9: 421.89496 | T9: 440.45383 | U9: 465.01849 | V9: 502.0437 | W9: 519.92114 | X9: 527.19287 | Y9: 512.67108 | Z9: 508.11087 | AA9: 511.39545 | AB9: 502.66962 | AC9: 509.82706 | AD9: 502.75842 | AE9: 516.5943 | AF9: 523.46216 | AG9: 0.029
A10: Total Gross Domestic Sales | B10: Electricity Trade: Gross Domestic Sales: Total: High Zero-Carbon Technology Cost | C10: AEO.2025.HIGHZTC.TRAD_TOT_ELEP_GDSE_SAL_NA_USA_BLNKWH.A | D10: BkWh | F10: 294.46338 | G10: 281.16812 | H10: 267.23379 | I10: 295.73062 | J10: 318.66809 | K10: 333.27387 | L10: 361.59625 | M10: 342.67523 | N10: 389.17938 | O10: 406.61569 | P10: 425.30133 | Q10: 441.86057 | R10: 437.30121 | S10: 459.79907 | T10: 477.52328 | U10: 501.03964 | V10: 536.95837 | W10: 553.86493 | X10: 560.04614 | Y10: 544.43384 | Z10: 539.12109 | AA10: 541.81415 | AB10: 532.51276 | AC10: 539.26929 | AD10: 531.79962 | AE10: 545.45532 | AF10: 552.20367 | AG10: 0.024
A11: Gross Domestic Sales (million 2024 dollars)
A12: Firm Power | B12: Electricity Trade: Gross Domestic Sales: Firm Power: High Zero-Carbon Technology Cost | C12: AEO.2025.HIGHZTC.KEI_FPW_ELEP_GDSE_SAL_NA_USA_MILLY13DLR.A | D12: million 2024 $ | F12: 3718.7073 | G12: 3565.7986 | H12: 3547.5679 | I12: 3528.7461 | J12: 3507.427 | K12: 3485.5107 | L12: 3463.3979 | M12: 3430.1152 | N12: 3396.8337 | O12: 3363.5518 | P12: 3309.4119 | Q12: 3252.5774 | R12: 3195.0867 | S12: 3123.7993 | T12: 3055.0083 | U12: 2968.6177 | V12: 2877.4314 | W12: 2797.4126 | X12: 2707.5398 | Y12: 2617.667 | Z12: 2555.6499 | AA12: 2506.9031 | AB12: 2459.4697 | AC12: 2426.4246 | AD12: 2393.3794 | AE12: 2378.5317 | AF12: 2368.6775 | AG12: -0.017
A13: Economy | B13: Electricity Trade: Gross Domestic Sales: Economy: High Zero-Carbon Technology Cost | C13: AEO.2025.HIGHZTC.KEI_ECN_ELEP_GDSE_SAL_NA_USA_MILLY13DLR.A | D13: million 2024 $ | F13: 10351.312 | G13: 8023.959 | H13: 7793.375 | I13: 8403.7236 | J13: 9362.542 | K13: 10238.698 | L13: 11769.411 | M13: 11374.511 | N13: 15617.239 | O13: 16802.051 | P13: 17691.258 | Q13: 18451.445 | R13: 17562.094 | S13: 17828.92 | T13: 18883.072 | U13: 19100.727 | V13: 20427.402 | W13: 22106.875 | X13: 22795.535 | Y13: 22820.969 | Z13: 23120.818 | AA13: 23484.168 | AB13: 23698.35 | AC13: 24435.113 | AD13: 24780.49 | AE13: 27138.383 | AF13: 28180.879 | AG13: 0.039
A14: Total Gross Domestic Sales | B14: Electricity Trade: Gross Domestic Sales: Total: High Zero-Carbon Technology Cost | C14: AEO.2025.HIGHZTC.KEI_TOT_ELEP_GDSE_SAL_NA_USA_MILLY13DLR.A | D14: million 2024 $ | F14: 14070.019 | G14: 11589.758 | H14: 11340.943 | I14: 11932.47 | J14: 12869.969 | K14: 13724.209 | L14: 15232.809 | M14: 14804.626 | N14: 19014.072 | O14: 20165.602 | P14: 21000.67 | Q14: 21704.023 | R14: 20757.18 | S14: 20952.719 | T14: 21938.08 | U14: 22069.344 | V14: 23304.834 | W14: 24904.287 | X14: 25503.074 | Y14: 25438.637 | Z14: 25676.469 | AA14: 25991.07 | AB14: 26157.82 | AC14: 26861.537 | AD14: 27173.869 | AE14: 29516.914 | AF14: 30549.557 | AG14: 0.03
A15: International Electricity Trade
A16: Imports from Canada and Mexico
A17: Firm Power | B17: Electricity Trade: Imports from Canada and Mexico: Firm Power: High Zero-Carbon Technology Cost | C17: AEO.2025.HIGHZTC.TRAD_FPW_ELEP_ICME_IMP_CANMEX_USA_BLNKWH.A | D17: BkWh | F17: 16.437441 | G17: 25.2062 | H17: 25.2062 | I17: 36.334553 | J17: 36.334553 | K17: 36.270779 | L17: 36.207008 | M17: 36.143234 | N17: 36.079464 | O17: 36.01569 | P17: 35.951916 | Q17: 35.888142 | R17: 35.545364 | S17: 35.48159 | T17: 35.41782 | U17: 35.41782 | V17: 35.41782 | W17: 35.41782 | X17: 35.41782 | Y17: 26.649057 | Z17: 26.649057 | AA17: 26.649057 | AB17: 26.649057 | AC17: 26.649057 | AD17: 26.649057 | AE17: 26.649057 | AF17: 26.649057 | AG17: 0.019
A18: Economy | B18: Electricity Trade: Imports from Canada and Mexico: Economy: High Zero-Carbon Technology Cost | C18: AEO.2025.HIGHZTC.TRAD_ECN_ELEP_ICME_IMP_CANMEX_USA_BLNKWH.A | D18: BkWh | F18: 29.155848 | G18: 25.677845 | H18: 32.730957 | I18: 39.317871 | J18: 51.182159 | K18: 56.444569 | L18: 64.044449 | M18: 66.023598 | N18: 67.974152 | O18: 70.4571 | P18: 71.004646 | Q18: 72.311829 | R18: 70.41851 | S18: 69.43647 | T18: 69.029602 | U18: 66.713844 | V18: 68.071274 | W18: 68.488014 | X18: 67.780701 | Y18: 70.681862 | Z18: 70.270073 | AA18: 69.597511 | AB18: 64.902161 | AC18: 61.668133 | AD18: 59.742859 | AE18: 56.808781 | AF18: 54.116707 | AG18: 0.024
A19: Total Imports from Canada and Mexico | B19: Electricity Trade: Imports from Canada and Mexico: Total: High Zero-Carbon Technology Cost | C19: AEO.2025.HIGHZTC.TRAD_TOT_ELEP_ICME_IMP_CANMEX_USA_BLNKWH.A | D19: BkWh | F19: 45.593288 | G19: 50.884045 | H19: 57.93716 | I19: 75.652428 | J19: 87.516708 | K19: 92.715347 | L19: 100.25146 | M19: 102.16683 | N19: 104.05361 | O19: 106.47279 | P19: 106.95656 | Q19: 108.19997 | R19: 105.96388 | S19: 104.91807 | T19: 104.44743 | U19: 102.13166 | V19: 103.4891 | W19: 103.90583 | X19: 103.19852 | Y19: 97.330917 | Z19: 96.919128 | AA19: 96.246567 | AB19: 91.551224 | AC19: 88.317192 | AD19: 86.391914 | AE19: 83.45784 | AF19: 80.765762 | AG19: 0.022
A20: Exports to Canada and Mexico
A21: Firm Power | B21: Electricity Trade: Exports to Canada and Mexico: Firm Power: High Zero-Carbon Technology Cost | C21: AEO.2025.HIGHZTC.TRAD_FPW_ELEP_EXCM_IMP_CANMEX_USA_BLNKWH.A | D21: BkWh | F21: 1.19574 | G21: 1.19574 | H21: 1.19574 | I21: 1.19574 | J21: 1.19574 | K21: 1.19574 | L21: 1.19574 | M21: 1.076166 | N21: 0.956592 | O21: 0.837018 | P21: 0.717444 | Q21: 0.59787 | R21: 0.478296 | S21: 0.358722 | T21: 0.239148 | U21: 0.119574 | V21: 0 | W21: 0 | X21: 0 | Y21: 0 | Z21: 0 | AA21: 0 | AB21: 0 | AC21: 0 | AD21: 0 | AE21: 0 | AF21: 0 | AG21: -1
A22: Economy | B22: Electricity Trade: Exports to Canada and Mexico: Economy: High Zero-Carbon Technology Cost | C22: AEO.2025.HIGHZTC.TRAD_ECN_ELEP_EXCM_IMP_CANMEX_USA_BLNKWH.A | D22: BkWh | F22: 14.989228 | G22: 14.989228 | H22: 14.989228 | I22: 14.989228 | J22: 14.989228 | K22: 14.989228 | L22: 14.989228 | M22: 15.108803 | N22: 15.228375 | O22: 15.34795 | P22: 15.467525 | Q22: 15.587098 | R22: 15.706673 | S22: 15.826247 | T22: 15.945821 | U22: 16.065393 | V22: 16.184969 | W22: 16.184969 | X22: 16.184969 | Y22: 16.184969 | Z22: 16.184969 | AA22: 16.184969 | AB22: 16.184969 | AC22: 16.184969 | AD22: 16.184969 | AE22: 16.184969 | AF22: 16.184969 | AG22: 0.003
A23: Total Exports to Canada and Mexico | B23: Electricity Trade: Exports to Canada and Mexico: Total: High Zero-Carbon Technology Cost | C23: AEO.2025.HIGHZTC.TRAD_TOT_ELEP_EXCM_IMP_CANMEX_USA_BLNKWH.A | D23: BkWh | F23: 16.184969 | G23: 16.184969 | H23: 16.184969 | I23: 16.184969 | J23: 16.184969 | K23: 16.184969 | L23: 16.184969 | M23: 16.184969 | N23: 16.184967 | O23: 16.184967 | P23: 16.184969 | Q23: 16.184969 | R23: 16.184969 | S23: 16.184969 | T23: 16.184969 | U23: 16.184969 | V23: 16.184969 | W23: 16.184969 | X23: 16.184969 | Y23: 16.184969 | Z23: 16.184969 | AA23: 16.184969 | AB23: 16.184969 | AC23: 16.184969 | AD23: 16.184969 | AE23: 16.184969 | AF23: 16.184969 | AG23: 0

Sheet Canada Generation Projection
A1: Select Report Version: Canada’s Energy Future 2021
A2: Select Appendices: Electricity Generation
A3: Select Case: Evolving Policies
A4: Select Type: Primary Fuel
A7: Canada
A8: _ | B8: 2005 | C8: 2006 | D8: 2007 | E8: 2008 | F8: 2009 | G8: 2010 | H8: 2011 | I8: 2012 | J8: 2013 | K8: 2014 | L8: 2015 | M8: 2016 | N8: 2017 | O8: 2018 | P8: 2019 | Q8: 2020 | R8: 2021 | S8: 2022 | T8: 2023 | U8: 2024 | V8: 2025 | W8: 2026 | X8: 2027 | Y8: 2028 | Z8: 2029 | AA8: 2030 | AB8: 2031 | AC8: 2032 | AD8: 2033 | AE8: 2034 | AF8: 2035 | AG8: 2036 | AH8: 2037 | AI8: 2038 | AJ8: 2039 | AK8: 2040 | AL8: 2041 | AM8: 2042 | AN8: 2043 | AO8: 2044 | AP8: 2045 | AQ8: 2046 | AR8: 2047 | AS8: 2048 | AT8: 2049 | AU8: 2050
A9: Hydro / Wave / Tidal | B9: 358380.8 | C9: 349124.5 | D9: 363798.5 | E9: 373817.3 | F9: 365011.8 | G9: 347937.5 | H9: 371953.2 | I9: 375760.2 | J9: 387396.2 | K9: 378786.2 | L9: 378498.4 | M9: 381710.1 | N9: 390771.5 | O9: 382163.9 | P9: 375998.3 | Q9: 386156.5 | R9: 392952.2 | S9: 414009.7 | T9: 419884.8 | U9: 420564 | V9: 426253.5 | W9: 426438 | X9: 426601.5 | Y9: 426631.5 | Z9: 426216.6 | AA9: 434736.9 | AB9: 435601.5 | AC9: 435569.8 | AD9: 435924.3 | AE9: 437012.9 | AF9: 437761.2 | AG9: 439366.8 | AH9: 440272.5 | AI9: 440771.5 | AJ9: 441186.3 | AK9: 441464.6 | AL9: 442329.7 | AM9: 442987.3 | AN9: 443420.1 | AO9: 443696.5 | AP9: 444111.5 | AQ9: 444504.2 | AR9: 445041.1 | AS9: 445453.3 | AT9: 445232.7 | AU9: 446455.8
A10: Wind | B10: 1453.41 | C10: 2529.41 | D10: 3683.41 | E10: 4715.44 | F10: 7031.23 | G10: 8354.23 | H10: 11622.99 | I10: 13716.78 | J10: 17544.74 | K10: 21484.5 | L10: 26692.57 | M10: 30624 | N10: 31197 | O10: 32814.01 | P10: 32333 | Q10: 35393.52 | R10: 37205.53 | S10: 48919.51 | T10: 49031.61 | U10: 52057.91 | V10: 54360.89 | W10: 54962.97 | X10: 62089.04 | Y10: 65911.72 | Z10: 70643.33 | AA10: 79872.47 | AB10: 86951.15 | AC10: 93863.48 | AD10: 94757.65 | AE10: 96735.03 | AF10: 98444.02 | AG10: 101702.69 | AH10: 105080.85 | AI10: 112793.77 | AJ10: 116892.24 | AK10: 124088.41 | AL10: 129402.83 | AM10: 138717.12 | AN10: 144897.52 | AO10: 155135.9 | AP10: 159912.83 | AQ10: 169032.28 | AR10: 173414.12 | AS10: 180922.35 | AT10: 184784.68 | AU10: 188617.4
A11: Biomass / Geothermal | B11: 6997.43 | C11: 7143.38 | D11: 6971.02 | E11: 6319.81 | F11: 6057.39 | G11: 8266.52 | H11: 8716.9 | I11: 9038.92 | J11: 9208.18 | K11: 11997.93 | L11: 8462.34 | M11: 10240.42 | N11: 6300.36 | O11: 9260.97 | P11: 8892.72 | Q11: 7758.32 | R11: 7918.38 | S11: 8085.39 | T11: 8145.5 | U11: 8172.13 | V11: 8203.73 | W11: 8229 | X11: 8180.23 | Y11: 8103.16 | Z11: 8045.48 | AA11: 7905.92 | AB11: 7834.53 | AC11: 7690.12 | AD11: 7689.75 | AE11: 7650.3 | AF11: 7634.06 | AG11: 7693.85 | AH11: 7715.96 | AI11: 7725.27 | AJ11: 7761.59 | AK11: 7755.49 | AL11: 7782.51 | AM11: 7774.67 | AN11: 7744.41 | AO11: 7721.08 | AP11: 7695.88 | AQ11: 7712.57 | AR11: 7701.84 | AS11: 7680.33 | AT11: 7670.09 | AU11: 7658.64
A12: Solar | B12: 0 | C12: 0 | D12: 0 | E12: 0 | F12: 5 | G12: 123 | H12: 398 | I12: 842 | J12: 1173 | K12: 1757.71 | L12: 1426 | M12: 1779 | N12: 2001 | O12: 2191 | P12: 2194 | Q12: 2254.11 | R12: 2590.53 | S12: 3479.48 | T12: 3729.67 | U12: 4101.36 | V12: 4339.71 | W12: 4948.63 | X12: 5294.32 | Y12: 5402.63 | Z12: 6775.5 | AA12: 7795.56 | AB12: 8732.41 | AC12: 9823.47 | AD12: 11227.58 | AE12: 12784.3 | AF12: 16546.83 | AG12: 18243.05 | AH12: 20134.38 | AI12: 22116.59 | AJ12: 24421.73 | AK12: 28835.14 | AL12: 32492.45 | AM12: 36514.71 | AN12: 41164.5 | AO12: 45590.8 | AP12: 51145.22 | AQ12: 54488.5 | AR12: 56975.57 | AS12: 58937.9 | AT12: 60762.67 | AU12: 62179.97
A13: Uranium | B13: 86668.58 | C13: 92144.58 | D13: 88190.58 | E13: 90585.23 | F13: 84992.27 | G13: 85526.59 | H13: 88291.22 | I13: 89487.62 | J13: 97581.99 | K13: 101207.8 | L13: 96045.98 | M13: 95687.01 | N13: 95565 | O13: 95029.01 | P13: 95470 | Q13: 83454.6 | R13: 78636.44 | S13: 81051.16 | T13: 69916.27 | U13: 80287.2 | V13: 73386.14 | W13: 68045.74 | X13: 74340.98 | Y13: 80779.09 | Z13: 75834.09 | AA13: 82677.41 | AB13: 75980.73 | AC13: 82824.05 | AD13: 82864.78 | AE13: 89708.09 | AF13: 91531.05 | AG13: 91531.05 | AH13: 91572.66 | AI13: 91572.66 | AJ13: 91655.88 | AK13: 91822.32 | AL13: 87048.12 | AM13: 87214.55 | AN13: 87381 | AO13: 92942.27 | AP13: 93150.33 | AQ13: 93566.44 | AR13: 94398.65 | AS13: 95230.82 | AT13: 96063.03 | AU13: 96063.03
A14: Coal & Coke | B14: 97362.16 | C14: 92204.69 | D14: 97287.24 | E14: 91097.93 | F14: 76661.64 | G14: 71258.57 | H14: 65177.45 | I14: 63091.11 | J14: 64779.21 | K14: 64238.38 | L14: 57142.41 | M14: 57243.38 | N14: 55265.55 | O14: 46520.81 | P14: 44038.21 | Q14: 31125.9 | R14: 35373.81 | S14: 19471.19 | T14: 5484.64 | U14: 5565.84 | V14: 4949.22 | W14: 4771.36 | X14: 4351.34 | Y14: 3905.76 | Z14: 3916.5 | AA14: 3738.32 | AB14: 3737.32 | AC14: 2584.93 | AD14: 2627.06 | AE14: 2645 | AF14: 2456.07 | AG14: 2499.37 | AH14: 2532.17 | AI14: 2500.78 | AJ14: 2120.31 | AK14: 2074.75 | AL14: 104.48 | AM14: 99.27 | AN14: 99.59 | AO14: 94.46 | AP14: 94.46 | AQ14: 90.07 | AR14: 90.72 | AS14: 86.92 | AT14: 87.73 | AU14: 88.62
A15: Natural Gas | B15: 40015.8 | C15: 43057.99 | D15: 47278.59 | E15: 43912.88 | F15: 42619.74 | G15: 54093.18 | H15: 63514.07 | I15: 63899.03 | J15: 60403.56 | K15: 59038.3 | L15: 65743.65 | M15: 63421.96 | N15: 62934.24 | O15: 66979.59 | P15: 69561.62 | Q15: 74470.26 | R15: 76989.41 | S15: 83922.45 | T15: 101916.1 | U15: 96186.95 | V15: 99728.41 | W15: 105182.5 | X15: 96821.06 | Y15: 93319.9 | Z15: 95666.85 | AA15: 88717.43 | AB15: 92233 | AC15: 85495.38 | AD15: 85813.2 | AE15: 82220.93 | AF15: 81566.97 | AG15: 70336.41 | AH15: 70043.93 | AI15: 68278.8 | AJ15: 68627.71 | AK15: 67198.62 | AL15: 67266.27 | AM15: 67505.6 | AN15: 68650.61 | AO15: 67873.7 | AP15: 68202.07 | AQ15: 67896.58 | AR15: 68472.27 | AS15: 68041.43 | AT15: 68614.28 | AU15: 69154.7
A16: Oil | B16: 8193.96 | C16: 7877.58 | D16: 8776.76 | E16: 6929.51 | F16: 7336.52 | G16: 5187.67 | H16: 4561.87 | I16: 4271.87 | J16: 4071.33 | K16: 6616.76 | L16: 5266.72 | M16: 5087.45 | N16: 4150.07 | O16: 4189.29 | P16: 3719.72 | Q16: 3511.56 | R16: 3358.75 | S16: 3196.07 | T16: 3370.57 | U16: 2789.51 | V16: 3529.05 | W16: 6677.83 | X16: 4558.28 | Y16: 3428.4 | Z16: 5989.77 | AA16: 2608.05 | AB16: 7298.25 | AC16: 4931.98 | AD16: 5902.13 | AE16: 4773.99 | AF16: 4550.53 | AG16: 6077.36 | AH16: 5635.85 | AI16: 5525.19 | AJ16: 5859.8 | AK16: 5233.61 | AL16: 7917.99 | AM16: 5884.44 | AN16: 6604.3 | AO16: 4278.48 | AP16: 4863.56 | AQ16: 4581.3 | AR16: 4987.65 | AS16: 4371.99 | AT16: 4825.29 | AU16: 5720.7
A18: Newfoundland and Labrador
A19: _ | B19: 2005 | C19: 2006 | D19: 2007 | E19: 2008 | F19: 2009 | G19: 2010 | H19: 2011 | I19: 2012 | J19: 2013 | K19: 2014 | L19: 2015 | M19: 2016 | N19: 2017 | O19: 2018 | P19: 2019 | Q19: 2020 | R19: 2021 | S19: 2022 | T19: 2023 | U19: 2024 | V19: 2025 | W19: 2026 | X19: 2027 | Y19: 2028 | Z19: 2029 | AA19: 2030 | AB19: 2031 | AC19: 2032 | AD19: 2033 | AE19: 2034 | AF19: 2035 | AG19: 2036 | AH19: 2037 | AI19: 2038 | AJ19: 2039 | AK19: 2040 | AL19: 2041 | AM19: 2042 | AN19: 2043 | AO19: 2044 | AP19: 2045 | AQ19: 2046 | AR19: 2047 | AS19: 2048 | AT19: 2049 | AU19: 2050
A20: Hydro / Wave / Tidal | B20: 40741.37 | C20: 41953.37 | D20: 40291.38 | E20: 41897.25 | F20: 36728 | G20: 40286.8 | H20: 40033.37 | I20: 42202.52 | J20: 41441.68 | K20: 39047.83 | L20: 39686 | M20: 39482.99 | N20: 36548 | O20: 41831 | P20: 40798 | Q20: 44285.91 | R20: 50459.12 | S20: 51302.94 | T20: 51450.95 | U20: 51596.33 | V20: 51687.53 | W20: 51766.57 | X20: 51847.05 | Y20: 52209.73 | Z20: 52221 | AA20: 52233.74 | AB20: 52247.11 | AC20: 52260.72 | AD20: 52273.37 | AE20: 52285.32 | AF20: 52368.24 | AG20: 52433.39 | AH20: 52442.84 | AI20: 52449.65 | AJ20: 52447.73 | AK20: 52450.65 | AL20: 52451.59 | AM20: 52454.57 | AN20: 52458.66 | AO20: 52458.86 | AP20: 52458.86 | AQ20: 52458.83 | AR20: 52458.85 | AS20: 52458.8 | AT20: 52458.82 | AU20: 52458.85
A21: Wind | B21: 0 | C21: 0 | D21: 0 | E21: 0 | F21: 102 | G21: 183 | H21: 198 | I21: 195 | J21: 192 | K21: 176.96 | L21: 172 | M21: 190 | N21: 186 | O21: 206 | P21: 182 | Q21: 181.8 | R21: 181.83 | S21: 181.91 | T21: 181.92 | U21: 181.93 | V21: 181.94 | W21: 182 | X21: 182.01 | Y21: 182.09 | Z21: 182.15 | AA21: 183.78 | AB21: 185.55 | AC21: 187.48 | AD21: 189.59 | AE21: 192.37 | AF21: 215.04 | AG21: 228.5 | AH21: 244.79 | AI21: 261.79 | AJ21: 285.81 | AK21: 319.59 | AL21: 371.08 | AM21: 442.3 | AN21: 536.27 | AO21: 643.33 | AP21: 759.27 | AQ21: 860.06 | AR21: 917.13 | AS21: 945.68 | AT21: 967.35 | AU21: 982.55
A22: Biomass / Geothermal | B22: 0 | C22: 0 | D22: 0 | E22: 0 | F22: 0 | G22: 0 | H22: 0 | I22: 0 | J22: 0 | K22: 0 | L22: 0 | M22: 0 | N22: 0 | O22: 0 | P22: 0 | Q22: 0 | R22: 0 | S22: 0 | T22: 0 | U22: 0 | V22: 0 | W22: 0 | X22: 0 | Y22: 0 | Z22: 0 | AA22: 0 | AB22: 0 | AC22: 0 | AD22: 0 | AE22: 0 | AF22: 0 | AG22: 0 | AH22: 0 | AI22: 0 | AJ22: 0 | AK22: 0 | AL22: 0 | AM22: 0 | AN22: 0 | AO22: 0 | AP22: 0 | AQ22: 0 | AR22: 0 | AS22: 0 | AT22: 0 | AU22: 0
A23: Solar | B23: 0 | C23: 0 | D23: 0 | E23: 0 | F23: 0 | G23: 0 | H23: 0 | I23: 0 | J23: 0 | K23: 0 | L23: 0 | M23: 0 | N23: 0 | O23: 0 | P23: 0 | Q23: 0 | R23: 0 | S23: 0 | T23: 0 | U23: 0 | V23: 0 | W23: 0 | X23: 0 | Y23: 0 | Z23: 0 | AA23: 0 | AB23: 0 | AC23: 0 | AD23: 0 | AE23: 0 | AF23: 0 | AG23: 0 | AH23: 0 | AI23: 0 | AJ23: 0 | AK23: 0 | AL23: 0 | AM23: 0 | AN23: 0 | AO23: 0 | AP23: 0 | AQ23: 0 | AR23: 0 | AS23: 0 | AT23: 0 | AU23: 0
A24: Uranium | B24: 0 | C24: 0 | D24: 0 | E24: 0 | F24: 0 | G24: 0 | H24: 0 | I24: 0 | J24: 0 | K24: 0 | L24: 0 | M24: 0 | N24: 0 | O24: 0 | P24: 0 | Q24: 0 | R24: 0 | S24: 0 | T24: 0 | U24: 0 | V24: 0 | W24: 0 | X24: 0 | Y24: 0 | Z24: 0 | AA24: 0 | AB24: 0 | AC24: 0 | AD24: 0 | AE24: 0 | AF24: 0 | AG24: 0 | AH24: 0 | AI24: 0 | AJ24: 0 | AK24: 0 | AL24: 0 | AM24: 0 | AN24: 0 | AO24: 0 | AP24: 0 | AQ24: 0 | AR24: 0 | AS24: 0 | AT24: 0 | AU24: 0
A25: Coal & Coke | B25: 0 | C25: 0 | D25: 0 | E25: 0 | F25: 0 | G25: 0 | H25: 0 | I25: 0 | J25: 0 | K25: 0 | L25: 0 | M25: 0 | N25: 0 | O25: 0 | P25: 0 | Q25: 0 | R25: 0 | S25: 0 | T25: 0 | U25: 0 | V25: 0 | W25: 0 | X25: 0 | Y25: 0 | Z25: 0 | AA25: 0 | AB25: 0 | AC25: 0 | AD25: 0 | AE25: 0 | AF25: 0 | AG25: 0 | AH25: 0 | AI25: 0 | AJ25: 0 | AK25: 0 | AL25: 0 | AM25: 0 | AN25: 0 | AO25: 0 | AP25: 0 | AQ25: 0 | AR25: 0 | AS25: 0 | AT25: 0 | AU25: 0
A26: Natural Gas | B26: 267.07 | C26: 277.82 | D26: 236.77 | E26: 456.94 | F26: 447.62 | G26: 454.97 | H26: 449.29 | I26: 418.8 | J26: 444.36 | K26: 416.68 | L26: 225.22 | M26: 265.72 | N26: 391.17 | O26: 113.27 | P26: 263.31 | Q26: 398.28 | R26: 413.95 | S26: 452.33 | T26: 458.89 | U26: 516.14 | V26: 555.08 | W26: 595.08 | X26: 630.86 | Y26: 341.65 | Z26: 350.7 | AA26: 361.93 | AB26: 370.79 | AC26: 385.85 | AD26: 403.13 | AE26: 422.53 | AF26: 488.69 | AG26: 560.97 | AH26: 566.85 | AI26: 569.88 | AJ26: 566.48 | AK26: 579.49 | AL26: 610.58 | AM26: 657.46 | AN26: 748.67 | AO26: 858.39 | AP26: 1003.78 | AQ26: 1145.14 | AR26: 1243.72 | AS26: 1317.47 | AT26: 1380.75 | AU26: 1413.07
A27: Oil | B27: 1306.21 | C27: 823.06 | D27: 1305.52 | E27: 1139.06 | F27: 1121.59 | G27: 1017.23 | H27: 1039.36 | I27: 998.93 | J27: 1179.72 | K27: 1595.16 | L27: 1669.78 | M27: 1909.28 | N27: 1778.83 | O27: 1483.73 | P27: 1450.69 | Q27: 926.58 | R27: 884.98 | S27: 183.79 | T27: 182.88 | U27: 184.15 | V27: 184.94 | W27: 211.07 | X27: 188.64 | Y27: 190.04 | Z27: 215.06 | AA27: 189.72 | AB27: 240.78 | AC27: 221.96 | AD27: 268.66 | AE27: 227.23 | AF27: 340.15 | AG27: 191.32 | AH27: 219.22 | AI27: 191.44 | AJ27: 204.18 | AK27: 190.3 | AL27: 220.29 | AM27: 185.71 | AN27: 190.24 | AO27: 191.16 | AP27: 194.79 | AQ27: 191.76 | AR27: 191.16 | AS27: 190.61 | AT27: 190.04 | AU27: 189.45
A29: Prince Edward Island
A30: _ | B30: 2005 | C30: 2006 | D30: 2007 | E30: 2008 | F30: 2009 | G30: 2010 | H30: 2011 | I30: 2012 | J30: 2013 | K30: 2014 | L30: 2015 | M30: 2016 | N30: 2017 | O30: 2018 | P30: 2019 | Q30: 2020 | R30: 2021 | S30: 2022 | T30: 2023 | U30: 2024 | V30: 2025 | W30: 2026 | X30: 2027 | Y30: 2028 | Z30: 2029 | AA30: 2030 | AB30: 2031 | AC30: 2032 | AD30: 2033 | AE30: 2034 | AF30: 2035 | AG30: 2036 | AH30: 2037 | AI30: 2038 | AJ30: 2039 | AK30: 2040 | AL30: 2041 | AM30: 2042 | AN30: 2043 | AO30: 2044 | AP30: 2045 | AQ30: 2046 | AR30: 2047 | AS30: 2048 | AT30: 2049 | AU30: 2050
A31: Hydro / Wave / Tidal | B31: 0 | C31: 0 | D31: 0 | E31: 0 | F31: 0 | G31: 0 | H31: 0 | I31: 0 | J31: 0 | K31: 0 | L31: 0 | M31: 0 | N31: 0 | O31: 0 | P31: 0 | Q31: 0 | R31: 0 | S31: 0 | T31: 0 | U31: 0 | V31: 0 | W31: 0 | X31: 0 | Y31: 0 | Z31: 0 | AA31: 0 | AB31: 0 | AC31: 0 | AD31: 0 | AE31: 0 | AF31: 0 | AG31: 0 | AH31: 0 | AI31: 0 | AJ31: 0 | AK31: 0 | AL31: 0 | AM31: 0 | AN31: 0 | AO31: 0 | AP31: 0 | AQ31: 0 | AR31: 0 | AS31: 0 | AT31: 0 | AU31: 0
A32: Wind | B32: 40 | C32: 36 | D32: 40 | E32: 142 | F32: 347 | G32: 458 | H32: 488 | I32: 468 | J32: 499 | K32: 611.28 | L32: 606 | M32: 594 | N32: 604 | O32: 640 | P32: 645 | Q32: 677.27 | R32: 940.07 | S32: 940.02 | T32: 947.11 | U32: 955.04 | V32: 1226.21 | W32: 1234.87 | X32: 1243.91 | Y32: 1253.13 | Z32: 1262.74 | AA32: 1539.39 | AB32: 1553.64 | AC32: 1568.21 | AD32: 1583.18 | AE32: 1598.55 | AF32: 1614.34 | AG32: 1630.47 | AH32: 1646.86 | AI32: 1663.7 | AJ32: 1680.8 | AK32: 1698.19 | AL32: 1715.94 | AM32: 1733.89 | AN32: 1752.17 | AO32: 1770.74 | AP32: 1789.25 | AQ32: 1807.9 | AR32: 1826.81 | AS32: 1846.04 | AT32: 1865.54 | AU32: 1885.59
A33: Biomass / Geothermal | B33: 0 | C33: 0 | D33: 0 | E33: 5 | F33: 5 | G33: 5 | H33: 5 | I33: 5 | J33: 5 | K33: 2.5 | L33: 3 | M33: 3 | N33: 2 | O33: 2 | P33: 3 | Q33: 3 | R33: 3 | S33: 3 | T33: 3 | U33: 3.53 | V33: 3.53 | W33: 3.53 | X33: 3.53 | Y33: 3.53 | Z33: 3.53 | AA33: 3.53 | AB33: 3.53 | AC33: 3.53 | AD33: 3.53 | AE33: 3.53 | AF33: 3.53 | AG33: 3.53 | AH33: 3.53 | AI33: 3.53 | AJ33: 3.53 | AK33: 3.53 | AL33: 3.53 | AM33: 3.53 | AN33: 3.53 | AO33: 3.53 | AP33: 3.53 | AQ33: 4.49 | AR33: 4.49 | AS33: 4.49 | AT33: 4.49 | AU33: 4.49
A34: Solar | B34: 0 | C34: 0 | D34: 0 | E34: 0 | F34: 0 | G34: 0 | H34: 0 | I34: 0 | J34: 0 | K34: 0 | L34: 0 | M34: 0 | N34: 0 | O34: 0 | P34: 0 | Q34: 0 | R34: 0 | S34: 3.65 | T34: 3.65 | U34: 7.98 | V34: 12.49 | W34: 17.15 | X34: 21.95 | Y34: 26.92 | Z34: 32.03 | AA34: 37.27 | AB34: 42.65 | AC34: 48.13 | AD34: 53.76 | AE34: 59.49 | AF34: 65.34 | AG34: 71.28 | AH34: 77.32 | AI34: 83.44 | AJ34: 89.63 | AK34: 95.9 | AL34: 102.24 | AM34: 108.64 | AN34: 115.07 | AO34: 121.46 | AP34: 127.83 | AQ34: 134.23 | AR34: 140.73 | AS34: 147.25 | AT34: 153.86 | AU34: 160.61
A35: Uranium | B35: 0 | C35: 0 | D35: 0 | E35: 0 | F35: 0 | G35: 0 | H35: 0 | I35: 0 | J35: 0 | K35: 0 | L35: 0 | M35: 0 | N35: 0 | O35: 0 | P35: 0 | Q35: 0 | R35: 0 | S35: 0 | T35: 0 | U35: 0 | V35: 0 | W35: 0 | X35: 0 | Y35: 0 | Z35: 0 | AA35: 0 | AB35: 0 | AC35: 0 | AD35: 0 | AE35: 0 | AF35: 0 | AG35: 0 | AH35: 0 | AI35: 0 | AJ35: 0 | AK35: 0 | AL35: 0 | AM35: 0 | AN35: 0 | AO35: 0 | AP35: 0 | AQ35: 0 | AR35: 0 | AS35: 0 | AT35: 0 | AU35: 0
A36: Coal & Coke | B36: 0 | C36: 0 | D36: 0 | E36: 0 | F36: 0 | G36: 0 | H36: 0 | I36: 0 | J36: 0 | K36: 0 | L36: 0 | M36: 0 | N36: 0 | O36: 0 | P36: 0 | Q36: 0 | R36: 0 | S36: 0 | T36: 0 | U36: 0 | V36: 0 | W36: 0 | X36: 0 | Y36: 0 | Z36: 0 | AA36: 0 | AB36: 0 | AC36: 0 | AD36: 0 | AE36: 0 | AF36: 0 | AG36: 0 | AH36: 0 | AI36: 0 | AJ36: 0 | AK36: 0 | AL36: 0 | AM36: 0 | AN36: 0 | AO36: 0 | AP36: 0 | AQ36: 0 | AR36: 0 | AS36: 0 | AT36: 0 | AU36: 0
A37: Natural Gas | B37: 0 | C37: 0 | D37: 0 | E37: 0 | F37: 0 | G37: 0 | H37: 0 | I37: 0 | J37: 0 | K37: 0 | L37: 0 | M37: 0 | N37: 0 | O37: 0 | P37: 0 | Q37: 0 | R37: 0 | S37: 0 | T37: 0 | U37: 0 | V37: 0 | W37: 0 | X37: 0 | Y37: 0 | Z37: 0 | AA37: 0 | AB37: 0 | AC37: 0 | AD37: 0 | AE37: 0 | AF37: 0 | AG37: 0 | AH37: 0 | AI37: 0 | AJ37: 0 | AK37: 0 | AL37: 0 | AM37: 0 | AN37: 0 | AO37: 0 | AP37: 0 | AQ37: 0 | AR37: 0 | AS37: 0 | AT37: 0 | AU37: 0
A38: Oil | B38: 0.88 | C38: 0.88 | D38: 0.88 | E38: 0.48 | F38: 2.72 | G38: 0 | H38: 0 | I38: 8.16 | J38: 2.17 | K38: 5.8 | L38: 7 | M38: 7 | N38: 7 | O38: 6 | P38: 3 | Q38: 18.79 | R38: 18.79 | S38: 48.27 | T38: 27.62 | U38: 27.62 | V38: 18.95 | W38: 53.14 | X38: 18.79 | Y38: 17.81 | Z38: 17.83 | AA38: 9.78 | AB38: 45.33 | AC38: 45.33 | AD38: 39.78 | AE38: 9.95 | AF38: 28.75 | AG38: 1.1 | AH38: 1.1 | AI38: 1.1 | AJ38: 1.1 | AK38: 1.1 | AL38: 485.2 | AM38: 339.03 | AN38: 342 | AO38: 45.15 | AP38: 48.27 | AQ38: 48.27 | AR38: 48.27 | AS38: 48.27 | AT38: 48.27 | AU38: 48.27
A40: Nova Scotia
A41: _ | B41: 2005 | C41: 2006 | D41: 2007 | E41: 2008 | F41: 2009 | G41: 2010 | H41: 2011 | I41: 2012 | J41: 2013 | K41: 2014 | L41: 2015 | M41: 2016 | N41: 2017 | O41: 2018 | P41: 2019 | Q41: 2020 | R41: 2021 | S41: 2022 | T41: 2023 | U41: 2024 | V41: 2025 | W41: 2026 | X41: 2027 | Y41: 2028 | Z41: 2029 | AA41: 2030 | AB41: 2031 | AC41: 2032 | AD41: 2033 | AE41: 2034 | AF41: 2035 | AG41: 2036 | AH41: 2037 | AI41: 2038 | AJ41: 2039 | AK41: 2040 | AL41: 2041 | AM41: 2042 | AN41: 2043 | AO41: 2044 | AP41: 2045 | AQ41: 2046 | AR41: 2047 | AS41: 2048 | AT41: 2049 | AU41: 2050
A42: Hydro / Wave / Tidal | B42: 926.06 | C42: 926.06 | D42: 926.06 | E42: 1096.66 | F42: 1074.14 | G42: 1007.81 | H42: 1112.47 | I42: 851.5 | J42: 1005.76 | K42: 1128.69 | L42: 979.2 | M42: 779.28 | N42: 824.89 | O42: 910.29 | P42: 1001.52 | Q42: 1001.51 | R42: 1001.53 | S42: 1001.5 | T42: 1001.5 | U42: 1001.53 | V42: 1001.51 | W42: 1001.51 | X42: 1001.53 | Y42: 1001.53 | Z42: 1001.53 | AA42: 1001.52 | AB42: 1001.52 | AC42: 1001.5 | AD42: 1001.52 | AE42: 1001.51 | AF42: 1001.52 | AG42: 1001.51 | AH42: 1001.52 | AI42: 1001.52 | AJ42: 1001.51 | AK42: 1001.53 | AL42: 1001.52 | AM42: 1001.52 | AN42: 1001.52 | AO42: 1001.52 | AP42: 1001.52 | AQ42: 1054.08 | AR42: 1105.85 | AS42: 1157.18 | AT42: 1207.82 | AU42: 1207.82
A43: Wind | B43: 85 | C43: 110 | D43: 157 | E43: 149 | F43: 154 | G43: 387 | H43: 664.19 | I43: 800 | J43: 765 | K43: 748.68 | L43: 803.57 | M43: 999 | N43: 1309 | O43: 1153 | P43: 1057 | Q43: 1056.93 | R43: 1057.31 | S43: 1058.1 | T43: 1101.22 | U43: 1102.26 | V43: 1147.93 | W43: 1193.73 | X43: 1239.51 | Y43: 1285.7 | Z43: 1332.66 | AA43: 1418.81 | AB43: 1506.32 | AC43: 1595.13 | AD43: 1686.43 | AE43: 1779.67 | AF43: 1875.69 | AG43: 1925.17 | AH43: 1978.23 | AI43: 2084.07 | AJ43: 2200.23 | AK43: 2327.44 | AL43: 2459.51 | AM43: 2603.59 | AN43: 2754.38 | AO43: 2902.41 | AP43: 3041.06 | AQ43: 3233.53 | AR43: 3422.88 | AS43: 3615.59 | AT43: 3810.58 | AU43: 3954
A44: Biomass / Geothermal | B44: 318 | C44: 318 | D44: 318 | E44: 322 | F44: 245 | G44: 378 | H44: 363 | I44: 387 | J44: 331 | K44: 253.9 | L44: 427 | M44: 395 | N44: 288 | O44: 487 | P44: 314 | Q44: 233.04 | R44: 265.93 | S44: 269.06 | T44: 265.93 | U44: 265.93 | V44: 264.62 | W44: 265.39 | X44: 265.93 | Y44: 264.06 | Z44: 264.06 | AA44: 264.06 | AB44: 264.06 | AC44: 210.35 | AD44: 210.35 | AE44: 210.35 | AF44: 210.35 | AG44: 210.35 | AH44: 210.35 | AI44: 210.35 | AJ44: 210.35 | AK44: 210.35 | AL44: 241.52 | AM44: 229.88 | AN44: 212.53 | AO44: 212.53 | AP44: 203.34 | AQ44: 195.92 | AR44: 196.96 | AS44: 198.8 | AT44: 200.63 | AU44: 200.63
A45: Solar | B45: 0 | C45: 0 | D45: 0 | E45: 0 | F45: 0 | G45: 0 | H45: 0 | I45: 0 | J45: 0 | K45: 0 | L45: 0 | M45: 0 | N45: 0 | O45: 0 | P45: 0 | Q45: 0 | R45: 0.22 | S45: 0.61 | T45: 1.03 | U45: 1.36 | V45: 1.78 | W45: 2.22 | X45: 2.64 | Y45: 3.06 | Z45: 3.5 | AA45: 4 | AB45: 4.56 | AC45: 5.84 | AD45: 7.2 | AE45: 26.8 | AF45: 28.92 | AG45: 31.78 | AH45: 35.59 | AI45: 58.67 | AJ45: 84.44 | AK45: 112.89 | AL45: 155.86 | AM45: 199.26 | AN45: 243.6 | AO45: 286.18 | AP45: 325.41 | AQ45: 362.55 | AR45: 400.36 | AS45: 441.67 | AT45: 485.07 | AU45: 528.46
A46: Uranium | B46: 0 | C46: 0 | D46: 0 | E46: 0 | F46: 0 | G46: 0 | H46: 0 | I46: 0 | J46: 0 | K46: 0 | L46: 0 | M46: 0 | N46: 0 | O46: 0 | P46: 0 | Q46: 0 | R46: 0 | S46: 0 | T46: 0 | U46: 0 | V46: 0 | W46: 0 | X46: 0 | Y46: 0 | Z46: 0 | AA46: 0 | AB46: 0 | AC46: 0 | AD46: 0 | AE46: 0 | AF46: 0 | AG46: 0 | AH46: 0 | AI46: 0 | AJ46: 0 | AK46: 0 | AL46: 0 | AM46: 0 | AN46: 0 | AO46: 0 | AP46: 0 | AQ46: 0 | AR46: 0 | AS46: 0 | AT46: 0 | AU46: 0
A47: Coal & Coke | B47: 8374.98 | C47: 8119.94 | D47: 8768.63 | E47: 8765.97 | F47: 7688.15 | G47: 7492.97 | H47: 6494.95 | I47: 6173.75 | J47: 6848.48 | K47: 5521.82 | L47: 4854.08 | M47: 4812.21 | N47: 4829.16 | O47: 4959.76 | P47: 4972.72 | Q47: 3725.57 | R47: 3842.88 | S47: 4108.59 | T47: 3869.49 | U47: 3950.68 | V47: 3334.07 | W47: 3378.63 | X47: 3380.7 | Y47: 3373.67 | Z47: 3384.41 | AA47: 3372.76 | AB47: 3406.32 | AC47: 2280.76 | AD47: 2323.83 | AE47: 2346.05 | AF47: 2158.25 | AG47: 2200.01 | AH47: 2233.2 | AI47: 2215.13 | AJ47: 1834.74 | AK47: 1799.29 | AL47: 0 | AM47: 0 | AN47: 0 | AO47: 0 | AP47: 0 | AQ47: 0 | AR47: 0 | AS47: 0 | AT47: 0 | AU47: 0
A48: Natural Gas | B48: 165.12 | C48: 354.87 | D48: 804.62 | E48: 1158.91 | F48: 1489.51 | G48: 2111.4 | H48: 2260.78 | I48: 2103.87 | J48: 1291.85 | K48: 1363.72 | L48: 2630.25 | M48: 2462.57 | N48: 2564.71 | O48: 2328.57 | P48: 2106.49 | Q48: 1156.43 | R48: 1090.7 | S48: 978.09 | T48: 1059.95 | U48: 880.78 | V48: 1474.43 | W48: 1419.39 | X48: 1414.75 | Y48: 1412.63 | Z48: 1411.56 | AA48: 1410.32 | AB48: 1407.75 | AC48: 2757.85 | AD48: 2798.09 | AE48: 2828.68 | AF48: 3047.81 | AG48: 3084.37 | AH48: 3118.41 | AI48: 3124.29 | AJ48: 3404.56 | AK48: 3398.26 | AL48: 3447.3 | AM48: 3386.2 | AN48: 3323.85 | AO48: 3253.48 | AP48: 3169.65 | AQ48: 3094.09 | AR48: 3047.93 | AS48: 2990.62 | AT48: 2930.7 | AU48: 2932.47
A49: Oil | B49: 1911.5 | C49: 1624.09 | D49: 1586.95 | E49: 708.16 | F49: 1014.59 | G49: 563.73 | H49: 693.24 | I49: 762.46 | J49: 512.59 | K49: 1608.56 | L49: 491.61 | M49: 348.22 | N49: 247.13 | O49: 309.67 | P49: 207.79 | Q49: 78.3 | R49: 98.34 | S49: 76.68 | T49: 150.4 | U49: 171.31 | V49: 137.75 | W49: 150.11 | X49: 152.65 | Y49: 156.13 | Z49: 160.62 | AA49: 163.81 | AB49: 169.88 | AC49: 46.27 | AD49: 57.77 | AE49: 65.05 | AF49: 113.32 | AG49: 118.6 | AH49: 122.92 | AI49: 119.62 | AJ49: 176.02 | AK49: 160.7 | AL49: 798.22 | AM49: 756.95 | AN49: 698.56 | AO49: 632.3 | AP49: 558.49 | AQ49: 559.81 | AR49: 497.69 | AS49: 438.72 | AT49: 407.32 | AU49: 407.56
A51: New Brunswick
A52: _ | B52: 2005 | C52: 2006 | D52: 2007 | E52: 2008 | F52: 2009 | G52: 2010 | H52: 2011 | I52: 2012 | J52: 2013 | K52: 2014 | L52: 2015 | M52: 2016 | N52: 2017 | O52: 2018 | P52: 2019 | Q52: 2020 | R52: 2021 | S52: 2022 | T52: 2023 | U52: 2024 | V52: 2025 | W52: 2026 | X52: 2027 | Y52: 2028 | Z52: 2029 | AA52: 2030 | AB52: 2031 | AC52: 2032 | AD52: 2033 | AE52: 2034 | AF52: 2035 | AG52: 2036 | AH52: 2037 | AI52: 2038 | AJ52: 2039 | AK52: 2040 | AL52: 2041 | AM52: 2042 | AN52: 2043 | AO52: 2044 | AP52: 2045 | AQ52: 2046 | AR52: 2047 | AS52: 2048 | AT52: 2049 | AU52: 2050
A53: Hydro / Wave / Tidal | B53: 3875 | C53: 3731 | D53: 2793.76 | E53: 3536.09 | F53: 2964.24 | G53: 3325.35 | H53: 3921.29 | I53: 2957.28 | J53: 3410.31 | K53: 2963.11 | L53: 2615 | M53: 3262 | N53: 2597 | O53: 2535 | P53: 2994 | Q53: 2994.02 | R53: 2993.98 | S53: 2993.98 | T53: 2994.01 | U53: 3033.23 | V53: 3033.24 | W53: 3033.24 | X53: 3033.24 | Y53: 3033.25 | Z53: 3033.25 | AA53: 3033.26 | AB53: 3033.23 | AC53: 3033.26 | AD53: 3033.23 | AE53: 3033.23 | AF53: 3033.27 | AG53: 3033.23 | AH53: 3033.25 | AI53: 3033.26 | AJ53: 3033.25 | AK53: 3033.23 | AL53: 3033.23 | AM53: 3033.25 | AN53: 3033.23 | AO53: 3033.24 | AP53: 3033.25 | AQ53: 3063.65 | AR53: 3093.78 | AS53: 3123.73 | AT53: 3123.74 | AU53: 3123.74
A54: Wind | B54: 0 | C54: 0 | D54: 0 | E54: 0 | F54: 270 | G54: 389 | H54: 693 | I54: 733 | J54: 737 | K54: 785.85 | L54: 792 | M54: 766 | N54: 781 | O54: 825 | P54: 888 | Q54: 888.01 | R54: 1030.39 | S54: 1153.45 | T54: 1188.75 | U54: 1222.44 | V54: 1255.77 | W54: 1289.03 | X54: 1322.22 | Y54: 1355.24 | Z54: 1388.23 | AA54: 1421.09 | AB54: 1453.85 | AC54: 1486.77 | AD54: 1624.79 | AE54: 1657.67 | AF54: 1749.22 | AG54: 1808.8 | AH54: 1870.01 | AI54: 1934.38 | AJ54: 2014.28 | AK54: 2117.09 | AL54: 2232.51 | AM54: 2390.03 | AN54: 2602.89 | AO54: 2890.01 | AP54: 3179.19 | AQ54: 3449.43 | AR54: 3613.69 | AS54: 3710.42 | AT54: 3736.47 | AU54: 3743.52
A55: Biomass / Geothermal | B55: 610 | C55: 610 | D55: 562 | E55: 647 | F55: 576 | G55: 585 | H55: 569 | I55: 579 | J55: 558 | K55: 474.7 | L55: 309 | M55: 328 | N55: 270 | O55: 508 | P55: 505 | Q55: 505 | R55: 505 | S55: 505 | T55: 505 | U55: 505 | V55: 505 | W55: 505 | X55: 505 | Y55: 505 | Z55: 505 | AA55: 505 | AB55: 505 | AC55: 505 | AD55: 505 | AE55: 505 | AF55: 505 | AG55: 505 | AH55: 505 | AI55: 505 | AJ55: 505 | AK55: 505 | AL55: 505 | AM55: 505 | AN55: 505 | AO55: 505 | AP55: 505 | AQ55: 509.39 | AR55: 509.39 | AS55: 509.39 | AT55: 509.39 | AU55: 509.39
A56: Solar | B56: 0 | C56: 0 | D56: 0 | E56: 0 | F56: 0 | G56: 0 | H56: 0 | I56: 0 | J56: 0 | K56: 0 | L56: 0 | M56: 0 | N56: 0 | O56: 0 | P56: 0 | Q56: 0 | R56: 0.14 | S56: 18.43 | T56: 18.68 | U56: 35.58 | V56: 105.26 | W56: 122.26 | X56: 139.28 | Y56: 156.21 | Z56: 172.99 | AA56: 189.78 | AB56: 206.31 | AC56: 222.86 | AD56: 239.36 | AE56: 255.74 | AF56: 291.57 | AG56: 317.96 | AH56: 345.06 | AI56: 370.1 | AJ56: 399.79 | AK56: 436.37 | AL56: 531.71 | AM56: 649.07 | AN56: 787.77 | AO56: 829.47 | AP56: 903.32 | AQ56: 974.54 | AR56: 1012.77 | AS56: 1033.11 | AT56: 1040.92 | AU56: 1042.67
A57: Uranium | B57: 4378 | C57: 4366 | D57: 4119 | E57: 1129 | F57: 0 | G57: 0 | H57: 0 | I57: 409 | J57: 4479 | K57: 5012.22 | L57: 4277 | M57: 4545 | N57: 5120 | O57: 4874 | P57: 5016 | Q57: 4940.64 | R57: 4940.64 | S57: 4940.64 | T57: 4940.64 | U57: 4940.64 | V57: 4940.64 | W57: 4940.64 | X57: 4940.64 | Y57: 4940.64 | Z57: 4940.64 | AA57: 4940.64 | AB57: 4940.64 | AC57: 4940.64 | AD57: 4940.64 | AE57: 4940.64 | AF57: 4940.64 | AG57: 4940.64 | AH57: 4940.64 | AI57: 4940.64 | AJ57: 4940.64 | AK57: 4940.64 | AL57: 0 | AM57: 0 | AN57: 0 | AO57: 5353.22 | AP57: 5353.23 | AQ57: 5353.25 | AR57: 5353.25 | AS57: 5353.23 | AT57: 5353.25 | AU57: 5353.24
A58: Coal & Coke | B58: 3101.05 | C58: 3107.93 | D58: 3093.98 | E58: 3127.39 | F58: 3123.34 | G58: 2308.09 | H58: 2613.65 | I58: 2110.21 | J58: 2612.52 | K58: 3100.21 | L58: 1734.25 | M58: 2206.12 | N58: 2106.72 | O58: 2351.71 | P58: 1831.15 | Q58: 2138.6 | R58: 2138.6 | S58: 2138.6 | T58: 171.09 | U58: 171.09 | V58: 171.09 | W58: 171.09 | X58: 171.09 | Y58: 171.09 | Z58: 171.09 | AA58: 171.09 | AB58: 171.09 | AC58: 171.09 | AD58: 171.09 | AE58: 171.09 | AF58: 171.09 | AG58: 171.09 | AH58: 171.09 | AI58: 171.09 | AJ58: 171.09 | AK58: 171.09 | AL58: 0 | AM58: 0 | AN58: 0 | AO58: 0 | AP58: 0 | AQ58: 0 | AR58: 0 | AS58: 0 | AT58: 0 | AU58: 0
A59: Natural Gas | B59: 1980 | C59: 2332 | D59: 1876 | E59: 1483 | F59: 1974 | G59: 2035 | H59: 2177 | I59: 1967 | J59: 1966 | K59: 2016.2 | L59: 3143 | M59: 3420 | N59: 2337 | O59: 2065 | P59: 1941 | Q59: 1304.76 | R59: 1166.85 | S59: 1186.61 | T59: 1166.86 | U59: 1164.87 | V59: 1186.64 | W59: 1234.08 | X59: 905.98 | Y59: 732.13 | Z59: 819.19 | AA59: 591.89 | AB59: 1002.01 | AC59: 982.33 | AD59: 945.03 | AE59: 909.17 | AF59: 937 | AG59: 586.91 | AH59: 596.66 | AI59: 365.66 | AJ59: 385.1 | AK59: 383.45 | AL59: 0.12 | AM59: 0.12 | AN59: 0.12 | AO59: 0.01 | AP59: 0.01 | AQ59: 0.03 | AR59: 0.03 | AS59: 0.01 | AT59: 0.01 | AU59: 0.01
A60: Oil | B60: 3622.76 | C60: 3622.79 | D60: 3622.74 | E60: 3341.97 | F60: 4200.75 | G60: 2546.01 | H60: 1910.48 | I60: 1629.3 | J60: 1323.38 | K60: 1592.6 | L60: 1069.75 | M60: 700.88 | N60: 253.28 | O60: 386.29 | P60: 184.85 | Q60: 1232.84 | R60: 835.85 | S60: 1463.66 | T60: 1136.24 | U60: 977.97 | V60: 1050.45 | W60: 1512.41 | X60: 851.87 | Y60: 576.27 | Z60: 927.46 | AA60: 309.67 | AB60: 1680.38 | AC60: 1579.86 | AD60: 1739.05 | AE60: 1615.61 | AF60: 1688.05 | AG60: 693.43 | AH60: 203.03 | AI60: 888.42 | AJ60: 971.75 | AK60: 964.68 | AL60: 1392.12 | AM60: 1071.39 | AN60: 1030.89 | AO60: 19.97 | AP60: 59.47 | AQ60: 54.66 | AR60: 99.67 | AS60: 75.98 | AT60: 78.52 | AU60: 90.41
A62: Quebec
A63: _ | B63: 2005 | C63: 2006 | D63: 2007 | E63: 2008 | F63: 2009 | G63: 2010 | H63: 2011 | I63: 2012 | J63: 2013 | K63: 2014 | L63: 2015 | M63: 2016 | N63: 2017 | O63: 2018 | P63: 2019 | Q63: 2020 | R63: 2021 | S63: 2022 | T63: 2023 | U63: 2024 | V63: 2025 | W63: 2026 | X63: 2027 | Y63: 2028 | Z63: 2029 | AA63: 2030 | AB63: 2031 | AC63: 2032 | AD63: 2033 | AE63: 2034 | AF63: 2035 | AG63: 2036 | AH63: 2037 | AI63: 2038 | AJ63: 2039 | AK63: 2040 | AL63: 2041 | AM63: 2042 | AN63: 2043 | AO63: 2044 | AP63: 2045 | AQ63: 2046 | AR63: 2047 | AS63: 2048 | AT63: 2049 | AU63: 2050
A64: Hydro / Wave / Tidal | B64: 173112.6 | C64: 172347.6 | D64: 180856.6 | E64: 187783.8 | F64: 189423 | G64: 177402.2 | H64: 189675.6 | I64: 191955.4 | J64: 202512.3 | K64: 197207.4 | L64: 194413.3 | M64: 197315.9 | N64: 201677.6 | O64: 199829.6 | P64: 199599.8 | Q64: 201613.1 | R64: 201612.9 | S64: 201613.1 | T64: 207642.5 | U64: 207984.9 | V64: 208292.9 | W64: 208293 | X64: 208292.8 | Y64: 208292.9 | Z64: 208293 | AA64: 216247 | AB64: 216524.5 | AC64: 216524.5 | AD64: 216524.5 | AE64: 216774.1 | AF64: 216774 | AG64: 216998.5 | AH64: 217200.9 | AI64: 217383 | AJ64: 217382.8 | AK64: 217546.6 | AL64: 217546.6 | AM64: 217546.6 | AN64: 217546.6 | AO64: 217546.6 | AP64: 217546.6 | AQ64: 217546.5 | AR64: 217546.6 | AS64: 217546.6 | AT64: 217546.6 | AU64: 217546.8
A65: Wind | B65: 416 | C65: 419 | D65: 617 | E65: 565 | F65: 1322 | G65: 1535.14 | H65: 1393.8 | I65: 2278.06 | J65: 4717.86 | K65: 6124.31 | L65: 6421 | M65: 9781 | N65: 9905 | O65: 10640 | P65: 11097 | Q65: 10587.86 | R65: 10588.55 | S65: 10590.22 | T65: 10950.85 | U65: 13124.59 | V65: 13402.85 | W65: 13745.53 | X65: 14090.14 | Y65: 14435.59 | Z65: 14780.64 | AA65: 15175.99 | AB65: 15578.16 | AC65: 15987.86 | AD65: 16407.01 | AE65: 16835.11 | AF65: 17319.31 | AG65: 17804.98 | AH65: 18303.8 | AI65: 18843.77 | AJ65: 19418.4 | AK65: 20219.37 | AL65: 21165.37 | AM65: 22210.97 | AN65: 23321.97 | AO65: 24396.64 | AP65: 25410.54 | AQ65: 26346.15 | AR65: 27153.79 | AS65: 27901.61 | AT65: 28625.62 | AU65: 29345.68
A66: Biomass / Geothermal | B66: 646 | C66: 646 | D66: 646 | E66: 439 | F66: 550 | G66: 843.91 | H66: 1088.82 | I66: 1232.85 | J66: 1613.84 | K66: 943.52 | L66: 925.31 | M66: 1348.41 | N66: 1705.73 | O66: 1627.51 | P66: 1511.07 | Q66: 1162.75 | R66: 1243.71 | S66: 1243.7 | T66: 1243.67 | U66: 1286.71 | V66: 1329.18 | W66: 1329 | X66: 1328.96 | Y66: 1328.92 | Z66: 1328.87 | AA66: 1328.81 | AB66: 1328.75 | AC66: 1328.72 | AD66: 1328.67 | AE66: 1328.6 | AF66: 1328.49 | AG66: 1369.34 | AH66: 1409.91 | AI66: 1449.5 | AJ66: 1489.65 | AK66: 1528.81 | AL66: 1528.49 | AM66: 1528.14 | AN66: 1527.73 | AO66: 1527.27 | AP66: 1526.7 | AQ66: 1562.61 | AR66: 1561.77 | AS66: 1560.77 | AT66: 1559.51 | AU66: 1557.93
A67: Solar | B67: 0 | C67: 0 | D67: 0 | E67: 0 | F67: 0 | G67: 0 | H67: 0 | I67: 0 | J67: 0 | K67: 0 | L67: 1 | M67: 1 | N67: 1 | O67: 1 | P67: 1 | Q67: 0.26 | R67: 0.95 | S67: 188.22 | T67: 372.99 | U67: 612.9 | V67: 730.36 | W67: 909.67 | X67: 1089.5 | Y67: 1269.24 | Z67: 1446.04 | AA67: 1625.64 | AB67: 1807.78 | AC67: 1991.71 | AD67: 2185.68 | AE67: 2381.35 | AF67: 2628.27 | AG67: 2872.66 | AH67: 3137.85 | AI67: 3430.51 | AJ67: 3797.85 | AK67: 4217.36 | AL67: 4766.13 | AM67: 5402.34 | AN67: 6095.36 | AO67: 6748.21 | AP67: 7350.14 | AQ67: 7873.87 | AR67: 8274.48 | AS67: 8614.82 | AT67: 8928.85 | AU67: 9235.25
A68: Uranium | B68: 4321.58 | C68: 4321.58 | D68: 4321.58 | E68: 3624.23 | F68: 3596.28 | G68: 3551.59 | H68: 3525.22 | I68: 4212.62 | J68: 0 | K68: 0 | L68: 0 | M68: 0 | N68: 0 | O68: 0 | P68: 0 | Q68: 0 | R68: 0 | S68: 0 | T68: 0 | U68: 0 | V68: 0 | W68: 0 | X68: 0 | Y68: 0 | Z68: 0 | AA68: 0 | AB68: 0 | AC68: 0 | AD68: 0 | AE68: 0 | AF68: 0 | AG68: 0 | AH68: 0 | AI68: 0 | AJ68: 0 | AK68: 0 | AL68: 0 | AM68: 0 | AN68: 0 | AO68: 0 | AP68: 0 | AQ68: 0 | AR68: 0 | AS68: 0 | AT68: 0 | AU68: 0
A69: Coal & Coke | B69: 0 | C69: 0 | D69: 0 | E69: 0 | F69: 0 | G69: 0 | H69: 0 | I69: 0 | J69: 0 | K69: 0 | L69: 0 | M69: 0 | N69: 0 | O69: 0 | P69: 0 | Q69: 0 | R69: 0 | S69: 0 | T69: 0 | U69: 0 | V69: 0 | W69: 0 | X69: 0 | Y69: 0 | Z69: 0 | AA69: 0 | AB69: 0 | AC69: 0 | AD69: 0 | AE69: 0 | AF69: 0 | AG69: 0 | AH69: 0 | AI69: 0 | AJ69: 0 | AK69: 0 | AL69: 0 | AM69: 0 | AN69: 0 | AO69: 0 | AP69: 0 | AQ69: 0 | AR69: 0 | AS69: 0 | AT69: 0 | AU69: 0
A70: Natural Gas | B70: 269 | C70: 1326 | D70: 3945 | E70: 228 | F70: 264 | G70: 222.4 | H70: 174.24 | I70: 185.01 | J70: 112.84 | K70: 156.54 | L70: 141.41 | M70: 164.89 | N70: 188.25 | O70: 169.76 | P70: 163.06 | Q70: 163.21 | R70: 153.14 | S70: 158.82 | T70: 159.8 | U70: 160.19 | V70: 160.55 | W70: 160.81 | X70: 161.49 | Y70: 162.25 | Z70: 163.29 | AA70: 164.42 | AB70: 164.75 | AC70: 164.46 | AD70: 164.35 | AE70: 164.47 | AF70: 165.41 | AG70: 165.8 | AH70: 166.73 | AI70: 167.37 | AJ70: 168.26 | AK70: 169.08 | AL70: 171.03 | AM70: 172.43 | AN70: 174.08 | AO70: 175.6 | AP70: 177.25 | AQ70: 179.03 | AR70: 180.84 | AS70: 182.64 | AT70: 184.57 | AU70: 186.63
A71: Oil | B71: 180.26 | C71: 366.03 | D71: 668.83 | E71: 532.89 | F71: 392.12 | G71: 585.88 | H71: 546.18 | I71: 518.65 | J71: 475.06 | K71: 496.68 | L71: 532.04 | M71: 660.06 | N71: 421.08 | O71: 593.07 | P71: 501.07 | Q71: 501.05 | R71: 501.03 | S71: 501.04 | T71: 501.07 | U71: 501.13 | V71: 501.23 | W71: 501.41 | X71: 501.45 | Y71: 501.49 | Z71: 501.54 | AA71: 501.6 | AB71: 501.66 | AC71: 501.69 | AD71: 501.74 | AE71: 501.81 | AF71: 393.94 | AG71: 394.08 | AH71: 394.25 | AI71: 394.43 | AJ71: 394.66 | AK71: 394.93 | AL71: 395.24 | AM71: 395.6 | AN71: 396.01 | AO71: 396.46 | AP71: 397.03 | AQ71: 397.74 | AR71: 398.58 | AS71: 399.58 | AT71: 400.84 | AU71: 402.43
A73: Ontario
A74: _ | B74: 2005 | C74: 2006 | D74: 2007 | E74: 2008 | F74: 2009 | G74: 2010 | H74: 2011 | I74: 2012 | J74: 2013 | K74: 2014 | L74: 2015 | M74: 2016 | N74: 2017 | O74: 2018 | P74: 2019 | Q74: 2020 | R74: 2021 | S74: 2022 | T74: 2023 | U74: 2024 | V74: 2025 | W74: 2026 | X74: 2027 | Y74: 2028 | Z74: 2029 | AA74: 2030 | AB74: 2031 | AC74: 2032 | AD74: 2033 | AE74: 2034 | AF74: 2035 | AG74: 2036 | AH74: 2037 | AI74: 2038 | AJ74: 2039 | AK74: 2040 | AL74: 2041 | AM74: 2042 | AN74: 2043 | AO74: 2044 | AP74: 2045 | AQ74: 2046 | AR74: 2047 | AS74: 2048 | AT74: 2049 | AU74: 2050
A75: Hydro / Wave / Tidal | B75: 35480 | C75: 36031.99 | D75: 34315 | E75: 39614.99 | F75: 39685.01 | G75: 32555 | H75: 34907 | I75: 33887 | J75: 37936 | K75: 39199.48 | L75: 35042.89 | M75: 36513 | N75: 40016.01 | O75: 38280.99 | P75: 36210.02 | Q75: 40201.39 | R75: 40194.48 | S75: 40229.9 | T75: 40230.12 | U75: 40193.25 | V75: 40193.36 | W75: 40262.2 | X75: 40228.11 | Y75: 40230.24 | Z75: 40262.21 | AA75: 40262.18 | AB75: 40863.48 | AC75: 40863.46 | AD75: 40863.46 | AE75: 41404.65 | AF75: 41404.67 | AG75: 41891.73 | AH75: 41891.72 | AI75: 41891.7 | AJ75: 41891.71 | AK75: 41891.71 | AL75: 42330.06 | AM75: 42724.61 | AN75: 42724.61 | AO75: 42724.59 | AP75: 42724.62 | AQ75: 42724.6 | AR75: 42724.61 | AS75: 42724.62 | AT75: 42724.63 | AU75: 42724.63
A76: Wind | B76: 26 | C76: 145 | D76: 494 | E76: 1400 | F76: 2300 | G76: 2800 | H76: 3900 | I76: 4600 | J76: 5200 | K76: 6900.64 | L76: 11396 | M76: 10758 | N76: 10464 | O76: 11922.01 | P76: 10957 | Q76: 14436.84 | R76: 15840.41 | S76: 15845.88 | T76: 15851.45 | U76: 15857.69 | V76: 15864.13 | W76: 15873.41 | X76: 15883.12 | Y76: 15893.64 | Z76: 15906.04 | AA76: 20454.37 | AB76: 23480.44 | AC76: 26519.73 | AD76: 27144.23 | AE76: 27777.52 | AF76: 28650.55 | AG76: 29519.65 | AH76: 30468.08 | AI76: 34029.57 | AJ76: 35345.52 | AK76: 39642.56 | AL76: 42406.09 | AM76: 48126.72 | AN76: 51957.77 | AO76: 57907.68 | AP76: 61081.6 | AQ76: 66113.36 | AR76: 67863.91 | AS76: 71512.89 | AT76: 72496.14 | AU76: 73400.41
A77: Biomass / Geothermal | B77: 807.53 | C77: 733.51 | D77: 598.95 | E77: 484.04 | F77: 657.05 | G77: 735.1 | H77: 607.89 | I77: 672.86 | J77: 586.34 | K77: 905.14 | L77: 937.11 | M77: 1444.15 | N77: 962.05 | O77: 1310.77 | P77: 1249.39 | Q77: 756.17 | R77: 767.62 | S77: 773.88 | T77: 772.61 | U77: 759.22 | V77: 758.82 | W77: 784.37 | X77: 770.68 | Y77: 769.88 | Z77: 781.76 | AA77: 780.58 | AB77: 780.41 | AC77: 767.81 | AD77: 780.87 | AE77: 754.83 | AF77: 754.27 | AG77: 779.3 | AH77: 765.67 | AI77: 765.03 | AJ77: 764.29 | AK77: 750.62 | AL77: 754.81 | AM77: 784.72 | AN77: 783.36 | AO77: 782.12 | AP77: 782.76 | AQ77: 787.71 | AR77: 786.25 | AS77: 784.8 | AT77: 783.24 | AU77: 783.61
A78: Solar | B78: 0 | C78: 0 | D78: 0 | E78: 0 | F78: 5 | G78: 123 | H78: 398 | I78: 842 | J78: 1173 | K78: 1757.71 | L78: 1425 | M78: 1776 | N78: 1998 | O78: 2163 | P78: 2168 | Q78: 2168 | R78: 2169.97 | S78: 2174.56 | T78: 2179.17 | U78: 2184.78 | V78: 2189.98 | W78: 2196.85 | X78: 2204.68 | Y78: 2213.55 | Z78: 2548.61 | AA78: 3038.16 | AB78: 3198.15 | AC78: 3699.65 | AD78: 4069.13 | AE78: 4459.73 | AF78: 5072.47 | AG78: 5675.31 | AH78: 6347.37 | AI78: 7330.43 | AJ78: 8323.26 | AK78: 9958.99 | AL78: 12186.32 | AM78: 15133.07 | AN78: 18326.67 | AO78: 21566.41 | AP78: 24227.89 | AQ78: 26587.89 | AR78: 27950.43 | AS78: 29111.9 | AT78: 29805.31 | AU78: 30297.55
A79: Uranium | B79: 77969 | C79: 83457 | D79: 79750 | E79: 85832 | F79: 81395.98 | G79: 81975 | H79: 84766 | I79: 84866 | J79: 93102.99 | K79: 96195.59 | L79: 91768.98 | M79: 91142.01 | N79: 90445 | O79: 90155.01 | P79: 90454 | Q79: 78513.96 | R79: 73695.8 | S79: 76110.52 | T79: 64975.64 | U79: 75346.56 | V79: 68445.5 | W79: 63105.11 | X79: 69400.34 | Y79: 75838.45 | Z79: 70893.45 | AA79: 77736.77 | AB79: 71040.09 | AC79: 77883.41 | AD79: 77924.14 | AE79: 84767.45 | AF79: 86590.41 | AG79: 86590.41 | AH79: 86632.02 | AI79: 86632.02 | AJ79: 86715.24 | AK79: 86881.68 | AL79: 87048.12 | AM79: 87214.55 | AN79: 87381 | AO79: 87589.05 | AP79: 87797.09 | AQ79: 88213.2 | AR79: 89045.4 | AS79: 89877.59 | AT79: 90709.79 | AU79: 90709.79
A80: Coal & Coke | B80: 28734.08 | C80: 23808.08 | D80: 27468.72 | E80: 22638.21 | F80: 10461.15 | G80: 10336.62 | H80: 4329.34 | I80: 3596.74 | J80: 2742.24 | K80: 94.81 | L80: 0 | M80: 0 | N80: 0 | O80: 0 | P80: 0 | Q80: 0 | R80: 0 | S80: 0 | T80: 0 | U80: 0 | V80: 0 | W80: 0 | X80: 0 | Y80: 0 | Z80: 0 | AA80: 0 | AB80: 0 | AC80: 0 | AD80: 0 | AE80: 0 | AF80: 0 | AG80: 0 | AH80: 0 | AI80: 0 | AJ80: 0 | AK80: 0 | AL80: 0 | AM80: 0 | AN80: 0 | AO80: 0 | AP80: 0 | AQ80: 0 | AR80: 0 | AS80: 0 | AT80: 0 | AU80: 0
A81: Natural Gas | B81: 13282.59 | C81: 11807.7 | D81: 13530.81 | E81: 11214.3 | F81: 7490.9 | G81: 16885.54 | H81: 24281.59 | I81: 23380.22 | J81: 18653.16 | K81: 15720.97 | L81: 16218.48 | M81: 14862.2 | N81: 8378.62 | O81: 11831.22 | P81: 11504.17 | Q81: 9751.43 | R81: 12661.08 | S81: 16084.9 | T81: 19884.34 | U81: 13823.89 | V81: 17526.53 | W81: 23150.5 | X81: 20545.72 | Y81: 19372.94 | Z81: 25389.35 | AA81: 21398.93 | AB81: 26543.49 | AC81: 20464.93 | AD81: 20015.42 | AE81: 16768.24 | AF81: 16155.25 | AG81: 5265.33 | AH81: 4989.55 | AI81: 4046.97 | AJ81: 4037.94 | AK81: 3694.78 | AL81: 3993.06 | AM81: 4469.17 | AN81: 4732.95 | AO81: 4432.57 | AP81: 4596.84 | AQ81: 4613.88 | AR81: 4757.44 | AS81: 4601.67 | AT81: 4709.57 | AU81: 4852.41
A82: Oil | B82: 309.95 | C82: 309.95 | D82: 309.95 | E82: 182.56 | F82: 215.24 | G82: 73.47 | H82: 45.67 | I82: 65.78 | J82: 45.15 | K82: 381.13 | L82: 657.48 | M82: 544.26 | N82: 377.97 | O82: 459.69 | P82: 409.18 | Q82: 15.38 | R82: 156.56 | S82: 132.34 | T82: 539.23 | U82: 84.08 | V82: 1000.86 | W82: 3605.96 | X82: 2234.28 | Y82: 1372.22 | Z82: 3631.94 | AA82: 875.73 | AB82: 4113.85 | AC82: 1998.32 | AD82: 2758.81 | AE82: 1821.14 | AF82: 1456.37 | AG82: 4175.85 | AH82: 4212.34 | AI82: 3408.68 | AJ82: 3589.03 | AK82: 3003.27 | AL82: 4115.29 | AM82: 2659.02 | AN82: 3427.68 | AO82: 2475.3 | AP82: 3127.13 | AQ82: 2847.24 | AR82: 3271.8 | AS82: 2712.5 | AT82: 3184.36 | AU82: 4029.9
A84: Manitoba
A85: _ | B85: 2005 | C85: 2006 | D85: 2007 | E85: 2008 | F85: 2009 | G85: 2010 | H85: 2011 | I85: 2012 | J85: 2013 | K85: 2014 | L85: 2015 | M85: 2016 | N85: 2017 | O85: 2018 | P85: 2019 | Q85: 2020 | R85: 2021 | S85: 2022 | T85: 2023 | U85: 2024 | V85: 2025 | W85: 2026 | X85: 2027 | Y85: 2028 | Z85: 2029 | AA85: 2030 | AB85: 2031 | AC85: 2032 | AD85: 2033 | AE85: 2034 | AF85: 2035 | AG85: 2036 | AH85: 2037 | AI85: 2038 | AJ85: 2039 | AK85: 2040 | AL85: 2041 | AM85: 2042 | AN85: 2043 | AO85: 2044 | AP85: 2045 | AQ85: 2046 | AR85: 2047 | AS85: 2048 | AT85: 2049 | AU85: 2050
A86: Hydro / Wave / Tidal | B86: 36440 | C86: 33651 | D86: 33513 | E86: 34588 | F86: 33549 | G86: 33269 | H86: 34206 | I86: 32185 | J86: 35337 | K86: 34494.88 | L86: 34774 | M86: 36599 | N86: 35991 | O86: 30732 | P86: 32935 | Q86: 33738.22 | R86: 34368.94 | S86: 38153.28 | T86: 38153.25 | U86: 38153.26 | V86: 38153.27 | W86: 38153.23 | X86: 38153.27 | Y86: 38191.41 | Z86: 38229.63 | AA86: 38267.86 | AB86: 38306.09 | AC86: 38344.42 | AD86: 38382.78 | AE86: 38421.12 | AF86: 38459.58 | AG86: 38498.03 | AH86: 38536.49 | AI86: 38575.08 | AJ86: 38613.64 | AK86: 38652.24 | AL86: 38690.93 | AM86: 38729.61 | AN86: 38768.31 | AO86: 38807.06 | AP86: 38845.89 | AQ86: 38884.71 | AR86: 38923.6 | AS86: 38962.55 | AT86: 39001.5 | AU86: 39040.56
A87: Wind | B87: 53 | C87: 325 | D87: 325 | E87: 412 | F87: 365 | G87: 343 | H87: 747 | I87: 877 | J87: 868 | K87: 911.32 | L87: 903 | M87: 966 | N87: 927 | O87: 873 | P87: 884 | Q87: 884 | R87: 885 | S87: 887.31 | T87: 889.64 | U87: 1008.18 | V87: 1124.35 | W87: 1245.17 | X87: 1369.69 | Y87: 1497.67 | Z87: 1628.83 | AA87: 1770.91 | AB87: 1916.32 | AC87: 2065.79 | AD87: 2223.11 | AE87: 2384.03 | AF87: 2552.8 | AG87: 2727.04 | AH87: 2908.15 | AI87: 3100.09 | AJ87: 3309.26 | AK87: 3548.76 | AL87: 3835.53 | AM87: 4146.99 | AN87: 4478.46 | AO87: 4795.55 | AP87: 5092.35 | AQ87: 5370.75 | AR87: 5619.18 | AS87: 5852.22 | AT87: 6080.23 | AU87: 6301.06
A88: Biomass / Geothermal | B88: 27.33 | C88: 32 | D88: 27 | E88: 38 | F88: 0 | G88: 0 | H88: 0 | I88: 39 | J88: 42 | K88: 64.4 | L88: 82 | M88: 108 | N88: 56 | O88: 46 | P88: 82 | Q88: 82 | R88: 82 | S88: 82 | T88: 82 | U88: 82 | V88: 82 | W88: 82 | X88: 82 | Y88: 82 | Z88: 82 | AA88: 82 | AB88: 82 | AC88: 82 | AD88: 82 | AE88: 82 | AF88: 82 | AG88: 82 | AH88: 82 | AI88: 82 | AJ88: 82 | AK88: 82 | AL88: 82 | AM88: 82 | AN88: 82 | AO88: 82 | AP88: 82 | AQ88: 82 | AR88: 82 | AS88: 82 | AT88: 82 | AU88: 82
A89: Solar | B89: 0 | C89: 0 | D89: 0 | E89: 0 | F89: 0 | G89: 0 | H89: 0 | I89: 0 | J89: 0 | K89: 0 | L89: 0 | M89: 0 | N89: 0 | O89: 0 | P89: 0 | Q89: 5.26 | R89: 6.26 | S89: 8.26 | T89: 10.37 | U89: 70.16 | V89: 72.97 | W89: 76.02 | X89: 79.27 | Y89: 82.78 | Z89: 86.69 | AA89: 90.97 | AB89: 95.48 | AC89: 100.62 | AD89: 110.4 | AE89: 120.88 | AF89: 136.36 | AG89: 154.73 | AH89: 244.35 | AI89: 345.37 | AJ89: 463.64 | AK89: 609.78 | AL89: 798.98 | AM89: 1010.43 | AN89: 1240.03 | AO89: 1455.72 | AP89: 1651.96 | AQ89: 1830.27 | AR89: 1979.73 | AS89: 2113.79 | AT89: 2234.43 | AU89: 2353.86
A90: Uranium | B90: 0 | C90: 0 | D90: 0 | E90: 0 | F90: 0 | G90: 0 | H90: 0 | I90: 0 | J90: 0 | K90: 0 | L90: 0 | M90: 0 | N90: 0 | O90: 0 | P90: 0 | Q90: 0 | R90: 0 | S90: 0 | T90: 0 | U90: 0 | V90: 0 | W90: 0 | X90: 0 | Y90: 0 | Z90: 0 | AA90: 0 | AB90: 0 | AC90: 0 | AD90: 0 | AE90: 0 | AF90: 0 | AG90: 0 | AH90: 0 | AI90: 0 | AJ90: 0 | AK90: 0 | AL90: 0 | AM90: 0 | AN90: 0 | AO90: 0 | AP90: 0 | AQ90: 0 | AR90: 0 | AS90: 0 | AT90: 0 | AU90: 0
A91: Coal & Coke | B91: 413.26 | C91: 316.98 | D91: 380.97 | E91: 380.18 | F91: 137.79 | G91: 43.57 | H91: 48.77 | I91: 50.54 | J91: 64.18 | K91: 67.62 | L91: 61.83 | M91: 27.48 | N91: 29.44 | O91: 4.91 | P91: 0 | Q91: 0 | R91: 0 | S91: 0 | T91: 0 | U91: 0 | V91: 0 | W91: 0 | X91: 0 | Y91: 0 | Z91: 0 | AA91: 0 | AB91: 0 | AC91: 0 | AD91: 0 | AE91: 0 | AF91: 0 | AG91: 0 | AH91: 0 | AI91: 0 | AJ91: 0 | AK91: 0 | AL91: 0 | AM91: 0 | AN91: 0 | AO91: 0 | AP91: 0 | AQ91: 0 | AR91: 0 | AS91: 0 | AT91: 0 | AU91: 0
A92: Natural Gas | B92: 41.65 | C92: 90.76 | D92: 172.59 | E92: 133.66 | F92: 129.41 | G92: 98.95 | H92: 109.3 | I92: 60.7 | J92: 30.49 | K92: 32.09 | L92: 119.35 | M92: 69.02 | N92: 70.72 | O92: 51.46 | P92: 39.9 | Q92: 247.24 | R92: 380.91 | S92: 151.2 | T92: 151.08 | U92: 116.1 | V92: 150.65 | W92: 115.51 | X92: 115.51 | Y92: 57.19 | Z92: 57.19 | AA92: 22.2 | AB92: 22.16 | AC92: 22.11 | AD92: 22.06 | AE92: 22.01 | AF92: 21.96 | AG92: 21.92 | AH92: 21.87 | AI92: 21.81 | AJ92: 21.75 | AK92: 21.7 | AL92: 21.7 | AM92: 21.7 | AN92: 21.7 | AO92: 21.69 | AP92: 21.69 | AQ92: 21.68 | AR92: 21.68 | AS92: 21.67 | AT92: 192.58 | AU92: 168.86
A93: Oil | B93: 8.29 | C93: 7.35 | D93: 10.64 | E93: 9.45 | F93: 4.71 | G93: 2.37 | H93: 3.53 | I93: 2.65 | J93: 1.93 | K93: 6.79 | L93: 5.82 | M93: 2.51 | N93: 2.84 | O93: 1.64 | P93: 1.1 | Q93: 10.78 | R93: 19.85 | S93: 0.47 | T93: 0.6 | U93: 0.77 | V93: 1.02 | W93: 1.37 | X93: 1.37 | Y93: 1.37 | Z93: 1.37 | AA93: 1.38 | AB93: 1.41 | AC93: 1.46 | AD93: 1.51 | AE93: 1.56 | AF93: 1.61 | AG93: 1.66 | AH93: 1.71 | AI93: 1.76 | AJ93: 1.82 | AK93: 1.88 | AL93: 1.87 | AM93: 1.87 | AN93: 1.87 | AO93: 1.88 | AP93: 1.89 | AQ93: 1.89 | AR93: 1.9 | AS93: 1.91 | AT93: 33.93 | AU93: 24.1
A95: Alberta
A96: _ | B96: 2005 | C96: 2006 | D96: 2007 | E96: 2008 | F96: 2009 | G96: 2010 | H96: 2011 | I96: 2012 | J96: 2013 | K96: 2014 | L96: 2015 | M96: 2016 | N96: 2017 | O96: 2018 | P96: 2019 | Q96: 2020 | R96: 2021 | S96: 2022 | T96: 2023 | U96: 2024 | V96: 2025 | W96: 2026 | X96: 2027 | Y96: 2028 | Z96: 2029 | AA96: 2030 | AB96: 2031 | AC96: 2032 | AD96: 2033 | AE96: 2034 | AF96: 2035 | AG96: 2036 | AH96: 2037 | AI96: 2038 | AJ96: 2039 | AK96: 2040 | AL96: 2041 | AM96: 2042 | AN96: 2043 | AO96: 2044 | AP96: 2045 | AQ96: 2046 | AR96: 2047 | AS96: 2048 | AT96: 2049 | AU96: 2050
A97: Hydro / Wave / Tidal | B97: 2316 | C97: 1966 | D97: 2113 | E97: 2150 | F97: 1695 | G97: 1620 | H97: 2036 | I97: 2319 | J97: 2028 | K97: 1821.38 | L97: 1977 | M97: 1971 | N97: 2062 | O97: 1991 | P97: 2043 | Q97: 2043.02 | R97: 2042.98 | S97: 2034.64 | T97: 1733.2 | U97: 1752.85 | V97: 1749.79 | W97: 1749.74 | X97: 1730.78 | Y97: 1306.46 | Z97: 800.58 | AA97: 1083.69 | AB97: 908.48 | AC97: 722.81 | AD97: 685.25 | AE97: 666.41 | AF97: 634.45 | AG97: 622.97 | AH97: 622.1 | AI97: 596.49 | AJ97: 599.95 | AK97: 554 | AL97: 557.14 | AM97: 529.51 | AN97: 524.26 | AO97: 508.21 | AP97: 493.01 | AQ97: 480.62 | AR97: 486.98 | AS97: 478.84 | AT97: 491.28 | AU97: 505.55
A98: Wind | B98: 741 | C98: 921 | D98: 1430 | E98: 1473 | F98: 1558 | G98: 1629 | H98: 2372 | I98: 2601 | J98: 3058 | K98: 3518.87 | L98: 4089 | M98: 4586 | N98: 4634 | O98: 4119 | P98: 4206 | Q98: 4206 | R98: 4206.11 | S98: 15769.94 | T98: 15347.17 | U98: 15301.37 | V98: 15129.24 | W98: 15071.71 | X98: 21206.05 | Y98: 23490.57 | Z98: 27204.89 | AA98: 29182.71 | AB98: 30569.98 | AC98: 31781.22 | AD98: 30619.53 | AE98: 30246.01 | AF98: 29004.62 | AG98: 29035.8 | AH98: 29254.17 | AI98: 29980.02 | AJ98: 30361.1 | AK98: 30113.61 | AL98: 30451.95 | AM98: 31252.58 | AN98: 30938.7 | AO98: 32060.54 | AP98: 31143.44 | AQ98: 32308.49 | AR98: 32693.2 | AS98: 34076.6 | AT98: 34900.14 | AU98: 35844.17
A99: Biomass / Geothermal | B99: 1725.17 | C99: 1855.17 | D99: 1870.36 | E99: 1917.39 | F99: 1861.5 | G99: 1908.78 | H99: 1972.19 | I99: 2089.12 | J99: 2250.1 | K99: 3497.7 | L99: 2120.3 | M99: 2127.45 | N99: 1158.51 | O99: 1837.13 | P99: 1844.11 | Q99: 1631.82 | R99: 1631.82 | S99: 1807.02 | T99: 1788.06 | U99: 1785.96 | V99: 1778.17 | W99: 1775.53 | X99: 1743 | Y99: 1671.79 | Z99: 1606.43 | AA99: 1482.13 | AB99: 1419.91 | AC99: 1353.69 | AD99: 1340.59 | AE99: 1333.82 | AF99: 1322.39 | AG99: 1318.26 | AH99: 1317.95 | AI99: 1308.77 | AJ99: 1310.01 | AK99: 1295.63 | AL99: 1296.79 | AM99: 1286.81 | AN99: 1284.92 | AO99: 1279.12 | AP99: 1273.63 | AQ99: 1269.14 | AR99: 1271.44 | AS99: 1268.5 | AT99: 1273 | AU99: 1278.17
A100: Solar | B100: 0 | C100: 0 | D100: 0 | E100: 0 | F100: 0 | G100: 0 | H100: 0 | I100: 0 | J100: 0 | K100: 0 | L100: 0 | M100: 2 | N100: 2 | O100: 25 | P100: 23 | Q100: 23 | R100: 319.41 | S100: 912.5 | T100: 888.66 | U100: 886.52 | V100: 876.85 | W100: 1015.56 | X100: 1102.56 | Y100: 989.34 | Z100: 1780.21 | AA100: 2017.55 | AB100: 2303.01 | AC100: 2376.67 | AD100: 2755.79 | AE100: 3185.11 | AF100: 4935.75 | AG100: 5068.67 | AH100: 5262.64 | AI100: 5271.81 | AJ100: 5422.67 | AK100: 7129.05 | AL100: 7325.38 | AM100: 7135.43 | AN100: 7082.7 | AO100: 6935.56 | AP100: 8459.59 | AQ100: 8325.47 | AR100: 8455.52 | AS100: 8385.52 | AT100: 8617.13 | AU100: 8876.16
A101: Uranium | B101: 0 | C101: 0 | D101: 0 | E101: 0 | F101: 0 | G101: 0 | H101: 0 | I101: 0 | J101: 0 | K101: 0 | L101: 0 | M101: 0 | N101: 0 | O101: 0 | P101: 0 | Q101: 0 | R101: 0 | S101: 0 | T101: 0 | U101: 0 | V101: 0 | W101: 0 | X101: 0 | Y101: 0 | Z101: 0 | AA101: 0 | AB101: 0 | AC101: 0 | AD101: 0 | AE101: 0 | AF101: 0 | AG101: 0 | AH101: 0 | AI101: 0 | AJ101: 0 | AK101: 0 | AL101: 0 | AM101: 0 | AN101: 0 | AO101: 0 | AP101: 0 | AQ101: 0 | AR101: 0 | AS101: 0 | AT101: 0 | AU101: 0
A102: Coal & Coke | B102: 43581.07 | C102: 44117.04 | D102: 43868.23 | E102: 42131.1 | F102: 40805 | G102: 37566.91 | H102: 38509.52 | I102: 38070.06 | J102: 38933.51 | K102: 43727.18 | L102: 38468.68 | M102: 38222.75 | N102: 36385.09 | O102: 28913.59 | P102: 27252.84 | Q102: 23554.78 | R102: 27816.82 | S102: 11779.94 | T102: 0 | U102: 0 | V102: 0 | W102: 0 | X102: 0 | Y102: 0 | Z102: 0 | AA102: 0 | AB102: 0 | AC102: 0 | AD102: 0 | AE102: 0 | AF102: 0 | AG102: 0 | AH102: 0 | AI102: 0 | AJ102: 0 | AK102: 0 | AL102: 0 | AM102: 0 | AN102: 0 | AO102: 0 | AP102: 0 | AQ102: 0 | AR102: 0 | AS102: 0 | AT102: 0 | AU102: 0
A103: Natural Gas | B103: 19568.76 | C103: 22063.15 | D103: 22337.97 | E103: 23347.1 | F103: 26233.32 | G103: 27594.87 | H103: 28106.9 | I103: 29938.05 | J103: 31739.48 | K103: 31585.45 | L103: 33998.07 | M103: 31541.04 | N103: 36050.99 | O103: 38692.25 | P103: 40690.34 | Q103: 45033.64 | R103: 44597.28 | S103: 48861.02 | T103: 62823.52 | U103: 63023.13 | V103: 62955.26 | W103: 62878.33 | X103: 57075.95 | Y103: 55581.21 | Z103: 52228.42 | AA103: 50221.23 | AB103: 49182.05 | AC103: 48479.39 | AD103: 49363.9 | AE103: 49454.04 | AF103: 49209.95 | AG103: 49402.66 | AH103: 49388.26 | AI103: 49331.63 | AJ103: 49391.52 | AK103: 48698.59 | AL103: 48755.52 | AM103: 48744.78 | AN103: 49579.11 | AO103: 49257.11 | AP103: 49388.85 | AQ103: 49129.14 | AR103: 49479.16 | AS103: 49305.12 | AT103: 49573.04 | AU103: 49880.18
A104: Oil | B104: 509.44 | C104: 860.08 | D104: 922.06 | E104: 635.87 | F104: 14.15 | G104: 26.51 | H104: 25.4 | I104: 28.93 | J104: 27 | K104: 78.41 | L104: 80.24 | M104: 48.21 | N104: 98.92 | O104: 38.16 | P104: 63.82 | Q104: 55.32 | R104: 117.3 | S104: 80.62 | T104: 82.7 | U104: 92.57 | V104: 101.95 | W104: 112.55 | X104: 103.49 | Y104: 89.13 | Z104: 75.93 | AA104: 54.75 | AB104: 46.32 | AC104: 37.94 | AD104: 36.9 | AE104: 36.14 | AF104: 34.27 | AG104: 33.31 | AH104: 33 | AI104: 31.58 | AJ104: 31.64 | AK104: 29.45 | AL104: 28.4 | AM104: 26.02 | AN104: 24.87 | AO104: 23.42 | AP104: 22.02 | AQ104: 20.74 | AR104: 20.36 | AS104: 19.41 | AT104: 19.25 | AU104: 19.08
A106: British Columbia
A107: _ | B107: 2005 | C107: 2006 | D107: 2007 | E107: 2008 | F107: 2009 | G107: 2010 | H107: 2011 | I107: 2012 | J107: 2013 | K107: 2014 | L107: 2015 | M107: 2016 | N107: 2017 | O107: 2018 | P107: 2019 | Q107: 2020 | R107: 2021 | S107: 2022 | T107: 2023 | U107: 2024 | V107: 2025 | W107: 2026 | X107: 2027 | Y107: 2028 | Z107: 2029 | AA107: 2030 | AB107: 2031 | AC107: 2032 | AD107: 2033 | AE107: 2034 | AF107: 2035 | AG107: 2036 | AH107: 2037 | AI107: 2038 | AJ107: 2039 | AK107: 2040 | AL107: 2041 | AM107: 2042 | AN107: 2043 | AO107: 2044 | AP107: 2045 | AQ107: 2046 | AR107: 2047 | AS107: 2048 | AT107: 2049 | AU107: 2050
A108: Hydro / Wave / Tidal | B108: 60327 | C108: 53902.91 | D108: 64015.8 | E108: 58525.63 | F108: 56298.4 | G108: 53970.88 | H108: 60772.07 | I108: 64477.04 | J108: 58666.27 | K108: 57572.87 | L108: 64999.01 | M108: 61840 | N108: 66503.02 | O108: 61791 | P108: 56107.99 | Q108: 56127.08 | R108: 56127.05 | S108: 72486.33 | T108: 72486.34 | U108: 72486.27 | V108: 77593.37 | W108: 77593.43 | X108: 77593.41 | Y108: 77593.44 | Z108: 77593.48 | AA108: 77954.07 | AB108: 78316.42 | AC108: 78680.71 | AD108: 79046.68 | AE108: 79414.53 | AF108: 80144.73 | AG108: 80840.68 | AH108: 81506.09 | AI108: 82144.13 | AJ108: 82521.28 | AK108: 82900.36 | AL108: 83281.26 | AM108: 83664.05 | AN108: 84048.87 | AO108: 84435.52 | AP108: 84824.08 | AQ108: 85214.98 | AR108: 85607.39 | AS108: 86001.7 | AT108: 85654.5 | AU108: 86796.58
A109: Wind | B109: 0 | C109: 0 | D109: 0 | E109: 0 | F109: 34 | G109: 123 | H109: 484.6 | I109: 507.98 | J109: 860 | K109: 1071.14 | L109: 868 | M109: 1223 | N109: 1631 | O109: 1724 | P109: 1693 | Q109: 1693 | R109: 1693.86 | S109: 1695.92 | T109: 1698.09 | U109: 1990.71 | V109: 2290.09 | W109: 2299.24 | X109: 2634.67 | Y109: 2987.27 | Z109: 3337.63 | AA109: 3740.1 | AB109: 4174.42 | AC109: 4651.75 | AD109: 5187.16 | AE109: 5769.82 | AF109: 6938.97 | AG109: 8308.9 | AH109: 9632.63 | AI109: 11012.51 | AJ109: 12317.75 | AK109: 13408.14 | AL109: 13982.74 | AM109: 14505.43 | AN109: 15136.01 | AO109: 15792.09 | AP109: 16357.15 | AQ109: 16932 | AR109: 17519.91 | AS109: 18122.06 | AT109: 18753.17 | AU109: 19386.72
A110: Biomass / Geothermal | B110: 2863.41 | C110: 2948.7 | D110: 2948.7 | E110: 2467.38 | F110: 2162.84 | G110: 3810.74 | H110: 4111 | I110: 4034.09 | J110: 3821.9 | K110: 5856.07 | L110: 3658.62 | M110: 4486.41 | N110: 1858.06 | O110: 3319.56 | P110: 3275.15 | Q110: 3275.54 | R110: 3310.29 | S110: 3292.73 | T110: 3288.62 | U110: 3287.18 | V110: 3285.82 | W110: 3284.92 | X110: 3281.87 | Y110: 3278.72 | Z110: 3274.56 | AA110: 3269.22 | AB110: 3268.4 | AC110: 3269.72 | AD110: 3270.62 | AE110: 3269.51 | AF110: 3266.8 | AG110: 3262.89 | AH110: 3258.86 | AI110: 3255.35 | AJ110: 3251.12 | AK110: 3246.78 | AL110: 3237.46 | AM110: 3228.3 | AN110: 3218.65 | AO110: 3209.34 | AP110: 3198.75 | AQ110: 3186.73 | AR110: 3174.13 | AS110: 3161 | AT110: 3146.22 | AU110: 3129.69
A111: Solar | B111: 0 | C111: 0 | D111: 0 | E111: 0 | F111: 0 | G111: 0 | H111: 0 | I111: 0 | J111: 0 | K111: 0 | L111: 0 | M111: 0 | N111: 0 | O111: 2 | P111: 2 | Q111: 19.54 | R111: 20.37 | S111: 22.15 | T111: 59.19 | U111: 61.25 | V111: 63.61 | W111: 102.16 | X111: 105.69 | Y111: 109.38 | Z111: 149.29 | AA111: 164.97 | AB111: 387.48 | AC111: 657.83 | AD111: 1007.56 | AE111: 1364.51 | AF111: 2282.84 | AG111: 2904.97 | AH111: 3515.96 | AI111: 4136.49 | AJ111: 4731.88 | AK111: 5110.41 | AL111: 5445.8 | AM111: 5730.04 | AN111: 6109.41 | AO111: 6514.28 | AP111: 6842.57 | AQ111: 7170.24 | AR111: 7508.62 | AS111: 7856.21 | AT111: 8235.89 | AU111: 8396.49
...

Sheet Canada NG Gen by Turbine Type
A1: Electric power generation, monthly generation by type of electricity 1 2
A2: Frequency: Monthly
A3: Table: 25-10-0015-01 (formerly CANSIM 127-0002)
A4: Release date: 2022-08-08
A5: Geography: Canada, Province or territory
A9: Geography | B9: Canada
A10: Class of electricity producer | B10: Electricity producers, electric utilities 3
A11: Type of electricity generation | B11: 42005 | C11: 42036 | D11: 42064 | E11: 42095 | F11: 42125 | G11: 42156 | H11: 42186 | I11: 42217 | J11: 42248 | K11: 42278 | L11: 42309 | M11: 42339 | N11: 2015 Total
B12: Megawatt hours
A13: Total all types of electricity generation | B13: 57211066 | C13: 51887549 | D13: 51928707 | E13: 44615918 | F13: 41273083 | G13: 40984150 | H13: 43038080 | I13: 42821817 | J13: 40051862 | K13: 41066197 | L13: 45130806 | M13: 50003722 | N13: =SUM(B13:M13) -> 550012957
A14: Hydraulic turbine 4 | B14: 37669235 | C14: 34013218 | D14: 33173669 | E14: 28699811 | F14: 25910082 | G14: 25327992 | H14: 25979724 | I14: 25478511 | J14: 25022584 | K14: 26123765 | L14: 27941235 | M14: 32045247 | N14: =SUM(B14:M14) -> 347385073
A15: Conventional steam turbine 5 | B15: 7190066 | C15: 6844655 | D15: 6613699 | E15: 5688669 | F15: 5082749 | G15: 5430405 | H15: 5991055 | I15: 6330435 | J15: 6041405 | K15: 6138156 | L15: 6294045 | M15: 6842938 | N15: =SUM(B15:M15) -> 74488277
A16: Nuclear steam turbine 6 | B16: 9180622 | C16: 8307371 | D16: 9230529 | E16: 7737381 | F16: 7985257 | G16: 8084872 | H16: 8900017 | I16: 8678391 | J16: 6965168 | K16: 6323797 | L16: 8448485 | M16: 8533084 | N16: =SUM(B16:M16) -> 98374974
A17: Internal combustion turbine 7 | B17: 92383 | C17: 85781 | D17: 84787 | E17: 74433 | F17: 66229 | G17: 63635 | H17: 66291 | I17: 69265 | J17: 65022 | K17: 73599 | L17: 74497 | M17: 84241 | N17: =SUM(B17:M17) -> 900163
A18: Combustion turbine 8 | B18: 2014274 | C18: 1874168 | D18: 1889483 | E18: 1556326 | F18: 1586397 | G18: 1577410 | H18: 1632967 | I18: 1756391 | J18: 1312213 | K18: 1476359 | L18: 1468138 | M18: 1615706 | N18: =SUM(B18:M18) -> 19759832
A19: Total electricity production from combustible fuels 9 | B19: .. | C19: .. | D19: .. | E19: .. | F19: .. | G19: .. | H19: .. | I19: .. | J19: .. | K19: .. | L19: .. | M19: .. | N19: ..
A20: Tidal power turbine 10 | B20: -124 | C20: -164 | D20: -13 | E20: 1538 | F20: 1615 | G20: 1951 | H20: 870 | I20: 22 | J20: 1791 | K20: 1524 | L20: 1979 | M20: 1831 | N20: =SUM(B20:M20) -> 12820
A21: Wind power turbine 11 | B21: 1053353 | C21: 748057 | D21: 924413 | E21: 832222 | F21: 611620 | G21: 469148 | H21: 435550 | I21: 477306 | J21: 616094 | K21: 907927 | L21: 885149 | M21: 872178 | N21: =SUM(B21:M21) -> 8833017
A22: Solar 12 | B22: 11257 | C22: 14463 | D22: 12140 | E22: 25538 | F22: 29134 | G22: 28737 | H22: 31620 | I22: 31496 | J22: 27584 | K22: 21070 | L22: 17278 | M22: 8498 | N22: =SUM(B22:M22) -> 258815
A23: Other types of electricity generation | B23: .. | C23: .. | D23: .. | E23: .. | F23: .. | G23: .. | H23: .. | I23: .. | J23: .. | K23: .. | L23: .. | M23: .. | N23: ..
A25: Symbol legend:
A26: .. | B26: not available for a specific reference period
A27: r | B27: revised
A32: Footnotes:
A33: 1 | B33: For monthly data prior to January 2008, please see table 25-10-0001-01 (terminated). For current monthly data on Electric power receipts and deliveries, see table 25-10-0016-01.
A34: 2 | B34: The target population for the Monthly Electricity Supply and Disposition Survey has been expanded to improve coverage of renewable energy in Canada, particularly wind and solar power. As a result of this change, users will have to use caution when comparing data for historical purposes. For wind power, significant changes occurred in British Columbia, Alberta, Ontario, Quebec and Prince Edward Island. For solar power, significant changes occurred in Ontario.
A35: 3 | B35: A utility is an organization that, as its prime purpose, generates, transmits and/or distributes electric energy for sale. It can be private or public (provincial or municipal).
A36: 4 | B36: Electric power generated from a plant in which the turbine generators are driven by flowing water. Prior to January 2008, hydro included wind and tidal generation. From January 2008 on, wind and tidal generation are reported separately.
A37: 5 | B37: A power plant in which the prime mover is a steam turbine. The steam used to drive the turbine is produced in a boiler where fossil fuels or other combustible materials are burned. From January 2016 on, this generation is reported as part of combustible fuel generation.
A38: 6 | B38: Electricity generated at an electric power plant whose turbines are driven by steam generated in a reactor by heat from the fission of nuclear fuel.
A39: 7 | B39: A power plant in which the prime mover is an internal combustion turbine. Electric power is generated by converting energy obtained by the rapid burning of a fuel-air mixture into mechanical energy. From January 2016 on, this generation is reported as part of combustible fuel generation.
A40: 8 | B40: A power plant in which the prime mover is a combustion turbine. Electric power is generated by converting energy obtained by burning fuel into mechanical energy. From January 2016 on, this generation is reported as part of combustible fuel generation.
A41: 9 | B41: Total combustible generation includes non-renewable combustible fuels (coal, natural gas, petroleum and other non-renewable combustible fuels) and biomass (wood, spent pulping liquor, methane, municipal waste, other waste and other types of biomass).
A42: 10 | B42: Electric power generated from a plant in which the turbine generators are driven by moving water from tidal flows.
A43: 11 | B43: A power plant in which the prime mover is a wind turbine. Electric power is generated by the conversion of wind power into mechanical energy.
A44: 12 | B44: Electricity created by converting solar radiation through photovoltaic processes or transforming solar radiation captured by concentrating thermal systems.
A48: How to cite: Statistics Canada. Table 25-10-0015-01 Electric power generation, monthly generation by type of electricity
A49: https://www150.statcan.gc.ca/t1/tbl1/en/tv.action?pid=2510001501
A52: NG Breakdown by EPS Plant Type
A53: natural gas steam turbine | B53: =N15/SUM(N15,N17:N18) -> 0.78286526
A54: natural gas combined cycle | B54: 0
A55: natural gas peaker | B55: =SUM(N17:N18)/SUM(N15,N17:N18) -> 0.21713474

Sheet Canada Elec Mix
B1: 2020 | C1: 2021 | D1: 2022 | E1: 2023 | F1: 2024 | G1: 2025 | H1: 2026 | I1: 2027 | J1: 2028 | K1: 2029 | L1: 2030 | M1: 2031 | N1: 2032 | O1: 2033 | P1: 2034 | Q1: 2035 | R1: 2036 | S1: 2037 | T1: 2038 | U1: 2039 | V1: 2040 | W1: 2041 | X1: 2042 | Y1: 2043 | Z1: 2044 | AA1: 2045 | AB1: 2046 | AC1: 2047 | AD1: 2048 | AE1: 2049 | AF1: 2050
A2: hard coal | B2: ='Canada Generation Projection'!Q14/B20 -> 0.049871278 | C2: ='Canada Generation Projection'!R14/C20 -> 0.05570459 | D2: ='Canada Generation Projection'!S14/D20 -> 0.029406679 | E2: ='Canada Generation Projection'!T14/E20 -> 0.0082914781 | F2: ='Canada Generation Projection'!U14/F20 -> 0.0083106362 | G2: ='Canada Generation Projection'!V14/G20 -> 0.0073348873 | H2: ='Canada Generation Projection'!W14/H20 -> 0.0070243911 | I2: ='Canada Generation Projection'!X14/I20 -> 0.0063780498 | ... AF2: ='Canada Generation Projection'!AU14/AF20 -> 0.00010117144
A3: natural gas steam turbine | B3: ='Canada Generation Projection'!Q$15/B$20*'Canada NG Gen by Turbine Type'!$B$53 -> 0.093411097 | C3: ='Canada Generation Projection'!R$15/C$20*'Canada NG Gen by Turbine Type'!$B$53 -> 0.094913318 | D3: ='Canada Generation Projection'!S$15/D$20*'Canada NG Gen by Turbine Type'!$B$53 -> 0.099224442 | E3: ='Canada Generation Projection'!T$15/E$20*'Canada NG Gen by Turbine Type'!$B$53 -> 0.12061842 | F3: ='Canada Generation Projection'!U$15/F$20*'Canada NG Gen by Turbine Type'!$B$53 -> 0.11243635 | G3: ='Canada Generation Projection'!V$15/G$20*'Canada NG Gen by Turbine Type'!$B$53 -> 0.11570779 | H3: ='Canada Generation Projection'!W$15/H$20*'Canada NG Gen by Turbine Type'!$B$53 -> 0.12122634 | I3: ='Canada Generation Projection'!X$15/I$20*'Canada NG Gen by Turbine Type'!$B$53 -> 0.11110197 | ... AF3: ='Canada Generation Projection'!AU$15/AF$20*'Canada NG Gen by Turbine Type'!$B$53 -> 0.061806611
A4: natural gas combined cycle | B4: ='Canada Generation Projection'!Q$15/B$20*'Canada NG Gen by Turbine Type'!$B$54 -> 0 | C4: ='Canada Generation Projection'!R$15/C$20*'Canada NG Gen by Turbine Type'!$B$54 -> 0 | D4: ='Canada Generation Projection'!S$15/D$20*'Canada NG Gen by Turbine Type'!$B$54 -> 0 | E4: ='Canada Generation Projection'!T$15/E$20*'Canada NG Gen by Turbine Type'!$B$54 -> 0 | F4: ='Canada Generation Projection'!U$15/F$20*'Canada NG Gen by Turbine Type'!$B$54 -> 0 | G4: ='Canada Generation Projection'!V$15/G$20*'Canada NG Gen by Turbine Type'!$B$54 -> 0 | H4: ='Canada Generation Projection'!W$15/H$20*'Canada NG Gen by Turbine Type'!$B$54 -> 0 | I4: ='Canada Generation Projection'!X$15/I$20*'Canada NG Gen by Turbine Type'!$B$54 -> 0 | ... AF4: ='Canada Generation Projection'!AU$15/AF$20*'Canada NG Gen by Turbine Type'!$B$54 -> 0
A5: nuclear | B5: ='Canada Generation Projection'!Q13/B20 -> 0.13371461 | C5: ='Canada Generation Projection'!R13/C20 -> 0.12383203 | D5: ='Canada Generation Projection'!S13/D20 -> 0.12240882 | E5: ='Canada Generation Projection'!T13/E20 -> 0.10569686 | F5: ='Canada Generation Projection'!U13/F20 -> 0.11988086 | G5: ='Canada Generation Projection'!V13/G20 -> 0.10876038 | H5: ='Canada Generation Projection'!W13/H20 -> 0.10017687 | I5: ='Canada Generation Projection'!X13/I20 -> 0.10896654 | ... AF5: ='Canada Generation Projection'!AU13/AF20 -> 0.10966865
A6: hydro | B6: ='Canada Generation Projection'!Q9/B20 -> 0.61871683 | C6: ='Canada Generation Projection'!R9/C20 -> 0.61879795 | D6: ='Canada Generation Projection'!S9/D20 -> 0.62526483 | E6: ='Canada Generation Projection'!T9/E20 -> 0.63476648 | F6: ='Canada Generation Projection'!U9/F20 -> 0.6279653 | G6: ='Canada Generation Projection'!V9/G20 -> 0.63172003 | H6: ='Canada Generation Projection'!W9/H20 -> 0.62780157 | I6: ='Canada Generation Projection'!X9/I20 -> 0.62529833 | ... AF6: ='Canada Generation Projection'!AU9/AF20 -> 0.50968831
A7: onshore wind | B7: ='Canada Generation Projection'!Q10/B20 -> 0.056709046 | C7: ='Canada Generation Projection'!R10/C20 -> 0.058589075 | D7: ='Canada Generation Projection'!S10/D20 -> 0.07388148 | E7: ='Canada Generation Projection'!T10/E20 -> 0.074124195 | F7: ='Canada Generation Projection'!U10/F20 -> 0.077730289 | G7: ='Canada Generation Projection'!V10/G20 -> 0.080564413 | H7: ='Canada Generation Projection'!W10/H20 -> 0.080916426 | I7: ='Canada Generation Projection'!X10/I20 -> 0.091008055 | ... AF7: ='Canada Generation Projection'!AU10/AF20 -> 0.2153317
A8: solar PV | B8: ='Canada Generation Projection'!Q12/B20 -> 0.0036116336 | C8: ='Canada Generation Projection'!R12/C20 -> 0.0040794139 | D8: ='Canada Generation Projection'!S12/D20 -> 0.0052549409 | E8: ='Canada Generation Projection'!T12/E20 -> 0.0056383787 | F8: ='Canada Generation Projection'!U12/F20 -> 0.0061239473 | G8: ='Canada Generation Projection'!V12/G20 -> 0.0064315759 | H8: ='Canada Generation Projection'!W12/H20 -> 0.0072853678 | I8: ='Canada Generation Projection'!X12/I20 -> 0.0077602387 | ... AF8: ='Canada Generation Projection'!AU12/AF20 -> 0.070986655
A9: solar thermal | B9: 0 | C9: 0 | D9: 0 | E9: 0 | F9: 0 | G9: 0 | H9: 0 | I9: 0 | J9: 0 | K9: 0 | L9: 0 | M9: 0 | N9: 0 | O9: 0 | P9: 0 | Q9: 0 | R9: 0 | S9: 0 | T9: 0 | U9: 0 | V9: 0 | W9: 0 | X9: 0 | Y9: 0 | Z9: 0 | AA9: 0 | AB9: 0 | AC9: 0 | AD9: 0 | AE9: 0 | AF9: 0
A10: biomass | B10: ='Canada Generation Projection'!Q11/B20 -> 0.01243072 | C10: ='Canada Generation Projection'!R11/C20 -> 0.012469398 | D10: ='Canada Generation Projection'!S11/D20 -> 0.012211091 | E10: ='Canada Generation Projection'!T11/E20 -> 0.012314069 | F10: ='Canada Generation Projection'!U11/F20 -> 0.012202219 | G10: ='Canada Generation Projection'!V11/G20 -> 0.012158165 | H10: ='Canada Generation Projection'!W11/H20 -> 0.012114725 | I10: ='Canada Generation Projection'!X11/I20 -> 0.01199031 | ... AF10: ='Canada Generation Projection'!AU11/AF20 -> 0.00874335
A11: geothermal | B11: 0 | C11: 0 | D11: 0 | E11: 0 | F11: 0 | G11: 0 | H11: 0 | I11: 0 | J11: 0 | K11: 0 | L11: 0 | M11: 0 | N11: 0 | O11: 0 | P11: 0 | Q11: 0 | R11: 0 | S11: 0 | T11: 0 | U11: 0 | V11: 0 | W11: 0 | X11: 0 | Y11: 0 | Z11: 0 | AA11: 0 | AB11: 0 | AC11: 0 | AD11: 0 | AE11: 0 | AF11: 0
A12: petroleum | B12: ='Canada Generation Projection'!Q16/B20 -> 0.005626375 | C12: ='Canada Generation Projection'!R16/C20 -> 0.0052891614 | D12: ='Canada Generation Projection'!S16/D20 -> 0.0048269163 | E12: ='Canada Generation Projection'!T16/E20 -> 0.0050955044 | F12: ='Canada Generation Projection'!U16/F20 -> 0.004165158 | G12: ='Canada Generation Projection'!V16/G20 -> 0.0052301543 | H12: ='Canada Generation Projection'!W16/H20 -> 0.0098310942 | I12: ='Canada Generation Projection'!X16/I20 -> 0.0066813756 | ... AF12: ='Canada Generation Projection'!AU16/AF20 -> 0.0065309353
A13: natural gas peaker | B13: ='Canada Generation Projection'!Q$15/B$20*'Canada NG Gen by Turbine Type'!$B$55 -> 0.02590841 | C13: ='Canada Generation Projection'!R$15/C$20*'Canada NG Gen by Turbine Type'!$B$55 -> 0.026325064 | D13: ='Canada Generation Projection'!S$15/D$20*'Canada NG Gen by Turbine Type'!$B$55 -> 0.027520793 | E13: ='Canada Generation Projection'!T$15/E$20*'Canada NG Gen by Turbine Type'!$B$55 -> 0.033454607 | F13: ='Canada Generation Projection'!U$15/F$20*'Canada NG Gen by Turbine Type'!$B$55 -> 0.031185235 | G13: ='Canada Generation Projection'!V$15/G$20*'Canada NG Gen by Turbine Type'!$B$55 -> 0.032092599 | H13: ='Canada Generation Projection'!W$15/H$20*'Canada NG Gen by Turbine Type'!$B$55 -> 0.033623219 | I13: ='Canada Generation Projection'!X$15/I$20*'Canada NG Gen by Turbine Type'!$B$55 -> 0.030815132 | ... AF13: ='Canada Generation Projection'!AU$15/AF$20*'Canada NG Gen by Turbine Type'!$B$55 -> 0.017142621
A14: lignite | B14: 0 | C14: 0 | D14: 0 | E14: 0 | F14: 0 | G14: 0 | H14: 0 | I14: 0 | J14: 0 | K14: 0 | L14: 0 | M14: 0 | N14: 0 | O14: 0 | P14: 0 | Q14: 0 | R14: 0 | S14: 0 | T14: 0 | U14: 0 | V14: 0 | W14: 0 | X14: 0 | Y14: 0 | Z14: 0 | AA14: 0 | AB14: 0 | AC14: 0 | AD14: 0 | AE14: 0 | AF14: 0
A15: offshore wind | B15: 0 | C15: 0 | D15: 0 | E15: 0 | F15: 0 | G15: 0 | H15: 0 | I15: 0 | J15: 0 | K15: 0 | L15: 0 | M15: 0 | N15: 0 | O15: 0 | P15: 0 | Q15: 0 | R15: 0 | S15: 0 | T15: 0 | U15: 0 | V15: 0 | W15: 0 | X15: 0 | Y15: 0 | Z15: 0 | AA15: 0 | AB15: 0 | AC15: 0 | AD15: 0 | AE15: 0 | AF15: 0
A16: crude oil | B16: 0 | C16: 0 | D16: 0 | E16: 0 | F16: 0 | G16: 0 | H16: 0 | I16: 0 | J16: 0 | K16: 0 | L16: 0 | M16: 0 | N16: 0 | O16: 0 | P16: 0 | Q16: 0 | R16: 0 | S16: 0 | T16: 0 | U16: 0 | V16: 0 | W16: 0 | X16: 0 | Y16: 0 | Z16: 0 | AA16: 0 | AB16: 0 | AC16: 0 | AD16: 0 | AE16: 0 | AF16: 0
A17: heavy or residual fuel oil | B17: 0 | C17: 0 | D17: 0 | E17: 0 | F17: 0 | G17: 0 | H17: 0 | I17: 0 | J17: 0 | K17: 0 | L17: 0 | M17: 0 | N17: 0 | O17: 0 | P17: 0 | Q17: 0 | R17: 0 | S17: 0 | T17: 0 | U17: 0 | V17: 0 | W17: 0 | X17: 0 | Y17: 0 | Z17: 0 | AA17: 0 | AB17: 0 | AC17: 0 | AD17: 0 | AE17: 0 | AF17: 0
A18: municipal solid waste | B18: 0 | C18: 0 | D18: 0 | E18: 0 | F18: 0 | G18: 0 | H18: 0 | I18: 0 | J18: 0 | K18: 0 | L18: 0 | M18: 0 | N18: 0 | O18: 0 | P18: 0 | Q18: 0 | R18: 0 | S18: 0 | T18: 0 | U18: 0 | V18: 0 | W18: 0 | X18: 0 | Y18: 0 | Z18: 0 | AA18: 0 | AB18: 0 | AC18: 0 | AD18: 0 | AE18: 0 | AF18: 0
A20: Sum of Canada Generation | B20: =SUM(Table15[2020]) -> 624124.77 | C20: =SUM(Table15[2021]) -> 635025.05 | D20: =SUM(Table15[2022]) -> 662134.95 | E20: =SUM(Table15[2023]) -> 661479.16 | F20: =SUM(Table15[2024]) -> 669724.9 | G20: =SUM(Table15[2025]) -> 674750.65 | H20: =SUM(Table15[2026]) -> 679256.03 | I20: =SUM(Table15[2027]) -> 682236.75 | J20: =SUM(Table15[2028]) -> 687482.16 | K20: =SUM(Table15[2029]) -> 693088.12 | L20: =SUM(Table15[2030]) -> 708052.06 | M20: =SUM(Table15[2031]) -> 718368.89 | N20: =SUM(Table15[2032]) -> 722783.21 | O20: =SUM(Table15[2033]) -> 726806.45 | P20: =SUM(Table15[2034]) -> 733530.54 | Q20: =SUM(Table15[2035]) -> 740490.73 | R20: =SUM(Table15[2036]) -> 737450.58 | S20: =SUM(Table15[2037]) -> 742988.3 | T20: =SUM(Table15[2038]) -> 751284.56 | U20: =SUM(Table15[2039]) -> 758525.56 | V20: =SUM(Table15[2040]) -> 768472.94 | W20: =SUM(Table15[2041]) -> 774344.35 | X20: =SUM(Table15[2042]) -> 786697.66 | Y20: =SUM(Table15[2043]) -> 799962.03 | Z20: =SUM(Table15[2044]) -> 817333.19 | AA20: =SUM(Table15[2045]) -> 829175.85 | AB20: =SUM(Table15[2046]) -> 841871.94 | AC20: =SUM(Table15[2047]) -> 851081.92 | AD20: =SUM(Table15[2048]) -> 860725.04 | AE20: =SUM(Table15[2049]) -> 868040.47 | AF20: =SUM(Table15[2050]) -> 875938.86

Sheet AEO Table 3 2025
A1: Table 3. Energy Prices by Sector and Source
A2: https://www.eia.gov/outlooks/aeo/data/browser/#/?id=3-AEO2025&cases=highZTC&sourcekey=0
A3: Tue Dec 02 2025 13:12:56 GMT-0800 (Pacific Standard Time)
A4: Source: U.S. Energy Information Administration
B5: full name | C5: api key | D5: units | E5: 2023 | F5: 2024 | G5: 2025 | H5: 2026 | I5: 2027 | J5: 2028 | K5: 2029 | L5: 2030 | M5: 2031 | N5: 2032 | O5: 2033 | P5: 2034 | Q5: 2035 | R5: 2036 | S5: 2037 | T5: 2038 | U5: 2039 | V5: 2040 | W5: 2041 | X5: 2042 | Y5: 2043 | Z5: 2044 | AA5: 2045 | AB5: 2046 | AC5: 2047 | AD5: 2048 | AE5: 2049 | AF5: 2050 | AG5: Growth (2024-2050)
A6: Residential
A7: Propane | B7: Energy Prices: Residential: Propane: High Zero-Carbon Technology Cost | C7: AEO.2025.HIGHZTC.PRCE_REAL_RESD_NA_PROP_NA_NA_Y13DLRPMMBTU.A | D7: 2024 $/MMBtu | F7: 26.593981 | G7: 25.690693 | H7: 25.882023 | I7: 25.734011 | J7: 25.761881 | K7: 25.984186 | L7: 26.494528 | M7: 27.035074 | N7: 27.848438 | O7: 28.895929 | P7: 29.836832 | Q7: 30.497536 | R7: 30.975727 | S7: 31.295523 | T7: 31.443632 | U7: 31.521713 | V7: 31.634783 | W7: 31.863678 | X7: 32.095478 | Y7: 32.443432 | Z7: 32.908676 | AA7: 33.216011 | AB7: 33.459888 | AC7: 33.58733 | AD7: 33.707253 | AE7: 33.953312 | AF7: 34.455376 | AG7: 0.01
A8: Distillate Fuel Oil | B8: Energy Prices: Residential: Distillate Fuel Oil: High Zero-Carbon Technology Cost | C8: AEO.2025.HIGHZTC.PRCE_REAL_RESD_NA_DFO_NA_NA_Y13DLRPMMBTU.A | D8: 2024 $/MMBtu | F8: 26.158379 | G8: 24.617764 | H8: 24.643763 | I8: 25.310112 | J8: 26.17977 | K8: 27.100401 | L8: 28.068832 | M8: 28.11725 | N8: 28.0326 | O8: 28.357315 | P8: 28.466999 | Q8: 28.689667 | R8: 28.809559 | S8: 29.071898 | T8: 29.171333 | U8: 29.291199 | V8: 29.469152 | W8: 29.758438 | X8: 29.994083 | Y8: 30.294477 | Z8: 30.955036 | AA8: 30.868721 | AB8: 30.956972 | AC8: 30.914091 | AD8: 30.902479 | AE8: 30.934729 | AF8: 31.279491 | AG8: 0.007
A9: Natural Gas | B9: Energy Prices: Residential: Natural Gas: High Zero-Carbon Technology Cost | C9: AEO.2025.HIGHZTC.PRCE_REAL_RESD_NA_NG_NA_NA_Y13DLRPMMBTU.A | D9: 2024 $/MMBtu | F9: 13.932205 | G9: 12.694278 | H9: 12.476946 | I9: 12.0713 | J9: 11.825522 | K9: 11.708606 | L9: 11.628035 | M9: 11.829365 | N9: 12.259671 | O9: 12.641685 | P9: 12.901601 | Q9: 13.046376 | R9: 13.061166 | S9: 13.048336 | T9: 13.026576 | U9: 12.968637 | V9: 13.000326 | W9: 13.125381 | X9: 13.234643 | Y9: 13.327177 | Z9: 13.385166 | AA9: 13.471466 | AB9: 13.568365 | AC9: 13.612545 | AD9: 13.641063 | AE9: 13.722773 | AF9: 13.794634 | AG9: 0
A10: Electricity | B10: Energy Prices: Residential: Electricity: High Zero-Carbon Technology Cost | C10: AEO.2025.HIGHZTC.PRCE_REAL_RESD_NA_ELC_NA_NA_Y13DLRPMMBTU.A | D10: 2024 $/MMBtu | F10: 45.553139 | G10: 45.024025 | H10: 42.541679 | I10: 40.45982 | J10: 40.182793 | K10: 40.569782 | L10: 41.046375 | M10: 41.716888 | N10: 42.268425 | O10: 43.117485 | P10: 43.465755 | Q10: 43.342434 | R10: 43.037926 | S10: 42.73064 | T10: 42.891632 | U10: 42.628983 | V10: 42.525494 | W10: 42.545128 | X10: 42.731728 | Y10: 42.921192 | Z10: 43.168861 | AA10: 43.377872 | AB10: 43.621025 | AC10: 43.79406 | AD10: 44.126114 | AE10: 44.423275 | AF10: 44.787258 | AG10: -0.001
A11: Commercial
A12: Propane | B12: Energy Prices: Commercial: Propane: High Zero-Carbon Technology Cost | C12: AEO.2025.HIGHZTC.PRCE_REAL_COMM_NA_PROP_NA_NA_Y13DLRPMMBTU.A | D12: 2024 $/MMBtu | F12: 19.0868 | G12: 19.071598 | H12: 19.969246 | I12: 19.804914 | J12: 19.920181 | K12: 20.219919 | L12: 20.798326 | M12: 21.250935 | N12: 22.027008 | O12: 22.973885 | P12: 23.6208 | Q12: 23.91017 | R12: 24.102671 | S12: 24.204554 | T12: 24.180492 | U12: 24.168512 | V12: 24.257711 | W12: 24.494383 | X12: 24.6768 | Y12: 25.001261 | Z12: 25.422537 | AA12: 25.562656 | AB12: 25.683006 | AC12: 25.692684 | AD12: 25.758125 | AE12: 26.007099 | AF12: 26.538202 | AG12: 0.013
A13: Distillate Fuel Oil | B13: Energy Prices: Commercial: Distillate Fuel Oil: High Zero-Carbon Technology Cost | C13: AEO.2025.HIGHZTC.PRCE_REAL_COMM_NA_DFO_NA_NA_Y13DLRPMMBTU.A | D13: 2024 $/MMBtu | F13: 26.207932 | G13: 24.707527 | H13: 23.565269 | I13: 23.058794 | J13: 22.754671 | K13: 22.501291 | L13: 22.297827 | M13: 22.340889 | N13: 22.216309 | O13: 22.527172 | P13: 22.633039 | Q13: 22.83795 | R13: 22.942883 | S13: 23.194223 | T13: 23.297205 | U13: 23.403837 | V13: 23.570314 | W13: 23.852497 | X13: 24.078636 | Y13: 24.381926 | Z13: 25.030125 | AA13: 24.942905 | AB13: 25.028816 | AC13: 24.984297 | AD13: 24.964209 | AE13: 25.003876 | AF13: 25.3452 | AG13: -0.001
A14: Residual Fuel Oil | B14: Energy Prices: Commercial: Residual Fuel: High Zero-Carbon Technology Cost | C14: AEO.2025.HIGHZTC.PRCE_REAL_COMM_NA_RFL_NA_NA_Y13DLRPMMBTU.A | D14: 2024 $/MMBtu | F14: 6.746078 | G14: 7.471698 | H14: 7.841193 | I14: 8.831597 | J14: 9.914908 | K14: 11.015342 | L14: 12.183045 | M14: 12.244162 | N14: 12.208694 | O14: 12.446174 | P14: 12.544676 | Q14: 12.678741 | R14: 12.753716 | S14: 12.87225 | T14: 12.979047 | U14: 12.997785 | V14: 13.118733 | W14: 13.235469 | X14: 13.365701 | Y14: 13.416109 | Z14: 13.347304 | AA14: 13.387928 | AB14: 13.678938 | AC14: 13.632569 | AD14: 13.671235 | AE14: 13.775191 | AF14: 14.322314 | AG14: 0.029
A15: Natural Gas | B15: Energy Prices: Commercial: Natural Gas: High Zero-Carbon Technology Cost | C15: AEO.2025.HIGHZTC.PRCE_REAL_COMM_NA_NG_NA_NA_Y13DLRPMMBTU.A | D15: 2024 $/MMBtu | F15: 9.555858 | G15: 8.473628 | H15: 8.571372 | I15: 8.513054 | J15: 8.593106 | K15: 8.767466 | L15: 8.976199 | M15: 9.121284 | N15: 9.472503 | O15: 9.787833 | P15: 9.988475 | Q15: 10.085086 | R15: 10.067373 | S15: 10.026683 | T15: 9.977905 | U15: 9.894558 | V15: 9.894806 | W15: 9.981339 | X15: 10.052937 | Y15: 10.11166 | Z15: 10.137436 | AA15: 10.191541 | AB15: 10.258538 | AC15: 10.274831 | AD15: 10.279621 | AE15: 10.336456 | AF15: 10.384078 | AG15: 0.003
A16: Electricity | B16: Energy Prices: Commercial: Electricity: High Zero-Carbon Technology Cost | C16: AEO.2025.HIGHZTC.PRCE_REAL_COMM_NA_ELC_NA_NA_Y13DLRPMMBTU.A | D16: 2024 $/MMBtu | F16: 38.551605 | G16: 37.602798 | H16: 35.105431 | I16: 33.124508 | J16: 32.965439 | K16: 33.32024 | L16: 33.809681 | M16: 34.413387 | N16: 34.929173 | O16: 35.701324 | P16: 35.979614 | Q16: 35.811676 | R16: 35.482807 | S16: 35.191898 | T16: 35.411739 | U16: 35.115093 | V16: 34.986004 | W16: 34.99255 | X16: 35.154461 | Y16: 35.305714 | Z16: 35.501835 | AA16: 35.64677 | AB16: 35.79763 | AC16: 35.841282 | AD16: 36.080368 | AE16: 36.286304 | AF16: 36.524944 | AG16: -0.002
A17: Industrial
A18: Propane | B18: Energy Prices: Industrial: Propane: High Zero-Carbon Technology Cost | C18: AEO.2025.HIGHZTC.PRCE_REAL_IDAL_NA_PROP_NA_NA_Y13DLRPMMBTU.A | D18: 2024 $/MMBtu | F18: 12.66026 | G18: 12.605674 | H18: 13.465074 | I18: 13.314802 | J18: 13.427592 | K18: 13.72262 | L18: 14.298682 | M18: 14.759735 | N18: 15.554036 | O18: 16.543209 | P18: 17.23724 | Q18: 17.555822 | R18: 17.767212 | S18: 17.880009 | T18: 17.856604 | U18: 17.844084 | V18: 17.93939 | W18: 18.19438 | X18: 18.394274 | Y18: 18.748419 | Z18: 19.21232 | AA18: 19.372681 | AB18: 19.508192 | AC18: 19.52129 | AD18: 19.593958 | AE18: 19.869528 | AF18: 20.462763 | AG18: 0.019
A19: Distillate Fuel Oil | B19: Energy Prices: Industrial: Distillate Fuel Oil: High Zero-Carbon Technology Cost | C19: AEO.2025.HIGHZTC.PRCE_REAL_IDAL_NA_DFO_NA_NA_Y13DLRPMMBTU.A | D19: 2024 $/MMBtu | F19: 26.091763 | G19: 24.600626 | H19: 23.425852 | I19: 22.88941 | J19: 22.557371 | K19: 22.274755 | L19: 22.032902 | M19: 22.079994 | N19: 21.943752 | O19: 22.273958 | P19: 22.39349 | Q19: 22.623447 | R19: 22.746523 | S19: 23.008989 | T19: 23.10652 | U19: 23.218241 | V19: 23.399351 | W19: 23.679426 | X19: 23.916767 | Y19: 24.223963 | Z19: 24.880014 | AA19: 24.792429 | AB19: 24.880751 | AC19: 24.838329 | AD19: 24.82336 | AE19: 24.858402 | AF19: 25.202454 | AG19: -0.001
A20: Residual Fuel Oil | B20: Energy Prices: Industrial: Residual Fuel Oil: High Zero-Carbon Technology Cost | C20: AEO.2025.HIGHZTC.PRCE_REAL_IDAL_NA_RFO_NA_NA_Y13DLRPMMBTU.A | D20: 2024 $/MMBtu | F20: 7.83466 | G20: 8.848094 | H20: 9.435161 | I20: 10.629246 | J20: 11.88067 | K20: 13.214781 | L20: 14.622335 | M20: 14.725853 | N20: 14.700524 | O20: 14.992572 | P20: 15.113938 | Q20: 15.285793 | R20: 15.383565 | S20: 15.518867 | T20: 15.634306 | U20: 15.663942 | V20: 15.779115 | W20: 15.889836 | X20: 16.038828 | Y20: 16.101131 | Z20: 16.053886 | AA20: 16.051018 | AB20: 16.34535 | AC20: 16.306047 | AD20: 16.344069 | AE20: 16.451635 | AF20: 16.998318 | AG20: 0.03
A21: Natural Gas | B21: Energy Prices: Industrial: Natural Gas: High Zero-Carbon Technology Cost | C21: AEO.2025.HIGHZTC.PRCE_REAL_IDAL_NA_NG_NA_NA_Y13DLRPMMBTU.A | D21: 2024 $/MMBtu | F21: 3.33707 | G21: 4.010599 | H21: 3.911485 | I21: 3.791521 | J21: 3.869612 | K21: 4.020249 | L21: 4.230658 | M21: 4.390093 | N21: 4.830755 | O21: 5.179088 | P21: 5.412342 | Q21: 5.494054 | R21: 5.481412 | S21: 5.430798 | T21: 5.370685 | U21: 5.290253 | V21: 5.310672 | W21: 5.403639 | X21: 5.486475 | Y21: 5.561241 | Z21: 5.615677 | AA21: 5.665632 | AB21: 5.71713 | AC21: 5.72265 | AD21: 5.7369 | AE21: 5.797705 | AF21: 5.862935 | AG21: 0.022
A22: Metallurgical Coal | B22: Energy Prices: Industrial: Metallurgical Coal: High Zero-Carbon Technology Cost | C22: AEO.2025.HIGHZTC.PRCE_REAL_IDAL_NA_MTC_NA_NA_Y13DLRPMMBTU.A | D22: 2024 $/MMBtu | F22: 7.767755 | G22: 7.639748 | H22: 7.585148 | I22: 7.555212 | J22: 7.520931 | K22: 7.512826 | L22: 7.510444 | M22: 7.515949 | N22: 7.537591 | O22: 7.537167 | P22: 7.49989 | Q22: 7.518089 | R22: 7.517967 | S22: 7.515557 | T22: 7.51727 | U22: 7.498265 | V22: 7.496222 | W22: 7.466915 | X22: 7.461041 | Y22: 7.453232 | Z22: 7.458103 | AA22: 7.471511 | AB22: 7.467525 | AC22: 7.46251 | AD22: 7.461265 | AE22: 7.469367 | AF22: 7.466943 | AG22: -0.002
A23: Other Industrial Coal | B23: Energy Prices: Industrial: Other Industrial Coal: High Zero-Carbon Technology Cost | C23: AEO.2025.HIGHZTC.PRCE_REAL_IDAL_NA_OIC_NA_NA_Y13DLRPMMBTU.A | D23: 2024 $/MMBtu | F23: 3.572155 | G23: 3.624099 | H23: 3.618806 | I23: 3.601768 | J23: 3.571336 | K23: 3.55915 | L23: 3.533537 | M23: 3.497851 | N23: 3.464142 | O23: 3.459587 | P23: 3.441433 | Q23: 3.415449 | R23: 3.421638 | S23: 3.423545 | T23: 3.432421 | U23: 3.428609 | V23: 3.430913 | W23: 3.425192 | X23: 3.418891 | Y23: 3.422088 | Z23: 3.426063 | AA23: 3.434236 | AB23: 3.444175 | AC23: 3.448749 | AD23: 3.448136 | AE23: 3.449347 | AF23: 3.454516 | AG23: -0.001
A24: Hydrogen | B24: Energy Prices: Industrial: Hydrogen: High Zero-Carbon Technology Cost | C24: AEO.2025.HIGHZTC.PRCE_REAL_IDAL_NA_HDG_NA_NA_Y13DLRPMMBTU.A | D24: 2024 $/MMBtu | F24: 9.533875 | G24: 10.619709 | H24: 10.514131 | I24: 10.426125 | J24: 10.55792 | K24: 10.787679 | L24: 11.065716 | M24: 11.319676 | N24: 11.63994 | O24: 12.155972 | P24: 12.524699 | Q24: 12.666781 | R24: 12.616203 | S24: 12.533028 | T24: 12.742199 | U24: 12.81229 | V24: 12.800771 | W24: 12.675635 | X24: 12.587033 | Y24: 12.651853 | Z24: 12.824852 | AA24: 12.7927 | AB24: 12.813029 | AC24: 12.789708 | AD24: 12.823941 | AE24: 12.685263 | AF24: 12.783066 | AG24: 0.011
A25: Electricity | B25: Energy Prices: Industrial: Electricity: High Zero-Carbon Technology Cost | C25: AEO.2025.HIGHZTC.PRCE_REAL_IDAL_NA_ELC_NA_NA_Y13DLRPMMBTU.A | D25: 2024 $/MMBtu | F25: 26.507746 | G25: 25.922054 | H25: 23.537739 | I25: 22.156487 | J25: 22.004316 | K25: 22.322678 | L25: 22.749052 | M25: 23.346399 | N25: 23.998974 | O25: 24.751463 | P25: 24.95269 | Q25: 24.768763 | R25: 24.45256 | S25: 24.243956 | T25: 24.34145 | U25: 24.228069 | V25: 24.145441 | W25: 24.157953 | X25: 24.287434 | Y25: 24.39603 | Z25: 24.534168 | AA25: 24.641457 | AB25: 24.755726 | AC25: 24.854349 | AD25: 25.022724 | AE25: 25.199516 | AF25: 25.411121 | AG25: -0.002
A26: Transportation
A27: Propane | B27: Energy Prices: Transportation: Propane: High Zero-Carbon Technology Cost | C27: AEO.2025.HIGHZTC.PRCE_REAL_TRN_NA_PROP_NA_NA_Y13DLRPMMBTU.A | D27: 2024 $/MMBtu | F27: 17.589245 | G27: 17.749908 | H27: 18.586613 | I27: 18.389212 | J27: 18.496126 | K27: 18.760077 | L27: 19.2631 | M27: 19.634487 | N27: 20.300226 | O27: 21.098251 | P27: 21.613922 | Q27: 21.826738 | R27: 21.975828 | S27: 22.052736 | T27: 22.024448 | U27: 22.014761 | V27: 22.09473 | W27: 22.299959 | X27: 22.448139 | Y27: 22.723597 | Z27: 23.076363 | AA27: 23.174244 | AB27: 23.269659 | AC27: 23.270405 | AD27: 23.326803 | AE27: 23.542395 | AF27: 23.995331 | AG27: 0.012
A28: E85 | B28: Energy Prices: Transportation: E85: High Zero-Carbon Technology Cost | C28: AEO.2025.HIGHZTC.PRCE_REAL_TRN_NA_E85_NA_NA_Y13DLRPMMBTU.A | D28: 2024 $/MMBtu | F28: 28.823729 | G28: 28.93619 | H28: 30.221819 | I28: 29.874352 | J28: 29.356659 | K28: 28.412943 | L28: 28.414833 | M28: 28.528875 | N28: 28.297775 | O28: 28.022879 | P28: 27.970562 | Q28: 27.737436 | R28: 27.879841 | S28: 27.706806 | T28: 27.335274 | U28: 27.221582 | V28: 26.936087 | W28: 26.624407 | X28: 26.243464 | Y28: 26.249161 | Z28: 24.929926 | AA28: 24.592495 | AB28: 24.79623 | AC28: 24.925064 | AD28: 24.988291 | AE28: 25.141323 | AF28: 25.433138 | AG28: -0.005
A29: Motor Gasoline | B29: Energy Prices: Transportation: Motor Gasoline: High Zero-Carbon Technology Cost | C29: AEO.2025.HIGHZTC.PRCE_REAL_TRN_NA_MGS_NA_NA_Y13DLRPMMBTU.A | D29: 2024 $/MMBtu | F29: 28.679842 | G29: 27.094545 | H29: 25.485424 | I29: 24.986969 | J29: 24.719851 | K29: 24.436867 | L29: 24.474363 | M29: 24.48147 | N29: 24.300167 | O29: 24.154732 | P29: 24.09795 | Q29: 23.894083 | R29: 24.019566 | S29: 23.870735 | T29: 23.556276 | U29: 23.430714 | V29: 23.173237 | W29: 22.909204 | X29: 22.57633 | Y29: 22.596951 | Z29: 21.468903 | AA29: 21.182211 | AB29: 21.356647 | AC29: 21.464962 | AD29: 21.509295 | AE29: 21.631233 | AF29: 21.869665 | AG29: -0.01
A30: Jet Fuel | B30: Energy Prices: Transportation: Jet Fuel: High Zero-Carbon Technology Cost | C30: AEO.2025.HIGHZTC.PRCE_REAL_TRN_NA_JFL_NA_NA_Y13DLRPMMBTU.A | D30: 2024 $/MMBtu | F30: 17.638924 | G30: 16.395 | H30: 16.197346 | I30: 16.576864 | J30: 17.167725 | K30: 17.774681 | L30: 18.432444 | M30: 18.550699 | N30: 18.432102 | O30: 18.750156 | P30: 18.878136 | Q30: 19.088032 | R30: 19.162302 | S30: 19.413189 | T30: 19.636925 | U30: 19.743242 | V30: 19.910463 | W30: 20.238554 | X30: 20.505775 | Y30: 20.876812 | Z30: 21.614872 | AA30: 21.580616 | AB30: 21.698483 | AC30: 21.705061 | AD30: 21.706541 | AE30: 21.788584 | AF30: 22.195864 | AG30: 0.009
A31: Diesel Fuel (distillate fuel oil) | B31: Energy Prices: Transportation: Diesel Fuel: High Zero-Carbon Technology Cost | C31: AEO.2025.HIGHZTC.PRCE_REAL_TRN_NA_DFU_NA_NA_Y13DLRPMMBTU.A | D31: 2024 $/MMBtu | F31: 27.283649 | G31: 25.591213 | H31: 25.016569 | I31: 25.029736 | J31: 25.250086 | K31: 25.481937 | L31: 25.837044 | M31: 25.879503 | N31: 25.733622 | O31: 26.102192 | P31: 26.219612 | Q31: 26.457941 | R31: 26.618042 | S31: 26.882929 | T31: 26.978115 | U31: 27.113096 | V31: 27.266804 | W31: 27.578503 | X31: 27.813025 | Y31: 28.145802 | Z31: 28.854143 | AA31: 28.858868 | AB31: 28.825182 | AC31: 28.706501 | AD31: 28.759977 | AE31: 28.70521 | AF31: 29.126087 | AG31: 0.003
A32: Residual Fuel Oil | B32: Energy Prices: Transportation: Residual Fuel Oil: High Zero-Carbon Technology Cost | C32: AEO.2025.HIGHZTC.PRCE_REAL_TRN_NA_RFO_NA_NA_Y13DLRPMMBTU.A | D32: 2024 $/MMBtu | F32: 13.401297 | G32: 11.843807 | H32: 12.665238 | I32: 12.576532 | J32: 12.510175 | K32: 12.503057 | L32: 12.525302 | M32: 12.597067 | N32: 12.550599 | O32: 12.745926 | P32: 12.831242 | Q32: 12.954171 | R32: 13.008114 | S32: 13.096881 | T32: 13.191089 | U32: 13.218472 | V32: 13.301097 | W32: 13.406687 | X32: 13.509968 | Y32: 13.614932 | Z32: 13.650314 | AA32: 13.473039 | AB32: 13.708124 | AC32: 13.688977 | AD32: 13.7072 | AE32: 13.794828 | AF32: 14.231298 | AG32: 0.002
A33: Natural Gas | B33: Energy Prices: Transportation: Natural Gas: High Zero-Carbon Technology Cost | C33: AEO.2025.HIGHZTC.PRCE_REAL_TRN_NA_NG_NA_NA_Y13DLRPMMBTU.A | D33: 2024 $/MMBtu | F33: 14.514303 | G33: 15.045484 | H33: 14.977668 | I33: 14.858115 | J33: 14.908598 | K33: 15.040533 | L33: 15.186421 | M33: 15.299401 | N33: 15.666859 | O33: 15.903211 | P33: 16.017698 | Q33: 16.016142 | R33: 15.907859 | S33: 15.77169 | T33: 15.650945 | U33: 15.47576 | V33: 15.403385 | W33: 15.417639 | X33: 15.41606 | Y33: 15.414666 | Z33: 15.384685 | AA33: 15.361653 | AB33: 15.353804 | AC33: 15.281762 | AD33: 15.215751 | AE33: 15.207031 | AF33: 15.19101 | AG33: 0.002
A34: Hydrogen | B34: Energy Prices: Transportation: Hydrogen: High Zero-Carbon Technology Cost | C34: AEO.2025.HIGHZTC.PRCE_REAL_TRN_NA_HDG_NA_NA_Y13DLRPMMBTU.A | D34: 2024 $/MMBtu | F34: 60.468231 | G34: 60.745255 | H34: 60.549759 | I34: 60.44437 | J34: 60.531708 | K34: 60.737736 | L34: 60.991833 | M34: 61.818279 | N34: 62.04599 | O34: 62.676136 | P34: 63.049198 | Q34: 63.198536 | R34: 63.044495 | S34: 62.949413 | T34: 63.204426 | U34: 63.33548 | V34: 63.306995 | W34: 63.132828 | X34: 62.969875 | Y34: 63.022812 | Z34: 63.25135 | AA34: 63.215389 | AB34: 63.382431 | AC34: 63.355698 | AD34: 63.409069 | AE34: 63.016552 | AF34: 63.101322 | AG34: 0.002
A35: Electricity | B35: Energy Prices: Transportation: Electricity: High Zero-Carbon Technology Cost | C35: AEO.2025.HIGHZTC.PRCE_REAL_TRN_NA_ELC_NA_NA_Y13DLRPMMBTU.A | D35: 2024 $/MMBtu | F35: 42.609589 | G35: 42.26667 | H35: 39.670399 | I35: 36.717178 | J35: 36.535248 | K35: 36.81496 | L35: 37.285934 | M35: 38.057724 | N35: 38.70388 | O35: 39.740459 | P35: 40.09803 | Q35: 40.153744 | R35: 40.057587 | S35: 39.782898 | T35: 40.15593 | U35: 39.589664 | V35: 39.300087 | W35: 39.269657 | X35: 39.614471 | Y35: 39.822304 | Z35: 40.184521 | AA35: 40.37289 | AB35: 40.537704 | AC35: 40.4916 | AD35: 41.027618 | AE35: 41.285618 | AF35: 41.592472 | AG35: -0.001
A36: Electric Power
A37: Distillate Fuel Oil | B37: Energy Prices: Electric Power: Distillate Fuel Oil: High Zero-Carbon Technology Cost | C37: AEO.2025.HIGHZTC.PRCE_REAL_ELEP_NA_DFO_NA_NA_Y13DLRPMMBTU.A | D37: 2024 $/MMBtu | F37: 26.137505 | G37: 24.653458 | H37: 23.463963 | I37: 22.977613 | J37: 22.593882 | K37: 22.342915 | L37: 22.213257 | M37: 22.156206 | N37: 22.726322 | O37: 23.003592 | P37: 23.077461 | Q37: 23.249807 | R37: 23.28072 | S37: 23.52141 | T37: 23.668085 | U37: 23.751266 | V37: 23.886726 | W37: 24.176956 | X37: 24.404095 | Y37: 24.709991 | Z37: 25.257483 | AA37: 25.158951 | AB37: 25.341908 | AC37: 25.316826 | AD37: 25.294249 | AE37: 25.372868 | AF37: 25.729799 | AG37: -0.001
A38: Residual Fuel Oil | B38: Energy Prices: Electric Power: Residual Fuel Oil: High Zero-Carbon Technology Cost | C38: AEO.2025.HIGHZTC.PRCE_REAL_ELEP_NA_RFO_NA_NA_Y13DLRPMMBTU.A | D38: 2024 $/MMBtu | F38: 17.394409 | G38: 13.672506 | H38: 13.615168 | I38: 14.296899 | J38: 15.031581 | K38: 15.753065 | L38: 16.474405 | M38: 16.627272 | N38: 16.536289 | O38: 16.771885 | P38: 16.909727 | Q38: 17.088612 | R38: 17.157686 | S38: 17.269447 | T38: 17.398418 | U38: 17.408293 | V38: 17.490879 | W38: 17.551632 | X38: 17.536398 | Y38: 17.589537 | Z38: 17.510019 | AA38: 16.884666 | AB38: 17.201757 | AC38: 17.213936 | AD38: 17.253027 | AE38: 17.380194 | AF38: 17.916069 | AG38: 0.001
A39: Natural Gas | B39: Energy Prices: Electric Power: Natural Gas: High Zero-Carbon Technology Cost | C39: AEO.2025.HIGHZTC.PRCE_REAL_ELEP_NA_NG_NA_NA_Y13DLRPMMBTU.A | D39: 2024 $/MMBtu | F39: 2.719399 | G39: 3.131506 | H39: 3.068464 | I39: 2.996603 | J39: 3.12604 | K39: 3.327426 | L39: 3.603756 | M39: 3.695694 | N39: 4.197338 | O39: 4.507975 | P39: 4.717876 | Q39: 4.789361 | R39: 4.78448 | S39: 4.749629 | T39: 4.715602 | U39: 4.659969 | V39: 4.690855 | W39: 4.769531 | X39: 4.842232 | Y39: 4.929382 | Z39: 5.014789 | AA39: 5.059572 | AB39: 5.116513 | AC39: 5.124822 | AD39: 5.147723 | AE39: 5.21766 | AF39: 5.297616 | AG39: 0.026
A40: Steam Coal | B40: Energy Prices: Electric Power: Steam Coal: High Zero-Carbon Technology Cost | C40: AEO.2025.HIGHZTC.PRCE_REAL_ELEP_NA_STC_NA_NA_Y13DLRPMMBTU.A | D40: 2024 $/MMBtu | F40: 2.489397 | G40: 2.427415 | H40: 2.375483 | I40: 2.326139 | J40: 2.226495 | K40: 2.226722 | L40: 2.247866 | M40: 2.217924 | N40: 2.149103 | O40: 2.152961 | P40: 2.139093 | Q40: 2.125588 | R40: 2.125613 | S40: 2.15652 | T40: 2.152304 | U40: 2.213794 | V40: 2.210829 | W40: 2.208087 | X40: 2.206623 | Y40: 2.207428 | Z40: 2.207163 | AA40: 2.196095 | AB40: 1.887973 | AC40: 2.178344 | AD40: 2.178153 | AE40: 2.195496 | AF40: 2.192112 | AG40: -0.005
A41: Uranium | B41: Energy Prices: Electric Power: Uranium: High Zero-Carbon Technology Cost | C41: AEO.2025.HIGHZTC.PRCE_REAL_ELEP_NA_U_NA_NA_Y13DLRPMMBTU.A | D41: 2024 $/MMBtu | F41: 0.753328 | G41: 0.753262 | H41: 0.753186 | I41: 0.753121 | J41: 0.753056 | K41: 0.75298 | L41: 0.752915 | M41: 0.752838 | N41: 0.752773 | O41: 0.752708 | P41: 0.752632 | Q41: 0.752567 | R41: 0.752491 | S41: 0.752425 | T41: 0.75236 | U41: 0.752284 | V41: 0.752219 | W41: 0.752154 | X41: 0.752078 | Y41: 0.752012 | Z41: 0.751936 | AA41: 0.751871 | AB41: 0.751806 | AC41: 0.75173 | AD41: 0.751665 | AE41: 0.751599 | AF41: 0.751523 | AG41: 0
A42: Hydrogen | B42: Energy Prices: Electric Power: Hydrogen: High Zero-Carbon Technology Cost | C42: AEO.2025.HIGHZTC.PRCE_REAL_ELEP_NA_HDG_NA_NA_Y13DLRPMMBTU.A | D42: 2024 $/MMBtu | F42: 9.533875 | G42: 10.619709 | H42: 10.514131 | I42: 10.426125 | J42: 10.55792 | K42: 10.787679 | L42: 11.065716 | M42: 11.319676 | N42: 13.51875 | O42: 13.970348 | P42: 14.314136 | Q42: 12.666781 | R42: 12.616203 | S42: 12.533028 | T42: 12.742199 | U42: 12.81229 | V42: 12.800771 | W42: 12.675635 | X42: 12.587033 | Y42: 12.651853 | Z42: 12.824852 | AA42: 12.7927 | AB42: 12.813029 | AC42: 12.789708 | AD42: 12.823941 | AE42: 12.685263 | AF42: 12.783066 | AG42: 0.011
A43: Average Price to All Users
A44: Propane | B44: Energy Prices: Average Price to All Users: Propane: High Zero-Carbon Technology Cost | C44: AEO.2025.HIGHZTC.PRCE_REAL_TEN_NA_PROP_NA_NA_Y13DLRPMMBTU.A | D44: 2024 $/MMBtu | F44: 23.10931 | G44: 21.964592 | H44: 22.480608 | I44: 22.283079 | J44: 22.302742 | K44: 22.505547 | L44: 22.995274 | M44: 23.450838 | N44: 24.190058 | O44: 25.158035 | P44: 25.926409 | Q44: 26.374306 | R44: 26.676216 | S44: 26.850521 | T44: 26.875446 | U44: 26.872549 | V44: 26.942244 | W44: 27.150986 | X44: 27.332554 | Y44: 27.645765 | Z44: 28.068441 | AA44: 28.264816 | AB44: 28.419424 | AC44: 28.45838 | AD44: 28.523825 | AE44: 28.746887 | AF44: 29.245407 | AG44: 0.009
A45: E85 | B45: Energy Prices: Average Price to All Users: E85: High Zero-Carbon Technology Cost | C45: AEO.2025.HIGHZTC.PRCE_REAL_TEN_NA_E85_NA_NA_Y13DLRPMMBTU.A | D45: 2024 $/MMBtu | F45: 28.823729 | G45: 28.93619 | H45: 30.221819 | I45: 29.874352 | J45: 29.356659 | K45: 28.412943 | L45: 28.414833 | M45: 28.528875 | N45: 28.297775 | O45: 28.022879 | P45: 27.970562 | Q45: 27.737436 | R45: 27.879841 | S45: 27.706806 | T45: 27.335274 | U45: 27.221582 | V45: 26.936087 | W45: 26.624407 | X45: 26.243464 | Y45: 26.249161 | Z45: 24.929926 | AA45: 24.592495 | AB45: 24.79623 | AC45: 24.925064 | AD45: 24.988291 | AE45: 25.141323 | AF45: 25.433138 | AG45: -0.005
A46: Motor Gasoline | B46: Energy Prices: Average Price to All Users: Motor Gasoline: High Zero-Carbon Technology Cost | C46: AEO.2025.HIGHZTC.PRCE_REAL_TEN_NA_MGS_NA_NA_Y13DLRPMMBTU.A | D46: 2024 $/MMBtu | F46: 28.684216 | G46: 27.125784 | H46: 25.527933 | I46: 25.03182 | J46: 24.761021 | K46: 24.469919 | L46: 24.496487 | M46: 24.505796 | N46: 24.326532 | O46: 24.183601 | P46: 24.129673 | Q46: 23.928679 | R46: 24.05728 | S46: 23.911495 | T46: 23.60075 | U46: 23.475494 | V46: 23.218733 | W46: 22.958654 | X46: 22.629124 | Y46: 22.653288 | Z46: 21.528265 | AA46: 21.244183 | AB46: 21.421278 | AC46: 21.532545 | AD46: 21.580334 | AE46: 21.704536 | AF46: 21.945274 | AG46: -0.01
A47: Jet Fuel | B47: Energy Prices: Average Price to All Users: Jet Fuel: High Zero-Carbon Technology Cost | C47: AEO.2025.HIGHZTC.PRCE_REAL_TEN_NA_JFL_NA_NA_Y13DLRPMMBTU.A | D47: 2024 $/MMBtu | F47: 17.638924 | G47: 16.395 | H47: 16.197346 | I47: 16.576864 | J47: 17.167725 | K47: 17.774681 | L47: 18.432444 | M47: 18.550699 | N47: 18.432102 | O47: 18.750156 | P47: 18.878136 | Q47: 19.088032 | R47: 19.162302 | S47: 19.413189 | T47: 19.636925 | U47: 19.743242 | V47: 19.910463 | W47: 20.238554 | X47: 20.505775 | Y47: 20.876812 | Z47: 21.614872 | AA47: 21.580616 | AB47: 21.698483 | AC47: 21.705061 | AD47: 21.706541 | AE47: 21.788584 | AF47: 22.195864 | AG47: 0.009
A48: Distillate Fuel Oil | B48: Energy Prices: Average Price to All Users: Distillate Fuel Oil: High Zero-Carbon Technology Cost | C48: AEO.2025.HIGHZTC.PRCE_REAL_TEN_NA_DFO_NA_NA_Y13DLRPMMBTU.A | D48: 2024 $/MMBtu | F48: 27.012424 | G48: 25.364977 | H48: 24.694891 | I48: 24.642532 | J48: 24.802452 | K48: 24.99939 | L48: 25.230318 | M48: 25.263414 | N48: 25.13209 | O48: 25.445631 | P48: 25.545443 | Q48: 25.775818 | R48: 25.891037 | S48: 26.145451 | T48: 26.220837 | U48: 26.325562 | V48: 26.498985 | W48: 26.760344 | X48: 26.992342 | Y48: 27.287764 | Z48: 27.935396 | AA48: 27.83683 | AB48: 27.914089 | AC48: 27.861572 | AD48: 27.845043 | AE48: 27.8617 | AF48: 28.192116 | AG48: 0.002
A49: Residual Fuel Oil | B49: Energy Prices: Average Price to All Users: Residual Fuel Oil: High Zero-Carbon Technology Cost | C49: AEO.2025.HIGHZTC.PRCE_REAL_TEN_NA_RFO_NA_NA_Y13DLRPMMBTU.A | D49: 2024 $/MMBtu | F49: 13.291615 | G49: 11.757444 | H49: 12.500851 | I49: 12.559112 | J49: 12.62952 | K49: 12.751574 | L49: 12.895062 | M49: 12.967169 | N49: 12.916404 | O49: 13.117395 | P49: 13.204977 | Q49: 13.33178 | R49: 13.382641 | S49: 13.467647 | T49: 13.557985 | U49: 13.576984 | V49: 13.653687 | W49: 13.73819 | X49: 13.818034 | Y49: 13.898582 | Z49: 13.903964 | AA49: 13.700245 | AB49: 13.939589 | AC49: 13.918885 | AD49: 13.937278 | AE49: 14.026111 | AF49: 14.469603 | AG49: 0.003
A50: Natural Gas | B50: Energy Prices: Average Price to All Users: Natural Gas: High Zero-Carbon Technology Cost | C50: AEO.2025.HIGHZTC.PRCE_REAL_TEN_NA_NG_NA_NA_Y13DLRPMMBTU.A | D50: 2024 $/MMBtu | F50: 5.358065 | G50: 5.60745 | H50: 5.603475 | I50: 5.429448 | J50: 5.4806 | K50: 5.600207 | L50: 5.770124 | M50: 5.905769 | N50: 6.242887 | O50: 6.591919 | P50: 6.833857 | Q50: 6.953874 | R50: 6.975764 | S50: 6.995045 | T50: 6.970082 | U50: 6.939922 | V50: 6.958767 | W50: 7.01943 | X50: 7.072737 | Y50: 7.132324 | Z50: 7.176168 | AA50: 7.216303 | AB50: 7.258737 | AC50: 7.256385 | AD50: 7.26004 | AE50: 7.309826 | AF50: 7.375858 | AG50: 0.012
A51: Metallurgical Coal | B51: Energy Prices: Average Price to All Users: Metallurgical Coal: High Zero-Carbon Technology Cost | C51: AEO.2025.HIGHZTC.PRCE_REAL_TEN_NA_MTC_NA_NA_Y13DLRPMMBTU.A | D51: 2024 $/MMBtu | F51: 7.767755 | G51: 7.639748 | H51: 7.585148 | I51: 7.555212 | J51: 7.520931 | K51: 7.512826 | L51: 7.510444 | M51: 7.515949 | N51: 7.537591 | O51: 7.537167 | P51: 7.49989 | Q51: 7.518089 | R51: 7.517967 | S51: 7.515557 | T51: 7.51727 | U51: 7.498265 | V51: 7.496222 | W51: 7.466915 | X51: 7.461041 | Y51: 7.453232 | Z51: 7.458103 | AA51: 7.471511 | AB51: 7.467525 | AC51: 7.46251 | AD51: 7.461265 | AE51: 7.469367 | AF51: 7.466943 | AG51: -0.002
A52: Other Coal | B52: Energy Prices: Average Price to All Users: Other Coal: High Zero-Carbon Technology Cost | C52: AEO.2025.HIGHZTC.PRCE_REAL_TEN_NA_OCA_NA_NA_Y13DLRPMMBTU.A | D52: 2024 $/MMBtu | F52: 2.544647 | G52: 2.490408 | H52: 2.452668 | I52: 2.423937 | J52: 2.334863 | K52: 2.340178 | L52: 2.379634 | M52: 2.359969 | N52: 2.608159 | O52: 2.607483 | P52: 2.600178 | Q52: 2.596767 | R52: 2.605588 | S52: 2.64105 | T52: 2.662963 | U52: 2.99238 | V52: 2.989484 | W52: 2.980852 | X52: 2.973089 | Y52: 2.971414 | Z52: 2.976025 | AA52: 2.999393 | AB52: 3.257445 | AC52: 3.293746 | AD52: 3.29155 | AE52: 3.301926 | AF52: 3.304214 | AG52: 0.01
A53: Hydrogen | B53: Energy Prices: Average Price to All Users: Hydrogen: High Zero-Carbon Technology Cost | C53: AEO.2025.HIGHZTC.PRCE_REAL_TEN_NA_HDG_NA_NA_Y13DLRPMMBTU.A | D53: 2024 $/MMBtu | F53: 9.573513 | G53: 10.759744 | H53: 10.814753 | I53: 10.970607 | J53: 11.467427 | K53: 12.125462 | L53: 12.869673 | M53: 14.186323 | N53: 16.70895 | O53: 19.089088 | P53: 20.999569 | Q53: 22.460648 | R53: 23.549911 | S53: 24.492126 | T53: 25.62182 | U53: 26.518492 | V53: 27.252636 | W53: 27.774517 | X53: 28.24732 | Y53: 28.807552 | Z53: 29.432905 | AA53: 29.795622 | AB53: 30.212788 | AC53: 30.48605 | AD53: 30.778925 | AE53: 30.779465 | AF53: 31.056328 | AG53: 0.046
A54: Electricity | B54: Energy Prices: Average Price to All Users: Electricity: High Zero-Carbon Technology Cost | C54: AEO.2025.HIGHZTC.PRCE_REAL_TEN_NA_ELC_NA_NA_Y13DLRPMMBTU.A | D54: 2024 $/MMBtu | F54: 38.098598 | G54: 37.333973 | H54: 34.881783 | I54: 33.049328 | J54: 32.874008 | K54: 33.237839 | L54: 33.692875 | M54: 34.296566 | N54: 34.825642 | O54: 35.589108 | P54: 35.82687 | Q54: 35.637054 | R54: 35.304626 | S54: 35.029667 | T54: 35.204475 | U54: 34.977581 | V54: 34.87011 | W54: 34.885918 | X54: 35.053295 | Y54: 35.213997 | Z54: 35.421429 | AA54: 35.584679 | AB54: 35.760864 | AC54: 35.86097 | AD54: 36.115452 | AE54: 36.344898 | AF54: 36.619953 | AG54: -0.002
A55: Non-Renewable Energy Expenditures by Sector
A56: (billion 2024 dollars)
A57: Residential | B57: Energy Expenditures: Non-Renewable Residential: High Zero-Carbon Technology Cost | C57: AEO.2025.HIGHZTC.EXPD_REAL_RESD_NA_NRN_NA_NA_BLNY13DLR.A | D57: billion 2024 $ | F57: 321.87134 | G57: 315.88342 | H57: 305.58066 | I57: 296.62158 | J57: 297.20978 | K57: 300.82953 | L57: 304.87982 | M57: 310.57489 | N57: 317.27094 | O57: 326.10974 | P57: 331.93753 | Q57: 335.42114 | R57: 337.75583 | S57: 340.22046 | T57: 345.05158 | U57: 347.16873 | V57: 350.45749 | W57: 354.74896 | X57: 359.83096 | Y57: 364.80817 | Z57: 369.94171 | AA57: 374.44733 | AB57: 379.10901 | AC57: 382.82822 | AD57: 387.42389 | AE57: 392.04144 | AF57: 397.16125 | AG57: 0.008
A58: Commercial | B58: Energy Expenditures: Non-Renewable Commercial: High Zero-Carbon Technology Cost | C58: AEO.2025.HIGHZTC.EXPD_REAL_COMM_NA_NRN_NA_NA_BLNY13DLR.A | D58: billion 2024 $ | F58: 241.12788 | G58: 237.06464 | H58: 224.32684 | I58: 216.67044 | J58: 218.1534 | K58: 223.83768 | L58: 230.04021 | M58: 237.12822 | N58: 245.24901 | O58: 254.96646 | P58: 262.06677 | Q58: 266.73019 | R58: 270.46622 | S58: 274.20633 | T58: 280.46323 | U58: 283.60974 | V58: 287.87076 | W58: 293.21573 | X58: 299.31854 | Y58: 305.4968 | Z58: 311.30548 | AA58: 317.04187 | AB58: 323.19623 | AC58: 328.30466 | AD58: 334.83005 | AE58: 341.48096 | AF58: 348.67667 | AG58: 0.014
A59: Industrial | B59: Energy Expenditures: Non-Renewable Industrial: High Zero-Carbon Technology Cost | C59: AEO.2025.HIGHZTC.EXPD_REAL_IDAL_NA_NRN_NA_NA_BLNY13DLR.A | D59: billion 2024 $ | F59: 225.6075 | G59: 228.66371 | H59: 224.17224 | I59: 218.50401 | J59: 219.97305 | K59: 224.7794 | L59: 232.18533 | M59: 239.67705 | N59: 251.39009 | O59: 263.95074 | P59: 272.88592 | Q59: 277.75275 | R59: 280.54141 | S59: 282.8479 | T59: 285.52365 | U59: 287.85333 | V59: 292.14374 | W59: 297.64972 | X59: 303.51181 | Y59: 308.79642 | Z59: 314.98047 | AA59: 319.06403 | AB59: 323.77768 | AC59: 327.83051 | AD59: 331.76517 | AE59: 337.71106 | AF59: 345.76858 | AG59: 0.017
A60: Transportation | B60: Energy Expenditures: Non-Renewable Transportation: High Zero-Carbon Technology Cost | C60: AEO.2025.HIGHZTC.EXPD_REAL_TRN_NA_NRN_NA_NA_BLNY13DLR.A | D60: billion 2024 $ | F60: 714.84161 | G60: 676.34644 | H60: 644.13318 | I60: 632.38385 | J60: 624.66571 | K60: 615.55078 | L60: 609.02887 | M60: 597.48749 | N60: 577.68488 | O60: 563.21027 | P60: 548.96338 | Q60: 534.35663 | R60: 522.66711 | S60: 509.74472 | T60: 495.17035 | U60: 483.18903 | V60: 472.33688 | W60: 463.27811 | X60: 453.93814 | Y60: 450.51828 | Z60: 439.83545 | AA60: 431.82056 | AB60: 430.39609 | AC60: 428.29285 | AD60: 425.13794 | AE60: 424.65317 | AF60: 428.82517 | AG60: -0.019
A61: Total Non-Renewable Expenditures | B61: Energy Expenditures: Total Non-Renewable: High Zero-Carbon Technology Cost | C61: AEO.2025.HIGHZTC.EXPD_REAL_TEN_NA_NRN_NA_NA_BLNY13DLR.A | D61: billion 2024 $ | F61: 1503.4482 | G61: 1457.9583 | H61: 1398.2129 | I61: 1364.1799 | J61: 1360.002 | K61: 1364.9974 | L61: 1376.1343 | M61: 1384.8677 | N61: 1391.595 | O61: 1408.2372 | P61: 1415.8535 | Q61: 1414.2607 | R61: 1411.4305 | S61: 1407.0194 | T61: 1406.2087 | U61: 1401.8208 | V61: 1402.8088 | W61: 1408.8926 | X61: 1416.5995 | Y61: 1429.6196 | Z61: 1436.0631 | AA61: 1442.3738 | AB61: 1456.479 | AC61: 1467.2562 | AD61: 1479.157 | AE61: 1495.8866 | AF61: 1520.4316 | AG61: 0
A62: Transportation Renewable Expenditures | B62: Energy Expenditures: Renewable Transportation: High Zero-Carbon Technology Cost | C62: AEO.2025.HIGHZTC.EXPD_REAL_TRN_NA_RNW_NA_NA_BLNY13DLR.A | D62: billion 2024 $ | F62: 0.107875 | G62: 0.100345 | H62: 0.093489 | I62: 0.086554 | J62: 0.08253 | K62: 0.082791 | L62: 0.078487 | M62: 0.072793 | N62: 0.067211 | O62: 0.062402 | P62: 0.058996 | Q62: 0.055041 | R62: 0.051815 | S62: 0.048885 | T62: 0.045543 | U62: 0.043307 | V62: 0.041884 | W62: 0.04052 | X62: 0.039222 | Y62: 0.03885 | Z62: 0.037436 | AA62: 0.035974 | AB62: 0.036186 | AC62: 0.037198 | AD62: 0.037176 | AE62: 0.037423 | AF62: 0.037653 | AG62: -0.04
A63: Total Expenditures | B63: Energy Expenditures: High Zero-Carbon Technology Cost | C63: AEO.2025.HIGHZTC.EXPD_REAL_TEN_NA_NA_NA_NA_BLNY13DLR.A | D63: billion 2024 $ | F63: 1503.5562 | G63: 1458.0586 | H63: 1398.3064 | I63: 1364.2665 | J63: 1360.0845 | K63: 1365.0802 | L63: 1376.2128 | M63: 1384.9404 | N63: 1391.6622 | O63: 1408.2996 | P63: 1415.9125 | Q63: 1414.3158 | R63: 1411.4823 | S63: 1407.0682 | T63: 1406.2543 | U63: 1401.8641 | V63: 1402.8507 | W63: 1408.9331 | X63: 1416.6387 | Y63: 1429.6584 | Z63: 1436.1006 | AA63: 1442.4098 | AB63: 1456.5151 | AC63: 1467.2935 | AD63: 1479.1942 | AE63: 1495.9241 | AF63: 1520.4692 | AG63: 0
A64: Prices in Nominal Dollars
A65: Residential
A66: Propane | B66: Energy Prices: Nominal: Residential: Propane: High Zero-Carbon Technology Cost | C66: AEO.2025.HIGHZTC.PRCE_NOM_RESD_NA_PROP_NA_NA_NDLRPMBTU.A | D66: nom $/MMBtu | F66: 26.593981 | G66: 26.216951 | H66: 26.858906 | I66: 27.152178 | J66: 27.696188 | K66: 28.433746 | L66: 29.537058 | M66: 30.762877 | N66: 32.364796 | O66: 34.319061 | P66: 36.227283 | Q66: 37.835377 | R66: 39.225212 | S66: 40.455105 | T66: 41.493401 | U66: 42.453186 | V66: 43.498753 | W66: 44.748333 | X66: 46.046326 | Y66: 47.565804 | Z66: 49.313976 | AA66: 50.883286 | AB66: 52.401012 | AC66: 53.792717 | AD66: 55.213657 | AE66: 56.888172 | AF66: 59.05526 | AG66: 0.031
A67: Distillate Fuel Oil | B67: Energy Prices: Nominal: Residential: Distillate Fuel Oil: High Zero-Carbon Technology Cost | C67: AEO.2025.HIGHZTC.PRCE_NOM_RESD_NA_DFO_NA_NA_NDLRPMBTU.A | D67: nom $/MMBtu | F67: 26.158379 | G67: 25.122044 | H67: 25.57391 | I67: 26.70492 | J67: 28.145452 | K67: 29.655188 | L67: 31.292149 | M67: 31.994268 | N67: 32.578827 | O67: 33.679363 | P67: 34.56406 | Q67: 35.592525 | R67: 36.482147 | S67: 37.580669 | T67: 38.49485 | U67: 39.449146 | V67: 40.520947 | W67: 41.791801 | X67: 43.031525 | Y67: 44.415188 | Z67: 46.386429 | AA67: 47.287495 | AB67: 48.481236 | AC67: 49.511318 | AD67: 50.619339 | AE67: 51.830589 | AF67: 53.611908 | AG67: 0.028
A68: Natural Gas | B68: Energy Prices: Nominal: Residential: Natural Gas: High Zero-Carbon Technology Cost | C68: AEO.2025.HIGHZTC.PRCE_NOM_RESD_NA_NG_NA_NA_NDLRPMBTU.A | D68: nom $/MMBtu | F68: 13.932205 | G68: 12.954311 | H68: 12.947871 | I68: 12.736533 | J68: 12.713431 | K68: 12.812389 | L68: 12.963352 | M68: 13.460487 | N68: 14.2479 | O68: 15.014253 | P68: 15.664865 | Q68: 16.185392 | R68: 16.539627 | S68: 16.867327 | T68: 17.190029 | U68: 17.466055 | V68: 17.87583 | W68: 18.432865 | X68: 18.987307 | Y68: 19.539175 | Z68: 20.057804 | AA68: 20.636808 | AB68: 21.249207 | AC68: 21.801548 | AD68: 22.344536 | AE68: 22.992262 | AF68: 23.643501 | AG68: 0.021
A69: Electricity | B69: Energy Prices: Nominal: Residential: Electricity: High Zero-Carbon Technology Cost | C69: AEO.2025.HIGHZTC.PRCE_NOM_RESD_NA_ELC_NA_NA_NDLRPMBTU.A | D69: nom $/MMBtu | F69: 45.553139 | G69: 45.946316 | H69: 44.147362 | I69: 42.68951 | J69: 43.199879 | K69: 44.394344 | L69: 45.759983 | M69: 47.469128 | N69: 49.123363 | O69: 51.20969 | P69: 52.775246 | Q69: 53.770809 | R69: 54.499828 | S69: 55.237061 | T69: 56.600323 | U69: 57.412365 | V69: 58.473801 | W69: 59.749023 | X69: 61.305805 | Y69: 62.927402 | Z69: 64.688965 | AA69: 66.450142 | AB69: 68.314209 | AC69: 70.139587 | AD69: 72.280113 | AE69: 74.430412 | AF69: 76.763725 | AG69: 0.02
A70: Commercial
A71: Propane | B71: Energy Prices: Nominal: Commercial: Propane: High Zero-Carbon Technology Cost | C71: AEO.2025.HIGHZTC.PRCE_NOM_COMM_NA_PROP_NA_NA_NDLRPMBTU.A | D71: nom $/MMBtu | F71: 19.0868 | G71: 19.462267 | H71: 20.722958 | I71: 20.896338 | J71: 21.415871 | K71: 22.126076 | L71: 23.186728 | M71: 24.181175 | N71: 25.599268 | O71: 27.285578 | P71: 28.679901 | Q71: 29.663061 | R71: 30.521715 | S71: 31.288752 | T71: 31.908875 | U71: 32.549953 | V71: 33.355064 | W71: 34.399128 | X71: 35.402992 | Y71: 36.654724 | Z71: 38.095921 | AA71: 39.159187 | AB71: 40.22176 | AC71: 41.14883 | AD71: 42.192711 | AE71: 43.574436 | AF71: 45.485512 | AG71: 0.034
A72: Distillate Fuel Oil | B72: Energy Prices: Nominal: Commercial: Distillate Fuel Oil: High Zero-Carbon Technology Cost | C72: AEO.2025.HIGHZTC.PRCE_NOM_COMM_NA_DFO_NA_NA_NDLRPMBTU.A | D72: nom $/MMBtu | F72: 26.207932 | G72: 25.213644 | H72: 24.45471 | I72: 24.329535 | J72: 24.463184 | K72: 24.622513 | L72: 24.858423 | M72: 25.421419 | N72: 25.819269 | O72: 26.75503 | P72: 27.480581 | Q72: 28.332861 | R72: 29.053051 | S72: 29.982716 | T72: 30.743277 | U72: 31.520094 | V72: 32.409874 | W72: 33.497684 | X72: 34.544827 | Y72: 35.746708 | Z72: 37.507889 | AA72: 38.209797 | AB72: 39.197243 | AC72: 40.01429 | AD72: 40.892246 | AE72: 41.893551 | AF72: 43.440746 | AG72: 0.02
A73: Residual Fuel Oil | B73: Energy Prices: Nominal: Commercial: Residual Fuel: High Zero-Carbon Technology Cost | C73: AEO.2025.HIGHZTC.PRCE_NOM_COMM_NA_RFL_NA_NA_NDLRPMBTU.A | D73: nom $/MMBtu | F73: 6.746078 | G73: 7.624751 | H73: 8.137149 | I73: 9.318295 | J73: 10.659361 | K73: 12.053771 | L73: 13.582099 | M73: 13.93248 | N73: 14.188656 | O73: 14.782047 | P73: 15.231493 | Q73: 15.7293 | R73: 16.150297 | S73: 16.639704 | T73: 17.12731 | U73: 17.50531 | V73: 18.038643 | W73: 18.587471 | X73: 19.175329 | Y73: 19.669559 | Z73: 20.001068 | AA73: 20.508837 | AB73: 21.422373 | AC73: 21.833618 | AD73: 22.393961 | AE73: 23.08009 | AF73: 24.547924 | AG73: 0.051
A74: Natural Gas | B74: Energy Prices: Nominal: Commercial: Natural Gas: High Zero-Carbon Technology Cost | C74: AEO.2025.HIGHZTC.PRCE_NOM_COMM_NA_NG_NA_NA_NDLRPMBTU.A | D74: nom $/MMBtu | F74: 9.555858 | G74: 8.647205 | H74: 8.894887 | I74: 8.982198 | J74: 9.238312 | K74: 9.593985 | L74: 10.006991 | M74: 10.378997 | N74: 11.008718 | O74: 11.624795 | P74: 12.127806 | Q74: 12.511601 | R74: 12.748526 | S74: 12.961295 | T74: 13.166965 | U74: 13.32591 | V74: 13.605648 | W74: 14.017473 | X74: 14.422617 | Y74: 14.824856 | Z74: 15.191047 | AA74: 15.612323 | AB74: 16.065739 | AC74: 16.455938 | AD74: 16.838379 | AE74: 17.31855 | AF74: 17.797932 | AG74: 0.024
A75: Electricity | B75: Energy Prices: Nominal: Commercial: Electricity: High Zero-Carbon Technology Cost | C75: AEO.2025.HIGHZTC.PRCE_NOM_COMM_NA_ELC_NA_NA_NDLRPMBTU.A | D75: nom $/MMBtu | F75: 38.551605 | G75: 38.373066 | H75: 36.430439 | I75: 34.949959 | J75: 35.440617 | K75: 36.461376 | L75: 37.692257 | M75: 39.158566 | N75: 40.593861 | O75: 42.40168 | P75: 43.685726 | Q75: 44.42812 | R75: 44.932621 | S75: 45.491875 | T75: 46.729763 | U75: 47.292721 | V75: 48.106781 | W75: 49.142422 | X75: 50.434948 | Y75: 51.762238 | Z75: 53.199848 | AA75: 54.606941 | AB75: 56.062115 | AC75: 57.402596 | AD75: 59.100903 | AE75: 60.797062 | AF75: 62.602421 | AG75: 0.019
A76: Industrial
A77: Propane | B77: Energy Prices: Nominal: Industrial: Propane: High Zero-Carbon Technology Cost | C77: AEO.2025.HIGHZTC.PRCE_NOM_IDAL_NA_PROP_NA_NA_NDLRPMBTU.A | D77: nom $/MMBtu | F77: 12.66026 | G77: 12.863893 | H77: 13.973295 | I77: 14.048564 | J77: 14.43579 | K77: 15.016267 | L77: 15.940687 | M77: 16.79492 | N77: 18.076534 | O77: 19.648006 | P77: 20.92911 | Q77: 21.779829 | R77: 22.498993 | S77: 23.113136 | T77: 23.563791 | U77: 24.032267 | V77: 24.667187 | W77: 25.551607 | X77: 26.38966 | Y77: 27.487337 | Z77: 28.789852 | AA77: 29.676821 | AB77: 30.551477 | AC77: 31.264862 | AD77: 32.095585 | AE77: 33.291042 | AF77: 35.07243 | AG77: 0.04
A78: Distillate Fuel Oil | B78: Energy Prices: Nominal: Industrial: Distillate Fuel Oil: High Zero-Carbon Technology Cost | C78: AEO.2025.HIGHZTC.PRCE_NOM_IDAL_NA_DFO_NA_NA_NDLRPMBTU.A | D78: nom $/MMBtu | F78: 26.091763 | G78: 25.104553 | H78: 24.31003 | I78: 24.150816 | J78: 24.251072 | K78: 24.374624 | L78: 24.563076 | M78: 25.124552 | N78: 25.502512 | O78: 26.454292 | P78: 27.189726 | Q78: 28.066748 | R78: 28.804398 | S78: 29.743267 | T78: 30.491646 | U78: 31.270138 | V78: 32.174793 | W78: 33.254627 | X78: 34.312599 | Y78: 35.515114 | Z78: 37.282944 | AA78: 37.979282 | AB78: 38.965359 | AC78: 39.780514 | AD78: 40.66153 | AE78: 41.649815 | AF78: 43.196087 | AG78: 0.02
A79: Residual Fuel Oil | B79: Energy Prices: Nominal: Industrial: Residual Fuel Oil: High Zero-Carbon Technology Cost | C79: AEO.2025.HIGHZTC.PRCE_NOM_IDAL_NA_RFO_NA_NA_NDLRPMBTU.A | D79: nom $/MMBtu | F79: 7.83466 | G79: 9.029342 | H79: 9.791279 | I79: 11.21501 | J79: 12.772719 | K79: 14.460553 | L79: 16.301508 | M79: 16.756365 | N79: 17.084602 | O79: 17.806349 | P79: 18.351042 | Q79: 18.963621 | R79: 19.48053 | S79: 20.060932 | T79: 20.631222 | U79: 21.096069 | V79: 21.696745 | W79: 22.315178 | X79: 23.010378 | Y79: 23.606112 | Z79: 24.056906 | AA79: 24.588398 | AB79: 25.5982 | AC79: 26.115402 | AD79: 26.772156 | AE79: 27.564425 | AF79: 29.134497 | AG79: 0.052
A80: Natural Gas | B80: Energy Prices: Nominal: Industrial: Natural Gas: High Zero-Carbon Technology Cost | C80: AEO.2025.HIGHZTC.PRCE_NOM_IDAL_NA_NG_NA_NA_NDLRPMBTU.A | D80: nom $/MMBtu | F80: 3.33707 | G80: 4.092753 | H80: 4.059119 | I80: 4.000466 | J80: 4.160158 | K80: 4.399243 | L80: 4.716491 | M80: 4.995432 | N80: 5.614189 | O80: 6.151089 | P80: 6.571557 | Q80: 6.815947 | R80: 6.941227 | S80: 7.020285 | T80: 7.087222 | U80: 7.124869 | V80: 7.302329 | W80: 7.588699 | X80: 7.871264 | Y80: 8.153418 | Z80: 8.415148 | AA80: 8.679128 | AB80: 8.953509 | AC80: 9.165268 | AD80: 9.397243 | AE80: 9.713953 | AF80: 10.048857 | AG80: 0.043
A81: Metallurgical Coal | B81: Energy Prices: Nominal: Industrial: Metallurgical Coal: High Zero-Carbon Technology Cost | C81: AEO.2025.HIGHZTC.PRCE_NOM_IDAL_NA_MTC_NA_NA_NDLRPMBTU.A | D81: nom $/MMBtu | F81: 7.767755 | G81: 7.796243 | H81: 7.871439 | I81: 7.97157 | J81: 8.085632 | K81: 8.221068 | L81: 8.372914 | M81: 8.552305 | N81: 8.76001 | O81: 8.951728 | P81: 9.106216 | Q81: 9.326975 | R81: 9.520159 | S81: 9.715213 | T81: 9.919882 | U81: 10.098601 | V81: 10.307525 | W81: 10.486297 | X81: 10.70411 | Y81: 10.927295 | Z81: 11.176041 | AA81: 11.445536 | AB81: 11.694777 | AC81: 11.95179 | AD81: 12.221812 | AE81: 12.514791 | AF81: 12.798068 | AG81: 0.019
A82: Other Industrial Coal | B82: Energy Prices: Nominal: Industrial: Other Industrial Coal: High Zero-Carbon Technology Cost | C82: AEO.2025.HIGHZTC.PRCE_NOM_IDAL_NA_OIC_NA_NA_NDLRPMBTU.A | D82: nom $/MMBtu | F82: 3.572155 | G82: 3.698336 | H82: 3.755393 | I82: 3.800257 | J82: 3.839487 | K82: 3.894675 | L82: 3.939315 | M82: 3.980161 | N82: 4.025944 | O82: 4.108876 | P82: 4.178519 | Q82: 4.237221 | R82: 4.332891 | S82: 4.425549 | T82: 4.529464 | U82: 4.617622 | V82: 4.717606 | W82: 4.81023 | X82: 4.90497 | Y82: 5.017175 | Z82: 5.133989 | AA82: 5.260872 | AB82: 5.393869 | AC82: 5.523439 | AD82: 5.648167 | AE82: 5.779319 | AF82: 5.920915 | AG82: 0.02
A83: Hydrogen | B83: Energy Prices: Nominal: Industrial: Hydrogen: High Zero-Carbon Technology Cost | C83: AEO.2025.HIGHZTC.PRCE_NOM_IDAL_NA_HDG_NA_NA_NDLRPMBTU.A | D83: nom $/MMBtu | F83: 9.533875 | G83: 10.837247 | H83: 10.910973 | I83: 11.000694 | J83: 11.350653 | K83: 11.804646 | L83: 12.33646 | M83: 12.88052 | N83: 13.527663 | O83: 14.437382 | P83: 15.207238 | Q83: 15.714464 | R83: 15.976162 | S83: 16.201199 | T83: 16.814762 | U83: 17.255487 | V83: 17.601435 | W83: 17.801258 | X83: 18.058201 | Y83: 18.54907 | Z83: 19.218168 | AA83: 19.597013 | AB83: 20.066286 | AC83: 20.483709 | AD83: 21.006063 | AE83: 21.253933 | AF83: 21.909708 | AG83: 0.033
A84: Electricity | B84: Energy Prices: Nominal: Industrial: Electricity: High Zero-Carbon Technology Cost | C84: AEO.2025.HIGHZTC.PRCE_NOM_IDAL_NA_ELC_NA_NA_NDLRPMBTU.A | D84: nom $/MMBtu | F84: 26.507746 | G84: 26.453053 | H84: 24.42614 | I84: 23.377502 | J84: 23.65649 | K84: 24.427061 | L84: 25.361465 | M84: 26.565578 | N84: 27.891041 | O84: 29.39677 | P84: 30.297054 | Q84: 30.728235 | R84: 30.964788 | S84: 31.339684 | T84: 32.121273 | U84: 32.630165 | V84: 33.200687 | W84: 33.926659 | X84: 34.844383 | Y84: 35.767387 | Z84: 36.76469 | AA84: 37.748009 | AB84: 38.769558 | AC84: 39.806171 | AD84: 40.988098 | AE84: 42.221344 | AF84: 43.553734 | AG84: 0.019
A85: Transportation
A86: Propane | B86: Energy Prices: Nominal: Transportation: Propane: High Zero-Carbon Technology Cost | C86: AEO.2025.HIGHZTC.PRCE_NOM_TRN_NA_PROP_NA_NA_NDLRPMBTU.A | D86: nom $/MMBtu | F86: 17.589245 | G86: 18.113504 | H86: 19.288139 | I86: 19.402617 | J86: 19.884892 | K86: 20.528612 | L86: 21.475201 | M86: 22.341841 | N86: 23.592443 | O86: 25.05793 | P86: 26.243191 | Q86: 27.078346 | R86: 27.828451 | S86: 28.507137 | T86: 29.06373 | U86: 29.6493 | V86: 30.380901 | W86: 31.31735 | X86: 32.205608 | Y86: 33.315407 | Z86: 34.580158 | AA86: 35.500401 | AB86: 36.442253 | AC86: 37.26936 | AD86: 38.210121 | AE86: 39.444866 | AF86: 41.127125 | AG86: 0.033
A87: E85 | B87: Energy Prices: Nominal: Transportation: E85: High Zero-Carbon Technology Cost | C87: AEO.2025.HIGHZTC.PRCE_NOM_TRN_NA_E85_NA_NA_NDLRPMBTU.A | D87: nom $/MMBtu | F87: 28.823729 | G87: 29.528929 | H87: 31.362501 | I87: 31.520689 | J87: 31.560877 | K87: 31.091465 | L87: 31.677883 | M87: 32.462654 | N87: 32.887005 | O87: 33.282158 | P87: 33.961296 | Q87: 34.411186 | R87: 35.304825 | S87: 35.816044 | T87: 36.07196 | U87: 36.661804 | V87: 37.03791 | W87: 37.390469 | X87: 37.650631 | Y87: 38.484287 | Z87: 37.357738 | AA87: 37.673004 | AB87: 38.832993 | AC87: 39.919426 | AD87: 40.931694 | AE87: 42.123844 | AF87: 43.591473 | AG87: 0.016
A88: Motor Gasoline | B88: Energy Prices: Nominal: Transportation: Motor Gasoline: High Zero-Carbon Technology Cost | C88: AEO.2025.HIGHZTC.PRCE_NOM_TRN_NA_MGS_NA_NA_NDLRPMBTU.A | D88: nom $/MMBtu | F88: 28.679842 | G88: 27.649559 | H88: 26.447338 | I88: 26.363968 | J88: 26.575916 | K88: 26.740559 | L88: 27.284904 | M88: 27.857161 | N88: 28.241079 | O88: 28.688046 | P88: 29.259247 | Q88: 29.643103 | R88: 30.416477 | S88: 30.857229 | T88: 31.08515 | U88: 31.556293 | V88: 31.86388 | W88: 32.172955 | X88: 32.389519 | Y88: 33.129726 | Z88: 32.171364 | AA88: 32.448826 | AB88: 33.446316 | AC88: 34.377804 | AD88: 35.232975 | AE88: 36.242748 | AF88: 37.483807 | AG88: 0.01
A89: Jet Fuel | B89: Energy Prices: Nominal: Transportation: Jet Fuel: High Zero-Carbon Technology Cost | C89: AEO.2025.HIGHZTC.PRCE_NOM_TRN_NA_JFL_NA_NA_NDLRPMBTU.A | D89: nom $/MMBtu | F89: 17.638924 | G89: 16.730843 | H89: 16.808693 | I89: 17.490393 | J89: 18.456747 | K89: 19.450321 | L89: 20.549154 | M89: 21.10861 | N89: 21.421352 | O89: 22.26915 | P89: 22.921453 | Q89: 23.680696 | R89: 24.265625 | S89: 25.095047 | T89: 25.913126 | U89: 26.590034 | V89: 27.37747 | W89: 28.422379 | X89: 29.418961 | Y89: 30.607809 | Z89: 32.390099 | AA89: 33.059135 | AB89: 33.981655 | AC89: 34.762341 | AD89: 35.556072 | AE89: 36.506386 | AF89: 38.042904 | AG89: 0.03
A90: Diesel Fuel (distillate fuel oil) | B90: Energy Prices: Nominal: Transportation: Diesel Fuel: High Zero-Carbon Technology Cost | C90: AEO.2025.HIGHZTC.PRCE_NOM_TRN_NA_DFU_NA_NA_NDLRPMBTU.A | D90: nom $/MMBtu | F90: 27.283649 | G90: 26.115433 | H90: 25.960787 | I90: 26.409092 | J90: 27.145966 | K90: 27.88415 | L90: 28.804071 | M90: 29.447966 | N90: 29.907007 | O90: 31.000999 | P90: 31.835327 | Q90: 32.823837 | R90: 33.706982 | S90: 34.75103 | T90: 35.600651 | U90: 36.515694 | V90: 37.492653 | W90: 38.73037 | X90: 39.902431 | Y90: 41.264984 | Z90: 43.238216 | AA90: 44.208622 | AB90: 45.142673 | AC90: 45.975689 | AD90: 47.109848 | AE90: 48.095074 | AF90: 49.921055 | AG90: 0.024
A91: Residual Fuel Oil | B91: Energy Prices: Nominal: Transportation: Residual Fuel Oil: High Zero-Carbon Technology Cost | C91: AEO.2025.HIGHZTC.PRCE_NOM_TRN_NA_RFO_NA_NA_NDLRPMBTU.A | D91: nom $/MMBtu | F91: 13.401297 | G91: 12.08642 | H91: 13.143271 | I91: 13.269609 | J91: 13.44949 | K91: 13.681735 | L91: 13.963659 | M91: 14.334046 | N91: 14.58601 | O91: 15.138056 | P91: 15.579436 | Q91: 16.071001 | R91: 16.472446 | S91: 16.93008 | T91: 17.407122 | U91: 17.802528 | V91: 18.289398 | W91: 18.827923 | X91: 19.382305 | Y91: 19.961056 | Z91: 20.45513 | AA91: 20.639217 | AB91: 21.468082 | AC91: 21.92396 | AD91: 22.452873 | AE91: 23.112991 | AF91: 24.391928 | AG91: 0.023
A92: Natural Gas | B92: Energy Prices: Nominal: Transportation: Natural Gas: High Zero-Carbon Technology Cost | C92: AEO.2025.HIGHZTC.PRCE_NOM_TRN_NA_NG_NA_NA_NDLRPMBTU.A | D92: nom $/MMBtu | F92: 14.514303 | G92: 15.353681 | H92: 15.54298 | I92: 15.676928 | J92: 16.027996 | K92: 16.458422 | L92: 16.930372 | M92: 17.408998 | N92: 18.207653 | O92: 18.887894 | P92: 19.448368 | Q92: 19.869696 | R92: 20.144455 | S92: 20.387754 | T92: 20.653177 | U92: 20.842625 | V92: 21.180105 | W92: 21.65204 | X92: 22.116915 | Y92: 22.599672 | Z92: 23.054102 | AA92: 23.532368 | AB92: 24.045355 | AC92: 24.47493 | AD92: 24.923931 | AE92: 25.479113 | AF92: 26.036837 | AG92: 0.023
A93: Electricity | B93: Energy Prices: Nominal: Transportation: Electricity: High Zero-Carbon Technology Cost | C93: AEO.2025.HIGHZTC.PRCE_NOM_TRN_NA_ELC_NA_NA_NDLRPMBTU.A | D93: nom $/MMBtu | F93: 42.609589 | G93: 43.132473 | H93: 41.167706 | I93: 38.740616 | J93: 39.278465 | K93: 40.285549 | L93: 41.567707 | M93: 43.305412 | N93: 44.980736 | O93: 47.198868 | P93: 48.686226 | Q93: 49.814907 | R93: 50.725761 | S93: 51.426571 | T93: 52.990257 | U93: 53.319035 | V93: 54.038769 | W93: 55.149055 | X93: 56.83358 | Y93: 58.384079 | Z93: 60.2169 | AA93: 61.84684 | AB93: 63.485474 | AC93: 64.850441 | AD93: 67.204674 | AE93: 69.173325 | AF93: 71.287987 | AG93: 0.02
A94: Electric Power
A95: Distillate Fuel Oil | B95: Energy Prices: Nominal: Electric Power: Distillate Fuel Oil: High Zero-Carbon Technology Cost | C95: AEO.2025.HIGHZTC.PRCE_NOM_ELEP_NA_DFO_NA_NA_NDLRPMBTU.A | D95: nom $/MMBtu | F95: 26.137505 | G95: 25.158468 | H95: 24.349579 | I95: 24.243881 | J95: 24.290323 | K95: 24.449207 | L95: 24.764141 | M95: 25.211271 | N95: 26.411995 | O95: 27.32086 | P95: 28.020191 | Q95: 28.843813 | R95: 29.480864 | S95: 30.405664 | T95: 31.232695 | U95: 31.98801 | V95: 32.844948 | W95: 33.953346 | X95: 35.011749 | Y95: 36.227688 | Z95: 37.848587 | AA95: 38.540752 | AB95: 39.687569 | AC95: 40.546864 | AD95: 41.432865 | AE95: 42.511791 | AF95: 44.099937 | AG95: 0.02
A96: Residual Fuel Oil | B96: Energy Prices: Nominal: Electric Power: Residual Fuel Oil: High Zero-Carbon Technology Cost | C96: AEO.2025.HIGHZTC.PRCE_NOM_ELEP_NA_RFO_NA_NA_NDLRPMBTU.A | D96: nom $/MMBtu | F96: 17.394409 | G96: 13.952579 | H96: 14.129054 | I96: 15.084783 | J96: 16.160213 | K96: 17.238125 | L96: 18.366262 | M96: 18.919966 | N96: 19.218084 | O96: 19.9196 | P96: 20.531452 | Q96: 21.200205 | R96: 21.727137 | S96: 22.323874 | T96: 22.959166 | U96: 23.445345 | V96: 24.05047 | W96: 24.648952 | X96: 25.158894 | Y96: 25.788282 | Z96: 26.238935 | AA96: 25.865458 | AB96: 26.939405 | AC96: 27.569456 | AD96: 28.261061 | AE96: 29.120207 | AF96: 30.707489 | AG96: 0.022
A97: Natural Gas | B97: Energy Prices: Nominal: Electric Power: Natural Gas: High Zero-Carbon Technology Cost | C97: AEO.2025.HIGHZTC.PRCE_NOM_ELEP_NA_NG_NA_NA_NDLRPMBTU.A | D97: nom $/MMBtu | F97: 2.719399 | G97: 3.195652 | H97: 3.184279 | I97: 3.161742 | J97: 3.360756 | K97: 3.641106 | L97: 4.017598 | M97: 4.205285 | N97: 4.878047 | O97: 5.354023 | P97: 5.728351 | Q97: 5.941702 | R97: 6.058687 | S97: 6.139751 | T97: 6.222767 | U97: 6.276008 | V97: 6.450063 | W97: 6.698177 | X97: 6.94699 | Y97: 7.227041 | Z97: 7.51471 | AA97: 7.75071 | AB97: 8.012893 | AC97: 8.2078 | AD97: 8.43215 | AE97: 8.742098 | AF97: 9.07992 | AG97: 0.047
A98: Steam Coal | B98: Energy Prices: Nominal: Electric Power: Steam Coal: High Zero-Carbon Technology Cost | C98: AEO.2025.HIGHZTC.PRCE_NOM_ELEP_NA_STC_NA_NA_NDLRPMBTU.A | D98: nom $/MMBtu | F98: 2.489397 | G98: 2.477139 | H98: 2.465143 | I98: 2.45433 | J98: 2.393669 | K98: 2.436637 | L98: 2.506002 | M98: 2.523748 | N98: 2.497636 | O98: 2.557025 | P98: 2.597243 | Q98: 2.637013 | R98: 2.691709 | S98: 2.787691 | T98: 2.840207 | U98: 2.981519 | V98: 3.039955 | W98: 3.100967 | X98: 3.165769 | Y98: 3.236343 | Z98: 3.307455 | AA98: 3.364176 | AB98: 2.956725 | AC98: 3.488788 | AD98: 3.567891 | AE98: 3.678514 | AF98: 3.757201 | AG98: 0.016
A99: Uranium | B99: Energy Prices: Nominal: Electric Power: Uranium: High Zero-Carbon Technology Cost | C99: AEO.2025.HIGHZTC.PRCE_NOM_ELEP_NA_U_NA_NA_NDLRPMBTU.A | D99: nom $/MMBtu | F99: 0.753328 | G99: 0.768692 | H99: 0.781614 | I99: 0.794625 | J99: 0.809598 | K99: 0.823964 | L99: 0.839376 | M99: 0.856646 | N99: 0.874855 | O99: 0.893975 | P99: 0.913831 | Q99: 0.933637 | R99: 0.952895 | S99: 0.972646 | T99: 0.992824 | U99: 1.01317 | V99: 1.034323 | W99: 1.056301 | X99: 1.078981 | Y99: 1.102537 | Z99: 1.126784 | AA99: 1.151784 | AB99: 1.177392 | AC99: 1.203954 | AD99: 1.231253 | AE99: 1.259292 | AF99: 1.288084 | AG99: 0.021
A100: Hydrogen | B100: Energy Prices: Nominal: Electric Power: Uranium: High Zero-Carbon Technology Cost | C100: AEO.2025.HIGHZTC.NA_NOM_ELEP_NA_HDG_NA_NA_NDLRPMBTU.A | D100: nom $/MMBtu | F100: 9.533875 | G100: 10.837247 | H100: 10.910973 | I100: 11.000694 | J100: 11.350653 | K100: 11.804646 | L100: 12.33646 | M100: 12.88052 | N100: 15.711172 | O100: 16.592278 | P100: 17.379936 | Q100: 15.714464 | R100: 15.976162 | S100: 16.201199 | T100: 16.814762 | U100: 17.255487 | V100: 17.601435 | W100: 17.801258 | X100: 18.058201 | Y100: 18.54907 | Z100: 19.218168 | AA100: 19.597013 | AB100: 20.066286 | AC100: 20.483709 | AD100: 21.006063 | AE100: 21.253933 | AF100: 21.909708 | AG100: 0.033
...

Sheet Calcs>

Sheet calcs
A1: Imported Electricity (MW*hour) | B1: 2024 | C1: 2025 | D1: 2026 | E1: 2027 | F1: 2028 | G1: 2029 | H1: 2030 | I1: 2031 | J1: 2032 | K1: 2033 | L1: 2034 | M1: 2035 | N1: 2036 | O1: 2037 | P1: 2038 | Q1: 2039 | R1: 2040 | S1: 2041 | T1: 2042 | U1: 2043 | V1: 2044 | W1: 2045 | X1: 2046 | Y1: 2047 | Z1: 2048 | AA1: 2049 | AB1: 2050
A2: hard coal | B2: =INDEX('AEO Table 10 2025'!$F$18:$AG$18,MATCH(B$1,'AEO Table 10 2025'!$F$5:$AG$5,0))*10^6*'Canada Elec Mix'!F2 -> 242303.65 | C2: =INDEX('AEO Table 10 2026'!$E$18:$AD$18,MATCH(C$1,'AEO Table 10 2026'!$E$5:$AD$5,0))*10^6*'Canada Elec Mix'!G2 -> 188299.69 | D2: =INDEX('AEO Table 10 2026'!$E$18:$AD$18,MATCH(D$1,'AEO Table 10 2026'!$E$5:$AD$5,0))*10^6*'Canada Elec Mix'!H2 -> 229288.15 | E2: =INDEX('AEO Table 10 2026'!$E$18:$AD$18,MATCH(E$1,'AEO Table 10 2026'!$E$5:$AD$5,0))*10^6*'Canada Elec Mix'!I2 -> 249351.33 | F2: =INDEX('AEO Table 10 2026'!$E$18:$AD$18,MATCH(F$1,'AEO Table 10 2026'!$E$5:$AD$5,0))*10^6*'Canada Elec Mix'!J2 -> 287873.73 | G2: =INDEX('AEO Table 10 2026'!$E$18:$AD$18,MATCH(G$1,'AEO Table 10 2026'!$E$5:$AD$5,0))*10^6*'Canada Elec Mix'!K2 -> 319784.4 | H2: =INDEX('AEO Table 10 2026'!$E$18:$AD$18,MATCH(H$1,'AEO Table 10 2026'!$E$5:$AD$5,0))*10^6*'Canada Elec Mix'!L2 -> 336857.31 | I2: =INDEX('AEO Table 10 2026'!$E$18:$AD$18,MATCH(I$1,'AEO Table 10 2026'!$E$5:$AD$5,0))*10^6*'Canada Elec Mix'!M2 -> 340648.82 | J2: =INDEX('AEO Table 10 2026'!$E$18:$AD$18,MATCH(J$1,'AEO Table 10 2026'!$E$5:$AD$5,0))*10^6*'Canada Elec Mix'!N2 -> 239780.05 | ... AB2: =INDEX('AEO Table 10 2026'!$E$18:$AD$18,MATCH(AB$1,'AEO Table 10 2026'!$E$5:$AD$5,0))*10^6*'Canada Elec Mix'!AF2 -> 5448.1601
A3: natural gas steam turbine | B3: =INDEX('AEO Table 10 2025'!$F$18:$AG$18,MATCH(B$1,'AEO Table 10 2025'!$F$5:$AG$5,0))*10^6*'Canada Elec Mix'!F3 -> 3278177.1 | C3: =INDEX('AEO Table 10 2026'!$E$18:$AD$18,MATCH(C$1,'AEO Table 10 2026'!$E$5:$AD$5,0))*10^6*'Canada Elec Mix'!G3 -> 2970426.3 | D3: =INDEX('AEO Table 10 2026'!$E$18:$AD$18,MATCH(D$1,'AEO Table 10 2026'!$E$5:$AD$5,0))*10^6*'Canada Elec Mix'!H3 -> 3957035.4 | E3: =INDEX('AEO Table 10 2026'!$E$18:$AD$18,MATCH(E$1,'AEO Table 10 2026'!$E$5:$AD$5,0))*10^6*'Canada Elec Mix'!I3 -> 4343556.9 | F3: =INDEX('AEO Table 10 2026'!$E$18:$AD$18,MATCH(F$1,'AEO Table 10 2026'!$E$5:$AD$5,0))*10^6*'Canada Elec Mix'!J3 -> 5384653.6 | G3: =INDEX('AEO Table 10 2026'!$E$18:$AD$18,MATCH(G$1,'AEO Table 10 2026'!$E$5:$AD$5,0))*10^6*'Canada Elec Mix'!K3 -> 6115157.4 | H3: =INDEX('AEO Table 10 2026'!$E$18:$AD$18,MATCH(H$1,'AEO Table 10 2026'!$E$5:$AD$5,0))*10^6*'Canada Elec Mix'!L3 -> 6258431.2 | I3: =INDEX('AEO Table 10 2026'!$E$18:$AD$18,MATCH(I$1,'AEO Table 10 2026'!$E$5:$AD$5,0))*10^6*'Canada Elec Mix'!M3 -> 6581425.4 | J3: =INDEX('AEO Table 10 2026'!$E$18:$AD$18,MATCH(J$1,'AEO Table 10 2026'!$E$5:$AD$5,0))*10^6*'Canada Elec Mix'!N3 -> 6208603.6 | ... AB3: =INDEX('AEO Table 10 2026'!$E$18:$AD$18,MATCH(AB$1,'AEO Table 10 2026'!$E$5:$AD$5,0))*10^6*'Canada Elec Mix'!AF3 -> 3328333.5
A4: natural gas combined cycle | B4: =INDEX('AEO Table 10 2025'!$F$18:$AG$18,MATCH(B$1,'AEO Table 10 2025'!$F$5:$AG$5,0))*10^6*'Canada Elec Mix'!F4 -> 0 | C4: =INDEX('AEO Table 10 2026'!$E$18:$AD$18,MATCH(C$1,'AEO Table 10 2026'!$E$5:$AD$5,0))*10^6*'Canada Elec Mix'!G4 -> 0 | D4: =INDEX('AEO Table 10 2026'!$E$18:$AD$18,MATCH(D$1,'AEO Table 10 2026'!$E$5:$AD$5,0))*10^6*'Canada Elec Mix'!H4 -> 0 | E4: =INDEX('AEO Table 10 2026'!$E$18:$AD$18,MATCH(E$1,'AEO Table 10 2026'!$E$5:$AD$5,0))*10^6*'Canada Elec Mix'!I4 -> 0 | F4: =INDEX('AEO Table 10 2026'!$E$18:$AD$18,MATCH(F$1,'AEO Table 10 2026'!$E$5:$AD$5,0))*10^6*'Canada Elec Mix'!J4 -> 0 | G4: =INDEX('AEO Table 10 2026'!$E$18:$AD$18,MATCH(G$1,'AEO Table 10 2026'!$E$5:$AD$5,0))*10^6*'Canada Elec Mix'!K4 -> 0 | H4: =INDEX('AEO Table 10 2026'!$E$18:$AD$18,MATCH(H$1,'AEO Table 10 2026'!$E$5:$AD$5,0))*10^6*'Canada Elec Mix'!L4 -> 0 | I4: =INDEX('AEO Table 10 2026'!$E$18:$AD$18,MATCH(I$1,'AEO Table 10 2026'!$E$5:$AD$5,0))*10^6*'Canada Elec Mix'!M4 -> 0 | J4: =INDEX('AEO Table 10 2026'!$E$18:$AD$18,MATCH(J$1,'AEO Table 10 2026'!$E$5:$AD$5,0))*10^6*'Canada Elec Mix'!N4 -> 0 | ... AB4: =INDEX('AEO Table 10 2026'!$E$18:$AD$18,MATCH(AB$1,'AEO Table 10 2026'!$E$5:$AD$5,0))*10^6*'Canada Elec Mix'!AF4 -> 0
A5: nuclear | B5: =INDEX('AEO Table 10 2025'!$F$18:$AG$18,MATCH(B$1,'AEO Table 10 2025'!$F$5:$AG$5,0))*10^6*'Canada Elec Mix'!F5 -> 3495228.3 | C5: =INDEX('AEO Table 10 2026'!$E$18:$AD$18,MATCH(C$1,'AEO Table 10 2026'!$E$5:$AD$5,0))*10^6*'Canada Elec Mix'!G5 -> 2792073.9 | D5: =INDEX('AEO Table 10 2026'!$E$18:$AD$18,MATCH(D$1,'AEO Table 10 2026'!$E$5:$AD$5,0))*10^6*'Canada Elec Mix'!H5 -> 3269944.4 | E5: =INDEX('AEO Table 10 2026'!$E$18:$AD$18,MATCH(E$1,'AEO Table 10 2026'!$E$5:$AD$5,0))*10^6*'Canada Elec Mix'!I5 -> 4260072.1 | F5: =INDEX('AEO Table 10 2026'!$E$18:$AD$18,MATCH(F$1,'AEO Table 10 2026'!$E$5:$AD$5,0))*10^6*'Canada Elec Mix'!J5 -> 5953816.4 | G5: =INDEX('AEO Table 10 2026'!$E$18:$AD$18,MATCH(G$1,'AEO Table 10 2026'!$E$5:$AD$5,0))*10^6*'Canada Elec Mix'!K5 -> 6191895.6 | H5: =INDEX('AEO Table 10 2026'!$E$18:$AD$18,MATCH(H$1,'AEO Table 10 2026'!$E$5:$AD$5,0))*10^6*'Canada Elec Mix'!L5 -> 7450001.6 | I5: =INDEX('AEO Table 10 2026'!$E$18:$AD$18,MATCH(I$1,'AEO Table 10 2026'!$E$5:$AD$5,0))*10^6*'Canada Elec Mix'!M5 -> 6925482.9 | J5: =INDEX('AEO Table 10 2026'!$E$18:$AD$18,MATCH(J$1,'AEO Table 10 2026'!$E$5:$AD$5,0))*10^6*'Canada Elec Mix'!N5 -> 7682821.2 | ... AB5: =INDEX('AEO Table 10 2026'!$E$18:$AD$18,MATCH(AB$1,'AEO Table 10 2026'!$E$5:$AD$5,0))*10^6*'Canada Elec Mix'!AF5 -> 5905741
A6: hydro | B6: =INDEX('AEO Table 10 2025'!$F$18:$AG$18,MATCH(B$1,'AEO Table 10 2025'!$F$5:$AG$5,0))*10^6*'Canada Elec Mix'!F6 -> 18308861 | C6: =INDEX('AEO Table 10 2026'!$E$18:$AD$18,MATCH(C$1,'AEO Table 10 2026'!$E$5:$AD$5,0))*10^6*'Canada Elec Mix'!G6 -> 16217385 | D6: =INDEX('AEO Table 10 2026'!$E$18:$AD$18,MATCH(D$1,'AEO Table 10 2026'!$E$5:$AD$5,0))*10^6*'Canada Elec Mix'!H6 -> 20492518 | E6: =INDEX('AEO Table 10 2026'!$E$18:$AD$18,MATCH(E$1,'AEO Table 10 2026'!$E$5:$AD$5,0))*10^6*'Canada Elec Mix'!I6 -> 24446182 | F6: =INDEX('AEO Table 10 2026'!$E$18:$AD$18,MATCH(F$1,'AEO Table 10 2026'!$E$5:$AD$5,0))*10^6*'Canada Elec Mix'!J6 -> 31444841 | G6: =INDEX('AEO Table 10 2026'!$E$18:$AD$18,MATCH(G$1,'AEO Table 10 2026'!$E$5:$AD$5,0))*10^6*'Canada Elec Mix'!K6 -> 34800822 | H6: =INDEX('AEO Table 10 2026'!$E$18:$AD$18,MATCH(H$1,'AEO Table 10 2026'!$E$5:$AD$5,0))*10^6*'Canada Elec Mix'!L6 -> 39173828 | I6: =INDEX('AEO Table 10 2026'!$E$18:$AD$18,MATCH(I$1,'AEO Table 10 2026'!$E$5:$AD$5,0))*10^6*'Canada Elec Mix'!M6 -> 39704156 | J6: =INDEX('AEO Table 10 2026'!$E$18:$AD$18,MATCH(J$1,'AEO Table 10 2026'!$E$5:$AD$5,0))*10^6*'Canada Elec Mix'!N6 -> 40403782 | ... AB6: =INDEX('AEO Table 10 2026'!$E$18:$AD$18,MATCH(AB$1,'AEO Table 10 2026'!$E$5:$AD$5,0))*10^6*'Canada Elec Mix'!AF6 -> 27447108
A7: onshore wind | B7: =INDEX('AEO Table 10 2025'!$F$18:$AG$18,MATCH(B$1,'AEO Table 10 2025'!$F$5:$AG$5,0))*10^6*'Canada Elec Mix'!F7 -> 2266292.5 | C7: =INDEX('AEO Table 10 2026'!$E$18:$AD$18,MATCH(C$1,'AEO Table 10 2026'!$E$5:$AD$5,0))*10^6*'Canada Elec Mix'!G7 -> 2068232.8 | D7: =INDEX('AEO Table 10 2026'!$E$18:$AD$18,MATCH(D$1,'AEO Table 10 2026'!$E$5:$AD$5,0))*10^6*'Canada Elec Mix'!H7 -> 2641250.7 | E7: =INDEX('AEO Table 10 2026'!$E$18:$AD$18,MATCH(E$1,'AEO Table 10 2026'!$E$5:$AD$5,0))*10^6*'Canada Elec Mix'!I7 -> 3557980.9 | F7: =INDEX('AEO Table 10 2026'!$E$18:$AD$18,MATCH(F$1,'AEO Table 10 2026'!$E$5:$AD$5,0))*10^6*'Canada Elec Mix'!J7 -> 4858018.1 | G7: =INDEX('AEO Table 10 2026'!$E$18:$AD$18,MATCH(G$1,'AEO Table 10 2026'!$E$5:$AD$5,0))*10^6*'Canada Elec Mix'!K7 -> 5768067.1 | H7: =INDEX('AEO Table 10 2026'!$E$18:$AD$18,MATCH(H$1,'AEO Table 10 2026'!$E$5:$AD$5,0))*10^6*'Canada Elec Mix'!L7 -> 7197250.5 | I7: =INDEX('AEO Table 10 2026'!$E$18:$AD$18,MATCH(I$1,'AEO Table 10 2026'!$E$5:$AD$5,0))*10^6*'Canada Elec Mix'!M7 -> 7925413.5 | J7: =INDEX('AEO Table 10 2026'!$E$18:$AD$18,MATCH(J$1,'AEO Table 10 2026'!$E$5:$AD$5,0))*10^6*'Canada Elec Mix'!N7 -> 8706847 | ... AB7: =INDEX('AEO Table 10 2026'!$E$18:$AD$18,MATCH(AB$1,'AEO Table 10 2026'!$E$5:$AD$5,0))*10^6*'Canada Elec Mix'!AF7 -> 11595777
A8: solar PV | B8: =INDEX('AEO Table 10 2025'!$F$18:$AG$18,MATCH(B$1,'AEO Table 10 2025'!$F$5:$AG$5,0))*10^6*'Canada Elec Mix'!F8 -> 178548.88 | C8: =INDEX('AEO Table 10 2026'!$E$18:$AD$18,MATCH(C$1,'AEO Table 10 2026'!$E$5:$AD$5,0))*10^6*'Canada Elec Mix'!G8 -> 165110.07 | D8: =INDEX('AEO Table 10 2026'!$E$18:$AD$18,MATCH(D$1,'AEO Table 10 2026'!$E$5:$AD$5,0))*10^6*'Canada Elec Mix'!H8 -> 237806.88 | E8: =INDEX('AEO Table 10 2026'!$E$18:$AD$18,MATCH(E$1,'AEO Table 10 2026'!$E$5:$AD$5,0))*10^6*'Canada Elec Mix'!I8 -> 303388.32 | F8: =INDEX('AEO Table 10 2026'!$E$18:$AD$18,MATCH(F$1,'AEO Table 10 2026'!$E$5:$AD$5,0))*10^6*'Canada Elec Mix'!J8 -> 398200.42 | G8: =INDEX('AEO Table 10 2026'!$E$18:$AD$18,MATCH(G$1,'AEO Table 10 2026'!$E$5:$AD$5,0))*10^6*'Canada Elec Mix'!K8 -> 553223.34 | H8: =INDEX('AEO Table 10 2026'!$E$18:$AD$18,MATCH(H$1,'AEO Table 10 2026'!$E$5:$AD$5,0))*10^6*'Canada Elec Mix'!L8 -> 702452.27 | I8: =INDEX('AEO Table 10 2026'!$E$18:$AD$18,MATCH(I$1,'AEO Table 10 2026'!$E$5:$AD$5,0))*10^6*'Canada Elec Mix'!M8 -> 795940.71 | J8: =INDEX('AEO Table 10 2026'!$E$18:$AD$18,MATCH(J$1,'AEO Table 10 2026'!$E$5:$AD$5,0))*10^6*'Canada Elec Mix'!N8 -> 911232.46 | ... AB8: =INDEX('AEO Table 10 2026'!$E$18:$AD$18,MATCH(AB$1,'AEO Table 10 2026'!$E$5:$AD$5,0))*10^6*'Canada Elec Mix'!AF8 -> 3822686
A9: solar thermal | B9: =INDEX('AEO Table 10 2025'!$F$18:$AG$18,MATCH(B$1,'AEO Table 10 2025'!$F$5:$AG$5,0))*10^6*'Canada Elec Mix'!F9 -> 0 | C9: =INDEX('AEO Table 10 2026'!$E$18:$AD$18,MATCH(C$1,'AEO Table 10 2026'!$E$5:$AD$5,0))*10^6*'Canada Elec Mix'!G9 -> 0 | D9: =INDEX('AEO Table 10 2026'!$E$18:$AD$18,MATCH(D$1,'AEO Table 10 2026'!$E$5:$AD$5,0))*10^6*'Canada Elec Mix'!H9 -> 0 | E9: =INDEX('AEO Table 10 2026'!$E$18:$AD$18,MATCH(E$1,'AEO Table 10 2026'!$E$5:$AD$5,0))*10^6*'Canada Elec Mix'!I9 -> 0 | F9: =INDEX('AEO Table 10 2026'!$E$18:$AD$18,MATCH(F$1,'AEO Table 10 2026'!$E$5:$AD$5,0))*10^6*'Canada Elec Mix'!J9 -> 0 | G9: =INDEX('AEO Table 10 2026'!$E$18:$AD$18,MATCH(G$1,'AEO Table 10 2026'!$E$5:$AD$5,0))*10^6*'Canada Elec Mix'!K9 -> 0 | H9: =INDEX('AEO Table 10 2026'!$E$18:$AD$18,MATCH(H$1,'AEO Table 10 2026'!$E$5:$AD$5,0))*10^6*'Canada Elec Mix'!L9 -> 0 | I9: =INDEX('AEO Table 10 2026'!$E$18:$AD$18,MATCH(I$1,'AEO Table 10 2026'!$E$5:$AD$5,0))*10^6*'Canada Elec Mix'!M9 -> 0 | J9: =INDEX('AEO Table 10 2026'!$E$18:$AD$18,MATCH(J$1,'AEO Table 10 2026'!$E$5:$AD$5,0))*10^6*'Canada Elec Mix'!N9 -> 0 | ... AB9: =INDEX('AEO Table 10 2026'!$E$18:$AD$18,MATCH(AB$1,'AEO Table 10 2026'!$E$5:$AD$5,0))*10^6*'Canada Elec Mix'!AF9 -> 0
A10: biomass | B10: =INDEX('AEO Table 10 2025'!$F$18:$AG$18,MATCH(B$1,'AEO Table 10 2025'!$F$5:$AG$5,0))*10^6*'Canada Elec Mix'!F10 -> 355766.05 | C10: =INDEX('AEO Table 10 2026'!$E$18:$AD$18,MATCH(C$1,'AEO Table 10 2026'!$E$5:$AD$5,0))*10^6*'Canada Elec Mix'!G10 -> 312121.88 | D10: =INDEX('AEO Table 10 2026'!$E$18:$AD$18,MATCH(D$1,'AEO Table 10 2026'!$E$5:$AD$5,0))*10^6*'Canada Elec Mix'!H10 -> 395445.36 | E10: =INDEX('AEO Table 10 2026'!$E$18:$AD$18,MATCH(E$1,'AEO Table 10 2026'!$E$5:$AD$5,0))*10^6*'Canada Elec Mix'!I10 -> 468763.92 | F10: =INDEX('AEO Table 10 2026'!$E$18:$AD$18,MATCH(F$1,'AEO Table 10 2026'!$E$5:$AD$5,0))*10^6*'Canada Elec Mix'!J10 -> 597242.76 | G10: =INDEX('AEO Table 10 2026'!$E$18:$AD$18,MATCH(G$1,'AEO Table 10 2026'!$E$5:$AD$5,0))*10^6*'Canada Elec Mix'!K10 -> 656917.91 | H10: =INDEX('AEO Table 10 2026'!$E$18:$AD$18,MATCH(H$1,'AEO Table 10 2026'!$E$5:$AD$5,0))*10^6*'Canada Elec Mix'!L10 -> 712396.73 | I10: =INDEX('AEO Table 10 2026'!$E$18:$AD$18,MATCH(I$1,'AEO Table 10 2026'!$E$5:$AD$5,0))*10^6*'Canada Elec Mix'!M10 -> 714100.85 | J10: =INDEX('AEO Table 10 2026'!$E$18:$AD$18,MATCH(J$1,'AEO Table 10 2026'!$E$5:$AD$5,0))*10^6*'Canada Elec Mix'!N10 -> 713341.31 | ... AB10: =INDEX('AEO Table 10 2026'!$E$18:$AD$18,MATCH(AB$1,'AEO Table 10 2026'!$E$5:$AD$5,0))*10^6*'Canada Elec Mix'!AF10 -> 470836.12
A11: geothermal | B11: =INDEX('AEO Table 10 2025'!$F$18:$AG$18,MATCH(B$1,'AEO Table 10 2025'!$F$5:$AG$5,0))*10^6*'Canada Elec Mix'!F11 -> 0 | C11: =INDEX('AEO Table 10 2026'!$E$18:$AD$18,MATCH(C$1,'AEO Table 10 2026'!$E$5:$AD$5,0))*10^6*'Canada Elec Mix'!G11 -> 0 | D11: =INDEX('AEO Table 10 2026'!$E$18:$AD$18,MATCH(D$1,'AEO Table 10 2026'!$E$5:$AD$5,0))*10^6*'Canada Elec Mix'!H11 -> 0 | E11: =INDEX('AEO Table 10 2026'!$E$18:$AD$18,MATCH(E$1,'AEO Table 10 2026'!$E$5:$AD$5,0))*10^6*'Canada Elec Mix'!I11 -> 0 | F11: =INDEX('AEO Table 10 2026'!$E$18:$AD$18,MATCH(F$1,'AEO Table 10 2026'!$E$5:$AD$5,0))*10^6*'Canada Elec Mix'!J11 -> 0 | G11: =INDEX('AEO Table 10 2026'!$E$18:$AD$18,MATCH(G$1,'AEO Table 10 2026'!$E$5:$AD$5,0))*10^6*'Canada Elec Mix'!K11 -> 0 | H11: =INDEX('AEO Table 10 2026'!$E$18:$AD$18,MATCH(H$1,'AEO Table 10 2026'!$E$5:$AD$5,0))*10^6*'Canada Elec Mix'!L11 -> 0 | I11: =INDEX('AEO Table 10 2026'!$E$18:$AD$18,MATCH(I$1,'AEO Table 10 2026'!$E$5:$AD$5,0))*10^6*'Canada Elec Mix'!M11 -> 0 | J11: =INDEX('AEO Table 10 2026'!$E$18:$AD$18,MATCH(J$1,'AEO Table 10 2026'!$E$5:$AD$5,0))*10^6*'Canada Elec Mix'!N11 -> 0 | ... AB11: =INDEX('AEO Table 10 2026'!$E$18:$AD$18,MATCH(AB$1,'AEO Table 10 2026'!$E$5:$AD$5,0))*10^6*'Canada Elec Mix'!AF11 -> 0
A12: petroleum | B12: =INDEX('AEO Table 10 2025'!$F$18:$AG$18,MATCH(B$1,'AEO Table 10 2025'!$F$5:$AG$5,0))*10^6*'Canada Elec Mix'!F12 -> 121438.71 | C12: =INDEX('AEO Table 10 2026'!$E$18:$AD$18,MATCH(C$1,'AEO Table 10 2026'!$E$5:$AD$5,0))*10^6*'Canada Elec Mix'!G12 -> 134267.43 | D12: =INDEX('AEO Table 10 2026'!$E$18:$AD$18,MATCH(D$1,'AEO Table 10 2026'!$E$5:$AD$5,0))*10^6*'Canada Elec Mix'!H12 -> 320903.74 | E12: =INDEX('AEO Table 10 2026'!$E$18:$AD$18,MATCH(E$1,'AEO Table 10 2026'!$E$5:$AD$5,0))*10^6*'Canada Elec Mix'!I12 -> 261209.92 | F12: =INDEX('AEO Table 10 2026'!$E$18:$AD$18,MATCH(F$1,'AEO Table 10 2026'!$E$5:$AD$5,0))*10^6*'Canada Elec Mix'!J12 -> 252689.95 | G12: =INDEX('AEO Table 10 2026'!$E$18:$AD$18,MATCH(G$1,'AEO Table 10 2026'!$E$5:$AD$5,0))*10^6*'Canada Elec Mix'!K12 -> 489068.05 | H12: =INDEX('AEO Table 10 2026'!$E$18:$AD$18,MATCH(H$1,'AEO Table 10 2026'!$E$5:$AD$5,0))*10^6*'Canada Elec Mix'!L12 -> 235009.5 | I12: =INDEX('AEO Table 10 2026'!$E$18:$AD$18,MATCH(I$1,'AEO Table 10 2026'!$E$5:$AD$5,0))*10^6*'Canada Elec Mix'!M12 -> 665220.06 | J12: =INDEX('AEO Table 10 2026'!$E$18:$AD$18,MATCH(J$1,'AEO Table 10 2026'!$E$5:$AD$5,0))*10^6*'Canada Elec Mix'!N12 -> 457494.17 | ... AB12: =INDEX('AEO Table 10 2026'!$E$18:$AD$18,MATCH(AB$1,'AEO Table 10 2026'!$E$5:$AD$5,0))*10^6*'Canada Elec Mix'!AF12 -> 351695.89
A13: natural gas peaker | B13: =INDEX('AEO Table 10 2025'!$F$18:$AG$18,MATCH(B$1,'AEO Table 10 2025'!$F$5:$AG$5,0))*10^6*'Canada Elec Mix'!F13 -> 909231.96 | C13: =INDEX('AEO Table 10 2026'!$E$18:$AD$18,MATCH(C$1,'AEO Table 10 2026'!$E$5:$AD$5,0))*10^6*'Canada Elec Mix'!G13 -> 823874.5 | D13: =INDEX('AEO Table 10 2026'!$E$18:$AD$18,MATCH(D$1,'AEO Table 10 2026'!$E$5:$AD$5,0))*10^6*'Canada Elec Mix'!H13 -> 1097519.4 | E13: =INDEX('AEO Table 10 2026'!$E$18:$AD$18,MATCH(E$1,'AEO Table 10 2026'!$E$5:$AD$5,0))*10^6*'Canada Elec Mix'!I13 -> 1204724.7 | F13: =INDEX('AEO Table 10 2026'!$E$18:$AD$18,MATCH(F$1,'AEO Table 10 2026'!$E$5:$AD$5,0))*10^6*'Canada Elec Mix'!J13 -> 1493482.2 | G13: =INDEX('AEO Table 10 2026'!$E$18:$AD$18,MATCH(G$1,'AEO Table 10 2026'!$E$5:$AD$5,0))*10^6*'Canada Elec Mix'!K13 -> 1696094 | H13: =INDEX('AEO Table 10 2026'!$E$18:$AD$18,MATCH(H$1,'AEO Table 10 2026'!$E$5:$AD$5,0))*10^6*'Canada Elec Mix'!L13 -> 1735832.3 | I13: =INDEX('AEO Table 10 2026'!$E$18:$AD$18,MATCH(I$1,'AEO Table 10 2026'!$E$5:$AD$5,0))*10^6*'Canada Elec Mix'!M13 -> 1825417.6 | J13: =INDEX('AEO Table 10 2026'!$E$18:$AD$18,MATCH(J$1,'AEO Table 10 2026'!$E$5:$AD$5,0))*10^6*'Canada Elec Mix'!N13 -> 1722012.2 | ... AB13: =INDEX('AEO Table 10 2026'!$E$18:$AD$18,MATCH(AB$1,'AEO Table 10 2026'!$E$5:$AD$5,0))*10^6*'Canada Elec Mix'!AF13 -> 923143.3
... A18: municipal solid waste | B18: =INDEX('AEO Table 10 2025'!$F$18:$AG$18,MATCH(B$1,'AEO Table 10 2025'!$F$5:$AG$5,0))*10^6*'Canada Elec Mix'!F18 -> 0 | C18: =INDEX('AEO Table 10 2026'!$E$18:$AD$18,MATCH(C$1,'AEO Table 10 2026'!$E$5:$AD$5,0))*10^6*'Canada Elec Mix'!G18 -> 0 | D18: =INDEX('AEO Table 10 2026'!$E$18:$AD$18,MATCH(D$1,'AEO Table 10 2026'!$E$5:$AD$5,0))*10^6*'Canada Elec Mix'!H18 -> 0 | E18: =INDEX('AEO Table 10 2026'!$E$18:$AD$18,MATCH(E$1,'AEO Table 10 2026'!$E$5:$AD$5,0))*10^6*'Canada Elec Mix'!I18 -> 0 | F18: =INDEX('AEO Table 10 2026'!$E$18:$AD$18,MATCH(F$1,'AEO Table 10 2026'!$E$5:$AD$5,0))*10^6*'Canada Elec Mix'!J18 -> 0 | G18: =INDEX('AEO Table 10 2026'!$E$18:$AD$18,MATCH(G$1,'AEO Table 10 2026'!$E$5:$AD$5,0))*10^6*'Canada Elec Mix'!K18 -> 0 | H18: =INDEX('AEO Table 10 2026'!$E$18:$AD$18,MATCH(H$1,'AEO Table 10 2026'!$E$5:$AD$5,0))*10^6*'Canada Elec Mix'!L18 -> 0 | I18: =INDEX('AEO Table 10 2026'!$E$18:$AD$18,MATCH(I$1,'AEO Table 10 2026'!$E$5:$AD$5,0))*10^6*'Canada Elec Mix'!M18 -> 0 | J18: =INDEX('AEO Table 10 2026'!$E$18:$AD$18,MATCH(J$1,'AEO Table 10 2026'!$E$5:$AD$5,0))*10^6*'Canada Elec Mix'!N18 -> 0 | ... AB18: =INDEX('AEO Table 10 2026'!$E$18:$AD$18,MATCH(AB$1,'AEO Table 10 2026'!$E$5:$AD$5,0))*10^6*'Canada Elec Mix'!AF18 -> 0
A19: hard coal w CCS | B19: 0 | C19: 0 | D19: 0 | E19: 0 | F19: 0 | G19: 0 | H19: 0 | I19: 0 | J19: 0 | K19: 0 | L19: 0 | M19: 0 | N19: 0 | O19: 0 | P19: 0 | Q19: 0 | R19: 0 | S19: 0 | T19: 0 | U19: 0 | V19: 0 | W19: 0 | X19: 0 | Y19: 0 | Z19: 0 | AA19: 0 | AB19: 0
A20: natural gas combined cycle w CCS | B20: 0 | C20: 0 | D20: 0 | E20: 0 | F20: 0 | G20: 0 | H20: 0 | I20: 0 | J20: 0 | K20: 0 | L20: 0 | M20: 0 | N20: 0 | O20: 0 | P20: 0 | Q20: 0 | R20: 0 | S20: 0 | T20: 0 | U20: 0 | V20: 0 | W20: 0 | X20: 0 | Y20: 0 | Z20: 0 | AA20: 0 | AB20: 0
A21: biomass w CCS | B21: 0 | C21: 0 | D21: 0 | E21: 0 | F21: 0 | G21: 0 | H21: 0 | I21: 0 | J21: 0 | K21: 0 | L21: 0 | M21: 0 | N21: 0 | O21: 0 | P21: 0 | Q21: 0 | R21: 0 | S21: 0 | T21: 0 | U21: 0 | V21: 0 | W21: 0 | X21: 0 | Y21: 0 | Z21: 0 | AA21: 0 | AB21: 0
A22: lignite w CCS | B22: 0 | C22: 0 | D22: 0 | E22: 0 | F22: 0 | G22: 0 | H22: 0 | I22: 0 | J22: 0 | K22: 0 | L22: 0 | M22: 0 | N22: 0 | O22: 0 | P22: 0 | Q22: 0 | R22: 0 | S22: 0 | T22: 0 | U22: 0 | V22: 0 | W22: 0 | X22: 0 | Y22: 0 | Z22: 0 | AA22: 0 | AB22: 0
A23: small modular reactor | B23: 0 | C23: 0 | D23: 0 | E23: 0 | F23: 0 | G23: 0 | H23: 0 | I23: 0 | J23: 0 | K23: 0 | L23: 0 | M23: 0 | N23: 0 | O23: 0 | P23: 0 | Q23: 0 | R23: 0 | S23: 0 | T23: 0 | U23: 0 | V23: 0 | W23: 0 | X23: 0 | Y23: 0 | Z23: 0 | AA23: 0 | AB23: 0
A24: hydrogen combustion turbine | B24: 0 | C24: 0 | D24: 0 | E24: 0 | F24: 0 | G24: 0 | H24: 0 | I24: 0 | J24: 0 | K24: 0 | L24: 0 | M24: 0 | N24: 0 | O24: 0 | P24: 0 | Q24: 0 | R24: 0 | S24: 0 | T24: 0 | U24: 0 | V24: 0 | W24: 0 | X24: 0 | Y24: 0 | Z24: 0 | AA24: 0 | AB24: 0
A25: hydrogen combined cycle | B25: 0 | C25: 0 | D25: 0 | E25: 0 | F25: 0 | G25: 0 | H25: 0 | I25: 0 | J25: 0 | K25: 0 | L25: 0 | M25: 0 | N25: 0 | O25: 0 | P25: 0 | Q25: 0 | R25: 0 | S25: 0 | T25: 0 | U25: 0 | V25: 0 | W25: 0 | X25: 0 | Y25: 0 | Z25: 0 | AA25: 0 | AB25: 0
A27: Exported Electricity (MW*hour) | B27: 2024 | C27: 2025 | D27: 2026 | E27: 2027 | F27: 2028 | G27: 2029 | H27: 2030 | I27: 2031 | J27: 2032 | K27: 2033 | L27: 2034 | M27: 2035 | N27: 2036 | O27: 2037 | P27: 2038 | Q27: 2039 | R27: 2040 | S27: 2041 | T27: 2042 | U27: 2043 | V27: 2044 | W27: 2045 | X27: 2046 | Y27: 2047 | Z27: 2048 | AA27: 2049 | AB27: 2050
A28: Electricity Exports (MWh) | B28: =INDEX('AEO Table 10 2025'!22:22,MATCH(B27,'AEO Table 10 2025'!5:5,0))*10^6 -> 14989228 | C28: =INDEX('AEO Table 10 2026'!22:22,MATCH(C27,'AEO Table 10 2026'!5:5,0))*10^6 -> 16798512 | D28: =INDEX('AEO Table 10 2026'!22:22,MATCH(D27,'AEO Table 10 2026'!5:5,0))*10^6 -> 16798512 | E28: =INDEX('AEO Table 10 2026'!22:22,MATCH(E27,'AEO Table 10 2026'!5:5,0))*10^6 -> 16798512 | F28: =INDEX('AEO Table 10 2026'!22:22,MATCH(F27,'AEO Table 10 2026'!5:5,0))*10^6 -> 16798512 | G28: =INDEX('AEO Table 10 2026'!22:22,MATCH(G27,'AEO Table 10 2026'!5:5,0))*10^6 -> 16798512 | H28: =INDEX('AEO Table 10 2026'!22:22,MATCH(H27,'AEO Table 10 2026'!5:5,0))*10^6 -> 16798512 | I28: =INDEX('AEO Table 10 2026'!22:22,MATCH(I27,'AEO Table 10 2026'!5:5,0))*10^6 -> 16918085 | J28: =INDEX('AEO Table 10 2026'!22:22,MATCH(J27,'AEO Table 10 2026'!5:5,0))*10^6 -> 17037659 | ... AB28: =INDEX('AEO Table 10 2026'!22:22,MATCH(AB27,'AEO Table 10 2026'!5:5,0))*10^6 -> 17994251
A30: Unit: 2012 USD/MWh | B30: 2024 | C30: 2025 | D30: 2026 | E30: 2027 | F30: 2028 | G30: 2029 | H30: 2030 | I30: 2031 | J30: 2032 | K30: 2033 | L30: 2034 | M30: 2035 | N30: 2036 | O30: 2037 | P30: 2038 | Q30: 2039 | R30: 2040 | S30: 2041 | T30: 2042 | U30: 2043 | V30: 2044 | W30: 2045 | X30: 2046 | Y30: 2047 | Z30: 2048 | AA30: 2049 | AB30: 2050
A31: Imported Electricity Price | B31: =INDEX('AEO Table 3 2025'!$54:$54,MATCH(B30,'AEO Table 3 2025'!$5:$5,0))/10^6*About!$A$60/About!$A$58 -> 95.149006 | C31: =INDEX('AEO Table 3 2026'!$54:$54,MATCH(C30,'AEO Table 3 2026'!$5:$5,0))/10^6*About!$A$61/About!$A$58 -> 96.530432 | D31: =INDEX('AEO Table 3 2026'!$54:$54,MATCH(D30,'AEO Table 3 2026'!$5:$5,0))/10^6*About!$A$61/About!$A$58 -> 96.086127 | E31: =INDEX('AEO Table 3 2026'!$54:$54,MATCH(E30,'AEO Table 3 2026'!$5:$5,0))/10^6*About!$A$61/About!$A$58 -> 93.174725 | F31: =INDEX('AEO Table 3 2026'!$54:$54,MATCH(F30,'AEO Table 3 2026'!$5:$5,0))/10^6*About!$A$61/About!$A$58 -> 91.06327 | G31: =INDEX('AEO Table 3 2026'!$54:$54,MATCH(G30,'AEO Table 3 2026'!$5:$5,0))/10^6*About!$A$61/About!$A$58 -> 91.770771 | H31: =INDEX('AEO Table 3 2026'!$54:$54,MATCH(H30,'AEO Table 3 2026'!$5:$5,0))/10^6*About!$A$61/About!$A$58 -> 92.818608 | I31: =INDEX('AEO Table 3 2026'!$54:$54,MATCH(I30,'AEO Table 3 2026'!$5:$5,0))/10^6*About!$A$61/About!$A$58 -> 93.769513 | J31: =INDEX('AEO Table 3 2026'!$54:$54,MATCH(J30,'AEO Table 3 2026'!$5:$5,0))/10^6*About!$A$61/About!$A$58 -> 94.275185 | ... AB31: =INDEX('AEO Table 3 2026'!$54:$54,MATCH(AB30,'AEO Table 3 2026'!$5:$5,0))/10^6*About!$A$61/About!$A$58 -> 98.59239

Sheet EIaE-BIE
A1: Imported Electricity (MW*hour) | B1: 2024 | C1: 2025 | D1: 2026 | E1: 2027 | F1: 2028 | G1: 2029 | H1: 2030 | I1: 2031 | J1: 2032 | K1: 2033 | L1: 2034 | M1: 2035 | N1: 2036 | O1: 2037 | P1: 2038 | Q1: 2039 | R1: 2040 | S1: 2041 | T1: 2042 | U1: 2043 | V1: 2044 | W1: 2045 | X1: 2046 | Y1: 2047 | Z1: 2048 | AA1: 2049 | AB1: 2050
A2: hard coal | B2: =calcs!B2 -> 242303.65 | C2: =calcs!C2 -> 188299.69 | D2: =calcs!D2 -> 229288.15 | E2: =calcs!E2 -> 249351.33 | F2: =calcs!F2 -> 287873.73 | G2: =calcs!G2 -> 319784.4 | H2: =calcs!H2 -> 336857.31 | I2: =calcs!I2 -> 340648.82 | ... AB2: =calcs!AB2 -> 5448.1601
A3: natural gas steam turbine | B3: =calcs!B3 -> 3278177.1 | C3: =calcs!C3 -> 2970426.3 | D3: =calcs!D3 -> 3957035.4 | E3: =calcs!E3 -> 4343556.9 | F3: =calcs!F3 -> 5384653.6 | G3: =calcs!G3 -> 6115157.4 | H3: =calcs!H3 -> 6258431.2 | I3: =calcs!I3 -> 6581425.4 | ... AB3: =calcs!AB3 -> 3328333.5
A4: natural gas combined cycle | B4: =calcs!B4 -> 0 | C4: =calcs!C4 -> 0 | D4: =calcs!D4 -> 0 | E4: =calcs!E4 -> 0 | F4: =calcs!F4 -> 0 | G4: =calcs!G4 -> 0 | H4: =calcs!H4 -> 0 | I4: =calcs!I4 -> 0 | ... AB4: =calcs!AB4 -> 0
A5: nuclear | B5: =calcs!B5 -> 3495228.3 | C5: =calcs!C5 -> 2792073.9 | D5: =calcs!D5 -> 3269944.4 | E5: =calcs!E5 -> 4260072.1 | F5: =calcs!F5 -> 5953816.4 | G5: =calcs!G5 -> 6191895.6 | H5: =calcs!H5 -> 7450001.6 | I5: =calcs!I5 -> 6925482.9 | ... AB5: =calcs!AB5 -> 5905741
A6: hydro | B6: =calcs!B6 -> 18308861 | C6: =calcs!C6 -> 16217385 | D6: =calcs!D6 -> 20492518 | E6: =calcs!E6 -> 24446182 | F6: =calcs!F6 -> 31444841 | G6: =calcs!G6 -> 34800822 | H6: =calcs!H6 -> 39173828 | I6: =calcs!I6 -> 39704156 | ... AB6: =calcs!AB6 -> 27447108
A7: onshore wind | B7: =calcs!B7 -> 2266292.5 | C7: =calcs!C7 -> 2068232.8 | D7: =calcs!D7 -> 2641250.7 | E7: =calcs!E7 -> 3557980.9 | F7: =calcs!F7 -> 4858018.1 | G7: =calcs!G7 -> 5768067.1 | H7: =calcs!H7 -> 7197250.5 | I7: =calcs!I7 -> 7925413.5 | ... AB7: =calcs!AB7 -> 11595777
A8: solar PV | B8: =calcs!B8 -> 178548.88 | C8: =calcs!C8 -> 165110.07 | D8: =calcs!D8 -> 237806.88 | E8: =calcs!E8 -> 303388.32 | F8: =calcs!F8 -> 398200.42 | G8: =calcs!G8 -> 553223.34 | H8: =calcs!H8 -> 702452.27 | I8: =calcs!I8 -> 795940.71 | ... AB8: =calcs!AB8 -> 3822686
A9: solar thermal | B9: =calcs!B9 -> 0 | C9: =calcs!C9 -> 0 | D9: =calcs!D9 -> 0 | E9: =calcs!E9 -> 0 | F9: =calcs!F9 -> 0 | G9: =calcs!G9 -> 0 | H9: =calcs!H9 -> 0 | I9: =calcs!I9 -> 0 | ... AB9: =calcs!AB9 -> 0
A10: biomass | B10: =calcs!B10 -> 355766.05 | C10: =calcs!C10 -> 312121.88 | D10: =calcs!D10 -> 395445.36 | E10: =calcs!E10 -> 468763.92 | F10: =calcs!F10 -> 597242.76 | G10: =calcs!G10 -> 656917.91 | H10: =calcs!H10 -> 712396.73 | I10: =calcs!I10 -> 714100.85 | ... AB10: =calcs!AB10 -> 470836.12
A11: geothermal | B11: =calcs!B11 -> 0 | C11: =calcs!C11 -> 0 | D11: =calcs!D11 -> 0 | E11: =calcs!E11 -> 0 | F11: =calcs!F11 -> 0 | G11: =calcs!G11 -> 0 | H11: =calcs!H11 -> 0 | I11: =calcs!I11 -> 0 | ... AB11: =calcs!AB11 -> 0
A12: petroleum | B12: =calcs!B12 -> 121438.71 | C12: =calcs!C12 -> 134267.43 | D12: =calcs!D12 -> 320903.74 | E12: =calcs!E12 -> 261209.92 | F12: =calcs!F12 -> 252689.95 | G12: =calcs!G12 -> 489068.05 | H12: =calcs!H12 -> 235009.5 | I12: =calcs!I12 -> 665220.06 | ... AB12: =calcs!AB12 -> 351695.89
A13: natural gas peaker | B13: =calcs!B13 -> 909231.96 | C13: =calcs!C13 -> 823874.5 | D13: =calcs!D13 -> 1097519.4 | E13: =calcs!E13 -> 1204724.7 | F13: =calcs!F13 -> 1493482.2 | G13: =calcs!G13 -> 1696094 | H13: =calcs!H13 -> 1735832.3 | I13: =calcs!I13 -> 1825417.6 | ... AB13: =calcs!AB13 -> 923143.3
... A25: hydrogen combined cycle | B25: =calcs!B25 -> 0 | C25: =calcs!C25 -> 0 | D25: =calcs!D25 -> 0 | E25: =calcs!E25 -> 0 | F25: =calcs!F25 -> 0 | G25: =calcs!G25 -> 0 | H25: =calcs!H25 -> 0 | I25: =calcs!I25 -> 0 | ... AB25: =calcs!AB25 -> 0

Sheet EIaE-BEE
A1: Exported Electricity (MW*hour) | B1: 2024 | C1: 2025 | D1: 2026 | E1: 2027 | F1: 2028 | G1: 2029 | H1: 2030 | I1: 2031 | J1: 2032 | K1: 2033 | L1: 2034 | M1: 2035 | N1: 2036 | O1: 2037 | P1: 2038 | Q1: 2039 | R1: 2040 | S1: 2041 | T1: 2042 | U1: 2043 | V1: 2044 | W1: 2045 | X1: 2046 | Y1: 2047 | Z1: 2048 | AA1: 2049 | AB1: 2050
A2: Electricity Exports (MWh) | B2: =calcs!B28 -> 14989228 | C2: =calcs!C28 -> 16798512 | D2: =calcs!D28 -> 16798512 | E2: =calcs!E28 -> 16798512 | F2: =calcs!F28 -> 16798512 | G2: =calcs!G28 -> 16798512 | H2: =calcs!H28 -> 16798512 | I2: =calcs!I28 -> 16918085 | ... AB2: =calcs!AB28 -> 17994251

Sheet EIaE-IEP
A1: Unit: 2012 USD/MWh | B1: 2024 | C1: 2025 | D1: 2026 | E1: 2027 | F1: 2028 | G1: 2029 | H1: 2030 | I1: 2031 | J1: 2032 | K1: 2033 | L1: 2034 | M1: 2035 | N1: 2036 | O1: 2037 | P1: 2038 | Q1: 2039 | R1: 2040 | S1: 2041 | T1: 2042 | U1: 2043 | V1: 2044 | W1: 2045 | X1: 2046 | Y1: 2047 | Z1: 2048 | AA1: 2049 | AB1: 2050
A2: Imported Electricity Price | B2: =calcs!B31 -> 95.149006 | C2: =calcs!C31 -> 96.530432 | D2: =calcs!D31 -> 96.086127 | E2: =calcs!E31 -> 93.174725 | F2: =calcs!F31 -> 91.06327 | G2: =calcs!G31 -> 91.770771 | H2: =calcs!H31 -> 92.818608 | I2: =calcs!I31 -> 93.769513 | ... AB2: =calcs!AB31 -> 98.59239

Sheet AEO Table 10 2026
A1: Table 10. Electricity Trade
A2: https://www.eia.gov/outlooks/aeo/data/browser/#/?id=10-AEO2026&cases=electrnp&sourcekey=0
A3: Thu Apr 23 2026 14:58:31 GMT-0700 (Pacific Daylight Time)
A4: Source: U.S. Energy Information Administration
B5: full name | C5: api key | D5: units | E5: 2025 | F5: 2026 | G5: 2027 | H5: 2028 | I5: 2029 | J5: 2030 | K5: 2031 | L5: 2032 | M5: 2033 | N5: 2034 | O5: 2035 | P5: 2036 | Q5: 2037 | R5: 2038 | S5: 2039 | T5: 2040 | U5: 2041 | V5: 2042 | W5: 2043 | X5: 2044 | Y5: 2045 | Z5: 2046 | AA5: 2047 | AB5: 2048 | AC5: 2049 | AD5: 2050 | AE5: Growth (2025-2050)
A6: Interregional Electricity Trade
A7: Gross Domestic Sales
A8: Firm Power | B8: Electricity Trade: Gross Domestic Sales: Firm Power: Alternative Electricity and Transportation | C8: AEO.2026.ELECTRNP.TRAD_FPW_ELEP_GDSE_SAL_NA_USA_BLNKWH.A | D8: BkWh | E8: 43.267345 | F8: 43.046135 | G8: 42.817745 | H8: 42.559071 | I8: 42.293137 | J8: 42.024815 | K8: 41.620972 | L8: 41.217129 | M8: 40.81329 | N8: 40.156349 | O8: 39.466724 | P8: 38.769131 | Q8: 37.904129 | R8: 37.069424 | S8: 36.021156 | T8: 34.914703 | U8: 33.94376 | V8: 32.853245 | W8: 31.762732 | X8: 31.010212 | Y8: 30.418718 | Z8: 29.843166 | AA8: 29.442198 | AB8: 29.041225 | AC8: 28.861069 | AD8: 28.741493 | AE8: -1.6%
A9: Economy | B9: Electricity Trade: Gross Domestic Sales: Economy: Alternative Electricity and Transportation | C9: AEO.2026.ELECTRNP.TRAD_ECN_ELEP_GDSE_SAL_NA_USA_BLNKWH.A | D9: BkWh | E9: 227.0865 | F9: 257.60294 | G9: 221.5576 | H9: 234.15179 | I9: 230.15884 | J9: 216.20694 | K9: 245.56892 | L9: 262.70157 | M9: 308.39023 | N9: 329.164 | O9: 326.20358 | P9: 331.19516 | Q9: 343.06909 | R9: 343.8689 | S9: 345.07162 | T9: 367.45209 | U9: 374.14414 | V9: 371.88303 | W9: 358.5751 | X9: 359.94458 | Y9: 358.89542 | Z9: 357.68662 | AA9: 361.43161 | AB9: 347.68426 | AC9: 346.94934 | AD9: 341.08478 | AE9: 1.6%
A10: Total Gross Domestic Sales | B10: Electricity Trade: Gross Domestic Sales: Total: Alternative Electricity and Transportation | C10: AEO.2026.ELECTRNP.TRAD_TOT_ELEP_GDSE_SAL_NA_USA_BLNKWH.A | D10: BkWh | E10: 270.35382 | F10: 300.64908 | G10: 264.37537 | H10: 276.71085 | I10: 272.452 | J10: 258.23175 | K10: 287.18988 | L10: 303.9187 | M10: 349.20352 | N10: 369.32037 | O10: 365.67029 | P10: 369.96429 | Q10: 380.97321 | R10: 380.93832 | S10: 381.09277 | T10: 402.36676 | U10: 408.08789 | V10: 404.73627 | W10: 390.33783 | X10: 390.9548 | Y10: 389.31415 | Z10: 387.52976 | AA10: 390.87381 | AB10: 376.72549 | AC10: 375.81039 | AD10: 369.82626 | AE10: 1.3%
A11: Gross Domestic Sales (million 2025 dollars)
A12: Firm Power | B12: Electricity Trade: Gross Domestic Sales: Firm Power: Alternative Electricity and Transportation | C12: AEO.2026.ELECTRNP.KEI_FPW_ELEP_GDSE_SAL_NA_USA_MILLY13DLR.A | D12: million 2025 $ | E12: 3673.3745 | F12: 3654.594 | G12: 3635.2043 | H12: 3613.2424 | I12: 3590.6648 | J12: 3567.8843 | K12: 3533.5984 | L12: 3499.3127 | M12: 3465.0264 | N12: 3409.2527 | O12: 3350.7041 | P12: 3291.4788 | Q12: 3218.041 | R12: 3147.1746 | S12: 3058.1772 | T12: 2964.24 | U12: 2881.8074 | V12: 2789.2234 | W12: 2696.6392 | X12: 2632.7507 | Y12: 2582.5332 | Z12: 2533.6692 | AA12: 2499.6272 | AB12: 2465.5847 | AC12: 2450.2893 | AD12: 2440.1377 | AE12: -1.6%
A13: Economy | B13: Electricity Trade: Gross Domestic Sales: Economy: Alternative Electricity and Transportation | C13: AEO.2026.ELECTRNP.KEI_ECN_ELEP_GDSE_SAL_NA_USA_MILLY13DLR.A | D13: million 2025 $ | E13: 8610.9062 | F13: 8204.7812 | G13: 8901.4961 | H13: 9228.2334 | I13: 9617.584 | J13: 9427.4102 | K13: 10566.174 | L13: 11124.008 | M13: 14541.546 | N13: 15228.291 | O13: 14933.671 | P13: 14720.894 | Q13: 15222.332 | R13: 15370.622 | S13: 15503.264 | T13: 16419.49 | U13: 16349.492 | V13: 15903.406 | W13: 14957.205 | X13: 14706.588 | Y13: 14445.519 | Z13: 14550.246 | AA13: 14818.775 | AB13: 14260.716 | AC13: 14263.159 | AD13: 13610.99 | AE13: 1.8%
A14: Total Gross Domestic Sales | B14: Electricity Trade: Gross Domestic Sales: Total: Alternative Electricity and Transportation | C14: AEO.2026.ELECTRNP.KEI_TOT_ELEP_GDSE_SAL_NA_USA_MILLY13DLR.A | D14: million 2025 $ | E14: 12284.281 | F14: 11859.375 | G14: 12536.7 | H14: 12841.476 | I14: 13208.249 | J14: 12995.295 | K14: 14099.772 | L14: 14623.32 | M14: 18006.572 | N14: 18637.543 | O14: 18284.375 | P14: 18012.373 | Q14: 18440.373 | R14: 18517.797 | S14: 18561.441 | T14: 19383.73 | U14: 19231.299 | V14: 18692.629 | W14: 17653.844 | X14: 17339.338 | Y14: 17028.051 | Z14: 17083.916 | AA14: 17318.402 | AB14: 16726.301 | AC14: 16713.449 | AD14: 16051.128 | AE14: 1.1%
A15: International Electricity Trade
A16: Imports from Canada and Mexico
A17: Firm Power | B17: Electricity Trade: Imports from Canada and Mexico: Firm Power: Alternative Electricity and Transportation | C17: AEO.2026.ELECTRNP.TRAD_FPW_ELEP_ICME_IMP_CANMEX_USA_BLNKWH.A | D17: BkWh | E17: 16.437441 | F17: 16.437441 | G17: 36.334557 | H17: 36.334557 | I17: 36.270782 | J17: 36.207008 | K17: 36.143234 | L17: 36.079464 | M17: 36.01569 | N17: 35.95192 | O17: 35.888145 | P17: 35.545368 | Q17: 35.481594 | R17: 35.417824 | S17: 35.417824 | T17: 35.417824 | U17: 35.417824 | V17: 35.417824 | W17: 26.649059 | X17: 26.649059 | Y17: 26.649059 | Z17: 26.649059 | AA17: 26.649059 | AB17: 26.649059 | AC17: 26.649059 | AD17: 26.649059 | AE17: 2.0%
A18: Economy | B18: Electricity Trade: Imports from Canada and Mexico: Economy: Alternative Electricity and Transportation | C18: AEO.2026.ELECTRNP.TRAD_ECN_ELEP_ICME_IMP_CANMEX_USA_BLNKWH.A | D18: BkWh | E18: 25.671791 | F18: 32.641712 | G18: 39.09523 | H18: 50.670818 | I18: 56.59103 | J18: 63.802059 | K18: 65.477806 | L18: 67.045914 | M18: 69.977684 | N18: 71.232239 | O18: 72.712395 | P18: 70.549866 | Q18: 70.123146 | R18: 69.78521 | S18: 68.762871 | T18: 69.670486 | U18: 69.581673 | V18: 65.785347 | W18: 71.285919 | X18: 69.940895 | Y18: 69.582108 | Z18: 65.06337 | AA18: 62.280926 | AB18: 59.586403 | AC18: 56.609764 | AD18: 53.850769 | AE18: 3.0%
A19: Total Imports from Canada and Mexico | B19: Electricity Trade: Imports from Canada and Mexico: Total: Alternative Electricity and Transportation | C19: AEO.2026.ELECTRNP.TRAD_TOT_ELEP_ICME_IMP_CANMEX_USA_BLNKWH.A | D19: BkWh | E19: 42.10923 | F19: 49.079151 | G19: 75.429787 | H19: 87.005379 | I19: 92.861816 | J19: 100.00906 | K19: 101.62104 | L19: 103.12538 | M19: 105.99337 | N19: 107.18416 | O19: 108.60054 | P19: 106.09523 | Q19: 105.60474 | R19: 105.20303 | S19: 104.1807 | T19: 105.08831 | U19: 104.9995 | V19: 101.20317 | W19: 97.934975 | X19: 96.589958 | Y19: 96.231163 | Z19: 91.712425 | AA19: 88.929985 | AB19: 86.235458 | AC19: 83.258827 | AD19: 80.499832 | AE19: 2.6%
A20: Exports to Canada and Mexico
A21: Firm Power | B21: Electricity Trade: Exports to Canada and Mexico: Firm Power: Alternative Electricity and Transportation | C21: AEO.2026.ELECTRNP.TRAD_FPW_ELEP_EXCM_IMP_CANMEX_USA_BLNKWH.A | D21: BkWh | E21: 1.19574 | F21: 1.19574 | G21: 1.19574 | H21: 1.19574 | I21: 1.19574 | J21: 1.19574 | K21: 1.076166 | L21: 0.956592 | M21: 0.837018 | N21: 0.717444 | O21: 0.59787 | P21: 0.478296 | Q21: 0.358722 | R21: 0.239148 | S21: 0.119574 | T21: 0 | U21: 0 | V21: 0 | W21: 0 | X21: 0 | Y21: 0 | Z21: 0 | AA21: 0 | AB21: 0 | AC21: 0 | AD21: 0 | AE21: -100.0%
A22: Economy | B22: Electricity Trade: Exports to Canada and Mexico: Economy: Alternative Electricity and Transportation | C22: AEO.2026.ELECTRNP.TRAD_ECN_ELEP_EXCM_IMP_CANMEX_USA_BLNKWH.A | D22: BkWh | E22: 16.798512 | F22: 16.798512 | G22: 16.798512 | H22: 16.798512 | I22: 16.798512 | J22: 16.798512 | K22: 16.918085 | L22: 17.037659 | M22: 17.157232 | N22: 17.276808 | O22: 17.396381 | P22: 17.515953 | Q22: 17.635529 | R22: 17.755102 | S22: 17.874676 | T22: 17.994251 | U22: 17.994251 | V22: 17.994251 | W22: 17.994251 | X22: 17.994251 | Y22: 17.994251 | Z22: 17.994251 | AA22: 17.994251 | AB22: 17.994251 | AC22: 17.994251 | AD22: 17.994251 | AE22: 0.3%
A23: Total Exports to Canada and Mexico | B23: Electricity Trade: Exports to Canada and Mexico: Total: Alternative Electricity and Transportation | C23: AEO.2026.ELECTRNP.TRAD_TOT_ELEP_EXCM_IMP_CANMEX_USA_BLNKWH.A | D23: BkWh | E23: 17.994251 | F23: 17.994251 | G23: 17.994251 | H23: 17.994251 | I23: 17.994251 | J23: 17.994251 | K23: 17.994251 | L23: 17.994251 | M23: 17.994251 | N23: 17.994251 | O23: 17.994251 | P23: 17.994251 | Q23: 17.994251 | R23: 17.994251 | S23: 17.994251 | T23: 17.994251 | U23: 17.994251 | V23: 17.994251 | W23: 17.994251 | X23: 17.994251 | Y23: 17.994251 | Z23: 17.994251 | AA23: 17.994251 | AB23: 17.994251 | AC23: 17.994251 | AD23: 17.994251 | AE23: 0.0%

Sheet AEO Table 3 2026
A1: Table 3. Energy Prices by Sector and Source
A2: https://www.eia.gov/outlooks/aeo/data/browser/#/?id=3-AEO2026&cases=electrnp&sourcekey=0
A3: Thu Apr 23 2026 14:57:36 GMT-0700 (Pacific Daylight Time)
A4: Source: U.S. Energy Information Administration
B5: full name | C5: api key | D5: units | E5: 2025 | F5: 2026 | G5: 2027 | H5: 2028 | I5: 2029 | J5: 2030 | K5: 2031 | L5: 2032 | M5: 2033 | N5: 2034 | O5: 2035 | P5: 2036 | Q5: 2037 | R5: 2038 | S5: 2039 | T5: 2040 | U5: 2041 | V5: 2042 | W5: 2043 | X5: 2044 | Y5: 2045 | Z5: 2046 | AA5: 2047 | AB5: 2048 | AC5: 2049 | AD5: 2050 | AE5: Growth (2025-2050)
A6: Residential
A7: Propane | B7: Energy Prices: Residential: Propane: Alternative Electricity and Transportation | C7: AEO.2026.ELECTRNP.PRCE_REAL_RESD_NA_PROP_NA_NA_Y13DLRPMMBTU.A | D7: 2025 $/MMBtu | E7: 26.563074 | F7: 24.660282 | G7: 24.022764 | H7: 24.267151 | I7: 24.828779 | J7: 25.713388 | K7: 26.943876 | L7: 27.941402 | M7: 29.000704 | N7: 29.730562 | O7: 30.396542 | P7: 31.023659 | Q7: 31.704144 | R7: 32.363785 | S7: 33.016689 | T7: 33.551872 | U7: 33.955025 | V7: 34.124786 | W7: 34.061459 | X7: 33.890648 | Y7: 33.857697 | Z7: 33.974369 | AA7: 34.165623 | AB7: 34.401737 | AC7: 34.609074 | AD7: 34.782436 | AE7: 1.1%
A8: Distillate Fuel Oil | B8: Energy Prices: Residential: Distillate Fuel Oil: Alternative Electricity and Transportation | C8: AEO.2026.ELECTRNP.PRCE_REAL_RESD_NA_DFO_NA_NA_Y13DLRPMMBTU.A | D8: 2025 $/MMBtu | E8: 26.297781 | F8: 23.841019 | G8: 24.852819 | H8: 25.492739 | I8: 26.044502 | J8: 26.356546 | K8: 26.889671 | L8: 26.986252 | M8: 27.431295 | N8: 27.476742 | O8: 27.74155 | P8: 27.989231 | Q8: 28.189903 | R8: 28.422253 | S8: 28.565861 | T8: 28.683638 | U8: 28.866655 | V8: 29.028748 | W8: 29.196308 | X8: 29.351231 | Y8: 29.645172 | Z8: 29.887751 | AA8: 30.086521 | AB8: 30.433371 | AC8: 30.751434 | AD8: 30.83054 | AE8: 0.6%
A9: Natural Gas | B9: Energy Prices: Residential: Natural Gas: Alternative Electricity and Transportation | C9: AEO.2026.ELECTRNP.PRCE_REAL_RESD_NA_NG_NA_NA_Y13DLRPMMBTU.A | D9: 2025 $/MMBtu | E9: 14.67222 | F9: 13.865501 | G9: 13.6013 | H9: 13.618066 | I9: 13.716167 | J9: 13.947049 | K9: 14.10574 | L9: 14.281732 | M9: 14.72492 | N9: 14.845181 | O9: 15.010983 | P9: 15.087603 | Q9: 15.280451 | R9: 15.384978 | S9: 15.491961 | T9: 15.581245 | U9: 15.632208 | V9: 15.597161 | W9: 15.534369 | X9: 15.445058 | Y9: 15.43466 | Z9: 15.500757 | AA9: 15.579066 | AB9: 15.646149 | AC9: 15.709329 | AD9: 15.750059 | AE9: 0.3%
A10: Electricity | B10: Energy Prices: Residential: Electricity: Alternative Electricity and Transportation | C10: AEO.2026.ELECTRNP.PRCE_REAL_RESD_NA_ELC_NA_NA_Y13DLRPMMBTU.A | D10: 2025 $/MMBtu | E10: 48.884674 | F10: 48.970573 | G10: 47.876259 | H10: 46.813107 | I10: 47.098038 | J10: 47.575283 | K10: 48.040817 | L10: 48.378601 | M10: 48.737003 | N10: 49.087418 | O10: 49.32822 | P10: 49.554005 | Q10: 49.935158 | R10: 50.217533 | S10: 50.544601 | T10: 50.909134 | U10: 51.109844 | V10: 51.163372 | W10: 51.117962 | X10: 51.094761 | Y10: 50.972771 | Z10: 51.227135 | AA10: 51.488991 | AB10: 51.754013 | AC10: 51.908321 | AD10: 52.146389 | AE10: 0.3%
A11: Commercial
A12: Propane | B12: Energy Prices: Commercial: Propane: Alternative Electricity and Transportation | C12: AEO.2026.ELECTRNP.PRCE_REAL_COMM_NA_PROP_NA_NA_Y13DLRPMMBTU.A | D12: 2025 $/MMBtu | E12: 19.614388 | F12: 17.773504 | G12: 17.948193 | H12: 18.789955 | I12: 19.533926 | J12: 20.45974 | K12: 21.646479 | L12: 22.261967 | M12: 23.033985 | N12: 23.463772 | O12: 23.878845 | P12: 24.288403 | Q12: 24.797268 | R12: 25.276108 | S12: 25.737419 | T12: 26.038733 | U12: 26.222591 | V12: 26.17038 | W12: 25.940657 | X12: 25.712225 | Y12: 25.750612 | Z12: 25.93557 | AA12: 26.134615 | AB12: 26.339758 | AC12: 26.472441 | AD12: 26.56786 | AE12: 1.2%
A13: Distillate Fuel Oil | B13: Energy Prices: Commercial: Distillate Fuel Oil: Alternative Electricity and Transportation | C13: AEO.2026.ELECTRNP.PRCE_REAL_COMM_NA_DFO_NA_NA_Y13DLRPMMBTU.A | D13: 2025 $/MMBtu | E13: 26.413055 | F13: 23.944263 | G13: 23.78701 | H13: 23.234953 | I13: 22.59086 | J13: 21.649616 | K13: 21.002819 | L13: 21.100346 | M13: 21.906805 | N13: 21.950172 | O13: 22.215946 | P13: 22.432451 | Q13: 22.700315 | R13: 22.930136 | S13: 23.061247 | T13: 23.163157 | U13: 23.336281 | V13: 23.506573 | W13: 23.667786 | X13: 23.831995 | Y13: 24.121313 | Z13: 24.360191 | AA13: 24.559891 | AB13: 24.900385 | AC13: 25.211374 | AD13: 25.282532 | AE13: -0.2%
A14: Residual Fuel Oil | B14: Energy Prices: Commercial: Residual Fuel: Alternative Electricity and Transportation | C14: AEO.2026.ELECTRNP.PRCE_REAL_COMM_NA_RFL_NA_NA_Y13DLRPMMBTU.A | D14: 2025 $/MMBtu | E14: 7.486679 | F14: 5.717993 | G14: 7.213068 | H14: 8.33526 | I14: 9.372824 | J14: 9.703115 | K14: 11.012938 | L14: 11.044285 | M14: 11.423374 | N14: 11.416125 | O14: 11.730696 | P14: 11.915172 | Q14: 12.021229 | R14: 12.222262 | S14: 12.36445 | T14: 12.640309 | U14: 12.962893 | V14: 13.141302 | W14: 13.291031 | X14: 13.447833 | Y14: 13.705943 | Z14: 13.882443 | AA14: 14.033334 | AB14: 14.408689 | AC14: 14.634272 | AD14: 14.791724 | AE14: 2.8%
A15: Natural Gas | B15: Energy Prices: Commercial: Natural Gas: Alternative Electricity and Transportation | C15: AEO.2026.ELECTRNP.PRCE_REAL_COMM_NA_NG_NA_NA_Y13DLRPMMBTU.A | D15: 2025 $/MMBtu | E15: 10.354016 | F15: 9.511374 | G15: 9.762173 | H15: 10.167947 | I15: 10.630009 | J15: 11.225421 | K15: 11.760633 | L15: 11.919279 | M15: 12.230326 | N15: 12.308634 | O15: 12.450624 | P15: 12.509456 | Q15: 12.673752 | R15: 12.76578 | S15: 12.863074 | T15: 12.941275 | U15: 12.976732 | V15: 12.925268 | W15: 12.84654 | X15: 12.738944 | Y15: 12.708939 | Z15: 12.752996 | AA15: 12.808952 | AB15: 12.853724 | AC15: 12.893847 | AD15: 12.912653 | AE15: 0.9%
A16: Electricity | B16: Energy Prices: Commercial: Electricity: Alternative Electricity and Transportation | C16: AEO.2026.ELECTRNP.PRCE_REAL_COMM_NA_ELC_NA_NA_Y13DLRPMMBTU.A | D16: 2025 $/MMBtu | E16: 39.50576 | F16: 39.254784 | G16: 38.00787 | H16: 37.027317 | I16: 37.270535 | J16: 37.676891 | K16: 38.013729 | L16: 38.169567 | M16: 38.377754 | N16: 38.628765 | O16: 38.712334 | P16: 38.766697 | Q16: 38.97871 | R16: 39.113335 | S16: 39.318199 | T16: 39.513145 | U16: 39.528194 | V16: 39.464729 | W16: 39.301834 | X16: 39.165123 | Y16: 38.864052 | Z16: 39.004269 | AA16: 39.126835 | AB16: 39.262093 | AC16: 39.271355 | AD16: 39.370186 | AE16: -0.0%
A17: Industrial
A18: Propane | B18: Energy Prices: Industrial: Propane: Alternative Electricity and Transportation | C18: AEO.2026.ELECTRNP.PRCE_REAL_IDAL_NA_PROP_NA_NA_Y13DLRPMMBTU.A | D18: 2025 $/MMBtu | E18: 12.803329 | F18: 11.070506 | G18: 11.206452 | H18: 11.985374 | I18: 12.701868 | J18: 13.610707 | K18: 14.804296 | L18: 15.44972 | M18: 15.938818 | N18: 16.397631 | O18: 16.843964 | P18: 17.28784 | Q18: 17.796278 | R18: 18.323847 | S18: 18.837675 | T18: 19.180521 | U18: 19.393515 | V18: 19.345053 | W18: 19.097935 | X18: 18.849525 | Y18: 18.891359 | Z18: 19.097252 | AA18: 19.322502 | AB18: 19.556145 | AC18: 19.710878 | AD18: 19.82361 | AE18: 1.8%
A19: Distillate Fuel Oil | B19: Energy Prices: Industrial: Distillate Fuel Oil: Alternative Electricity and Transportation | C19: AEO.2026.ELECTRNP.PRCE_REAL_IDAL_NA_DFO_NA_NA_Y13DLRPMMBTU.A | D19: 2025 $/MMBtu | E19: 26.296053 | F19: 23.833601 | G19: 23.638857 | H19: 23.038036 | I19: 22.345837 | J19: 21.403448 | K19: 20.701952 | L19: 20.792048 | M19: 21.235609 | N19: 21.284655 | O19: 21.554102 | P19: 21.790516 | Q19: 21.993568 | R19: 22.218029 | S19: 22.360266 | T19: 22.468481 | U19: 22.646593 | V19: 22.818218 | W19: 22.982805 | X19: 23.14827 | Y19: 23.446985 | Z19: 23.691965 | AA19: 23.897724 | AB19: 24.253218 | AC19: 24.570869 | AD19: 24.648556 | AE19: -0.3%
A20: Residual Fuel Oil | B20: Energy Prices: Industrial: Residual Fuel Oil: Alternative Electricity and Transportation | C20: AEO.2026.ELECTRNP.PRCE_REAL_IDAL_NA_RFO_NA_NA_Y13DLRPMMBTU.A | D20: 2025 $/MMBtu | E20: 8.660571 | F20: 6.715567 | G20: 8.522038 | H20: 9.873669 | I20: 11.099524 | J20: 11.661168 | K20: 13.208466 | L20: 13.227586 | M20: 13.603677 | N20: 13.60303 | O20: 13.923897 | P20: 14.127029 | Q20: 14.24397 | R20: 14.455325 | S20: 14.636956 | T20: 14.920378 | U20: 15.235559 | V20: 15.414781 | W20: 15.55131 | X20: 15.699274 | Y20: 15.955344 | Z20: 16.133854 | AA20: 16.286076 | AB20: 16.658579 | AC20: 16.88113 | AD20: 16.995434 | AE20: 2.7%
A21: Natural Gas | B21: Energy Prices: Industrial: Natural Gas: Alternative Electricity and Transportation | C21: AEO.2026.ELECTRNP.PRCE_REAL_IDAL_NA_NG_NA_NA_Y13DLRPMMBTU.A | D21: 2025 $/MMBtu | E21: 4.50558 | F21: 4.762314 | G21: 4.653281 | H21: 4.763201 | I21: 4.869151 | J21: 5.331843 | K21: 5.603321 | L21: 5.732351 | M21: 5.729695 | N21: 5.753252 | O21: 5.833182 | P21: 5.894095 | Q21: 5.954556 | R21: 6.014329 | S21: 6.085847 | T21: 6.137111 | U21: 6.097115 | V21: 5.918629 | W21: 5.685004 | X21: 5.45957 | Y21: 5.35239 | Z21: 5.345496 | AA21: 5.358559 | AB21: 5.360599 | AC21: 5.342124 | AD21: 5.304864 | AE21: 0.7%
A22: Metallurgical Coal | B22: Energy Prices: Industrial: Metallurgical Coal: Alternative Electricity and Transportation | C22: AEO.2026.ELECTRNP.PRCE_REAL_IDAL_NA_MTC_NA_NA_Y13DLRPMMBTU.A | D22: 2025 $/MMBtu | E22: 6.417383 | F22: 6.420651 | G22: 6.426186 | H22: 6.438872 | I22: 6.430643 | J22: 6.445238 | K22: 6.428822 | L22: 6.450939 | M22: 6.448793 | N22: 6.427662 | O22: 6.431542 | P22: 6.396736 | Q22: 6.402119 | R22: 6.399268 | S22: 6.369291 | T22: 6.372983 | U22: 6.362854 | V22: 6.351582 | W22: 6.346869 | X22: 6.336841 | Y22: 6.341089 | Z22: 6.332882 | AA22: 6.343362 | AB22: 6.351777 | AC22: 6.326384 | AD22: 6.320745 | AE22: -0.1%
A23: Other Industrial Coal | B23: Energy Prices: Industrial: Other Industrial Coal: Alternative Electricity and Transportation | C23: AEO.2026.ELECTRNP.PRCE_REAL_IDAL_NA_OIC_NA_NA_Y13DLRPMMBTU.A | D23: 2025 $/MMBtu | E23: 3.995581 | F23: 3.856261 | G23: 3.764525 | H23: 3.757948 | I23: 3.763418 | J23: 3.732887 | K23: 3.730853 | L23: 3.714679 | M23: 3.707622 | N23: 3.688801 | O23: 3.676832 | P23: 3.676414 | Q23: 3.681888 | R23: 3.688266 | S23: 3.674037 | T23: 3.689501 | U23: 3.687816 | V23: 3.694248 | W23: 3.693033 | X23: 3.691283 | Y23: 3.694595 | Z23: 3.684059 | AA23: 3.691954 | AB23: 3.702715 | AC23: 3.733721 | AD23: 3.733987 | AE23: -0.3%
A24: Hydrogen | B24: Energy Prices: Industrial: Hydrogen: Alternative Electricity and Transportation | C24: AEO.2026.ELECTRNP.PRCE_REAL_IDAL_NA_HDG_NA_NA_Y13DLRPMMBTU.A | D24: 2025 $/MMBtu | E24: 11.501233 | F24: 11.889143 | G24: 11.882795 | H24: 12.018814 | I24: 12.101516 | J24: 12.795125 | K24: 13.07889 | L24: 13.222679 | M24: 13.297702 | N24: 13.326265 | O24: 13.258114 | P24: 13.428031 | Q24: 13.448741 | R24: 13.548419 | S24: 13.640569 | T24: 13.690514 | U24: 13.610089 | V24: 13.418937 | W24: 13.098224 | X24: 12.831071 | Y24: 12.693266 | Z24: 12.639281 | AA24: 12.648698 | AB24: 12.653787 | AC24: 12.621601 | AD24: 12.580778 | AE24: 0.4%
A25: Electricity | B25: Energy Prices: Industrial: Electricity: Alternative Electricity and Transportation | C25: AEO.2026.ELECTRNP.PRCE_REAL_IDAL_NA_ELC_NA_NA_Y13DLRPMMBTU.A | D25: 2025 $/MMBtu | E25: 26.595726 | F25: 26.456028 | G25: 25.259417 | H25: 24.60338 | I25: 24.805864 | J25: 25.174835 | K25: 25.531858 | L25: 25.659849 | M25: 25.863104 | N25: 25.987514 | O25: 26.078087 | P25: 26.141869 | Q25: 26.27035 | R25: 26.342882 | S25: 26.495277 | T25: 26.657043 | U25: 26.650555 | V25: 26.505461 | W25: 26.353251 | X25: 26.213223 | Y25: 26.001282 | Z25: 26.1353 | AA25: 26.219656 | AB25: 26.274858 | AC25: 26.257725 | AD25: 26.297056 | AE25: -0.0%
A26: Transportation
A27: Propane | B27: Energy Prices: Transportation: Propane: Alternative Electricity and Transportation | C27: AEO.2026.ELECTRNP.PRCE_REAL_TRN_NA_PROP_NA_NA_Y13DLRPMMBTU.A | D27: 2025 $/MMBtu | E27: 18.230301 | F27: 16.552263 | G27: 16.820892 | H27: 17.604309 | I27: 18.24124 | J27: 19.043062 | K27: 20.069946 | L27: 20.552721 | M27: 21.146692 | N27: 21.506077 | O27: 21.854965 | P27: 22.199589 | Q27: 22.626129 | R27: 23.029554 | S27: 23.41511 | T27: 23.656843 | U27: 23.802324 | V27: 23.743452 | W27: 23.539431 | X27: 23.348461 | Y27: 23.399086 | Z27: 23.56638 | AA27: 23.736202 | AB27: 23.909195 | AC27: 24.016409 | AD27: 24.094131 | AE27: 1.1%
A28: E85 | B28: Energy Prices: Transportation: E85: Alternative Electricity and Transportation | C28: AEO.2026.ELECTRNP.PRCE_REAL_TRN_NA_E85_NA_NA_Y13DLRPMMBTU.A | D28: 2025 $/MMBtu | E28: 30.587164 | F28: 30.36919 | G28: 28.677048 | H28: 28.2055 | I28: 28.333576 | J28: 27.90696 | K28: 28.297533 | L28: 28.363214 | M28: 28.906786 | N28: 29.033493 | O28: 29.410183 | P28: 29.609522 | Q28: 30.050383 | R28: 30.233578 | S28: 30.387833 | T28: 30.462471 | U28: 30.467457 | V28: 30.653212 | W28: 30.740496 | X28: 30.804457 | Y28: 31.101137 | Z28: 31.1141 | AA28: 31.294554 | AB28: 31.505432 | AC28: 31.763111 | AD28: 31.845535 | AE28: 0.2%
A29: Motor Gasoline | B29: Energy Prices: Transportation: Motor Gasoline: Alternative Electricity and Transportation | C29: AEO.2026.ELECTRNP.PRCE_REAL_TRN_NA_MGS_NA_NA_Y13DLRPMMBTU.A | D29: 2025 $/MMBtu | E29: 26.463598 | F29: 24.831171 | G29: 23.518368 | H29: 23.004744 | I29: 23.038351 | J29: 23.289743 | K29: 23.568689 | L29: 23.684021 | M29: 24.450918 | N29: 24.526552 | O29: 24.818319 | P29: 24.988811 | Q29: 25.278088 | R29: 25.447397 | S29: 25.542393 | T29: 25.600281 | U29: 25.635571 | V29: 25.792301 | W29: 25.817257 | X29: 25.84659 | Y29: 26.046753 | Z29: 26.044968 | AA29: 26.29113 | AB29: 26.432318 | AC29: 26.660412 | AD29: 26.726423 | AE29: 0.0%
A30: Jet Fuel | B30: Energy Prices: Transportation: Jet Fuel: Alternative Electricity and Transportation | C30: AEO.2026.ELECTRNP.PRCE_REAL_TRN_NA_JFL_NA_NA_Y13DLRPMMBTU.A | D30: 2025 $/MMBtu | E30: 16.24399 | F30: 14.4871 | G30: 15.513252 | H30: 16.03964 | I30: 16.462814 | J30: 16.312712 | K30: 16.80451 | L30: 16.986189 | M30: 17.484211 | N30: 17.613974 | O30: 17.961834 | P30: 18.126896 | Q30: 18.469297 | R30: 18.758896 | S30: 18.889296 | T30: 19.018703 | U30: 19.250025 | V30: 19.479725 | W30: 19.698156 | X30: 19.915535 | Y30: 20.284185 | Z30: 20.584663 | AA30: 20.83234 | AB30: 21.223341 | AC30: 21.568563 | AD30: 21.66478 | AE30: 1.2%
A31: Diesel Fuel (distillate fuel oil) | B31: Energy Prices: Transportation: Diesel Fuel: Alternative Electricity and Transportation | C31: AEO.2026.ELECTRNP.PRCE_REAL_TRN_NA_DFU_NA_NA_Y13DLRPMMBTU.A | D31: 2025 $/MMBtu | E31: 26.549246 | F31: 24.754402 | G31: 25.146049 | H31: 25.384148 | I31: 25.486162 | J31: 25.511885 | K31: 25.44924 | L31: 25.436338 | M31: 26.519083 | N31: 26.532316 | O31: 26.699427 | P31: 27.012766 | Q31: 27.32885 | R31: 27.564703 | S31: 27.733109 | T31: 27.806482 | U31: 27.91873 | V31: 28.089151 | W31: 28.242386 | X31: 28.371828 | Y31: 28.690002 | Z31: 28.967188 | AA31: 29.070974 | AB31: 29.503574 | AC31: 29.85874 | AD31: 29.888166 | AE31: 0.5%
A32: Residual Fuel Oil | B32: Energy Prices: Transportation: Residual Fuel Oil: Alternative Electricity and Transportation | C32: AEO.2026.ELECTRNP.PRCE_REAL_TRN_NA_RFO_NA_NA_Y13DLRPMMBTU.A | D32: 2025 $/MMBtu | E32: 11.500687 | F32: 8.931035 | G32: 9.992164 | H32: 10.493447 | I32: 10.883081 | J32: 10.811728 | K32: 11.4814 | L32: 11.471013 | M32: 11.732704 | N32: 11.79624 | O32: 11.959019 | P32: 12.090819 | Q32: 12.15266 | R32: 12.296811 | S32: 12.393431 | T32: 12.606599 | U32: 12.850627 | V32: 12.981843 | W32: 13.100346 | X32: 13.21874 | Y32: 13.412382 | Z32: 13.543149 | AA32: 13.652481 | AB32: 13.942177 | AC32: 14.112513 | AD32: 14.196051 | AE32: 0.8%
A33: Natural Gas | B33: Energy Prices: Transportation: Natural Gas: Alternative Electricity and Transportation | C33: AEO.2026.ELECTRNP.PRCE_REAL_TRN_NA_NG_NA_NA_Y13DLRPMMBTU.A | D33: 2025 $/MMBtu | E33: 17.201744 | F33: 17.367626 | G33: 17.20513 | H33: 17.230907 | I33: 17.254618 | J33: 17.582851 | K33: 17.762487 | L33: 17.762171 | M33: 18.35153 | N33: 18.259518 | O33: 18.228081 | P33: 18.170092 | Q33: 18.233154 | R33: 18.165155 | S33: 18.111385 | T33: 18.037727 | U33: 17.903183 | V33: 17.6322 | W33: 17.3223 | X33: 17.006472 | Y33: 16.781309 | Z33: 16.668741 | AA33: 16.575771 | AB33: 16.473715 | AC33: 16.353365 | AD33: 16.210371 | AE33: -0.2%
A34: Hydrogen | B34: Energy Prices: Transportation: Hydrogen: Alternative Electricity and Transportation | C34: AEO.2026.ELECTRNP.PRCE_REAL_TRN_NA_HDG_NA_NA_Y13DLRPMMBTU.A | D34: 2025 $/MMBtu | E34: 62.374836 | F34: 62.746746 | G34: 62.738457 | H34: 63.015266 | I34: 63.048782 | J34: 63.657555 | K34: 64.013809 | L34: 64.172546 | M34: 63.995075 | N34: 64.052963 | O34: 64.015572 | P34: 64.193886 | Q34: 64.200798 | R34: 64.280998 | S34: 64.31958 | T34: 64.383682 | U34: 64.349739 | V34: 64.173012 | W34: 63.824421 | X34: 63.489323 | Y34: 63.327377 | Z34: 63.308292 | AA34: 63.319298 | AB34: 63.316147 | AC34: 63.268272 | AD34: 63.212685 | AE34: 0.1%
A35: Electricity | B35: Energy Prices: Transportation: Electricity: Alternative Electricity and Transportation | C35: AEO.2026.ELECTRNP.PRCE_REAL_TRN_NA_ELC_NA_NA_Y13DLRPMMBTU.A | D35: 2025 $/MMBtu | E35: 45.167717 | F35: 45.211803 | G35: 43.827431 | H35: 42.073334 | I35: 42.334553 | J35: 42.817829 | K35: 42.929928 | L35: 42.931519 | M35: 43.02079 | N35: 43.47242 | O35: 43.645496 | P35: 43.821453 | Q35: 44.27552 | R35: 44.603706 | S35: 44.946266 | T35: 45.146526 | U35: 45.177845 | V35: 45.216255 | W35: 45.159939 | X35: 45.161938 | Y35: 45.029476 | Z35: 45.154152 | AA35: 45.380165 | AB35: 45.611683 | AC35: 45.634094 | AD35: 45.765835 | AE35: 0.1%
A36: Electric Power
A37: Distillate Fuel Oil | B37: Energy Prices: Electric Power: Distillate Fuel Oil: Alternative Electricity and Transportation | C37: AEO.2026.ELECTRNP.PRCE_REAL_ELEP_NA_DFO_NA_NA_Y13DLRPMMBTU.A | D37: 2025 $/MMBtu | E37: 26.278624 | F37: 23.83396 | G37: 23.667582 | H37: 23.0767 | I37: 22.468193 | J37: 21.169487 | K37: 20.318287 | L37: 20.499811 | M37: 20.884249 | N37: 20.985836 | O37: 21.269566 | P37: 21.363935 | Q37: 21.671391 | R37: 21.886341 | S37: 21.976656 | T37: 22.05175 | U37: 22.177374 | V37: 22.304358 | W37: 22.457405 | X37: 22.544127 | Y37: 22.767513 | Z37: 23.029613 | AA37: 23.194906 | AB37: 23.517214 | AC37: 23.876028 | AD37: 23.956615 | AE37: -0.4%
A38: Residual Fuel Oil | B38: Energy Prices: Electric Power: Residual Fuel Oil: Alternative Electricity and Transportation | C38: AEO.2026.ELECTRNP.PRCE_REAL_ELEP_NA_RFO_NA_NA_Y13DLRPMMBTU.A | D38: 2025 $/MMBtu | E38: 15.195043 | F38: 11.392761 | G38: 12.551583 | H38: 13.300132 | I38: 13.720533 | J38: 13.623014 | K38: 14.514482 | L38: 14.386337 | M38: 14.620389 | N38: 14.717921 | O38: 14.781165 | P38: 14.877487 | Q38: 14.899772 | R38: 14.996532 | S38: 15.10175 | T38: 15.246218 | U38: 15.251705 | V38: 15.076466 | W38: 14.716722 | X38: 14.241821 | Y38: 13.642546 | Z38: 13.774843 | AA38: 13.929864 | AB38: 14.288077 | AC38: 14.514351 | AD38: 14.621839 | AE38: -0.2%
A39: Natural Gas | B39: Energy Prices: Electric Power: Natural Gas: Alternative Electricity and Transportation | C39: AEO.2026.ELECTRNP.PRCE_REAL_ELEP_NA_NG_NA_NA_Y13DLRPMMBTU.A | D39: 2025 $/MMBtu | E39: 3.808666 | F39: 3.996138 | G39: 3.841855 | H39: 3.903839 | I39: 4.022358 | J39: 4.488593 | K39: 4.807109 | L39: 4.867753 | M39: 4.861639 | N39: 4.921796 | O39: 4.90788 | P39: 4.991194 | Q39: 5.102775 | R39: 5.07047 | S39: 5.177992 | T39: 5.210255 | U39: 5.140097 | V39: 4.979245 | W39: 4.803178 | X39: 4.618877 | Y39: 4.497294 | Z39: 4.476685 | AA39: 4.468712 | AB39: 4.490125 | AC39: 4.482105 | AD39: 4.460569 | AE39: 0.6%
A40: Steam Coal | B40: Energy Prices: Electric Power: Steam Coal: Alternative Electricity and Transportation | C40: AEO.2026.ELECTRNP.PRCE_REAL_ELEP_NA_STC_NA_NA_Y13DLRPMMBTU.A | D40: 2025 $/MMBtu | E40: 2.563418 | F40: 2.517128 | G40: 2.476177 | H40: 2.460434 | I40: 2.453598 | J40: 2.465424 | K40: 2.420226 | L40: 2.404923 | M40: 2.399562 | N40: 2.37884 | O40: 2.376873 | P40: 2.373297 | Q40: 2.412463 | R40: 2.417426 | S40: 2.434603 | T40: 2.440476 | U40: 2.433299 | V40: 2.431062 | W40: 2.44073 | X40: 2.431652 | Y40: 2.441896 | Z40: 2.455096 | AA40: 2.464806 | AB40: 2.473632 | AC40: 2.503402 | AD40: 2.503686 | AE40: -0.1%
A41: Nuclear Fuel | B41: Energy Prices: Electric Power: Nuclear Fuel: Alternative Electricity and Transportation | C41: AEO.2026.ELECTRNP.PRCE_REAL_ELEP_NA_U_NA_NA_Y13DLRPMMBTU.A | D41: 2025 $/MMBtu | E41: 0.549997 | F41: 0.545068 | G41: 0.544083 | H41: 0.542111 | I41: 0.54014 | J41: 0.538169 | K41: 0.535212 | L41: 0.532255 | M41: 0.529298 | N41: 0.525355 | O41: 0.521413 | P41: 0.51747 | Q41: 0.514513 | R41: 0.511556 | S41: 0.508599 | T41: 0.504656 | U41: 0.501699 | V41: 0.497757 | W41: 0.4948 | X41: 0.490857 | Y41: 0.486915 | Z41: 0.482972 | AA41: 0.480015 | AB41: 0.476072 | AC41: 0.47213 | AD41: 0.468187 | AE41: -0.6%
A42: Hydrogen | B42: Energy Prices: Electric Power: Hydrogen: Alternative Electricity and Transportation | C42: AEO.2026.ELECTRNP.PRCE_REAL_ELEP_NA_HDG_NA_NA_Y13DLRPMMBTU.A | D42: 2025 $/MMBtu | E42: 11.501233 | F42: 11.889143 | G42: 11.882795 | H42: 12.018814 | I42: 12.101516 | J42: 12.795125 | K42: 13.07889 | L42: 13.222679 | M42: 13.297702 | N42: 13.326265 | O42: 13.258114 | P42: 13.428031 | Q42: 13.448741 | R42: 13.548419 | S42: 13.640569 | T42: 13.690514 | U42: 13.610089 | V42: 13.418937 | W42: 13.098224 | X42: 12.831071 | Y42: 12.693266 | Z42: 12.639281 | AA42: 12.648698 | AB42: 12.653787 | AC42: 12.621601 | AD42: 12.580778 | AE42: 0.4%
A43: Average Price to All Users
A44: Propane | B44: Energy Prices: Average Price to All Users: Propane: Alternative Electricity and Transportation | C44: AEO.2026.ELECTRNP.PRCE_REAL_TEN_NA_PROP_NA_NA_Y13DLRPMMBTU.A | D44: 2025 $/MMBtu | E44: 22.702044 | F44: 22.01132 | G44: 19.890575 | H44: 20.410051 | I44: 21.036221 | J44: 21.90551 | K44: 23.090216 | L44: 23.818689 | M44: 24.668346 | N44: 25.227968 | O44: 25.747189 | P44: 26.245014 | Q44: 26.785839 | R44: 27.313734 | S44: 27.835369 | T44: 28.224968 | U44: 28.504122 | V44: 28.541237 | W44: 28.373795 | X44: 28.155216 | Y44: 28.14237 | Z44: 28.278894 | AA44: 28.458744 | AB44: 28.665367 | AC44: 28.819273 | AD44: 28.935324 | AE44: 1.0%
A45: E85 | B45: Energy Prices: Average Price to All Users: E85: Alternative Electricity and Transportation | C45: AEO.2026.ELECTRNP.PRCE_REAL_TEN_NA_E85_NA_NA_Y13DLRPMMBTU.A | D45: 2025 $/MMBtu | E45: 30.587164 | F45: 30.36919 | G45: 28.677048 | H45: 28.2055 | I45: 28.333576 | J45: 27.90696 | K45: 28.297533 | L45: 28.363214 | M45: 28.906786 | N45: 29.033493 | O45: 29.410183 | P45: 29.609522 | Q45: 30.050383 | R45: 30.233578 | S45: 30.387833 | T45: 30.462471 | U45: 30.467457 | V45: 30.653212 | W45: 30.740496 | X45: 30.804457 | Y45: 31.101137 | Z45: 31.1141 | AA45: 31.294554 | AB45: 31.505432 | AC45: 31.763111 | AD45: 31.845535 | AE45: 0.2%
A46: Motor Gasoline | B46: Energy Prices: Average Price to All Users: Motor Gasoline: Alternative Electricity and Transportation | C46: AEO.2026.ELECTRNP.PRCE_REAL_TEN_NA_MGS_NA_NA_Y13DLRPMMBTU.A | D46: 2025 $/MMBtu | E46: 26.495358 | F46: 24.872759 | G46: 23.603987 | H46: 23.102119 | I46: 23.124382 | J46: 23.349243 | K46: 23.592163 | L46: 23.708321 | M46: 24.476206 | N46: 24.552603 | O46: 24.845331 | P46: 25.016809 | Q46: 25.307272 | R46: 25.477606 | S46: 25.573629 | T46: 25.632381 | U46: 25.668381 | V46: 25.825891 | W46: 25.851852 | X46: 25.881882 | Y46: 26.082901 | Z46: 26.081779 | AA46: 26.328762 | AB46: 26.4711 | AC46: 26.700232 | AD46: 26.76704 | AE46: 0.0%
A47: Jet Fuel | B47: Energy Prices: Average Price to All Users: Jet Fuel: Alternative Electricity and Transportation | C47: AEO.2026.ELECTRNP.PRCE_REAL_TEN_NA_JFL_NA_NA_Y13DLRPMMBTU.A | D47: 2025 $/MMBtu | E47: 16.24399 | F47: 14.4871 | G47: 15.513252 | H47: 16.03964 | I47: 16.462814 | J47: 16.312712 | K47: 16.80451 | L47: 16.986189 | M47: 17.484211 | N47: 17.613974 | O47: 17.961834 | P47: 18.126896 | Q47: 18.469297 | R47: 18.758896 | S47: 18.889296 | T47: 19.018703 | U47: 19.250025 | V47: 19.479725 | W47: 19.698156 | X47: 19.915535 | Y47: 20.284185 | Z47: 20.584663 | AA47: 20.83234 | AB47: 21.223341 | AC47: 21.568563 | AD47: 21.66478 | AE47: 1.2%
A48: Distillate Fuel Oil | B48: Energy Prices: Average Price to All Users: Distillate Fuel Oil: Alternative Electricity and Transportation | C48: AEO.2026.ELECTRNP.PRCE_REAL_TEN_NA_DFO_NA_NA_Y13DLRPMMBTU.A | D48: 2025 $/MMBtu | E48: 26.48362 | F48: 24.537634 | G48: 24.933687 | H48: 24.947424 | I48: 24.864519 | J48: 24.596664 | K48: 24.478802 | L48: 24.558308 | M48: 25.454048 | N48: 25.480738 | O48: 25.735588 | P48: 25.989059 | Q48: 26.231991 | R48: 26.447695 | S48: 26.59292 | T48: 26.702436 | U48: 26.871063 | V48: 27.024204 | W48: 27.179129 | X48: 27.326935 | Y48: 27.619408 | Z48: 27.856705 | AA48: 28.047062 | AB48: 28.40428 | AC48: 28.716272 | AD48: 28.790123 | AE48: 0.3%
A49: Residual Fuel Oil | B49: Energy Prices: Average Price to All Users: Residual Fuel Oil: Alternative Electricity and Transportation | C49: AEO.2026.ELECTRNP.PRCE_REAL_TEN_NA_RFO_NA_NA_Y13DLRPMMBTU.A | D49: 2025 $/MMBtu | E49: 11.658544 | F49: 9.018538 | G49: 10.140831 | H49: 10.694611 | I49: 11.126874 | J49: 11.083372 | K49: 11.808846 | L49: 11.781062 | M49: 12.035919 | N49: 12.088141 | O49: 12.242559 | P49: 12.36689 | Q49: 12.420006 | R49: 12.556002 | S49: 12.649469 | T49: 12.854072 | U49: 13.074571 | V49: 13.178183 | W49: 13.26378 | X49: 13.350979 | Y49: 13.516272 | Z49: 13.647001 | AA49: 13.757747 | AB49: 14.050404 | AC49: 14.222381 | AD49: 14.306244 | AE49: 0.8%
A50: Natural Gas | B50: Energy Prices: Average Price to All Users: Natural Gas: Alternative Electricity and Transportation | C50: AEO.2026.ELECTRNP.PRCE_REAL_TEN_NA_NG_NA_NA_Y13DLRPMMBTU.A | D50: 2025 $/MMBtu | E50: 6.555398 | F50: 6.404567 | G50: 6.472768 | H50: 6.604234 | I50: 6.772833 | J50: 7.227516 | K50: 7.473804 | L50: 7.557317 | M50: 7.646621 | N50: 7.692187 | O50: 7.754945 | P50: 7.822206 | Q50: 7.914823 | R50: 7.924808 | S50: 7.998958 | T50: 8.022047 | U50: 7.968006 | V50: 7.79886 | W50: 7.590972 | X50: 7.379402 | Y50: 7.251836 | Z50: 7.218354 | AA50: 7.206153 | AB50: 7.201671 | AC50: 7.175305 | AD50: 7.138707 | AE50: 0.3%
