Workbook

Sheet About
A1: TBCC Thermal Battery Capital Cost per Unit Annual Energy Served
A3: Sources: | B3: Component capital costs (charging equipment, heat delivery, storage medium)
B4: Rissman & Gimon (2023)
B5: "Thermal Batteries: Decarbonizing U.S. Industry While Supporting a High-Renewables Grid," Energy Innovation, p.15
B6: 2023
B7: https://energyinnovation.org/report/thermal-batteries-decarbonizing-u-s-industry-while-supporting-a-high-renewables-grid/
B8: 2023 USD component costs: charging equipment $100/kW-in; steam-side heat delivery $300/kW-out; storage medium $5/kWh-th (range $1.5-10/kWh-th). System spec assumed: continuous load, 6-hour charging window => 4.0 kW-in and 18 kWh-th storage per kW-out. All derivation formulas are visible on the 'TBCC Components' tab.
B10: Direct-heat discharge equipment cost (blower), used for bands where steam infrastructure is not the relevant discharge path
B11: Stack, Curtis & Forsberg (2019)
B12: "Performance of firebrick resistance-heated energy storage for industrial heat applications and round-trip electricity storage," Applied Energy, Table 3 (installed cost)
B13: 2019
B14: https://www.sciencedirect.com/science/article/pii/S0306261919305082
B15: Blower (discharge-side) installed cost $6.47/kW-discharge, 2017 USD, at a 50 MWt base-case unit; deflated to 2023 USD via CPI-U (245.120 -> 304.702) on the 'TBCC Components' tab (rows 22-25). BOUNDARY NOTE: this is an installed-cost figure for a bare industrial blower forcing air through a firebrick stack -- a different (and much cheaper) discharge technology than the $300/kW-out steam-side heat-delivery equipment R&G price. The workbook blends the two by each band's steam share w_b ('Band Weights' tab) rather than picking one uniformly. Both source figures may mix installed vs. equipment-only cost scope differently; where that is uncertain we have NOT tried to correct for it, which is conservative in the direction of not understating discharge-side cost (see Industry_ThermalBattery_Stack2019_Extract.md, repo root, for the full extraction and a note that R&G's $300/kW figure is ~46x Stack's blower figure with no reconciliation found in either source).
B17: Industrial steam vs. direct-heat split, by industry (weights the discharge-equipment blend by how much of each temperature band is steam- vs. direct-fired)
B18: EIA, Manufacturing Energy Consumption Survey (MECS) 2022
B19: Table 5.2, "End uses of fuel consumption, 2022"
B20: 2022
B21: https://www.eia.gov/consumption/manufacturing/data/2022/xls/Table5_2.xlsx
B22: Rolled up to EPS Industry Categories on the 'MECS 2022' tab. Full extraction, method, and data-quality caveats: Industry_ThermalBattery_MECS_SteamShares.md (repo root). Key caveats (see Notes below for the full discussion): the CHP-fuel steam/power split is not reported by MECS and is assumed here (CHP-steam fraction = 0.6, an editable cell on the MECS 2022 tab); 35.5% of national manufacturing fuel use is not classified to any end use at all (worst in paper, refining, and iron & steel -- treat those three plus wood products as the least reliable category splits); category-level splits carry roughly +-5-10% sampling noise on top of that.
B24: Band heat demand by Industry Category, 2025 (denominator for the steam-share waterfall; also the basis the demand cap itself uses)
B25: EPS model (this repo)
B26: Thermal Battery Demand Cap in Electricity Equivalent[Industry Category,Industrial Process], 2025 column, electricity-equivalent BTU/yr
B27: 2026
B28: https://github.com/EnergyInnovation/eps-us
B29: EPS defaults run TB_omrm_newdef, extracted 2026-08-20 (TB_bandheat.tab, repo root). Pasted verbatim onto the 'Band Heat 2025' tab. This is a model output, not an external primary source -- it will drift if the underlying demand-cap logic or input data changes, and should be re-extracted if this workbook is revisited long after 2026-08-20.
A32: Notes:
A33: Result | B33: Five band values, 2012 USD per BTU/yr of annual energy service (electricity equivalent), computed on the 'TBCC' export tab from the 'Band Weights' tab's per-band system cost: heat<100C 1.82e-5, heat100-200C 1.78e-5, heat200-500C 1.37e-5, heat500-1000C and heat>1000C both 1.26e-5 (the two highest bands share w_b=0 -- no steam infrastructure reaches them -- so they get the same all-blower discharge cost). See the 'Checks' tab for the formula-vs-CSV comparison (all five bands agree with TBCC.csv to within ~0.1%, well inside the 0.5% tolerance).
A34: Derivation chain | B34: Component costs ('TBCC Components' tab) -> MECS steam shares by category ('MECS 2022') -> IC-to-category mapping and a per-IC waterfall that fills each Industry Category's steam heat into bands left-to-right up to a 300C ceiling ('Band Weights') -> demand-weighted steam share w_b per band -> discharge-cost blend (w_b x steam-side $300/kW-out + (1-w_b) x blower $/kW-out) -> full system cost -> CPI-U deflation to 2012 USD -> $/BTU-yr ('TBCC' export tab). Editing any source or assumption cell recomputes every downstream value.
A35: The 300C ceiling and the one-third-band-slice assumption | B35: Steam heat above ~300C in practice is rare (atmospheric/low-pressure steam tops out well under the 200-500C band's upper edge); this workbook treats 300C as the steam ceiling and assumes heat is spread uniformly within the 200-500C band, so only the bottom third of that band (one of three equal 100C sub-ranges: 200-300, 300-400, 400-500) is treated as steam-reachable capacity. Bands above 500C get zero steam capacity outright. Both are simplifying assumptions, not measured facts -- flagged for review.
A36: Waterfall clips | B36: For a handful of Industry Categories, the steam heat implied by the MECS-based share (s_i x total band-eligible heat) exceeds what the 300C-ceiling caps can absorb in the available bands; the excess is clipped (left unfilled, not carried into a higher band, since steam physically doesn't reach there). Largest clips: chemicals ~14%, pulp/paper/printing ~10%, food/beverage/tobacco ~6% of that category's steam heat. See the 'clip' column on the 'Band Weights' tab for every category.
A37: MECS method and the CHP ambiguity | B37: MECS reports fuel burned in a CHP/cogeneration unit as a single line, with no split between the electricity/shaft-power output and the useful-heat output. This workbook assumes 60% of CHP fuel is steam output (CHP-steam fraction, 'MECS 2022' tab B1); the published bounds if that assumption were 100% vs. 0% are 48.0% vs. 21.5% manufacturing-wide steam share (national row on the MECS 2022 tab) -- a wide range, and the single biggest source of uncertainty in this workbook. Separately, 35.5% of all manufacturing fuel use nationally is not classified to any end use at all (mostly byproduct/waste fuels MECS never allocates), worst in paper, coke & refined petroleum, and iron & steel (each >40% unclassified) -- treat those category splits, plus wood products, as the least reliable. Every category split also carries an estimated +-5-10% ordinary sampling/footing noise on top of the CHP and unclassified-fuel issues. Full writeup: Industry_ThermalBattery_MECS_SteamShares.md (repo root).
A38: Non-MECS Industry Categories and the sensitivity check | B38: Industry Categories outside NAICS manufacturing (agriculture and forestry, coal mining, oil and gas extraction, other mining and quarrying, construction) have no MECS steam/direct-heat split available; they default to a 0.10 steam share ('Band Weights' tab B1), i.e. assumed mostly direct-fired. Oil and gas extraction alone is 21.5% of all Industry Categories' total eligible heat in the 2025 band-heat data, so this assumption is doing real work, not a rounding footnote. Sensitivity alternative: 0.399, the manufacturing-wide average steam share at the CHP=0.6 assumption ('MECS 2022' national row) -- i.e., if non-MECS categories instead ran a typical manufacturing steam mix rather than mostly-direct-fired equipment. This alternative is documented here but NOT wired into the shipped calculation; a team decision on which is more defensible for extraction/ag/construction processes (largely field/kiln/dryer direct heat, arguably supporting the 0.10 default) is still open.
A39: O&M is separate | B39: Operations & maintenance is NOT included in this capital-cost figure -- see TBOM (2% of TBCC per year, an unverified proxy; see TBOM/TBOM.xlsx for that derivation).
A40: Band heat basis | B40: The 'Band Heat 2025' tab pastes the model's own Thermal Battery Demand Cap in Electricity Equivalent by Industry Category and heat band -- an electricity-equivalent BTU figure, not raw fuel BTU -- because that is the basis the demand cap (and hence eligible adoption) is computed on. It is a single-year (2025) snapshot; the steam-share weights derived from it are not re-derived year by year.
A41: KNOWN BOUNDARY AMBIGUITY (component costs, flagged for review) | B41: The R&G source report does not state whether component costs are equipment-only or fully installed; the $100/kW-in charging-equipment figure is benchmarked to Li-ion equipment analogs, so an installation/balance-of-plant markup (often 30-100% for industrial equipment) may be missing. NREL Kocher et al. 2024 (Energy & Environmental Science 17:2206, DOI 10.1039/D3EE03594H) could not be retrieved full-text at compilation time and should be checked against this figure before external release. Separately, the R&G $300/kW-out steam-side figure and Stack et al.'s $6.47/kW-out blower figure differ by ~46x with no reconciliation found in either source -- see the blower source entry above.
A42: Provenance | B42: Component-cost block written by Claude Code, issue #387, 2026-08-17. MECS steam-share derivation (MECS 2022 / Band Heat 2025 / Band Weights / Checks tabs, and this rewritten About tab) written by Claude Code, 2026-08-20, per Industry_ThermalBattery_MECS_SteamShares.md and the session scratchpad script tbcc_weights.py. Reviewed by: (pending).
A43: Verification status | B43: All figures herein are inputs for staff review, not a finished model input or published position -- verify against the primary sources above before use in any external work product. This document and its assumptions (CHP fraction, non-MECS default, 300C ceiling) are open to revision by the team.
A44: 18h storage-duration convention (ratified) | B44: The 18-hour storage-duration convention used in the 'TBCC Components' tab (24 minus the 6-hour TBCH charging window => 4.0 kW-in and 18 kWh-th storage per kW-out; see the Sources block above) was ratified by Dan O'Brien, 2026-08-20, as internally consistent with TBCH Thermal Battery Daily Charging Hours (6 h/day) elsewhere in the model. The published literature on optimal thermal-battery storage duration clusters in the 15-24 hour range, and Rissman & Gimon's own reported optimum is 24 hours (i.e., a shorter, ~0-hour charging window) -- a documented alternative, not adopted here, since a 24-hour duration would be inconsistent with the 6-hour TBCH charging-window spec this workbook is built to match. Revisit both together if either changes.

Sheet TBCC Components
A1: Component | B1: Value | C1: Unit | D1: Source
A2: Charging equipment cost | B2: 100 | C2: $/kW-in (2023 USD) | D2: Rissman & Gimon 2023 p.15
A3: Heat delivery equipment cost | B3: 300 | C3: $/kW-out (2023 USD) | D3: Rissman & Gimon 2023 p.15
A4: Storage medium cost - low | B4: 1.5 | C4: $/kWh-th (2023 USD) | D4: ibid (range)
A5: Storage medium cost - central | B5: 5 | C5: $/kWh-th (2023 USD) | D5: ibid
A6: Storage medium cost - high | B6: 10 | C6: $/kWh-th (2023 USD) | D6: ibid (range)
A7: Charging window | B7: 6 | C7: hours/day | D7: Jeff Rissman, issue #387
A8: Charge rate multiple | B8: =24/B7 -> 4 | C8: kW-in per kW-out
A9: Storage hours | B9: =24-B7 -> 18 | C9: kWh-th per kW-out
A10: System cost per kW-out - low | B10: =B2*B8+B3+B4*B9 -> 727 | C10: $/kW-out (2023 USD)
A11: System cost per kW-out - central | B11: =B2*B8+B3+B5*B9 -> 790 | C11: $/kW-out (2023 USD)
A12: System cost per kW-out - high | B12: =B2*B8+B3+B6*B9 -> 880 | C12: $/kW-out (2023 USD)
A13: Annual heat served per kW-out | B13: 8760 | C13: kWh-th/yr | D13: continuous service
A14: BTU per kWh | B14: 3412.14 | C14: BTU/kWh
A15: CPI-U 2012 | B15: 229.594 | C15: index | D15: BLS annual average
A16: CPI-U 2023 | B16: 304.702 | C16: index | D16: BLS annual average
A17: Deflator 2023->2012 | B17: =B15/B16 -> 0.75350342 | C17: dimensionless
A18: TBCC - low | B18: =B10*B17/(B13*B14) -> 1.8326887e-05 | C18: $/BTU-yr (2012 USD)
A19: TBCC - central | B19: =B11*B17/(B13*B14) -> 1.9915049e-05 | C19: $/BTU-yr (2012 USD) | D19: value exported to TBCC.csv
A20: TBCC - high | B20: =B12*B17/(B13*B14) -> 2.2183852e-05 | C20: $/BTU-yr (2012 USD)
A22: Direct-heat discharge equipmt (blower) cost, 2017 | B22: 6.47 | C22: $/kW-th (2017 USD, installed) | D22: Stack, Curtis & Forsberg 2019, Applied Energy, Table 3
A23: CPI-U 2017 | B23: 245.12 | C23: index | D23: BLS annual average
A24: Blower cost inflator, 2017->2023 | B24: =B16/B23 -> 1.2430728 | C24: dimensionless
A25: Direct-heat discharge equipmt cost, 2023 USD | B25: =B22*B24 -> 8.0426809 | C25: $/kW-th (2023 USD, installed) | D25: used by Band Weights tab per-band discharge blend

Sheet MECS 2022
A1: CHP-steam fraction (assumption, editable): | B1: 0.6
A2: Share of CHP/cogeneration fuel input attributed to steam output (vs. power/shaft-work output); MECS reports fuel input only, not the heat/power split (see About tab).
A4: EPS Industry Category (MECS rollup) | B4: Boiler (TBtu) | C4: CHP (TBtu) | D4: Process Heating (TBtu) | E4: Steam share s (this workbook, CHP frac = B1) | F4: Steam % incl. all CHP (upper bound) | G4: Steam % excl. CHP (lower bound) | H4: Not classified to any end use (published, informational)
A5: Food, beverage, tobacco | B5: 168 | C5: 304 | D5: 239 | E5: =(B5+$B$1*C5)/(B5+$B$1*C5+D5) -> 0.59450288 | F5: =(B5+C5)/(B5+C5+D5) -> 0.66385373 | G5: =B5/(B5+D5) -> 0.41277641 | H5: 0.135
A6: Textiles, apparel, leather | B6: 8 | C6: 6 | D6: 16 | E6: =(B6+$B$1*C6)/(B6+$B$1*C6+D6) -> 0.42028986 | F6: =(B6+C6)/(B6+C6+D6) -> 0.46666667 | G6: =B6/(B6+D6) -> 0.33333333 | H6: 0.049
A7: Wood products | B7: 6 | C7: 14 | D7: 51 | E7: =(B7+$B$1*C7)/(B7+$B$1*C7+D7) -> 0.22018349 | F7: =(B7+C7)/(B7+C7+D7) -> 0.28169014 | G7: =B7/(B7+D7) -> 0.10526316 | H7: 0.611
A8: Paper | B8: 76 | C8: 378 | D8: 154 | E8: =(B8+$B$1*C8)/(B8+$B$1*C8+D8) -> 0.66287215 | F8: =(B8+C8)/(B8+C8+D8) -> 0.74671053 | G8: =B8/(B8+D8) -> 0.33043478 | H8: 0.584
A9: Coke & refined petroleum | B9: 112 | C9: 246 | D9: 651 | E9: =(B9+$B$1*C9)/(B9+$B$1*C9+D9) -> 0.28508676 | F9: =(B9+C9)/(B9+C9+D9) -> 0.35480674 | G9: =B9/(B9+D9) -> 0.14678899 | H9: 0.631
A10: Chemicals | B10: 484 | C10: 993 | D10: 801 | E10: =(B10+$B$1*C10)/(B10+$B$1*C10+D10) -> 0.5741174 | F10: =(B10+C10)/(B10+C10+D10) -> 0.64837577 | G10: =B10/(B10+D10) -> 0.3766537 | H10: 0.217
A11: Rubber & plastics | B11: 22 | C11: 29 | D11: 48 | E11: =(B11+$B$1*C11)/(B11+$B$1*C11+D11) -> 0.45080092 | F11: =(B11+C11)/(B11+C11+D11) -> 0.51515152 | G11: =B11/(B11+D11) -> 0.31428571 | H11: 0
A12: Glass & cement (non-metallic minerals) | B12: 5 | C12: 12 | D12: 582 | E12: =(B12+$B$1*C12)/(B12+$B$1*C12+D12) -> 0.020531807 | F12: =(B12+C12)/(B12+C12+D12) -> 0.028380634 | G12: =B12/(B12+D12) -> 0.0085178876 | H12: 0.281
A13: Iron & steel | B13: 13 | C13: 35 | D13: 352 | E13: =(B13+$B$1*C13)/(B13+$B$1*C13+D13) -> 0.088082902 | F13: =(B13+C13)/(B13+C13+D13) -> 0.12 | G13: =B13/(B13+D13) -> 0.035616438 | H13: 0.429
A14: Other metals | B14: 8 | C14: 23 | D14: 189 | E14: =(B14+$B$1*C14)/(B14+$B$1*C14+D14) -> 0.10341556 | F14: =(B14+C14)/(B14+C14+D14) -> 0.14090909 | G14: =B14/(B14+D14) -> 0.040609137 | H14: 0.05
A15: Fabricated metal/machinery/electronics/vehicles | B15: 24 | C15: 18 | D15: 314 | E15: =(B15+$B$1*C15)/(B15+$B$1*C15+D15) -> 0.099770642 | F15: =(B15+C15)/(B15+C15+D15) -> 0.11797753 | G15: =B15/(B15+D15) -> 0.071005917 | H15: 0.036
A16: Other manufacturing | B16: 3 | C16: 3 | D16: 22 | E16: =(B16+$B$1*C16)/(B16+$B$1*C16+D16) -> 0.17910448 | F16: =(B16+C16)/(B16+C16+D16) -> 0.21428571 | G16: =B16/(B16+D16) -> 0.12 | H16: 0.039
A18: National total (all manufacturing, 311-339) | B18: 941 | C18: 2228 | D18: 3435 | E18: =(B18+$B$1*C18)/(B18+$B$1*C18+D18) -> 0.39871867 | F18: =(B18+C18)/(B18+C18+D18) -> 0.47986069 | G18: =B18/(B18+D18) -> 0.21503656 | H18: 0.355
A20: Source: EIA MECS 2022, Table 5.2 "End uses of fuel consumption, 2022" (https://www.eia.gov/consumption/manufacturing/data/2022/xls/Table5_2.xlsx). Rolled up to EPS Industry Categories per Industry_ThermalBattery_MECS_SteamShares.md (repo root), Section 5. National row (E18) is the manufacturing-wide steam share at the CHP assumption in B1 -- used in the About tab as the non-MECS-IC sensitivity alternative (0.399 at CHP frac 0.6).

Sheet Band Heat 2025
A1: Source: EPS defaults run TB_omrm_newdef, extracted 2026-08-20. Thermal Battery Demand Cap in Electricity Equivalent[Industry Category,Industrial Process], 2025 column, TB_bandheat.tab (BTU/yr, electricity-equivalent).
A2: Industry Category | B2: heat < 100 C | C2: heat 100 - 200 C | D2: heat 200 - 500 C | E2: heat 500 - 1000 C | F2: heat > 1000 C | G2: Total heat (all bands)
A3: agriculture and forestry 01T03 | B3: 95182700000000 | C3: 0 | D3: 0 | E3: 0 | F3: 0 | G3: =SUM(B3:F3) -> 95182700000000
A4: coal mining 05 | B4: 0 | C4: 0 | D4: 0 | E4: 0 | F4: 0 | G4: =SUM(B4:F4) -> 0
A5: oil and gas extraction 06 | B5: 67808300000000 | C5: 266432000000000 | D5: 1.05194e+15 | E5: 198903000000000 | F5: 0 | G5: =SUM(B5:F5) -> 1.5850833e+15
A6: other mining and quarrying 07T08 | B6: 60351000000000 | C6: 0 | D6: 0 | E6: 0 | F6: 0 | G6: =SUM(B6:F6) -> 60351000000000
A7: food beverage and tobacco 10T12 | B7: 47231200000000 | C7: 73812400000000 | D7: 282194000000000 | E7: 2383190000 | F7: 0 | G7: =SUM(B7:F7) -> 403239983190000
A8: textiles apparel and leather 13T15 | B8: 1237420000000 | C8: 807725000000 | D8: 2169290000000 | E8: 48598600000 | F8: 70537000000 | G8: =SUM(B8:F8) -> 4333570600000
A9: wood products 16 | B9: 8847760000000 | C9: 45213500000000 | D9: 114301000000000 | E9: 0 | F9: 0 | G9: =SUM(B9:F9) -> 168362260000000
A10: pulp paper and printing 17T18 | B10: 142216000000000 | C10: 190069000000000 | D10: 558254000000000 | E10: 32102700000000 | F10: 0 | G10: =SUM(B10:F10) -> 922641700000000
A11: refined petroleum and coke 19 | B11: 314578000000000 | C11: 329389000000000 | D11: 889339000000000 | E11: 206316000000000 | F11: 55929200000000 | G11: =SUM(B11:F11) -> 1.7955512e+15
A12: chemicals 20 | B12: 62164400000000 | C12: 229148000000000 | D12: 889348000000000 | E12: 169244000000000 | F12: 9632490000 | G12: =SUM(B12:F12) -> 1.349914e+15
A13: rubber and plastic products 22 | B13: 3131390000000 | C13: 12579600000000 | D13: 32111200000000 | E13: 7323910000000 | F13: 0 | G13: =SUM(B13:F13) -> 55146100000000
A14: glass and glass products 231 | B14: 0 | C14: 0 | D14: 1104560000000 | E14: 4545930000000 | F14: 58003100000000 | G14: =SUM(B14:F14) -> 63653590000000
... A27: construction 41T43 | B27: 62863500000000 | C27: 0 | D27: 0 | E27: 0 | F27: 0 | G27: =SUM(B27:F27) -> 62863500000000

Sheet Band Weights
A1: Non-MECS IC steam share (assumption, editable): | B1: 0.1 | C1: Applies to Industry Categories outside NAICS manufacturing (agriculture, mining, oil & gas extraction, construction) and zero-heat categories. Sensitivity alternative 0.399 (manufacturing-wide average at CHP frac 0.6, see 'MECS 2022' national row) is discussed in the About tab, not wired in here.
A3: Industry Category | B3: Mapped MECS category (assignment) | C3: s_i (steam share) | D3: heat < 100 C | E3: heat 100 - 200 C | F3: heat 200 - 500 C | G3: heat 500 - 1000 C | H3: heat > 1000 C | I3: Total heat T_i | J3: Steam heat S_i = s_i*T_i | K3: cap0 (=heat0) | L3: cap1 (=heat1) | M3: cap2 (=heat2/3, 300C ceiling) | N3: fill0 | O3: rem1 | P3: fill1 | Q3: rem2 | R3: fill2 | S3: clip (unfilled S_i, >300C) | T3: fill3 | U3: fill4
A4: agriculture and forestry 01T03 | B4: non-MECS default | C4: =$B$1 -> 0.1 | D4: =VLOOKUP($A4,'Band Heat 2025'!$A$3:$F$27,2,FALSE) -> 95182700000000 | E4: =VLOOKUP($A4,'Band Heat 2025'!$A$3:$F$27,3,FALSE) -> 0 | F4: =VLOOKUP($A4,'Band Heat 2025'!$A$3:$F$27,4,FALSE) -> 0 | G4: =VLOOKUP($A4,'Band Heat 2025'!$A$3:$F$27,5,FALSE) -> 0 | H4: =VLOOKUP($A4,'Band Heat 2025'!$A$3:$F$27,6,FALSE) -> 0 | I4: =SUM(D4:H4) -> 95182700000000 | J4: =C4*I4 -> 9518270000000 | K4: =D4 -> 95182700000000 | L4: =E4 -> 0 | M4: =F4/3 -> 0 | N4: =MIN(K4,J4) -> 9518270000000 | O4: =J4-N4 -> 0 | P4: =MIN(L4,O4) -> 0 | Q4: =O4-P4 -> 0 | R4: =MIN(M4,Q4) -> 0 | S4: =Q4-R4 -> 0 | T4: 0 | U4: 0
A5: coal mining 05 | B5: non-MECS default | C5: =$B$1 -> 0.1 | D5: =VLOOKUP($A5,'Band Heat 2025'!$A$3:$F$27,2,FALSE) -> 0 | E5: =VLOOKUP($A5,'Band Heat 2025'!$A$3:$F$27,3,FALSE) -> 0 | F5: =VLOOKUP($A5,'Band Heat 2025'!$A$3:$F$27,4,FALSE) -> 0 | G5: =VLOOKUP($A5,'Band Heat 2025'!$A$3:$F$27,5,FALSE) -> 0 | H5: =VLOOKUP($A5,'Band Heat 2025'!$A$3:$F$27,6,FALSE) -> 0 | I5: =SUM(D5:H5) -> 0 | J5: =C5*I5 -> 0 | K5: =D5 -> 0 | L5: =E5 -> 0 | M5: =F5/3 -> 0 | N5: =MIN(K5,J5) -> 0 | O5: =J5-N5 -> 0 | P5: =MIN(L5,O5) -> 0 | Q5: =O5-P5 -> 0 | R5: =MIN(M5,Q5) -> 0 | S5: =Q5-R5 -> 0 | T5: 0 | U5: 0
A6: oil and gas extraction 06 | B6: non-MECS default | C6: =$B$1 -> 0.1 | D6: =VLOOKUP($A6,'Band Heat 2025'!$A$3:$F$27,2,FALSE) -> 67808300000000 | E6: =VLOOKUP($A6,'Band Heat 2025'!$A$3:$F$27,3,FALSE) -> 266432000000000 | F6: =VLOOKUP($A6,'Band Heat 2025'!$A$3:$F$27,4,FALSE) -> 1.05194e+15 | G6: =VLOOKUP($A6,'Band Heat 2025'!$A$3:$F$27,5,FALSE) -> 198903000000000 | H6: =VLOOKUP($A6,'Band Heat 2025'!$A$3:$F$27,6,FALSE) -> 0 | I6: =SUM(D6:H6) -> 1.5850833e+15 | J6: =C6*I6 -> 158508330000000 | K6: =D6 -> 67808300000000 | L6: =E6 -> 266432000000000 | M6: =F6/3 -> 3.5064667e+14 | N6: =MIN(K6,J6) -> 67808300000000 | O6: =J6-N6 -> 90700030000000 | P6: =MIN(L6,O6) -> 90700030000000 | Q6: =O6-P6 -> 0 | R6: =MIN(M6,Q6) -> 0 | S6: =Q6-R6 -> 0 | T6: 0 | U6: 0
A7: other mining and quarrying 07T08 | B7: non-MECS default | C7: =$B$1 -> 0.1 | D7: =VLOOKUP($A7,'Band Heat 2025'!$A$3:$F$27,2,FALSE) -> 60351000000000 | E7: =VLOOKUP($A7,'Band Heat 2025'!$A$3:$F$27,3,FALSE) -> 0 | F7: =VLOOKUP($A7,'Band Heat 2025'!$A$3:$F$27,4,FALSE) -> 0 | G7: =VLOOKUP($A7,'Band Heat 2025'!$A$3:$F$27,5,FALSE) -> 0 | H7: =VLOOKUP($A7,'Band Heat 2025'!$A$3:$F$27,6,FALSE) -> 0 | I7: =SUM(D7:H7) -> 60351000000000 | J7: =C7*I7 -> 6035100000000 | K7: =D7 -> 60351000000000 | L7: =E7 -> 0 | M7: =F7/3 -> 0 | N7: =MIN(K7,J7) -> 6035100000000 | O7: =J7-N7 -> 0 | P7: =MIN(L7,O7) -> 0 | Q7: =O7-P7 -> 0 | R7: =MIN(M7,Q7) -> 0 | S7: =Q7-R7 -> 0 | T7: 0 | U7: 0
A8: food beverage and tobacco 10T12 | B8: Food, beverage, tobacco | C8: =VLOOKUP(B8,'MECS 2022'!$A$5:$E$16,5,FALSE) -> 0.59450288 | D8: =VLOOKUP($A8,'Band Heat 2025'!$A$3:$F$27,2,FALSE) -> 47231200000000 | E8: =VLOOKUP($A8,'Band Heat 2025'!$A$3:$F$27,3,FALSE) -> 73812400000000 | F8: =VLOOKUP($A8,'Band Heat 2025'!$A$3:$F$27,4,FALSE) -> 282194000000000 | G8: =VLOOKUP($A8,'Band Heat 2025'!$A$3:$F$27,5,FALSE) -> 2383190000 | H8: =VLOOKUP($A8,'Band Heat 2025'!$A$3:$F$27,6,FALSE) -> 0 | I8: =SUM(D8:H8) -> 403239983190000 | J8: =C8*I8 -> 2.3972733e+14 | K8: =D8 -> 47231200000000 | L8: =E8 -> 73812400000000 | M8: =F8/3 -> 9.4064667e+13 | N8: =MIN(K8,J8) -> 47231200000000 | O8: =J8-N8 -> 1.9249613e+14 | P8: =MIN(L8,O8) -> 73812400000000 | Q8: =O8-P8 -> 1.1868373e+14 | R8: =MIN(M8,Q8) -> 9.4064667e+13 | S8: =Q8-R8 -> 2.4619066e+13 | T8: 0 | U8: 0
A9: textiles apparel and leather 13T15 | B9: Textiles, apparel, leather | C9: =VLOOKUP(B9,'MECS 2022'!$A$5:$E$16,5,FALSE) -> 0.42028986 | D9: =VLOOKUP($A9,'Band Heat 2025'!$A$3:$F$27,2,FALSE) -> 1237420000000 | E9: =VLOOKUP($A9,'Band Heat 2025'!$A$3:$F$27,3,FALSE) -> 807725000000 | F9: =VLOOKUP($A9,'Band Heat 2025'!$A$3:$F$27,4,FALSE) -> 2169290000000 | G9: =VLOOKUP($A9,'Band Heat 2025'!$A$3:$F$27,5,FALSE) -> 48598600000 | H9: =VLOOKUP($A9,'Band Heat 2025'!$A$3:$F$27,6,FALSE) -> 70537000000 | I9: =SUM(D9:H9) -> 4333570600000 | J9: =C9*I9 -> 1.8213558e+12 | K9: =D9 -> 1237420000000 | L9: =E9 -> 807725000000 | M9: =F9/3 -> 7.2309667e+11 | N9: =MIN(K9,J9) -> 1237420000000 | O9: =J9-N9 -> 5.8393576e+11 | P9: =MIN(L9,O9) -> 5.8393576e+11 | Q9: =O9-P9 -> 0 | R9: =MIN(M9,Q9) -> 0 | S9: =Q9-R9 -> 0 | T9: 0 | U9: 0
A10: wood products 16 | B10: Wood products | C10: =VLOOKUP(B10,'MECS 2022'!$A$5:$E$16,5,FALSE) -> 0.22018349 | D10: =VLOOKUP($A10,'Band Heat 2025'!$A$3:$F$27,2,FALSE) -> 8847760000000 | E10: =VLOOKUP($A10,'Band Heat 2025'!$A$3:$F$27,3,FALSE) -> 45213500000000 | F10: =VLOOKUP($A10,'Band Heat 2025'!$A$3:$F$27,4,FALSE) -> 114301000000000 | G10: =VLOOKUP($A10,'Band Heat 2025'!$A$3:$F$27,5,FALSE) -> 0 | H10: =VLOOKUP($A10,'Band Heat 2025'!$A$3:$F$27,6,FALSE) -> 0 | I10: =SUM(D10:H10) -> 168362260000000 | J10: =C10*I10 -> 3.7070589e+13 | K10: =D10 -> 8847760000000 | L10: =E10 -> 45213500000000 | M10: =F10/3 -> 3.8100333e+13 | N10: =MIN(K10,J10) -> 8847760000000 | O10: =J10-N10 -> 2.8222829e+13 | P10: =MIN(L10,O10) -> 2.8222829e+13 | Q10: =O10-P10 -> 0 | R10: =MIN(M10,Q10) -> 0 | S10: =Q10-R10 -> 0 | T10: 0 | U10: 0
A11: pulp paper and printing 17T18 | B11: Paper | C11: =VLOOKUP(B11,'MECS 2022'!$A$5:$E$16,5,FALSE) -> 0.66287215 | D11: =VLOOKUP($A11,'Band Heat 2025'!$A$3:$F$27,2,FALSE) -> 142216000000000 | E11: =VLOOKUP($A11,'Band Heat 2025'!$A$3:$F$27,3,FALSE) -> 190069000000000 | F11: =VLOOKUP($A11,'Band Heat 2025'!$A$3:$F$27,4,FALSE) -> 558254000000000 | G11: =VLOOKUP($A11,'Band Heat 2025'!$A$3:$F$27,5,FALSE) -> 32102700000000 | H11: =VLOOKUP($A11,'Band Heat 2025'!$A$3:$F$27,6,FALSE) -> 0 | I11: =SUM(D11:H11) -> 922641700000000 | J11: =C11*I11 -> 6.1159349e+14 | K11: =D11 -> 142216000000000 | L11: =E11 -> 190069000000000 | M11: =F11/3 -> 1.8608467e+14 | N11: =MIN(K11,J11) -> 142216000000000 | O11: =J11-N11 -> 4.6937749e+14 | P11: =MIN(L11,O11) -> 190069000000000 | Q11: =O11-P11 -> 2.7930849e+14 | R11: =MIN(M11,Q11) -> 1.8608467e+14 | S11: =Q11-R11 -> 9.3223824e+13 | T11: 0 | U11: 0
A12: refined petroleum and coke 19 | B12: Coke & refined petroleum | C12: =VLOOKUP(B12,'MECS 2022'!$A$5:$E$16,5,FALSE) -> 0.28508676 | D12: =VLOOKUP($A12,'Band Heat 2025'!$A$3:$F$27,2,FALSE) -> 314578000000000 | E12: =VLOOKUP($A12,'Band Heat 2025'!$A$3:$F$27,3,FALSE) -> 329389000000000 | F12: =VLOOKUP($A12,'Band Heat 2025'!$A$3:$F$27,4,FALSE) -> 889339000000000 | G12: =VLOOKUP($A12,'Band Heat 2025'!$A$3:$F$27,5,FALSE) -> 206316000000000 | H12: =VLOOKUP($A12,'Band Heat 2025'!$A$3:$F$27,6,FALSE) -> 55929200000000 | I12: =SUM(D12:H12) -> 1.7955512e+15 | J12: =C12*I12 -> 5.1188787e+14 | K12: =D12 -> 314578000000000 | L12: =E12 -> 329389000000000 | M12: =F12/3 -> 2.9644633e+14 | N12: =MIN(K12,J12) -> 314578000000000 | O12: =J12-N12 -> 1.9730987e+14 | P12: =MIN(L12,O12) -> 1.9730987e+14 | Q12: =O12-P12 -> 0 | R12: =MIN(M12,Q12) -> 0 | S12: =Q12-R12 -> 0 | T12: 0 | U12: 0
A13: chemicals 20 | B13: Chemicals | C13: =VLOOKUP(B13,'MECS 2022'!$A$5:$E$16,5,FALSE) -> 0.5741174 | D13: =VLOOKUP($A13,'Band Heat 2025'!$A$3:$F$27,2,FALSE) -> 62164400000000 | E13: =VLOOKUP($A13,'Band Heat 2025'!$A$3:$F$27,3,FALSE) -> 229148000000000 | F13: =VLOOKUP($A13,'Band Heat 2025'!$A$3:$F$27,4,FALSE) -> 889348000000000 | G13: =VLOOKUP($A13,'Band Heat 2025'!$A$3:$F$27,5,FALSE) -> 169244000000000 | H13: =VLOOKUP($A13,'Band Heat 2025'!$A$3:$F$27,6,FALSE) -> 9632490000 | I13: =SUM(D13:H13) -> 1.349914e+15 | J13: =C13*I13 -> 7.7500913e+14 | K13: =D13 -> 62164400000000 | L13: =E13 -> 229148000000000 | M13: =F13/3 -> 2.9644933e+14 | N13: =MIN(K13,J13) -> 62164400000000 | O13: =J13-N13 -> 7.1284473e+14 | P13: =MIN(L13,O13) -> 229148000000000 | Q13: =O13-P13 -> 4.8369673e+14 | R13: =MIN(M13,Q13) -> 2.9644933e+14 | S13: =Q13-R13 -> 1.872474e+14 | T13: 0 | U13: 0
A14: rubber and plastic products 22 | B14: Rubber & plastics | C14: =VLOOKUP(B14,'MECS 2022'!$A$5:$E$16,5,FALSE) -> 0.45080092 | D14: =VLOOKUP($A14,'Band Heat 2025'!$A$3:$F$27,2,FALSE) -> 3131390000000 | E14: =VLOOKUP($A14,'Band Heat 2025'!$A$3:$F$27,3,FALSE) -> 12579600000000 | F14: =VLOOKUP($A14,'Band Heat 2025'!$A$3:$F$27,4,FALSE) -> 32111200000000 | G14: =VLOOKUP($A14,'Band Heat 2025'!$A$3:$F$27,5,FALSE) -> 7323910000000 | H14: =VLOOKUP($A14,'Band Heat 2025'!$A$3:$F$27,6,FALSE) -> 0 | I14: =SUM(D14:H14) -> 55146100000000 | J14: =C14*I14 -> 2.4859912e+13 | K14: =D14 -> 3131390000000 | L14: =E14 -> 12579600000000 | M14: =F14/3 -> 1.0703733e+13 | N14: =MIN(K14,J14) -> 3131390000000 | O14: =J14-N14 -> 2.1728522e+13 | P14: =MIN(L14,O14) -> 12579600000000 | Q14: =O14-P14 -> 9.1489224e+12 | R14: =MIN(M14,Q14) -> 9.1489224e+12 | S14: =Q14-R14 -> 0 | T14: 0 | U14: 0
A15: glass and glass products 231 | B15: Glass & cement (non-metallic minerals) | C15: =VLOOKUP(B15,'MECS 2022'!$A$5:$E$16,5,FALSE) -> 0.020531807 | D15: =VLOOKUP($A15,'Band Heat 2025'!$A$3:$F$27,2,FALSE) -> 0 | E15: =VLOOKUP($A15,'Band Heat 2025'!$A$3:$F$27,3,FALSE) -> 0 | F15: =VLOOKUP($A15,'Band Heat 2025'!$A$3:$F$27,4,FALSE) -> 1104560000000 | G15: =VLOOKUP($A15,'Band Heat 2025'!$A$3:$F$27,5,FALSE) -> 4545930000000 | H15: =VLOOKUP($A15,'Band Heat 2025'!$A$3:$F$27,6,FALSE) -> 58003100000000 | I15: =SUM(D15:H15) -> 63653590000000 | J15: =C15*I15 -> 1.3069233e+12 | K15: =D15 -> 0 | L15: =E15 -> 0 | M15: =F15/3 -> 3.6818667e+11 | N15: =MIN(K15,J15) -> 0 | O15: =J15-N15 -> 1.3069233e+12 | P15: =MIN(L15,O15) -> 0 | Q15: =O15-P15 -> 1.3069233e+12 | R15: =MIN(M15,Q15) -> 3.6818667e+11 | S15: =Q15-R15 -> 9.3873659e+11 | T15: 0 | U15: 0
A16: cement and other nonmetallic minerals 239 | B16: Glass & cement (non-metallic minerals) | C16: =VLOOKUP(B16,'MECS 2022'!$A$5:$E$16,5,FALSE) -> 0.020531807 | D16: =VLOOKUP($A16,'Band Heat 2025'!$A$3:$F$27,2,FALSE) -> 5450870000000 | E16: =VLOOKUP($A16,'Band Heat 2025'!$A$3:$F$27,3,FALSE) -> 6520840000 | F16: =VLOOKUP($A16,'Band Heat 2025'!$A$3:$F$27,4,FALSE) -> 14232000000000 | G16: =VLOOKUP($A16,'Band Heat 2025'!$A$3:$F$27,5,FALSE) -> 56269600000000 | H16: =VLOOKUP($A16,'Band Heat 2025'!$A$3:$F$27,6,FALSE) -> 153450000000000 | I16: =SUM(D16:H16) -> 229408990840000 | J16: =C16*I16 -> 4.7101812e+12 | K16: =D16 -> 5450870000000 | L16: =E16 -> 6520840000 | M16: =F16/3 -> 4744000000000 | N16: =MIN(K16,J16) -> 4.7101812e+12 | O16: =J16-N16 -> 0 | P16: =MIN(L16,O16) -> 0 | Q16: =O16-P16 -> 0 | R16: =MIN(M16,Q16) -> 0 | S16: =Q16-R16 -> 0 | T16: 0 | U16: 0
A17: iron and steel 241 | B17: Iron & steel | C17: =VLOOKUP(B17,'MECS 2022'!$A$5:$E$16,5,FALSE) -> 0.088082902 | D17: =VLOOKUP($A17,'Band Heat 2025'!$A$3:$F$27,2,FALSE) -> 1020910000000 | E17: =VLOOKUP($A17,'Band Heat 2025'!$A$3:$F$27,3,FALSE) -> 1135030000000 | F17: =VLOOKUP($A17,'Band Heat 2025'!$A$3:$F$27,4,FALSE) -> 4215560000000 | G17: =VLOOKUP($A17,'Band Heat 2025'!$A$3:$F$27,5,FALSE) -> 5800080000000 | H17: =VLOOKUP($A17,'Band Heat 2025'!$A$3:$F$27,6,FALSE) -> 261558000000000 | I17: =SUM(D17:H17) -> 273729580000000 | J17: =C17*I17 -> 2.4110896e+13 | K17: =D17 -> 1020910000000 | L17: =E17 -> 1135030000000 | M17: =F17/3 -> 1.4051867e+12 | N17: =MIN(K17,J17) -> 1020910000000 | O17: =J17-N17 -> 2.3089986e+13 | P17: =MIN(L17,O17) -> 1135030000000 | Q17: =O17-P17 -> 2.1954956e+13 | R17: =MIN(M17,Q17) -> 1.4051867e+12 | S17: =Q17-R17 -> 2.0549769e+13 | T17: 0 | U17: 0
A18: other metals 242 | B18: Other metals | C18: =VLOOKUP(B18,'MECS 2022'!$A$5:$E$16,5,FALSE) -> 0.10341556 | D18: =VLOOKUP($A18,'Band Heat 2025'!$A$3:$F$27,2,FALSE) -> 14111700000 | E18: =VLOOKUP($A18,'Band Heat 2025'!$A$3:$F$27,3,FALSE) -> 23986500000000 | F18: =VLOOKUP($A18,'Band Heat 2025'!$A$3:$F$27,4,FALSE) -> 63023400000000 | G18: =VLOOKUP($A18,'Band Heat 2025'!$A$3:$F$27,5,FALSE) -> 13489300000000 | H18: =VLOOKUP($A18,'Band Heat 2025'!$A$3:$F$27,6,FALSE) -> 33171300000000 | I18: =SUM(D18:H18) -> 133684611700000 | J18: =C18*I18 -> 1.3825069e+13 | K18: =D18 -> 14111700000 | L18: =E18 -> 23986500000000 | M18: =F18/3 -> 21007800000000 | N18: =MIN(K18,J18) -> 14111700000 | O18: =J18-N18 -> 1.3810957e+13 | P18: =MIN(L18,O18) -> 1.3810957e+13 | Q18: =O18-P18 -> 0 | R18: =MIN(M18,Q18) -> 0 | S18: =Q18-R18 -> 0 | T18: 0 | U18: 0
A19: metal products except machinery and vehicles 25 | B19: Fabricated metal/machinery/electronics/vehicles | C19: =VLOOKUP(B19,'MECS 2022'!$A$5:$E$16,5,FALSE) -> 0.099770642 | D19: =VLOOKUP($A19,'Band Heat 2025'!$A$3:$F$27,2,FALSE) -> 3912250000000 | E19: =VLOOKUP($A19,'Band Heat 2025'!$A$3:$F$27,3,FALSE) -> 3981140000000 | F19: =VLOOKUP($A19,'Band Heat 2025'!$A$3:$F$27,4,FALSE) -> 11782400000000 | G19: =VLOOKUP($A19,'Band Heat 2025'!$A$3:$F$27,5,FALSE) -> 7758640000000 | H19: =VLOOKUP($A19,'Band Heat 2025'!$A$3:$F$27,6,FALSE) -> 32594200000000 | I19: =SUM(D19:H19) -> 60028630000000 | J19: =C19*I19 -> 5.989095e+12 | K19: =D19 -> 3912250000000 | L19: =E19 -> 3981140000000 | M19: =F19/3 -> 3.9274667e+12 | N19: =MIN(K19,J19) -> 3912250000000 | O19: =J19-N19 -> 2.076845e+12 | P19: =MIN(L19,O19) -> 2.076845e+12 | Q19: =O19-P19 -> 0 | R19: =MIN(M19,Q19) -> 0 | S19: =Q19-R19 -> 0 | T19: 0 | U19: 0
... A25: other manufacturing 31T33 | B25: Other manufacturing | C25: =VLOOKUP(B25,'MECS 2022'!$A$5:$E$16,5,FALSE) -> 0.17910448 | D25: =VLOOKUP($A25,'Band Heat 2025'!$A$3:$F$27,2,FALSE) -> 4690580000000 | E25: =VLOOKUP($A25,'Band Heat 2025'!$A$3:$F$27,3,FALSE) -> 2190220000000 | F25: =VLOOKUP($A25,'Band Heat 2025'!$A$3:$F$27,4,FALSE) -> 7423970000000 | G25: =VLOOKUP($A25,'Band Heat 2025'!$A$3:$F$27,5,FALSE) -> 5882150000000 | H25: =VLOOKUP($A25,'Band Heat 2025'!$A$3:$F$27,6,FALSE) -> 6096050000000 | I25: =SUM(D25:H25) -> 26282970000000 | J25: =C25*I25 -> 4.7073976e+12 | K25: =D25 -> 4690580000000 | L25: =E25 -> 2190220000000 | M25: =F25/3 -> 2.4746567e+12 | N25: =MIN(K25,J25) -> 4690580000000 | O25: =J25-N25 -> 1.6817612e+10 | P25: =MIN(L25,O25) -> 1.6817612e+10 | Q25: =O25-P25 -> 0 | R25: =MIN(M25,Q25) -> 0 | S25: =Q25-R25 -> 0 | T25: 0 | U25: 0
A26: energy pipelines and gas processing 352T353 | B26: non-MECS default | C26: =$B$1 -> 0.1 | D26: =VLOOKUP($A26,'Band Heat 2025'!$A$3:$F$27,2,FALSE) -> 0 | E26: =VLOOKUP($A26,'Band Heat 2025'!$A$3:$F$27,3,FALSE) -> 0 | F26: =VLOOKUP($A26,'Band Heat 2025'!$A$3:$F$27,4,FALSE) -> 0 | G26: =VLOOKUP($A26,'Band Heat 2025'!$A$3:$F$27,5,FALSE) -> 0 | H26: =VLOOKUP($A26,'Band Heat 2025'!$A$3:$F$27,6,FALSE) -> 0 | I26: =SUM(D26:H26) -> 0 | J26: =C26*I26 -> 0 | K26: =D26 -> 0 | L26: =E26 -> 0 | M26: =F26/3 -> 0 | N26: =MIN(K26,J26) -> 0 | O26: =J26-N26 -> 0 | P26: =MIN(L26,O26) -> 0 | Q26: =O26-P26 -> 0 | R26: =MIN(M26,Q26) -> 0 | S26: =Q26-R26 -> 0 | T26: 0 | U26: 0
A27: water and waste 36T39 | B27: non-MECS default | C27: =$B$1 -> 0.1 | D27: =VLOOKUP($A27,'Band Heat 2025'!$A$3:$F$27,2,FALSE) -> 0 | E27: =VLOOKUP($A27,'Band Heat 2025'!$A$3:$F$27,3,FALSE) -> 0 | F27: =VLOOKUP($A27,'Band Heat 2025'!$A$3:$F$27,4,FALSE) -> 0 | G27: =VLOOKUP($A27,'Band Heat 2025'!$A$3:$F$27,5,FALSE) -> 0 | H27: =VLOOKUP($A27,'Band Heat 2025'!$A$3:$F$27,6,FALSE) -> 0 | I27: =SUM(D27:H27) -> 0 | J27: =C27*I27 -> 0 | K27: =D27 -> 0 | L27: =E27 -> 0 | M27: =F27/3 -> 0 | N27: =MIN(K27,J27) -> 0 | O27: =J27-N27 -> 0 | P27: =MIN(L27,O27) -> 0 | Q27: =O27-P27 -> 0 | R27: =MIN(M27,Q27) -> 0 | S27: =Q27-R27 -> 0 | T27: 0 | U27: 0
A28: construction 41T43 | B28: non-MECS default | C28: =$B$1 -> 0.1 | D28: =VLOOKUP($A28,'Band Heat 2025'!$A$3:$F$27,2,FALSE) -> 62863500000000 | E28: =VLOOKUP($A28,'Band Heat 2025'!$A$3:$F$27,3,FALSE) -> 0 | F28: =VLOOKUP($A28,'Band Heat 2025'!$A$3:$F$27,4,FALSE) -> 0 | G28: =VLOOKUP($A28,'Band Heat 2025'!$A$3:$F$27,5,FALSE) -> 0 | H28: =VLOOKUP($A28,'Band Heat 2025'!$A$3:$F$27,6,FALSE) -> 0 | I28: =SUM(D28:H28) -> 62863500000000 | J28: =C28*I28 -> 6286350000000 | K28: =D28 -> 62863500000000 | L28: =E28 -> 0 | M28: =F28/3 -> 0 | N28: =MIN(K28,J28) -> 6286350000000 | O28: =J28-N28 -> 0 | P28: =MIN(L28,O28) -> 0 | Q28: =O28-P28 -> 0 | R28: =MIN(M28,Q28) -> 0 | S28: =Q28-R28 -> 0 | T28: 0 | U28: 0
A30: TOTALS | D30: =SUM(D4:D28) -> 900243101700000 | E30: =SUM(E4:E28) -> 1.1879432e+15 | F30: =SUM(F4:F28) -> 3.9471992e+15 | G30: =SUM(G4:G28) -> 713328833110000 | H30: =SUM(H4:H28) -> 617535079490000 | N30: =SUM(N4:N28) -> 6.9106378e+14 | P30: =SUM(P4:P28) -> 8.3946531e+14 | R30: =SUM(R4:R28) -> 5.8752096e+14 | T30: =SUM(T4:T28) -> 0 | U30: =SUM(U4:U28) -> 0
A32: Band | B32: Band heat total | C32: Fill (steam-served) total | D32: w_b = fill / heat
A33: heat < 100 C | B33: =D30 -> 900243101700000 | C33: =N30 -> 6.9106378e+14 | D33: =IFERROR(C33/B33,0) -> 0.76764129
A34: heat 100 - 200 C | B34: =E30 -> 1.1879432e+15 | C34: =P30 -> 8.3946531e+14 | D34: =IFERROR(C34/B34,0) -> 0.70665442
A35: heat 200 - 500 C | B35: =F30 -> 3.9471992e+15 | C35: =R30 -> 5.8752096e+14 | D35: =IFERROR(C35/B35,0) -> 0.14884503
A36: heat 500 - 1000 C | B36: =G30 -> 713328833110000 | C36: =T30 -> 0 | D36: =IFERROR(C36/B36,0) -> 0
A37: heat > 1000 C | B37: =H30 -> 617535079490000 | C37: =U30 -> 0 | D37: =IFERROR(C37/B37,0) -> 0
A40: Band | B40: w_b | C40: Discharge cost_b (2023 USD/kW-out) | D40: System cost_b (2023 USD/kW-out) | E40: TBCC_b (2012 USD/BTU-yr)
A41: heat < 100 C | B41: =D33 -> 0.76764129 | C41: =D33*'TBCC Components'!$B$3+(1-D33)*'TBCC Components'!$B$25 -> 232.16117 | D41: ='TBCC Components'!$B$2*'TBCC Components'!$B$8+C41+'TBCC Components'!$B$5*'TBCC Components'!$B$9 -> 722.16117 | E41: =D41*'TBCC Components'!$B$17/('TBCC Components'!$B$13*'TBCC Components'!$B$14) -> 1.8204905e-05
A42: heat 100 - 200 C | B42: =D34 -> 0.70665442 | C42: =D34*'TBCC Components'!$B$3+(1-D34)*'TBCC Components'!$B$25 -> 214.35561 | D42: ='TBCC Components'!$B$2*'TBCC Components'!$B$8+C42+'TBCC Components'!$B$5*'TBCC Components'!$B$9 -> 704.35561 | E42: =D42*'TBCC Components'!$B$17/('TBCC Components'!$B$13*'TBCC Components'!$B$14) -> 1.7756046e-05
A43: heat 200 - 500 C | B43: =D35 -> 0.14884503 | C43: =D35*'TBCC Components'!$B$3+(1-D35)*'TBCC Components'!$B$25 -> 51.499076 | D43: ='TBCC Components'!$B$2*'TBCC Components'!$B$8+C43+'TBCC Components'!$B$5*'TBCC Components'!$B$9 -> 541.49908 | E43: =D43*'TBCC Components'!$B$17/('TBCC Components'!$B$13*'TBCC Components'!$B$14) -> 1.3650608e-05
A44: heat 500 - 1000 C | B44: =D36 -> 0 | C44: =D36*'TBCC Components'!$B$3+(1-D36)*'TBCC Components'!$B$25 -> 8.0426809 | D44: ='TBCC Components'!$B$2*'TBCC Components'!$B$8+C44+'TBCC Components'!$B$5*'TBCC Components'!$B$9 -> 498.04268 | E44: =D44*'TBCC Components'!$B$17/('TBCC Components'!$B$13*'TBCC Components'!$B$14) -> 1.2555119e-05
A45: heat > 1000 C | B45: =D37 -> 0 | C45: =D37*'TBCC Components'!$B$3+(1-D37)*'TBCC Components'!$B$25 -> 8.0426809 | D45: ='TBCC Components'!$B$2*'TBCC Components'!$B$8+C45+'TBCC Components'!$B$5*'TBCC Components'!$B$9 -> 498.04268 | E45: =D45*'TBCC Components'!$B$17/('TBCC Components'!$B$13*'TBCC Components'!$B$14) -> 1.2555119e-05

Sheet Checks
A1: Verification: computed TBCC_b (Band Weights tab) vs. authoritative TBCC.csv
A3: Band | B3: Computed TBCC_b | C3: TBCC.csv value | D3: Abs % diff | E3: Check (<0.5%)
A4: heat < 100 C | B4: ='Band Weights'!E41 -> 1.8204905e-05 | C4: 1.8206e-05 | D4: =ABS(B4-C4)/C4 -> 6.0144937e-05 | E4: =IF(D4<0.005,"PASS","FAIL") -> PASS
A5: heat 100 - 200 C | B5: ='Band Weights'!E42 -> 1.7756046e-05 | C5: 1.7757e-05 | D5: =ABS(B5-C5)/C5 -> 5.3728346e-05 | E5: =IF(D5<0.005,"PASS","FAIL") -> PASS
A6: heat 200 - 500 C | B6: ='Band Weights'!E43 -> 1.3650608e-05 | C6: 1.3651e-05 | D6: =ABS(B6-C6)/C6 -> 2.8702789e-05 | E6: =IF(D6<0.005,"PASS","FAIL") -> PASS
A7: heat 500 - 1000 C | B7: ='Band Weights'!E44 -> 1.2555119e-05 | C7: 1.2555e-05 | D7: =ABS(B7-C7)/C7 -> 9.5018956e-06 | E7: =IF(D7<0.005,"PASS","FAIL") -> PASS
A8: heat > 1000 C | B8: ='Band Weights'!E45 -> 1.2555119e-05 | C8: 1.2555e-05 | D8: =ABS(B8-C8)/C8 -> 9.5018956e-06 | E8: =IF(D8<0.005,"PASS","FAIL") -> PASS

Sheet TBCC
A1: Unit: 2012 USD per BTU of annual energy service (electricity equivalent) | B1: Capital Cost
A2: heat < 100 C | B2: ='Band Weights'!E41 -> 1.8204905e-05
A3: heat 100 - 200 C | B3: ='Band Weights'!E42 -> 1.7756046e-05
A4: heat 200 - 500 C | B4: ='Band Weights'!E43 -> 1.3650608e-05
A5: heat 500 - 1000 C | B5: ='Band Weights'!E44 -> 1.2555119e-05
A6: heat > 1000 C | B6: ='Band Weights'!E45 -> 1.2555119e-05
