Workbook

Sheet About
A1: FoPTaFbIC Fractions of Products That are Fuels by ISIC Code
A3: Sources: | B3: U.S. Energy Information Administration
B4: U.S. Energy Information Administration
B5: 2026
B6: Annual Energy Outlook 2026
B7: Alternative electricity and transportation:Table 2, Table 3, Table 6, Table 17
B8: https://www.eia.gov/outlooks/aeo/tables_side_xls.php
B10: Table numbers specified on "Calculations" tab
B12: Also relies on data from io-model/BObIC and fuels/BFPaT
A14: Notes
A15: This variable expresses what share of the products of a particular ISIC code
A16: consist of fuels. For example, ISIC 19 (Coke and refined petroleum products)
A17: mostly consists of refined fuels, but refineries also produce some chemicals
A18: sold to the chemicals industry (such as BTX aromatics), which are not fuels.
A20: For most industries, the fraction in this variable should be zero, because most
A21: industries do not produce any fuels at all.
A23: Energy carriers such as electricity and heat are considered fuels in this variable.
A25: Fuel | B25: Producer ISIC Code | C25: ISIC Meaning
A26: electricity | B26: ISIC 351 | C26: Electricity generation and distribution
A27: hard coal | B27: ISIC 05 | C27: Coal mining
A28: natural gas | B28: ISIC 352T353 | C28: Energy pipelines and gas processing
A29: nuclear | B29: ISIC 07T08 | C29: Mining and quarrying of uranium and non-energy-producing products
A30: hydro | B30: ISIC 351 | C30: Electricity generation and distribution
A31: wind | B31: ISIC 351 | C31: Electricity generation and distribution
A32: solar | B32: ISIC 351 | C32: Electricity generation and distribution
A33: biomass | B33: ISIC 01T03 | C33: Agriculture, forestry and fishing
A34: petroleum gasoline | B34: ISIC 19 | C34: Refining
A35: petroleum diesel | B35: ISIC 19 | C35: Refining
A36: biofuel gasoline | B36: ISIC 19 | C36: Refining
... A46: hydrogen | B46: ISIC 352T353 | C46: Energy pipelines and gas processing
A48: 42-code sibling (build_sector_shares_42):
A49: This workbook is the 42-code (un-split) sibling of the 52-code expansion. The 42 scheme is the 52 scheme with the six OECD-native parents
A50: left merged (ISIC 01T03, 07T08, 30, 49T53, 69T82, 90T96); the BEA carves ISIC 231/239 and 351/352T353 are retained (present in both
A51: schemes).
A53: The output tabs are the stock derivation, unchanged and live: the stock workbook is natively 42-code (its output columns already are the
A54: 42-code ISIC list, in canonical order), so no child split is applied here. This is a RATE file (fraction of each code's products that are
A55: fuels), not an allocation, so its columns are NOT expected to sum to 1 across ISIC. It is emitted verbatim at 42 codes.

Sheet source data>

Sheet AEO 2025 Table 2
A1: Table 2. Energy Consumption by Sector and Source
A2: https://www.eia.gov/outlooks/aeo/data/browser/#/?id=2-AEO2025&cases=highZTC&sourcekey=0
A3: Tue Dec 02 2025 13:12:48 GMT-0800 (Pacific Standard Time)
A4: Source: U.S. Energy Information Administration
B5: full name | C5: api key | D5: units | E5: 2023 | F5: 2024 | G5: 2025 | H5: 2026 | I5: 2027 | J5: 2028 | K5: 2029 | L5: 2030 | M5: 2031 | N5: 2032 | O5: 2033 | P5: 2034 | Q5: 2035 | R5: 2036 | S5: 2037 | T5: 2038 | U5: 2039 | V5: 2040 | W5: 2041 | X5: 2042 | Y5: 2043 | Z5: 2044 | AA5: 2045 | AB5: 2046 | AC5: 2047 | AD5: 2048 | AE5: 2049 | AF5: 2050 | AG5: Growth (2024-2050)
A6: Residential
A7: Propane | B7: Energy Use: Residential: Propane: High Zero-Carbon Technology Cost | C7: AEO.2025.HIGHZTC.CNSM_ENU_RESD_NA_PROP_NA_NA_QBTU.A | D7: quads | F7: 0.445585 | G7: 0.480711 | H7: 0.477666 | I7: 0.473743 | J7: 0.469514 | K7: 0.464486 | L7: 0.458849 | M7: 0.453163 | N7: 0.447466 | O7: 0.442258 | P7: 0.437043 | Q7: 0.432687 | R7: 0.429065 | S7: 0.426084 | T7: 0.423529 | U7: 0.421347 | V7: 0.419476 | W7: 0.417701 | X7: 0.416029 | Y7: 0.414376 | Z7: 0.412896 | AA7: 0.411593 | AB7: 0.41062 | AC7: 0.409815 | AD7: 0.409114 | AE7: 0.408349 | AF7: 0.407288 | AG7: -0.003
A8: Distillate Fuel Oil | B8: Energy Use: Residential: Distillate Fuel Oil: High Zero-Carbon Technology Cost | C8: AEO.2025.HIGHZTC.CNSM_ENU_RESD_NA_DFO_NA_NA_QBTU.A | D8: quads | F8: 0.445877 | G8: 0.475235 | H8: 0.468476 | I8: 0.459419 | J8: 0.449316 | K8: 0.439104 | L8: 0.429291 | M8: 0.420822 | N8: 0.413547 | O8: 0.407175 | P8: 0.400771 | Q8: 0.394716 | R8: 0.388874 | S8: 0.383074 | T8: 0.377439 | U8: 0.371949 | V8: 0.366483 | W8: 0.361042 | X8: 0.355729 | Y8: 0.350562 | Z8: 0.345267 | AA8: 0.340544 | AB8: 0.335973 | AC8: 0.331592 | AD8: 0.327346 | AE8: 0.323188 | AF8: 0.318975 | AG8: -0.013
A9: Petroleum and Other Liquids Subtotal | B9: Energy Use: Residential: Liquid Fuels Subtotal: High Zero-Carbon Technology Cost | C9: AEO.2025.HIGHZTC.CNSM_ENU_RESD_NA_LFL_NA_NA_QBTU.A | D9: quads | F9: 0.891462 | G9: 0.955946 | H9: 0.946142 | I9: 0.933162 | J9: 0.918829 | K9: 0.90359 | L9: 0.88814 | M9: 0.873986 | N9: 0.861013 | O9: 0.849433 | P9: 0.837815 | Q9: 0.827403 | R9: 0.817938 | S9: 0.809158 | T9: 0.800968 | U9: 0.793296 | V9: 0.785959 | W9: 0.778743 | X9: 0.771758 | Y9: 0.764938 | Z9: 0.758162 | AA9: 0.752137 | AB9: 0.746593 | AC9: 0.741407 | AD9: 0.73646 | AE9: 0.731537 | AF9: 0.726263 | AG9: -0.008
A10: Natural Gas | B10: Energy Use: Residential: Natural Gas: High Zero-Carbon Technology Cost | C10: AEO.2025.HIGHZTC.CNSM_ENU_RESD_NA_NG_NA_NA_QBTU.A | D10: quads | F10: 4.60344 | G10: 4.966208 | H10: 4.999522 | I10: 5.019517 | J10: 5.029608 | K10: 5.016108 | L10: 4.994521 | M10: 4.960952 | N10: 4.913073 | O10: 4.871797 | P10: 4.830965 | Q10: 4.800086 | R10: 4.776269 | S10: 4.75662 | T10: 4.738029 | U10: 4.720499 | V10: 4.700645 | W10: 4.675209 | X10: 4.647515 | Y10: 4.6187 | Z10: 4.591101 | AA10: 4.565073 | AB10: 4.53873 | AC10: 4.513139 | AD10: 4.488929 | AE10: 4.465213 | AF10: 4.441305 | AG10: -0.001
A11: Renewable Energy | B11: Energy Use: Residential: Renewable Energy: High Zero-Carbon Technology Cost | C11: AEO.2025.HIGHZTC.CNSM_ENU_RESD_NA_REN_NA_NA_QBTU.A | D11: quads | F11: 0.357584 | G11: 0.365094 | H11: 0.352654 | I11: 0.347295 | J11: 0.345718 | K11: 0.345503 | L11: 0.34529 | M11: 0.342499 | N11: 0.337295 | O11: 0.332838 | P11: 0.328234 | Q11: 0.323965 | R11: 0.319381 | S11: 0.315221 | T11: 0.311018 | U11: 0.306564 | V11: 0.302182 | W11: 0.2981 | X11: 0.294377 | Y11: 0.29095 | Z11: 0.288536 | AA11: 0.284935 | AB11: 0.281377 | AC11: 0.277692 | AD11: 0.273872 | AE11: 0.270572 | AF11: 0.26805 | AG11: -0.011
A12: Purchased Electricity for Residential Use | B12: Energy Use: Residential: Electricity: High Zero-Carbon Technology Cost | C12: AEO.2025.HIGHZTC.CNSM_ENU_RESD_NA_ELC_NA_NA_QBTU.A | D12: quads | F12: 5.097395 | G12: 5.01535 | H12: 5.056309 | I12: 5.103827 | J12: 5.128921 | K12: 5.120373 | L12: 5.090785 | M12: 5.051124 | N12: 5.01591 | O12: 4.988002 | P12: 4.969066 | Q12: 4.970526 | R12: 4.986686 | S12: 5.011181 | T12: 5.033259 | U12: 5.06003 | V12: 5.086498 | W12: 5.113048 | X12: 5.141541 | Y12: 5.172765 | Z12: 5.203447 | AA12: 5.233101 | AB12: 5.262091 | AC12: 5.290592 | AD12: 5.318973 | AE12: 5.348809 | AF12: 5.378547 | AG12: 0.002
A13: Delivered Energy | B13: Energy Use: Residential: Delivered Energy: High Zero-Carbon Technology Cost | C13: AEO.2025.HIGHZTC.CNSM_ENU_RESD_NA_DELE_NA_NA_QBTU.A | D13: quads | F13: 10.949879 | G13: 11.302598 | H13: 11.354626 | I13: 11.403802 | J13: 11.423075 | K13: 11.385574 | L13: 11.318736 | M13: 11.22856 | N13: 11.127291 | O13: 11.04207 | P13: 10.96608 | Q13: 10.921979 | R13: 10.900274 | S13: 10.892181 | T13: 10.883274 | U13: 10.880389 | V13: 10.875284 | W13: 10.865099 | X13: 10.855191 | Y13: 10.847352 | Z13: 10.841247 | AA13: 10.835244 | AB13: 10.828792 | AC13: 10.82283 | AD13: 10.818233 | AE13: 10.81613 | AF13: 10.814168 | AG13: 0
A14: Electricity-Related Losses | B14: Energy Use: Residential: Electricity Related Losses: High Zero-Carbon Technology Cost | C14: AEO.2025.HIGHZTC.CNSM_ENU_RESD_NA_ERL_NA_NA_QBTU.A | D14: quads | F14: 7.245147 | G14: 6.912201 | H14: 6.553731 | I14: 6.362611 | J14: 6.252065 | K14: 6.13198 | L14: 5.851551 | M14: 5.620308 | N14: 5.220071 | O14: 5.0221 | P14: 4.822125 | Q14: 4.611793 | R14: 4.429836 | S14: 4.219049 | T14: 4.103611 | U14: 3.878483 | V14: 3.828674 | W14: 3.840003 | X14: 3.853276 | Y14: 3.849748 | Z14: 3.852274 | AA14: 3.831165 | AB14: 3.808954 | AC14: 3.799681 | AD14: 3.800865 | AE14: 3.810485 | AF14: 3.790734 | AG14: -0.025
A15: Total | B15: Energy Use: Residential: Total: High Zero-Carbon Technology Cost | C15: AEO.2025.HIGHZTC.CNSM_ENU_RESD_NA_TOT_NA_NA_QBTU.A | D15: quads | F15: 18.195026 | G15: 18.2148 | H15: 17.908356 | I15: 17.766413 | J15: 17.67514 | K15: 17.517555 | L15: 17.170286 | M15: 16.848869 | N15: 16.347363 | O15: 16.064171 | P15: 15.788204 | Q15: 15.533772 | R15: 15.330111 | S15: 15.111231 | T15: 14.986885 | U15: 14.758872 | V15: 14.703958 | W15: 14.705102 | X15: 14.708467 | Y15: 14.6971 | Z15: 14.693521 | AA15: 14.666409 | AB15: 14.637746 | AC15: 14.622511 | AD15: 14.619099 | AE15: 14.626616 | AF15: 14.604902 | AG15: -0.008
A16: Commercial
A17: Propane | B17: Energy Use: Commercial: Propane: High Zero-Carbon Technology Cost | C17: AEO.2025.HIGHZTC.CNSM_ENU_COMM_NA_PROP_NA_NA_QBTU.A | D17: quads | F17: 0.203527 | G17: 0.207036 | H17: 0.211189 | I17: 0.21576 | J17: 0.220555 | K17: 0.224618 | L17: 0.228576 | M17: 0.232463 | N17: 0.236365 | O17: 0.240305 | P17: 0.244263 | Q17: 0.248203 | R17: 0.252085 | S17: 0.255888 | T17: 0.25962 | U17: 0.263292 | V17: 0.266917 | W17: 0.270508 | X17: 0.274074 | Y17: 0.277623 | Z17: 0.281163 | AA17: 0.284705 | AB17: 0.288254 | AC17: 0.29182 | AD17: 0.295404 | AE17: 0.299009 | AF17: 0.302635 | AG17: 0.015
A18: Motor Gasoline | B18: Energy Use: Commercial: Motor Gasoline: High Zero-Carbon Technology Cost | C18: AEO.2025.HIGHZTC.CNSM_ENU_COMM_NA_MGS_NA_NA_QBTU.A | D18: quads | F18: 0.433115 | G18: 0.438858 | H18: 0.445824 | I18: 0.453659 | J18: 0.46196 | K18: 0.470477 | L18: 0.478778 | M18: 0.486934 | N18: 0.495121 | O18: 0.503391 | P18: 0.5117 | Q18: 0.519974 | R18: 0.52813 | S18: 0.536125 | T18: 0.543972 | U18: 0.551696 | V18: 0.559325 | W18: 0.566886 | X18: 0.574397 | Y18: 0.581873 | Z18: 0.589333 | AA18: 0.596798 | AB18: 0.604282 | AC18: 0.6118 | AD18: 0.619359 | AE18: 0.626964 | AF18: 0.634613 | AG18: 0.015
A19: Kerosene | B19: Energy Use: Commercial: Kerosene: High Zero-Carbon Technology Cost | C19: AEO.2025.HIGHZTC.CNSM_ENU_COMM_NA_KRS_NA_NA_QBTU.A | D19: quads | F19: 0.002101 | G19: 0.001663 | H19: 0.003083 | I19: 0.0031 | J19: 0.00296 | K19: 0.002497 | L19: 0.002105 | M19: 0.002033 | N19: 0.002065 | O19: 0.00189 | P19: 0.001818 | Q19: 0.001706 | R19: 0.001673 | S19: 0.001536 | T19: 0.00143 | U19: 0.001377 | V19: 0.001275 | W19: 0.001142 | X19: 0.001025 | Y19: 0.000888 | Z19: 0.000688 | AA19: 0.000707 | AB19: 0.000673 | AC19: 0.000662 | AD19: 0.00067 | AE19: 0.000649 | AF19: 0.00061 | AG19: -0.046
A20: Distillate Fuel Oil | B20: Energy Use: Commercial: Distillate Fuel Oil: High Zero-Carbon Technology Cost | C20: AEO.2025.HIGHZTC.CNSM_ENU_COMM_NA_DFO_NA_NA_QBTU.A | D20: quads | F20: 0.308284 | G20: 0.316531 | H20: 0.320091 | I20: 0.322023 | J20: 0.322813 | K20: 0.322871 | L20: 0.32285 | M20: 0.322282 | N20: 0.32166 | O20: 0.320479 | P20: 0.319178 | Q20: 0.317716 | R20: 0.316511 | S20: 0.315075 | T20: 0.313805 | U20: 0.312652 | V20: 0.311396 | W20: 0.310069 | X20: 0.30861 | Y20: 0.307126 | Z20: 0.305111 | AA20: 0.303931 | AB20: 0.302812 | AC20: 0.302144 | AD20: 0.301719 | AE20: 0.30106 | AF20: 0.30013 | AG20: -0.001
A21: Residual Fuel Oil | B21: Energy Use: Commercial: Residual Fuel Oil: High Zero-Carbon Technology Cost | C21: AEO.2025.HIGHZTC.CNSM_ENU_COMM_NA_RFO_NA_NA_QBTU.A | D21: quads | F21: 0.00255 | G21: 0.000986 | H21: 0.000986 | I21: 0.001056 | J21: 0.001132 | K21: 0.001157 | L21: 0.00118 | M21: 0.001204 | N21: 0.001227 | O21: 0.001251 | P21: 0.001274 | Q21: 0.001298 | R21: 0.001321 | S21: 0.001343 | T21: 0.001365 | U21: 0.001386 | V21: 0.001407 | W21: 0.001427 | X21: 0.001447 | Y21: 0.001467 | Z21: 0.001487 | AA21: 0.001507 | AB21: 0.001527 | AC21: 0.001546 | AD21: 0.001566 | AE21: 0.001586 | AF21: 0.001606 | AG21: -0.018
A22: Petroleum and Other Liquids Subtotal | B22: Energy Use: Commercial: Liquid Fuels Subtotal: High Zero-Carbon Technology Cost | C22: AEO.2025.HIGHZTC.CNSM_ENU_COMM_NA_LFL_NA_NA_QBTU.A | D22: quads | F22: 0.949578 | G22: 0.965074 | H22: 0.981173 | I22: 0.995598 | J22: 1.009419 | K22: 1.02162 | L22: 1.033489 | M22: 1.044916 | N22: 1.056438 | O22: 1.067316 | P22: 1.078234 | Q22: 1.088896 | R22: 1.099719 | S22: 1.109967 | T22: 1.120192 | U22: 1.130402 | V22: 1.140319 | W22: 1.150033 | X22: 1.159553 | Y22: 1.168977 | Z22: 1.177783 | AA22: 1.187648 | AB22: 1.197548 | AC22: 1.207972 | AD22: 1.218718 | AE22: 1.229268 | AF22: 1.239594 | AG22: 0.01
A23: Natural Gas | B23: Energy Use: Commercial: Natural Gas: High Zero-Carbon Technology Cost | C23: AEO.2025.HIGHZTC.CNSM_ENU_COMM_NA_NG_NA_NA_QBTU.A | D23: quads | F23: 3.426704 | G23: 3.611178 | H23: 3.645448 | I23: 3.652436 | J23: 3.643887 | K23: 3.643972 | L23: 3.636758 | M23: 3.632056 | N23: 3.618527 | O23: 3.602453 | P23: 3.590345 | Q23: 3.58766 | R23: 3.594494 | S23: 3.606606 | T23: 3.620292 | U23: 3.636338 | V23: 3.64947 | W23: 3.657411 | X23: 3.662507 | Y23: 3.666111 | Z23: 3.672477 | AA23: 3.67936 | AB23: 3.683807 | AC23: 3.690529 | AD23: 3.699193 | AE23: 3.706769 | AF23: 3.713181 | AG23: 0.003
A24: Coal | B24: Energy Use: Commercial: Coal: High Zero-Carbon Technology Cost | C24: AEO.2025.HIGHZTC.CNSM_ENU_COMM_NA_CL_NA_NA_QBTU.A | D24: quads | F24: 0.012118 | G24: 0.01267 | H24: 0.016739 | I24: 0.017261 | J24: 0.018487 | K24: 0.017758 | L24: 0.018493 | M24: 0.019202 | N24: 0.020131 | O24: 0.020423 | P24: 0.021234 | Q24: 0.021901 | R24: 0.022011 | S24: 0.022176 | T24: 0.021845 | U24: 0.022261 | V24: 0.022491 | W24: 0.022289 | X24: 0.022298 | Y24: 0.022141 | Z24: 0.021983 | AA24: 0.021868 | AB24: 0.021568 | AC24: 0.021554 | AD24: 0.021545 | AE24: 0.021557 | AF24: 0.021255 | AG24: 0.022
A25: Renewable Energy | B25: Energy Use: Commercial: Renewable Energy: High Zero-Carbon Technology Cost | C25: AEO.2025.HIGHZTC.CNSM_ENU_COMM_NA_REN_NA_NA_QBTU.A | D25: quads | F25: 0.158104 | G25: 0.158104 | H25: 0.158104 | I25: 0.158104 | J25: 0.158104 | K25: 0.158104 | L25: 0.158104 | M25: 0.158104 | N25: 0.158104 | O25: 0.158104 | P25: 0.158104 | Q25: 0.158104 | R25: 0.158104 | S25: 0.158104 | T25: 0.158104 | U25: 0.158104 | V25: 0.158104 | W25: 0.158104 | X25: 0.158104 | Y25: 0.158104 | Z25: 0.158104 | AA25: 0.158104 | AB25: 0.158104 | AC25: 0.158104 | AD25: 0.158104 | AE25: 0.158104 | AF25: 0.158104 | AG25: 0
A26: Purchased Electricity for Commercial Use | B26: Energy Use: Commercial: Electricity: High Zero-Carbon Technology Cost | C26: AEO.2025.HIGHZTC.CNSM_ENU_COMM_NA_ELC_NA_NA_QBTU.A | D26: quads | F26: 4.749338 | G26: 4.82175 | H26: 4.782341 | I26: 4.826618 | J26: 4.861098 | K26: 4.927334 | L26: 4.967134 | M26: 5.003686 | N26: 5.045472 | O26: 5.084223 | P26: 5.135777 | Q26: 5.202976 | R26: 5.281009 | S26: 5.36371 | T26: 5.440923 | U26: 5.525065 | V26: 5.609845 | W26: 5.695757 | X26: 5.78301 | Y26: 5.872692 | Z26: 5.964936 | AA26: 6.058793 | AB26: 6.155428 | AC26: 6.253218 | AD26: 6.354017 | AE26: 6.457747 | AF26: 6.564499 | AG26: 0.013
A27: Delivered Energy | B27: Energy Use: Commercial: Delivered Energy: High Zero-Carbon Technology Cost | C27: AEO.2025.HIGHZTC.CNSM_ENU_COMM_NA_DELE_NA_NA_QBTU.A | D27: quads | F27: 9.295842 | G27: 9.568778 | H27: 9.583804 | I27: 9.650017 | J27: 9.690993 | K27: 9.768787 | L27: 9.813977 | M27: 9.857964 | N27: 9.898672 | O27: 9.932518 | P27: 9.983692 | Q27: 10.059537 | R27: 10.155337 | S27: 10.260563 | T27: 10.361356 | U27: 10.472172 | V27: 10.58023 | W27: 10.683596 | X27: 10.785473 | Y27: 10.888024 | Z27: 10.995282 | AA27: 11.105772 | AB27: 11.216454 | AC27: 11.331375 | AD27: 11.451575 | AE27: 11.573444 | AF27: 11.696633 | AG27: 0.009
A28: Electricity-Related Losses | B28: Energy Use: Commercial: Electricity Related Losses: High Zero-Carbon Technology Cost | C28: AEO.2025.HIGHZTC.CNSM_ENU_COMM_NA_ERL_NA_NA_QBTU.A | D28: quads | F28: 6.750439 | G28: 6.64538 | H28: 6.198627 | I28: 6.017033 | J28: 5.925594 | K28: 5.900803 | L28: 5.709422 | M28: 5.567525 | N28: 5.250836 | O28: 5.118978 | P28: 4.983905 | Q28: 4.827467 | R28: 4.691292 | S28: 4.515852 | T28: 4.43598 | U28: 4.234931 | V28: 4.222603 | W28: 4.277629 | X28: 4.334019 | Y28: 4.370658 | Z28: 4.416029 | AA28: 4.435656 | AB28: 4.455595 | AC28: 4.491035 | AD28: 4.540494 | AE28: 4.600491 | AF28: 4.626578 | AG28: -0.014
A29: Total | B29: Energy Use: Commercial: Total: High Zero-Carbon Technology Cost | C29: AEO.2025.HIGHZTC.CNSM_ENU_COMM_NA_TOT_NA_NA_QBTU.A | D29: quads | F29: 16.046282 | G29: 16.214157 | H29: 15.782431 | I29: 15.667049 | J29: 15.616587 | K29: 15.66959 | L29: 15.523399 | M29: 15.425488 | N29: 15.149508 | O29: 15.051496 | P29: 14.967597 | Q29: 14.887005 | R29: 14.84663 | S29: 14.776415 | T29: 14.797336 | U29: 14.707102 | V29: 14.802834 | W29: 14.961225 | X29: 15.119492 | Y29: 15.258682 | Z29: 15.411311 | AA29: 15.541428 | AB29: 15.672049 | AC29: 15.82241 | AD29: 15.992069 | AE29: 16.173935 | AF29: 16.323212 | AG29: 0.001
A30: Industrial
A31: Hydrocarbon Gas Liquids | B31: Energy Use: Industrial: Hydrocarbon Gas Liquids: High Zero-Carbon Technology Cost | C31: AEO.2025.HIGHZTC.CNSM_ENU_IDAL_NA_LPG_NA_NA_QBTU.A | D31: quads | F31: 3.549334 | G31: 3.612091 | H31: 3.608268 | I31: 3.613257 | J31: 3.619893 | K31: 3.625968 | L31: 3.630452 | M31: 3.632591 | N31: 3.634803 | O31: 3.636342 | P31: 3.633108 | Q31: 3.629704 | R31: 3.62797 | S31: 3.623356 | T31: 3.653424 | U31: 3.722283 | V31: 3.797693 | W31: 3.858349 | X31: 3.921485 | Y31: 3.966205 | Z31: 3.93869 | AA31: 3.899894 | AB31: 3.9388 | AC31: 4.012206 | AD31: 4.06568 | AE31: 4.039013 | AF31: 4.011276 | AG31: 0.005
A32: Motor Gasoline | B32: Energy Use: Industrial: Motor Gasoline: High Zero-Carbon Technology Cost | C32: AEO.2025.HIGHZTC.CNSM_ENU_IDAL_NA_MGS_NA_NA_QBTU.A | D32: quads | F32: 0.281291 | G32: 0.285247 | H32: 0.288387 | I32: 0.292239 | J32: 0.297109 | K32: 0.302658 | L32: 0.307115 | M32: 0.310404 | N32: 0.313444 | O32: 0.31532 | P32: 0.316919 | Q32: 0.319351 | R32: 0.322235 | S32: 0.32399 | T32: 0.3259 | U32: 0.327691 | V32: 0.329586 | W32: 0.33104 | X32: 0.333046 | Y32: 0.334606 | Z32: 0.336343 | AA32: 0.339079 | AB32: 0.342198 | AC32: 0.345227 | AD32: 0.348264 | AE32: 0.351611 | AF32: 0.3547 | AG32: 0.009
A33: Distillate Fuel Oil | B33: Energy Use: Industrial: Distillate Fuel Oil: High Zero-Carbon Technology Cost | C33: AEO.2025.HIGHZTC.CNSM_ENU_IDAL_NA_DFO_NA_NA_QBTU.A | D33: quads | F33: 1.140013 | G33: 1.15177 | H33: 1.163439 | I33: 1.177088 | J33: 1.195205 | K33: 1.216104 | L33: 1.23274 | M33: 1.246904 | N33: 1.260956 | O33: 1.269289 | P33: 1.277959 | Q33: 1.288505 | R33: 1.299513 | S33: 1.308196 | T33: 1.317186 | U33: 1.324638 | V33: 1.332429 | W33: 1.337751 | X33: 1.344097 | Y33: 1.349923 | Z33: 1.356099 | AA33: 1.364485 | AB33: 1.374968 | AC33: 1.385294 | AD33: 1.394428 | AE33: 1.405687 | AF33: 1.41575 | AG33: 0.008
A34: Residual Fuel Oil | B34: Energy Use: Industrial: Residual Fuel Oil: High Zero-Carbon Technology Cost | C34: AEO.2025.HIGHZTC.CNSM_ENU_IDAL_NA_RFO_NA_NA_QBTU.A | D34: quads | F34: 0.041174 | G34: 0.04198 | H34: 0.041255 | I34: 0.040061 | J34: 0.038841 | K34: 0.037551 | L34: 0.036369 | M34: 0.035532 | N34: 0.035132 | O34: 0.03466 | P34: 0.034279 | Q34: 0.033786 | R34: 0.033265 | S34: 0.032701 | T34: 0.032198 | U34: 0.031759 | V34: 0.031438 | W34: 0.031172 | X34: 0.030896 | Y34: 0.030629 | Z34: 0.03044 | AA34: 0.03024 | AB34: 0.029949 | AC34: 0.029728 | AD34: 0.029473 | AE34: 0.029252 | AF34: 0.028857 | AG34: -0.014
A35: Petrochemical Feedstocks | B35: Energy Use: Industrial: Petrochemical Feedstocks: High Zero-Carbon Technology Cost | C35: AEO.2025.HIGHZTC.CNSM_ENU_IDAL_NA_PCF_NA_NA_QBTU.A | D35: quads | F35: 0.390525 | G35: 0.355 | H35: 0.55 | I35: 0.55 | J35: 0.55 | K35: 0.55 | L35: 0.55 | M35: 0.55 | N35: 0.55 | O35: 0.55 | P35: 0.55 | Q35: 0.55 | R35: 0.55 | S35: 0.55 | T35: 0.55 | U35: 0.55 | V35: 0.55 | W35: 0.55 | X35: 0.55 | Y35: 0.55 | Z35: 0.69558 | AA35: 0.84116 | AB35: 0.84116 | AC35: 0.84116 | AD35: 0.84116 | AE35: 0.964095 | AF35: 1.087029 | AG35: 0.04
A36: Other Petroleum | B36: Energy Use: Industrial: Other Petroleum: High Zero-Carbon Technology Cost | C36: AEO.2025.HIGHZTC.CNSM_ENU_IDAL_NA_ONP_NA_NA_QBTU.A | D36: quads | F36: 3.074002 | G36: 3.114025 | H36: 3.07424 | I36: 3.102287 | J36: 3.148089 | K36: 3.139748 | L36: 3.174176 | M36: 3.191782 | N36: 3.191282 | O36: 3.177934 | P36: 3.190891 | Q36: 3.189156 | R36: 3.203246 | S36: 3.207888 | T36: 3.208309 | U36: 3.218726 | V36: 3.236173 | W36: 3.244213 | X36: 3.23302 | Y36: 3.249378 | Z36: 3.249571 | AA36: 3.248773 | AB36: 3.261228 | AC36: 3.279748 | AD36: 3.279907 | AE36: 3.276667 | AF36: 3.263268 | AG36: 0.002
A37: Petroleum and Other Liquids Subtotal | B37: Energy Use: Industrial: Liquid Fuels Subtotal: High Zero-Carbon Technology Cost | C37: AEO.2025.HIGHZTC.CNSM_ENU_IDAL_NA_LFL_NA_NA_QBTU.A | D37: quads | F37: 8.476339 | G37: 8.560113 | H37: 8.72559 | I37: 8.774933 | J37: 8.849136 | K37: 8.872029 | L37: 8.930853 | M37: 8.967214 | N37: 8.985618 | O37: 8.983544 | P37: 9.003156 | Q37: 9.010503 | R37: 9.036229 | S37: 9.046131 | T37: 9.087018 | U37: 9.175098 | V37: 9.277319 | W37: 9.352525 | X37: 9.412545 | Y37: 9.480742 | Z37: 9.606723 | AA37: 9.723632 | AB37: 9.788304 | AC37: 9.893365 | AD37: 9.958912 | AE37: 10.066326 | AF37: 10.16088 | AG37: 0.007
A38: Natural Gas | B38: Energy Use: Industrial: Natural Gas: High Zero-Carbon Technology Cost | C38: AEO.2025.HIGHZTC.CNSM_ENU_IDAL_NA_NG_NA_NA_QBTU.A | D38: quads | F38: 7.80328 | G38: 7.915454 | H38: 7.686133 | I38: 7.688715 | J38: 7.692211 | K38: 7.711431 | L38: 7.726192 | M38: 7.761615 | N38: 7.771588 | O38: 7.73987 | P38: 7.705995 | Q38: 7.678161 | R38: 7.665715 | S38: 7.666882 | T38: 7.698881 | U38: 7.741982 | V38: 7.785161 | W38: 7.798125 | X38: 7.81503 | Y38: 7.852369 | Z38: 7.872563 | AA38: 7.894576 | AB38: 7.920349 | AC38: 7.972322 | AD38: 8.010198 | AE38: 8.04101 | AF38: 8.062402 | AG38: 0.001
A39: Lease and Plant Fuel | B39: Energy Use: Industrial: Lease and Plant Fuel: High Zero-Carbon Technology Cost | C39: AEO.2025.HIGHZTC.CNSM_ENU_IDAL_NA_LSAPFL_NA_NA_QBTU.A | D39: quads | F39: 2.045295 | G39: 2.052198 | H39: 2.151558 | I39: 2.160423 | J39: 2.206005 | K39: 2.226782 | L39: 2.238047 | M39: 2.23259 | N39: 2.285561 | O39: 2.298938 | P39: 2.313583 | Q39: 2.305008 | R39: 2.296317 | S39: 2.271652 | T39: 2.265647 | U39: 2.24652 | V39: 2.25015 | W39: 2.26053 | X39: 2.271182 | Y39: 2.275658 | Z39: 2.278661 | AA39: 2.28227 | AB39: 2.29152 | AC39: 2.301058 | AD39: 2.305694 | AE39: 2.311272 | AF39: 2.318181 | AG39: 0.005
A40: Natural Gas Subtotal | B40: Energy Use: Industrial: Natural Gas Subtotal: High Zero-Carbon Technology Cost | C40: AEO.2025.HIGHZTC.CNSM_ENU_IDAL_NA_NGS_NA_NA_QBTU.A | D40: quads | F40: 9.848575 | G40: 9.967653 | H40: 9.837691 | I40: 9.849138 | J40: 9.898215 | K40: 9.938212 | L40: 9.964239 | M40: 9.994205 | N40: 10.057149 | O40: 10.038807 | P40: 10.019579 | Q40: 9.983169 | R40: 9.962032 | S40: 9.938534 | T40: 9.964528 | U40: 9.988503 | V40: 10.035312 | W40: 10.058655 | X40: 10.086212 | Y40: 10.128028 | Z40: 10.151224 | AA40: 10.176846 | AB40: 10.211869 | AC40: 10.273379 | AD40: 10.315892 | AE40: 10.352282 | AF40: 10.380583 | AG40: 0.002
A41: Metallurgical Coal | B41: Energy Use: Industrial: Metallurgical Coal: High Zero-Carbon Technology Cost | C41: AEO.2025.HIGHZTC.CNSM_ENU_IDAL_NA_MTC_NA_NA_QBTU.A | D41: quads | F41: 0.439918 | G41: 0.435673 | H41: 0.438461 | I41: 0.428289 | J41: 0.411773 | K41: 0.397336 | L41: 0.389217 | M41: 0.383361 | N41: 0.377719 | O41: 0.365618 | P41: 0.35786 | Q41: 0.349664 | R41: 0.341143 | S41: 0.336128 | T41: 0.329678 | U41: 0.322872 | V41: 0.318494 | W41: 0.312377 | X41: 0.305367 | Y41: 0.30015 | Z41: 0.294061 | AA41: 0.286897 | AB41: 0.279237 | AC41: 0.272919 | AD41: 0.265611 | AE41: 0.257843 | AF41: 0.249977 | AG41: -0.022
A42: Other Industrial Coal | B42: Energy Use: Industrial: Other Industrial Coal: High Zero-Carbon Technology Cost | C42: AEO.2025.HIGHZTC.CNSM_ENU_IDAL_NA_OIC_NA_NA_QBTU.A | D42: quads | F42: 0.346719 | G42: 0.359046 | H42: 0.366194 | I42: 0.371799 | J42: 0.377274 | K42: 0.379576 | L42: 0.382468 | M42: 0.38463 | N42: 0.388406 | O42: 0.388644 | P42: 0.387373 | Q42: 0.38355 | R42: 0.377761 | S42: 0.371891 | T42: 0.366035 | U42: 0.360937 | V42: 0.356924 | W42: 0.353338 | X42: 0.349361 | Y42: 0.345152 | Z42: 0.340854 | AA42: 0.336664 | AB42: 0.33276 | AC42: 0.328976 | AD42: 0.325349 | AE42: 0.322 | AF42: 0.317922 | AG42: -0.003
... A52: Total | B52: Energy Use: Industrial: Total: High Zero-Carbon Technology Cost | C52: AEO.2025.HIGHZTC.CNSM_ENU_IDAL_NA_TOT_NA_NA_QBTU.A | D52: quads | F52: 31.18813 | G52: 31.434951 | H52: 31.323631 | I52: 31.263987 | J52: 31.322799 | K52: 31.378703 | L52: 31.417871 | M52: 31.491981 | N52: 31.493468 | O52: 31.508798 | P52: 31.602716 | Q52: 31.624946 | R52: 31.669591 | S52: 31.610552 | T52: 31.6734 | U52: 31.68539 | V52: 31.911348 | W52: 32.099259 | X52: 32.27078 | Y52: 32.434256 | Z52: 32.646597 | AA52: 32.838162 | AB52: 32.990003 | AC52: 33.240052 | AD52: 33.419795 | AE52: 33.647184 | AF52: 33.819919 | AG52: 0.003
A53: Transportation
A54: Propane | B54: Energy Use: Transportation: Propane: High Zero-Carbon Technology Cost | C54: AEO.2025.HIGHZTC.CNSM_ENU_TRN_NA_PROP_NA_NA_QBTU.A | D54: quads | F54: 0.011195 | G54: 0.011326 | H54: 0.011342 | I54: 0.011297 | J54: 0.011205 | K54: 0.011043 | L54: 0.010857 | M54: 0.010561 | N54: 0.010184 | O54: 0.009805 | P54: 0.009444 | Q54: 0.009081 | R54: 0.008732 | S54: 0.008407 | T54: 0.008075 | U54: 0.007765 | V54: 0.007471 | W54: 0.007193 | X54: 0.006933 | Y54: 0.006679 | Z54: 0.006451 | AA54: 0.006268 | AB54: 0.006127 | AC54: 0.006008 | AD54: 0.005888 | AE54: 0.005772 | AF54: 0.005668 | AG54: -0.026
A55: Motor Gasoline | B55: Energy Use: Transportation: Motor Gasoline: High Zero-Carbon Technology Cost | C55: AEO.2025.HIGHZTC.CNSM_ENU_TRN_NA_MGS_NA_NA_QBTU.A | D55: quads | F55: 16.210775 | G55: 16.221838 | H55: 16.069057 | I55: 15.822627 | J55: 15.572903 | K55: 15.260414 | L55: 14.868507 | M55: 14.476609 | N55: 14.007551 | O55: 13.530052 | P55: 13.070603 | Q55: 12.609262 | R55: 12.128078 | S55: 11.655457 | T55: 11.219964 | U55: 10.806561 | V55: 10.438981 | W55: 10.102791 | X55: 9.771683 | Y55: 9.506667 | Z55: 9.242884 | AA55: 9.030723 | AB55: 8.832698 | AC55: 8.677147 | AD55: 8.489945 | AE55: 8.36577 | AF55: 8.268996 | AG55: -0.026
A56: of which: E85 | B56: Energy Use: Transportation: E85: High Zero-Carbon Technology Cost | C56: AEO.2025.HIGHZTC.CNSM_ENU_TRN_NA_E85_NA_NA_QBTU.A | D56: quads | F56: 0.003743 | G56: 0.003468 | H56: 0.003093 | I56: 0.002897 | J56: 0.002811 | K56: 0.002914 | L56: 0.002762 | M56: 0.002552 | N56: 0.002375 | O56: 0.002227 | P56: 0.002109 | Q56: 0.001984 | R56: 0.001859 | S56: 0.001764 | T56: 0.001666 | U56: 0.001591 | V56: 0.001555 | W56: 0.001522 | X56: 0.001495 | Y56: 0.00148 | Z56: 0.001502 | AA56: 0.001463 | AB56: 0.001459 | AC56: 0.001492 | AD56: 0.001488 | AE56: 0.001488 | AF56: 0.00148 | AG56: -0.035
A57: Jet Fuel | B57: Energy Use: Transportation: Jet Fuel: High Zero-Carbon Technology Cost | C57: AEO.2025.HIGHZTC.CNSM_ENU_TRN_NA_JFL_NA_NA_QBTU.A | D57: quads | F57: 3.58187 | G57: 3.579366 | H57: 3.586501 | I57: 3.600646 | J57: 3.628514 | K57: 3.662887 | L57: 3.692876 | M57: 3.713435 | N57: 3.737798 | O57: 3.761729 | P57: 3.78585 | Q57: 3.81914 | R57: 3.851299 | S57: 3.887622 | T57: 3.926214 | U57: 3.966387 | V57: 4.009383 | W57: 4.048131 | X57: 4.089222 | Y57: 4.127379 | Z57: 4.165935 | AA57: 4.203361 | AB57: 4.241859 | AC57: 4.280355 | AD57: 4.318392 | AE57: 4.357455 | AF57: 4.396165 | AG57: 0.008
A58: Distillate Fuel Oil | B58: Energy Use: Transportation: Distillate Fuel Oil: High Zero-Carbon Technology Cost | C58: AEO.2025.HIGHZTC.CNSM_ENU_TRN_NA_DFO_NA_NA_QBTU.A | D58: quads | F58: 6.99791 | G58: 7.058537 | H58: 6.995649 | I58: 6.88976 | J58: 6.818944 | K58: 6.736662 | L58: 6.624677 | M58: 6.487075 | N58: 6.279246 | O58: 6.086525 | P58: 5.918643 | Q58: 5.760507 | R58: 5.620604 | S58: 5.494559 | T58: 5.380577 | U58: 5.268323 | V58: 5.179173 | W58: 5.090663 | X58: 5.017412 | Y58: 4.950412 | Z58: 4.892042 | AA58: 4.846307 | AB58: 4.813289 | AC58: 4.788403 | AD58: 4.763983 | AE58: 4.74893 | AF58: 4.732318 | AG58: -0.015
A59: Residual Fuel Oil | B59: Energy Use: Transportation: Residual Fuel Oil: High Zero-Carbon Technology Cost | C59: AEO.2025.HIGHZTC.CNSM_ENU_TRN_NA_RFO_NA_NA_QBTU.A | D59: quads | F59: 0.551691 | G59: 0.515297 | H59: 0.511951 | I59: 0.520945 | J59: 0.527158 | K59: 0.535401 | L59: 0.543707 | M59: 0.550164 | N59: 0.555139 | O59: 0.559197 | P59: 0.565728 | Q59: 0.571437 | R59: 0.575996 | S59: 0.582075 | T59: 0.586215 | U59: 0.591766 | V59: 0.596724 | W59: 0.600921 | X59: 0.605367 | Y59: 0.609503 | Z59: 0.617037 | AA59: 0.620632 | AB59: 0.623818 | AC59: 0.628822 | AD59: 0.63301 | AE59: 0.636594 | AF59: 0.638595 | AG59: 0.006
A60: Other Petroleum | B60: Energy Use: Transportation: Other Petroleum: High Zero-Carbon Technology Cost | C60: AEO.2025.HIGHZTC.CNSM_ENU_TRN_NA_ONP_NA_NA_QBTU.A | D60: quads | F60: 0.156663 | G60: 0.157053 | H60: 0.157726 | I60: 0.158201 | J60: 0.158427 | K60: 0.158552 | L60: 0.158616 | M60: 0.158537 | N60: 0.158417 | O60: 0.158373 | P60: 0.158394 | Q60: 0.158401 | R60: 0.158391 | S60: 0.158389 | T60: 0.158414 | U60: 0.15848 | V60: 0.158544 | W60: 0.158546 | X60: 0.158538 | Y60: 0.158515 | Z60: 0.15848 | AA60: 0.158447 | AB60: 0.158414 | AC60: 0.15835 | AD60: 0.158273 | AE60: 0.158182 | AF60: 0.158066 | AG60: 0
A61: Petroleum and Other Liquids Subtotal | B61: Energy Use: Transportation: Liquid Fuels Subtotal: High Zero-Carbon Technology Cost | C61: AEO.2025.HIGHZTC.CNSM_ENU_TRN_NA_LFL_NA_NA_QBTU.A | D61: quads | F61: 27.510107 | G61: 27.543419 | H61: 27.332226 | I61: 27.003475 | J61: 26.71715 | K61: 26.364956 | L61: 25.899239 | M61: 25.396381 | N61: 24.748335 | O61: 24.10568 | P61: 23.508663 | Q61: 22.927826 | R61: 22.343102 | S61: 21.786507 | T61: 21.279457 | U61: 20.799284 | V61: 20.390274 | W61: 20.008244 | X61: 19.649155 | Y61: 19.359158 | Z61: 19.082829 | AA61: 18.865738 | AB61: 18.676207 | AC61: 18.539085 | AD61: 18.36949 | AE61: 18.272703 | AF61: 18.199812 | AG61: -0.016
A62: Pipeline and Distribution Fuel Natural Gas | B62: Energy Use: Transportation: Pipeline Fuel Natural Gas: High Zero-Carbon Technology Cost | C62: AEO.2025.HIGHZTC.CNSM_ENU_TRN_NA_PFN_NA_NA_QBTU.A | D62: quads | F62: 0.924188 | G62: 0.870456 | H62: 0.864423 | I62: 0.836058 | J62: 0.79698 | K62: 0.765965 | L62: 0.728791 | M62: 0.71577 | N62: 0.724214 | O62: 0.717663 | P62: 0.716695 | Q62: 0.718068 | R62: 0.719897 | S62: 0.718308 | T62: 0.719704 | U62: 0.722538 | V62: 0.730927 | W62: 0.740044 | X62: 0.751189 | Y62: 0.764559 | Z62: 0.780261 | AA62: 0.795535 | AB62: 0.807068 | AC62: 0.819466 | AD62: 0.833344 | AE62: 0.848647 | AF62: 0.866417 | AG62: -0.002
A63: Natural Gas to Liquefy Gas for Export | B63: Energy Use: Transportation: Liquefaction: High Zero-Carbon Technology Cost | C63: AEO.2025.HIGHZTC.CNSM_ENU_IDAL_NA_LQFCT_NA_NA_QBTU.A | D63: quads | F63: 0.36799 | G63: 0.420411 | H63: 0.447693 | I63: 0.448493 | J63: 0.534997 | K63: 0.595588 | L63: 0.658577 | M63: 0.675613 | N63: 0.693994 | O63: 0.709179 | P63: 0.725923 | Q63: 0.734315 | R63: 0.744344 | S63: 0.751137 | T63: 0.751137 | U63: 0.751137 | V63: 0.752735 | W63: 0.751137 | X63: 0.751053 | Y63: 0.747796 | Z63: 0.745887 | AA63: 0.744061 | AB63: 0.741294 | AC63: 0.741682 | AD63: 0.740833 | AE63: 0.738851 | AF63: 0.741926 | AG63: 0.027
A64: Compressed / Liquefied Natural Gas | B64: Energy Use: Transportation: Natural Gas: High Zero-Carbon Technology Cost | C64: AEO.2025.HIGHZTC.CNSM_ENU_TRN_NA_NG_NA_NA_QBTU.A | D64: quads | F64: 0.08866 | G64: 0.096425 | H64: 0.10255 | I64: 0.107257 | J64: 0.110931 | K64: 0.114057 | L64: 0.116278 | M64: 0.11768 | N64: 0.117485 | O64: 0.116937 | P64: 0.116963 | Q64: 0.11753 | R64: 0.118685 | S64: 0.120592 | T64: 0.123544 | U64: 0.127728 | V64: 0.134127 | W64: 0.141426 | X64: 0.149802 | Y64: 0.159253 | Z64: 0.16911 | AA64: 0.179605 | AB64: 0.191033 | AC64: 0.202673 | AD64: 0.214615 | AE64: 0.22709 | AF64: 0.239965 | AG64: 0.039
A65: Hydrogen | B65: Energy Use: Transportation: Hydrogen: High Zero-Carbon Technology Cost | C65: AEO.2025.HIGHZTC.CNSM_ENU_TRN_NA_HDG_NA_NA_QBTU.A | D65: quads | F65: 0.000814 | G65: 0.002967 | H65: 0.006519 | I65: 0.011925 | J65: 0.020097 | K65: 0.029844 | L65: 0.041045 | M65: 0.06635 | N65: 0.124156 | O65: 0.177429 | P65: 0.226746 | Q65: 0.272239 | R65: 0.315546 | S65: 0.356881 | T65: 0.395804 | U65: 0.432659 | V65: 0.468641 | W65: 0.501854 | X65: 0.532824 | Y65: 0.560657 | Z65: 0.586483 | AA65: 0.610152 | AB65: 0.631826 | AC65: 0.651459 | AD65: 0.66846 | AE65: 0.684152 | AF65: 0.697325 | AG65: 0.297
... A73: Total | B73: Energy Use: Transportation: Total: High Zero-Carbon Technology Cost | C73: AEO.2025.HIGHZTC.CNSM_ENU_TRN_NA_TOT_NA_NA_QBTU.A | D73: quads | F73: 29.100668 | G73: 29.216925 | H73: 29.136339 | I73: 28.924061 | J73: 28.865067 | K73: 28.758085 | L73: 28.57081 | M73: 28.364347 | N73: 28.093412 | O73: 27.828226 | P73: 27.598871 | Q73: 27.34617 | R73: 27.070158 | S73: 26.779694 | T73: 26.539318 | U73: 26.2621 | V73: 26.106363 | W73: 25.978071 | X73: 25.855669 | Y73: 25.770792 | Z73: 25.685043 | AA73: 25.629858 | AB73: 25.582588 | AC73: 25.58367 | AD73: 25.541851 | AE73: 25.563349 | AF73: 25.592537 | AG73: -0.005
A74: Unspecified Sector
A75: Total | B75: Energy Use: Unspecified: Total: High Zero-Carbon Technology Cost | C75: AEO.2025.HIGHZTC.CNSM_ENU_OTH_NA_TOT_NA_NA_QBTU.A | D75: quads | F75: -0.741691 | G75: -0.534668 | H75: -0.407275 | I75: -0.280571 | J75: -0.276677 | K75: -0.271866 | L75: -0.265723 | M75: -0.259304 | N75: -0.251183 | O75: -0.243105 | P75: -0.235512 | Q75: -0.22801 | R75: -0.220434 | S75: -0.213116 | T75: -0.206405 | U75: -0.199997 | V75: -0.194422 | W75: -0.18925 | X75: -0.184303 | Y75: -0.180268 | Z75: -0.176336 | AA75: -0.173199 | AB75: -0.170374 | AC75: -0.16818 | AD75: -0.165581 | AE75: -0.163894 | AF75: -0.162543 | AG75: -0.057
A76: Delivered Energy Consumption | B76: All Sectors
A77: Liquefied Petroleum Gases and Other | B77: Energy Use: Delivered: All Sectors: Liquefied Petroleum Gases: High Zero-Carbon Technology Cost | C77: AEO.2025.HIGHZTC.CNSM_ENU_ALLS_NA_LPG_DELV_NA_QBTU.A | D77: quads | F77: 4.209641 | G77: 4.311163 | H77: 4.308465 | I77: 4.314057 | J77: 4.321166 | K77: 4.326116 | L77: 4.328734 | M77: 4.328779 | N77: 4.328817 | O77: 4.328709 | P77: 4.323857 | Q77: 4.319674 | R77: 4.317852 | S77: 4.313735 | T77: 4.344649 | U77: 4.414688 | V77: 4.491556 | W77: 4.553751 | X77: 4.618521 | Y77: 4.664883 | Z77: 4.6392 | AA77: 4.602459 | AB77: 4.643802 | AC77: 4.719849 | AD77: 4.776085 | AE77: 4.752143 | AF77: 4.726868 | AG77: 0.004
A78: Motor Gasoline | B78: Energy Use: Delivered: All Sectors: Motor Gasoline: High Zero-Carbon Technology Cost | C78: AEO.2025.HIGHZTC.CNSM_ENU_ALLS_NA_MGS_DELV_NA_QBTU.A | D78: quads | F78: 16.513548 | G78: 16.489157 | H78: 16.473249 | I78: 16.364161 | J78: 16.130833 | K78: 15.836448 | L78: 15.462359 | M78: 15.086967 | N78: 14.635193 | O78: 14.174006 | P78: 13.730399 | Q78: 13.285722 | R78: 12.821792 | S78: 12.365026 | T78: 11.944914 | U78: 11.546367 | V78: 11.193057 | W78: 10.870225 | X78: 10.552912 | Y78: 10.300356 | Z78: 10.049176 | AA78: 9.849957 | AB78: 9.665093 | AC78: 9.522099 | AD78: 9.347912 | AE78: 9.236293 | AF78: 9.151505 | AG78: -0.022
A79: of which: E85 | B79: Energy Use: Delivered: All Sectors: E85: High Zero-Carbon Technology Cost | C79: AEO.2025.HIGHZTC.CNSM_ENU_ALLS_NA_E85_DELV_NA_QBTU.A | D79: quads | F79: 0.003743 | G79: 0.003468 | H79: 0.003093 | I79: 0.002897 | J79: 0.002811 | K79: 0.002914 | L79: 0.002762 | M79: 0.002552 | N79: 0.002375 | O79: 0.002227 | P79: 0.002109 | Q79: 0.001984 | R79: 0.001859 | S79: 0.001764 | T79: 0.001666 | U79: 0.001591 | V79: 0.001555 | W79: 0.001522 | X79: 0.001495 | Y79: 0.00148 | Z79: 0.001502 | AA79: 0.001463 | AB79: 0.001459 | AC79: 0.001492 | AD79: 0.001488 | AE79: 0.001488 | AF79: 0.00148 | AG79: -0.035
A80: Jet Fuel | B80: Energy Use: Delivered: All Sectors: Jet Fuel: High Zero-Carbon Technology Cost | C80: AEO.2025.HIGHZTC.CNSM_ENU_ALLS_NA_JFL_DELV_NA_QBTU.A | D80: quads | F80: 3.520226 | G80: 3.573043 | H80: 3.580164 | I80: 3.594285 | J80: 3.622104 | K80: 3.656416 | L80: 3.686351 | M80: 3.706875 | N80: 3.731194 | O80: 3.755083 | P80: 3.779161 | Q80: 3.812392 | R80: 3.844495 | S80: 3.880754 | T80: 3.919277 | U80: 3.959379 | V80: 4.002299 | W80: 4.040978 | X80: 4.081998 | Y80: 4.120088 | Z80: 4.158575 | AA80: 4.195935 | AB80: 4.234365 | AC80: 4.272793 | AD80: 4.310762 | AE80: 4.349757 | AF80: 4.388399 | AG80: 0.009
A81: Kerosene | B81: Energy Use: Delivered: All Sectors: Kerosene: High Zero-Carbon Technology Cost | C81: AEO.2025.HIGHZTC.CNSM_ENU_ALLS_NA_KRS_DELV_NA_QBTU.A | D81: quads | F81: 0.003189 | G81: 0.002751 | H81: 0.004171 | I81: 0.004188 | J81: 0.004048 | K81: 0.003585 | L81: 0.003193 | M81: 0.003121 | N81: 0.003153 | O81: 0.002978 | P81: 0.002906 | Q81: 0.002794 | R81: 0.002761 | S81: 0.002624 | T81: 0.002518 | U81: 0.002465 | V81: 0.002363 | W81: 0.00223 | X81: 0.002113 | Y81: 0.001976 | Z81: 0.001776 | AA81: 0.001795 | AB81: 0.001761 | AC81: 0.00175 | AD81: 0.001758 | AE81: 0.001737 | AF81: 0.001698 | AG81: -0.024
A82: Distillate Fuel Oil | B82: Energy Use: Delivered: All Sectors: Distillate Fuel Oil: High Zero-Carbon Technology Cost | C82: AEO.2025.HIGHZTC.CNSM_ENU_ALLS_NA_DFO_DELV_NA_QBTU.A | D82: quads | F82: 8.623672 | G82: 8.930517 | H82: 8.876737 | I82: 8.778446 | J82: 8.717151 | K82: 8.646449 | L82: 8.5424 | M82: 8.411321 | N82: 8.211753 | O82: 8.021768 | P82: 7.856551 | Q82: 7.703047 | R82: 7.568524 | S82: 7.445202 | T82: 7.334461 | U82: 7.224154 | V82: 7.136977 | W82: 7.047919 | X82: 6.974985 | Y82: 6.907838 | Z82: 6.848926 | AA82: 6.806139 | AB82: 6.778246 | AC82: 6.758892 | AD82: 6.739182 | AE82: 6.730723 | AF82: 6.719199 | AG82: -0.01
A83: Residual Fuel Oil | B83: Energy Use: Delivered: All Sectors: Residual Fuel Oil: High Zero-Carbon Technology Cost | C83: AEO.2025.HIGHZTC.CNSM_ENU_ALLS_NA_RFO_DELV_NA_QBTU.A | D83: quads | F83: 0.595414 | G83: 0.558263 | H83: 0.554193 | I83: 0.562062 | J83: 0.56713 | K83: 0.574108 | L83: 0.581256 | M83: 0.5869 | N83: 0.591499 | O83: 0.595108 | P83: 0.601281 | Q83: 0.606521 | R83: 0.610582 | S83: 0.616119 | T83: 0.619778 | U83: 0.624911 | V83: 0.629569 | W83: 0.633519 | X83: 0.63771 | Y83: 0.641599 | Z83: 0.648964 | AA83: 0.652379 | AB83: 0.655293 | AC83: 0.660097 | AD83: 0.664049 | AE83: 0.667432 | AF83: 0.669058 | AG83: 0.004
A84: Petrochemical Feedstocks | B84: Energy Use: Delivered: All Sectors: Petrochemical Feedstocks: High Zero-Carbon Technology Cost | C84: AEO.2025.HIGHZTC.CNSM_ENU_ALLS_NA_PCF_DELV_NA_QBTU.A | D84: quads | F84: 0.390525 | G84: 0.355 | H84: 0.55 | I84: 0.55 | J84: 0.55 | K84: 0.55 | L84: 0.55 | M84: 0.55 | N84: 0.55 | O84: 0.55 | P84: 0.55 | Q84: 0.55 | R84: 0.55 | S84: 0.55 | T84: 0.55 | U84: 0.55 | V84: 0.55 | W84: 0.55 | X84: 0.55 | Y84: 0.55 | Z84: 0.69558 | AA84: 0.84116 | AB84: 0.84116 | AC84: 0.84116 | AD84: 0.84116 | AE84: 0.964095 | AF84: 1.087029 | AG84: 0.04
A85: Other Petroleum | B85: Energy Use: Delivered: All Sectors: Other Petroleum: High Zero-Carbon Technology Cost | C85: AEO.2025.HIGHZTC.CNSM_ENU_ALLS_NA_ONP_DELV_NA_QBTU.A | D85: quads | F85: 3.229577 | G85: 3.269989 | H85: 3.230878 | I85: 3.2594 | J85: 3.305429 | K85: 3.297212 | L85: 3.331703 | M85: 3.34923 | N85: 3.348611 | O85: 3.33522 | P85: 3.348197 | Q85: 3.346469 | R85: 3.360548 | S85: 3.365189 | T85: 3.365635 | U85: 3.376118 | V85: 3.393629 | W85: 3.40167 | X85: 3.390471 | Y85: 3.406804 | Z85: 3.406963 | AA85: 3.406132 | AB85: 3.418554 | AC85: 3.437011 | AD85: 3.437091 | AE85: 3.433762 | AF85: 3.420246 | AG85: 0.002
A86: Petroleum and Other Liquids Subtotal | B86: Energy Use: Delivered: All Sectors: Liquid Fuels Subtotal: High Zero-Carbon Technology Cost | C86: AEO.2025.HIGHZTC.CNSM_ENU_ALLS_NA_LFL_DELV_NA_QBTU.A | D86: quads | F86: 37.085793 | G86: 37.489883 | H86: 37.577854 | I86: 37.426598 | J86: 37.217857 | K86: 36.890331 | L86: 36.485996 | M86: 36.023193 | N86: 35.400219 | O86: 34.762871 | P86: 34.192352 | Q86: 33.626617 | R86: 33.076553 | S86: 32.538647 | T86: 32.081234 | U86: 31.69808 | V86: 31.399448 | W86: 31.100292 | X86: 30.808708 | Y86: 30.593544 | Z86: 30.449158 | AA86: 30.355955 | AB86: 30.238276 | AC86: 30.21365 | AD86: 30.118 | AE86: 30.135941 | AF86: 30.164 | AG86: -0.008
A87: Natural Gas | B87: Energy Use: Delivered: All Sectors: Natural Gas: High Zero-Carbon Technology Cost | C87: AEO.2025.HIGHZTC.CNSM_ENU_ALLS_NA_NG_DELV_NA_QBTU.A | D87: quads | F87: 15.922085 | G87: 16.589268 | H87: 16.433655 | I87: 16.467926 | J87: 16.476635 | K87: 16.485569 | L87: 16.473749 | M87: 16.472303 | N87: 16.420673 | O87: 16.331055 | P87: 16.244268 | Q87: 16.183437 | R87: 16.155165 | S87: 16.150698 | T87: 16.180746 | U87: 16.226549 | V87: 16.269405 | W87: 16.272173 | X87: 16.274857 | Y87: 16.296432 | Z87: 16.30525 | AA87: 16.318613 | AB87: 16.333918 | AC87: 16.378664 | AD87: 16.412935 | AE87: 16.440083 | AF87: 16.456854 | AG87: 0.001
A88: Lease and Plant Fuel | B88: Energy Use: Delivered: All Sectors: Lease and Plant Fuel: High Zero-Carbon Technology Cost | C88: AEO.2025.HIGHZTC.CNSM_ENU_ALLS_NA_LSAPFL_DELV_NA_QBTU.A | D88: quads | F88: 2.045295 | G88: 2.052198 | H88: 2.151558 | I88: 2.160423 | J88: 2.206005 | K88: 2.226782 | L88: 2.238047 | M88: 2.23259 | N88: 2.285561 | O88: 2.298938 | P88: 2.313583 | Q88: 2.305008 | R88: 2.296317 | S88: 2.271652 | T88: 2.265647 | U88: 2.24652 | V88: 2.25015 | W88: 2.26053 | X88: 2.271182 | Y88: 2.275658 | Z88: 2.278661 | AA88: 2.28227 | AB88: 2.29152 | AC88: 2.301058 | AD88: 2.305694 | AE88: 2.311272 | AF88: 2.318181 | AG88: 0.005
... A103: Total | B103: Energy Use: Delivered: All Sectors: Total: High Zero-Carbon Technology Cost | C103: AEO.2025.HIGHZTC.CNSM_ENU_ALLS_NA_TOT_NA_NA_QBTU.A | D103: quads | F103: 93.788419 | G103: 94.546169 | H103: 93.743479 | I103: 93.340944 | J103: 93.20291 | K103: 93.052064 | L103: 92.416649 | M103: 91.871381 | N103: 90.832564 | O103: 90.209591 | P103: 89.721876 | Q103: 89.163886 | R103: 88.696052 | S103: 88.064775 | T103: 87.79054 | U103: 87.213465 | V103: 87.330084 | W103: 87.554408 | X103: 87.770105 | Y103: 87.98056 | Z103: 88.260143 | AA103: 88.502663 | AB103: 88.712009 | AC103: 89.100469 | AD103: 89.407232 | AE103: 89.847187 | AF103: 90.178018 | AG103: -0.002
A104: Electric Power
A105: Distillate Fuel Oil | B105: Energy Use: Electric Power: Distillate Fuel Oil: High Zero-Carbon Technology Cost | C105: AEO.2025.HIGHZTC.CNSM_ENU_ELEP_NA_DFO_NA_NA_QBTU.A | D105: quads | F105: 0.066403 | G105: 0.065482 | H105: 0.059722 | I105: 0.051562 | J105: 0.047604 | K105: 0.045219 | L105: 0.040859 | M105: 0.037158 | N105: 0.026274 | O105: 0.025523 | P105: 0.025487 | Q105: 0.024426 | R105: 0.024424 | S105: 0.023857 | T105: 0.023149 | U105: 0.023078 | V105: 0.023018 | W105: 0.022389 | X105: 0.021226 | Y105: 0.020516 | Z105: 0.019154 | AA105: 0.018159 | AB105: 0.017685 | AC105: 0.017484 | AD105: 0.017671 | AE105: 0.017884 | AF105: 0.018142 | AG105: -0.049
A106: Residual Fuel Oil | B106: Energy Use: Electric Power: Residual Fuel Oil: High Zero-Carbon Technology Cost | C106: AEO.2025.HIGHZTC.CNSM_ENU_ELEP_NA_RFO_NA_NA_QBTU.A | D106: quads | F106: 0.044083 | G106: 0.042744 | H106: 0.042099 | I106: 0.041532 | J106: 0.039579 | K106: 0.039204 | L106: 0.038852 | M106: 0.038796 | N106: 0.039023 | O106: 0.039286 | P106: 0.039635 | Q106: 0.040089 | R106: 0.039733 | S106: 0.039333 | T106: 0.038802 | U106: 0.038284 | V106: 0.037614 | W106: 0.034838 | X106: 0.031878 | Y106: 0.028755 | Z106: 0.025484 | AA106: 0.022106 | AB106: 0.022298 | AC106: 0.022473 | AD106: 0.022656 | AE106: 0.022861 | AF106: 0.023052 | AG106: -0.025
A107: Petroleum and Other Liquids Subtotal | B107: Energy Use: Electric Power: Liquid Fuels Subtotal: High Zero-Carbon Technology Cost | C107: AEO.2025.HIGHZTC.CNSM_ENU_ELEP_NA_LFL_NA_NA_QBTU.A | D107: quads | F107: 0.110486 | G107: 0.108227 | H107: 0.10182 | I107: 0.093094 | J107: 0.087183 | K107: 0.084423 | L107: 0.079711 | M107: 0.075954 | N107: 0.065298 | O107: 0.064809 | P107: 0.065122 | Q107: 0.064516 | R107: 0.064157 | S107: 0.06319 | T107: 0.061951 | U107: 0.061362 | V107: 0.060632 | W107: 0.057227 | X107: 0.053104 | Y107: 0.049271 | Z107: 0.044638 | AA107: 0.040265 | AB107: 0.039983 | AC107: 0.039957 | AD107: 0.040327 | AE107: 0.040745 | AF107: 0.041194 | AG107: -0.037
A108: Natural Gas | B108: Energy Use: Electric Power: Natural Gas: High Zero-Carbon Technology Cost | C108: AEO.2025.HIGHZTC.CNSM_ENU_ELEP_NA_NG_NA_NA_QBTU.A | D108: quads | F108: 13.928752 | G108: 12.961791 | H108: 12.332006 | I108: 12.814469 | J108: 12.775032 | K108: 12.874219 | L108: 13.066365 | M108: 12.920246 | N108: 14.43693 | O108: 13.99907 | P108: 13.549019 | Q108: 12.973681 | R108: 12.49203 | S108: 11.657304 | T108: 11.344967 | U108: 10.781556 | V108: 10.757802 | W108: 11.080935 | X108: 11.368726 | Y108: 11.544607 | Z108: 11.729016 | AA108: 11.844905 | AB108: 12.052026 | AC108: 12.196947 | AD108: 12.346659 | AE108: 12.542368 | AF108: 12.544281 | AG108: -0.004
A109: Steam Coal | B109: Energy Use: Electric Power: Steam Coal: High Zero-Carbon Technology Cost | C109: AEO.2025.HIGHZTC.CNSM_ENU_ELEP_NA_STC_NA_NA_QBTU.A | D109: quads | F109: 6.771428 | G109: 6.757551 | H109: 5.814224 | I109: 4.703229 | J109: 4.521891 | K109: 4.283468 | L109: 3.519291 | M109: 3.239121 | N109: 0.761253 | O109: 0.765657 | P109: 0.743908 | Q109: 0.702316 | R109: 0.677316 | S109: 0.63364 | T109: 0.582054 | U109: 0.212819 | V109: 0.213328 | W109: 0.213855 | X109: 0.214184 | Y109: 0.21473 | Z109: 0.210605 | AA109: 0.192386 | AB109: 0.047468 | AC109: 0.047543 | AD109: 0.047598 | AE109: 0.044523 | AF109: 0.04471 | AG109: -0.176
A110: Nuclear / Uranium | B110: Energy Use: Electric Power: Nuclear: High Zero-Carbon Technology Cost | C110: AEO.2025.HIGHZTC.CNSM_ENU_ELEP_NA_NUC_NA_NA_QBTU.A | D110: quads | F110: 8.122566 | G110: 8.281053 | H110: 8.359651 | I110: 8.340639 | J110: 8.340502 | K110: 8.340389 | L110: 8.247139 | M110: 8.160346 | N110: 8.160302 | O110: 8.160461 | P110: 8.160461 | Q110: 8.139178 | R110: 8.087199 | S110: 8.127986 | T110: 8.12495 | U110: 8.1107 | V110: 8.109373 | W110: 8.110039 | X110: 8.110383 | Y110: 8.110783 | Z110: 8.108737 | AA110: 8.110209 | AB110: 8.106524 | AC110: 8.109944 | AD110: 8.109 | AE110: 8.107161 | AF110: 8.107944 | AG110: 0
A111: Renewable Energy | B111: Energy Use: Electric Power: Renewable Energy: High Zero-Carbon Technology Cost | C111: AEO.2025.HIGHZTC.CNSM_ENU_ELEP_NA_REN_NA_NA_QBTU.A | D111: quads | F111: 3.409441 | G111: 3.802485 | H111: 4.36894 | I111: 4.692803 | J111: 4.844075 | K111: 5.067399 | L111: 5.415483 | M111: 5.793836 | N111: 6.225559 | O111: 6.674434 | P111: 7.210944 | Q111: 7.849945 | R111: 8.451016 | S111: 9.167359 | T111: 9.648984 | U111: 10.328339 | V111: 10.649783 | W111: 10.803039 | X111: 10.975296 | Y111: 11.190047 | Z111: 11.380852 | AA111: 11.55542 | AB111: 11.771945 | AC111: 11.940047 | AD111: 12.114095 | AE111: 12.275303 | AF111: 12.507335 | AG111: 0.051
A112: Hydrogen | B112: Energy Use: Electric Power: Hydrogen: High Zero-Carbon Technology Cost | C112: AEO.2025.HIGHZTC.CNSM_ENU_ELEP_NA_HDG_NA_NA_QBTU.A | D112: quads | F112: 0 | G112: 0 | H112: 0 | I112: 0 | J112: 0 | K112: 0 | L112: 0 | M112: 0 | N112: 0.091394 | O112: 0.105557 | P112: 0.117968 | Q112: 0 | R112: 0 | S112: 0 | T112: 0 | U112: 0 | V112: 0 | W112: 0 | X112: 0 | Y112: 0 | Z112: 0 | AA112: 0 | AB112: 0 | AC112: 0 | AD112: 0 | AE112: 0 | AF112: 0 | AG112: - -
A113: Non-biogenic Municipal Waste | B113: Energy Use: Electric Power: Non-biogenic Municipal Waste: High Zero-Carbon Technology Cost | C113: AEO.2025.HIGHZTC.CNSM_ENU_ELEP_NA_NBMSW_NA_NA_QBTU.A | D113: quads | F113: 0.08799 | G113: 0.08799 | H113: 0.08799 | I113: 0.08799 | J113: 0.08799 | K113: 0.08799 | L113: 0.08799 | M113: 0.08799 | N113: 0.08799 | O113: 0.08799 | P113: 0.08799 | Q113: 0.08799 | R113: 0.08799 | S113: 0.08799 | T113: 0.08799 | U113: 0.08799 | V113: 0.08799 | W113: 0.08799 | X113: 0.08799 | Y113: 0.08799 | Z113: 0.08799 | AA113: 0.08799 | AB113: 0.08799 | AC113: 0.08799 | AD113: 0.08799 | AE113: 0.08799 | AF113: 0.08799 | AG113: 0
A114: Electricity Imports | B114: Energy Use: Electric Power: Electricity Imports: High Zero-Carbon Technology Cost | C114: AEO.2025.HIGHZTC.CNSM_ENU_ELEP_NA_ELI_NA_NA_QBTU.A | D114: quads | F114: 0.100341 | G114: 0.118393 | H114: 0.142458 | I114: 0.202903 | J114: 0.243384 | K114: 0.261122 | L114: 0.286835 | M114: 0.29337 | N114: 0.299808 | O114: 0.308062 | P114: 0.309713 | Q114: 0.313955 | R114: 0.306326 | S114: 0.302757 | T114: 0.301151 | U114: 0.29325 | V114: 0.297882 | W114: 0.299304 | X114: 0.29689 | Y114: 0.27687 | Z114: 0.275465 | AA114: 0.27317 | AB114: 0.25715 | AC114: 0.246115 | AD114: 0.239546 | AE114: 0.229535 | AF114: 0.22035 | AG114: 0.031
A115: Total Energy | B115: Energy Use: Electric Power: Total Energy: High Zero-Carbon Technology Cost | C115: AEO.2025.HIGHZTC.CNSM_ENU_ELEP_NA_TEN_NA_NA_QBTU.A | D115: quads | F115: 32.531006 | G115: 32.117489 | H115: 31.207094 | I115: 30.935127 | J115: 30.900059 | K115: 30.99901 | L115: 30.702814 | M115: 30.57086 | N115: 30.037231 | O115: 30.060589 | P115: 30.127275 | Q115: 30.131582 | R115: 30.166039 | S115: 30.04023 | T115: 30.15205 | U115: 29.876017 | V115: 30.17679 | W115: 30.652388 | X115: 31.106575 | Y115: 31.474298 | Z115: 31.837303 | AA115: 32.104343 | AB115: 32.363087 | AC115: 32.668545 | AD115: 32.985218 | AE115: 33.327621 | AF115: 33.553802 | AG115: 0.001
A116: Hydrogen-Related Losses | B116: Energy Use: Electric Power: Hydrogen Related Losses: High Zero-Carbon Technology Cost | C116: AEO.2025.HIGHZTC.CNSM_ENU_ELEP_NA_H2RELLOS_NA_NA_QBTU.A | D116: quads | F116: 0 | G116: 0 | H116: 0 | I116: 0 | J116: 0 | K116: 0 | L116: 0 | M116: 0 | N116: 3.6e-05 | O116: 4.2e-05 | P116: 4.7e-05 | Q116: 0 | R116: 0 | S116: 0 | T116: 0 | U116: 0 | V116: 0 | W116: 0 | X116: 0 | Y116: 0 | Z116: 0 | AA116: 0 | AB116: 0 | AC116: 0 | AD116: 0 | AE116: 0 | AF116: 0 | AG116: - -
A117: Total | B117: Energy Use: Electric Power: Total: High Zero-Carbon Technology Cost | C117: AEO.2025.HIGHZTC.CNSM_ENU_ELEP_NA_TOT_NA_NA_QBTU.A | D117: quads | F117: 32.531006 | G117: 32.117489 | H117: 31.207094 | I117: 30.935127 | J117: 30.900059 | K117: 30.99901 | L117: 30.702814 | M117: 30.57086 | N117: 30.037268 | O117: 30.060631 | P117: 30.127323 | Q117: 30.131582 | R117: 30.166039 | S117: 30.04023 | T117: 30.15205 | U117: 29.876017 | V117: 30.17679 | W117: 30.652388 | X117: 31.106575 | Y117: 31.474298 | Z117: 31.837303 | AA117: 32.104343 | AB117: 32.363087 | AC117: 32.668545 | AD117: 32.985218 | AE117: 33.327621 | AF117: 33.553802 | AG117: 0.001
A118: Industrial: Hydrogen Production
A119: Natural Gas | B119: Energy Use: Industrial: Hydrogen Production: Natural Gas: High Zero-Carbon Technology Cost | C119: AEO.2025.HIGHZTC.INDH2_ENU_TEN_NA_NGAS_NA_NA_QBTU.A | D119: quads | F119: 1.060482 | G119: 1.078702 | H119: 1.109975 | I119: 1.125627 | J119: 1.134902 | K119: 1.148471 | L119: 1.176577 | M119: 1.222061 | N119: 1.309051 | O119: 1.392089 | P119: 1.470061 | Q119: 1.543265 | R119: 1.61245 | S119: 1.673084 | T119: 1.73002 | U119: 1.78201 | V119: 1.831471 | W119: 1.879031 | X119: 1.921309 | Y119: 1.963548 | Z119: 2.008058 | AA119: 2.04883 | AB119: 2.080037 | AC119: 2.103617 | AD119: 2.127657 | AE119: 2.147919 | AF119: 2.171506 | AG119: 0.028
A120: Purchased Electricity | B120: Energy Use: Industrial: Hydrogen Production: Purchased Electricity: High Zero-Carbon Technology Cost | C120: AEO.2025.HIGHZTC.INDH2_ENU_TEN_NA_PURCHELEC_NA_NA_QBTU.A | D120: quads | F120: 0.003649 | G120: 0.003693 | H120: 0.004606 | I120: 0.00474 | J120: 0.004824 | K120: 0.004945 | L120: 0.00514 | M120: 0.005446 | N120: 0.006487 | O120: 0.008055 | P120: 0.009578 | Q120: 0.011226 | R120: 0.011394 | S120: 0.010609 | T120: 0.009896 | U120: 0.009901 | V120: 0.009976 | W120: 0.010061 | X120: 0.009907 | Y120: 0.009796 | Z120: 0.009301 | AA120: 0.008584 | AB120: 0.008001 | AC120: 0.007289 | AD120: 0.007356 | AE120: 0.005232 | AF120: 0.00529 | AG120: 0.014
A121: Byproduct Hydrogen | B121: Energy Use: High Zero-Carbon Technology Cost | C121: AEO.2025.HIGHZTC.INDH2_ENU_TEN_NA_NA_NA_NA_NA.A | D121: quads | F121: 0.281298 | G121: 0.283792 | H121: 0.285599 | I121: 0.285823 | J121: 0.286192 | K121: 0.286404 | L121: 0.286444 | M121: 0.286411 | N121: 0.287263 | O121: 0.28826 | P121: 0.29223 | Q121: 0.294417 | R121: 0.295349 | S121: 0.298215 | T121: 0.301544 | U121: 0.307375 | V121: 0.314352 | W121: 0.319438 | X121: 0.325521 | Y121: 0.328208 | Z121: 0.327497 | AA121: 0.325066 | AB121: 0.328165 | AC121: 0.334948 | AD121: 0.339649 | AE121: 0.340652 | AF121: 0.340464 | AG121: 0.007
A122: Total Energy | B122: Energy Use: Industrial: Hydrogen Production: Total Energy: High Zero-Carbon Technology Cost | C122: AEO.2025.HIGHZTC.INDH2_ENU_TEN_NA_TEN_NA_NA_QBTU.A | D122: quads | F122: 1.345429 | G122: 1.366186 | H122: 1.40018 | I122: 1.41619 | J122: 1.425918 | K122: 1.43982 | L122: 1.468161 | M122: 1.513918 | N122: 1.602801 | O122: 1.688404 | P122: 1.771869 | Q122: 1.848909 | R122: 1.919193 | S122: 1.981908 | T122: 2.04146 | U122: 2.099286 | V122: 2.155799 | W122: 2.208529 | X122: 2.256737 | Y122: 2.301552 | Z122: 2.344856 | AA122: 2.38248 | AB122: 2.416203 | AC122: 2.445855 | AD122: 2.474662 | AE122: 2.493803 | AF122: 2.51726 | AG122: 0.024
A123: Electricity-Related Losses | B123: Energy Use: Industrial: Hydrogen Production: Electricity Related Losses: High Zero-Carbon Technology Cost | C123: AEO.2025.HIGHZTC.INDH2_ENU_TEN_NA_ELC_NA_NA_QBTU.A | D123: quads | F123: 0.005186 | G123: 0.00509 | H123: 0.00597 | I123: 0.005909 | J123: 0.005881 | K123: 0.005922 | L123: 0.005908 | M123: 0.00606 | N123: 0.006751 | O123: 0.00811 | P123: 0.009294 | Q123: 0.010416 | R123: 0.010122 | S123: 0.008932 | T123: 0.008069 | U123: 0.007589 | V123: 0.007509 | W123: 0.007556 | X123: 0.007424 | Y123: 0.007291 | Z123: 0.006886 | AA123: 0.006285 | AB123: 0.005792 | AC123: 0.005235 | AD123: 0.005256 | AE123: 0.003727 | AF123: 0.003728 | AG123: -0.013
A124: Total | B124: Energy Use: Industrial: Hydrogen Production: Total: High Zero-Carbon Technology Cost | C124: AEO.2025.HIGHZTC.INDH2_ENU_TEN_NA_TOT_NA_NA_QBTU.A | D124: quads | F124: 1.350615 | G124: 1.371276 | H124: 1.406149 | I124: 1.422099 | J124: 1.431799 | K124: 1.445741 | L124: 1.474069 | M124: 1.519978 | N124: 1.609552 | O124: 1.696515 | P124: 1.781163 | Q124: 1.859325 | R124: 1.929315 | S124: 1.99084 | T124: 2.049528 | U124: 2.106875 | V124: 2.163309 | W124: 2.216085 | X124: 2.264161 | Y124: 2.308843 | Z124: 2.351742 | AA124: 2.388765 | AB124: 2.421995 | AC124: 2.451091 | AD124: 2.479919 | AE124: 2.49753 | AF124: 2.520988 | AG124: 0.024
A125: Total Energy Consumption
A126: Liquefied Petroleum Gases and Other | B126: Energy Use: Total: Liquefied Petroleum Gases: High Zero-Carbon Technology Cost | C126: AEO.2025.HIGHZTC.CNSM_ENU_TEN_NA_LPG_NA_NA_QBTU.A | D126: quads | F126: 4.209641 | G126: 4.311163 | H126: 4.308465 | I126: 4.314057 | J126: 4.321166 | K126: 4.326116 | L126: 4.328734 | M126: 4.328779 | N126: 4.328817 | O126: 4.328709 | P126: 4.323857 | Q126: 4.319674 | R126: 4.317852 | S126: 4.313735 | T126: 4.344649 | U126: 4.414688 | V126: 4.491556 | W126: 4.553751 | X126: 4.618521 | Y126: 4.664883 | Z126: 4.6392 | AA126: 4.602459 | AB126: 4.643802 | AC126: 4.719849 | AD126: 4.776085 | AE126: 4.752143 | AF126: 4.726868 | AG126: 0.004
A127: Motor Gasoline | B127: Energy Use: Total: Motor Gasoline: High Zero-Carbon Technology Cost | C127: AEO.2025.HIGHZTC.CNSM_ENU_TEN_NA_MGS_NA_NA_QBTU.A | D127: quads | F127: 16.513548 | G127: 16.489157 | H127: 16.473249 | I127: 16.364161 | J127: 16.130833 | K127: 15.836448 | L127: 15.462359 | M127: 15.086967 | N127: 14.635193 | O127: 14.174006 | P127: 13.730399 | Q127: 13.285722 | R127: 12.821792 | S127: 12.365026 | T127: 11.944914 | U127: 11.546367 | V127: 11.193057 | W127: 10.870225 | X127: 10.552912 | Y127: 10.300356 | Z127: 10.049176 | AA127: 9.849957 | AB127: 9.665093 | AC127: 9.522099 | AD127: 9.347912 | AE127: 9.236293 | AF127: 9.151505 | AG127: -0.022
A128: of which: E85 | B128: Energy Use: Total: E85: High Zero-Carbon Technology Cost | C128: AEO.2025.HIGHZTC.CNSM_ENU_TEN_NA_E85_NA_NA_QBTU.A | D128: quads | F128: 0.003743 | G128: 0.003468 | H128: 0.003093 | I128: 0.002897 | J128: 0.002811 | K128: 0.002914 | L128: 0.002762 | M128: 0.002552 | N128: 0.002375 | O128: 0.002227 | P128: 0.002109 | Q128: 0.001984 | R128: 0.001859 | S128: 0.001764 | T128: 0.001666 | U128: 0.001591 | V128: 0.001555 | W128: 0.001522 | X128: 0.001495 | Y128: 0.00148 | Z128: 0.001502 | AA128: 0.001463 | AB128: 0.001459 | AC128: 0.001492 | AD128: 0.001488 | AE128: 0.001488 | AF128: 0.00148 | AG128: -0.035
A129: Jet Fuel | B129: Energy Use: Total: Jet Fuel: High Zero-Carbon Technology Cost | C129: AEO.2025.HIGHZTC.CNSM_ENU_TEN_NA_JFL_NA_NA_QBTU.A | D129: quads | F129: 3.520226 | G129: 3.573043 | H129: 3.580164 | I129: 3.594285 | J129: 3.622104 | K129: 3.656416 | L129: 3.686351 | M129: 3.706875 | N129: 3.731194 | O129: 3.755083 | P129: 3.779161 | Q129: 3.812392 | R129: 3.844495 | S129: 3.880754 | T129: 3.919277 | U129: 3.959379 | V129: 4.002299 | W129: 4.040978 | X129: 4.081998 | Y129: 4.120088 | Z129: 4.158575 | AA129: 4.195935 | AB129: 4.234365 | AC129: 4.272793 | AD129: 4.310762 | AE129: 4.349757 | AF129: 4.388399 | AG129: 0.009
A130: Kerosene | B130: Energy Use: Total: Kerosene: High Zero-Carbon Technology Cost | C130: AEO.2025.HIGHZTC.CNSM_ENU_TEN_NA_KRS_NA_NA_QBTU.A | D130: quads | F130: 0.003189 | G130: 0.002751 | H130: 0.004171 | I130: 0.004188 | J130: 0.004048 | K130: 0.003585 | L130: 0.003193 | M130: 0.003121 | N130: 0.003153 | O130: 0.002978 | P130: 0.002906 | Q130: 0.002794 | R130: 0.002761 | S130: 0.002624 | T130: 0.002518 | U130: 0.002465 | V130: 0.002363 | W130: 0.00223 | X130: 0.002113 | Y130: 0.001976 | Z130: 0.001776 | AA130: 0.001795 | AB130: 0.001761 | AC130: 0.00175 | AD130: 0.001758 | AE130: 0.001737 | AF130: 0.001698 | AG130: -0.024
...

Sheet AEO 2025 Table 3
A1: Table 3. Energy Prices by Sector and Source
A2: https://www.eia.gov/outlooks/aeo/data/browser/#/?id=3-AEO2025&cases=highZTC&sourcekey=0
A3: Tue Dec 02 2025 13:12:56 GMT-0800 (Pacific Standard Time)
A4: Source: U.S. Energy Information Administration
B5: full name | C5: api key | D5: units | E5: 2023 | F5: 2024 | G5: 2025 | H5: 2026 | I5: 2027 | J5: 2028 | K5: 2029 | L5: 2030 | M5: 2031 | N5: 2032 | O5: 2033 | P5: 2034 | Q5: 2035 | R5: 2036 | S5: 2037 | T5: 2038 | U5: 2039 | V5: 2040 | W5: 2041 | X5: 2042 | Y5: 2043 | Z5: 2044 | AA5: 2045 | AB5: 2046 | AC5: 2047 | AD5: 2048 | AE5: 2049 | AF5: 2050 | AG5: Growth (2024-2050)
A6: Residential
A7: Propane | B7: Energy Prices: Residential: Propane: High Zero-Carbon Technology Cost | C7: AEO.2025.HIGHZTC.PRCE_REAL_RESD_NA_PROP_NA_NA_Y13DLRPMMBTU.A | D7: 2024 $/MMBtu | F7: 26.593981 | G7: 25.690693 | H7: 25.882023 | I7: 25.734011 | J7: 25.761881 | K7: 25.984186 | L7: 26.494528 | M7: 27.035074 | N7: 27.848438 | O7: 28.895929 | P7: 29.836832 | Q7: 30.497536 | R7: 30.975727 | S7: 31.295523 | T7: 31.443632 | U7: 31.521713 | V7: 31.634783 | W7: 31.863678 | X7: 32.095478 | Y7: 32.443432 | Z7: 32.908676 | AA7: 33.216011 | AB7: 33.459888 | AC7: 33.58733 | AD7: 33.707253 | AE7: 33.953312 | AF7: 34.455376 | AG7: 0.01
A8: Distillate Fuel Oil | B8: Energy Prices: Residential: Distillate Fuel Oil: High Zero-Carbon Technology Cost | C8: AEO.2025.HIGHZTC.PRCE_REAL_RESD_NA_DFO_NA_NA_Y13DLRPMMBTU.A | D8: 2024 $/MMBtu | F8: 26.158379 | G8: 24.617764 | H8: 24.643763 | I8: 25.310112 | J8: 26.17977 | K8: 27.100401 | L8: 28.068832 | M8: 28.11725 | N8: 28.0326 | O8: 28.357315 | P8: 28.466999 | Q8: 28.689667 | R8: 28.809559 | S8: 29.071898 | T8: 29.171333 | U8: 29.291199 | V8: 29.469152 | W8: 29.758438 | X8: 29.994083 | Y8: 30.294477 | Z8: 30.955036 | AA8: 30.868721 | AB8: 30.956972 | AC8: 30.914091 | AD8: 30.902479 | AE8: 30.934729 | AF8: 31.279491 | AG8: 0.007
A9: Natural Gas | B9: Energy Prices: Residential: Natural Gas: High Zero-Carbon Technology Cost | C9: AEO.2025.HIGHZTC.PRCE_REAL_RESD_NA_NG_NA_NA_Y13DLRPMMBTU.A | D9: 2024 $/MMBtu | F9: 13.932205 | G9: 12.694278 | H9: 12.476946 | I9: 12.0713 | J9: 11.825522 | K9: 11.708606 | L9: 11.628035 | M9: 11.829365 | N9: 12.259671 | O9: 12.641685 | P9: 12.901601 | Q9: 13.046376 | R9: 13.061166 | S9: 13.048336 | T9: 13.026576 | U9: 12.968637 | V9: 13.000326 | W9: 13.125381 | X9: 13.234643 | Y9: 13.327177 | Z9: 13.385166 | AA9: 13.471466 | AB9: 13.568365 | AC9: 13.612545 | AD9: 13.641063 | AE9: 13.722773 | AF9: 13.794634 | AG9: 0
A10: Electricity | B10: Energy Prices: Residential: Electricity: High Zero-Carbon Technology Cost | C10: AEO.2025.HIGHZTC.PRCE_REAL_RESD_NA_ELC_NA_NA_Y13DLRPMMBTU.A | D10: 2024 $/MMBtu | F10: 45.553139 | G10: 45.024025 | H10: 42.541679 | I10: 40.45982 | J10: 40.182793 | K10: 40.569782 | L10: 41.046375 | M10: 41.716888 | N10: 42.268425 | O10: 43.117485 | P10: 43.465755 | Q10: 43.342434 | R10: 43.037926 | S10: 42.73064 | T10: 42.891632 | U10: 42.628983 | V10: 42.525494 | W10: 42.545128 | X10: 42.731728 | Y10: 42.921192 | Z10: 43.168861 | AA10: 43.377872 | AB10: 43.621025 | AC10: 43.79406 | AD10: 44.126114 | AE10: 44.423275 | AF10: 44.787258 | AG10: -0.001
A11: Commercial
A12: Propane | B12: Energy Prices: Commercial: Propane: High Zero-Carbon Technology Cost | C12: AEO.2025.HIGHZTC.PRCE_REAL_COMM_NA_PROP_NA_NA_Y13DLRPMMBTU.A | D12: 2024 $/MMBtu | F12: 19.0868 | G12: 19.071598 | H12: 19.969246 | I12: 19.804914 | J12: 19.920181 | K12: 20.219919 | L12: 20.798326 | M12: 21.250935 | N12: 22.027008 | O12: 22.973885 | P12: 23.6208 | Q12: 23.91017 | R12: 24.102671 | S12: 24.204554 | T12: 24.180492 | U12: 24.168512 | V12: 24.257711 | W12: 24.494383 | X12: 24.6768 | Y12: 25.001261 | Z12: 25.422537 | AA12: 25.562656 | AB12: 25.683006 | AC12: 25.692684 | AD12: 25.758125 | AE12: 26.007099 | AF12: 26.538202 | AG12: 0.013
A13: Distillate Fuel Oil | B13: Energy Prices: Commercial: Distillate Fuel Oil: High Zero-Carbon Technology Cost | C13: AEO.2025.HIGHZTC.PRCE_REAL_COMM_NA_DFO_NA_NA_Y13DLRPMMBTU.A | D13: 2024 $/MMBtu | F13: 26.207932 | G13: 24.707527 | H13: 23.565269 | I13: 23.058794 | J13: 22.754671 | K13: 22.501291 | L13: 22.297827 | M13: 22.340889 | N13: 22.216309 | O13: 22.527172 | P13: 22.633039 | Q13: 22.83795 | R13: 22.942883 | S13: 23.194223 | T13: 23.297205 | U13: 23.403837 | V13: 23.570314 | W13: 23.852497 | X13: 24.078636 | Y13: 24.381926 | Z13: 25.030125 | AA13: 24.942905 | AB13: 25.028816 | AC13: 24.984297 | AD13: 24.964209 | AE13: 25.003876 | AF13: 25.3452 | AG13: -0.001
A14: Residual Fuel Oil | B14: Energy Prices: Commercial: Residual Fuel: High Zero-Carbon Technology Cost | C14: AEO.2025.HIGHZTC.PRCE_REAL_COMM_NA_RFL_NA_NA_Y13DLRPMMBTU.A | D14: 2024 $/MMBtu | F14: 6.746078 | G14: 7.471698 | H14: 7.841193 | I14: 8.831597 | J14: 9.914908 | K14: 11.015342 | L14: 12.183045 | M14: 12.244162 | N14: 12.208694 | O14: 12.446174 | P14: 12.544676 | Q14: 12.678741 | R14: 12.753716 | S14: 12.87225 | T14: 12.979047 | U14: 12.997785 | V14: 13.118733 | W14: 13.235469 | X14: 13.365701 | Y14: 13.416109 | Z14: 13.347304 | AA14: 13.387928 | AB14: 13.678938 | AC14: 13.632569 | AD14: 13.671235 | AE14: 13.775191 | AF14: 14.322314 | AG14: 0.029
A15: Natural Gas | B15: Energy Prices: Commercial: Natural Gas: High Zero-Carbon Technology Cost | C15: AEO.2025.HIGHZTC.PRCE_REAL_COMM_NA_NG_NA_NA_Y13DLRPMMBTU.A | D15: 2024 $/MMBtu | F15: 9.555858 | G15: 8.473628 | H15: 8.571372 | I15: 8.513054 | J15: 8.593106 | K15: 8.767466 | L15: 8.976199 | M15: 9.121284 | N15: 9.472503 | O15: 9.787833 | P15: 9.988475 | Q15: 10.085086 | R15: 10.067373 | S15: 10.026683 | T15: 9.977905 | U15: 9.894558 | V15: 9.894806 | W15: 9.981339 | X15: 10.052937 | Y15: 10.11166 | Z15: 10.137436 | AA15: 10.191541 | AB15: 10.258538 | AC15: 10.274831 | AD15: 10.279621 | AE15: 10.336456 | AF15: 10.384078 | AG15: 0.003
A16: Electricity | B16: Energy Prices: Commercial: Electricity: High Zero-Carbon Technology Cost | C16: AEO.2025.HIGHZTC.PRCE_REAL_COMM_NA_ELC_NA_NA_Y13DLRPMMBTU.A | D16: 2024 $/MMBtu | F16: 38.551605 | G16: 37.602798 | H16: 35.105431 | I16: 33.124508 | J16: 32.965439 | K16: 33.32024 | L16: 33.809681 | M16: 34.413387 | N16: 34.929173 | O16: 35.701324 | P16: 35.979614 | Q16: 35.811676 | R16: 35.482807 | S16: 35.191898 | T16: 35.411739 | U16: 35.115093 | V16: 34.986004 | W16: 34.99255 | X16: 35.154461 | Y16: 35.305714 | Z16: 35.501835 | AA16: 35.64677 | AB16: 35.79763 | AC16: 35.841282 | AD16: 36.080368 | AE16: 36.286304 | AF16: 36.524944 | AG16: -0.002
A17: Industrial
A18: Propane | B18: Energy Prices: Industrial: Propane: High Zero-Carbon Technology Cost | C18: AEO.2025.HIGHZTC.PRCE_REAL_IDAL_NA_PROP_NA_NA_Y13DLRPMMBTU.A | D18: 2024 $/MMBtu | F18: 12.66026 | G18: 12.605674 | H18: 13.465074 | I18: 13.314802 | J18: 13.427592 | K18: 13.72262 | L18: 14.298682 | M18: 14.759735 | N18: 15.554036 | O18: 16.543209 | P18: 17.23724 | Q18: 17.555822 | R18: 17.767212 | S18: 17.880009 | T18: 17.856604 | U18: 17.844084 | V18: 17.93939 | W18: 18.19438 | X18: 18.394274 | Y18: 18.748419 | Z18: 19.21232 | AA18: 19.372681 | AB18: 19.508192 | AC18: 19.52129 | AD18: 19.593958 | AE18: 19.869528 | AF18: 20.462763 | AG18: 0.019
A19: Distillate Fuel Oil | B19: Energy Prices: Industrial: Distillate Fuel Oil: High Zero-Carbon Technology Cost | C19: AEO.2025.HIGHZTC.PRCE_REAL_IDAL_NA_DFO_NA_NA_Y13DLRPMMBTU.A | D19: 2024 $/MMBtu | F19: 26.091763 | G19: 24.600626 | H19: 23.425852 | I19: 22.88941 | J19: 22.557371 | K19: 22.274755 | L19: 22.032902 | M19: 22.079994 | N19: 21.943752 | O19: 22.273958 | P19: 22.39349 | Q19: 22.623447 | R19: 22.746523 | S19: 23.008989 | T19: 23.10652 | U19: 23.218241 | V19: 23.399351 | W19: 23.679426 | X19: 23.916767 | Y19: 24.223963 | Z19: 24.880014 | AA19: 24.792429 | AB19: 24.880751 | AC19: 24.838329 | AD19: 24.82336 | AE19: 24.858402 | AF19: 25.202454 | AG19: -0.001
A20: Residual Fuel Oil | B20: Energy Prices: Industrial: Residual Fuel Oil: High Zero-Carbon Technology Cost | C20: AEO.2025.HIGHZTC.PRCE_REAL_IDAL_NA_RFO_NA_NA_Y13DLRPMMBTU.A | D20: 2024 $/MMBtu | F20: 7.83466 | G20: 8.848094 | H20: 9.435161 | I20: 10.629246 | J20: 11.88067 | K20: 13.214781 | L20: 14.622335 | M20: 14.725853 | N20: 14.700524 | O20: 14.992572 | P20: 15.113938 | Q20: 15.285793 | R20: 15.383565 | S20: 15.518867 | T20: 15.634306 | U20: 15.663942 | V20: 15.779115 | W20: 15.889836 | X20: 16.038828 | Y20: 16.101131 | Z20: 16.053886 | AA20: 16.051018 | AB20: 16.34535 | AC20: 16.306047 | AD20: 16.344069 | AE20: 16.451635 | AF20: 16.998318 | AG20: 0.03
A21: Natural Gas | B21: Energy Prices: Industrial: Natural Gas: High Zero-Carbon Technology Cost | C21: AEO.2025.HIGHZTC.PRCE_REAL_IDAL_NA_NG_NA_NA_Y13DLRPMMBTU.A | D21: 2024 $/MMBtu | F21: 3.33707 | G21: 4.010599 | H21: 3.911485 | I21: 3.791521 | J21: 3.869612 | K21: 4.020249 | L21: 4.230658 | M21: 4.390093 | N21: 4.830755 | O21: 5.179088 | P21: 5.412342 | Q21: 5.494054 | R21: 5.481412 | S21: 5.430798 | T21: 5.370685 | U21: 5.290253 | V21: 5.310672 | W21: 5.403639 | X21: 5.486475 | Y21: 5.561241 | Z21: 5.615677 | AA21: 5.665632 | AB21: 5.71713 | AC21: 5.72265 | AD21: 5.7369 | AE21: 5.797705 | AF21: 5.862935 | AG21: 0.022
A22: Metallurgical Coal | B22: Energy Prices: Industrial: Metallurgical Coal: High Zero-Carbon Technology Cost | C22: AEO.2025.HIGHZTC.PRCE_REAL_IDAL_NA_MTC_NA_NA_Y13DLRPMMBTU.A | D22: 2024 $/MMBtu | F22: 7.767755 | G22: 7.639748 | H22: 7.585148 | I22: 7.555212 | J22: 7.520931 | K22: 7.512826 | L22: 7.510444 | M22: 7.515949 | N22: 7.537591 | O22: 7.537167 | P22: 7.49989 | Q22: 7.518089 | R22: 7.517967 | S22: 7.515557 | T22: 7.51727 | U22: 7.498265 | V22: 7.496222 | W22: 7.466915 | X22: 7.461041 | Y22: 7.453232 | Z22: 7.458103 | AA22: 7.471511 | AB22: 7.467525 | AC22: 7.46251 | AD22: 7.461265 | AE22: 7.469367 | AF22: 7.466943 | AG22: -0.002
A23: Other Industrial Coal | B23: Energy Prices: Industrial: Other Industrial Coal: High Zero-Carbon Technology Cost | C23: AEO.2025.HIGHZTC.PRCE_REAL_IDAL_NA_OIC_NA_NA_Y13DLRPMMBTU.A | D23: 2024 $/MMBtu | F23: 3.572155 | G23: 3.624099 | H23: 3.618806 | I23: 3.601768 | J23: 3.571336 | K23: 3.55915 | L23: 3.533537 | M23: 3.497851 | N23: 3.464142 | O23: 3.459587 | P23: 3.441433 | Q23: 3.415449 | R23: 3.421638 | S23: 3.423545 | T23: 3.432421 | U23: 3.428609 | V23: 3.430913 | W23: 3.425192 | X23: 3.418891 | Y23: 3.422088 | Z23: 3.426063 | AA23: 3.434236 | AB23: 3.444175 | AC23: 3.448749 | AD23: 3.448136 | AE23: 3.449347 | AF23: 3.454516 | AG23: -0.001
A24: Hydrogen | B24: Energy Prices: Industrial: Hydrogen: High Zero-Carbon Technology Cost | C24: AEO.2025.HIGHZTC.PRCE_REAL_IDAL_NA_HDG_NA_NA_Y13DLRPMMBTU.A | D24: 2024 $/MMBtu | F24: 9.533875 | G24: 10.619709 | H24: 10.514131 | I24: 10.426125 | J24: 10.55792 | K24: 10.787679 | L24: 11.065716 | M24: 11.319676 | N24: 11.63994 | O24: 12.155972 | P24: 12.524699 | Q24: 12.666781 | R24: 12.616203 | S24: 12.533028 | T24: 12.742199 | U24: 12.81229 | V24: 12.800771 | W24: 12.675635 | X24: 12.587033 | Y24: 12.651853 | Z24: 12.824852 | AA24: 12.7927 | AB24: 12.813029 | AC24: 12.789708 | AD24: 12.823941 | AE24: 12.685263 | AF24: 12.783066 | AG24: 0.011
A25: Electricity | B25: Energy Prices: Industrial: Electricity: High Zero-Carbon Technology Cost | C25: AEO.2025.HIGHZTC.PRCE_REAL_IDAL_NA_ELC_NA_NA_Y13DLRPMMBTU.A | D25: 2024 $/MMBtu | F25: 26.507746 | G25: 25.922054 | H25: 23.537739 | I25: 22.156487 | J25: 22.004316 | K25: 22.322678 | L25: 22.749052 | M25: 23.346399 | N25: 23.998974 | O25: 24.751463 | P25: 24.95269 | Q25: 24.768763 | R25: 24.45256 | S25: 24.243956 | T25: 24.34145 | U25: 24.228069 | V25: 24.145441 | W25: 24.157953 | X25: 24.287434 | Y25: 24.39603 | Z25: 24.534168 | AA25: 24.641457 | AB25: 24.755726 | AC25: 24.854349 | AD25: 25.022724 | AE25: 25.199516 | AF25: 25.411121 | AG25: -0.002
A26: Transportation
A27: Propane | B27: Energy Prices: Transportation: Propane: High Zero-Carbon Technology Cost | C27: AEO.2025.HIGHZTC.PRCE_REAL_TRN_NA_PROP_NA_NA_Y13DLRPMMBTU.A | D27: 2024 $/MMBtu | F27: 17.589245 | G27: 17.749908 | H27: 18.586613 | I27: 18.389212 | J27: 18.496126 | K27: 18.760077 | L27: 19.2631 | M27: 19.634487 | N27: 20.300226 | O27: 21.098251 | P27: 21.613922 | Q27: 21.826738 | R27: 21.975828 | S27: 22.052736 | T27: 22.024448 | U27: 22.014761 | V27: 22.09473 | W27: 22.299959 | X27: 22.448139 | Y27: 22.723597 | Z27: 23.076363 | AA27: 23.174244 | AB27: 23.269659 | AC27: 23.270405 | AD27: 23.326803 | AE27: 23.542395 | AF27: 23.995331 | AG27: 0.012
A28: E85 | B28: Energy Prices: Transportation: E85: High Zero-Carbon Technology Cost | C28: AEO.2025.HIGHZTC.PRCE_REAL_TRN_NA_E85_NA_NA_Y13DLRPMMBTU.A | D28: 2024 $/MMBtu | F28: 28.823729 | G28: 28.93619 | H28: 30.221819 | I28: 29.874352 | J28: 29.356659 | K28: 28.412943 | L28: 28.414833 | M28: 28.528875 | N28: 28.297775 | O28: 28.022879 | P28: 27.970562 | Q28: 27.737436 | R28: 27.879841 | S28: 27.706806 | T28: 27.335274 | U28: 27.221582 | V28: 26.936087 | W28: 26.624407 | X28: 26.243464 | Y28: 26.249161 | Z28: 24.929926 | AA28: 24.592495 | AB28: 24.79623 | AC28: 24.925064 | AD28: 24.988291 | AE28: 25.141323 | AF28: 25.433138 | AG28: -0.005
A29: Motor Gasoline | B29: Energy Prices: Transportation: Motor Gasoline: High Zero-Carbon Technology Cost | C29: AEO.2025.HIGHZTC.PRCE_REAL_TRN_NA_MGS_NA_NA_Y13DLRPMMBTU.A | D29: 2024 $/MMBtu | F29: 28.679842 | G29: 27.094545 | H29: 25.485424 | I29: 24.986969 | J29: 24.719851 | K29: 24.436867 | L29: 24.474363 | M29: 24.48147 | N29: 24.300167 | O29: 24.154732 | P29: 24.09795 | Q29: 23.894083 | R29: 24.019566 | S29: 23.870735 | T29: 23.556276 | U29: 23.430714 | V29: 23.173237 | W29: 22.909204 | X29: 22.57633 | Y29: 22.596951 | Z29: 21.468903 | AA29: 21.182211 | AB29: 21.356647 | AC29: 21.464962 | AD29: 21.509295 | AE29: 21.631233 | AF29: 21.869665 | AG29: -0.01
A30: Jet Fuel | B30: Energy Prices: Transportation: Jet Fuel: High Zero-Carbon Technology Cost | C30: AEO.2025.HIGHZTC.PRCE_REAL_TRN_NA_JFL_NA_NA_Y13DLRPMMBTU.A | D30: 2024 $/MMBtu | F30: 17.638924 | G30: 16.395 | H30: 16.197346 | I30: 16.576864 | J30: 17.167725 | K30: 17.774681 | L30: 18.432444 | M30: 18.550699 | N30: 18.432102 | O30: 18.750156 | P30: 18.878136 | Q30: 19.088032 | R30: 19.162302 | S30: 19.413189 | T30: 19.636925 | U30: 19.743242 | V30: 19.910463 | W30: 20.238554 | X30: 20.505775 | Y30: 20.876812 | Z30: 21.614872 | AA30: 21.580616 | AB30: 21.698483 | AC30: 21.705061 | AD30: 21.706541 | AE30: 21.788584 | AF30: 22.195864 | AG30: 0.009
A31: Diesel Fuel (distillate fuel oil) | B31: Energy Prices: Transportation: Diesel Fuel: High Zero-Carbon Technology Cost | C31: AEO.2025.HIGHZTC.PRCE_REAL_TRN_NA_DFU_NA_NA_Y13DLRPMMBTU.A | D31: 2024 $/MMBtu | F31: 27.283649 | G31: 25.591213 | H31: 25.016569 | I31: 25.029736 | J31: 25.250086 | K31: 25.481937 | L31: 25.837044 | M31: 25.879503 | N31: 25.733622 | O31: 26.102192 | P31: 26.219612 | Q31: 26.457941 | R31: 26.618042 | S31: 26.882929 | T31: 26.978115 | U31: 27.113096 | V31: 27.266804 | W31: 27.578503 | X31: 27.813025 | Y31: 28.145802 | Z31: 28.854143 | AA31: 28.858868 | AB31: 28.825182 | AC31: 28.706501 | AD31: 28.759977 | AE31: 28.70521 | AF31: 29.126087 | AG31: 0.003
A32: Residual Fuel Oil | B32: Energy Prices: Transportation: Residual Fuel Oil: High Zero-Carbon Technology Cost | C32: AEO.2025.HIGHZTC.PRCE_REAL_TRN_NA_RFO_NA_NA_Y13DLRPMMBTU.A | D32: 2024 $/MMBtu | F32: 13.401297 | G32: 11.843807 | H32: 12.665238 | I32: 12.576532 | J32: 12.510175 | K32: 12.503057 | L32: 12.525302 | M32: 12.597067 | N32: 12.550599 | O32: 12.745926 | P32: 12.831242 | Q32: 12.954171 | R32: 13.008114 | S32: 13.096881 | T32: 13.191089 | U32: 13.218472 | V32: 13.301097 | W32: 13.406687 | X32: 13.509968 | Y32: 13.614932 | Z32: 13.650314 | AA32: 13.473039 | AB32: 13.708124 | AC32: 13.688977 | AD32: 13.7072 | AE32: 13.794828 | AF32: 14.231298 | AG32: 0.002
A33: Natural Gas | B33: Energy Prices: Transportation: Natural Gas: High Zero-Carbon Technology Cost | C33: AEO.2025.HIGHZTC.PRCE_REAL_TRN_NA_NG_NA_NA_Y13DLRPMMBTU.A | D33: 2024 $/MMBtu | F33: 14.514303 | G33: 15.045484 | H33: 14.977668 | I33: 14.858115 | J33: 14.908598 | K33: 15.040533 | L33: 15.186421 | M33: 15.299401 | N33: 15.666859 | O33: 15.903211 | P33: 16.017698 | Q33: 16.016142 | R33: 15.907859 | S33: 15.77169 | T33: 15.650945 | U33: 15.47576 | V33: 15.403385 | W33: 15.417639 | X33: 15.41606 | Y33: 15.414666 | Z33: 15.384685 | AA33: 15.361653 | AB33: 15.353804 | AC33: 15.281762 | AD33: 15.215751 | AE33: 15.207031 | AF33: 15.19101 | AG33: 0.002
A34: Hydrogen | B34: Energy Prices: Transportation: Hydrogen: High Zero-Carbon Technology Cost | C34: AEO.2025.HIGHZTC.PRCE_REAL_TRN_NA_HDG_NA_NA_Y13DLRPMMBTU.A | D34: 2024 $/MMBtu | F34: 60.468231 | G34: 60.745255 | H34: 60.549759 | I34: 60.44437 | J34: 60.531708 | K34: 60.737736 | L34: 60.991833 | M34: 61.818279 | N34: 62.04599 | O34: 62.676136 | P34: 63.049198 | Q34: 63.198536 | R34: 63.044495 | S34: 62.949413 | T34: 63.204426 | U34: 63.33548 | V34: 63.306995 | W34: 63.132828 | X34: 62.969875 | Y34: 63.022812 | Z34: 63.25135 | AA34: 63.215389 | AB34: 63.382431 | AC34: 63.355698 | AD34: 63.409069 | AE34: 63.016552 | AF34: 63.101322 | AG34: 0.002
A35: Electricity | B35: Energy Prices: Transportation: Electricity: High Zero-Carbon Technology Cost | C35: AEO.2025.HIGHZTC.PRCE_REAL_TRN_NA_ELC_NA_NA_Y13DLRPMMBTU.A | D35: 2024 $/MMBtu | F35: 42.609589 | G35: 42.26667 | H35: 39.670399 | I35: 36.717178 | J35: 36.535248 | K35: 36.81496 | L35: 37.285934 | M35: 38.057724 | N35: 38.70388 | O35: 39.740459 | P35: 40.09803 | Q35: 40.153744 | R35: 40.057587 | S35: 39.782898 | T35: 40.15593 | U35: 39.589664 | V35: 39.300087 | W35: 39.269657 | X35: 39.614471 | Y35: 39.822304 | Z35: 40.184521 | AA35: 40.37289 | AB35: 40.537704 | AC35: 40.4916 | AD35: 41.027618 | AE35: 41.285618 | AF35: 41.592472 | AG35: -0.001
A36: Electric Power
A37: Distillate Fuel Oil | B37: Energy Prices: Electric Power: Distillate Fuel Oil: High Zero-Carbon Technology Cost | C37: AEO.2025.HIGHZTC.PRCE_REAL_ELEP_NA_DFO_NA_NA_Y13DLRPMMBTU.A | D37: 2024 $/MMBtu | F37: 26.137505 | G37: 24.653458 | H37: 23.463963 | I37: 22.977613 | J37: 22.593882 | K37: 22.342915 | L37: 22.213257 | M37: 22.156206 | N37: 22.726322 | O37: 23.003592 | P37: 23.077461 | Q37: 23.249807 | R37: 23.28072 | S37: 23.52141 | T37: 23.668085 | U37: 23.751266 | V37: 23.886726 | W37: 24.176956 | X37: 24.404095 | Y37: 24.709991 | Z37: 25.257483 | AA37: 25.158951 | AB37: 25.341908 | AC37: 25.316826 | AD37: 25.294249 | AE37: 25.372868 | AF37: 25.729799 | AG37: -0.001
A38: Residual Fuel Oil | B38: Energy Prices: Electric Power: Residual Fuel Oil: High Zero-Carbon Technology Cost | C38: AEO.2025.HIGHZTC.PRCE_REAL_ELEP_NA_RFO_NA_NA_Y13DLRPMMBTU.A | D38: 2024 $/MMBtu | F38: 17.394409 | G38: 13.672506 | H38: 13.615168 | I38: 14.296899 | J38: 15.031581 | K38: 15.753065 | L38: 16.474405 | M38: 16.627272 | N38: 16.536289 | O38: 16.771885 | P38: 16.909727 | Q38: 17.088612 | R38: 17.157686 | S38: 17.269447 | T38: 17.398418 | U38: 17.408293 | V38: 17.490879 | W38: 17.551632 | X38: 17.536398 | Y38: 17.589537 | Z38: 17.510019 | AA38: 16.884666 | AB38: 17.201757 | AC38: 17.213936 | AD38: 17.253027 | AE38: 17.380194 | AF38: 17.916069 | AG38: 0.001
A39: Natural Gas | B39: Energy Prices: Electric Power: Natural Gas: High Zero-Carbon Technology Cost | C39: AEO.2025.HIGHZTC.PRCE_REAL_ELEP_NA_NG_NA_NA_Y13DLRPMMBTU.A | D39: 2024 $/MMBtu | F39: 2.719399 | G39: 3.131506 | H39: 3.068464 | I39: 2.996603 | J39: 3.12604 | K39: 3.327426 | L39: 3.603756 | M39: 3.695694 | N39: 4.197338 | O39: 4.507975 | P39: 4.717876 | Q39: 4.789361 | R39: 4.78448 | S39: 4.749629 | T39: 4.715602 | U39: 4.659969 | V39: 4.690855 | W39: 4.769531 | X39: 4.842232 | Y39: 4.929382 | Z39: 5.014789 | AA39: 5.059572 | AB39: 5.116513 | AC39: 5.124822 | AD39: 5.147723 | AE39: 5.21766 | AF39: 5.297616 | AG39: 0.026
A40: Steam Coal | B40: Energy Prices: Electric Power: Steam Coal: High Zero-Carbon Technology Cost | C40: AEO.2025.HIGHZTC.PRCE_REAL_ELEP_NA_STC_NA_NA_Y13DLRPMMBTU.A | D40: 2024 $/MMBtu | F40: 2.489397 | G40: 2.427415 | H40: 2.375483 | I40: 2.326139 | J40: 2.226495 | K40: 2.226722 | L40: 2.247866 | M40: 2.217924 | N40: 2.149103 | O40: 2.152961 | P40: 2.139093 | Q40: 2.125588 | R40: 2.125613 | S40: 2.15652 | T40: 2.152304 | U40: 2.213794 | V40: 2.210829 | W40: 2.208087 | X40: 2.206623 | Y40: 2.207428 | Z40: 2.207163 | AA40: 2.196095 | AB40: 1.887973 | AC40: 2.178344 | AD40: 2.178153 | AE40: 2.195496 | AF40: 2.192112 | AG40: -0.005
A41: Uranium | B41: Energy Prices: Electric Power: Uranium: High Zero-Carbon Technology Cost | C41: AEO.2025.HIGHZTC.PRCE_REAL_ELEP_NA_U_NA_NA_Y13DLRPMMBTU.A | D41: 2024 $/MMBtu | F41: 0.753328 | G41: 0.753262 | H41: 0.753186 | I41: 0.753121 | J41: 0.753056 | K41: 0.75298 | L41: 0.752915 | M41: 0.752838 | N41: 0.752773 | O41: 0.752708 | P41: 0.752632 | Q41: 0.752567 | R41: 0.752491 | S41: 0.752425 | T41: 0.75236 | U41: 0.752284 | V41: 0.752219 | W41: 0.752154 | X41: 0.752078 | Y41: 0.752012 | Z41: 0.751936 | AA41: 0.751871 | AB41: 0.751806 | AC41: 0.75173 | AD41: 0.751665 | AE41: 0.751599 | AF41: 0.751523 | AG41: 0
A42: Hydrogen | B42: Energy Prices: Electric Power: Hydrogen: High Zero-Carbon Technology Cost | C42: AEO.2025.HIGHZTC.PRCE_REAL_ELEP_NA_HDG_NA_NA_Y13DLRPMMBTU.A | D42: 2024 $/MMBtu | F42: 9.533875 | G42: 10.619709 | H42: 10.514131 | I42: 10.426125 | J42: 10.55792 | K42: 10.787679 | L42: 11.065716 | M42: 11.319676 | N42: 13.51875 | O42: 13.970348 | P42: 14.314136 | Q42: 12.666781 | R42: 12.616203 | S42: 12.533028 | T42: 12.742199 | U42: 12.81229 | V42: 12.800771 | W42: 12.675635 | X42: 12.587033 | Y42: 12.651853 | Z42: 12.824852 | AA42: 12.7927 | AB42: 12.813029 | AC42: 12.789708 | AD42: 12.823941 | AE42: 12.685263 | AF42: 12.783066 | AG42: 0.011
A43: Average Price to All Users
A44: Propane | B44: Energy Prices: Average Price to All Users: Propane: High Zero-Carbon Technology Cost | C44: AEO.2025.HIGHZTC.PRCE_REAL_TEN_NA_PROP_NA_NA_Y13DLRPMMBTU.A | D44: 2024 $/MMBtu | F44: 23.10931 | G44: 21.964592 | H44: 22.480608 | I44: 22.283079 | J44: 22.302742 | K44: 22.505547 | L44: 22.995274 | M44: 23.450838 | N44: 24.190058 | O44: 25.158035 | P44: 25.926409 | Q44: 26.374306 | R44: 26.676216 | S44: 26.850521 | T44: 26.875446 | U44: 26.872549 | V44: 26.942244 | W44: 27.150986 | X44: 27.332554 | Y44: 27.645765 | Z44: 28.068441 | AA44: 28.264816 | AB44: 28.419424 | AC44: 28.45838 | AD44: 28.523825 | AE44: 28.746887 | AF44: 29.245407 | AG44: 0.009
A45: E85 | B45: Energy Prices: Average Price to All Users: E85: High Zero-Carbon Technology Cost | C45: AEO.2025.HIGHZTC.PRCE_REAL_TEN_NA_E85_NA_NA_Y13DLRPMMBTU.A | D45: 2024 $/MMBtu | F45: 28.823729 | G45: 28.93619 | H45: 30.221819 | I45: 29.874352 | J45: 29.356659 | K45: 28.412943 | L45: 28.414833 | M45: 28.528875 | N45: 28.297775 | O45: 28.022879 | P45: 27.970562 | Q45: 27.737436 | R45: 27.879841 | S45: 27.706806 | T45: 27.335274 | U45: 27.221582 | V45: 26.936087 | W45: 26.624407 | X45: 26.243464 | Y45: 26.249161 | Z45: 24.929926 | AA45: 24.592495 | AB45: 24.79623 | AC45: 24.925064 | AD45: 24.988291 | AE45: 25.141323 | AF45: 25.433138 | AG45: -0.005
A46: Motor Gasoline | B46: Energy Prices: Average Price to All Users: Motor Gasoline: High Zero-Carbon Technology Cost | C46: AEO.2025.HIGHZTC.PRCE_REAL_TEN_NA_MGS_NA_NA_Y13DLRPMMBTU.A | D46: 2024 $/MMBtu | F46: 28.684216 | G46: 27.125784 | H46: 25.527933 | I46: 25.03182 | J46: 24.761021 | K46: 24.469919 | L46: 24.496487 | M46: 24.505796 | N46: 24.326532 | O46: 24.183601 | P46: 24.129673 | Q46: 23.928679 | R46: 24.05728 | S46: 23.911495 | T46: 23.60075 | U46: 23.475494 | V46: 23.218733 | W46: 22.958654 | X46: 22.629124 | Y46: 22.653288 | Z46: 21.528265 | AA46: 21.244183 | AB46: 21.421278 | AC46: 21.532545 | AD46: 21.580334 | AE46: 21.704536 | AF46: 21.945274 | AG46: -0.01
A47: Jet Fuel | B47: Energy Prices: Average Price to All Users: Jet Fuel: High Zero-Carbon Technology Cost | C47: AEO.2025.HIGHZTC.PRCE_REAL_TEN_NA_JFL_NA_NA_Y13DLRPMMBTU.A | D47: 2024 $/MMBtu | F47: 17.638924 | G47: 16.395 | H47: 16.197346 | I47: 16.576864 | J47: 17.167725 | K47: 17.774681 | L47: 18.432444 | M47: 18.550699 | N47: 18.432102 | O47: 18.750156 | P47: 18.878136 | Q47: 19.088032 | R47: 19.162302 | S47: 19.413189 | T47: 19.636925 | U47: 19.743242 | V47: 19.910463 | W47: 20.238554 | X47: 20.505775 | Y47: 20.876812 | Z47: 21.614872 | AA47: 21.580616 | AB47: 21.698483 | AC47: 21.705061 | AD47: 21.706541 | AE47: 21.788584 | AF47: 22.195864 | AG47: 0.009
A48: Distillate Fuel Oil | B48: Energy Prices: Average Price to All Users: Distillate Fuel Oil: High Zero-Carbon Technology Cost | C48: AEO.2025.HIGHZTC.PRCE_REAL_TEN_NA_DFO_NA_NA_Y13DLRPMMBTU.A | D48: 2024 $/MMBtu | F48: 27.012424 | G48: 25.364977 | H48: 24.694891 | I48: 24.642532 | J48: 24.802452 | K48: 24.99939 | L48: 25.230318 | M48: 25.263414 | N48: 25.13209 | O48: 25.445631 | P48: 25.545443 | Q48: 25.775818 | R48: 25.891037 | S48: 26.145451 | T48: 26.220837 | U48: 26.325562 | V48: 26.498985 | W48: 26.760344 | X48: 26.992342 | Y48: 27.287764 | Z48: 27.935396 | AA48: 27.83683 | AB48: 27.914089 | AC48: 27.861572 | AD48: 27.845043 | AE48: 27.8617 | AF48: 28.192116 | AG48: 0.002
A49: Residual Fuel Oil | B49: Energy Prices: Average Price to All Users: Residual Fuel Oil: High Zero-Carbon Technology Cost | C49: AEO.2025.HIGHZTC.PRCE_REAL_TEN_NA_RFO_NA_NA_Y13DLRPMMBTU.A | D49: 2024 $/MMBtu | F49: 13.291615 | G49: 11.757444 | H49: 12.500851 | I49: 12.559112 | J49: 12.62952 | K49: 12.751574 | L49: 12.895062 | M49: 12.967169 | N49: 12.916404 | O49: 13.117395 | P49: 13.204977 | Q49: 13.33178 | R49: 13.382641 | S49: 13.467647 | T49: 13.557985 | U49: 13.576984 | V49: 13.653687 | W49: 13.73819 | X49: 13.818034 | Y49: 13.898582 | Z49: 13.903964 | AA49: 13.700245 | AB49: 13.939589 | AC49: 13.918885 | AD49: 13.937278 | AE49: 14.026111 | AF49: 14.469603 | AG49: 0.003
A50: Natural Gas | B50: Energy Prices: Average Price to All Users: Natural Gas: High Zero-Carbon Technology Cost | C50: AEO.2025.HIGHZTC.PRCE_REAL_TEN_NA_NG_NA_NA_Y13DLRPMMBTU.A | D50: 2024 $/MMBtu | F50: 5.358065 | G50: 5.60745 | H50: 5.603475 | I50: 5.429448 | J50: 5.4806 | K50: 5.600207 | L50: 5.770124 | M50: 5.905769 | N50: 6.242887 | O50: 6.591919 | P50: 6.833857 | Q50: 6.953874 | R50: 6.975764 | S50: 6.995045 | T50: 6.970082 | U50: 6.939922 | V50: 6.958767 | W50: 7.01943 | X50: 7.072737 | Y50: 7.132324 | Z50: 7.176168 | AA50: 7.216303 | AB50: 7.258737 | AC50: 7.256385 | AD50: 7.26004 | AE50: 7.309826 | AF50: 7.375858 | AG50: 0.012
A51: Metallurgical Coal | B51: Energy Prices: Average Price to All Users: Metallurgical Coal: High Zero-Carbon Technology Cost | C51: AEO.2025.HIGHZTC.PRCE_REAL_TEN_NA_MTC_NA_NA_Y13DLRPMMBTU.A | D51: 2024 $/MMBtu | F51: 7.767755 | G51: 7.639748 | H51: 7.585148 | I51: 7.555212 | J51: 7.520931 | K51: 7.512826 | L51: 7.510444 | M51: 7.515949 | N51: 7.537591 | O51: 7.537167 | P51: 7.49989 | Q51: 7.518089 | R51: 7.517967 | S51: 7.515557 | T51: 7.51727 | U51: 7.498265 | V51: 7.496222 | W51: 7.466915 | X51: 7.461041 | Y51: 7.453232 | Z51: 7.458103 | AA51: 7.471511 | AB51: 7.467525 | AC51: 7.46251 | AD51: 7.461265 | AE51: 7.469367 | AF51: 7.466943 | AG51: -0.002
A52: Other Coal | B52: Energy Prices: Average Price to All Users: Other Coal: High Zero-Carbon Technology Cost | C52: AEO.2025.HIGHZTC.PRCE_REAL_TEN_NA_OCA_NA_NA_Y13DLRPMMBTU.A | D52: 2024 $/MMBtu | F52: 2.544647 | G52: 2.490408 | H52: 2.452668 | I52: 2.423937 | J52: 2.334863 | K52: 2.340178 | L52: 2.379634 | M52: 2.359969 | N52: 2.608159 | O52: 2.607483 | P52: 2.600178 | Q52: 2.596767 | R52: 2.605588 | S52: 2.64105 | T52: 2.662963 | U52: 2.99238 | V52: 2.989484 | W52: 2.980852 | X52: 2.973089 | Y52: 2.971414 | Z52: 2.976025 | AA52: 2.999393 | AB52: 3.257445 | AC52: 3.293746 | AD52: 3.29155 | AE52: 3.301926 | AF52: 3.304214 | AG52: 0.01
A53: Hydrogen | B53: Energy Prices: Average Price to All Users: Hydrogen: High Zero-Carbon Technology Cost | C53: AEO.2025.HIGHZTC.PRCE_REAL_TEN_NA_HDG_NA_NA_Y13DLRPMMBTU.A | D53: 2024 $/MMBtu | F53: 9.573513 | G53: 10.759744 | H53: 10.814753 | I53: 10.970607 | J53: 11.467427 | K53: 12.125462 | L53: 12.869673 | M53: 14.186323 | N53: 16.70895 | O53: 19.089088 | P53: 20.999569 | Q53: 22.460648 | R53: 23.549911 | S53: 24.492126 | T53: 25.62182 | U53: 26.518492 | V53: 27.252636 | W53: 27.774517 | X53: 28.24732 | Y53: 28.807552 | Z53: 29.432905 | AA53: 29.795622 | AB53: 30.212788 | AC53: 30.48605 | AD53: 30.778925 | AE53: 30.779465 | AF53: 31.056328 | AG53: 0.046
A54: Electricity | B54: Energy Prices: Average Price to All Users: Electricity: High Zero-Carbon Technology Cost | C54: AEO.2025.HIGHZTC.PRCE_REAL_TEN_NA_ELC_NA_NA_Y13DLRPMMBTU.A | D54: 2024 $/MMBtu | F54: 38.098598 | G54: 37.333973 | H54: 34.881783 | I54: 33.049328 | J54: 32.874008 | K54: 33.237839 | L54: 33.692875 | M54: 34.296566 | N54: 34.825642 | O54: 35.589108 | P54: 35.82687 | Q54: 35.637054 | R54: 35.304626 | S54: 35.029667 | T54: 35.204475 | U54: 34.977581 | V54: 34.87011 | W54: 34.885918 | X54: 35.053295 | Y54: 35.213997 | Z54: 35.421429 | AA54: 35.584679 | AB54: 35.760864 | AC54: 35.86097 | AD54: 36.115452 | AE54: 36.344898 | AF54: 36.619953 | AG54: -0.002
A55: Non-Renewable Energy Expenditures by Sector
A56: (billion 2024 dollars)
A57: Residential | B57: Energy Expenditures: Non-Renewable Residential: High Zero-Carbon Technology Cost | C57: AEO.2025.HIGHZTC.EXPD_REAL_RESD_NA_NRN_NA_NA_BLNY13DLR.A | D57: billion 2024 $ | F57: 321.87134 | G57: 315.88342 | H57: 305.58066 | I57: 296.62158 | J57: 297.20978 | K57: 300.82953 | L57: 304.87982 | M57: 310.57489 | N57: 317.27094 | O57: 326.10974 | P57: 331.93753 | Q57: 335.42114 | R57: 337.75583 | S57: 340.22046 | T57: 345.05158 | U57: 347.16873 | V57: 350.45749 | W57: 354.74896 | X57: 359.83096 | Y57: 364.80817 | Z57: 369.94171 | AA57: 374.44733 | AB57: 379.10901 | AC57: 382.82822 | AD57: 387.42389 | AE57: 392.04144 | AF57: 397.16125 | AG57: 0.008
A58: Commercial | B58: Energy Expenditures: Non-Renewable Commercial: High Zero-Carbon Technology Cost | C58: AEO.2025.HIGHZTC.EXPD_REAL_COMM_NA_NRN_NA_NA_BLNY13DLR.A | D58: billion 2024 $ | F58: 241.12788 | G58: 237.06464 | H58: 224.32684 | I58: 216.67044 | J58: 218.1534 | K58: 223.83768 | L58: 230.04021 | M58: 237.12822 | N58: 245.24901 | O58: 254.96646 | P58: 262.06677 | Q58: 266.73019 | R58: 270.46622 | S58: 274.20633 | T58: 280.46323 | U58: 283.60974 | V58: 287.87076 | W58: 293.21573 | X58: 299.31854 | Y58: 305.4968 | Z58: 311.30548 | AA58: 317.04187 | AB58: 323.19623 | AC58: 328.30466 | AD58: 334.83005 | AE58: 341.48096 | AF58: 348.67667 | AG58: 0.014
A59: Industrial | B59: Energy Expenditures: Non-Renewable Industrial: High Zero-Carbon Technology Cost | C59: AEO.2025.HIGHZTC.EXPD_REAL_IDAL_NA_NRN_NA_NA_BLNY13DLR.A | D59: billion 2024 $ | F59: 225.6075 | G59: 228.66371 | H59: 224.17224 | I59: 218.50401 | J59: 219.97305 | K59: 224.7794 | L59: 232.18533 | M59: 239.67705 | N59: 251.39009 | O59: 263.95074 | P59: 272.88592 | Q59: 277.75275 | R59: 280.54141 | S59: 282.8479 | T59: 285.52365 | U59: 287.85333 | V59: 292.14374 | W59: 297.64972 | X59: 303.51181 | Y59: 308.79642 | Z59: 314.98047 | AA59: 319.06403 | AB59: 323.77768 | AC59: 327.83051 | AD59: 331.76517 | AE59: 337.71106 | AF59: 345.76858 | AG59: 0.017
A60: Transportation | B60: Energy Expenditures: Non-Renewable Transportation: High Zero-Carbon Technology Cost | C60: AEO.2025.HIGHZTC.EXPD_REAL_TRN_NA_NRN_NA_NA_BLNY13DLR.A | D60: billion 2024 $ | F60: 714.84161 | G60: 676.34644 | H60: 644.13318 | I60: 632.38385 | J60: 624.66571 | K60: 615.55078 | L60: 609.02887 | M60: 597.48749 | N60: 577.68488 | O60: 563.21027 | P60: 548.96338 | Q60: 534.35663 | R60: 522.66711 | S60: 509.74472 | T60: 495.17035 | U60: 483.18903 | V60: 472.33688 | W60: 463.27811 | X60: 453.93814 | Y60: 450.51828 | Z60: 439.83545 | AA60: 431.82056 | AB60: 430.39609 | AC60: 428.29285 | AD60: 425.13794 | AE60: 424.65317 | AF60: 428.82517 | AG60: -0.019
A61: Total Non-Renewable Expenditures | B61: Energy Expenditures: Total Non-Renewable: High Zero-Carbon Technology Cost | C61: AEO.2025.HIGHZTC.EXPD_REAL_TEN_NA_NRN_NA_NA_BLNY13DLR.A | D61: billion 2024 $ | F61: 1503.4482 | G61: 1457.9583 | H61: 1398.2129 | I61: 1364.1799 | J61: 1360.002 | K61: 1364.9974 | L61: 1376.1343 | M61: 1384.8677 | N61: 1391.595 | O61: 1408.2372 | P61: 1415.8535 | Q61: 1414.2607 | R61: 1411.4305 | S61: 1407.0194 | T61: 1406.2087 | U61: 1401.8208 | V61: 1402.8088 | W61: 1408.8926 | X61: 1416.5995 | Y61: 1429.6196 | Z61: 1436.0631 | AA61: 1442.3738 | AB61: 1456.479 | AC61: 1467.2562 | AD61: 1479.157 | AE61: 1495.8866 | AF61: 1520.4316 | AG61: 0
A62: Transportation Renewable Expenditures | B62: Energy Expenditures: Renewable Transportation: High Zero-Carbon Technology Cost | C62: AEO.2025.HIGHZTC.EXPD_REAL_TRN_NA_RNW_NA_NA_BLNY13DLR.A | D62: billion 2024 $ | F62: 0.107875 | G62: 0.100345 | H62: 0.093489 | I62: 0.086554 | J62: 0.08253 | K62: 0.082791 | L62: 0.078487 | M62: 0.072793 | N62: 0.067211 | O62: 0.062402 | P62: 0.058996 | Q62: 0.055041 | R62: 0.051815 | S62: 0.048885 | T62: 0.045543 | U62: 0.043307 | V62: 0.041884 | W62: 0.04052 | X62: 0.039222 | Y62: 0.03885 | Z62: 0.037436 | AA62: 0.035974 | AB62: 0.036186 | AC62: 0.037198 | AD62: 0.037176 | AE62: 0.037423 | AF62: 0.037653 | AG62: -0.04
A63: Total Expenditures | B63: Energy Expenditures: High Zero-Carbon Technology Cost | C63: AEO.2025.HIGHZTC.EXPD_REAL_TEN_NA_NA_NA_NA_BLNY13DLR.A | D63: billion 2024 $ | F63: 1503.5562 | G63: 1458.0586 | H63: 1398.3064 | I63: 1364.2665 | J63: 1360.0845 | K63: 1365.0802 | L63: 1376.2128 | M63: 1384.9404 | N63: 1391.6622 | O63: 1408.2996 | P63: 1415.9125 | Q63: 1414.3158 | R63: 1411.4823 | S63: 1407.0682 | T63: 1406.2543 | U63: 1401.8641 | V63: 1402.8507 | W63: 1408.9331 | X63: 1416.6387 | Y63: 1429.6584 | Z63: 1436.1006 | AA63: 1442.4098 | AB63: 1456.5151 | AC63: 1467.2935 | AD63: 1479.1942 | AE63: 1495.9241 | AF63: 1520.4692 | AG63: 0
A64: Prices in Nominal Dollars
A65: Residential
A66: Propane | B66: Energy Prices: Nominal: Residential: Propane: High Zero-Carbon Technology Cost | C66: AEO.2025.HIGHZTC.PRCE_NOM_RESD_NA_PROP_NA_NA_NDLRPMBTU.A | D66: nom $/MMBtu | F66: 26.593981 | G66: 26.216951 | H66: 26.858906 | I66: 27.152178 | J66: 27.696188 | K66: 28.433746 | L66: 29.537058 | M66: 30.762877 | N66: 32.364796 | O66: 34.319061 | P66: 36.227283 | Q66: 37.835377 | R66: 39.225212 | S66: 40.455105 | T66: 41.493401 | U66: 42.453186 | V66: 43.498753 | W66: 44.748333 | X66: 46.046326 | Y66: 47.565804 | Z66: 49.313976 | AA66: 50.883286 | AB66: 52.401012 | AC66: 53.792717 | AD66: 55.213657 | AE66: 56.888172 | AF66: 59.05526 | AG66: 0.031
A67: Distillate Fuel Oil | B67: Energy Prices: Nominal: Residential: Distillate Fuel Oil: High Zero-Carbon Technology Cost | C67: AEO.2025.HIGHZTC.PRCE_NOM_RESD_NA_DFO_NA_NA_NDLRPMBTU.A | D67: nom $/MMBtu | F67: 26.158379 | G67: 25.122044 | H67: 25.57391 | I67: 26.70492 | J67: 28.145452 | K67: 29.655188 | L67: 31.292149 | M67: 31.994268 | N67: 32.578827 | O67: 33.679363 | P67: 34.56406 | Q67: 35.592525 | R67: 36.482147 | S67: 37.580669 | T67: 38.49485 | U67: 39.449146 | V67: 40.520947 | W67: 41.791801 | X67: 43.031525 | Y67: 44.415188 | Z67: 46.386429 | AA67: 47.287495 | AB67: 48.481236 | AC67: 49.511318 | AD67: 50.619339 | AE67: 51.830589 | AF67: 53.611908 | AG67: 0.028
A68: Natural Gas | B68: Energy Prices: Nominal: Residential: Natural Gas: High Zero-Carbon Technology Cost | C68: AEO.2025.HIGHZTC.PRCE_NOM_RESD_NA_NG_NA_NA_NDLRPMBTU.A | D68: nom $/MMBtu | F68: 13.932205 | G68: 12.954311 | H68: 12.947871 | I68: 12.736533 | J68: 12.713431 | K68: 12.812389 | L68: 12.963352 | M68: 13.460487 | N68: 14.2479 | O68: 15.014253 | P68: 15.664865 | Q68: 16.185392 | R68: 16.539627 | S68: 16.867327 | T68: 17.190029 | U68: 17.466055 | V68: 17.87583 | W68: 18.432865 | X68: 18.987307 | Y68: 19.539175 | Z68: 20.057804 | AA68: 20.636808 | AB68: 21.249207 | AC68: 21.801548 | AD68: 22.344536 | AE68: 22.992262 | AF68: 23.643501 | AG68: 0.021
A69: Electricity | B69: Energy Prices: Nominal: Residential: Electricity: High Zero-Carbon Technology Cost | C69: AEO.2025.HIGHZTC.PRCE_NOM_RESD_NA_ELC_NA_NA_NDLRPMBTU.A | D69: nom $/MMBtu | F69: 45.553139 | G69: 45.946316 | H69: 44.147362 | I69: 42.68951 | J69: 43.199879 | K69: 44.394344 | L69: 45.759983 | M69: 47.469128 | N69: 49.123363 | O69: 51.20969 | P69: 52.775246 | Q69: 53.770809 | R69: 54.499828 | S69: 55.237061 | T69: 56.600323 | U69: 57.412365 | V69: 58.473801 | W69: 59.749023 | X69: 61.305805 | Y69: 62.927402 | Z69: 64.688965 | AA69: 66.450142 | AB69: 68.314209 | AC69: 70.139587 | AD69: 72.280113 | AE69: 74.430412 | AF69: 76.763725 | AG69: 0.02
A70: Commercial
A71: Propane | B71: Energy Prices: Nominal: Commercial: Propane: High Zero-Carbon Technology Cost | C71: AEO.2025.HIGHZTC.PRCE_NOM_COMM_NA_PROP_NA_NA_NDLRPMBTU.A | D71: nom $/MMBtu | F71: 19.0868 | G71: 19.462267 | H71: 20.722958 | I71: 20.896338 | J71: 21.415871 | K71: 22.126076 | L71: 23.186728 | M71: 24.181175 | N71: 25.599268 | O71: 27.285578 | P71: 28.679901 | Q71: 29.663061 | R71: 30.521715 | S71: 31.288752 | T71: 31.908875 | U71: 32.549953 | V71: 33.355064 | W71: 34.399128 | X71: 35.402992 | Y71: 36.654724 | Z71: 38.095921 | AA71: 39.159187 | AB71: 40.22176 | AC71: 41.14883 | AD71: 42.192711 | AE71: 43.574436 | AF71: 45.485512 | AG71: 0.034
A72: Distillate Fuel Oil | B72: Energy Prices: Nominal: Commercial: Distillate Fuel Oil: High Zero-Carbon Technology Cost | C72: AEO.2025.HIGHZTC.PRCE_NOM_COMM_NA_DFO_NA_NA_NDLRPMBTU.A | D72: nom $/MMBtu | F72: 26.207932 | G72: 25.213644 | H72: 24.45471 | I72: 24.329535 | J72: 24.463184 | K72: 24.622513 | L72: 24.858423 | M72: 25.421419 | N72: 25.819269 | O72: 26.75503 | P72: 27.480581 | Q72: 28.332861 | R72: 29.053051 | S72: 29.982716 | T72: 30.743277 | U72: 31.520094 | V72: 32.409874 | W72: 33.497684 | X72: 34.544827 | Y72: 35.746708 | Z72: 37.507889 | AA72: 38.209797 | AB72: 39.197243 | AC72: 40.01429 | AD72: 40.892246 | AE72: 41.893551 | AF72: 43.440746 | AG72: 0.02
A73: Residual Fuel Oil | B73: Energy Prices: Nominal: Commercial: Residual Fuel: High Zero-Carbon Technology Cost | C73: AEO.2025.HIGHZTC.PRCE_NOM_COMM_NA_RFL_NA_NA_NDLRPMBTU.A | D73: nom $/MMBtu | F73: 6.746078 | G73: 7.624751 | H73: 8.137149 | I73: 9.318295 | J73: 10.659361 | K73: 12.053771 | L73: 13.582099 | M73: 13.93248 | N73: 14.188656 | O73: 14.782047 | P73: 15.231493 | Q73: 15.7293 | R73: 16.150297 | S73: 16.639704 | T73: 17.12731 | U73: 17.50531 | V73: 18.038643 | W73: 18.587471 | X73: 19.175329 | Y73: 19.669559 | Z73: 20.001068 | AA73: 20.508837 | AB73: 21.422373 | AC73: 21.833618 | AD73: 22.393961 | AE73: 23.08009 | AF73: 24.547924 | AG73: 0.051
A74: Natural Gas | B74: Energy Prices: Nominal: Commercial: Natural Gas: High Zero-Carbon Technology Cost | C74: AEO.2025.HIGHZTC.PRCE_NOM_COMM_NA_NG_NA_NA_NDLRPMBTU.A | D74: nom $/MMBtu | F74: 9.555858 | G74: 8.647205 | H74: 8.894887 | I74: 8.982198 | J74: 9.238312 | K74: 9.593985 | L74: 10.006991 | M74: 10.378997 | N74: 11.008718 | O74: 11.624795 | P74: 12.127806 | Q74: 12.511601 | R74: 12.748526 | S74: 12.961295 | T74: 13.166965 | U74: 13.32591 | V74: 13.605648 | W74: 14.017473 | X74: 14.422617 | Y74: 14.824856 | Z74: 15.191047 | AA74: 15.612323 | AB74: 16.065739 | AC74: 16.455938 | AD74: 16.838379 | AE74: 17.31855 | AF74: 17.797932 | AG74: 0.024
A75: Electricity | B75: Energy Prices: Nominal: Commercial: Electricity: High Zero-Carbon Technology Cost | C75: AEO.2025.HIGHZTC.PRCE_NOM_COMM_NA_ELC_NA_NA_NDLRPMBTU.A | D75: nom $/MMBtu | F75: 38.551605 | G75: 38.373066 | H75: 36.430439 | I75: 34.949959 | J75: 35.440617 | K75: 36.461376 | L75: 37.692257 | M75: 39.158566 | N75: 40.593861 | O75: 42.40168 | P75: 43.685726 | Q75: 44.42812 | R75: 44.932621 | S75: 45.491875 | T75: 46.729763 | U75: 47.292721 | V75: 48.106781 | W75: 49.142422 | X75: 50.434948 | Y75: 51.762238 | Z75: 53.199848 | AA75: 54.606941 | AB75: 56.062115 | AC75: 57.402596 | AD75: 59.100903 | AE75: 60.797062 | AF75: 62.602421 | AG75: 0.019
A76: Industrial
A77: Propane | B77: Energy Prices: Nominal: Industrial: Propane: High Zero-Carbon Technology Cost | C77: AEO.2025.HIGHZTC.PRCE_NOM_IDAL_NA_PROP_NA_NA_NDLRPMBTU.A | D77: nom $/MMBtu | F77: 12.66026 | G77: 12.863893 | H77: 13.973295 | I77: 14.048564 | J77: 14.43579 | K77: 15.016267 | L77: 15.940687 | M77: 16.79492 | N77: 18.076534 | O77: 19.648006 | P77: 20.92911 | Q77: 21.779829 | R77: 22.498993 | S77: 23.113136 | T77: 23.563791 | U77: 24.032267 | V77: 24.667187 | W77: 25.551607 | X77: 26.38966 | Y77: 27.487337 | Z77: 28.789852 | AA77: 29.676821 | AB77: 30.551477 | AC77: 31.264862 | AD77: 32.095585 | AE77: 33.291042 | AF77: 35.07243 | AG77: 0.04
A78: Distillate Fuel Oil | B78: Energy Prices: Nominal: Industrial: Distillate Fuel Oil: High Zero-Carbon Technology Cost | C78: AEO.2025.HIGHZTC.PRCE_NOM_IDAL_NA_DFO_NA_NA_NDLRPMBTU.A | D78: nom $/MMBtu | F78: 26.091763 | G78: 25.104553 | H78: 24.31003 | I78: 24.150816 | J78: 24.251072 | K78: 24.374624 | L78: 24.563076 | M78: 25.124552 | N78: 25.502512 | O78: 26.454292 | P78: 27.189726 | Q78: 28.066748 | R78: 28.804398 | S78: 29.743267 | T78: 30.491646 | U78: 31.270138 | V78: 32.174793 | W78: 33.254627 | X78: 34.312599 | Y78: 35.515114 | Z78: 37.282944 | AA78: 37.979282 | AB78: 38.965359 | AC78: 39.780514 | AD78: 40.66153 | AE78: 41.649815 | AF78: 43.196087 | AG78: 0.02
A79: Residual Fuel Oil | B79: Energy Prices: Nominal: Industrial: Residual Fuel Oil: High Zero-Carbon Technology Cost | C79: AEO.2025.HIGHZTC.PRCE_NOM_IDAL_NA_RFO_NA_NA_NDLRPMBTU.A | D79: nom $/MMBtu | F79: 7.83466 | G79: 9.029342 | H79: 9.791279 | I79: 11.21501 | J79: 12.772719 | K79: 14.460553 | L79: 16.301508 | M79: 16.756365 | N79: 17.084602 | O79: 17.806349 | P79: 18.351042 | Q79: 18.963621 | R79: 19.48053 | S79: 20.060932 | T79: 20.631222 | U79: 21.096069 | V79: 21.696745 | W79: 22.315178 | X79: 23.010378 | Y79: 23.606112 | Z79: 24.056906 | AA79: 24.588398 | AB79: 25.5982 | AC79: 26.115402 | AD79: 26.772156 | AE79: 27.564425 | AF79: 29.134497 | AG79: 0.052
A80: Natural Gas | B80: Energy Prices: Nominal: Industrial: Natural Gas: High Zero-Carbon Technology Cost | C80: AEO.2025.HIGHZTC.PRCE_NOM_IDAL_NA_NG_NA_NA_NDLRPMBTU.A | D80: nom $/MMBtu | F80: 3.33707 | G80: 4.092753 | H80: 4.059119 | I80: 4.000466 | J80: 4.160158 | K80: 4.399243 | L80: 4.716491 | M80: 4.995432 | N80: 5.614189 | O80: 6.151089 | P80: 6.571557 | Q80: 6.815947 | R80: 6.941227 | S80: 7.020285 | T80: 7.087222 | U80: 7.124869 | V80: 7.302329 | W80: 7.588699 | X80: 7.871264 | Y80: 8.153418 | Z80: 8.415148 | AA80: 8.679128 | AB80: 8.953509 | AC80: 9.165268 | AD80: 9.397243 | AE80: 9.713953 | AF80: 10.048857 | AG80: 0.043
A81: Metallurgical Coal | B81: Energy Prices: Nominal: Industrial: Metallurgical Coal: High Zero-Carbon Technology Cost | C81: AEO.2025.HIGHZTC.PRCE_NOM_IDAL_NA_MTC_NA_NA_NDLRPMBTU.A | D81: nom $/MMBtu | F81: 7.767755 | G81: 7.796243 | H81: 7.871439 | I81: 7.97157 | J81: 8.085632 | K81: 8.221068 | L81: 8.372914 | M81: 8.552305 | N81: 8.76001 | O81: 8.951728 | P81: 9.106216 | Q81: 9.326975 | R81: 9.520159 | S81: 9.715213 | T81: 9.919882 | U81: 10.098601 | V81: 10.307525 | W81: 10.486297 | X81: 10.70411 | Y81: 10.927295 | Z81: 11.176041 | AA81: 11.445536 | AB81: 11.694777 | AC81: 11.95179 | AD81: 12.221812 | AE81: 12.514791 | AF81: 12.798068 | AG81: 0.019
A82: Other Industrial Coal | B82: Energy Prices: Nominal: Industrial: Other Industrial Coal: High Zero-Carbon Technology Cost | C82: AEO.2025.HIGHZTC.PRCE_NOM_IDAL_NA_OIC_NA_NA_NDLRPMBTU.A | D82: nom $/MMBtu | F82: 3.572155 | G82: 3.698336 | H82: 3.755393 | I82: 3.800257 | J82: 3.839487 | K82: 3.894675 | L82: 3.939315 | M82: 3.980161 | N82: 4.025944 | O82: 4.108876 | P82: 4.178519 | Q82: 4.237221 | R82: 4.332891 | S82: 4.425549 | T82: 4.529464 | U82: 4.617622 | V82: 4.717606 | W82: 4.81023 | X82: 4.90497 | Y82: 5.017175 | Z82: 5.133989 | AA82: 5.260872 | AB82: 5.393869 | AC82: 5.523439 | AD82: 5.648167 | AE82: 5.779319 | AF82: 5.920915 | AG82: 0.02
A83: Hydrogen | B83: Energy Prices: Nominal: Industrial: Hydrogen: High Zero-Carbon Technology Cost | C83: AEO.2025.HIGHZTC.PRCE_NOM_IDAL_NA_HDG_NA_NA_NDLRPMBTU.A | D83: nom $/MMBtu | F83: 9.533875 | G83: 10.837247 | H83: 10.910973 | I83: 11.000694 | J83: 11.350653 | K83: 11.804646 | L83: 12.33646 | M83: 12.88052 | N83: 13.527663 | O83: 14.437382 | P83: 15.207238 | Q83: 15.714464 | R83: 15.976162 | S83: 16.201199 | T83: 16.814762 | U83: 17.255487 | V83: 17.601435 | W83: 17.801258 | X83: 18.058201 | Y83: 18.54907 | Z83: 19.218168 | AA83: 19.597013 | AB83: 20.066286 | AC83: 20.483709 | AD83: 21.006063 | AE83: 21.253933 | AF83: 21.909708 | AG83: 0.033
A84: Electricity | B84: Energy Prices: Nominal: Industrial: Electricity: High Zero-Carbon Technology Cost | C84: AEO.2025.HIGHZTC.PRCE_NOM_IDAL_NA_ELC_NA_NA_NDLRPMBTU.A | D84: nom $/MMBtu | F84: 26.507746 | G84: 26.453053 | H84: 24.42614 | I84: 23.377502 | J84: 23.65649 | K84: 24.427061 | L84: 25.361465 | M84: 26.565578 | N84: 27.891041 | O84: 29.39677 | P84: 30.297054 | Q84: 30.728235 | R84: 30.964788 | S84: 31.339684 | T84: 32.121273 | U84: 32.630165 | V84: 33.200687 | W84: 33.926659 | X84: 34.844383 | Y84: 35.767387 | Z84: 36.76469 | AA84: 37.748009 | AB84: 38.769558 | AC84: 39.806171 | AD84: 40.988098 | AE84: 42.221344 | AF84: 43.553734 | AG84: 0.019
A85: Transportation
A86: Propane | B86: Energy Prices: Nominal: Transportation: Propane: High Zero-Carbon Technology Cost | C86: AEO.2025.HIGHZTC.PRCE_NOM_TRN_NA_PROP_NA_NA_NDLRPMBTU.A | D86: nom $/MMBtu | F86: 17.589245 | G86: 18.113504 | H86: 19.288139 | I86: 19.402617 | J86: 19.884892 | K86: 20.528612 | L86: 21.475201 | M86: 22.341841 | N86: 23.592443 | O86: 25.05793 | P86: 26.243191 | Q86: 27.078346 | R86: 27.828451 | S86: 28.507137 | T86: 29.06373 | U86: 29.6493 | V86: 30.380901 | W86: 31.31735 | X86: 32.205608 | Y86: 33.315407 | Z86: 34.580158 | AA86: 35.500401 | AB86: 36.442253 | AC86: 37.26936 | AD86: 38.210121 | AE86: 39.444866 | AF86: 41.127125 | AG86: 0.033
A87: E85 | B87: Energy Prices: Nominal: Transportation: E85: High Zero-Carbon Technology Cost | C87: AEO.2025.HIGHZTC.PRCE_NOM_TRN_NA_E85_NA_NA_NDLRPMBTU.A | D87: nom $/MMBtu | F87: 28.823729 | G87: 29.528929 | H87: 31.362501 | I87: 31.520689 | J87: 31.560877 | K87: 31.091465 | L87: 31.677883 | M87: 32.462654 | N87: 32.887005 | O87: 33.282158 | P87: 33.961296 | Q87: 34.411186 | R87: 35.304825 | S87: 35.816044 | T87: 36.07196 | U87: 36.661804 | V87: 37.03791 | W87: 37.390469 | X87: 37.650631 | Y87: 38.484287 | Z87: 37.357738 | AA87: 37.673004 | AB87: 38.832993 | AC87: 39.919426 | AD87: 40.931694 | AE87: 42.123844 | AF87: 43.591473 | AG87: 0.016
A88: Motor Gasoline | B88: Energy Prices: Nominal: Transportation: Motor Gasoline: High Zero-Carbon Technology Cost | C88: AEO.2025.HIGHZTC.PRCE_NOM_TRN_NA_MGS_NA_NA_NDLRPMBTU.A | D88: nom $/MMBtu | F88: 28.679842 | G88: 27.649559 | H88: 26.447338 | I88: 26.363968 | J88: 26.575916 | K88: 26.740559 | L88: 27.284904 | M88: 27.857161 | N88: 28.241079 | O88: 28.688046 | P88: 29.259247 | Q88: 29.643103 | R88: 30.416477 | S88: 30.857229 | T88: 31.08515 | U88: 31.556293 | V88: 31.86388 | W88: 32.172955 | X88: 32.389519 | Y88: 33.129726 | Z88: 32.171364 | AA88: 32.448826 | AB88: 33.446316 | AC88: 34.377804 | AD88: 35.232975 | AE88: 36.242748 | AF88: 37.483807 | AG88: 0.01
A89: Jet Fuel | B89: Energy Prices: Nominal: Transportation: Jet Fuel: High Zero-Carbon Technology Cost | C89: AEO.2025.HIGHZTC.PRCE_NOM_TRN_NA_JFL_NA_NA_NDLRPMBTU.A | D89: nom $/MMBtu | F89: 17.638924 | G89: 16.730843 | H89: 16.808693 | I89: 17.490393 | J89: 18.456747 | K89: 19.450321 | L89: 20.549154 | M89: 21.10861 | N89: 21.421352 | O89: 22.26915 | P89: 22.921453 | Q89: 23.680696 | R89: 24.265625 | S89: 25.095047 | T89: 25.913126 | U89: 26.590034 | V89: 27.37747 | W89: 28.422379 | X89: 29.418961 | Y89: 30.607809 | Z89: 32.390099 | AA89: 33.059135 | AB89: 33.981655 | AC89: 34.762341 | AD89: 35.556072 | AE89: 36.506386 | AF89: 38.042904 | AG89: 0.03
A90: Diesel Fuel (distillate fuel oil) | B90: Energy Prices: Nominal: Transportation: Diesel Fuel: High Zero-Carbon Technology Cost | C90: AEO.2025.HIGHZTC.PRCE_NOM_TRN_NA_DFU_NA_NA_NDLRPMBTU.A | D90: nom $/MMBtu | F90: 27.283649 | G90: 26.115433 | H90: 25.960787 | I90: 26.409092 | J90: 27.145966 | K90: 27.88415 | L90: 28.804071 | M90: 29.447966 | N90: 29.907007 | O90: 31.000999 | P90: 31.835327 | Q90: 32.823837 | R90: 33.706982 | S90: 34.75103 | T90: 35.600651 | U90: 36.515694 | V90: 37.492653 | W90: 38.73037 | X90: 39.902431 | Y90: 41.264984 | Z90: 43.238216 | AA90: 44.208622 | AB90: 45.142673 | AC90: 45.975689 | AD90: 47.109848 | AE90: 48.095074 | AF90: 49.921055 | AG90: 0.024
A91: Residual Fuel Oil | B91: Energy Prices: Nominal: Transportation: Residual Fuel Oil: High Zero-Carbon Technology Cost | C91: AEO.2025.HIGHZTC.PRCE_NOM_TRN_NA_RFO_NA_NA_NDLRPMBTU.A | D91: nom $/MMBtu | F91: 13.401297 | G91: 12.08642 | H91: 13.143271 | I91: 13.269609 | J91: 13.44949 | K91: 13.681735 | L91: 13.963659 | M91: 14.334046 | N91: 14.58601 | O91: 15.138056 | P91: 15.579436 | Q91: 16.071001 | R91: 16.472446 | S91: 16.93008 | T91: 17.407122 | U91: 17.802528 | V91: 18.289398 | W91: 18.827923 | X91: 19.382305 | Y91: 19.961056 | Z91: 20.45513 | AA91: 20.639217 | AB91: 21.468082 | AC91: 21.92396 | AD91: 22.452873 | AE91: 23.112991 | AF91: 24.391928 | AG91: 0.023
A92: Natural Gas | B92: Energy Prices: Nominal: Transportation: Natural Gas: High Zero-Carbon Technology Cost | C92: AEO.2025.HIGHZTC.PRCE_NOM_TRN_NA_NG_NA_NA_NDLRPMBTU.A | D92: nom $/MMBtu | F92: 14.514303 | G92: 15.353681 | H92: 15.54298 | I92: 15.676928 | J92: 16.027996 | K92: 16.458422 | L92: 16.930372 | M92: 17.408998 | N92: 18.207653 | O92: 18.887894 | P92: 19.448368 | Q92: 19.869696 | R92: 20.144455 | S92: 20.387754 | T92: 20.653177 | U92: 20.842625 | V92: 21.180105 | W92: 21.65204 | X92: 22.116915 | Y92: 22.599672 | Z92: 23.054102 | AA92: 23.532368 | AB92: 24.045355 | AC92: 24.47493 | AD92: 24.923931 | AE92: 25.479113 | AF92: 26.036837 | AG92: 0.023
A93: Electricity | B93: Energy Prices: Nominal: Transportation: Electricity: High Zero-Carbon Technology Cost | C93: AEO.2025.HIGHZTC.PRCE_NOM_TRN_NA_ELC_NA_NA_NDLRPMBTU.A | D93: nom $/MMBtu | F93: 42.609589 | G93: 43.132473 | H93: 41.167706 | I93: 38.740616 | J93: 39.278465 | K93: 40.285549 | L93: 41.567707 | M93: 43.305412 | N93: 44.980736 | O93: 47.198868 | P93: 48.686226 | Q93: 49.814907 | R93: 50.725761 | S93: 51.426571 | T93: 52.990257 | U93: 53.319035 | V93: 54.038769 | W93: 55.149055 | X93: 56.83358 | Y93: 58.384079 | Z93: 60.2169 | AA93: 61.84684 | AB93: 63.485474 | AC93: 64.850441 | AD93: 67.204674 | AE93: 69.173325 | AF93: 71.287987 | AG93: 0.02
A94: Electric Power
A95: Distillate Fuel Oil | B95: Energy Prices: Nominal: Electric Power: Distillate Fuel Oil: High Zero-Carbon Technology Cost | C95: AEO.2025.HIGHZTC.PRCE_NOM_ELEP_NA_DFO_NA_NA_NDLRPMBTU.A | D95: nom $/MMBtu | F95: 26.137505 | G95: 25.158468 | H95: 24.349579 | I95: 24.243881 | J95: 24.290323 | K95: 24.449207 | L95: 24.764141 | M95: 25.211271 | N95: 26.411995 | O95: 27.32086 | P95: 28.020191 | Q95: 28.843813 | R95: 29.480864 | S95: 30.405664 | T95: 31.232695 | U95: 31.98801 | V95: 32.844948 | W95: 33.953346 | X95: 35.011749 | Y95: 36.227688 | Z95: 37.848587 | AA95: 38.540752 | AB95: 39.687569 | AC95: 40.546864 | AD95: 41.432865 | AE95: 42.511791 | AF95: 44.099937 | AG95: 0.02
A96: Residual Fuel Oil | B96: Energy Prices: Nominal: Electric Power: Residual Fuel Oil: High Zero-Carbon Technology Cost | C96: AEO.2025.HIGHZTC.PRCE_NOM_ELEP_NA_RFO_NA_NA_NDLRPMBTU.A | D96: nom $/MMBtu | F96: 17.394409 | G96: 13.952579 | H96: 14.129054 | I96: 15.084783 | J96: 16.160213 | K96: 17.238125 | L96: 18.366262 | M96: 18.919966 | N96: 19.218084 | O96: 19.9196 | P96: 20.531452 | Q96: 21.200205 | R96: 21.727137 | S96: 22.323874 | T96: 22.959166 | U96: 23.445345 | V96: 24.05047 | W96: 24.648952 | X96: 25.158894 | Y96: 25.788282 | Z96: 26.238935 | AA96: 25.865458 | AB96: 26.939405 | AC96: 27.569456 | AD96: 28.261061 | AE96: 29.120207 | AF96: 30.707489 | AG96: 0.022
A97: Natural Gas | B97: Energy Prices: Nominal: Electric Power: Natural Gas: High Zero-Carbon Technology Cost | C97: AEO.2025.HIGHZTC.PRCE_NOM_ELEP_NA_NG_NA_NA_NDLRPMBTU.A | D97: nom $/MMBtu | F97: 2.719399 | G97: 3.195652 | H97: 3.184279 | I97: 3.161742 | J97: 3.360756 | K97: 3.641106 | L97: 4.017598 | M97: 4.205285 | N97: 4.878047 | O97: 5.354023 | P97: 5.728351 | Q97: 5.941702 | R97: 6.058687 | S97: 6.139751 | T97: 6.222767 | U97: 6.276008 | V97: 6.450063 | W97: 6.698177 | X97: 6.94699 | Y97: 7.227041 | Z97: 7.51471 | AA97: 7.75071 | AB97: 8.012893 | AC97: 8.2078 | AD97: 8.43215 | AE97: 8.742098 | AF97: 9.07992 | AG97: 0.047
A98: Steam Coal | B98: Energy Prices: Nominal: Electric Power: Steam Coal: High Zero-Carbon Technology Cost | C98: AEO.2025.HIGHZTC.PRCE_NOM_ELEP_NA_STC_NA_NA_NDLRPMBTU.A | D98: nom $/MMBtu | F98: 2.489397 | G98: 2.477139 | H98: 2.465143 | I98: 2.45433 | J98: 2.393669 | K98: 2.436637 | L98: 2.506002 | M98: 2.523748 | N98: 2.497636 | O98: 2.557025 | P98: 2.597243 | Q98: 2.637013 | R98: 2.691709 | S98: 2.787691 | T98: 2.840207 | U98: 2.981519 | V98: 3.039955 | W98: 3.100967 | X98: 3.165769 | Y98: 3.236343 | Z98: 3.307455 | AA98: 3.364176 | AB98: 2.956725 | AC98: 3.488788 | AD98: 3.567891 | AE98: 3.678514 | AF98: 3.757201 | AG98: 0.016
A99: Uranium | B99: Energy Prices: Nominal: Electric Power: Uranium: High Zero-Carbon Technology Cost | C99: AEO.2025.HIGHZTC.PRCE_NOM_ELEP_NA_U_NA_NA_NDLRPMBTU.A | D99: nom $/MMBtu | F99: 0.753328 | G99: 0.768692 | H99: 0.781614 | I99: 0.794625 | J99: 0.809598 | K99: 0.823964 | L99: 0.839376 | M99: 0.856646 | N99: 0.874855 | O99: 0.893975 | P99: 0.913831 | Q99: 0.933637 | R99: 0.952895 | S99: 0.972646 | T99: 0.992824 | U99: 1.01317 | V99: 1.034323 | W99: 1.056301 | X99: 1.078981 | Y99: 1.102537 | Z99: 1.126784 | AA99: 1.151784 | AB99: 1.177392 | AC99: 1.203954 | AD99: 1.231253 | AE99: 1.259292 | AF99: 1.288084 | AG99: 0.021
A100: Hydrogen | B100: Energy Prices: Nominal: Electric Power: Uranium: High Zero-Carbon Technology Cost | C100: AEO.2025.HIGHZTC.NA_NOM_ELEP_NA_HDG_NA_NA_NDLRPMBTU.A | D100: nom $/MMBtu | F100: 9.533875 | G100: 10.837247 | H100: 10.910973 | I100: 11.000694 | J100: 11.350653 | K100: 11.804646 | L100: 12.33646 | M100: 12.88052 | N100: 15.711172 | O100: 16.592278 | P100: 17.379936 | Q100: 15.714464 | R100: 15.976162 | S100: 16.201199 | T100: 16.814762 | U100: 17.255487 | V100: 17.601435 | W100: 17.801258 | X100: 18.058201 | Y100: 18.54907 | Z100: 19.218168 | AA100: 19.597013 | AB100: 20.066286 | AC100: 20.483709 | AD100: 21.006063 | AE100: 21.253933 | AF100: 21.909708 | AG100: 0.033
...

Sheet AEO 2025 Table 6
A1: Table 6. Industrial Sector Key Indicators and Consumption
A2: https://www.eia.gov/outlooks/aeo/data/browser/#/?id=6-AEO2025&cases=highZTC&sourcekey=0
A3: Tue Dec 02 2025 13:18:59 GMT-0800 (Pacific Standard Time)
A4: Source: U.S. Energy Information Administration
B5: full name | C5: api key | D5: units | E5: 2023 | F5: 2024 | G5: 2025 | H5: 2026 | I5: 2027 | J5: 2028 | K5: 2029 | L5: 2030 | M5: 2031 | N5: 2032 | O5: 2033 | P5: 2034 | Q5: 2035 | R5: 2036 | S5: 2037 | T5: 2038 | U5: 2039 | V5: 2040 | W5: 2041 | X5: 2042 | Y5: 2043 | Z5: 2044 | AA5: 2045 | AB5: 2046 | AC5: 2047 | AD5: 2048 | AE5: 2049 | AF5: 2050 | AG5: Growth (2024-2050)
A6: Value of Shipments
A7: (billion 2012 dollars)
A8: Manufacturing | B8: Industrial: Value of Shipments: Manufacturing: High Zero-Carbon Technology Cost | C8: AEO.2025.HIGHZTC.ECI_NA_IDAL_MANF_VOS_NA_USA_BLNY09DLR.A | D8: billion 2012 $ | F8: 5974.9639 | G8: 6102.1035 | H8: 6220.3818 | I8: 6297.689 | J8: 6359.1074 | K8: 6419.7266 | L8: 6479.293 | M8: 6523.9873 | N8: 6577.8892 | O8: 6614.6309 | P8: 6684.3379 | Q8: 6740.0898 | R8: 6793.6846 | S8: 6856.6504 | T8: 6918.3003 | U8: 6987.396 | V8: 7063.019 | W8: 7128.4629 | X8: 7196.8643 | Y8: 7256.6079 | Z8: 7322.8701 | AA8: 7384.3311 | AB8: 7454.5503 | AC8: 7535.2563 | AD8: 7606.2373 | AE8: 7681.5273 | AF8: 7743.6045 | AG8: 0.01
A9: Agriculture | B9: Mining | C9: and Construction | D9: Industrial: Value of Shipments: Agriculture, Mining, and Construction: High Zero-Carbon Technology Cost | E9: AEO.2025.HIGHZTC.ECI_NA_IDAL_NMFG_VOS_NA_USA_BLNY09DLR.A | F9: billion 2012 $ | H9: 2718.2505 | I9: 2777.918 | J9: 2803.5085 | K9: 2839.2778 | L9: 2891.1875 | M9: 2948.4795 | N9: 2992.1099 | O9: 3020.3398 | P9: 3053.4861 | Q9: 3066.2 | R9: 3074.7314 | S9: 3093.0898 | T9: 3117.248 | U9: 3128.8452 | V9: 3144.9646 | W9: 3159.1543 | X9: 3177.1714 | Y9: 3191.8076 | Z9: 3212.5195 | AA9: 3226.1709 | AB9: 3241.9814 | AC9: 3269.1504 | AD9: 3302.4121 | AE9: 3332.9824 | AF9: 3363.4294 | AG9: 3398.2007 | AH9: 3430.1721 | AI9: 0.009
A10: Total | B10: Industrial: Value of Shipments: Total: High Zero-Carbon Technology Cost | C10: AEO.2025.HIGHZTC.ECI_NA_IDAL_NA_VOS_NA_USA_BLNY09DLR.A | D10: billion 2012 $ | F10: 8693.2148 | G10: 8880.0215 | H10: 9023.8906 | I10: 9136.9668 | J10: 9250.2949 | K10: 9368.2061 | L10: 9471.4023 | M10: 9544.3271 | N10: 9631.375 | O10: 9680.8311 | P10: 9759.0693 | Q10: 9833.1797 | R10: 9910.9326 | S10: 9985.4961 | T10: 10063.265 | U10: 10146.551 | V10: 10240.19 | W10: 10320.271 | X10: 10409.384 | Y10: 10482.779 | Z10: 10564.852 | AA10: 10653.481 | AB10: 10756.963 | AC10: 10868.238 | AD10: 10969.667 | AE10: 11079.729 | AF10: 11173.776 | AG10: 0.01
A11: Energy Prices
A12: (2024 dollars per MMBtu)
A13: Propane | B13: Industrial: Energy Prices: Propane: High Zero-Carbon Technology Cost | C13: AEO.2025.HIGHZTC.PRCE_NA_IDAL_HAP_PROP_NA_USA_Y13DLRPMMBTU.A | D13: 2024 $/MMBtu | F13: 12.66026 | G13: 12.605674 | H13: 13.465074 | I13: 13.314802 | J13: 13.427592 | K13: 13.72262 | L13: 14.298682 | M13: 14.759735 | N13: 15.554036 | O13: 16.543209 | P13: 17.23724 | Q13: 17.555822 | R13: 17.767212 | S13: 17.880009 | T13: 17.856604 | U13: 17.844084 | V13: 17.93939 | W13: 18.19438 | X13: 18.394274 | Y13: 18.748419 | Z13: 19.21232 | AA13: 19.372681 | AB13: 19.508192 | AC13: 19.52129 | AD13: 19.593958 | AE13: 19.869528 | AF13: 20.462763 | AG13: 0.019
A14: Motor Gasoline | B14: Industrial: Energy Prices: Motor Gasoline: High Zero-Carbon Technology Cost | C14: AEO.2025.HIGHZTC.PRCE_NA_IDAL_NA_MGS_NA_USA_Y13DLRPMMBTU.A | D14: 2024 $/MMBtu | F14: 28.673464 | G14: 27.674664 | H14: 26.287764 | I14: 25.797014 | J14: 25.399086 | K14: 24.899 | L14: 24.675621 | M14: 24.706846 | N14: 24.538458 | O14: 24.413212 | P14: 24.381813 | Q14: 24.200912 | R14: 24.348745 | S14: 24.217527 | T14: 23.927593 | U14: 23.785702 | V14: 23.517384 | W14: 23.278688 | X14: 22.960827 | Y14: 23.000324 | Z14: 21.883543 | AA14: 21.605103 | AB14: 21.787703 | AC14: 21.908485 | AD14: 21.966629 | AE14: 22.09486 | AF14: 22.340118 | AG14: -0.01
A15: Distillate Fuel Oil | B15: Industrial: Energy Prices: Distillate Fuel Oil: High Zero-Carbon Technology Cost | C15: AEO.2025.HIGHZTC.PRCE_NA_IDAL_NA_DFO_NA_USA_Y13DLRPMMBTU.A | D15: 2024 $/MMBtu | F15: 26.091763 | G15: 24.600626 | H15: 23.425852 | I15: 22.88941 | J15: 22.557371 | K15: 22.274755 | L15: 22.032902 | M15: 22.079994 | N15: 21.943752 | O15: 22.273958 | P15: 22.39349 | Q15: 22.623447 | R15: 22.746523 | S15: 23.008989 | T15: 23.10652 | U15: 23.218241 | V15: 23.399351 | W15: 23.679426 | X15: 23.916767 | Y15: 24.223963 | Z15: 24.880014 | AA15: 24.792429 | AB15: 24.880751 | AC15: 24.838329 | AD15: 24.82336 | AE15: 24.858402 | AF15: 25.202454 | AG15: -0.001
A16: Residual Fuel Oil | B16: Industrial: Energy Prices: Residual Fuel Oil: High Zero-Carbon Technology Cost | C16: AEO.2025.HIGHZTC.PRCE_NA_IDAL_NA_RFO_NA_USA_Y13DLRPMMBTU.A | D16: 2024 $/MMBtu | F16: 7.83466 | G16: 8.848094 | H16: 9.435161 | I16: 10.629246 | J16: 11.88067 | K16: 13.214781 | L16: 14.622335 | M16: 14.725853 | N16: 14.700524 | O16: 14.992572 | P16: 15.113938 | Q16: 15.285793 | R16: 15.383565 | S16: 15.518867 | T16: 15.634306 | U16: 15.663942 | V16: 15.779115 | W16: 15.889836 | X16: 16.038828 | Y16: 16.101131 | Z16: 16.053886 | AA16: 16.051018 | AB16: 16.34535 | AC16: 16.306047 | AD16: 16.344069 | AE16: 16.451635 | AF16: 16.998318 | AG16: 0.03
A17: Asphalt and Road Oil | B17: Industrial: Energy Prices: Asphalt and Road Oil: High Zero-Carbon Technology Cost | C17: AEO.2025.HIGHZTC.PRCE_NA_IDAL_NA_ARO_NA_USA_Y13DLRPMMBTU.A | D17: 2024 $/MMBtu | F17: 7.535996 | G17: 8.807061 | H17: 8.571714 | I17: 8.758927 | J17: 8.982862 | K17: 9.272329 | L17: 9.597788 | M17: 9.626869 | N17: 9.576499 | O17: 9.736337 | P17: 9.803224 | Q17: 9.889682 | R17: 9.94466 | S17: 10.012337 | T17: 10.073389 | U17: 10.068779 | V17: 10.152576 | W17: 10.247764 | X17: 10.325734 | Y17: 10.296822 | Z17: 10.155124 | AA17: 10.215075 | AB17: 10.342485 | AC17: 10.290125 | AD17: 10.252983 | AE17: 10.41711 | AF17: 10.703161 | AG17: 0.014
A18: Natural Gas | B18: Industrial: Energy Prices: Natural Gas: High Zero-Carbon Technology Cost | C18: AEO.2025.HIGHZTC.PRCE_NA_IDAL_NA_NG_NA_USA_Y13DLRPMMBTU.A | D18: 2024 $/MMBtu | F18: 3.36092 | G18: 4.039081 | H18: 3.947378 | I18: 3.823099 | J18: 3.901809 | K18: 4.050515 | L18: 4.267354 | M18: 4.432152 | N18: 4.875979 | O18: 5.225038 | P18: 5.456037 | Q18: 5.537374 | R18: 5.522622 | S18: 5.471223 | T18: 5.405282 | U18: 5.327897 | V18: 5.350899 | W18: 5.447668 | X18: 5.53614 | Y18: 5.607039 | Z18: 5.661417 | AA18: 5.721578 | AB18: 5.771735 | AC18: 5.777755 | AD18: 5.79364 | AE18: 5.855846 | AF18: 5.927567 | AG18: 0.022
A19: Hydrogen | B19: Industrial: Energy Prices: Hydrogen: High Zero-Carbon Technology Cost | C19: AEO.2025.HIGHZTC.PRCE_NA_IDAL_NA_HDG_NA_USA_Y13DLRPMMBTU.A | D19: 2024 $/MMBtu | F19: 9.533875 | G19: 10.619709 | H19: 10.514131 | I19: 10.426125 | J19: 10.55792 | K19: 10.787679 | L19: 11.065716 | M19: 11.319676 | N19: 11.63994 | O19: 12.155972 | P19: 12.524699 | Q19: 12.666781 | R19: 12.616203 | S19: 12.533028 | T19: 12.742199 | U19: 12.81229 | V19: 12.800771 | W19: 12.675635 | X19: 12.587033 | Y19: 12.651853 | Z19: 12.824852 | AA19: 12.7927 | AB19: 12.813029 | AC19: 12.789708 | AD19: 12.823941 | AE19: 12.685263 | AF19: 12.783066 | AG19: 0.011
A20: Metallurgical Coal | B20: Industrial: Energy Prices: Metallurgical Coal: High Zero-Carbon Technology Cost | C20: AEO.2025.HIGHZTC.PRCE_NA_IDAL_NA_MTC_NA_USA_Y13DLRPMMBTU.A | D20: 2024 $/MMBtu | F20: 7.767755 | G20: 7.639748 | H20: 7.585148 | I20: 7.555212 | J20: 7.520931 | K20: 7.512826 | L20: 7.510444 | M20: 7.515949 | N20: 7.537591 | O20: 7.537167 | P20: 7.49989 | Q20: 7.518089 | R20: 7.517967 | S20: 7.515557 | T20: 7.51727 | U20: 7.498265 | V20: 7.496222 | W20: 7.466915 | X20: 7.461041 | Y20: 7.453232 | Z20: 7.458103 | AA20: 7.471511 | AB20: 7.467525 | AC20: 7.46251 | AD20: 7.461265 | AE20: 7.469367 | AF20: 7.466943 | AG20: -0.002
A21: Steam Coal | B21: Industrial: Energy Prices: Other Industrial Coal: High Zero-Carbon Technology Cost | C21: AEO.2025.HIGHZTC.PRCE_NA_IDAL_NA_STC_NA_USA_Y13DLRPMMBTU.A | D21: 2024 $/MMBtu | F21: 3.572155 | G21: 3.624099 | H21: 3.618806 | I21: 3.601768 | J21: 3.571336 | K21: 3.55915 | L21: 3.533537 | M21: 3.497851 | N21: 3.464142 | O21: 3.459587 | P21: 3.441433 | Q21: 3.415449 | R21: 3.421638 | S21: 3.423545 | T21: 3.432421 | U21: 3.428609 | V21: 3.430913 | W21: 3.425192 | X21: 3.418891 | Y21: 3.422088 | Z21: 3.426063 | AA21: 3.434236 | AB21: 3.444175 | AC21: 3.448749 | AD21: 3.448136 | AE21: 3.449347 | AF21: 3.454516 | AG21: -0.001
A22: Electricity | B22: Industrial: Energy Prices: Electricity: High Zero-Carbon Technology Cost | C22: AEO.2025.HIGHZTC.PRCE_NA_IDAL_NA_ELC_NA_USA_Y13DLRPMMBTU.A | D22: 2024 $/MMBtu | F22: 26.507746 | G22: 25.922054 | H22: 23.537739 | I22: 22.156487 | J22: 22.004316 | K22: 22.322678 | L22: 22.749052 | M22: 23.346399 | N22: 23.998974 | O22: 24.751463 | P22: 24.95269 | Q22: 24.768763 | R22: 24.45256 | S22: 24.243956 | T22: 24.34145 | U22: 24.228069 | V22: 24.145441 | W22: 24.157953 | X22: 24.287434 | Y22: 24.39603 | Z22: 24.534168 | AA22: 24.641457 | AB22: 24.755726 | AC22: 24.854349 | AD22: 25.022724 | AE22: 25.199516 | AF22: 25.411121 | AG22: -0.002
A23: (nominal dollars per MMBtu)
A24: Propane | B24: Industrial: Energy Prices: Nominal: Propane: High Zero-Carbon Technology Cost | C24: AEO.2025.HIGHZTC.PRCE_NA_IDAL_HAP_PROP_NA_USA_NDLRPMBTU.A | D24: nom $/MMBtu | F24: 12.66026 | G24: 12.863893 | H24: 13.973295 | I24: 14.048564 | J24: 14.43579 | K24: 15.016267 | L24: 15.940687 | M24: 16.79492 | N24: 18.076534 | O24: 19.648006 | P24: 20.92911 | Q24: 21.779829 | R24: 22.498993 | S24: 23.113136 | T24: 23.563791 | U24: 24.032267 | V24: 24.667187 | W24: 25.551607 | X24: 26.38966 | Y24: 27.487337 | Z24: 28.789852 | AA24: 29.676821 | AB24: 30.551477 | AC24: 31.264862 | AD24: 32.095585 | AE24: 33.291042 | AF24: 35.07243 | AG24: 0.04
A25: Motor Gasoline | B25: Industrial: Energy Prices: Nominal: Motor Gasoline: High Zero-Carbon Technology Cost | C25: AEO.2025.HIGHZTC.PRCE_NA_IDAL_NA_MGS_NA_USA_NDLRPMBTU.A | D25: nom $/MMBtu | F25: 28.673464 | G25: 28.241562 | H25: 27.279961 | I25: 27.218655 | J25: 27.306154 | K25: 27.246258 | L25: 27.509274 | M25: 28.113613 | N25: 28.518017 | O25: 28.995035 | P25: 29.603909 | Q25: 30.023756 | R25: 30.833324 | S25: 31.305521 | T25: 31.575144 | U25: 32.034389 | V25: 32.337093 | W25: 32.691845 | X25: 32.941139 | Y25: 33.721119 | Z25: 32.792706 | AA25: 33.096645 | AB25: 34.121384 | AC25: 35.088142 | AD25: 35.982105 | AE25: 37.01955 | AF25: 38.29015 | AG25: 0.011
A26: Distillate Fuel Oil | B26: Industrial: Energy Prices: Nominal: Distillate Fuel Oil: High Zero-Carbon Technology Cost | C26: AEO.2025.HIGHZTC.PRCE_NA_IDAL_NA_DFO_NA_USA_NDLRPMBTU.A | D26: nom $/MMBtu | F26: 26.091763 | G26: 25.104553 | H26: 24.31003 | I26: 24.150816 | J26: 24.251072 | K26: 24.374624 | L26: 24.563076 | M26: 25.124552 | N26: 25.502512 | O26: 26.454292 | P26: 27.189726 | Q26: 28.066748 | R26: 28.804398 | S26: 29.743267 | T26: 30.491646 | U26: 31.270138 | V26: 32.174793 | W26: 33.254627 | X26: 34.312599 | Y26: 35.515114 | Z26: 37.282944 | AA26: 37.979282 | AB26: 38.965359 | AC26: 39.780514 | AD26: 40.66153 | AE26: 41.649815 | AF26: 43.196087 | AG26: 0.02
A27: Residual Fuel Oil | B27: Industrial: Energy Prices: Nominal: Residual Fuel Oil: High Zero-Carbon Technology Cost | C27: AEO.2025.HIGHZTC.PRCE_NA_IDAL_NA_RFO_NA_USA_NDLRPMBTU.A | D27: nom $/MMBtu | F27: 7.83466 | G27: 9.029342 | H27: 9.791279 | I27: 11.21501 | J27: 12.772719 | K27: 14.460553 | L27: 16.301508 | M27: 16.756365 | N27: 17.084602 | O27: 17.806349 | P27: 18.351042 | Q27: 18.963621 | R27: 19.48053 | S27: 20.060932 | T27: 20.631222 | U27: 21.096069 | V27: 21.696745 | W27: 22.315178 | X27: 23.010378 | Y27: 23.606112 | Z27: 24.056906 | AA27: 24.588398 | AB27: 25.5982 | AC27: 26.115402 | AD27: 26.772156 | AE27: 27.564425 | AF27: 29.134497 | AG27: 0.052
A28: Asphalt and Road Oil | B28: Industrial: Energy Prices: Nominal: Asphalt and Road Oil: High Zero-Carbon Technology Cost | C28: AEO.2025.HIGHZTC.PRCE_NA_IDAL_NA_ARO_NA_USA_NDLRPMBTU.A | D28: nom $/MMBtu | F28: 7.535996 | G28: 8.987468 | H28: 8.895243 | I28: 9.241621 | J28: 9.657331 | K28: 10.146442 | L28: 10.699961 | M28: 10.954295 | N28: 11.12958 | O28: 11.563634 | P28: 11.902878 | Q28: 12.269182 | R28: 12.593131 | S28: 12.942751 | T28: 13.292968 | U28: 13.56055 | V28: 13.96009 | W28: 14.391631 | X28: 14.813991 | Y28: 15.096324 | Z28: 15.217553 | AA28: 15.648374 | AB28: 16.197206 | AC28: 16.480434 | AD28: 16.794744 | AE28: 17.453684 | AF28: 18.344828 | AG28: 0.035
A29: Natural Gas | B29: Industrial: Energy Prices: Nominal: Natural Gas Heat: High Zero-Carbon Technology Cost | C29: AEO.2025.HIGHZTC.PRCE_NA_IDAL_NA_NG_NA_USA_NDLRPMBTU.A | D29: nom $/MMBtu | F29: 3.36092 | G29: 4.121819 | H29: 4.096367 | I29: 4.033785 | J29: 4.194773 | K29: 4.432362 | L29: 4.7574 | M29: 5.043291 | N29: 5.666748 | O29: 6.205663 | P29: 6.62461 | Q29: 6.86969 | R29: 6.993411 | S29: 7.072542 | T29: 7.132877 | U29: 7.175567 | V29: 7.357642 | W29: 7.65053 | X29: 7.942518 | Y29: 8.220565 | Z29: 8.483688 | AA29: 8.76483 | AB29: 9.039025 | AC29: 9.253523 | AD29: 9.490184 | AE29: 9.811368 | AF29: 10.159634 | AG29: 0.043
A30: Hydrogen | B30: Industrial: Energy Prices: Nominal: Hydrogen: High Zero-Carbon Technology Cost | C30: AEO.2025.HIGHZTC.PRCE_NA_IDAL_NA_HDG_NA_USA_NDLRPMBTU.A | D30: nom $/MMBtu | F30: 9.533875 | G30: 10.837247 | H30: 10.910973 | I30: 11.000694 | J30: 11.350653 | K30: 11.804646 | L30: 12.33646 | M30: 12.88052 | N30: 13.527663 | O30: 14.437382 | P30: 15.207238 | Q30: 15.714464 | R30: 15.976162 | S30: 16.201199 | T30: 16.814762 | U30: 17.255487 | V30: 17.601435 | W30: 17.801258 | X30: 18.058201 | Y30: 18.54907 | Z30: 19.218168 | AA30: 19.597013 | AB30: 20.066286 | AC30: 20.483709 | AD30: 21.006063 | AE30: 21.253933 | AF30: 21.909708 | AG30: 0.033
A31: Metallurgical Coal | B31: Industrial: Energy Prices: Nominal: Metallurgical Coal: High Zero-Carbon Technology Cost | C31: AEO.2025.HIGHZTC.PRCE_NA_IDAL_NA_MTC_NA_USA_NDLRPMBTU.A | D31: nom $/MMBtu | F31: 7.767755 | G31: 7.796243 | H31: 7.871439 | I31: 7.97157 | J31: 8.085632 | K31: 8.221068 | L31: 8.372914 | M31: 8.552305 | N31: 8.76001 | O31: 8.951728 | P31: 9.106216 | Q31: 9.326975 | R31: 9.520159 | S31: 9.715213 | T31: 9.919882 | U31: 10.098601 | V31: 10.307525 | W31: 10.486297 | X31: 10.70411 | Y31: 10.927295 | Z31: 11.176041 | AA31: 11.445536 | AB31: 11.694777 | AC31: 11.95179 | AD31: 12.221812 | AE31: 12.514791 | AF31: 12.798068 | AG31: 0.019
A32: Steam Coal | B32: Industrial: Energy Prices: Nominal: Other Industrial Coal: High Zero-Carbon Technology Cost | C32: AEO.2025.HIGHZTC.PRCE_NA_IDAL_NA_STC_NA_USA_NDLRPMBTU.A | D32: nom $/MMBtu | F32: 3.572155 | G32: 3.698336 | H32: 3.755393 | I32: 3.800257 | J32: 3.839487 | K32: 3.894675 | L32: 3.939315 | M32: 3.980161 | N32: 4.025944 | O32: 4.108876 | P32: 4.178519 | Q32: 4.237221 | R32: 4.332891 | S32: 4.425549 | T32: 4.529464 | U32: 4.617622 | V32: 4.717606 | W32: 4.81023 | X32: 4.90497 | Y32: 5.017175 | Z32: 5.133989 | AA32: 5.260872 | AB32: 5.393869 | AC32: 5.523439 | AD32: 5.648167 | AE32: 5.779319 | AF32: 5.920915 | AG32: 0.02
A33: Electricity | B33: Industrial: Energy Prices: Nominal: Electricity: High Zero-Carbon Technology Cost | C33: AEO.2025.HIGHZTC.PRCE_NA_IDAL_NA_ELC_NA_USA_NDLRPMBTU.A | D33: nom $/MMBtu | F33: 26.507746 | G33: 26.453053 | H33: 24.42614 | I33: 23.377502 | J33: 23.65649 | K33: 24.427061 | L33: 25.361465 | M33: 26.565578 | N33: 27.891041 | O33: 29.39677 | P33: 30.297054 | Q33: 30.728235 | R33: 30.964788 | S33: 31.339684 | T33: 32.121273 | U33: 32.630165 | V33: 33.200687 | W33: 33.926659 | X33: 34.844383 | Y33: 35.767387 | Z33: 36.76469 | AA33: 37.748009 | AB33: 38.769558 | AC33: 39.806171 | AD33: 40.988098 | AE33: 42.221344 | AF33: 43.553734 | AG33: 0.019
A34: Energy Consumption (quadrillion Btu)
A35: Industrial End-Use Consumption Excluding Refining and Hydrogen Production
A36: Propane Heat and Power | B36: Industrial: Energy Use: Excluding Refining: Propane Heat and Power: High Zero-Carbon Technology Cost | C36: AEO.2025.HIGHZTC.CNSM_NA_IDAL_IDEI_LPGHP_NA_USA_QBTU.A | D36: quads | F36: 0.057545 | G36: 0.1155 | H36: 0.116488 | I36: 0.117768 | J36: 0.118981 | K36: 0.120806 | L36: 0.122225 | M36: 0.123407 | N36: 0.125766 | O36: 0.126346 | P36: 0.127184 | Q36: 0.128271 | R36: 0.129641 | S36: 0.131156 | T36: 0.132603 | U36: 0.133936 | V36: 0.135029 | W36: 0.135651 | X36: 0.136466 | Y36: 0.13723 | Z36: 0.138026 | AA36: 0.139073 | AB36: 0.140203 | AC36: 0.141396 | AD36: 0.142557 | AE36: 0.143824 | AF36: 0.144934 | AG36: 0.036
A37: Hydrocarbon Gas Liquid Feedstocks | B37: Industrial: Energy Use: Excluding Refining: LPG and Other Feedstocks: High Zero-Carbon Technology Cost | C37: AEO.2025.HIGHZTC.CNSM_NA_IDAL_IDEI_LPGF_NA_USA_QBTU.A | D37: quads | F37: 3.485 | G37: 3.489802 | H37: 3.49178 | I37: 3.495489 | J37: 3.500911 | K37: 3.505162 | L37: 3.508227 | M37: 3.509183 | N37: 3.509037 | O37: 3.509996 | P37: 3.505924 | Q37: 3.501432 | R37: 3.498329 | S37: 3.492201 | T37: 3.520821 | U37: 3.588347 | V37: 3.662664 | W37: 3.722698 | X37: 3.785018 | Y37: 3.828975 | Z37: 3.800663 | AA37: 3.760822 | AB37: 3.798597 | AC37: 3.870811 | AD37: 3.923123 | AE37: 3.895189 | AF37: 3.866342 | AG37: 0.004
A38: Ethane | B38: Industrial: Energy Use: Excluding Refining: Ethane: High Zero-Carbon Technology Cost | C38: AEO.2025.HIGHZTC.CNSM_NA_IDAL_IDEI_C2H6_NA_USA_QBTU.A | D38: quads | F38: 2.2998 | G38: 2.288902 | H38: 2.283691 | I38: 2.285511 | J38: 2.28945 | K38: 2.290154 | L38: 2.287243 | M38: 2.28496 | N38: 2.311105 | O38: 2.340163 | P38: 2.466583 | Q38: 2.539263 | R38: 2.57182 | S38: 2.667409 | T38: 2.730169 | U38: 2.816665 | V38: 2.928883 | W38: 3.002764 | X38: 3.103962 | Y38: 3.126492 | Z38: 3.08027 | AA38: 2.997216 | AB38: 3.040648 | AC38: 3.1498 | AD38: 3.222384 | AE38: 3.237635 | AF38: 3.217825 | AG38: 0.013
A39: Propane | B39: Industrial: Energy Use: Excluding Refining: Propane: High Zero-Carbon Technology Cost | C39: AEO.2025.HIGHZTC.CNSM_NA_IDAL_IDEI_PROP_NA_USA_QBTU.A | D39: quads | F39: 0.3216 | G39: 0.3929 | H39: 0.386771 | I39: 0.387701 | J39: 0.388432 | K39: 0.390179 | L39: 0.393122 | M39: 0.394717 | N39: 0.381769 | O39: 0.367931 | P39: 0.303667 | Q39: 0.265661 | R39: 0.248099 | S39: 0.198006 | T39: 0.181193 | U39: 0.17185 | V39: 0.153185 | W39: 0.146365 | X39: 0.127219 | Y39: 0.137771 | Z39: 0.146592 | AA39: 0.167873 | AB39: 0.165087 | AC39: 0.146896 | AD39: 0.136912 | AE39: 0.115645 | AF39: 0.111194 | AG39: -0.04
A40: Propylene | B40: Industrial: Energy Use: Excluding Refining: Propylene: High Zero-Carbon Technology Cost | C40: AEO.2025.HIGHZTC.CNSM_NA_IDAL_IDEI_PPL_NA_USA_QBTU.A | D40: quads | F40: 0.3857 | G40: 0.4031 | H40: 0.422732 | I40: 0.422732 | J40: 0.422732 | K40: 0.422732 | L40: 0.422732 | M40: 0.422732 | N40: 0.422732 | O40: 0.422732 | P40: 0.422732 | Q40: 0.422732 | R40: 0.422732 | S40: 0.422732 | T40: 0.422732 | U40: 0.422732 | V40: 0.422732 | W40: 0.422732 | X40: 0.422732 | Y40: 0.422732 | Z40: 0.422732 | AA40: 0.422732 | AB40: 0.422732 | AC40: 0.422732 | AD40: 0.422732 | AE40: 0.422732 | AF40: 0.422732 | AG40: 0.004
A41: Butane | B41: Industrial: Energy Use: Excluding Refining: Butane: High Zero-Carbon Technology Cost | C41: AEO.2025.HIGHZTC.CNSM_NA_IDAL_IDEI_NBTN_NA_USA_QBTU.A | D41: quads | F41: 0.4779 | G41: 0.4049 | H41: 0.398585 | I41: 0.399544 | J41: 0.400297 | K41: 0.402097 | L41: 0.40513 | M41: 0.406774 | N41: 0.39343 | O41: 0.379169 | P41: 0.312942 | Q41: 0.273775 | R41: 0.255677 | S41: 0.204053 | T41: 0.186727 | U41: 0.177099 | V41: 0.157864 | W41: 0.150836 | X41: 0.131105 | Y41: 0.14198 | Z41: 0.15107 | AA41: 0.173001 | AB41: 0.17013 | AC41: 0.151383 | AD41: 0.141094 | AE41: 0.119177 | AF41: 0.114591 | AG41: -0.053
A42: Natural Gasoline | B42: Industrial: Energy Use: Excluding Refining: Natural Gas: High Zero-Carbon Technology Cost | C42: AEO.2025.HIGHZTC.CNSM_NA_IDAL_IDEI_NG_NA_USA_QBTU.A | D42: quads | F42: 0 | G42: 0 | H42: 0 | I42: 0 | J42: 0 | K42: 0 | L42: 0 | M42: 0 | N42: 0 | O42: 0 | P42: 0 | Q42: 0 | R42: 0 | S42: 0 | T42: 0 | U42: 0 | V42: 0 | W42: 0 | X42: 0 | Y42: 0 | Z42: 0 | AA42: 0 | AB42: 0 | AC42: 0 | AD42: 0 | AE42: 0 | AF42: 0 | AG42: - -
A43: Motor Gasoline | B43: Industrial: Energy Use: Excluding Refining: Motor Gasoline: High Zero-Carbon Technology Cost | C43: AEO.2025.HIGHZTC.CNSM_NA_IDAL_IDEI_MGS_NA_USA_QBTU.A | D43: quads | F43: 0.281291 | G43: 0.285247 | H43: 0.288387 | I43: 0.292239 | J43: 0.297109 | K43: 0.302658 | L43: 0.307115 | M43: 0.310404 | N43: 0.313444 | O43: 0.31532 | P43: 0.316919 | Q43: 0.319351 | R43: 0.322235 | S43: 0.32399 | T43: 0.3259 | U43: 0.327691 | V43: 0.329586 | W43: 0.33104 | X43: 0.333046 | Y43: 0.334606 | Z43: 0.336343 | AA43: 0.339079 | AB43: 0.342198 | AC43: 0.345227 | AD43: 0.348264 | AE43: 0.351611 | AF43: 0.3547 | AG43: 0.009
A44: Distillate Fuel Oil | B44: Industrial: Energy Use: Excluding Refining: Distillate Fuel Oil: High Zero-Carbon Technology Cost | C44: AEO.2025.HIGHZTC.CNSM_NA_IDAL_IDEI_DFO_NA_USA_QBTU.A | D44: quads | F44: 1.138439 | G44: 1.150196 | H44: 1.163439 | I44: 1.177088 | J44: 1.195205 | K44: 1.216104 | L44: 1.23274 | M44: 1.246904 | N44: 1.260956 | O44: 1.269289 | P44: 1.277959 | Q44: 1.288505 | R44: 1.299513 | S44: 1.308196 | T44: 1.317186 | U44: 1.324638 | V44: 1.332429 | W44: 1.337751 | X44: 1.344097 | Y44: 1.349923 | Z44: 1.356099 | AA44: 1.364485 | AB44: 1.374968 | AC44: 1.385294 | AD44: 1.394428 | AE44: 1.405687 | AF44: 1.41575 | AG44: 0.008
A45: Residual Fuel Oil | B45: Industrial: Energy Use: Excluding Refining: Residual Fuel Oil: High Zero-Carbon Technology Cost | C45: AEO.2025.HIGHZTC.CNSM_NA_IDAL_IDEI_RFO_NA_USA_QBTU.A | D45: quads | F45: 0.040886 | G45: 0.041692 | H45: 0.041255 | I45: 0.040061 | J45: 0.038841 | K45: 0.037551 | L45: 0.036369 | M45: 0.035532 | N45: 0.035132 | O45: 0.03466 | P45: 0.034279 | Q45: 0.033786 | R45: 0.033265 | S45: 0.032701 | T45: 0.032198 | U45: 0.031759 | V45: 0.031438 | W45: 0.031172 | X45: 0.030896 | Y45: 0.030629 | Z45: 0.03044 | AA45: 0.03024 | AB45: 0.029949 | AC45: 0.029728 | AD45: 0.029473 | AE45: 0.029252 | AF45: 0.028857 | AG45: -0.013
A46: Petrochemical Feedstocks | B46: Industrial: Energy Use: Excluding Refining: Petrochemical Feedstocks: High Zero-Carbon Technology Cost | C46: AEO.2025.HIGHZTC.CNSM_NA_IDAL_IDEI_PCF_NA_USA_QBTU.A | D46: quads | F46: 0.390525 | G46: 0.355 | H46: 0.55 | I46: 0.55 | J46: 0.55 | K46: 0.55 | L46: 0.55 | M46: 0.55 | N46: 0.55 | O46: 0.55 | P46: 0.55 | Q46: 0.55 | R46: 0.55 | S46: 0.55 | T46: 0.55 | U46: 0.55 | V46: 0.55 | W46: 0.55 | X46: 0.55 | Y46: 0.55 | Z46: 0.69558 | AA46: 0.84116 | AB46: 0.84116 | AC46: 0.84116 | AD46: 0.84116 | AE46: 0.964095 | AF46: 1.087029 | AG46: 0.04
A47: Petroleum Coke | B47: Industrial: Energy Use: Excluding Refining: Petroleum Coke: High Zero-Carbon Technology Cost | C47: AEO.2025.HIGHZTC.CNSM_NA_IDAL_IDEI_PCK_NA_USA_QBTU.A | D47: quads | F47: 0.038646 | G47: 0.036 | H47: 0.032849 | I47: 0.029931 | J47: 0.027424 | K47: 0.02518 | L47: 0.023056 | M47: 0.021245 | N47: 0.019763 | O47: 0.018299 | P47: 0.016906 | Q47: 0.015416 | R47: 0.013953 | S47: 0.012476 | T47: 0.010969 | U47: 0.011109 | V47: 0.0113 | W47: 0.011536 | X47: 0.011763 | Y47: 0.011997 | Z47: 0.012281 | AA47: 0.012526 | AB47: 0.012661 | AC47: 0.012856 | AD47: 0.013039 | AE47: 0.013234 | AF47: 0.01327 | AG47: -0.04
A48: Asphalt and Road Oil | B48: Industrial: Energy Use: Excluding Refining: Asphalt and Road Oil: High Zero-Carbon Technology Cost | C48: AEO.2025.HIGHZTC.CNSM_NA_IDAL_IDEI_ARO_NA_USA_QBTU.A | D48: quads | F48: 0.877838 | G48: 0.878262 | H48: 0.886157 | I48: 0.903224 | J48: 0.905428 | K48: 0.911496 | L48: 0.918598 | M48: 0.924407 | N48: 0.921001 | O48: 0.922841 | P48: 0.924252 | Q48: 0.928084 | R48: 0.931994 | S48: 0.934567 | T48: 0.937317 | U48: 0.940415 | V48: 0.943471 | W48: 0.945335 | X48: 0.945887 | Y48: 0.947661 | Z48: 0.948485 | AA48: 0.950643 | AB48: 0.954573 | AC48: 0.955311 | AD48: 0.955716 | AE48: 0.956251 | AF48: 0.95571 | AG48: 0.003
A49: Miscellaneous Petroleum | B49: Industrial: Energy Use: Excluding Refining: Miscellaneous Petroleum: High Zero-Carbon Technology Cost | C49: AEO.2025.HIGHZTC.CNSM_NA_IDAL_IDEI_MPET_NA_USA_QBTU.A | D49: quads | F49: 0.309378 | G49: 0.328623 | H49: 0.342637 | I49: 0.357038 | J49: 0.370456 | K49: 0.383074 | L49: 0.396238 | M49: 0.409119 | N49: 0.420807 | O49: 0.43005 | P49: 0.439309 | Q49: 0.446838 | R49: 0.451958 | S49: 0.456283 | T49: 0.460827 | U49: 0.465389 | V49: 0.470238 | W49: 0.474359 | X49: 0.478482 | Y49: 0.481599 | Z49: 0.484916 | AA49: 0.488158 | AB49: 0.491589 | AC49: 0.496293 | AD49: 0.50039 | AE49: 0.504026 | AF49: 0.506913 | AG49: 0.019
A50: Petroleum and Other Liquids Subtotal | B50: Industrial: Energy Use: Excluding Refining: Petroleum Subtotal: High Zero-Carbon Technology Cost | C50: AEO.2025.HIGHZTC.CNSM_NA_IDAL_IDEI_PET_NA_USA_QBTU.A | D50: quads | F50: 6.619549 | G50: 6.680323 | H50: 6.912992 | I50: 6.962838 | J50: 7.004356 | K50: 7.052031 | L50: 7.09457 | M50: 7.130203 | N50: 7.155908 | O50: 7.1768 | P50: 7.192731 | Q50: 7.211684 | R50: 7.230889 | S50: 7.24157 | T50: 7.287822 | U50: 7.373284 | V50: 7.466155 | W50: 7.539543 | X50: 7.615656 | Y50: 7.672621 | Z50: 7.802835 | AA50: 7.926186 | AB50: 7.985898 | AC50: 8.078075 | AD50: 8.14815 | AE50: 8.263169 | AF50: 8.373507 | AG50: 0.009
A51: Natural Gas Heat and Power | B51: Industrial: Energy Use: Excluding Refining: Natural Gas Heat and Power: High Zero-Carbon Technology Cost | C51: AEO.2025.HIGHZTC.CNSM_NA_IDAL_IDEI_NHP_NA_USA_QBTU.A | D51: quads | F51: 6.213014 | G51: 6.289489 | H51: 6.332743 | I51: 6.344821 | J51: 6.37491 | K51: 6.392155 | L51: 6.42648 | M51: 6.458994 | N51: 6.465123 | O51: 6.435061 | P51: 6.419324 | Q51: 6.403265 | R51: 6.3917 | S51: 6.399674 | T51: 6.425906 | U51: 6.460387 | V51: 6.495418 | W51: 6.515205 | X51: 6.535622 | Y51: 6.554292 | Z51: 6.579194 | AA51: 6.598233 | AB51: 6.619295 | AC51: 6.656179 | AD51: 6.685795 | AE51: 6.706171 | AF51: 6.72133 | AG51: 0.003
A52: Natural Gas Feedstocks | B52: Industrial: Energy Use: Excluding Refining: Natural Gas Feedstocks: High Zero-Carbon Technology Cost | C52: AEO.2025.HIGHZTC.CNSM_NA_IDAL_IDEI_NGF_NA_USA_QBTU.A | D52: quads | F52: 0.2663 | G52: 0.302 | H52: 0.282443 | I52: 0.274513 | J52: 0.266967 | K52: 0.264995 | L52: 0.262831 | M52: 0.267202 | N52: 0.289189 | O52: 0.287614 | P52: 0.29199 | Q52: 0.297377 | R52: 0.301545 | S52: 0.31213 | T52: 0.323549 | U52: 0.334959 | V52: 0.34501 | W52: 0.350901 | X52: 0.356068 | Y52: 0.361999 | Z52: 0.368496 | AA52: 0.374646 | AB52: 0.378679 | AC52: 0.384896 | AD52: 0.389878 | AE52: 0.392776 | AF52: 0.39716 | AG52: 0.015
A53: Lease and Plant Fuel | B53: Industrial: Energy Use: Excluding Refining: Lease and Plant Fuel: High Zero-Carbon Technology Cost | C53: AEO.2025.HIGHZTC.CNSM_NA_IDAL_IDEI_LSAPFL_NA_USA_QBTU.A | D53: quads | F53: 2.045295 | G53: 2.052198 | H53: 2.151558 | I53: 2.160423 | J53: 2.206005 | K53: 2.226782 | L53: 2.238047 | M53: 2.23259 | N53: 2.285561 | O53: 2.298938 | P53: 2.313583 | Q53: 2.305008 | R53: 2.296317 | S53: 2.271652 | T53: 2.265647 | U53: 2.24652 | V53: 2.25015 | W53: 2.26053 | X53: 2.271182 | Y53: 2.275658 | Z53: 2.278661 | AA53: 2.28227 | AB53: 2.29152 | AC53: 2.301058 | AD53: 2.305694 | AE53: 2.311272 | AF53: 2.318181 | AG53: 0.005
A54: Natural Gas Subtotal | B54: Industrial: Energy Use: Excluding Refining: Natural Gas Subtotal: High Zero-Carbon Technology Cost | C54: AEO.2025.HIGHZTC.CNSM_NA_IDAL_IDEI_NGS_NA_USA_QBTU.A | D54: quads | F54: 8.52461 | G54: 8.643687 | H54: 8.766745 | I54: 8.779757 | J54: 8.847881 | K54: 8.883932 | L54: 8.927358 | M54: 8.958786 | N54: 9.039873 | O54: 9.021612 | P54: 9.024898 | Q54: 9.00565 | R54: 8.989562 | S54: 8.983457 | T54: 9.015101 | U54: 9.041866 | V54: 9.090578 | W54: 9.126637 | X54: 9.162871 | Y54: 9.19195 | Z54: 9.226351 | AA54: 9.255148 | AB54: 9.289494 | AC54: 9.342133 | AD54: 9.381367 | AE54: 9.410219 | AF54: 9.43667 | AG54: 0.004
... A64: Total | B64: Industrial: Energy Use: Excluding Refining: Total: High Zero-Carbon Technology Cost | C64: AEO.2025.HIGHZTC.CNSM_NA_IDAL_IDEI_TOT_NA_USA_QBTU.A | D64: quads | F64: 25.889074 | G64: 26.098766 | H64: 26.328085 | I64: 26.277851 | J64: 26.330227 | K64: 26.421551 | L64: 26.471388 | M64: 26.564415 | N64: 26.615934 | O64: 26.674561 | P64: 26.809347 | Q64: 26.885712 | R64: 26.945147 | S64: 26.934441 | T64: 27.032976 | U64: 27.064486 | V64: 27.288336 | W64: 27.500862 | X64: 27.710382 | Y64: 27.852989 | Z64: 28.086958 | AA64: 28.290026 | AB64: 28.440632 | AC64: 28.667852 | AD64: 28.850975 | AE64: 29.079557 | AF64: 29.264708 | AG64: 0.005
A65: Refining Consumption
A66: Propane Heat and Power | B66: Industrial: Refining Use: Propane Heat and Power: High Zero-Carbon Technology Cost | C66: AEO.2025.HIGHZTC.CNSM_NA_IDAL_REFU_LPGHP_NA_USA_QBTU.A | D66: quads | F66: 0.006789 | G66: 0.006789 | H66: 0 | I66: 0 | J66: 0 | K66: 0 | L66: 0 | M66: 0 | N66: 0 | O66: 0 | P66: 0 | Q66: 0 | R66: 0 | S66: 0 | T66: 0 | U66: 0 | V66: 0 | W66: 0 | X66: 0 | Y66: 0 | Z66: 0 | AA66: 0 | AB66: 0 | AC66: 0 | AD66: 0 | AE66: 0 | AF66: 0 | AG66: -1
A67: Distillate Fuel Oil | B67: Industrial: Refining Use: Distillate Fuel Oil: High Zero-Carbon Technology Cost | C67: AEO.2025.HIGHZTC.CNSM_NA_IDAL_REFU_DFO_NA_USA_QBTU.A | D67: quads | F67: 0.001574 | G67: 0.001574 | H67: 0 | I67: 0 | J67: 0 | K67: 0 | L67: 0 | M67: 0 | N67: 0 | O67: 0 | P67: 0 | Q67: 0 | R67: 0 | S67: 0 | T67: 0 | U67: 0 | V67: 0 | W67: 0 | X67: 0 | Y67: 0 | Z67: 0 | AA67: 0 | AB67: 0 | AC67: 0 | AD67: 0 | AE67: 0 | AF67: 0 | AG67: -1
A68: Residual Fuel Oil | B68: Industrial: Refining Use: Residual Fuel Oil: High Zero-Carbon Technology Cost | C68: AEO.2025.HIGHZTC.CNSM_NA_IDAL_REFU_RFO_NA_USA_QBTU.A | D68: quads | F68: 0.000288 | G68: 0.000288 | H68: 0 | I68: 0 | J68: 0 | K68: 0 | L68: 0 | M68: 0 | N68: 0 | O68: 0 | P68: 0 | Q68: 0 | R68: 0 | S68: 0 | T68: 0 | U68: 0 | V68: 0 | W68: 0 | X68: 0 | Y68: 0 | Z68: 0 | AA68: 0 | AB68: 0 | AC68: 0 | AD68: 0 | AE68: 0 | AF68: 0 | AG68: -1
A69: Petroleum Coke | B69: Industrial: Refining Use: Petroleum Coke: High Zero-Carbon Technology Cost | C69: AEO.2025.HIGHZTC.CNSM_NA_IDAL_REFU_PCK_NA_USA_QBTU.A | D69: quads | F69: 0.451 | G69: 0.474 | H69: 0.484495 | I69: 0.487048 | J69: 0.48873 | K69: 0.488317 | L69: 0.488519 | M69: 0.486516 | N69: 0.478378 | O69: 0.477729 | P69: 0.476476 | Q69: 0.471355 | R69: 0.471853 | S69: 0.470069 | T69: 0.462492 | U69: 0.460415 | V69: 0.463848 | W69: 0.457426 | X69: 0.449132 | Y69: 0.455471 | Z69: 0.453882 | AA69: 0.451971 | AB69: 0.451586 | AC69: 0.455616 | AD69: 0.456846 | AE69: 0.451523 | AF69: 0.449541 | AG69: 0
A70: Still Gas | B70: Industrial: Refining Use: Still Gas: High Zero-Carbon Technology Cost | C70: AEO.2025.HIGHZTC.CNSM_NA_IDAL_REFU_SLG_NA_USA_QBTU.A | D70: quads | F70: 1.391026 | G70: 1.391026 | H70: 1.321003 | I70: 1.31785 | J70: 1.348322 | K70: 1.323102 | L70: 1.339976 | M70: 1.343422 | N70: 1.344145 | O70: 1.321252 | P70: 1.322574 | Q70: 1.309428 | R70: 1.321005 | S70: 1.322053 | T70: 1.322975 | U70: 1.327446 | V70: 1.332115 | W70: 1.334623 | X70: 1.318845 | Y70: 1.333938 | Z70: 1.330232 | AA70: 1.329636 | AB70: 1.334931 | AC70: 1.344992 | AD70: 1.33997 | AE70: 1.337579 | AF70: 1.324381 | AG70: -0.002
A71: Miscellaneous Petroleum | B71: Industrial: Refining Use: Miscellaneous Petroleum: High Zero-Carbon Technology Cost | C71: AEO.2025.HIGHZTC.CNSM_NA_IDAL_REFU_MPET_NA_USA_QBTU.A | D71: quads | F71: 0.006113 | G71: 0.006113 | H71: 0.0071 | I71: 0.007196 | J71: 0.007729 | K71: 0.00858 | L71: 0.007789 | M71: 0.007072 | N71: 0.007187 | O71: 0.007764 | P71: 0.011374 | Q71: 0.018034 | R71: 0.012482 | S71: 0.012439 | T71: 0.013728 | U71: 0.013953 | V71: 0.015202 | W71: 0.020933 | X71: 0.028912 | Y71: 0.018712 | Z71: 0.019775 | AA71: 0.01584 | AB71: 0.015888 | AC71: 0.01468 | AD71: 0.013945 | AE71: 0.014054 | AF71: 0.013451 | AG71: 0.031
A72: Petroleum and Other Liquids Subtotal | B72: Industrial: Refining Use: Petroleum Subtotal: High Zero-Carbon Technology Cost | C72: AEO.2025.HIGHZTC.CNSM_NA_IDAL_REFU_PET_NA_USA_QBTU.A | D72: quads | F72: 1.85679 | G72: 1.87979 | H72: 1.812598 | I72: 1.812094 | J72: 1.844781 | K72: 1.819998 | L72: 1.836284 | M72: 1.83701 | N72: 1.82971 | O72: 1.806744 | P72: 1.810424 | Q72: 1.798818 | R72: 1.80534 | S72: 1.804562 | T72: 1.799196 | U72: 1.801813 | V72: 1.811164 | W72: 1.812983 | X72: 1.796888 | Y72: 1.808121 | Z72: 1.803889 | AA72: 1.797447 | AB72: 1.802406 | AC72: 1.815288 | AD72: 1.810762 | AE72: 1.803156 | AF72: 1.787373 | AG72: -0.001
A73: Natural Gas Heat and Power | B73: Industrial: Refining Use: Natural Gas Heat and Power: High Zero-Carbon Technology Cost | C73: AEO.2025.HIGHZTC.CNSM_NA_IDAL_REFU_NHP_NA_USA_QBTU.A | D73: quads | F73: 1.323966 | G73: 1.323966 | H73: 1.070948 | I73: 1.06938 | J73: 1.050334 | K73: 1.054281 | L73: 1.036882 | M73: 1.035419 | N73: 1.017276 | O73: 1.017196 | P73: 0.994681 | Q73: 0.97752 | R73: 0.972469 | S73: 0.955077 | T73: 0.949427 | U73: 0.946635 | V73: 0.944733 | W73: 0.932018 | X73: 0.92334 | Y73: 0.936078 | Z73: 0.924873 | AA73: 0.921697 | AB73: 0.922375 | AC73: 0.931246 | AD73: 0.934524 | AE73: 0.942062 | AF73: 0.943912 | AG73: -0.013
A74: Hydrogen Consumed as Feedstocks | B74: Industrial: Refining Use: Hydrogen Feedstocks: High Zero-Carbon Technology Cost | C74: AEO.2025.HIGHZTC.CNSM_NA_IDAL_REFU_H2FEEDSTK_NA_USA_QBTU.A | D74: quads | F74: 0.517 | G74: 0.517 | H74: 0.517 | I74: 0.517 | J74: 0.517 | K74: 0.513853 | L74: 0.517 | M74: 0.517 | N74: 0.517 | O74: 0.517 | P74: 0.517 | Q74: 0.517 | R74: 0.517 | S74: 0.517 | T74: 0.517 | U74: 0.517 | V74: 0.517 | W74: 0.517 | X74: 0.517 | Y74: 0.517 | Z74: 0.517 | AA74: 0.517 | AB74: 0.517 | AC74: 0.517 | AD74: 0.517 | AE74: 0.517 | AF74: 0.517 | AG74: 0
A75: Steam Coal | B75: Industrial: Refining Use: Other Industrial Coal: High Zero-Carbon Technology Cost | C75: AEO.2025.HIGHZTC.CNSM_NA_IDAL_REFU_OIC_NA_USA_QBTU.A | D75: quads | F75: 0.124711 | G75: 0.124711 | H75: 0.124711 | I75: 0.124711 | J75: 0.124711 | K75: 0.124711 | L75: 0.124711 | M75: 0.124711 | N75: 0.124711 | O75: 0.124711 | P75: 0.124711 | Q75: 0.124711 | R75: 0.124711 | S75: 0.124711 | T75: 0.124711 | U75: 0.124711 | V75: 0.124711 | W75: 0.124711 | X75: 0.124711 | Y75: 0.124711 | Z75: 0.124711 | AA75: 0.124711 | AB75: 0.124711 | AC75: 0.124711 | AD75: 0.124711 | AE75: 0.124711 | AF75: 0.124711 | AG75: 0
A76: Biofuels Heat and Coproducts | B76: Industrial: Refining Use: Biofuels Heat and Coproducts: High Zero-Carbon Technology Cost | C76: AEO.2025.HIGHZTC.CNSM_NA_IDAL_REFU_BFH_NA_USA_QBTU.A | D76: quads | F76: 0.894331 | G76: 0.916568 | H76: 0.914158 | I76: 0.914463 | J76: 0.913182 | K76: 0.908272 | L76: 0.903837 | M76: 0.892968 | N76: 0.883689 | O76: 0.868351 | P76: 0.853619 | Q76: 0.83833 | R76: 0.828071 | S76: 0.811011 | T76: 0.79575 | U76: 0.784349 | V76: 0.782166 | W76: 0.771797 | X76: 0.761696 | Y76: 0.755206 | Z76: 0.753325 | AA76: 0.75422 | AB76: 0.751773 | AC76: 0.751816 | AD76: 0.75012 | AE76: 0.752011 | AF76: 0.755675 | AG76: -0.006
A77: Purchased Electricity | B77: Industrial: Refining Use: Purchased Electricity: High Zero-Carbon Technology Cost | C77: AEO.2025.HIGHZTC.CNSM_NA_IDAL_REFU_PRC_NA_USA_QBTU.A | D77: quads | F77: 0.178516 | G77: 0.178516 | H77: 0.176154 | I77: 0.176112 | J77: 0.176107 | K77: 0.175114 | L77: 0.174827 | M77: 0.17377 | N77: 0.171946 | O77: 0.170422 | P77: 0.168709 | Q77: 0.165856 | R77: 0.165527 | S77: 0.163066 | T77: 0.160524 | U77: 0.160592 | V77: 0.160063 | W77: 0.15809 | X77: 0.156531 | Y77: 0.158886 | Z77: 0.156683 | AA77: 0.155812 | AB77: 0.155658 | AC77: 0.15729 | AD77: 0.157314 | AE77: 0.15673 | AF77: 0.156028 | AG77: -0.005
... A81: Total | B81: Industrial: Refining Use: Total: High Zero-Carbon Technology Cost | C81: AEO.2025.HIGHZTC.CNSM_NA_IDAL_REFU_TOT_NA_USA_QBTU.A | D81: quads | F81: 5.297298 | G81: 5.334639 | H81: 4.994009 | I81: 4.984343 | J81: 4.991287 | K81: 4.95592 | L81: 4.94565 | M81: 4.926788 | N81: 4.877632 | O81: 4.834194 | P81: 4.793511 | Q81: 4.73945 | R81: 4.724513 | S81: 4.676251 | T81: 4.640505 | U81: 4.621018 | V81: 4.62309 | W81: 4.59837 | X81: 4.560313 | Y81: 4.581173 | Z81: 4.559504 | AA81: 4.547963 | AB81: 4.549151 | AC81: 4.571927 | AD81: 4.568469 | AE81: 4.567237 | AF81: 4.55485 | AG81: -0.006
A82: Hydrogen Production-Related Consumption (quadrillon Btu)
A83: Natural Gas Heat and Power | B83: Industrial: Hydrogen Production: Natural Gas Heat and Power: High Zero-Carbon Technology Cost | C83: AEO.2025.HIGHZTC.CNSM_NA_IDAL_H2PROD_NHP_NA_NA_QBTU.A | D83: quads | F83: 0.1554 | G83: 0.158069 | H83: 0.162681 | I83: 0.164978 | J83: 0.166338 | K83: 0.16833 | L83: 0.172452 | M83: 0.179122 | N83: 0.191896 | O83: 0.204111 | P83: 0.215582 | Q83: 0.22636 | R83: 0.236496 | S83: 0.245345 | T83: 0.253655 | U83: 0.261267 | V83: 0.268511 | W83: 0.275478 | X83: 0.281662 | Y83: 0.287842 | Z83: 0.294341 | AA83: 0.300284 | AB83: 0.304832 | AC83: 0.308259 | AD83: 0.311781 | AE83: 0.314671 | AF83: 0.318126 | AG83: 0.028
A84: Natural Gas Feedstocks | B84: Industrial: Hydrogen Production: Natural Gas Feedstocks: High Zero-Carbon Technology Cost | C84: AEO.2025.HIGHZTC.CNSM_NA_IDAL_H2PROD_NGF_NA_NA_QBTU.A | D84: quads | F84: 0.905083 | G84: 0.920633 | H84: 0.947294 | I84: 0.96065 | J84: 0.968563 | K84: 0.980142 | L84: 1.004125 | M84: 1.042939 | N84: 1.117155 | O84: 1.187979 | P84: 1.254479 | Q84: 1.316905 | R84: 1.375955 | S84: 1.42774 | T84: 1.476365 | U84: 1.520743 | V84: 1.56296 | W84: 1.603553 | X84: 1.639647 | Y84: 1.675705 | Z84: 1.713717 | AA84: 1.748545 | AB84: 1.775204 | AC84: 1.795358 | AD84: 1.815876 | AE84: 1.833248 | AF84: 1.85338 | AG84: 0.028
A85: Natural Gas Subtotal | B85: Industrial: Hydrogen Production: Natural Gas Subtotal: High Zero-Carbon Technology Cost | C85: AEO.2025.HIGHZTC.CNSM_NA_IDAL_H2PROD_NGS_NA_NA_QBTU.A | D85: quads | F85: 1.060482 | G85: 1.078702 | H85: 1.109975 | I85: 1.125627 | J85: 1.134902 | K85: 1.148471 | L85: 1.176577 | M85: 1.222061 | N85: 1.309051 | O85: 1.39209 | P85: 1.470061 | Q85: 1.543266 | R85: 1.61245 | S85: 1.673084 | T85: 1.73002 | U85: 1.78201 | V85: 1.831471 | W85: 1.879031 | X85: 1.921309 | Y85: 1.963548 | Z85: 2.008058 | AA85: 2.04883 | AB85: 2.080037 | AC85: 2.103617 | AD85: 2.127657 | AE85: 2.147919 | AF85: 2.171506 | AG85: 0.028
A86: Purchased Electricity | B86: Industrial: Hydrogen Production: Purchased Electricity: High Zero-Carbon Technology Cost | C86: AEO.2025.HIGHZTC.CNSM_NA_IDAL_H2PROD_PRC_NA_NA_QBTU.A | D86: quads | F86: 0.003649 | G86: 0.003693 | H86: 0.004606 | I86: 0.00474 | J86: 0.004824 | K86: 0.004945 | L86: 0.00514 | M86: 0.005446 | N86: 0.006487 | O86: 0.008055 | P86: 0.009578 | Q86: 0.011226 | R86: 0.011394 | S86: 0.010609 | T86: 0.009896 | U86: 0.009901 | V86: 0.009976 | W86: 0.010061 | X86: 0.009907 | Y86: 0.009796 | Z86: 0.009301 | AA86: 0.008584 | AB86: 0.008001 | AC86: 0.007289 | AD86: 0.007356 | AE86: 0.005232 | AF86: 0.00529 | AG86: 0.014
A87: Delivered Energy | B87: Industrial: Hydrogen Production: Delivered Energy: High Zero-Carbon Technology Cost | C87: AEO.2025.HIGHZTC.CNSM_NA_IDAL_H2PROD_DELE_NA_NA_QBTU.A | D87: quads | F87: 1.064131 | G87: 1.082395 | H87: 1.114581 | I87: 1.130368 | J87: 1.139726 | K87: 1.153416 | L87: 1.181717 | M87: 1.227507 | N87: 1.315538 | O87: 1.400145 | P87: 1.479639 | Q87: 1.554492 | R87: 1.623845 | S87: 1.683693 | T87: 1.739916 | U87: 1.791911 | V87: 1.841447 | W87: 1.889092 | X87: 1.931216 | Y87: 1.973344 | Z87: 2.017359 | AA87: 2.057414 | AB87: 2.088038 | AC87: 2.110907 | AD87: 2.135013 | AE87: 2.153151 | AF87: 2.176796 | AG87: 0.028
A88: Electricity-Related Losses | B88: Industrial: Hydrogen Production: Electricity-Related Losses: High Zero-Carbon Technology Cost | C88: AEO.2025.HIGHZTC.CNSM_NA_IDAL_H2PROD_ELECRELOS_NA_NA_QBTU.A | D88: quads | F88: 0.005186 | G88: 0.00509 | H88: 0.00597 | I88: 0.005909 | J88: 0.005881 | K88: 0.005922 | L88: 0.005908 | M88: 0.00606 | N88: 0.006751 | O88: 0.00811 | P88: 0.009294 | Q88: 0.010416 | R88: 0.010122 | S88: 0.008932 | T88: 0.008069 | U88: 0.007589 | V88: 0.007509 | W88: 0.007556 | X88: 0.007424 | Y88: 0.007291 | Z88: 0.006886 | AA88: 0.006285 | AB88: 0.005792 | AC88: 0.005235 | AD88: 0.005256 | AE88: 0.003727 | AF88: 0.003728 | AG88: -0.013
A89: Total | B89: Industrial: Hydrogen Production: Total: High Zero-Carbon Technology Cost | C89: AEO.2025.HIGHZTC.CNSM_NA_IDAL_H2PROD_TOT_NA_NA_QBTU.A | D89: quads | F89: 1.069317 | G89: 1.087484 | H89: 1.120551 | I89: 1.136277 | J89: 1.145607 | K89: 1.159338 | L89: 1.187625 | M89: 1.233567 | N89: 1.322288 | O89: 1.408255 | P89: 1.488933 | Q89: 1.564908 | R89: 1.633967 | S89: 1.692625 | T89: 1.747985 | U89: 1.799499 | V89: 1.848956 | W89: 1.896648 | X89: 1.93864 | Y89: 1.980635 | Z89: 2.024245 | AA89: 2.063699 | AB89: 2.093829 | AC89: 2.116142 | AD89: 2.14027 | AE89: 2.156878 | AF89: 2.180524 | AG89: 0.028
A90: Industrial Sector End-Use Consumption Excluding Hydrogen Production
A91: Propane Heat and Power | B91: Industrial: Total Industrial Sector Use Excluding H2 Production: Propane Heat and Power: High Zero-Carbon Technology Cost | C91: AEO.2025.HIGHZTC.CNSM_NA_IDAL_NA_LPGHP_NA_USA_QBTU.A | D91: quads | F91: 0.064334 | G91: 0.122289 | H91: 0.116488 | I91: 0.117768 | J91: 0.118981 | K91: 0.120806 | L91: 0.122225 | M91: 0.123407 | N91: 0.125766 | O91: 0.126346 | P91: 0.127184 | Q91: 0.128271 | R91: 0.129641 | S91: 0.131156 | T91: 0.132603 | U91: 0.133936 | V91: 0.135029 | W91: 0.135651 | X91: 0.136466 | Y91: 0.13723 | Z91: 0.138026 | AA91: 0.139073 | AB91: 0.140203 | AC91: 0.141396 | AD91: 0.142557 | AE91: 0.143824 | AF91: 0.144934 | AG91: 0.032
A92: Hydrocarbon Gas Liquid Feedstocks | B92: Industrial: Total Industrial Sector Use Excluding H2 Production: LPG and Other Feedstocks: High Zero-Carbon Technology Cost | C92: AEO.2025.HIGHZTC.CNSM_NA_IDAL_NA_LPGF_NA_USA_QBTU.A | D92: quads | F92: 3.485 | G92: 3.489802 | H92: 3.49178 | I92: 3.495489 | J92: 3.500911 | K92: 3.505162 | L92: 3.508227 | M92: 3.509183 | N92: 3.509037 | O92: 3.509996 | P92: 3.505924 | Q92: 3.501432 | R92: 3.498329 | S92: 3.492201 | T92: 3.520821 | U92: 3.588347 | V92: 3.662664 | W92: 3.722698 | X92: 3.785018 | Y92: 3.828975 | Z92: 3.800663 | AA92: 3.760822 | AB92: 3.798597 | AC92: 3.870811 | AD92: 3.923123 | AE92: 3.895189 | AF92: 3.866342 | AG92: 0.004
A93: Motor Gasoline | B93: Industrial: Total Industrial Sector Use Excluding H2 Production: Motor Gasoline: High Zero-Carbon Technology Cost | C93: AEO.2025.HIGHZTC.CNSM_NA_IDAL_NA_MGS_NA_USA_QBTU.A | D93: quads | F93: 0.281291 | G93: 0.285247 | H93: 0.288387 | I93: 0.292239 | J93: 0.297109 | K93: 0.302658 | L93: 0.307115 | M93: 0.310404 | N93: 0.313444 | O93: 0.31532 | P93: 0.316919 | Q93: 0.319351 | R93: 0.322235 | S93: 0.32399 | T93: 0.3259 | U93: 0.327691 | V93: 0.329586 | W93: 0.33104 | X93: 0.333046 | Y93: 0.334606 | Z93: 0.336343 | AA93: 0.339079 | AB93: 0.342198 | AC93: 0.345227 | AD93: 0.348264 | AE93: 0.351611 | AF93: 0.3547 | AG93: 0.009
A94: Distillate Fuel Oil | B94: Industrial: Total Industrial Sector Use Excluding H2 Production: Distillate Fuel Oil: High Zero-Carbon Technology Cost | C94: AEO.2025.HIGHZTC.CNSM_NA_IDAL_NA_DFO_NA_USA_QBTU.A | D94: quads | F94: 1.140013 | G94: 1.15177 | H94: 1.163439 | I94: 1.177088 | J94: 1.195205 | K94: 1.216104 | L94: 1.23274 | M94: 1.246904 | N94: 1.260956 | O94: 1.269289 | P94: 1.277959 | Q94: 1.288505 | R94: 1.299513 | S94: 1.308196 | T94: 1.317186 | U94: 1.324638 | V94: 1.332429 | W94: 1.337751 | X94: 1.344097 | Y94: 1.349923 | Z94: 1.356099 | AA94: 1.364485 | AB94: 1.374968 | AC94: 1.385294 | AD94: 1.394428 | AE94: 1.405687 | AF94: 1.41575 | AG94: 0.008
A95: Residual Fuel Oil | B95: Industrial: Total Industrial Sector Use Excluding H2 Production: Residual Fuel Oil: High Zero-Carbon Technology Cost | C95: AEO.2025.HIGHZTC.CNSM_NA_IDAL_NA_RFO_NA_USA_QBTU.A | D95: quads | F95: 0.041174 | G95: 0.04198 | H95: 0.041255 | I95: 0.040061 | J95: 0.038841 | K95: 0.037551 | L95: 0.036369 | M95: 0.035532 | N95: 0.035132 | O95: 0.03466 | P95: 0.034279 | Q95: 0.033786 | R95: 0.033265 | S95: 0.032701 | T95: 0.032198 | U95: 0.031759 | V95: 0.031438 | W95: 0.031172 | X95: 0.030896 | Y95: 0.030629 | Z95: 0.03044 | AA95: 0.03024 | AB95: 0.029949 | AC95: 0.029728 | AD95: 0.029473 | AE95: 0.029252 | AF95: 0.028857 | AG95: -0.014
A96: Petrochemical Feedstocks | B96: Industrial: Total Industrial Sector Use Excluding H2 Production: Petrochemical Feedstocks: High Zero-Carbon Technology Cost | C96: AEO.2025.HIGHZTC.CNSM_NA_IDAL_NA_PCF_NA_USA_QBTU.A | D96: quads | F96: 0.390525 | G96: 0.355 | H96: 0.55 | I96: 0.55 | J96: 0.55 | K96: 0.55 | L96: 0.55 | M96: 0.55 | N96: 0.55 | O96: 0.55 | P96: 0.55 | Q96: 0.55 | R96: 0.55 | S96: 0.55 | T96: 0.55 | U96: 0.55 | V96: 0.55 | W96: 0.55 | X96: 0.55 | Y96: 0.55 | Z96: 0.69558 | AA96: 0.84116 | AB96: 0.84116 | AC96: 0.84116 | AD96: 0.84116 | AE96: 0.964095 | AF96: 1.087029 | AG96: 0.04
A97: Petroleum Coke | B97: Industrial: Total Industrial Sector Use Excluding H2 Production: Petroleum Coke: High Zero-Carbon Technology Cost | C97: AEO.2025.HIGHZTC.CNSM_NA_IDAL_NA_PCK_NA_USA_QBTU.A | D97: quads | F97: 0.489646 | G97: 0.51 | H97: 0.517343 | I97: 0.516978 | J97: 0.516155 | K97: 0.513497 | L97: 0.511575 | M97: 0.507761 | N97: 0.498141 | O97: 0.496027 | P97: 0.493382 | Q97: 0.486771 | R97: 0.485807 | S97: 0.482546 | T97: 0.473462 | U97: 0.471524 | V97: 0.475148 | W97: 0.468962 | X97: 0.460895 | Y97: 0.467468 | Z97: 0.466162 | AA97: 0.464497 | AB97: 0.464247 | AC97: 0.468472 | AD97: 0.469885 | AE97: 0.464757 | AF97: 0.462812 | AG97: -0.002
A98: Asphalt and Road Oil | B98: Industrial: Total Industrial Sector Use Excluding H2 Production: Asphalt and Road Oil: High Zero-Carbon Technology Cost | C98: AEO.2025.HIGHZTC.CNSM_NA_IDAL_NA_ARO_NA_USA_QBTU.A | D98: quads | F98: 0.877838 | G98: 0.878262 | H98: 0.886157 | I98: 0.903224 | J98: 0.905428 | K98: 0.911496 | L98: 0.918598 | M98: 0.924407 | N98: 0.921001 | O98: 0.922841 | P98: 0.924252 | Q98: 0.928084 | R98: 0.931994 | S98: 0.934567 | T98: 0.937317 | U98: 0.940415 | V98: 0.943471 | W98: 0.945335 | X98: 0.945887 | Y98: 0.947661 | Z98: 0.948485 | AA98: 0.950643 | AB98: 0.954573 | AC98: 0.955311 | AD98: 0.955716 | AE98: 0.956251 | AF98: 0.95571 | AG98: 0.003
A99: Still Gas | B99: Industrial: Total Industrial Sector Use Excluding H2 Production: Still Gas: High Zero-Carbon Technology Cost | C99: AEO.2025.HIGHZTC.CNSM_NA_IDAL_NA_SLG_NA_USA_QBTU.A | D99: quads | F99: 1.391026 | G99: 1.391026 | H99: 1.321003 | I99: 1.31785 | J99: 1.348322 | K99: 1.323102 | L99: 1.339976 | M99: 1.343422 | N99: 1.344145 | O99: 1.321252 | P99: 1.322574 | Q99: 1.309428 | R99: 1.321005 | S99: 1.322053 | T99: 1.322975 | U99: 1.327446 | V99: 1.332115 | W99: 1.334623 | X99: 1.318845 | Y99: 1.333938 | Z99: 1.330232 | AA99: 1.329636 | AB99: 1.334931 | AC99: 1.344992 | AD99: 1.33997 | AE99: 1.337579 | AF99: 1.324381 | AG99: -0.002
A100: Miscellaneous Petroleum | B100: Industrial: Total Industrial Sector Use Excluding H2 Production: Miscellaneous Petroleum: High Zero-Carbon Technology Cost | C100: AEO.2025.HIGHZTC.CNSM_NA_IDAL_NA_MPET_NA_USA_QBTU.A | D100: quads | F100: 0.315491 | G100: 0.334736 | H100: 0.349737 | I100: 0.364234 | J100: 0.378184 | K100: 0.391654 | L100: 0.404027 | M100: 0.416191 | N100: 0.427995 | O100: 0.437814 | P100: 0.450684 | Q100: 0.464872 | R100: 0.46444 | S100: 0.468722 | T100: 0.474556 | U100: 0.479341 | V100: 0.485439 | W100: 0.495292 | X100: 0.507394 | Y100: 0.500311 | Z100: 0.504691 | AA100: 0.503998 | AB100: 0.507477 | AC100: 0.510973 | AD100: 0.514335 | AE100: 0.51808 | AF100: 0.520364 | AG100: 0.019
A101: Petroleum and Other Liquids Subtotal | B101: Industrial: Total Industrial Sector Use Excluding H2 Production: Petroleum Subtotal: High Zero-Carbon Technology Cost | C101: AEO.2025.HIGHZTC.CNSM_NA_IDAL_NA_PET_NA_USA_QBTU.A | D101: quads | F101: 8.476339 | G101: 8.560114 | H101: 8.72559 | I101: 8.774933 | J101: 8.849136 | K101: 8.872029 | L101: 8.930853 | M101: 8.967213 | N101: 8.985618 | O101: 8.983544 | P101: 9.003156 | Q101: 9.010502 | R101: 9.036229 | S101: 9.046132 | T101: 9.087017 | U101: 9.175098 | V101: 9.277319 | W101: 9.352524 | X101: 9.412545 | Y101: 9.480742 | Z101: 9.606724 | AA101: 9.723633 | AB101: 9.788303 | AC101: 9.893365 | AD101: 9.958912 | AE101: 10.066326 | AF101: 10.16088 | AG101: 0.007
A102: Natural Gas Heat and Power | B102: Industrial: Total Industrial Sector Use Excluding H2 Production: Natural Gas Heat and Power: High Zero-Carbon Technology Cost | C102: AEO.2025.HIGHZTC.CNSM_NA_IDAL_NA_NHP_NA_USA_QBTU.A | D102: quads | F102: 7.53698 | G102: 7.613454 | H102: 7.403691 | I102: 7.414203 | J102: 7.425244 | K102: 7.446435 | L102: 7.463361 | M102: 7.494413 | N102: 7.4824 | O102: 7.452256 | P102: 7.414006 | Q102: 7.380784 | R102: 7.36417 | S102: 7.354751 | T102: 7.375332 | U102: 7.407023 | V102: 7.440151 | W102: 7.447224 | X102: 7.458963 | Y102: 7.49037 | Z102: 7.504067 | AA102: 7.51993 | AB102: 7.54167 | AC102: 7.587425 | AD102: 7.62032 | AE102: 7.648234 | AF102: 7.665242 | AG102: 0.001
... A116: Total | B116: Industrial: Total Industrial Sector Use: Total: High Zero-Carbon Technology Cost | C116: AEO.2025.HIGHZTC.CNSM_NA_IDAL_NA_TOT_NA_USA_QBTU.A | D116: quads | F116: 31.186375 | G116: 31.433406 | H116: 31.322095 | I116: 31.262198 | J116: 31.321515 | K116: 31.377471 | L116: 31.417041 | M116: 31.491202 | N116: 31.493565 | O116: 31.508755 | P116: 31.602858 | Q116: 31.625162 | R116: 31.66966 | S116: 31.61069 | T116: 31.67348 | U116: 31.685504 | V116: 31.911426 | W116: 32.099232 | X116: 32.270695 | Y116: 32.434163 | Z116: 32.646461 | AA116: 32.837991 | AB116: 32.989783 | AC116: 33.239783 | AD116: 33.419444 | AE116: 33.646794 | AF116: 33.81956 | AG116: 0.003
A117: Total Industrial Sector Primary Consumption
A118: Propane Heat and Power | B118: Industrial: Total Industrial Sector Primary Consumption: Propane Heat and Power: High Zero-Carbon Technology Cost | C118: AEO.2025.HIGHZTC.CNSM_NA_IDAL_NA_LPGHP_NA_USA_QBTU.A | D118: quads | F118: 0.064334 | G118: 0.122289 | H118: 0.116488 | I118: 0.117768 | J118: 0.118981 | K118: 0.120806 | L118: 0.122225 | M118: 0.123407 | N118: 0.125766 | O118: 0.126346 | P118: 0.127184 | Q118: 0.128271 | R118: 0.129641 | S118: 0.131156 | T118: 0.132603 | U118: 0.133936 | V118: 0.135029 | W118: 0.135651 | X118: 0.136466 | Y118: 0.13723 | Z118: 0.138026 | AA118: 0.139073 | AB118: 0.140203 | AC118: 0.141396 | AD118: 0.142557 | AE118: 0.143824 | AF118: 0.144934 | AG118: 0.032
A119: Hydrocarbon Gas Liquid Feedstocks | B119: Industrial: Total Industrial Sector Primary Consumption: LPG and Other Feedstocks: High Zero-Carbon Technology Cost | C119: AEO.2025.HIGHZTC.CNSM_NA_IDAL_NA_LPGF_NA_USA_QBTU.A | D119: quads | F119: 3.485 | G119: 3.489802 | H119: 3.49178 | I119: 3.495489 | J119: 3.500911 | K119: 3.505162 | L119: 3.508227 | M119: 3.509183 | N119: 3.509037 | O119: 3.509996 | P119: 3.505924 | Q119: 3.501432 | R119: 3.498329 | S119: 3.492201 | T119: 3.520821 | U119: 3.588347 | V119: 3.662664 | W119: 3.722698 | X119: 3.785018 | Y119: 3.828975 | Z119: 3.800663 | AA119: 3.760822 | AB119: 3.798597 | AC119: 3.870811 | AD119: 3.923123 | AE119: 3.895189 | AF119: 3.866342 | AG119: 0.004
A120: Motor Gasoline | B120: Industrial: Total Industrial Sector Primary Consumption: Motor Gasoline: High Zero-Carbon Technology Cost | C120: AEO.2025.HIGHZTC.CNSM_NA_IDAL_NA_MGS_NA_USA_QBTU.A | D120: quads | F120: 0.281291 | G120: 0.285247 | H120: 0.288387 | I120: 0.292239 | J120: 0.297109 | K120: 0.302658 | L120: 0.307115 | M120: 0.310404 | N120: 0.313444 | O120: 0.31532 | P120: 0.316919 | Q120: 0.319351 | R120: 0.322235 | S120: 0.32399 | T120: 0.3259 | U120: 0.327691 | V120: 0.329586 | W120: 0.33104 | X120: 0.333046 | Y120: 0.334606 | Z120: 0.336343 | AA120: 0.339079 | AB120: 0.342198 | AC120: 0.345227 | AD120: 0.348264 | AE120: 0.351611 | AF120: 0.3547 | AG120: 0.009
A121: Distillate Fuel Oil | B121: Industrial: Total Industrial Sector Primary Consumption: Distillate Fuel Oil: High Zero-Carbon Technology Cost | C121: AEO.2025.HIGHZTC.CNSM_NA_IDAL_NA_DFO_NA_USA_QBTU.A | D121: quads | F121: 1.140013 | G121: 1.15177 | H121: 1.163439 | I121: 1.177088 | J121: 1.195205 | K121: 1.216104 | L121: 1.23274 | M121: 1.246904 | N121: 1.260956 | O121: 1.269289 | P121: 1.277959 | Q121: 1.288505 | R121: 1.299513 | S121: 1.308196 | T121: 1.317186 | U121: 1.324638 | V121: 1.332429 | W121: 1.337751 | X121: 1.344097 | Y121: 1.349923 | Z121: 1.356099 | AA121: 1.364485 | AB121: 1.374968 | AC121: 1.385294 | AD121: 1.394428 | AE121: 1.405687 | AF121: 1.41575 | AG121: 0.008
A122: Residual Fuel Oil | B122: Industrial: Total Industrial Sector Primary Consumption: Residual Fuel Oil: High Zero-Carbon Technology Cost | C122: AEO.2025.HIGHZTC.CNSM_NA_IDAL_NA_RFO_NA_USA_QBTU.A | D122: quads | F122: 0.041174 | G122: 0.04198 | H122: 0.041255 | I122: 0.040061 | J122: 0.038841 | K122: 0.037551 | L122: 0.036369 | M122: 0.035532 | N122: 0.035132 | O122: 0.03466 | P122: 0.034279 | Q122: 0.033786 | R122: 0.033265 | S122: 0.032701 | T122: 0.032198 | U122: 0.031759 | V122: 0.031438 | W122: 0.031172 | X122: 0.030896 | Y122: 0.030629 | Z122: 0.03044 | AA122: 0.03024 | AB122: 0.029949 | AC122: 0.029728 | AD122: 0.029473 | AE122: 0.029252 | AF122: 0.028857 | AG122: -0.014
A123: Petrochemical Feedstocks | B123: Industrial: Total Industrial Sector Primary Consumption: Petrochemical Feedstocks: High Zero-Carbon Technology Cost | C123: AEO.2025.HIGHZTC.CNSM_NA_IDAL_NA_PCF_NA_USA_QBTU.A | D123: quads | F123: 0.390525 | G123: 0.355 | H123: 0.55 | I123: 0.55 | J123: 0.55 | K123: 0.55 | L123: 0.55 | M123: 0.55 | N123: 0.55 | O123: 0.55 | P123: 0.55 | Q123: 0.55 | R123: 0.55 | S123: 0.55 | T123: 0.55 | U123: 0.55 | V123: 0.55 | W123: 0.55 | X123: 0.55 | Y123: 0.55 | Z123: 0.69558 | AA123: 0.84116 | AB123: 0.84116 | AC123: 0.84116 | AD123: 0.84116 | AE123: 0.964095 | AF123: 1.087029 | AG123: 0.04
A124: Petroleum Coke | B124: Industrial: Total Industrial Sector Primary Consumption: Petroleum Coke: High Zero-Carbon Technology Cost | C124: AEO.2025.HIGHZTC.CNSM_NA_IDAL_NA_PCK_NA_USA_QBTU.A | D124: quads | F124: 0.489646 | G124: 0.51 | H124: 0.517343 | I124: 0.516978 | J124: 0.516155 | K124: 0.513497 | L124: 0.511575 | M124: 0.507761 | N124: 0.498141 | O124: 0.496027 | P124: 0.493382 | Q124: 0.486771 | R124: 0.485807 | S124: 0.482546 | T124: 0.473462 | U124: 0.471524 | V124: 0.475148 | W124: 0.468962 | X124: 0.460895 | Y124: 0.467468 | Z124: 0.466162 | AA124: 0.464497 | AB124: 0.464247 | AC124: 0.468472 | AD124: 0.469885 | AE124: 0.464757 | AF124: 0.462812 | AG124: -0.002
A125: Asphalt and Road Oil | B125: Industrial: Total Industrial Sector Primary Consumption: Asphalt and Road Oil: High Zero-Carbon Technology Cost | C125: AEO.2025.HIGHZTC.CNSM_NA_IDAL_NA_ARO_NA_USA_QBTU.A | D125: quads | F125: 0.877838 | G125: 0.878262 | H125: 0.886157 | I125: 0.903224 | J125: 0.905428 | K125: 0.911496 | L125: 0.918598 | M125: 0.924407 | N125: 0.921001 | O125: 0.922841 | P125: 0.924252 | Q125: 0.928084 | R125: 0.931994 | S125: 0.934567 | T125: 0.937317 | U125: 0.940415 | V125: 0.943471 | W125: 0.945335 | X125: 0.945887 | Y125: 0.947661 | Z125: 0.948485 | AA125: 0.950643 | AB125: 0.954573 | AC125: 0.955311 | AD125: 0.955716 | AE125: 0.956251 | AF125: 0.95571 | AG125: 0.003
...

Sheet AEO 2025 Table 17
A1: Table 17. Renewable Energy Consumption by Sector and Source
A2: https://www.eia.gov/outlooks/aeo/data/browser/#/?id=24-AEO2025&cases=highZTC&sourcekey=0
A3: Tue Dec 02 2025 13:21:06 GMT-0800 (Pacific Standard Time)
A4: Source: U.S. Energy Information Administration
B5: full name | C5: api key | D5: units | E5: 2023 | F5: 2024 | G5: 2025 | H5: 2026 | I5: 2027 | J5: 2028 | K5: 2029 | L5: 2030 | M5: 2031 | N5: 2032 | O5: 2033 | P5: 2034 | Q5: 2035 | R5: 2036 | S5: 2037 | T5: 2038 | U5: 2039 | V5: 2040 | W5: 2041 | X5: 2042 | Y5: 2043 | Z5: 2044 | AA5: 2045 | AB5: 2046 | AC5: 2047 | AD5: 2048 | AE5: 2049 | AF5: 2050 | AG5: Growth (2024-2050)
A6: Marketed Renewable Energy
A7: Residential (wood) | B7: Renewable Energy: Marketed Use: Residential: Wood: High Zero-Carbon Technology Cost | C7: AEO.2025.HIGHZTC.CNSM_NA_RESD_NA_BMS_NA_NA_QBTU.A | D7: quads | F7: 0.357584 | G7: 0.365094 | H7: 0.352654 | I7: 0.347295 | J7: 0.345718 | K7: 0.345503 | L7: 0.34529 | M7: 0.342499 | N7: 0.337295 | O7: 0.332838 | P7: 0.328234 | Q7: 0.323965 | R7: 0.319381 | S7: 0.315221 | T7: 0.311018 | U7: 0.306564 | V7: 0.302182 | W7: 0.2981 | X7: 0.294377 | Y7: 0.29095 | Z7: 0.288536 | AA7: 0.284935 | AB7: 0.281377 | AC7: 0.277692 | AD7: 0.273872 | AE7: 0.270572 | AF7: 0.26805 | AG7: -0.011
A8: Commercial (biomass) | B8: Renewable Energy: Marketed Use: Commercial: Biomass: High Zero-Carbon Technology Cost | C8: AEO.2025.HIGHZTC.CNSM_NA_COMM_NA_BMS_NA_NA_QBTU.A | D8: quads | F8: 0.158104 | G8: 0.158104 | H8: 0.158104 | I8: 0.158104 | J8: 0.158104 | K8: 0.158104 | L8: 0.158104 | M8: 0.158104 | N8: 0.158104 | O8: 0.158104 | P8: 0.158104 | Q8: 0.158104 | R8: 0.158104 | S8: 0.158104 | T8: 0.158104 | U8: 0.158104 | V8: 0.158104 | W8: 0.158104 | X8: 0.158104 | Y8: 0.158104 | Z8: 0.158104 | AA8: 0.158104 | AB8: 0.158104 | AC8: 0.158104 | AD8: 0.158104 | AE8: 0.158104 | AF8: 0.158104 | AG8: 0
A9: Industrial | B9: Renewable Energy: Marketed Use: Industrial: High Zero-Carbon Technology Cost | C9: AEO.2025.HIGHZTC.CNSM_NA_IDAL_NA_MRE_NA_NA_QBTU.A | D9: quads | F9: 2.298446 | G9: 2.340962 | H9: 2.361106 | I9: 2.360003 | J9: 2.365569 | K9: 2.382703 | L9: 2.398932 | M9: 2.411637 | N9: 2.420296 | O9: 2.411936 | P9: 2.416436 | Q9: 2.420991 | R9: 2.442281 | S9: 2.448889 | T9: 2.450308 | U9: 2.460661 | V9: 2.474311 | W9: 2.462655 | X9: 2.457231 | Y9: 2.446465 | Z9: 2.450154 | AA9: 2.46415 | AB9: 2.479432 | AC9: 2.502332 | AD9: 2.522075 | AE9: 2.546465 | AF9: 2.569529 | AG9: 0.004
A10: Conventional Hydroelectric Power | B10: Renewable Energy: Marketed Use: Industrial: Hydropower: High Zero-Carbon Technology Cost | C10: AEO.2025.HIGHZTC.CNSM_NA_IDAL_NA_HYD_CNV_NA_QBTU.A | D10: quads | F10: 0 | G10: 0 | H10: 0 | I10: 0 | J10: 0 | K10: 0 | L10: 0 | M10: 0 | N10: 0 | O10: 0 | P10: 0 | Q10: 0 | R10: 0 | S10: 0 | T10: 0 | U10: 0 | V10: 0 | W10: 0 | X10: 0 | Y10: 0 | Z10: 0 | AA10: 0 | AB10: 0 | AC10: 0 | AD10: 0 | AE10: 0 | AF10: 0 | AG10: - -
A11: Municipal Waste | B11: Renewable Energy: Marketed Use: Industrial: Municipal Waste: High Zero-Carbon Technology Cost | C11: AEO.2025.HIGHZTC.CNSM_NA_IDAL_NA_MUNWST_NA_NA_QBTU.A | D11: quads | F11: 0.153715 | G11: 0.157617 | H11: 0.162141 | I11: 0.166759 | J11: 0.170764 | K11: 0.175069 | L11: 0.17912 | M11: 0.182615 | N11: 0.18587 | O11: 0.188766 | P11: 0.191556 | Q11: 0.193985 | R11: 0.196077 | S11: 0.197824 | T11: 0.19954 | U11: 0.201352 | V11: 0.203029 | W11: 0.204674 | X11: 0.206428 | Y11: 0.208098 | Z11: 0.209768 | AA11: 0.211422 | AB11: 0.213109 | AC11: 0.214787 | AD11: 0.216472 | AE11: 0.218222 | AF11: 0.219935 | AG11: 0.014
A12: Biomass | B12: Renewable Energy: Marketed Use: Industrial: Biomass: High Zero-Carbon Technology Cost | C12: AEO.2025.HIGHZTC.CNSM_NA_IDAL_NA_BMS_NA_NA_QBTU.A | D12: quads | F12: 1.250399 | G12: 1.266777 | H12: 1.284807 | I12: 1.278781 | J12: 1.281623 | K12: 1.299362 | L12: 1.315974 | M12: 1.336054 | N12: 1.350737 | O12: 1.35482 | P12: 1.371261 | Q12: 1.388677 | R12: 1.418132 | S12: 1.440053 | T12: 1.455018 | U12: 1.474959 | V12: 1.489115 | W12: 1.486184 | X12: 1.489107 | Y12: 1.483161 | Z12: 1.487062 | AA12: 1.498508 | AB12: 1.51455 | AC12: 1.535729 | AD12: 1.555482 | AE12: 1.576231 | AF12: 1.593919 | AG12: 0.009
A13: Biofuels Heat and Coproducts | B13: Renewable Energy: Marketed Use: Industrial: Biofuels Heat and Coproducts: High Zero-Carbon Technology Cost | C13: AEO.2025.HIGHZTC.CNSM_NA_IDAL_NA_BFH_NA_NA_QBTU.A | D13: quads | F13: 0.894331 | G13: 0.916568 | H13: 0.914158 | I13: 0.914463 | J13: 0.913182 | K13: 0.908272 | L13: 0.903837 | M13: 0.892968 | N13: 0.883689 | O13: 0.868351 | P13: 0.853619 | Q13: 0.83833 | R13: 0.828071 | S13: 0.811011 | T13: 0.79575 | U13: 0.784349 | V13: 0.782166 | W13: 0.771797 | X13: 0.761696 | Y13: 0.755206 | Z13: 0.753325 | AA13: 0.75422 | AB13: 0.751773 | AC13: 0.751816 | AD13: 0.75012 | AE13: 0.752011 | AF13: 0.755675 | AG13: -0.006
A14: Transportation | B14: Renewable Energy: Marketed Use: Transportation: High Zero-Carbon Technology Cost | C14: AEO.2025.HIGHZTC.CNSM_NA_TRN_NA_NA_NA_NA_QBTU.A | D14: quads | F14: 1.779031 | G14: 1.798202 | H14: 1.840455 | I14: 1.818957 | J14: 1.65284 | K14: 1.652911 | L14: 1.651971 | M14: 1.650766 | N14: 1.649971 | O14: 1.649804 | P14: 1.649323 | Q14: 1.648011 | R14: 1.646139 | S14: 1.644258 | T14: 1.642699 | U14: 1.64108 | V14: 1.639198 | W14: 1.637743 | X14: 1.636214 | Y14: 1.634694 | Z14: 1.632965 | AA14: 1.631249 | AB14: 1.629651 | AC14: 1.62807 | AD14: 1.626433 | AE14: 1.624858 | AF14: 1.623228 | AG14: -0.004
A15: Ethanol used in E85 | B15: Renewable Energy: Marketed Use: Transportation: Ethanol used in E85: High Zero-Carbon Technology Cost | C15: AEO.2025.HIGHZTC.CNSM_NA_TRN_NA_ETE_NA_NA_QBTU.A | D15: quads | F15: 0.00247 | G15: 0.002289 | H15: 0.002042 | I15: 0.001912 | J15: 0.001856 | K15: 0.001923 | L15: 0.001823 | M15: 0.001684 | N15: 0.001568 | O15: 0.00147 | P15: 0.001392 | Q15: 0.00131 | R15: 0.001227 | S15: 0.001165 | T15: 0.0011 | U15: 0.00105 | V15: 0.001026 | W15: 0.001005 | X15: 0.000987 | Y15: 0.000977 | Z15: 0.000991 | AA15: 0.000966 | AB15: 0.000963 | AC15: 0.000985 | AD15: 0.000982 | AE15: 0.000983 | AF15: 0.000977 | AG15: -0.035
A16: Ethanol used in Gasoline Blending | B16: Renewable Energy: Marketed Use: Transportation: Ethanol used in Gasoline Blending: High Zero-Carbon Technology Cost | C16: AEO.2025.HIGHZTC.CNSM_NA_TRN_NA_EBL_NA_NA_QBTU.A | D16: quads | F16: 1.159613 | G16: 1.165416 | H16: 1.188011 | I16: 1.188534 | J16: 1.179669 | K16: 1.166131 | L16: 1.146274 | M16: 1.126136 | N16: 1.099874 | O16: 1.072452 | P16: 1.045892 | Q16: 1.018797 | R16: 0.988496 | S16: 0.958549 | T16: 0.930869 | U16: 0.904472 | V16: 0.881031 | W16: 0.859533 | X16: 0.838272 | Y16: 0.821939 | Z16: 0.805321 | AA16: 0.792732 | AB16: 0.781266 | AC16: 0.773098 | AD16: 0.762308 | AE16: 0.756545 | AF16: 0.752895 | AG16: -0.016
A17: Biodiesel used in Distillate Blending | B17: Renewable Energy: Marketed Use: Transportation: Biodiesel used in Distillate Blending: High Zero-Carbon Technology Cost | C17: AEO.2025.HIGHZTC.CNSM_NA_TRN_NA_BUD_NA_NA_QBTU.A | D17: quads | F17: 0.237455 | G17: 0.197546 | H17: 0.2017 | I17: 0.193368 | J17: 0.081132 | K17: 0.110168 | L17: 0.120147 | M17: 0.117683 | N17: 0.128085 | O17: 0.154412 | P17: 0.173353 | Q17: 0.172654 | R17: 0.165617 | S17: 0.153023 | T17: 0.148424 | U17: 0.142497 | V17: 0.136675 | W17: 0.135084 | X17: 0.132216 | Y17: 0.128964 | Z17: 0.12501 | AA17: 0.120905 | AB17: 0.116645 | AC17: 0.112229 | AD17: 0.107652 | AE17: 0.102967 | AF17: 0.098282 | AG17: -0.033
A18: Biobutanol | B18: Renewable Energy: Marketed Use: Transportation: Biobutanol: High Zero-Carbon Technology Cost | C18: AEO.2025.HIGHZTC.CNSM_NA_TRN_NA_BIOB_NA_NA_NA.A | D18: quads | F18: 0 | G18: 0 | H18: 0 | I18: 0 | J18: 0 | K18: 0 | L18: 0 | M18: 0 | N18: 0 | O18: 0 | P18: 0 | Q18: 0 | R18: 0 | S18: 0 | T18: 0 | U18: 0 | V18: 0 | W18: 0 | X18: 0 | Y18: 0 | Z18: 0 | AA18: 0 | AB18: 0 | AC18: 0 | AD18: 0 | AE18: 0 | AF18: 0 | AG18: - -
A19: Liquids from Biomass | B19: Renewable Energy: Marketed Use: Transportation: Liquids from Biomass: High Zero-Carbon Technology Cost | C19: AEO.2025.HIGHZTC.CNSM_NA_TRN_NA_LFB_NA_NA_QBTU.A | D19: quads | F19: 0.003143 | G19: 0.004242 | H19: 0.004192 | I19: 0.004247 | J19: 0.004249 | K19: 0.004249 | L19: 0.004249 | M19: 0.004192 | N19: 0.004199 | O19: 0.004193 | P19: 0.004193 | Q19: 0.004193 | R19: 0.004193 | S19: 0.004194 | T19: 0.004194 | U19: 0.004194 | V19: 0.004194 | W19: 0.004194 | X19: 0.004194 | Y19: 0.004194 | Z19: 0.004195 | AA19: 0.004195 | AB19: 0.004195 | AC19: 0.004195 | AD19: 0.004195 | AE19: 0.004195 | AF19: 0.004195 | AG19: 0.011
A20: Renewable Diesel and Gasoline | B20: Renewable Energy: Marketed Use: Transportation: Green Liquids: High Zero-Carbon Technology Cost | C20: AEO.2025.HIGHZTC.CNSM_NA_TRN_NA_GLQ_NA_NA_QBTU.A | D20: quads | F20: 0.376349 | G20: 0.428709 | H20: 0.444511 | I20: 0.430895 | J20: 0.385936 | K20: 0.37044 | L20: 0.379478 | M20: 0.401071 | N20: 0.416245 | O20: 0.417277 | P20: 0.424492 | Q20: 0.451056 | R20: 0.486606 | S20: 0.527328 | T20: 0.558113 | U20: 0.588867 | V20: 0.616272 | W20: 0.637928 | X20: 0.660545 | Y20: 0.678621 | Z20: 0.697449 | AA20: 0.712452 | AB20: 0.726581 | AC20: 0.737563 | AD20: 0.751297 | AE20: 0.760169 | AF20: 0.766878 | AG20: 0.028
A21: Electric Power | B21: Renewable Energy: Marketed Use: Electric Power: High Zero-Carbon Technology Cost | C21: AEO.2025.HIGHZTC.CNSM_NA_ELEP_NA_NA_NA_NA_QBTU.A | D21: quads | F21: 3.409441 | G21: 3.802485 | H21: 4.36894 | I21: 4.692803 | J21: 4.844075 | K21: 5.067399 | L21: 5.415482 | M21: 5.793836 | N21: 6.225558 | O21: 6.674434 | P21: 7.210943 | Q21: 7.849944 | R21: 8.451016 | S21: 9.167359 | T21: 9.648984 | U21: 10.328339 | V21: 10.649784 | W21: 10.80304 | X21: 10.975296 | Y21: 11.190046 | Z21: 11.380852 | AA21: 11.55542 | AB21: 11.771946 | AC21: 11.940047 | AD21: 12.114096 | AE21: 12.275303 | AF21: 12.507336 | AG21: 0.051
A22: Conventional Hydroelectric Power | B22: Renewable Energy: Marketed Use: Electric Power: Hydropower: High Zero-Carbon Technology Cost | C22: AEO.2025.HIGHZTC.CNSM_NA_ELEP_NA_HYD_CNV_NA_QBTU.A | D22: quads | F22: 0.826728 | G22: 0.897152 | H22: 0.931477 | I22: 0.9659 | J22: 0.966652 | K22: 0.966602 | L22: 0.968512 | M22: 0.968752 | N22: 0.969003 | O22: 0.969075 | P22: 0.969638 | Q22: 0.967771 | R22: 0.964381 | S22: 0.960529 | T22: 0.958948 | U22: 0.951818 | V22: 0.950544 | W22: 0.95869 | X22: 0.949528 | Y22: 0.936356 | Z22: 0.934708 | AA22: 0.932852 | AB22: 0.919088 | AC22: 0.934345 | AD22: 0.921085 | AE22: 0.936604 | AF22: 0.935078 | AG22: 0.005
A23: Geothermal | B23: Renewable Energy: Marketed Use: Electric Power: Geothermal: High Zero-Carbon Technology Cost | C23: AEO.2025.HIGHZTC.CNSM_NA_ELEP_NA_GEOTHM_NA_NA_QBTU.A | D23: quads | F23: 0.054585 | G23: 0.052606 | H23: 0.057384 | I23: 0.059912 | J23: 0.065179 | K23: 0.071533 | L23: 0.078267 | M23: 0.085013 | N23: 0.093808 | O23: 0.101664 | P23: 0.109557 | Q23: 0.117412 | R23: 0.125235 | S23: 0.134185 | T23: 0.142483 | U23: 0.149106 | V23: 0.156946 | W23: 0.163073 | X23: 0.169849 | Y23: 0.175511 | Z23: 0.181788 | AA23: 0.187546 | AB23: 0.192745 | AC23: 0.196904 | AD23: 0.199697 | AE23: 0.201521 | AF23: 0.20325 | AG23: 0.052
A24: Biogenic Municipal Waste | B24: Renewable Energy: Marketed Use: Electric Power: Biogenic Municipal Waste: High Zero-Carbon Technology Cost | C24: AEO.2025.HIGHZTC.CNSM_NA_ELEP_NA_BGM_NA_NA_QBTU.A | D24: quads | F24: 0.140012 | G24: 0.149728 | H24: 0.158626 | I24: 0.166548 | J24: 0.170602 | K24: 0.177605 | L24: 0.18093 | M24: 0.188011 | N24: 0.196481 | O24: 0.204321 | P24: 0.21057 | Q24: 0.216608 | R24: 0.223235 | S24: 0.231373 | T24: 0.240032 | U24: 0.245649 | V24: 0.251244 | W24: 0.257648 | X24: 0.26419 | Y24: 0.270703 | Z24: 0.274451 | AA24: 0.278182 | AB24: 0.281335 | AC24: 0.284447 | AD24: 0.287747 | AE24: 0.287894 | AF24: 0.288127 | AG24: 0.028
A25: Biomass | B25: Renewable Energy: Marketed Use: Electric Power: Biomass: High Zero-Carbon Technology Cost | C25: AEO.2025.HIGHZTC.CNSM_NA_ELEP_NA_BMS_NA_NA_QBTU.A | D25: quads | F25: 0.167184 | G25: 0.1668 | H25: 0.166415 | I25: 0.166081 | J25: 0.155723 | K25: 0.155788 | L25: 0.157543 | M25: 0.156527 | N25: 0.160985 | O25: 0.161799 | P25: 0.16109 | Q25: 0.161113 | R25: 0.160452 | S25: 0.158351 | T25: 0.157438 | U25: 0.158791 | V25: 0.159685 | W25: 0.159987 | X25: 0.159966 | Y25: 0.159964 | Z25: 0.159915 | AA25: 0.159685 | AB25: 0.15992 | AC25: 0.160882 | AD25: 0.161696 | AE25: 0.165736 | AF25: 0.169202 | AG25: 0
A26: Dedicated Plants | B26: Renewable Energy: Marketed Use: Electric Power: Biomass: Dedicated Plants: High Zero-Carbon Technology Cost | C26: AEO.2025.HIGHZTC.CNSM_NA_ELEP_NA_DPE_NA_NA_QBTU.A | D26: quads | F26: 0.13592 | G26: 0.136125 | H26: 0.136176 | I26: 0.135907 | J26: 0.127875 | K26: 0.128431 | L26: 0.129779 | M26: 0.128913 | N26: 0.133544 | O26: 0.13424 | P26: 0.132904 | Q26: 0.132916 | R26: 0.13237 | S26: 0.130415 | T26: 0.129501 | U26: 0.131083 | V26: 0.132436 | W26: 0.13273 | X26: 0.132705 | Y26: 0.132653 | Z26: 0.1326 | AA26: 0.13239 | AB26: 0.132604 | AC26: 0.133492 | AD26: 0.134088 | AE26: 0.134859 | AF26: 0.137713 | AG26: 0.001
A27: Cofiring | B27: Renewable Energy: Marketed Use: Electric Power: Biomass: Cofiring: High Zero-Carbon Technology Cost | C27: AEO.2025.HIGHZTC.CNSM_NA_ELEP_NA_CFR_NA_NA_QBTU.A | D27: quads | F27: 0.031265 | G27: 0.030674 | H27: 0.030239 | I27: 0.030174 | J27: 0.027848 | K27: 0.027357 | L27: 0.027764 | M27: 0.027614 | N27: 0.027441 | O27: 0.027559 | P27: 0.028187 | Q27: 0.028197 | R27: 0.028081 | S27: 0.027936 | T27: 0.027937 | U27: 0.027708 | V27: 0.027249 | W27: 0.027258 | X27: 0.027261 | Y27: 0.027312 | Z27: 0.027314 | AA27: 0.027295 | AB27: 0.027315 | AC27: 0.02739 | AD27: 0.027608 | AE27: 0.030877 | AF27: 0.031489 | AG27: 0
A28: Solar Thermal | B28: Renewable Energy: Marketed Use: Electric Power: Solar Thermal: High Zero-Carbon Technology Cost | C28: AEO.2025.HIGHZTC.CNSM_NA_ELEP_NA_SLR_THERM_NA_QBTU.A | D28: quads | F28: 0.009175 | G28: 0.008686 | H28: 0.009688 | I28: 0.009693 | J28: 0.009657 | K28: 0.009675 | L28: 0.00968 | M28: 0.009669 | N28: 0.009663 | O28: 0.009687 | P28: 0.009677 | Q28: 0.009697 | R28: 0.009656 | S28: 0.00956 | T28: 0.009468 | U28: 0.007554 | V28: 0.006445 | W28: 0.007569 | X28: 0.007597 | Y28: 0.009075 | Z28: 0.009301 | AA28: 0.00924 | AB28: 0.00926 | AC28: 0.009197 | AD28: 0.00929 | AE28: 0.009221 | AF28: 0.009227 | AG28: 0
A29: Solar Photovoltaic | B29: Renewable Energy: Marketed Use: Electric Power: Solar Photovoltaic: High Zero-Carbon Technology Cost | C29: AEO.2025.HIGHZTC.CNSM_NA_ELEP_NA_SLR_PHTVL_NA_QBTU.A | D29: quads | F29: 0.687705 | G29: 0.930381 | H29: 1.247354 | I29: 1.342533 | J29: 1.36697 | K29: 1.436344 | L29: 1.580732 | M29: 1.732823 | N29: 1.908199 | O29: 2.036301 | P29: 2.170271 | Q29: 2.335254 | R29: 2.394927 | S29: 2.483112 | T29: 2.575211 | U29: 2.717169 | V29: 2.765637 | W29: 2.787745 | X29: 2.835044 | Y29: 2.950677 | Z29: 3.003978 | AA29: 3.085895 | AB29: 3.187423 | AC29: 3.275896 | AD29: 3.377473 | AE29: 3.452082 | AF29: 3.582758 | AG29: 0.066
A30: Wind | B30: Renewable Energy: Marketed Use: Electric Power: Wind: High Zero-Carbon Technology Cost | C30: AEO.2025.HIGHZTC.CNSM_NA_ELEP_NA_WND_NA_NA_QBTU.A | D30: quads | F30: 1.524052 | G30: 1.597133 | H30: 1.797997 | I30: 1.982137 | J30: 2.109292 | K30: 2.249853 | L30: 2.439818 | M30: 2.653042 | N30: 2.887419 | O30: 3.191586 | P30: 3.580139 | Q30: 4.04209 | R30: 4.573131 | S30: 5.190249 | T30: 5.565403 | U30: 6.098251 | V30: 6.359282 | W30: 6.468328 | X30: 6.589122 | Y30: 6.68776 | Z30: 6.816711 | AA30: 6.90202 | AB30: 7.022176 | AC30: 7.078376 | AD30: 7.157106 | AE30: 7.222245 | AF30: 7.319693 | AG30: 0.062
A31: Total Marketed Renewable Energy | B31: Renewable Energy: Total Marketed Renewable Energy Use: High Zero-Carbon Technology Cost | C31: AEO.2025.HIGHZTC.CNSM_NA_NA_NA_NA_NA_NA_QBTU.A | D31: quads | F31: 8.002606 | G31: 8.464848 | H31: 9.081259 | I31: 9.377162 | J31: 9.366306 | K31: 9.60662 | L31: 9.969779 | M31: 10.356842 | N31: 10.791225 | O31: 11.227115 | P31: 11.76304 | Q31: 12.401015 | R31: 13.016922 | S31: 13.733831 | T31: 14.211114 | U31: 14.894747 | V31: 15.223579 | W31: 15.359642 | X31: 15.521223 | Y31: 15.720259 | Z31: 15.910612 | AA31: 16.093858 | AB31: 16.32051 | AC31: 16.506245 | AD31: 16.69458 | AE31: 16.875301 | AF31: 17.126247 | AG31: 0.03
A32: Sources of Ethanol
A33: From Corn and Other Starch | B33: Renewable Energy: Sources of Ethanol: From Corn: High Zero-Carbon Technology Cost | C33: AEO.2025.HIGHZTC.SUP_PRD_FCO_NA_ETH_NA_NA_QBTU.A | D33: quads | F33: 1.319797 | G33: 1.32233 | H33: 1.33887 | I33: 1.339538 | J33: 1.339392 | K33: 1.331488 | L33: 1.324212 | M33: 1.308426 | N33: 1.294733 | O33: 1.272076 | P33: 1.250427 | Q33: 1.228365 | R33: 1.212994 | S33: 1.188613 | T33: 1.166628 | U33: 1.146074 | V33: 1.139453 | W33: 1.124409 | X33: 1.109761 | Y33: 1.100222 | Z33: 1.096753 | AA33: 1.097313 | AB33: 1.093469 | AC33: 1.093145 | AD33: 1.090353 | AE33: 1.092808 | AF33: 1.097584 | AG33: -0.007
A34: From Cellulose | B34: Renewable Energy: Sources of Ethanol: From Cellulose: High Zero-Carbon Technology Cost | C34: AEO.2025.HIGHZTC.SUP_PRD_FCE_NA_ETH_NA_NA_QBTU.A | D34: quads | F34: 0.001493 | G34: 0.001479 | H34: 0.001468 | I34: 0.001468 | J34: 0.001468 | K34: 0.001468 | L34: 0.001468 | M34: 0.001468 | N34: 0.001468 | O34: 0.001468 | P34: 0.001468 | Q34: 0.001468 | R34: 0.001468 | S34: 0.001468 | T34: 0.001468 | U34: 0.001468 | V34: 0.001468 | W34: 0.001468 | X34: 0.001468 | Y34: 0.001468 | Z34: 0.001468 | AA34: 0.001468 | AB34: 0.001468 | AC34: 0.001468 | AD34: 0.001468 | AE34: 0.001468 | AF34: 0.001468 | AG34: -0.001
A35: Net Imports | B35: Renewable Energy: Sources of Ethanol: Net Imports: High Zero-Carbon Technology Cost | C35: AEO.2025.HIGHZTC.SUP_NETIMP_NA_NA_ETH_NA_NA_QBTU.A | D35: quads | F35: -0.159206 | G35: -0.156104 | H35: -0.150285 | I35: -0.15056 | J35: -0.159336 | K35: -0.164902 | L35: -0.177583 | M35: -0.182073 | N35: -0.194759 | O35: -0.199622 | P35: -0.204611 | Q35: -0.209726 | R35: -0.224739 | S35: -0.230367 | T35: -0.236128 | U35: -0.24202 | V35: -0.258864 | W35: -0.26534 | X35: -0.271971 | Y35: -0.278774 | Z35: -0.291909 | AA35: -0.305083 | AB35: -0.312708 | AC35: -0.32053 | AD35: -0.328531 | AE35: -0.336748 | AF35: -0.34518 | AG35: 0.03
A36: Total U.S. Supply of Ethanol | B36: Renewable Energy: Total U.S. Supply of Ethanol: High Zero-Carbon Technology Cost | C36: AEO.2025.HIGHZTC.SUP_NA_NA_NA_ETH_NA_NA_QBTU.A | D36: quads | F36: 1.162084 | G36: 1.167705 | H36: 1.190053 | I36: 1.190446 | J36: 1.181524 | K36: 1.168054 | L36: 1.148098 | M36: 1.12782 | N36: 1.101442 | O36: 1.073922 | P36: 1.047284 | Q36: 1.020107 | R36: 0.989723 | S36: 0.959713 | T36: 0.931968 | U36: 0.905522 | V36: 0.882057 | W36: 0.860537 | X36: 0.839259 | Y36: 0.822916 | Z36: 0.806312 | AA36: 0.793698 | AB36: 0.782229 | AC36: 0.774083 | AD36: 0.76329 | AE36: 0.757528 | AF36: 0.753872 | AG36: -0.017
A37: Nonmarketed Renewable Energy
A38: Selected Consumption
A39: Residential | B39: Renewable Energy: Nonmarketed Selected Use: Residential: High Zero-Carbon Technology Cost | C39: AEO.2025.HIGHZTC.CNSM_NA_RESD_NA_NA_NA_NA_QBTU.A | D39: quads | F39: 0.25071 | G39: 0.287551 | H39: 0.325135 | I39: 0.359367 | J39: 0.394318 | K39: 0.425814 | L39: 0.460232 | M39: 0.496958 | N39: 0.533473 | O39: 0.567727 | P39: 0.602256 | Q39: 0.628411 | R39: 0.655407 | S39: 0.682429 | T39: 0.710772 | U39: 0.73927 | V39: 0.767411 | W39: 0.796545 | X39: 0.826706 | Y39: 0.857196 | Z39: 0.888113 | AA39: 0.920087 | AB39: 0.952824 | AC39: 0.986141 | AD39: 1.020414 | AE39: 1.055277 | AF39: 1.090701 | AG39: 0.058
A40: Solar Hot Water Heating | B40: Renewable Energy: Nonmarketed Selected Use: Residential: Solar Hot Water Heating: High Zero-Carbon Technology Cost | C40: AEO.2025.HIGHZTC.CNSM_NA_RESD_NA_SHW_NA_NA_QBTU.A | D40: quads | F40: 0.035525 | G40: 0.042155 | H40: 0.049198 | I40: 0.055102 | J40: 0.061131 | K40: 0.063327 | L40: 0.066036 | M40: 0.068474 | N40: 0.071069 | O40: 0.071029 | P40: 0.07183 | Q40: 0.071849 | R40: 0.071916 | S40: 0.071802 | T40: 0.071685 | U40: 0.071601 | V40: 0.070627 | W40: 0.070499 | X40: 0.070575 | Y40: 0.070644 | Z40: 0.070711 | AA40: 0.070803 | AB40: 0.071024 | AC40: 0.070883 | AD40: 0.070941 | AE40: 0.070838 | AF40: 0.07093 | AG40: 0.027
A41: Solar Photovoltaic | B41: Renewable Energy: Nonmarketed Selected Use: Residential: Solar Photovoltaic: High Zero-Carbon Technology Cost | C41: AEO.2025.HIGHZTC.CNSM_NA_RESD_NA_SLR_PHTVL_NA_QBTU.A | D41: quads | F41: 0.213925 | G41: 0.243256 | H41: 0.272936 | I41: 0.300863 | J41: 0.329338 | K41: 0.358154 | L41: 0.388935 | M41: 0.422001 | N41: 0.45468 | O41: 0.488552 | P41: 0.522083 | Q41: 0.548214 | R41: 0.575139 | S41: 0.602267 | T41: 0.630719 | U41: 0.659294 | V41: 0.6884 | W41: 0.717651 | X41: 0.747724 | Y41: 0.778135 | Z41: 0.808973 | AA41: 0.840843 | AB41: 0.873347 | AC41: 0.906792 | AD41: 0.940992 | AE41: 0.975945 | AF41: 1.011262 | AG41: 0.062
A42: Wind | B42: Renewable Energy: Nonmarketed Selected Use: Residential: Wind: High Zero-Carbon Technology Cost | C42: AEO.2025.HIGHZTC.CNSM_NA_RESD_NA_WND_NA_NA_QBTU.A | D42: quads | F42: 0.00126 | G42: 0.00214 | H42: 0.003001 | I42: 0.003401 | J42: 0.003849 | K42: 0.004333 | L42: 0.005261 | M42: 0.006483 | N42: 0.007725 | O42: 0.008146 | P42: 0.008342 | Q42: 0.008347 | R42: 0.008353 | S42: 0.008359 | T42: 0.008367 | U42: 0.008375 | V42: 0.008385 | W42: 0.008395 | X42: 0.008406 | Y42: 0.008417 | Z42: 0.008429 | AA42: 0.008441 | AB42: 0.008453 | AC42: 0.008466 | AD42: 0.00848 | AE42: 0.008494 | AF42: 0.008509 | AG42: 0.076
A43: Commercial | B43: Renewable Energy: Nonmarketed Selected Use: Commercial: High Zero-Carbon Technology Cost | C43: AEO.2025.HIGHZTC.CNSM_NA_COMM_NA_NA_NA_NA_QBTU.A | D43: quads | F43: 0.208187 | G43: 0.222623 | H43: 0.238958 | I43: 0.245164 | J43: 0.251295 | K43: 0.260626 | L43: 0.272261 | M43: 0.286451 | N43: 0.299791 | O43: 0.313572 | P43: 0.324101 | Q43: 0.330456 | R43: 0.335851 | S43: 0.341582 | T43: 0.35017 | U43: 0.354886 | V43: 0.359193 | W43: 0.36735 | X43: 0.375429 | Y43: 0.384299 | Z43: 0.393278 | AA43: 0.402495 | AB43: 0.410938 | AC43: 0.42058 | AD43: 0.430687 | AE43: 0.440464 | AF43: 0.451111 | AG43: 0.03
A44: Solar Thermal | B44: Renewable Energy: Nonmarketed Selected Use: Commercial: Solar Thermal: High Zero-Carbon Technology Cost | C44: AEO.2025.HIGHZTC.CNSM_NA_COMM_NA_SLR_THERM_NA_QBTU.A | D44: quads | F44: 0.06597 | G44: 0.063523 | H44: 0.063384 | I44: 0.062599 | J44: 0.061945 | K44: 0.061423 | L44: 0.061378 | M44: 0.060735 | N44: 0.060531 | O44: 0.05826 | P44: 0.058207 | Q44: 0.058237 | R44: 0.05822 | S44: 0.058091 | T44: 0.057848 | U44: 0.057545 | V44: 0.056179 | W44: 0.05599 | X44: 0.055925 | Y44: 0.055866 | Z44: 0.055858 | AA44: 0.055775 | AB44: 0.055778 | AC44: 0.055605 | AD44: 0.055572 | AE44: 0.055527 | AF44: 0.05545 | AG44: -0.007
A45: Solar Photovoltaic | B45: Renewable Energy: Nonmarketed Selected Use: Commercial: Solar Photovoltaic: High Zero-Carbon Technology Cost | C45: AEO.2025.HIGHZTC.CNSM_NA_COMM_NA_SLR_PHTVL_NA_QBTU.A | D45: quads | F45: 0.139688 | G45: 0.156569 | H45: 0.173044 | I45: 0.180036 | J45: 0.186819 | K45: 0.196667 | L45: 0.208341 | M45: 0.223166 | N45: 0.2367 | O45: 0.252736 | P45: 0.263313 | Q45: 0.269636 | R45: 0.275047 | S45: 0.280907 | T45: 0.289735 | U45: 0.29475 | V45: 0.300421 | W45: 0.308763 | X45: 0.316904 | Y45: 0.325831 | Z45: 0.334814 | AA45: 0.34411 | AB45: 0.352546 | AC45: 0.362357 | AD45: 0.372492 | AE45: 0.382311 | AF45: 0.393028 | AG45: 0.041
A46: Wind | B46: Renewable Energy: Nonmarketed Selected Use: Commercial: Wind: High Zero-Carbon Technology Cost | C46: AEO.2025.HIGHZTC.CNSM_NA_COMM_NA_WND_NA_NA_QBTU.A | D46: quads | F46: 0.002529 | G46: 0.002531 | H46: 0.00253 | I46: 0.00253 | J46: 0.00253 | K46: 0.002536 | L46: 0.002542 | M46: 0.002549 | N46: 0.00256 | O46: 0.002576 | P46: 0.002582 | Q46: 0.002583 | R46: 0.002584 | S46: 0.002585 | T46: 0.002588 | U46: 0.00259 | V46: 0.002593 | W46: 0.002597 | X46: 0.0026 | Y46: 0.002602 | Z46: 0.002606 | AA46: 0.002611 | AB46: 0.002614 | AC46: 0.002618 | AD46: 0.002622 | AE46: 0.002626 | AF46: 0.002632 | AG46: 0.002

Sheet AEO 2026 Table 2
A1: Table 2. Energy Consumption by Sector and Source
A2: https://www.eia.gov/outlooks/aeo/data/browser/#/?id=2-AEO2026&cases=electrnp&sourcekey=0
A3: Thu Apr 23 2026 14:57:29 GMT-0700 (Pacific Daylight Time)
A4: Source: U.S. Energy Information Administration
B5: full name | C5: api key | D5: units | E5: 2025 | F5: 2026 | G5: 2027 | H5: 2028 | I5: 2029 | J5: 2030 | K5: 2031 | L5: 2032 | M5: 2033 | N5: 2034 | O5: 2035 | P5: 2036 | Q5: 2037 | R5: 2038 | S5: 2039 | T5: 2040 | U5: 2041 | V5: 2042 | W5: 2043 | X5: 2044 | Y5: 2045 | Z5: 2046 | AA5: 2047 | AB5: 2048 | AC5: 2049 | AD5: 2050 | AE5: Growth (2025-2050)
A6: Residential
A7: Propane | B7: Energy Use: Residential: Propane: Alternative Electricity and Transportation | C7: AEO.2026.ELECTRNP.CNSM_ENU_RESD_NA_PROP_NA_NA_QBTU.A | D7: quads | E7: 0.5245 | F7: 0.51372 | G7: 0.495541 | H7: 0.496211 | I7: 0.493311 | J7: 0.488928 | K7: 0.483486 | L7: 0.478163 | M7: 0.473203 | N7: 0.469062 | O7: 0.465621 | P7: 0.462483 | Q7: 0.459429 | R7: 0.456475 | S7: 0.453566 | T7: 0.450898 | U7: 0.448539 | V7: 0.446738 | W7: 0.445416 | X7: 0.444479 | Y7: 0.443746 | Z7: 0.442976 | AA7: 0.442012 | AB7: 0.440991 | AC7: 0.44002 | AD7: 0.439191 | AE7: -0.7%
A8: Distillate Fuel Oil | B8: Energy Use: Residential: Distillate Fuel Oil: Alternative Electricity and Transportation | C8: AEO.2026.ELECTRNP.CNSM_ENU_RESD_NA_DFO_NA_NA_QBTU.A | D8: quads | E8: 0.48928 | F8: 0.47136 | G8: 0.464952 | H8: 0.4565 | I8: 0.447624 | J8: 0.439746 | K8: 0.431983 | L8: 0.424812 | M8: 0.417945 | N8: 0.411851 | O8: 0.406073 | P8: 0.400473 | Q8: 0.395019 | R8: 0.389742 | S8: 0.38464 | T8: 0.379595 | U8: 0.374572 | V8: 0.369741 | W8: 0.364969 | X8: 0.360335 | Y8: 0.35574 | Z8: 0.351238 | AA8: 0.346724 | AB8: 0.342244 | AC8: 0.337805 | AD8: 0.333547 | AE8: -1.5%
A9: Petroleum and Other Liquids Subtotal | B9: Energy Use: Residential: Liquid Fuels Subtotal: Alternative Electricity and Transportation | C9: AEO.2026.ELECTRNP.CNSM_ENU_RESD_NA_LFL_NA_NA_QBTU.A | D9: quads | E9: 1.01378 | F9: 0.98508 | G9: 0.960492 | H9: 0.952711 | I9: 0.940935 | J9: 0.928674 | K9: 0.915469 | L9: 0.902975 | M9: 0.891148 | N9: 0.880914 | O9: 0.871694 | P9: 0.862955 | Q9: 0.854449 | R9: 0.846217 | S9: 0.838206 | T9: 0.830493 | U9: 0.82311 | V9: 0.816479 | W9: 0.810385 | X9: 0.804814 | Y9: 0.799486 | Z9: 0.794214 | AA9: 0.788736 | AB9: 0.783235 | AC9: 0.777824 | AD9: 0.772738 | AE9: -1.1%
A10: Natural Gas | B10: Energy Use: Residential: Natural Gas: Alternative Electricity and Transportation | C10: AEO.2026.ELECTRNP.CNSM_ENU_RESD_NA_NG_NA_NA_QBTU.A | D10: quads | E10: 4.92608 | F10: 4.756272 | G10: 4.887193 | H10: 4.880057 | I10: 4.841941 | J10: 4.792875 | K10: 4.741629 | L10: 4.695206 | M10: 4.647789 | N10: 4.605699 | O10: 4.566593 | P10: 4.529979 | Q10: 4.491732 | R10: 4.45528 | S10: 4.419171 | T10: 4.384261 | U10: 4.349348 | V10: 4.318778 | W10: 4.290055 | X10: 4.262946 | Y10: 4.23648 | Z10: 4.207667 | AA10: 4.176517 | AB10: 4.145389 | AC10: 4.115045 | AD10: 4.086372 | AE10: -0.7%
A11: Renewable Energy | B11: Energy Use: Residential: Renewable Energy: Alternative Electricity and Transportation | C11: AEO.2026.ELECTRNP.CNSM_ENU_RESD_NA_REN_NA_NA_QBTU.A | D11: quads | E11: 0.371387 | F11: 0.342901 | G11: 0.33499 | H11: 0.331205 | I11: 0.328954 | J11: 0.323627 | K11: 0.319369 | L11: 0.315643 | M11: 0.312812 | N11: 0.309126 | O11: 0.305829 | P11: 0.302008 | Q11: 0.298094 | R11: 0.294199 | S11: 0.289954 | T11: 0.285538 | U11: 0.28127 | V11: 0.277378 | W11: 0.273631 | X11: 0.270078 | Y11: 0.266974 | Z11: 0.263978 | AA11: 0.26129 | AB11: 0.258824 | AC11: 0.256576 | AD11: 0.254137 | AE11: -1.5%
A12: Purchased Electricity for Residential Use | B12: Energy Use: Residential: Electricity: Alternative Electricity and Transportation | C12: AEO.2026.ELECTRNP.CNSM_ENU_RESD_NA_ELC_NA_NA_QBTU.A | D12: quads | E12: 5.146283 | F12: 5.165968 | G12: 5.063568 | H12: 5.097425 | I12: 5.110842 | J12: 5.101124 | K12: 5.084683 | L12: 5.071815 | M12: 5.063284 | N12: 5.061672 | O12: 5.064488 | P12: 5.071559 | Q12: 5.081708 | R12: 5.095572 | S12: 5.111459 | T12: 5.122882 | U12: 5.139645 | V12: 5.162683 | W12: 5.191554 | X12: 5.221573 | Y12: 5.249293 | Z12: 5.279313 | AA12: 5.307253 | AB12: 5.334354 | AC12: 5.364092 | AD12: 5.394052 | AE12: 0.2%
A13: Delivered Energy | B13: Energy Use: Residential: Delivered Energy: Alternative Electricity and Transportation | C13: AEO.2026.ELECTRNP.CNSM_ENU_RESD_NA_DELE_NA_NA_QBTU.A | D13: quads | E13: 11.457531 | F13: 11.25022 | G13: 11.246243 | H13: 11.2614 | I13: 11.222671 | J13: 11.146299 | K13: 11.06115 | L13: 10.98564 | M13: 10.915031 | N13: 10.85741 | O13: 10.808603 | P13: 10.7665 | Q13: 10.725982 | R13: 10.691268 | S13: 10.658791 | T13: 10.623175 | U13: 10.593373 | V13: 10.57532 | W13: 10.565623 | X13: 10.559411 | Y13: 10.552234 | Z13: 10.545171 | AA13: 10.533794 | AB13: 10.5218 | AC13: 10.513536 | AD13: 10.5073 | AE13: -0.3%
A14: Electricity-Related Losses | B14: Energy Use: Residential: Electricity Related Losses: Alternative Electricity and Transportation | C14: AEO.2026.ELECTRNP.CNSM_ENU_RESD_NA_ERL_NA_NA_QBTU.A | D14: quads | E14: 7.071282 | F14: 7.030098 | G14: 6.364577 | H14: 6.131857 | I14: 6.008963 | J14: 5.890632 | K14: 5.684556 | L14: 5.5596 | M14: 5.483474 | N14: 5.37458 | O14: 5.297432 | P14: 5.223444 | Q14: 5.182245 | R14: 5.157815 | S14: 5.1249 | T14: 5.075423 | U14: 5.032132 | V14: 5.019648 | W14: 5.019057 | X14: 5.021711 | Y14: 5.022737 | Z14: 5.028126 | AA14: 5.036541 | AB14: 5.04317 | AC14: 5.033889 | AD14: 5.040434 | AE14: -1.3%
A15: Total | B15: Energy Use: Residential: Total: Alternative Electricity and Transportation | C15: AEO.2026.ELECTRNP.CNSM_ENU_RESD_NA_TOT_NA_NA_QBTU.A | D15: quads | E15: 18.528812 | F15: 18.280319 | G15: 17.610821 | H15: 17.393257 | I15: 17.231632 | J15: 17.03693 | K15: 16.745705 | L15: 16.54524 | M15: 16.398506 | N15: 16.231991 | O15: 16.106035 | P15: 15.989944 | Q15: 15.908227 | R15: 15.849083 | S15: 15.783691 | T15: 15.698598 | U15: 15.625505 | V15: 15.594969 | W15: 15.584681 | X15: 15.581122 | Y15: 15.57497 | Z15: 15.573297 | AA15: 15.570335 | AB15: 15.56497 | AC15: 15.547426 | AD15: 15.547734 | AE15: -0.7%
A16: Commercial
A17: Propane | B17: Energy Use: Commercial: Propane: Alternative Electricity and Transportation | C17: AEO.2026.ELECTRNP.CNSM_ENU_COMM_NA_PROP_NA_NA_QBTU.A | D17: quads | E17: 0.215225 | F17: 0.219131 | G17: 0.221612 | H17: 0.224037 | I17: 0.226424 | J17: 0.228837 | K17: 0.231314 | L17: 0.233862 | M17: 0.236496 | N17: 0.239221 | O17: 0.242036 | P17: 0.244938 | Q17: 0.247903 | R17: 0.250787 | S17: 0.253585 | T17: 0.256302 | U17: 0.258878 | V17: 0.261334 | W17: 0.263708 | X17: 0.266017 | Y17: 0.268283 | Z17: 0.270516 | AA17: 0.27272 | AB17: 0.274898 | AC17: 0.277053 | AD17: 0.279188 | AE17: 1.0%
A18: Motor Gasoline | B18: Energy Use: Commercial: Motor Gasoline: Alternative Electricity and Transportation | C18: AEO.2026.ELECTRNP.CNSM_ENU_COMM_NA_MGS_NA_NA_QBTU.A | D18: quads | E18: 0.414315 | F18: 0.420968 | G18: 0.426488 | H18: 0.431913 | I18: 0.437276 | J18: 0.442694 | K18: 0.448233 | L18: 0.453909 | M18: 0.459748 | N18: 0.465758 | O18: 0.47194 | P18: 0.478287 | Q18: 0.484756 | R18: 0.491087 | S18: 0.497269 | T18: 0.503313 | U18: 0.509108 | V18: 0.514691 | W18: 0.520132 | X18: 0.525461 | Y18: 0.530719 | Z18: 0.535923 | AA18: 0.541079 | AB18: 0.546196 | AC18: 0.551277 | AD18: 0.556329 | AE18: 1.2%
