Workbook
Name income: Calculations!#REF!
Name Range_EV: Calculations!#REF!
Name range_ICE: Calculations!#REF!

Sheet About
A1: BNoEVC BAU Number of EV Chargers
A3: Source: | B3: Number of Gas pumps
B4: CleanTechnica
B5: 2018
B6: Stop Comparing the Number of Gas Stations to EV Charging Stations
B7: https://cleantechnica.com/2018/03/07/stop-comparing-number-gas-stations-ev-charging-stations/
B9: Number of EVSE Ports
B10: Alternative Fuels Data Center
B11: 2023
B12: Electric Vehicle Charging Station Locations
B13: https://afdc.energy.gov/fuels/electricity_locations.html#/analyze?fuel=ELEC&country=US
A15: Notes
A16: Currency Conversion | B16: 0.89805482
A17: 2019 to 2012 USD | B17: 0.84730413
A18: 2021 to 2012 USD | B18: 0.785
A19: 2022 to 2012 USD
A21: We assume that prior to the IIJA or IRA, the number of EV ports would slowly grow with time to equal the number of gas pumps by 2050.
A22: We adjust our calculations by an estimated number of public charger additions from both the Infrastructure Investment and Jobs Act
A23: and the Inflation Reduction Act (see tabs for methodology).

Sheet IIJA
A1: We assume EV charger additions based on investments in the Infrastructure Investment and Jobs Act
A2: ($7.5 billion between 2022 and 2026), assuming 80% of the costs are paid for by the government.
A4: Total government funding: | B4: 7500000000
A5: Total government + private funding: | B5: =B4/0.8 -> 9375000000
A6: Total funding in 2012 $ | B6: =B5*About!B17 -> 7.9434762e+09
A8: Average weighted charger cost (see trans/EVCC): | B8: 24443
A10: Annual chargers added through 2026 | B10: =B6/B8/5 -> 64995.919

Sheet Inflation Reduction Act
A1: Methodology:
A2: We calculate an incremental number of chargers deployed based on funding in the Inflation Reduction Act and the model's weighted average charger cost. We take estimated funding from the released JCT scores and assume 80% of the spending is directed toward public chargers. We do not attempt to model the effects of private chargers. The number of additional chargers is then fed into the shadow price used to represent range/charging anxiety for passenger LDV owners, which is partially determined by the ratio of charging infrastructure to gasoline pumps. This adjustment helps to drop the shadow price in response to additional infrastructure and increase consumer adoption of electric vehicles.
A4: Source: https://www.jct.gov/publications/2022/jcx-18-22/
A6: Calculations:
A7: EPS Weighted Avg Charger Cost (see trans/EVCC): | B7: 24443
A8: 2022 to 2012 $ | B8: 0.785
A10: Alternative fuel refueling property credit amount | B10: 0.3
A12: Assumed Amount of Spending Directed Toward Public LDV Chargers | B12: 0.8
B15: 2022 | C15: 2023 | D15: 2024 | E15: 2025 | F15: 2026 | G15: 2027 | H15: 2028 | I15: 2029 | J15: 2030 | K15: 2031 | L15: 2032
A16: JCT Estimates for Alternative fuel refueling property credit (million 2022$) | C16: 138 | D16: 128 | E16: 145 | F16: 164 | G16: 184 | H16: 207 | I16: 231 | J16: 257 | K16: 284
A18: Government Outlays After Transferability Multiplier of 7.5% | C18: =C16*0.925 -> 127.65 | D18: =D16*0.925 -> 118.4 | E18: =E16*0.925 -> 134.125 | F18: =F16*0.925 -> 151.7 | G18: =G16*0.925 -> 170.2 | H18: =H16*0.925 -> 191.475 | I18: =I16*0.925 -> 213.675 | J18: =J16*0.925 -> 237.725 | ... L18: =L16*0.925 -> 0
B20: 2022 | C20: 2023 | D20: 2024 | E20: 2025 | F20: 2026 | G20: 2027 | H20: 2028 | I20: 2029 | J20: 2030 | K20: 2031 | L20: 2032
A21: Number of Chargers Added | B21: 0 | C21: =(C18*10^6)/$B$10/($B$7/$B$8)*$B$12 -> 10932.128 | D21: =(D18*10^6)/$B$10/($B$7/$B$8)*$B$12 -> 10139.945 | E21: =(E18*10^6)/$B$10/($B$7/$B$8)*$B$12 -> 11486.656 | F21: =(F18*10^6)/$B$10/($B$7/$B$8)*$B$12 -> 12991.804 | G21: =(G18*10^6)/$B$10/($B$7/$B$8)*$B$12 -> 14576.17 | H21: =(H18*10^6)/$B$10/($B$7/$B$8)*$B$12 -> 16398.192 | I21: =(I18*10^6)/$B$10/($B$7/$B$8)*$B$12 -> 18299.431 | J21: =(J18*10^6)/$B$10/($B$7/$B$8)*$B$12 -> 20359.108 | K21: =(K18*10^6)/$B$10/($B$7/$B$8)*$B$12 -> 22498.002 | L21: =(L18*10^6)/$B$10/$B$7*$B$12 -> 0
A23: Chargers Added by 2032 | B23: =SUM(C21:K21) -> 137681.44

Sheet Calculations
A1: Number of gas pumps | B1: 1200000
A3: Assumed Number of EVSE ports
A4: 2022 | B4: 137902
A5: 2050 | B5: 1200000
B7: 2020 | C7: 2021 | D7: 2022 | E7: 2023 | F7: 2024 | G7: 2025 | H7: 2026 | I7: 2027 | J7: 2028 | K7: 2029 | L7: 2030 | M7: 2031 | N7: 2032 | O7: 2033 | P7: 2034 | Q7: 2035 | R7: 2036 | S7: 2037 | T7: 2038 | U7: 2039 | V7: 2040 | W7: 2041 | X7: 2042 | Y7: 2043 | Z7: 2044 | AA7: 2045 | AB7: 2046 | AC7: 2047 | AD7: 2048 | AE7: 2049 | AF7: 2050
A8: Pre-IIJA and IRA Assumption, Number of Chargers | B8: =D8 -> 137902 | C8: =D8 -> 137902 | D8: {=TREND($B$4:$B$5,$A$4:$A$5,D7)} -> 137902 | E8: {=TREND($B$4:$B$5,$A$4:$A$5,E7)} -> 175834.07 | F8: {=TREND($B$4:$B$5,$A$4:$A$5,F7)} -> 213766.14 | G8: {=TREND($B$4:$B$5,$A$4:$A$5,G7)} -> 251698.21 | H8: {=TREND($B$4:$B$5,$A$4:$A$5,H7)} -> 289630.29 | I8: {=TREND($B$4:$B$5,$A$4:$A$5,I7)} -> 327562.36 | J8: {=TREND($B$4:$B$5,$A$4:$A$5,J7)} -> 365494.43 | K8: {=TREND($B$4:$B$5,$A$4:$A$5,K7)} -> 403426.5 | ... AF8: {=TREND($B$4:$B$5,$A$4:$A$5,AF7)} -> 1200000
A9: IIJA Additional Chargers | B9: 0 | C9: 0 | E9: =IIJA!$B$10 -> 64995.919 | F9: =IIJA!$B$10 -> 64995.919 | G9: =IIJA!$B$10 -> 64995.919 | H9: =IIJA!$B$10 -> 64995.919 | I9: 0 | J9: 0 | K9: 0 | L9: 0 | M9: 0 | N9: 0 | O9: 0 | P9: 0 | Q9: 0 | R9: 0 | S9: 0 | T9: 0 | U9: 0 | V9: 0 | W9: 0 | X9: 0 | Y9: 0 | Z9: 0 | AA9: 0 | AB9: 0 | AC9: 0 | AD9: 0 | AE9: 0 | AF9: 0
A10: IRA Additional Chargers | B10: 0 | C10: 0 | D10: 0 | E10: ='Inflation Reduction Act'!C21 -> 10932.128 | F10: ='Inflation Reduction Act'!D21 -> 10139.945 | G10: ='Inflation Reduction Act'!E21 -> 11486.656 | H10: 0 | I10: 0 | J10: 0 | K10: 0 | L10: 0 | M10: 0 | N10: 0 | O10: 0 | P10: 0 | Q10: 0 | R10: 0 | S10: 0 | T10: 0 | U10: 0 | V10: 0 | W10: 0 | X10: 0 | Y10: 0 | Z10: 0 | AA10: 0 | AB10: 0 | AC10: 0 | AD10: 0 | AE10: 0 | AF10: 0
A11: Number of Chargers with IIJA and IRA Additions | B11: =SUM(B8:B10) -> 137902 | C11: =SUM(C8:C10) -> 137902 | D11: =C11+(D8-C8)+SUM(D9:D10) -> 137902 | E11: =D11+(E8-D8)+SUM(E9:E10) -> 251762.12 | F11: =E11+(F8-E8)+SUM(F9:F10) -> 364830.05 | G11: =F11+(G8-F8)+SUM(G9:G10) -> 479244.7 | H11: =G11+(H8-G8)+SUM(H9:H10) -> 582172.69 | I11: =H11+(I8-H8)+SUM(I9:I10) -> 620104.76 | J11: =I11+(J8-I8)+SUM(J9:J10) -> 658036.83 | K11: =J11+(K8-J8)+SUM(K9:K10) -> 695968.9 | ... AF11: =AE11+(AF8-AE8)+SUM(AF9:AF10) -> 1492542.4

Sheet SYNoEVC
A1: Number of chargers | B1: 2020
A2: BAU EV Chargers | B2: =Calculations!B8 -> 137902
