Workbook

Sheet About
A1: AVL Avg Vehicle Lifetime
A3: Sources: | B3: LDV Lifetimes | D3: Bus fleet and sales (bus lifetime)
B4: Calibrated | D4: U.S. Federal Highway Administration; School Bus Fleet; Bureau of Transportation Statistics; BloombergNEF
D5: FHWA Highway Statistics MV-1 (via BTS NTS 1-11); School Bus Fleet OEM sales survey; BTS NTS 1-12 transit bus deliveries; BNEF transit bus sales and fleet 2021
B6: LDVs: Market Shares of Cars and Light Trucks | D6: 2026
B7: Bureau of Transportation Statistics | D7: https://www.bts.gov/content/number-us-aircraft-vehicles-vessels-and-other-conveyances
B8: 2016 | D8: On tab 'Freight and Buses'. School and transit buses are the only bus segments with published sales, so the selected life is their turnover; registered-bus totals include private buses with no sales series.
B9: National Transportation Statistics 2015
B10: http://www.rita.dot.gov/bts/sites/rita.dot.gov.bts/files/publications/national_transportation_statistics/index.html | D10: Motorcycle fleet and sales (motorbike lifetime)
B11: Table 1-20 | D11: U.S. Federal Highway Administration; Motorcycle Industry Council
D12: FHWA Highway Statistics MV-1 registered motorcycles 2015-2024; MIC on-highway, dual-sport and scooter retail sales
B13: Freight HDVs | D13: 2026
B14: Oak Ridge National Laboratory | D14: https://www.fhwa.dot.gov/policyinformation/statistics.cfm
B15: 2015 | D15: On tab 'Calculations' (motorbike block). On-road sales only; the BTS motorcycle sales series includes off-highway bikes and would overstate turnover.
B16: Transportation Energy Data Book Ed. 34
B17: http://cta.ornl.gov/data/tedb34/Spreadsheets/Table3_14.xls | D17: Registered boats and boat sales (recreational boat lifetime)
B18: Table 3-14, Row 43 | D18: U.S. Coast Guard; National Marine Manufacturers Association
D19: USCG Recreational Boating Statistics, registered vessels 2015-2024 (via BTS NTS 1-11); NMMA new powerboat retail units 2016-2021 (BTS NTS 1-12) and 2024-2025 (NMMA releases)
B20: Passenger HDVs (Buses) | D20: 2026
B21: ThoughtCo | D21: https://www.uscgboating.org/statistics/
B22: 2019 | D22: On tab 'Calculations' (boat block). NMMA's powerboat count includes personal watercraft and excludes sailboats, which matches the registered fleet well enough for a turnover rate.
B23: How Long Do Buses and Other Transit Vehicles Last?
B24: https://www.thoughtco.com/buses-and-other-transit-lifetime-2798844 | D24: Rail vehicles and years built (passenger rail lifetime)
D25: Federal Transit Administration, National Transit Database; Bureau of Transportation Statistics
B26: aircraft | D26: NTD Vehicles - Age Distribution, 2024 report year (rail vehicles by year built); BTS NTS Table 1-11 transit rail vehicles 2014 and 2024
B27: Jiang, Helen. Boeing. | D27: 2026
B28: 2013 | D28: https://data.transportation.gov/Public-Transit/2022-2025-NTD-Annual-Data-Vehicles-Age-Distribution-/6abt-uhgq
B29: Key Findings on Airplane Economic Life | D29: On tab 'Calculations' (passenger rail block). Vehicles built 2012-19 that are still in the fleet stand in for deliveries; later years are under-reported as agencies catch up, so they are not used.
B30: http://www.boeing.com/assets/pdf/commercial/aircraft_economic_life_whitepaper.pdf
B31: Exhibits 1-3
B33: rail and ships
B34: California State Controller's Office
B35: 1992 (but still current)
B36: Audit Guidelines and Uniform Accounting Systems: Special Districts
B37: http://www.sco.ca.gov/ard_local_rep_uas_special_dist.html
B38: Appendix A: Suggested Useful Lives of Fixed Assets
B40: motorbikes
B41: Bureau of Transportation Statistics
B42: 2009
B43: Motorcycle Trends in the United States
B44: http://www.rita.dot.gov/bts/sites/rita.dot.gov.bts/files/publications/special_reports_and_issue_briefs/special_report/2009_05_14/pdf/entire.pdf
B45: Page 3, Table 1
B47: U.S. Energy Information Administration
B48: 2025
B49: Annual Energy Outlook 2025
B50: Scenario: Alternative Transportation
B51: https://www.eia.gov/outlooks/aeo/tables_side_xls.php
B52: Table 44, 45, 38, 49
A53: Notes:
A54: What this file is | B54: The median lifetime of each vehicle type, in whole years. It sets the survival curves (the VWSPbV, VWSbV and VWLbV files) for every type that has no fitted curve of its own, and so the retirement flow that the model replaces each year. Passenger LDVs, freight LDVs and heavy trucks carry fitted survival curves, so their values here are used only where a single number is needed. Where a stock-flow is used below, the lifetime is the fleet divided by the retirements that sales and fleet change imply, converted from a mean to a median with the survival curve's shape; the 'Calculations' and 'Freight and Buses' tabs show each step. The dark-blue tab is exported.
A55: Passenger LDVs, 17 years | B55: Calibrated so that the model's passenger LDV sales match observed sales (about 15 million a year), starting from average car and light-truck lifetimes of 13 and 14 years in the BTS motor-vehicle data.
A56: Freight LDVs, 15 years | B56: The same calibration logic applied to commercial light and medium trucks, against AEO's sales-to-stock replacement time.
A57: Buses, 13 years | B57: The turnover of the segments with published sales: about 480,000 school buses and 103,000 transit buses against roughly 45,000 sales a year. Transit buses average 7 years old and school buses are older, consistent with 13. A longer life would make the model buy far fewer buses than are sold; the registered-bus total, which includes private buses with no sales series, is not used.
A58: Heavy trucks, 20 years | B58: AEO's class 7-8 sales-to-stock replacement time, consistent with the Transportation Energy Data Book's 28-year maximum age.
A59: Passenger and freight aircraft, 24 years | B59: Boeing's analysis of aircraft economic life: aircraft in service average 23-24 years and leave service at 22-26 years (passenger) and 31-36 (freighters). One value is used for both.
A60: Passenger rail, 47 years | B60: Stock-flow of NTD data on the car basis: about 575 rail vehicles a year were built in 2012-19 and are still in service, while the fleet grew about 160 a year, so retirements are about 420 a year, 2% of the fleet. NTD shows 30% of rail vehicles over 30 years old and an average age of 23, so a long median is what the fleet looks like; FTA's 25-year useful life is a minimum for funding, not an observed life.
A61: Freight rail, 34 years | B61: The California State Controller's suggested asset lives for railroads (33) and electric locomotives (35). The AAR year-built data show 42% of Class I locomotives built before 2000, consistent with a long life; rebuilds extend it further but are not modeled separately.
A62: Recreational boats, 38 years | B62: Stock-flow of Coast Guard registrations against NMMA powerboat sales: about 270,000 boats sold a year against a fleet falling 20,000 a year gives about 290,000 retirements, 2.5% of 11.8 million boats. The 33-year ocean motor-vessel life applies to freight ships, not boats.
A63: Freight ships, 33 years | B63: The California State Controller's suggested asset life for ocean diesel motor vessels.
A64: Motorbikes, 22 years | B64: Stock-flow of FHWA registered motorcycles (growing 73,000 a year over 2015-24) against on-road sales of 354,000 to 386,000: retirements of about 300,000 a year, 3.3% of the fleet. The older 17-year figure came from the 2000s motorcycle boom with off-highway bikes included. Freight motorbikes do not exist in the U.S. model and take the same value.

Sheet source data>

Sheet NTS 1-20
A1: Table 1-20: Productions, Production Shares, and Production-Weighted Fuel Economies of New Domestic and Imported Automobiles (Thousands of vehicles)
B2: 1980 | C2: 1985 | D2: 1990 | E2: 1991 | F2: 1992 | G2: 1993 | H2: 1994 | I2: 1995 | J2: 1996 | K2: 1997 | L2: 1998 | M2: 1999 | N2: 2000 | O2: 2001 | P2: 2002 | Q2: 2003 | R2: 2004 | S2: 2005 | T2: 2006 | U2: 2007 | V2: 2008 | W2: 2009 | X2: 2010 | Y2: 2011 | Z2: 2012 | AA2: 2013 | AB2: 2014
A3: TOTAL productions | B3: 11306 | C3: 14460 | D3: 12615 | E3: 12573 | F3: 12172 | G3: 13211 | H3: 14125 | I3: 15145 | J3: 13144 | K3: 14458 | L3: 14456 | M3: 15215 | N3: 16571 | O3: 15605 | P3: 16115 | Q3: 15773 | R3: 15709 | S3: 15892 | T3: 15104 | U3: 15276 | V3: 13898 | W3: 9316 | X3: 11110 | Y3: 12003 | Z3: 13438 | AA3: 14846 | AB3: N
A4: Car | B4: 9443 | C4: 10791 | D4: 8810 | E4: 8524 | F4: 8108 | G4: 8456 | H4: 8415 | I4: 9396 | J4: 7890 | K4: 8334 | L4: 7971 | M4: 8376 | N4: 9125 | O4: 8405 | P4: 8301 | Q4: 7921 | R4: 7537 | S4: 8027 | T4: 7993 | U4: 8082 | V4: 7319 | W4: 5636 | X4: 6055 | Y4: 5728 | Z4: 7379 | AA4: 7907 | AB4: N
A5: Car SUV | B5: 0 | C5: 88 | D5: 65 | E5: 224 | F5: 243 | G5: 473 | H5: 332 | I5: 220 | J5: 287 | K5: 361 | L5: 454 | M5: 488 | N5: 617 | O5: 743 | P5: 603 | Q5: 575 | R5: 639 | S5: 813 | T5: 751 | U5: 919 | V5: 924 | W5: 608 | X5: 915 | Y5: 1207 | Z5: 1269 | AA5: 1470 | AB5: N
A6: Pickup | B6: 1437 | C6: 2078 | D6: 1835 | E6: 1920 | F6: 1840 | G6: 2002 | H6: 2669 | I6: 2271 | J6: 1955 | K6: 2408 | L6: 2415 | M6: 2544 | N6: 2612 | O6: 2519 | P6: 2380 | Q6: 2474 | R6: 2505 | S6: 2300 | T6: 2188 | U6: 2113 | V6: 1794 | W6: 989 | X6: 1276 | Y6: 1479 | Z6: 1357 | AA6: 1577 | AB6: N
A7: Van | B7: 242 | C7: 855 | D7: 1262 | E7: 1034 | F7: 1221 | G7: 1441 | H7: 1418 | I7: 1662 | J7: 1409 | K7: 1265 | L7: 1489 | M7: 1463 | N7: 1691 | O7: 1232 | P7: 1243 | Q7: 1232 | R7: 953 | S7: 1481 | T7: 1166 | U7: 847 | V7: 790 | W7: 368 | X7: 559 | Y7: 521 | Z7: 661 | AA7: 571 | AB7: N
A8: Truck SUV | B8: 184 | C8: 648 | D8: 643 | E8: 871 | F8: 761 | G8: 838 | H8: 1291 | I8: 1596 | J8: 1603 | K8: 2089 | L8: 2127 | M8: 2342 | N8: 2526 | O8: 2707 | P8: 3588 | Q8: 3571 | R8: 4075 | S8: 3272 | T8: 3006 | U8: 3314 | V8: 3072 | W8: 1713 | X8: 2305 | Y8: 3069 | Z8: 2773 | AA8: 3321 | AB8: N
A9: Market share, percent
A10: Car | B10: =B4/B$3*100 -> 83.522024 | C10: =C4/C$3*100 -> 74.626556 | D10: 69.8 | E10: 67.8 | F10: 66.6 | G10: 64 | H10: 59.6 | I10: 62 | J10: 60 | K10: 57.6 | L10: 55.1 | M10: 55.1 | N10: 55.1 | O10: 53.9 | P10: 51.5 | Q10: 50.2 | R10: 48 | S10: 50.5 | T10: 52.9 | U10: 52.9 | V10: 52.7 | W10: 60.5 | X10: 54.5 | Y10: 47.7 | Z10: 54.9 | AA10: 53.3 | AB10: 51.3
A11: Car SUV | B11: 0 | C11: 0.6 | D11: 0.5 | E11: 1.8 | F11: 2 | G11: 3.6 | H11: 2.3 | I11: 1.5 | J11: 2.2 | K11: 2.5 | L11: 3.1 | M11: 3.2 | N11: 3.7 | O11: 4.8 | P11: 3.7 | Q11: 3.6 | R11: 4.1 | S11: 5.1 | T11: 5 | U11: 6 | V11: 6.6 | W11: 6.5 | X11: 8.2 | Y11: 10.1 | Z11: 9.4 | AA11: 9.9 | AB11: 10
A12: Pickup | B12: 12.7 | C12: 14.4 | D12: 14.5 | E12: 15.3 | F12: 15.1 | G12: 15.2 | H12: 18.9 | I12: 15 | J12: 14.9 | K12: 16.7 | L12: 16.7 | M12: 16.7 | N12: 15.8 | O12: 16.1 | P12: 14.8 | Q12: 15.7 | R12: 15.9 | S12: 14.5 | T12: 14.5 | U12: 13.8 | V12: 12.9 | W12: 10.6 | X12: 11.5 | Y12: 12.3 | Z12: 10.1 | AA12: 10.6 | AB12: 11.5
A13: Van | B13: 2.1 | C13: 5.9 | D13: 10 | E13: 8.2 | F13: 10 | G13: 10.9 | H13: 10 | I13: 11 | J13: 10.7 | K13: 8.8 | L13: 10.3 | M13: 9.6 | N13: 10.2 | O13: 7.9 | P13: 7.7 | Q13: 7.8 | R13: 6.1 | S13: 9.3 | T13: 7.7 | U13: 5.5 | V13: 5.7 | W13: 4 | X13: 5 | Y13: 4.3 | Z13: 4.9 | AA13: 3.8 | AB13: 3.9
A14: Truck SUV | B14: 1.6 | C14: 4.5 | D14: 5.1 | E14: 6.9 | F14: 6.2 | G14: 6.3 | H14: 9.1 | I14: 10.5 | J14: 12.2 | K14: 14.5 | L14: 14.7 | M14: 15.4 | N14: 15.2 | O14: 17.3 | P14: 22.3 | Q14: 22.6 | R14: 25.9 | S14: 20.6 | T14: 19.9 | U14: 21.7 | V14: 22.1 | W14: 18.4 | X14: 20.8 | Y14: 25.6 | Z14: 20.6 | AA14: 22.4 | AB14: 23.3
A15: Fuel economy, mpg
A16: Car | B16: 20 | C16: 23 | D16: 23.3 | E16: 23.4 | F16: 23.1 | G16: 23.5 | H16: 23.3 | I16: 23.4 | J16: 23.3 | K16: 23.4 | L16: 23.4 | M16: 23 | N16: 22.9 | O16: 23 | P16: 23.1 | Q16: 23.3 | R16: 23.1 | S16: 23.5 | T16: 23.3 | U16: 24.1 | V16: 24.3 | W16: 25.3 | X16: 26.2 | Y16: 26 | Z16: 27.8 | AA16: 28.3 | AB16: 28.7
A17: Car SUV | B17: 14.6 | C17: 20.1 | D17: 18.8 | E17: 18.2 | F17: 17.8 | G17: 17 | H17: 18 | I17: 17.8 | J17: 18.4 | K17: 19.2 | L17: 18.2 | M17: 18.5 | N17: 17.9 | O17: 18.8 | P17: 19.3 | Q17: 19.9 | R17: 20 | S17: 20.2 | T17: 20.5 | U17: 20.6 | V17: 21.2 | W17: 22 | X17: 23 | Y17: 23.6 | Z17: 23.4 | AA17: 24.5 | AB17: 24.3
A18: Pickup | B18: 16.5 | C18: 18.2 | D18: 17.4 | E18: 18.2 | F18: 17.5 | G18: 17.6 | H18: 17.4 | I18: 16.9 | J18: 17.1 | K18: 16.8 | L18: 17 | M18: 16.3 | N18: 16.7 | O18: 16 | P18: 15.8 | Q18: 16.1 | R18: 15.7 | S18: 15.8 | T18: 16.1 | U18: 16.2 | V18: 16.5 | W18: 16.9 | X18: 16.9 | Y18: 17.2 | Z18: 17.2 | AA18: 17.4 | AB18: 18
A19: Van | B19: 14.1 | C19: 16.5 | D19: 17.8 | E19: 17.9 | F19: 17.9 | G19: 18.2 | H19: 17.8 | I19: 18.1 | J19: 18.3 | K19: 18.2 | L19: 18.7 | M19: 18.3 | N19: 18.6 | O19: 18 | P19: 18.7 | Q19: 19 | R19: 19.2 | S19: 19.3 | T19: 19.5 | U19: 19.5 | V19: 19.8 | W19: 20.1 | X19: 20.1 | Y19: 21 | Z19: 21.4 | AA19: 21.1 | AB19: 21.2
A20: Truck SUV | B20: 13.2 | C20: 16.5 | D20: 16.4 | E20: 16.7 | F20: 16.2 | G20: 16.3 | H20: 16 | I20: 16 | J20: 16.2 | K20: 16.1 | L20: 16.2 | M20: 16.1 | N20: 16 | O20: 16.4 | P20: 16.3 | Q20: 16.4 | R20: 16.5 | S20: 16.7 | T20: 17.2 | U20: 17.7 | V20: 18.2 | W20: 19.3 | X20: 19.7 | Y20: 19.8 | Z20: 20 | AA20: 20.9 | AB20: 21.2
A21: KEY: mpg = miles per gallon; N = data are not available; R = revised; SUV = sport utility vehicle.
A23: NOTES
A24: Numbers may not add to totals due to rounding.
A25: This table is not comparable to previous publication's tables due to changes in the source data.
A26: The Environmental Protection Agency changed the vehicle classifications, combining wagons with the rest of the cars and dropping the small, medium, large categories of cars, pickups, sport-utilities, and vans. The fuel economy displayed in those tables has been adjusted to provide the best estimate of real-world performance.
A28: SOURCE
A29: U.S. Department of Energy, Office of Energy Efficiency and Renewable Energy, Transportation Energy Data Book, Edition 33, tables 4.7, table 4.9 and table 4.11 (Oak Ridge, TN), available at http://cta.ornl.gov/data/index.shtml as of Dec. 8, 2015.

Sheet AEO 2026 Table 45
A1: Table 45. Transportation Fleet Car and Truck Stock by Type and Technology
A2: https://www.eia.gov/outlooks/aeo/data/browser/#/?id=55-AEO2026&cases=electrnp&sourcekey=0
A3: Thu Apr 23 2026 15:04:58 GMT-0700 (Pacific Daylight Time)
A4: Source: U.S. Energy Information Administration
B5: full name | C5: api key | D5: units | E5: 2025 | F5: 2026 | G5: 2027 | H5: 2028 | I5: 2029 | J5: 2030 | K5: 2031 | L5: 2032 | M5: 2033 | N5: 2034 | O5: 2035 | P5: 2036 | Q5: 2037 | R5: 2038 | S5: 2039 | T5: 2040 | U5: 2041 | V5: 2042 | W5: 2043 | X5: 2044 | Y5: 2045 | Z5: 2046 | AA5: 2047 | AB5: 2048 | AC5: 2049 | AD5: 2050 | AE5: Growth (2025-2050)
A6: Car Stock
A7: Conventional Cars
A8: Gasoline ICE Vehicles | B8: Fleet Vehicle Stock: Conventional Cars: Gasoline: Alternative Electricity and Transportation | C8: AEO.2026.ELECTRNP.ECI_STK_CNV_FLC_GSL_NA_NA_TH.A | D8: thousands | E8: 5200.4526 | F8: 4904.3384 | G8: 4575.9521 | H8: 4294.0498 | I8: 4068.2461 | J8: 3891.0559 | K8: 3732.8235 | L8: 3585.3479 | M8: 3451.0632 | N8: 3324.0464 | O8: 3205.0349 | P8: 3085.6714 | Q8: 2977.6858 | R8: 2880.26 | S8: 2790.3772 | T8: 2705.311 | U8: 2623.4365 | V8: 2544.8809 | W8: 2468.8469 | X8: 2396.1611 | Y8: 2328.1196 | Z8: 2262.8105 | AA8: 2201.9463 | AB8: 2142.689 | AC8: 2084.9839 | AD8: 2026.223 | AE8: -0.037
A9: TDI Diesel ICE | B9: Fleet Vehicle Stock: Conventional Cars: TDI Diesel: Alternative Electricity and Transportation | C9: AEO.2026.ELECTRNP.ECI_STK_CNV_FLC_TDS_NA_NA_TH.A | D9: thousands | E9: 15.814128 | F9: 13.938295 | G9: 12.193138 | H9: 10.563546 | I9: 9.060416 | J9: 7.707277 | K9: 6.508159 | L9: 5.461804 | M9: 4.575233 | N9: 3.841874 | O9: 3.24966 | P9: 2.781465 | Q9: 2.41583 | R9: 2.134801 | S9: 1.917431 | T9: 1.736284 | U9: 1.57695 | V9: 1.436198 | W9: 1.310303 | X9: 1.196242 | Y9: 1.09238 | Z9: 0.997788 | AA9: 0.911623 | AB9: 0.833118 | AC9: 0.761579 | AD9: 0.696374 | AE9: -0.117
A10: Total Conventional Cars | B10: Fleet Vehicle Stock: Conventional Cars: Total: Alternative Electricity and Transportation | C10: AEO.2026.ELECTRNP.ECI_STK_CNV_FLC_NA_NA_NA_TH.A | D10: thousands | E10: 5216.2666 | F10: 4918.2769 | G10: 4588.1455 | H10: 4304.6133 | I10: 4077.3064 | J10: 3898.7632 | K10: 3739.3315 | L10: 3590.8098 | M10: 3455.6384 | N10: 3327.8882 | O10: 3208.2847 | P10: 3088.4529 | Q10: 2980.1016 | R10: 2882.3948 | S10: 2792.2947 | T10: 2707.0474 | U10: 2625.0134 | V10: 2546.3171 | W10: 2470.1572 | X10: 2397.3574 | Y10: 2329.2119 | Z10: 2263.8083 | AA10: 2202.8579 | AB10: 2143.522 | AC10: 2085.7454 | AD10: 2026.9194 | AE10: -0.037
A11: Alternative-Fuel Cars
A12: Ethanol-Flex Fuel ICE | B12: Fleet Vehicle Stock: Alternative-Fuel Cars: Ethanol-Flex Fuel ICE: Alternative Electricity and Transportation | C12: AEO.2026.ELECTRNP.ECI_STK_ALF1_FLC_EFFI_NA_NA_TH.A | D12: thousands | E12: 193.21745 | F12: 159.50981 | G12: 136.48273 | H12: 116.07923 | I12: 97.928757 | J12: 81.966225 | K12: 68.266495 | L12: 56.709991 | M12: 47.370358 | N12: 39.852268 | O12: 33.936234 | P12: 29.400446 | Q12: 25.805008 | R12: 22.915279 | S12: 20.616272 | T12: 18.729715 | U12: 17.147816 | V12: 15.794521 | W12: 14.636535 | X12: 13.635636 | Y12: 12.752481 | Z12: 11.956233 | AA12: 11.247208 | AB12: 10.631876 | AC12: 10.063699 | AD12: 9.538871 | AE12: -0.113
A13: 100-Mile Electric Vehicle | B13: Fleet Vehicle Stock: Alternative-Fuel Cars: 100-Mile Electric Vehicle: Alternative Electricity and Transportation | C13: AEO.2026.ELECTRNP.ECI_STK_ALF1_FLC_100MIEV_NA_NA_TH.A | D13: thousands | E13: 12.823667 | F13: 12.981208 | G13: 12.843882 | H13: 12.388824 | I13: 12.017113 | J13: 11.894691 | K13: 11.852228 | L13: 11.957543 | M13: 12.171066 | N13: 12.487912 | O13: 12.924793 | P13: 13.402992 | Q13: 13.933009 | R13: 14.512439 | S13: 15.111438 | T13: 15.709825 | U13: 16.255154 | V13: 16.760593 | W13: 17.227583 | X13: 17.645254 | Y13: 18.057564 | Z13: 18.413551 | AA13: 18.755608 | AB13: 19.067127 | AC13: 19.337585 | AD13: 19.542181 | AE13: 0.017
A14: 200-Mile Electric Vehicle | B14: Fleet Vehicle Stock: Alternative-Fuel Cars: 200-Mile Electric Vehicle: Alternative Electricity and Transportation | C14: AEO.2026.ELECTRNP.ECI_STK_ALF1_FLC_200MIEV_NA_NA_TH.A | D14: thousands | E14: 49.358566 | F14: 58.074745 | G14: 76.353798 | H14: 89.212097 | I14: 96.488159 | J14: 97.371002 | K14: 99.096672 | L14: 101.12775 | M14: 105.95017 | N14: 112.0268 | O14: 119.13989 | P14: 125.43132 | Q14: 131.71814 | R14: 137.8517 | S14: 143.6964 | T14: 148.72258 | U14: 153.47376 | V14: 157.99193 | W14: 162.17264 | X14: 165.96719 | Y14: 169.20833 | Z14: 172.41849 | AA14: 175.7299 | AB14: 178.67452 | AC14: 181.32904 | AD14: 183.35115 | AE14: 0.054
A15: 300-Mile Electric Vehicle | B15: Fleet Vehicle Stock: Alternative-Fuel Cars: 300-Mile Electric Vehicle: Alternative Electricity and Transportation | C15: AEO.2026.ELECTRNP.ECI_STK_ALF1_FLC_300MIEV_NA_NA_TH.A | D15: thousands | E15: 263.59168 | F15: 300.86673 | G15: 348.64984 | H15: 384.50433 | I15: 434.91431 | J15: 488.20209 | K15: 545.43536 | L15: 600.52863 | M15: 657.31561 | N15: 711.00708 | O15: 764.95624 | P15: 812.79352 | Q15: 858.64795 | R15: 902.62231 | S15: 944.09613 | T15: 981.4776 | U15: 1014.7573 | V15: 1044.864 | W15: 1071.6549 | X15: 1095.3257 | Y15: 1117.1243 | Z15: 1136.2902 | AA15: 1154.9224 | AB15: 1171.0825 | AC15: 1184.9039 | AD15: 1194.4635 | AE15: 0.062
A16: Plug-in 20 Gasoline Hybrid | B16: Fleet Vehicle Stock: Alternative-Fuel Cars: Plug-in 20 Gasoline Hybrid: Alternative Electricity and Transportation | C16: AEO.2026.ELECTRNP.ECI_STK_ALF1_FLC_PI20GH_NA_NA_TH.A | D16: thousands | E16: 34.596752 | F16: 30.608488 | G16: 27.326748 | H16: 26.614899 | I16: 25.900885 | J16: 25.315302 | K16: 24.233877 | L16: 23.190699 | M16: 22.490473 | N16: 21.979679 | O16: 21.573814 | P16: 21.04114 | Q16: 20.545706 | R16: 20.059357 | S16: 19.597324 | T16: 19.087015 | U16: 18.624937 | V16: 18.216772 | W16: 17.840681 | X16: 17.466496 | Y16: 17.061407 | Z16: 16.704313 | AA16: 16.385477 | AB16: 16.069012 | AC16: 15.745203 | AD16: 15.398971 | AE16: -0.032
A17: Plug-in 50 Gasoline Hybrid | B17: Fleet Vehicle Stock: Alternative-Fuel Cars: Plug-in 50 Gasoline Hybrid: Alternative Electricity and Transportation | C17: AEO.2026.ELECTRNP.ECI_STK_ALF1_FLC_PI50GH_NA_NA_TH.A | D17: thousands | E17: 19.589474 | F17: 24.650236 | G17: 32.934143 | H17: 39.004486 | I17: 37.118404 | J17: 33.069084 | K17: 29.835768 | L17: 27.469379 | M17: 26.31011 | N17: 25.836098 | O17: 25.82777 | P17: 25.819584 | Q17: 25.847315 | R17: 25.905813 | S17: 26.000364 | T17: 26.069088 | U17: 26.039118 | V17: 25.966375 | W17: 25.866949 | X17: 25.739273 | Y17: 25.665237 | Z17: 25.554262 | AA17: 25.507757 | AB17: 25.466749 | AC17: 25.447727 | AD17: 25.379066 | AE17: 0.01
A18: Electric-Gasoline Hybrid | B18: Fleet Vehicle Stock: Alternative-Fuel Cars: Electric-Gasoline Hybrid: Alternative Electricity and Transportation | C18: AEO.2026.ELECTRNP.ECI_STK_ALF1_FLC_EGH_NA_NA_TH.A | D18: thousands | E18: 287.18549 | F18: 318.71747 | G18: 342.02924 | H18: 352.97415 | I18: 359.95718 | J18: 369.39511 | K18: 381.5592 | L18: 393.66666 | M18: 407.05731 | N18: 419.79788 | O18: 432.14249 | P18: 441.82434 | Q18: 451.03738 | R18: 459.88 | S18: 468.02075 | T18: 475.0647 | U18: 480.99243 | V18: 485.98746 | W18: 489.92267 | X18: 493.09201 | Y18: 496.01276 | Z18: 498.5032 | AA18: 501.18487 | AB18: 503.39868 | AC18: 505.07394 | AD18: 505.58981 | AE18: 0.023
A19: Fuel Cell Hydrogen | B19: Fleet Vehicle Stock: Alternative-Fuel Cars: Fuel Cell Hydrogen: Alternative Electricity and Transportation | C19: AEO.2026.ELECTRNP.ECI_STK_ALF1_FLC_FCH_NA_NA_TH.A | D19: thousands | E19: 0.949052 | F19: 0.864998 | G19: 0.796722 | H19: 0.735669 | I19: 0.676834 | J19: 0.619557 | K19: 0.561393 | L19: 0.502012 | M19: 0.443478 | N19: 0.385677 | O19: 0.330998 | P19: 0.279892 | Q19: 0.233957 | R19: 0.193587 | S19: 0.159393 | T19: 0.13141 | U19: 0.109955 | V19: 0.093902 | W19: 0.081649 | X19: 0.072316 | Y19: 0.065349 | Z19: 0.060264 | AA19: 0.056443 | AB19: 0.053208 | AC19: 0.050313 | AD19: 0.047672 | AE19: -0.113
A20: Total Alternative Cars | B20: Fleet Vehicle Stock: Alternative-Fuel Cars: Total: Alternative Electricity and Transportation | C20: AEO.2026.ELECTRNP.ECI_STK_ALF1_FLC_NA_NA_NA_TH.A | D20: thousands | E20: 874.46881 | F20: 918.14514 | G20: 988.16138 | H20: 1031.1885 | I20: 1073.6791 | J20: 1115.6639 | K20: 1167.8727 | L20: 1221.469 | M20: 1284.7955 | N20: 1348.5228 | O20: 1415.5183 | P20: 1474.2825 | Q20: 1531.7611 | R20: 1587.6694 | S20: 1640.7957 | T20: 1688.2784 | U20: 1730.4884 | V20: 1768.5769 | W20: 1802.1298 | X20: 1831.5054 | Y20: 1858.3541 | Z20: 1882.1621 | AA20: 1905.9146 | AB20: 1926.4403 | AC20: 1943.8274 | AD20: 1955.074 | AE20: 0.033
A21: Total Car Stock | B21: Fleet Vehicle Stock: Cars: Total: Alternative Electricity and Transportation | C21: AEO.2026.ELECTRNP.ECI_STK_NA_FLC_NA_NA_NA_TH.A | D21: thousands | E21: 6090.7354 | F21: 5836.4219 | G21: 5576.3066 | H21: 5335.8018 | I21: 5150.9854 | J21: 5014.4272 | K21: 4907.2041 | L21: 4812.2788 | M21: 4740.4341 | N21: 4676.4111 | O21: 4623.8027 | P21: 4562.7354 | Q21: 4511.8628 | R21: 4470.0645 | S21: 4433.0903 | T21: 4395.3257 | U21: 4355.502 | V21: 4314.894 | W21: 4272.2871 | X21: 4228.8628 | Y21: 4187.5659 | Z21: 4145.9707 | AA21: 4108.7725 | AB21: 4069.9624 | AC21: 4029.5728 | AD21: 3981.9934 | AE21: -0.017
A22: Light Truck Stock
A23: Conventional Light Trucks
A24: Gasoline ICE Vehicles | B24: Fleet Vehicle Stock: Conventional Light Trucks: Gasoline: Alternative Electricity and Transportation | C24: AEO.2026.ELECTRNP.ECI_STK_CNV_FLTR_GSL_NA_NA_TH.A | D24: thousands | E24: 9500.2549 | F24: 9485.5742 | G24: 9426.8271 | H24: 9374.4473 | I24: 9420.6514 | J24: 9537.374 | K24: 9692.0547 | L24: 9842.9268 | M24: 9938.6143 | N24: 9986.3018 | O24: 9994.792 | P24: 9961.7373 | Q24: 9912.3682 | R24: 9851.3711 | S24: 9766.0889 | T24: 9673.0342 | U24: 9571.8486 | V24: 9462.0811 | W24: 9347.7188 | X24: 9230.7568 | Y24: 9111.1758 | Z24: 8989.4072 | AA24: 8862.6318 | AB24: 8731.4199 | AC24: 8593.6182 | AD24: 8447.0303 | AE24: -0.005
A25: TDI Diesel ICE | B25: Fleet Vehicle Stock: Conventional Light Trucks: TDI Diesel: Alternative Electricity and Transportation | C25: AEO.2026.ELECTRNP.ECI_STK_CNV_FLTR_TDS_NA_NA_TH.A | D25: thousands | E25: 110.0193 | F25: 122.5195 | G25: 132.05486 | H25: 139.49692 | I25: 146.40074 | J25: 153.45625 | K25: 160.04947 | L25: 166.03966 | M25: 171.30579 | N25: 176.15753 | O25: 180.27542 | P25: 183.36118 | Q25: 185.92255 | R25: 188.11433 | S25: 189.85066 | T25: 191.04047 | U25: 191.84402 | V25: 192.33519 | W25: 192.52586 | X25: 192.42023 | Y25: 191.95677 | Z25: 191.46834 | AA25: 190.80849 | AB25: 190.02399 | AC25: 188.93823 | AD25: 187.62779 | AE25: 0.022
A26: Total Conventional Light Trucks | B26: Fleet Vehicle Stock: Conventional Light Trucks: Total: Alternative Electricity and Transportation | C26: AEO.2026.ELECTRNP.ECI_STK_CNV_FLTR_NA_NA_NA_TH.A | D26: thousands | E26: 9610.2744 | F26: 9608.0938 | G26: 9558.8818 | H26: 9513.9443 | I26: 9567.0518 | J26: 9690.8301 | K26: 9852.1045 | L26: 10008.967 | M26: 10109.92 | N26: 10162.459 | O26: 10175.067 | P26: 10145.099 | Q26: 10098.291 | R26: 10039.485 | S26: 9955.9395 | T26: 9864.0742 | U26: 9763.6924 | V26: 9654.416 | W26: 9540.2441 | X26: 9423.1768 | Y26: 9303.1328 | Z26: 9180.876 | AA26: 9053.4404 | AB26: 8921.4443 | AC26: 8782.5566 | AD26: 8634.6582 | AE26: -0.004
A27: Alternative-Fuel Light Trucks
A28: Ethanol-Flex Fuel ICE | B28: Fleet Vehicle Stock: Alternative-Fuel Light Trucks: Ethanol-Flex Fuel ICE: Alternative Electricity and Transportation | C28: AEO.2026.ELECTRNP.ECI_STK_ALF1_FLTR_EFFI_NA_NA_TH.A | D28: thousands | E28: 1007.2556 | F28: 870.78906 | G28: 771.02258 | H28: 680.4483 | I28: 596.8443 | J28: 520.00269 | K28: 450.6156 | L28: 388.65585 | M28: 333.94754 | N28: 286.29788 | O28: 245.38309 | P28: 210.63995 | Q28: 181.58752 | R28: 157.65451 | S28: 137.72523 | T28: 120.98581 | U28: 107.05018 | V28: 95.466614 | W28: 85.941582 | X28: 78.031693 | Y28: 71.333115 | Z28: 65.642509 | AA28: 60.793465 | AB28: 56.536846 | AC28: 52.695965 | AD28: 49.226734 | AE28: -0.114
A29: 100-Mile Electric Vehicle | B29: Fleet Vehicle Stock: Alternative-Fuel Light Trucks: 100-Mile Electric Vehicle: Alternative Electricity and Transportation | C29: AEO.2026.ELECTRNP.ECI_STK_ALF1_FLTR_100MIEV_NA_NA_TH.A | D29: thousands | E29: 0.998046 | F29: 1.224324 | G29: 1.434016 | H29: 1.612743 | I29: 1.81001 | J29: 2.057015 | K29: 2.332481 | L29: 2.638899 | M29: 2.970936 | N29: 3.312224 | O29: 3.669823 | P29: 4.024693 | Q29: 4.383288 | R29: 4.745573 | S29: 5.111744 | T29: 5.478789 | U29: 5.831968 | V29: 6.173477 | W29: 6.504694 | X29: 6.826125 | Y29: 7.145949 | Z29: 7.445385 | AA29: 7.733372 | AB29: 8.003904 | AC29: 8.257642 | AD29: 8.483736 | AE29: 0.089
A30: 200-Mile Electric Vehicle | B30: Fleet Vehicle Stock: Alternative-Fuel Light Trucks: 200-Mile Electric Vehicle: Alternative Electricity and Transportation | C30: AEO.2026.ELECTRNP.ECI_STK_ALF1_FLTR_200MIEV_NA_NA_TH.A | D30: thousands | E30: 31.350508 | F30: 74.368172 | G30: 136.70589 | H30: 204.58423 | I30: 264.52899 | J30: 302.96585 | K30: 327.23053 | L30: 339.48434 | M30: 359.05701 | N30: 385 | O30: 416.31107 | P30: 447.93219 | Q30: 480.79114 | R30: 514.51483 | S30: 547.89514 | T30: 581.35474 | U30: 613.88788 | V30: 645.62732 | W30: 676.58795 | X30: 706.87476 | Y30: 736.98785 | Z30: 765.62231 | AA30: 793.84613 | AB30: 820.5882 | AC30: 846.39441 | AD30: 869.89203 | AE30: 0.142
A31: 300-Mile Electric Vehicle | B31: Fleet Vehicle Stock: Alternative-Fuel Light Trucks: 300-Mile Electric Vehicle: Alternative Electricity and Transportation | C31: AEO.2026.ELECTRNP.ECI_STK_ALF1_FLTR_300MIEV_NA_NA_TH.A | D31: thousands | E31: 131.8945 | F31: 218.22766 | G31: 319.21445 | H31: 427.61621 | I31: 519.14703 | J31: 598.8775 | K31: 652.34125 | L31: 703.94128 | M31: 767.26276 | N31: 840.14691 | O31: 920.04553 | P31: 998.25732 | Q31: 1077.3264 | R31: 1156.8517 | S31: 1235.5844 | T31: 1313.3093 | U31: 1387.3439 | V31: 1458.1968 | W31: 1526.0869 | X31: 1591.3063 | Y31: 1655.2568 | Z31: 1714.7753 | AA31: 1772.1117 | AB31: 1825.3832 | AC31: 1875.2927 | AD31: 1919.2892 | AE31: 0.113
A32: Plug-in 20 Gasoline Hybrid | B32: Fleet Vehicle Stock: Alternative-Fuel Light Trucks: Plug-in 20 Gasoline Hybrid: Alternative Electricity and Transportation | C32: AEO.2026.ELECTRNP.ECI_STK_ALF1_FLTR_PI20GH_NA_NA_TH.A | D32: thousands | E32: 122.12784 | F32: 109.80188 | G32: 105.26385 | H32: 112.53404 | I32: 120.32596 | J32: 128.97658 | K32: 138.9632 | L32: 149.43585 | M32: 160.94911 | N32: 173.17796 | O32: 186.35577 | P32: 198.1078 | Q32: 209.28947 | R32: 220.11481 | S32: 230.61597 | T32: 240.00815 | U32: 248.14912 | V32: 255.41205 | W32: 262.11166 | X32: 268.10059 | Y32: 273.49014 | Z32: 278.10757 | AA32: 282.30191 | AB32: 285.72101 | AC32: 288.57199 | AD32: 290.41791 | AE32: 0.035
A33: Plug-in 50 Gasoline Hybrid | B33: Fleet Vehicle Stock: Alternative-Fuel Light Trucks: Plug-in 50 Gasoline Hybrid: Alternative Electricity and Transportation | C33: AEO.2026.ELECTRNP.ECI_STK_ALF1_FLTR_PI50GH_NA_NA_TH.A | D33: thousands | E33: 21.128172 | F33: 63.923275 | G33: 127.46903 | H33: 198.09959 | I33: 204.47481 | J33: 194.68616 | K33: 177.24062 | L33: 158.29658 | M33: 146.7289 | N33: 141.22395 | O33: 138.79694 | P33: 136.70372 | Q33: 134.75311 | R33: 132.77786 | S33: 130.82497 | T33: 128.74747 | U33: 126.18153 | V33: 123.2283 | W33: 120.0466 | X33: 116.77601 | Y33: 113.73335 | Z33: 110.68338 | AA33: 107.94883 | AB33: 105.44351 | AC33: 103.29976 | AD33: 101.36417 | AE33: 0.065
A34: Electric-Gasoline Hybrid | B34: Fleet Vehicle Stock: Alternative-Fuel Light Trucks: Electric-Gasoline Hybrid: Alternative Electricity and Transportation | C34: AEO.2026.ELECTRNP.ECI_STK_ALF1_FLTR_EGH_NA_NA_TH.A | D34: thousands | E34: 532.14844 | F34: 776.49652 | G34: 993.47315 | H34: 1195.9524 | I34: 1387.8796 | J34: 1573.0736 | K34: 1745.166 | L34: 1900.5806 | M34: 2044.6385 | N34: 2176.8999 | O34: 2298.969 | P34: 2405.2585 | Q34: 2503.7341 | R34: 2594.5647 | S34: 2690.9143 | T34: 2777.6707 | U34: 2850.6106 | V34: 2910.7866 | W34: 2963.3218 | X34: 3010.3772 | Y34: 3053.2241 | Z34: 3091.2175 | AA34: 3124.9641 | AB34: 3153.6448 | AC34: 3178.0256 | AD34: 3196.3552 | AE34: 0.074
A35: Fuel Cell Hydrogen | B35: Fleet Vehicle Stock: Alternative-Fuel Light Trucks: Fuel Cell Hydrogen: Alternative Electricity and Transportation | C35: AEO.2026.ELECTRNP.ECI_STK_ALF1_FLTR_FCH_NA_NA_TH.A | D35: thousands | E35: 0 | F35: 0 | G35: 0 | H35: 0 | I35: 0 | J35: 0 | K35: 0 | L35: 0 | M35: 0 | N35: 0 | O35: 0 | P35: 0 | Q35: 0 | R35: 0 | S35: 0 | T35: 0 | U35: 0 | V35: 0 | W35: 0 | X35: 0 | Y35: 0 | Z35: 0 | AA35: 0 | AB35: 0 | AC35: 0 | AD35: 0 | AE35: - -
A36: Total Alternative Light Trucks | B36: Fleet Vehicle Stock: Alternative-Fuel Light Trucks: Total: Alternative Electricity and Transportation | C36: AEO.2026.ELECTRNP.ECI_STK_ALF1_FLTR_NA_NA_NA_TH.A | D36: thousands | E36: 1858.9742 | F36: 2126.1035 | G36: 2465.1501 | H36: 2830.7666 | I36: 3104.3303 | J36: 3329.3943 | K36: 3502.1111 | L36: 3650.751 | M36: 3822.7976 | N36: 4012.8557 | O36: 4215.9092 | P36: 4406.9121 | Q36: 4597.4941 | R36: 4786.5161 | S36: 4983.6494 | T36: 5172.2368 | U36: 5343.459 | V36: 5499.0332 | W36: 5644.4971 | X36: 5781.9575 | Y36: 5914.6187 | Z36: 6036.7368 | AA36: 6152.7495 | AB36: 6258.1904 | AC36: 6355.2363 | AD36: 6437.5669 | AE36: 0.051
A37: Total Light Truck Stock | B37: Fleet Vehicle Stock: Light Trucks: Total: Alternative Electricity and Transportation | C37: AEO.2026.ELECTRNP.ECI_STK_NA_FLTR_NA_NA_NA_TH.A | D37: thousands | E37: 11469.249 | F37: 11734.197 | G37: 12024.032 | H37: 12344.711 | I37: 12671.382 | J37: 13020.225 | K37: 13354.216 | L37: 13659.718 | M37: 13932.718 | N37: 14175.314 | O37: 14390.977 | P37: 14552.011 | Q37: 14695.785 | R37: 14826.002 | S37: 14939.589 | T37: 15036.311 | U37: 15107.151 | V37: 15153.449 | W37: 15184.741 | X37: 15205.135 | Y37: 15217.752 | Z37: 15217.613 | AA37: 15206.189 | AB37: 15179.635 | AC37: 15137.793 | AD37: 15072.225 | AE37: 0.011
A38: Total Fleet Vehicles | B38: Fleet Stock: Total Fleet Vehicles: Alternative Electricity and Transportation | C38: AEO.2026.ELECTRNP.ECI_STK_NA_NA_NA_NA_NA_TH.A | D38: thousands | E38: 17559.984 | F38: 17570.619 | G38: 17600.34 | H38: 17680.512 | I38: 17822.367 | J38: 18034.652 | K38: 18261.42 | L38: 18471.996 | M38: 18673.152 | N38: 18851.727 | O38: 19014.779 | P38: 19114.746 | Q38: 19207.648 | R38: 19296.066 | S38: 19372.68 | T38: 19431.637 | U38: 19462.652 | V38: 19468.344 | W38: 19457.027 | X38: 19433.998 | Y38: 19405.318 | Z38: 19363.584 | AA38: 19314.961 | AB38: 19249.598 | AC38: 19167.365 | AD38: 19054.219 | AE38: 0.003
A39: Motor Gasoline | B39: Fleet Stock: Commercial Light Trucks: Gasoline: Alternative Electricity and Transportation | C39: AEO.2026.ELECTRNP.ECI_STK_NA_CLTR_GSL_NA_NA_TH.A | D39: thousands | E39: 7882.2637 | F39: 7718.1157 | G39: 7629.0815 | H39: 7589.3721 | I39: 7590.8135 | J39: 7633.5 | K39: 7698.8799 | L39: 7782.9263 | M39: 7859.0767 | N39: 7919.3301 | O39: 7952.2817 | P39: 7956.8364 | Q39: 7931.2661 | R39: 7882.021 | S39: 7812.3657 | T39: 7721.0332 | U39: 7608.1904 | V39: 7477.1328 | W39: 7346.2534 | X39: 7216.3901 | Y39: 7075.6992 | Z39: 6920.3643 | AA39: 6762.7627 | AB39: 6594.4473 | AC39: 6411.7974 | AD39: 6213.7129 | AE39: -0.009
A40: Diesel | B40: Fleet Stock: Commercial Light Trucks: TDI Diesel: Alternative Electricity and Transportation | C40: AEO.2026.ELECTRNP.ECI_STK_NA_CLTR_TDS_NA_NA_TH.A | D40: thousands | E40: 5002.978 | F40: 4920.6372 | G40: 4838.4229 | H40: 4754.917 | I40: 4667.8301 | J40: 4577.2856 | K40: 4477.2271 | L40: 4384.5674 | M40: 4277.0864 | N40: 4162.5894 | O40: 4032.8044 | P40: 3892.822 | Q40: 3743.9099 | R40: 3586.1233 | S40: 3426.6826 | T40: 3261.0994 | U40: 3103.415 | V40: 2952.2263 | W40: 2821.3669 | X40: 2704.1667 | Y40: 2587.6079 | Z40: 2472.3601 | AA40: 2362.5249 | AB40: 2255.0486 | AC40: 2139.4744 | AD40: 2021.7506 | AE40: -0.036
A41: Propane | B41: Fleet Stock: Commercial Light Trucks: Propane: Alternative Electricity and Transportation | C41: AEO.2026.ELECTRNP.ECI_STK_NA_CLTR_PROP_NA_NA_TH.A | D41: thousands | E41: 0.02939 | F41: 0.02805 | G41: 0.028767 | H41: 0.030853 | I41: 0.03399 | J41: 0.037803 | K41: 0.04211 | L41: 0.046904 | M41: 0.05197 | N41: 0.056927 | O41: 0.06194 | P41: 0.066981 | Q41: 0.07206 | R41: 0.077115 | S41: 0.082076 | T41: 0.086895 | U41: 0.091472 | V41: 0.09579 | W41: 0.099874 | X41: 0.103683 | Y41: 0.107246 | Z41: 0.110537 | AA41: 0.113551 | AB41: 0.116289 | AC41: 0.118748 | AD41: 0.120917 | AE41: 0.058
A42: Compressed/Liquefied Natural Gas | B42: Fleet Stock: Commercial Light Trucks: CNG/LNG: Alternative Electricity and Transportation | C42: AEO.2026.ELECTRNP.ECI_STK_NA_CLTR_NG_NA_NA_TH.A | D42: thousands | E42: 14.123592 | F42: 17.557981 | G42: 19.892176 | H42: 21.965725 | I42: 23.452375 | J42: 25.092058 | K42: 26.851217 | L42: 29.061224 | M42: 31.537632 | N42: 34.389294 | O42: 38.13509 | P42: 42.418118 | Q42: 47.842068 | R42: 54.623901 | S42: 62.418179 | T42: 72.016266 | U42: 82.636162 | V42: 94.554367 | W42: 107.83039 | X42: 122.37821 | Y42: 138.17296 | Z42: 155.49026 | AA42: 173.50885 | AB42: 192.23401 | AC42: 211.13888 | AD42: 230.72141 | AE42: 0.118
A43: Ethanol-Flex Fuel | B43: Fleet Stock: Commercial Light Trucks: Ethanol Flex: Alternative Electricity and Transportation | C43: AEO.2026.ELECTRNP.ECI_STK_NA_CLTR_EFFI_NA_NA_TH.A | D43: thousands | E43: 1585.9047 | F43: 1550.9897 | G43: 1511.9269 | H43: 1469.2751 | I43: 1421.6934 | J43: 1369.3641 | K43: 1312.3472 | L43: 1251.1041 | M43: 1187.1036 | N43: 1120.3492 | O43: 1052.595 | P43: 985.46448 | Q43: 919.91101 | R43: 856.78522 | S43: 796.59528 | T43: 740.64648 | U43: 689.74896 | V43: 644.09656 | W43: 603.90698 | X43: 562.47321 | Y43: 520.17755 | Z43: 480.65726 | AA43: 438.79761 | AB43: 395.52585 | AC43: 348.95233 | AD43: 302.43564 | AE43: -0.064
A44: Electric | B44: Fleet Stock: Commercial Light Trucks: Electric: Alternative Electricity and Transportation | C44: AEO.2026.ELECTRNP.ECI_STK_NA_CLTR_ELE_NA_NA_TH.A | D44: thousands | E44: 130.8921 | F44: 184.41905 | G44: 240.56279 | H44: 297.98135 | I44: 357.10168 | J44: 418.34268 | K44: 481.03696 | L44: 544.87824 | M44: 608.8667 | N44: 672.64398 | O44: 735.47906 | P44: 796.1358 | Q44: 855.44586 | R44: 912.94464 | S44: 968.20538 | T44: 1024.2092 | U44: 1077.5193 | V44: 1124.5135 | W44: 1169.1033 | X44: 1212.9623 | Y44: 1256.3027 | Z44: 1298.7156 | AA44: 1340.1121 | AB44: 1380.2031 | AC44: 1420.7427 | AD44: 1463.7196 | AE44: 0.101
A45: Plug-in Gasoline Hybrid | B45: Fleet Stock: Commercial Light Trucks: Plug-in Gas: Alternative Electricity and Transportation | C45: AEO.2026.ELECTRNP.ECI_STK_NA_CLTR_EGH_NA_NA_TH.A | D45: thousands | E45: 0 | F45: 0 | G45: 0 | H45: 0 | I45: 0 | J45: 0 | K45: 0 | L45: 0 | M45: 0 | N45: 0 | O45: 0 | P45: 0 | Q45: 0 | R45: 0 | S45: 0 | T45: 0 | U45: 0 | V45: 0 | W45: 0 | X45: 0 | Y45: 0 | Z45: 0 | AA45: 0 | AB45: 0 | AC45: 0 | AD45: 0 | AE45: - -
A46: Plug-in Diesel Hybrid | B46: Fleet Stock: Commercial Light Trucks: Plug-in Diesel: Alternative Electricity and Transportation | C46: AEO.2026.ELECTRNP.ECI_STK_NA_CLTR_EDH_NA_NA_TH.A | D46: thousands | E46: 0 | F46: 0 | G46: 0 | H46: 0 | I46: 0 | J46: 0 | K46: 0 | L46: 0 | M46: 0 | N46: 0 | O46: 0 | P46: 0 | Q46: 0 | R46: 0 | S46: 0 | T46: 0 | U46: 0 | V46: 0 | W46: 0 | X46: 0 | Y46: 0 | Z46: 0 | AA46: 0 | AB46: 0 | AC46: 0 | AD46: 0 | AE46: - -
A47: Fuel Cell | B47: Fleet Stock: Commercial Light Trucks: Fuel Cell: Alternative Electricity and Transportation | C47: AEO.2026.ELECTRNP.ECI_STK_NA_CLTR_FUC_NA_NA_TH.A | D47: thousands | E47: 0 | F47: 0 | G47: 0 | H47: 0 | I47: 0 | J47: 0 | K47: 0 | L47: 0 | M47: 0 | N47: 0 | O47: 0 | P47: 0 | Q47: 0 | R47: 0 | S47: 0 | T47: 0 | U47: 0 | V47: 0 | W47: 0 | X47: 0 | Y47: 0 | Z47: 0 | AA47: 0 | AB47: 0 | AC47: 0 | AD47: 0 | AE47: - -
A48: Fuel Cell Battery Dominant | B48: Fleet Stock: Commercial Light Trucks: Fuel Cell Battery Dominant: Alternative Electricity and Transportation | C48: AEO.2026.ELECTRNP.ECI_STK_NA_CLTR_FEUCELBATDOM_NA_NA_TH.A | D48: thousands | E48: 0 | F48: 0 | G48: 0 | H48: 0 | I48: 0 | J48: 0 | K48: 0 | L48: 0 | M48: 0 | N48: 0 | O48: 0 | P48: 0 | Q48: 0 | R48: 0 | S48: 0 | T48: 0 | U48: 0 | V48: 0 | W48: 0 | X48: 0 | Y48: 0 | Z48: 0 | AA48: 0 | AB48: 0 | AC48: 0 | AD48: 0 | AE48: - -
A49: Gasoline Hybrid | B49: Fleet Stock: Commercial Light Trucks: Gasoline Hybrid: Alternative Electricity and Transportation | C49: AEO.2026.ELECTRNP.ECI_STK_NA_CLTR_GASHEV_NA_NA_TH.A | D49: thousands | E49: 1.945617 | F49: 5.289766 | G49: 10.007407 | H49: 16.609016 | I49: 26.195984 | J49: 41.144138 | K49: 62.356422 | L49: 95.123329 | M49: 143.91638 | N49: 208.26347 | O49: 302.78372 | P49: 423.18008 | Q49: 572.72717 | R49: 744.17895 | S49: 939.29535 | T49: 1154.3612 | U49: 1395.0466 | V49: 1656.1902 | W49: 1923.7261 | X49: 2200.1877 | Y49: 2485.5327 | Z49: 2771.0725 | AA49: 3051.8728 | AB49: 3335.4336 | AC49: 3618.0688 | AD49: 3892.0657 | AE49: 0.355
A50: Hydrogen ICE | B50: Fleet Stock: Commercial Light Trucks: Hydrogen ICE: Alternative Electricity and Transportation | C50: AEO.2026.ELECTRNP.ECI_STK_NA_CLTR_HYDICE_NA_NA_TH.A | D50: thousands | E50: 0 | F50: 0 | G50: 0 | H50: 0 | I50: 0 | J50: 0 | K50: 0 | L50: 0 | M50: 0 | N50: 0 | O50: 0 | P50: 0 | Q50: 0 | R50: 0 | S50: 0 | T50: 0 | U50: 0 | V50: 0 | W50: 0 | X50: 0 | Y50: 0 | Z50: 0 | AA50: 0 | AB50: 0 | AC50: 0 | AD50: 0 | AE50: - -
A51: Total Commercial Light Truck Stock | B51: Fleet Stock: Commercial Light Trucks: Total: Alternative Electricity and Transportation | C51: AEO.2026.ELECTRNP.ECI_STK_NA_CLTR_NA_NA_NA_TH.A | D51: thousands | E51: 14618.138 | F51: 14397.037 | G51: 14249.922 | H51: 14150.152 | I51: 14087.121 | J51: 14064.767 | K51: 14058.741 | L51: 14087.708 | M51: 14107.639 | N51: 14117.623 | O51: 14114.141 | P51: 14096.924 | Q51: 14071.175 | R51: 14036.754 | S51: 14005.645 | T51: 13973.453 | U51: 13956.648 | V51: 13948.811 | W51: 13972.287 | X51: 14018.661 | Y51: 14063.6 | Z51: 14098.771 | AA51: 14129.692 | AB51: 14153.009 | AC51: 14150.293 | AD51: 14124.527 | AE51: -0.001

Sheet AEO 2026 Table 44
A1: Table 44. Transportation Fleet Car and Truck Sales by Type and Technology
A2: https://www.eia.gov/outlooks/aeo/data/browser/#/?id=54-AEO2026&cases=electrnp&sourcekey=0
A3: Thu Apr 23 2026 15:04:49 GMT-0700 (Pacific Daylight Time)
A4: Source: U.S. Energy Information Administration
B5: full name | C5: api key | D5: units | E5: 2025 | F5: 2026 | G5: 2027 | H5: 2028 | I5: 2029 | J5: 2030 | K5: 2031 | L5: 2032 | M5: 2033 | N5: 2034 | O5: 2035 | P5: 2036 | Q5: 2037 | R5: 2038 | S5: 2039 | T5: 2040 | U5: 2041 | V5: 2042 | W5: 2043 | X5: 2044 | Y5: 2045 | Z5: 2046 | AA5: 2047 | AB5: 2048 | AC5: 2049 | AD5: 2050 | AE5: Growth (2025-2050)
A6: New Car Sales
A7: Conventional Cars | D7: thousands
A8: Gasoline ICE Vehicles | B8: Fleet Vehicle Sales: Conventional Cars: Gasoline: Alternative Electricity and Transportation | C8: AEO.2026.ELECTRNP.ECI_SAL_CNV_FLC_GSL_NA_NA_TH.A | D8: thousands | E8: 714.64008 | F8: 635.59387 | G8: 589.33008 | H8: 570.05371 | I8: 565.56348 | J8: 572.2243 | K8: 565.49054 | L8: 559.52759 | M8: 556.60181 | N8: 545.70154 | O8: 535.82147 | P8: 516.50177 | Q8: 506.77213 | R8: 495.89575 | S8: 483.99036 | T8: 472.22794 | U8: 459.40717 | V8: 447.20297 | W8: 434.76849 | X8: 423.66336 | Y8: 414.56082 | Z8: 404.51852 | AA8: 397.13562 | AB8: 387.71933 | AC8: 378.78668 | AD8: 367.43161 | AE8: -0.026
A9: TDI Diesel ICE | B9: Fleet Vehicle Sales: Conventional Cars: TDI Diesel: Alternative Electricity and Transportation | C9: AEO.2026.ELECTRNP.ECI_SAL_CNV_FLC_TDS_NA_NA_TH.A | D9: thousands | E9: 0 | F9: 0 | G9: 0 | H9: 0 | I9: 0 | J9: 0 | K9: 0 | L9: 0 | M9: 0 | N9: 0 | O9: 0 | P9: 0 | Q9: 0 | R9: 0 | S9: 0 | T9: 0 | U9: 0 | V9: 0 | W9: 0 | X9: 0 | Y9: 0 | Z9: 0 | AA9: 0 | AB9: 0 | AC9: 0 | AD9: 0 | AE9: - -
A10: Total Conventional Cars | B10: Fleet Vehicle Sales: Conventional Cars: Total: Alternative Electricity and Transportation | C10: AEO.2026.ELECTRNP.ECI_SAL_CNV_FLC_NA_NA_NA_TH.A | D10: thousands | E10: 714.64008 | F10: 635.59387 | G10: 589.33008 | H10: 570.05371 | I10: 565.56348 | J10: 572.2243 | K10: 565.49054 | L10: 559.52759 | M10: 556.60181 | N10: 545.70154 | O10: 535.82147 | P10: 516.50177 | Q10: 506.77213 | R10: 495.89575 | S10: 483.99036 | T10: 472.22794 | U10: 459.40717 | V10: 447.20297 | W10: 434.76849 | X10: 423.66336 | Y10: 414.56082 | Z10: 404.51852 | AA10: 397.13562 | AB10: 387.71933 | AC10: 378.78668 | AD10: 367.43161 | AE10: -0.026
A11: Alternative-Fuel Cars
A12: Ethanol-Flex Fuel ICE | B12: Fleet Vehicle Sales: Alternative-Fuel Cars: Ethanol-Flex Fuel ICE: Alternative Electricity and Transportation | C12: AEO.2026.ELECTRNP.ECI_SAL_ALF1_FLC_EFFI_NA_NA_TH.A | D12: thousands | E12: 0 | F12: 0 | G12: 0 | H12: 0 | I12: 0 | J12: 0 | K12: 0 | L12: 0 | M12: 0 | N12: 0 | O12: 0 | P12: 0 | Q12: 0 | R12: 0 | S12: 0 | T12: 0 | U12: 0 | V12: 0 | W12: 0 | X12: 0 | Y12: 0 | Z12: 0 | AA12: 0 | AB12: 0 | AC12: 0 | AD12: 0 | AE12: - -
A13: 100-Mile Electric Vehicle | B13: Fleet Vehicle Sales: Alternative-Fuel Cars: 100-Mile Electric Vehicle: Alternative Electricity and Transportation | C13: AEO.2026.ELECTRNP.ECI_SAL_ALF1_FLC_100MIEV_NA_NA_TH.A | D13: thousands | E13: 2.206993 | F13: 1.606914 | G13: 1.736317 | H13: 1.700917 | I13: 1.723562 | J13: 1.962003 | K13: 2.042335 | L13: 2.218868 | M13: 2.376864 | N13: 2.52936 | O13: 2.693957 | P13: 2.791865 | Q13: 2.91197 | R13: 3.033377 | S13: 3.137336 | T13: 3.230299 | U13: 3.278135 | V13: 3.333602 | W13: 3.382076 | X13: 3.413587 | Y13: 3.481877 | Z13: 3.49565 | AA13: 3.547434 | AB13: 3.578463 | AC13: 3.593718 | AD13: 3.582147 | AE13: 0.02
A14: 200-Mile Electric Vehicle | B14: Fleet Vehicle Sales: Alternative-Fuel Cars: 200-Mile Electric Vehicle: Alternative Electricity and Transportation | C14: AEO.2026.ELECTRNP.ECI_SAL_ALF1_FLC_200MIEV_NA_NA_TH.A | D14: thousands | E14: 11.116908 | F14: 18.056486 | G14: 27.353477 | H14: 27.236639 | I14: 26.829969 | J14: 23.219538 | K14: 23.897659 | L14: 23.307835 | M14: 25.566116 | N14: 27.35363 | O14: 29.537977 | P14: 30.553305 | Q14: 32.302368 | R14: 33.748753 | S14: 34.955544 | T14: 35.629601 | U14: 36.613506 | V14: 37.451954 | W14: 38.109138 | X14: 38.691471 | Y14: 38.999683 | Z14: 39.68388 | AA14: 40.41082 | AB14: 40.720421 | AC14: 41.141041 | AD14: 41.111855 | AE14: 0.054
A15: 300-Mile Electric Vehicle | B15: Fleet Vehicle Sales: Alternative-Fuel Cars: 300-Mile Electric Vehicle: Alternative Electricity and Transportation | C15: AEO.2026.ELECTRNP.ECI_SAL_ALF1_FLC_300MIEV_NA_NA_TH.A | D15: thousands | E15: 96.054329 | F15: 90.126595 | G15: 102.83265 | H15: 100.90676 | I15: 121.4275 | J15: 132.38582 | K15: 146.47841 | L15: 156.11507 | M15: 168.88031 | N15: 177.80548 | O15: 189.09126 | P15: 194.10586 | Q15: 202.39836 | R15: 209.87733 | S15: 216.15157 | T15: 220.77983 | U15: 224.53557 | V15: 228.19815 | W15: 230.88274 | X15: 233.22369 | Y15: 236.1741 | Z15: 237.93591 | AA15: 241.45105 | AB15: 242.95039 | AC15: 244.44386 | AD15: 243.58099 | AE15: 0.038
A16: Plug-in 20 Gasoline Hybrid | B16: Fleet Vehicle Sales: Alternative-Fuel Cars: Plug-in 20 Gasoline Hybrid: Alternative Electricity and Transportation | C16: AEO.2026.ELECTRNP.ECI_SAL_ALF1_FLC_PI20GH_NA_NA_TH.A | D16: thousands | E16: 4.26343 | F16: 3.861525 | G16: 4.148829 | H16: 4.075779 | I16: 4.029793 | J16: 4.182173 | K16: 3.705255 | L16: 3.725301 | M16: 3.934903 | N16: 4.017191 | O16: 4.162245 | P16: 4.076983 | Q16: 4.104201 | R16: 4.05821 | S16: 3.996465 | T16: 3.856699 | U16: 3.781538 | V16: 3.694863 | W16: 3.602088 | X16: 3.496382 | Y16: 3.362428 | Z16: 3.30533 | AA16: 3.241091 | AB16: 3.160586 | AC16: 3.085132 | AD16: 2.995053 | AE16: -0.014
A17: Plug-in 50 Gasoline Hybrid | B17: Fleet Vehicle Sales: Alternative-Fuel Cars: Plug-in 50 Gasoline Hybrid: Alternative Electricity and Transportation | C17: AEO.2026.ELECTRNP.ECI_SAL_ALF1_FLC_PI50GH_NA_NA_TH.A | D17: thousands | E17: 3.723038 | F17: 7.36446 | G17: 12.089196 | H17: 12.113542 | I17: 6.245296 | J17: 4.512235 | K17: 3.883534 | L17: 3.104065 | M17: 3.453829 | N17: 3.696776 | O17: 4.049677 | P17: 4.183536 | Q17: 4.384931 | R17: 4.566596 | S17: 4.73197 | T17: 4.846192 | U17: 4.873715 | V17: 4.918883 | W17: 4.940303 | X17: 4.931192 | Y17: 4.980022 | Z17: 4.92065 | AA17: 4.949115 | AB17: 4.916635 | AC17: 4.904805 | AD17: 4.832694 | AE17: 0.01
A18: Electric-Gasoline Hybrid | B18: Fleet Vehicle Sales: Alternative-Fuel Cars: Electric-Gasoline Hybrid: Alternative Electricity and Transportation | C18: AEO.2026.ELECTRNP.ECI_SAL_ALF1_FLC_EGH_NA_NA_TH.A | D18: thousands | E18: 66.824852 | F18: 75.54911 | G18: 82.896721 | H18: 83.659462 | I18: 83.83902 | J18: 88.014381 | K18: 91.698105 | L18: 93.357445 | M18: 97.07724 | N18: 98.67495 | O18: 100.41347 | P18: 99.80909 | Q18: 100.74165 | R18: 101.40453 | S18: 101.69147 | T18: 101.77615 | U18: 101.70591 | V18: 101.65527 | W18: 101.35596 | X18: 101.22368 | Y18: 101.48513 | Z18: 101.54466 | AA18: 102.25279 | AB18: 102.36383 | AC18: 102.40939 | AD18: 101.73265 | AE18: 0.017
A19: Natural Gas ICE | B19: Fleet Vehicle Sales: Alternative-Fuel Cars: Natural Gas ICE: Alternative Electricity and Transportation | C19: AEO.2026.ELECTRNP.ECI_SAL_ALF1_FLC_NGI_NA_NA_TH.A | D19: thousands | E19: 0 | F19: 0 | G19: 0 | H19: 0 | I19: 0 | J19: 0 | K19: 0 | L19: 0 | M19: 0 | N19: 0 | O19: 0 | P19: 0 | Q19: 0 | R19: 0 | S19: 0 | T19: 0 | U19: 0 | V19: 0 | W19: 0 | X19: 0 | Y19: 0 | Z19: 0 | AA19: 0 | AB19: 0 | AC19: 0 | AD19: 0 | AE19: - -
A20: Natural Gas Bi-fuel | B20: Fleet Vehicle Sales: Alternative-Fuel Cars: Natural Gas Bi-fuel: Alternative Electricity and Transportation | C20: AEO.2026.ELECTRNP.ECI_SAL_ALF1_FLC_NBF_NA_NA_TH.A | D20: thousands | E20: 0 | F20: 0 | G20: 0 | H20: 0 | I20: 0 | J20: 0 | K20: 0 | L20: 0 | M20: 0 | N20: 0 | O20: 0 | P20: 0 | Q20: 0 | R20: 0 | S20: 0 | T20: 0 | U20: 0 | V20: 0 | W20: 0 | X20: 0 | Y20: 0 | Z20: 0 | AA20: 0 | AB20: 0 | AC20: 0 | AD20: 0 | AE20: - -
A21: Propane ICE | B21: Fleet Vehicle Sales: Alternative-Fuel Cars: Propane ICE: Alternative Electricity and Transportation | C21: AEO.2026.ELECTRNP.ECI_SAL_ALF1_FLC_PROP_NA_NA_TH.A | D21: thousands | E21: 0 | F21: 0 | G21: 0 | H21: 0 | I21: 0 | J21: 0 | K21: 0 | L21: 0 | M21: 0 | N21: 0 | O21: 0 | P21: 0 | Q21: 0 | R21: 0 | S21: 0 | T21: 0 | U21: 0 | V21: 0 | W21: 0 | X21: 0 | Y21: 0 | Z21: 0 | AA21: 0 | AB21: 0 | AC21: 0 | AD21: 0 | AE21: - -
A22: Propane Bi-fuel | B22: Fleet Vehicle Sales: Alternative-Fuel Cars: Propane Bi-fuel: Alternative Electricity and Transportation | C22: AEO.2026.ELECTRNP.ECI_SAL_ALF1_FLC_PBF_NA_NA_TH.A | D22: thousands | E22: 0 | F22: 0 | G22: 0 | H22: 0 | I22: 0 | J22: 0 | K22: 0 | L22: 0 | M22: 0 | N22: 0 | O22: 0 | P22: 0 | Q22: 0 | R22: 0 | S22: 0 | T22: 0 | U22: 0 | V22: 0 | W22: 0 | X22: 0 | Y22: 0 | Z22: 0 | AA22: 0 | AB22: 0 | AC22: 0 | AD22: 0 | AE22: - -
A23: Fuel Cell Hydrogen | B23: Fleet Vehicle Sales: Alternative-Fuel cars: Fuel Cell Hydrogen: Alternative Electricity and Transportation | C23: AEO.2026.ELECTRNP.ECI_SAL_ALF1_FLC_FCH_NA_NA_TH.A | D23: thousands | E23: 0.037471 | F23: 0.013645 | G23: 0.013157 | H23: 0.009 | I23: 0.006575 | J23: 0.007138 | K23: 0.006808 | L23: 0.006451 | M23: 0.006877 | N23: 0.006139 | O23: 0.006198 | P23: 0.005658 | Q23: 0.005438 | R23: 0.005134 | S23: 0.004983 | T23: 0.004842 | U23: 0.004685 | V23: 0.004541 | W23: 0.004401 | X23: 0.004281 | Y23: 0.00419 | Z23: 0.004053 | AA23: 0.003988 | AB23: 0.003867 | AC23: 0.003787 | AD23: 0.003661 | AE23: -0.089
A24: Total Alternative Cars | B24: Fleet Vehicle Sales: Alternative-Fuel Cars: Total: Alternative Electricity and Transportation | C24: AEO.2026.ELECTRNP.ECI_SAL_ALF1_FLC_NA_NA_NA_TH.A | D24: thousands | E24: 184.22702 | F24: 196.57873 | G24: 231.07034 | H24: 229.70212 | I24: 244.10173 | J24: 254.2833 | K24: 271.7121 | L24: 281.83502 | M24: 301.29611 | N24: 314.08353 | O24: 329.9548 | P24: 335.52628 | Q24: 346.84891 | R24: 356.69391 | S24: 364.66934 | T24: 370.12363 | U24: 374.79309 | V24: 379.25726 | W24: 382.2767 | X24: 384.98428 | Y24: 388.48743 | Z24: 390.89014 | AA24: 395.85629 | AB24: 397.69418 | AC24: 399.58173 | AD24: 397.83905 | AE24: 0.031
A25: Percentage Alternative Car Sales | B25: Fleet Vehicle Sales: Percentage Alternative Car: Alternative Electricity and Transportation | C25: AEO.2026.ELECTRNP.ECI_SAL_ALF1_FLC_NA_NA_NA_PCT.A | D25: percent | E25: 20.495468 | F25: 23.622351 | G25: 28.165558 | H25: 28.721529 | I25: 30.148476 | J25: 30.765999 | K25: 32.454758 | L25: 33.497448 | M25: 35.120277 | N25: 36.530472 | O25: 38.110863 | P25: 39.379723 | Q25: 40.632656 | R25: 41.836529 | S25: 42.970036 | T25: 43.939327 | U25: 44.928432 | V25: 45.889359 | W25: 46.787708 | X25: 47.60841 | Y25: 48.376598 | Z25: 49.143307 | AA25: 49.919334 | AB25: 50.635002 | AC25: 51.335812 | AD25: 51.986713 | AE25: 0.038
A26: Total New Car Sales | B26: Fleet Vehicle Sales: Total New Car: Alternative Electricity and Transportation | C26: AEO.2026.ELECTRNP.ECI_SAL_NA_FLC_NA_NA_NA_TH.A | D26: thousands | E26: 898.86707 | F26: 832.17261 | G26: 820.40039 | H26: 799.75586 | I26: 809.66522 | J26: 826.50757 | K26: 837.20264 | L26: 841.36261 | M26: 857.89795 | N26: 859.78503 | O26: 865.77625 | P26: 852.02808 | Q26: 853.62103 | R26: 852.58966 | S26: 848.65967 | T26: 842.35156 | U26: 834.20026 | V26: 826.4602 | W26: 817.04517 | X26: 808.64764 | Y26: 803.04822 | Z26: 795.40869 | AA26: 792.99194 | AB26: 785.41351 | AC26: 778.36841 | AD26: 765.27063 | AE26: -0.006
A27: New Light Truck Sales
A28: Conventional Light Trucks
A29: Gasoline ICE Vehicles | B29: Fleet Vehicle Sales: Conventional Light Trucks: Gasoline: Alternative Electricity and Transportation | C29: AEO.2026.ELECTRNP.ECI_SAL_CNV_FLTR_GSL_NA_NA_TH.A | D29: thousands | E29: 1437.173 | F29: 1280.6257 | G29: 1267.8079 | H29: 1227.0704 | I29: 1292.2639 | J29: 1355.6544 | K29: 1409.1293 | L29: 1440.6362 | M29: 1422.0645 | N29: 1402.7307 | O29: 1376.9635 | P29: 1336.5696 | Q29: 1314.984 | R29: 1293.8232 | S29: 1258.4368 | T29: 1238.3679 | U29: 1214.6133 | V29: 1189.9836 | W29: 1170.0724 | X29: 1151.5096 | Y29: 1133.5857 | Z29: 1116.7258 | AA29: 1097.0377 | AB29: 1077.1228 | AC29: 1054.2616 | AD29: 1028.1942 | AE29: -0.013
A30: TDI Diesel ICE | B30: Fleet Vehicle Sales: Conventional Light Trucks: TDI Diesel: Alternative Electricity and Transportation | C30: AEO.2026.ELECTRNP.ECI_SAL_CNV_FLTR_TDS_NA_NA_TH.A | D30: thousands | E30: 21.510231 | F30: 22.414324 | G30: 22.295994 | H30: 22.462799 | I30: 22.7118 | J30: 23.527294 | K30: 23.790461 | L30: 24.008343 | M30: 24.06229 | N30: 24.345695 | O30: 24.239101 | P30: 23.786434 | Q30: 23.735018 | R30: 23.701374 | S30: 23.534876 | T30: 23.222321 | U30: 23.034515 | V30: 22.8575 | W30: 22.660404 | X30: 22.448957 | Y30: 22.106741 | Z30: 22.052914 | AA30: 21.828384 | AB30: 21.665068 | AC30: 21.316776 | AD30: 20.988546 | AE30: -0.001
A31: Total Conventional Light Trucks | B31: Fleet Vehicle Sales: Conventional Light Trucks: Total: Alternative Electricity and Transportation | C31: AEO.2026.ELECTRNP.ECI_SAL_CNV_FLTR_NA_NA_NA_TH.A | D31: thousands | E31: 1458.6832 | F31: 1303.04 | G31: 1290.1039 | H31: 1249.5332 | I31: 1314.9757 | J31: 1379.1818 | K31: 1432.9197 | L31: 1464.6445 | M31: 1446.1267 | N31: 1427.0764 | O31: 1401.2026 | P31: 1360.356 | Q31: 1338.719 | R31: 1317.5247 | S31: 1281.9717 | T31: 1261.5902 | U31: 1237.6478 | V31: 1212.8412 | W31: 1192.7328 | X31: 1173.9586 | Y31: 1155.6924 | Z31: 1138.7787 | AA31: 1118.8661 | AB31: 1098.7878 | AC31: 1075.5784 | AD31: 1049.1827 | AE31: -0.013
A32: Alternative-Fuel Light Trucks
A33: Ethanol-Flex Fuel ICE | B33: Fleet Vehicle Sales: Alternative-Fuel Light Trucks: Ethanol-Flex Fuel ICE: Alternative Electricity and Transportation | C33: AEO.2026.ELECTRNP.ECI_SAL_ALF1_FLTR_EFFI_NA_NA_TH.A | D33: thousands | E33: 0.372822 | F33: 0.372309 | G33: 0.391655 | H33: 0.395681 | I33: 0.408074 | J33: 0.423958 | K33: 0.43165 | L33: 0.437611 | M33: 0.438934 | N33: 0.442066 | O33: 0.441668 | P33: 0.437692 | Q33: 0.436797 | R33: 0.43691 | S33: 0.43595 | T33: 0.434601 | U33: 0.431886 | V33: 0.428321 | W33: 0.426536 | X33: 0.424182 | Y33: 0.421887 | Z33: 0.420009 | AA33: 0.415897 | AB33: 0.412711 | AC33: 0.406969 | AD33: 0.400532 | AE33: 0.003
A34: 100-Mile Electric Vehicle | B34: Fleet Vehicle Sales: Alternative-Fuel Light Trucks: 100-Mile Electric Vehicle: Alternative Electricity and Transportation | C34: AEO.2026.ELECTRNP.ECI_SAL_ALF1_FLTR_100MIEV_NA_NA_TH.A | D34: thousands | E34: 0.438531 | F34: 0.307967 | G34: 0.356011 | H34: 0.376499 | I34: 0.402728 | J34: 0.470826 | K34: 0.526172 | L34: 0.589313 | M34: 0.651888 | N34: 0.70149 | O34: 0.759006 | P34: 0.798581 | Q34: 0.845509 | R34: 0.892578 | S34: 0.940033 | T34: 0.985847 | U34: 1.017161 | V34: 1.049405 | W34: 1.0807 | X34: 1.110321 | Y34: 1.147108 | Z34: 1.165064 | AA34: 1.191065 | AB34: 1.208701 | AC34: 1.224608 | AD34: 1.228536 | AE34: 0.042
A35: 200-Mile Electric Vehicle | B35: Fleet Vehicle Sales: Alternative-Fuel Light Trucks: 200-Mile Electric Vehicle: Alternative Electricity and Transportation | C35: AEO.2026.ELECTRNP.ECI_SAL_ALF1_FLTR_200MIEV_NA_NA_TH.A | D35: thousands | E35: 14.50286 | F35: 46.362995 | G35: 71.392891 | H35: 86.57637 | I35: 89.548294 | J35: 78.577286 | K35: 71.332283 | L35: 61.137123 | M35: 67.188408 | N35: 72.739761 | O35: 79.61319 | P35: 83.990189 | Q35: 89.878098 | R35: 95.494774 | S35: 99.948608 | T35: 104.95778 | U35: 108.87504 | V35: 112.86192 | W35: 116.73233 | X35: 120.47168 | Y35: 124.54692 | Z35: 127.16966 | AA35: 130.62906 | AB35: 132.75278 | AC35: 135.19066 | AD35: 136.03778 | AE35: 0.094
A36: 300-Mile Electric Vehicle | B36: Fleet Vehicle Sales: Alternative-Fuel Light Trucks: 300-Mile Electric Vehicle: Alternative Electricity and Transportation | C36: AEO.2026.ELECTRNP.ECI_SAL_ALF1_FLTR_300MIEV_NA_NA_TH.A | D36: thousands | E36: 69.390381 | F36: 98.883827 | G36: 128.46678 | H36: 153.13013 | I36: 151.60406 | J36: 154.36659 | K36: 140.18541 | L36: 144.5824 | M36: 158.72485 | N36: 170.94873 | O36: 185.01433 | P36: 193.63051 | Q36: 205.1306 | R36: 216.07722 | S36: 225.78798 | T36: 235.52168 | U36: 242.4572 | V36: 249.53416 | W36: 256.2612 | X36: 262.66656 | Y36: 270.07767 | Z36: 274.06888 | AA36: 279.84992 | AB36: 283.20371 | AC36: 286.69702 | AD36: 287.20252 | AE36: 0.058
A37: Plug-in 20 Gasoline Hybrid | B37: Fleet Vehicle Sales: Alternative-Fuel Light Trucks: Plug-in 20 Gasoline Hybrid: Alternative Electricity and Transportation | C37: AEO.2026.ELECTRNP.ECI_SAL_ALF1_FLTR_PI20GH_NA_NA_TH.A | D37: thousands | E37: 37.805 | F37: 26.940199 | G37: 29.180897 | H37: 29.918764 | I37: 29.766842 | J37: 31.682257 | K37: 34.03854 | L37: 36.009048 | M37: 39.023567 | N37: 41.944893 | O37: 45.362904 | P37: 46.736874 | Q37: 48.87421 | R37: 50.853432 | S37: 52.637215 | T37: 53.667587 | U37: 54.320786 | V37: 54.984226 | W37: 55.655186 | X37: 56.045773 | Y37: 56.453976 | Z37: 56.572586 | AA37: 56.907936 | AB37: 56.807114 | AC37: 56.826561 | AD37: 56.319984 | AE37: 0.016
A38: Plug-in 50 Gasoline Hybrid | B38: Fleet Vehicle Sales: Alternative-Fuel Light Trucks: Plug-in 50 Gasoline Hybrid: Alternative Electricity and Transportation | C38: AEO.2026.ELECTRNP.ECI_SAL_ALF1_FLTR_PI50GH_NA_NA_TH.A | D38: thousands | E38: 10.351457 | F38: 45.225361 | G38: 71.672699 | H38: 92.527695 | I38: 45.882923 | J38: 36.908356 | K38: 22.379274 | L38: 9.34068 | M38: 10.058076 | N38: 10.48983 | O38: 11.277993 | P38: 11.468544 | Q38: 11.854759 | R38: 12.145212 | S38: 12.498743 | T38: 12.771282 | U38: 12.710954 | V38: 12.699977 | W38: 12.69642 | X38: 12.664415 | Y38: 12.771111 | Z38: 12.526513 | AA38: 12.483051 | AB38: 12.270146 | AC38: 12.171361 | AD38: 11.912324 | AE38: 0.006
A39: Electric-Gasoline Hybrid | B39: Fleet Vehicle Sales: Alternative-Fuel Light Trucks: Electric-Gasoline Hybrid: Alternative Electricity and Transportation | C39: AEO.2026.ELECTRNP.ECI_SAL_ALF1_FLTR_EGH_NA_NA_TH.A | D39: thousands | E39: 231.93541 | F39: 300.65042 | G39: 321.92755 | H39: 358.1427 | I39: 381.94684 | J39: 403.00726 | K39: 416.13809 | L39: 421.31039 | M39: 429.03586 | N39: 433.79871 | O39: 438.41574 | P39: 436.38498 | Q39: 440.9809 | R39: 444.8045 | S39: 461.72449 | T39: 465.76788 | U39: 467.22736 | V39: 468.23367 | W39: 470.55792 | X39: 473.60718 | Y39: 477.20618 | Z39: 479.81244 | AA39: 482.48285 | AB39: 483.47772 | AC39: 484.22485 | AD39: 482.24207 | AE39: 0.03
A40: Natural Gas ICE | B40: Fleet Vehicle Sales: Alternative-Fuel Light Trucks: Natural Gas ICE: Alternative Electricity and Transportation | C40: AEO.2026.ELECTRNP.ECI_SAL_ALF1_FLTR_NGI_NA_NA_TH.A | D40: thousands | E40: 0 | F40: 0 | G40: 0 | H40: 0 | I40: 0 | J40: 0 | K40: 0 | L40: 0 | M40: 0 | N40: 0 | O40: 0 | P40: 0 | Q40: 0 | R40: 0 | S40: 0 | T40: 0 | U40: 0 | V40: 0 | W40: 0 | X40: 0 | Y40: 0 | Z40: 0 | AA40: 0 | AB40: 0 | AC40: 0 | AD40: 0 | AE40: - -
A41: Natural Gas Bi-fuel | B41: Fleet Vehicle Sales: Alternative-Fuel Light Trucks: Natural Gas Bi-fuel: Alternative Electricity and Transportation | C41: AEO.2026.ELECTRNP.ECI_SAL_ALF1_FLTR_NBF_NA_NA_TH.A | D41: thousands | E41: 0 | F41: 0 | G41: 0 | H41: 0 | I41: 0 | J41: 0 | K41: 0 | L41: 0 | M41: 0 | N41: 0 | O41: 0 | P41: 0 | Q41: 0 | R41: 0 | S41: 0 | T41: 0 | U41: 0 | V41: 0 | W41: 0 | X41: 0 | Y41: 0 | Z41: 0 | AA41: 0 | AB41: 0 | AC41: 0 | AD41: 0 | AE41: - -
A42: Propane ICE | B42: Fleet Vehicle Sales: Alternative-Fuel Light Trucks: Propane ICE: Alternative Electricity and Transportation | C42: AEO.2026.ELECTRNP.ECI_SAL_ALF1_FLTR_PROP_NA_NA_TH.A | D42: thousands | E42: 0 | F42: 0 | G42: 0 | H42: 0 | I42: 0 | J42: 0 | K42: 0 | L42: 0 | M42: 0 | N42: 0 | O42: 0 | P42: 0 | Q42: 0 | R42: 0 | S42: 0 | T42: 0 | U42: 0 | V42: 0 | W42: 0 | X42: 0 | Y42: 0 | Z42: 0 | AA42: 0 | AB42: 0 | AC42: 0 | AD42: 0 | AE42: - -
A43: Propane Bi-fuel | B43: Fleet Vehicle Sales: Alternative-Fuel Light Trucks: Propane Bi-fuel: Alternative Electricity and Transportation | C43: AEO.2026.ELECTRNP.ECI_SAL_ALF1_FLTR_PBF_NA_NA_TH.A | D43: thousands | E43: 0 | F43: 0 | G43: 0 | H43: 0 | I43: 0 | J43: 0 | K43: 0 | L43: 0 | M43: 0 | N43: 0 | O43: 0 | P43: 0 | Q43: 0 | R43: 0 | S43: 0 | T43: 0 | U43: 0 | V43: 0 | W43: 0 | X43: 0 | Y43: 0 | Z43: 0 | AA43: 0 | AB43: 0 | AC43: 0 | AD43: 0 | AE43: - -
A44: Fuel Cell Hydrogen | B44: Fleet Vehicle Sales: Alternative-Fuel Light Trucks: Fuel Cell Hydrogen: Alternative Electricity and Transportation | C44: AEO.2026.ELECTRNP.ECI_SAL_ALF1_FLTR_FCH_NA_NA_TH.A | D44: thousands | E44: 0 | F44: 0 | G44: 0 | H44: 0 | I44: 0 | J44: 0 | K44: 0 | L44: 0 | M44: 0 | N44: 0 | O44: 0 | P44: 0 | Q44: 0 | R44: 0 | S44: 0 | T44: 0 | U44: 0 | V44: 0 | W44: 0 | X44: 0 | Y44: 0 | Z44: 0 | AA44: 0 | AB44: 0 | AC44: 0 | AD44: 0 | AE44: - -
A45: Total Alternative Light Trucks | B45: Fleet Vehicle Sales: Alternative-Fuel Light Trucks: Total: Alternative Electricity and Transportation | C45: AEO.2026.ELECTRNP.ECI_SAL_ALF1_FLTR_NA_NA_NA_TH.A | D45: thousands | E45: 364.79645 | F45: 518.7431 | G45: 623.38849 | H45: 721.06787 | I45: 699.55975 | J45: 705.43652 | K45: 685.03143 | L45: 673.40656 | M45: 705.12158 | N45: 731.06549 | O45: 760.88483 | P45: 773.44739 | Q45: 798.00085 | R45: 820.70465 | S45: 853.97302 | T45: 874.10663 | U45: 887.0404 | V45: 899.79169 | W45: 913.41028 | X45: 926.99011 | Y45: 942.62488 | Z45: 951.73511 | AA45: 963.95978 | AB45: 970.13293 | AC45: 976.74207 | AD45: 975.34375 | AE45: 0.04
A46: Percentage Alternative Light Truck Sales | B46: Fleet Vehicle Sales: Light Trucks: Percentage Alternative: Alternative Electricity and Transportation | C46: AEO.2026.ELECTRNP.ECI_SAL_ALF1_FLTR_NA_NA_NA_PCT.A | D46: percent | E46: 20.00551 | F46: 28.47447 | G46: 32.578571 | H46: 36.591263 | I46: 34.725613 | J46: 33.840084 | K46: 32.344063 | L46: 31.496281 | M46: 32.777321 | N46: 33.874763 | O46: 35.192142 | P46: 36.247364 | Q46: 37.347008 | R46: 38.382442 | S46: 39.981045 | T46: 40.928406 | U46: 41.749203 | V46: 42.591011 | W46: 43.368862 | X46: 44.122452 | Y46: 44.922894 | Z46: 45.526375 | AA46: 46.281342 | AB46: 46.89077 | AC46: 47.592087 | AD46: 48.176392 | AE46: 0.036
A47: Total New Light Truck Sales | B47: Fleet Vehicle Sales: Light Trucks: Total: Alternative Electricity and Transportation | C47: AEO.2026.ELECTRNP.ECI_SAL_NA_FLTR_NA_NA_NA_TH.A | D47: thousands | E47: 1823.4797 | F47: 1821.7832 | G47: 1913.4924 | H47: 1970.6011 | I47: 2014.5354 | J47: 2084.6182 | K47: 2117.9512 | L47: 2138.051 | M47: 2151.2483 | N47: 2158.1418 | O47: 2162.0874 | P47: 2133.8032 | Q47: 2136.7197 | R47: 2138.2292 | S47: 2135.9448 | T47: 2135.6968 | U47: 2124.6882 | V47: 2112.6328 | W47: 2106.1431 | X47: 2100.9487 | Y47: 2098.3174 | Z47: 2090.5137 | AA47: 2082.8259 | AB47: 2068.9209 | AC47: 2052.3203 | AD47: 2024.5265 | AE47: 0.004
A48: Total Fleet Vehicles | B48: Transportation Fleet Vehicle Sales: Total Fleet Vehicles: Alternative Electricity and Transportation | C48: AEO.2026.ELECTRNP.ECI_SAL_NA_NA_NA_NA_NA_TH.A | D48: thousands | E48: 2722.3467 | F48: 2653.9558 | G48: 2733.8928 | H48: 2770.3569 | I48: 2824.2007 | J48: 2911.1257 | K48: 2955.1538 | L48: 2979.4136 | M48: 3009.1462 | N48: 3017.9268 | O48: 3027.8638 | P48: 2985.8313 | Q48: 2990.3408 | R48: 2990.8188 | S48: 2984.6045 | T48: 2978.0483 | U48: 2958.8884 | V48: 2939.093 | W48: 2923.1882 | X48: 2909.5964 | Y48: 2901.3657 | Z48: 2885.9224 | AA48: 2875.8179 | AB48: 2854.3345 | AC48: 2830.6887 | AD48: 2789.7971 | AE48: 0.001
A49: Commercial Light Truck Sales
A50: Motor Gasoline | B50: Fleet Vehicle Sales: Commercial Light Trucks: Gasoline: Alternative Electricity and Transportation | C50: AEO.2026.ELECTRNP.ECI_SAL_NA_CLTR_GSL_NA_NA_TH.A | D50: thousands | E50: 345.68704 | F50: 345.4176 | G50: 365.44742 | H50: 377.73923 | I50: 393.0145 | J50: 409.08804 | K50: 419.39945 | L50: 422.76517 | M50: 415.46695 | N50: 404.7681 | O50: 381.00851 | P50: 352.53677 | Q50: 327.62057 | R50: 307.57791 | S50: 284.72662 | T50: 261.07242 | U50: 233.37149 | V50: 212.33559 | W50: 199.73291 | X50: 183.51184 | Y50: 167.88559 | Z50: 157.4729 | AA50: 152.49068 | AB50: 139.11157 | AC50: 126.87086 | AD50: 115.81142 | AE50: -0.043
A51: Diesel | B51: Fleet Vehicle Sales: Commercial Light Trucks: TDI Diesel: Alternative Electricity and Transportation | C51: AEO.2026.ELECTRNP.ECI_SAL_NA_CLTR_TDS_NA_NA_TH.A | D51: thousands | E51: 90.062431 | F51: 87.36586 | G51: 89.953827 | H51: 90.661263 | I51: 92.168373 | J51: 93.87532 | K51: 94.328156 | L51: 93.289268 | M51: 90.06205 | N51: 86.36145 | O51: 79.997955 | P51: 73.011383 | Q51: 67.012062 | R51: 62.247208 | S51: 57.147076 | T51: 51.966373 | U51: 46.07719 | V51: 41.614193 | W51: 38.890713 | X51: 35.540524 | Y51: 32.348991 | Z51: 30.182585 | AA51: 29.084726 | AB51: 26.415228 | AC51: 23.995899 | AD51: 21.827421 | AE51: -0.055
A52: Propane | B52: Fleet Vehicle Sales: Commercial Light Trucks: Propane: Alternative Electricity and Transportation | C52: AEO.2026.ELECTRNP.ECI_SAL_NA_CLTR_PROP_NA_NA_TH.A | D52: thousands | E52: 0.004938 | F52: 0.004931 | G52: 0.005188 | H52: 0.005353 | I52: 0.005569 | J52: 0.005832 | K52: 0.006026 | L52: 0.006188 | M52: 0.006256 | N52: 0.006279 | O52: 0.006293 | P52: 0.0062 | Q52: 0.006203 | R52: 0.006199 | S52: 0.006182 | T52: 0.006166 | U52: 0.00612 | V52: 0.006074 | W52: 0.006034 | X52: 0.006 | Y52: 0.00598 | Z52: 0.00594 | AA52: 0.005914 | AB52: 0.005863 | AC52: 0.005809 | AD52: 0.005719 | AE52: 0.006
A53: Compressed/Liquefied Natural Gas | B53: Fleet Vehicle Sales: Commercial Light Trucks: CNG/LNG: Alternative Electricity and Transportation | C53: AEO.2026.ELECTRNP.ECI_SAL_NA_CLTR_NG_NA_NA_TH.A | D53: thousands | E53: 2.880567 | F53: 3.859653 | G53: 2.784169 | H53: 2.579134 | I53: 2.066722 | J53: 2.296823 | K53: 2.463187 | L53: 3.002775 | M53: 3.368927 | N53: 3.715154 | O53: 4.601557 | P53: 5.129253 | Q53: 6.285594 | R53: 7.684091 | S53: 8.738005 | T53: 10.625904 | U53: 11.774923 | V53: 13.239506 | W53: 14.760299 | X53: 16.216478 | Y53: 17.696083 | Z53: 19.540121 | AA53: 20.631931 | AB53: 21.651274 | AC53: 22.201729 | AD53: 23.176111 | AE53: 0.087
A54: Ethanol-Flex Fuel | B54: Fleet Vehicle Sales: Commercial Light Trucks: Ethanol Flex: Alternative Electricity and Transportation | C54: AEO.2026.ELECTRNP.ECI_SAL_NA_CLTR_EFFI_NA_NA_TH.A | D54: thousands | E54: 0 | F54: 0 | G54: 0 | H54: 0 | I54: 0 | J54: 0 | K54: 0 | L54: 0 | M54: 0 | N54: 0 | O54: 0 | P54: 0 | Q54: 0 | R54: 0 | S54: 0 | T54: 0 | U54: 0 | V54: 0 | W54: 0 | X54: 0 | Y54: 0 | Z54: 0 | AA54: 0 | AB54: 0 | AC54: 0 | AD54: 0 | AE54: - -
A55: Electric | B55: Fleet Vehicle Sales: Commercial Light Trucks: Electric: Alternative Electricity and Transportation | C55: AEO.2026.ELECTRNP.ECI_SAL_NA_CLTR_ELE_NA_NA_TH.A | D55: thousands | E55: 53.202854 | F55: 53.131798 | G55: 55.900131 | H55: 57.67561 | I55: 60.005566 | J55: 62.835323 | K55: 64.924469 | L55: 66.659569 | M55: 67.386307 | N55: 67.901688 | O55: 67.952377 | P55: 67.017159 | Q55: 67.15963 | R55: 67.19175 | S55: 67.057251 | T55: 70.221779 | U55: 70.046516 | V55: 66.311012 | W55: 66.651138 | X55: 68.555161 | Y55: 70.667061 | Z55: 72.571846 | AA55: 74.324776 | AB55: 75.733002 | AC55: 78.688454 | AD55: 83.44725 | AE55: 0.018
A56: Plug-in Gasoline Hybrid | B56: Fleet Vehicle Sales: Commercial Light Trucks: Plug-in Gas: Alternative Electricity and Transportation | C56: AEO.2026.ELECTRNP.ECI_SAL_NA_CLTR_EGH_NA_NA_TH.A | D56: thousands | E56: 0 | F56: 0 | G56: 0 | H56: 0 | I56: 0 | J56: 0 | K56: 0 | L56: 0 | M56: 0 | N56: 0 | O56: 0 | P56: 0 | Q56: 0 | R56: 0 | S56: 0 | T56: 0 | U56: 0 | V56: 0 | W56: 0 | X56: 0 | Y56: 0 | Z56: 0 | AA56: 0 | AB56: 0 | AC56: 0 | AD56: 0 | AE56: - -
A57: Plug-in Diesel Hybrid | B57: Fleet Vehicle Sales: Commercial Light Trucks: Plug-in Diesel: Alternative Electricity and Transportation | C57: AEO.2026.ELECTRNP.ECI_SAL_NA_CLTR_EDH_NA_NA_TH.A | D57: thousands | E57: 0 | F57: 0 | G57: 0 | H57: 0 | I57: 0 | J57: 0 | K57: 0 | L57: 0 | M57: 0 | N57: 0 | O57: 0 | P57: 0 | Q57: 0 | R57: 0 | S57: 0 | T57: 0 | U57: 0 | V57: 0 | W57: 0 | X57: 0 | Y57: 0 | Z57: 0 | AA57: 0 | AB57: 0 | AC57: 0 | AD57: 0 | AE57: - -
A58: Fuel Cell | B58: Fleet Vehicle Sales: Commercial Light Trucks: Fuel Cell: Alternative Electricity and Transportation | C58: AEO.2026.ELECTRNP.ECI_SAL_NA_CLTR_FUC_NA_NA_TH.A | D58: thousands | E58: 0 | F58: 0 | G58: 0 | H58: 0 | I58: 0 | J58: 0 | K58: 0 | L58: 0 | M58: 0 | N58: 0 | O58: 0 | P58: 0 | Q58: 0 | R58: 0 | S58: 0 | T58: 0 | U58: 0 | V58: 0 | W58: 0 | X58: 0 | Y58: 0 | Z58: 0 | AA58: 0 | AB58: 0 | AC58: 0 | AD58: 0 | AE58: - -
A59: Fuel Cell Battery Dominant | B59: Fleet Vehicle Sales: Commercial Light Trucks: Fuel Cell Battery Dominant: Alternative Electricity and Transportation | C59: AEO.2026.ELECTRNP.ECI_SAL_NA_CLTR_FEUCELBATDOM_NA_NA_TH.A | D59: thousands | E59: 0 | F59: 0 | G59: 0 | H59: 0 | I59: 0 | J59: 0 | K59: 0 | L59: 0 | M59: 0 | N59: 0 | O59: 0 | P59: 0 | Q59: 0 | R59: 0 | S59: 0 | T59: 0 | U59: 0 | V59: 0 | W59: 0 | X59: 0 | Y59: 0 | Z59: 0 | AA59: 0 | AB59: 0 | AC59: 0 | AD59: 0 | AE59: - -
A60: Gasoline Hybrid | B60: Fleet Vehicle Sales: Commercial Light Trucks: Gasoline Hybrid: Alternative Electricity and Transportation | C60: AEO.2026.ELECTRNP.ECI_SAL_NA_CLTR_GASHEV_NA_NA_TH.A | D60: thousands | E60: 1.945617 | F60: 3.344156 | G60: 4.726586 | H60: 6.635186 | I60: 9.659758 | J60: 15.082555 | K60: 21.452257 | L60: 33.139454 | M60: 49.350224 | N60: 65.193207 | O60: 95.815041 | P60: 122.33759 | Q60: 152.29301 | R60: 175.29872 | S60: 200.64145 | T60: 222.76621 | U60: 250.80702 | V60: 273.9274 | W60: 283.48727 | X60: 296.27051 | Y60: 309.44702 | Z60: 314.34524 | AA60: 314.94934 | AB60: 323.63983 | AC60: 329.37491 | AD60: 327.96307 | AE60: 0.228
A61: Hydrogen ICE | B61: Fleet Vehicle Sales: Commercial Light Trucks: Hydrogen ICE: Alternative Electricity and Transportation | C61: AEO.2026.ELECTRNP.ECI_SAL_NA_CLTR_HYDICE_NA_NA_TH.A | D61: thousands | E61: 0 | F61: 0 | G61: 0 | H61: 0 | I61: 0 | J61: 0 | K61: 0 | L61: 0 | M61: 0 | N61: 0 | O61: 0 | P61: 0 | Q61: 0 | R61: 0 | S61: 0 | T61: 0 | U61: 0 | V61: 0 | W61: 0 | X61: 0 | Y61: 0 | Z61: 0 | AA61: 0 | AB61: 0 | AC61: 0 | AD61: 0 | AE61: - -
A62: Total Commercial Light Truck Sales | B62: Fleet Vehicle Sales: Commercial Light Trucks: Total: Alternative Electricity and Transportation | C62: AEO.2026.ELECTRNP.ECI_SAL_NA_CLTR_NA_NA_NA_TH.A | D62: thousands | E62: 493.78345 | F62: 493.12399 | G62: 518.81732 | H62: 535.29578 | I62: 556.92041 | J62: 583.1839 | K62: 602.57361 | L62: 618.86237 | M62: 625.64069 | N62: 627.94592 | O62: 629.38177 | P62: 620.03833 | Q62: 620.37707 | R62: 620.00586 | S62: 618.31659 | T62: 616.65881 | U62: 612.08325 | V62: 607.43378 | W62: 603.52832 | X62: 600.10052 | Y62: 598.05072 | Z62: 594.11865 | AA62: 591.48737 | AB62: 586.55676 | AC62: 581.1377 | AD62: 572.23102 | AE62: 0.006

Sheet AEO 2026 Table 49
A1: Table 49. Freight Transportation Energy Use
A2: https://www.eia.gov/outlooks/aeo/data/browser/#/?id=58-AEO2026&cases=electrnp&sourcekey=0
A3: Thu Apr 23 2026 15:05:43 GMT-0700 (Pacific Daylight Time)
A4: Source: U.S. Energy Information Administration
B5: full name | C5: api key | D5: units | E5: 2025 | F5: 2026 | G5: 2027 | H5: 2028 | I5: 2029 | J5: 2030 | K5: 2031 | L5: 2032 | M5: 2033 | N5: 2034 | O5: 2035 | P5: 2036 | Q5: 2037 | R5: 2038 | S5: 2039 | T5: 2040 | U5: 2041 | V5: 2042 | W5: 2043 | X5: 2044 | Y5: 2045 | Z5: 2046 | AA5: 2047 | AB5: 2048 | AC5: 2049 | AD5: 2050 | AE5: Growth (2025-2050)
A6: Freight Truck Stock by Size Class
A7: Vehicle Miles Traveled (billion miles)
A8: Light Medium
A9: Diesel | B9: Freight: Truck Stock: Vehicle Miles Traveled: Light Medium: Diesel: Alternative Electricity and Transportation | C9: AEO.2026.ELECTRNP.ECI_VMT_FGHT_LITEMEDS_DSL_NA_NA_BLNMLS.A | D9: billion miles | E9: 58.413017 | F9: 57.420311 | G9: 56.362801 | H9: 55.456158 | I9: 54.686531 | J9: 54.216652 | K9: 53.628971 | L9: 53.071381 | M9: 52.386211 | N9: 51.729412 | O9: 50.979725 | P9: 50.103706 | Q9: 49.202808 | R9: 48.319229 | S9: 47.434059 | T9: 46.587254 | U9: 45.608746 | V9: 44.484791 | W9: 43.169189 | X9: 41.718536 | Y9: 40.212212 | Z9: 38.761288 | AA9: 37.372833 | AB9: 35.951756 | AC9: 34.608257 | AD9: 33.299496 | AE9: -0.022
A10: Motor Gasoline | B10: Freight: Truck Stock: Vehicle Miles Traveled: Light Medium: Motor Gasoline: Alternative Electricity and Transportation | C10: AEO.2026.ELECTRNP.ECI_VMT_FGHT_LITEMEDS_MGS_NA_NA_BLNMLS.A | D10: billion miles | E10: 27.328077 | F10: 28.272638 | G10: 29.206049 | H10: 30.198536 | I10: 31.257954 | J10: 32.472885 | K10: 33.565792 | L10: 34.62991 | M10: 35.530155 | N10: 36.361717 | O10: 37.028927 | P10: 37.488136 | Q10: 37.843647 | R10: 38.147228 | S10: 38.407978 | T10: 38.634766 | U10: 38.685001 | V10: 38.508476 | W10: 38.076015 | X10: 37.432987 | Y10: 36.696804 | Z10: 35.933998 | AA10: 35.163811 | AB10: 34.305832 | AC10: 33.493919 | AD10: 32.678135 | AE10: 0.007
A11: Propane | B11: Freight: Truck Stock: Vehicle Miles Traveled: Light Medium: Propane: Alternative Electricity and Transportation | C11: AEO.2026.ELECTRNP.ECI_VMT_FGHT_LITEMEDS_PROP_NA_NA_BLNMLS.A | D11: billion miles | E11: 0.000624 | F11: 0.000625 | G11: 0.000632 | H11: 0.000652 | I11: 0.000673 | J11: 0.000696 | K11: 0.000721 | L11: 0.000747 | M11: 0.000747 | N11: 0.00074 | O11: 0.000747 | P11: 0.000764 | Q11: 0.000788 | R11: 0.000817 | S11: 0.000849 | T11: 0.000884 | U11: 0.000918 | V11: 0.000951 | W11: 0.000982 | X11: 0.001012 | Y11: 0.001043 | Z11: 0.001075 | AA11: 0.001107 | AB11: 0.001138 | AC11: 0.001168 | AD11: 0.001194 | AE11: 0.026
A12: Compressed/Liquefied Natural Gas | B12: Freight: Truck Stock: Vehicle Miles Traveled: Light Medium: Natural Gas: Alternative Electricity and Transportation | C12: AEO.2026.ELECTRNP.ECI_VMT_FGHT_LITEMEDS_NG_NA_NA_BLNMLS.A | D12: billion miles | E12: 0.1018 | F12: 0.14121 | G12: 0.143647 | H12: 0.138923 | I12: 0.134816 | J12: 0.132154 | K12: 0.130291 | L12: 0.130465 | M12: 0.131806 | N12: 0.134191 | O12: 0.138595 | P12: 0.14476 | Q12: 0.157973 | R12: 0.173051 | S12: 0.190677 | T12: 0.217789 | U12: 0.252384 | V12: 0.300604 | W12: 0.35725 | X12: 0.422417 | Y12: 0.500916 | Z12: 0.582305 | AA12: 0.680468 | AB12: 0.791074 | AC12: 0.906443 | AD12: 1.041519 | AE12: 0.097
A13: Ethanol-Flex Fuel | B13: Freight: Truck Stock: Vehicle Miles Traveled: Light Medium: Ethanol-Flex Fuel: Alternative Electricity and Transportation | C13: AEO.2026.ELECTRNP.ECI_VMT_FGHT_LITEMEDS_EFFI_NA_NA_BLNMLS.A | D13: billion miles | E13: 2.734304 | F13: 2.478483 | G13: 2.234351 | H13: 2.013251 | I13: 1.81403 | J13: 1.636645 | K13: 1.472175 | L13: 1.323703 | M13: 1.187042 | N13: 1.067449 | O13: 0.958435 | P13: 0.85986 | Q13: 0.76879 | R13: 0.688141 | S13: 0.613102 | T13: 0.547159 | U13: 0.490353 | V13: 0.43976 | W13: 0.395778 | X13: 0.353755 | Y13: 0.311554 | Z13: 0.272084 | AA13: 0.236563 | AB13: 0.199415 | AC13: 0.163905 | AD13: 0.130143 | AE13: -0.115
A14: Electric | B14: Freight: Truck Stock: Vehicle Miles Traveled: Light Medium: Electric: Alternative Electricity and Transportation | C14: AEO.2026.ELECTRNP.ECI_VMT_FGHT_LITEMEDS_ELE_NA_NA_BLNMLS.A | D14: billion miles | E14: 0.201876 | F14: 0.235023 | G14: 0.265451 | H14: 0.293527 | I14: 0.321031 | J14: 0.349323 | K14: 0.375645 | L14: 0.401731 | M14: 0.426124 | N14: 0.450529 | O14: 0.473888 | P14: 0.496025 | Q14: 0.517966 | R14: 0.540045 | S14: 0.561847 | T14: 0.659889 | U14: 0.976502 | V14: 1.636871 | W14: 2.631784 | X14: 4.008795 | Y14: 5.728106 | Z14: 7.605267 | AA14: 9.642061 | AB14: 11.816639 | AC14: 14.05707 | AD14: 16.278847 | AE14: 0.192
A15: Plug-in Diesel Hybrid | B15: Freight: Truck Stock: Vehicle Miles Traveled: Light Medium: Plug-in Diesel Hybrid: Alternative Electricity and Transportation | C15: AEO.2026.ELECTRNP.ECI_VMT_FGHT_LITEMEDS_EDH_NA_NA_BLNMLS.A | D15: billion miles | E15: 0 | F15: 0 | G15: 0 | H15: 0 | I15: 0 | J15: 0 | K15: 0 | L15: 0 | M15: 0 | N15: 0 | O15: 0 | P15: 0 | Q15: 0 | R15: 0 | S15: 0 | T15: 0 | U15: 0 | V15: 0 | W15: 0 | X15: 0 | Y15: 0 | Z15: 0 | AA15: 0 | AB15: 0 | AC15: 0 | AD15: 0 | AE15: - -
A16: Plug-in Gasoline Hybrid | B16: Freight: Truck Stock: Vehicle Miles Traveled: Light Medium: Plug-in Gasoline Hybrid: Alternative Electricity and Transportation | C16: AEO.2026.ELECTRNP.ECI_VMT_FGHT_LITEMEDS_EGH_NA_NA_BLNMLS.A | D16: billion miles | E16: 0 | F16: 0 | G16: 0 | H16: 0 | I16: 0 | J16: 0 | K16: 0 | L16: 0 | M16: 0 | N16: 0 | O16: 0 | P16: 0 | Q16: 0 | R16: 0 | S16: 0 | T16: 0 | U16: 0 | V16: 0 | W16: 0 | X16: 0 | Y16: 0 | Z16: 0 | AA16: 0 | AB16: 0 | AC16: 0 | AD16: 0 | AE16: - -
A17: Fuel Cell | B17: Freight: Truck Stock: Vehicle Miles Traveled: Light Medium: Fuel Cell: Alternative Electricity and Transportation | C17: AEO.2026.ELECTRNP.ECI_VMT_FGHT_LITEMEDS_FUC_NA_NA_BLNMLS.A | D17: billion miles | E17: 0 | F17: 0 | G17: 0 | H17: 0 | I17: 0 | J17: 0 | K17: 0 | L17: 0 | M17: 0 | N17: 0 | O17: 0 | P17: 0 | Q17: 0 | R17: 0 | S17: 0 | T17: 0 | U17: 0 | V17: 0 | W17: 0 | X17: 0 | Y17: 0 | Z17: 0 | AA17: 0 | AB17: 0 | AC17: 0 | AD17: 0 | AE17: - -
A18: Fuel Cell Battery Dominant | B18: Freight: Truck Stock: Vehicle Miles Traveled: Light Medium: Fuel Cell Battery Dominant: Alternative Electricity and Transportation | C18: AEO.2026.ELECTRNP.ECI_VMT_FGHT_LITEMEDS_FEUCELBATDOM_NA_NA_BLNMLS.A | D18: billion miles | E18: 0 | F18: 0 | G18: 0 | H18: 0 | I18: 0 | J18: 0 | K18: 0 | L18: 0 | M18: 0 | N18: 0 | O18: 0 | P18: 0 | Q18: 0 | R18: 0 | S18: 0 | T18: 0 | U18: 0 | V18: 0 | W18: 0 | X18: 0 | Y18: 0 | Z18: 0 | AA18: 0 | AB18: 0 | AC18: 0 | AD18: 0 | AE18: - -
A19: Gasoline Hybrid | B19: Freight: Truck Stock: Vehicle Miles Traveled: Light Medium: Gasoline Hybrid: Alternative Electricity and Transportation | C19: AEO.2026.ELECTRNP.ECI_VMT_FGHT_LITEMEDS_GASHEV_NA_NA_BLNMLS.A | D19: billion miles | E19: 0.097703 | F19: 0.263975 | G19: 0.48311 | H19: 0.75416 | I19: 1.100802 | J19: 1.58399 | K19: 2.203856 | L19: 2.995292 | M19: 4.011751 | N19: 5.298637 | O19: 6.892163 | P19: 8.837455 | Q19: 11.058461 | R19: 13.483864 | S19: 16.040926 | T19: 18.654707 | U19: 21.234295 | V19: 23.733828 | W19: 26.101175 | X19: 28.37425 | Y19: 30.614744 | Z19: 32.802284 | AA19: 34.960983 | AB19: 37.017426 | AC19: 38.97467 | AD19: 40.763081 | AE19: 0.273
A20: Hydrogen ICE | B20: Freight: Truck Stock: Vehicle Miles Traveled: Light Medium: Hydrogen ICE: Alternative Electricity and Transportation | C20: AEO.2026.ELECTRNP.ECI_VMT_FGHT_LITEMEDS_HYDICE_NA_NA_BLNMLS.A | D20: billion miles | E20: 0 | F20: 0 | G20: 0 | H20: 0 | I20: 0 | J20: 0 | K20: 0 | L20: 0 | M20: 0 | N20: 0 | O20: 0 | P20: 0 | Q20: 0 | R20: 0 | S20: 0 | T20: 0 | U20: 0 | V20: 0 | W20: 0 | X20: 0 | Y20: 0 | Z20: 0 | AA20: 0 | AB20: 0 | AC20: 0 | AD20: 0 | AE20: - -
A21: Light Medium Subtotal | B21: Freight: Truck Stock: Vehicle Miles Traveled: Light Medium: Alternative Electricity and Transportation | C21: AEO.2026.ELECTRNP.ECI_VMT_FGHT_LITEMEDS_NA_NA_NA_BLNMLS.A | D21: billion miles | E21: 88.87738 | F21: 88.81218 | G21: 88.69593 | H21: 88.855186 | I21: 89.315735 | J21: 90.392151 | K21: 91.377357 | L21: 92.553032 | M21: 93.673729 | N21: 95.042549 | O21: 96.472305 | P21: 97.930557 | Q21: 99.550018 | R21: 101.35216 | S21: 103.24905 | T21: 105.30214 | U21: 107.24771 | V21: 109.10486 | W21: 110.73187 | X21: 112.31132 | Y21: 114.06494 | Z21: 115.95789 | AA21: 118.0573 | AB21: 120.08257 | AC21: 122.2047 | AD21: 124.19183 | AE21: 0.013
A22: Medium
A23: Diesel | B23: Freight: Truck Stock: Vehicle Miles Traveled: Medium: Diesel: Alternative Electricity and Transportation | C23: AEO.2026.ELECTRNP.ECI_VMT_FGHT_SOSOS_DSL_NA_NA_BLNMLS.A | D23: billion miles | E23: 35.473877 | F23: 34.636177 | G23: 33.951637 | H23: 33.342804 | I23: 32.749153 | J23: 32.298199 | K23: 31.77066 | L23: 31.311335 | M23: 30.799314 | N23: 30.333715 | O23: 29.880741 | P23: 29.443609 | Q23: 29.022797 | R23: 28.609694 | S23: 28.222281 | T23: 27.871525 | U23: 27.527695 | V23: 27.212862 | W23: 26.924488 | X23: 26.683699 | Y23: 26.514278 | Z23: 26.380215 | AA23: 26.283073 | AB23: 26.17104 | AC23: 26.08226 | AD23: 25.990124 | AE23: -0.012
A24: Motor Gasoline | B24: Freight: Truck Stock: Vehicle Miles Traveled: Medium: Motor Gasoline: Alternative Electricity and Transportation | C24: AEO.2026.ELECTRNP.ECI_VMT_FGHT_SOSOS_MGS_NA_NA_BLNMLS.A | D24: billion miles | E24: 22.472101 | F24: 22.273155 | G24: 22.199646 | H24: 22.199471 | I24: 22.203886 | J24: 22.291555 | K24: 22.325485 | L24: 22.409365 | M24: 22.439425 | N24: 22.504622 | O24: 22.556879 | P24: 22.584263 | Q24: 22.614752 | R24: 22.633869 | S24: 22.65753 | T24: 22.692263 | U24: 22.726048 | V24: 22.763575 | W24: 22.784922 | X24: 22.818722 | Y24: 22.893072 | Z24: 22.978222 | AA24: 23.073374 | AB24: 23.140879 | AC24: 23.219425 | AD24: 23.281679 | AE24: 0.001
A25: Propane | B25: Freight: Truck Stock: Vehicle Miles Traveled: Medium: Propane: Alternative Electricity and Transportation | C25: AEO.2026.ELECTRNP.ECI_VMT_FGHT_SOSOS_PROP_NA_NA_BLNMLS.A | D25: billion miles | E25: 0.021876 | F25: 0.019477 | G25: 0.017259 | H25: 0.015325 | I25: 0.012689 | J25: 0.011285 | K25: 0.009969 | L25: 0.008869 | M25: 0.007902 | N25: 0.006905 | O25: 0.006157 | P25: 0.005567 | Q25: 0.005097 | R25: 0.004691 | S25: 0.004345 | T25: 0.004065 | U25: 0.003807 | V25: 0.003581 | W25: 0.003376 | X25: 0.003178 | Y25: 0.003057 | Z25: 0.002919 | AA25: 0.002794 | AB25: 0.002472 | AC25: 0.00196 | AD25: 0.001558 | AE25: -0.1
A26: Compressed/Liquefied Natural Gas | B26: Freight: Truck Stock: Vehicle Miles Traveled: Medium: Natural Gas: Alternative Electricity and Transportation | C26: AEO.2026.ELECTRNP.ECI_VMT_FGHT_SOSOS_NG_NA_NA_BLNMLS.A | D26: billion miles | E26: 0.198516 | F26: 0.227574 | G26: 0.254634 | H26: 0.278156 | I26: 0.29812 | J26: 0.317631 | K26: 0.334468 | L26: 0.350501 | M26: 0.364306 | N26: 0.377323 | O26: 0.389464 | P26: 0.400456 | Q26: 0.410077 | R26: 0.418767 | S26: 0.426908 | T26: 0.435692 | U26: 0.443724 | V26: 0.451052 | W26: 0.457884 | X26: 0.465338 | Y26: 0.474029 | Z26: 0.483517 | AA26: 0.493363 | AB26: 0.502124 | AC26: 0.51023 | AD26: 0.518272 | AE26: 0.039
A27: Ethanol-Flex Fuel | B27: Freight: Truck Stock: Vehicle Miles Traveled: Medium: Ethanol-Flex Fuel: Alternative Electricity and Transportation | C27: AEO.2026.ELECTRNP.ECI_VMT_FGHT_SOSOS_EFFI_NA_NA_BLNMLS.A | D27: billion miles | E27: 0.471747 | F27: 0.424195 | G27: 0.37903 | H27: 0.338592 | I27: 0.303526 | J27: 0.27229 | K27: 0.243349 | L27: 0.218305 | M27: 0.194632 | N27: 0.174528 | O27: 0.157624 | P27: 0.143036 | Q27: 0.13103 | R27: 0.120871 | S27: 0.112196 | T27: 0.104912 | U27: 0.098112 | V27: 0.091597 | W27: 0.085259 | X27: 0.079067 | Y27: 0.072946 | Z27: 0.06667 | AA27: 0.059992 | AB27: 0.053042 | AC27: 0.046259 | AD27: 0.039101 | AE27: -0.095
A28: Electric | B28: Freight: Truck Stock: Vehicle Miles Traveled: Medium: Electric: Alternative Electricity and Transportation | C28: AEO.2026.ELECTRNP.ECI_VMT_FGHT_SOSOS_ELE_NA_NA_BLNMLS.A | D28: billion miles | E28: 0.03286 | F28: 0.038334 | G28: 0.043723 | H28: 0.048565 | I28: 0.052798 | J28: 0.056869 | K28: 0.060378 | L28: 0.063791 | M28: 0.066864 | N28: 0.069822 | O28: 0.07253 | P28: 0.074932 | Q28: 0.077126 | R28: 0.079027 | S28: 0.080831 | T28: 0.08258 | U28: 0.08423 | V28: 0.08576 | W28: 0.087098 | X28: 0.088384 | Y28: 0.089767 | Z28: 0.091137 | AA28: 0.092493 | AB28: 0.093719 | AC28: 0.094979 | AD28: 0.096184 | AE28: 0.044
A29: Plug-in Diesel Hybrid | B29: Freight: Truck Stock: Vehicle Miles Traveled: Medium: Plug-in Diesel Hybrid: Alternative Electricity and Transportation | C29: AEO.2026.ELECTRNP.ECI_VMT_FGHT_SOSOS_EDH_NA_NA_BLNMLS.A | D29: billion miles | E29: 0 | F29: 0 | G29: 0 | H29: 0 | I29: 0 | J29: 0 | K29: 0 | L29: 0 | M29: 0 | N29: 0 | O29: 0 | P29: 0 | Q29: 0 | R29: 0 | S29: 0 | T29: 0 | U29: 0 | V29: 0 | W29: 0 | X29: 0 | Y29: 0 | Z29: 0 | AA29: 0 | AB29: 0 | AC29: 0 | AD29: 0 | AE29: - -
A30: Plug-in Gasoline Hybrid | B30: Freight: Truck Stock: Vehicle Miles Traveled: Medium: Plug-in Gasoline Hybrid: Alternative Electricity and Transportation | C30: AEO.2026.ELECTRNP.ECI_VMT_FGHT_SOSOS_EGH_NA_NA_BLNMLS.A | D30: billion miles | E30: 0.007038 | F30: 0.006426 | G30: 0.00586 | H30: 0.005317 | I30: 0.004858 | J30: 0.004444 | K30: 0.004071 | L30: 0.003772 | M30: 0.003449 | N30: 0.003161 | O30: 0.002848 | P30: 0.002602 | Q30: 0.002382 | R30: 0.002184 | S30: 0.002012 | T30: 0.001845 | U30: 0.001676 | V30: 0.001532 | W30: 0.001382 | X30: 0.001241 | Y30: 0.001165 | Z30: 0.001079 | AA30: 0.001006 | AB30: 0.000935 | AC30: 0.000865 | AD30: 0.000801 | AE30: -0.083
A31: Fuel Cell | B31: Freight: Truck Stock: Vehicle Miles Traveled: Medium: Fuel Cell: Alternative Electricity and Transportation | C31: AEO.2026.ELECTRNP.ECI_VMT_FGHT_SOSOS_FUC_NA_NA_BLNMLS.A | D31: billion miles | E31: 0 | F31: 0 | G31: 0 | H31: 0 | I31: 0 | J31: 0 | K31: 0 | L31: 0 | M31: 0 | N31: 0 | O31: 0 | P31: 0 | Q31: 0 | R31: 0 | S31: 0 | T31: 0 | U31: 0 | V31: 0 | W31: 0 | X31: 0 | Y31: 0 | Z31: 0 | AA31: 0 | AB31: 0 | AC31: 0 | AD31: 0 | AE31: - -
A32: Fuel Cell Battery Dominant | B32: Freight: Truck Stock: Vehicle Miles Traveled: Medium: Fuel Cell Battery Dominant: Alternative Electricity and Transportation | C32: AEO.2026.ELECTRNP.ECI_VMT_FGHT_SOSOS_FEUCELBATDOM_NA_NA_BLNMLS.A | D32: billion miles | E32: 0 | F32: 0 | G32: 0 | H32: 0 | I32: 0 | J32: 0 | K32: 0 | L32: 0 | M32: 0 | N32: 0 | O32: 0 | P32: 0 | Q32: 0 | R32: 0 | S32: 0 | T32: 0 | U32: 0 | V32: 0 | W32: 0 | X32: 0 | Y32: 0 | Z32: 0 | AA32: 0 | AB32: 0 | AC32: 0 | AD32: 0 | AE32: - -
A33: Gasoline Hybrid | B33: Freight: Truck Stock: Vehicle Miles Traveled: Medium: Gasoline Hybrid: Alternative Electricity and Transportation | C33: AEO.2026.ELECTRNP.ECI_VMT_FGHT_SOSOS_GASHEV_NA_NA_BLNMLS.A | D33: billion miles | E33: 0.046002 | F33: 0.107735 | G33: 0.184516 | H33: 0.270278 | I33: 0.363758 | J33: 0.475325 | K33: 0.612879 | L33: 0.791703 | M33: 1.023004 | N33: 1.317616 | O33: 1.678429 | P33: 2.094684 | Q33: 2.552488 | R33: 3.034955 | S33: 3.528108 | T33: 4.02558 | U33: 4.513166 | V33: 4.980268 | W33: 5.41933 | X33: 5.834762 | Y33: 6.233894 | Z33: 6.608096 | AA33: 6.956055 | AB33: 7.267446 | AC33: 7.558473 | AD33: 7.826682 | AE33: 0.228
A34: Hydrogen ICE | B34: Freight: Truck Stock: Vehicle Miles Traveled: Medium: Hydrogen ICE: Alternative Electricity and Transportation | C34: AEO.2026.ELECTRNP.ECI_VMT_FGHT_SOSOS_HYDICE_NA_NA_BLNMLS.A | D34: billion miles | E34: 0 | F34: 0 | G34: 0 | H34: 0 | I34: 0 | J34: 0 | K34: 0 | L34: 0 | M34: 0 | N34: 0 | O34: 0 | P34: 0 | Q34: 0 | R34: 0 | S34: 0 | T34: 0 | U34: 0 | V34: 0 | W34: 0 | X34: 0 | Y34: 0 | Z34: 0 | AA34: 0 | AB34: 0 | AC34: 0 | AD34: 0 | AE34: - -
A35: Medium Subtotal | B35: Freight: Truck Stock: Vehicle Miles Traveled: Medium: Alternative Electricity and Transportation | C35: AEO.2026.ELECTRNP.ECI_VMT_FGHT_SOSOS_NA_NA_NA_BLNMLS.A | D35: billion miles | E35: 58.723938 | F35: 57.732971 | G35: 57.03632 | H35: 56.498383 | I35: 55.988701 | J35: 55.72757 | K35: 55.361137 | L35: 55.157551 | M35: 54.898758 | N35: 54.787544 | O35: 54.744614 | P35: 54.748993 | Q35: 54.815586 | R35: 54.903839 | S35: 55.034004 | T35: 55.218201 | U35: 55.398125 | V35: 55.589947 | W35: 55.763374 | X35: 55.974079 | Y35: 56.281857 | Z35: 56.611492 | AA35: 56.961727 | AB35: 57.231262 | AC35: 57.514015 | AD35: 57.753994 | AE35: -0.001
A36: Heavy
A37: Diesel | B37: Freight: Truck Stock: Vehicle Miles Traveled: Heavy: Diesel: Alternative Electricity and Transportation | C37: AEO.2026.ELECTRNP.ECI_VMT_FGHT_RADS_DSL_NA_NA_BLNMLS.A | D37: billion miles | E37: 187.04558 | F37: 189.13751 | G37: 192.07028 | H37: 194.86043 | I37: 197.17221 | J37: 199.93974 | K37: 201.88611 | L37: 204.01027 | M37: 205.7254 | N37: 207.68256 | O37: 209.61925 | P37: 211.40707 | Q37: 213.05916 | R37: 214.51825 | S37: 215.86418 | T37: 217.23761 | U37: 218.5592 | V37: 219.76907 | W37: 220.76521 | X37: 221.80159 | Y37: 223.12463 | Z37: 224.45613 | AA37: 225.67697 | AB37: 226.43829 | AC37: 227.10455 | AD37: 227.55908 | AE37: 0.008
A38: Motor Gasoline | B38: Freight: Truck Stock: Vehicle Miles Traveled: Heavy: Motor Gasoline: Alternative Electricity and Transportation | C38: AEO.2026.ELECTRNP.ECI_VMT_FGHT_RADS_MGS_NA_NA_BLNMLS.A | D38: billion miles | E38: 0.165662 | F38: 0.143937 | G38: 0.127268 | H38: 0.114864 | I38: 0.105215 | J38: 0.09804 | K38: 0.092852 | L38: 0.088693 | M38: 0.084903 | N38: 0.082496 | O38: 0.080517 | P38: 0.079052 | Q38: 0.077437 | R38: 0.075494 | S38: 0.072833 | T38: 0.071006 | U38: 0.069542 | V38: 0.068475 | W38: 0.067472 | X38: 0.066792 | Y38: 0.066506 | Z38: 0.066525 | AA38: 0.066572 | AB38: 0.066626 | AC38: 0.06672 | AD38: 0.066769 | AE38: -0.036
A39: Propane | B39: Freight: Truck Stock: Vehicle Miles Traveled: Heavy: Propane: Alternative Electricity and Transportation | C39: AEO.2026.ELECTRNP.ECI_VMT_FGHT_RADS_PROP_NA_NA_BLNMLS.A | D39: billion miles | E39: 0.030493 | F39: 0.028196 | G39: 0.026203 | H39: 0.024307 | I39: 0.022731 | J39: 0.021214 | K39: 0.019474 | L39: 0.017863 | M39: 0.016196 | N39: 0.014772 | O39: 0.013275 | P39: 0.01183 | Q39: 0.010407 | R39: 0.009225 | S39: 0.008261 | T39: 0.007476 | U39: 0.006732 | V39: 0.006059 | W39: 0.005435 | X39: 0.004909 | Y39: 0.004471 | Z39: 0.004118 | AA39: 0.003807 | AB39: 0.003459 | AC39: 0.003019 | AD39: 0.002639 | AE39: -0.093
A40: Compressed/Liquefied Natural Gas | B40: Freight: Truck Stock: Vehicle Miles Traveled: Heavy: Natural Gas: Alternative Electricity and Transportation | C40: AEO.2026.ELECTRNP.ECI_VMT_FGHT_RADS_NG_NA_NA_BLNMLS.A | D40: billion miles | E40: 2.111317 | F40: 2.228705 | G40: 2.310136 | H40: 2.377032 | I40: 2.43647 | J40: 2.498318 | K40: 2.552162 | L40: 2.612388 | M40: 2.672212 | N40: 2.739973 | O40: 2.811877 | P40: 2.886451 | Q40: 2.970621 | R40: 3.058638 | S40: 3.154885 | T40: 3.263404 | U40: 3.380116 | V40: 3.50952 | W40: 3.656821 | X40: 3.829383 | Y40: 4.091002 | Z40: 4.39124 | AA40: 4.788629 | AB40: 5.226109 | AC40: 5.746711 | AD40: 6.368496 | AE40: 0.045
A41: Ethanol-Flex Fuel | B41: Freight: Truck Stock: Vehicle Miles Traveled: Heavy: Ethanol-Flex Fuel: Alternative Electricity and Transportation | C41: AEO.2026.ELECTRNP.ECI_VMT_FGHT_RADS_EFFI_NA_NA_BLNMLS.A | D41: billion miles | E41: 0 | F41: 0 | G41: 0 | H41: 0 | I41: 0 | J41: 0 | K41: 0 | L41: 0 | M41: 0 | N41: 0 | O41: 0 | P41: 0 | Q41: 0 | R41: 0 | S41: 0 | T41: 0 | U41: 0 | V41: 0 | W41: 0 | X41: 0 | Y41: 0 | Z41: 0 | AA41: 0 | AB41: 0 | AC41: 0 | AD41: 0 | AE41: - -
A42: Electric | B42: Freight: Truck Stock: Vehicle Miles Traveled: Heavy: Electric: Alternative Electricity and Transportation | C42: AEO.2026.ELECTRNP.ECI_VMT_FGHT_RADS_ELE_NA_NA_BLNMLS.A | D42: billion miles | E42: 0.244567 | F42: 0.303315 | G42: 0.360797 | H42: 0.412789 | I42: 0.458465 | J42: 0.500613 | K42: 0.536893 | L42: 0.56998 | M42: 0.598776 | N42: 0.625187 | O42: 0.64862 | P42: 0.669041 | Q42: 0.68673 | R42: 0.702045 | S42: 0.715437 | T42: 0.727905 | U42: 0.739043 | V42: 0.748973 | W42: 0.757505 | X42: 0.765736 | Y42: 0.775099 | Z42: 0.784654 | AA42: 0.794258 | AB42: 0.80264 | AC42: 0.811257 | AD42: 0.819398 | AE42: 0.05
A43: Plug-in Diesel Hybrid | B43: Freight: Truck Stock: Vehicle Miles Traveled: Heavy: Plug-in Diesel Hybrid: Alternative Electricity and Transportation | C43: AEO.2026.ELECTRNP.ECI_VMT_FGHT_RADS_EDH_NA_NA_BLNMLS.A | D43: billion miles | E43: 0 | F43: 0 | G43: 0 | H43: 0 | I43: 0 | J43: 0 | K43: 0 | L43: 0 | M43: 0 | N43: 0 | O43: 0 | P43: 0 | Q43: 0 | R43: 0 | S43: 0 | T43: 0 | U43: 0 | V43: 0 | W43: 0 | X43: 0 | Y43: 0 | Z43: 0 | AA43: 0 | AB43: 0 | AC43: 0 | AD43: 0 | AE43: - -
A44: Plug-in Gasoline Hybrid | B44: Freight: Truck Stock: Vehicle Miles Traveled: Heavy: Plug-in Gasoline Hybrid: Alternative Electricity and Transportation | C44: AEO.2026.ELECTRNP.ECI_VMT_FGHT_RADS_EGH_NA_NA_BLNMLS.A | D44: billion miles | E44: 0 | F44: 0 | G44: 0 | H44: 0 | I44: 0 | J44: 0 | K44: 0 | L44: 0 | M44: 0 | N44: 0 | O44: 0 | P44: 0 | Q44: 0 | R44: 0 | S44: 0 | T44: 0 | U44: 0 | V44: 0 | W44: 0 | X44: 0 | Y44: 0 | Z44: 0 | AA44: 0 | AB44: 0 | AC44: 0 | AD44: 0 | AE44: - -
A45: Fuel Cell | B45: Freight: Truck Stock: Vehicle Miles Traveled: Heavy: Fuel Cell: Alternative Electricity and Transportation | C45: AEO.2026.ELECTRNP.ECI_VMT_FGHT_RADS_FUC_NA_NA_BLNMLS.A | D45: billion miles | E45: 0 | F45: 0 | G45: 0 | H45: 0 | I45: 0 | J45: 0 | K45: 0 | L45: 0 | M45: 0 | N45: 0 | O45: 0 | P45: 0 | Q45: 0 | R45: 0 | S45: 0 | T45: 0 | U45: 0 | V45: 0 | W45: 0 | X45: 0 | Y45: 0 | Z45: 0 | AA45: 0 | AB45: 0 | AC45: 0 | AD45: 0 | AE45: - -
A46: Fuel Cell Battery Dominant | B46: Freight: Truck Stock: Vehicle Miles Traveled: Heavy: Fuel Cell Battery Dominant: Alternative Electricity and Transportation | C46: AEO.2026.ELECTRNP.ECI_VMT_FGHT_RADS_FEUCELBATDOM_NA_NA_BLNMLS.A | D46: billion miles | E46: 0 | F46: 0 | G46: 0 | H46: 0 | I46: 0 | J46: 0 | K46: 0 | L46: 0 | M46: 0 | N46: 0 | O46: 0 | P46: 0 | Q46: 0 | R46: 0 | S46: 0 | T46: 0 | U46: 0 | V46: 0 | W46: 0 | X46: 0 | Y46: 0 | Z46: 0 | AA46: 0 | AB46: 0 | AC46: 0 | AD46: 0 | AE46: - -
A47: Gasoline Hybrid | B47: Freight: Truck Stock: Vehicle Miles Traveled: Heavy: Gasoline Hybrid: Alternative Electricity and Transportation | C47: AEO.2026.ELECTRNP.ECI_VMT_FGHT_RADS_GASHEV_NA_NA_BLNMLS.A | D47: billion miles | E47: 0 | F47: 0 | G47: 0 | H47: 0 | I47: 0 | J47: 0 | K47: 0 | L47: 0 | M47: 0 | N47: 0 | O47: 0 | P47: 0 | Q47: 0 | R47: 0 | S47: 0 | T47: 0 | U47: 0 | V47: 0 | W47: 0 | X47: 0 | Y47: 0 | Z47: 0 | AA47: 0 | AB47: 0 | AC47: 0 | AD47: 0 | AE47: - -
A48: Hydrogen ICE | B48: Freight: Truck Stock: Vehicle Miles Traveled: Heavy: Hydrogen ICE: Alternative Electricity and Transportation | C48: AEO.2026.ELECTRNP.ECI_VMT_FGHT_RADS_HYDICE_NA_NA_BLNMLS.A | D48: billion miles | E48: 0 | F48: 0 | G48: 0 | H48: 0 | I48: 0 | J48: 0 | K48: 0 | L48: 0 | M48: 0 | N48: 0 | O48: 0 | P48: 0 | Q48: 0 | R48: 0 | S48: 0 | T48: 0 | U48: 0 | V48: 0 | W48: 0 | X48: 0 | Y48: 0 | Z48: 0 | AA48: 0 | AB48: 0 | AC48: 0 | AD48: 0 | AE48: - -
A49: Heavy Subtotal | B49: Freight: Truck Stock: Vehicle Miles Traveled: Heavy: Alternative Electricity and Transportation | C49: AEO.2026.ELECTRNP.ECI_VMT_FGHT_RADS_NA_NA_NA_BLNMLS.A | D49: billion miles | E49: 189.59769 | F49: 191.84149 | G49: 194.89471 | H49: 197.78938 | I49: 200.19478 | J49: 203.05797 | K49: 205.08691 | L49: 207.29878 | M49: 209.09715 | N49: 211.14455 | O49: 213.17319 | P49: 215.05342 | Q49: 216.8042 | R49: 218.36322 | S49: 219.81549 | T49: 221.30699 | U49: 222.75424 | V49: 224.10158 | W49: 225.25174 | X49: 226.46799 | Y49: 228.06123 | Z49: 229.70213 | AA49: 231.32983 | AB49: 232.53667 | AC49: 233.73163 | AD49: 234.81615 | AE49: 0.009
A50: Total Vehicle Miles Traveled | B50: Freight: Truck Stock: Vehicle Miles Traveled: Alternative Electricity and Transportation | C50: AEO.2026.ELECTRNP.ECI_VMT_FGHT_STK_NA_NA_NA_BLNMLS.A | D50: billion miles | E50: 337.19702 | F50: 338.3859 | G50: 340.62534 | H50: 343.14169 | I50: 345.49872 | J50: 349.17612 | K50: 351.8241 | L50: 355.00659 | M50: 357.66717 | N50: 360.97314 | O50: 364.38873 | P50: 367.73077 | Q50: 371.1673 | R50: 374.61731 | S50: 378.0961 | T50: 381.82568 | U50: 385.39795 | V50: 388.79471 | W50: 391.74475 | X50: 394.75171 | Y50: 398.40692 | Z50: 402.26953 | AA50: 406.34686 | AB50: 409.84818 | AC50: 413.44949 | AD50: 416.75958 | AE50: 0.009
A51: Consumption (trillion Btu)
A52: Light Medium
A53: Diesel | B53: Freight: Truck Stock: Use: Light Medium: Diesel: Alternative Electricity and Transportation | C53: AEO.2026.ELECTRNP.CNSM_NA_FGHT_LITEMEDS_DSL_NA_NA_TRLBTU.A | D53: trillion Btu | E53: 559.32806 | F53: 548.47369 | G53: 536.50122 | H53: 525.61969 | I53: 515.81494 | J53: 508.76144 | K53: 500.73199 | L53: 493.09927 | M53: 484.52698 | N53: 476.50729 | O53: 467.92551 | P53: 458.43347 | Q53: 448.89548 | R53: 439.64508 | S53: 430.47848 | T53: 421.82758 | U53: 412.07047 | V53: 401.17856 | W53: 388.73264 | X53: 375.1691 | Y53: 361.14011 | Z53: 347.65848 | AA53: 334.77768 | AB53: 321.59348 | AC53: 309.08731 | AD53: 296.88892 | AE53: -0.025
A54: Motor Gasoline | B54: Freight: Truck Stock: Use: Light Medium: Motor Gasoline: Alternative Electricity and Transportation | C54: AEO.2026.ELECTRNP.CNSM_NA_FGHT_LITEMEDS_MGS_NA_NA_TRLBTU.A | D54: trillion Btu | E54: 281.99057 | F54: 290.57605 | G54: 299.06045 | H54: 308.1488 | I54: 317.93369 | J54: 329.26114 | K54: 339.38684 | L54: 349.26779 | M54: 357.56308 | N54: 365.23904 | O54: 371.35327 | P54: 375.4549 | Q54: 378.56671 | R54: 381.20209 | S54: 383.44101 | T54: 385.38263 | U54: 385.5737 | V54: 383.51254 | W54: 378.90652 | X54: 372.17584 | Y54: 364.46542 | Z54: 356.44775 | AA54: 348.29224 | AB54: 339.18091 | AC54: 330.47165 | AD54: 321.69217 | AE54: 0.005
A55: Propane | B55: Freight: Truck Stock: Use: Light Medium: Propane: Alternative Electricity and Transportation | C55: AEO.2026.ELECTRNP.CNSM_NA_FGHT_LITEMEDS_PROP_NA_NA_TRLBTU.A | D55: trillion Btu | E55: 0.008242 | F55: 0.008059 | G55: 0.007956 | H55: 0.00804 | I55: 0.008162 | J55: 0.008313 | K55: 0.008484 | L55: 0.008684 | M55: 0.008545 | N55: 0.008299 | O55: 0.008249 | P55: 0.008328 | Q55: 0.008508 | R55: 0.008756 | S55: 0.009048 | T55: 0.009368 | U55: 0.00969 | V55: 0.010005 | W55: 0.010301 | X55: 0.010592 | Y55: 0.010899 | Z55: 0.011209 | AA55: 0.011527 | AB55: 0.01183 | AC55: 0.012118 | AD55: 0.01237 | AE55: 0.016
A56: Compressed/Liquefied Natural Gas | B56: Freight: Truck Stock: Use: Light Medium: Natural Gas: Alternative Electricity and Transportation | C56: AEO.2026.ELECTRNP.CNSM_NA_FGHT_LITEMEDS_NG_NA_NA_TRLBTU.A | D56: trillion Btu | E56: 1.133067 | F56: 1.563024 | G56: 1.587048 | H56: 1.532792 | I56: 1.484739 | J56: 1.452088 | K56: 1.427351 | L56: 1.423106 | M56: 1.430199 | N56: 1.447141 | O56: 1.48364 | P56: 1.537105 | Q56: 1.660259 | R56: 1.801264 | S56: 1.968136 | T56: 2.229018 | U56: 2.564938 | V56: 3.0347 | W56: 3.586609 | X56: 4.221781 | Y56: 4.987718 | Z56: 5.781014 | AA56: 6.73877 | AB56: 7.818509 | AC56: 8.94422 | AD56: 10.26375 | AE56: 0.092
A57: Ethanol-Flex Fuel | B57: Freight: Truck Stock: Use: Light Medium: Ethanol-Flex Fuel: Alternative Electricity and Transportation | C57: AEO.2026.ELECTRNP.CNSM_NA_FGHT_LITEMEDS_EFFI_NA_NA_TRLBTU.A | D57: trillion Btu | E57: 32.525826 | F57: 29.478151 | G57: 26.565994 | H57: 23.928398 | I57: 21.550608 | J57: 19.435328 | K57: 17.476297 | L57: 15.711514 | M57: 14.090517 | N57: 12.675261 | O57: 11.383523 | P57: 10.210846 | Q57: 9.125027 | R57: 8.162225 | S57: 7.267303 | T57: 6.484042 | U57: 5.810884 | V57: 5.210881 | W57: 4.687827 | X57: 4.186725 | Y57: 3.690507 | Z57: 3.229255 | AA57: 2.812924 | AB57: 2.369786 | AC57: 1.940977 | AD57: 1.532972 | AE57: -0.115
A58: Electric | B58: Freight: Truck Stock: Use: Light Medium: Electric: Alternative Electricity and Transportation | C58: AEO.2026.ELECTRNP.CNSM_NA_FGHT_LITEMEDS_ELE_NA_NA_TRLBTU.A | D58: trillion Btu | E58: 0.777796 | F58: 0.89676 | G58: 1.004183 | H58: 1.101862 | I58: 1.196472 | J58: 1.293012 | K58: 1.381444 | L58: 1.468041 | M58: 1.556085 | N58: 1.644188 | O58: 1.728561 | P58: 1.808479 | Q58: 1.887774 | R58: 1.967588 | S58: 2.046446 | T58: 2.402431 | U58: 3.552777 | V58: 5.952444 | W58: 9.567954 | X58: 14.571869 | Y58: 20.820326 | Z58: 27.642302 | AA58: 35.043915 | AB58: 42.947105 | AC58: 51.088852 | AD58: 59.163055 | AE58: 0.189
A59: Plug-in Diesel Hybrid | B59: Freight: Truck Stock: Use: Light Medium: Plug-in Diesel Hybrid: Alternative Electricity and Transportation | C59: AEO.2026.ELECTRNP.CNSM_NA_FGHT_LITEMEDS_EDH_NA_NA_TRLBTU.A | D59: trillion Btu | E59: 0 | F59: 0 | G59: 0 | H59: 0 | I59: 0 | J59: 0 | K59: 0 | L59: 0 | M59: 0 | N59: 0 | O59: 0 | P59: 0 | Q59: 0 | R59: 0 | S59: 0 | T59: 0 | U59: 0 | V59: 0 | W59: 0 | X59: 0 | Y59: 0 | Z59: 0 | AA59: 0 | AB59: 0 | AC59: 0 | AD59: 0 | AE59: - -
A60: Plug-in Gasoline Hybrid | B60: Freight: Truck Stock: Use: Light Medium: Plug-in Gasoline Hybrid: Alternative Electricity and Transportation | C60: AEO.2026.ELECTRNP.CNSM_NA_FGHT_LITEMEDS_EGH_NA_NA_TRLBTU.A | D60: trillion Btu | E60: 0 | F60: 0 | G60: 0 | H60: 0 | I60: 0 | J60: 0 | K60: 0 | L60: 0 | M60: 0 | N60: 0 | O60: 0 | P60: 0 | Q60: 0 | R60: 0 | S60: 0 | T60: 0 | U60: 0 | V60: 0 | W60: 0 | X60: 0 | Y60: 0 | Z60: 0 | AA60: 0 | AB60: 0 | AC60: 0 | AD60: 0 | AE60: - -
A61: Fuel Cell | B61: Freight: Truck Stock: Use: Light Medium: Fuel Cell: Alternative Electricity and Transportation | C61: AEO.2026.ELECTRNP.CNSM_NA_FGHT_LITEMEDS_FUC_NA_NA_TRLBTU.A | D61: trillion Btu | E61: 0 | F61: 0 | G61: 0 | H61: 0 | I61: 0 | J61: 0 | K61: 0 | L61: 0 | M61: 0 | N61: 0 | O61: 0 | P61: 0 | Q61: 0 | R61: 0 | S61: 0 | T61: 0 | U61: 0 | V61: 0 | W61: 0 | X61: 0 | Y61: 0 | Z61: 0 | AA61: 0 | AB61: 0 | AC61: 0 | AD61: 0 | AE61: - -
A62: Fuel Cell Battery Dominant | B62: Freight: Truck Stock: Use: Light Medium: Fuel Cell Battery Dominant: Alternative Electricity and Transportation | C62: AEO.2026.ELECTRNP.CNSM_NA_FGHT_LITEMEDS_FEUCELBATDOM_NA_NA_TRLBTU.A | D62: trillion Btu | E62: 0 | F62: 0 | G62: 0 | H62: 0 | I62: 0 | J62: 0 | K62: 0 | L62: 0 | M62: 0 | N62: 0 | O62: 0 | P62: 0 | Q62: 0 | R62: 0 | S62: 0 | T62: 0 | U62: 0 | V62: 0 | W62: 0 | X62: 0 | Y62: 0 | Z62: 0 | AA62: 0 | AB62: 0 | AC62: 0 | AD62: 0 | AE62: - -
A63: Gasoline Hybrid | B63: Freight: Truck Stock: Use: Light Medium: Gasoline Hybrid: Alternative Electricity and Transportation | C63: AEO.2026.ELECTRNP.CNSM_NA_FGHT_LITEMEDS_GASHEV_NA_NA_TRLBTU.A | D63: trillion Btu | E63: 0.837901 | F63: 2.263584 | G63: 4.139219 | H63: 6.453267 | I63: 9.403066 | J63: 13.499775 | K63: 18.724775 | L63: 25.357943 | M63: 33.825836 | N63: 44.474449 | O63: 57.589203 | P63: 73.550865 | Q63: 91.764168 | R63: 111.66672 | S63: 132.6768 | T63: 154.1756 | U63: 175.41454 | V63: 196.01135 | W63: 215.5347 | X63: 234.2953 | Y63: 252.79953 | Z63: 270.87717 | AA63: 288.72415 | AB63: 305.73019 | AC63: 321.91486 | AD63: 336.70279 | AE63: 0.271
A64: Hydrogen ICE | B64: Freight: Truck Stock: Use: Light Medium: Hydrogen ICE: Alternative Electricity and Transportation | C64: AEO.2026.ELECTRNP.CNSM_NA_FGHT_LITEMEDS_HYDICE_NA_NA_TRLBTU.A | D64: trillion Btu | E64: 0 | F64: 0 | G64: 0 | H64: 0 | I64: 0 | J64: 0 | K64: 0 | L64: 0 | M64: 0 | N64: 0 | O64: 0 | P64: 0 | Q64: 0 | R64: 0 | S64: 0 | T64: 0 | U64: 0 | V64: 0 | W64: 0 | X64: 0 | Y64: 0 | Z64: 0 | AA64: 0 | AB64: 0 | AC64: 0 | AD64: 0 | AE64: - -
A65: Light Medium Subtotal | B65: Freight: Truck Stock: Use: Light Medium: Alternative Electricity and Transportation | C65: AEO.2026.ELECTRNP.CNSM_NA_FGHT_LITEMEDS_NA_NA_NA_TRLBTU.A | D65: trillion Btu | E65: 876.60132 | F65: 873.2594 | G65: 868.86621 | H65: 866.79273 | I65: 867.3916 | J65: 873.71118 | K65: 879.13708 | L65: 886.33618 | M65: 893.0011 | N65: 901.99554 | O65: 911.47192 | P65: 921.00403 | Q65: 931.90784 | R65: 944.45337 | S65: 957.88721 | T65: 972.51056 | U65: 984.99719 | V65: 994.91058 | W65: 1001.0264 | X65: 1004.631 | Y65: 1007.9145 | Z65: 1011.647 | AA65: 1016.4012 | AB65: 1019.6517 | AC65: 1023.4595 | AD65: 1026.2562 | AE65: 0.006
A66: Medium
A67: Diesel | B67: Freight: Truck Stock: Use: Medium: Diesel: Alternative Electricity and Transportation | C67: AEO.2026.ELECTRNP.CNSM_NA_FGHT_SOSOS_DSL_NA_NA_TRLBTU.A | D67: trillion Btu | E67: 538.64502 | F67: 520.90051 | G67: 504.8053 | H67: 489.66006 | I67: 474.32492 | J67: 461.08807 | K67: 446.93625 | L67: 434.01623 | M67: 420.72662 | N67: 408.56439 | O67: 397.1925 | P67: 386.80505 | Q67: 377.30804 | R67: 368.44412 | S67: 360.36447 | T67: 353.10284 | U67: 346.18735 | V67: 340.00372 | W67: 334.53412 | X67: 329.96927 | Y67: 326.4758 | Z67: 323.56586 | AA67: 321.26538 | AB67: 318.91361 | AC67: 316.91791 | AD67: 314.91171 | AE67: -0.021
A68: Motor Gasoline | B68: Freight: Truck Stock: Use: Medium: Motor Gasoline: Alternative Electricity and Transportation | C68: AEO.2026.ELECTRNP.CNSM_NA_FGHT_SOSOS_MGS_NA_NA_TRLBTU.A | D68: trillion Btu | E68: 308.45126 | F68: 304.80548 | G68: 302.31372 | H68: 300.34561 | I68: 298.06372 | J68: 296.58276 | K68: 294.20575 | L68: 292.43842 | M68: 290.03494 | N68: 288.24084 | O68: 286.46951 | P68: 284.71582 | Q68: 283.27158 | R68: 281.90774 | S68: 280.78604 | T68: 279.90537 | U68: 279.13348 | V68: 278.56583 | W68: 277.89999 | X68: 277.45187 | Y68: 277.53906 | Z68: 277.82657 | AA68: 278.3057 | AB68: 278.51498 | AC68: 278.89319 | AD68: 279.0885 | AE68: -0.004
A69: Propane | B69: Freight: Truck Stock: Use: Medium: Propane: Alternative Electricity and Transportation | C69: AEO.2026.ELECTRNP.CNSM_NA_FGHT_SOSOS_PROP_NA_NA_TRLBTU.A | D69: trillion Btu | E69: 0.375728 | F69: 0.333719 | G69: 0.295049 | H69: 0.261401 | I69: 0.215777 | J69: 0.191362 | K69: 0.168542 | L69: 0.149451 | M69: 0.13291 | N69: 0.116113 | O69: 0.103551 | P69: 0.093568 | Q69: 0.085559 | R69: 0.078581 | S69: 0.072608 | T69: 0.067739 | U69: 0.063253 | V69: 0.05929 | W69: 0.0557 | X69: 0.052217 | Y69: 0.050058 | Z69: 0.047622 | AA69: 0.045401 | AB69: 0.039812 | AC69: 0.030988 | AD69: 0.024039 | AE69: -0.104
A70: Compressed/Liquefied Natural Gas | B70: Freight: Truck Stock: Use: Medium: Natural Gas: Alternative Electricity and Transportation | C70: AEO.2026.ELECTRNP.CNSM_NA_FGHT_SOSOS_NG_NA_NA_TRLBTU.A | D70: trillion Btu | E70: 3.344743 | F70: 3.758847 | G70: 4.122656 | H70: 4.418305 | I70: 4.65016 | J70: 4.867208 | K70: 5.035945 | L70: 5.188134 | M70: 5.307139 | N70: 5.414169 | O70: 5.510268 | P70: 5.595399 | Q70: 5.66502 | R70: 5.727298 | S70: 5.787545 | T70: 5.860857 | U70: 5.928517 | V70: 5.990308 | W70: 6.04956 | X70: 6.119152 | Y70: 6.208257 | Z70: 6.310294 | AA70: 6.419319 | AB70: 6.516281 | AC70: 6.607411 | AD70: 6.699282 | AE70: 0.028
A71: Ethanol-Flex Fuel | B71: Freight: Truck Stock: Use: Medium: Ethanol-Flex Fuel: Alternative Electricity and Transportation | C71: AEO.2026.ELECTRNP.CNSM_NA_FGHT_SOSOS_EFFI_NA_NA_TRLBTU.A | D71: trillion Btu | E71: 7.211479 | F71: 6.481194 | G71: 5.788253 | H71: 5.168367 | I71: 4.631076 | J71: 4.152858 | K71: 3.710075 | L71: 3.32774 | M71: 2.967162 | N71: 2.661098 | O71: 2.403502 | P71: 2.181325 | Q71: 1.998322 | R71: 1.843387 | S71: 1.710891 | T71: 1.599372 | U71: 1.49527 | V71: 1.395506 | W71: 1.298364 | X71: 1.20317 | Y71: 1.108185 | Z71: 1.010719 | AA71: 0.907554 | AB71: 0.800719 | AC71: 0.696891 | AD71: 0.587977 | AE71: -0.095
A72: Electric | B72: Freight: Truck Stock: Use: Medium: Electric: Alternative Electricity and Transportation | C72: AEO.2026.ELECTRNP.CNSM_NA_FGHT_SOSOS_ELE_NA_NA_TRLBTU.A | D72: trillion Btu | E72: 0.221221 | F72: 0.264066 | G72: 0.305133 | H72: 0.341033 | I72: 0.371499 | J72: 0.399786 | K72: 0.423556 | L72: 0.446013 | M72: 0.468216 | N72: 0.489433 | O72: 0.508854 | P72: 0.526125 | Q72: 0.541909 | R72: 0.55546 | S72: 0.568332 | T72: 0.58083 | U72: 0.592578 | V72: 0.603422 | W72: 0.612903 | X72: 0.622026 | Y72: 0.631857 | Z72: 0.641612 | AA72: 0.651258 | AB72: 0.659971 | AC72: 0.668905 | AD72: 0.677477 | AE72: 0.046
A73: Plug-in Diesel Hybrid | B73: Freight: Truck Stock: Use: Medium: Plug-in Diesel Hybrid: Alternative Electricity and Transportation | C73: AEO.2026.ELECTRNP.CNSM_NA_FGHT_SOSOS_EDH_NA_NA_TRLBTU.A | D73: trillion Btu | E73: 0 | F73: 0 | G73: 0 | H73: 0 | I73: 0 | J73: 0 | K73: 0 | L73: 0 | M73: 0 | N73: 0 | O73: 0 | P73: 0 | Q73: 0 | R73: 0 | S73: 0 | T73: 0 | U73: 0 | V73: 0 | W73: 0 | X73: 0 | Y73: 0 | Z73: 0 | AA73: 0 | AB73: 0 | AC73: 0 | AD73: 0 | AE73: - -
A74: Plug-in Gasoline Hybrid | B74: Freight: Truck Stock: Use: Medium: Plug-in Gasoline Hybrid: Alternative Electricity and Transportation | C74: AEO.2026.ELECTRNP.CNSM_NA_FGHT_SOSOS_EGH_NA_NA_TRLBTU.A | D74: trillion Btu | E74: 0.091743 | F74: 0.083749 | G74: 0.076348 | H74: 0.069262 | I74: 0.063265 | J74: 0.057866 | K74: 0.052988 | L74: 0.049093 | M74: 0.044872 | N74: 0.041121 | O74: 0.037034 | P74: 0.033831 | Q74: 0.030966 | R74: 0.02839 | S74: 0.02614 | T74: 0.023975 | U74: 0.021774 | V74: 0.019893 | W74: 0.017948 | X74: 0.016112 | Y74: 0.015117 | Z74: 0.014002 | AA74: 0.013052 | AB74: 0.012132 | AC74: 0.011224 | AD74: 0.010387 | AE74: -0.083
A75: Fuel Cell | B75: Freight: Truck Stock: Use: Medium: Fuel Cell: Alternative Electricity and Transportation | C75: AEO.2026.ELECTRNP.CNSM_NA_FGHT_SOSOS_FUC_NA_NA_TRLBTU.A | D75: trillion Btu | E75: 0 | F75: 0 | G75: 0 | H75: 0 | I75: 0 | J75: 0 | K75: 0 | L75: 0 | M75: 0 | N75: 0 | O75: 0 | P75: 0 | Q75: 0 | R75: 0 | S75: 0 | T75: 0 | U75: 0 | V75: 0 | W75: 0 | X75: 0 | Y75: 0 | Z75: 0 | AA75: 0 | AB75: 0 | AC75: 0 | AD75: 0 | AE75: - -
A76: Fuel Cell Battery Dominant | B76: Freight: Truck Stock: Use: Medium: Fuel Cell Battery Dominant: Alternative Electricity and Transportation | C76: AEO.2026.ELECTRNP.CNSM_NA_FGHT_SOSOS_FEUCELBATDOM_NA_NA_TRLBTU.A | D76: trillion Btu | E76: 0 | F76: 0 | G76: 0 | H76: 0 | I76: 0 | J76: 0 | K76: 0 | L76: 0 | M76: 0 | N76: 0 | O76: 0 | P76: 0 | Q76: 0 | R76: 0 | S76: 0 | T76: 0 | U76: 0 | V76: 0 | W76: 0 | X76: 0 | Y76: 0 | Z76: 0 | AA76: 0 | AB76: 0 | AC76: 0 | AD76: 0 | AE76: - -
A77: Gasoline Hybrid | B77: Freight: Truck Stock: Use: Medium: Gasoline Hybrid: Alternative Electricity and Transportation | C77: AEO.2026.ELECTRNP.CNSM_NA_FGHT_SOSOS_GASHEV_NA_NA_TRLBTU.A | D77: trillion Btu | E77: 0.561466 | F77: 1.309784 | G77: 2.239366 | H77: 3.275999 | I77: 4.404085 | J77: 5.746706 | K77: 7.380975 | L77: 9.478567 | M77: 12.151581 | N77: 15.518043 | O77: 19.619717 | P77: 24.337212 | Q77: 29.516897 | R77: 34.967583 | S77: 40.532394 | T77: 46.140942 | U77: 51.637432 | V77: 56.900673 | W77: 61.844921 | X77: 66.521111 | Y77: 71.013214 | Z77: 75.223206 | AA77: 79.136635 | AB77: 82.635941 | AC77: 85.90538 | AD77: 88.91713 | AE77: 0.225
A78: Hydrogen ICE | B78: Freight: Truck Stock: Use: Medium: Hydrogen ICE: Alternative Electricity and Transportation | C78: AEO.2026.ELECTRNP.CNSM_NA_FGHT_SOSOS_HYDICE_NA_NA_TRLBTU.A | D78: trillion Btu | E78: 0 | F78: 0 | G78: 0 | H78: 0 | I78: 0 | J78: 0 | K78: 0 | L78: 0 | M78: 0 | N78: 0 | O78: 0 | P78: 0 | Q78: 0 | R78: 0 | S78: 0 | T78: 0 | U78: 0 | V78: 0 | W78: 0 | X78: 0 | Y78: 0 | Z78: 0 | AA78: 0 | AB78: 0 | AC78: 0 | AD78: 0 | AE78: - -
A79: Medium Subtotal | B79: Freight: Truck Stock: Use: Medium: Alternative Electricity and Transportation | C79: AEO.2026.ELECTRNP.CNSM_NA_FGHT_SOSOS_NA_NA_NA_TRLBTU.A | D79: trillion Btu | E79: 858.90247 | F79: 837.93744 | G79: 819.94568 | H79: 803.53992 | I79: 786.7243 | J79: 773.08643 | K79: 757.91376 | L79: 745.09357 | M79: 731.83337 | N79: 721.04523 | O79: 711.84491 | P79: 704.28845 | Q79: 698.41852 | R79: 693.55243 | S79: 689.84839 | T79: 687.2821 | U79: 685.05988 | V79: 683.53888 | W79: 682.31335 | X79: 681.95477 | Y79: 683.04169 | Z79: 684.63977 | AA79: 686.74438 | AB79: 688.09338 | AC79: 689.73199 | AD79: 690.91626 | AE79: -0.009
A80: Heavy
A81: Diesel | B81: Freight: Truck Stock: Use: Heavy: Diesel: Alternative Electricity and Transportation | C81: AEO.2026.ELECTRNP.CNSM_NA_FGHT_RADS_DSL_NA_NA_TRLBTU.A | D81: trillion Btu | E81: 3899.1636 | F81: 3905.7332 | G81: 3919.7505 | H81: 3927.7983 | I81: 3927.4458 | J81: 3935.9219 | K81: 3928.9243 | L81: 3915.9395 | M81: 3894.9814 | N81: 3881.8469 | O81: 3872.3608 | P81: 3865.115 | Q81: 3860.0361 | R81: 3855.165 | S81: 3851.2703 | T81: 3850.0676 | U81: 3850.9358 | V81: 3853.0911 | W81: 3854.3923 | X81: 3858.7817 | Y81: 3870.1294 | Z81: 3882.9868 | AA81: 3895.2659 | AB81: 3900.7173 | AC81: 3905.2625 | AD81: 3907.053 | AE81: 0
A82: Motor Gasoline | B82: Freight: Truck Stock: Use: Heavy: Motor Gasoline: Alternative Electricity and Transportation | C82: AEO.2026.ELECTRNP.CNSM_NA_FGHT_RADS_MGS_NA_NA_TRLBTU.A | D82: trillion Btu | E82: 3.895916 | F82: 3.373479 | G82: 2.96873 | H82: 2.663699 | I82: 2.423965 | J82: 2.243072 | K82: 2.106568 | L82: 1.992644 | M82: 1.886332 | N82: 1.812256 | O82: 1.74804 | P82: 1.696694 | Q82: 1.642306 | R82: 1.58075 | S82: 1.504948 | T82: 1.448926 | U82: 1.401966 | V82: 1.364058 | W82: 1.329388 | X82: 1.303317 | Y82: 1.286953 | Z82: 1.27807 | AA82: 1.270674 | AB82: 1.26439 | AC82: 1.259528 | AD82: 1.254148 | AE82: -0.044
A83: Propane | B83: Freight: Truck Stock: Use: Heavy: Propane: Alternative Electricity and Transportation | C83: AEO.2026.ELECTRNP.CNSM_NA_FGHT_RADS_PROP_NA_NA_TRLBTU.A | D83: trillion Btu | E83: 0.717862 | F83: 0.663727 | G83: 0.616877 | H83: 0.572515 | I83: 0.53569 | J83: 0.500334 | K83: 0.459703 | L83: 0.421886 | M83: 0.382629 | N83: 0.349054 | O83: 0.313692 | P83: 0.279545 | Q83: 0.245901 | R83: 0.217977 | S83: 0.195179 | T83: 0.176598 | U83: 0.159026 | V83: 0.143094 | W83: 0.12835 | X83: 0.115912 | Y83: 0.105559 | Z83: 0.097199 | AA83: 0.089838 | AB83: 0.081618 | AC83: 0.071222 | AD83: 0.062255 | AE83: -0.093
A84: Compressed/Liquefied Natural Gas | B84: Freight: Truck Stock: Use: Heavy: Natural Gas: Alternative Electricity and Transportation | C84: AEO.2026.ELECTRNP.CNSM_NA_FGHT_RADS_NG_NA_NA_TRLBTU.A | D84: trillion Btu | E84: 48.444195 | F84: 51.019062 | G84: 52.691902 | H84: 53.91468 | I84: 54.875397 | J84: 55.802639 | K84: 56.484993 | L84: 57.177017 | M84: 57.819721 | N84: 58.623337 | O84: 59.513756 | P84: 60.490047 | Q84: 61.677158 | R84: 62.966042 | S84: 64.430603 | T84: 66.139656 | U84: 68.012878 | V84: 70.134583 | W84: 72.576805 | X84: 75.479759 | Y84: 79.939537 | Z84: 85.082169 | AA84: 91.89286 | AB84: 99.368225 | AC84: 108.25826 | AD84: 118.88348 | AE84: 0.037
A85: Ethanol-Flex Fuel | B85: Freight: Truck Stock: Use: Heavy: Ethanol-Flex Fuel: Alternative Electricity and Transportation | C85: AEO.2026.ELECTRNP.CNSM_NA_FGHT_RADS_EFFI_NA_NA_TRLBTU.A | D85: trillion Btu | E85: 0 | F85: 0 | G85: 0 | H85: 0 | I85: 0 | J85: 0 | K85: 0 | L85: 0 | M85: 0 | N85: 0 | O85: 0 | P85: 0 | Q85: 0 | R85: 0 | S85: 0 | T85: 0 | U85: 0 | V85: 0 | W85: 0 | X85: 0 | Y85: 0 | Z85: 0 | AA85: 0 | AB85: 0 | AC85: 0 | AD85: 0 | AE85: - -
A86: Electric | B86: Freight: Truck Stock: Use: Heavy: Electric: Alternative Electricity and Transportation | C86: AEO.2026.ELECTRNP.CNSM_NA_FGHT_RADS_ELE_NA_NA_TRLBTU.A | D86: trillion Btu | E86: 2.735252 | F86: 3.411249 | G86: 4.053236 | H86: 4.613712 | I86: 5.089569 | J86: 5.504602 | K86: 5.841859 | L86: 6.132011 | M86: 6.398458 | N86: 6.636843 | O86: 6.842374 | P86: 7.016326 | Q86: 7.162564 | R86: 7.284901 | S86: 7.387438 | T86: 7.481786 | U86: 7.563673 | V86: 7.636228 | W86: 7.698185 | X86: 7.760623 | Y86: 7.838179 | Z86: 7.920609 | AA86: 8.006039 | AB86: 8.081525 | AC86: 8.16096 | AD86: 8.236738 | AE86: 0.045
A87: Plug-in Diesel Hybrid | B87: Freight: Truck Stock: Use: Heavy: Plug-in Diesel Hybrid: Alternative Electricity and Transportation | C87: AEO.2026.ELECTRNP.CNSM_NA_FGHT_RADS_EDH_NA_NA_TRLBTU.A | D87: trillion Btu | E87: 0 | F87: 0 | G87: 0 | H87: 0 | I87: 0 | J87: 0 | K87: 0 | L87: 0 | M87: 0 | N87: 0 | O87: 0 | P87: 0 | Q87: 0 | R87: 0 | S87: 0 | T87: 0 | U87: 0 | V87: 0 | W87: 0 | X87: 0 | Y87: 0 | Z87: 0 | AA87: 0 | AB87: 0 | AC87: 0 | AD87: 0 | AE87: - -
A88: Plug-in Gasoline Hybrid | B88: Freight: Truck Stock: Use: Heavy: Plug-in Gasoline Hybrid: Alternative Electricity and Transportation | C88: AEO.2026.ELECTRNP.CNSM_NA_FGHT_RADS_EGH_NA_NA_TRLBTU.A | D88: trillion Btu | E88: 0 | F88: 0 | G88: 0 | H88: 0 | I88: 0 | J88: 0 | K88: 0 | L88: 0 | M88: 0 | N88: 0 | O88: 0 | P88: 0 | Q88: 0 | R88: 0 | S88: 0 | T88: 0 | U88: 0 | V88: 0 | W88: 0 | X88: 0 | Y88: 0 | Z88: 0 | AA88: 0 | AB88: 0 | AC88: 0 | AD88: 0 | AE88: - -
A89: Fuel Cell | B89: Freight: Truck Stock: Use: Heavy: Fuel Cell: Alternative Electricity and Transportation | C89: AEO.2026.ELECTRNP.CNSM_NA_FGHT_RADS_FUC_NA_NA_TRLBTU.A | D89: trillion Btu | E89: 0 | F89: 0 | G89: 0 | H89: 0 | I89: 0 | J89: 0 | K89: 0 | L89: 0 | M89: 0 | N89: 0 | O89: 0 | P89: 0 | Q89: 0 | R89: 0 | S89: 0 | T89: 0 | U89: 0 | V89: 0 | W89: 0 | X89: 0 | Y89: 0 | Z89: 0 | AA89: 0 | AB89: 0 | AC89: 0 | AD89: 0 | AE89: - -
A90: Fuel Cell Battery Dominant | B90: Freight: Truck Stock: Use: Heavy: Fuel Cell Battery Dominant: Alternative Electricity and Transportation | C90: AEO.2026.ELECTRNP.CNSM_NA_FGHT_RADS_FEUCELBATDOM_NA_NA_TRLBTU.A | D90: trillion Btu | E90: 0 | F90: 0 | G90: 0 | H90: 0 | I90: 0 | J90: 0 | K90: 0 | L90: 0 | M90: 0 | N90: 0 | O90: 0 | P90: 0 | Q90: 0 | R90: 0 | S90: 0 | T90: 0 | U90: 0 | V90: 0 | W90: 0 | X90: 0 | Y90: 0 | Z90: 0 | AA90: 0 | AB90: 0 | AC90: 0 | AD90: 0 | AE90: - -
A91: Gasoline Hybrid | B91: Freight: Truck Stock: Use: Heavy: Gasoline Hybrid: Alternative Electricity and Transportation | C91: AEO.2026.ELECTRNP.CNSM_NA_FGHT_RADS_GASHEV_NA_NA_TRLBTU.A | D91: trillion Btu | E91: 0 | F91: 0 | G91: 0 | H91: 0 | I91: 0 | J91: 0 | K91: 0 | L91: 0 | M91: 0 | N91: 0 | O91: 0 | P91: 0 | Q91: 0 | R91: 0 | S91: 0 | T91: 0 | U91: 0 | V91: 0 | W91: 0 | X91: 0 | Y91: 0 | Z91: 0 | AA91: 0 | AB91: 0 | AC91: 0 | AD91: 0 | AE91: - -
A92: Hydrogen ICE | B92: Freight: Truck Stock: Use: Heavy: Hydrogen ICE: Alternative Electricity and Transportation | C92: AEO.2026.ELECTRNP.CNSM_NA_FGHT_RADS_HYDICE_NA_NA_TRLBTU.A | D92: trillion Btu | E92: 0 | F92: 0 | G92: 0 | H92: 0 | I92: 0 | J92: 0 | K92: 0 | L92: 0 | M92: 0 | N92: 0 | O92: 0 | P92: 0 | Q92: 0 | R92: 0 | S92: 0 | T92: 0 | U92: 0 | V92: 0 | W92: 0 | X92: 0 | Y92: 0 | Z92: 0 | AA92: 0 | AB92: 0 | AC92: 0 | AD92: 0 | AE92: - -
A93: Heavy Subtotal | B93: Freight: Truck Stock: Use: Heavy: Alternative Electricity and Transportation | C93: AEO.2026.ELECTRNP.CNSM_NA_FGHT_RADS_NA_NA_NA_TRLBTU.A | D93: trillion Btu | E93: 3954.9565 | F93: 3964.2004 | G93: 3980.0811 | H93: 3989.563 | I93: 3990.3696 | J93: 3999.9722 | K93: 3993.8181 | L93: 3981.6636 | M93: 3961.4685 | N93: 3949.2686 | O93: 3940.7786 | P93: 3934.5979 | Q93: 3930.7651 | R93: 3927.2139 | S93: 3924.7883 | T93: 3925.3149 | U93: 3928.0737 | V93: 3932.3694 | W93: 3936.1252 | X93: 3943.4412 | Y93: 3959.2993 | Z93: 3977.3645 | AA93: 3996.5256 | AB93: 4009.5125 | AC93: 4023.0125 | AD93: 4035.4893 | AE93: 0.001
A94: Light Medium | B94: Medium | C94: and Heavy Total
A95: Diesel | B95: Freight: Truck Stock: Use: Light Medium, Medium, and Heavy: Diesel: Alternative Electricity and Transportation | C95: AEO.2026.ELECTRNP.CNSM_NA_FGHT_STK_DSL_NA_NA_TRLBTU.A | D95: trillion Btu | E95: 4997.1367 | F95: 4975.1074 | G95: 4961.0571 | H95: 4943.0781 | I95: 4917.5859 | J95: 4905.7715 | K95: 4876.5928 | L95: 4843.0547 | M95: 4800.2349 | N95: 4766.9185 | O95: 4737.479 | P95: 4710.3535 | Q95: 4686.2397 | R95: 4663.2544 | S95: 4642.1133 | T95: 4624.998 | U95: 4609.1934 | V95: 4594.2734 | W95: 4577.6592 | X95: 4563.9199 | Y95: 4557.7451 | Z95: 4554.2109 | AA95: 4551.3091 | AB95: 4541.2246 | AC95: 4531.2676 | AD95: 4518.8535 | AE95: -0.004
A96: Motor Gasoline | B96: Freight: Truck Stock: Use: Light Medium, Medium, and Heavy: Motor Gasoline: Alternative Electricity and Transportation | C96: AEO.2026.ELECTRNP.CNSM_NA_FGHT_STK_MGS_NA_NA_TRLBTU.A | D96: trillion Btu | E96: 594.33777 | F96: 598.755 | G96: 604.3429 | H96: 611.15808 | I96: 618.42139 | J96: 628.08691 | K96: 635.69916 | L96: 643.69879 | M96: 649.48438 | N96: 655.29211 | O96: 659.5708 | P96: 661.86743 | Q96: 663.48059 | R96: 664.69061 | S96: 665.73199 | T96: 666.73688 | U96: 666.10913 | V96: 663.44244 | W96: 658.13593 | X96: 650.93103 | Y96: 643.29144 | Z96: 635.55237 | AA96: 627.86859 | AB96: 618.96033 | AC96: 610.62439 | AD96: 602.03479 | AE96: 0.001
A97: Propane | B97: Freight: Truck Stock: Use: Light Medium, Medium, and Heavy: Propane: Alternative Electricity and Transportation | C97: AEO.2026.ELECTRNP.CNSM_NA_FGHT_STK_PROP_NA_NA_TRLBTU.A | D97: trillion Btu | E97: 1.101832 | F97: 1.005505 | G97: 0.919882 | H97: 0.841956 | I97: 0.759629 | J97: 0.700009 | K97: 0.636729 | L97: 0.580021 | M97: 0.524084 | N97: 0.473467 | O97: 0.425491 | P97: 0.381441 | Q97: 0.339968 | R97: 0.305314 | S97: 0.276835 | T97: 0.253706 | U97: 0.231968 | V97: 0.212388 | W97: 0.194351 | X97: 0.17872 | Y97: 0.166517 | Z97: 0.156031 | AA97: 0.146766 | AB97: 0.13326 | AC97: 0.114328 | AD97: 0.098664 | AE97: -0.092
A98: Compressed/Liquefied Natural Gas | B98: Freight: Truck Stock: Use: Light Medium, Medium, and Heavy: Natural Gas: Alternative Electricity and Transportation | C98: AEO.2026.ELECTRNP.CNSM_NA_FGHT_STK_NG_NA_NA_TRLBTU.A | D98: trillion Btu | E98: 52.922005 | F98: 56.340935 | G98: 58.401608 | H98: 59.865776 | I98: 61.010296 | J98: 62.121937 | K98: 62.948288 | L98: 63.788258 | M98: 64.55706 | N98: 65.48465 | O98: 66.50766 | P98: 67.622551 | Q98: 69.002441 | R98: 70.494606 | S98: 72.186287 | T98: 74.22953 | U98: 76.506332 | V98: 79.159592 | W98: 82.212975 | X98: 85.820694 | Y98: 91.135513 | Z98: 97.173477 | AA98: 105.05095 | AB98: 113.70302 | AC98: 123.80988 | AD98: 135.84651 | AE98: 0.038
A99: Ethanol-Flex Fuel | B99: Freight: Truck Stock: Use: Light Medium, Medium, and Heavy: Ethanol-Flex Fuel: Alternative Electricity and Transportation | C99: AEO.2026.ELECTRNP.CNSM_NA_FGHT_STK_EFFI_NA_NA_TRLBTU.A | D99: trillion Btu | E99: 39.737305 | F99: 35.959343 | G99: 32.354248 | H99: 29.096766 | I99: 26.181684 | J99: 23.588186 | K99: 21.186373 | L99: 19.039253 | M99: 17.05768 | N99: 15.336359 | O99: 13.787025 | P99: 12.392171 | Q99: 11.123348 | R99: 10.005611 | S99: 8.978194 | T99: 8.083414 | U99: 7.306155 | V99: 6.606387 | W99: 5.986191 | X99: 5.389895 | Y99: 4.798692 | Z99: 4.239973 | AA99: 3.720478 | AB99: 3.170504 | AC99: 2.637868 | AD99: 2.120949 | AE99: -0.111
A100: Electric | B100: Freight: Truck Stock: Use: Light Medium, Medium, and Heavy: Electric: Alternative Electricity and Transportation | C100: AEO.2026.ELECTRNP.CNSM_NA_FGHT_STK_ELE_NA_NA_TRLBTU.A | D100: trillion Btu | E100: 3.734269 | F100: 4.572075 | G100: 5.362552 | H100: 6.056607 | I100: 6.657541 | J100: 7.197401 | K100: 7.646859 | L100: 8.046065 | M100: 8.422758 | N100: 8.770464 | O100: 9.079788 | P100: 9.350931 | Q100: 9.592247 | R100: 9.807949 | S100: 10.002215 | T100: 10.465047 | U100: 11.709027 | V100: 14.192094 | W100: 17.879042 | X100: 22.954517 | Y100: 29.290361 | Z100: 36.204525 | AA100: 43.70121 | AB100: 51.688599 | AC100: 59.918716 | AD100: 68.077271 | AE100: 0.123
...

Sheet calcs>

Sheet Calculations
A1: LDVs
A2: Car Avg Lifetime, years (Page 22, Table 7) | B2: Light Truck Avg Lifetime, years (Page 25, Table 8) | C2: Avg Car Sales from 2010-2013, thousands of vehicles (Table 1-20, Rows 4-5) | D2: Avg Light Truck Sales from 2010-2013, thousands of vehicles (Table 1-20, Rows 6-8) | E2: Market Share-Weighted Average LDV Lifetime
A3: 13 | B3: 14 | C3: =AVERAGE(SUM('NTS 1-20'!X4:X5),SUM('NTS 1-20'!Y4:Y5),SUM('NTS 1-20'!Z4:Z5),SUM('NTS 1-20'!AA4:AA5)) -> 7982.5 | D3: =AVERAGE(SUM('NTS 1-20'!X6:X8),SUM('NTS 1-20'!Y6:Y8),SUM('NTS 1-20'!Z6:Z8),SUM('NTS 1-20'!AA6:AA8)) -> 4867.25 | E3: =(A3*C3+B3*D3)/(C3+D3) -> 13.378782
A5: HDVs
A6: Heavy Truck Avg Lifetime, years (Table 3-14, Row 43) | B6: Heavy Truck Start Year Vehicles | C6: Bus Lifetime | D6: Bus Start Year Vehicle
A7: 28 | B7: 11932239 | C7: 23 | D7: 1007829.3
A10: aircraft
A11: Exhibits 1-3 illustrate roughly the same results.
A12: Exhibit 1: | B12: Non-dotted lines (aircraft in service) have been constant at 23-24 years for the last 15 years.
A13: Exhibit 2: | B13: Non-dashed lines (aircraft age when they leave service) has been 22-26 for Pax (passengers) and 31-36 for freighters over the last 15 years.
A14: Exhibit 3: | B14: The curves for all aircraft except the 707 Pax and the 737-100/200 Pax cross or are on track to cross 50% survival around age 23-24.
A15: Value selected for use in model
A16: 24
A18: rail
A19: Table | B19: CA Asset Type | C19: Lifetime (years)
A20: 2000 - Water Utility | B20: railroads | C20: 33
A21: 5000 - Transit | B21: locomotives, electric | C21: 35
B22: Value selected for use in model | C22: 34
A23: Neither of these asset types is exactly what I'd prefer (which would be something like "locomotives, diesel"
A24: or "locomotives, freight"), but they seem like reasonable values and are close to each other.
A26: ships
A27: Table | B27: CA Asset Type | C27: Lifetime (years)
A28: 3000 - Harbor & Port | B28: Motor vessels - diesel, ocean | C28: 33
A30: motorbikes
A31: Year | B31: Registered Motorcycles | C31: Motorcycles sold (new) | D31: Retiring Motorcycles | E31: Percentage of Fleet That Retired This Year
A32: 1997 | B32: 3826373 | C32: 260000
A33: 1998 | B33: 3879450 | C33: 311000 | D33: =C33-(B33-B32) -> 257923 | E33: =D33/B33 -> 0.066484424
A34: 1999 | B34: 4152433 | C34: 394000 | D34: =C34-(B34-B33) -> 121017 | E34: =D34/B34 -> 0.029143637
A35: 2000 | B35: 4346068 | C35: 490000 | D35: =C35-(B35-B34) -> 296365 | E35: =D35/B35 -> 0.068191524
A36: 2001 | B36: 4903056 | C36: 577000 | D36: =C36-(B36-B35) -> 20012 | E36: =D36/B36 -> 0.0040815361
A37: 2002 | B37: 5004156 | C37: 640000 | D37: =C37-(B37-B36) -> 538900 | E37: =D37/B37 -> 0.10769049
A38: 2003 | B38: 5370035 | C38: 683000 | D38: =C38-(B38-B37) -> 317121 | E38: =D38/B38 -> 0.059053805
A39: 2004 | B39: 5780870 | C39: 750000 | D39: =C39-(B39-B38) -> 339165 | E39: =D39/B39 -> 0.058670235
A40: 2005 | B40: 6227146 | C40: 831000 | D40: =C40-(B40-B39) -> 384724 | E40: =D40/B40 -> 0.061781754
A41: 2006 | B41: 6678958 | C41: 892000 | D41: =C41-(B41-B40) -> 440188 | E41: =D41/B41 -> 0.065906688
A42: 2007 | B42: 7138476 | C42: 885000 | D42: =C42-(B42-B41) -> 425482 | E42: =D42/B42 -> 0.059604039
A44: Average Percent Fleet Retirement per Year
A45: =AVERAGE(E33:E42) -> 0.058060813
A47: Estimated Lifetime of Motorcycle (years)
A48: =1/A45 -> 17.223321
A51: Motorbike lifetime on the on-road scope
A52: FHWA MV-1 registered motorcycles 2015 (BTS NTS 1-11) | B52: 8600936
A53: FHWA MV-1 registered motorcycles 2024 | B53: 9261249
A54: Fleet growth per year, 2015-2024 | B54: =(B53-B52)/9 -> 73368.111
A55: MIC on-road new sales 2024 (on-highway + dual-sport + scooter; MIC via RevZilla Common Tread 2026-02-03) | B55: 386168
A56: MIC on-road new sales 2025 (same source) | B56: 354354
A57: Implied retirements per year (average on-road sales - fleet growth) | B57: =AVERAGE(B55:B56)-B54 -> 296892.89
A58: Implied retirement rate on the 2015-2024 average fleet | B58: =B57/AVERAGE(B52:B53) -> 0.033242617
A59: Implied mean life (years) = 1 / rate; the default survival tier (shape 1.06) puts the median at ~0.72 x mean | B59: =1/B58 -> 30.081867
A60: Selected median lifetime, years. The 17.2 above (rows 31-48) is a 1997-2007 stock-flow on MIC totals that include off-highway bikes | B60: 22
A62: Recreational boat lifetime from the registration/NMMA stock-flow
A63: USCG registered recreational vessels 2015 | B63: 11867049
A64: USCG registered recreational vessels 2024 | B64: 11674073
A65: fleet change per year 2015-2024 | B65: =(B64-B63)/9 -> -21441.778
A66: NMMA new powerboat retail units (incl. PWC), 2016-2021 (BTS NTS 1-12) and 2024-2025 (NMMA release / trade press)
A67: year | B67: 2016 | C67: 2017 | D67: 2018 | E67: 2019 | F67: 2020 | G67: 2021 | H67: 2024 | I67: 2025
A68: units | B68: 248000 | C68: 262000 | D68: 281800 | E68: 280000 | F68: 318550 | G68: 305734 | H68: 231576 | I68: 215237
A69: average sales | B69: =AVERAGE(B68:I68) -> 267862.12
A70: implied retirements per year = average sales - fleet change | B70: =B69-B65 -> 289303.9
A71: retirement rate on the average fleet | B71: =B70/AVERAGE(B63:B64) -> 0.024578599
A72: mean life = 1 / rate; median = mean x LN(2)^(1/k) / GAMMA(1+1/k) with the default shape k = 2 (VWSPbV) | B72: =1/B71 -> 40.685801 | C72: =B72*LN(2)^(1/2)/EXP(GAMMALN(1+1/2)) -> 38.221758
A73: Selected median lifetime, passenger ships (recreational boats), years | B73: =ROUND(C72,0) -> 38
A76: Passenger rail lifetime from the NTD deliveries / NTS fleet stock-flow, car basis
A77: Rail revenue vehicles built in year (NTD 2024 age-distribution file, vehicles still in the fleet; ages 5-12 used, newer years under-reported)
A78: year built | B78: 2012 | C78: 2013 | D78: 2014 | E78: 2015 | F78: 2016 | G78: 2017 | H78: 2018 | I78: 2019 | J78: 2020 | K78: 2021 | L78: 2022 | M78: 2023 | N78: 2024
A79: vehicles | B79: 555 | C79: 746 | D79: 806 | E79: 377 | F79: 315 | G79: 486 | H79: 538 | I79: 778 | J79: 304 | K79: 567 | L79: 383 | M79: 366 | N79: 195
A80: average vehicles built per year, 2012-2019 | B80: =AVERAGE(B79:I79) -> 575.125
A81: transit rail vehicles 2014 and 2024 (BTS NTS 1-11: light + heavy + commuter cars and locomotives) | B81: 20172 | C81: 21728
A82: fleet change per year 2014-2024 | B82: =(C81-B81)/10 -> 155.6
A83: implied retirements per year = vehicles built - fleet change | B83: =B80-B82 -> 419.525
A84: retirement rate on the average fleet | B84: =B83/AVERAGE(B81:C81) -> 0.02002506
A85: mean life = 1 / rate; median = mean x LN(2)^(1/k) / GAMMA(1+1/k) with the default shape k = 2 (VWSPbV rail) | B85: =1/B84 -> 49.937429 | C85: =B85*LN(2)^(1/2)/EXP(GAMMALN(1+1/2)) -> 46.913083
A86: Selected median lifetime, passenger rail vehicles, years | B86: =ROUND(C85,0) -> 47
A87: Note: FTA's minimum useful life for rail cars is 25 years; NTD 2024 shows 30% of rail vehicles over 30 years old and an average age of 22.7, consistent with a long median.

Sheet Freight and Buses
A2: commercial truck sales | B2: ='AEO 2026 Table 44'!E62*1000 -> 493783.45
A3: commercial truck stock | B3: ='AEO 2026 Table 45'!E51*1000 -> 14618138
A4: Average replacement time | B4: =1/(B2/B3) -> 29.604349
A7: LDV/MDV sales | B7: =SUM('AEO 2026 Table 49'!E255,'AEO 2026 Table 49'!E269)*1000 -> 468456.33
A8: LDV/MDV stock | B8: =SUM('AEO 2026 Table 49'!E166,'AEO 2026 Table 49'!E180)*10^6 -> 9777321
A9: Average replacement time | B9: =1/(B7/B8) -> 20.871361
A11: HDV sales | B11: ='AEO 2026 Table 49'!E283*1000 -> 287910.31
A12: HDV stock | B12: ='AEO 2026 Table 49'!E194*10^6 -> 5720675
A13: Average replacement time | B13: =1/(B11/B12) -> 19.869643
A15: BNEF, bus sales 2021 | B15: 6000
A16: BNEF, bus fleet 2021 | B16: 73000
A17: average replacement time | B17: =1/(B15/B16) -> 12.166667
A19: BNEF, LDV sales 2021 (M) | B19: 14
A20: BNEF, LDV fleet 2021 (M) | B20: 237
A21: average replacement time | B21: =1/(B19/B20) -> 16.928571
A23: Bus lifetime, all registered buses
A24: FHWA registered buses, 2015-2023 average (MV-1 via BTS NTS 1-11, Jul 2026) | B24: 965000
A25: School bus sales, 2015-2024 average (School Bus Fleet OEM survey, US) | B25: 36100
A26: Transit bus deliveries, 2015-2021 average (BTS NTS 1-12) | B26: 8500
A27: Implied replacement time from these two sales series alone (lower bound on sales, so an upper bound on life) | B27: =1/((B25+B26)/B24) -> 21.636771
A28: Transit buses (NTD, ~100k) average 7.2 years old, consistent with the BNEF 12-year figure above; school buses (~500k) average 9-10 years old, implying 16-18 years; coaches and shuttle/private buses (~450k) have no published sales
A29: Selected bus lifetime, years: the turnover of the observable segments (school ~480k + transit ~103k buses against ~45k sales/yr = 13 years). The FHWA fleet above carries ~450k further registered buses with no sales, travel or AEO counterpart (scope issue logged ), so modeled sales on that fleet exceed published sales by design | B29: 13

Sheet AVL
A1: Vehicle Lifetime (years) | B1: Passenger | C1: Freight
A2: LDVs | B2: 17 | C2: 15
A3: HDVs | B3: ='Freight and Buses'!B29 -> 13 | C3: =ROUND('Freight and Buses'!B13,0) -> 20
A4: aircraft | B4: =ROUND(Calculations!A16,0) -> 24 | C4: =B4 -> 24
A5: rail | B5: =Calculations!B86 -> 47 | C5: =ROUND(Calculations!C22,0) -> 34
A6: ships | B6: =Calculations!B73 -> 38 | C6: =ROUND(Calculations!C28,0) -> 33
A7: motorbikes | B7: =Calculations!B60 -> 22 | C7: =B7 -> 22
