Workbook

Sheet About
A1: BCoISC-WACCbI Weighted Average Cost of Capital by Industry
A2: BCoISC-FIRbI Financing Interest Rate by Industry
A3: BCoISC-RPfE Risk Premium for Equity [REFERENCE ONLY - not exported, not read by EPS.mdl]
A5: Source: | B5: Cost of Capital for Industry Sector Projects
B6: NYU
B7: 2026
B8: Cost of equity and capital (updateable)
B9: https://people.stern.nyu.edu/adamodar/New_Home_Page/datafile/wacc.html
B10: Aswath Damodaran
A12: Notes
A13: This variable expresses the financing cost of capital/debt by industry.
A14: For debt-based financing, it should be the interest rate on the debt.
A15: For equity-based financing, it should be the share of equity in the project given to the financier.
A16: Projects are often a mixture of debt-based and equity-based financing. For that reason, we use a
A17: weighted average cost of capital.
A19: Inflation Adjustment
A20: Since the EPS works in real (inflation-adjusted) currency units, and interest rates are set by
A21: banks and financial firms in nominal terms (factoring in their expectations of future inflation),
A22: we need to adjust published interest rates by subtracting out the share that represents
A23: inflation (i.e., the payment they demand just to keep up with inflation).
A25: We use the nominal WACC/CoD from NYU then adjust it by inflation.
... A49: financed share (cost of debt) from the unfinanced share (cost of equity).

Sheet NYU Data
A1: Date updated: | B1: 46027 | H1: YouTube Video explaining estimation choices and process. | I1: Notes
A2: Created by: | B2: Aswath Damodaran, adamodar@stern.nyu.edu | I2: Notes on how cost of capital is estimated for firms in US dollars and how to convert that into a cost of capital in a different currency
A3: What is this data? | B3: Cost of equity and capital (updateable) | F3: US companies
A4: Home Page: | B4: http://www.damodaran.com
A5: Data website: | B5: https://pages.stern.nyu.edu/~adamodar/New_Home_Page/data.html
A6: Companies in each industry: | B6: https://pages.stern.nyu.edu/~adamodar/pc/datasets/indname.xls
A7: Variable definitions: | B7: https://pages.stern.nyu.edu/~adamodar/New_Home_Page/datafile/variable.htm
A8: To update this spreadsheet, enter the following | G8: Cost of Debt Lookup Table (based on std dev in stock prices)
A9: Long Term Treasury bond rate = | D9: 0.0395 | G9: Standard Deviation | I9: Basis Spread
A10: Risk Premium to Use for Equity = | D10: 0.0446 | G10: 0 | H10: 0.3 | I10: 0.005506
A11: Global Default Spread to add to cost of debt = | D11: 0.0023 | G11: 0.30001 | H11: 0.45 | I11: 0.008872
A12: Do you want to use the marginal tax rate for cost of debt? | F12: Yes | G12: 0.45001 | H12: 0.65 | I12: 0.011113
A13: If yes, enter the marginal tax rate to use | F13: 0.25 | G13: 0.650001 | H13: 0.8 | I13: 0.018395
G14: 0.800001 | H14: 0.9 | I14: 0.032098
A15: These costs of capital are in US$. To convert to a different currency, please enter | G15: 0.900001 | H15: 1 | I15: 0.050899
A16: Expected inflation rate in local currency = | C16: 0.025 | G16: 1.000001 | H16: 10 | I16: 0.0885
A17: Expected inflation rate in US $ = | C17: 0.025
A19: Industry Name | B19: Number of Firms | C19: Beta | D19: Cost of Equity | E19: E/(D+E) | F19: Std Dev in Stock | G19: Cost of Debt | H19: Tax Rate | I19: After-tax Cost of Debt | J19: D/(D+E) | K19: Cost of Capital | L19: Cost of Capital (Local Currency)
A20: Advertising | B20: 52 | C20: 1.210507 | D20: 0.093488611 | E20: 0.71326642 | F20: 0.62914804 | G20: 0.052913 | H20: 0.050166602 | I20: 0.03968475 | J20: 0.28673358 | K20: 0.078061237 | L20: 0.078061237
A21: Aerospace/Defense | B21: 79 | C21: 0.94549148 | D21: 0.08166892 | E21: 0.86533188 | F21: 0.464523 | G21: 0.052913 | H21: 0.11575254 | I21: 0.03968475 | J21: 0.13466812 | K21: 0.076014991 | L21: 0.076014991
A22: Air Transport | B22: 23 | C22: 1.1854651 | D22: 0.092371743 | E22: 0.52309307 | F22: 0.59004326 | G22: 0.052913 | H22: 0.082925786 | I22: 0.03968475 | J22: 0.47690693 | K22: 0.067244951 | L22: 0.067244951
A23: Apparel | B23: 35 | C23: 0.93587446 | D23: 0.081240001 | E23: 0.76165944 | F23: 0.46263737 | G23: 0.052913 | H23: 0.096125003 | I23: 0.03968475 | J23: 0.23834056 | K23: 0.071335699 | L23: 0.071335699
A24: Auto & Truck | B24: 33 | C24: 1.4564933 | D24: 0.1044596 | E24: 0.83545064 | F24: 0.61834605 | G24: 0.052913 | H24: 0.03737151 | I24: 0.03968475 | J24: 0.16454936 | K24: 0.093800941 | L24: 0.093800941
A25: Auto Parts | B25: 35 | C25: 1.3394464 | D25: 0.099239308 | E25: 0.70689361 | F25: 0.4987204 | G25: 0.052913 | H25: 0.14999691 | I25: 0.03968475 | J25: 0.29310639 | K25: 0.081783486 | L25: 0.081783486
A26: Bank (Money Center) | B26: 15 | C26: 0.76104618 | D26: 0.07344266 | E26: 0.37851594 | F26: 0.22738718 | G26: 0.047306 | H26: 0.18434784 | I26: 0.0354795 | J26: 0.62148406 | K26: 0.049849161 | L26: 0.049849161
A27: Banks (Regional) | B27: 568 | C27: 0.39847656 | D27: 0.057272054 | E27: 0.65745229 | F27: 0.22682558 | G27: 0.047306 | H27: 0.17609708 | I27: 0.0354795 | J27: 0.34254771 | K27: 0.049807065 | L27: 0.049807065
A28: Beverage (Alcoholic) | B28: 14 | C28: 0.81247563 | D28: 0.075736413 | E28: 0.69764972 | F28: 0.55961937 | G28: 0.052913 | H28: 0.1234988 | I28: 0.03968475 | J28: 0.30235028 | K28: 0.064836183 | L28: 0.064836183
A29: Beverage (Soft) | B29: 27 | C29: 0.64146871 | D29: 0.068109504 | E29: 0.82927597 | F29: 0.57886898 | G29: 0.052913 | H29: 0.068462797 | I29: 0.03968475 | J29: 0.17072403 | K29: 0.063256716 | L29: 0.063256716
A30: Broadcasting | B30: 24 | C30: 0.47075205 | D30: 0.060495541 | E30: 0.53805591 | F30: 0.4662307 | G30: 0.052913 | H30: 0.077288595 | I30: 0.03968475 | J30: 0.46194409 | K30: 0.050882119 | L30: 0.050882119
A31: Brokerage & Investment Banking | B31: 32 | C31: 1.1714571 | D31: 0.091746985 | E31: 0.42449574 | F31: 0.3660856 | G31: 0.050672 | H31: 0.15273178 | I31: 0.038004 | J31: 0.57550426 | K31: 0.060817668 | L31: 0.060817668
... A115: Total Market (without financials) | B115: 4822 | C115: 0.99129597 | D115: 0.0837118 | E115: 0.85260238 | F115: 0.52764819 | G115: 0.052913 | H115: 0.071032604 | I115: 0.03968475 | J115: 0.14739762 | K115: 0.077222318 | L115: 0.077222318

Sheet EPS <> NYU Industry CoC Map
B2: EPS Industry Category | C2: NYU Industry 1 | D2: NYU Industry 2 | E2: NYU Industry 3 | G2: WACC 1 | H2: WACC 2 | I2: WACC 3 | K2: Average WACC
B3: agriculture and forestry 01T03 | C3: Farming/Agriculture | G3: =IFERROR(INDEX('Pretax WACC Build'!$K$11:$K$105,MATCH(C3,'Pretax WACC Build'!$A$11:$A$105,0)),"") -> 0.075239224 | H3: =IFERROR(INDEX('Pretax WACC Build'!$K$11:$K$105,MATCH(D3,'Pretax WACC Build'!$A$11:$A$105,0)),"") | I3: =IFERROR(INDEX('Pretax WACC Build'!$K$11:$K$105,MATCH(E3,'Pretax WACC Build'!$A$11:$A$105,0)),"") | K3: =AVERAGE(G3:I3) -> 0.075239224
B4: coal mining 05 | C4: Coal & Related Energy | G4: =IFERROR(INDEX('Pretax WACC Build'!$K$11:$K$105,MATCH(C4,'Pretax WACC Build'!$A$11:$A$105,0)),"") -> 0.092177654 | H4: =IFERROR(INDEX('Pretax WACC Build'!$K$11:$K$105,MATCH(D4,'Pretax WACC Build'!$A$11:$A$105,0)),"") | I4: =IFERROR(INDEX('Pretax WACC Build'!$K$11:$K$105,MATCH(E4,'Pretax WACC Build'!$A$11:$A$105,0)),"") | K4: =AVERAGE(G4:I4) -> 0.092177654
B5: oil and gas extraction 06 | C5: Oil/Gas (Production and Exploration) | G5: =IFERROR(INDEX('Pretax WACC Build'!$K$11:$K$105,MATCH(C5,'Pretax WACC Build'!$A$11:$A$105,0)),"") -> 0.073222739 | H5: =IFERROR(INDEX('Pretax WACC Build'!$K$11:$K$105,MATCH(D5,'Pretax WACC Build'!$A$11:$A$105,0)),"") | I5: =IFERROR(INDEX('Pretax WACC Build'!$K$11:$K$105,MATCH(E5,'Pretax WACC Build'!$A$11:$A$105,0)),"") | K5: =AVERAGE(G5:I5) -> 0.073222739
B6: other mining and quarrying 07T08 | C6: Metals & Mining | G6: =IFERROR(INDEX('Pretax WACC Build'!$K$11:$K$105,MATCH(C6,'Pretax WACC Build'!$A$11:$A$105,0)),"") -> 0.084926931 | H6: =IFERROR(INDEX('Pretax WACC Build'!$K$11:$K$105,MATCH(D6,'Pretax WACC Build'!$A$11:$A$105,0)),"") | I6: =IFERROR(INDEX('Pretax WACC Build'!$K$11:$K$105,MATCH(E6,'Pretax WACC Build'!$A$11:$A$105,0)),"") | K6: =AVERAGE(G6:I6) -> 0.084926931
B7: food beverage and tobacco 10T12 | C7: Food Processing | D7: Food Wholesalers | E7: Tobacco | G7: =IFERROR(INDEX('Pretax WACC Build'!$K$11:$K$105,MATCH(C7,'Pretax WACC Build'!$A$11:$A$105,0)),"") -> 0.063106774 | H7: =IFERROR(INDEX('Pretax WACC Build'!$K$11:$K$105,MATCH(D7,'Pretax WACC Build'!$A$11:$A$105,0)),"") -> 0.070994514 | I7: =IFERROR(INDEX('Pretax WACC Build'!$K$11:$K$105,MATCH(E7,'Pretax WACC Build'!$A$11:$A$105,0)),"") -> 0.088684446 | K7: =AVERAGE(G7:I7) -> 0.074261912
B8: textiles apparel and leather 13T15 | C8: Apparel | G8: =IFERROR(INDEX('Pretax WACC Build'!$K$11:$K$105,MATCH(C8,'Pretax WACC Build'!$A$11:$A$105,0)),"") -> 0.080453162 | H8: =IFERROR(INDEX('Pretax WACC Build'!$K$11:$K$105,MATCH(D8,'Pretax WACC Build'!$A$11:$A$105,0)),"") | I8: =IFERROR(INDEX('Pretax WACC Build'!$K$11:$K$105,MATCH(E8,'Pretax WACC Build'!$A$11:$A$105,0)),"") | K8: =AVERAGE(G8:I8) -> 0.080453162
B9: wood products 16 | C9: Paper/Forest Products | G9: =IFERROR(INDEX('Pretax WACC Build'!$K$11:$K$105,MATCH(C9,'Pretax WACC Build'!$A$11:$A$105,0)),"") -> 0.085100813 | H9: =IFERROR(INDEX('Pretax WACC Build'!$K$11:$K$105,MATCH(D9,'Pretax WACC Build'!$A$11:$A$105,0)),"") | I9: =IFERROR(INDEX('Pretax WACC Build'!$K$11:$K$105,MATCH(E9,'Pretax WACC Build'!$A$11:$A$105,0)),"") | K9: =AVERAGE(G9:I9) -> 0.085100813
B10: pulp paper and printing 17T18 | C10: Paper/Forest Products | D10: Publishing & Newspapers | G10: =IFERROR(INDEX('Pretax WACC Build'!$K$11:$K$105,MATCH(C10,'Pretax WACC Build'!$A$11:$A$105,0)),"") -> 0.085100813 | H10: =IFERROR(INDEX('Pretax WACC Build'!$K$11:$K$105,MATCH(D10,'Pretax WACC Build'!$A$11:$A$105,0)),"") -> 0.071133151 | I10: =IFERROR(INDEX('Pretax WACC Build'!$K$11:$K$105,MATCH(E10,'Pretax WACC Build'!$A$11:$A$105,0)),"") | K10: =AVERAGE(G10:I10) -> 0.078116982
B11: refined petroleum and coke 19 | C11: Oil/Gas (Integrated) | G11: =IFERROR(INDEX('Pretax WACC Build'!$K$11:$K$105,MATCH(C11,'Pretax WACC Build'!$A$11:$A$105,0)),"") -> 0.064260545 | H11: =IFERROR(INDEX('Pretax WACC Build'!$K$11:$K$105,MATCH(D11,'Pretax WACC Build'!$A$11:$A$105,0)),"") | I11: =IFERROR(INDEX('Pretax WACC Build'!$K$11:$K$105,MATCH(E11,'Pretax WACC Build'!$A$11:$A$105,0)),"") | K11: =AVERAGE(G11:I11) -> 0.064260545
B12: chemicals 20 | C12: Chemical (Basic) | D12: Chemical (Diversified) | E12: Chemical (Specialty) | G12: =IFERROR(INDEX('Pretax WACC Build'!$K$11:$K$105,MATCH(C12,'Pretax WACC Build'!$A$11:$A$105,0)),"") -> 0.071372034 | H12: =IFERROR(INDEX('Pretax WACC Build'!$K$11:$K$105,MATCH(D12,'Pretax WACC Build'!$A$11:$A$105,0)),"") -> 0.064356565 | I12: =IFERROR(INDEX('Pretax WACC Build'!$K$11:$K$105,MATCH(E12,'Pretax WACC Build'!$A$11:$A$105,0)),"") -> 0.078606774 | K12: =AVERAGE(G12:I12) -> 0.071445124
B13: rubber and plastic products 22 | C13: Rubber& Tires | G13: =IFERROR(INDEX('Pretax WACC Build'!$K$11:$K$105,MATCH(C13,'Pretax WACC Build'!$A$11:$A$105,0)),"") -> 0.056522925 | H13: =IFERROR(INDEX('Pretax WACC Build'!$K$11:$K$105,MATCH(D13,'Pretax WACC Build'!$A$11:$A$105,0)),"") | I13: =IFERROR(INDEX('Pretax WACC Build'!$K$11:$K$105,MATCH(E13,'Pretax WACC Build'!$A$11:$A$105,0)),"") | K13: =AVERAGE(G13:I13) -> 0.056522925
B14: glass and glass products 231 | C14: Building Materials | G14: =IFERROR(INDEX('Pretax WACC Build'!$K$11:$K$105,MATCH(C14,'Pretax WACC Build'!$A$11:$A$105,0)),"") -> 0.086640268 | H14: =IFERROR(INDEX('Pretax WACC Build'!$K$11:$K$105,MATCH(D14,'Pretax WACC Build'!$A$11:$A$105,0)),"") | I14: =IFERROR(INDEX('Pretax WACC Build'!$K$11:$K$105,MATCH(E14,'Pretax WACC Build'!$A$11:$A$105,0)),"") | K14: =AVERAGE(G14:I14) -> 0.086640268
B15: cement and other nonmetallic minerals 239 | C15: Building Materials | G15: =IFERROR(INDEX('Pretax WACC Build'!$K$11:$K$105,MATCH(C15,'Pretax WACC Build'!$A$11:$A$105,0)),"") -> 0.086640268 | H15: =IFERROR(INDEX('Pretax WACC Build'!$K$11:$K$105,MATCH(D15,'Pretax WACC Build'!$A$11:$A$105,0)),"") | I15: =IFERROR(INDEX('Pretax WACC Build'!$K$11:$K$105,MATCH(E15,'Pretax WACC Build'!$A$11:$A$105,0)),"") | K15: =AVERAGE(G15:I15) -> 0.086640268
B16: iron and steel 241 | C16: Steel | G16: =IFERROR(INDEX('Pretax WACC Build'!$K$11:$K$105,MATCH(C16,'Pretax WACC Build'!$A$11:$A$105,0)),"") -> 0.083075907 | H16: =IFERROR(INDEX('Pretax WACC Build'!$K$11:$K$105,MATCH(D16,'Pretax WACC Build'!$A$11:$A$105,0)),"") | I16: =IFERROR(INDEX('Pretax WACC Build'!$K$11:$K$105,MATCH(E16,'Pretax WACC Build'!$A$11:$A$105,0)),"") | K16: =AVERAGE(G16:I16) -> 0.083075907
B17: other metals 242 | C17: Metals & Mining | G17: =IFERROR(INDEX('Pretax WACC Build'!$K$11:$K$105,MATCH(C17,'Pretax WACC Build'!$A$11:$A$105,0)),"") -> 0.084926931 | H17: =IFERROR(INDEX('Pretax WACC Build'!$K$11:$K$105,MATCH(D17,'Pretax WACC Build'!$A$11:$A$105,0)),"") | I17: =IFERROR(INDEX('Pretax WACC Build'!$K$11:$K$105,MATCH(E17,'Pretax WACC Build'!$A$11:$A$105,0)),"") | K17: =AVERAGE(G17:I17) -> 0.084926931
B18: metal products except machinery and vehicles 25 | C18: Metals & Mining | G18: =IFERROR(INDEX('Pretax WACC Build'!$K$11:$K$105,MATCH(C18,'Pretax WACC Build'!$A$11:$A$105,0)),"") -> 0.084926931 | H18: =IFERROR(INDEX('Pretax WACC Build'!$K$11:$K$105,MATCH(D18,'Pretax WACC Build'!$A$11:$A$105,0)),"") | I18: =IFERROR(INDEX('Pretax WACC Build'!$K$11:$K$105,MATCH(E18,'Pretax WACC Build'!$A$11:$A$105,0)),"") | K18: =AVERAGE(G18:I18) -> 0.084926931
B19: computers and electronics 26 | C19: Electronics (Consumer & Office) | D19: Electronics (General) | G19: =IFERROR(INDEX('Pretax WACC Build'!$K$11:$K$105,MATCH(C19,'Pretax WACC Build'!$A$11:$A$105,0)),"") -> 0.089319311 | H19: =IFERROR(INDEX('Pretax WACC Build'!$K$11:$K$105,MATCH(D19,'Pretax WACC Build'!$A$11:$A$105,0)),"") -> 0.082662841 | I19: =IFERROR(INDEX('Pretax WACC Build'!$K$11:$K$105,MATCH(E19,'Pretax WACC Build'!$A$11:$A$105,0)),"") | K19: =AVERAGE(G19:I19) -> 0.085991076
B20: appliances and electrical equipment 27 | C20: Furn/Home Furnishings | D20: Electrical Equipment | G20: =IFERROR(INDEX('Pretax WACC Build'!$K$11:$K$105,MATCH(C20,'Pretax WACC Build'!$A$11:$A$105,0)),"") -> 0.075352251 | H20: =IFERROR(INDEX('Pretax WACC Build'!$K$11:$K$105,MATCH(D20,'Pretax WACC Build'!$A$11:$A$105,0)),"") -> 0.094993388 | I20: =IFERROR(INDEX('Pretax WACC Build'!$K$11:$K$105,MATCH(E20,'Pretax WACC Build'!$A$11:$A$105,0)),"") | K20: =AVERAGE(G20:I20) -> 0.085172819
B21: other machinery 28 | C21: Machinery | G21: =IFERROR(INDEX('Pretax WACC Build'!$K$11:$K$105,MATCH(C21,'Pretax WACC Build'!$A$11:$A$105,0)),"") -> 0.082843829 | H21: =IFERROR(INDEX('Pretax WACC Build'!$K$11:$K$105,MATCH(D21,'Pretax WACC Build'!$A$11:$A$105,0)),"") | I21: =IFERROR(INDEX('Pretax WACC Build'!$K$11:$K$105,MATCH(E21,'Pretax WACC Build'!$A$11:$A$105,0)),"") | K21: =AVERAGE(G21:I21) -> 0.082843829
B22: road vehicles 29 | C22: Transportation | D22: Trucking | G22: =IFERROR(INDEX('Pretax WACC Build'!$K$11:$K$105,MATCH(C22,'Pretax WACC Build'!$A$11:$A$105,0)),"") -> 0.076834298 | H22: =IFERROR(INDEX('Pretax WACC Build'!$K$11:$K$105,MATCH(D22,'Pretax WACC Build'!$A$11:$A$105,0)),"") -> 0.084574035 | I22: =IFERROR(INDEX('Pretax WACC Build'!$K$11:$K$105,MATCH(E22,'Pretax WACC Build'!$A$11:$A$105,0)),"") | K22: =AVERAGE(G22:I22) -> 0.080704166
B23: nonroad vehicles 30 | C23: Transportation (Railroads) | G23: =IFERROR(INDEX('Pretax WACC Build'!$K$11:$K$105,MATCH(C23,'Pretax WACC Build'!$A$11:$A$105,0)),"") -> 0.076901828 | H23: =IFERROR(INDEX('Pretax WACC Build'!$K$11:$K$105,MATCH(D23,'Pretax WACC Build'!$A$11:$A$105,0)),"") | I23: =IFERROR(INDEX('Pretax WACC Build'!$K$11:$K$105,MATCH(E23,'Pretax WACC Build'!$A$11:$A$105,0)),"") | K23: =AVERAGE(G23:I23) -> 0.076901828
B24: other manufacturing 31T33 | C24: Machinery | G24: =IFERROR(INDEX('Pretax WACC Build'!$K$11:$K$105,MATCH(C24,'Pretax WACC Build'!$A$11:$A$105,0)),"") -> 0.082843829 | H24: =IFERROR(INDEX('Pretax WACC Build'!$K$11:$K$105,MATCH(D24,'Pretax WACC Build'!$A$11:$A$105,0)),"") | I24: =IFERROR(INDEX('Pretax WACC Build'!$K$11:$K$105,MATCH(E24,'Pretax WACC Build'!$A$11:$A$105,0)),"") | K24: =AVERAGE(G24:I24) -> 0.082843829
B25: energy pipelines and gas processing 352T353 | C25: Oil/Gas Distribution | G25: =IFERROR(INDEX('Pretax WACC Build'!$K$11:$K$105,MATCH(C25,'Pretax WACC Build'!$A$11:$A$105,0)),"") -> 0.066173572 | H25: =IFERROR(INDEX('Pretax WACC Build'!$K$11:$K$105,MATCH(D25,'Pretax WACC Build'!$A$11:$A$105,0)),"") | I25: =IFERROR(INDEX('Pretax WACC Build'!$K$11:$K$105,MATCH(E25,'Pretax WACC Build'!$A$11:$A$105,0)),"") | K25: =AVERAGE(G25:I25) -> 0.066173572
B26: water and waste 36T39 | C26: Utility (Water) | G26: =IFERROR(INDEX('Pretax WACC Build'!$K$11:$K$105,MATCH(C26,'Pretax WACC Build'!$A$11:$A$105,0)),"") -> 0.062809596 | H26: =IFERROR(INDEX('Pretax WACC Build'!$K$11:$K$105,MATCH(D26,'Pretax WACC Build'!$A$11:$A$105,0)),"") | I26: =IFERROR(INDEX('Pretax WACC Build'!$K$11:$K$105,MATCH(E26,'Pretax WACC Build'!$A$11:$A$105,0)),"") | K26: =AVERAGE(G26:I26) -> 0.062809596
B27: construction 41T43 | C27: Engineering/Construction | G27: =IFERROR(INDEX('Pretax WACC Build'!$K$11:$K$105,MATCH(C27,'Pretax WACC Build'!$A$11:$A$105,0)),"") -> 0.083741949 | H27: =IFERROR(INDEX('Pretax WACC Build'!$K$11:$K$105,MATCH(D27,'Pretax WACC Build'!$A$11:$A$105,0)),"") | I27: =IFERROR(INDEX('Pretax WACC Build'!$K$11:$K$105,MATCH(E27,'Pretax WACC Build'!$A$11:$A$105,0)),"") | K27: =AVERAGE(G27:I27) -> 0.083741949

Sheet Pretax WACC Build
A1: Pretax WACC Build - multi-vintage beta average
A2: Purpose: EPS discounts PRETAX cash flows (no industry income tax in the fuel choice), so the decision-side WACC must be pretax. Damodaran published Cost of Capital (NYU Data col K) is AFTER-tax.
A3: Method: Cost of Equity = risk-free + mean(beta across 4 vintages) x ERP, using the CURRENT Jan-2026 risk-free rate and ERP (NYU Data D9 / D10).
A4: Pretax WACC = E/(D+E) x Cost of Equity + D/(D+E) x PRETAX Cost of Debt (NYU Data col G). Leverage is current-vintage.
A5: Why average betas: single-vintage regression betas are noisy and mean-revert. Four consecutive vintages show a systematic decline
A6: (e.g. Oil/Gas Integrated 0.978 -> 0.671 -> 0.484 -> 0.299) which produced implausible sector WACCs, including one BELOW its own cost of debt.
A7: A 4-vintage mean agrees closely with standard Blume/Bloomberg shrinkage (0.67*raw + 0.33*1.0) for every affected sector.
A8: Beta sources = col C of each vintage Industry Averages sheet, https://pages.stern.nyu.edu/~adamodar/pc/ :
A9: Jan2023 = archives/wacc22.xls | Jan2024 = archives/wacc23.xls | Jan2025 = archives/wacc24.xls | Jan2026 = datasets/wacc.xls (matches NYU Data tab)
A10: Industry Name | B10: Beta Jan2023 | C10: Beta Jan2024 | D10: Beta Jan2025 | E10: Beta Jan2026 | F10: Mean Beta | G10: E/(D+E) | H10: D/(D+E) | I10: Pretax Cost of Debt | J10: Cost of Equity | K10: Pretax WACC
A11: Advertising | B11: 1.631738 | C11: 1.372326 | D11: 1.337294 | E11: 1.210507 | F11: =IF(COUNT(B11:E11)=0,"",AVERAGE(B11:E11)) -> 1.3879662 | G11: =IFERROR(INDEX('NYU Data'!$E$20:$E$114,MATCH($A11,'NYU Data'!$A$20:$A$114,0)),"") -> 0.71326642 | H11: =IFERROR(INDEX('NYU Data'!$J$20:$J$114,MATCH($A11,'NYU Data'!$A$20:$A$114,0)),"") -> 0.28673358 | I11: =IFERROR(INDEX('NYU Data'!$G$20:$G$114,MATCH($A11,'NYU Data'!$A$20:$A$114,0)),"") -> 0.052913 | J11: =IF(F11="","",'NYU Data'!$D$9+F11*'NYU Data'!$D$10) -> 0.10140329 | K11: =IF(OR(F11="",G11=""),"",G11*J11+H11*I11) -> 0.087499499
A12: Aerospace/Defense | B12: 1.414182 | C12: 1.076405 | D12: 0.901553 | E12: 0.945491 | F12: =IF(COUNT(B12:E12)=0,"",AVERAGE(B12:E12)) -> 1.0844078 | G12: =IFERROR(INDEX('NYU Data'!$E$20:$E$114,MATCH($A12,'NYU Data'!$A$20:$A$114,0)),"") -> 0.86533188 | H12: =IFERROR(INDEX('NYU Data'!$J$20:$J$114,MATCH($A12,'NYU Data'!$A$20:$A$114,0)),"") -> 0.13466812 | I12: =IFERROR(INDEX('NYU Data'!$G$20:$G$114,MATCH($A12,'NYU Data'!$A$20:$A$114,0)),"") -> 0.052913 | J12: =IF(F12="","",'NYU Data'!$D$9+F12*'NYU Data'!$D$10) -> 0.087864586 | K12: =IF(OR(F12="",G12=""),"",G12*J12+H12*I12) -> 0.083157721
A13: Air Transport | B13: 1.415965 | C13: 1.26684 | D13: 1.236007 | E13: 1.185465 | F13: =IF(COUNT(B13:E13)=0,"",AVERAGE(B13:E13)) -> 1.2760692 | G13: =IFERROR(INDEX('NYU Data'!$E$20:$E$114,MATCH($A13,'NYU Data'!$A$20:$A$114,0)),"") -> 0.52309307 | H13: =IFERROR(INDEX('NYU Data'!$J$20:$J$114,MATCH($A13,'NYU Data'!$A$20:$A$114,0)),"") -> 0.47690693 | I13: =IFERROR(INDEX('NYU Data'!$G$20:$G$114,MATCH($A13,'NYU Data'!$A$20:$A$114,0)),"") -> 0.052913 | J13: =IF(F13="","",'NYU Data'!$D$9+F13*'NYU Data'!$D$10) -> 0.096412689 | K13: =IF(OR(F13="",G13=""),"",G13*J13+H13*I13) -> 0.075667386
A14: Apparel | B14: 1.324697 | C14: 1.1947 | D14: 0.990568 | E14: 0.935874 | F14: =IF(COUNT(B14:E14)=0,"",AVERAGE(B14:E14)) -> 1.1114598 | G14: =IFERROR(INDEX('NYU Data'!$E$20:$E$114,MATCH($A14,'NYU Data'!$A$20:$A$114,0)),"") -> 0.76165944 | H14: =IFERROR(INDEX('NYU Data'!$J$20:$J$114,MATCH($A14,'NYU Data'!$A$20:$A$114,0)),"") -> 0.23834056 | I14: =IFERROR(INDEX('NYU Data'!$G$20:$G$114,MATCH($A14,'NYU Data'!$A$20:$A$114,0)),"") -> 0.052913 | J14: =IF(F14="","",'NYU Data'!$D$9+F14*'NYU Data'!$D$10) -> 0.089071105 | K14: =IF(OR(F14="",G14=""),"",G14*J14+H14*I14) -> 0.080453162
A15: Auto & Truck | B15: 1.540598 | C15: 1.522378 | D15: 1.615413 | E15: 1.456493 | F15: =IF(COUNT(B15:E15)=0,"",AVERAGE(B15:E15)) -> 1.5337205 | G15: =IFERROR(INDEX('NYU Data'!$E$20:$E$114,MATCH($A15,'NYU Data'!$A$20:$A$114,0)),"") -> 0.83545064 | H15: =IFERROR(INDEX('NYU Data'!$J$20:$J$114,MATCH($A15,'NYU Data'!$A$20:$A$114,0)),"") -> 0.16454936 | I15: =IFERROR(INDEX('NYU Data'!$G$20:$G$114,MATCH($A15,'NYU Data'!$A$20:$A$114,0)),"") -> 0.052913 | J15: =IF(F15="","",'NYU Data'!$D$9+F15*'NYU Data'!$D$10) -> 0.10790393 | K15: =IF(OR(F15="",G15=""),"",G15*J15+H15*I15) -> 0.098855212
A16: Auto Parts | B16: 1.473992 | C16: 1.344427 | D16: 1.225124 | E16: 1.339446 | F16: =IF(COUNT(B16:E16)=0,"",AVERAGE(B16:E16)) -> 1.3457472 | G16: =IFERROR(INDEX('NYU Data'!$E$20:$E$114,MATCH($A16,'NYU Data'!$A$20:$A$114,0)),"") -> 0.70689361 | H16: =IFERROR(INDEX('NYU Data'!$J$20:$J$114,MATCH($A16,'NYU Data'!$A$20:$A$114,0)),"") -> 0.29310639 | I16: =IFERROR(INDEX('NYU Data'!$G$20:$G$114,MATCH($A16,'NYU Data'!$A$20:$A$114,0)),"") -> 0.052913 | J16: =IF(F16="","",'NYU Data'!$D$9+F16*'NYU Data'!$D$10) -> 0.099520327 | K16: =IF(OR(F16="",G16=""),"",G16*J16+H16*I16) -> 0.085859422
A17: Bank (Money Center) | B17: 1.080102 | C17: 1.061376 | D17: 0.875253 | E17: 0.761046 | F17: =IF(COUNT(B17:E17)=0,"",AVERAGE(B17:E17)) -> 0.94444425 | G17: =IFERROR(INDEX('NYU Data'!$E$20:$E$114,MATCH($A17,'NYU Data'!$A$20:$A$114,0)),"") -> 0.37851594 | H17: =IFERROR(INDEX('NYU Data'!$J$20:$J$114,MATCH($A17,'NYU Data'!$A$20:$A$114,0)),"") -> 0.62148406 | I17: =IFERROR(INDEX('NYU Data'!$G$20:$G$114,MATCH($A17,'NYU Data'!$A$20:$A$114,0)),"") -> 0.047306 | J17: =IF(F17="","",'NYU Data'!$D$9+F17*'NYU Data'!$D$10) -> 0.081622214 | K17: =IF(OR(F17="",G17=""),"",G17*J17+H17*I17) -> 0.060295234
A18: Banks (Regional) | B18: 0.504874 | C18: 0.461158 | D18: 0.519261 | E18: 0.398477 | F18: =IF(COUNT(B18:E18)=0,"",AVERAGE(B18:E18)) -> 0.4709425 | G18: =IFERROR(INDEX('NYU Data'!$E$20:$E$114,MATCH($A18,'NYU Data'!$A$20:$A$114,0)),"") -> 0.65745229 | H18: =IFERROR(INDEX('NYU Data'!$J$20:$J$114,MATCH($A18,'NYU Data'!$A$20:$A$114,0)),"") -> 0.34254771 | I18: =IFERROR(INDEX('NYU Data'!$G$20:$G$114,MATCH($A18,'NYU Data'!$A$20:$A$114,0)),"") -> 0.047306 | J18: =IF(F18="","",'NYU Data'!$D$9+F18*'NYU Data'!$D$10) -> 0.060504035 | K18: =IF(OR(F18="",G18=""),"",G18*J18+H18*I18) -> 0.055983079
A19: Beverage (Alcoholic) | B19: 1.012974 | C19: 1.131835 | D19: 0.610298 | E19: 0.812476 | F19: =IF(COUNT(B19:E19)=0,"",AVERAGE(B19:E19)) -> 0.89189575 | G19: =IFERROR(INDEX('NYU Data'!$E$20:$E$114,MATCH($A19,'NYU Data'!$A$20:$A$114,0)),"") -> 0.69764972 | H19: =IFERROR(INDEX('NYU Data'!$J$20:$J$114,MATCH($A19,'NYU Data'!$A$20:$A$114,0)),"") -> 0.30235028 | I19: =IFERROR(INDEX('NYU Data'!$G$20:$G$114,MATCH($A19,'NYU Data'!$A$20:$A$114,0)),"") -> 0.052913 | J19: =IF(F19="","",'NYU Data'!$D$9+F19*'NYU Data'!$D$10) -> 0.07927855 | K19: =IF(OR(F19="",G19=""),"",G19*J19+H19*I19) -> 0.071306919
A20: Beverage (Soft) | B20: 1.303443 | C20: 0.764146 | D20: 0.567766 | E20: 0.641469 | F20: =IF(COUNT(B20:E20)=0,"",AVERAGE(B20:E20)) -> 0.819206 | G20: =IFERROR(INDEX('NYU Data'!$E$20:$E$114,MATCH($A20,'NYU Data'!$A$20:$A$114,0)),"") -> 0.82927597 | H20: =IFERROR(INDEX('NYU Data'!$J$20:$J$114,MATCH($A20,'NYU Data'!$A$20:$A$114,0)),"") -> 0.17072403 | I20: =IFERROR(INDEX('NYU Data'!$G$20:$G$114,MATCH($A20,'NYU Data'!$A$20:$A$114,0)),"") -> 0.052913 | J20: =IF(F20="","",'NYU Data'!$D$9+F20*'NYU Data'!$D$10) -> 0.076036588 | K20: =IF(OR(F20="",G20=""),"",G20*J20+H20*I20) -> 0.072088836
A21: Broadcasting | B21: 1.322059 | C21: 1.060924 | D21: 0.917524 | E21: 0.470752 | F21: =IF(COUNT(B21:E21)=0,"",AVERAGE(B21:E21)) -> 0.94281475 | G21: =IFERROR(INDEX('NYU Data'!$E$20:$E$114,MATCH($A21,'NYU Data'!$A$20:$A$114,0)),"") -> 0.53805591 | H21: =IFERROR(INDEX('NYU Data'!$J$20:$J$114,MATCH($A21,'NYU Data'!$A$20:$A$114,0)),"") -> 0.46194409 | I21: =IFERROR(INDEX('NYU Data'!$G$20:$G$114,MATCH($A21,'NYU Data'!$A$20:$A$114,0)),"") -> 0.052913 | J21: =IF(F21="","",'NYU Data'!$D$9+F21*'NYU Data'!$D$10) -> 0.081549538 | K21: =IF(OR(F21="",G21=""),"",G21*J21+H21*I21) -> 0.068321059
A22: Brokerage & Investment Banking | B22: 1.204808 | C22: 1.120326 | D22: 0.952267 | E22: 1.171457 | F22: =IF(COUNT(B22:E22)=0,"",AVERAGE(B22:E22)) -> 1.1122145 | G22: =IFERROR(INDEX('NYU Data'!$E$20:$E$114,MATCH($A22,'NYU Data'!$A$20:$A$114,0)),"") -> 0.42449574 | H22: =IFERROR(INDEX('NYU Data'!$J$20:$J$114,MATCH($A22,'NYU Data'!$A$20:$A$114,0)),"") -> 0.57550426 | I22: =IFERROR(INDEX('NYU Data'!$G$20:$G$114,MATCH($A22,'NYU Data'!$A$20:$A$114,0)),"") -> 0.050672 | J22: =IF(F22="","",'NYU Data'!$D$9+F22*'NYU Data'!$D$10) -> 0.089104767 | K22: =IF(OR(F22="",G22=""),"",G22*J22+H22*I22) -> 0.066986546
... A84: Retail (Grocery and Food) | B84: 0.66757 | C84: 0.493608 | D84: 0.579407 | E84: 1.118304 | F84: =IF(COUNT(B84:E84)=0,"",AVERAGE(B84:E84)) -> 0.71472225 | G84: =IFERROR(INDEX('NYU Data'!$E$20:$E$114,MATCH($A84,'NYU Data'!$A$20:$A$114,0)),"") -> 0.65811047 | H84: =IFERROR(INDEX('NYU Data'!$J$20:$J$114,MATCH($A84,'NYU Data'!$A$20:$A$114,0)),"") -> 0.34188953 | I84: =IFERROR(INDEX('NYU Data'!$G$20:$G$114,MATCH($A84,'NYU Data'!$A$20:$A$114,0)),"") -> 0.052913 | J84: =IF(F84="","",'NYU Data'!$D$9+F84*'NYU Data'!$D$10) -> 0.071376612 | K84: =IF(OR(F84="",G84=""),"",G84*J84+H84*I84) -> 0.065064097
A85: Retail (REITs) | C85: 1.120868 | D85: 0.947589 | E85: 0.620739 | F85: =IF(COUNT(B85:E85)=0,"",AVERAGE(B85:E85)) -> 0.89639867 | G85: =IFERROR(INDEX('NYU Data'!$E$20:$E$114,MATCH($A85,'NYU Data'!$A$20:$A$114,0)),"") -> 0.63930519 | H85: =IFERROR(INDEX('NYU Data'!$J$20:$J$114,MATCH($A85,'NYU Data'!$A$20:$A$114,0)),"") -> 0.36069481 | I85: =IFERROR(INDEX('NYU Data'!$G$20:$G$114,MATCH($A85,'NYU Data'!$A$20:$A$114,0)),"") -> 0.047306 | J85: =IF(F85="","",'NYU Data'!$D$9+F85*'NYU Data'!$D$10) -> 0.079479381 | K85: =IF(OR(F85="",G85=""),"",G85*J85+H85*I85) -> 0.067874609
A86: Retail (Special Lines) | B86: 1.475207 | C86: 1.181406 | D86: 1.223963 | E86: 1.0894 | F86: =IF(COUNT(B86:E86)=0,"",AVERAGE(B86:E86)) -> 1.242494 | G86: =IFERROR(INDEX('NYU Data'!$E$20:$E$114,MATCH($A86,'NYU Data'!$A$20:$A$114,0)),"") -> 0.83499652 | H86: =IFERROR(INDEX('NYU Data'!$J$20:$J$114,MATCH($A86,'NYU Data'!$A$20:$A$114,0)),"") -> 0.16500348 | I86: =IFERROR(INDEX('NYU Data'!$G$20:$G$114,MATCH($A86,'NYU Data'!$A$20:$A$114,0)),"") -> 0.052913 | J86: =IF(F86="","",'NYU Data'!$D$9+F86*'NYU Data'!$D$10) -> 0.094915232 | K86: =IF(OR(F86="",G86=""),"",G86*J86+H86*I86) -> 0.087984718
A87: Rubber& Tires | B87: 0.838015 | C87: 0.67452 | D87: 0.645345 | E87: 0.52943 | F87: =IF(COUNT(B87:E87)=0,"",AVERAGE(B87:E87)) -> 0.6718275 | G87: =IFERROR(INDEX('NYU Data'!$E$20:$E$114,MATCH($A87,'NYU Data'!$A$20:$A$114,0)),"") -> 0.21811566 | H87: =IFERROR(INDEX('NYU Data'!$J$20:$J$114,MATCH($A87,'NYU Data'!$A$20:$A$114,0)),"") -> 0.78188434 | I87: =IFERROR(INDEX('NYU Data'!$G$20:$G$114,MATCH($A87,'NYU Data'!$A$20:$A$114,0)),"") -> 0.052913 | J87: =IF(F87="","",'NYU Data'!$D$9+F87*'NYU Data'!$D$10) -> 0.069463506 | K87: =IF(OR(F87="",G87=""),"",G87*J87+H87*I87) -> 0.056522925
A88: Semiconductor | B88: 1.607746 | C88: 1.495241 | D88: 1.485872 | E88: 1.518199 | F88: =IF(COUNT(B88:E88)=0,"",AVERAGE(B88:E88)) -> 1.5267645 | G88: =IFERROR(INDEX('NYU Data'!$E$20:$E$114,MATCH($A88,'NYU Data'!$A$20:$A$114,0)),"") -> 0.97474338 | H88: =IFERROR(INDEX('NYU Data'!$J$20:$J$114,MATCH($A88,'NYU Data'!$A$20:$A$114,0)),"") -> 0.025256622 | I88: =IFERROR(INDEX('NYU Data'!$G$20:$G$114,MATCH($A88,'NYU Data'!$A$20:$A$114,0)),"") -> 0.052913 | J88: =IF(F88="","",'NYU Data'!$D$9+F88*'NYU Data'!$D$10) -> 0.1075937 | K88: =IF(OR(F88="",G88=""),"",G88*J88+H88*I88) -> 0.10621265
A89: Semiconductor Equip | B89: 1.757143 | C89: 1.527982 | D89: 1.484976 | E89: 1.397223 | F89: =IF(COUNT(B89:E89)=0,"",AVERAGE(B89:E89)) -> 1.541831 | G89: =IFERROR(INDEX('NYU Data'!$E$20:$E$114,MATCH($A89,'NYU Data'!$A$20:$A$114,0)),"") -> 0.95364098 | H89: =IFERROR(INDEX('NYU Data'!$J$20:$J$114,MATCH($A89,'NYU Data'!$A$20:$A$114,0)),"") -> 0.046359019 | I89: =IFERROR(INDEX('NYU Data'!$G$20:$G$114,MATCH($A89,'NYU Data'!$A$20:$A$114,0)),"") -> 0.052913 | J89: =IF(F89="","",'NYU Data'!$D$9+F89*'NYU Data'!$D$10) -> 0.10826566 | K89: =IF(OR(F89="",G89=""),"",G89*J89+H89*I89) -> 0.10569957
A90: Shipbuilding & Marine | B90: 0.943739 | C90: 0.810836 | D90: 0.57845 | E90: 0.752933 | F90: =IF(COUNT(B90:E90)=0,"",AVERAGE(B90:E90)) -> 0.7714895 | G90: =IFERROR(INDEX('NYU Data'!$E$20:$E$114,MATCH($A90,'NYU Data'!$A$20:$A$114,0)),"") -> 0.81599216 | H90: =IFERROR(INDEX('NYU Data'!$J$20:$J$114,MATCH($A90,'NYU Data'!$A$20:$A$114,0)),"") -> 0.18400784 | I90: =IFERROR(INDEX('NYU Data'!$G$20:$G$114,MATCH($A90,'NYU Data'!$A$20:$A$114,0)),"") -> 0.052913 | J90: =IF(F90="","",'NYU Data'!$D$9+F90*'NYU Data'!$D$10) -> 0.073908432 | K90: =IF(OR(F90="",G90=""),"",G90*J90+H90*I90) -> 0.070045108
A91: Shoe | B91: 1.327693 | C91: 1.291579 | D91: 1.424208 | E91: 1.017318 | F91: =IF(COUNT(B91:E91)=0,"",AVERAGE(B91:E91)) -> 1.2651995 | G91: =IFERROR(INDEX('NYU Data'!$E$20:$E$114,MATCH($A91,'NYU Data'!$A$20:$A$114,0)),"") -> 0.89329798 | H91: =IFERROR(INDEX('NYU Data'!$J$20:$J$114,MATCH($A91,'NYU Data'!$A$20:$A$114,0)),"") -> 0.10670202 | I91: =IFERROR(INDEX('NYU Data'!$G$20:$G$114,MATCH($A91,'NYU Data'!$A$20:$A$114,0)),"") -> 0.052913 | J91: =IF(F91="","",'NYU Data'!$D$9+F91*'NYU Data'!$D$10) -> 0.095927898 | K91: =IF(OR(F91="",G91=""),"",G91*J91+H91*I91) -> 0.091338121
A92: Software (Entertainment) | B92: 1.363576 | C92: 1.108331 | D92: 1.182782 | E92: 1.028311 | F92: =IF(COUNT(B92:E92)=0,"",AVERAGE(B92:E92)) -> 1.17075 | G92: =IFERROR(INDEX('NYU Data'!$E$20:$E$114,MATCH($A92,'NYU Data'!$A$20:$A$114,0)),"") -> 0.97996357 | H92: =IFERROR(INDEX('NYU Data'!$J$20:$J$114,MATCH($A92,'NYU Data'!$A$20:$A$114,0)),"") -> 0.020036431 | I92: =IFERROR(INDEX('NYU Data'!$G$20:$G$114,MATCH($A92,'NYU Data'!$A$20:$A$114,0)),"") -> 0.052913 | J92: =IF(F92="","",'NYU Data'!$D$9+F92*'NYU Data'!$D$10) -> 0.09171545 | K92: =IF(OR(F92="",G92=""),"",G92*J92+H92*I92) -> 0.090937987
A93: Software (Internet) | B93: 1.551306 | C93: 1.616084 | D93: 1.687026 | E93: 1.688676 | F93: =IF(COUNT(B93:E93)=0,"",AVERAGE(B93:E93)) -> 1.635773 | G93: =IFERROR(INDEX('NYU Data'!$E$20:$E$114,MATCH($A93,'NYU Data'!$A$20:$A$114,0)),"") -> 0.89048058 | H93: =IFERROR(INDEX('NYU Data'!$J$20:$J$114,MATCH($A93,'NYU Data'!$A$20:$A$114,0)),"") -> 0.10951942 | I93: =IFERROR(INDEX('NYU Data'!$G$20:$G$114,MATCH($A93,'NYU Data'!$A$20:$A$114,0)),"") -> 0.052913 | J93: =IF(F93="","",'NYU Data'!$D$9+F93*'NYU Data'!$D$10) -> 0.11245548 | K93: =IF(OR(F93="",G93=""),"",G93*J93+H93*I93) -> 0.10593442
A94: Software (System & Application) | B94: 1.469771 | C94: 1.293965 | D94: 1.241761 | E94: 1.276648 | F94: =IF(COUNT(B94:E94)=0,"",AVERAGE(B94:E94)) -> 1.3205362 | G94: =IFERROR(INDEX('NYU Data'!$E$20:$E$114,MATCH($A94,'NYU Data'!$A$20:$A$114,0)),"") -> 0.94717481 | H94: =IFERROR(INDEX('NYU Data'!$J$20:$J$114,MATCH($A94,'NYU Data'!$A$20:$A$114,0)),"") -> 0.052825189 | I94: =IFERROR(INDEX('NYU Data'!$G$20:$G$114,MATCH($A94,'NYU Data'!$A$20:$A$114,0)),"") -> 0.052913 | J94: =IF(F94="","",'NYU Data'!$D$9+F94*'NYU Data'!$D$10) -> 0.098395917 | K94: =IF(OR(F94="",G94=""),"",G94*J94+H94*I94) -> 0.095993273
A95: Steel | B95: 1.342484 | C95: 1.126372 | D95: 1.059779 | E95: 1.062846 | F95: =IF(COUNT(B95:E95)=0,"",AVERAGE(B95:E95)) -> 1.1478702 | G95: =IFERROR(INDEX('NYU Data'!$E$20:$E$114,MATCH($A95,'NYU Data'!$A$20:$A$114,0)),"") -> 0.80963186 | H95: =IFERROR(INDEX('NYU Data'!$J$20:$J$114,MATCH($A95,'NYU Data'!$A$20:$A$114,0)),"") -> 0.19036814 | I95: =IFERROR(INDEX('NYU Data'!$G$20:$G$114,MATCH($A95,'NYU Data'!$A$20:$A$114,0)),"") -> 0.050672 | J95: =IF(F95="","",'NYU Data'!$D$9+F95*'NYU Data'!$D$10) -> 0.090695013 | K95: =IF(OR(F95="",G95=""),"",G95*J95+H95*I95) -> 0.083075907
A96: Telecom (Wireless) | B96: 1.030974 | C96: 1.087361 | D96: 0.772539 | E96: 0.538135 | F96: =IF(COUNT(B96:E96)=0,"",AVERAGE(B96:E96)) -> 0.85725225 | G96: =IFERROR(INDEX('NYU Data'!$E$20:$E$114,MATCH($A96,'NYU Data'!$A$20:$A$114,0)),"") -> 0.65812552 | H96: =IFERROR(INDEX('NYU Data'!$J$20:$J$114,MATCH($A96,'NYU Data'!$A$20:$A$114,0)),"") -> 0.34187448 | I96: =IFERROR(INDEX('NYU Data'!$G$20:$G$114,MATCH($A96,'NYU Data'!$A$20:$A$114,0)),"") -> 0.050672 | J96: =IF(F96="","",'NYU Data'!$D$9+F96*'NYU Data'!$D$10) -> 0.07773345 | K96: =IF(OR(F96="",G96=""),"",G96*J96+H96*I96) -> 0.068481831
A97: Telecom. Equipment | B97: 1.233119 | C97: 1.080507 | D97: 0.999615 | E97: 0.92322 | F97: =IF(COUNT(B97:E97)=0,"",AVERAGE(B97:E97)) -> 1.0591153 | G97: =IFERROR(INDEX('NYU Data'!$E$20:$E$114,MATCH($A97,'NYU Data'!$A$20:$A$114,0)),"") -> 0.91556019 | H97: =IFERROR(INDEX('NYU Data'!$J$20:$J$114,MATCH($A97,'NYU Data'!$A$20:$A$114,0)),"") -> 0.084439813 | I97: =IFERROR(INDEX('NYU Data'!$G$20:$G$114,MATCH($A97,'NYU Data'!$A$20:$A$114,0)),"") -> 0.052913 | J97: =IF(F97="","",'NYU Data'!$D$9+F97*'NYU Data'!$D$10) -> 0.08673654 | K97: =IF(OR(F97="",G97=""),"",G97*J97+H97*I97) -> 0.083880487
... A105: Total Market | B105: 1.15727 | C105: 1.000223 | D105: 1.00278 | E105: 0.912111 | F105: =IF(COUNT(B105:E105)=0,"",AVERAGE(B105:E105)) -> 1.018096 | G105: =IFERROR(INDEX('NYU Data'!$E$20:$E$114,MATCH($A105,'NYU Data'!$A$20:$A$114,0)),"") -> 0.7398023 | H105: =IFERROR(INDEX('NYU Data'!$J$20:$J$114,MATCH($A105,'NYU Data'!$A$20:$A$114,0)),"") -> 0.2601977 | I105: =IFERROR(INDEX('NYU Data'!$G$20:$G$114,MATCH($A105,'NYU Data'!$A$20:$A$114,0)),"") -> 0.052913 | J105: =IF(F105="","",'NYU Data'!$D$9+F105*'NYU Data'!$D$10) -> 0.084907082 | K105: =IF(OR(F105="",G105=""),"",G105*J105+H105*I105) -> 0.076582295

Sheet EPS <> NYU Industry CoD Map
B2: EPS Industry Category | C2: NYU Industry 1 | D2: NYU Industry 2 | E2: NYU Industry 3 | G2: WACC 1 | H2: WACC 2 | I2: WACC 3 | K2: Average WACC
B3: agriculture and forestry 01T03 | C3: Farming/Agriculture | G3: =IFERROR(INDEX('NYU Data'!$G$20:$G$114,MATCH(C3,'NYU Data'!$A$20:$A$114,0)),"") -> 0.052913 | H3: =IFERROR(INDEX('NYU Data'!$G$20:$G$114,MATCH(D3,'NYU Data'!$A$20:$A$114,0)),"") | I3: =IFERROR(INDEX('NYU Data'!$G$20:$G$114,MATCH(E3,'NYU Data'!$A$20:$A$114,0)),"") | K3: =AVERAGE(G3:I3) -> 0.052913
B4: coal mining 05 | C4: Coal & Related Energy | G4: =IFERROR(INDEX('NYU Data'!$G$20:$G$114,MATCH(C4,'NYU Data'!$A$20:$A$114,0)),"") -> 0.052913 | H4: =IFERROR(INDEX('NYU Data'!$G$20:$G$114,MATCH(D4,'NYU Data'!$A$20:$A$114,0)),"") | I4: =IFERROR(INDEX('NYU Data'!$G$20:$G$114,MATCH(E4,'NYU Data'!$A$20:$A$114,0)),"") | K4: =AVERAGE(G4:I4) -> 0.052913
B5: oil and gas extraction 06 | C5: Oil/Gas (Production and Exploration) | G5: =IFERROR(INDEX('NYU Data'!$G$20:$G$114,MATCH(C5,'NYU Data'!$A$20:$A$114,0)),"") -> 0.050672 | H5: =IFERROR(INDEX('NYU Data'!$G$20:$G$114,MATCH(D5,'NYU Data'!$A$20:$A$114,0)),"") | I5: =IFERROR(INDEX('NYU Data'!$G$20:$G$114,MATCH(E5,'NYU Data'!$A$20:$A$114,0)),"") | K5: =AVERAGE(G5:I5) -> 0.050672
B6: other mining and quarrying 07T08 | C6: Metals & Mining | G6: =IFERROR(INDEX('NYU Data'!$G$20:$G$114,MATCH(C6,'NYU Data'!$A$20:$A$114,0)),"") -> 0.060195 | H6: =IFERROR(INDEX('NYU Data'!$G$20:$G$114,MATCH(D6,'NYU Data'!$A$20:$A$114,0)),"") | I6: =IFERROR(INDEX('NYU Data'!$G$20:$G$114,MATCH(E6,'NYU Data'!$A$20:$A$114,0)),"") | K6: =AVERAGE(G6:I6) -> 0.060195
B7: food beverage and tobacco 10T12 | C7: Food Processing | D7: Food Wholesalers | E7: Tobacco | G7: =IFERROR(INDEX('NYU Data'!$G$20:$G$114,MATCH(C7,'NYU Data'!$A$20:$A$114,0)),"") -> 0.050672 | H7: =IFERROR(INDEX('NYU Data'!$G$20:$G$114,MATCH(D7,'NYU Data'!$A$20:$A$114,0)),"") -> 0.050672 | I7: =IFERROR(INDEX('NYU Data'!$G$20:$G$114,MATCH(E7,'NYU Data'!$A$20:$A$114,0)),"") -> 0.060195 | K7: =AVERAGE(G7:I7) -> 0.053846333
B8: textiles apparel and leather 13T15 | C8: Apparel | G8: =IFERROR(INDEX('NYU Data'!$G$20:$G$114,MATCH(C8,'NYU Data'!$A$20:$A$114,0)),"") -> 0.052913 | H8: =IFERROR(INDEX('NYU Data'!$G$20:$G$114,MATCH(D8,'NYU Data'!$A$20:$A$114,0)),"") | I8: =IFERROR(INDEX('NYU Data'!$G$20:$G$114,MATCH(E8,'NYU Data'!$A$20:$A$114,0)),"") | K8: =AVERAGE(G8:I8) -> 0.052913
B9: wood products 16 | C9: Paper/Forest Products | G9: =IFERROR(INDEX('NYU Data'!$G$20:$G$114,MATCH(C9,'NYU Data'!$A$20:$A$114,0)),"") -> 0.052913 | H9: =IFERROR(INDEX('NYU Data'!$G$20:$G$114,MATCH(D9,'NYU Data'!$A$20:$A$114,0)),"") | I9: =IFERROR(INDEX('NYU Data'!$G$20:$G$114,MATCH(E9,'NYU Data'!$A$20:$A$114,0)),"") | K9: =AVERAGE(G9:I9) -> 0.052913
B10: pulp paper and printing 17T18 | C10: Paper/Forest Products | D10: Publishing & Newspapers | G10: =IFERROR(INDEX('NYU Data'!$G$20:$G$114,MATCH(C10,'NYU Data'!$A$20:$A$114,0)),"") -> 0.052913 | H10: =IFERROR(INDEX('NYU Data'!$G$20:$G$114,MATCH(D10,'NYU Data'!$A$20:$A$114,0)),"") -> 0.050672 | I10: =IFERROR(INDEX('NYU Data'!$G$20:$G$114,MATCH(E10,'NYU Data'!$A$20:$A$114,0)),"") | K10: =AVERAGE(G10:I10) -> 0.0517925
B11: refined petroleum and coke 19 | C11: Oil/Gas (Integrated) | G11: =IFERROR(INDEX('NYU Data'!$G$20:$G$114,MATCH(C11,'NYU Data'!$A$20:$A$114,0)),"") -> 0.047306 | H11: =IFERROR(INDEX('NYU Data'!$G$20:$G$114,MATCH(D11,'NYU Data'!$A$20:$A$114,0)),"") | I11: =IFERROR(INDEX('NYU Data'!$G$20:$G$114,MATCH(E11,'NYU Data'!$A$20:$A$114,0)),"") | K11: =AVERAGE(G11:I11) -> 0.047306
B12: chemicals 20 | C12: Chemical (Basic) | D12: Chemical (Diversified) | E12: Chemical (Specialty) | G12: =IFERROR(INDEX('NYU Data'!$G$20:$G$114,MATCH(C12,'NYU Data'!$A$20:$A$114,0)),"") -> 0.052913 | H12: =IFERROR(INDEX('NYU Data'!$G$20:$G$114,MATCH(D12,'NYU Data'!$A$20:$A$114,0)),"") -> 0.050672 | I12: =IFERROR(INDEX('NYU Data'!$G$20:$G$114,MATCH(E12,'NYU Data'!$A$20:$A$114,0)),"") -> 0.050672 | K12: =AVERAGE(G12:I12) -> 0.051419
B13: rubber and plastic products 22 | C13: Rubber& Tires | G13: =IFERROR(INDEX('NYU Data'!$G$20:$G$114,MATCH(C13,'NYU Data'!$A$20:$A$114,0)),"") -> 0.052913 | H13: =IFERROR(INDEX('NYU Data'!$G$20:$G$114,MATCH(D13,'NYU Data'!$A$20:$A$114,0)),"") | I13: =IFERROR(INDEX('NYU Data'!$G$20:$G$114,MATCH(E13,'NYU Data'!$A$20:$A$114,0)),"") | K13: =AVERAGE(G13:I13) -> 0.052913
B14: glass and glass products 231 | C14: Building Materials | G14: =IFERROR(INDEX('NYU Data'!$G$20:$G$114,MATCH(C14,'NYU Data'!$A$20:$A$114,0)),"") -> 0.050672 | H14: =IFERROR(INDEX('NYU Data'!$G$20:$G$114,MATCH(D14,'NYU Data'!$A$20:$A$114,0)),"") | I14: =IFERROR(INDEX('NYU Data'!$G$20:$G$114,MATCH(E14,'NYU Data'!$A$20:$A$114,0)),"") | K14: =AVERAGE(G14:I14) -> 0.050672
B15: cement and other nonmetallic minerals 239 | C15: Building Materials | G15: =IFERROR(INDEX('NYU Data'!$G$20:$G$114,MATCH(C15,'NYU Data'!$A$20:$A$114,0)),"") -> 0.050672 | H15: =IFERROR(INDEX('NYU Data'!$G$20:$G$114,MATCH(D15,'NYU Data'!$A$20:$A$114,0)),"") | I15: =IFERROR(INDEX('NYU Data'!$G$20:$G$114,MATCH(E15,'NYU Data'!$A$20:$A$114,0)),"") | K15: =AVERAGE(G15:I15) -> 0.050672
B16: iron and steel 241 | C16: Steel | G16: =IFERROR(INDEX('NYU Data'!$G$20:$G$114,MATCH(C16,'NYU Data'!$A$20:$A$114,0)),"") -> 0.050672 | H16: =IFERROR(INDEX('NYU Data'!$G$20:$G$114,MATCH(D16,'NYU Data'!$A$20:$A$114,0)),"") | I16: =IFERROR(INDEX('NYU Data'!$G$20:$G$114,MATCH(E16,'NYU Data'!$A$20:$A$114,0)),"") | K16: =AVERAGE(G16:I16) -> 0.050672
B17: other metals 242 | C17: Metals & Mining | G17: =IFERROR(INDEX('NYU Data'!$G$20:$G$114,MATCH(C17,'NYU Data'!$A$20:$A$114,0)),"") -> 0.060195 | H17: =IFERROR(INDEX('NYU Data'!$G$20:$G$114,MATCH(D17,'NYU Data'!$A$20:$A$114,0)),"") | I17: =IFERROR(INDEX('NYU Data'!$G$20:$G$114,MATCH(E17,'NYU Data'!$A$20:$A$114,0)),"") | K17: =AVERAGE(G17:I17) -> 0.060195
B18: metal products except machinery and vehicles 25 | C18: Metals & Mining | G18: =IFERROR(INDEX('NYU Data'!$G$20:$G$114,MATCH(C18,'NYU Data'!$A$20:$A$114,0)),"") -> 0.060195 | H18: =IFERROR(INDEX('NYU Data'!$G$20:$G$114,MATCH(D18,'NYU Data'!$A$20:$A$114,0)),"") | I18: =IFERROR(INDEX('NYU Data'!$G$20:$G$114,MATCH(E18,'NYU Data'!$A$20:$A$114,0)),"") | K18: =AVERAGE(G18:I18) -> 0.060195
B19: computers and electronics 26 | C19: Electronics (Consumer & Office) | D19: Electronics (General) | G19: =IFERROR(INDEX('NYU Data'!$G$20:$G$114,MATCH(C19,'NYU Data'!$A$20:$A$114,0)),"") -> 0.060195 | H19: =IFERROR(INDEX('NYU Data'!$G$20:$G$114,MATCH(D19,'NYU Data'!$A$20:$A$114,0)),"") -> 0.052913 | I19: =IFERROR(INDEX('NYU Data'!$G$20:$G$114,MATCH(E19,'NYU Data'!$A$20:$A$114,0)),"") | K19: =AVERAGE(G19:I19) -> 0.056554
B20: appliances and electrical equipment 27 | C20: Furn/Home Furnishings | D20: Electrical Equipment | G20: =IFERROR(INDEX('NYU Data'!$G$20:$G$114,MATCH(C20,'NYU Data'!$A$20:$A$114,0)),"") -> 0.052913 | H20: =IFERROR(INDEX('NYU Data'!$G$20:$G$114,MATCH(D20,'NYU Data'!$A$20:$A$114,0)),"") -> 0.060195 | I20: =IFERROR(INDEX('NYU Data'!$G$20:$G$114,MATCH(E20,'NYU Data'!$A$20:$A$114,0)),"") | K20: =AVERAGE(G20:I20) -> 0.056554
B21: other machinery 28 | C21: Machinery | G21: =IFERROR(INDEX('NYU Data'!$G$20:$G$114,MATCH(C21,'NYU Data'!$A$20:$A$114,0)),"") -> 0.052913 | H21: =IFERROR(INDEX('NYU Data'!$G$20:$G$114,MATCH(D21,'NYU Data'!$A$20:$A$114,0)),"") | I21: =IFERROR(INDEX('NYU Data'!$G$20:$G$114,MATCH(E21,'NYU Data'!$A$20:$A$114,0)),"") | K21: =AVERAGE(G21:I21) -> 0.052913
B22: road vehicles 29 | C22: Transportation | D22: Trucking | G22: =IFERROR(INDEX('NYU Data'!$G$20:$G$114,MATCH(C22,'NYU Data'!$A$20:$A$114,0)),"") -> 0.050672 | H22: =IFERROR(INDEX('NYU Data'!$G$20:$G$114,MATCH(D22,'NYU Data'!$A$20:$A$114,0)),"") -> 0.050672 | I22: =IFERROR(INDEX('NYU Data'!$G$20:$G$114,MATCH(E22,'NYU Data'!$A$20:$A$114,0)),"") | K22: =AVERAGE(G22:I22) -> 0.050672
B23: nonroad vehicles 30 | C23: Transportation (Railroads) | G23: =IFERROR(INDEX('NYU Data'!$G$20:$G$114,MATCH(C23,'NYU Data'!$A$20:$A$114,0)),"") -> 0.047306 | H23: =IFERROR(INDEX('NYU Data'!$G$20:$G$114,MATCH(D23,'NYU Data'!$A$20:$A$114,0)),"") | I23: =IFERROR(INDEX('NYU Data'!$G$20:$G$114,MATCH(E23,'NYU Data'!$A$20:$A$114,0)),"") | K23: =AVERAGE(G23:I23) -> 0.047306
B24: other manufacturing 31T33 | C24: Machinery | G24: =IFERROR(INDEX('NYU Data'!$G$20:$G$114,MATCH(C24,'NYU Data'!$A$20:$A$114,0)),"") -> 0.052913 | H24: =IFERROR(INDEX('NYU Data'!$G$20:$G$114,MATCH(D24,'NYU Data'!$A$20:$A$114,0)),"") | I24: =IFERROR(INDEX('NYU Data'!$G$20:$G$114,MATCH(E24,'NYU Data'!$A$20:$A$114,0)),"") | K24: =AVERAGE(G24:I24) -> 0.052913
B25: energy pipelines and gas processing 352T353 | C25: Oil/Gas Distribution | G25: =IFERROR(INDEX('NYU Data'!$G$20:$G$114,MATCH(C25,'NYU Data'!$A$20:$A$114,0)),"") -> 0.050672 | H25: =IFERROR(INDEX('NYU Data'!$G$20:$G$114,MATCH(D25,'NYU Data'!$A$20:$A$114,0)),"") | I25: =IFERROR(INDEX('NYU Data'!$G$20:$G$114,MATCH(E25,'NYU Data'!$A$20:$A$114,0)),"") | K25: =AVERAGE(G25:I25) -> 0.050672
B26: water and waste 36T39 | C26: Utility (Water) | G26: =IFERROR(INDEX('NYU Data'!$G$20:$G$114,MATCH(C26,'NYU Data'!$A$20:$A$114,0)),"") -> 0.047306 | H26: =IFERROR(INDEX('NYU Data'!$G$20:$G$114,MATCH(D26,'NYU Data'!$A$20:$A$114,0)),"") | I26: =IFERROR(INDEX('NYU Data'!$G$20:$G$114,MATCH(E26,'NYU Data'!$A$20:$A$114,0)),"") | K26: =AVERAGE(G26:I26) -> 0.047306
B27: construction 41T43 | C27: Engineering/Construction | G27: =IFERROR(INDEX('NYU Data'!$G$20:$G$114,MATCH(C27,'NYU Data'!$A$20:$A$114,0)),"") -> 0.052913 | H27: =IFERROR(INDEX('NYU Data'!$G$20:$G$114,MATCH(D27,'NYU Data'!$A$20:$A$114,0)),"") | I27: =IFERROR(INDEX('NYU Data'!$G$20:$G$114,MATCH(E27,'NYU Data'!$A$20:$A$114,0)),"") | K27: =AVERAGE(G27:I27) -> 0.052913

Sheet BCoISC-WACCbI
A1: Unit: dimensionless (% of project cost) | B1: Weighted Average Cost of Capital
A2: agriculture and forestry 01T03 | B2: =(1+'EPS <> NYU Industry CoC Map'!K3)/(1+'NYU Data'!C$17)-1 -> 0.049013877
A3: coal mining 05 | B3: =(1+'EPS <> NYU Industry CoC Map'!K4)/(1+'NYU Data'!C$17)-1 -> 0.065539174
A4: oil and gas extraction 06 | B4: =(1+'EPS <> NYU Industry CoC Map'!K5)/(1+'NYU Data'!C$17)-1 -> 0.047046574
A5: other mining and quarrying 07T08 | B5: =(1+'EPS <> NYU Industry CoC Map'!K6)/(1+'NYU Data'!C$17)-1 -> 0.058465298
A6: food beverage and tobacco 10T12 | B6: =(1+'EPS <> NYU Industry CoC Map'!K7)/(1+'NYU Data'!C$17)-1 -> 0.048060402
A7: textiles apparel and leather 13T15 | B7: =(1+'EPS <> NYU Industry CoC Map'!K8)/(1+'NYU Data'!C$17)-1 -> 0.054100646
A8: wood products 16 | B8: =(1+'EPS <> NYU Industry CoC Map'!K9)/(1+'NYU Data'!C$17)-1 -> 0.058634939
A9: pulp paper and printing 17T18 | B9: =(1+'EPS <> NYU Industry CoC Map'!K10)/(1+'NYU Data'!C$17)-1 -> 0.051821446
A10: refined petroleum and coke 19 | B10: =(1+'EPS <> NYU Industry CoC Map'!K11)/(1+'NYU Data'!C$17)-1 -> 0.038302971
A11: chemicals 20 | B11: =(1+'EPS <> NYU Industry CoC Map'!K12)/(1+'NYU Data'!C$17)-1 -> 0.045312316
A12: rubber and plastic products 22 | B12: =(1+'EPS <> NYU Industry CoC Map'!K13)/(1+'NYU Data'!C$17)-1 -> 0.030754073
A13: glass and glass products 231 | B13: =(1+'EPS <> NYU Industry CoC Map'!K14)/(1+'NYU Data'!C$17)-1 -> 0.060136847
... A26: construction 41T43 | B26: =(1+'EPS <> NYU Industry CoC Map'!K27)/(1+'NYU Data'!C$17)-1 -> 0.057309218

Sheet BCoISC-FIRbI
A1: Unit: dimensionless (% of project cost) | B1: Weighted Average Cost of Debt
A2: agriculture and forestry 01T03 | B2: =(1+'EPS <> NYU Industry CoD Map'!K3)/(1+'NYU Data'!C$17)-1 -> 0.027232195
A3: coal mining 05 | B3: =(1+'EPS <> NYU Industry CoD Map'!K4)/(1+'NYU Data'!C$17)-1 -> 0.027232195
A4: oil and gas extraction 06 | B4: =(1+'EPS <> NYU Industry CoD Map'!K5)/(1+'NYU Data'!C$17)-1 -> 0.025045854
A5: other mining and quarrying 07T08 | B5: =(1+'EPS <> NYU Industry CoD Map'!K6)/(1+'NYU Data'!C$17)-1 -> 0.034336585
A6: food beverage and tobacco 10T12 | B6: =(1+'EPS <> NYU Industry CoD Map'!K7)/(1+'NYU Data'!C$17)-1 -> 0.028142764
A7: textiles apparel and leather 13T15 | B7: =(1+'EPS <> NYU Industry CoD Map'!K8)/(1+'NYU Data'!C$17)-1 -> 0.027232195
A8: wood products 16 | B8: =(1+'EPS <> NYU Industry CoD Map'!K9)/(1+'NYU Data'!C$17)-1 -> 0.027232195
A9: pulp paper and printing 17T18 | B9: =(1+'EPS <> NYU Industry CoD Map'!K10)/(1+'NYU Data'!C$17)-1 -> 0.026139024
A10: refined petroleum and coke 19 | B10: =(1+'EPS <> NYU Industry CoD Map'!K11)/(1+'NYU Data'!C$17)-1 -> 0.021761951
A11: chemicals 20 | B11: =(1+'EPS <> NYU Industry CoD Map'!K12)/(1+'NYU Data'!C$17)-1 -> 0.025774634
A12: rubber and plastic products 22 | B12: =(1+'EPS <> NYU Industry CoD Map'!K13)/(1+'NYU Data'!C$17)-1 -> 0.027232195
A13: glass and glass products 231 | B13: =(1+'EPS <> NYU Industry CoD Map'!K14)/(1+'NYU Data'!C$17)-1 -> 0.025045854
... A26: construction 41T43 | B26: =(1+'EPS <> NYU Industry CoD Map'!K27)/(1+'NYU Data'!C$17)-1 -> 0.027232195

Sheet RPfE (not exported)
A1: Unit: dimensionless (% of project cost) | B1: Risk Premium for Equity
A2: industry-wide | B2: ='NYU Data'!D10 -> 0.0446
