Workbook
Name a: #REF!
Name AsphaltStore: [1]Control!$D$50
Name base.year: #REF!
Name BaseYear: 2018
Name BTV11_15: #REF!
Name BVT17_15: #REF!
Name CAAGR_tolerance: 200
Name CH4_to_CO2e: '[2]Cross-Page Data'!$C$12
Name CH4GWP: #REF!
Name CO2_T4_APS: #REF!
Name CO2_T4_NZE: #REF!
Name CO2_T4_STEPS: #REF!
Name CO2_T5_APS: #REF!
Name CO2_T5_CPS: #REF!
Name CO2_T5_NZE: #REF!
Name CO2_T5_STEPS: #REF!
Name coal.past: #REF!
Name COAL_PRODUCTION: #REF!
Name Coal_trade: #REF!
Name coaldemand: #REF!
Name CokeCoalStore: [1]Control!$D$63
Name Constants.Density.Diesel: #REF!
Name Constants.Density.Ethanol: #REF!
Name Constants.Density.JetFuel: #REF!
Name Constants.Density.MotorSpirit: #REF!
Name ConsumeBlock1: '[1]Default State Energy Data Table'!$A$6:$AM$67
Name Conversion.to.average.power: #REF!
Name Conversion.water.L: #REF!
Name Conversion.water.units: #REF!
Name Conversions.Area.m2: #REF!
Name Conversions.Area.Units: #REF!
Name Conversions.Energy.Joules: #REF!
Name Conversions.Energy.Units: #REF!
Name Conversions.Money.GBP: #REF!
Name Conversions.Money.Units: #REF!
Name Conversions.Power.Units: #REF!
Name Conversions.Power.Watts: #REF!
Name Cost.Capital.Scenario: #REF!
Name Cost.Finance.Scenario: #REF!
Name Cost.Fuel.Scenario: #REF!
Name Cost.Infrastructure.Scenario: #REF!
Name cpi_2010to2012: #REF!
Name cpi_2013to2012: #REF!
Name cpi_2014to2012: #REF!
Name cpi_2016to2012: #REF!
Name CreateRegions: #REF!
Name csp.capacity: #REF!
Name CSVfilepath: #REF!
Name D: #REF!
Name dd: #REF!
Name ddd: #REF!
Name ddddd: #REF!
Name dddddd: #REF!
Name deflator_year: "$2018"
Name DeflatorYear: "$2018"
Name discount_factors: #REF!
Name DistillStore: [1]Control!$D$51
Name DW_EDO_022WV: #REF!
Name DW_EDO_023WV: #REF!
Name DW_EDO_024WV: #REF!

Sheet About
A1: BIEEI BAU Industrial Equipment Efficiency Improvement
A4: Sources: | B4: Annual Energy Outlook
B5: Energy Information Administration
B6: 2025
B7: Assumptions to the Annual Energy Outlook 2025: Industrial Demand Module
B8: https://www.eia.gov/outlooks/aeo/assumptions/
B9: Table 3
A11: Notes:
A12: This variable should contain the BAU annual efficiency improvement of industrial equipment
A13: subscripted by industrial process.
A15: Methodology update:
A16: All efficiency-improvement rates are sourced from AEO 2025 IDM Assumptions Table 3 (base year 2022), via the MECS tab.
A17: Table 3 inputs were refreshed from the prior 2018-base vintage to the current 2022-base release.
A18: New-equipment REI is interpolated to 2021 (TREND), and the 2021-2050 improvement is annualized at a constant rate.
A19: The 'DEA rates' tab (Danish Energy Agency technology data) is retained for reference but is not linked to the BIEEI outputs.
A21: Combustion heat-band update (Worklog T3.1–T3.3):
A22: The five combustion heat bands in BIEEI-other (rows 2–6) are no longer a uniform MECS rate. They now carry year-specific
A23: BAU improvement rates from the 'Combustion BAU Trajectory' tab, driven by growing burner-integral waste-heat-recovery (WHR) penetration.
A24: Penetration pen(t) starts at the completed start-year installed mix (0% / 0% / 5% / 17.4% / 58.7% by band) and trends linearly to a
... A40: Kermeli 2050 implementation rates are BAT-mitigation-scenario values, not BAU; only a 30% gap-closure share (blue input, 'Combustion BAU Trajectory'!G13) is assumed autonomous in the U.S. BAU, preserving the remaining potential for the price-responsive cost-curve file.
A41: Additional source: | B41: Energy efficiency potentials in the EU industry: impacts of deep decarbonization technologies
B42: Kermeli, K., Edelenbosch, O.Y., Crijns-Graus, W., van Ruijven, B.J., van Vuuren, D.P., Worrell, E.
B44: Energy Efficiency 15, 55 (2022)
B45: https://link.springer.com/article/10.1007/s12053-022-10071-8
B46: Supplementary material: energy savings & cost of measures by industry (2015 diffusion, 2030/2050 implementation)
A48: Band 2050 adoption targets use full-coverage industry weighting: every industry's band-heat share ('indst heat consumption') × its mapped burner-adoption level ('Combustion BAU Trajectory' rows 56–80). Targets = start-year penetration + mapping-implied 2015→2050 delta, computed on a consistent basis so industries with no additional adoption contribute zero change.
A49: Refining, chemicals, and all unmapped industries are held at the Kermeli 'Other' level (10% diffusion, no additional adoption): fired-heater WHR in these sectors is achieved via convection sections and central air preheat — system WHR (ε=0.4 scope), whose savings are priced in the separate cost-curve file. Refs: DOE, Waste Heat Recovery: Technology and Opportunities in U.S. Industry (BCS Inc., 2008); ACEEE Summer Study 2007 (<5% of U.S. manufacturing facilities use waste-heat recovery).
A50: Data caveat: Kermeli et al. (2022) assume identical 2015 diffusion rates across all countries due to lack of data, and no U.S.-specific burner-penetration statistics were found in DOE/ORNL/ACEEE literature. Band heat composition, not adoption statistics, is what drives the band targets here.
A51: Bands <200 °C: burner-integral regen/recup technology not applicable, so these bands carry no WHR-driven improvement; their BAU improvement comes solely from the residual equipment-native rate (see below).
A52: KEY ASSUMPTION — RESIDUAL EQUIPMENT-NATIVE IMPROVEMENT: all five heat bands carry an additional 0.2%/yr efficiency drift ('Combustion BAU Trajectory'!G14, blue/yellow input) on top of the burner-WHR sweep, compounded and capped at the tech-matched ceiling. It represents non-WHR, non-price-driven improvement only: combustion control/O2 trim becoming standard practice, refractory & insulation upgrades at rebuild, furnace pressure control, and vintage design improvement at stock turnover. Basis: EIA NEMS Industrial Demand Module 'technology possibility curves' (trend-based improvement of new + existing equipment; https://www.eia.gov/outlooks/aeo/nems/overview/industrial.html); prior all-mechanism MECS/AEO rate was 0.535%/yr. It EXCLUDES all WHR and all price-responsive measures — those savings live in the system-WHR scope and the separate cost-curve file respectively, so none are double-counted here.

Sheet MECS
D2: UEC 2022 (trillion British thermal | E2: REI 2050 | F2: 2022 | G2: 2050 | K2: improvement
B3: End use | C3: Fuel | D3: units per billion 2012$ of shipments) | E3: existing | F3: new REI | G3: new REI | I3: 2021 | J3: 2050 | K3: over model run | M3: annual improvement
B4: Heat | C4: Natural gas | D4: 0.243 | E4: 0.862 | F4: 0.965 | G4: 0.83 | I4: {=TREND(F4:G4,$F$2:$G$2,$I$3)} -> 0.96982143 | J4: =G4 -> 0.83 | K4: =1-J4/I4 -> 0.14417234 | M4: =1-(1-K4)^(1/($J$3-$I$3)) -> 0.0053541071
B5: Heat | C5: Electricity | D5: 0.023 | E5: 0.929 | F5: 0.983 | G5: 0.938 | I5: {=TREND(F5:G5,$F$2:$G$2,$I$3)} -> 0.98460714 | J5: =G5 -> 0.938 | K5: =1-J5/I5 -> 0.047335776 | M5: =1-(1-K5)^(1/($J$3-$I$3)) -> 0.0016707673
B6: Heat | C6: Steam | D6: 0.375 | E6: 0.862 | F6: 0.965 | G6: 0.829 | I6: {=TREND(F6:G6,$F$2:$G$2,$I$3)} -> 0.96985714 | J6: =G6 -> 0.829 | K6: =1-J6/I6 -> 0.14523494 | M6: =1-(1-K6)^(1/($J$3-$I$3)) -> 0.0053967172
B7: Refrigeration | C7: Electricity | D7: 0.043 | E7: 0.923 | F7: 0.966 | G7: 0.9 | I7: {=TREND(F7:G7,$F$2:$G$2,$I$3)} -> 0.96835714 | J7: =G7 -> 0.9 | K7: =1-J7/I7 -> 0.070590839 | M7: =1-(1-K7)^(1/($J$3-$I$3)) -> 0.0025211684
B8: Machine drive | C8: Natural gas | D8: 0.029 | E8: 0.882 | F8: 0.97 | G8: 0.829 | I8: {=TREND(F8:G8,$F$2:$G$2,$I$3)} -> 0.97503571 | J8: =G8 -> 0.829 | K8: =1-J8/I8 -> 0.14977473 | M8: =1-(1-K8)^(1/($J$3-$I$3)) -> 0.005579341
B9: Machine drive | C9: Electricity | D9: 0.225 | E9: 0.929 | F9: 0.983 | G9: 0.909 | I9: {=TREND(F9:G9,$F$2:$G$2,$I$3)} -> 0.98564286 | J9: =G9 -> 0.909 | K9: =1-J9/I9 -> 0.077759258 | M9: =1-(1-K9)^(1/($J$3-$I$3)) -> 0.002787452
B10: Electrochemical | C10: Electricity | D10: 0.009 | E10: 0.919 | F10: 0.947 | G10: 0.642 | I10: {=TREND(F10:G10,$F$2:$G$2,$I$3)} -> 0.95789286 | J10: =G10 -> 0.642 | K10: =1-J10/I10 -> 0.3297789 | M10: =1-(1-K10)^(1/($J$3-$I$3)) -> 0.013703435
B11: processes Other | C11: Natural gas | D11: 0.019 | E11: 0.893 | F11: 0.969 | G11: 0.845 | I11: {=TREND(F11:G11,$F$2:$G$2,$I$3)} -> 0.97342857 | J11: =G11 -> 0.845 | K11: =1-J11/I11 -> 0.13193425 | M11: =1-(1-K11)^(1/($J$3-$I$3)) -> 0.004867008
B12: Other | C12: Electricity | D12: 0.009 | E12: 0.922 | F12: 0.983 | G12: 0.903 | I12: {=TREND(F12:G12,$F$2:$G$2,$I$3)} -> 0.98585714 | J12: =G12 -> 0.903 | K12: =1-J12/I12 -> 0.08404579 | M12: =1-(1-K12)^(1/($J$3-$I$3)) -> 0.0030226263

Sheet lighting
B5: 2024 | C5: 0.853075 | D5: =1/C5 -> 1.1722299 | E5: start year lighting efficiency from SYIEUEFbIPaF
B6: 2050 | C6: 0.9 | D6: =1/C6 -> 1.1111111 | E6: assumed efficiency 2050 (all LEDs)
D8: =1-D6/D5 -> 0.052138889
F9: =D8/25 -> 0.0020855556
D14: =1-(1-D8)^(1/($B$6-$B$5)) -> 0.002057392

Sheet Other data ->
A1: https://ens.dk/en/analyses-and-statistics/technology-data-industrial-process-heat
A2: Technology Data for Industrial Process Heat

Sheet 1.1 Traditional heat pump
A1: Technology | C1: Heat pump, up to 60 °C, Temp lift = 40 K
A2: year | C2: 2025 | D2: 2030 | E2: 2035 | F2: 2040 | G2: 2050 | H2: 2025 | I2: 2025 | J2: 2050 | K2: 2050 | L2: Note | M2: Ref
A3: est | C3: ctrl | D3: ctrl | E3: ctrl | F3: ctrl | G3: ctrl | H3: lower | I3: upper | J3: lower | K3: upper | L3: - | M3: -
A4: cat | B4: par
A5: Energy/technical data
B6: Heat generation capacity for one unit [MW] | C6: 3 | D6: 3 | E6: 3 | F6: 3 | G6: 3 | H6: 0.5 | I6: 5 | J6: 0.5 | K6: 5 | L6: A | M6: [1, 2]
B7: Total efficiency, net [%], nominel load | C7: 5.33 | D7: =C7*1.03 -> 5.4899 | E7: 5.55 | F7: =D7*1.02 -> 5.599698 | G7: =F7*1.01 -> 5.655695 | H7: =C7 -> 5.33 | I7: =C7*1.05 -> 5.5965 | J7: =G7*0.97 -> 5.4860241 | K7: =G7*1.02 -> 5.7688089 | L7: B | M7: [1, 3]
B8: Total efficiency, net [%], annual average | C8: =C7-5% -> 5.28 | D8: =D7-5% -> 5.4399 | E8: =E7-5% -> 5.5 | F8: =F7-5% -> 5.549698 | G8: =G7-5% -> 5.605695 | H8: =H7-5% -> 5.28 | I8: =I7-5% -> 5.5465 | J8: =J7-5% -> 5.4360241 | K8: =K7-5% -> 5.7188089 | L8: B,C
B9: Auxiliary electricity consumption [% of heat gen] | C9: 0.01 | D9: 0.01 | E9: 0.01 | F9: 0.01 | G9: 0.01 | H9: 0.01 | I9: 0.04 | J9: 0.01 | K9: 0.04 | M9: 2
B10: Forced outage [%] | C10: 0 | D10: 0 | E10: 0 | F10: 0 | G10: 0 | H10: 0 | I10: 0.01 | J10: 0 | K10: 0.01 | L10: D | M10: 2
B11: Planned outage [weeks per year] | C11: 1 | D11: 1 | E11: 1 | F11: 1 | G11: 1 | H11: 0.5 | I11: 2 | J11: 0.5 | K11: 2 | M11: 2
B12: Technical lifetime [years] | C12: 25 | D12: 25 | E12: 25 | F12: 25 | G12: 25 | H12: 15 | I12: 40 | J12: 15 | K12: 40 | M12: 2
B13: Construction time [years] | C13: 0.5 | D13: 0.5 | E13: 0.5 | F13: 0.5 | G13: 0.5 | H13: 0.3 | I13: 1 | J13: 0.3 | K13: 1 | M13: 2
A14: Regulation Ability
B15: Minimum load [% of full load] | C15: 0.25 | D15: 0.25 | E15: 0.25 | F15: 0.25 | G15: 0.25 | H15: 0.1 | I15: 0.5 | J15: 0.1 | K15: 0.5 | M15: 2
B16: Warm start-up time [hours] | C16: 0.1 | D16: 0.1 | E16: 0.1 | F16: 0.1 | G16: 0.1 | H16: 0.1 | I16: 0.2 | J16: 0.1 | K16: 0.2 | M16: 2
B17: Cold start-up time [hours] | C17: 1 | D17: 1 | E17: 1 | F17: 1 | G17: 1 | H17: 0.2 | I17: 1 | J17: 0.2 | K17: 1 | M17: 2
A18: Financial data
B19: Nominal investment [M€/MW] | C19: 0.95 | D19: 0.94 | E19: 0.91 | F19: 0.91 | G19: 0.89 | H19: 0.91 | I19: 0.95 | J19: 0.88 | K19: 0.95 | M19: 2
B20: - of which equipment [%] | C20: 0.4 | D20: 0.4 | E20: 0.4 | F20: 0.4 | G20: 0.4 | L20: E | M20: 2
B21: - of which installation and other costs [%] | C21: 0.6 | D21: 0.6 | E21: 0.6 | F21: 0.6 | G21: 0.6 | L21: F | M21: 2
B22: Fixed O&M [€/MJ/s/year] | C22: 2127 | D22: 2095 | E22: 2032 | F22: 2032 | G22: 2001 | H22: 2032 | I22: 2127 | J22: 1970 | K22: 2127 | M22: 2
B23: Variable O&M [€/MWh] | C23: 3.07 | D23: 3.02 | E23: 2.93 | F23: 2.93 | G23: 2.89 | H23: 2.93 | I23: 3.07 | J23: 2.84 | K23: 3.07 | M23: 2
A24: Technology-specific data
B25: Indirect investments cost [M€/MW] | C25: =C19*0.2 -> 0.19 | D25: =D19*0.2 -> 0.188 | E25: =E19*0.2 -> 0.182 | F25: =F19*0.2 -> 0.182 | G25: =G19*0.2 -> 0.178 | L25: H
B26: Non energy gains [M€/MW] | C26: - | D26: - | E26: - | F26: - | G26: -
B27: Startup cost [€/MW/startup] | C27: 10 | D27: 10 | E27: 10 | F27: 10 | G27: 10
B28: Temperature heat source supply [°C] | C28: 30 | D28: 30 | E28: 30 | F28: 30 | G28: 30 | L28: I
B29: Temperature heat source return [°C] | C29: 20 | D29: 20 | E29: 20 | F29: 20 | G29: 20 | L29: I
B30: - Total efficiency, net [%], nominel load. Based on a temperature lift of 50 K, 70°C max | C30: 4.52 | D30: 4.6 | E30: 4.65 | F30: 4.7 | G30: 4.74 | H30: 4.47 | I30: 4.69 | J30: 4.6 | K30: 4.84 | L30: G
B31: - Total efficiency, net [%], nominel load. Based on a temperature lift of 60 K, 80°C max | C31: 3.95 | D31: 4 | E31: 4.04 | F31: 4.08 | G31: 4.12 | H31: 3.88 | I31: 4.07 | J31: 3.99 | K31: 4.2 | L31: G
B32: Cooling generation capacity for one unit [MW] | C32: - | D32: - | E32: - | F32: - | G32: -
A35: Notes:
A36: A | B36: 0,5-5 MW
A37: B | B37: Estimated based on cases presented in [3]
A38: C | B38: Based on lost produktion during startup/shutdown
A39: D | B39: May vary depending on heat source availability
A40: E | B40: Very individual, can vary ÷ 20 %
A41: F | B41: Very individual, can vary + 20 %
A42: G | B42: Based on the old technology catalogue on process heat from 2020.
A43: H | B43: Going from current implementation to potential
A44: I | B44: Uses waste heat
A46: References:
A47: 1 | B47: Viegand Maagøe, 2019.
A48: 2 | B48: Danish Enegy Agency, Technology Data - Energy Plants for Electricity and District heating generation, 2025
A49: 3 | B49: EHPA, Large Scale heat pumps in Europe, 2019

Sheet 1.2 heat_cool hp 80 C 75 K 
A1: Technology | C1: Combined heating and cooling heat pump, up to 80 °C, Temp lift = 75 K
A2: year | C2: 2025 | D2: 2030 | E2: 2035 | F2: 2040 | G2: 2050 | H2: 2025 | I2: 2025 | J2: 2050 | K2: 2050 | L2: Note | M2: Ref
A3: est | C3: ctrl | D3: ctrl | E3: ctrl | F3: ctrl | G3: ctrl | H3: lower | I3: upper | J3: lower | K3: upper | L3: - | M3: -
A4: cat | B4: par
A5: Energy/technical data
B6: Heat generation capacity for one unit [MW] | C6: 3 | D6: 3 | E6: 3 | F6: 3 | G6: 3 | H6: 0.5 | I6: 5 | J6: 0.5 | K6: 5 | L6: A | M6: [1, 2]
B7: Total efficiency, net [%], nominel load | C7: 3.35 | D7: 3.43 | E7: 3.48 | F7: =D7*1.02 -> 3.4986 | G7: =F7*1.01 -> 3.533586 | H7: 3.33 | I7: =C7*1.05 -> 3.5175 | J7: =G7*0.97 -> 3.4275784 | K7: =G7*1.02 -> 3.6042577 | L7: B | M7: [1, 3]
B8: Total efficiency, net [%], annual average | C8: =C7-5% -> 3.3 | D8: =D7-5% -> 3.38 | E8: =E7-5% -> 3.43 | F8: =F7-5% -> 3.4486 | G8: =G7-5% -> 3.483586 | H8: =H7-5% -> 3.28 | I8: =I7-5% -> 3.4675 | J8: =J7-5% -> 3.3775784 | K8: =K7-5% -> 3.5542577 | L8: B,C
B9: Auxiliary electricity consumption [% of heat gen] | C9: 0.01 | D9: 0.01 | E9: 0.01 | F9: 0.01 | G9: 0.01 | H9: 0.01 | I9: 0.04 | J9: 0.01 | K9: 0.04 | M9: 2
B10: Forced outage [%] | C10: 0 | D10: 0 | E10: 0 | F10: 0 | G10: 0 | H10: 0 | I10: 0.01 | J10: 0 | K10: 0.01 | L10: D | M10: 2
B11: Planned outage [weeks per year] | C11: 1 | D11: 1 | E11: 1 | F11: 1 | G11: 1 | H11: 0.5 | I11: 2 | J11: 0.5 | K11: 2 | M11: 2
B12: Technical lifetime [years] | C12: 25 | D12: 25 | E12: 25 | F12: 25 | G12: 25 | H12: 15 | I12: 40 | J12: 15 | K12: 40 | M12: 2
B13: Construction time [years] | C13: 0.5 | D13: 0.5 | E13: 0.5 | F13: 0.5 | G13: 0.5 | H13: 0.3 | I13: 1 | J13: 0.3 | K13: 1 | M13: 2
A14: Regulation Ability
B15: Minimum load [% of full load] | C15: 0.25 | D15: 0.25 | E15: 0.25 | F15: 0.25 | G15: 0.25 | H15: 0.1 | I15: 0.5 | J15: 0.1 | K15: 0.5 | M15: 2
B16: Warm start-up time [hours] | C16: 0.1 | D16: 0.1 | E16: 0.1 | F16: 0.1 | G16: 0.1 | H16: 0.1 | I16: 0.2 | J16: 0.1 | K16: 0.2 | M16: 2
B17: Cold start-up time [hours] | C17: 1 | D17: 1 | E17: 1 | F17: 1 | G17: 1 | H17: 0.2 | I17: 1 | J17: 0.2 | K17: 1 | M17: 2
A18: Financial data
B19: Nominal investment [M€/MW] | C19: 0.95 | D19: 0.94 | E19: 0.91 | F19: 0.91 | G19: 0.89 | H19: 0.91 | I19: 0.95 | J19: 0.88 | K19: 0.95 | M19: 2
B20: - of which equipment [%] | C20: 0.4 | D20: 0.4 | E20: 0.4 | F20: 0.4 | G20: 0.4 | L20: E | M20: 2
B21: - of which installation and other costs [%] | C21: 0.6 | D21: 0.6 | E21: 0.6 | F21: 0.6 | G21: 0.6 | L21: F | M21: 2
B22: Fixed O&M [€/MJ/s/year] | C22: 2127 | D22: 2095 | E22: 2032 | F22: 2032 | G22: 2001 | H22: 2032 | I22: 2127 | J22: 1970 | K22: 2127 | M22: 2
B23: Variable O&M [€/MWh] | C23: 3.07 | D23: 3.02 | E23: 2.93 | F23: 2.93 | G23: 2.89 | H23: 2.93 | I23: 3.07 | J23: 2.84 | K23: 3.07 | M23: 2
A24: Technology-specific data
B25: Indirect investments cost [M€/MW] | C25: =C19*0.2 -> 0.19 | D25: =D19*0.2 -> 0.188 | E25: =E19*0.2 -> 0.182 | F25: =F19*0.2 -> 0.182 | G25: =G19*0.2 -> 0.178 | L25: H
B26: Non energy gains [M€/MW] | C26: - | D26: - | E26: - | F26: - | G26: -
B27: Startup cost [€/MW/startup] | C27: 10 | D27: 10 | E27: 10 | F27: 10 | G27: 10
B28: Temperature heat source supply [°C] | C28: 15 | D28: 15 | E28: 15 | F28: 15 | G28: 15 | L28: I
B29: Temperature heat source return [°C] | C29: 5 | D29: 5 | E29: 5 | F29: 5 | G29: 5 | L29: I
B30: Cooling generation capacity for one unit [MW] | C30: =C6-C6/(C7/100) -> -86.552239 | D30: =D6-D6/(D7/100) -> -84.463557 | E30: =E6-E6/(E7/100) -> -83.206897 | F30: =F6-F6/(F7/100) -> -82.748585 | G30: =G6-G6/(G7/100) -> -81.899589
A33: Notes:
A34: A | B34: 0,5-5 MW
A35: B | B35: Estimated based on cases presented in [3]
A36: C | B36: Based on lost produktion during startup/shutdown
A37: D | B37: May vary depending on heat source availability
A38: E | B38: Very individual, can vary ÷ 20 %
A39: F | B39: Very individual, can vary + 20 %
A40: G | B40: Based on the old technology catalogue on process heat from 2020.
A41: H | B41: Going from current implementation to potential
A42: I | B42: Uses waste heat
A44: References
A45: 1 | B45: Viegand Maagøe, 2019.
A46: 2 | B46: Danish Enegy Agency, Technology Data - Energy Plants for Electricity and District heating generation, 2025
A47: 3 | B47: EHPA, Large Scale heat pumps in Europe, 2019

Sheet 2.a High temp. hp Up to 125C
A1: Technology | C1: High-temperature heat pumps up to 125 °C
A2: year | C2: 2025 | D2: 2030 | E2: 2035 | F2: 2040 | G2: 2050 | H2: 2025 | I2: 2025 | J2: 2050 | K2: 2050 | L2: Note | M2: Ref
A3: est | C3: ctrl | D3: ctrl | E3: ctrl | F3: ctrl | G3: ctrl | H3: lower | I3: upper | J3: lower | K3: upper | L3: - | M3: -
A4: cat | B4: par
A5: Energy/technical data
B6: Heat generation capacity for one unit [MW] | C6: 2 | D6: 2 | E6: 3 | F6: 3 | G6: 3 | H6: 0.3 | I6: 25 | J6: 0.2 | K6: 50 | L6: B | M6: 4
B7: Total efficiency, net [%], nominel load. Based on a temperature lift of 65 K | C7: 2.75 | D7: 2.85 | E7: 2.9 | F7: 2.95 | G7: 3 | H7: 2.25 | I7: 4 | J7: 2.5 | K7: 4.5 | L7: C, H | M7: 1
B8: Total efficiency, net [%], annual average | C8: 2.7 | D8: 2.8 | E8: 2.85 | F8: 2.9 | G8: 2.95 | H8: 2.2 | I8: 3.95 | J8: 2.45 | K8: 4.45
B9: Auxiliary electricity consumption [% of heat gen] | C9: 0.02 | D9: 0.02 | E9: 0.02 | F9: 0.02 | G9: 0.02 | H9: 0.01 | I9: 0.07 | J9: 0.01 | K9: 0.07 | M9: 1
B10: Forced outage [days] | C10: 0 | D10: 0 | E10: 0 | F10: 0 | G10: 0 | H10: 0 | I10: 1 | J10: 0 | K10: 1 | M10: 4
B11: Planned outage [weeks per year] | C11: 0.5 | D11: 0.5 | E11: 0.5 | F11: 0.5 | G11: 0.5 | H11: 0 | I11: 1 | J11: 0 | K11: 1 | M11: 4
B12: Technical lifetime [years] | C12: 20 | D12: 20 | E12: 20 | F12: 20 | G12: 20 | H12: 15 | I12: 30 | J12: 15 | K12: 30 | L12: D | M12: 4
B13: Construction time [years] | C13: 0.6 | D13: 0.5 | E13: 0.4 | F13: 0.4 | G13: 0.4 | H13: 0.4 | I13: 0.8 | J13: 0.2 | K13: 0.8 | L13: E | M13: 4
B14: Space requirement [1000 m2/MW_e] | C14: 0.02 | D14: 0.02 | E14: 0.02 | F14: 0.02 | G14: 0.02 | H14: 0.01 | I14: 0.04 | J14: 0.01 | K14: 0.04
A15: Regulation ability
B16: Primary regulation (of full load, per 30 seconds) [] | C16: 0.05 | D16: 0.07 | E16: 0.08 | F16: 0.09 | G16: 0.1 | H16: 0.02 | I16: 0.1 | J16: 0.05 | K16: 0.2
B17: Secondary regulation (of full load, per minute) [] | C17: 0.1 | D17: 0.14 | E17: 0.16 | F17: 0.18 | G17: 0.2 | H17: 0.04 | I17: 0.2 | J17: 0.1 | K17: 0.4
B18: Minimum load (of full load) [] | C18: 0.25 | D18: 0.25 | E18: 0.25 | F18: 0.25 | G18: 0.25 | H18: 0.1 | I18: 0.5 | J18: 0.1 | K18: 0.5 | L18: F | M18: 4
B19: Warm start-up time [hours] | C19: 0.25 | D19: 0.25 | E19: 0.25 | F19: 0.25 | G19: 0.25 | H19: 0.1 | I19: 0.5 | J19: 0.1 | K19: 0.25 | M19: 4
B20: Cold start-up time [hours] | C20: 1 | D20: 1 | E20: 1 | F20: 1 | G20: 1 | H20: 0.5 | I20: 1.5 | J20: 0.5 | K20: 1.5 | M20: 4
A21: Financial data
B22: Nominal investment (*total) [MEUR/MW] | C22: 1.2 | D22: 1.15 | E22: 1.1 | F22: 1.05 | G22: 1 | H22: 0.9 | I22: 1.5 | J22: 0.7 | K22: 1.3 | L22: G | M22: [1, 4]
B23: - of which equipment [%] | C23: 0.4 | D23: 0.4 | E23: 0.4 | F23: 0.4 | G23: 0.4 | H23: 0.25 | I23: 0.6 | J23: 0.25 | K23: 0.7 | L23: A | M23: 1
B24: - of which installation [%] | C24: 0.6 | D24: 0.6 | E24: 0.6 | F24: 0.6 | G24: 0.6 | H24: 0.4 | I24: 0.75 | J24: 0.3 | K24: 0.75 | L24: A | M24: 3
B25: Fixed O&M [EUR/MW_y] | C25: 2494 | D25: 2456 | E25: 2382 | F25: 2382 | G25: 2345 | M25: 2
B26: Variable O&M [EUR/MWh] | C26: 3.6 | D26: 3.54 | E26: 3.43 | F26: 3.43 | G26: 3.39 | M26: 2
A27: Technology-specific data
B28: Technology dependent
B29: Indirect investment cost [M€/MW] | C29: 0.23 | D29: 0.23 | E29: 0.23 | F29: 0.23 | G29: 0.23 | L29: I
B30: - Steam generation decreases COP [%-point] | C30: -0.15 | D30: -0.1 | E30: -0.05 | F30: -0.05 | G30: -0.05 | H30: -0.05 | I30: -0.2 | J30: -0.05 | K30: -0.15 | M30: [1, 4]
B31: - Steam generation increases equipment cost by [MEUR/MW] | C31: 0.2 | D31: 0.15 | E31: 0.1 | F31: 0.1 | G31: 0.1 | H31: 0.05 | I31: 0.3 | J31: 0.05 | K31: 0.2 | M31: [1, 4]
B32: - Additional equipment cost for temperature lift above 75 K [MEUR/MW] | C32: =MROUND(C22*C23*0.3,0.05) -> 0.15 | D32: =MROUND(D22*D23*0.3,0.05) -> 0.15 | E32: =MROUND(E22*E23*0.3,0.05) -> 0.15 | F32: =MROUND(F22*F23*0.3,0.05) -> 0.15 | G32: =MROUND(G22*G23*0.3,0.05) -> 0.1 | H32: =MROUND(H22*H23*0.3,0.05) -> 0.05 | I32: =MROUND(I22*I23*0.3,0.05) -> 0.25 | J32: =MROUND(J22*J23*0.3,0.05) -> 0.05 | K32: =MROUND(K22*K23*0.3,0.05) -> 0.25 | M32: [1, 4]
B33: - Total efficiency, net [%], nominel load. Based on a temperature lift of 40 K | C33: 4.45 | D33: 4.65 | E33: 4.7 | F33: 4.8 | G33: 4.9 | H33: 3.65 | I33: 6.5 | J33: 4.05 | K33: 7.3 | M33: [1, 4]
B34: - Total efficiency, net [%], nominel load. Based on a temperature lift of 80 K | C34: 2.4 | D34: 2.45 | E34: 2.5 | F34: 2.55 | G34: 2.6 | H34: 2 | I34: 3.4 | J34: 2.2 | K34: 3.8 | M34: [1, 4]
B35: - Total efficiency, net [%], nominel load. Based on a temperature lift of 100 K | C35: 2.05 | D35: 2.1 | E35: 2.15 | F35: 2.2 | G35: 2.2 | H35: 1.7 | I35: 2.85 | J35: 1.9 | K35: 3.2 | M35: [1, 4]
A38: Notes:
A39: A | B39: Depends on production infrastructure. If HTHP replaces another HTHP, there will be lower investment in new installation
A40: B | B40: Unit sizes vary a lot and depends on production infrastructure. Lower capacities for specific production processes and higher capacities for central hot water supply
A41: C | B41: Efficiency depends on temperature lift of HTHP. High temperature lift reduces COP.
A42: D | B42: Both depends on lifetime of parts and new technology with higher efficiencies leading to replacement of existing systems
A43: E | B43: Expected to be lower in future when serial production is gaining traction
A44: F | B44: HTHPs are frequency controlled but typically a higher minimum load means smaller losses in COP
A45: G | B45: Expected to be lower in future due to serial production and better integration knowledge
A46: H | B46: Efficiency depends on technology of HTHP and production processes
A47: I | B47: Relevant when needing to install new hot water piping instead of existing steam piping. Assumed similar to gas boiler.
A49: References:
A50: 1 | B50: Danish Technological Institute
A51: 2 | B51: Danish Enegy Agency, Technology Data - Energy Plants for Electricity and District heating generation, 2025
A52: 3 | B52: Viegand Maagøe
A53: 4 | B53: Annex 58
A54: 5 | B54: Fraunhofer ISI, "Direct electrification of industrial process heat. An assessment of technologies, potentials and future prospects for the EU. Study on behalf of Agora Industry", 2024

Sheet 2.b High temp. hp Up to 150
A1: Technology | C1: High-temperature heat pumps up to 150 °C
A2: year | C2: 2025 | D2: 2030 | E2: 2035 | F2: 2040 | G2: 2050 | H2: 2025 | I2: 2025 | J2: 2050 | K2: 2050 | L2: Note | M2: Ref
A3: est | C3: ctrl | D3: ctrl | E3: ctrl | F3: ctrl | G3: ctrl | H3: lower | I3: upper | J3: lower | K3: upper | L3: - | M3: -
A4: cat | B4: par
A5: Energy/technical data
B6: Heat generation capacity for one unit [MW] | C6: 2 | D6: 2 | E6: 3 | F6: 3 | G6: 3 | H6: 0.5 | I6: 80 | J6: 0.5 | K6: 100 | L6: B | M6: 4
B7: Total efficiency, net [%], nominel load. Based on a temperature lift of 65 K | C7: 2.75 | D7: 2.85 | E7: 2.9 | F7: 2.95 | G7: 3 | H7: 2.25 | I7: 4 | J7: 2.5 | K7: 4.5 | L7: C, H | M7: 1
B8: Total efficiency, net [%], annual average | C8: 2.7 | D8: 2.8 | E8: 2.85 | F8: 2.9 | G8: 2.95 | H8: 2.2 | I8: 3.95 | J8: 2.45 | K8: 4.45
B9: Auxiliary electricity consumption [% of heat gen] | C9: 0.02 | D9: 0.02 | E9: 0.02 | F9: 0.02 | G9: 0.02 | H9: 0.01 | I9: 0.07 | J9: 0.01 | K9: 0.07 | M9: 1
B10: Forced outage [days] | C10: 0 | D10: 0 | E10: 0 | F10: 0 | G10: 0 | H10: 0 | I10: 1 | J10: 0 | K10: 1 | M10: 4
B11: Planned outage [weeks per year] | C11: 0.5 | D11: 0.5 | E11: 0.5 | F11: 0.5 | G11: 0.5 | H11: 0 | I11: 1 | J11: 0 | K11: 1 | M11: 4
B12: Technical lifetime [years] | C12: 20 | D12: 20 | E12: 20 | F12: 20 | G12: 20 | H12: 15 | I12: 30 | J12: 15 | K12: 30 | L12: D | M12: 4
B13: Construction time [years] | C13: 0.6 | D13: 0.5 | E13: 0.4 | F13: 0.4 | G13: 0.4 | H13: 0.4 | I13: 0.8 | J13: 0.2 | K13: 0.8 | L13: E | M13: 4
B14: Space requirement [1000 m2/MW_e] | C14: 0.03 | D14: 0.03 | E14: 0.03 | F14: 0.03 | G14: 0.03 | H14: 0.02 | I14: 0.06 | J14: 0.01 | K14: 0.05
A15: Regulation ability
B16: Primary regulation (of full load, per 30 seconds) [] | C16: 0.05 | D16: 0.07 | E16: 0.08 | F16: 0.09 | G16: 0.1 | H16: 0.02 | I16: 0.1 | J16: 0.05 | K16: 0.2
B17: Secondary regulation (of full load, per minute) [] | C17: 0.1 | D17: 0.14 | E17: 0.16 | F17: 0.18 | G17: 0.2 | H17: 0.04 | I17: 0.2 | J17: 0.1 | K17: 0.4
B18: Minimum load (of full load) [] | C18: 0.25 | D18: 0.25 | E18: 0.25 | F18: 0.25 | G18: 0.25 | H18: 0.1 | I18: 0.5 | J18: 0.1 | K18: 0.5 | L18: F | M18: 4
B19: Warm start-up time [hours] | C19: 0.25 | D19: 0.25 | E19: 0.25 | F19: 0.25 | G19: 0.25 | H19: 0.1 | I19: 0.5 | J19: 0.1 | K19: 0.25 | M19: 4
B20: Cold start-up time [hours] | C20: 1 | D20: 1 | E20: 1 | F20: 1 | G20: 1 | H20: 0.5 | I20: 1.5 | J20: 0.5 | K20: 1.5 | M20: 4
A21: Financial data
B22: Nominal investment (*total) [MEUR/MW] | C22: 1.55 | D22: 1.5 | E22: 1.45 | F22: 1.4 | G22: 1.35 | H22: 1.25 | I22: 1.8 | J22: 1.1 | K22: 1.65 | L22: G
B23: - of which equipment [%] | C23: 0.4 | D23: 0.4 | E23: 0.4 | F23: 0.4 | G23: 0.4 | H23: 0.25 | I23: 0.6 | J23: 0.25 | K23: 0.7 | L23: A | M23: 1
B24: - of which installation [%] | C24: 0.6 | D24: 0.6 | E24: 0.6 | F24: 0.6 | G24: 0.6 | H24: 0.4 | I24: 0.75 | J24: 0.3 | K24: 0.75 | L24: A | M24: 3
B25: Fixed O&M [EUR/MW_y], from last update in 2019 | C25: 2494 | D25: 2456 | E25: 2382 | F25: 2382 | G25: 2345 | M25: 2
B26: Variable O&M [EUR/MWh], from last update in 2019 | C26: 3.6 | D26: 3.54 | E26: 3.43 | F26: 3.43 | G26: 3.39 | M26: 1
A27: Technology-specific data
B28: Technology dependent
B29: Indirect investment cost [M€/MW] | C29: 0.23 | D29: 0.23 | E29: 0.23 | F29: 0.23 | G29: 0.23 | L29: I
B30: - Steam generation decreases COP [%-point] | C30: -0.15 | D30: -0.1 | E30: -0.05 | F30: -0.05 | G30: -0.05 | H30: -0.05 | I30: -0.2 | J30: -0.05 | K30: -0.15 | M30: [1, 4]
B31: - Steam generation increases equipment cost by [MEUR/MW] | C31: 0.2 | D31: 0.15 | E31: 0.1 | F31: 0.1 | G31: 0.1 | H31: 0.05 | I31: 0.3 | J31: 0.05 | K31: 0.2 | M31: [1, 4]
B32: - Additional equipment cost for temperature lift above 75 K [MEUR/MW] | C32: =MROUND(C22*C23*0.3,0.05) -> 0.2 | D32: =MROUND(D22*D23*0.3,0.05) -> 0.2 | E32: =MROUND(E22*E23*0.3,0.05) -> 0.15 | F32: =MROUND(F22*F23*0.3,0.05) -> 0.15 | G32: =MROUND(G22*G23*0.3,0.05) -> 0.15 | H32: =MROUND(H22*H23*0.3,0.05) -> 0.1 | I32: =MROUND(I22*I23*0.3,0.05) -> 0.3 | J32: =MROUND(J22*J23*0.3,0.05) -> 0.1 | K32: =MROUND(K22*K23*0.3,0.05) -> 0.35 | M32: [1, 4]
B33: - Total efficiency, net [%], nominel load. Based on a temperature lift of 40 K | C33: 4.45 | D33: 4.65 | E33: 4.7 | F33: 4.8 | G33: 4.9 | H33: 3.65 | I33: 6.5 | J33: 4.05 | K33: 7.3 | M33: [1, 4]
B34: - Total efficiency, net [%], nominel load. Based on a temperature lift of 80 K | C34: 2.4 | D34: 2.45 | E34: 2.5 | F34: 2.55 | G34: 2.6 | H34: 2 | I34: 3.4 | J34: 2.2 | K34: 3.8 | M34: [1, 4]
B35: - Total efficiency, net [%], nominel load. Based on a temperature lift of 100 K | C35: 2.05 | D35: 2.1 | E35: 2.15 | F35: 2.2 | G35: 2.2 | H35: 1.7 | I35: 2.85 | J35: 1.9 | K35: 3.2 | M35: [1, 4]
A38: Notes:
A39: A | B39: Depends on production infrastructure. If HTHP replaces another HTHP, there will be lower investment in new installation
A40: B | B40: Unit sizes vary a lot and depends on production infrastructure. Lower capacities for specific production processes and higher capacities for central hot water supply
A41: C | B41: Efficiency depends on temperature lift of HTHP. High temperature lift reduces COP.
A42: D | B42: Both depends on lifetime of parts and new technology with higher efficiencies leading to replacement of existing systems
A43: E | B43: Expected to be lower in future when serial production is gaining traction
A44: F | B44: HTHPs are frequency controlled but typically a higher minimum load means smaller losses in COP
A45: G | B45: Expected to be lower in future due to serial production and better integration knowledge
A46: H | B46: Efficiency depends on technology of HTHP and production processes
A47: I | B47: Relevant when needing to install new hot water piping instead of existing steam piping. Assumed similar to gas boiler.
A49: References:
A50: 1 | B50: Danish Technological Institute
A51: 2 | B51: Jensen, J., Elmegaard, B., and Markussen, W. Industrial heat pumps for high temperature process applications.: A numerical study of the ammonia-water hybrid absorption-compression heat pump. PhD thesis. ,2016
A52: 3 | B52: Viegand Maagøe
A53: 4 | B53: Annex 58

Sheet 4 MVR 5 K
A1: Technology | C1: Mechanical vapor recompression
A2: year | C2: 2025 | D2: 2030 | E2: 2035 | F2: 2040 | G2: 2050 | H2: 2025 | I2: 2025 | J2: 2050 | K2: 2050 | L2: Note | M2: Ref
A3: est | C3: ctrl | D3: ctrl | E3: ctrl | F3: ctrl | G3: ctrl | H3: lower | I3: upper | J3: lower | K3: upper | L3: - | M3: -
A4: cat | B4: par
A5: Energy/technical data
B6: Heat generation capacity for one unit [MW] | C6: 20 | D6: 20 | E6: 20 | F6: 20 | G6: 20 | H6: 5 | I6: 50 | J6: 5 | K6: 50 | L6: A | M6: 1
B7: Total efficiency, net [%], nominel load | C7: 12.6 | D7: 13.2 | E7: 13.5 | F7: 13.8 | G7: 14.3 | H7: 10 | I7: 15.12 | J7: 10.56 | K7: 17.16 | L7: B | M7: 1
B8: Total efficiency, net [%], annual average | C8: =C7-50% -> 12.1 | D8: =D7-50% -> 12.7 | E8: =E7-50% -> 13 | F8: =F7-50% -> 13.3 | G8: =G7-50% -> 13.8 | H8: =H7-50% -> 9.5 | I8: =I7-50% -> 14.62 | J8: =J7-50% -> 10.06 | K8: =K7-50% -> 16.66
B9: Auxiliary electricity consumption [% of heat gen] | C9: 0.01 | D9: 0.01 | E9: 0.01 | F9: 0.01 | G9: 0.01 | H9: 0 | I9: 0.02 | J9: 0 | K9: 0.02 | M9: 3
B10: Forced outage [%] | C10: 0 | D10: 0 | E10: 0 | F10: 0 | G10: 0 | H10: 0 | I10: 0.01 | J10: 0 | K10: 0.01 | M10: 2
B11: Planned outage [weeks per year] | C11: 0.5 | D11: 0.5 | E11: 0.5 | F11: 0.5 | G11: 0.5 | H11: 0 | I11: 1 | J11: 0 | K11: 1 | M11: 2
B12: Technical lifetime [years] | C12: 25 | D12: 25 | E12: 25 | F12: 25 | G12: 25 | H12: 15 | I12: 35 | J12: 15 | K12: 35 | M12: [1, 2]
B13: Construction time [years] | C13: 0.1 | D13: 0.1 | E13: 0.1 | F13: 0.1 | G13: 0.1 | H13: 0.05 | I13: 0.2 | J13: 0.05 | K13: 0.2 | M13: [1, 3]
A14: Regulation Ability
B15: Minimum load [% of full load] | C15: 0.15 | D15: 0.15 | E15: 0.15 | F15: 0.15 | G15: 0.15 | M15: 4
B16: Warm start-up time [hours] | C16: 0.5 | D16: 0.5 | E16: 0.5 | F16: 0.5 | G16: 0.5 | M16: 3
B17: Cold start-up time [hours] | C17: 1 | D17: 1 | E17: 1 | F17: 1 | G17: 1 | M17: 3
A18: Financial data
B19: Nominal investment [M€/MW] | C19: 0.41 | D19: 0.39 | E19: 0.39 | F19: 0.38 | G19: 0.36 | M19: [1, 5]
B20: - of which equipment [%] | C20: 0.6 | D20: 0.6 | E20: 0.6 | F20: 0.6 | G20: 0.6 | M20: [1, 5]
B21: - of which installation [%] | C21: 0.4 | D21: 0.4 | E21: 0.4 | F21: 0.4 | G21: 0.4 | M21: [1, 5]
B22: Fixed O&M [€/MJ/s/year] | C22: 2345 | D22: 2345 | E22: 2345 | F22: 2345 | G22: 2345 | M22: 2
B23: Variable O&M [€/MWh] | C23: 2.1 | D23: 2 | E23: 2 | F23: 2 | G23: 1.9 | M23: 2
A26: Notes:
A27: A | B27: 5-50 MW
A28: B | B28: Assumed temperature lift of 5 K (saturation temperatur)
A30: References:
A31: 1 | B31: Viegand Maagøe, MVR, 2018
A32: 2 | B32: Technological data for energi plants (Compressions Heat Pumps for DH), Energistyrelsen, 2017
A33: 3 | B33: Viegand Maagøe, 2019
A34: 4 | B34: EPCON, EVAPORATION TECHNOLOGY, 2019
A35: 5 | B35: EPCON investment cost offer, 2017.

Sheet 5.1a Electric boiler steam
A1: Technology | C1: Electric boiler, 0,4-0,69 kV, steam, 1-12 bar
A2: year | C2: 2025 | D2: 2030 | E2: 2035 | F2: 2040 | G2: 2050 | H2: 2025 | I2: 2025 | J2: 2050 | K2: 2050 | L2: Note | M2: Ref
A3: est | C3: ctrl | D3: ctrl | E3: ctrl | F3: ctrl | G3: ctrl | H3: lower | I3: upper | J3: lower | K3: upper | L3: - | M3: -
A4: cat | B4: par
A5: Energy/technical data
B6: Heat generation capacity for one unit [MW] | C6: 2 | D6: 2 | E6: 2 | F6: 2 | G6: 2 | H6: 1 | I6: 5 | J6: 1 | K6: 5 | L6: A
B7: Total efficiency, net [%], nominel load | C7: 0.99 | D7: 0.99 | E7: 0.99 | F7: 0.99 | G7: 0.99 | H7: 0.98 | I7: 1 | J7: 0.98 | K7: 1 | M7: [1, 2]
B8: Total efficiency, net [%], annual average | C8: 0.99 | D8: 0.99 | E8: 0.99 | F8: 0.99 | G8: 0.99 | H8: 0.98 | I8: 0.99 | J8: 0.98 | K8: 0.99 | M8: [1, 2]
B9: Auxiliary electricity consumption [% of heat gen] | C9: 0.005 | D9: 0.005 | E9: 0.005 | F9: 0.005 | G9: 0.005 | H9: 0.001 | I9: 0.005 | J9: 0.001 | K9: 0.005 | M9: [1, 2]
B10: Forced outage [%] | C10: 0.01 | D10: 0.01 | E10: 0.01 | F10: 0.01 | G10: 0.01 | H10: 0.005 | I10: 0.01 | J10: 0.005 | K10: 0.01 | M10: [1, 2]
B11: Planned outage [weeks per year] | C11: 0.2 | D11: 0.2 | E11: 0.2 | F11: 0.2 | G11: 0.2 | H11: 0.2 | I11: 0.2 | J11: 0.2 | K11: 0.2 | M11: 2
B12: Technical lifetime [years] | C12: 25 | D12: 25 | E12: 25 | F12: 25 | G12: 25 | H12: 20 | I12: 25 | J12: 20 | K12: 25 | M12: 2
B13: Construction time [years] | C13: 0.5 | D13: 0.5 | E13: 0.5 | F13: 0.5 | G13: 0.5 | H13: 0.5 | I13: 1 | J13: 0.5 | K13: 1 | M13: 1
A14: Regulation Ability
B15: Minimum load [% of full load] | C15: 0.02 | D15: 0.02 | E15: 0.02 | F15: 0.02 | G15: 0.02 | M15: 2
B16: Warm start-up time [hours] | C16: 0.03 | D16: 0.03 | E16: 0.03 | F16: 0.03 | G16: 0.03 | M16: 2
B17: Cold start-up time [hours] | C17: 0.17 | D17: 0.17 | E17: 0.17 | F17: 0.17 | G17: 0.17 | M17: 2
A18: Financial data
B19: Nominal investment [M€/MW] | C19: 0.25 | D19: 0.22 | E19: 0.22 | F19: 0.22 | G19: 0.22 | L19: B,C | M19: [1, 2, 4]
B20: - of which equipment [%] | C20: 0.75 | D20: 0.75 | E20: 0.75 | F20: 0.75 | G20: 0.75 | M20: [2, 4]
B21: - of which installation [%] | C21: 0.25 | D21: 0.25 | E21: 0.25 | F21: 0.25 | G21: 0.25 | M21: [2, 4]
B22: Fixed O&M [€/MJ/s/year] | C22: 1442 | D22: 1375 | E22: 1341 | F22: 1307 | G22: 1240 | M22: [2, 3, 4]
B23: Variable O&M [€/MWh] | C23: 0.674 | D23: 0.642 | E23: 0.627 | F23: 0.611 | G23: 0.578 | M23: [2, 3, 4]
A24: Technology-specific data
B25: Additional investments cost for 12-16 bar boilers [M€/MW] | C25: 0.064 | D25: 0.057 | E25: 0.057 | F25: 0.057 | G25: 0.057
A28: Notes:
A29: A | B29: 1-5 MW
A30: B | B30: Electrode boilers at low voltage typically needs a transformer from distribution grid. Costs for the transformer are included in the equipment costs.
A31: C | B31: Investment cost is slightly higher than for a hot water boiler.
A33: References:
A34: 1 | B34: Danish Enegy Agency, Technology Data - Energy Plants for Electricity and District heating generation, 2022
A35: 2 | B35: AS:scan, Personal communication, 2022
A36: 3 | B36: Tjæreborg Industri, Personal communication, 2022
A37: 4 | B37: Nordheat, Personal communication, 2022

Sheet 5.1b Electric boiler steam
A1: Technology | C1: Electric boiler, 10 kV, steam, 1-12 bar
A2: year | C2: 2025 | D2: 2030 | E2: 2035 | F2: 2040 | G2: 2050 | H2: 2025 | I2: 2025 | J2: 2050 | K2: 2050 | L2: Note | M2: Ref
A3: est | C3: ctrl | D3: ctrl | E3: ctrl | F3: ctrl | G3: ctrl | H3: lower | I3: upper | J3: lower | K3: upper | L3: - | M3: -
A4: cat | B4: par
A5: Energy/technical data
B6: Heat generation capacity for one unit [MW] | C6: 15 | D6: 15 | E6: 15 | F6: 15 | G6: 15 | H6: 5 | I6: 60 | J6: 5 | K6: 60 | L6: A
B7: Total efficiency, net [%], nominel load | C7: 0.99 | D7: 0.99 | E7: 0.99 | F7: 0.99 | G7: 0.99 | H7: 0.98 | I7: 1 | J7: 0.98 | K7: 1 | M7: [1, 2]
B8: Total efficiency, net [%], annual average | C8: 0.99 | D8: 0.99 | E8: 0.99 | F8: 0.99 | G8: 0.99 | H8: 0.98 | I8: 0.99 | J8: 0.98 | K8: 0.99 | M8: [1, 2]
B9: Auxiliary electricity consumption [% of heat gen] | C9: 0.005 | D9: 0.005 | E9: 0.005 | F9: 0.005 | G9: 0.005 | H9: 0.001 | I9: 0.005 | J9: 0.001 | K9: 0.005 | M9: [1, 2]
B10: Forced outage [%] | C10: 0.01 | D10: 0.01 | E10: 0.01 | F10: 0.01 | G10: 0.01 | H10: 0.005 | I10: 0.01 | J10: 0.005 | K10: 0.01 | M10: [1, 2]
B11: Planned outage [weeks per year] | C11: 0.2 | D11: 0.2 | E11: 0.2 | F11: 0.2 | G11: 0.2 | H11: 0.2 | I11: 0.2 | J11: 0.2 | K11: 0.2 | M11: 2
B12: Technical lifetime [years] | C12: 25 | D12: 25 | E12: 25 | F12: 25 | G12: 25 | H12: 20 | I12: 25 | J12: 20 | K12: 25 | M12: 2
B13: Construction time [years] | C13: 0.5 | D13: 0.5 | E13: 0.5 | F13: 0.5 | G13: 0.5 | H13: 0.5 | I13: 1 | J13: 0.5 | K13: 1 | M13: 1
A14: Regulation Ability
B15: Minimum load [% of full load] | C15: 0.02 | D15: 0.02 | E15: 0.02 | F15: 0.02 | G15: 0.02 | M15: 2
B16: Warm start-up time [hours] | C16: 0.03 | D16: 0.03 | E16: 0.03 | F16: 0.03 | G16: 0.03 | M16: 2
B17: Cold start-up time [hours] | C17: 0.17 | D17: 0.17 | E17: 0.17 | F17: 0.17 | G17: 0.17 | M17: 2
A18: Financial data
B19: Nominal investment [M€/MW] | C19: 0.11 | D19: 0.1 | E19: 0.1 | F19: 0.1 | G19: 0.1 | L19: B,C | M19: [1, 2, 4]
B20: - of which equipment [%] | C20: 0.85 | D20: 0.85 | E20: 0.85 | F20: 0.85 | G20: 0.85 | M20: 2
B21: - of which installation [%] | C21: 0.15 | D21: 0.15 | E21: 0.15 | F21: 0.15 | G21: 0.15 | M21: 2
B22: Fixed O&M [€/MJ/s/year] | C22: 1298 | D22: 1237 | E22: 1208 | F22: 1177 | G22: 1116 | M22: [2, 3, 4]
B23: Variable O&M [€/MWh] | C23: 0.61 | D23: 0.58 | E23: 0.56 | F23: 0.55 | G23: 0.52 | M23: [2, 3, 4]
A24: Technology-specific data
B25: Additional investments cost for 12-16 bar boilers [M€/MW] | C25: 0.021 | D25: 0.018 | E25: 0.018 | F25: 0.018 | G25: 0.018
A28: Notes:
A29: A | B29: 5-60 MW
A30: B | B30: Electrode boilers at medium-high voltage are directly connected to the distribution grid. Costs for the distribution board are included in the equipment costs.
A31: C | B31: Investment cost is slightly higher than for a hot water boiler.
A33: References:
A34: 1 | B34: Danish Enegy Agency, Technology Data - Energy Plants for Electricity and District heating generation, 2022
A35: 2 | B35: AS:scan, Personal communication, 2022
A36: 3 | B36: Tjæreborg Industri, Personal communication, 2022
A37: 4 | B37: Nordheat, Personal communication, 2022

Sheet 5.2a Electric boiler hot wate
A1: Technology | C1: Electric boiler, 0,4-0,69 kV, hot water, 1-12 bar
A2: year | C2: 2025 | D2: 2030 | E2: 2035 | F2: 2040 | G2: 2050 | H2: 2025 | I2: 2025 | J2: 2050 | K2: 2050 | L2: Note | M2: Ref
A3: est | C3: ctrl | D3: ctrl | E3: ctrl | F3: ctrl | G3: ctrl | H3: lower | I3: upper | J3: lower | K3: upper | L3: - | M3: -
A4: cat | B4: par
A5: Energy/technical data
B6: Heat generation capacity for one unit [MW] | C6: 2 | D6: 2 | E6: 2 | F6: 2 | G6: 2 | H6: 1 | I6: 5 | J6: 1 | K6: 5 | L6: A
B7: Total efficiency, net [%], nominel load | C7: 0.99 | D7: 0.99 | E7: 0.99 | F7: 0.99 | G7: 0.99 | H7: 0.98 | I7: 1 | J7: 0.98 | K7: 1 | M7: [1, 2]
B8: Total efficiency, net [%], annual average | C8: 0.99 | D8: 0.99 | E8: 0.99 | F8: 0.99 | G8: 0.99 | H8: 0.98 | I8: 0.99 | J8: 0.98 | K8: 0.99 | M8: [1, 2]
B9: Auxiliary electricity consumption [% of heat gen] | C9: 0.005 | D9: 0.005 | E9: 0.005 | F9: 0.005 | G9: 0.005 | H9: 0.001 | I9: 0.005 | J9: 0.001 | K9: 0.005 | M9: [1, 2]
B10: Forced outage [%] | C10: 0.01 | D10: 0.01 | E10: 0.01 | F10: 0.01 | G10: 0.01 | H10: 0.005 | I10: 0.01 | J10: 0.005 | K10: 0.01 | M10: [1, 2]
B11: Planned outage [weeks per year] | C11: 0.2 | D11: 0.2 | E11: 0.2 | F11: 0.2 | G11: 0.2 | H11: 0.2 | I11: 0.2 | J11: 0.2 | K11: 0.2 | M11: 1
B12: Technical lifetime [years] | C12: 25 | D12: 25 | E12: 25 | F12: 25 | G12: 25 | H12: 20 | I12: 25 | J12: 20 | K12: 25 | M12: 2
B13: Construction time [years] | C13: 0.5 | D13: 0.5 | E13: 0.5 | F13: 0.5 | G13: 0.5 | H13: 0.5 | I13: 1 | J13: 0.5 | K13: 1 | M13: 1
A14: Regulation Ability
B15: Minimum load [% of full load] | C15: 0.05 | D15: 0.05 | E15: 0.05 | F15: 0.05 | G15: 0.05 | M15: 1
B16: Warm start-up time [hours] | C16: 0.008 | D16: 0.008 | E16: 0.008 | F16: 0.008 | G16: 0.008 | M16: 1
B17: Cold start-up time [hours] | C17: 0.08 | D17: 0.08 | E17: 0.08 | F17: 0.08 | G17: 0.08 | M17: 1
A18: Financial data
B19: Nominal investment [M€/MW] | C19: 0.202 | D19: 0.187 | E19: 0.187 | F19: 0.187 | G19: 0.187 | L19: B,C | M19: [1, 2, 4]
B20: - of which equipment [%] | C20: 0.75 | D20: 0.75 | E20: 0.75 | F20: 0.75 | G20: 0.75 | M20: 2
B21: - of which installation [%] | C21: 0.25 | D21: 0.25 | E21: 0.25 | F21: 0.25 | G21: 0.25 | M21: 2
B22: Fixed O&M [€/MJ/s/year] | C22: 1254 | D22: 1196 | E22: 1166 | F22: 1137 | G22: 1079 | M22: 1
B23: Variable O&M [€/MWh] | C23: 0.59 | D23: 0.56 | E23: 0.54 | F23: 0.53 | G23: 0.5 | M23: [2, 3, 4]
A24: Technology-specific data
B25: Indirect investments cost [M€/MW] | C25: =C19*0.5 -> 0.101 | D25: =D19*0.5 -> 0.0935 | E25: =E19*0.5 -> 0.0935 | F25: =F19*0.5 -> 0.0935 | G25: =G19*0.5 -> 0.0935 | L25: D
B26: Additional investments cost for 12-16 bar boilers [M€/MW] | C26: 0.057 | D26: 0.049 | E26: 0.049 | F26: 0.049 | G26: 0.049
A29: Notes:
A30: A | B30: 1-5 MW
A31: B | B31: Electrode boilers at low voltage typically needs a transformer from distribution grid. Costs for the transformer are included in the equipment costs.
A32: C | B32: Investment cost is slightly lower than for a steam boiler.
A33: D | B33: Going from current implementation to potential
A35: References:
A36: 1 | B36: Danish Enegy Agency, Technology Data - Energy Plants for Electricity and District heating generation, 2022
A37: 2 | B37: AS:scan, Personal communication, 2022
A38: 3 | B38: Tjæreborg Industri, Personal communication, 2019
A39: 4 | B39: Nordheat, Personal communication, 2022

Sheet 5.2b Electric boiler hot wate
A1: Technology | C1: Electric boiler,10 kV, hot water, 1-12 bar
A2: year | C2: 2025 | D2: 2030 | E2: 2035 | F2: 2040 | G2: 2050 | H2: 2025 | I2: 2025 | J2: 2050 | K2: 2050 | L2: Note | M2: Ref
A3: est | C3: ctrl | D3: ctrl | E3: ctrl | F3: ctrl | G3: ctrl | H3: lower | I3: upper | J3: lower | K3: upper | L3: - | M3: -
A4: cat | B4: par
A5: Energy/technical data
B6: Heat generation capacity for one unit [MW] | C6: 15 | D6: 15 | E6: 15 | F6: 15 | G6: 15 | H6: 5 | I6: 60 | J6: 5 | K6: 60 | L6: A
B7: Total efficiency, net [%], nominel load | C7: 0.99 | D7: 0.99 | E7: 0.99 | F7: 0.99 | G7: 0.99 | H7: 0.98 | I7: 1 | J7: 0.98 | K7: 1 | M7: [1, 2]
B8: Total efficiency, net [%], annual average | C8: 0.99 | D8: 0.99 | E8: 0.99 | F8: 0.99 | G8: 0.99 | H8: 0.98 | I8: 0.99 | J8: 0.98 | K8: 0.99 | M8: [1, 2]
B9: Auxiliary electricity consumption [% of heat gen] | C9: 0.005 | D9: 0.005 | E9: 0.005 | F9: 0.005 | G9: 0.005 | H9: 0.001 | I9: 0.005 | J9: 0.001 | K9: 0.005 | M9: [1, 2]
B10: Forced outage [%] | C10: 0.01 | D10: 0.01 | E10: 0.01 | F10: 0.01 | G10: 0.01 | H10: 0.005 | I10: 0.01 | J10: 0.005 | K10: 0.01 | M10: [1, 2]
B11: Planned outage [weeks per year] | C11: 0.2 | D11: 0.2 | E11: 0.2 | F11: 0.2 | G11: 0.2 | H11: 0.2 | I11: 0.2 | J11: 0.2 | K11: 0.2 | M11: 1
B12: Technical lifetime [years] | C12: 25 | D12: 25 | E12: 25 | F12: 25 | G12: 25 | H12: 20 | I12: 25 | J12: 20 | K12: 25 | M12: 2
B13: Construction time [years] | C13: 0.5 | D13: 0.5 | E13: 0.5 | F13: 0.5 | G13: 0.5 | H13: 0.5 | I13: 1 | J13: 0.5 | K13: 1 | M13: 1
A14: Regulation Ability
B15: Minimum load [% of full load] | C15: 0.05 | D15: 0.05 | E15: 0.05 | F15: 0.05 | G15: 0.05 | M15: 1
B16: Warm start-up time [hours] | C16: 0.008 | D16: 0.008 | E16: 0.008 | F16: 0.008 | G16: 0.008 | M16: 1
B17: Cold start-up time [hours] | C17: 0.08 | D17: 0.08 | E17: 0.08 | F17: 0.08 | G17: 0.08 | M17: 1
A18: Financial data
B19: Nominal investment [M€/MW] | C19: 0.089 | D19: 0.084 | E19: 0.084 | F19: 0.084 | G19: 0.084 | L19: B,C | M19: [1, 2, 4]
B20: - of which equipment [%] | C20: 0.85 | D20: 0.85 | E20: 0.85 | F20: 0.85 | G20: 0.85 | M20: 2
B21: - of which installation [%] | C21: 0.15 | D21: 0.15 | E21: 0.15 | F21: 0.15 | G21: 0.15 | M21: 2
B22: Fixed O&M [€/MJ/s/year] | C22: 1103 | D22: 1076 | E22: 1050 | F22: 1023 | G22: 971 | M22: [1, 2, 4]
B23: Variable O&M [€/MWh] | C23: 0.53 | D23: 0.5 | E23: 0.49 | F23: 0.48 | G23: 0.45 | M23: [2, 3, 4]
A24: Technology-specific data
B25: Indirect investments cost [M€/MW] | C25: =C19/2 -> 0.0445 | D25: =D19/2 -> 0.042 | E25: =E19/2 -> 0.042 | F25: =F19/2 -> 0.042 | G25: =G19/2 -> 0.042 | L25: D
B26: Additional investments cost for 12-16 bar boilers [M€/MW] | C26: 0.018 | D26: 0.016 | E26: 0.016 | F26: 0.016 | G26: 0.016
A29: Notes:
A30: A | B30: 5-60 MW
A31: B | B31: Electrode boilers at medium-high voltage are directly connected to the distribution grid. Costs for the distribution board are included in the equipment costs.
A32: C | B32: Investment cost is slightly lower than for a steam boiler.
A33: D | B33: Going from current implementation to potential
A35: References:
A36: 1 | B36: Danish Enegy Agency, Technology Data - Energy Plants for Electricity and District heating generation, 2022
A37: 2 | B37: AS:scan, Personal communication, 2022
A38: 3 | B38: Tjæreborg Industri, Personal communication, 2022
A39: 4 | B39: Nordheat, Personal communication, 2022

Sheet 6.1 Boiler, gas and oil
A1: Technology | C1: Boiler, gas and oil
A2: year | C2: 2025 | D2: 2030 | E2: 2035 | F2: 2040 | G2: 2050 | H2: 2025 | I2: 2025 | J2: 2050 | K2: 2050 | L2: Note | M2: Ref
A3: est | C3: ctrl | D3: ctrl | E3: ctrl | F3: ctrl | G3: ctrl | H3: lower | I3: upper | J3: lower | K3: upper | L3: - | M3: -
A4: cat | B4: par
A5: Energy/technical data
B6: Heat generation capacity for one unit [MW] | C6: 5 | D6: 5 | E6: 5 | F6: 5 | G6: 5 | H6: 0.5 | I6: 50 | J6: 0.5 | K6: 50 | M6: [1, 2, 3, 6]
B7: Total efficiency, net [%], nominel load | C7: 0.94 | D7: 0.94 | E7: 0.94 | F7: 0.94 | G7: 0.94 | H7: 0.92 | I7: 0.95 | J7: 0.92 | K7: 0.95 | L7: A, B, E | M7: [1, 4, 6]
B8: Total efficiency, net [%], annual average | C8: 0.939 | D8: 0.939 | E8: 0.939 | F8: 0.939 | G8: 0.939 | H8: 0.919 | I8: 0.949 | J8: 0.919 | K8: 0.949 | L8: A, B, D | M8: [1, 4]
B9: Auxiliary electricity consumption [% of heat gen] | C9: 0.0015 | D9: 0.0015 | E9: 0.0015 | F9: 0.0015 | G9: 0.0015 | H9: 0 | I9: 0.0015 | J9: 0 | K9: 0.0015 | M9: [1, 2]
B10: Forced outage [%] | C10: 0.01 | D10: 0.01 | E10: 0.01 | F10: 0.01 | G10: 0.01 | H10: 0 | I10: 0.02 | J10: 0 | K10: 0.02 | M10: 1
B11: Planned outage [weeks per year] | C11: 0.5 | D11: 0.5 | E11: 0.5 | F11: 0.5 | G11: 0.5 | H11: 0.3 | I11: 0.6 | J11: 0.3 | K11: 0.6 | M11: [1, 2]
B12: Technical lifetime [years] | C12: 25 | D12: 25 | E12: 25 | F12: 25 | G12: 25 | H12: 25 | J12: 25 | M12: 1
B13: Construction time [years] | C13: 0.2 | D13: 0.2 | E13: 0.2 | F13: 0.2 | G13: 0.2 | H13: 0.02 | I13: 0.7 | J13: 0.02 | K13: 0.7 | M13: [1, 2]
B14: Space requirement [1000 m2/MW_e] | C14: 0.008 | D14: 0.008 | E14: 0.008 | F14: 0.008 | G14: 0.008 | H14: 0.007 | I14: 0.01 | J14: 0.007 | K14: 0.01 | M14: [2, 3]
A15: Regulation ability
B16: Primary regulation (of full load, per 30 seconds) [%] | C16: 0.15 | D16: 0.15 | E16: 0.15 | F16: 0.15 | G16: 0.15 | H16: 0.035 | I16: 0.3 | L16: H | M16: [1, 2, 6]
B17: Secondary regulation (of full load, per minute) [%] | C17: 0.3 | D17: 0.3 | E17: 0.3 | F17: 0.3 | G17: 0.3 | H17: 0.07 | I17: 0.6 | L17: H | M17: [1, 2, 6]
B18: Minimum load (of full load) [%] | C18: 0.15 | D18: 0.15 | E18: 0.15 | F18: 0.15 | G18: 0.15 | H18: 0.1 | I18: 0.2 | M18: [1, 2, 6]
B19: Warm start-up time [hours] | C19: 0.06 | D19: 0.06 | E19: 0.06 | F19: 0.06 | G19: 0.06 | H19: 0.025 | I19: 0.2 | M19: [1, 2, 6]
B20: Cold start-up time [hours] | C20: 0.5 | D20: 0.5 | E20: 0.5 | F20: 0.5 | G20: 0.5 | H20: 0.3 | I20: 1 | M20: [1, 2, 6]
A21: Financial data
B22: Nominal investment (*total) [MEUR/MW] | C22: 0.09 | D22: 0.09 | E22: 0.09 | F22: 0.09 | G22: 0.09 | L22: C, B | M22: [1, 2, 6]
B23: - of which equipment [%] | C23: 0.66 | D23: 0.66 | E23: 0.66 | F23: 0.66 | G23: 0.66 | M23: [1, 2]
B24: - of which installation [%] | C24: 0.34 | D24: 0.34 | E24: 0.34 | F24: 0.34 | G24: 0.34 | M24: [1, 2]
B25: Fixed O&M [EUR/MW_y] | C25: 2000 | D25: 2000 | E25: 2000 | F25: 2000 | G25: 2000 | M25: [1, 2]
B26: Variable O&M [EUR/MWh] | C26: 1.23 | D26: 1.23 | E26: 1.23 | F26: 1.23 | G26: 1.23 | M26: 1
A27: Technology-specific data
B28: Indirect investment cost [M€/MW] | C28: 0.23 | D28: 0.23 | E28: 0.23 | F28: 0.23 | G28: 0.23 | L28: J | M28: 2
B29: Technology dependent
B30: - Adding flue gas condenser (after economiser) increases efficiency by [%-point] (gas only) | C30: 0.06 | D30: 0.06 | E30: 0.06 | F30: 0.06 | G30: 0.06 | L30: I, E | M30: [1, 2, 5]
B31: - Adding flue gas condenser (after economiser) increases nominal investment by [%] (gas only) | C31: 0.1 | D31: 0.1 | E31: 0.1 | F31: 0.1 | G31: 0.1 | L31: I | M31: 2
B32: - Hot water boiler instead of steam boiler increases efficiency by [%-point] | C32: 0.01 | D32: 0.01 | E32: 0.01 | F32: 0.01 | G32: 0.01 | L32: F
B33: - Hot water boiler instead of steam boiler reduces nominal investment by [%] | C33: 0.3 | D33: 0.3 | E33: 0.3 | F33: 0.3 | G33: 0.3 | L33: G | M33: [2, 3]
A36: Notes:
A37: A | B37: Effeciency for unit with economiser (but not flue gas condenser) installed.
A38: B | B38: Values for steam boiler (see technology-specific data for differences with hot water boiler)
A39: C | B39: Prices include boiler, firing equipment, pumps, economiser, water-treatment system, chimney and installation.
A40: D | B40: Assuming 10 starts a year.
A41: E | B41: For condensing boilers, efficiencies above 100% are possible, since the standard efficiency calculation using the lower heating value (LHV) as denominator.
A42: F | B42: 1 %-point higher for hot water boiler, due to assumed lower flue gas temperature. If no flue gas condenser and economiser is used, the increase will be higher.
A43: G | B43: Hot water boiler is generally operating at lower pressure levels, so pressure vessel is cheaper. Water treatment system not necessary for hot water boiler.
A44: H | B44: Assumes warm operation.
A45: I | B45: Flue gas condenser not possible for oil boilers as its combustion products contain pollutants which would heavily corrode the heat exchanger surfaces if condensed.
A46: J | B46: Relevant for hot water boiler when needing to install new hot water piping instead of existing steam piping.
A48: References:
A49: 1 | B49: Danish Energy Agency, Energy Plants for Electricity and District heating generation, 2016 (updated 2025) ."44 Natural Gas DH Only"
A50: 2 | B50: Bosch Industrial, Personal correspondence & product catalogue, 2025
A51: 3 | B51: Viessmann, Personal correspondence & product catalogue, 2025
A52: 4 | B52: Vakklianainen, Esa. Steam Generation from Biomass. 2017. (Chapter 3, Boiler processes)
A53: 5 | B53: Chen, Q., Finney, K., Li, H., Zhang, X., Zhou, J., Sharifi, V., Swithenbank, J. Condensing boiler applications in the process industry. Applied Energy, 89, 30-36, 2012
A54: 6 | B54: Danstoker, Personal correspondence & product catalogue, 2025

Sheet 6.2 Boiler, biomass
A1: Technology | C1: Boiler, biomass
A2: year | C2: 2025 | D2: 2030 | E2: 2035 | F2: 2040 | G2: 2050 | H2: 2025 | I2: 2025 | J2: 2050 | K2: 2050 | L2: Note | M2: Ref
A3: est | C3: ctrl | D3: ctrl | E3: ctrl | F3: ctrl | G3: ctrl | H3: lower | I3: upper | J3: lower | K3: upper | L3: - | M3: -
A4: cat | B4: par
A5: Energy/technical data
B6: Heat generation capacity for one unit [MW] | C6: 6.5 | D6: 6.5 | E6: 6.5 | F6: 6.5 | G6: 6.5 | H6: 0.3 | I6: 50 | J6: 0.3 | K6: 50 | M6: [1, 4, 5]
B7: Total efficiency, net [%], nominel load | C7: 0.89 | D7: 0.89 | E7: 0.89 | F7: 0.89 | G7: 0.89 | H7: 0.87 | I7: 0.91 | J7: 0.87 | K7: 0.91 | L7: A, B | M7: 2
B8: Total efficiency, net [%], annual average | C8: 0.889 | D8: 0.889 | E8: 0.889 | F8: 0.889 | G8: 0.889 | H8: 0.869 | I8: 0.909 | J8: 0.869 | K8: 0.909 | L8: A, B, D | M8: 2
B9: Auxiliary electricity consumption [% of heat gen] | C9: 0.02 | D9: 0.02 | E9: 0.02 | F9: 0.02 | G9: 0.02 | H9: 0.02 | I9: 0.02 | J9: 0.02 | K9: 0.02 | M9: 1
B10: Forced outage [%] | C10: 0.03 | D10: 0.03 | E10: 0.03 | F10: 0.03 | G10: 0.03 | H10: 0.03 | I10: 0.03 | J10: 0.03 | K10: 0.03 | M10: 1
B11: Planned outage [weeks per year] | C11: 2 | D11: 2 | E11: 2 | F11: 2 | G11: 2 | H11: 1.7 | I11: 2.3 | J11: 1.5 | K11: 2.5 | M11: 1
B12: Technical lifetime [years] | C12: 25 | D12: 25 | E12: 25 | F12: 25 | G12: 25 | H12: 20 | I12: 35 | J12: 20 | K12: 35 | M12: 1
B13: Construction time [years] | C13: 1 | D13: 1 | E13: 1 | F13: 1 | G13: 1 | H13: 0.5 | I13: 1.5 | J13: 0.5 | K13: 1.5 | M13: 1
B14: Space requirement [1000 m2/MW_e] | C14: 0.2 | D14: 0.2 | E14: 0.2 | F14: 0.2 | G14: 0.2 | H14: 0.14 | I14: 0.25 | J14: 0.12 | K14: 0.27 | M14: 1
A15: Regulation ability
B16: Primary regulation (of full load, per 30 seconds) [%]
B17: Secondary regulation (of full load, per minute) [%] | C17: 0.1 | D17: 0.1 | E17: 0.1 | F17: 0.1 | G17: 0.1 | M17: 1
B18: Minimum load (of full load) [%] | C18: 0.2 | D18: 0.2 | E18: 0.2 | F18: 0.2 | G18: 0.2 | M18: 1
B19: Warm start-up time [hours] | C19: 0.25 | D19: 0.25 | E19: 0.25 | F19: 0.25 | G19: 0.25 | M19: 1
B20: Cold start-up time [hours] | C20: 0.5 | D20: 0.5 | E20: 0.5 | F20: 0.5 | G20: 0.5 | M20: 1
A21: Financial data
B22: Nominal investment (*total) [MEUR/MW] | C22: 0.87840721 | D22: 0.82891948 | E22: 0.8072686 | F22: 0.78561772 | G22: 0.74231596 | M22: 1
B23: - of which equipment [%] | C23: 0.6 | D23: 0.6 | E23: 0.6 | F23: 0.6 | G23: 0.6 | M23: 1
B24: - of which installation [%] | C24: 0.4 | D24: 0.4 | E24: 0.4 | F24: 0.4 | G24: 0.4 | M24: 1
B25: Fixed O&M [EUR/MW_y] | C25: 39500 | D25: 38700 | E25: 37900 | F25: 37100 | G25: 35600 | M25: 1
B26: Variable O&M [EUR/MWh] | C26: 1.45 | D26: 1.45 | E26: 1.45 | F26: 1.45 | G26: 1.45 | L26: C, H | M26: 1
A27: Technology-specific data
B28: Indirect investment cost [M€/MW] | C28: 0.23 | D28: 0.23 | E28: 0.23 | F28: 0.23 | G28: 0.23 | L28: K, J
B29: Technology dependent
B30: - Using wood chips, and adding flue gas condenser (after economiser) increases efficiency by [%-point] | C30: 0.25 | D30: 0.25 | E30: 0.25 | F30: 0.25 | G30: 0.25 | L30: F, E | M30: [1, 3]
B31: - Using wood pellets, and adding flue gas condenser (after economiser) increases efficiency by [%-point] | C31: 0.12 | D31: 0.12 | E31: 0.12 | F31: 0.12 | G31: 0.12 | L31: E, I | M31: [1, 3]
B32: - Hot water boiler instead of steam boiler increases efficiency by [%-point] | C32: 0.01 | D32: 0.01 | E32: 0.01 | F32: 0.01 | G32: 0.01 | L32: G
B33: - Wood pellets (instead of wood chips) reduces Variable O&M by [%] | C33: 0.5 | D33: 0.5 | E33: 0.5 | F33: 0.5 | G33: 0.5 | M33: 1
A36: Notes:
A37: A | B37: Effeciency for unit with economiser (but not flue gas condenser) installed.
A38: B | B38: Values for steam boiler (see technology-specific data for differences with hot water boiler)
A39: C | B39: Values for wood chips (see technology-specific data for differences with wood pellets)
A40: D | B40: Assuming 10 starts a year.
A41: E | B41: For condensing boilers, efficiencies above 100% are possible, since the standard efficiency calculation using the lower heating value (LHV) as denominator.
A42: F | B42: Large increase in efficiency using flue gas condensen because of large water content in wood chips.
A43: G | B43: 1 %-point higher for hot water boiler, due to assumed lower flue gas temperature
A44: H | B44: Variable O&M cost includes consumables (for FGT etc.), disposal of residues, small share of staff-cost and maintenance cost
A45: I | B45: Wood pellets have lower water content than wood chips, and therefore the advantage of using flue gas condensation is smaller.
A46: J | B46: Assumed similar to gas and oil boiler.
A47: K | B47: Relevant for hot water boiler when needing to install new hot water piping instead of existing steam piping.
A49: References:
A50: 1 | B50: Danish Energy Agency, Energy Plants for Electricity and District heating generation, 2016 (updated 2025) ." 09a Wood Chips HOP (heat-only plant), small" and "09b Wood Pellets HOP"
A51: 2 | B51: Vakklianainen, Esa. Steam Generation from Biomass. 2017. (Chapter 3, Boiler processes)
A52: 3 | B52: Chen, Q., Finney, K., Li, H., Zhang, X., Zhou, J., Sharifi, V., Swithenbank, J. Condensing boiler applications in the process industry. Applied Energy, 89, 30-36, 2012
A53: 4 | B53: Tjæreborg Industri, Referenceliste for fasbrændselsanlæg (Reference list for solid fuel plants), 2024
A54: 5 | B54: Danstoker product catalogue, 2025

Sheet 6.3 Boiler, coal
A1: Technology | C1: Boiler, coal
A2: year | C2: 2025 | D2: 2030 | E2: 2035 | F2: 2040 | G2: 2050 | H2: 2025 | I2: 2025 | J2: 2050 | K2: 2050 | L2: Note | M2: Ref
A3: est | C3: ctrl | D3: ctrl | E3: ctrl | F3: ctrl | G3: ctrl | H3: lower | I3: upper | J3: lower | K3: upper | L3: - | M3: -
A4: cat | B4: par
A5: Energy/technical data
B6: Heat generation capacity for one unit [MW] | C6: 5 | D6: 5 | E6: 5 | F6: 5 | G6: 5 | H6: 1.6 | I6: 50 | J6: 1.6 | K6: 50 | M6: [3, 4]
B7: Total efficiency, net [%], nominel load | C7: 0.9 | D7: 0.9 | E7: 0.9 | F7: 0.9 | G7: 0.9 | H7: 0.88 | I7: 0.92 | J7: 0.88 | K7: 0.92 | L7: A, B, C | M7: 2
B8: Total efficiency, net [%], annual average | C8: 0.899 | D8: 0.899 | E8: 0.899 | F8: 0.899 | G8: 0.899 | H8: 0.879 | I8: 0.919 | J8: 0.879 | K8: 0.919 | L8: A, B, C, D | M8: 2
B9: Auxiliary electricity consumption [% of heat gen] | C9: 0.02 | D9: 0.02 | E9: 0.02 | F9: 0.02 | G9: 0.02 | H9: 0.02 | I9: 0.02 | J9: 0.02 | K9: 0.02 | L9: F | M9: 1
B10: Forced outage [%] | C10: 0.03 | D10: 0.03 | E10: 0.03 | F10: 0.03 | G10: 0.03 | H10: 0.03 | I10: 0.03 | J10: 0.03 | K10: 0.03 | L10: F | M10: 1
B11: Planned outage [weeks per year] | C11: 2 | D11: 2 | E11: 2 | F11: 2 | G11: 2 | H11: 1.7 | I11: 2.3 | J11: 1.5 | K11: 2.5 | L11: F | M11: 1
B12: Technical lifetime [years] | C12: 25 | D12: 25 | E12: 25 | F12: 25 | G12: 25 | H12: 20 | I12: 35 | J12: 20 | K12: 35 | L12: E, F | M12: 1
B13: Construction time [years] | C13: 1 | D13: 1 | E13: 1 | F13: 1 | G13: 1 | H13: 0.5 | I13: 1.5 | J13: 0.5 | K13: 1.5 | L13: F | M13: 1
B14: Space requirement [1000 m2/MW_e] | C14: 0.2 | D14: 0.2 | E14: 0.2 | F14: 0.2 | G14: 0.2 | H14: 0.14 | I14: 0.25 | J14: 0.12 | K14: 0.27 | L14: F | M14: 1
A15: Regulation ability
B16: Primary regulation (of full load, per 30 seconds) [%]
B17: Secondary regulation (of full load, per minute) [%] | C17: 0.1 | D17: 0.1 | E17: 0.1 | F17: 0.1 | G17: 0.1 | L17: F | M17: 1
B18: Minimum load (of full load) [%] | C18: 0.15 | D18: 0.15 | E18: 0.15 | F18: 0.15 | G18: 0.15 | L18: E | M18: 1
B19: Warm start-up time [hours] | C19: 0.25 | D19: 0.25 | E19: 0.25 | F19: 0.25 | G19: 0.25 | L19: F | M19: 1
B20: Cold start-up time [hours] | C20: 0.5 | D20: 0.5 | E20: 0.5 | F20: 0.5 | G20: 0.5 | L20: F | M20: 1
A21: Financial data
B22: Nominal investment (*total) [MEUR/MW] | C22: 0.565 | D22: 0.545 | E22: 0.533 | F22: 0.521 | G22: 0.515 | L22: F, H | M22: 1
B23: - of which equipment [%] | C23: 0.6 | D23: 0.6 | E23: 0.6 | F23: 0.6 | G23: 0.6 | M23: 1
B24: - of which installation [%] | C24: 0.4 | D24: 0.4 | E24: 0.4 | F24: 0.4 | G24: 0.4 | M24: 1
B25: Fixed O&M [EUR/MW_y] | C25: 40000 | D25: 39500 | E25: 39000 | F25: 38500 | G25: 37500 | L25: E, F | M25: 1
B26: Variable O&M [EUR/MWh] | C26: 1.45 | D26: 1.45 | E26: 1.45 | F26: 1.45 | G26: 1.45 | L26: F | M26: 1
A27: Technology-specific data
B28: Indirect investment cost [M€/MW] | C28: 0.23 | D28: 0.23 | E28: 0.23 | F28: 0.23 | G28: 0.23 | L28: I, J
B29: Technology dependent
B30: - Hot water boiler instead of steam boiler increases efficiency by [%-point] | C30: 0.01 | D30: 0.01 | E30: 0.01 | F30: 0.01 | G30: 0.01 | L30: G
A33: Notes:
A34: A | B34: Effeciency for unit with economiser (but not flue gas condenser) installed.
A35: B | B35: Values for steam boiler (see technology-specific data for differences with hot water boiler)
A36: C | B36: Flue gas condenser not possible for coal boiler, since no water vapor is present in flue gas.
A37: D | B37: Assuming 10 starts a year.
A38: E | B38: Values estimated based on "01 Coal CHP" from ref. 1.
A39: F | B39: Values estimated based on "09b Wood Pellets HOP"/"09a Wood Chips HOP, small" from ref. 1 (since they are solid fuels, and often the same boiler can used either biomass or coal)
A40: G | B40: 1 %-point higher for hot water boiler, due to assumed lower flue gas temperature
A41: H | B41: Viegand Maagøe A/S experience
A42: I | B42: Relevant for hot water boiler when needing to install new hot water piping instead of existing steam piping.
A43: J | B43: Assumed similar to gas and oil boiler.
A45: References:
A46: 1 | B46: Danish Energy Agency, Energy Plants for Electricity and District heating generation, 2016 (updated 2025).
A47: 2 | B47: Vakklianainen, Esa. Steam Generation from Biomass. 2017. (Chapter 3, Boiler processes)
A48: 3 | B48: Tjæreborg Industri, Referenceliste for fasbrændselsanlæg (Reference list for solid fuel plants), 2024
A49: 4 | B49: Danstoker product catalogue, 2025

Sheet 7.1 Direct firing Natural Gas
A1: Technology | C1: Direct firing, Natural gas
A2: year | C2: 2025 | D2: 2030 | E2: 2035 | F2: 2040 | G2: 2050 | H2: 2025 | I2: 2025 | J2: 2050 | K2: 2050 | L2: Note | M2: Ref
A3: est | C3: ctrl | D3: ctrl | E3: ctrl | F3: ctrl | G3: ctrl | H3: lower | I3: upper | J3: lower | K3: upper | L3: - | M3: -
A4: cat | B4: par
A5: Energy/technical data
B6: Heat generation capacity for one unit [MW] | C6: 2.5 | D6: 2.5 | E6: 2.5 | F6: 2.5 | G6: 2.5 | H6: 1 | I6: 10 | J6: 1 | K6: 10 | M6: 2
B7: Total efficiency, net [%], nominel load | C7: 1 | D7: 1 | E7: 1 | F7: 1 | G7: 1 | H7: 1 | I7: 1 | J7: 1 | K7: 1 | L7: A | M7: 2
B8: Total efficiency, net [%], annual average | C8: 1 | D8: 1 | E8: 1 | F8: 1 | G8: 1 | H8: 1 | I8: 1 | J8: 1 | K8: 1 | L8: A | M8: 2
B9: Auxiliary electricity consumption [% of heat gen] | C9: 0.0025 | D9: 0.0025 | E9: 0.0025 | F9: 0.0025 | G9: 0.0025 | H9: 0.001 | I9: 0.01 | J9: 0.001 | K9: 0.01 | M9: [8, 9]
B10: Forced outage [%] | C10: 0.0025 | D10: 0.0025 | E10: 0.0025 | F10: 0.0025 | G10: 0.0025 | H10: 0 | I10: 0.005 | J10: 0 | K10: 0.005 | M10: 2
B11: Planned outage [weeks per year] | C11: 0.5 | D11: 0.5 | E11: 0.5 | F11: 0.5 | G11: 0.5 | H11: 0 | I11: 1 | J11: 0 | K11: 1 | M11: 2
B12: Technical lifetime [years] | C12: 15 | D12: 15 | E12: 15 | F12: 15 | G12: 15 | H12: 10 | I12: 20 | J12: 10 | K12: 20 | M12: 4
B13: Construction time [years] | C13: 0.01 | D13: 0.01 | E13: 0.01 | F13: 0.01 | G13: 0.01 | H13: 0.01 | I13: 0.04 | J13: 0.01 | K13: 0.04 | M13: 2
A14: Regulation Ability
B15: Minimum load [% of full load] | C15: 0.1 | D15: 0.1 | E15: 0.1 | F15: 0.1 | G15: 0.1 | M15: 6
B16: Warm start-up time [hours] | C16: 0.01 | D16: 0.01 | E16: 0.01 | F16: 0.01 | G16: 0.01 | M16: 2
B17: Cold start-up time [hours] | C17: 0.01 | D17: 0.01 | E17: 0.01 | F17: 0.01 | G17: 0.01 | M17: 2
A18: Environment
B19: SO2 [g per GJ fuel] | C19: 0.3 | D19: 0.3 | E19: 0.3 | F19: 0.3 | G19: 0.3 | M19: 1
B20: PM2.5 [g per GJ fuel] | C20: 0.1 | D20: 0.1 | E20: 0.1 | F20: 0.1 | G20: 0.1 | M20: 1
B21: NOX [g per GJ fuel] | C21: 9 | D21: 7 | E21: 7 | F21: 6 | G21: 6 | M21: 1
B22: CH4 [g per GJ fuel] | C22: 3 | D22: 2 | E22: 2 | F22: 2 | G22: 2 | M22: 1
B23: N2O [g per GJ fuel] | C23: 1 | D23: 1 | E23: 1 | F23: 1 | G23: 1 | M23: 1
A24: Financial data
B25: Nominal investment [M€/MW] | C25: 0.0176 | D25: 0.0176 | E25: 0.0176 | F25: 0.0176 | G25: 0.0176 | L25: B | M25: [4, 7]
B26: - of which equipment [%] | C26: 0.66666667 | D26: 0.66666667 | E26: 0.66666667 | F26: 0.66666667 | G26: 0.66666667 | M26: 7
B27: - of which installation [%] | C27: 0.33333333 | D27: 0.33333333 | E27: 0.33333333 | F27: 0.33333333 | G27: 0.33333333 | M27: 7
B28: Fixed O&M [€/MJ/s/year] | C28: 213 | D28: 208 | E28: 205 | F28: 202 | G28: 181 | L28: C | M28: [2, 1]
B29: Variable O&M [€/MWh] | C29: 0.117 | D29: 0.105 | E29: 0.105 | F29: 0.105 | G29: 0.105 | L29: C | M29: 1
A30: Technology-specific data
B31: Indirect investments cost [M€/MW] | C31: - | D31: - | E31: - | F31: - | G31: - | L31: E | M31: -
A34: Notes:
A35: A | B35: The efficiency of the burner is set equal to the lower heating value, the process will determine how well the flue gas is utilised, and thus the final efficiency.
A36: B | B36: Unit price is based on Miton Megatherms 2.5 MW burner, installed price assessed by Viegand Maagøe. The assessment is an experience based guess as no concrete data was retrieved.
A37: C | B37: Assumed to be equal to 10% of the boiler O&M from [1].
A38: D | B38: The cost of auxiliary electricity consumption is calculated using the following electricity prices in €/MWh: 2020: 73, 2030: 75, 2040: 76, 2050: 76. Includes transport tarif
A39: E | B39: The indirect costs will be too strong a function of the process to put into a single value across all industries.
A41: References:
A42: 1 | B42: Danish Energy Agency, Technology Data Generation of Electricity and District Heating, August 2016 - Updated November 2019
A43: 2 | B43: Viegand Maagøe, Direct Firing, 2018
A44: 3 | B44: Danish Energy Agency, Forudsætninger for samfundsøkonomiske analyser på energiområdet, 2016
A45: 4 | B45: Milton Megatherm, Correspondance 2019
A46: 5 | B46: IOGP, The potential for CCS and CCU in Europe, REPORT TO THE THIRTY SECOND MEETING OF THE EUROPEAN GAS REGULATORY FORUM 5-6 JUNE 2019
A47: 6 | B47: Eclipse, Vortometric Burner Series Datasheet 128-3, 20/2/2015
A48: 7 | B48: Viegand Maagøe assessment, 2019
A49: 8 | B49: Eclipse, Eclipse AirHeat Burners Datasheet 115-11, 30/9/2010
A50: 9 | B50: Eclipse, Eclipse RatioAir Burners Datasheet 135, 21/10/2010

Sheet 7.2 Direct firing Solid Fuels
A1: Technology | C1: Direct firing, Solid fuels
A2: year | C2: 2025 | D2: 2030 | E2: 2035 | F2: 2040 | G2: 2050 | H2: 2025 | I2: 2025 | J2: 2050 | K2: 2050 | L2: Note | M2: Ref
A3: est | C3: ctrl | D3: ctrl | E3: ctrl | F3: ctrl | G3: ctrl | H3: lower | I3: upper | J3: lower | K3: upper | L3: - | M3: -
A4: cat | B4: par
A5: Energy/technical data
B6: Heat generation capacity for one unit [MW] | C6: 10 | D6: 10 | E6: 10 | F6: 10 | G6: 10 | H6: 10 | I6: 10 | J6: 10 | K6: 10
B7: Total efficiency, net [%], nominel load | C7: 1 | D7: 1 | E7: 1 | F7: 1 | G7: 1 | H7: 1 | I7: 1 | J7: 1 | K7: 1 | L7: A | M7: 2
B8: Total efficiency, net [%], annual average | C8: 1 | D8: 1 | E8: 1 | F8: 1 | G8: 1 | H8: 1 | I8: 1 | J8: 1 | K8: 1 | L8: A | M8: 2
B9: Auxiliary electricity consumption [% of heat gen] | C9: 0.0025 | D9: 0.0025 | E9: 0.0025 | F9: 0.0025 | G9: 0.0025 | H9: 0.001 | I9: 0.01 | J9: 0.001 | K9: 0.01 | L9: B | M9: [8, 9]
B10: Forced outage [%] | C10: 0.0025 | D10: 0.0025 | E10: 0.0025 | F10: 0.0025 | G10: 0.0025 | H10: 0 | I10: 0.005 | J10: 0 | K10: 0.005 | M10: 2
B11: Planned outage [weeks per year] | C11: 3.5 | D11: 3.5 | E11: 3.5 | F11: 3.5 | G11: 3.5 | H11: 2 | I11: 5 | J11: 2 | K11: 5 | M11: 4
B12: Technical lifetime [years] | C12: 15 | D12: 15 | E12: 15 | F12: 15 | G12: 15 | H12: 10 | I12: 20 | J12: 10 | K12: 20 | M12: [2, 4]
B13: Construction time [years] | C13: 0.01 | D13: 0.01 | E13: 0.01 | F13: 0.01 | G13: 0.01 | H13: 0.001 | I13: 0.015 | J13: 0.001 | K13: 0.015 | L13: I | M13: [2, 4]
A14: Regulation Ability
B15: Minimum load [% of full load] | C15: 0.1 | D15: 0.1 | E15: 0.1 | F15: 0.1 | G15: 0.1 | M15: 6
B16: Warm start-up time [hours] | C16: 0.01 | D16: 0.01 | E16: 0.01 | F16: 0.01 | G16: 0.01 | L16: F | M16: 2
B17: Cold start-up time [hours] | C17: 0.01 | D17: 0.01 | E17: 0.01 | F17: 0.01 | G17: 0.01 | L17: F | M17: 2
A18: Environment
B19: SO2 [g per GJ fuel] | L19: D
B20: PM2.5 [g per GJ fuel] | L20: D
B21: NOX [g per GJ fuel] | L21: D
B22: CH4 [g per GJ fuel] | L22: D
B23: N2O [g per GJ fuel] | L23: D
A24: Financial data
B25: Nominal investment [M€/MW] | C25: 0.258 | D25: 0.258 | E25: 0.258 | F25: 0.258 | G25: 0.258 | L25: E, G, H | M25: [4, 7]
B26: - of which equipment [%] | C26: 0.66666667 | D26: 0.66666667 | E26: 0.66666667 | F26: 0.66666667 | G26: 0.66666667 | M26: 7
B27: - of which installation [%] | C27: 0.33333333 | D27: 0.33333333 | E27: 0.33333333 | F27: 0.33333333 | G27: 0.33333333 | M27: 7
B28: Fixed O&M [€/MJ/s/year] | C28: 3986 | D28: 3869 | E28: 3810 | F28: 3751 | G28: 3634 | L28: C | M28: [2, 1]
B29: Variable O&M [€/MWh] | C29: 0.167 | D29: 0.167 | E29: 0.167 | F29: 0.167 | G29: 0.167 | L29: C | M29: [2, 7]
A30: Technology-specific data
B31: Indirect investments cost [M€/MW] | C31: - | D31: - | E31: - | F31: - | G31: - | L31: J
A34: Notes:
A35: A | B35: The efficiency of the burner is set equal to the lower heating value, the process will determine how well the flue gas is utilised, and thus the final efficiency.
A36: B | B36: Auxilliary consumption based on gas burner as the fan power is comparable. Electricity for fuel feed systems are not included.
A37: C | B37: Assumed to be equal to 10% of the coal boiler O&M from [1]. With gaseous or liquid fuels the O&M will be lower.
A38: D | B38: Depends on the solid fuel mix used
A39: E | B39: Unit price from FLSmidth, installed price and auxilliary equipment assessed by Viegand Maagøe. The assessment is an experience based guess as no concrete data was retrieved.
A40: F | B40: The burner itself can start up quickly. However, in e.g. Cement industry the process equipment will limit the startup time to between 8 (warm) and 72 (cold) hours.
A41: G | B41: Capacity increase in multifuel burners comes with an attractive economy of scale. Going up 10 times in size will correspond toa 150% increase in pricing .
A42: H | B42: Auxilliary systems for solid fuels has been included, these correspond to a large part of the investment and will be a function of the chosen fuel.
A43: I | B43: Corresponds to a burner change, establishing a feed system has a longer construction period.
A44: J | B44: The indirect costs will be too strong a function of the process to put into a single value across all industries.
A46: References:
A47: 1 | B47: Danish Energy Agency, Technology Data Generation of Electricity and District Heating, August 2016 - Updated November 2019
A48: 2 | B48: Viegand Maagøe, Direct Firing, 2018
A49: 3 | B49: Danish Energy Agency, Forudsætninger for samfundsøkonomiske analyser på energiområdet, 2016
A50: 4 | B50: FLSmidth - Burner & PLM for HOTDISC, Correspondance 2019
A51: 5 | B51: IOGP, The potential for CCS and CCU in Europe, REPORT TO THE THIRTY SECOND MEETING OF THE EUROPEAN GAS REGULATORY FORUM 5-6 JUNE 2019
A52: 6 | B52: FCT International Burners, Correspondance 2019.
A53: 7 | B53: Viegand Maagøe assessment, 2019
A54: 8 | B54: Eclipse, Eclipse AirHeat Burners Datasheet 115-11, 30/9/2010
A55: 9 | B55: Eclipse, Eclipse RatioAir Burners Datasheet 135, 21/10/2010

Sheet 7.3 Direct electric firing
A1: Technology | C1: Direct electric heating
A2: year | C2: 2025 | D2: 2030 | E2: 2035 | F2: 2040 | G2: 2050 | H2: 2025 | I2: 2025 | J2: 2050 | K2: 2050 | L2: Note | M2: Ref
A3: est | C3: ctrl | D3: ctrl | E3: ctrl | F3: ctrl | G3: ctrl | H3: lower | I3: upper | J3: lower | K3: upper | L3: - | M3: -
A4: cat | B4: par
A5: Energy/technical data
B6: Heat generation capacity for one unit [MW] | C6: 5 | D6: 5 | E6: 5 | F6: 5 | G6: 5 | H6: 1 | I6: 10 | J6: 1 | K6: 10 | M6: [1, 2]
B7: Total efficiency, net [%], nominel load | C7: 1 | D7: 1 | E7: 1 | F7: 1 | G7: 1 | H7: 1 | I7: 1 | J7: 1 | K7: 1 | L7: A | M7: [3, 4]
B8: Total efficiency, net [%], annual average | C8: 1 | D8: 1 | E8: 1 | F8: 1 | G8: 1 | H8: 1 | I8: 1 | J8: 1 | K8: 1 | L8: A | M8: [3, 4]
B9: Auxiliary electricity consumption [% of heat gen] | C9: 0.0025 | D9: 0.0025 | E9: 0.0025 | F9: 0.0025 | G9: 0.0025 | H9: 0.001 | I9: 0.01 | J9: 0.001 | K9: 0.01 | L9: B | M9: [6, 7]
B10: Forced outage [days] | C10: 0 | D10: 0 | E10: 0 | F10: 0 | G10: 0 | H10: 0 | I10: 0.5 | J10: 0 | K10: 0.5 | L10: C | M10: 1
B11: Planned outage [weeks per year] | C11: 0 | D11: 0 | E11: 0 | F11: 0 | G11: 0 | H11: 0 | I11: 1 | J11: 0 | K11: 1 | L11: C | M11: 1
B12: Technical lifetime [years] | C12: 20 | D12: 20 | E12: 20 | F12: 20 | G12: 20 | M12: 8
B13: Construction time [years] | C13: 0.04 | D13: 0.04 | E13: 0.04 | F13: 0.04 | G13: 0.04 | M13: 1
B14: Space requirement [1000 m2/MW_e] | C14: =(1/80)/1000*1000 -> 0.0125 | D14: =(1/200)/1000*1000 -> 0.005 | E14: =(1/1000)/1000*1000 -> 0.001 | F14: =(1/1000)/1000*1000 -> 0.001 | G14: =(1/1000)/1000*1000 -> 0.001 | M14: 5
A15: Regulation ability
B16: Primary regulation (of full load, per 30 seconds) [%] | C16: 1 | D16: 1 | E16: 1 | F16: 1 | G16: 1 | L16: G | M16: 11
B17: Secondary regulation (of full load, per minute) [%] | C17: 1 | D17: 1 | E17: 1 | F17: 1 | G17: 1 | L17: G | M17: 11
B18: Minimum load [% of full load] | C18: 0.15 | D18: 0.15 | E18: 0.15 | F18: 0.15 | G18: 0.15 | L18: D | M18: 8
B19: Warm start-up time [hours] | C19: 0.01 | D19: 0.01 | E19: 0.01 | F19: 0.01 | G19: 0.01 | M19: [5, 9]
B20: Cold start-up time [hours] | C20: 0.01 | D20: 0.01 | E20: 0.01 | F20: 0.01 | G20: 0.01 | M20: [5, 9]
A21: Financial data
B22: Nominal investment (*total) [MEUR/MW] , from last update in 2019 | C22: 0.07 | D22: 0.07 | E22: 0.07 | F22: 0.07 | G22: 0.07 | L22: E, H | M22: [9, 10]
B23: - of which equipment [%] | C23: 0.66666667 | D23: 0.66666667 | E23: 0.66666667 | F23: 0.66666667 | G23: 0.66666667 | M23: 9
B24: - of which installation [%] | C24: 0.33333333 | D24: 0.33333333 | E24: 0.33333333 | F24: 0.33333333 | G24: 0.33333333 | M24: 9
B25: Fixed O&M [EUR/MW_y] | C25: 0 | D25: 0 | E25: 0 | F25: 0 | G25: 0 | L25: C | M25: 5
B26: Variable O&M [EUR/MWh] | C26: 0.235 | D26: 0.235 | E26: 0.235 | F26: 0.235 | G26: 0.235 | L26: C
A27: Technology-specific data
B28: Indirect investments cost [M€ per MW] | C28: - | D28: - | E28: - | F28: - | G28: - | L28: F
B29: Non energy gains [M€ per MW] | C29: - | D29: - | E29: - | F29: - | G29: - | L29: F
B30: Startup cost [€/MW/startup] | C30: - | D30: - | E30: - | F30: - | G30: - | L30: F
B31: Temperature heat supply, maximum [°C] | C31: 1800 | D31: 2000 | E31: 2000 | F31: 2000 | G31: 2000 | M31: [4, 5]
A34: Notes:
A35: A | B35: Transformer electricity losses are not included, and the efficiency will thus be 100%.
A36: B | B36: Auxilliary consumption estimation based on conventional industrial systems like gas burner/boilers as the fan power is comparable.
A37: C | B37: Units are composed of multiple heating elements, each unit is installed with backup elements that can be enabled if some of the elements fail, resulting in minimal downtime and O&M during the lifetime of the equipment.
A38: D | B38: The regulation is dependant on the flow conditions and the subsequent surface temperature, the chosen value is an average.
A39: E | B39: Unit price from San Electro Heat, installed price assessed by Viegand Maagøe. The assessment is an experience based guess as no concrete data was retrieved.
A40: F | B40: The indirect costs will be too strong a function of the process to put into a single value across all industries. This includes site updgrades to facilitate the installation of direct firing systems.
A41: G | B41: The electric heating element is able to adjust capacity almost instantly. The surrounding process equipment will be the limiting factor.
A42: H | B42: The cost has been corrected for inflation.
A44: References:
A45: 1 | B45: SAN Electro Heat A/S , Correspondance 2019
A46: 2 | B46: DTU, "Electrification of processes and technologies for Danish Industry: Elforsk project 350-038", 2021
A47: 3 | B47: Viegand Maagøe, Direct Firing, 2018
A48: 4 | B48: Renewable Thermal Collaborative, "Electrification Action Plan", 2024
A49: 5 | B49: Fraunhofer ISI, "Direct electrification of industrial process heat. An assessment of technologies, potentials and future prospects for the EU. Study on behalf of Agora Industry", 2024
A50: 6 | B50: Eclipse, Eclipse AirHeat Burners Datasheet 115-11, 30/9/2010
A51: 7 | B51: Eclipse, Eclipse RatioAir Burners Datasheet 135, 21/10/2010
A52: 8 | B52: Ashabi et al., "Assessing power-to-heat technologies for industrial electrification: A multi-criteria decision analysis approach", 2025
A53: 9 | B53: TNO, Technology factsheet Electric Industrial Boiler, 2018
A54: 10 | B54: Viegand Maagøe assessment, 2019
A55: 11 | B55: Energy Efficiency and Conservation Authority - New Zealand government, "Electrode and ElectricResistance Steam Generatorsand Hot Water Heaters for low carbon process heating", 2019

Sheet Combustion Efficiency
A1: Combustion Efficiency Without Waste Heat Recovery
A2: Low-Temp Data | B2: Efficiency | C2: Source | D2: Ratio Relative to Natural Gas
A3: Coal-fired boiler or furnace (<500 °C) | B3: 0.8 | C3: 25 | D3: =B3/$B$5 -> 0.86956522
A4: Petroleum-fired boiler or furnace (<500 °C) | B4: 0.88 | C4: 8 | D4: =B4/$B$5 -> 0.95652174
A5: Natural gas-fired boiler or furnace (<500 °C) | B5: 0.92 | C5: 25 | D5: =B5/$B$5 -> 1
A7: DOE Temperature vs. Efficiency Curve
A8: Source: 23
A35: We select a reference temperature to represent each temperature band in this study. We pick temperatures that line up with one of the
A36: 200-F increment lines in the DOE figure above and that are close to the center of each temperature band. (The temperature bands are
A37: defined in Celsius.)
A39: Then we choose the value on the 10% excess air curve from the DOE figure above. We use the 10% curve because
A40: DOE indicates: "Most high temperature direct-fired furnaces, radiant tubes, and boilers operate with about 10% to 20% excess combustion air at high fire to prevent the formation of dangerous carbon monoxide and soot deposits on heat transfer surfaces and inside radiant tubes."
A42: Temperature band from this study | B42: Reference temp. (F) | C42: Reference temp (C) | D42: Efficiency from DOE Curve | E42: Note
A43: <100 C | B43: 200 | C43: 93 | D43: 0.85 | E43: Extrapolated from DOE efficiency curve, which does not go lower than 300 F
A44: 100-200 C | B44: 300 | C44: 149 | D44: 0.83
A45: 200-500 C | B45: 600 | C45: 315 | D45: 0.75
A46: 500-1000 C | B46: 1400 | C46: 760 | D46: 0.57
A47: 1000-1800 C | B47: 2600 | C47: 1426 | D47: 0.23
A49: Fuel Type Adjustments
A50: Temperature band from this study | B50: Coal efficiency | C50: Petroleum efficiency | D50: NG efficiency
A51: <100 °C | B51: =D43*$D$3 -> 0.73913043 | C51: =D43*$D$4 -> 0.81304348 | D51: =D43 -> 0.85
A52: 100-200 °C | B52: =D44*$D$3 -> 0.72173913 | C52: =D44*$D$4 -> 0.79391304 | D52: =D44 -> 0.83
A53: 200-500 °C | B53: =D45*$D$3 -> 0.65217391 | C53: =D45*$D$4 -> 0.7173913 | D53: =D45 -> 0.75
A54: 500-1000 °C | B54: =D46*$D$3 -> 0.49565217 | C54: =D46*$D$4 -> 0.54521739 | D54: =D46 -> 0.57
A55: 1000-1800 °C | B55: =D47*$D$3 -> 0.2 | C55: =D47*$D$4 -> 0.22 | D55: =D47 -> 0.23
A57: Combustion Efficiency With Waste Heat Recovery
A58: Efficiency Curve for Equipment with Waste Heat Recovery
A59: Source: 26
A80: The ɛ = 0 curve roughly corresponds to the 10% excess air curve on the DOE graph above. On this graphs, the ɛ = 0.4 curve, ɛ = 0.6 curve,
A81: and ɛ = 0.8 curve show the efficiency of industrial gas-burning equipment using different waste heat recovery technologies.
A83: To estimate the efficiency of gas combustion equipment retrofitted with waste heat recovery, we select the value on the ɛ = 0.4 curve that
A84: corresponds with the reference temperature for each temperature band.
A85: We use the same reference temperatures as chosen for the DOE graph above for consistency, which is why the reference temps are not round numbers.
A87: Graph Scaling Factors | B87: Value | C87: Pixels (mesured)
A88: Degrees Celsius (X-axis) | B88: 1000 | C88: 1016
A89: 100% efficiency (Y-axis) | B89: 1 | C89: 847.2
A91: Temperature band from this study | B91: Reference temp. (°C) | C91: Temp. (pixels, calculated) | D91: Corresponding efficiency (pixels, measured) | E91: Corresponding efficiency from ɛ = 0.4 curve (%)
A92: <100 °C | B92: =C43 -> 93 | C92: =B92*($C$88/$B$88) -> 94.488 | D92: 821.5 | E92: =D92*($B$89/$C$89) -> 0.96966478
A93: 100-200 °C | B93: =C44 -> 149 | C93: =B93*($C$88/$B$88) -> 151.384 | D93: 807.1 | E93: =D93*($B$89/$C$89) -> 0.95266761
A94: 200-500 °C | B94: =C45 -> 315 | C94: =B94*($C$88/$B$88) -> 320.04 | D94: 765.8 | E94: =D94*($B$89/$C$89) -> 0.90391879
A95: 500-1000 °C | B95: =C46 -> 760 | C95: =B95*($C$88/$B$88) -> 772.16 | D95: 647.9 | E95: =D95*($B$89/$C$89) -> 0.76475449
A96: 1000-1800 °C | B96: =C47 -> 1426 | C96: =B96*($C$88/$B$88) -> 1448.816 | D96: 450.8 | E96: =D96*($B$89/$C$89) -> 0.53210576
A98: Fuel Type Adjustments
A99: Temperature band from this study | B99: Coal efficiency | C99: Petroleum efficiency | D99: NG efficiency
A100: <100 °C | B100: =E92*$D$3 -> 0.84318676 | C100: =E92*$D$4 -> 0.92750544 | D100: =E92 -> 0.96966478
A101: 100-200 °C | B101: =E93*$D$3 -> 0.82840662 | C101: =E93*$D$4 -> 0.91124728 | D101: =E93 -> 0.95266761
A102: 200-500 °C | B102: =E94*$D$3 -> 0.78601634 | C102: =E94*$D$4 -> 0.86461797 | D102: =E94 -> 0.90391879
A103: 500-1000 °C | B103: =E95*$D$3 -> 0.6650039 | C103: =E95*$D$4 -> 0.73150429 | D103: =E95 -> 0.76475449
A104: 1000-1800 °C | B104: =E96*$D$3 -> 0.46270066 | C104: =E96*$D$4 -> 0.50897073 | D104: =E96 -> 0.53210576
A111: The ε = 0 curve roughly corresponds to the 10% excess air curve on the DOE graph above. On these curves, ε is the fraction of available waste heat
A112: recovered. The Mickey/Thermal Processing burner-efficiency curves distinguish burner-integral (UNIT-level) recovery from system-level recovery:
A113: • ε = 0.6 = Recuperative burners (burner-integral WHR — this file's baseline with-recovery class)
A114: • ε = 0.8 = Regenerative burners (burner-integral WHR — established practice for glass furnaces, steel stoves/reheat, other >500 °C furnaces)
A115: • ε = 0.4 = Central heat exchangers / fired-heater air preheaters = SYSTEM WHR — EXCLUDED from this unit-equipment file.
A116: We take the with-recovery efficiency from the ε = 0.6 and ε = 0.8 burner curves at each band's reference temperature (rounded to nearest 10).
A119: Temperature band from this study | B119: Reference temp. (°C) | C119: Eff. from ε = 0.6 curve (recuperative) | D119: Eff. from ε = 0.8 curve (regenerative)
A120: <100 °C | B120: 90 | C120: 0.9743 | D120: 0.9855
A121: 100-200 °C | B121: 150 | C121: 0.961 | D121: 0.976
A122: 200-500 °C | B122: 350 | C122: 0.9158 | D122: 0.9441
A123: 500-1000 °C | B123: 750 | C123: 0.8222 | D123: 0.8789
A124: 1000-1800 °C | B124: 1500 | C124: 0.6354 | D124: 0.752
A126: Fuel Type Adjustments
A127: Temperature band from this study | B127: Coal efficiency | C127: Petroleum efficiency | D127: NG efficiency
A128: <100 °C | B128: 0.88 | C128: 0.92 | D128: 0.99 | E128: Technology-matched (NG=condensing 99%, oil=condensing 92%, coal=economizer 88%); recuperative burners not the archetype <200 °C
A129: 100-200 °C | B129: 0.88 | C129: 0.92 | D129: 0.99 | E129: Technology-matched (NG=condensing 99%, oil=condensing 92%, coal=economizer 88%); recuperative burners not the archetype <200 °C
A130: 200-500 °C | B130: 0.79634783 | C130: 0.87598261 | D130: 0.9158
A131: 500-1000 °C | B131: 0.76426087 | C131: 0.84068696 | D131: 0.8789 | E131: ε = 0.8 regenerative basis (option c): established practice ≥500 °C — steel stoves/reheat furnaces
A132: 1000-1800 °C | B132: 0.65391304 | C132: 0.71930435 | D132: 0.752 | E132: ε = 0.8 regenerative basis (option c): established practice — glass furnaces, high-temp reheat
A134: Blended Efficiency (WHR penetration weighted)
A135: Temperature band from this study | B135: Coal efficiency | C135: Petroleum efficiency | D135: NG efficiency | E135: WHR penetration
A136: <100 °C | B136: 0.88 | C136: 0.92 | D136: 0.99 | E136: 1
A137: 100-200 °C | B137: 0.88 | C137: 0.92 | D137: 0.99 | E137: 1
A138: 200-500 °C | B138: 0.79634783 | C138: 0.87598261 | D138: 0.9158 | E138: 1
A139: 500-1000 °C | B139: 0.76426087 | C139: 0.84068696 | D139: 0.8789 | E139: 1
A140: 1000-1800 °C | B140: 0.65391304 | C140: 0.71930435 | D140: 0.752 | E140: 1
A142: Why WHR Penetration = 100% and ε-Class Basis (Best-Possible File)
A143: This file represents best-achievable efficiency, so burner-integral (unit-WHR) recovery is assumed universal (100% penetration in every band). The
A144: with-recovery basis is technology-matched: condensing boiler (~99%) for the two <200 °C bands (recuperative burners are not the right archetype there), ε=0.6 recuperative for 200-500 °C, ε=0.8 regenerative for the two >500 °C bands (glass, steel stoves/reheat). ε=0.4 (central HX / air preheat) = SYSTEM WHR, excluded. See table below.
A147: Best-Possible Factor Table — ε-Class Options + Technology-Matched Curve for the 100%-Penetration Basis
A148: Factors are NG-basis energy intensities (1 / efficiency). The model is wired to Option (d) technology-matched: condensing boiler <200 °C, ε=0.6 recuperative 200-500 °C, ε=0.8 regenerative >500 °C — each band uses the burner/boiler archetype actually deployed there (see About).
A150: Temperature band | B150: Ref temp (°C) | C150: (a) ε=0.6 universal | D150: (b) ε=0.8 universal | E150: (c) band/industry-specific | G150: (d) technology-matched (LIVE)
A151: <100 °C | B151: 90 | C151: 1.0263779 | D151: 1.0147133 | E151: 1.0263779 | F151: ε=0.6 (regenerative not established <500 °C) | G151: 1.010101
A152: 100-200 °C | B152: 150 | C152: 1.0405827 | D152: 1.0245902 | E152: 1.0405827 | F152: ε=0.6 | G152: 1.010101
A153: 200-500 °C | B153: 350 | C153: 1.0919415 | D153: 1.0592098 | E153: 1.0919415 | F153: ε=0.6 | G153: 1.0919415
A154: 500-1000 °C | B154: 750 | C154: 1.2162491 | D154: 1.1377859 | E154: 1.1377859 | F154: ε=0.8 (regenerative established >500 °C: steel stoves/reheat) | G154: 1.1377859
A155: 1000-1800 °C | B155: 1500 | C155: 1.5738118 | D155: 1.3297872 | E155: 1.3297872 | F155: ε=0.8 (regenerative established: glass furnaces, high-temp reheat) | G155: 1.3297872

Sheet Combustion BAU Trajectory
A1: Combustion Heat-Band BAU Efficiency Trajectory (WHR penetration sweep)
A2: Sweeps BAU efficiency from the start-year installed WHR mix toward the best-possible ceiling. With-recovery basis = ε=0.6 recuperative burner + ε=0.8 regenerative credit on the glass share of the two >500°C bands. ε=0.4 (system WHR) excluded. See About.
A4: 1. Band assumptions (installed-mix basis)
A5: Temperature band | B5: Without-WHR eff (NG) | C5: ε=0.6 eff | D5: ε=0.8 eff | E5: Glass share of band | F5: With-WHR blended eff | G5: Start-yr pen (2021) | H5: Ceiling eff (best-possible)
A6: <100 °C | B6: ='Combustion Efficiency'!D51 -> 0.85 | C6: ='Combustion Efficiency'!C120 -> 0.9743 | D6: ='Combustion Efficiency'!D120 -> 0.9855 | E6: 0 | F6: =C6*(1-E6)+D6*E6 -> 0.9743 | G6: 0 | H6: =1/'Combustion Efficiency'!G151 -> 0.99
A7: 100-200 °C | B7: ='Combustion Efficiency'!D52 -> 0.83 | C7: ='Combustion Efficiency'!C121 -> 0.961 | D7: ='Combustion Efficiency'!D121 -> 0.976 | E7: 0 | F7: =C7*(1-E7)+D7*E7 -> 0.961 | G7: 0 | H7: =1/'Combustion Efficiency'!G152 -> 0.99
A8: 200-500 °C | B8: ='Combustion Efficiency'!D53 -> 0.75 | C8: ='Combustion Efficiency'!C122 -> 0.9158 | D8: ='Combustion Efficiency'!D122 -> 0.9441 | E8: 0 | F8: =C8*(1-E8)+D8*E8 -> 0.9158 | G8: 0.05 | H8: =1/'Combustion Efficiency'!G153 -> 0.9158
A9: 500-1000 °C | B9: ='Combustion Efficiency'!D54 -> 0.57 | C9: ='Combustion Efficiency'!C123 -> 0.8222 | D9: ='Combustion Efficiency'!D123 -> 0.8789 | E9: ='indst heat consumption'!L15 -> 0.011795949 | F9: =C9*(1-E9)+D9*E9 -> 0.82286883 | G9: 0.174 | H9: =1/'Combustion Efficiency'!G154 -> 0.8789
A10: >1000 °C | B10: ='Combustion Efficiency'!D55 -> 0.23 | C10: ='Combustion Efficiency'!C124 -> 0.6354 | D10: ='Combustion Efficiency'!D124 -> 0.752 | E10: ='indst heat consumption'!M15 -> 0.11556765 | F10: =C10*(1-E10)+D10*E10 -> 0.64887519 | G10: 0.587 | H10: =1/'Combustion Efficiency'!G155 -> 0.752
A12: 2. Kermeli-implied 2050 penetration target per band
A13: Per-industry burner WHR adoption: 2015 diffusion + scalar (G13) × Kermeli 2050 'Implementation' additional × remaining headroom (1−pen), capped 100%; aggregated to bands via industry band-heat shares on 'indst heat consumption'.
A14: Industry (burner-integral WHR) | B14: 2015 diffusion | C14: Kermeli 2050 additional | D14: 2050 level (capped) | F14: Residual equipment-native improvement (ALL bands, %/yr): | G14: 0.002 | I14: BAU share of Kermeli gap closure → | J14: 0.3
A15: Secondary aluminum | B15: 0.3 | C15: ='Kermeli Data'!E12 -> 0.5 | D15: =MIN(1,B15+$J$14*C15*(1-B15)) -> 0.405
A16: Aluminum foundries | B16: 0.5 | C16: ='Kermeli Data'!E15 -> 0.3 | D16: =MIN(1,B16+$J$14*C16*(1-B16)) -> 0.545
A17: Iron & steel (stoves/coke + reheat blend) | B17: 0.8 | C17: ='Kermeli Data'!E34 -> 0.6 | D17: =MIN(1,B17+$J$14*C17*(1-B17)) -> 0.836
A18: Glass | B18: 0.9 | C18: ='Kermeli Data'!E42 -> 0.25 | D18: =MIN(1,B18+$J$14*C18*(1-B18)) -> 0.9075
A19: Cement | B19: 0.49 | C19: 0 | D19: =MIN(1,B19+$J$14*C19*(1-B19)) -> 0.49
A20: Refinery/chemical (Other) | B20: 0.1 | C20: 0 | D20: =MIN(1,B20+$J$14*C20*(1-B20)) -> 0.1
A21: Band 2050 target (start-year pen + mapping-implied 2015→2050 delta)
A22: Targets = start-year pen (G6:G10) + Σ [industry band-heat share × (2050 − 2015 mapped adoption level)] over ALL industries — full-coverage mapping in section 4 below (delta method keeps the basis consistent with the given start pens). Bands <200 °C: burner-integral WHR not applicable → target = start pen.
A23: Weights = anchor-industry share of that band's heat (indst heat consumption I:M rows 15,16,17). Bands <200°C have no burner-integral WHR industries → target 0.
A24: Band | B24: 2050 target pen
A25: <100 °C | B25: 0
A26: 100-200 °C | B26: 0
A27: 200-500 °C | B27: {=MIN(1,$G$8+SUMPRODUCT($C$56:$C$80-$B$56:$B$80,D56:D80)/SUM(D56:D80))} -> 0.052267471
A28: 500-1000 °C | B28: {=MIN(1,$G$9+SUMPRODUCT($C$56:$C$80-$B$56:$B$80,E56:E80)/SUM(E56:E80))} -> 0.17717876
A29: >1000 °C | B29: {=MIN(1,$G$10+SUMPRODUCT($C$56:$C$80-$B$56:$B$80,F56:F80)/SUM(F56:F80))} -> 0.60672754
A32: 3. Year grid: penetration pen(t), band efficiency, and YoY improvement rate
A33: Year | B33: 2021 | C33: 2022 | D33: 2023 | E33: 2024 | F33: 2025 | G33: 2026 | H33: 2027 | I33: 2028 | J33: 2029 | K33: 2030 | L33: 2031 | M33: 2032 | N33: 2033 | O33: 2034 | P33: 2035 | Q33: 2036 | R33: 2037 | S33: 2038 | T33: 2039 | U33: 2040 | V33: 2041 | W33: 2042 | X33: 2043 | Y33: 2044 | Z33: 2045 | AA33: 2046 | AB33: 2047 | AC33: 2048 | AD33: 2049 | AE33: 2050
A34: Penetration pen(t) — share of band fuel with burner-integral WHR
A35: <100 °C pen | B35: =$G$6 -> 0 | C35: =MIN(1,$B35+($B$25-$B35)*(C$33-$B$33)/($AE$33-$B$33)) -> 0 | D35: =MIN(1,$B35+($B$25-$B35)*(D$33-$B$33)/($AE$33-$B$33)) -> 0 | E35: =MIN(1,$B35+($B$25-$B35)*(E$33-$B$33)/($AE$33-$B$33)) -> 0 | F35: =MIN(1,$B35+($B$25-$B35)*(F$33-$B$33)/($AE$33-$B$33)) -> 0 | G35: =MIN(1,$B35+($B$25-$B35)*(G$33-$B$33)/($AE$33-$B$33)) -> 0 | H35: =MIN(1,$B35+($B$25-$B35)*(H$33-$B$33)/($AE$33-$B$33)) -> 0 | I35: =MIN(1,$B35+($B$25-$B35)*(I$33-$B$33)/($AE$33-$B$33)) -> 0 | J35: =MIN(1,$B35+($B$25-$B35)*(J$33-$B$33)/($AE$33-$B$33)) -> 0 | ... AE35: =MIN(1,$B35+($B$25-$B35)*(AE$33-$B$33)/($AE$33-$B$33)) -> 0
A36: 100-200 °C pen | B36: =$G$7 -> 0 | C36: =MIN(1,$B36+($B$26-$B36)*(C$33-$B$33)/($AE$33-$B$33)) -> 0 | D36: =MIN(1,$B36+($B$26-$B36)*(D$33-$B$33)/($AE$33-$B$33)) -> 0 | E36: =MIN(1,$B36+($B$26-$B36)*(E$33-$B$33)/($AE$33-$B$33)) -> 0 | F36: =MIN(1,$B36+($B$26-$B36)*(F$33-$B$33)/($AE$33-$B$33)) -> 0 | G36: =MIN(1,$B36+($B$26-$B36)*(G$33-$B$33)/($AE$33-$B$33)) -> 0 | H36: =MIN(1,$B36+($B$26-$B36)*(H$33-$B$33)/($AE$33-$B$33)) -> 0 | I36: =MIN(1,$B36+($B$26-$B36)*(I$33-$B$33)/($AE$33-$B$33)) -> 0 | J36: =MIN(1,$B36+($B$26-$B36)*(J$33-$B$33)/($AE$33-$B$33)) -> 0 | ... AE36: =MIN(1,$B36+($B$26-$B36)*(AE$33-$B$33)/($AE$33-$B$33)) -> 0
A37: 200-500 °C pen | B37: =$G$8 -> 0.05 | C37: =MIN(1,$B37+($B$27-$B37)*(C$33-$B$33)/($AE$33-$B$33)) -> 0.050078189 | D37: =MIN(1,$B37+($B$27-$B37)*(D$33-$B$33)/($AE$33-$B$33)) -> 0.050156377 | E37: =MIN(1,$B37+($B$27-$B37)*(E$33-$B$33)/($AE$33-$B$33)) -> 0.050234566 | F37: =MIN(1,$B37+($B$27-$B37)*(F$33-$B$33)/($AE$33-$B$33)) -> 0.050312755 | G37: =MIN(1,$B37+($B$27-$B37)*(G$33-$B$33)/($AE$33-$B$33)) -> 0.050390943 | H37: =MIN(1,$B37+($B$27-$B37)*(H$33-$B$33)/($AE$33-$B$33)) -> 0.050469132 | I37: =MIN(1,$B37+($B$27-$B37)*(I$33-$B$33)/($AE$33-$B$33)) -> 0.050547321 | J37: =MIN(1,$B37+($B$27-$B37)*(J$33-$B$33)/($AE$33-$B$33)) -> 0.050625509 | ... AE37: =MIN(1,$B37+($B$27-$B37)*(AE$33-$B$33)/($AE$33-$B$33)) -> 0.052267471
A38: 500-1000 °C pen | B38: =$G$9 -> 0.174 | C38: =MIN(1,$B38+($B$28-$B38)*(C$33-$B$33)/($AE$33-$B$33)) -> 0.17410961 | D38: =MIN(1,$B38+($B$28-$B38)*(D$33-$B$33)/($AE$33-$B$33)) -> 0.17421922 | E38: =MIN(1,$B38+($B$28-$B38)*(E$33-$B$33)/($AE$33-$B$33)) -> 0.17432884 | F38: =MIN(1,$B38+($B$28-$B38)*(F$33-$B$33)/($AE$33-$B$33)) -> 0.17443845 | G38: =MIN(1,$B38+($B$28-$B38)*(G$33-$B$33)/($AE$33-$B$33)) -> 0.17454806 | H38: =MIN(1,$B38+($B$28-$B38)*(H$33-$B$33)/($AE$33-$B$33)) -> 0.17465767 | I38: =MIN(1,$B38+($B$28-$B38)*(I$33-$B$33)/($AE$33-$B$33)) -> 0.17476729 | J38: =MIN(1,$B38+($B$28-$B38)*(J$33-$B$33)/($AE$33-$B$33)) -> 0.1748769 | ... AE38: =MIN(1,$B38+($B$28-$B38)*(AE$33-$B$33)/($AE$33-$B$33)) -> 0.17717876
A39: >1000 °C pen | B39: =$G$10 -> 0.587 | C39: =MIN(1,$B39+($B$29-$B39)*(C$33-$B$33)/($AE$33-$B$33)) -> 0.58768026 | D39: =MIN(1,$B39+($B$29-$B39)*(D$33-$B$33)/($AE$33-$B$33)) -> 0.58836052 | E39: =MIN(1,$B39+($B$29-$B39)*(E$33-$B$33)/($AE$33-$B$33)) -> 0.58904078 | F39: =MIN(1,$B39+($B$29-$B39)*(F$33-$B$33)/($AE$33-$B$33)) -> 0.58972104 | G39: =MIN(1,$B39+($B$29-$B39)*(G$33-$B$33)/($AE$33-$B$33)) -> 0.5904013 | H39: =MIN(1,$B39+($B$29-$B39)*(H$33-$B$33)/($AE$33-$B$33)) -> 0.59108156 | I39: =MIN(1,$B39+($B$29-$B39)*(I$33-$B$33)/($AE$33-$B$33)) -> 0.59176182 | J39: =MIN(1,$B39+($B$29-$B39)*(J$33-$B$33)/($AE$33-$B$33)) -> 0.59244208 | ... AE39: =MIN(1,$B39+($B$29-$B39)*(AE$33-$B$33)/($AE$33-$B$33)) -> 0.60672754
A40: Band average efficiency η(t) = without-WHR·(1−pen) + with-WHR·pen, clamped to ceiling
A41: <100 °C η | B41: =MIN($H$6,$B$6*(1-B35)+$F$6*B35) -> 0.85 | C41: =MIN($H$6,$B$6*(1-C35)+$F$6*C35) -> 0.85 | D41: =MIN($H$6,$B$6*(1-D35)+$F$6*D35) -> 0.85 | E41: =MIN($H$6,$B$6*(1-E35)+$F$6*E35) -> 0.85 | F41: =MIN($H$6,$B$6*(1-F35)+$F$6*F35) -> 0.85 | G41: =MIN($H$6,$B$6*(1-G35)+$F$6*G35) -> 0.85 | H41: =MIN($H$6,$B$6*(1-H35)+$F$6*H35) -> 0.85 | I41: =MIN($H$6,$B$6*(1-I35)+$F$6*I35) -> 0.85 | ... AE41: =MIN($H$6,$B$6*(1-AE35)+$F$6*AE35) -> 0.85
A42: 100-200 °C η | B42: =MIN($H$7,$B$7*(1-B36)+$F$7*B36) -> 0.83 | C42: =MIN($H$7,$B$7*(1-C36)+$F$7*C36) -> 0.83 | D42: =MIN($H$7,$B$7*(1-D36)+$F$7*D36) -> 0.83 | E42: =MIN($H$7,$B$7*(1-E36)+$F$7*E36) -> 0.83 | F42: =MIN($H$7,$B$7*(1-F36)+$F$7*F36) -> 0.83 | G42: =MIN($H$7,$B$7*(1-G36)+$F$7*G36) -> 0.83 | H42: =MIN($H$7,$B$7*(1-H36)+$F$7*H36) -> 0.83 | I42: =MIN($H$7,$B$7*(1-I36)+$F$7*I36) -> 0.83 | ... AE42: =MIN($H$7,$B$7*(1-AE36)+$F$7*AE36) -> 0.83
A43: 200-500 °C η | B43: =MIN($H$8,$B$8*(1-B37)+$F$8*B37) -> 0.75829 | C43: =MIN($H$8,$B$8*(1-C37)+$F$8*C37) -> 0.75830296 | D43: =MIN($H$8,$B$8*(1-D37)+$F$8*D37) -> 0.75831593 | E43: =MIN($H$8,$B$8*(1-E37)+$F$8*E37) -> 0.75832889 | F43: =MIN($H$8,$B$8*(1-F37)+$F$8*F37) -> 0.75834185 | G43: =MIN($H$8,$B$8*(1-G37)+$F$8*G37) -> 0.75835482 | H43: =MIN($H$8,$B$8*(1-H37)+$F$8*H37) -> 0.75836778 | I43: =MIN($H$8,$B$8*(1-I37)+$F$8*I37) -> 0.75838075 | ... AE43: =MIN($H$8,$B$8*(1-AE37)+$F$8*AE37) -> 0.75866595
A44: 500-1000 °C η | B44: =MIN($H$9,$B$9*(1-B38)+$F$9*B38) -> 0.61399918 | C44: =MIN($H$9,$B$9*(1-C38)+$F$9*C38) -> 0.61402689 | D44: =MIN($H$9,$B$9*(1-D38)+$F$9*D38) -> 0.61405461 | E44: =MIN($H$9,$B$9*(1-E38)+$F$9*E38) -> 0.61408233 | F44: =MIN($H$9,$B$9*(1-F38)+$F$9*F38) -> 0.61411005 | G44: =MIN($H$9,$B$9*(1-G38)+$F$9*G38) -> 0.61413776 | H44: =MIN($H$9,$B$9*(1-H38)+$F$9*H38) -> 0.61416548 | I44: =MIN($H$9,$B$9*(1-I38)+$F$9*I38) -> 0.6141932 | ... AE44: =MIN($H$9,$B$9*(1-AE38)+$F$9*AE38) -> 0.61480299
A45: >1000 °C η | B45: =MIN($H$10,$B$10*(1-B39)+$F$10*B39) -> 0.47587974 | C45: =MIN($H$10,$B$10*(1-C39)+$F$10*C39) -> 0.47616468 | D45: =MIN($H$10,$B$10*(1-D39)+$F$10*D39) -> 0.47644962 | E45: =MIN($H$10,$B$10*(1-E39)+$F$10*E39) -> 0.47673457 | F45: =MIN($H$10,$B$10*(1-F39)+$F$10*F39) -> 0.47701951 | G45: =MIN($H$10,$B$10*(1-G39)+$F$10*G39) -> 0.47730446 | H45: =MIN($H$10,$B$10*(1-H39)+$F$10*H39) -> 0.4775894 | I45: =MIN($H$10,$B$10*(1-I39)+$F$10*I39) -> 0.47787434 | ... AE45: =MIN($H$10,$B$10*(1-AE39)+$F$10*AE39) -> 0.48414311
A46: YoY improvement rate from WHR sweep only = 1 − η(t−1)/η(t) [INTERMEDIATE decomposition — excludes residual; BIEEI-other pulls the TOTAL rates in section 5, rows 91–95]
A47: <100 °C rate | C47: =1-B41/C41 -> 0 | D47: =1-C41/D41 -> 0 | E47: =1-D41/E41 -> 0 | F47: =1-E41/F41 -> 0 | G47: =1-F41/G41 -> 0 | H47: =1-G41/H41 -> 0 | I47: =1-H41/I41 -> 0 | J47: =1-I41/J41 -> 0 | ... AE47: =1-AD41/AE41 -> 0
A48: 100-200 °C rate | C48: =1-B42/C42 -> 0 | D48: =1-C42/D42 -> 0 | E48: =1-D42/E42 -> 0 | F48: =1-E42/F42 -> 0 | G48: =1-F42/G42 -> 0 | H48: =1-G42/H42 -> 0 | I48: =1-H42/I42 -> 0 | J48: =1-I42/J42 -> 0 | ... AE48: =1-AD42/AE42 -> 0
A49: 200-500 °C rate | C49: =1-B43/C43 -> 1.7095648e-05 | D49: =1-C43/D43 -> 1.7095356e-05 | E49: =1-D43/E43 -> 1.7095063e-05 | F49: =1-E43/F43 -> 1.7094771e-05 | G49: =1-F43/G43 -> 1.7094479e-05 | H49: =1-G43/H43 -> 1.7094187e-05 | I49: =1-H43/I43 -> 1.7093894e-05 | J49: =1-I43/J43 -> 1.7093602e-05 | ... AE49: =1-AD43/AE43 -> 1.7087468e-05
A50: 500-1000 °C rate | C50: =1-B44/C44 -> 4.5140657e-05 | D50: =1-C44/D44 -> 4.5138619e-05 | E50: =1-D44/E44 -> 4.5136582e-05 | F50: =1-E44/F44 -> 4.5134544e-05 | G50: =1-F44/G44 -> 4.5132507e-05 | H50: =1-G44/H44 -> 4.513047e-05 | I50: =1-H44/I44 -> 4.5128434e-05 | J50: =1-I44/J44 -> 4.5126397e-05 | ... AE50: =1-AD44/AE44 -> 4.5083674e-05
A51: >1000 °C rate | C51: =1-B45/C45 -> 0.00059841476 | D51: =1-C45/D45 -> 0.00059805687 | E51: =1-D45/E45 -> 0.00059769941 | F51: =1-E45/F45 -> 0.00059734238 | G51: =1-F45/G45 -> 0.00059698578 | H51: =1-G45/H45 -> 0.0005966296 | I51: =1-H45/I45 -> 0.00059627384 | J51: =1-I45/J45 -> 0.00059591851 | ... AE51: =1-AD45/AE45 -> 0.00058855319
A53: 4. Full-coverage industry weighting for band 2050 targets
A54: Every industry with heat in a band is weighted by its band-heat share. Unmapped industries default to Kermeli 'Other' (10% diffusion, no additional — their fired-heater WHR is system air-preheat, priced in the cost-curve file). Band targets = start-year pen + weighted (2050 − 2015) adoption delta, so the default rows contribute zero change.
A55: Industry | B55: 2015 level | C55: 2050 level (scalar-adj) | D55: Share 200-500°C | E55: Share 500-1000°C | F55: Share >1000°C | G55: Mapping
A56: ='indst heat consumption'!B4 -> agriculture and forestry 01T03 | B56: =$B$20 -> 0.1 | C56: =$D$20 -> 0.1 | D56: ='indst heat consumption'!K4 -> 0 | E56: ='indst heat consumption'!L4 -> 0 | F56: ='indst heat consumption'!M4 -> 0 | G56: Default: Other (10%, no additional)
A57: ='indst heat consumption'!B5 -> coal mining 05 | B57: =$B$20 -> 0.1 | C57: =$D$20 -> 0.1 | D57: ='indst heat consumption'!K5 -> 0 | E57: ='indst heat consumption'!L5 -> 0 | F57: ='indst heat consumption'!M5 -> 0 | G57: Default: Other (10%, no additional)
A58: ='indst heat consumption'!B6 -> oil and gas extraction 06 | B58: =$B$20 -> 0.1 | C58: =$D$20 -> 0.1 | D58: ='indst heat consumption'!K6 -> 0.05537122 | E58: ='indst heat consumption'!L6 -> 0.07021543 | F58: ='indst heat consumption'!M6 -> 0 | G58: Default: Other (10%, no additional)
A59: ='indst heat consumption'!B7 -> other mining and quarrying 07T08 | B59: =$B$20 -> 0.1 | C59: =$D$20 -> 0.1 | D59: ='indst heat consumption'!K7 -> 0 | E59: ='indst heat consumption'!L7 -> 0 | F59: ='indst heat consumption'!M7 -> 0 | G59: Default: Other (10%, no additional)
A60: ='indst heat consumption'!B8 -> food beverage and tobacco 10T12 | B60: =$B$20 -> 0.1 | C60: =$D$20 -> 0.1 | D60: ='indst heat consumption'!K8 -> 0.12721462 | E60: ='indst heat consumption'!L8 -> 0 | F60: ='indst heat consumption'!M8 -> 0 | G60: Default: Other (10%, no additional)
A61: ='indst heat consumption'!B9 -> textiles apparel and leather 13T15 | B61: =$B$20 -> 0.1 | C61: =$D$20 -> 0.1 | D61: ='indst heat consumption'!K9 -> 0.0028739125 | E61: ='indst heat consumption'!L9 -> 0 | F61: ='indst heat consumption'!M9 -> 0 | G61: Default: Other (10%, no additional)
A62: ='indst heat consumption'!B10 -> wood products 16 | B62: =$B$20 -> 0.1 | C62: =$D$20 -> 0.1 | D62: ='indst heat consumption'!K10 -> 0.087769462 | E62: ='indst heat consumption'!L10 -> 0 | F62: ='indst heat consumption'!M10 -> 0 | G62: Default: Other (10%, no additional)
A63: ='indst heat consumption'!B11 -> pulp paper and printing 17T18 | B63: =$B$20 -> 0.1 | C63: =$D$20 -> 0.1 | D63: ='indst heat consumption'!K11 -> 0.18116113 | E63: ='indst heat consumption'!L11 -> 0.070590966 | F63: ='indst heat consumption'!M11 -> 0 | G63: Default: Other (10%, no additional)
A64: ='indst heat consumption'!B12 -> refined petroleum and coke 19 | B64: =$B$20 -> 0.1 | C64: =$D$20 -> 0.1 | D64: ='indst heat consumption'!K12 -> 0.1451429 | E64: ='indst heat consumption'!L12 -> 0.18405358 | F64: ='indst heat consumption'!M12 -> 0 | G64: Fired heaters: WHR via system air-preheat (ε=0.4 scope, cost-curve file) — burner-integral held at Other level
A65: ='indst heat consumption'!B13 -> chemicals 20 | B65: =$B$20 -> 0.1 | C65: =$D$20 -> 0.1 | D65: ='indst heat consumption'!K13 -> 0.33030523 | E65: ='indst heat consumption'!L13 -> 0.4188552 | F65: ='indst heat consumption'!M13 -> 0 | G65: Fired heaters: WHR via system air-preheat (ε=0.4 scope, cost-curve file) — burner-integral held at Other level
A66: ='indst heat consumption'!B14 -> rubber and plastic products 22 | B66: =$B$20 -> 0.1 | C66: =$D$20 -> 0.1 | D66: ='indst heat consumption'!K14 -> 0.014354793 | E66: ='indst heat consumption'!L14 -> 0.018203101 | F66: ='indst heat consumption'!M14 -> 0 | G66: Default: Other (10%, no additional)
A67: ='indst heat consumption'!B15 -> glass and glass products 231 | B67: =$B$18 -> 0.9 | C67: =$D$18 -> 0.9075 | D67: ='indst heat consumption'!K15 -> 0.00048565564 | E67: ='indst heat consumption'!L15 -> 0.011795949 | F67: ='indst heat consumption'!M15 -> 0.11556765 | G67: Kermeli: glass
A68: ='indst heat consumption'!B16 -> cement and other nonmetallic minerals 239 | B68: =$B$19 -> 0.49 | C68: =$D$19 -> 0.49 | D68: ='indst heat consumption'!K16 -> 0.0048497662 | E68: ='indst heat consumption'!L16 -> 0.11779457 | F68: ='indst heat consumption'!M16 -> 0.26760828 | G68: Kermeli: cement
A69: ='indst heat consumption'!B17 -> iron and steel 241 | B69: =$B$17 -> 0.8 | C69: =$D$17 -> 0.836 | D69: ='indst heat consumption'!K17 -> 0.0013764882 | E69: ='indst heat consumption'!L17 -> 0.011144374 | F69: ='indst heat consumption'!M17 -> 0.38669341 | G69: Kermeli: iron & steel (blended stoves/regenerators + reheat)
A70: ='indst heat consumption'!B18 -> other metals 242 | B70: =AVERAGE($B$15:$B$16) -> 0.4 | C70: =AVERAGE($D$15:$D$16) -> 0.475 | D70: ='indst heat consumption'!K18 -> 0.02952367 | E70: ='indst heat consumption'!L18 -> 0.035854594 | F70: ='indst heat consumption'!M18 -> 0.065864207 | G70: Avg of secondary Al & Al foundries
A71: ='indst heat consumption'!B19 -> metal products except machinery and vehicles 25 | B71: =$B$20 -> 0.1 | C71: =$D$20 -> 0.1 | D71: ='indst heat consumption'!K19 -> 0.010461599 | E71: ='indst heat consumption'!L19 -> 0.034337669 | F71: ='indst heat consumption'!M19 -> 0.12895874 | G71: Default: Other (10%, no additional)
A72: ='indst heat consumption'!B20 -> computers and electronics 26 | B72: =$B$20 -> 0.1 | C72: =$D$20 -> 0.1 | D72: ='indst heat consumption'!K20 -> 0.0009031391 | E72: ='indst heat consumption'!L20 -> 0.0043872169 | F72: ='indst heat consumption'!M20 -> 0.0043778555 | G72: Default: Other (10%, no additional)
A73: ='indst heat consumption'!B21 -> appliances and electrical equipment 27 | B73: =$B$20 -> 0.1 | C73: =$D$20 -> 0.1 | D73: ='indst heat consumption'!K21 -> 0.0012358746 | E73: ='indst heat consumption'!L21 -> 0.0060035599 | F73: ='indst heat consumption'!M21 -> 0.0059907496 | G73: Default: Other (10%, no additional)
A74: ='indst heat consumption'!B22 -> other machinery 28 | B74: =$B$20 -> 0.1 | C74: =$D$20 -> 0.1 | D74: ='indst heat consumption'!K22 -> 0.0014735427 | E74: ='indst heat consumption'!L22 -> 0.0071580907 | F74: ='indst heat consumption'!M22 -> 0.0071428168 | G74: Default: Other (10%, no additional)
A75: ='indst heat consumption'!B23 -> road vehicles 29 | B75: =$B$20 -> 0.1 | C75: =$D$20 -> 0.1 | D75: ='indst heat consumption'!K23 -> 0.0021548582 | E75: ='indst heat consumption'!L23 -> 0 | F75: ='indst heat consumption'!M23 -> 0.0050272025 | G75: Default: Other (10%, no additional)
A76: ='indst heat consumption'!B24 -> nonroad vehicles 30 | B76: =$B$20 -> 0.1 | C76: =$D$20 -> 0.1 | D76: ='indst heat consumption'!K24 -> 0.0013647435 | E76: ='indst heat consumption'!L24 -> 0 | F76: ='indst heat consumption'!M24 -> 0.0031838949 | G76: Default: Other (10%, no additional)
A77: ='indst heat consumption'!B25 -> other manufacturing 31T33 | B77: =$B$20 -> 0.1 | C77: =$D$20 -> 0.1 | D77: ='indst heat consumption'!K25 -> 0.0019773993 | E77: ='indst heat consumption'!L25 -> 0.0096056958 | F77: ='indst heat consumption'!M25 -> 0.0095851994 | G77: Default: Other (10%, no additional)
A78: ='indst heat consumption'!B26 -> energy pipelines and gas processing 352T353 | B78: =$B$20 -> 0.1 | C78: =$D$20 -> 0.1 | D78: ='indst heat consumption'!K26 -> 0 | E78: ='indst heat consumption'!L26 -> 0 | F78: ='indst heat consumption'!M26 -> 0 | G78: Default: Other (10%, no additional)
A79: ='indst heat consumption'!B27 -> water and waste 36T39 | B79: =$B$20 -> 0.1 | C79: =$D$20 -> 0.1 | D79: ='indst heat consumption'!K27 -> 0 | E79: ='indst heat consumption'!L27 -> 0 | F79: ='indst heat consumption'!M27 -> 0 | G79: Default: Other (10%, no additional)
A80: ='indst heat consumption'!B28 -> construction 41T43 | B80: =$B$20 -> 0.1 | C80: =$D$20 -> 0.1 | D80: ='indst heat consumption'!K28 -> 0 | E80: ='indst heat consumption'!L28 -> 0 | F80: ='indst heat consumption'!M28 -> 0 | G80: Default: Other (10%, no additional)
A82: 5. TOTAL BAU TRAJECTORY — burner-WHR sweep + residual equipment-native improvement (feeds BIEEI-other)
A83: ASSUMPTION (G14): total band efficiency η_tot(t) = η_WHR(t) × (1 + residual)^(t−2021), capped at the tech-matched ceiling (col H). Residual = 0.2%/yr equipment-native drift (controls/O2 trim, refractory/insulation, pressure control, vintage effect) — EXCLUDES all WHR and all price-responsive measures (cost-curve file). See G14 note and About tab.
A84: Year | B84: =B33 -> 2021 | C84: =C33 -> 2022 | D84: =D33 -> 2023 | E84: =E33 -> 2024 | F84: =F33 -> 2025 | G84: =G33 -> 2026 | H84: =H33 -> 2027 | I84: =I33 -> 2028 | ... AE84: =AE33 -> 2050
A85: η_tot <100 °C | B85: =MIN($H$6,B41*(1+$G$14)^(B$33-$B$33)) -> 0.85 | C85: =MIN($H$6,C41*(1+$G$14)^(C$33-$B$33)) -> 0.8517 | D85: =MIN($H$6,D41*(1+$G$14)^(D$33-$B$33)) -> 0.8534034 | E85: =MIN($H$6,E41*(1+$G$14)^(E$33-$B$33)) -> 0.85511021 | F85: =MIN($H$6,F41*(1+$G$14)^(F$33-$B$33)) -> 0.85682043 | G85: =MIN($H$6,G41*(1+$G$14)^(G$33-$B$33)) -> 0.85853407 | H85: =MIN($H$6,H41*(1+$G$14)^(H$33-$B$33)) -> 0.86025114 | I85: =MIN($H$6,I41*(1+$G$14)^(I$33-$B$33)) -> 0.86197164 | ... AE85: =MIN($H$6,AE41*(1+$G$14)^(AE$33-$B$33)) -> 0.90070557
A86: η_tot 100–200 °C | B86: =MIN($H$7,B42*(1+$G$14)^(B$33-$B$33)) -> 0.83 | C86: =MIN($H$7,C42*(1+$G$14)^(C$33-$B$33)) -> 0.83166 | D86: =MIN($H$7,D42*(1+$G$14)^(D$33-$B$33)) -> 0.83332332 | E86: =MIN($H$7,E42*(1+$G$14)^(E$33-$B$33)) -> 0.83498997 | F86: =MIN($H$7,F42*(1+$G$14)^(F$33-$B$33)) -> 0.83665995 | G86: =MIN($H$7,G42*(1+$G$14)^(G$33-$B$33)) -> 0.83833327 | H86: =MIN($H$7,H42*(1+$G$14)^(H$33-$B$33)) -> 0.84000993 | I86: =MIN($H$7,I42*(1+$G$14)^(I$33-$B$33)) -> 0.84168995 | ... AE86: =MIN($H$7,AE42*(1+$G$14)^(AE$33-$B$33)) -> 0.8795125
A87: η_tot 200–500 °C | B87: =MIN($H$8,B43*(1+$G$14)^(B$33-$B$33)) -> 0.75829 | C87: =MIN($H$8,C43*(1+$G$14)^(C$33-$B$33)) -> 0.75981957 | D87: =MIN($H$8,D43*(1+$G$14)^(D$33-$B$33)) -> 0.76135222 | E87: =MIN($H$8,E43*(1+$G$14)^(E$33-$B$33)) -> 0.76288797 | F87: =MIN($H$8,F43*(1+$G$14)^(F$33-$B$33)) -> 0.76442681 | G87: =MIN($H$8,G43*(1+$G$14)^(G$33-$B$33)) -> 0.76596876 | H87: =MIN($H$8,H43*(1+$G$14)^(H$33-$B$33)) -> 0.76751382 | I87: =MIN($H$8,I43*(1+$G$14)^(I$33-$B$33)) -> 0.76906199 | ... AE87: =MIN($H$8,AE43*(1+$G$14)^(AE$33-$B$33)) -> 0.80392311
A88: η_tot 500–1000 °C | B88: =MIN($H$9,B44*(1+$G$14)^(B$33-$B$33)) -> 0.61399918 | C88: =MIN($H$9,C44*(1+$G$14)^(C$33-$B$33)) -> 0.61525495 | D88: =MIN($H$9,D44*(1+$G$14)^(D$33-$B$33)) -> 0.61651329 | E88: =MIN($H$9,E44*(1+$G$14)^(E$33-$B$33)) -> 0.6177742 | F88: =MIN($H$9,F44*(1+$G$14)^(F$33-$B$33)) -> 0.61903769 | G88: =MIN($H$9,G44*(1+$G$14)^(G$33-$B$33)) -> 0.62030376 | H88: =MIN($H$9,H44*(1+$G$14)^(H$33-$B$33)) -> 0.62157242 | I88: =MIN($H$9,I44*(1+$G$14)^(I$33-$B$33)) -> 0.62284367 | ... AE88: =MIN($H$9,AE44*(1+$G$14)^(AE$33-$B$33)) -> 0.65147821
A89: η_tot >1000 °C | B89: =MIN($H$10,B45*(1+$G$14)^(B$33-$B$33)) -> 0.47587974 | C89: =MIN($H$10,C45*(1+$G$14)^(C$33-$B$33)) -> 0.47711701 | D89: =MIN($H$10,D45*(1+$G$14)^(D$33-$B$33)) -> 0.47835733 | E89: =MIN($H$10,E45*(1+$G$14)^(E$33-$B$33)) -> 0.4796007 | F89: =MIN($H$10,F45*(1+$G$14)^(F$33-$B$33)) -> 0.48084713 | G89: =MIN($H$10,G45*(1+$G$14)^(G$33-$B$33)) -> 0.48209663 | H89: =MIN($H$10,H45*(1+$G$14)^(H$33-$B$33)) -> 0.4833492 | I89: =MIN($H$10,I45*(1+$G$14)^(I$33-$B$33)) -> 0.48460486 | ... AE89: =MIN($H$10,AE45*(1+$G$14)^(AE$33-$B$33)) -> 0.513024
A90: Annual improvement rates incl. residual (BIEEI-other pulls these):
A91: Rate <100 °C | C91: =1-B85/C85 -> 0.001996008 | D91: =1-C85/D85 -> 0.001996008 | E91: =1-D85/E85 -> 0.001996008 | F91: =1-E85/F85 -> 0.001996008 | G91: =1-F85/G85 -> 0.001996008 | H91: =1-G85/H85 -> 0.001996008 | I91: =1-H85/I85 -> 0.001996008 | J91: =1-I85/J85 -> 0.001996008 | ... AE91: =1-AD85/AE85 -> 0.001996008
A92: Rate 100–200 °C | C92: =1-B86/C86 -> 0.001996008 | D92: =1-C86/D86 -> 0.001996008 | E92: =1-D86/E86 -> 0.001996008 | F92: =1-E86/F86 -> 0.001996008 | G92: =1-F86/G86 -> 0.001996008 | H92: =1-G86/H86 -> 0.001996008 | I92: =1-H86/I86 -> 0.001996008 | J92: =1-I86/J86 -> 0.001996008 | ... AE92: =1-AD86/AE86 -> 0.001996008
A93: Rate 200–500 °C | C93: =1-B87/C87 -> 0.0020130695 | D93: =1-C87/D87 -> 0.0020130692 | E93: =1-D87/E87 -> 0.0020130689 | F93: =1-E87/F87 -> 0.0020130686 | G93: =1-F87/G87 -> 0.0020130683 | H93: =1-G87/H87 -> 0.0020130681 | I93: =1-H87/I87 -> 0.0020130678 | J93: =1-I87/J87 -> 0.0020130675 | ... AE93: =1-AD87/AE87 -> 0.0020130613
A94: Rate 500–1000 °C | C94: =1-B88/C88 -> 0.0020410585 | D94: =1-C88/D88 -> 0.0020410565 | E94: =1-D88/E88 -> 0.0020410545 | F94: =1-E88/F88 -> 0.0020410524 | G94: =1-F88/G88 -> 0.0020410504 | H94: =1-G88/H88 -> 0.0020410484 | I94: =1-H88/I88 -> 0.0020410463 | J94: =1-I88/J88 -> 0.0020410443 | ... AE94: =1-AD88/AE88 -> 0.0020410017
A95: Rate >1000 °C | C95: =1-B89/C89 -> 0.0025932283 | D95: =1-C89/D89 -> 0.0025928711 | E95: =1-D89/E89 -> 0.0025925144 | F95: =1-E89/F89 -> 0.0025921581 | G95: =1-F89/G89 -> 0.0025918022 | H95: =1-G89/H89 -> 0.0025914467 | I95: =1-H89/I89 -> 0.0025910917 | J95: =1-I89/J89 -> 0.002590737 | ... AE95: =1-AD89/AE89 -> 0.0025833864

Sheet indst heat consumption
D2: Temperature mapping | I2: Share of all energy for heat at various temp bands
B3: Industry Category | C3: Share of all industry boiler/nonboiler heat | D3: < 100°C | E3: 100-200°C | F3: 200-500°C | G3: 500-1000°C | H3: > 1000°C | I3: < 100°C | J3: 100-200°C | K3: 200-500°C | L3: 500-1000°C | M3: > 1000°C
B4: agriculture and forestry 01T03 | C4: 0.041094089 | D4: 1 | E4: 0 | F4: 0 | G4: 0 | H4: 0 | I4: =$C4*D4/SUMPRODUCT($C$4:$C$28,D$4:D$28) -> 0.18630249 | J4: =$C4*E4/SUMPRODUCT($C$4:$C$28,E$4:E$28) -> 0 | K4: =$C4*F4/SUMPRODUCT($C$4:$C$28,F$4:F$28) -> 0 | L4: =$C4*G4/SUMPRODUCT($C$4:$C$28,G$4:G$28) -> 0 | M4: =$C4*H4/SUMPRODUCT($C$4:$C$28,H$4:H$28) -> 0
B5: coal mining 05 | C5: 0 | D5: 1 | E5: 0 | F5: 0 | G5: 0 | H5: 0 | I5: =$C5*D5/SUMPRODUCT($C$4:$C$28,D$4:D$28) -> 0 | J5: =$C5*E5/SUMPRODUCT($C$4:$C$28,E$4:E$28) -> 0 | K5: =$C5*F5/SUMPRODUCT($C$4:$C$28,F$4:F$28) -> 0 | L5: =$C5*G5/SUMPRODUCT($C$4:$C$28,G$4:G$28) -> 0 | M5: =$C5*H5/SUMPRODUCT($C$4:$C$28,H$4:H$28) -> 0
B6: oil and gas extraction 06 | C6: 0.040805825 | D6: 0.076923077 | E6: 0.25213675 | F6: 0.53205128 | G6: 0.13888889 | H6: 0 | I6: =$C6*D6/SUMPRODUCT($C$4:$C$28,D$4:D$28) -> 0.014230433 | J6: =$C6*E6/SUMPRODUCT($C$4:$C$28,E$4:E$28) -> 0.054733821 | K6: =$C6*F6/SUMPRODUCT($C$4:$C$28,F$4:F$28) -> 0.05537122 | L6: =$C6*G6/SUMPRODUCT($C$4:$C$28,G$4:G$28) -> 0.07021543 | M6: =$C6*H6/SUMPRODUCT($C$4:$C$28,H$4:H$28) -> 0
B7: other mining and quarrying 07T08 | C7: 0.023082653 | D7: 1 | E7: 0 | F7: 0 | G7: 0 | H7: 0 | I7: =$C7*D7/SUMPRODUCT($C$4:$C$28,D$4:D$28) -> 0.10464658 | J7: =$C7*E7/SUMPRODUCT($C$4:$C$28,E$4:E$28) -> 0 | K7: =$C7*F7/SUMPRODUCT($C$4:$C$28,F$4:F$28) -> 0 | L7: =$C7*G7/SUMPRODUCT($C$4:$C$28,G$4:G$28) -> 0 | M7: =$C7*H7/SUMPRODUCT($C$4:$C$28,H$4:H$28) -> 0
B8: food beverage and tobacco 10T12 | C8: 0.097591785 | D8: 0.23333333 | E8: 0.25555556 | F8: 0.51111111 | G8: 0 | H8: 0 | I8: =$C8*D8/SUMPRODUCT($C$4:$C$28,D$4:D$28) -> 0.10323557 | J8: =$C8*E8/SUMPRODUCT($C$4:$C$28,E$4:E$28) -> 0.13267712 | K8: =$C8*F8/SUMPRODUCT($C$4:$C$28,F$4:F$28) -> 0.12721462 | L8: =$C8*G8/SUMPRODUCT($C$4:$C$28,G$4:G$28) -> 0 | M8: =$C8*H8/SUMPRODUCT($C$4:$C$28,H$4:H$28) -> 0
B9: textiles apparel and leather 13T15 | C9: 0.0032056866 | D9: 0.47272727 | E9: 0.17575758 | F9: 0.35151515 | G9: 0 | H9: 0 | I9: =$C9*D9/SUMPRODUCT($C$4:$C$28,D$4:D$28) -> 0.0068702259 | J9: =$C9*E9/SUMPRODUCT($C$4:$C$28,E$4:E$28) -> 0.0029973162 | K9: =$C9*F9/SUMPRODUCT($C$4:$C$28,F$4:F$28) -> 0.0028739125 | L9: =$C9*G9/SUMPRODUCT($C$4:$C$28,G$4:G$28) -> 0 | M9: =$C9*H9/SUMPRODUCT($C$4:$C$28,H$4:H$28) -> 0
B10: wood products 16 | C10: 0.05850378 | D10: 0.11764706 | E10: 0.29411765 | F10: 0.58823529 | G10: 0 | H10: 0 | I10: =$C10*D10/SUMPRODUCT($C$4:$C$28,D$4:D$28) -> 0.031203571 | J10: =$C10*E10/SUMPRODUCT($C$4:$C$28,E$4:E$28) -> 0.091538218 | K10: =$C10*F10/SUMPRODUCT($C$4:$C$28,F$4:F$28) -> 0.087769462 | L10: =$C10*G10/SUMPRODUCT($C$4:$C$28,G$4:G$28) -> 0 | M10: =$C10*H10/SUMPRODUCT($C$4:$C$28,H$4:H$28) -> 0
B11: pulp paper and printing 17T18 | C11: 0.17093362 | D11: 0.34666667 | E11: 0.20444444 | F11: 0.41555556 | G11: 0.033333333 | H11: 0 | I11: =$C11*D11/SUMPRODUCT($C$4:$C$28,D$4:D$28) -> 0.26864507 | J11: =$C11*E11/SUMPRODUCT($C$4:$C$28,E$4:E$28) -> 0.18590893 | K11: =$C11*F11/SUMPRODUCT($C$4:$C$28,F$4:F$28) -> 0.18116113 | L11: =$C11*G11/SUMPRODUCT($C$4:$C$28,G$4:G$28) -> 0.070590966 | M11: =$C11*H11/SUMPRODUCT($C$4:$C$28,H$4:H$28) -> 0
B12: refined petroleum and coke 19 | C12: 0.10696308 | D12: 0.076923077 | E12: 0.25213675 | F12: 0.53205128 | G12: 0.13888889 | H12: 0 | I12: =$C12*D12/SUMPRODUCT($C$4:$C$28,D$4:D$28) -> 0.037301803 | J12: =$C12*E12/SUMPRODUCT($C$4:$C$28,E$4:E$28) -> 0.14347211 | K12: =$C12*F12/SUMPRODUCT($C$4:$C$28,F$4:F$28) -> 0.1451429 | L12: =$C12*G12/SUMPRODUCT($C$4:$C$28,G$4:G$28) -> 0.18405358 | M12: =$C12*H12/SUMPRODUCT($C$4:$C$28,H$4:H$28) -> 0
B13: chemicals 20 | C13: 0.24341847 | D13: 0.076923077 | E13: 0.25213675 | F13: 0.53205128 | G13: 0.13888889 | H13: 0 | I13: =$C13*D13/SUMPRODUCT($C$4:$C$28,D$4:D$28) -> 0.084888619 | J13: =$C13*E13/SUMPRODUCT($C$4:$C$28,E$4:E$28) -> 0.32650296 | K13: =$C13*F13/SUMPRODUCT($C$4:$C$28,F$4:F$28) -> 0.33030523 | L13: =$C13*G13/SUMPRODUCT($C$4:$C$28,G$4:G$28) -> 0.4188552 | M13: =$C13*H13/SUMPRODUCT($C$4:$C$28,H$4:H$28) -> 0
B14: rubber and plastic products 22 | C14: 0.010578766 | D14: 0.076923077 | E14: 0.25213675 | F14: 0.53205128 | G14: 0.13888889 | H14: 0 | I14: =$C14*D14/SUMPRODUCT($C$4:$C$28,D$4:D$28) -> 0.0036891893 | J14: =$C14*E14/SUMPRODUCT($C$4:$C$28,E$4:E$28) -> 0.014189549 | K14: =$C14*F14/SUMPRODUCT($C$4:$C$28,F$4:F$28) -> 0.014354793 | L14: =$C14*G14/SUMPRODUCT($C$4:$C$28,G$4:G$28) -> 0.018203101 | M14: =$C14*H14/SUMPRODUCT($C$4:$C$28,H$4:H$28) -> 0
B15: glass and glass products 231 | C15: 0.014853014 | D15: 0 | E15: 0 | F15: 0.012820513 | G15: 0.064102564 | H15: 0.92307692 | I15: =$C15*D15/SUMPRODUCT($C$4:$C$28,D$4:D$28) -> 0 | J15: =$C15*E15/SUMPRODUCT($C$4:$C$28,E$4:E$28) -> 0 | K15: =$C15*F15/SUMPRODUCT($C$4:$C$28,F$4:F$28) -> 0.00048565564 | L15: =$C15*G15/SUMPRODUCT($C$4:$C$28,G$4:G$28) -> 0.011795949 | M15: =$C15*H15/SUMPRODUCT($C$4:$C$28,H$4:H$28) -> 0.11556765
... B28: construction 41T43 | C28: 0.023229687 | D28: 1 | E28: 0 | F28: 0 | G28: 0 | H28: 0 | I28: =$C28*D28/SUMPRODUCT($C$4:$C$28,D$4:D$28) -> 0.10531316 | J28: =$C28*E28/SUMPRODUCT($C$4:$C$28,E$4:E$28) -> 0 | K28: =$C28*F28/SUMPRODUCT($C$4:$C$28,F$4:F$28) -> 0 | L28: =$C28*G28/SUMPRODUCT($C$4:$C$28,G$4:G$28) -> 0 | M28: =$C28*H28/SUMPRODUCT($C$4:$C$28,H$4:H$28) -> 0
C29: * from indst/BPFUbIP file

Sheet Kermeli Data
A1: Calculations
A2: Data from Kermeli et al. (SM) | B2: https://link.springer.com/article/10.1007/s12053-022-10071-8#Sec10
A3: NPV =CF0 + CF1/(1+r)1 + CF2/(1+r)2 + … + CFn/(1+r)n
A4: r = hurdle rate = WACC + risk premium
A5: https://capitalgains.thediff.co/p/hurdle-rates
A7: Energy Savings & Cost of Measures from Kermeli et al.
A8: Product / Process | B8: Technology / Measure | C8: 2015 Diffusion | D8: 2030 Implementation | E8: 2050 Implementation | F8: Fuel Savings (GJ/t) | G8: Elec. Savings (GJ/t) | H8: H2 Savings (GJ/t) | I8: Investment (€/t) | J8: Technical lifetime (years) | K8: Annual O&M Costs (€/t)
A9: Primary aluminum | B9: PFPBa | C9: 0.9 | D9: 0.1 | E9: 0.1 | F9: 0 | G9: 2.8 | H9: 0 | I9: 2340 | J9: 20 | K9: 0
A10: Primary aluminum | B10: Optimization electrolysis controlc | C10: 0.55 | D10: 0.35 | E10: 0.45 | F10: 0 | G10: 3.6 | H10: 0 | I10: 188 | J10: 5 | K10: -65
A11: Primary aluminum | B11: Optimization cell designc | C11: 0.55 | D11: 0.35 | E11: 0.45 | F11: 0 | G11: 2.5 | H11: 0 | I11: 236 | J11: 6 | K11: 0
A12: Secondary aluminum | B12: Regenerative or recuperative burnerd | C12: 0.3 | D12: 0.25 | E12: 0.5 | F12: 2 | G12: 0 | H12: 0 | I12: 14 | J12: 20 | K12: 0.4
A13: Secondary aluminum | B13: New decoating equipmentd | C13: 0 | D13: 0.15 | E13: 0.6 | F13: 0.4 | G13: 0 | H13: 0 | I13: 40 | J13: 10 | K13: 40
A14: Aluminum foundries | B14: Improved process schedulinge | C14: 0.6 | D14: 0.39 | E14: 0.4 | F14: 1.8 | G14: 0 | H14: 0 | I14: 25 | J14: 20 | K14: 0
A15: Aluminum foundries | B15: Regenerative or recuperative burnere | C15: 0.5 | D15: 0.05 | E15: 0.3 | F15: 4.8 | G15: 0 | H15: 0 | I15: 10 | J15: 20 | K15: 0.7
A16: Aluminum foundries | B16: Liquid metal as feedstocke | C16: 0.05 | D16: 0.2 | E16: 0.45 | F16: 8.7 | G16: 0 | H16: 0 | I16: 25 | J16: 20 | K16: 0
A17: Coke oven | B17: Programmed heatinga | C17: 0.3 | D17: 0.5 | E17: 0.7 | F17: 0.2 | G17: 0 | H17: 0 | I17: 0.2 | J17: 10 | K17: 0
A18: Coke oven | B18: Variable speed drive on compressorsa | C18: 0.3 | D18: 0.5 | E18: 0.7 | F18: 0 | G18: 0 | H18: 0 | I18: 0.3 | J18: 15 | K18: 0
A19: Coke oven | B19: Coal moisture controla | C19: 0.3 | D19: 0.5 | E19: 0.7 | F19: 0.3 | G19: 0 | H19: 0 | I19: 6.5 | J19: 10 | K19: 0
A20: Pig iron | B20: Waste heat recovery blast furnace slagb | C20: 0 | D20: 0.43 | E20: 0.8 | F20: 0.4 | G20: 0 | H20: 0 | I20: 54.5 | J20: 20 | K20: 0
... A175: Soda ash | B175: High temperature heat pump | C175: 0 | D175: 0.04 | E175: 0.4 | F175: 11.2 | G175: -2.4 | H175: 0 | I175: 841 | J175: 15 | K175: 0

Sheet DEA rates
A1: DEA-derived annual efficiency gains (Danish Energy Agency, Technology Data for Industrial Process Heat)
A3: DEA technology | B3: Eff/COP start | C3: Eff/COP 2050 | D3: Start yr | E3: End yr | F3: Annual efficiency gain
A4: 1.1 Heat pump up to 60 C | B4: ='1.1 Traditional heat pump'!C7 -> 5.33 | C4: ='1.1 Traditional heat pump'!G7 -> 5.655695 | D4: ='1.1 Traditional heat pump'!C2 -> 2025 | E4: ='1.1 Traditional heat pump'!G2 -> 2050 | F4: =1-(B4/C4)^(1/(E4-D4)) -> 0.0023696583
A5: 1.2 Heat/cool HP up to 80 C | B5: ='1.2 heat_cool hp 80 C 75 K '!C7 -> 3.35 | C5: ='1.2 heat_cool hp 80 C 75 K '!G7 -> 3.533586 | D5: ='1.2 heat_cool hp 80 C 75 K '!C2 -> 2025 | E5: ='1.2 heat_cool hp 80 C 75 K '!G2 -> 2050 | F5: =1-(B5/C5)^(1/(E5-D5)) -> 0.0021318393
A6: 2.a High-temp HP up to 125 C | B6: ='2.a High temp. hp Up to 125C'!C7 -> 2.75 | C6: ='2.a High temp. hp Up to 125C'!G7 -> 3 | D6: ='2.a High temp. hp Up to 125C'!C2 -> 2025 | E6: ='2.a High temp. hp Up to 125C'!G2 -> 2050 | F6: =1-(B6/C6)^(1/(E6-D6)) -> 0.0034744053
A7: 2.b High-temp HP up to 150 C | B7: ='2.b High temp. hp Up to 150'!C7 -> 2.75 | C7: ='2.b High temp. hp Up to 150'!G7 -> 3 | D7: ='2.b High temp. hp Up to 150'!C2 -> 2025 | E7: ='2.b High temp. hp Up to 150'!G2 -> 2050 | F7: =1-(B7/C7)^(1/(E7-D7)) -> 0.0034744053
A8: 4 MVR (5 K) | B8: ='4 MVR 5 K'!C7 -> 12.6 | C8: ='4 MVR 5 K'!G7 -> 14.3 | D8: ='4 MVR 5 K'!C2 -> 2025 | E8: ='4 MVR 5 K'!G2 -> 2050 | F8: =1-(B8/C8)^(1/(E8-D8)) -> 0.005049716
A9: 5.1a Electric boiler steam (LV) | B9: ='5.1a Electric boiler steam'!C7 -> 0.99 | C9: ='5.1a Electric boiler steam'!G7 -> 0.99 | D9: ='5.1a Electric boiler steam'!C2 -> 2025 | E9: ='5.1a Electric boiler steam'!G2 -> 2050 | F9: =1-(B9/C9)^(1/(E9-D9)) -> 0
A10: 5.1b Electric boiler steam (HV) | B10: ='5.1b Electric boiler steam'!C7 -> 0.99 | C10: ='5.1b Electric boiler steam'!G7 -> 0.99 | D10: ='5.1b Electric boiler steam'!C2 -> 2025 | E10: ='5.1b Electric boiler steam'!G2 -> 2050 | F10: =1-(B10/C10)^(1/(E10-D10)) -> 0
A11: 5.2a Electric boiler hot water (LV) | B11: ='5.2a Electric boiler hot wate'!C7 -> 0.99 | C11: ='5.2a Electric boiler hot wate'!G7 -> 0.99 | D11: ='5.2a Electric boiler hot wate'!C2 -> 2025 | E11: ='5.2a Electric boiler hot wate'!G2 -> 2050 | F11: =1-(B11/C11)^(1/(E11-D11)) -> 0
A12: 5.2b Electric boiler hot water (HV) | B12: ='5.2b Electric boiler hot wate'!C7 -> 0.99 | C12: ='5.2b Electric boiler hot wate'!G7 -> 0.99 | D12: ='5.2b Electric boiler hot wate'!C2 -> 2025 | E12: ='5.2b Electric boiler hot wate'!G2 -> 2050 | F12: =1-(B12/C12)^(1/(E12-D12)) -> 0
A13: 7.3 Direct electric firing | B13: ='7.3 Direct electric firing'!C7 -> 1 | C13: ='7.3 Direct electric firing'!G7 -> 1 | D13: ='7.3 Direct electric firing'!C2 -> 2025 | E13: ='7.3 Direct electric firing'!G2 -> 2050 | F13: =1-(B13/C13)^(1/(E13-D13)) -> 0
A15: BIEEI-elec end-use band | B15: DEA annual gain | C15: Mapped DEA technologies
A16: heat below 100 C | B16: =F5 -> 0.0021318393 | C16: Heat pumps up to 60 / 80 C (1.1, 1.2)
A17: heat 100 to 200 C | B17: =AVERAGE(F6:F7) -> 0.0034744053 | C17: High-temp HP up to 125/150 C (2.a, 2.b)
A18: heat 200 to 500 C | B18: =AVERAGE(F9:F13) -> 0 | C18: Electric boilers / direct electric (5.x, 7.3) - no headroom
A19: heat 500 to 1000 C | B19: =F13 -> 0 | C19: Direct electric firing (7.3)
A20: heat above 1000 C | B20: =F13 -> 0 | C20: Direct electric firing (7.3)
A22: Combustion technologies (BIEEI-other)
A23: 6.1 Boiler, gas & oil | B23: ='6.1 Boiler, gas and oil'!C7 -> 0.94 | C23: ='6.1 Boiler, gas and oil'!G7 -> 0.94 | D23: ='6.1 Boiler, gas and oil'!C2 -> 2025 | E23: ='6.1 Boiler, gas and oil'!G2 -> 2050 | F23: =1-(B23/C23)^(1/(E23-D23)) -> 0
A24: 6.2 Boiler, biomass | B24: ='6.2 Boiler, biomass'!C7 -> 0.89 | C24: ='6.2 Boiler, biomass'!G7 -> 0.89 | D24: ='6.2 Boiler, biomass'!C2 -> 2025 | E24: ='6.2 Boiler, biomass'!G2 -> 2050 | F24: =1-(B24/C24)^(1/(E24-D24)) -> 0
A25: 6.3 Boiler, coal | B25: ='6.3 Boiler, coal'!C7 -> 0.9 | C25: ='6.3 Boiler, coal'!G7 -> 0.9 | D25: ='6.3 Boiler, coal'!C2 -> 2025 | E25: ='6.3 Boiler, coal'!G2 -> 2050 | F25: =1-(B25/C25)^(1/(E25-D25)) -> 0
A26: 7.1 Direct firing, natural gas | B26: ='7.1 Direct firing Natural Gas'!C7 -> 1 | C26: ='7.1 Direct firing Natural Gas'!G7 -> 1 | D26: ='7.1 Direct firing Natural Gas'!C2 -> 2025 | E26: ='7.1 Direct firing Natural Gas'!G2 -> 2050 | F26: =1-(B26/C26)^(1/(E26-D26)) -> 0
A27: 7.2 Direct firing, solid fuels | B27: ='7.2 Direct firing Solid Fuels'!C7 -> 1 | C27: ='7.2 Direct firing Solid Fuels'!G7 -> 1 | D27: ='7.2 Direct firing Solid Fuels'!C2 -> 2025 | E27: ='7.2 Direct firing Solid Fuels'!G2 -> 2050 | F27: =1-(B27/C27)^(1/(E27-D27)) -> 0
A29: BIEEI-other end-use band | B29: DEA annual gain | C29: Mapped DEA technologies
A30: heat below 100 C | B30: =F23 -> 0 | C30: Gas & oil boiler (6.1) - no headroom
A31: heat 100 to 200 C | B31: =F23 -> 0 | C31: Gas & oil boiler (6.1) - no headroom
A32: heat 200 to 500 C | B32: =F23 -> 0 | C32: Gas & oil boiler (6.1) - no headroom
A33: heat 500 to 1000 C | B33: =F26 -> 0 | C33: Direct firing, natural gas (7.1)
A34: heat above 1000 C | B34: =F26 -> 0 | C34: Direct firing, natural gas (7.1)

Sheet SYIEUEFbIPaF
A1: Unit: dimensionless | B1: <100 °C | C1: 100-200 °C | D1: 200-500 °C | E1: 500-1000 °C | F1: >1000 °C | G1: Cooling | H1: Machine Drive | I1: Other process | J1: Facility HVAC | K1: Facility Lighting | L1: Other nonprocess
A2: electricity if | B2: 0.27027027 | C2: 0.44843049 | D2: 1.010101 | E2: 1.010101 | F2: 1.305638 | G2: 0.19019146 | H2: 1.1974604 | I2: 1.6393443 | J2: 0.28571429 | K2: 1.1722299 | L2: 1.4079278
A3: hard coal if | B3: 1.3529412 | C3: 1.3855422 | D3: 1.5165702 | E3: 1.8715373 | F3: 2.394809 | G3: 0.8974359 | H3: 2.5 | I3: 1.6393443 | J3: 1.3529412 | K3: 3.3492282 | L3: 3.2788295
A4: natural gas if | B4: 1.1764706 | C4: 1.2048193 | D4: 1.3187567 | E4: 1.6274237 | F4: 2.0824426 | G4: 0.8974359 | H4: 2.5 | I4: 1.6393443 | J4: 1.1764706 | K4: 3.3492282 | L4: 3.2788295
A5: biomass if | B5: 1.3529412 | C5: 1.3855422 | D5: 1.5165702 | E5: 1.8715373 | F5: 2.394809 | G5: 0.8974359 | H5: 2.5 | I5: 1.6393443 | J5: 1.3529412 | K5: 3.3492282 | L5: 3.2788295
A6: petroleum diesel if | B6: 1.2299465 | C6: 1.2595838 | D6: 1.3787002 | E6: 1.7013975 | F6: 2.1770991 | G6: 0.8974359 | H6: 2.5 | I6: 1.6393443 | J6: 1.2299465 | K6: 3.3492282 | L6: 3.2788295
A7: heat if | B7: 1.05 | C7: 1.05 | D7: 1.05 | E7: 1.05 | F7: 1.05 | G7: 0.8974359 | H7: 2.5 | I7: 1.6393443 | J7: 1.05 | K7: 3.3492282 | L7: 3.2788295
A8: crude oil if | B8: 1.2299465 | C8: 1.2595838 | D8: 1.3787002 | E8: 1.7013975 | F8: 2.1770991 | G8: 0.8974359 | H8: 2.5 | I8: 1.6393443 | J8: 1.2299465 | K8: 3.3492282 | L8: 3.2788295
A9: heavy or residual fuel oil if | B9: 1.2299465 | C9: 1.2595838 | D9: 1.3787002 | E9: 1.7013975 | F9: 2.1770991 | G9: 0.8974359 | H9: 2.5 | I9: 1.6393443 | J9: 1.2299465 | K9: 3.3492282 | L9: 3.2788295
A10: LPG propane or butane if | B10: 1.1764706 | C10: 1.2048193 | D10: 1.3187567 | E10: 1.6274237 | F10: 2.0824426 | G10: 0.8974359 | H10: 2.5 | I10: 1.6393443 | J10: 1.1764706 | K10: 3.3492282 | L10: 3.2788295
A11: hydrogen if | B11: 1.1764706 | C11: 1.2048193 | D11: 1.3187567 | E11: 1.6274237 | F11: 2.0824426 | G11: 0.8974359 | H11: 2.5 | I11: 1.6393443 | J11: 1.1764706 | K11: 3.3492282 | L11: 3.2788295
A12: green hydrogen if | B12: 1.1764706 | C12: 1.2048193 | D12: 1.3187567 | E12: 1.6274237 | F12: 2.0824426 | G12: 0.8974359 | H12: 2.5 | I12: 1.6393443 | J12: 1.1764706 | K12: 3.3492282 | L12: 3.2788295
A13: low carbon hydrogen if | B13: 1.1764706 | C13: 1.2048193 | D13: 1.3187567 | E13: 1.6274237 | F13: 2.0824426 | G13: 0.8974359 | H13: 2.5 | I13: 1.6393443 | J13: 1.1764706 | K13: 3.3492282 | L13: 3.2788295

Sheet BIEEI-elec
A1: Unit: BTU | B1: 2021 | C1: 2022 | D1: 2023 | E1: 2024 | F1: 2025 | G1: 2026 | H1: 2027 | I1: 2028 | J1: 2029 | K1: 2030 | L1: 2031 | M1: 2032 | N1: 2033 | O1: 2034 | P1: 2035 | Q1: 2036 | R1: 2037 | S1: 2038 | T1: 2039 | U1: 2040 | V1: 2041 | W1: 2042 | X1: 2043 | Y1: 2044 | Z1: 2045 | AA1: 2046 | AB1: 2047 | AC1: 2048 | AD1: 2049 | AE1: 2050
A2: heat below 100 C | B2: 0 | C2: =MECS!$M$5 -> 0.0016707673 | D2: =MECS!$M$5 -> 0.0016707673 | E2: =MECS!$M$5 -> 0.0016707673 | F2: =MECS!$M$5 -> 0.0016707673 | G2: =MECS!$M$5 -> 0.0016707673 | H2: =MECS!$M$5 -> 0.0016707673 | I2: =MECS!$M$5 -> 0.0016707673 | J2: =MECS!$M$5 -> 0.0016707673 | ... AE2: =MECS!$M$5 -> 0.0016707673
A3: heat 100 to 200 C | B3: 0 | C3: =MECS!$M$5 -> 0.0016707673 | D3: =MECS!$M$5 -> 0.0016707673 | E3: =MECS!$M$5 -> 0.0016707673 | F3: =MECS!$M$5 -> 0.0016707673 | G3: =MECS!$M$5 -> 0.0016707673 | H3: =MECS!$M$5 -> 0.0016707673 | I3: =MECS!$M$5 -> 0.0016707673 | J3: =MECS!$M$5 -> 0.0016707673 | ... AE3: =MECS!$M$5 -> 0.0016707673
A4: heat 200 to 500 C | B4: 0 | C4: =MECS!$M$5 -> 0.0016707673 | D4: =MECS!$M$5 -> 0.0016707673 | E4: =MECS!$M$5 -> 0.0016707673 | F4: =MECS!$M$5 -> 0.0016707673 | G4: =MECS!$M$5 -> 0.0016707673 | H4: =MECS!$M$5 -> 0.0016707673 | I4: =MECS!$M$5 -> 0.0016707673 | J4: =MECS!$M$5 -> 0.0016707673 | ... AE4: =MECS!$M$5 -> 0.0016707673
A5: heat 500 to 1000 C | B5: 0 | C5: =MECS!$M$5 -> 0.0016707673 | D5: =MECS!$M$5 -> 0.0016707673 | E5: =MECS!$M$5 -> 0.0016707673 | F5: =MECS!$M$5 -> 0.0016707673 | G5: =MECS!$M$5 -> 0.0016707673 | H5: =MECS!$M$5 -> 0.0016707673 | I5: =MECS!$M$5 -> 0.0016707673 | J5: =MECS!$M$5 -> 0.0016707673 | ... AE5: =MECS!$M$5 -> 0.0016707673
A6: heat above 1000 C | B6: 0 | C6: =MECS!$M$5 -> 0.0016707673 | D6: =MECS!$M$5 -> 0.0016707673 | E6: =MECS!$M$5 -> 0.0016707673 | F6: =MECS!$M$5 -> 0.0016707673 | G6: =MECS!$M$5 -> 0.0016707673 | H6: =MECS!$M$5 -> 0.0016707673 | I6: =MECS!$M$5 -> 0.0016707673 | J6: =MECS!$M$5 -> 0.0016707673 | ... AE6: =MECS!$M$5 -> 0.0016707673
A7: Cooling | B7: 0 | C7: =MECS!$M$7 -> 0.0025211684 | D7: =MECS!$M$7 -> 0.0025211684 | E7: =MECS!$M$7 -> 0.0025211684 | F7: =MECS!$M$7 -> 0.0025211684 | G7: =MECS!$M$7 -> 0.0025211684 | H7: =MECS!$M$7 -> 0.0025211684 | I7: =MECS!$M$7 -> 0.0025211684 | J7: =MECS!$M$7 -> 0.0025211684 | ... AE7: =MECS!$M$7 -> 0.0025211684
A8: Machine Drive | B8: 0 | C8: =MECS!$M$9 -> 0.002787452 | D8: =MECS!$M$9 -> 0.002787452 | E8: =MECS!$M$9 -> 0.002787452 | F8: =MECS!$M$9 -> 0.002787452 | G8: =MECS!$M$9 -> 0.002787452 | H8: =MECS!$M$9 -> 0.002787452 | I8: =MECS!$M$9 -> 0.002787452 | J8: =MECS!$M$9 -> 0.002787452 | ... AE8: =MECS!$M$9 -> 0.002787452
A9: Other process | B9: 0 | C9: =AVERAGE(MECS!$M$12,MECS!$M$10) -> 0.0083630308 | D9: =AVERAGE(MECS!$M$12,MECS!$M$10) -> 0.0083630308 | E9: =AVERAGE(MECS!$M$12,MECS!$M$10) -> 0.0083630308 | F9: =AVERAGE(MECS!$M$12,MECS!$M$10) -> 0.0083630308 | G9: =AVERAGE(MECS!$M$12,MECS!$M$10) -> 0.0083630308 | H9: =AVERAGE(MECS!$M$12,MECS!$M$10) -> 0.0083630308 | I9: =AVERAGE(MECS!$M$12,MECS!$M$10) -> 0.0083630308 | J9: =AVERAGE(MECS!$M$12,MECS!$M$10) -> 0.0083630308 | ... AE9: =AVERAGE(MECS!$M$12,MECS!$M$10) -> 0.0083630308
A10: Facility HVAC | B10: =B2 -> 0 | C10: =C2 -> 0.0016707673 | D10: =D2 -> 0.0016707673 | E10: =E2 -> 0.0016707673 | F10: =F2 -> 0.0016707673 | G10: =G2 -> 0.0016707673 | H10: =H2 -> 0.0016707673 | I10: =I2 -> 0.0016707673 | ... AE10: =AE2 -> 0.0016707673
A11: Facility lighting | B11: =B3 -> 0 | C11: =lighting!$D$14 -> 0.002057392 | D11: =lighting!$D$14 -> 0.002057392 | E11: =lighting!$D$14 -> 0.002057392 | F11: =lighting!$D$14 -> 0.002057392 | G11: =lighting!$D$14 -> 0.002057392 | H11: =lighting!$D$14 -> 0.002057392 | I11: =lighting!$D$14 -> 0.002057392 | J11: =lighting!$D$14 -> 0.002057392 | ... AE11: =lighting!$D$14 -> 0.002057392
A12: Other nonprocess | B12: =AVERAGE(B2:B11) -> 0 | C12: =AVERAGE(C2:C11) -> 0.0025753647 | D12: =AVERAGE(D2:D11) -> 0.0025753647 | E12: =AVERAGE(E2:E11) -> 0.0025753647 | F12: =AVERAGE(F2:F11) -> 0.0025753647 | G12: =AVERAGE(G2:G11) -> 0.0025753647 | H12: =AVERAGE(H2:H11) -> 0.0025753647 | I12: =AVERAGE(I2:I11) -> 0.0025753647 | ... AE12: =AVERAGE(AE2:AE11) -> 0.0025753647

Sheet BIEEI-other
A1: Unit: BTU | B1: 2021 | C1: 2022 | D1: 2023 | E1: 2024 | F1: 2025 | G1: 2026 | H1: 2027 | I1: 2028 | J1: 2029 | K1: 2030 | L1: 2031 | M1: 2032 | N1: 2033 | O1: 2034 | P1: 2035 | Q1: 2036 | R1: 2037 | S1: 2038 | T1: 2039 | U1: 2040 | V1: 2041 | W1: 2042 | X1: 2043 | Y1: 2044 | Z1: 2045 | AA1: 2046 | AB1: 2047 | AC1: 2048 | AD1: 2049 | AE1: 2050
A2: heat below 100 C | B2: 0 | C2: ='Combustion BAU Trajectory'!C91 -> 0.001996008 | D2: ='Combustion BAU Trajectory'!D91 -> 0.001996008 | E2: ='Combustion BAU Trajectory'!E91 -> 0.001996008 | F2: ='Combustion BAU Trajectory'!F91 -> 0.001996008 | G2: ='Combustion BAU Trajectory'!G91 -> 0.001996008 | H2: ='Combustion BAU Trajectory'!H91 -> 0.001996008 | I2: ='Combustion BAU Trajectory'!I91 -> 0.001996008 | J2: ='Combustion BAU Trajectory'!J91 -> 0.001996008 | ... AE2: ='Combustion BAU Trajectory'!AE91 -> 0.001996008
A3: heat 100 to 200 C | B3: 0 | C3: ='Combustion BAU Trajectory'!C92 -> 0.001996008 | D3: ='Combustion BAU Trajectory'!D92 -> 0.001996008 | E3: ='Combustion BAU Trajectory'!E92 -> 0.001996008 | F3: ='Combustion BAU Trajectory'!F92 -> 0.001996008 | G3: ='Combustion BAU Trajectory'!G92 -> 0.001996008 | H3: ='Combustion BAU Trajectory'!H92 -> 0.001996008 | I3: ='Combustion BAU Trajectory'!I92 -> 0.001996008 | J3: ='Combustion BAU Trajectory'!J92 -> 0.001996008 | ... AE3: ='Combustion BAU Trajectory'!AE92 -> 0.001996008
A4: heat 200 to 500 C | B4: 0 | C4: ='Combustion BAU Trajectory'!C93 -> 0.0020130695 | D4: ='Combustion BAU Trajectory'!D93 -> 0.0020130692 | E4: ='Combustion BAU Trajectory'!E93 -> 0.0020130689 | F4: ='Combustion BAU Trajectory'!F93 -> 0.0020130686 | G4: ='Combustion BAU Trajectory'!G93 -> 0.0020130683 | H4: ='Combustion BAU Trajectory'!H93 -> 0.0020130681 | I4: ='Combustion BAU Trajectory'!I93 -> 0.0020130678 | J4: ='Combustion BAU Trajectory'!J93 -> 0.0020130675 | ... AE4: ='Combustion BAU Trajectory'!AE93 -> 0.0020130613
A5: heat 500 to 1000 C | B5: 0 | C5: ='Combustion BAU Trajectory'!C94 -> 0.0020410585 | D5: ='Combustion BAU Trajectory'!D94 -> 0.0020410565 | E5: ='Combustion BAU Trajectory'!E94 -> 0.0020410545 | F5: ='Combustion BAU Trajectory'!F94 -> 0.0020410524 | G5: ='Combustion BAU Trajectory'!G94 -> 0.0020410504 | H5: ='Combustion BAU Trajectory'!H94 -> 0.0020410484 | I5: ='Combustion BAU Trajectory'!I94 -> 0.0020410463 | J5: ='Combustion BAU Trajectory'!J94 -> 0.0020410443 | ... AE5: ='Combustion BAU Trajectory'!AE94 -> 0.0020410017
A6: heat above 1000 C | B6: 0 | C6: ='Combustion BAU Trajectory'!C95 -> 0.0025932283 | D6: ='Combustion BAU Trajectory'!D95 -> 0.0025928711 | E6: ='Combustion BAU Trajectory'!E95 -> 0.0025925144 | F6: ='Combustion BAU Trajectory'!F95 -> 0.0025921581 | G6: ='Combustion BAU Trajectory'!G95 -> 0.0025918022 | H6: ='Combustion BAU Trajectory'!H95 -> 0.0025914467 | I6: ='Combustion BAU Trajectory'!I95 -> 0.0025910917 | J6: ='Combustion BAU Trajectory'!J95 -> 0.002590737 | ... AE6: ='Combustion BAU Trajectory'!AE95 -> 0.0025833864
A7: Cooling | B7: 0 | C7: =MECS!$M$7 -> 0.0025211684 | D7: =MECS!$M$7 -> 0.0025211684 | E7: =MECS!$M$7 -> 0.0025211684 | F7: =MECS!$M$7 -> 0.0025211684 | G7: =MECS!$M$7 -> 0.0025211684 | H7: =MECS!$M$7 -> 0.0025211684 | I7: =MECS!$M$7 -> 0.0025211684 | J7: =MECS!$M$7 -> 0.0025211684 | ... AE7: =MECS!$M$7 -> 0.0025211684
A8: Machine Drive | B8: 0 | C8: =MECS!$M$8 -> 0.005579341 | D8: =MECS!$M$8 -> 0.005579341 | E8: =MECS!$M$8 -> 0.005579341 | F8: =MECS!$M$8 -> 0.005579341 | G8: =MECS!$M$8 -> 0.005579341 | H8: =MECS!$M$8 -> 0.005579341 | I8: =MECS!$M$8 -> 0.005579341 | J8: =MECS!$M$8 -> 0.005579341 | ... AE8: =MECS!$M$8 -> 0.005579341
A9: Other process | B9: 0 | C9: =MECS!$M$11 -> 0.004867008 | D9: =MECS!$M$11 -> 0.004867008 | E9: =MECS!$M$11 -> 0.004867008 | F9: =MECS!$M$11 -> 0.004867008 | G9: =MECS!$M$11 -> 0.004867008 | H9: =MECS!$M$11 -> 0.004867008 | I9: =MECS!$M$11 -> 0.004867008 | J9: =MECS!$M$11 -> 0.004867008 | ... AE9: =MECS!$M$11 -> 0.004867008
A10: Facility HVAC | B10: 0 | C10: =C8 -> 0.005579341 | D10: =D8 -> 0.005579341 | E10: =E8 -> 0.005579341 | F10: =F8 -> 0.005579341 | G10: =G8 -> 0.005579341 | H10: =H8 -> 0.005579341 | I10: =I8 -> 0.005579341 | J10: =J8 -> 0.005579341 | ... AE10: =AE8 -> 0.005579341
A11: Facility lighting | B11: ='BIEEI-elec'!B11 -> 0 | C11: ='BIEEI-elec'!C11 -> 0.002057392 | D11: ='BIEEI-elec'!D11 -> 0.002057392 | E11: ='BIEEI-elec'!E11 -> 0.002057392 | F11: ='BIEEI-elec'!F11 -> 0.002057392 | G11: ='BIEEI-elec'!G11 -> 0.002057392 | H11: ='BIEEI-elec'!H11 -> 0.002057392 | I11: ='BIEEI-elec'!I11 -> 0.002057392 | ... AE11: ='BIEEI-elec'!AE11 -> 0.002057392
A12: Other nonprocess | B12: =AVERAGE(B2:B11) -> 0 | C12: =AVERAGE(C2:C11) -> 0.0031243623 | D12: =AVERAGE(D2:D11) -> 0.0031243263 | E12: =AVERAGE(E2:E11) -> 0.0031242904 | F12: =AVERAGE(F2:F11) -> 0.0031242545 | G12: =AVERAGE(G2:G11) -> 0.0031242187 | H12: =AVERAGE(H2:H11) -> 0.0031241829 | I12: =AVERAGE(I2:I11) -> 0.0031241472 | ... AE12: =AVERAGE(AE2:AE11) -> 0.0031233716
