Workbook

Sheet About
A1: VRSbRIC Vehicle Revenue Share by Recipient ISIC Code
A3: Sources: | B3: Passenger LDVs
B4: EPA
B5: 2009
B6: Automobile Industry Retail Price Equivalent and Indirect Cost Multipliers
B7: Link
B8: Table 3-3
B10: Freight LDVs and HDVs and Passenger HDVs
B11: EPA
B12: 2010
B13: Heavy Duty Truck Retail Price Equivalent and Indirect Cost Multipliers
B14: Link
B15: Table 3-3
A21: Notes: | B21: We assume the same cost breakdowns for all technologies, but assign non-road to non-road vehicle manufacturing
B22: The RPEF file also controls whether or not these values are used
A24: 42-code sibling (build_sector_shares_42):
B25: This workbook is the 42-code (un-split) sibling of the 52-code expansion. The 42 scheme is the 52 scheme with the six OECD-native parents
B26: left merged (ISIC 01T03, 07T08, 30, 49T53, 69T82, 90T96); the BEA carves ISIC 231/239 and 351/352T353 are retained (present in both
B27: schemes).
B29: The output tabs are the stock derivation, unchanged and live: the stock workbook is natively 42-code (its output columns already are the
B30: 42-code ISIC list, in canonical order), so no child split is applied here. The motorbike row is corrected to match LDVs: the stock file
B31: (4.0.6 and 4.1) pointed its ISIC 45T47 cell at the HDV dealer share, so the row summed to 0.890 instead of 1 (user decision 2026-07-20).

Sheet LDV Data
A1: Category | B1: Item | C1: Industy Average Total | D1: Industry Average RPE Only | E1: ISIC Code
A2: Vehicle Manufacturing | B2: Cost of Sales | C2: 1 | D2: N/A
A3: Production Overhead | B3: Warranty | C3: 0.03 | D3: =C3/($C$16-$C$2) -> 0.065217391 | E3: ISIC 29
A4: Production Overhead | B4: R&D (product dev) | C4: 0.05 | D4: =C4/($C$16-$C$2) -> 0.10869565 | E4: ISIC 29
A5: Production Overhead | B5: Depreciation and amortization | C5: 0.07 | D5: =C5/($C$16-$C$2) -> 0.15217391 | E5: ISIC 29
A6: Production Overhead | B6: Maintenance, repair, operations cost | C6: 0.03 | D6: =C6/($C$16-$C$2) -> 0.065217391 | E6: ISIC 29
A7: Corporate Overhead | B7: General and aministrative | C7: 0.07 | D7: =C7/($C$16-$C$2) -> 0.15217391 | E7: ISIC 29
A8: Corporate Overhead | B8: Retirement | C8: 0 | D8: =C8/($C$16-$C$2) -> 0 | E8: ISIC 29
A9: Corporate Overhead | B9: Health | C9: 0.01 | D9: =C9/($C$16-$C$2) -> 0.02173913 | E9: ISIC 29
A10: Selling | B10: Transportation | C10: 0.04 | D10: =C10/($C$16-$C$2) -> 0.086956522 | E10: ISIC 45T47
A11: Selling | B11: Marketing | C11: 0.04 | D11: =C11/($C$16-$C$2) -> 0.086956522 | E11: ISIC 45T47
A12: Dealers | B12: New vehicle net profit | C12: 0 | D12: =C12/($C$16-$C$2) -> 0 | E12: ISIC 45T47
A13: Dealers | B13: New vehicle selling cost | C13: 0.06 | D13: =C13/($C$16-$C$2) -> 0.13043478 | E13: ISIC 45T47
A14: Other | B14: Net income | C14: 0.06 | D14: =C14/($C$16-$C$2) -> 0.13043478 | E14: ISIC 29
A16: TOTAL | C16: =SUM(C2:C14) -> 1.46
A25: ISIC 01T03 | B25: {Agriculture, forestry and fishing}
A26: ISIC 05 | B26: {Coal mining}
A27: ISIC 06 | B27: {Oil and gas extraction}
A28: ISIC 07T08 | B28: {Mining and quarrying of non-energy producing products}
A29: ISIC 09 | B29: {Mining support service activities}
A30: ISIC 10T12 | B30: {Food products, beverages and tobacco}
A31: ISIC 13T15 | B31: {Textiles, wearing apparel, leather and related products}
A32: ISIC 16 | B32: {Wood and of products of wood and cork (except furniture)}
A33: ISIC 17T18 | B33: {Paper products and printing}
A34: ISIC 19 | B34: {Coke and refined petroleum products}
A35: ISIC 20 | B35: {Chemicals}
A36: ISIC 21 | B36: {Pharmaceuticals}
... A66: ISIC 97T98 | B66: {Private households with employed persons}

Sheet Checks
A1: Validation checks (42-code sibling)
A2: Allocation output rows sum to 1 across the 42 ISIC codes (rate files excluded — see note).
A4: VRSbRIC.csv
A5: LDVs | B5: =SUM(VRSbRIC!B2:AQ2) -> 1 | C5: =IF(ABS(B5-1)<0.000001,"=1",IF(ABS(B5)<0.000001,"=0","CHECK")) -> =1
A6: HDVs | B6: =SUM(VRSbRIC!B3:AQ3) -> 1 | C6: =IF(ABS(B6-1)<0.000001,"=1",IF(ABS(B6)<0.000001,"=0","CHECK")) -> =1
A7: aircraft | B7: =SUM(VRSbRIC!B4:AQ4) -> 1 | C7: =IF(ABS(B7-1)<0.000001,"=1",IF(ABS(B7)<0.000001,"=0","CHECK")) -> =1
A8: rail | B8: =SUM(VRSbRIC!B5:AQ5) -> 1 | C8: =IF(ABS(B8-1)<0.000001,"=1",IF(ABS(B8)<0.000001,"=0","CHECK")) -> =1
A9: ships | B9: =SUM(VRSbRIC!B6:AQ6) -> 1 | C9: =IF(ABS(B9-1)<0.000001,"=1",IF(ABS(B9)<0.000001,"=0","CHECK")) -> =1
A10: motorbike | B10: =SUM(VRSbRIC!B7:AQ7) -> 1 | C10: =IF(ABS(B10-1)<0.000001,"=1",IF(ABS(B10)<0.000001,"=0","CHECK")) -> =1

Sheet HDV Data
A1: Category | B1: Item | C1: Trauck Manufacturers Industry Average | D1: Industry Average RPE Only | E1: ISIC Code
A2: Vehicle Manufacturing | B2: Manufacturing Cost | C2: 1 | D2: N/A
A3: Production Overhead | B3: Warranty | C3: 0.04 | D3: =C3/($C$16-$C$2) -> 0.11111111 | E3: ISIC 29
A4: Production Overhead | B4: R&D (product dev) | C4: 0.05 | D4: =C4/($C$16-$C$2) -> 0.13888889 | E4: ISIC 29
A5: Production Overhead | B5: Depreciation and amortization | C5: 0.04 | D5: =C5/($C$16-$C$2) -> 0.11111111 | E5: ISIC 29
A6: Production Overhead | B6: Maintenance, repair, operations cost | C6: 0.02 | D6: =C6/($C$16-$C$2) -> 0.055555556 | E6: ISIC 29
A7: Corporate Overhead | B7: General and aministrative | C7: 0.07 | D7: =C7/($C$16-$C$2) -> 0.19444444 | E7: ISIC 29
A8: Corporate Overhead | B8: Retirement | C8: 0.01 | D8: =C8/($C$16-$C$2) -> 0.027777778 | E8: ISIC 29
A9: Corporate Overhead | B9: Health | C9: 0.01 | D9: =C9/($C$16-$C$2) -> 0.027777778 | E9: ISIC 29
A10: Selling | B10: Transportation | C10: 0 | D10: =C10/($C$16-$C$2) -> 0 | E10: ISIC 45T47
A11: Selling | B11: Marketing | C11: 0.01 | D11: =C11/($C$16-$C$2) -> 0.027777778 | E11: ISIC 45T47
A12: Dealers | B12: Dealer new vehicle net income | C12: 0 | D12: =C12/($C$16-$C$2) -> 0 | E12: ISIC 45T47
A13: Dealers | B13: Dealer new vehicle selling expense | C13: 0.06 | D13: =C13/($C$16-$C$2) -> 0.16666667 | E13: ISIC 45T47
A14: Other | B14: Net income | C14: 0.05 | D14: =C14/($C$16-$C$2) -> 0.13888889 | E14: ISIC 29
A16: TOTAL | C16: =SUM(C2:C14) -> 1.36
A25: ISIC 01T03 | B25: {Agriculture, forestry and fishing}
A26: ISIC 05 | B26: {Coal mining}
A27: ISIC 06 | B27: {Oil and gas extraction}
A28: ISIC 07T08 | B28: {Mining and quarrying of non-energy producing products}
A29: ISIC 09 | B29: {Mining support service activities}
A30: ISIC 10T12 | B30: {Food products, beverages and tobacco}
A31: ISIC 13T15 | B31: {Textiles, wearing apparel, leather and related products}
A32: ISIC 16 | B32: {Wood and of products of wood and cork (except furniture)}
A33: ISIC 17T18 | B33: {Paper products and printing}
A34: ISIC 19 | B34: {Coke and refined petroleum products}
A35: ISIC 20 | B35: {Chemicals}
A36: ISIC 21 | B36: {Pharmaceuticals}
... A66: ISIC 97T98 | B66: {Private households with employed persons}

Sheet VRSbRIC
A1: Vehicle Type | B1: ISIC 01T03 | C1: ISIC 05 | D1: ISIC 06 | E1: ISIC 07T08 | F1: ISIC 09 | G1: ISIC 10T12 | H1: ISIC 13T15 | I1: ISIC 16 | J1: ISIC 17T18 | K1: ISIC 19 | L1: ISIC 20 | M1: ISIC 21 | N1: ISIC 22 | O1: ISIC 231 | P1: ISIC 239 | Q1: ISIC 241 | R1: ISIC 242 | S1: ISIC 25 | T1: ISIC 26 | U1: ISIC 27 | V1: ISIC 28 | W1: ISIC 29 | X1: ISIC 30 | Y1: ISIC 31T33 | Z1: ISIC 351 | AA1: ISIC 352T353 | AB1: ISIC 36T39 | AC1: ISIC 41T43 | AD1: ISIC 45T47 | AE1: ISIC 49T53 | AF1: ISIC 55T56 | AG1: ISIC 58T60 | AH1: ISIC 61 | AI1: ISIC 62T63 | AJ1: ISIC 64T66 | AK1: ISIC 68 | AL1: ISIC 69T82 | AM1: ISIC 84 | AN1: ISIC 85 | AO1: ISIC 86T88 | AP1: ISIC 90T96 | AQ1: ISIC 97T98
A2: LDVs | B2: =SUMIFS('LDV Data'!$D$3:$D$14,'LDV Data'!$E$3:$E$14,B1) -> 0 | C2: =SUMIFS('LDV Data'!$D$3:$D$14,'LDV Data'!$E$3:$E$14,C1) -> 0 | D2: =SUMIFS('LDV Data'!$D$3:$D$14,'LDV Data'!$E$3:$E$14,D1) -> 0 | E2: =SUMIFS('LDV Data'!$D$3:$D$14,'LDV Data'!$E$3:$E$14,E1) -> 0 | F2: =SUMIFS('LDV Data'!$D$3:$D$14,'LDV Data'!$E$3:$E$14,F1) -> 0 | G2: =SUMIFS('LDV Data'!$D$3:$D$14,'LDV Data'!$E$3:$E$14,G1) -> 0 | H2: =SUMIFS('LDV Data'!$D$3:$D$14,'LDV Data'!$E$3:$E$14,H1) -> 0 | I2: =SUMIFS('LDV Data'!$D$3:$D$14,'LDV Data'!$E$3:$E$14,I1) -> 0 | ... AQ2: =SUMIFS('LDV Data'!$D$3:$D$14,'LDV Data'!$E$3:$E$14,AQ1) -> 0
A3: HDVs | B3: =SUMIFS('HDV Data'!$D$3:$D$14,'HDV Data'!$E$3:$E$14,B1) -> 0 | C3: =SUMIFS('HDV Data'!$D$3:$D$14,'HDV Data'!$E$3:$E$14,C1) -> 0 | D3: =SUMIFS('HDV Data'!$D$3:$D$14,'HDV Data'!$E$3:$E$14,D1) -> 0 | E3: =SUMIFS('HDV Data'!$D$3:$D$14,'HDV Data'!$E$3:$E$14,E1) -> 0 | F3: =SUMIFS('HDV Data'!$D$3:$D$14,'HDV Data'!$E$3:$E$14,F1) -> 0 | G3: =SUMIFS('HDV Data'!$D$3:$D$14,'HDV Data'!$E$3:$E$14,G1) -> 0 | H3: =SUMIFS('HDV Data'!$D$3:$D$14,'HDV Data'!$E$3:$E$14,H1) -> 0 | I3: =SUMIFS('HDV Data'!$D$3:$D$14,'HDV Data'!$E$3:$E$14,I1) -> 0 | ... AQ3: =SUMIFS('HDV Data'!$D$3:$D$14,'HDV Data'!$E$3:$E$14,AQ1) -> 0
A4: aircraft | B4: =B3 -> 0 | C4: =C3 -> 0 | D4: =D3 -> 0 | E4: =E3 -> 0 | F4: =F3 -> 0 | G4: =G3 -> 0 | H4: =H3 -> 0 | I4: =I3 -> 0 | ... V4: =V3 -> 0 | W4: 0 | X4: =W3 -> 0.80555556 | Y4: =Y3 -> 0 | Z4: =Z3 -> 0 | AA4: =AA3 -> 0 | AB4: =AB3 -> 0 | AC4: =AC3 -> 0 | AD4: =AD3 -> 0.19444444 | AE4: =AE3 -> 0 | AF4: =AF3 -> 0 | ... AQ4: =AQ3 -> 0
A5: rail | B5: =B4 -> 0 | C5: =C4 -> 0 | D5: =D4 -> 0 | E5: =E4 -> 0 | F5: =F4 -> 0 | G5: =G4 -> 0 | H5: =H4 -> 0 | I5: =I4 -> 0 | ... V5: =V4 -> 0 | W5: 0 | X5: =X4 -> 0.80555556 | Y5: =Y4 -> 0 | Z5: =Z4 -> 0 | AA5: =AA4 -> 0 | AB5: =AB4 -> 0 | AC5: =AC4 -> 0 | AD5: =AD4 -> 0.19444444 | AE5: =AE4 -> 0 | ... AQ5: =AQ4 -> 0
A6: ships | B6: =B5 -> 0 | C6: =C5 -> 0 | D6: =D5 -> 0 | E6: =E5 -> 0 | F6: =F5 -> 0 | G6: =G5 -> 0 | H6: =H5 -> 0 | I6: =I5 -> 0 | ... V6: =V5 -> 0 | W6: 0 | X6: =X5 -> 0.80555556 | Y6: =Y5 -> 0 | Z6: =Z5 -> 0 | AA6: =AA5 -> 0 | AB6: =AB5 -> 0 | AC6: =AC5 -> 0 | AD6: =AD5 -> 0.19444444 | AE6: =AE5 -> 0 | ... AQ6: =AQ5 -> 0
A7: motorbike | B7: =B6 -> 0 | C7: =C6 -> 0 | D7: =D6 -> 0 | E7: =E6 -> 0 | F7: =F6 -> 0 | G7: =G6 -> 0 | H7: =H6 -> 0 | I7: =I6 -> 0 | ... V7: =V6 -> 0 | W7: =W2 -> 0.69565217 | X7: 0 | Y7: =Y6 -> 0 | Z7: =Z6 -> 0 | AA7: =AA6 -> 0 | AB7: =AB6 -> 0 | AC7: =AC6 -> 0 | AD7: =SUMIFS('LDV Data'!$D$3:$D$14,'LDV Data'!$E$3:$E$14,AD1) -> 0.30434783 | AE7: =AE6 -> 0 | AF7: =AF6 -> 0 | AG7: =AG6 -> 0 | AH7: =AH6 -> 0 | AI7: =AI6 -> 0 | AJ7: =AJ6 -> 0 | AK7: =AK6 -> 0 | AL7: =AL6 -> 0 | ... AQ7: =AQ6 -> 0
