Workbook

Sheet About
A1: BIISRP BAU Individual Industrial Site Retirement Profiles
A2: BIISRP Boolean Use Individual Industrial Site Retirement Profiles
A4: Source: | B4: Iron & steelmaking plants
B5: Global Energy Monitor
B6: 2025
B7: Global Iron and Steel Tracker (September 2025 release)
B8: https://globalenergymonitor.org/projects/global-iron-and-steel-tracker/dashboard/
B9: Multiple tables
A12: Notes
A13: This file allows the user to define explicit retirement profiles for specific industries.
A14: In small regions, there may be a limited number of facilities of a certain type -- for
A15: example, one integrated steelmaking plant. Therefore, using a smooth retirement curve
A16: as defined in indst/IESD might not reflect the quantized retirement that would be expected.
A18: Instead, you can use this file to define an explicit retirement profile. Maybe that one
A19: integrated plant will phase down from 2028 to 2030. You can use this file to define that
A20: retirement curve.

Sheet Steel ->

Sheet Plant data
A1: Plant ID | B1: Plant name (English) | C1: Owner GEM ID | D1: Municipality | E1: Subnational unit (province/state) | F1: Country/Area | G1: Region | H1: GEM wiki page | I1: Plant age (years) | J1: Announced date | K1: Construction date | L1: Start date | M1: Pre-retirement announcement date | N1: Idled date | O1: Retired date | P1: Main production equipment | Q1: Power source | R1: Most Recent Relining
A2: P100000120004 | B2: Kurum International Elbasan steel plant | C2: E100000130992 | D2: Bradashesh | E2: Elbasan | F2: Albania | G2: Europe | H2: https://www.gem.wiki/Kurum_International_Elbasan_steel_plant | I2: 27 | J2: unknown | K2: unknown | L2: 1998 | M2: unknown | N2: unknown | O2: unknown | P2: EAF | Q2: Hydraulic, integrated plants; Four hydropower plants used as captive power plants | R2: =INDEX('Blast furnaces'!$R:$R,MATCH(A2,'Blast furnaces'!$A:$A,0)) -> #N/A
A3: P100000120439 | B3: Algerian Qatari Steel Jijel plant | C3: E100001000957 | D3: El-Milia | E3: Jijel | F3: Algeria | G3: Africa | H3: https://www.gem.wiki/Algerian_Qatari_Steel_Jijel_plant | I3: 8 | J3: 2013 | K3: 2015 | L3: 2017 | M3: unknown | N3: unknown | O3: unknown | P3: EAF; DRI | Q3: unknown | R3: =INDEX('Blast furnaces'!$R:$R,MATCH(A3,'Blast furnaces'!$A:$A,0)) -> #N/A
A4: P100000120442 | B4: ETRHB Annaba steel plant | C4: E100001010275 | D4: Berrahal | E4: Annaba | F4: Algeria | G4: Africa | H4: https://www.gem.wiki/ETRHB_Annaba_steel_plant | I4: unknown | J4: 2017 | K4: 2018 | L4: unknown | M4: unknown | N4: unknown | O4: 44958 | P4: EAF | Q4: unknown | R4: =INDEX('Blast furnaces'!$R:$R,MATCH(A4,'Blast furnaces'!$A:$A,0)) -> #N/A
A5: P100000121198 | B5: Ozmert Algeria steel plant | C5: E100001012196 | D5: Tebessa | E5: Tebessa | F5: Algeria | G5: Africa | H5: https://www.gem.wiki/Ozmert_Algeria_Steel_Plant | I5: unknown | J5: unknown | K5: unknown | L5: unknown | M5: unknown | N5: unknown | O5: unknown | P5: EAF; DRI | Q5: unknown | R5: =INDEX('Blast furnaces'!$R:$R,MATCH(A5,'Blast furnaces'!$A:$A,0)) -> #N/A
A6: P100000120440 | B6: Sider El Hadjar Annaba steel plant | C6: E100001000960 | D6: Sidi Amar | E6: Annaba | F6: Algeria | G6: Africa | H6: https://www.gem.wiki/Sider_El_Hadjar_Annaba_steel_plant | I6: 56 | J6: 1964 | K6: unknown | L6: 1969 | M6: unknown | N6: unknown | O6: unknown | P6: BF; BOF; EAF; DRI | Q6: unknown | R6: =INDEX('Blast furnaces'!$R:$R,MATCH(A6,'Blast furnaces'!$A:$A,0)) -> 0
A7: P100000120441 | B7: Tosyali Algerie Oran steel plant | C7: E100000131071 | D7: Bethiqua | E7: Oran | F7: Algeria | G7: Africa | H7: https://www.gem.wiki/Tosyali_Algerie_Oran_steel_plant | I7: 12 | J7: unknown | K7: unknown | L7: 2013 | M7: unknown | N7: unknown | O7: unknown | P7: EAF; DRI | Q7: unknown | R7: =INDEX('Blast furnaces'!$R:$R,MATCH(A7,'Blast furnaces'!$A:$A,0)) -> #N/A
A8: P100000120005 | B8: Aceria Angola Bengo steel plant | C8: E100000131097 | D8: Barra de Dande | E8: Bengo | F8: Angola | G8: Africa | H8: https://www.gem.wiki/Aceria_Angola_Bengo_steel_plant | I8: 10 | J8: unknown | K8: 2013 | L8: 2015 | M8: unknown | N8: unknown | O8: unknown | P8: Steel other/unspecified | Q8: 50 km transmission line (220kV electricity) | R8: =INDEX('Blast furnaces'!$R:$R,MATCH(A8,'Blast furnaces'!$A:$A,0)) -> #N/A
A9: P100000121215 | B9: Companhia Siderurgica do Cuchi pig iron plant | C9: E100001012404 | D9: Cuchi | E9: Cuando Cubango | F9: Angola | G9: Africa | H9: https://www.gem.wiki/Companhia_Siderurgica_do_Cuchi_pig_iron_plant | I9: 2.03 | J9: unknown | K9: unknown | L9: 45170 | M9: unknown | N9: unknown | O9: unknown | P9: BF | Q9: 15 MW captive thermoelectric plant | R9: =INDEX('Blast furnaces'!$R:$R,MATCH(A9,'Blast furnaces'!$A:$A,0)) -> 0
A10: P100001042927 | B10: Tosyali Sonangol Kassinga Iron and Steel Plant | C10: E100002003752; E100000000004 | D10: Kassinga | E10: Huíla | F10: Angola | G10: Africa | H10: https://www.gem.wiki/Tosyali_Sonangol_Kassinga_Iron_and_Steel_Plant | J10: 2019 | K10: unknown | L10: 2027 | M10: unknown | N10: unknown | O10: unknown | P10: EAF; DRI | Q10: unknown | R10: =INDEX('Blast furnaces'!$R:$R,MATCH(A10,'Blast furnaces'!$A:$A,0)) -> #N/A
A11: P100000120006 | B11: ArcelorMittal Acindar Villa Constitución steel plant | C11: E100001010109 | D11: Villa Constitución | E11: Santa Fe | F11: Argentina | G11: Central & South America | H11: https://www.gem.wiki/ArcelorMittal_Acindar_Villa_Constitución_steel_plant | I11: 79 | J11: unknown | K11: unknown | L11: 1946 | M11: unknown | N11: unknown | O11: unknown | P11: EAF; DRI | Q11: Signed agreement with Petroquimica Comodoro Rivadavia (PCR) to invest $140 million in a renewable energy project in the San Luis Norte wind farm. | R11: =INDEX('Blast furnaces'!$R:$R,MATCH(A11,'Blast furnaces'!$A:$A,0)) -> #N/A
A12: P100000120009 | B12: Gerdau Sipar Pérez steel plant | C12: E100001010274 | D12: Pérez | E12: Santa Fe | F12: Argentina | G12: Central & South America | H12: https://www.gem.wiki/Gerdau_Sipar_Pérez_steel_plant | I12: 8 | J12: unknown | K12: unknown | L12: 2017 | M12: unknown | N12: unknown | O12: unknown | P12: EAF | Q12: unknown | R12: =INDEX('Blast furnaces'!$R:$R,MATCH(A12,'Blast furnaces'!$A:$A,0)) -> #N/A
A13: P100000120007 | B13: TenarisSiderca Campana steel plant | C13: E100000001765 | D13: Campana | E13: Buenos Aires | F13: Argentina | G13: Central & South America | H13: https://www.gem.wiki/TenarisSiderca_Campana_steel_plant | I13: 65.13 | J13: unknown | K13: unknown | L13: 22122 | M13: unknown | N13: unknown | O13: unknown | P13: EAF; DRI | Q13: Since Oct 2023, The Buena Ventura wind farm now supplies 100 MW of power, through the interconnected grid, to our industrial facilities in Campana, meeting close to 50% of its total electric power requirements and contributing to a lower energy costs. | R13: =INDEX('Blast furnaces'!$R:$R,MATCH(A13,'Blast furnaces'!$A:$A,0)) -> #N/A
A14: P100000120008 | B14: Ternium Siderar San Nicolás steel plant | C14: E100000130688 | D14: San Nicolás de los Arroyos | E14: Buenos Aires | F14: Argentina | G14: Central & South America | H14: https://www.gem.wiki/Ternium_Siderar_San_Nicolás_steel_plant | I14: 65 | J14: unknown | K14: unknown | L14: 1960 | M14: unknown | N14: unknown | O14: unknown | P14: BF; BOF | Q14: Thermoelectric, integrated | R14: =INDEX('Blast furnaces'!$R:$R,MATCH(A14,'Blast furnaces'!$A:$A,0)) -> 39448
A15: P100000120012 | B15: BlueScope Port Kembla steel plant | C15: E100000130689 | D15: Port Kembla | E15: New South Wales | F15: Australia | G15: Asia Pacific | H15: https://www.gem.wiki/BlueScope_Port_Kembla_steel_plant | I15: 97 | J15: unknown | K15: 1926 | L15: 1928 | M15: unknown | N15: unknown | O15: unknown | P15: BF; BOF | Q15: unknown | R15: =INDEX('Blast furnaces'!$R:$R,MATCH(A15,'Blast furnaces'!$A:$A,0)) -> 40026
A16: P100001043035 | B16: Fortescue Christmas Creek Green Metal Project | C16: E100001011127 | D16: Christmas Creek | E16: Western Australia | F16: Australia | G16: Asia Pacific | H16: https://www.gem.wiki/Fortescue_Christmas_Creek_Green_Metal_Project | I16: 0 | J16: unknown | K16: 45505 | L16: 2025 | M16: unknown | N16: unknown | O16: unknown | P16: Iron other/unspecified | Q16: Solar Power | R16: =INDEX('Blast furnaces'!$R:$R,MATCH(A16,'Blast furnaces'!$A:$A,0)) -> #N/A
A17: P100000120014 | B17: GFG Liberty Laverton Steel Mill | C17: E100001010334 | D17: Laverton | E17: Victoria | F17: Australia | G17: Asia Pacific | H17: https://www.gem.wiki/GFG_Liberty_Laverton_Steel_Mill | I17: 33 | J17: unknown | K17: unknown | L17: 1992 | M17: unknown | N17: unknown | O17: unknown | P17: EAF | Q17: 128 MW Numurkah Solar Farm | R17: =INDEX('Blast furnaces'!$R:$R,MATCH(A17,'Blast furnaces'!$A:$A,0)) -> #N/A
A18: P100000120013 | B18: GFG Liberty Steel Australia Whyalla steel plant | C18: E100001000556 | D18: Whyalla | E18: South Australia | F18: Australia | G18: Asia Pacific | H18: https://www.gem.wiki/GFG_Liberty_Steel_Australia_Whyalla_steel_plant | I18: 84 | J18: unknown | K18: unknown | L18: 1941 | M18: unknown | N18: unknown | O18: unknown | P18: BF; BOF; EAF; DRI | Q18: 66.5 MW Captive Power Plant; South Australian Grid, Santos (gas supplier) | R18: =INDEX('Blast furnaces'!$R:$R,MATCH(A18,'Blast furnaces'!$A:$A,0)) -> 40695
A19: P100000120015 | B19: GFG Liberty Sydney Steel Mill | C19: E100001010334 | D19: Rooty Hill | E19: New South Wales | F19: Australia | G19: Asia Pacific | H19: https://www.gem.wiki/GFG_Liberty_Sydney_Steel_Mill | I19: 43 | J19: unknown | K19: unknown | L19: 1982 | M19: unknown | N19: unknown | O19: unknown | P19: EAF | Q19: unknown | R19: =INDEX('Blast furnaces'!$R:$R,MATCH(A19,'Blast furnaces'!$A:$A,0)) -> #N/A
A20: P100000121147 | B20: Green Steel of WA Collie Steel plant | C20: E100001012187 | D20: Collie | E20: Western Australia | F20: Australia | G20: Asia Pacific | H20: https://www.gem.wiki/Green_Steel_of_WA_Collie_Steel_plant | J20: 2022 | K20: 2024 | L20: 2026 | M20: unknown | N20: unknown | O20: unknown | P20: EAF | Q20: renewable electricity | R20: =INDEX('Blast furnaces'!$R:$R,MATCH(A20,'Blast furnaces'!$A:$A,0)) -> #N/A
A21: P100000121163 | B21: Green Steel of WA Geraldton Steel plant | C21: E100001012187 | D21: Geraldton | E21: Mid-West Australia | F21: Australia | G21: Asia Pacific | H21: https://www.gem.wiki/Green_Steel_of_WA_Geraldton_Steel_plant | J21: 45039 | K21: unknown | L21: 2027 | M21: unknown | N21: unknown | O21: unknown | P21: DRI | Q21: Renewable energy | R21: =INDEX('Blast furnaces'!$R:$R,MATCH(A21,'Blast furnaces'!$A:$A,0)) -> #N/A
A22: P100001026026 | B22: GreenSteel Australia New South Wales Steel Plant | C22: E100000131094 | D22: Wollongong | E22: New South Wales | F22: Australia | G22: Asia Pacific | H22: https://www.gem.wiki/GreenSteel_Australia_New_South_Wales_Steel_Plant | J22: unknown | K22: 2025 | L22: 2026 | M22: unknown | N22: unknown | O22: unknown | P22: EAF; DRI | Q22: Renewable energy | R22: =INDEX('Blast furnaces'!$R:$R,MATCH(A22,'Blast furnaces'!$A:$A,0)) -> #N/A
A23: P100000121161 | B23: POSCO Port Hedland Iron Project | C23: E100002009156 | D23: Boodarie Strategic Industrial Area | E23: Western Australia | F23: Australia | G23: Asia Pacific | H23: https://www.gem.wiki/POSCO_Port_Hedland_Steel_Plant | J23: 44682 | K23: 2025 | L23: 2028 | M23: unknown | N23: unknown | O23: unknown | P23: DRI | Q23: renewable energy project in Pilbara with Engie | R23: =INDEX('Blast furnaces'!$R:$R,MATCH(A23,'Blast furnaces'!$A:$A,0)) -> #N/A
A24: P100000120011 | B24: Voestalpine Stahl Donawitz steel plant | C24: E100000130917 | D24: Leoben | E24: Styria | F24: Austria | G24: Europe | H24: https://www.gem.wiki/Voestalpine_Stahl_Donawitz_steel_plant | I24: 147 | J24: unknown | K24: unknown | L24: 1878 | M24: unknown | N24: unknown | O24: unknown | P24: BF; BOF; EAF; DRI | Q24: Captive power plant | R24: =INDEX('Blast furnaces'!$R:$R,MATCH(A24,'Blast furnaces'!$A:$A,0)) -> 43368
A25: P100000120010 | B25: Voestalpine Stahl Linz steel plant | C25: E100000130978 | D25: Linz | E25: Upper Austria | F25: Austria | G25: Europe | H25: https://www.gem.wiki/Voestalpine_Stahl_Linz_steel_plant | I25: 85 | J25: unknown | K25: unknown | L25: 1940 | M25: unknown | N25: unknown | O25: unknown | P25: BF; BOF; EAF | Q25: unknown | R25: =INDEX('Blast furnaces'!$R:$R,MATCH(A25,'Blast furnaces'!$A:$A,0)) -> 43344
A26: P100000121043 | B26: Azerbaijan Integrated Steel Mill Complex | C26: E100000131069 | D26: Ganja | E26: Ganja-Dashkasan | F26: Azerbaijan | G26: Eurasia | H26: https://www.gem.wiki/Azerbaijan_Integrated_Steel_Mill_Complex | I26: unknown | J26: 2018 | K26: unknown | L26: unknown | M26: unknown | N26: unknown | O26: unknown | P26: EAF; DRI | Q26: unknown | R26: =INDEX('Blast furnaces'!$R:$R,MATCH(A26,'Blast furnaces'!$A:$A,0)) -> #N/A
A27: P100000120016 | B27: Baku Steel Company steel plant | C27: E100000131003 | D27: Baku | E27: Narimanov | F27: Azerbaijan | G27: Eurasia | H27: https://www.gem.wiki/Baku_Steel_Company_steel_plant | I27: 24 | J27: unknown | K27: unknown | L27: 2001 | M27: unknown | N27: unknown | O27: unknown | P27: EAF | Q27: unknown | R27: =INDEX('Blast furnaces'!$R:$R,MATCH(A27,'Blast furnaces'!$A:$A,0)) -> #N/A
A28: P100000120032 | B28: Sulb Bahrain Al Hidd steel plant | C28: E100000131139 | D28: Al Hidd | E28: Muharraq | F28: Bahrain | G28: Middle East | H28: https://www.gem.wiki/Sulb_Bahrain_Al_Hidd_steel_plant | I28: 13 | J28: 2009 | K28: unknown | L28: 2012 | M28: unknown | N28: unknown | O28: unknown | P28: EAF; DRI | Q28: unknown | R28: =INDEX('Blast furnaces'!$R:$R,MATCH(A28,'Blast furnaces'!$A:$A,0)) -> #N/A
A29: P100000120020 | B29: Abul Khair Steel Sitakunda plant | C29: E100000131068 | D29: Sitakunda | E29: Chittagong | F29: Bangladesh | G29: Asia Pacific | H29: https://www.gem.wiki/Abul_Khair_Steel_Sitakunda_plant | I29: 10 | J29: unknown | K29: unknown | L29: 2015 | M29: unknown | N29: unknown | O29: unknown | P29: EAF | Q29: unknown | R29: =INDEX('Blast furnaces'!$R:$R,MATCH(A29,'Blast furnaces'!$A:$A,0)) -> #N/A
A30: P100000120019 | B30: Bashundhara Steel Mirsarai plant | C30: E100002006720 | D30: Mirsarai | E30: Chittagong | F30: Bangladesh | G30: Asia Pacific | H30: https://www.gem.wiki/Bashundhara_Steel_Mirsarai_plant | J30: 2020 | K30: 44805 | L30: 2026 | M30: unknown | N30: unknown | O30: unknown | P30: EAF; DRI | Q30: unknown | R30: =INDEX('Blast furnaces'!$R:$R,MATCH(A30,'Blast furnaces'!$A:$A,0)) -> #N/A
A31: P100000120022 | B31: BSRM Ltd Mirsarai plant | C31: E100000120118 | D31: Mirsarai | E31: Chattogram | F31: Bangladesh | G31: Asia Pacific | H31: https://www.gem.wiki/BSRM_Ltd_Mirsarai_plant | I31: 9.28 | J31: unknown | K31: unknown | L31: 42522 | M31: unknown | N31: unknown | O31: unknown | P31: Steel other/unspecified | Q31: unknown | R31: =INDEX('Blast furnaces'!$R:$R,MATCH(A31,'Blast furnaces'!$A:$A,0)) -> #N/A
A32: P100000120021 | B32: BSRM Steels Mirsarai plant | C32: E100000130854 | D32: Mirsarai | E32: Chattogram | F32: Bangladesh | G32: Asia Pacific | H32: https://www.gem.wiki/BSRM_Steels_Mirsarai_plant | I32: 6 | J32: 2016 | K32: unknown | L32: 2019 | M32: unknown | N32: unknown | O32: unknown | P32: Steel other/unspecified | Q32: unknown | R32: =INDEX('Blast furnaces'!$R:$R,MATCH(A32,'Blast furnaces'!$A:$A,0)) -> #N/A
A33: P100000120018 | B33: GPH Steel Sitakunda plant | C33: E100000130987 | D33: Kumira | E33: Chittagong | F33: Bangladesh | G33: Asia Pacific | H33: https://www.gem.wiki/GPH_Steel_Sitakunda_plant | I33: 17.05 | J33: unknown | K33: unknown | L33: 39681 | M33: unknown | N33: unknown | O33: unknown | P33: EAF; Steel other/unspecified | Q33: Captive power plant | R33: =INDEX('Blast furnaces'!$R:$R,MATCH(A33,'Blast furnaces'!$A:$A,0)) -> #N/A
A34: P100000120024 | B34: KSRM Sitakunda steel plant | C34: E100000131041 | D34: Sitakunda | E34: Chittagong | F34: Bangladesh | G34: Asia Pacific | H34: https://www.gem.wiki/KSRM_Sitakunda_steel_plant | I34: 41 | J34: unknown | K34: unknown | L34: 1984 | M34: unknown | N34: unknown | O34: unknown | P34: EAF | Q34: 56MW gas-based Captive Power plant | R34: =INDEX('Blast furnaces'!$R:$R,MATCH(A34,'Blast furnaces'!$A:$A,0)) -> #N/A
A35: P100001042845 | B35: Megnha Re-rolling and Steel Mills steel plant | C35: E100002005771 | D35: Meghna | E35: Chittagong | F35: Bangladesh | G35: Asia Pacific | H35: https://www.gem.wiki/Megnha_Re-rolling_and_Steel_Mills_steel_plant | I35: unknown | J35: 45525 | K35: unknown | L35: unknown | M35: unknown | N35: unknown | O35: unknown | P35: EAF | Q35: unknown | R35: =INDEX('Blast furnaces'!$R:$R,MATCH(A35,'Blast furnaces'!$A:$A,0)) -> #N/A
A36: P100000120025 | B36: Star Consortium steel plant | C36: E100000131025 | D36: Mirsarai | E36: Chittagong | F36: Bangladesh | G36: Asia Pacific | H36: https://www.gem.wiki/Star_Consortium_steel_plant | I36: 2 | J36: 42856 | K36: unknown | L36: 2023 | M36: unknown | N36: unknown | O36: unknown | P36: BF; BOF | Q36: 167 MW coal-fired power plant | R36: =INDEX('Blast furnaces'!$R:$R,MATCH(A36,'Blast furnaces'!$A:$A,0)) -> 0
A37: P100001042855 | B37: Unitex Steel Mills Feni steel plant | C37: E100002005773 | D37: Muhuriganj | E37: Chittagong | F37: Bangladesh | G37: Asia Pacific | H37: https://www.gem.wiki/Unitex_Steel_Mills_Feni_steel_plant | I37: unknown | J37: 2020-19-18 | K37: 45231 | L37: unknown | M37: unknown | N37: unknown | O37: unknown | P37: EAF | Q37: Korerhat 400/230/132/33 kV Substation of PGCB | R37: =INDEX('Blast furnaces'!$R:$R,MATCH(A37,'Blast furnaces'!$A:$A,0)) -> #N/A
A38: P100000120056 | B38: Byelorussian Steel Works | C38: E100000130960 | D38: Zhlobin | E38: Gomel Region | F38: Belarus | G38: Europe | H38: https://www.gem.wiki/Byelorussian_Steel_Works | I38: 41 | J38: unknown | K38: unknown | L38: 1984 | M38: unknown | N38: unknown | O38: unknown | P38: EAF | Q38: Lukoml GRES power station | R38: =INDEX('Blast furnaces'!$R:$R,MATCH(A38,'Blast furnaces'!$A:$A,0)) -> #N/A
A39: P100000120029 | B39: Aperam Stainless Belgium Châtelet steel plant | C39: E100000130918 | D39: Châtelet | E39: Wallonie | F39: Belgium | G39: Europe | H39: https://www.gem.wiki/Aperam_Stainless_Belgium_Châtelet_steel_plant | I39: 49 | J39: unknown | K39: unknown | L39: 1976 | M39: unknown | N39: unknown | O39: unknown | P39: EAF | Q39: unknown | R39: =INDEX('Blast furnaces'!$R:$R,MATCH(A39,'Blast furnaces'!$A:$A,0)) -> #N/A
A40: P100000120028 | B40: Aperam Stainless Belgium Genk steel plant | C40: E100000130918 | D40: Genk | E40: Limburg | F40: Belgium | G40: Europe | H40: https://www.gem.wiki/Aperam_Stainless_Belgium_Genk_steel_plant | I40: 55 | J40: unknown | K40: unknown | L40: 1970 | M40: unknown | N40: unknown | O40: unknown | P40: EAF | Q40: unknown | R40: =INDEX('Blast furnaces'!$R:$R,MATCH(A40,'Blast furnaces'!$A:$A,0)) -> #N/A
A41: P100000120027 | B41: ArcelorMittal Gent steel plant | C41: E100000000687 | D41: Gent | E41: Vlaanderen | F41: Belgium | G41: Europe | H41: https://www.gem.wiki/ArcelorMittal_Gent_steel_plant | I41: 59 | J41: unknown | K41: unknown | L41: 1966 | M41: unknown | N41: unknown | O41: unknown | P41: BF; BOF; EAF; DRI | Q41: Committed to purchasing all electricity generated at the Storm wind farm being built on the site for the next 20 years . | R41: =INDEX('Blast furnaces'!$R:$R,MATCH(A41,'Blast furnaces'!$A:$A,0)) -> 44256
A42: P100000120030 | B42: Thy Marcinelle Charleroi steel plant | C42: E100001010367 | D42: Charleroi | E42: Wallonie | F42: Belgium | G42: Europe | H42: https://www.gem.wiki/Thy_Marcinelle_Charleroi_steel_plant | I42: 36 | J42: unknown | K42: unknown | L42: 1989 | M42: unknown | N42: unknown | O42: unknown | P42: EAF | Q42: unknown | R42: =INDEX('Blast furnaces'!$R:$R,MATCH(A42,'Blast furnaces'!$A:$A,0)) -> #N/A
A43: P100000121153 | B43: ESM Mutún steel plant | C43: E100002000080 | D43: Puerto Suárez | E43: Santa Cruz | F43: Bolivia | G43: Central & South America | H43: https://www.gem.wiki/ESM_Mutún_steel_plant | I43: 0.53 | J43: 42430 | K43: 43466 | L43: 45717 | M43: unknown | N43: unknown | O43: unknown | P43: EAF; DRI | Q43: onsite power plant | R43: =INDEX('Blast furnaces'!$R:$R,MATCH(A43,'Blast furnaces'!$A:$A,0)) -> #N/A
A44: P100000120017 | B44: Pavgord Zenica steel plant | C44: E100001013687 | D44: Zenica | E44: Zenica-Doboj | F44: Bosnia and Herzegovina | G44: Europe | H44: https://www.gem.wiki/ArcelorMittal_Zenica_steel_plant | I44: 133 | J44: unknown | K44: unknown | L44: 1892 | M44: unknown | N44: unknown | O44: unknown | P44: BF; BOF; EAF | Q44: Toplana Zenica | R44: =INDEX('Blast furnaces'!$R:$R,MATCH(A44,'Blast furnaces'!$A:$A,0)) -> 43252
A45: P100000120053 | B45: Aperam Timóteo steel plant | C45: E100000130690 | D45: Timóteo | E45: Minas Gerais | F45: Brazil | G45: Central & South America | H45: https://www.gem.wiki/Aperam_Timóteo_steel_plant | I45: 76 | J45: unknown | K45: unknown | L45: 1949 | M45: unknown | N45: unknown | O45: unknown | P45: BF; EAF | Q45: unknown | R45: =INDEX('Blast furnaces'!$R:$R,MATCH(A45,'Blast furnaces'!$A:$A,0)) -> 44562
A46: P100000120050 | B46: ArcelorMittal Barra Mansa steel plant | C46: E100001000493 | D46: Barra Mansa | E46: Rio de Janeiro | F46: Brazil | G46: Central & South America | H46: https://www.gem.wiki/ArcelorMittal_Barra_Mansa_steel_plant | I46: 88 | J46: unknown | K46: unknown | L46: 1937 | M46: unknown | N46: unknown | O46: unknown | P46: EAF | Q46: unknown | R46: =INDEX('Blast furnaces'!$R:$R,MATCH(A46,'Blast furnaces'!$A:$A,0)) -> #N/A
A47: P100000120045 | B47: ArcelorMittal Juiz de Fora steel plant | C47: E100001000493 | D47: Juiz de Fora | E47: Minas Gerais | F47: Brazil | G47: Central & South America | H47: https://www.gem.wiki/ArcelorMittal_Juiz_de_Fora_steel_plant | I47: 41 | J47: unknown | K47: unknown | L47: 1984 | M47: unknown | N47: unknown | O47: unknown | P47: BF; EAF | Q47: unknown | R47: =INDEX('Blast furnaces'!$R:$R,MATCH(A47,'Blast furnaces'!$A:$A,0)) -> 44166
A48: P100000120035 | B48: ArcelorMittal Monlevade steel plant | C48: E100001000493 | D48: João Monlevade | E48: Minas Gerais | F48: Brazil | G48: Central & South America | H48: https://www.gem.wiki/ArcelorMittal_Monlevade_steel_plant | I48: 88 | J48: unknown | K48: unknown | L48: 1937 | M48: unknown | N48: unknown | O48: unknown | P48: BF; BOF; EAF | Q48: unknown | R48: =INDEX('Blast furnaces'!$R:$R,MATCH(A48,'Blast furnaces'!$A:$A,0)) -> 42948
A49: P100000120040 | B49: ArcelorMittal Pecém steel plant | C49: E100001000493 | D49: São Gonçalo do Amarante | E49: Ceará | F49: Brazil | G49: Central & South America | H49: https://www.gem.wiki/ArcelorMittal_Pecém_steel_plant | I49: 9 | J49: unknown | K49: unknown | L49: 2016 | M49: unknown | N49: unknown | O49: unknown | P49: BF; BOF | Q49: onsite 218MW gas-fired power plant | R49: =INDEX('Blast furnaces'!$R:$R,MATCH(A49,'Blast furnaces'!$A:$A,0)) -> 0
A50: P100000120041 | B50: ArcelorMittal Piracicaba steel plant | C50: E100001000493 | D50: Piracicaba | E50: São Paulo | F50: Brazil | G50: Central & South America | H50: https://www.gem.wiki/ArcelorMittal_Piracicaba_steel_plant | I50: 70 | J50: unknown | K50: unknown | L50: 1955 | M50: unknown | N50: unknown | O50: unknown | P50: EAF | Q50: unknown | R50: =INDEX('Blast furnaces'!$R:$R,MATCH(A50,'Blast furnaces'!$A:$A,0)) -> #N/A
A51: P100000120036 | B51: ArcelorMittal Resende steel plant | C51: E100001000493 | D51: Resende | E51: Rio de Janeiro | F51: Brazil | G51: Central & South America | H51: https://www.gem.wiki/ArcelorMittal_Resende_steel_plant | I51: 16 | J51: unknown | K51: unknown | L51: 2009 | M51: unknown | N51: unknown | O51: unknown | P51: EAF | Q51: unknown | R51: =INDEX('Blast furnaces'!$R:$R,MATCH(A51,'Blast furnaces'!$A:$A,0)) -> #N/A
A52: P100000120034 | B52: ArcelorMittal Tubarão steel plant | C52: E100001000507 | D52: Tubarão, Serra | E52: Espírito Santo | F52: Brazil | G52: Central & South America | H52: https://www.gem.wiki/ArcelorMittal_Tubarão_steel_plant | I52: 42 | J52: unknown | K52: unknown | L52: 1983 | M52: unknown | N52: unknown | O52: unknown | P52: BF; BOF | Q52: Generates approximate 115% of energy required for production from gases from production process | R52: =INDEX('Blast furnaces'!$R:$R,MATCH(A52,'Blast furnaces'!$A:$A,0)) -> 41091
A53: P100000120046 | B53: AVB Açailândia steel plant | C53: E100000130886 | D53: Açailândia | E53: Maranhão | F53: Brazil | G53: Central & South America | H53: https://www.gem.wiki/AVB_Açailândia_steel_plant | I53: 10 | J53: unknown | K53: unknown | L53: 2015 | M53: unknown | N53: unknown | O53: unknown | P53: BF; BOF | Q53: onsite power plant fueled by blast furnace (BF) gases | R53: =INDEX('Blast furnaces'!$R:$R,MATCH(A53,'Blast furnaces'!$A:$A,0)) -> 0
A54: P100000120039 | B54: CSN Volta Redonda steel plant | C54: E100001000652 | D54: Volta Redonda | E54: Rio de Janeiro | F54: Brazil | G54: Central & South America | H54: https://www.gem.wiki/CSN_Volta_Redonda_steel_plant | I54: 79 | J54: unknown | K54: unknown | L54: 1946 | M54: unknown | N54: unknown | O54: unknown | P54: BF; BOF; EAF | Q54: CSN owns two hydroelectric plants (Ita and Igarapava) and a thermoelectric plant in Volta Redondo | R54: =INDEX('Blast furnaces'!$R:$R,MATCH(A54,'Blast furnaces'!$A:$A,0)) -> 43705
A55: P100000120033 | B55: Gerdau Açominas Ouro Branco steel plant | C55: E100001010278 | D55: Ouro Branco | E55: Minas Gerais | F55: Brazil | G55: Central & South America | H55: https://www.gem.wiki/Gerdau_Açominas_Ouro_Branco_steel_plant | I55: 39 | J55: unknown | K55: unknown | L55: 1986 | M55: unknown | N55: unknown | O55: unknown | P55: BF; BOF | Q55: unknown | R55: =INDEX('Blast furnaces'!$R:$R,MATCH(A55,'Blast furnaces'!$A:$A,0)) -> 37043
... A64: P100000120038 | B64: Ternium Brasil Santa Cruz steel plant | C64: E100000131066 | D64: Santa Cruz | E64: Rio de Janeiro | F64: Brazil | G64: Central & South America | H64: https://www.gem.wiki/Ternium_Brasil_Santa_Cruz_steel_plant | I64: 15 | J64: unknown | K64: unknown | L64: 2010 | M64: unknown | N64: unknown | O64: unknown | P64: BF; BOF | Q64: Onsite power plant generating all energy required for steelmaking using gases from production process | R64: =INDEX('Blast furnaces'!$R:$R,MATCH(A64,'Blast furnaces'!$A:$A,0)) -> 0
A65: P100000120037 | B65: Usiminas Cubatão steel plant | C65: E100000130691 | D65: Cubatão | E65: São Paulo | F65: Brazil | G65: Central & South America | H65: https://www.gem.wiki/Usiminas_Cubatão_steel_plant | I65: 62 | J65: unknown | K65: unknown | L65: 1963 | M65: unknown | N65: 2016 | O65: unknown | P65: BF; BOF | Q65: unknown | R65: =INDEX('Blast furnaces'!$R:$R,MATCH(A65,'Blast furnaces'!$A:$A,0)) -> 36892
A66: P100000120043 | B66: Usiminas Ipatinga steel plant | C66: E100000130691 | D66: Ipatinga | E66: Minas Gerais | F66: Brazil | G66: Central & South America | H66: https://www.gem.wiki/Usiminas_Ipatinga_steel_plant | I66: 63 | J66: unknown | K66: unknown | L66: 1962 | M66: unknown | N66: unknown | O66: unknown | P66: BF; BOF | Q66: unknown | R66: =INDEX('Blast furnaces'!$R:$R,MATCH(A66,'Blast furnaces'!$A:$A,0)) -> 43191
A67: P100000121175 | B67: Vale Tecnored Marabá iron plant | C67: E100001000480 | D67: Marabá | E67: Pará | F67: Brazil | G67: Central & South America | H67: https://www.gem.wiki/Vale_Tecnored_Marabá_iron_plant | I67: 0 | J67: unknown | K67: 44652 | L67: 2025 | M67: unknown | N67: unknown | O67: unknown | P67: Iron other/unspecified | Q67: unknown | R67: =INDEX('Blast furnaces'!$R:$R,MATCH(A67,'Blast furnaces'!$A:$A,0)) -> #N/A
A68: P100000120044 | B68: Vallourec Jeceaba steel plant | C68: E100000130951 | D68: Jeceaba | E68: Minas Gerais | F68: Brazil | G68: Central & South America | H68: https://www.gem.wiki/Vallourec_Jeceaba_steel_plant | I68: 14 | J68: unknown | K68: unknown | L68: 2011 | M68: unknown | N68: unknown | O68: unknown | P68: BF; EAF | Q68: unknown | R68: =INDEX('Blast furnaces'!$R:$R,MATCH(A68,'Blast furnaces'!$A:$A,0)) -> 0
A69: P100000120054 | B69: Viena Açailândia iron works | C69: E100000130884 | D69: Açailândia | E69: Maranhão | F69: Brazil | G69: Central & South America | H69: https://www.gem.wiki/Viena_Açailândia_iron_works | I69: 37 | J69: unknown | K69: unknown | L69: 1988 | M69: unknown | N69: unknown | O69: unknown | P69: BF | Q69: unknown | R69: =INDEX('Blast furnaces'!$R:$R,MATCH(A69,'Blast furnaces'!$A:$A,0)) -> 0
A70: P100000120031 | B70: Stomana Industry Pernik steel plant | C70: E100000130943 | D70: Pernik | E70: Pernik | F70: Bulgaria | G70: Europe | H70: https://www.gem.wiki/Stomana_Industry_Pernik_steel_plant | I70: 67 | J70: unknown | K70: unknown | L70: 1958 | M70: unknown | N70: unknown | O70: unknown | P70: EAF | Q70: "All electricity used at Stomana’s facilities is sourced from the national grid" | R70: =INDEX('Blast furnaces'!$R:$R,MATCH(A70,'Blast furnaces'!$A:$A,0)) -> #N/A
A71: P100000121154 | B71: Cambodia Iron and Steel Preah Vihear Plant | C71: E100001012105 | D71: unknown | E71: Preah Vihear | F71: Cambodia | G71: Asia Pacific | H71: https://www.gem.wiki/Cambodia_Iron_and_Steel_Preah_Vihear_Plant | I71: unknown | J71: 40868 | K71: unknown | L71: unknown | M71: unknown | N71: unknown | O71: 2019 | P71: BF; BOF | Q71: Captive Power Plant (coal) | R71: =INDEX('Blast furnaces'!$R:$R,MATCH(A71,'Blast furnaces'!$A:$A,0)) -> 0
A72: P100000120686 | B72: China Baowu Phnom Penh steel plant | C72: E100000130983 | D72: Phnom Penh | E72: Phnom Penh | F72: Cambodia | G72: Asia Pacific | H72: https://www.gem.wiki/China_Baowu_Phnom_Penh_steel_plant | I72: unknown | J72: 43609 | K72: unknown | L72: unknown | M72: unknown | N72: unknown | O72: unknown | P72: BF; BOF | Q72: unknown | R72: =INDEX('Blast furnaces'!$R:$R,MATCH(A72,'Blast furnaces'!$A:$A,0)) -> 0
A73: P100000120059 | B73: Algoma steel plant | C73: E100000001817 | D73: Sault Ste. Marie | E73: Ontario | F73: Canada | G73: North America | H73: https://www.gem.wiki/Algoma_steel_plant | I73: 124 | J73: unknown | K73: unknown | L73: 1901 | M73: unknown | N73: unknown | O73: unknown | P73: BF; BOF; EAF | Q73: Ontario electricity grid; Lake Superior Power project upgrade with gas-fired turbines | R73: =INDEX('Blast furnaces'!$R:$R,MATCH(A73,'Blast furnaces'!$A:$A,0)) -> 2007
A74: P100000120058 | B74: ArcelorMittal Dofasco steel plant | C74: E100001000495 | D74: Hamilton | E74: Ontario | F74: Canada | G74: North America | H74: https://www.gem.wiki/ArcelorMittal_Dofasco_steel_plant | I74: 113 | J74: unknown | K74: unknown | L74: 1912 | M74: unknown | N74: unknown | O74: unknown | P74: BF; BOF; EAF; DRI | Q74: unknown | R74: =INDEX('Blast furnaces'!$R:$R,MATCH(A74,'Blast furnaces'!$A:$A,0)) -> 38534
A75: P100000120057 | B75: ArcelorMittal Montreal steel plant | C75: E100001000502 | D75: Contrecœur | E75: Quebec | F75: Canada | G75: North America | H75: https://www.gem.wiki/ArcelorMittal_Montreal_steel_plant | I75: 111 | J75: unknown | K75: unknown | L75: 1914 | M75: unknown | N75: unknown | O75: unknown | P75: EAF; DRI | Q75: unknown | R75: =INDEX('Blast furnaces'!$R:$R,MATCH(A75,'Blast furnaces'!$A:$A,0)) -> #N/A
A76: P100000120061 | B76: Cleveland-Cliffs Lake Erie steel plant | C76: E100001000649 | D76: Nanticoke | E76: Ontario | F76: Canada | G76: North America | H76: https://www.gem.wiki/Cleveland-Cliffs_Lake_Erie_steel_plant | I76: 45 | J76: unknown | K76: unknown | L76: 1980 | M76: unknown | N76: unknown | O76: unknown | P76: BF; BOF | Q76: unknown | R76: =INDEX('Blast furnaces'!$R:$R,MATCH(A76,'Blast furnaces'!$A:$A,0)) -> 44119
A77: P100000120060 | B77: Evraz Regina Steel plant | C77: E100000131019 | D77: Regina | E77: Saskatchewan | F77: Canada | G77: North America | H77: https://www.gem.wiki/Evraz_Regina_Steel_plant | I77: 64 | J77: unknown | K77: unknown | L77: 1961 | M77: unknown | N77: unknown | O77: unknown | P77: EAF | Q77: unknown | R77: =INDEX('Blast furnaces'!$R:$R,MATCH(A77,'Blast furnaces'!$A:$A,0)) -> #N/A
A78: P100000120062 | B78: Gerdau Whitby Steel Mill | C78: E100001010298 | D78: Whitby | E78: Ontario | F78: Canada | G78: North America | H78: https://www.gem.wiki/Gerdau_Whitby_Steel_Mill | I78: 61 | J78: unknown | K78: unknown | L78: 1964 | M78: unknown | N78: unknown | O78: unknown | P78: EAF | Q78: unknown | R78: =INDEX('Blast furnaces'!$R:$R,MATCH(A78,'Blast furnaces'!$A:$A,0)) -> #N/A
A79: P100000120063 | B79: Ivaco Rolling Mills steel plant | C79: E100000130855 | D79: L'Orignal | E79: Ontario | F79: Canada | G79: North America | H79: https://www.gem.wiki/Ivaco_Rolling_Mills_steel_plant | I79: 54 | J79: unknown | K79: unknown | L79: 1971 | M79: unknown | N79: unknown | O79: unknown | P79: EAF | Q79: unknown | R79: =INDEX('Blast furnaces'!$R:$R,MATCH(A79,'Blast furnaces'!$A:$A,0)) -> #N/A
A80: P100000120064 | B80: Rio Tinto Fer et Titane steel plant | C80: E100000131063 | D80: Sorel-Tracy | E80: Quebec | F80: Canada | G80: North America | H80: https://www.gem.wiki/Rio_Tinto_Fer_et_Titane_steel_plant | I80: 75 | J80: unknown | K80: unknown | L80: 1950 | M80: unknown | N80: unknown | O80: unknown | P80: BOF | Q80: unknown | R80: =INDEX('Blast furnaces'!$R:$R,MATCH(A80,'Blast furnaces'!$A:$A,0)) -> #N/A
A81: P100000120067 | B81: AZA Colina steel plant | C81: E100000131104 | D81: Colina | E81: Región Metropolitana | F81: Chile | G81: Central & South America | H81: https://www.gem.wiki/AZA_Colina_steel_plant | I81: 26.24 | J81: unknown | K81: unknown | L81: 36326 | M81: unknown | N81: unknown | O81: unknown | P81: EAF | Q81: unknown | R81: =INDEX('Blast furnaces'!$R:$R,MATCH(A81,'Blast furnaces'!$A:$A,0)) -> #N/A
A82: P100000120066 | B82: CAP Acero Huachipato steel plant | C82: E100000130911 | D82: Talcahuano | E82: Concepción | F82: Chile | G82: Central & South America | H82: https://www.gem.wiki/CAP_Acero_Huachipato_steel_plant | I82: 75 | J82: unknown | K82: unknown | L82: 1950 | M82: unknown | N82: 45551 | O82: unknown | P82: BF; BOF | Q82: unknown | R82: =INDEX('Blast furnaces'!$R:$R,MATCH(A82,'Blast furnaces'!$A:$A,0)) -> 0
A83: P100000120163 | B83: Angang Group Xinyang Iron and Steel Co Ltd | C83: E100000127277 | D83: Minggang | E83: Henan | F83: China | G83: Asia Pacific | H83: https://www.gem.wiki/Angang_Group_Xinyang_Iron_and_Steel_Co_Ltd | I83: 54 | J83: unknown | K83: unknown | L83: 1971 | M83: unknown | N83: unknown | O83: unknown | P83: BF; BOF | Q83: unknown | R83: =INDEX('Blast furnaces'!$R:$R,MATCH(A83,'Blast furnaces'!$A:$A,0)) -> 0
A84: P100000120089 | B84: Angang Lianzhong Stainless Steel Co Ltd | C84: E100000127397 | D84: Economic and Technological Development Zone | E84: Guangdong | F84: China | G84: Asia Pacific | H84: https://www.gem.wiki/Angang_Lianzhong_Stainless_Steel_Co_Ltd | I84: 24 | J84: unknown | K84: unknown | L84: 2001 | M84: unknown | N84: unknown | O84: unknown | P84: EAF | Q84: Distributed Photovoltaic Power Generation | R84: =INDEX('Blast furnaces'!$R:$R,MATCH(A84,'Blast furnaces'!$A:$A,0)) -> #N/A
A85: P100000120219 | B85: Angang Steel Co Ltd | C85: E100000126769 | D85: unknown | E85: Liaoning | F85: China | G85: Asia Pacific | H85: https://www.gem.wiki/Angang_Steel_Co_Ltd | I85: 26.99 | J85: unknown | K85: unknown | L85: 36052 | M85: unknown | N85: unknown | O85: unknown | P85: BF; BOF | Q85: the world's first 180-megawatt split-type blast furnace gas combined cycle power generation | R85: =INDEX('Blast furnaces'!$R:$R,MATCH(A85,'Blast furnaces'!$A:$A,0)) -> 43415
A86: P100000120220 | B86: Angang Steel Co Ltd Bayuquan branch | C86: E100000126769 | D86: Yingkou Economic and Technological Development Zone | E86: Liaoning | F86: China | G86: Asia Pacific | H86: https://www.gem.wiki/Angang_Steel_Co_Ltd_Bayuquan_branch | I86: 19 | J86: unknown | K86: unknown | L86: 2006 | M86: unknown | N86: unknown | O86: unknown | P86: BF; BOF | Q86: the world's first 180-megawatt split-type blast furnace gas combined cycle power generation | R86: =INDEX('Blast furnaces'!$R:$R,MATCH(A86,'Blast furnaces'!$A:$A,0)) -> 0
A87: P100000120070 | B87: Anhui Changjiang Steel Co Ltd | C87: E100000123155 | D87: unknown | E87: Anhui | F87: China | G87: Asia Pacific | H87: https://www.gem.wiki/Anhui_Changjiang_Steel_Co_Ltd | I87: 22 | J87: unknown | K87: unknown | L87: 2003 | M87: unknown | N87: unknown | O87: unknown | P87: BF; BOF; EAF | Q87: 3.5 MW Rooftop Distributed Photovoltaic Power Generation | R87: =INDEX('Blast furnaces'!$R:$R,MATCH(A87,'Blast furnaces'!$A:$A,0)) -> 43593
A88: P100000120071 | B88: Anhui Guihang Special Steel Co Ltd | C88: E100000126525 | D88: Chizhou | E88: Anhui | F88: China | G88: Asia Pacific | H88: https://www.gem.wiki/Anhui_Guihang_Special_Steel_Co_Ltd | I88: 15.44 | J88: unknown | K88: unknown | L88: 40269 | M88: unknown | N88: unknown | O88: unknown | P88: BF; BOF | Q88: Distributed Photovoltaic Power Generation | R88: =INDEX('Blast furnaces'!$R:$R,MATCH(A88,'Blast furnaces'!$A:$A,0)) -> 0
A89: P100000120391 | B89: Anhui Jin an Stainless Steel Casting Co Ltd | C89: E100000126390 | D89: Lu'an | E89: Anhui | F89: China | G89: Asia Pacific | H89: https://www.gem.wiki/Anhui_Jin_an_Stainless_Steel_Casting_Co_Ltd | I89: 3 | J89: 44440 | K89: unknown | L89: 2022 | M89: unknown | N89: unknown | O89: unknown | P89: EAF | Q89: County Power Supply Company | R89: =INDEX('Blast furnaces'!$R:$R,MATCH(A89,'Blast furnaces'!$A:$A,0)) -> #N/A
A90: P100000120417 | B90: Anhui Jingxian Longxin Iron and Steel Co Ltd | C90: E100000126157 | D90: Xuancheng | E90: Anhui | F90: China | G90: Asia Pacific | H90: https://www.gem.wiki/Anhui_Jingxian_Longxin_Iron_and_Steel_Co_Ltd | I90: 17 | J90: unknown | K90: unknown | L90: 2008 | M90: unknown | N90: unknown | O90: unknown | P90: EAF | Q90: 5.9 MW roof photovoltaic power generation-Phase I | R90: =INDEX('Blast furnaces'!$R:$R,MATCH(A90,'Blast furnaces'!$A:$A,0)) -> #N/A
A91: P100000120402 | B91: Anhui Langxi Hongtai Iron and Steel Co Ltd | C91: E100000126133 | D91: Xuancheng | E91: Anhui | F91: China | G91: Asia Pacific | H91: https://www.gem.wiki/Anhui_Langxi_Hongtai_Iron_and_Steel_Co_Ltd | I91: 23 | J91: unknown | K91: unknown | L91: 2002 | M91: unknown | N91: unknown | O91: unknown | P91: EAF | Q91: Langxi Power Grid | R91: =INDEX('Blast furnaces'!$R:$R,MATCH(A91,'Blast furnaces'!$A:$A,0)) -> #N/A
A92: P100001025923 | B92: Anhui Lixin Special Steel Co Ltd | C92: E100002005337 | D92: Guangde | E92: Anhui | F92: China | G92: Asia Pacific | H92: https://www.gem.wiki/Anhui_Lixin_Special_Steel_Co_Ltd | I92: 13.79 | J92: unknown | K92: unknown | L92: 40872 | M92: unknown | N92: unknown | O92: unknown | P92: EAF | Q92: unknown | R92: =INDEX('Blast furnaces'!$R:$R,MATCH(A92,'Blast furnaces'!$A:$A,0)) -> #N/A
A93: P100000120313 | B93: Anhui Shoukuang Dachang Metal Material Co Ltd | C93: E100000126761 | D93: liuan | E93: Anhui | F93: China | G93: Asia Pacific | H93: https://www.gem.wiki/Anhui_Shoukuang_Dachang_Metal_Material_Co_Ltd | I93: 15 | J93: unknown | K93: unknown | L93: 2010 | M93: unknown | N93: unknown | O93: unknown | P93: BF; BOF | Q93: Ultra-high Temperature Subcritical Coal Gas Power Generation Unit | R93: =INDEX('Blast furnaces'!$R:$R,MATCH(A93,'Blast furnaces'!$A:$A,0)) -> 0
A94: P100000120231 | B94: Anshan Baode Iron and Steel Co Ltd | C94: E100000126417 | D94: unknown | E94: Liaoning | F94: China | G94: Asia Pacific | H94: https://www.gem.wiki/Anshan_Baode_Iron_and_Steel_Co_Ltd | I94: 26.29 | J94: unknown | K94: unknown | L94: 36308 | M94: unknown | N94: unknown | O94: unknown | P94: BF; BOF | Q94: A 45-megawatt surplus energy supercritical temperature and supercritical pressure power station | R94: =INDEX('Blast furnaces'!$R:$R,MATCH(A94,'Blast furnaces'!$A:$A,0)) -> 0
A95: P100000120221 | B95: Ansteel Group Chaoyang Steel and Iron Co Ltd | C95: E100000126769 | D95: Xidayingzi | E95: Liaoning | F95: China | G95: Asia Pacific | H95: https://www.gem.wiki/Ansteel_Group_Chaoyang_Steel_and_Iron_Co_Ltd | I95: 18.15 | J95: unknown | K95: unknown | L95: 39282 | M95: unknown | N95: unknown | O95: unknown | P95: BF; BOF | Q95: the world's first 180-megawatt split-type blast furnace gas combined cycle power generation | R95: =INDEX('Blast furnaces'!$R:$R,MATCH(A95,'Blast furnaces'!$A:$A,0)) -> 41219
A96: P100000120170 | B96: Anyang Huixin Special Steel Co Ltd | C96: E100000126643 | D96: Anyang | E96: Henan | F96: China | G96: Asia Pacific | H96: https://www.gem.wiki/Anyang_Huixin_Special_Steel_Co_Ltd | I96: 21 | J96: unknown | K96: unknown | L96: 2004 | M96: 45084 | N96: unknown | O96: 2025 | P96: BF; BOF | Q96: unknown | R96: =INDEX('Blast furnaces'!$R:$R,MATCH(A96,'Blast furnaces'!$A:$A,0)) -> 0
A97: P100000120160 | B97: Anyang Iron and Steel Co Ltd | C97: E100001000432 | D97: Anyang | E97: Henan | F97: China | G97: Asia Pacific | H97: https://www.gem.wiki/Anyang_Iron_and_Steel_Co_Ltd | I97: 67 | J97: unknown | K97: unknown | L97: 1958 | M97: unknown | N97: unknown | O97: unknown | P97: BF; BOF; EAF | Q97: coal gas recovery power station&waste heat power generation unit | R97: =INDEX('Blast furnaces'!$R:$R,MATCH(A97,'Blast furnaces'!$A:$A,0)) -> 0
A98: P100000120166 | B98: Anyang Xinpu Steel Co Ltd | C98: E100000126159 | D98: Anyang | E98: Henan | F98: China | G98: Asia Pacific | H98: https://www.gem.wiki/Anyang_Xinpu_Steel_Co_Ltd | I98: 20 | J98: unknown | K98: unknown | L98: 2005 | M98: 44900 | N98: unknown | O98: 2025 | P98: BF; BOF | Q98: unknown | R98: =INDEX('Blast furnaces'!$R:$R,MATCH(A98,'Blast furnaces'!$A:$A,0)) -> 0
A99: P100000120384 | B99: Baicheng Fuda Bar Rolling Co Ltd | C99: E100000127199 | D99: Baicheng Industrial Park | E99: Jilin | F99: China | G99: Asia Pacific | H99: https://www.gem.wiki/Baicheng_Fuda_Bar_Rolling_Co_Ltd | I99: 15.87 | J99: unknown | K99: unknown | L99: 40113 | M99: unknown | N99: unknown | O99: unknown | P99: EAF | Q99: State Power Investment Corporation Jilin Longhua Baicheng Combined Heat and Power Plant. | R99: =INDEX('Blast furnaces'!$R:$R,MATCH(A99,'Blast furnaces'!$A:$A,0)) -> #N/A
A100: P100000120256 | B100: Baoshan Iron and Steel Co Ltd Headquarters | C100: E100000122571 | D100: unknown | E100: Shanghai | F100: China | G100: Asia Pacific | H100: https://www.gem.wiki/Baoshan_Iron_and_Steel_Co_Ltd_Headquarters | I100: 48 | J100: unknown | K100: unknown | L100: 1977 | M100: unknown | N100: unknown | O100: unknown | P100: BF; BOF; EAF | Q100: Baoshan Iron & Steel Co., Ltd. Power Plant | R100: =INDEX('Blast furnaces'!$R:$R,MATCH(A100,'Blast furnaces'!$A:$A,0)) -> 41594
A101: P100000120336 | B101: Baosteel Desheng Stainless Steel Co Ltd | C101: E100000127278 | D101: Fuzhou | E101: Fujian | F101: China | G101: Asia Pacific | H101: https://www.gem.wiki/Baosteel_Desheng_Stainless_Steel_Co_Ltd | I101: 14 | J101: unknown | K101: unknown | L101: 2011 | M101: unknown | N101: unknown | O101: unknown | P101: BF; BOF | Q101: 27.54MW Photovoltaic Power Station | R101: =INDEX('Blast furnaces'!$R:$R,MATCH(A101,'Blast furnaces'!$A:$A,0)) -> 2022
A102: P100000120289 | B102: Baosteel Group Xinjiang Bayi Iron and Steel Co Ltd | C102: E100001012045 | D102: Ürümqi | E102: Xinjiang | F102: China | G102: Asia Pacific | H102: https://www.gem.wiki/Baosteel_Group_Xinjiang_Bayi_Iron_and_Steel_Co_Ltd | I102: 29.89 | J102: unknown | K102: unknown | L102: 34992 | M102: unknown | N102: unknown | O102: unknown | P102: BF; BOF; EAF | Q102: Xinjiang Electric Power Company | R102: =INDEX('Blast furnaces'!$R:$R,MATCH(A102,'Blast furnaces'!$A:$A,0)) -> 41122
A103: P100000120257 | B103: Baosteel Special Steel Co Ltd | C103: E100000127209 | D103: Wusong Industrial Zone | E103: Shanghai | F103: China | G103: Asia Pacific | H103: https://www.gem.wiki/Baosteel_Special_Steel_Co_Ltd | I103: 65.41 | J103: unknown | K103: unknown | L103: 1958 | M103: 44706 | N103: unknown | O103: 45078 | P103: EAF | Q103: 150MW Gas-fired Power Generation Unit | R103: =INDEX('Blast furnaces'!$R:$R,MATCH(A103,'Blast furnaces'!$A:$A,0)) -> #N/A
A104: P100000120085 | B104: Baosteel Zhanjiang Iron and Steel Co Ltd | C104: E100000121815 | D104: Zhanjiang | E104: Guangdong | F104: China | G104: Asia Pacific | H104: https://www.gem.wiki/Baosteel_Zhanjiang_Iron_and_Steel_Co_Ltd | I104: 14 | J104: unknown | K104: unknown | L104: 2011 | M104: unknown | N104: unknown | O104: unknown | P104: BF; BOF; EAF; DRI | Q104: Photovoltaic Power Generation | R104: =INDEX('Blast furnaces'!$R:$R,MATCH(A104,'Blast furnaces'!$A:$A,0)) -> 45094
A105: P100000121076 | B105: Baotou Baoxin Special Steel Co Ltd | C105: E100000126820 | D105: unknown | E105: Inner Mongolia | F105: China | G105: Asia Pacific | H105: https://www.gem.wiki/Baotou_Baoxin_Special_Steel_Co_Ltd | I105: 18.17 | J105: unknown | K105: unknown | L105: 39274 | M105: unknown | N105: 44741 | O105: unknown | P105: BF; BOF | Q105: unknown | R105: =INDEX('Blast furnaces'!$R:$R,MATCH(A105,'Blast furnaces'!$A:$A,0)) -> 0
A106: P100000121143 | B106: Baotou Da'an Iron and Steel Co Ltd Kundulun District | C106: E100000126606 | D106: Burhantu | E106: Inner Mongolia | F106: China | G106: Asia Pacific | H106: https://www.gem.wiki/Baotou_Da'an_Iron_and_Steel_Co_Ltd_Kundulun_District | I106: unknown | J106: 44652 | K106: unknown | L106: unknown | M106: unknown | N106: unknown | O106: unknown | P106: BF; BOF | Q106: unknown | R106: =INDEX('Blast furnaces'!$R:$R,MATCH(A106,'Blast furnaces'!$A:$A,0)) -> 0
A107: P100000120186 | B107: Baotou Daan Iron and Steel Co Ltd Hondlon District | C107: E100000126606 | D107: Bu'er Hantu | E107: Inner Mongolia | F107: China | G107: Asia Pacific | H107: https://www.gem.wiki/Baotou_Daan_Iron_and_Steel_Co_Ltd_Hondlon_District | I107: 22.81 | J107: unknown | K107: unknown | L107: 2002 | M107: 44664 | N107: 2023 | O107: 45588 | P107: BF; BOF | Q107: unknown | R107: =INDEX('Blast furnaces'!$R:$R,MATCH(A107,'Blast furnaces'!$A:$A,0)) -> 44166
A108: P100000121142 | B108: Baotou Deshun Special Steel Co Ltd | C108: E100001012095 | D108: Baotou | E108: Inner Mongolia | F108: China | G108: Asia Pacific | H108: https://www.gem.wiki/Baotou_Deshun_Special_Steel_Co_Ltd | I108: 18.46 | J108: unknown | K108: unknown | L108: 39168 | M108: unknown | N108: unknown | O108: unknown | P108: BF; BOF | Q108: unknown | R108: =INDEX('Blast furnaces'!$R:$R,MATCH(A108,'Blast furnaces'!$A:$A,0)) -> 0
...

Sheet Blast furnaces
A1: GEM Plant ID | B1: Municipality | C1: Subnational unit (province/state) | D1: Country/Area | E1: GEM Unit ID | F1: Unit Name | G1: GEM Wiki Page | H1: Unit Status | I1: Announced Date | J1: Construction Date | K1: Start Date | L1: Unit Age | M1: Pre-retirement Announcement Date | N1: Idled Date | O1: Retired Date | P1: Current Capacity (ttpa) | Q1: Current Size (m3) | R1: Most Recent Relining | S1: Relining (Date Format) | T1: Next Relining | U1: Next Relining Year | V1: Share of Capacity
A2: P100000120008 | B2: =INDEX('Plant data'!D:D,MATCH('Blast furnaces'!$A2,'Plant data'!$A:$A,0)) -> San Nicolás de los Arroyos | C2: =INDEX('Plant data'!E:E,MATCH('Blast furnaces'!$A2,'Plant data'!$A:$A,0)) -> Buenos Aires | D2: =INDEX('Plant data'!F:F,MATCH('Blast furnaces'!$A2,'Plant data'!$A:$A,0)) -> Argentina | E2: U100000140001 | F2: BF 2 | G2: https://www.gem.wiki/Ternium_Siderar_San_Nicolás_steel_plant | H2: operating | I2: unknown | J2: unknown | K2: 1974 | L2: 51 | M2: unknown | N2: unknown | O2: unknown | P2: 2628 | Q2: 2340 | R2: 39448 | S2: =_xlfn.LET( _xlpm.x, R2, _xlpm.t, TEXT(R2,"@"), IF(R2="","", IF(ISNUMBER(_xlpm.x), IF(_xlpm.x>=30000, _xlpm.x, DATE(_xlpm.x,1,1)), DATE( LEFT(_xlpm.t,4), IF(LEN(_xlpm.t)>=7, MID(_xlpm.t,6,2), 1), IF(LEN(_xlpm.t)>=10, RIGHT(_xlpm.t,2), 1) ) ) ) ) -> 39448 | T2: =IF(R2="","",EDATE(S2,240)) -> 46753
A3: P100000120008 | B3: =INDEX('Plant data'!D:D,MATCH('Blast furnaces'!$A3,'Plant data'!$A:$A,0)) -> San Nicolás de los Arroyos | C3: =INDEX('Plant data'!E:E,MATCH('Blast furnaces'!$A3,'Plant data'!$A:$A,0)) -> Buenos Aires | D3: =INDEX('Plant data'!F:F,MATCH('Blast furnaces'!$A3,'Plant data'!$A:$A,0)) -> Argentina | E3: U100000140002 | F3: BF 1 | G3: https://www.gem.wiki/Ternium_Siderar_San_Nicolás_steel_plant | H3: operating | I3: unknown | J3: unknown | K3: 1960 | L3: 65 | M3: unknown | N3: unknown | O3: unknown | P3: 1387 | Q3: 1548 | R3: 39845 | S3: =_xlfn.LET( _xlpm.x, R3, _xlpm.t, TEXT(R3,"@"), IF(R3="","", IF(ISNUMBER(_xlpm.x), IF(_xlpm.x>=30000, _xlpm.x, DATE(_xlpm.x,1,1)), DATE( LEFT(_xlpm.t,4), IF(LEN(_xlpm.t)>=7, MID(_xlpm.t,6,2), 1), IF(LEN(_xlpm.t)>=10, RIGHT(_xlpm.t,2), 1) ) ) ) ) -> 39845 | T3: =IF(R3="","",EDATE(S3,240)) -> 47150
A4: P100000120010 | B4: =INDEX('Plant data'!D:D,MATCH('Blast furnaces'!$A4,'Plant data'!$A:$A,0)) -> Linz | C4: =INDEX('Plant data'!E:E,MATCH('Blast furnaces'!$A4,'Plant data'!$A:$A,0)) -> Upper Austria | D4: =INDEX('Plant data'!F:F,MATCH('Blast furnaces'!$A4,'Plant data'!$A:$A,0)) -> Austria | E4: U100000140003 | F4: BF A | G4: https://www.gem.wiki/Voestalpine_Stahl_Linz_steel_plant | H4: operating | I4: unknown | J4: unknown | K4: 1977 | L4: 48 | M4: unknown | N4: unknown | O4: unknown | P4: 3300 | Q4: unknown | R4: 43344 | S4: =_xlfn.LET( _xlpm.x, R4, _xlpm.t, TEXT(R4,"@"), IF(R4="","", IF(ISNUMBER(_xlpm.x), IF(_xlpm.x>=30000, _xlpm.x, DATE(_xlpm.x,1,1)), DATE( LEFT(_xlpm.t,4), IF(LEN(_xlpm.t)>=7, MID(_xlpm.t,6,2), 1), IF(LEN(_xlpm.t)>=10, RIGHT(_xlpm.t,2), 1) ) ) ) ) -> 43344 | T4: =IF(R4="","",EDATE(S4,240)) -> 50649
A5: P100000120010 | B5: =INDEX('Plant data'!D:D,MATCH('Blast furnaces'!$A5,'Plant data'!$A:$A,0)) -> Linz | C5: =INDEX('Plant data'!E:E,MATCH('Blast furnaces'!$A5,'Plant data'!$A:$A,0)) -> Upper Austria | D5: =INDEX('Plant data'!F:F,MATCH('Blast furnaces'!$A5,'Plant data'!$A:$A,0)) -> Austria | E5: U100000140004 | F5: BF 5 | G5: https://www.gem.wiki/Voestalpine_Stahl_Linz_steel_plant | H5: operating pre-retirement | I5: unknown | J5: unknown | K5: 1941 | L5: 86 | M5: 2023 | N5: unknown | O5: 2027 | P5: 850 | Q5: unknown | R5: 45222 | S5: =_xlfn.LET( _xlpm.x, R5, _xlpm.t, TEXT(R5,"@"), IF(R5="","", IF(ISNUMBER(_xlpm.x), IF(_xlpm.x>=30000, _xlpm.x, DATE(_xlpm.x,1,1)), DATE( LEFT(_xlpm.t,4), IF(LEN(_xlpm.t)>=7, MID(_xlpm.t,6,2), 1), IF(LEN(_xlpm.t)>=10, RIGHT(_xlpm.t,2), 1) ) ) ) ) -> 45222 | T5: =IF(R5="","",EDATE(S5,240)) -> 52527
A6: P100000120010 | B6: =INDEX('Plant data'!D:D,MATCH('Blast furnaces'!$A6,'Plant data'!$A:$A,0)) -> Linz | C6: =INDEX('Plant data'!E:E,MATCH('Blast furnaces'!$A6,'Plant data'!$A:$A,0)) -> Upper Austria | D6: =INDEX('Plant data'!F:F,MATCH('Blast furnaces'!$A6,'Plant data'!$A:$A,0)) -> Austria | E6: U100000140005 | F6: BF 6 | G6: https://www.gem.wiki/Voestalpine_Stahl_Linz_steel_plant | H6: operating pre-retirement | I6: unknown | J6: unknown | K6: 1941 | L6: 89 | M6: 2023 | N6: unknown | O6: 2030 | P6: 850 | Q6: 1200 | R6: 45566 | S6: =_xlfn.LET( _xlpm.x, R6, _xlpm.t, TEXT(R6,"@"), IF(R6="","", IF(ISNUMBER(_xlpm.x), IF(_xlpm.x>=30000, _xlpm.x, DATE(_xlpm.x,1,1)), DATE( LEFT(_xlpm.t,4), IF(LEN(_xlpm.t)>=7, MID(_xlpm.t,6,2), 1), IF(LEN(_xlpm.t)>=10, RIGHT(_xlpm.t,2), 1) ) ) ) ) -> 45566 | T6: =IF(R6="","",EDATE(S6,240)) -> 52871
A7: P100000120011 | B7: =INDEX('Plant data'!D:D,MATCH('Blast furnaces'!$A7,'Plant data'!$A:$A,0)) -> Leoben | C7: =INDEX('Plant data'!E:E,MATCH('Blast furnaces'!$A7,'Plant data'!$A:$A,0)) -> Styria | D7: =INDEX('Plant data'!F:F,MATCH('Blast furnaces'!$A7,'Plant data'!$A:$A,0)) -> Austria | E7: U100000140006 | F7: BF 1 | G7: https://www.gem.wiki/Voestalpine_Stahl_Donawitz_steel_plant | H7: operating | I7: unknown | J7: unknown | K7: unknown | L7: unknown | M7: unknown | N7: unknown | O7: unknown | P7: 825 | Q7: 1205 | R7: 43368 | S7: =_xlfn.LET( _xlpm.x, R7, _xlpm.t, TEXT(R7,"@"), IF(R7="","", IF(ISNUMBER(_xlpm.x), IF(_xlpm.x>=30000, _xlpm.x, DATE(_xlpm.x,1,1)), DATE( LEFT(_xlpm.t,4), IF(LEN(_xlpm.t)>=7, MID(_xlpm.t,6,2), 1), IF(LEN(_xlpm.t)>=10, RIGHT(_xlpm.t,2), 1) ) ) ) ) -> 43368 | T7: =IF(R7="","",EDATE(S7,240)) -> 50673
A8: P100000120011 | B8: =INDEX('Plant data'!D:D,MATCH('Blast furnaces'!$A8,'Plant data'!$A:$A,0)) -> Leoben | C8: =INDEX('Plant data'!E:E,MATCH('Blast furnaces'!$A8,'Plant data'!$A:$A,0)) -> Styria | D8: =INDEX('Plant data'!F:F,MATCH('Blast furnaces'!$A8,'Plant data'!$A:$A,0)) -> Austria | E8: U100000140007 | F8: BF 4 | G8: https://www.gem.wiki/Voestalpine_Stahl_Donawitz_steel_plant | H8: operating pre-retirement | I8: unknown | J8: unknown | K8: 1941 | L8: 86 | M8: 2023 | N8: unknown | O8: 2027 | P8: 825 | Q8: 1343 | R8: 2016 | S8: =_xlfn.LET( _xlpm.x, R8, _xlpm.t, TEXT(R8,"@"), IF(R8="","", IF(ISNUMBER(_xlpm.x), IF(_xlpm.x>=30000, _xlpm.x, DATE(_xlpm.x,1,1)), DATE( LEFT(_xlpm.t,4), IF(LEN(_xlpm.t)>=7, MID(_xlpm.t,6,2), 1), IF(LEN(_xlpm.t)>=10, RIGHT(_xlpm.t,2), 1) ) ) ) ) -> 42370 | T8: =IF(R8="","",EDATE(S8,240)) -> 49675
A9: P100000120012 | B9: =INDEX('Plant data'!D:D,MATCH('Blast furnaces'!$A9,'Plant data'!$A:$A,0)) -> Port Kembla | C9: =INDEX('Plant data'!E:E,MATCH('Blast furnaces'!$A9,'Plant data'!$A:$A,0)) -> New South Wales | D9: =INDEX('Plant data'!F:F,MATCH('Blast furnaces'!$A9,'Plant data'!$A:$A,0)) -> Australia | E9: U100000140008 | F9: BF 5 | G9: https://www.gem.wiki/BlueScope_Port_Kembla_steel_plant | H9: operating pre-retirement | I9: unknown | J9: unknown | K9: 1972 | L9: 58 | M9: unknown | N9: unknown | O9: 2030 | P9: 3000 | Q9: 3427 | R9: 40026 | S9: =_xlfn.LET( _xlpm.x, R9, _xlpm.t, TEXT(R9,"@"), IF(R9="","", IF(ISNUMBER(_xlpm.x), IF(_xlpm.x>=30000, _xlpm.x, DATE(_xlpm.x,1,1)), DATE( LEFT(_xlpm.t,4), IF(LEN(_xlpm.t)>=7, MID(_xlpm.t,6,2), 1), IF(LEN(_xlpm.t)>=10, RIGHT(_xlpm.t,2), 1) ) ) ) ) -> 40026 | T9: =IF(R9="","",EDATE(S9,240)) -> 47331
A10: P100000120012 | B10: =INDEX('Plant data'!D:D,MATCH('Blast furnaces'!$A10,'Plant data'!$A:$A,0)) -> Port Kembla | C10: =INDEX('Plant data'!E:E,MATCH('Blast furnaces'!$A10,'Plant data'!$A:$A,0)) -> New South Wales | D10: =INDEX('Plant data'!F:F,MATCH('Blast furnaces'!$A10,'Plant data'!$A:$A,0)) -> Australia | E10: U100000140009 | F10: BF 6 | G10: https://www.gem.wiki/BlueScope_Port_Kembla_steel_plant | H10: mothballed | I10: unknown | J10: unknown | K10: 1996 | L10: 29 | M10: unknown | N10: 2011 | O10: unknown | P10: 3000 | Q10: 3208 | S10: =_xlfn.LET( _xlpm.x, R10, _xlpm.t, TEXT(R10,"@"), IF(R10="","", IF(ISNUMBER(_xlpm.x), IF(_xlpm.x>=30000, _xlpm.x, DATE(_xlpm.x,1,1)), DATE( LEFT(_xlpm.t,4), IF(LEN(_xlpm.t)>=7, MID(_xlpm.t,6,2), 1), IF(LEN(_xlpm.t)>=10, RIGHT(_xlpm.t,2), 1) ) ) ) )
A11: P100000120013 | B11: =INDEX('Plant data'!D:D,MATCH('Blast furnaces'!$A11,'Plant data'!$A:$A,0)) -> Whyalla | C11: =INDEX('Plant data'!E:E,MATCH('Blast furnaces'!$A11,'Plant data'!$A:$A,0)) -> South Australia | D11: =INDEX('Plant data'!F:F,MATCH('Blast furnaces'!$A11,'Plant data'!$A:$A,0)) -> Australia | E11: U100000140010 | F11: BF 2 | G11: https://www.gem.wiki/GFG_Liberty_Steel_Australia_Whyalla_steel_plant | H11: operating pre-retirement | I11: unknown | J11: 1965 | K11: 1965 | L11: 60 | M11: unknown | N11: unknown | O11: unknown | P11: 1200 | Q11: 1884 | R11: 40695 | S11: =_xlfn.LET( _xlpm.x, R11, _xlpm.t, TEXT(R11,"@"), IF(R11="","", IF(ISNUMBER(_xlpm.x), IF(_xlpm.x>=30000, _xlpm.x, DATE(_xlpm.x,1,1)), DATE( LEFT(_xlpm.t,4), IF(LEN(_xlpm.t)>=7, MID(_xlpm.t,6,2), 1), IF(LEN(_xlpm.t)>=10, RIGHT(_xlpm.t,2), 1) ) ) ) ) -> 40695 | T11: =IF(R11="","",EDATE(S11,240)) -> 48000
A12: P100000120017 | B12: =INDEX('Plant data'!D:D,MATCH('Blast furnaces'!$A12,'Plant data'!$A:$A,0)) -> Zenica | C12: =INDEX('Plant data'!E:E,MATCH('Blast furnaces'!$A12,'Plant data'!$A:$A,0)) -> Zenica-Doboj | D12: =INDEX('Plant data'!F:F,MATCH('Blast furnaces'!$A12,'Plant data'!$A:$A,0)) -> Bosnia and Herzegovina | E12: U100000140011 | F12: BF 4 | G12: https://www.gem.wiki/ArcelorMittal_Zenica_steel_plant | H12: operating | I12: unknown | J12: unknown | K12: 2004 | L12: 21 | M12: unknown | N12: unknown | O12: unknown | P12: 1100 | Q12: 2024 | R12: 43252 | S12: =_xlfn.LET( _xlpm.x, R12, _xlpm.t, TEXT(R12,"@"), IF(R12="","", IF(ISNUMBER(_xlpm.x), IF(_xlpm.x>=30000, _xlpm.x, DATE(_xlpm.x,1,1)), DATE( LEFT(_xlpm.t,4), IF(LEN(_xlpm.t)>=7, MID(_xlpm.t,6,2), 1), IF(LEN(_xlpm.t)>=10, RIGHT(_xlpm.t,2), 1) ) ) ) ) -> 43252 | T12: =IF(R12="","",EDATE(S12,240)) -> 50557
A13: P100000120025 | B13: =INDEX('Plant data'!D:D,MATCH('Blast furnaces'!$A13,'Plant data'!$A:$A,0)) -> Mirsarai | C13: =INDEX('Plant data'!E:E,MATCH('Blast furnaces'!$A13,'Plant data'!$A:$A,0)) -> Chittagong | D13: =INDEX('Plant data'!F:F,MATCH('Blast furnaces'!$A13,'Plant data'!$A:$A,0)) -> Bangladesh | E13: U100000140012 | F13: unknown BF (1) | G13: https://www.gem.wiki/Star_Consortium_steel_plant | H13: cancelled | I13: 42856 | J13: unknown | K13: 2023 | L13: 2 | M13: unknown | N13: unknown | O13: unknown | P13: 2000 | Q13: unknown | S13: =_xlfn.LET( _xlpm.x, R13, _xlpm.t, TEXT(R13,"@"), IF(R13="","", IF(ISNUMBER(_xlpm.x), IF(_xlpm.x>=30000, _xlpm.x, DATE(_xlpm.x,1,1)), DATE( LEFT(_xlpm.t,4), IF(LEN(_xlpm.t)>=7, MID(_xlpm.t,6,2), 1), IF(LEN(_xlpm.t)>=10, RIGHT(_xlpm.t,2), 1) ) ) ) )
A14: P100000120027 | B14: =INDEX('Plant data'!D:D,MATCH('Blast furnaces'!$A14,'Plant data'!$A:$A,0)) -> Gent | C14: =INDEX('Plant data'!E:E,MATCH('Blast furnaces'!$A14,'Plant data'!$A:$A,0)) -> Vlaanderen | D14: =INDEX('Plant data'!F:F,MATCH('Blast furnaces'!$A14,'Plant data'!$A:$A,0)) -> Belgium | E14: U100000140013 | F14: BF B | G14: https://www.gem.wiki/ArcelorMittal_Gent_steel_plant | H14: operating | I14: unknown | J14: unknown | K14: 1967 | L14: 58 | M14: unknown | N14: unknown | O14: unknown | P14: 2300 | Q14: 2347 | R14: 44256 | S14: =_xlfn.LET( _xlpm.x, R14, _xlpm.t, TEXT(R14,"@"), IF(R14="","", IF(ISNUMBER(_xlpm.x), IF(_xlpm.x>=30000, _xlpm.x, DATE(_xlpm.x,1,1)), DATE( LEFT(_xlpm.t,4), IF(LEN(_xlpm.t)>=7, MID(_xlpm.t,6,2), 1), IF(LEN(_xlpm.t)>=10, RIGHT(_xlpm.t,2), 1) ) ) ) ) -> 44256 | T14: =IF(R14="","",EDATE(S14,240)) -> 51561
A15: P100000120027 | B15: =INDEX('Plant data'!D:D,MATCH('Blast furnaces'!$A15,'Plant data'!$A:$A,0)) -> Gent | C15: =INDEX('Plant data'!E:E,MATCH('Blast furnaces'!$A15,'Plant data'!$A:$A,0)) -> Vlaanderen | D15: =INDEX('Plant data'!F:F,MATCH('Blast furnaces'!$A15,'Plant data'!$A:$A,0)) -> Belgium | E15: U100000140014 | F15: BF A | G15: https://www.gem.wiki/ArcelorMittal_Gent_steel_plant | H15: operating pre-retirement | I15: unknown | J15: unknown | K15: 1966 | L15: 64 | M15: 44440 | N15: unknown | O15: 2030 | P15: 2700 | Q15: 2550 | R15: 45270 | S15: =_xlfn.LET( _xlpm.x, R15, _xlpm.t, TEXT(R15,"@"), IF(R15="","", IF(ISNUMBER(_xlpm.x), IF(_xlpm.x>=30000, _xlpm.x, DATE(_xlpm.x,1,1)), DATE( LEFT(_xlpm.t,4), IF(LEN(_xlpm.t)>=7, MID(_xlpm.t,6,2), 1), IF(LEN(_xlpm.t)>=10, RIGHT(_xlpm.t,2), 1) ) ) ) ) -> 45270 | T15: =IF(R15="","",EDATE(S15,240)) -> 52575
A16: P100000120033 | B16: =INDEX('Plant data'!D:D,MATCH('Blast furnaces'!$A16,'Plant data'!$A:$A,0)) -> Ouro Branco | C16: =INDEX('Plant data'!E:E,MATCH('Blast furnaces'!$A16,'Plant data'!$A:$A,0)) -> Minas Gerais | D16: =INDEX('Plant data'!F:F,MATCH('Blast furnaces'!$A16,'Plant data'!$A:$A,0)) -> Brazil | E16: U100000140015 | F16: BF 1 | G16: https://www.gem.wiki/Gerdau_Açominas_Ouro_Branco_steel_plant | H16: operating | I16: unknown | J16: unknown | K16: 1986 | L16: 39 | M16: unknown | N16: unknown | O16: unknown | P16: 2815 | Q16: 2652 | R16: 37043 | S16: =_xlfn.LET( _xlpm.x, R16, _xlpm.t, TEXT(R16,"@"), IF(R16="","", IF(ISNUMBER(_xlpm.x), IF(_xlpm.x>=30000, _xlpm.x, DATE(_xlpm.x,1,1)), DATE( LEFT(_xlpm.t,4), IF(LEN(_xlpm.t)>=7, MID(_xlpm.t,6,2), 1), IF(LEN(_xlpm.t)>=10, RIGHT(_xlpm.t,2), 1) ) ) ) ) -> 37043 | T16: =IF(R16="","",EDATE(S16,240)) -> 44348
A17: P100000120033 | B17: =INDEX('Plant data'!D:D,MATCH('Blast furnaces'!$A17,'Plant data'!$A:$A,0)) -> Ouro Branco | C17: =INDEX('Plant data'!E:E,MATCH('Blast furnaces'!$A17,'Plant data'!$A:$A,0)) -> Minas Gerais | D17: =INDEX('Plant data'!F:F,MATCH('Blast furnaces'!$A17,'Plant data'!$A:$A,0)) -> Brazil | E17: U100000140016 | F17: BF 2 | G17: https://www.gem.wiki/Gerdau_Açominas_Ouro_Branco_steel_plant | H17: operating | I17: unknown | J17: 38657 | K17: 2007 | L17: 18 | M17: unknown | N17: unknown | O17: unknown | P17: 1533 | Q17: 1420 | S17: =_xlfn.LET( _xlpm.x, R17, _xlpm.t, TEXT(R17,"@"), IF(R17="","", IF(ISNUMBER(_xlpm.x), IF(_xlpm.x>=30000, _xlpm.x, DATE(_xlpm.x,1,1)), DATE( LEFT(_xlpm.t,4), IF(LEN(_xlpm.t)>=7, MID(_xlpm.t,6,2), 1), IF(LEN(_xlpm.t)>=10, RIGHT(_xlpm.t,2), 1) ) ) ) ) | T17: =IF(R17="","",EDATE(S17,240))
A18: P100000120034 | B18: =INDEX('Plant data'!D:D,MATCH('Blast furnaces'!$A18,'Plant data'!$A:$A,0)) -> Tubarão, Serra | C18: =INDEX('Plant data'!E:E,MATCH('Blast furnaces'!$A18,'Plant data'!$A:$A,0)) -> Espírito Santo | D18: =INDEX('Plant data'!F:F,MATCH('Blast furnaces'!$A18,'Plant data'!$A:$A,0)) -> Brazil | E18: U100000140017 | F18: BF 1 | G18: https://www.gem.wiki/ArcelorMittal_Tubarão_steel_plant | H18: operating | I18: unknown | J18: unknown | K18: 1983 | L18: 42 | M18: unknown | N18: unknown | O18: unknown | P18: 3280 | Q18: 320 | R18: 41091 | S18: =_xlfn.LET( _xlpm.x, R18, _xlpm.t, TEXT(R18,"@"), IF(R18="","", IF(ISNUMBER(_xlpm.x), IF(_xlpm.x>=30000, _xlpm.x, DATE(_xlpm.x,1,1)), DATE( LEFT(_xlpm.t,4), IF(LEN(_xlpm.t)>=7, MID(_xlpm.t,6,2), 1), IF(LEN(_xlpm.t)>=10, RIGHT(_xlpm.t,2), 1) ) ) ) ) -> 41091 | T18: =IF(R18="","",EDATE(S18,240)) -> 48396
A19: P100000120034 | B19: =INDEX('Plant data'!D:D,MATCH('Blast furnaces'!$A19,'Plant data'!$A:$A,0)) -> Tubarão, Serra | C19: =INDEX('Plant data'!E:E,MATCH('Blast furnaces'!$A19,'Plant data'!$A:$A,0)) -> Espírito Santo | D19: =INDEX('Plant data'!F:F,MATCH('Blast furnaces'!$A19,'Plant data'!$A:$A,0)) -> Brazil | E19: U100000140018 | F19: BF 2 | G19: https://www.gem.wiki/ArcelorMittal_Tubarão_steel_plant | H19: operating | I19: unknown | J19: unknown | K19: 1998 | L19: 27 | M19: unknown | N19: unknown | O19: unknown | P19: 1200 | Q19: 1374 | R19: 43800 | S19: =_xlfn.LET( _xlpm.x, R19, _xlpm.t, TEXT(R19,"@"), IF(R19="","", IF(ISNUMBER(_xlpm.x), IF(_xlpm.x>=30000, _xlpm.x, DATE(_xlpm.x,1,1)), DATE( LEFT(_xlpm.t,4), IF(LEN(_xlpm.t)>=7, MID(_xlpm.t,6,2), 1), IF(LEN(_xlpm.t)>=10, RIGHT(_xlpm.t,2), 1) ) ) ) ) -> 43800 | T19: =IF(R19="","",EDATE(S19,240)) -> 51105
A20: P100000120034 | B20: =INDEX('Plant data'!D:D,MATCH('Blast furnaces'!$A20,'Plant data'!$A:$A,0)) -> Tubarão, Serra | C20: =INDEX('Plant data'!E:E,MATCH('Blast furnaces'!$A20,'Plant data'!$A:$A,0)) -> Espírito Santo | D20: =INDEX('Plant data'!F:F,MATCH('Blast furnaces'!$A20,'Plant data'!$A:$A,0)) -> Brazil | E20: U100000140019 | F20: BF 3 | G20: https://www.gem.wiki/ArcelorMittal_Tubarão_steel_plant | H20: operating | I20: unknown | J20: unknown | K20: 2007 | L20: 18 | M20: unknown | N20: unknown | O20: unknown | P20: 2800 | Q20: 3126 | S20: =_xlfn.LET( _xlpm.x, R20, _xlpm.t, TEXT(R20,"@"), IF(R20="","", IF(ISNUMBER(_xlpm.x), IF(_xlpm.x>=30000, _xlpm.x, DATE(_xlpm.x,1,1)), DATE( LEFT(_xlpm.t,4), IF(LEN(_xlpm.t)>=7, MID(_xlpm.t,6,2), 1), IF(LEN(_xlpm.t)>=10, RIGHT(_xlpm.t,2), 1) ) ) ) ) | T20: =IF(R20="","",EDATE(S20,240))
A21: P100000120035 | B21: =INDEX('Plant data'!D:D,MATCH('Blast furnaces'!$A21,'Plant data'!$A:$A,0)) -> João Monlevade | C21: =INDEX('Plant data'!E:E,MATCH('Blast furnaces'!$A21,'Plant data'!$A:$A,0)) -> Minas Gerais | D21: =INDEX('Plant data'!F:F,MATCH('Blast furnaces'!$A21,'Plant data'!$A:$A,0)) -> Brazil | E21: U100000140020 | F21: BF A | G21: https://www.gem.wiki/ArcelorMittal_Monlevade_steel_plant | H21: operating | I21: unknown | J21: unknown | K21: 1999 | L21: 26 | M21: unknown | N21: unknown | O21: unknown | P21: 1040 | Q21: 1357 | R21: 42948 | S21: =_xlfn.LET( _xlpm.x, R21, _xlpm.t, TEXT(R21,"@"), IF(R21="","", IF(ISNUMBER(_xlpm.x), IF(_xlpm.x>=30000, _xlpm.x, DATE(_xlpm.x,1,1)), DATE( LEFT(_xlpm.t,4), IF(LEN(_xlpm.t)>=7, MID(_xlpm.t,6,2), 1), IF(LEN(_xlpm.t)>=10, RIGHT(_xlpm.t,2), 1) ) ) ) ) -> 42948 | T21: =IF(R21="","",EDATE(S21,240)) -> 50253
A22: P100000120035 | B22: =INDEX('Plant data'!D:D,MATCH('Blast furnaces'!$A22,'Plant data'!$A:$A,0)) -> João Monlevade | C22: =INDEX('Plant data'!E:E,MATCH('Blast furnaces'!$A22,'Plant data'!$A:$A,0)) -> Minas Gerais | D22: =INDEX('Plant data'!F:F,MATCH('Blast furnaces'!$A22,'Plant data'!$A:$A,0)) -> Brazil | E22: U100000140021 | F22: BF B | G22: https://www.gem.wiki/ArcelorMittal_Monlevade_steel_plant | H22: cancelled | I22: 40391 | J22: 2021 | K22: 2026 | M22: unknown | N22: unknown | O22: unknown | P22: 1200 | Q22: 1524 | S22: =_xlfn.LET( _xlpm.x, R22, _xlpm.t, TEXT(R22,"@"), IF(R22="","", IF(ISNUMBER(_xlpm.x), IF(_xlpm.x>=30000, _xlpm.x, DATE(_xlpm.x,1,1)), DATE( LEFT(_xlpm.t,4), IF(LEN(_xlpm.t)>=7, MID(_xlpm.t,6,2), 1), IF(LEN(_xlpm.t)>=10, RIGHT(_xlpm.t,2), 1) ) ) ) )
A23: P100000120037 | B23: =INDEX('Plant data'!D:D,MATCH('Blast furnaces'!$A23,'Plant data'!$A:$A,0)) -> Cubatão | C23: =INDEX('Plant data'!E:E,MATCH('Blast furnaces'!$A23,'Plant data'!$A:$A,0)) -> São Paulo | D23: =INDEX('Plant data'!F:F,MATCH('Blast furnaces'!$A23,'Plant data'!$A:$A,0)) -> Brazil | E23: U100000140022 | F23: BF 1 | G23: https://www.gem.wiki/Usiminas_Cubatão_steel_plant | H23: mothballed | I23: unknown | J23: unknown | K23: 1965 | L23: 60 | M23: unknown | N23: 42125 | O23: unknown | P23: 1600 | Q23: 1820 | R23: 36892 | S23: =_xlfn.LET( _xlpm.x, R23, _xlpm.t, TEXT(R23,"@"), IF(R23="","", IF(ISNUMBER(_xlpm.x), IF(_xlpm.x>=30000, _xlpm.x, DATE(_xlpm.x,1,1)), DATE( LEFT(_xlpm.t,4), IF(LEN(_xlpm.t)>=7, MID(_xlpm.t,6,2), 1), IF(LEN(_xlpm.t)>=10, RIGHT(_xlpm.t,2), 1) ) ) ) ) -> 36892
A24: P100000120037 | B24: =INDEX('Plant data'!D:D,MATCH('Blast furnaces'!$A24,'Plant data'!$A:$A,0)) -> Cubatão | C24: =INDEX('Plant data'!E:E,MATCH('Blast furnaces'!$A24,'Plant data'!$A:$A,0)) -> São Paulo | D24: =INDEX('Plant data'!F:F,MATCH('Blast furnaces'!$A24,'Plant data'!$A:$A,0)) -> Brazil | E24: U100000140023 | F24: BF 2 | G24: https://www.gem.wiki/Usiminas_Cubatão_steel_plant | H24: mothballed | I24: unknown | J24: unknown | K24: 1976 | L24: 49 | M24: unknown | N24: 2016 | O24: unknown | P24: 2900 | Q24: 3365 | R24: 37165 | S24: =_xlfn.LET( _xlpm.x, R24, _xlpm.t, TEXT(R24,"@"), IF(R24="","", IF(ISNUMBER(_xlpm.x), IF(_xlpm.x>=30000, _xlpm.x, DATE(_xlpm.x,1,1)), DATE( LEFT(_xlpm.t,4), IF(LEN(_xlpm.t)>=7, MID(_xlpm.t,6,2), 1), IF(LEN(_xlpm.t)>=10, RIGHT(_xlpm.t,2), 1) ) ) ) ) -> 37165
A25: P100000120038 | B25: =INDEX('Plant data'!D:D,MATCH('Blast furnaces'!$A25,'Plant data'!$A:$A,0)) -> Santa Cruz | C25: =INDEX('Plant data'!E:E,MATCH('Blast furnaces'!$A25,'Plant data'!$A:$A,0)) -> Rio de Janeiro | D25: =INDEX('Plant data'!F:F,MATCH('Blast furnaces'!$A25,'Plant data'!$A:$A,0)) -> Brazil | E25: U100000140024 | F25: BF 1 | G25: https://www.gem.wiki/Ternium_Brasil_Santa_Cruz_steel_plant | H25: operating | I25: unknown | J25: unknown | K25: 2010 | L25: 15 | M25: unknown | N25: unknown | O25: unknown | P25: 2650 | Q25: 3300 | S25: =_xlfn.LET( _xlpm.x, R25, _xlpm.t, TEXT(R25,"@"), IF(R25="","", IF(ISNUMBER(_xlpm.x), IF(_xlpm.x>=30000, _xlpm.x, DATE(_xlpm.x,1,1)), DATE( LEFT(_xlpm.t,4), IF(LEN(_xlpm.t)>=7, MID(_xlpm.t,6,2), 1), IF(LEN(_xlpm.t)>=10, RIGHT(_xlpm.t,2), 1) ) ) ) ) | T25: =IF(R25="","",EDATE(S25,240))
A26: P100000120038 | B26: =INDEX('Plant data'!D:D,MATCH('Blast furnaces'!$A26,'Plant data'!$A:$A,0)) -> Santa Cruz | C26: =INDEX('Plant data'!E:E,MATCH('Blast furnaces'!$A26,'Plant data'!$A:$A,0)) -> Rio de Janeiro | D26: =INDEX('Plant data'!F:F,MATCH('Blast furnaces'!$A26,'Plant data'!$A:$A,0)) -> Brazil | E26: U100000140025 | F26: BF 2 | G26: https://www.gem.wiki/Ternium_Brasil_Santa_Cruz_steel_plant | H26: operating | I26: unknown | J26: unknown | K26: 2010 | L26: 15 | M26: unknown | N26: unknown | O26: unknown | P26: 2650 | Q26: 3300 | S26: =_xlfn.LET( _xlpm.x, R26, _xlpm.t, TEXT(R26,"@"), IF(R26="","", IF(ISNUMBER(_xlpm.x), IF(_xlpm.x>=30000, _xlpm.x, DATE(_xlpm.x,1,1)), DATE( LEFT(_xlpm.t,4), IF(LEN(_xlpm.t)>=7, MID(_xlpm.t,6,2), 1), IF(LEN(_xlpm.t)>=10, RIGHT(_xlpm.t,2), 1) ) ) ) ) | T26: =IF(R26="","",EDATE(S26,240))
A27: P100000120039 | B27: =INDEX('Plant data'!D:D,MATCH('Blast furnaces'!$A27,'Plant data'!$A:$A,0)) -> Volta Redonda | C27: =INDEX('Plant data'!E:E,MATCH('Blast furnaces'!$A27,'Plant data'!$A:$A,0)) -> Rio de Janeiro | D27: =INDEX('Plant data'!F:F,MATCH('Blast furnaces'!$A27,'Plant data'!$A:$A,0)) -> Brazil | E27: U100000140026 | F27: BF 3 | G27: https://www.gem.wiki/CSN_Volta_Redonda_steel_plant | H27: operating | I27: unknown | J27: unknown | K27: 1976 | L27: 49 | M27: unknown | N27: unknown | O27: unknown | P27: 3900 | Q27: 4247 | R27: 43705 | S27: =_xlfn.LET( _xlpm.x, R27, _xlpm.t, TEXT(R27,"@"), IF(R27="","", IF(ISNUMBER(_xlpm.x), IF(_xlpm.x>=30000, _xlpm.x, DATE(_xlpm.x,1,1)), DATE( LEFT(_xlpm.t,4), IF(LEN(_xlpm.t)>=7, MID(_xlpm.t,6,2), 1), IF(LEN(_xlpm.t)>=10, RIGHT(_xlpm.t,2), 1) ) ) ) ) -> 43705 | T27: =IF(R27="","",EDATE(S27,240)) -> 51010
A28: P100000120039 | B28: =INDEX('Plant data'!D:D,MATCH('Blast furnaces'!$A28,'Plant data'!$A:$A,0)) -> Volta Redonda | C28: =INDEX('Plant data'!E:E,MATCH('Blast furnaces'!$A28,'Plant data'!$A:$A,0)) -> Rio de Janeiro | D28: =INDEX('Plant data'!F:F,MATCH('Blast furnaces'!$A28,'Plant data'!$A:$A,0)) -> Brazil | E28: U100000140027 | F28: BF 2 | G28: https://www.gem.wiki/CSN_Volta_Redonda_steel_plant | H28: operating | I28: unknown | J28: unknown | K28: 1954 | L28: 71 | M28: unknown | N28: unknown | O28: unknown | P28: 1680 | Q28: 1653 | R28: 42644 | S28: =_xlfn.LET( _xlpm.x, R28, _xlpm.t, TEXT(R28,"@"), IF(R28="","", IF(ISNUMBER(_xlpm.x), IF(_xlpm.x>=30000, _xlpm.x, DATE(_xlpm.x,1,1)), DATE( LEFT(_xlpm.t,4), IF(LEN(_xlpm.t)>=7, MID(_xlpm.t,6,2), 1), IF(LEN(_xlpm.t)>=10, RIGHT(_xlpm.t,2), 1) ) ) ) ) -> 42644 | T28: =IF(R28="","",EDATE(S28,240)) -> 49949
A29: P100000120040 | B29: =INDEX('Plant data'!D:D,MATCH('Blast furnaces'!$A29,'Plant data'!$A:$A,0)) -> São Gonçalo do Amarante | C29: =INDEX('Plant data'!E:E,MATCH('Blast furnaces'!$A29,'Plant data'!$A:$A,0)) -> Ceará | D29: =INDEX('Plant data'!F:F,MATCH('Blast furnaces'!$A29,'Plant data'!$A:$A,0)) -> Brazil | E29: U100000140028 | F29: BF 1 | G29: https://www.gem.wiki/ArcelorMittal_Pecém_steel_plant | H29: operating | I29: unknown | J29: 44743 | K29: 2016 | L29: 9 | M29: unknown | N29: unknown | O29: unknown | P29: 3192 | Q29: 3800 | S29: =_xlfn.LET( _xlpm.x, R29, _xlpm.t, TEXT(R29,"@"), IF(R29="","", IF(ISNUMBER(_xlpm.x), IF(_xlpm.x>=30000, _xlpm.x, DATE(_xlpm.x,1,1)), DATE( LEFT(_xlpm.t,4), IF(LEN(_xlpm.t)>=7, MID(_xlpm.t,6,2), 1), IF(LEN(_xlpm.t)>=10, RIGHT(_xlpm.t,2), 1) ) ) ) ) | T29: =IF(R29="","",EDATE(S29,240))
A30: P100000120043 | B30: =INDEX('Plant data'!D:D,MATCH('Blast furnaces'!$A30,'Plant data'!$A:$A,0)) -> Ipatinga | C30: =INDEX('Plant data'!E:E,MATCH('Blast furnaces'!$A30,'Plant data'!$A:$A,0)) -> Minas Gerais | D30: =INDEX('Plant data'!F:F,MATCH('Blast furnaces'!$A30,'Plant data'!$A:$A,0)) -> Brazil | E30: U100000140029 | F30: BF 1 | G30: https://www.gem.wiki/Usiminas_Ipatinga_steel_plant | H30: mothballed | I30: unknown | J30: unknown | K30: 1962 | L30: 63 | M30: unknown | N30: unknown | O30: unknown | P30: 660 | Q30: 777 | R30: 43191 | S30: =_xlfn.LET( _xlpm.x, R30, _xlpm.t, TEXT(R30,"@"), IF(R30="","", IF(ISNUMBER(_xlpm.x), IF(_xlpm.x>=30000, _xlpm.x, DATE(_xlpm.x,1,1)), DATE( LEFT(_xlpm.t,4), IF(LEN(_xlpm.t)>=7, MID(_xlpm.t,6,2), 1), IF(LEN(_xlpm.t)>=10, RIGHT(_xlpm.t,2), 1) ) ) ) ) -> 43191
A31: P100000120043 | B31: =INDEX('Plant data'!D:D,MATCH('Blast furnaces'!$A31,'Plant data'!$A:$A,0)) -> Ipatinga | C31: =INDEX('Plant data'!E:E,MATCH('Blast furnaces'!$A31,'Plant data'!$A:$A,0)) -> Minas Gerais | D31: =INDEX('Plant data'!F:F,MATCH('Blast furnaces'!$A31,'Plant data'!$A:$A,0)) -> Brazil | E31: U100000140030 | F31: BF 2 | G31: https://www.gem.wiki/Usiminas_Ipatinga_steel_plant | H31: operating | I31: unknown | J31: unknown | K31: 1965 | L31: 60 | M31: unknown | N31: unknown | O31: unknown | P31: 660 | Q31: 777 | R31: 44348 | S31: =_xlfn.LET( _xlpm.x, R31, _xlpm.t, TEXT(R31,"@"), IF(R31="","", IF(ISNUMBER(_xlpm.x), IF(_xlpm.x>=30000, _xlpm.x, DATE(_xlpm.x,1,1)), DATE( LEFT(_xlpm.t,4), IF(LEN(_xlpm.t)>=7, MID(_xlpm.t,6,2), 1), IF(LEN(_xlpm.t)>=10, RIGHT(_xlpm.t,2), 1) ) ) ) ) -> 44348 | T31: =IF(R31="","",EDATE(S31,240)) -> 51653
A32: P100000120043 | B32: =INDEX('Plant data'!D:D,MATCH('Blast furnaces'!$A32,'Plant data'!$A:$A,0)) -> Ipatinga | C32: =INDEX('Plant data'!E:E,MATCH('Blast furnaces'!$A32,'Plant data'!$A:$A,0)) -> Minas Gerais | D32: =INDEX('Plant data'!F:F,MATCH('Blast furnaces'!$A32,'Plant data'!$A:$A,0)) -> Brazil | E32: U100000140031 | F32: BF 3 | G32: https://www.gem.wiki/Usiminas_Ipatinga_steel_plant | H32: operating | I32: unknown | J32: unknown | K32: 1974 | L32: 51 | M32: unknown | N32: unknown | O32: unknown | P32: 3000 | Q32: 2722 | R32: 45231 | S32: =_xlfn.LET( _xlpm.x, R32, _xlpm.t, TEXT(R32,"@"), IF(R32="","", IF(ISNUMBER(_xlpm.x), IF(_xlpm.x>=30000, _xlpm.x, DATE(_xlpm.x,1,1)), DATE( LEFT(_xlpm.t,4), IF(LEN(_xlpm.t)>=7, MID(_xlpm.t,6,2), 1), IF(LEN(_xlpm.t)>=10, RIGHT(_xlpm.t,2), 1) ) ) ) ) -> 45231 | T32: =IF(R32="","",EDATE(S32,240)) -> 52536
A33: P100000120044 | B33: =INDEX('Plant data'!D:D,MATCH('Blast furnaces'!$A33,'Plant data'!$A:$A,0)) -> Jeceaba | C33: =INDEX('Plant data'!E:E,MATCH('Blast furnaces'!$A33,'Plant data'!$A:$A,0)) -> Minas Gerais | D33: =INDEX('Plant data'!F:F,MATCH('Blast furnaces'!$A33,'Plant data'!$A:$A,0)) -> Brazil | E33: U100000140032 | F33: BF 2 | G33: https://www.gem.wiki/Vallourec_Jeceaba_steel_plant | H33: operating | I33: unknown | J33: unknown | K33: 2014 | L33: 11 | M33: unknown | N33: unknown | O33: unknown | P33: 350 | Q33: 350 | S33: =_xlfn.LET( _xlpm.x, R33, _xlpm.t, TEXT(R33,"@"), IF(R33="","", IF(ISNUMBER(_xlpm.x), IF(_xlpm.x>=30000, _xlpm.x, DATE(_xlpm.x,1,1)), DATE( LEFT(_xlpm.t,4), IF(LEN(_xlpm.t)>=7, MID(_xlpm.t,6,2), 1), IF(LEN(_xlpm.t)>=10, RIGHT(_xlpm.t,2), 1) ) ) ) ) | T33: =IF(R33="","",EDATE(S33,240))
A34: P100000120044 | B34: =INDEX('Plant data'!D:D,MATCH('Blast furnaces'!$A34,'Plant data'!$A:$A,0)) -> Jeceaba | C34: =INDEX('Plant data'!E:E,MATCH('Blast furnaces'!$A34,'Plant data'!$A:$A,0)) -> Minas Gerais | D34: =INDEX('Plant data'!F:F,MATCH('Blast furnaces'!$A34,'Plant data'!$A:$A,0)) -> Brazil | E34: U100000140033 | F34: BF 1 | G34: https://www.gem.wiki/Vallourec_Jeceaba_steel_plant | H34: cancelled | I34: unknown | J34: unknown | K34: unknown | L34: unknown | M34: unknown | N34: unknown | O34: unknown | P34: 500 | Q34: 350 | S34: =_xlfn.LET( _xlpm.x, R34, _xlpm.t, TEXT(R34,"@"), IF(R34="","", IF(ISNUMBER(_xlpm.x), IF(_xlpm.x>=30000, _xlpm.x, DATE(_xlpm.x,1,1)), DATE( LEFT(_xlpm.t,4), IF(LEN(_xlpm.t)>=7, MID(_xlpm.t,6,2), 1), IF(LEN(_xlpm.t)>=10, RIGHT(_xlpm.t,2), 1) ) ) ) )
A35: P100000120045 | B35: =INDEX('Plant data'!D:D,MATCH('Blast furnaces'!$A35,'Plant data'!$A:$A,0)) -> Juiz de Fora | C35: =INDEX('Plant data'!E:E,MATCH('Blast furnaces'!$A35,'Plant data'!$A:$A,0)) -> Minas Gerais | D35: =INDEX('Plant data'!F:F,MATCH('Blast furnaces'!$A35,'Plant data'!$A:$A,0)) -> Brazil | E35: U100000140034 | F35: BF 1 | G35: https://www.gem.wiki/ArcelorMittal_Juiz_de_Fora_steel_plant | H35: operating | I35: unknown | J35: unknown | K35: 2007 | L35: 18 | M35: unknown | N35: unknown | O35: unknown | P35: 180 | Q35: 250 | R35: 44166 | S35: =_xlfn.LET( _xlpm.x, R35, _xlpm.t, TEXT(R35,"@"), IF(R35="","", IF(ISNUMBER(_xlpm.x), IF(_xlpm.x>=30000, _xlpm.x, DATE(_xlpm.x,1,1)), DATE( LEFT(_xlpm.t,4), IF(LEN(_xlpm.t)>=7, MID(_xlpm.t,6,2), 1), IF(LEN(_xlpm.t)>=10, RIGHT(_xlpm.t,2), 1) ) ) ) ) -> 44166 | T35: =IF(R35="","",EDATE(S35,240)) -> 51471
A36: P100000120045 | B36: =INDEX('Plant data'!D:D,MATCH('Blast furnaces'!$A36,'Plant data'!$A:$A,0)) -> Juiz de Fora | C36: =INDEX('Plant data'!E:E,MATCH('Blast furnaces'!$A36,'Plant data'!$A:$A,0)) -> Minas Gerais | D36: =INDEX('Plant data'!F:F,MATCH('Blast furnaces'!$A36,'Plant data'!$A:$A,0)) -> Brazil | E36: U100000140035 | F36: BF 2 | G36: https://www.gem.wiki/ArcelorMittal_Juiz_de_Fora_steel_plant | H36: operating | I36: unknown | J36: unknown | K36: 2007 | L36: 18 | M36: unknown | N36: unknown | O36: unknown | P36: 180 | Q36: 250 | R36: 44440 | S36: =_xlfn.LET( _xlpm.x, R36, _xlpm.t, TEXT(R36,"@"), IF(R36="","", IF(ISNUMBER(_xlpm.x), IF(_xlpm.x>=30000, _xlpm.x, DATE(_xlpm.x,1,1)), DATE( LEFT(_xlpm.t,4), IF(LEN(_xlpm.t)>=7, MID(_xlpm.t,6,2), 1), IF(LEN(_xlpm.t)>=10, RIGHT(_xlpm.t,2), 1) ) ) ) ) -> 44440 | T36: =IF(R36="","",EDATE(S36,240)) -> 51745
A37: P100000120046 | B37: =INDEX('Plant data'!D:D,MATCH('Blast furnaces'!$A37,'Plant data'!$A:$A,0)) -> Açailândia | C37: =INDEX('Plant data'!E:E,MATCH('Blast furnaces'!$A37,'Plant data'!$A:$A,0)) -> Maranhão | D37: =INDEX('Plant data'!F:F,MATCH('Blast furnaces'!$A37,'Plant data'!$A:$A,0)) -> Brazil | E37: U100000140036 | F37: BF 1; "Roberta" | G37: https://www.gem.wiki/AVB_Açailândia_steel_plant | H37: operating | I37: unknown | J37: unknown | K37: 2018 | L37: 7 | M37: unknown | N37: unknown | O37: unknown | P37: 360 | Q37: 352 | S37: =_xlfn.LET( _xlpm.x, R37, _xlpm.t, TEXT(R37,"@"), IF(R37="","", IF(ISNUMBER(_xlpm.x), IF(_xlpm.x>=30000, _xlpm.x, DATE(_xlpm.x,1,1)), DATE( LEFT(_xlpm.t,4), IF(LEN(_xlpm.t)>=7, MID(_xlpm.t,6,2), 1), IF(LEN(_xlpm.t)>=10, RIGHT(_xlpm.t,2), 1) ) ) ) ) | T37: =IF(R37="","",EDATE(S37,240))
A38: P100000120046 | B38: =INDEX('Plant data'!D:D,MATCH('Blast furnaces'!$A38,'Plant data'!$A:$A,0)) -> Açailândia | C38: =INDEX('Plant data'!E:E,MATCH('Blast furnaces'!$A38,'Plant data'!$A:$A,0)) -> Maranhão | D38: =INDEX('Plant data'!F:F,MATCH('Blast furnaces'!$A38,'Plant data'!$A:$A,0)) -> Brazil | E38: U100000140037 | F38: BF 2; "Regina" | G38: https://www.gem.wiki/AVB_Açailândia_steel_plant | H38: operating | I38: unknown | J38: unknown | K38: 2021 | L38: 4 | M38: unknown | N38: unknown | O38: unknown | P38: 360 | Q38: 352 | S38: =_xlfn.LET( _xlpm.x, R38, _xlpm.t, TEXT(R38,"@"), IF(R38="","", IF(ISNUMBER(_xlpm.x), IF(_xlpm.x>=30000, _xlpm.x, DATE(_xlpm.x,1,1)), DATE( LEFT(_xlpm.t,4), IF(LEN(_xlpm.t)>=7, MID(_xlpm.t,6,2), 1), IF(LEN(_xlpm.t)>=10, RIGHT(_xlpm.t,2), 1) ) ) ) ) | T38: =IF(R38="","",EDATE(S38,240))
A39: P100000120047 | B39: =INDEX('Plant data'!D:D,MATCH('Blast furnaces'!$A39,'Plant data'!$A:$A,0)) -> Divinópolis | C39: =INDEX('Plant data'!E:E,MATCH('Blast furnaces'!$A39,'Plant data'!$A:$A,0)) -> Minas Gerais | D39: =INDEX('Plant data'!F:F,MATCH('Blast furnaces'!$A39,'Plant data'!$A:$A,0)) -> Brazil | E39: U100000140038 | F39: BF 1 | G39: https://www.gem.wiki/Gerdau_Divinópolis_steel_plant | H39: operating | I39: unknown | J39: unknown | K39: 1957 | L39: 68 | M39: unknown | N39: unknown | O39: unknown | P39: 112 | Q39: 110 | R39: 44713 | S39: =_xlfn.LET( _xlpm.x, R39, _xlpm.t, TEXT(R39,"@"), IF(R39="","", IF(ISNUMBER(_xlpm.x), IF(_xlpm.x>=30000, _xlpm.x, DATE(_xlpm.x,1,1)), DATE( LEFT(_xlpm.t,4), IF(LEN(_xlpm.t)>=7, MID(_xlpm.t,6,2), 1), IF(LEN(_xlpm.t)>=10, RIGHT(_xlpm.t,2), 1) ) ) ) ) -> 44713 | T39: =IF(R39="","",EDATE(S39,240)) -> 52018
A40: P100000120047 | B40: =INDEX('Plant data'!D:D,MATCH('Blast furnaces'!$A40,'Plant data'!$A:$A,0)) -> Divinópolis | C40: =INDEX('Plant data'!E:E,MATCH('Blast furnaces'!$A40,'Plant data'!$A:$A,0)) -> Minas Gerais | D40: =INDEX('Plant data'!F:F,MATCH('Blast furnaces'!$A40,'Plant data'!$A:$A,0)) -> Brazil | E40: U100000140039 | F40: BF 3 | G40: https://www.gem.wiki/Gerdau_Divinópolis_steel_plant | H40: operating | I40: unknown | J40: unknown | K40: unknown | L40: unknown | M40: unknown | N40: unknown | O40: unknown | P40: 128 | Q40: 125 | R40: 44713 | S40: =_xlfn.LET( _xlpm.x, R40, _xlpm.t, TEXT(R40,"@"), IF(R40="","", IF(ISNUMBER(_xlpm.x), IF(_xlpm.x>=30000, _xlpm.x, DATE(_xlpm.x,1,1)), DATE( LEFT(_xlpm.t,4), IF(LEN(_xlpm.t)>=7, MID(_xlpm.t,6,2), 1), IF(LEN(_xlpm.t)>=10, RIGHT(_xlpm.t,2), 1) ) ) ) ) -> 44713 | T40: =IF(R40="","",EDATE(S40,240)) -> 52018
A41: P100000120047 | B41: =INDEX('Plant data'!D:D,MATCH('Blast furnaces'!$A41,'Plant data'!$A:$A,0)) -> Divinópolis | C41: =INDEX('Plant data'!E:E,MATCH('Blast furnaces'!$A41,'Plant data'!$A:$A,0)) -> Minas Gerais | D41: =INDEX('Plant data'!F:F,MATCH('Blast furnaces'!$A41,'Plant data'!$A:$A,0)) -> Brazil | E41: U100000141457 | F41: BF 2 | G41: https://www.gem.wiki/Gerdau_Divinópolis_steel_plant | H41: operating | I41: unknown | J41: unknown | K41: 2005 | L41: 20 | M41: unknown | N41: unknown | O41: unknown | P41: 190 | Q41: 192 | R41: 44713 | S41: =_xlfn.LET( _xlpm.x, R41, _xlpm.t, TEXT(R41,"@"), IF(R41="","", IF(ISNUMBER(_xlpm.x), IF(_xlpm.x>=30000, _xlpm.x, DATE(_xlpm.x,1,1)), DATE( LEFT(_xlpm.t,4), IF(LEN(_xlpm.t)>=7, MID(_xlpm.t,6,2), 1), IF(LEN(_xlpm.t)>=10, RIGHT(_xlpm.t,2), 1) ) ) ) ) -> 44713 | T41: =IF(R41="","",EDATE(S41,240)) -> 52018
A42: P100000120053 | B42: =INDEX('Plant data'!D:D,MATCH('Blast furnaces'!$A42,'Plant data'!$A:$A,0)) -> Timóteo | C42: =INDEX('Plant data'!E:E,MATCH('Blast furnaces'!$A42,'Plant data'!$A:$A,0)) -> Minas Gerais | D42: =INDEX('Plant data'!F:F,MATCH('Blast furnaces'!$A42,'Plant data'!$A:$A,0)) -> Brazil | E42: U100000140040 | F42: BF 1 | G42: https://www.gem.wiki/Aperam_Timóteo_steel_plant | H42: operating | I42: unknown | J42: unknown | K42: 1949 | L42: 76 | M42: unknown | N42: unknown | O42: unknown | P42: 237 | Q42: 294 | R42: 44562 | S42: =_xlfn.LET( _xlpm.x, R42, _xlpm.t, TEXT(R42,"@"), IF(R42="","", IF(ISNUMBER(_xlpm.x), IF(_xlpm.x>=30000, _xlpm.x, DATE(_xlpm.x,1,1)), DATE( LEFT(_xlpm.t,4), IF(LEN(_xlpm.t)>=7, MID(_xlpm.t,6,2), 1), IF(LEN(_xlpm.t)>=10, RIGHT(_xlpm.t,2), 1) ) ) ) ) -> 44562 | T42: =IF(R42="","",EDATE(S42,240)) -> 51867
A43: P100000120053 | B43: =INDEX('Plant data'!D:D,MATCH('Blast furnaces'!$A43,'Plant data'!$A:$A,0)) -> Timóteo | C43: =INDEX('Plant data'!E:E,MATCH('Blast furnaces'!$A43,'Plant data'!$A:$A,0)) -> Minas Gerais | D43: =INDEX('Plant data'!F:F,MATCH('Blast furnaces'!$A43,'Plant data'!$A:$A,0)) -> Brazil | E43: U100000140041 | F43: BF 2 | G43: https://www.gem.wiki/Aperam_Timóteo_steel_plant | H43: operating | I43: unknown | J43: unknown | K43: 1979 | L43: 46 | M43: unknown | N43: unknown | O43: unknown | P43: 464 | Q43: 631 | R43: 38480 | S43: =_xlfn.LET( _xlpm.x, R43, _xlpm.t, TEXT(R43,"@"), IF(R43="","", IF(ISNUMBER(_xlpm.x), IF(_xlpm.x>=30000, _xlpm.x, DATE(_xlpm.x,1,1)), DATE( LEFT(_xlpm.t,4), IF(LEN(_xlpm.t)>=7, MID(_xlpm.t,6,2), 1), IF(LEN(_xlpm.t)>=10, RIGHT(_xlpm.t,2), 1) ) ) ) ) -> 38480 | T43: =IF(R43="","",EDATE(S43,240)) -> 45785
A44: P100000120054 | B44: =INDEX('Plant data'!D:D,MATCH('Blast furnaces'!$A44,'Plant data'!$A:$A,0)) -> Açailândia | C44: =INDEX('Plant data'!E:E,MATCH('Blast furnaces'!$A44,'Plant data'!$A:$A,0)) -> Maranhão | D44: =INDEX('Plant data'!F:F,MATCH('Blast furnaces'!$A44,'Plant data'!$A:$A,0)) -> Brazil | E44: U100000140042 | F44: BF 1 | G44: https://www.gem.wiki/Viena_Açailândia_iron_works | H44: operating | I44: unknown | J44: unknown | K44: 1988 | L44: 37 | M44: unknown | N44: unknown | O44: unknown | P44: 100 | Q44: unknown | S44: =_xlfn.LET( _xlpm.x, R44, _xlpm.t, TEXT(R44,"@"), IF(R44="","", IF(ISNUMBER(_xlpm.x), IF(_xlpm.x>=30000, _xlpm.x, DATE(_xlpm.x,1,1)), DATE( LEFT(_xlpm.t,4), IF(LEN(_xlpm.t)>=7, MID(_xlpm.t,6,2), 1), IF(LEN(_xlpm.t)>=10, RIGHT(_xlpm.t,2), 1) ) ) ) ) | T44: =IF(R44="","",EDATE(S44,240))
A45: P100000120054 | B45: =INDEX('Plant data'!D:D,MATCH('Blast furnaces'!$A45,'Plant data'!$A:$A,0)) -> Açailândia | C45: =INDEX('Plant data'!E:E,MATCH('Blast furnaces'!$A45,'Plant data'!$A:$A,0)) -> Maranhão | D45: =INDEX('Plant data'!F:F,MATCH('Blast furnaces'!$A45,'Plant data'!$A:$A,0)) -> Brazil | E45: U100000140043 | F45: BF 2 | G45: https://www.gem.wiki/Viena_Açailândia_iron_works | H45: operating | I45: unknown | J45: unknown | K45: 1990 | L45: 35 | M45: unknown | N45: unknown | O45: unknown | P45: 100 | Q45: unknown | S45: =_xlfn.LET( _xlpm.x, R45, _xlpm.t, TEXT(R45,"@"), IF(R45="","", IF(ISNUMBER(_xlpm.x), IF(_xlpm.x>=30000, _xlpm.x, DATE(_xlpm.x,1,1)), DATE( LEFT(_xlpm.t,4), IF(LEN(_xlpm.t)>=7, MID(_xlpm.t,6,2), 1), IF(LEN(_xlpm.t)>=10, RIGHT(_xlpm.t,2), 1) ) ) ) ) | T45: =IF(R45="","",EDATE(S45,240))
A46: P100000120054 | B46: =INDEX('Plant data'!D:D,MATCH('Blast furnaces'!$A46,'Plant data'!$A:$A,0)) -> Açailândia | C46: =INDEX('Plant data'!E:E,MATCH('Blast furnaces'!$A46,'Plant data'!$A:$A,0)) -> Maranhão | D46: =INDEX('Plant data'!F:F,MATCH('Blast furnaces'!$A46,'Plant data'!$A:$A,0)) -> Brazil | E46: U100000140044 | F46: BF 3 | G46: https://www.gem.wiki/Viena_Açailândia_iron_works | H46: operating | I46: unknown | J46: unknown | K46: 1992 | L46: 33 | M46: unknown | N46: unknown | O46: unknown | P46: 100 | Q46: unknown | S46: =_xlfn.LET( _xlpm.x, R46, _xlpm.t, TEXT(R46,"@"), IF(R46="","", IF(ISNUMBER(_xlpm.x), IF(_xlpm.x>=30000, _xlpm.x, DATE(_xlpm.x,1,1)), DATE( LEFT(_xlpm.t,4), IF(LEN(_xlpm.t)>=7, MID(_xlpm.t,6,2), 1), IF(LEN(_xlpm.t)>=10, RIGHT(_xlpm.t,2), 1) ) ) ) ) | T46: =IF(R46="","",EDATE(S46,240))
A47: P100000120054 | B47: =INDEX('Plant data'!D:D,MATCH('Blast furnaces'!$A47,'Plant data'!$A:$A,0)) -> Açailândia | C47: =INDEX('Plant data'!E:E,MATCH('Blast furnaces'!$A47,'Plant data'!$A:$A,0)) -> Maranhão | D47: =INDEX('Plant data'!F:F,MATCH('Blast furnaces'!$A47,'Plant data'!$A:$A,0)) -> Brazil | E47: U100000140045 | F47: BF 4 | G47: https://www.gem.wiki/Viena_Açailândia_iron_works | H47: operating | I47: unknown | J47: unknown | K47: 1999 | L47: 26 | M47: unknown | N47: unknown | O47: unknown | P47: 100 | Q47: unknown | S47: =_xlfn.LET( _xlpm.x, R47, _xlpm.t, TEXT(R47,"@"), IF(R47="","", IF(ISNUMBER(_xlpm.x), IF(_xlpm.x>=30000, _xlpm.x, DATE(_xlpm.x,1,1)), DATE( LEFT(_xlpm.t,4), IF(LEN(_xlpm.t)>=7, MID(_xlpm.t,6,2), 1), IF(LEN(_xlpm.t)>=10, RIGHT(_xlpm.t,2), 1) ) ) ) ) | T47: =IF(R47="","",EDATE(S47,240))
A48: P100000120054 | B48: =INDEX('Plant data'!D:D,MATCH('Blast furnaces'!$A48,'Plant data'!$A:$A,0)) -> Açailândia | C48: =INDEX('Plant data'!E:E,MATCH('Blast furnaces'!$A48,'Plant data'!$A:$A,0)) -> Maranhão | D48: =INDEX('Plant data'!F:F,MATCH('Blast furnaces'!$A48,'Plant data'!$A:$A,0)) -> Brazil | E48: U100000140046 | F48: BF 5 | G48: https://www.gem.wiki/Viena_Açailândia_iron_works | H48: operating | I48: unknown | J48: unknown | K48: 2004 | L48: 21 | M48: unknown | N48: unknown | O48: unknown | P48: 100 | Q48: unknown | S48: =_xlfn.LET( _xlpm.x, R48, _xlpm.t, TEXT(R48,"@"), IF(R48="","", IF(ISNUMBER(_xlpm.x), IF(_xlpm.x>=30000, _xlpm.x, DATE(_xlpm.x,1,1)), DATE( LEFT(_xlpm.t,4), IF(LEN(_xlpm.t)>=7, MID(_xlpm.t,6,2), 1), IF(LEN(_xlpm.t)>=10, RIGHT(_xlpm.t,2), 1) ) ) ) ) | T48: =IF(R48="","",EDATE(S48,240))
A49: P100000120058 | B49: =INDEX('Plant data'!D:D,MATCH('Blast furnaces'!$A49,'Plant data'!$A:$A,0)) -> Hamilton | C49: =INDEX('Plant data'!E:E,MATCH('Blast furnaces'!$A49,'Plant data'!$A:$A,0)) -> Ontario | D49: =INDEX('Plant data'!F:F,MATCH('Blast furnaces'!$A49,'Plant data'!$A:$A,0)) -> Canada | E49: U100000140047 | F49: BF 2 | G49: https://www.gem.wiki/ArcelorMittal_Dofasco_steel_plant | H49: operating pre-retirement | I49: unknown | J49: unknown | K49: 1957 | L49: 71 | M49: 44440 | N49: unknown | O49: 2028 | P49: 785 | Q49: 1062 | R49: 38534 | S49: =_xlfn.LET( _xlpm.x, R49, _xlpm.t, TEXT(R49,"@"), IF(R49="","", IF(ISNUMBER(_xlpm.x), IF(_xlpm.x>=30000, _xlpm.x, DATE(_xlpm.x,1,1)), DATE( LEFT(_xlpm.t,4), IF(LEN(_xlpm.t)>=7, MID(_xlpm.t,6,2), 1), IF(LEN(_xlpm.t)>=10, RIGHT(_xlpm.t,2), 1) ) ) ) ) -> 38534 | T49: =IF(R49="","",EDATE(S49,240)) -> 45839
A50: P100000120058 | B50: =INDEX('Plant data'!D:D,MATCH('Blast furnaces'!$A50,'Plant data'!$A:$A,0)) -> Hamilton | C50: =INDEX('Plant data'!E:E,MATCH('Blast furnaces'!$A50,'Plant data'!$A:$A,0)) -> Ontario | D50: =INDEX('Plant data'!F:F,MATCH('Blast furnaces'!$A50,'Plant data'!$A:$A,0)) -> Canada | E50: U100000140048 | F50: BF 3 | G50: https://www.gem.wiki/ArcelorMittal_Dofasco_steel_plant | H50: mothballed | I50: unknown | J50: unknown | K50: 2010 | L50: 18 | M50: 44440 | N50: 43922 | O50: 2028 | P50: 716 | Q50: 925 | R50: 2010 | S50: =_xlfn.LET( _xlpm.x, R50, _xlpm.t, TEXT(R50,"@"), IF(R50="","", IF(ISNUMBER(_xlpm.x), IF(_xlpm.x>=30000, _xlpm.x, DATE(_xlpm.x,1,1)), DATE( LEFT(_xlpm.t,4), IF(LEN(_xlpm.t)>=7, MID(_xlpm.t,6,2), 1), IF(LEN(_xlpm.t)>=10, RIGHT(_xlpm.t,2), 1) ) ) ) ) -> 40179
A51: P100000120058 | B51: =INDEX('Plant data'!D:D,MATCH('Blast furnaces'!$A51,'Plant data'!$A:$A,0)) -> Hamilton | C51: =INDEX('Plant data'!E:E,MATCH('Blast furnaces'!$A51,'Plant data'!$A:$A,0)) -> Ontario | D51: =INDEX('Plant data'!F:F,MATCH('Blast furnaces'!$A51,'Plant data'!$A:$A,0)) -> Canada | E51: U100000140049 | F51: BF 4 | G51: https://www.gem.wiki/ArcelorMittal_Dofasco_steel_plant | H51: operating pre-retirement | I51: unknown | J51: unknown | K51: 1971 | L51: 57 | M51: 44440 | N51: unknown | O51: 2028 | P51: 1523 | Q51: 1609 | S51: =_xlfn.LET( _xlpm.x, R51, _xlpm.t, TEXT(R51,"@"), IF(R51="","", IF(ISNUMBER(_xlpm.x), IF(_xlpm.x>=30000, _xlpm.x, DATE(_xlpm.x,1,1)), DATE( LEFT(_xlpm.t,4), IF(LEN(_xlpm.t)>=7, MID(_xlpm.t,6,2), 1), IF(LEN(_xlpm.t)>=10, RIGHT(_xlpm.t,2), 1) ) ) ) ) | T51: =IF(R51="","",EDATE(S51,240))
A52: P100000120059 | B52: =INDEX('Plant data'!D:D,MATCH('Blast furnaces'!$A52,'Plant data'!$A:$A,0)) -> Sault Ste. Marie | C52: =INDEX('Plant data'!E:E,MATCH('Blast furnaces'!$A52,'Plant data'!$A:$A,0)) -> Ontario | D52: =INDEX('Plant data'!F:F,MATCH('Blast furnaces'!$A52,'Plant data'!$A:$A,0)) -> Canada | E52: U100000140050 | F52: BF 7 | G52: https://www.gem.wiki/Algoma_steel_plant | H52: operating pre-retirement | I52: unknown | J52: unknown | K52: 1975 | L52: 55 | M52: 44511 | N52: unknown | O52: 2030 | P52: 2690 | Q52: 2478 | R52: 2007 | S52: =_xlfn.LET( _xlpm.x, R52, _xlpm.t, TEXT(R52,"@"), IF(R52="","", IF(ISNUMBER(_xlpm.x), IF(_xlpm.x>=30000, _xlpm.x, DATE(_xlpm.x,1,1)), DATE( LEFT(_xlpm.t,4), IF(LEN(_xlpm.t)>=7, MID(_xlpm.t,6,2), 1), IF(LEN(_xlpm.t)>=10, RIGHT(_xlpm.t,2), 1) ) ) ) ) -> 39083 | T52: =IF(R52="","",EDATE(S52,240)) -> 46388
A53: P100000120059 | B53: =INDEX('Plant data'!D:D,MATCH('Blast furnaces'!$A53,'Plant data'!$A:$A,0)) -> Sault Ste. Marie | C53: =INDEX('Plant data'!E:E,MATCH('Blast furnaces'!$A53,'Plant data'!$A:$A,0)) -> Ontario | D53: =INDEX('Plant data'!F:F,MATCH('Blast furnaces'!$A53,'Plant data'!$A:$A,0)) -> Canada | E53: U100000141356 | F53: BF 6 | G53: https://www.gem.wiki/Algoma_steel_plant | H53: mothballed | I53: unknown | J53: unknown | K53: 1953 | L53: 72 | M53: unknown | N53: 2008 | O53: unknown | P53: 1000 | Q53: 1270 | R53: 29526 | S53: =_xlfn.LET( _xlpm.x, R53, _xlpm.t, TEXT(R53,"@"), IF(R53="","", IF(ISNUMBER(_xlpm.x), IF(_xlpm.x>=30000, _xlpm.x, DATE(_xlpm.x,1,1)), DATE( LEFT(_xlpm.t,4), IF(LEN(_xlpm.t)>=7, MID(_xlpm.t,6,2), 1), IF(LEN(_xlpm.t)>=10, RIGHT(_xlpm.t,2), 1) ) ) ) ) -> #NUM!
A54: P100000120061 | B54: =INDEX('Plant data'!D:D,MATCH('Blast furnaces'!$A54,'Plant data'!$A:$A,0)) -> Nanticoke | C54: =INDEX('Plant data'!E:E,MATCH('Blast furnaces'!$A54,'Plant data'!$A:$A,0)) -> Ontario | D54: =INDEX('Plant data'!F:F,MATCH('Blast furnaces'!$A54,'Plant data'!$A:$A,0)) -> Canada | E54: U100000140051 | F54: BF 1 | G54: https://www.gem.wiki/Cleveland-Cliffs_Lake_Erie_steel_plant | H54: operating | I54: unknown | J54: unknown | K54: 1980 | L54: 45 | M54: unknown | N54: unknown | O54: unknown | P54: 2400 | Q54: 2418 | R54: 44119 | S54: =_xlfn.LET( _xlpm.x, R54, _xlpm.t, TEXT(R54,"@"), IF(R54="","", IF(ISNUMBER(_xlpm.x), IF(_xlpm.x>=30000, _xlpm.x, DATE(_xlpm.x,1,1)), DATE( LEFT(_xlpm.t,4), IF(LEN(_xlpm.t)>=7, MID(_xlpm.t,6,2), 1), IF(LEN(_xlpm.t)>=10, RIGHT(_xlpm.t,2), 1) ) ) ) ) -> 44119 | T54: =IF(R54="","",EDATE(S54,240)) -> 51424
A55: P100000120066 | B55: =INDEX('Plant data'!D:D,MATCH('Blast furnaces'!$A55,'Plant data'!$A:$A,0)) -> Talcahuano | C55: =INDEX('Plant data'!E:E,MATCH('Blast furnaces'!$A55,'Plant data'!$A:$A,0)) -> Concepción | D55: =INDEX('Plant data'!F:F,MATCH('Blast furnaces'!$A55,'Plant data'!$A:$A,0)) -> Chile | E55: U100000140052 | F55: BF 1 | G55: https://www.gem.wiki/CAP_Acero_Huachipato_steel_plant | H55: mothballed | I55: unknown | J55: unknown | K55: 1950 | L55: 75 | M55: unknown | N55: 45551 | O55: unknown | P55: 730 | Q55: 755 | S55: =_xlfn.LET( _xlpm.x, R55, _xlpm.t, TEXT(R55,"@"), IF(R55="","", IF(ISNUMBER(_xlpm.x), IF(_xlpm.x>=30000, _xlpm.x, DATE(_xlpm.x,1,1)), DATE( LEFT(_xlpm.t,4), IF(LEN(_xlpm.t)>=7, MID(_xlpm.t,6,2), 1), IF(LEN(_xlpm.t)>=10, RIGHT(_xlpm.t,2), 1) ) ) ) )
A56: P100000120066 | B56: =INDEX('Plant data'!D:D,MATCH('Blast furnaces'!$A56,'Plant data'!$A:$A,0)) -> Talcahuano | C56: =INDEX('Plant data'!E:E,MATCH('Blast furnaces'!$A56,'Plant data'!$A:$A,0)) -> Concepción | D56: =INDEX('Plant data'!F:F,MATCH('Blast furnaces'!$A56,'Plant data'!$A:$A,0)) -> Chile | E56: U100000140053 | F56: BF 2 | G56: https://www.gem.wiki/CAP_Acero_Huachipato_steel_plant | H56: mothballed | I56: unknown | J56: unknown | K56: 1966 | L56: 59 | M56: unknown | N56: 45551 | O56: unknown | P56: 752 | Q56: 881 | R56: 43556 | S56: =_xlfn.LET( _xlpm.x, R56, _xlpm.t, TEXT(R56,"@"), IF(R56="","", IF(ISNUMBER(_xlpm.x), IF(_xlpm.x>=30000, _xlpm.x, DATE(_xlpm.x,1,1)), DATE( LEFT(_xlpm.t,4), IF(LEN(_xlpm.t)>=7, MID(_xlpm.t,6,2), 1), IF(LEN(_xlpm.t)>=10, RIGHT(_xlpm.t,2), 1) ) ) ) ) -> 43556
A57: P100000120068 | B57: =INDEX('Plant data'!D:D,MATCH('Blast furnaces'!$A57,'Plant data'!$A:$A,0)) -> Wuhu | C57: =INDEX('Plant data'!E:E,MATCH('Blast furnaces'!$A57,'Plant data'!$A:$A,0)) -> Anhui | D57: =INDEX('Plant data'!F:F,MATCH('Blast furnaces'!$A57,'Plant data'!$A:$A,0)) -> China | E57: U100000140054 | F57: BF #1 | G57: https://www.gem.wiki/Wuhu_Xinxing_Ductile_Iron_Pipes_Co_Ltd | H57: operating | I57: unknown | J57: unknown | K57: 2016 | L57: 9 | M57: unknown | N57: unknown | O57: unknown | P57: 990 | Q57: 1280 | R57: 44948 | S57: =_xlfn.LET( _xlpm.x, R57, _xlpm.t, TEXT(R57,"@"), IF(R57="","", IF(ISNUMBER(_xlpm.x), IF(_xlpm.x>=30000, _xlpm.x, DATE(_xlpm.x,1,1)), DATE( LEFT(_xlpm.t,4), IF(LEN(_xlpm.t)>=7, MID(_xlpm.t,6,2), 1), IF(LEN(_xlpm.t)>=10, RIGHT(_xlpm.t,2), 1) ) ) ) ) -> 44948 | T57: =IF(R57="","",EDATE(S57,240)) -> 52253
A58: P100000120068 | B58: =INDEX('Plant data'!D:D,MATCH('Blast furnaces'!$A58,'Plant data'!$A:$A,0)) -> Wuhu | C58: =INDEX('Plant data'!E:E,MATCH('Blast furnaces'!$A58,'Plant data'!$A:$A,0)) -> Anhui | D58: =INDEX('Plant data'!F:F,MATCH('Blast furnaces'!$A58,'Plant data'!$A:$A,0)) -> China | E58: U100000140055 | F58: unknown BF (1) | G58: https://www.gem.wiki/Wuhu_Xinxing_Ductile_Iron_Pipes_Co_Ltd | H58: operating | I58: unknown | J58: unknown | K58: 2016 | L58: 9 | M58: unknown | N58: unknown | O58: unknown | P58: 990 | Q58: 1280 | S58: =_xlfn.LET( _xlpm.x, R58, _xlpm.t, TEXT(R58,"@"), IF(R58="","", IF(ISNUMBER(_xlpm.x), IF(_xlpm.x>=30000, _xlpm.x, DATE(_xlpm.x,1,1)), DATE( LEFT(_xlpm.t,4), IF(LEN(_xlpm.t)>=7, MID(_xlpm.t,6,2), 1), IF(LEN(_xlpm.t)>=10, RIGHT(_xlpm.t,2), 1) ) ) ) ) | T58: =IF(R58="","",EDATE(S58,240))
A59: P100000120069 | B59: =INDEX('Plant data'!D:D,MATCH('Blast furnaces'!$A59,'Plant data'!$A:$A,0)) -> Ma'anshan | C59: =INDEX('Plant data'!E:E,MATCH('Blast furnaces'!$A59,'Plant data'!$A:$A,0)) -> Anhui | D59: =INDEX('Plant data'!F:F,MATCH('Blast furnaces'!$A59,'Plant data'!$A:$A,0)) -> China | E59: U100000140056 | F59: BF 3 | G59: https://www.gem.wiki/Maanshan_Iron_and_Steel_Co_Ltd | H59: operating | I59: unknown | J59: unknown | K59: 2004 | L59: 21 | M59: unknown | N59: unknown | O59: unknown | P59: 1000 | Q59: 1000 | S59: =_xlfn.LET( _xlpm.x, R59, _xlpm.t, TEXT(R59,"@"), IF(R59="","", IF(ISNUMBER(_xlpm.x), IF(_xlpm.x>=30000, _xlpm.x, DATE(_xlpm.x,1,1)), DATE( LEFT(_xlpm.t,4), IF(LEN(_xlpm.t)>=7, MID(_xlpm.t,6,2), 1), IF(LEN(_xlpm.t)>=10, RIGHT(_xlpm.t,2), 1) ) ) ) ) | T59: =IF(R59="","",EDATE(S59,240))
A60: P100000120069 | B60: =INDEX('Plant data'!D:D,MATCH('Blast furnaces'!$A60,'Plant data'!$A:$A,0)) -> Ma'anshan | C60: =INDEX('Plant data'!E:E,MATCH('Blast furnaces'!$A60,'Plant data'!$A:$A,0)) -> Anhui | D60: =INDEX('Plant data'!F:F,MATCH('Blast furnaces'!$A60,'Plant data'!$A:$A,0)) -> China | E60: U100000140057 | F60: BF 1 | G60: https://www.gem.wiki/Maanshan_Iron_and_Steel_Co_Ltd | H60: operating | I60: unknown | J60: unknown | K60: 1994 | L60: 31 | M60: unknown | N60: unknown | O60: unknown | P60: 2200 | Q60: 2500 | R60: 43520 | S60: =_xlfn.LET( _xlpm.x, R60, _xlpm.t, TEXT(R60,"@"), IF(R60="","", IF(ISNUMBER(_xlpm.x), IF(_xlpm.x>=30000, _xlpm.x, DATE(_xlpm.x,1,1)), DATE( LEFT(_xlpm.t,4), IF(LEN(_xlpm.t)>=7, MID(_xlpm.t,6,2), 1), IF(LEN(_xlpm.t)>=10, RIGHT(_xlpm.t,2), 1) ) ) ) ) -> 43520 | T60: =IF(R60="","",EDATE(S60,240)) -> 50825
A61: P100000120069 | B61: =INDEX('Plant data'!D:D,MATCH('Blast furnaces'!$A61,'Plant data'!$A:$A,0)) -> Ma'anshan | C61: =INDEX('Plant data'!E:E,MATCH('Blast furnaces'!$A61,'Plant data'!$A:$A,0)) -> Anhui | D61: =INDEX('Plant data'!F:F,MATCH('Blast furnaces'!$A61,'Plant data'!$A:$A,0)) -> China | E61: U100000140058 | F61: BF 2 | G61: https://www.gem.wiki/Maanshan_Iron_and_Steel_Co_Ltd | H61: operating | I61: unknown | J61: unknown | K61: 2003 | L61: 22 | M61: unknown | N61: unknown | O61: unknown | P61: 2200 | Q61: 2500 | R61: 2017 | S61: =_xlfn.LET( _xlpm.x, R61, _xlpm.t, TEXT(R61,"@"), IF(R61="","", IF(ISNUMBER(_xlpm.x), IF(_xlpm.x>=30000, _xlpm.x, DATE(_xlpm.x,1,1)), DATE( LEFT(_xlpm.t,4), IF(LEN(_xlpm.t)>=7, MID(_xlpm.t,6,2), 1), IF(LEN(_xlpm.t)>=10, RIGHT(_xlpm.t,2), 1) ) ) ) ) -> 42736 | T61: =IF(R61="","",EDATE(S61,240)) -> 50041
A62: P100000120069 | B62: =INDEX('Plant data'!D:D,MATCH('Blast furnaces'!$A62,'Plant data'!$A:$A,0)) -> Ma'anshan | C62: =INDEX('Plant data'!E:E,MATCH('Blast furnaces'!$A62,'Plant data'!$A:$A,0)) -> Anhui | D62: =INDEX('Plant data'!F:F,MATCH('Blast furnaces'!$A62,'Plant data'!$A:$A,0)) -> China | E62: U100000140059 | F62: BF 4 | G62: https://www.gem.wiki/Maanshan_Iron_and_Steel_Co_Ltd | H62: operating | I62: unknown | J62: unknown | K62: 2016 | L62: 9 | M62: unknown | N62: unknown | O62: unknown | P62: 2700 | Q62: 3200 | S62: =_xlfn.LET( _xlpm.x, R62, _xlpm.t, TEXT(R62,"@"), IF(R62="","", IF(ISNUMBER(_xlpm.x), IF(_xlpm.x>=30000, _xlpm.x, DATE(_xlpm.x,1,1)), DATE( LEFT(_xlpm.t,4), IF(LEN(_xlpm.t)>=7, MID(_xlpm.t,6,2), 1), IF(LEN(_xlpm.t)>=10, RIGHT(_xlpm.t,2), 1) ) ) ) ) | T62: =IF(R62="","",EDATE(S62,240))
A63: P100000120069 | B63: =INDEX('Plant data'!D:D,MATCH('Blast furnaces'!$A63,'Plant data'!$A:$A,0)) -> Ma'anshan | C63: =INDEX('Plant data'!E:E,MATCH('Blast furnaces'!$A63,'Plant data'!$A:$A,0)) -> Anhui | D63: =INDEX('Plant data'!F:F,MATCH('Blast furnaces'!$A63,'Plant data'!$A:$A,0)) -> China | E63: U100000140060 | F63: BF A | G63: https://www.gem.wiki/Maanshan_Iron_and_Steel_Co_Ltd | H63: operating | I63: unknown | J63: unknown | K63: 2007 | L63: 18 | M63: unknown | N63: unknown | O63: unknown | P63: 3200 | Q63: 4000 | R63: 45269 | S63: =_xlfn.LET( _xlpm.x, R63, _xlpm.t, TEXT(R63,"@"), IF(R63="","", IF(ISNUMBER(_xlpm.x), IF(_xlpm.x>=30000, _xlpm.x, DATE(_xlpm.x,1,1)), DATE( LEFT(_xlpm.t,4), IF(LEN(_xlpm.t)>=7, MID(_xlpm.t,6,2), 1), IF(LEN(_xlpm.t)>=10, RIGHT(_xlpm.t,2), 1) ) ) ) ) -> 45269 | T63: =IF(R63="","",EDATE(S63,240)) -> 52574
A64: P100000120069 | B64: =INDEX('Plant data'!D:D,MATCH('Blast furnaces'!$A64,'Plant data'!$A:$A,0)) -> Ma'anshan | C64: =INDEX('Plant data'!E:E,MATCH('Blast furnaces'!$A64,'Plant data'!$A:$A,0)) -> Anhui | D64: =INDEX('Plant data'!F:F,MATCH('Blast furnaces'!$A64,'Plant data'!$A:$A,0)) -> China | E64: U100000140061 | F64: BF B | G64: https://www.gem.wiki/Maanshan_Iron_and_Steel_Co_Ltd | H64: operating | I64: unknown | J64: unknown | K64: 2007 | L64: 18 | M64: unknown | N64: unknown | O64: unknown | P64: 3200 | Q64: 4000 | R64: 44909 | S64: =_xlfn.LET( _xlpm.x, R64, _xlpm.t, TEXT(R64,"@"), IF(R64="","", IF(ISNUMBER(_xlpm.x), IF(_xlpm.x>=30000, _xlpm.x, DATE(_xlpm.x,1,1)), DATE( LEFT(_xlpm.t,4), IF(LEN(_xlpm.t)>=7, MID(_xlpm.t,6,2), 1), IF(LEN(_xlpm.t)>=10, RIGHT(_xlpm.t,2), 1) ) ) ) ) -> 44909 | T64: =IF(R64="","",EDATE(S64,240)) -> 52214
A65: P100000120070 | B65: =INDEX('Plant data'!D:D,MATCH('Blast furnaces'!$A65,'Plant data'!$A:$A,0)) -> unknown | C65: =INDEX('Plant data'!E:E,MATCH('Blast furnaces'!$A65,'Plant data'!$A:$A,0)) -> Anhui | D65: =INDEX('Plant data'!F:F,MATCH('Blast furnaces'!$A65,'Plant data'!$A:$A,0)) -> China | E65: U100000140064 | F65: BF #1 | G65: https://www.gem.wiki/Anhui_Changjiang_Steel_Co_Ltd | H65: operating | I65: unknown | J65: unknown | K65: unknown | L65: unknown | M65: unknown | N65: unknown | O65: unknown | P65: 1150 | Q65: 1250 | R65: 43593 | S65: =_xlfn.LET( _xlpm.x, R65, _xlpm.t, TEXT(R65,"@"), IF(R65="","", IF(ISNUMBER(_xlpm.x), IF(_xlpm.x>=30000, _xlpm.x, DATE(_xlpm.x,1,1)), DATE( LEFT(_xlpm.t,4), IF(LEN(_xlpm.t)>=7, MID(_xlpm.t,6,2), 1), IF(LEN(_xlpm.t)>=10, RIGHT(_xlpm.t,2), 1) ) ) ) ) -> 43593 | T65: =IF(R65="","",EDATE(S65,240)) -> 50898
A66: P100000120070 | B66: =INDEX('Plant data'!D:D,MATCH('Blast furnaces'!$A66,'Plant data'!$A:$A,0)) -> unknown | C66: =INDEX('Plant data'!E:E,MATCH('Blast furnaces'!$A66,'Plant data'!$A:$A,0)) -> Anhui | D66: =INDEX('Plant data'!F:F,MATCH('Blast furnaces'!$A66,'Plant data'!$A:$A,0)) -> China | E66: U100000140065 | F66: BF 2 | G66: https://www.gem.wiki/Anhui_Changjiang_Steel_Co_Ltd | H66: operating | I66: unknown | J66: unknown | K66: unknown | L66: unknown | M66: unknown | N66: unknown | O66: unknown | P66: 1040 | Q66: 1080 | R66: 44625 | S66: =_xlfn.LET( _xlpm.x, R66, _xlpm.t, TEXT(R66,"@"), IF(R66="","", IF(ISNUMBER(_xlpm.x), IF(_xlpm.x>=30000, _xlpm.x, DATE(_xlpm.x,1,1)), DATE( LEFT(_xlpm.t,4), IF(LEN(_xlpm.t)>=7, MID(_xlpm.t,6,2), 1), IF(LEN(_xlpm.t)>=10, RIGHT(_xlpm.t,2), 1) ) ) ) ) -> 44625 | T66: =IF(R66="","",EDATE(S66,240)) -> 51930
A67: P100000120070 | B67: =INDEX('Plant data'!D:D,MATCH('Blast furnaces'!$A67,'Plant data'!$A:$A,0)) -> unknown | C67: =INDEX('Plant data'!E:E,MATCH('Blast furnaces'!$A67,'Plant data'!$A:$A,0)) -> Anhui | D67: =INDEX('Plant data'!F:F,MATCH('Blast furnaces'!$A67,'Plant data'!$A:$A,0)) -> China | E67: U100000140066 | F67: BF 3 | G67: https://www.gem.wiki/Anhui_Changjiang_Steel_Co_Ltd | H67: operating | I67: unknown | J67: unknown | K67: 2013 | L67: 12 | M67: unknown | N67: unknown | O67: unknown | P67: 1150 | Q67: 1250 | R67: 44848 | S67: =_xlfn.LET( _xlpm.x, R67, _xlpm.t, TEXT(R67,"@"), IF(R67="","", IF(ISNUMBER(_xlpm.x), IF(_xlpm.x>=30000, _xlpm.x, DATE(_xlpm.x,1,1)), DATE( LEFT(_xlpm.t,4), IF(LEN(_xlpm.t)>=7, MID(_xlpm.t,6,2), 1), IF(LEN(_xlpm.t)>=10, RIGHT(_xlpm.t,2), 1) ) ) ) ) -> 44848 | T67: =IF(R67="","",EDATE(S67,240)) -> 52153
A68: P100000120071 | B68: =INDEX('Plant data'!D:D,MATCH('Blast furnaces'!$A68,'Plant data'!$A:$A,0)) -> Chizhou | C68: =INDEX('Plant data'!E:E,MATCH('Blast furnaces'!$A68,'Plant data'!$A:$A,0)) -> Anhui | D68: =INDEX('Plant data'!F:F,MATCH('Blast furnaces'!$A68,'Plant data'!$A:$A,0)) -> China | E68: U100000140067 | F68: BF 1 | G68: https://www.gem.wiki/Anhui_Guihang_Special_Steel_Co_Ltd | H68: operating | I68: unknown | J68: unknown | K68: 2011 | L68: 14 | M68: unknown | N68: unknown | O68: unknown | P68: 1040 | Q68: 1080 | S68: =_xlfn.LET( _xlpm.x, R68, _xlpm.t, TEXT(R68,"@"), IF(R68="","", IF(ISNUMBER(_xlpm.x), IF(_xlpm.x>=30000, _xlpm.x, DATE(_xlpm.x,1,1)), DATE( LEFT(_xlpm.t,4), IF(LEN(_xlpm.t)>=7, MID(_xlpm.t,6,2), 1), IF(LEN(_xlpm.t)>=10, RIGHT(_xlpm.t,2), 1) ) ) ) ) | T68: =IF(R68="","",EDATE(S68,240))
A69: P100000120071 | B69: =INDEX('Plant data'!D:D,MATCH('Blast furnaces'!$A69,'Plant data'!$A:$A,0)) -> Chizhou | C69: =INDEX('Plant data'!E:E,MATCH('Blast furnaces'!$A69,'Plant data'!$A:$A,0)) -> Anhui | D69: =INDEX('Plant data'!F:F,MATCH('Blast furnaces'!$A69,'Plant data'!$A:$A,0)) -> China | E69: U100000140068 | F69: BF 2 | G69: https://www.gem.wiki/Anhui_Guihang_Special_Steel_Co_Ltd | H69: operating | I69: unknown | J69: unknown | K69: 2012 | L69: 13 | M69: unknown | N69: unknown | O69: unknown | P69: 1040 | Q69: 1080 | S69: =_xlfn.LET( _xlpm.x, R69, _xlpm.t, TEXT(R69,"@"), IF(R69="","", IF(ISNUMBER(_xlpm.x), IF(_xlpm.x>=30000, _xlpm.x, DATE(_xlpm.x,1,1)), DATE( LEFT(_xlpm.t,4), IF(LEN(_xlpm.t)>=7, MID(_xlpm.t,6,2), 1), IF(LEN(_xlpm.t)>=10, RIGHT(_xlpm.t,2), 1) ) ) ) ) | T69: =IF(R69="","",EDATE(S69,240))
A70: P100000120072 | B70: =INDEX('Plant data'!D:D,MATCH('Blast furnaces'!$A70,'Plant data'!$A:$A,0)) -> Tongling | C70: =INDEX('Plant data'!E:E,MATCH('Blast furnaces'!$A70,'Plant data'!$A:$A,0)) -> Anhui | D70: =INDEX('Plant data'!F:F,MATCH('Blast furnaces'!$A70,'Plant data'!$A:$A,0)) -> China | E70: U100000140069 | F70: unknown BF (1) | G70: https://www.gem.wiki/Tongling_Fuxin_Iron_and_Steel_Co_Ltd | H70: operating | I70: unknown | J70: unknown | K70: 2021 | L70: 4 | M70: unknown | N70: unknown | O70: unknown | P70: 1180 | Q70: 1280 | R70: 44768 | S70: =_xlfn.LET( _xlpm.x, R70, _xlpm.t, TEXT(R70,"@"), IF(R70="","", IF(ISNUMBER(_xlpm.x), IF(_xlpm.x>=30000, _xlpm.x, DATE(_xlpm.x,1,1)), DATE( LEFT(_xlpm.t,4), IF(LEN(_xlpm.t)>=7, MID(_xlpm.t,6,2), 1), IF(LEN(_xlpm.t)>=10, RIGHT(_xlpm.t,2), 1) ) ) ) ) -> 44768 | T70: =IF(R70="","",EDATE(S70,240)) -> 52073
A71: P100000120073 | B71: =INDEX('Plant data'!D:D,MATCH('Blast furnaces'!$A71,'Plant data'!$A:$A,0)) -> Wuhu | C71: =INDEX('Plant data'!E:E,MATCH('Blast furnaces'!$A71,'Plant data'!$A:$A,0)) -> Anhui | D71: =INDEX('Plant data'!F:F,MATCH('Blast furnaces'!$A71,'Plant data'!$A:$A,0)) -> China | E71: U100000140070 | F71: unknown BF (1) | G71: https://www.gem.wiki/Wuhu_Fuxin_Iron_and_Steel_Co_Ltd | H71: operating | I71: unknown | J71: 2008 | K71: 2010 | L71: 15 | M71: unknown | N71: unknown | O71: unknown | P71: 730 | Q71: 680 | R71: 2022 | S71: =_xlfn.LET( _xlpm.x, R71, _xlpm.t, TEXT(R71,"@"), IF(R71="","", IF(ISNUMBER(_xlpm.x), IF(_xlpm.x>=30000, _xlpm.x, DATE(_xlpm.x,1,1)), DATE( LEFT(_xlpm.t,4), IF(LEN(_xlpm.t)>=7, MID(_xlpm.t,6,2), 1), IF(LEN(_xlpm.t)>=10, RIGHT(_xlpm.t,2), 1) ) ) ) ) -> 44562 | T71: =IF(R71="","",EDATE(S71,240)) -> 51867
A72: P100000120073 | B72: =INDEX('Plant data'!D:D,MATCH('Blast furnaces'!$A72,'Plant data'!$A:$A,0)) -> Wuhu | C72: =INDEX('Plant data'!E:E,MATCH('Blast furnaces'!$A72,'Plant data'!$A:$A,0)) -> Anhui | D72: =INDEX('Plant data'!F:F,MATCH('Blast furnaces'!$A72,'Plant data'!$A:$A,0)) -> China | E72: U100000140071 | F72: unknown BF (2) | G72: https://www.gem.wiki/Wuhu_Fuxin_Iron_and_Steel_Co_Ltd | H72: operating | I72: unknown | J72: 40603 | K72: 2012 | L72: 13 | M72: unknown | N72: unknown | O72: unknown | P72: 1040 | Q72: 1080 | S72: =_xlfn.LET( _xlpm.x, R72, _xlpm.t, TEXT(R72,"@"), IF(R72="","", IF(ISNUMBER(_xlpm.x), IF(_xlpm.x>=30000, _xlpm.x, DATE(_xlpm.x,1,1)), DATE( LEFT(_xlpm.t,4), IF(LEN(_xlpm.t)>=7, MID(_xlpm.t,6,2), 1), IF(LEN(_xlpm.t)>=10, RIGHT(_xlpm.t,2), 1) ) ) ) ) | T72: =IF(R72="","",EDATE(S72,240))
A73: P100000120074 | B73: =INDEX('Plant data'!D:D,MATCH('Blast furnaces'!$A73,'Plant data'!$A:$A,0)) -> Changshou | C73: =INDEX('Plant data'!E:E,MATCH('Blast furnaces'!$A73,'Plant data'!$A:$A,0)) -> Chongqing | D73: =INDEX('Plant data'!F:F,MATCH('Blast furnaces'!$A73,'Plant data'!$A:$A,0)) -> China | E73: U100000140072 | F73: BF 4 | G73: https://www.gem.wiki/Chongqing_Iron_and_Steel_Co_Ltd | H73: operating | I73: unknown | J73: unknown | K73: unknown | L73: unknown | M73: unknown | N73: unknown | O73: unknown | P73: 2070 | Q73: 1750 | R73: 44393 | S73: =_xlfn.LET( _xlpm.x, R73, _xlpm.t, TEXT(R73,"@"), IF(R73="","", IF(ISNUMBER(_xlpm.x), IF(_xlpm.x>=30000, _xlpm.x, DATE(_xlpm.x,1,1)), DATE( LEFT(_xlpm.t,4), IF(LEN(_xlpm.t)>=7, MID(_xlpm.t,6,2), 1), IF(LEN(_xlpm.t)>=10, RIGHT(_xlpm.t,2), 1) ) ) ) ) -> 44393 | T73: =IF(R73="","",EDATE(S73,240)) -> 51698
A74: P100000120074 | B74: =INDEX('Plant data'!D:D,MATCH('Blast furnaces'!$A74,'Plant data'!$A:$A,0)) -> Changshou | C74: =INDEX('Plant data'!E:E,MATCH('Blast furnaces'!$A74,'Plant data'!$A:$A,0)) -> Chongqing | D74: =INDEX('Plant data'!F:F,MATCH('Blast furnaces'!$A74,'Plant data'!$A:$A,0)) -> China | E74: U100000140073 | F74: BF 1 | G74: https://www.gem.wiki/Chongqing_Iron_and_Steel_Co_Ltd | H74: operating | I74: unknown | J74: unknown | K74: 2010 | L74: 15 | M74: unknown | N74: unknown | O74: unknown | P74: 2555 | Q74: 2500 | R74: 43891 | S74: =_xlfn.LET( _xlpm.x, R74, _xlpm.t, TEXT(R74,"@"), IF(R74="","", IF(ISNUMBER(_xlpm.x), IF(_xlpm.x>=30000, _xlpm.x, DATE(_xlpm.x,1,1)), DATE( LEFT(_xlpm.t,4), IF(LEN(_xlpm.t)>=7, MID(_xlpm.t,6,2), 1), IF(LEN(_xlpm.t)>=10, RIGHT(_xlpm.t,2), 1) ) ) ) ) -> 43891 | T74: =IF(R74="","",EDATE(S74,240)) -> 51196
A75: P100000120074 | B75: =INDEX('Plant data'!D:D,MATCH('Blast furnaces'!$A75,'Plant data'!$A:$A,0)) -> Changshou | C75: =INDEX('Plant data'!E:E,MATCH('Blast furnaces'!$A75,'Plant data'!$A:$A,0)) -> Chongqing | D75: =INDEX('Plant data'!F:F,MATCH('Blast furnaces'!$A75,'Plant data'!$A:$A,0)) -> China | E75: U100000140074 | F75: BF 2 | G75: https://www.gem.wiki/Chongqing_Iron_and_Steel_Co_Ltd | H75: operating | I75: unknown | J75: unknown | K75: 2011 | L75: 14 | M75: unknown | N75: unknown | O75: unknown | P75: 2555 | Q75: 2500 | R75: 44165 | S75: =_xlfn.LET( _xlpm.x, R75, _xlpm.t, TEXT(R75,"@"), IF(R75="","", IF(ISNUMBER(_xlpm.x), IF(_xlpm.x>=30000, _xlpm.x, DATE(_xlpm.x,1,1)), DATE( LEFT(_xlpm.t,4), IF(LEN(_xlpm.t)>=7, MID(_xlpm.t,6,2), 1), IF(LEN(_xlpm.t)>=10, RIGHT(_xlpm.t,2), 1) ) ) ) ) -> 44165 | T75: =IF(R75="","",EDATE(S75,240)) -> 51470
A76: P100000120074 | B76: =INDEX('Plant data'!D:D,MATCH('Blast furnaces'!$A76,'Plant data'!$A:$A,0)) -> Changshou | C76: =INDEX('Plant data'!E:E,MATCH('Blast furnaces'!$A76,'Plant data'!$A:$A,0)) -> Chongqing | D76: =INDEX('Plant data'!F:F,MATCH('Blast furnaces'!$A76,'Plant data'!$A:$A,0)) -> China | E76: U100000140075 | F76: BF 3 | G76: https://www.gem.wiki/Chongqing_Iron_and_Steel_Co_Ltd | H76: operating | I76: unknown | J76: unknown | K76: 2011 | L76: 14 | M76: unknown | N76: unknown | O76: unknown | P76: 2555 | Q76: 2500 | R76: 44230 | S76: =_xlfn.LET( _xlpm.x, R76, _xlpm.t, TEXT(R76,"@"), IF(R76="","", IF(ISNUMBER(_xlpm.x), IF(_xlpm.x>=30000, _xlpm.x, DATE(_xlpm.x,1,1)), DATE( LEFT(_xlpm.t,4), IF(LEN(_xlpm.t)>=7, MID(_xlpm.t,6,2), 1), IF(LEN(_xlpm.t)>=10, RIGHT(_xlpm.t,2), 1) ) ) ) ) -> 44230 | T76: =IF(R76="","",EDATE(S76,240)) -> 51535
A77: P100000120075 | B77: =INDEX('Plant data'!D:D,MATCH('Blast furnaces'!$A77,'Plant data'!$A:$A,0)) -> Leshan | C77: =INDEX('Plant data'!E:E,MATCH('Blast furnaces'!$A77,'Plant data'!$A:$A,0)) -> Chongqing | D77: =INDEX('Plant data'!F:F,MATCH('Blast furnaces'!$A77,'Plant data'!$A:$A,0)) -> China | E77: U100000140076 | F77: BF 1 | G77: https://www.gem.wiki/Sichuan_Desheng_Group_Vanadium_and_Titanium_Co_Ltd | H77: retired | I77: unknown | J77: unknown | K77: unknown | L77: unknown | M77: 43586 | N77: 44501 | O77: 44904 | P77: 500 | Q77: 420 | R77: 44515 | S77: =_xlfn.LET( _xlpm.x, R77, _xlpm.t, TEXT(R77,"@"), IF(R77="","", IF(ISNUMBER(_xlpm.x), IF(_xlpm.x>=30000, _xlpm.x, DATE(_xlpm.x,1,1)), DATE( LEFT(_xlpm.t,4), IF(LEN(_xlpm.t)>=7, MID(_xlpm.t,6,2), 1), IF(LEN(_xlpm.t)>=10, RIGHT(_xlpm.t,2), 1) ) ) ) ) -> 44515
A78: P100000120075 | B78: =INDEX('Plant data'!D:D,MATCH('Blast furnaces'!$A78,'Plant data'!$A:$A,0)) -> Leshan | C78: =INDEX('Plant data'!E:E,MATCH('Blast furnaces'!$A78,'Plant data'!$A:$A,0)) -> Chongqing | D78: =INDEX('Plant data'!F:F,MATCH('Blast furnaces'!$A78,'Plant data'!$A:$A,0)) -> China | E78: U100000140077 | F78: BF 2 | G78: https://www.gem.wiki/Sichuan_Desheng_Group_Vanadium_and_Titanium_Co_Ltd | H78: retired | I78: unknown | J78: unknown | K78: unknown | L78: unknown | M78: 43586 | N78: 44501 | O78: 44904 | P78: 500 | Q78: 420 | R78: 44560 | S78: =_xlfn.LET( _xlpm.x, R78, _xlpm.t, TEXT(R78,"@"), IF(R78="","", IF(ISNUMBER(_xlpm.x), IF(_xlpm.x>=30000, _xlpm.x, DATE(_xlpm.x,1,1)), DATE( LEFT(_xlpm.t,4), IF(LEN(_xlpm.t)>=7, MID(_xlpm.t,6,2), 1), IF(LEN(_xlpm.t)>=10, RIGHT(_xlpm.t,2), 1) ) ) ) ) -> 44560
A79: P100000120075 | B79: =INDEX('Plant data'!D:D,MATCH('Blast furnaces'!$A79,'Plant data'!$A:$A,0)) -> Leshan | C79: =INDEX('Plant data'!E:E,MATCH('Blast furnaces'!$A79,'Plant data'!$A:$A,0)) -> Chongqing | D79: =INDEX('Plant data'!F:F,MATCH('Blast furnaces'!$A79,'Plant data'!$A:$A,0)) -> China | E79: U100000140078 | F79: BF 3 | G79: https://www.gem.wiki/Sichuan_Desheng_Group_Vanadium_and_Titanium_Co_Ltd | H79: operating | I79: unknown | J79: unknown | K79: 2010 | L79: 15 | M79: unknown | N79: unknown | O79: unknown | P79: 1100 | Q79: 1250 | R79: 44531 | S79: =_xlfn.LET( _xlpm.x, R79, _xlpm.t, TEXT(R79,"@"), IF(R79="","", IF(ISNUMBER(_xlpm.x), IF(_xlpm.x>=30000, _xlpm.x, DATE(_xlpm.x,1,1)), DATE( LEFT(_xlpm.t,4), IF(LEN(_xlpm.t)>=7, MID(_xlpm.t,6,2), 1), IF(LEN(_xlpm.t)>=10, RIGHT(_xlpm.t,2), 1) ) ) ) ) -> 44531 | T79: =IF(R79="","",EDATE(S79,240)) -> 51836
A80: P100000120075 | B80: =INDEX('Plant data'!D:D,MATCH('Blast furnaces'!$A80,'Plant data'!$A:$A,0)) -> Leshan | C80: =INDEX('Plant data'!E:E,MATCH('Blast furnaces'!$A80,'Plant data'!$A:$A,0)) -> Chongqing | D80: =INDEX('Plant data'!F:F,MATCH('Blast furnaces'!$A80,'Plant data'!$A:$A,0)) -> China | E80: U100000140079 | F80: BF 4 | G80: https://www.gem.wiki/Sichuan_Desheng_Group_Vanadium_and_Titanium_Co_Ltd | H80: operating | I80: 43586 | J80: 44501 | K80: 2022 | L80: 3 | M80: unknown | N80: unknown | O80: unknown | P80: 1150 | Q80: 1250 | S80: =_xlfn.LET( _xlpm.x, R80, _xlpm.t, TEXT(R80,"@"), IF(R80="","", IF(ISNUMBER(_xlpm.x), IF(_xlpm.x>=30000, _xlpm.x, DATE(_xlpm.x,1,1)), DATE( LEFT(_xlpm.t,4), IF(LEN(_xlpm.t)>=7, MID(_xlpm.t,6,2), 1), IF(LEN(_xlpm.t)>=10, RIGHT(_xlpm.t,2), 1) ) ) ) ) | T80: =IF(R80="","",EDATE(S80,240))
A81: P100000120076 | B81: =INDEX('Plant data'!D:D,MATCH('Blast furnaces'!$A81,'Plant data'!$A:$A,0)) -> Sanming | C81: =INDEX('Plant data'!E:E,MATCH('Blast furnaces'!$A81,'Plant data'!$A:$A,0)) -> Fujian | D81: =INDEX('Plant data'!F:F,MATCH('Blast furnaces'!$A81,'Plant data'!$A:$A,0)) -> China | E81: U100000140080 | F81: BF 4 | G81: https://www.gem.wiki/Sansteel_Minguang_Co_Ltd_Fujian_plant | H81: retired | I81: unknown | J81: unknown | K81: 2004 | L81: 19.75 | M81: 44470 | N81: 44743 | O81: 45199 | P81: 1301 | Q81: 1050 | R81: 41141 | S81: =_xlfn.LET( _xlpm.x, R81, _xlpm.t, TEXT(R81,"@"), IF(R81="","", IF(ISNUMBER(_xlpm.x), IF(_xlpm.x>=30000, _xlpm.x, DATE(_xlpm.x,1,1)), DATE( LEFT(_xlpm.t,4), IF(LEN(_xlpm.t)>=7, MID(_xlpm.t,6,2), 1), IF(LEN(_xlpm.t)>=10, RIGHT(_xlpm.t,2), 1) ) ) ) ) -> 41141
A82: P100000120076 | B82: =INDEX('Plant data'!D:D,MATCH('Blast furnaces'!$A82,'Plant data'!$A:$A,0)) -> Sanming | C82: =INDEX('Plant data'!E:E,MATCH('Blast furnaces'!$A82,'Plant data'!$A:$A,0)) -> Fujian | D82: =INDEX('Plant data'!F:F,MATCH('Blast furnaces'!$A82,'Plant data'!$A:$A,0)) -> China | E82: U100000140081 | F82: BF 5 | G82: https://www.gem.wiki/Sansteel_Minguang_Co_Ltd_Fujian_plant | H82: retired | I82: unknown | J82: unknown | K82: 2007 | L82: 16.74 | M82: 44470 | N82: 44743 | O82: 45199 | P82: 1081 | Q82: 1250 | R82: 43423 | S82: =_xlfn.LET( _xlpm.x, R82, _xlpm.t, TEXT(R82,"@"), IF(R82="","", IF(ISNUMBER(_xlpm.x), IF(_xlpm.x>=30000, _xlpm.x, DATE(_xlpm.x,1,1)), DATE( LEFT(_xlpm.t,4), IF(LEN(_xlpm.t)>=7, MID(_xlpm.t,6,2), 1), IF(LEN(_xlpm.t)>=10, RIGHT(_xlpm.t,2), 1) ) ) ) ) -> 43423
A83: P100000120076 | B83: =INDEX('Plant data'!D:D,MATCH('Blast furnaces'!$A83,'Plant data'!$A:$A,0)) -> Sanming | C83: =INDEX('Plant data'!E:E,MATCH('Blast furnaces'!$A83,'Plant data'!$A:$A,0)) -> Fujian | D83: =INDEX('Plant data'!F:F,MATCH('Blast furnaces'!$A83,'Plant data'!$A:$A,0)) -> China | E83: U100000140082 | F83: BF 6 | G83: https://www.gem.wiki/Sansteel_Minguang_Co_Ltd_Fujian_plant | H83: operating | I83: unknown | J83: unknown | K83: 2012 | L83: 13 | M83: unknown | N83: unknown | O83: unknown | P83: 1535 | Q83: 1800 | R83: 44198 | S83: =_xlfn.LET( _xlpm.x, R83, _xlpm.t, TEXT(R83,"@"), IF(R83="","", IF(ISNUMBER(_xlpm.x), IF(_xlpm.x>=30000, _xlpm.x, DATE(_xlpm.x,1,1)), DATE( LEFT(_xlpm.t,4), IF(LEN(_xlpm.t)>=7, MID(_xlpm.t,6,2), 1), IF(LEN(_xlpm.t)>=10, RIGHT(_xlpm.t,2), 1) ) ) ) ) -> 44198 | T83: =IF(R83="","",EDATE(S83,240)) -> 51503
A84: P100000120076 | B84: =INDEX('Plant data'!D:D,MATCH('Blast furnaces'!$A84,'Plant data'!$A:$A,0)) -> Sanming | C84: =INDEX('Plant data'!E:E,MATCH('Blast furnaces'!$A84,'Plant data'!$A:$A,0)) -> Fujian | D84: =INDEX('Plant data'!F:F,MATCH('Blast furnaces'!$A84,'Plant data'!$A:$A,0)) -> China | E84: U100000140083 | F84: BF New#1 | G84: https://www.gem.wiki/Sansteel_Minguang_Co_Ltd_Fujian_plant | H84: operating | I84: 44470 | J84: 44743 | K84: 2023 | L84: 2 | M84: unknown | N84: unknown | O84: unknown | P84: 1659 | Q84: 1950 | S84: =_xlfn.LET( _xlpm.x, R84, _xlpm.t, TEXT(R84,"@"), IF(R84="","", IF(ISNUMBER(_xlpm.x), IF(_xlpm.x>=30000, _xlpm.x, DATE(_xlpm.x,1,1)), DATE( LEFT(_xlpm.t,4), IF(LEN(_xlpm.t)>=7, MID(_xlpm.t,6,2), 1), IF(LEN(_xlpm.t)>=10, RIGHT(_xlpm.t,2), 1) ) ) ) ) | T84: =IF(R84="","",EDATE(S84,240))
A85: P100000120076 | B85: =INDEX('Plant data'!D:D,MATCH('Blast furnaces'!$A85,'Plant data'!$A:$A,0)) -> Sanming | C85: =INDEX('Plant data'!E:E,MATCH('Blast furnaces'!$A85,'Plant data'!$A:$A,0)) -> Fujian | D85: =INDEX('Plant data'!F:F,MATCH('Blast furnaces'!$A85,'Plant data'!$A:$A,0)) -> China | E85: U100000140084 | F85: BF New#2 | G85: https://www.gem.wiki/Sansteel_Minguang_Co_Ltd_Fujian_plant | H85: operating | I85: 44470 | J85: 2024 | K85: 2024 | L85: 1 | M85: unknown | N85: unknown | O85: unknown | P85: 1659 | Q85: 1950 | S85: =_xlfn.LET( _xlpm.x, R85, _xlpm.t, TEXT(R85,"@"), IF(R85="","", IF(ISNUMBER(_xlpm.x), IF(_xlpm.x>=30000, _xlpm.x, DATE(_xlpm.x,1,1)), DATE( LEFT(_xlpm.t,4), IF(LEN(_xlpm.t)>=7, MID(_xlpm.t,6,2), 1), IF(LEN(_xlpm.t)>=10, RIGHT(_xlpm.t,2), 1) ) ) ) ) | T85: =IF(R85="","",EDATE(S85,240))
A86: P100000120076 | B86: =INDEX('Plant data'!D:D,MATCH('Blast furnaces'!$A86,'Plant data'!$A:$A,0)) -> Sanming | C86: =INDEX('Plant data'!E:E,MATCH('Blast furnaces'!$A86,'Plant data'!$A:$A,0)) -> Fujian | D86: =INDEX('Plant data'!F:F,MATCH('Blast furnaces'!$A86,'Plant data'!$A:$A,0)) -> China | E86: U100000141421 | F86: BF 1 | G86: https://www.gem.wiki/Sansteel_Minguang_Co_Ltd_Fujian_plant | H86: retired | I86: unknown | J86: unknown | K86: unknown | L86: unknown | M86: 44470 | N86: 44743 | O86: 44378 | P86: 394 | Q86: 420 | S86: =_xlfn.LET( _xlpm.x, R86, _xlpm.t, TEXT(R86,"@"), IF(R86="","", IF(ISNUMBER(_xlpm.x), IF(_xlpm.x>=30000, _xlpm.x, DATE(_xlpm.x,1,1)), DATE( LEFT(_xlpm.t,4), IF(LEN(_xlpm.t)>=7, MID(_xlpm.t,6,2), 1), IF(LEN(_xlpm.t)>=10, RIGHT(_xlpm.t,2), 1) ) ) ) )
A87: P100000120076 | B87: =INDEX('Plant data'!D:D,MATCH('Blast furnaces'!$A87,'Plant data'!$A:$A,0)) -> Sanming | C87: =INDEX('Plant data'!E:E,MATCH('Blast furnaces'!$A87,'Plant data'!$A:$A,0)) -> Fujian | D87: =INDEX('Plant data'!F:F,MATCH('Blast furnaces'!$A87,'Plant data'!$A:$A,0)) -> China | E87: U100000141422 | F87: BF 2 | G87: https://www.gem.wiki/Sansteel_Minguang_Co_Ltd_Fujian_plant | H87: retired | I87: unknown | J87: unknown | K87: unknown | L87: unknown | M87: 44470 | N87: 44743 | O87: 44378 | P87: 394 | Q87: 420 | S87: =_xlfn.LET( _xlpm.x, R87, _xlpm.t, TEXT(R87,"@"), IF(R87="","", IF(ISNUMBER(_xlpm.x), IF(_xlpm.x>=30000, _xlpm.x, DATE(_xlpm.x,1,1)), DATE( LEFT(_xlpm.t,4), IF(LEN(_xlpm.t)>=7, MID(_xlpm.t,6,2), 1), IF(LEN(_xlpm.t)>=10, RIGHT(_xlpm.t,2), 1) ) ) ) )
A88: P100000120076 | B88: =INDEX('Plant data'!D:D,MATCH('Blast furnaces'!$A88,'Plant data'!$A:$A,0)) -> Sanming | C88: =INDEX('Plant data'!E:E,MATCH('Blast furnaces'!$A88,'Plant data'!$A:$A,0)) -> Fujian | D88: =INDEX('Plant data'!F:F,MATCH('Blast furnaces'!$A88,'Plant data'!$A:$A,0)) -> China | E88: U100000141423 | F88: BF 3 | G88: https://www.gem.wiki/Sansteel_Minguang_Co_Ltd_Fujian_plant | H88: retired | I88: unknown | J88: unknown | K88: unknown | L88: unknown | M88: 44470 | N88: 44743 | O88: 44378 | P88: 394 | Q88: 420 | S88: =_xlfn.LET( _xlpm.x, R88, _xlpm.t, TEXT(R88,"@"), IF(R88="","", IF(ISNUMBER(_xlpm.x), IF(_xlpm.x>=30000, _xlpm.x, DATE(_xlpm.x,1,1)), DATE( LEFT(_xlpm.t,4), IF(LEN(_xlpm.t)>=7, MID(_xlpm.t,6,2), 1), IF(LEN(_xlpm.t)>=10, RIGHT(_xlpm.t,2), 1) ) ) ) )
A89: P100000120077 | B89: =INDEX('Plant data'!D:D,MATCH('Blast furnaces'!$A89,'Plant data'!$A:$A,0)) -> Quanzhou | C89: =INDEX('Plant data'!E:E,MATCH('Blast furnaces'!$A89,'Plant data'!$A:$A,0)) -> Fujian | D89: =INDEX('Plant data'!F:F,MATCH('Blast furnaces'!$A89,'Plant data'!$A:$A,0)) -> China | E89: U100000140085 | F89: BF 1 | G89: https://www.gem.wiki/Fujian_Quanzhou_Minguang_Iron_and_Steel_Co_Ltd | H89: retired | I89: unknown | J89: unknown | K89: unknown | L89: unknown | M89: 44925 | N89: unknown | O89: 2024 | P89: 534 | Q89: 550 | S89: =_xlfn.LET( _xlpm.x, R89, _xlpm.t, TEXT(R89,"@"), IF(R89="","", IF(ISNUMBER(_xlpm.x), IF(_xlpm.x>=30000, _xlpm.x, DATE(_xlpm.x,1,1)), DATE( LEFT(_xlpm.t,4), IF(LEN(_xlpm.t)>=7, MID(_xlpm.t,6,2), 1), IF(LEN(_xlpm.t)>=10, RIGHT(_xlpm.t,2), 1) ) ) ) )
A90: P100000120077 | B90: =INDEX('Plant data'!D:D,MATCH('Blast furnaces'!$A90,'Plant data'!$A:$A,0)) -> Quanzhou | C90: =INDEX('Plant data'!E:E,MATCH('Blast furnaces'!$A90,'Plant data'!$A:$A,0)) -> Fujian | D90: =INDEX('Plant data'!F:F,MATCH('Blast furnaces'!$A90,'Plant data'!$A:$A,0)) -> China | E90: U100000140086 | F90: BF 2 | G90: https://www.gem.wiki/Fujian_Quanzhou_Minguang_Iron_and_Steel_Co_Ltd | H90: retired | I90: unknown | J90: unknown | K90: unknown | L90: unknown | M90: 44925 | N90: unknown | O90: 2024 | P90: 534 | Q90: 550 | S90: =_xlfn.LET( _xlpm.x, R90, _xlpm.t, TEXT(R90,"@"), IF(R90="","", IF(ISNUMBER(_xlpm.x), IF(_xlpm.x>=30000, _xlpm.x, DATE(_xlpm.x,1,1)), DATE( LEFT(_xlpm.t,4), IF(LEN(_xlpm.t)>=7, MID(_xlpm.t,6,2), 1), IF(LEN(_xlpm.t)>=10, RIGHT(_xlpm.t,2), 1) ) ) ) )
A91: P100000120077 | B91: =INDEX('Plant data'!D:D,MATCH('Blast furnaces'!$A91,'Plant data'!$A:$A,0)) -> Quanzhou | C91: =INDEX('Plant data'!E:E,MATCH('Blast furnaces'!$A91,'Plant data'!$A:$A,0)) -> Fujian | D91: =INDEX('Plant data'!F:F,MATCH('Blast furnaces'!$A91,'Plant data'!$A:$A,0)) -> China | E91: U100000140087 | F91: BF 3 | G91: https://www.gem.wiki/Fujian_Quanzhou_Minguang_Iron_and_Steel_Co_Ltd | H91: retired | I91: unknown | J91: unknown | K91: 2011 | L91: 13 | M91: 44925 | N91: unknown | O91: 2024 | P91: 1213 | Q91: 1000 | S91: =_xlfn.LET( _xlpm.x, R91, _xlpm.t, TEXT(R91,"@"), IF(R91="","", IF(ISNUMBER(_xlpm.x), IF(_xlpm.x>=30000, _xlpm.x, DATE(_xlpm.x,1,1)), DATE( LEFT(_xlpm.t,4), IF(LEN(_xlpm.t)>=7, MID(_xlpm.t,6,2), 1), IF(LEN(_xlpm.t)>=10, RIGHT(_xlpm.t,2), 1) ) ) ) )
A92: P100000120077 | B92: =INDEX('Plant data'!D:D,MATCH('Blast furnaces'!$A92,'Plant data'!$A:$A,0)) -> Quanzhou | C92: =INDEX('Plant data'!E:E,MATCH('Blast furnaces'!$A92,'Plant data'!$A:$A,0)) -> Fujian | D92: =INDEX('Plant data'!F:F,MATCH('Blast furnaces'!$A92,'Plant data'!$A:$A,0)) -> China | E92: U100000141442 | F92: unknown BF (1) | G92: https://www.gem.wiki/Fujian_Quanzhou_Minguang_Iron_and_Steel_Co_Ltd | H92: operating | I92: 44896 | J92: 2023 | K92: 2024 | L92: 1 | M92: unknown | N92: unknown | O92: unknown | P92: 1130 | Q92: 1200 | S92: =_xlfn.LET( _xlpm.x, R92, _xlpm.t, TEXT(R92,"@"), IF(R92="","", IF(ISNUMBER(_xlpm.x), IF(_xlpm.x>=30000, _xlpm.x, DATE(_xlpm.x,1,1)), DATE( LEFT(_xlpm.t,4), IF(LEN(_xlpm.t)>=7, MID(_xlpm.t,6,2), 1), IF(LEN(_xlpm.t)>=10, RIGHT(_xlpm.t,2), 1) ) ) ) ) | T92: =IF(R92="","",EDATE(S92,240))
A93: P100000120077 | B93: =INDEX('Plant data'!D:D,MATCH('Blast furnaces'!$A93,'Plant data'!$A:$A,0)) -> Quanzhou | C93: =INDEX('Plant data'!E:E,MATCH('Blast furnaces'!$A93,'Plant data'!$A:$A,0)) -> Fujian | D93: =INDEX('Plant data'!F:F,MATCH('Blast furnaces'!$A93,'Plant data'!$A:$A,0)) -> China | E93: U100000141443 | F93: unknown BF (2) | G93: https://www.gem.wiki/Fujian_Quanzhou_Minguang_Iron_and_Steel_Co_Ltd | H93: operating | I93: 44896 | J93: 2023 | K93: 2024 | L93: 1 | M93: unknown | N93: unknown | O93: unknown | P93: 1150 | Q93: 1250 | S93: =_xlfn.LET( _xlpm.x, R93, _xlpm.t, TEXT(R93,"@"), IF(R93="","", IF(ISNUMBER(_xlpm.x), IF(_xlpm.x>=30000, _xlpm.x, DATE(_xlpm.x,1,1)), DATE( LEFT(_xlpm.t,4), IF(LEN(_xlpm.t)>=7, MID(_xlpm.t,6,2), 1), IF(LEN(_xlpm.t)>=10, RIGHT(_xlpm.t,2), 1) ) ) ) ) | T93: =IF(R93="","",EDATE(S93,240))
A94: P100000120078 | B94: =INDEX('Plant data'!D:D,MATCH('Blast furnaces'!$A94,'Plant data'!$A:$A,0)) -> Zhangzhou | C94: =INDEX('Plant data'!E:E,MATCH('Blast furnaces'!$A94,'Plant data'!$A:$A,0)) -> Fujian | D94: =INDEX('Plant data'!F:F,MATCH('Blast furnaces'!$A94,'Plant data'!$A:$A,0)) -> China | E94: U100000140088 | F94: BF New 1 | G94: https://www.gem.wiki/Fujian_Sanbao_Steel_Co_Ltd | H94: operating | I94: unknown | J94: unknown | K94: 2020 | L94: 5 | M94: unknown | N94: unknown | O94: unknown | P94: 1460 | Q94: 1700 | S94: =_xlfn.LET( _xlpm.x, R94, _xlpm.t, TEXT(R94,"@"), IF(R94="","", IF(ISNUMBER(_xlpm.x), IF(_xlpm.x>=30000, _xlpm.x, DATE(_xlpm.x,1,1)), DATE( LEFT(_xlpm.t,4), IF(LEN(_xlpm.t)>=7, MID(_xlpm.t,6,2), 1), IF(LEN(_xlpm.t)>=10, RIGHT(_xlpm.t,2), 1) ) ) ) ) | T94: =IF(R94="","",EDATE(S94,240))
A95: P100000120078 | B95: =INDEX('Plant data'!D:D,MATCH('Blast furnaces'!$A95,'Plant data'!$A:$A,0)) -> Zhangzhou | C95: =INDEX('Plant data'!E:E,MATCH('Blast furnaces'!$A95,'Plant data'!$A:$A,0)) -> Fujian | D95: =INDEX('Plant data'!F:F,MATCH('Blast furnaces'!$A95,'Plant data'!$A:$A,0)) -> China | E95: U100000140089 | F95: BF 2 | G95: https://www.gem.wiki/Fujian_Sanbao_Steel_Co_Ltd | H95: operating | I95: unknown | J95: unknown | K95: 2013 | L95: 12 | M95: unknown | N95: unknown | O95: unknown | P95: 1040 | Q95: 1080 | R95: 44806 | S95: =_xlfn.LET( _xlpm.x, R95, _xlpm.t, TEXT(R95,"@"), IF(R95="","", IF(ISNUMBER(_xlpm.x), IF(_xlpm.x>=30000, _xlpm.x, DATE(_xlpm.x,1,1)), DATE( LEFT(_xlpm.t,4), IF(LEN(_xlpm.t)>=7, MID(_xlpm.t,6,2), 1), IF(LEN(_xlpm.t)>=10, RIGHT(_xlpm.t,2), 1) ) ) ) ) -> 44806 | T95: =IF(R95="","",EDATE(S95,240)) -> 52111
A96: P100000120079 | B96: =INDEX('Plant data'!D:D,MATCH('Blast furnaces'!$A96,'Plant data'!$A:$A,0)) -> Fuzhou | C96: =INDEX('Plant data'!E:E,MATCH('Blast furnaces'!$A96,'Plant data'!$A:$A,0)) -> Fujian | D96: =INDEX('Plant data'!F:F,MATCH('Blast furnaces'!$A96,'Plant data'!$A:$A,0)) -> China | E96: U100000140090 | F96: BF #1 | G96: https://www.gem.wiki/Fujian_Yixin_Steel_Co_Ltd | H96: operating pre-retirement | I96: unknown | J96: unknown | K96: unknown | L96: unknown | M96: 43770 | N96: unknown | O96: unknown | P96: 550 | Q96: 450 | S96: =_xlfn.LET( _xlpm.x, R96, _xlpm.t, TEXT(R96,"@"), IF(R96="","", IF(ISNUMBER(_xlpm.x), IF(_xlpm.x>=30000, _xlpm.x, DATE(_xlpm.x,1,1)), DATE( LEFT(_xlpm.t,4), IF(LEN(_xlpm.t)>=7, MID(_xlpm.t,6,2), 1), IF(LEN(_xlpm.t)>=10, RIGHT(_xlpm.t,2), 1) ) ) ) ) | T96: =IF(R96="","",EDATE(S96,240))
A97: P100000120079 | B97: =INDEX('Plant data'!D:D,MATCH('Blast furnaces'!$A97,'Plant data'!$A:$A,0)) -> Fuzhou | C97: =INDEX('Plant data'!E:E,MATCH('Blast furnaces'!$A97,'Plant data'!$A:$A,0)) -> Fujian | D97: =INDEX('Plant data'!F:F,MATCH('Blast furnaces'!$A97,'Plant data'!$A:$A,0)) -> China | E97: U100000140091 | F97: BF #2 | G97: https://www.gem.wiki/Fujian_Yixin_Steel_Co_Ltd | H97: operating pre-retirement | I97: unknown | J97: unknown | K97: unknown | L97: unknown | M97: 43770 | N97: unknown | O97: unknown | P97: 550 | Q97: 450 | R97: 2020 | S97: =_xlfn.LET( _xlpm.x, R97, _xlpm.t, TEXT(R97,"@"), IF(R97="","", IF(ISNUMBER(_xlpm.x), IF(_xlpm.x>=30000, _xlpm.x, DATE(_xlpm.x,1,1)), DATE( LEFT(_xlpm.t,4), IF(LEN(_xlpm.t)>=7, MID(_xlpm.t,6,2), 1), IF(LEN(_xlpm.t)>=10, RIGHT(_xlpm.t,2), 1) ) ) ) ) -> 43831 | T97: =IF(R97="","",EDATE(S97,240)) -> 51136
A98: P100000120079 | B98: =INDEX('Plant data'!D:D,MATCH('Blast furnaces'!$A98,'Plant data'!$A:$A,0)) -> Fuzhou | C98: =INDEX('Plant data'!E:E,MATCH('Blast furnaces'!$A98,'Plant data'!$A:$A,0)) -> Fujian | D98: =INDEX('Plant data'!F:F,MATCH('Blast furnaces'!$A98,'Plant data'!$A:$A,0)) -> China | E98: U100000140092 | F98: unknown BF (1) | G98: https://www.gem.wiki/Fujian_Yixin_Steel_Co_Ltd | H98: construction | I98: 43770 | J98: 2020 | K98: unknown | L98: unknown | M98: unknown | N98: unknown | O98: unknown | P98: 1130 | Q98: 1200 | S98: =_xlfn.LET( _xlpm.x, R98, _xlpm.t, TEXT(R98,"@"), IF(R98="","", IF(ISNUMBER(_xlpm.x), IF(_xlpm.x>=30000, _xlpm.x, DATE(_xlpm.x,1,1)), DATE( LEFT(_xlpm.t,4), IF(LEN(_xlpm.t)>=7, MID(_xlpm.t,6,2), 1), IF(LEN(_xlpm.t)>=10, RIGHT(_xlpm.t,2), 1) ) ) ) )
A99: P100000120080 | B99: =INDEX('Plant data'!D:D,MATCH('Blast furnaces'!$A99,'Plant data'!$A:$A,0)) -> Fuzhou | C99: =INDEX('Plant data'!E:E,MATCH('Blast furnaces'!$A99,'Plant data'!$A:$A,0)) -> Fujian | D99: =INDEX('Plant data'!F:F,MATCH('Blast furnaces'!$A99,'Plant data'!$A:$A,0)) -> China | E99: U100000140093 | F99: unknown BF (1) | G99: https://www.gem.wiki/Fujian_Luoyuan_Minguang_Iron_and_Steel_Co_Ltd | H99: retired | I99: unknown | J99: unknown | K99: unknown | L99: unknown | M99: 2017 | N99: unknown | O99: 2019 | P99: 600 | Q99: 500 | S99: =_xlfn.LET( _xlpm.x, R99, _xlpm.t, TEXT(R99,"@"), IF(R99="","", IF(ISNUMBER(_xlpm.x), IF(_xlpm.x>=30000, _xlpm.x, DATE(_xlpm.x,1,1)), DATE( LEFT(_xlpm.t,4), IF(LEN(_xlpm.t)>=7, MID(_xlpm.t,6,2), 1), IF(LEN(_xlpm.t)>=10, RIGHT(_xlpm.t,2), 1) ) ) ) )
A100: P100000120080 | B100: =INDEX('Plant data'!D:D,MATCH('Blast furnaces'!$A100,'Plant data'!$A:$A,0)) -> Fuzhou | C100: =INDEX('Plant data'!E:E,MATCH('Blast furnaces'!$A100,'Plant data'!$A:$A,0)) -> Fujian | D100: =INDEX('Plant data'!F:F,MATCH('Blast furnaces'!$A100,'Plant data'!$A:$A,0)) -> China | E100: U100000140094 | F100: unknown BF (2) | G100: https://www.gem.wiki/Fujian_Luoyuan_Minguang_Iron_and_Steel_Co_Ltd | H100: retired | I100: unknown | J100: unknown | K100: unknown | L100: unknown | M100: 2017 | N100: unknown | O100: 2019 | P100: 734 | Q100: 660 | S100: =_xlfn.LET( _xlpm.x, R100, _xlpm.t, TEXT(R100,"@"), IF(R100="","", IF(ISNUMBER(_xlpm.x), IF(_xlpm.x>=30000, _xlpm.x, DATE(_xlpm.x,1,1)), DATE( LEFT(_xlpm.t,4), IF(LEN(_xlpm.t)>=7, MID(_xlpm.t,6,2), 1), IF(LEN(_xlpm.t)>=10, RIGHT(_xlpm.t,2), 1) ) ) ) )
...

Sheet DRI furnaces
A1: GEM Plant ID | B1: Municipality | C1: Subnational unit (province/state) | D1: Country/Area | E1: GEM Unit ID | F1: Unit Name | G1: GEM Wiki Page | H1: Unit Status | I1: Announced Date | J1: Construction Date | K1: Start Date | L1: Unit Age | M1: Pre-retirement Announcement Date | N1: Idled Date | O1: Retired Date | P1: Furnace Manufacturer | Q1: Furnace Model | R1: Furnace Type | S1: Current Capacity (ttpa) | T1: CCS/CCUS | U1: Reductant | V1: Retirement Date
A2: P100000120001 | B2: =INDEX('Plant data'!D:D,MATCH($A2,'Plant data'!$A:$A,0)) -> Abu Dhabi Industrial City | C2: =INDEX('Plant data'!E:E,MATCH($A2,'Plant data'!$A:$A,0)) -> Abu Dhabi | D2: =INDEX('Plant data'!F:F,MATCH($A2,'Plant data'!$A:$A,0)) -> United Arab Emirates | E2: U100000143280 | F2: DRI 1 | G2: https://www.gem.wiki/Emsteel_Abu_Dhabi_plant | H2: operating | I2: unknown | J2: unknown | K2: 2009 | L2: 16 | M2: unknown | N2: unknown | O2: unknown | P2: Tenova HYL and Danieli & C | Q2: Energiron | R2: shaft furnace | S2: 2000 | T2: No | U2: hydrogen | V2: =IFERROR(K2+40,"") -> 2049
A3: P100000120001 | B3: =INDEX('Plant data'!D:D,MATCH($A3,'Plant data'!$A:$A,0)) -> Abu Dhabi Industrial City | C3: =INDEX('Plant data'!E:E,MATCH($A3,'Plant data'!$A:$A,0)) -> Abu Dhabi | D3: =INDEX('Plant data'!F:F,MATCH($A3,'Plant data'!$A:$A,0)) -> United Arab Emirates | E3: U100000143281 | F3: DRI 2 | G3: https://www.gem.wiki/Emsteel_Abu_Dhabi_plant | H3: operating | I3: unknown | J3: unknown | K3: 2011 | L3: 14 | M3: unknown | N3: unknown | O3: unknown | P3: Tenova HYL and Danieli & C | Q3: Energiron | R3: shaft furnace | S3: 2000 | T3: No | U3: methane | V3: =IFERROR(K3+40,"") -> 2051
A4: P100000120001 | B4: =INDEX('Plant data'!D:D,MATCH($A4,'Plant data'!$A:$A,0)) -> Abu Dhabi Industrial City | C4: =INDEX('Plant data'!E:E,MATCH($A4,'Plant data'!$A:$A,0)) -> Abu Dhabi | D4: =INDEX('Plant data'!F:F,MATCH($A4,'Plant data'!$A:$A,0)) -> United Arab Emirates | E4: U100001030327 | F4: DRI 3 | G4: https://www.gem.wiki/Emsteel_Abu_Dhabi_plant | H4: operating | I4: unknown | J4: unknown | K4: unknown | L4: unknown | M4: unknown | N4: unknown | O4: unknown | P4: unknown | Q4: unknown | R4: unknown | S4: 200 | T4: No | U4: unknown | V4: =IFERROR(K4+40,"")
A5: P100000120006 | B5: =INDEX('Plant data'!D:D,MATCH($A5,'Plant data'!$A:$A,0)) -> Villa Constitución | C5: =INDEX('Plant data'!E:E,MATCH($A5,'Plant data'!$A:$A,0)) -> Santa Fe | D5: =INDEX('Plant data'!F:F,MATCH($A5,'Plant data'!$A:$A,0)) -> Argentina | E5: U100000143284 | F5: unknown DRI (1) | G5: https://www.gem.wiki/ArcelorMittal_Acindar_Villa_Constitución_steel_plant | H5: operating | I5: unknown | J5: unknown | K5: 1978 | L5: 47 | M5: unknown | N5: unknown | O5: unknown | P5: unknown | Q5: Midrex | R5: shaft furnace | S5: 600 | T5: No | U5: unknown | V5: =IFERROR(K5+40,"") -> 2018
A6: P100000120007 | B6: =INDEX('Plant data'!D:D,MATCH($A6,'Plant data'!$A:$A,0)) -> Campana | C6: =INDEX('Plant data'!E:E,MATCH($A6,'Plant data'!$A:$A,0)) -> Buenos Aires | D6: =INDEX('Plant data'!F:F,MATCH($A6,'Plant data'!$A:$A,0)) -> Argentina | E6: U100000143285 | F6: unknown DRI (1) | G6: https://www.gem.wiki/TenarisSiderca_Campana_steel_plant | H6: operating | I6: unknown | J6: unknown | K6: 1976 | L6: 49 | M6: unknown | N6: unknown | O6: unknown | P6: unknown | Q6: Midrex | R6: shaft furnace | S6: 960 | T6: No | U6: unknown | V6: =IFERROR(K6+40,"") -> 2016
A7: P100000120011 | B7: =INDEX('Plant data'!D:D,MATCH($A7,'Plant data'!$A:$A,0)) -> Leoben | C7: =INDEX('Plant data'!E:E,MATCH($A7,'Plant data'!$A:$A,0)) -> Styria | D7: =INDEX('Plant data'!F:F,MATCH($A7,'Plant data'!$A:$A,0)) -> Austria | E7: U100001048461 | F7: DRI Hyfor | G7: https://www.gem.wiki/Voestalpine_Stahl_Donawitz_steel_plant | H7: operating | I7: unknown | J7: unknown | K7: 2024 | L7: 1 | M7: unknown | N7: unknown | O7: unknown | P7: Primetals | Q7: unknown | R7: shaft furnace | S7: 1 | T7: No | U7: hydrogen | V7: =IFERROR(K7+40,"") -> 2064
A8: P100000120013 | B8: =INDEX(#REF!,MATCH($A8,#REF!,0)) -> #REF! | C8: =INDEX(#REF!,MATCH($A8,#REF!,0)) -> #REF! | D8: =INDEX(#REF!,MATCH($A8,#REF!,0)) -> #REF! | E8: U100000143286 | F8: unknown DRI (1) | G8: https://www.gem.wiki/GFG_Liberty_Steel_Australia_Whyalla_steel_plant | H8: announced | I8: unknown | J8: unknown | K8: 2027 | M8: unknown | N8: unknown | O8: unknown | P8: unknown | Q8: unknown | R8: unknown | S8: 1800 | T8: No | U8: unknown | V8: =IFERROR(K8+40,"") -> 2067
A9: P100000120019 | B9: =INDEX(#REF!,MATCH($A9,#REF!,0)) -> #REF! | C9: =INDEX(#REF!,MATCH($A9,#REF!,0)) -> #REF! | D9: =INDEX(#REF!,MATCH($A9,#REF!,0)) -> #REF! | E9: U100000144885 | F9: unknown DRI (1) | G9: https://www.gem.wiki/Bashundhara_Steel_Mirsarai_plant | H9: announced | I9: 2022 | J9: unknown | K9: 2026 | M9: unknown | N9: unknown | O9: unknown | P9: unknown | Q9: unknown | R9: unknown | S9: 2200 | T9: No | U9: unknown | V9: =IFERROR(K9+40,"") -> 2066
A10: P100000120027 | B10: =INDEX(#REF!,MATCH($A10,#REF!,0)) -> #REF! | C10: =INDEX(#REF!,MATCH($A10,#REF!,0)) -> #REF! | D10: =INDEX(#REF!,MATCH($A10,#REF!,0)) -> #REF! | E10: U100000143287 | F10: unknown DRI (1) | G10: https://www.gem.wiki/ArcelorMittal_Gent_steel_plant | H10: announced | I10: unknown | J10: unknown | K10: unknown | L10: unknown | M10: unknown | N10: unknown | O10: unknown | P10: unknown | Q10: unknown | R10: unknown | S10: 2500 | T10: No | U10: unknown | V10: =IFERROR(K10+40,"")
A11: P100000120032 | B11: =INDEX('Plant data'!D:D,MATCH($A11,'Plant data'!$A:$A,0)) -> Al Hidd | C11: =INDEX('Plant data'!E:E,MATCH($A11,'Plant data'!$A:$A,0)) -> Muharraq | D11: =INDEX('Plant data'!F:F,MATCH($A11,'Plant data'!$A:$A,0)) -> Bahrain | E11: U100000143288 | F11: unknown DRI (1) | G11: https://www.gem.wiki/Sulb_Bahrain_Al_Hidd_steel_plant | H11: operating | I11: unknown | J11: unknown | K11: 2013 | L11: 12 | M11: unknown | N11: unknown | O11: unknown | P11: Midrex | Q11: unknown | R11: shaft furnace | S11: 1619 | T11: No | U11: methane | V11: =IFERROR(K11+40,"") -> 2053
A12: P100000120057 | B12: =INDEX('Plant data'!D:D,MATCH($A12,'Plant data'!$A:$A,0)) -> Contrecœur | C12: =INDEX('Plant data'!E:E,MATCH($A12,'Plant data'!$A:$A,0)) -> Quebec | D12: =INDEX('Plant data'!F:F,MATCH($A12,'Plant data'!$A:$A,0)) -> Canada | E12: U100000143289 | F12: DRI 1 | G12: https://www.gem.wiki/ArcelorMittal_Montreal_steel_plant | H12: operating | I12: unknown | J12: unknown | K12: unknown | L12: unknown | M12: unknown | N12: unknown | O12: unknown | P12: unknown | Q12: unknown | R12: shaft furnace | S12: 650 | T12: No | U12: methane | V12: =IFERROR(K12+40,"")
A13: P100000120057 | B13: =INDEX('Plant data'!D:D,MATCH($A13,'Plant data'!$A:$A,0)) -> Contrecœur | C13: =INDEX('Plant data'!E:E,MATCH($A13,'Plant data'!$A:$A,0)) -> Quebec | D13: =INDEX('Plant data'!F:F,MATCH($A13,'Plant data'!$A:$A,0)) -> Canada | E13: U100000143290 | F13: DRI 2 | G13: https://www.gem.wiki/ArcelorMittal_Montreal_steel_plant | H13: operating | I13: unknown | J13: unknown | K13: unknown | L13: unknown | M13: unknown | N13: unknown | O13: unknown | P13: unknown | Q13: unknown | R13: shaft furnace | S13: 1000 | T13: No | U13: methane | V13: =IFERROR(K13+40,"")
A14: P100000120058 | B14: =INDEX(#REF!,MATCH($A14,#REF!,0)) -> #REF! | C14: =INDEX(#REF!,MATCH($A14,#REF!,0)) -> #REF! | D14: =INDEX(#REF!,MATCH($A14,#REF!,0)) -> #REF! | E14: U100000143291 | F14: unknown DRI (1) | G14: https://www.gem.wiki/ArcelorMittal_Dofasco_steel_plant | H14: announced | I14: unknown | J14: unknown | K14: 2028 | M14: unknown | N14: unknown | O14: unknown | P14: unknown | Q14: unknown | R14: shaft furnace | S14: 2500 | T14: No | U14: methane | V14: =IFERROR(K14+40,"") -> 2068
A15: P100000120085 | B15: =INDEX('Plant data'!D:D,MATCH($A15,'Plant data'!$A:$A,0)) -> Zhanjiang | C15: =INDEX('Plant data'!E:E,MATCH($A15,'Plant data'!$A:$A,0)) -> Guangdong | D15: =INDEX('Plant data'!F:F,MATCH($A15,'Plant data'!$A:$A,0)) -> China | E15: U100000143292 | F15: unknown DRI (1) | G15: https://www.gem.wiki/Baosteel_Zhanjiang_Iron_and_Steel_Co_Ltd | H15: operating | I15: 44409 | J15: 44607 | K15: 2023 | L15: 2 | M15: unknown | N15: unknown | O15: unknown | P15: Danieli, Tenova | Q15: Energiron ZR | R15: shaft furnace | S15: 1000 | T15: Yes | U15: waste gas recovery (coke oven gas) | V15: =IFERROR(K15+40,"") -> 2063
A16: P100000120240 | B16: =INDEX(#REF!,MATCH($A16,#REF!,0)) -> #REF! | C16: =INDEX(#REF!,MATCH($A16,#REF!,0)) -> #REF! | D16: =INDEX(#REF!,MATCH($A16,#REF!,0)) -> #REF! | E16: U100001052736 | F16: unknown DRI (1) | G16: https://www.gem.wiki/Rizhao_Steel_Holding_Group_Co_Ltd | H16: announced | I16: 43952 | J16: unknown | K16: unknown | L16: unknown | M16: unknown | N16: unknown | O16: unknown | P16: unknown | Q16: unknown | R16: unknown | S16: 500 | T16: No | U16: unknown | V16: =IFERROR(K16+40,"")
A17: P100000120282 | B17: =INDEX('Plant data'!D:D,MATCH($A17,'Plant data'!$A:$A,0)) -> unknown | C17: =INDEX('Plant data'!E:E,MATCH($A17,'Plant data'!$A:$A,0)) -> Tianjin | D17: =INDEX('Plant data'!F:F,MATCH($A17,'Plant data'!$A:$A,0)) -> China | E17: U100000144518 | F17: unknown DRI (1) | G17: https://www.gem.wiki/Tianjin_Pipe_Corporation | H17: operating | I17: unknown | J17: unknown | K17: unknown | L17: unknown | M17: unknown | N17: unknown | O17: unknown | P17: DAVY | Q17: DAVY DRC | R17: rotary kiln | S17: 150 | T17: No | U17: coal | V17: =IFERROR(K17+40,"")
A18: P100000120282 | B18: =INDEX('Plant data'!D:D,MATCH($A18,'Plant data'!$A:$A,0)) -> unknown | C18: =INDEX('Plant data'!E:E,MATCH($A18,'Plant data'!$A:$A,0)) -> Tianjin | D18: =INDEX('Plant data'!F:F,MATCH($A18,'Plant data'!$A:$A,0)) -> China | E18: U100000144519 | F18: unknown DRI (2) | G18: https://www.gem.wiki/Tianjin_Pipe_Corporation | H18: operating | I18: unknown | J18: unknown | K18: unknown | L18: unknown | M18: unknown | N18: unknown | O18: unknown | P18: DAVY | Q18: unknown | R18: rotary kiln | S18: 150 | T18: No | U18: coal | V18: =IFERROR(K18+40,"")
A19: P100000120401 | B19: =INDEX('Plant data'!D:D,MATCH($A19,'Plant data'!$A:$A,0)) -> Zhangjiakou | C19: =INDEX('Plant data'!E:E,MATCH($A19,'Plant data'!$A:$A,0)) -> Hebei | D19: =INDEX('Plant data'!F:F,MATCH($A19,'Plant data'!$A:$A,0)) -> China | E19: U100000143294 | F19: unknown DRI (1) | G19: https://www.gem.wiki/Hebei_Zhangxuan_High_Tech_Co_Ltd | H19: operating | I19: 44652 | J19: unknown | K19: 2023 | L19: 2 | M19: unknown | N19: unknown | O19: unknown | P19: unknown | Q19: Energiron | R19: shaft furnace | S19: 555 | T19: Yes | U19: waste gas recovery (coke oven gas) | V19: =IFERROR(K19+40,"") -> 2063
A20: P100000120401 | B20: =INDEX('Plant data'!D:D,MATCH($A20,'Plant data'!$A:$A,0)) -> Zhangjiakou | C20: =INDEX('Plant data'!E:E,MATCH($A20,'Plant data'!$A:$A,0)) -> Hebei | D20: =INDEX('Plant data'!F:F,MATCH($A20,'Plant data'!$A:$A,0)) -> China | E20: U100000143293 | F20: unknown DRI (2) | G20: https://www.gem.wiki/Hebei_Zhangxuan_High_Tech_Co_Ltd | H20: operating | I20: 44652 | J20: unknown | K20: 2023 | L20: 2 | M20: unknown | N20: unknown | O20: unknown | P20: unknown | Q20: Energiron | R20: shaft furnace | S20: 555 | T20: Yes | U20: waste gas recovery (coke oven gas) | V20: =IFERROR(K20+40,"") -> 2063
A21: P100000120421 | B21: =INDEX(#REF!,MATCH($A21,#REF!,0)) -> #REF! | C21: =INDEX(#REF!,MATCH($A21,#REF!,0)) -> #REF! | D21: =INDEX(#REF!,MATCH($A21,#REF!,0)) -> #REF! | E21: U100000143478 | F21: unknown DRI (1) | G21: https://www.gem.wiki/ThyssenKrupp_Steel_Duisburg_steel_plant | H21: announced | I21: 44805 | J21: unknown | K21: 2026 | M21: unknown | N21: unknown | O21: unknown | P21: TS Elino | Q21: midrex | R21: shaft furnace | S21: 2500 | T21: No | U21: unknown | V21: =IFERROR(K21+40,"") -> 2066
A22: P100000120422 | B22: =INDEX(#REF!,MATCH($A22,#REF!,0)) -> #REF! | C22: =INDEX(#REF!,MATCH($A22,#REF!,0)) -> #REF! | D22: =INDEX(#REF!,MATCH($A22,#REF!,0)) -> #REF! | E22: U100000143296 | F22: unknown DRI (1) | G22: https://www.gem.wiki/Hüttenwerke_Krupp_Mannesmann_(HKM)_steel_plant | H22: announced | I22: unknown | J22: unknown | K22: 2025 | L22: 0 | M22: unknown | N22: unknown | O22: unknown | P22: unknown | Q22: unknown | R22: shaft furnace | S22: >0 | T22: No | U22: methane | V22: =IFERROR(K22+40,"") -> 2065
A23: P100000120422 | B23: =INDEX(#REF!,MATCH($A23,#REF!,0)) -> #REF! | C23: =INDEX(#REF!,MATCH($A23,#REF!,0)) -> #REF! | D23: =INDEX(#REF!,MATCH($A23,#REF!,0)) -> #REF! | E23: U100000143295 | F23: unknown DRI (2) | G23: https://www.gem.wiki/Hüttenwerke_Krupp_Mannesmann_(HKM)_steel_plant | H23: announced | I23: unknown | J23: unknown | K23: 2045 | M23: unknown | N23: unknown | O23: unknown | P23: unknown | Q23: unknown | R23: shaft furnace | S23: >0 | T23: No | U23: methane | V23: =IFERROR(K23+40,"") -> 2085
A24: P100000120423 | B24: =INDEX(#REF!,MATCH($A24,#REF!,0)) -> #REF! | C24: =INDEX(#REF!,MATCH($A24,#REF!,0)) -> #REF! | D24: =INDEX(#REF!,MATCH($A24,#REF!,0)) -> #REF! | E24: U100000143297 | F24: unknown DRI (1) | G24: https://www.gem.wiki/AG_der_Dillinger_Hüttenwerke_Dillingen_steel_plant | H24: announced | I24: 44713 | J24: unknown | K24: 2027 | M24: unknown | N24: unknown | O24: unknown | P24: Primetals | Q24: Midrex | R24: shaft furnace | S24: 2500 | T24: No | U24: unknown | V24: =IFERROR(K24+40,"") -> 2067
A25: P100000120424 | B25: =INDEX('Plant data'!D:D,MATCH($A25,'Plant data'!$A:$A,0)) -> Salzgitter | C25: =INDEX('Plant data'!E:E,MATCH($A25,'Plant data'!$A:$A,0)) -> Lower Saxony | D25: =INDEX('Plant data'!F:F,MATCH($A25,'Plant data'!$A:$A,0)) -> Germany | E25: U100000143298 | F25: unknown DRI (1) | G25: https://www.gem.wiki/Salzgitter_Flachstahl_steel_plant | H25: construction | I25: 2015 | J25: 2022 | K25: 2026 | M25: unknown | N25: unknown | O25: unknown | P25: Tenova, Danieli, DSD Steel Group | Q25: Energiron ZR | R25: shaft furnace | S25: 2100 | T25: No | U25: methane | V25: =IFERROR(K25+40,"") -> 2066
A26: P100000120424 | B26: =INDEX(#REF!,MATCH($A26,#REF!,0)) -> #REF! | C26: =INDEX(#REF!,MATCH($A26,#REF!,0)) -> #REF! | D26: =INDEX(#REF!,MATCH($A26,#REF!,0)) -> #REF! | E26: U100000144333 | F26: unknown DRI (2) | G26: https://www.gem.wiki/Salzgitter_Flachstahl_steel_plant | H26: announced | I26: unknown | J26: unknown | K26: unknown | L26: unknown | M26: unknown | N26: unknown | O26: unknown | P26: unknown | Q26: unknown | R26: unknown | S26: >0 | T26: No | U26: unknown | V26: =IFERROR(K26+40,"")
A27: P100000120425 | B27: =INDEX(#REF!,MATCH($A27,#REF!,0)) -> #REF! | C27: =INDEX(#REF!,MATCH($A27,#REF!,0)) -> #REF! | D27: =INDEX(#REF!,MATCH($A27,#REF!,0)) -> #REF! | E27: U100000143299 | F27: unknown DRI (1) | G27: https://www.gem.wiki/ArcelorMittal_Eisenhüttenstadt_steel_plant | H27: cancelled | I27: unknown | J27: unknown | K27: unknown | L27: unknown | M27: unknown | N27: unknown | O27: 45778 | P27: unknown | Q27: unknown | R27: unknown | S27: 150 | T27: No | U27: unknown | V27: =IFERROR(K27+40,"")
A28: P100000120426 | B28: =INDEX(#REF!,MATCH($A28,#REF!,0)) -> #REF! | C28: =INDEX(#REF!,MATCH($A28,#REF!,0)) -> #REF! | D28: =INDEX(#REF!,MATCH($A28,#REF!,0)) -> #REF! | E28: U100000143300 | F28: unknown DRI (1) | G28: https://www.gem.wiki/ArcelorMittal_Bremen_steel_plant | H28: cancelled | I28: unknown | J28: unknown | K28: unknown | L28: unknown | M28: unknown | N28: unknown | O28: 45778 | P28: unknown | Q28: unknown | R28: shaft furnace | S28: 2000 | T28: No | U28: methane | V28: =IFERROR(K28+40,"")
A29: P100000120427 | B29: =INDEX(#REF!,MATCH($A29,#REF!,0)) -> #REF! | C29: =INDEX(#REF!,MATCH($A29,#REF!,0)) -> #REF! | D29: =INDEX(#REF!,MATCH($A29,#REF!,0)) -> #REF! | E29: U100000143464 | F29: unknown DRI (1) | G29: https://www.gem.wiki/ArcelorMittal_Hamburg_steel_plant | H29: announced | I29: 43709 | J29: unknown | K29: 2026 | M29: unknown | N29: unknown | O29: unknown | P29: unknown | Q29: unknown | R29: shaft furnace | S29: 100 | T29: No | U29: unknown | V29: =IFERROR(K29+40,"") -> 2066
A30: P100000120427 | B30: =INDEX('Plant data'!D:D,MATCH($A30,'Plant data'!$A:$A,0)) -> Hamburg | C30: =INDEX('Plant data'!E:E,MATCH($A30,'Plant data'!$A:$A,0)) -> Hamburg | D30: =INDEX('Plant data'!F:F,MATCH($A30,'Plant data'!$A:$A,0)) -> Germany | E30: U100000143301 | F30: unknown DRI (2) | G30: https://www.gem.wiki/ArcelorMittal_Hamburg_steel_plant | H30: operating | I30: unknown | J30: unknown | K30: 1971 | L30: 54 | M30: unknown | N30: unknown | O30: unknown | P30: unknown | Q30: Midrex | R30: shaft furnace | S30: 600 | T30: No | U30: methane | V30: =IFERROR(K30+40,"") -> 2011
A31: P100000120439 | B31: =INDEX('Plant data'!D:D,MATCH($A31,'Plant data'!$A:$A,0)) -> El-Milia | C31: =INDEX('Plant data'!E:E,MATCH($A31,'Plant data'!$A:$A,0)) -> Jijel | D31: =INDEX('Plant data'!F:F,MATCH($A31,'Plant data'!$A:$A,0)) -> Algeria | E31: U100000143302 | F31: unknown DRI (1) | G31: https://www.gem.wiki/Algerian_Qatari_Steel_Jijel_plant | H31: operating | I31: unknown | J31: unknown | K31: 2020 | L31: 5 | M31: unknown | N31: unknown | O31: unknown | P31: Midrex | Q31: unknown | R31: unknown | S31: 2500 | T31: No | U31: unknown | V31: =IFERROR(K31+40,"") -> 2060
A32: P100000120439 | B32: =INDEX(#REF!,MATCH($A32,#REF!,0)) -> #REF! | C32: =INDEX(#REF!,MATCH($A32,#REF!,0)) -> #REF! | D32: =INDEX(#REF!,MATCH($A32,#REF!,0)) -> #REF! | E32: U100000144862 | F32: unknown DRI (2) | G32: https://www.gem.wiki/Algerian_Qatari_Steel_Jijel_plant | H32: announced | I32: 2022 | J32: unknown | K32: 2026 | M32: unknown | N32: unknown | O32: unknown | P32: unknown | Q32: unknown | R32: unknown | S32: 2500 | T32: No | U32: unknown | V32: =IFERROR(K32+40,"") -> 2066
A33: P100000120440 | B33: =INDEX(#REF!,MATCH($A33,#REF!,0)) -> #REF! | C33: =INDEX(#REF!,MATCH($A33,#REF!,0)) -> #REF! | D33: =INDEX(#REF!,MATCH($A33,#REF!,0)) -> #REF! | E33: U100000143303 | F33: unknown DRI (1) | G33: https://www.gem.wiki/Sider_El_Hadjar_Annaba_steel_plant | H33: cancelled | I33: 2018 | J33: unknown | K33: unknown | L33: unknown | M33: unknown | N33: unknown | O33: 2020 | P33: unknown | Q33: unknown | R33: unknown | S33: 2500 | T33: No | U33: unknown | V33: =IFERROR(K33+40,"")
A34: P100000120441 | B34: =INDEX('Plant data'!D:D,MATCH($A34,'Plant data'!$A:$A,0)) -> Bethiqua | C34: =INDEX('Plant data'!E:E,MATCH($A34,'Plant data'!$A:$A,0)) -> Oran | D34: =INDEX('Plant data'!F:F,MATCH($A34,'Plant data'!$A:$A,0)) -> Algeria | E34: U100000143304 | F34: DRI Plant - 1 | G34: https://www.gem.wiki/Tosyali_Algerie_Oran_steel_plant | H34: operating | I34: unknown | J34: unknown | K34: 2018 | L34: 7 | M34: unknown | N34: unknown | O34: unknown | P34: Midrex | Q34: unknown | R34: shaft furnace | S34: 2500 | T34: No | U34: methane | V34: =IFERROR(K34+40,"") -> 2058
A35: P100000120441 | B35: =INDEX('Plant data'!D:D,MATCH($A35,'Plant data'!$A:$A,0)) -> Bethiqua | C35: =INDEX('Plant data'!E:E,MATCH($A35,'Plant data'!$A:$A,0)) -> Oran | D35: =INDEX('Plant data'!F:F,MATCH($A35,'Plant data'!$A:$A,0)) -> Algeria | E35: U100000143305 | F35: DRI Plant - 2 | G35: https://www.gem.wiki/Tosyali_Algerie_Oran_steel_plant | H35: operating | I35: unknown | J35: 2021 | K35: 2024 | L35: 1 | M35: unknown | N35: unknown | O35: unknown | P35: Midrex; Paul Wurth | Q35: Midrex | R35: shaft furnace | S35: 2500 | T35: No | U35: methane | V35: =IFERROR(K35+40,"") -> 2064
A36: P100000120445 | B36: =INDEX('Plant data'!D:D,MATCH($A36,'Plant data'!$A:$A,0)) -> Sadat City | C36: =INDEX('Plant data'!E:E,MATCH($A36,'Plant data'!$A:$A,0)) -> Menofia | D36: =INDEX('Plant data'!F:F,MATCH($A36,'Plant data'!$A:$A,0)) -> Egypt | E36: U100000143306 | F36: unknown DRI (1) | G36: https://www.gem.wiki/Egyptian_Sponge_Iron_and_Steel_Company_Sadat_City_plant | H36: operating | I36: unknown | J36: unknown | K36: 2015 | L36: 10 | M36: unknown | N36: unknown | O36: unknown | P36: Midrex | Q36: unknown | R36: unknown | S36: 1800 | T36: No | U36: unknown | V36: =IFERROR(K36+40,"") -> 2055
A37: P100000120446 | B37: =INDEX('Plant data'!D:D,MATCH($A37,'Plant data'!$A:$A,0)) -> Alexandria | C37: =INDEX('Plant data'!E:E,MATCH($A37,'Plant data'!$A:$A,0)) -> Alexandria | D37: =INDEX('Plant data'!F:F,MATCH($A37,'Plant data'!$A:$A,0)) -> Egypt | E37: U100000143307 | F37: DRI Midrex 1 | G37: https://www.gem.wiki/Al-Ezz_Dekheila_Steel_Alexandria_plant | H37: operating | I37: unknown | J37: unknown | K37: 1986 | L37: 39 | M37: unknown | N37: unknown | O37: unknown | P37: Midrex | Q37: Midrex | R37: shaft furnace | S37: 720 | T37: No | U37: methane | V37: =IFERROR(K37+40,"") -> 2026
A38: P100000120446 | B38: =INDEX('Plant data'!D:D,MATCH($A38,'Plant data'!$A:$A,0)) -> Alexandria | C38: =INDEX('Plant data'!E:E,MATCH($A38,'Plant data'!$A:$A,0)) -> Alexandria | D38: =INDEX('Plant data'!F:F,MATCH($A38,'Plant data'!$A:$A,0)) -> Egypt | E38: U100000143308 | F38: DRI Midrex 2 | G38: https://www.gem.wiki/Al-Ezz_Dekheila_Steel_Alexandria_plant | H38: operating | I38: unknown | J38: unknown | K38: 1997 | L38: 28 | M38: unknown | N38: unknown | O38: unknown | P38: Midrex | Q38: Midrex | R38: shaft furnace | S38: 800 | T38: No | U38: methane | V38: =IFERROR(K38+40,"") -> 2037
A39: P100000120446 | B39: =INDEX('Plant data'!D:D,MATCH($A39,'Plant data'!$A:$A,0)) -> Alexandria | C39: =INDEX('Plant data'!E:E,MATCH($A39,'Plant data'!$A:$A,0)) -> Alexandria | D39: =INDEX('Plant data'!F:F,MATCH($A39,'Plant data'!$A:$A,0)) -> Egypt | E39: U100000143309 | F39: DRI Midrex 3 | G39: https://www.gem.wiki/Al-Ezz_Dekheila_Steel_Alexandria_plant | H39: operating | I39: unknown | J39: unknown | K39: 2000 | L39: 25 | M39: unknown | N39: unknown | O39: unknown | P39: Midrex | Q39: Midrex | R39: shaft furnace | S39: 800 | T39: No | U39: methane | V39: =IFERROR(K39+40,"") -> 2040
A40: P100000120447 | B40: =INDEX('Plant data'!D:D,MATCH($A40,'Plant data'!$A:$A,0)) -> Ain Sokhna | C40: =INDEX('Plant data'!E:E,MATCH($A40,'Plant data'!$A:$A,0)) -> Suez | D40: =INDEX('Plant data'!F:F,MATCH($A40,'Plant data'!$A:$A,0)) -> Egypt | E40: U100000143310 | F40: unknown DRI (1) | G40: https://www.gem.wiki/Ezz_Flat_Steel_Ain_Sokhna_plant | H40: operating | I40: unknown | J40: 2009 | K40: 2016 | L40: 9 | M40: unknown | N40: unknown | O40: unknown | P40: Danieli | Q40: HYL | R40: shaft furnace | S40: 1900 | T40: No | U40: methane | V40: =IFERROR(K40+40,"") -> 2056
A41: P100000120449 | B41: =INDEX('Plant data'!D:D,MATCH($A41,'Plant data'!$A:$A,0)) -> Attaka | C41: =INDEX('Plant data'!E:E,MATCH($A41,'Plant data'!$A:$A,0)) -> Suez | D41: =INDEX('Plant data'!F:F,MATCH($A41,'Plant data'!$A:$A,0)) -> Egypt | E41: U100000143311 | F41: unknown DRI (1) | G41: https://www.gem.wiki/Suez_Steel_Solb_Misr_Attaka_plant | H41: operating | I41: unknown | J41: unknown | K41: 2014 | L41: 11 | M41: unknown | N41: unknown | O41: unknown | P41: unknown | Q41: unknown | R41: unknown | S41: 2100 | T41: No | U41: unknown | V41: =IFERROR(K41+40,"") -> 2054
A42: P100000120452 | B42: =INDEX(#REF!,MATCH($A42,#REF!,0)) -> #REF! | C42: =INDEX(#REF!,MATCH($A42,#REF!,0)) -> #REF! | D42: =INDEX(#REF!,MATCH($A42,#REF!,0)) -> #REF! | E42: U100000143312 | F42: unknown DRI (1) | G42: https://www.gem.wiki/ArcelorMittal_Asturias_(Gijón)_steel_plant | H42: announced | I42: unknown | J42: unknown | K42: unknown | L42: unknown | M42: unknown | N42: unknown | O42: unknown | P42: unknown | Q42: unknown | R42: unknown | S42: 2300 | T42: No | U42: unknown | V42: =IFERROR(K42+40,"")
A43: P100000120466 | B43: =INDEX(#REF!,MATCH($A43,#REF!,0)) -> #REF! | C43: =INDEX(#REF!,MATCH($A43,#REF!,0)) -> #REF! | D43: =INDEX(#REF!,MATCH($A43,#REF!,0)) -> #REF! | E43: U100000144640 | F43: unknown DRI (1) | G43: https://www.gem.wiki/Hydnum_Steel_Castilla-La_Mancha_plant | H43: announced | I43: 45078 | J43: 2025 | K43: 2029 | M43: unknown | N43: unknown | O43: unknown | P43: unknown | Q43: unknown | R43: shaft furnace | S43: >0 | T43: No | U43: unknown | V43: =IFERROR(K43+40,"") -> 2069
A44: P100000120468 | B44: =INDEX(#REF!,MATCH($A44,#REF!,0)) -> #REF! | C44: =INDEX(#REF!,MATCH($A44,#REF!,0)) -> #REF! | D44: =INDEX(#REF!,MATCH($A44,#REF!,0)) -> #REF! | E44: U100000144871 | F44: unknown DRI (1) | G44: https://www.gem.wiki/SSAB_Raahe_steel_plant | H44: announced | I44: unknown | J44: unknown | K44: unknown | L44: unknown | M44: unknown | N44: unknown | O44: unknown | P44: unknown | Q44: unknown | R44: unknown | S44: >0 | T44: No | U44: unknown | V44: =IFERROR(K44+40,"")
A45: P100000120471 | B45: =INDEX(#REF!,MATCH($A45,#REF!,0)) -> #REF! | C45: =INDEX(#REF!,MATCH($A45,#REF!,0)) -> #REF! | D45: =INDEX(#REF!,MATCH($A45,#REF!,0)) -> #REF! | E45: U100000144864 | F45: unknown DRI (1) | G45: https://www.gem.wiki/Blastr_Inkoo_steel_plant | H45: announced | I45: 44850 | J45: unknown | K45: 2026 | M45: unknown | N45: unknown | O45: unknown | P45: Midrex; Primetals | Q45: Midrex H2 | R45: shaft furnace | S45: 2000 | T45: No | U45: unknown | V45: =IFERROR(K45+40,"") -> 2066
A46: P100000120472 | B46: =INDEX(#REF!,MATCH($A46,#REF!,0)) -> #REF! | C46: =INDEX(#REF!,MATCH($A46,#REF!,0)) -> #REF! | D46: =INDEX(#REF!,MATCH($A46,#REF!,0)) -> #REF! | E46: U100000143313 | F46: unknown DRI (1) | G46: https://www.gem.wiki/ArcelorMittal_Dunkerque_steel_plant | H46: cancelled | I46: 2022 | J46: unknown | K46: unknown | L46: unknown | M46: unknown | N46: unknown | O46: 45839 | P46: unknown | Q46: unknown | R46: unknown | S46: 2500 | T46: No | U46: unknown | V46: =IFERROR(K46+40,"")
A47: P100000120499 | B47: =INDEX(#REF!,MATCH($A47,#REF!,0)) -> #REF! | C47: =INDEX(#REF!,MATCH($A47,#REF!,0)) -> #REF! | D47: =INDEX(#REF!,MATCH($A47,#REF!,0)) -> #REF! | E47: U100000144868 | F47: unknown DRI (1) | G47: https://www.gem.wiki/Gunung_Raja_Paksi_West_Java_steel_plant | H47: announced | I47: 44879 | J47: unknown | K47: unknown | L47: unknown | M47: unknown | N47: unknown | O47: unknown | P47: unknown | Q47: unknown | R47: unknown | S47: >0 | T47: No | U47: unknown | V47: =IFERROR(K47+40,"")
A48: P100000120501 | B48: =INDEX(#REF!,MATCH($A48,#REF!,0)) -> #REF! | C48: =INDEX(#REF!,MATCH($A48,#REF!,0)) -> #REF! | D48: =INDEX(#REF!,MATCH($A48,#REF!,0)) -> #REF! | E48: U100000143314 | F48: unknown DRI (1) | G48: https://www.gem.wiki/Krakatau_Steel_Cilegon_plant | H48: mothballed | I48: unknown | J48: unknown | K48: 1978 | L48: 47 | M48: unknown | N48: 2022 | O48: unknown | P48: Tenova and Danieli | Q48: HYL/Energiron | R48: unknown | S48: 675 | T48: No | U48: methane | V48: =IFERROR(K48+40,"") -> 2018
A49: P100000120501 | B49: =INDEX(#REF!,MATCH($A49,#REF!,0)) -> #REF! | C49: =INDEX(#REF!,MATCH($A49,#REF!,0)) -> #REF! | D49: =INDEX(#REF!,MATCH($A49,#REF!,0)) -> #REF! | E49: U100000144742 | F49: unknown DRI (2) | G49: https://www.gem.wiki/Krakatau_Steel_Cilegon_plant | H49: mothballed | I49: unknown | J49: unknown | K49: 1978 | L49: 47 | M49: unknown | N49: 2022 | O49: unknown | P49: Tenova and Danieli | Q49: HYL/Energiron | R49: unknown | S49: 675 | T49: No | U49: methane | V49: =IFERROR(K49+40,"") -> 2018
A50: P100000120504 | B50: =INDEX('Plant data'!D:D,MATCH($A50,'Plant data'!$A:$A,0)) -> Bahodopi | C50: =INDEX('Plant data'!E:E,MATCH($A50,'Plant data'!$A:$A,0)) -> Central Sulawesi | D50: =INDEX('Plant data'!F:F,MATCH($A50,'Plant data'!$A:$A,0)) -> Indonesia | E50: U100000144909 | F50: unknown DRI (1) | G50: https://www.gem.wiki/Dexin_Steel_Morowali_plant | H50: operating | I50: unknown | J50: 44610 | K50: 2023 | L50: 2 | M50: unknown | N50: unknown | O50: unknown | P50: unknown | Q50: unknown | R50: unknown | S50: 1500 | T50: No | U50: unknown | V50: =IFERROR(K50+40,"") -> 2063
A51: P100000120510 | B51: =INDEX('Plant data'!D:D,MATCH($A51,'Plant data'!$A:$A,0)) -> Thelkoloi | C51: =INDEX('Plant data'!E:E,MATCH($A51,'Plant data'!$A:$A,0)) -> Odisha | D51: =INDEX('Plant data'!F:F,MATCH($A51,'Plant data'!$A:$A,0)) -> India | E51: U100000143315 | F51: unknown DRI (1) | G51: https://www.gem.wiki/JSW_BPSL_Jharsuguda_steel_plant | H51: operating | I51: unknown | J51: unknown | K51: 2005 | L51: 20 | M51: unknown | N51: unknown | O51: unknown | P51: Lurgi Technology, Thyssen Krupp, Ferry Capital | Q51: unknown | R51: rotary kiln | S51: 160 | T51: No | U51: coal | V51: =IFERROR(K51+40,"") -> 2045
A52: P100000120510 | B52: =INDEX('Plant data'!D:D,MATCH($A52,'Plant data'!$A:$A,0)) -> Thelkoloi | C52: =INDEX('Plant data'!E:E,MATCH($A52,'Plant data'!$A:$A,0)) -> Odisha | D52: =INDEX('Plant data'!F:F,MATCH($A52,'Plant data'!$A:$A,0)) -> India | E52: U100000144194 | F52: unknown DRI (10) | G52: https://www.gem.wiki/JSW_BPSL_Jharsuguda_steel_plant | H52: operating | I52: unknown | J52: unknown | K52: 2012 | L52: 13 | M52: unknown | N52: unknown | O52: unknown | P52: unknown | Q52: unknown | R52: rotary kiln | S52: 160 | T52: No | U52: coal | V52: =IFERROR(K52+40,"") -> 2052
A53: P100000120510 | B53: =INDEX('Plant data'!D:D,MATCH($A53,'Plant data'!$A:$A,0)) -> Thelkoloi | C53: =INDEX('Plant data'!E:E,MATCH($A53,'Plant data'!$A:$A,0)) -> Odisha | D53: =INDEX('Plant data'!F:F,MATCH($A53,'Plant data'!$A:$A,0)) -> India | E53: U100000144373 | F53: unknown DRI (11) | G53: https://www.gem.wiki/JSW_BPSL_Jharsuguda_steel_plant | H53: operating | I53: unknown | J53: unknown | K53: 2014 | L53: 11 | M53: unknown | N53: unknown | O53: unknown | P53: unknown | Q53: unknown | R53: rotary kiln | S53: 160 | T53: No | U53: coal | V53: =IFERROR(K53+40,"") -> 2054
A54: P100000120510 | B54: =INDEX('Plant data'!D:D,MATCH($A54,'Plant data'!$A:$A,0)) -> Thelkoloi | C54: =INDEX('Plant data'!E:E,MATCH($A54,'Plant data'!$A:$A,0)) -> Odisha | D54: =INDEX('Plant data'!F:F,MATCH($A54,'Plant data'!$A:$A,0)) -> India | E54: U100000144374 | F54: unknown DRI (12) | G54: https://www.gem.wiki/JSW_BPSL_Jharsuguda_steel_plant | H54: operating | I54: unknown | J54: unknown | K54: 2014 | L54: 11 | M54: unknown | N54: unknown | O54: unknown | P54: unknown | Q54: unknown | R54: rotary kiln | S54: 160 | T54: No | U54: coal | V54: =IFERROR(K54+40,"") -> 2054
A55: P100000120510 | B55: =INDEX('Plant data'!D:D,MATCH($A55,'Plant data'!$A:$A,0)) -> Thelkoloi | C55: =INDEX('Plant data'!E:E,MATCH($A55,'Plant data'!$A:$A,0)) -> Odisha | D55: =INDEX('Plant data'!F:F,MATCH($A55,'Plant data'!$A:$A,0)) -> India | E55: U100000144186 | F55: unknown DRI (2) | G55: https://www.gem.wiki/JSW_BPSL_Jharsuguda_steel_plant | H55: operating | I55: unknown | J55: unknown | K55: 2005 | L55: 20 | M55: unknown | N55: unknown | O55: unknown | P55: Lurgi Technology, Thyssen Krupp, Ferry Capital | Q55: unknown | R55: rotary kiln | S55: 160 | T55: No | U55: coal | V55: =IFERROR(K55+40,"") -> 2045
A56: P100000120510 | B56: =INDEX('Plant data'!D:D,MATCH($A56,'Plant data'!$A:$A,0)) -> Thelkoloi | C56: =INDEX('Plant data'!E:E,MATCH($A56,'Plant data'!$A:$A,0)) -> Odisha | D56: =INDEX('Plant data'!F:F,MATCH($A56,'Plant data'!$A:$A,0)) -> India | E56: U100000144187 | F56: unknown DRI (3) | G56: https://www.gem.wiki/JSW_BPSL_Jharsuguda_steel_plant | H56: operating | I56: unknown | J56: unknown | K56: 2005 | L56: 20 | M56: unknown | N56: unknown | O56: unknown | P56: Lurgi Technology, Thyssen Krupp, Ferry Capital | Q56: unknown | R56: rotary kiln | S56: 160 | T56: No | U56: coal | V56: =IFERROR(K56+40,"") -> 2045
A57: P100000120510 | B57: =INDEX('Plant data'!D:D,MATCH($A57,'Plant data'!$A:$A,0)) -> Thelkoloi | C57: =INDEX('Plant data'!E:E,MATCH($A57,'Plant data'!$A:$A,0)) -> Odisha | D57: =INDEX('Plant data'!F:F,MATCH($A57,'Plant data'!$A:$A,0)) -> India | E57: U100000144188 | F57: unknown DRI (4) | G57: https://www.gem.wiki/JSW_BPSL_Jharsuguda_steel_plant | H57: operating | I57: unknown | J57: unknown | K57: 2005 | L57: 20 | M57: unknown | N57: unknown | O57: unknown | P57: Lurgi Technology, Thyssen Krupp, Ferry Capital | Q57: unknown | R57: rotary kiln | S57: 160 | T57: No | U57: coal | V57: =IFERROR(K57+40,"") -> 2045
A58: P100000120510 | B58: =INDEX('Plant data'!D:D,MATCH($A58,'Plant data'!$A:$A,0)) -> Thelkoloi | C58: =INDEX('Plant data'!E:E,MATCH($A58,'Plant data'!$A:$A,0)) -> Odisha | D58: =INDEX('Plant data'!F:F,MATCH($A58,'Plant data'!$A:$A,0)) -> India | E58: U100000144189 | F58: unknown DRI (5) | G58: https://www.gem.wiki/JSW_BPSL_Jharsuguda_steel_plant | H58: operating | I58: unknown | J58: unknown | K58: 2011 | L58: 14 | M58: unknown | N58: unknown | O58: unknown | P58: unknown | Q58: unknown | R58: rotary kiln | S58: 160 | T58: No | U58: coal | V58: =IFERROR(K58+40,"") -> 2051
A59: P100000120510 | B59: =INDEX('Plant data'!D:D,MATCH($A59,'Plant data'!$A:$A,0)) -> Thelkoloi | C59: =INDEX('Plant data'!E:E,MATCH($A59,'Plant data'!$A:$A,0)) -> Odisha | D59: =INDEX('Plant data'!F:F,MATCH($A59,'Plant data'!$A:$A,0)) -> India | E59: U100000144190 | F59: unknown DRI (6) | G59: https://www.gem.wiki/JSW_BPSL_Jharsuguda_steel_plant | H59: operating | I59: unknown | J59: unknown | K59: 2011 | L59: 14 | M59: unknown | N59: unknown | O59: unknown | P59: unknown | Q59: unknown | R59: rotary kiln | S59: 160 | T59: No | U59: coal | V59: =IFERROR(K59+40,"") -> 2051
A60: P100000120510 | B60: =INDEX('Plant data'!D:D,MATCH($A60,'Plant data'!$A:$A,0)) -> Thelkoloi | C60: =INDEX('Plant data'!E:E,MATCH($A60,'Plant data'!$A:$A,0)) -> Odisha | D60: =INDEX('Plant data'!F:F,MATCH($A60,'Plant data'!$A:$A,0)) -> India | E60: U100000144191 | F60: unknown DRI (7) | G60: https://www.gem.wiki/JSW_BPSL_Jharsuguda_steel_plant | H60: operating | I60: unknown | J60: unknown | K60: 2011 | L60: 14 | M60: unknown | N60: unknown | O60: unknown | P60: unknown | Q60: unknown | R60: rotary kiln | S60: 160 | T60: No | U60: coal | V60: =IFERROR(K60+40,"") -> 2051
A61: P100000120510 | B61: =INDEX('Plant data'!D:D,MATCH($A61,'Plant data'!$A:$A,0)) -> Thelkoloi | C61: =INDEX('Plant data'!E:E,MATCH($A61,'Plant data'!$A:$A,0)) -> Odisha | D61: =INDEX('Plant data'!F:F,MATCH($A61,'Plant data'!$A:$A,0)) -> India | E61: U100000144192 | F61: unknown DRI (8) | G61: https://www.gem.wiki/JSW_BPSL_Jharsuguda_steel_plant | H61: operating | I61: unknown | J61: unknown | K61: 2012 | L61: 13 | M61: unknown | N61: unknown | O61: unknown | P61: unknown | Q61: unknown | R61: rotary kiln | S61: 160 | T61: No | U61: coal | V61: =IFERROR(K61+40,"") -> 2052
A62: P100000120510 | B62: =INDEX('Plant data'!D:D,MATCH($A62,'Plant data'!$A:$A,0)) -> Thelkoloi | C62: =INDEX('Plant data'!E:E,MATCH($A62,'Plant data'!$A:$A,0)) -> Odisha | D62: =INDEX('Plant data'!F:F,MATCH($A62,'Plant data'!$A:$A,0)) -> India | E62: U100000144193 | F62: unknown DRI (9) | G62: https://www.gem.wiki/JSW_BPSL_Jharsuguda_steel_plant | H62: operating | I62: unknown | J62: unknown | K62: 2012 | L62: 13 | M62: unknown | N62: unknown | O62: unknown | P62: unknown | Q62: unknown | R62: rotary kiln | S62: 160 | T62: No | U62: coal | V62: =IFERROR(K62+40,"") -> 2052
... A64: P100000120511 | B64: =INDEX('Plant data'!D:D,MATCH($A64,'Plant data'!$A:$A,0)) -> Meramandali | C64: =INDEX('Plant data'!E:E,MATCH($A64,'Plant data'!$A:$A,0)) -> Odisha | D64: =INDEX('Plant data'!F:F,MATCH($A64,'Plant data'!$A:$A,0)) -> India | E64: U100001031057 | F64: unknown DRI (10) | G64: https://www.gem.wiki/Tata_Steel_BSL_Meramandali_steel_plant | H64: operating | I64: unknown | J64: unknown | K64: 2007 | L64: 18 | M64: unknown | N64: unknown | O64: unknown | P64: unknown | Q64: Lurgi | R64: rotary kiln | S64: 150 | T64: No | U64: coal | V64: =IFERROR(K64+40,"") -> 2047
A65: P100000120511 | B65: =INDEX(#REF!,MATCH($A65,#REF!,0)) -> #REF! | C65: =INDEX(#REF!,MATCH($A65,#REF!,0)) -> #REF! | D65: =INDEX(#REF!,MATCH($A65,#REF!,0)) -> #REF! | E65: U100000144149 | F65: unknown DRI (11) | G65: https://www.gem.wiki/Tata_Steel_BSL_Meramandali_steel_plant | H65: announced | I65: unknown | J65: unknown | K65: 2030 | M65: unknown | N65: unknown | O65: unknown | P65: unknown | Q65: Midrex | R65: shaft furnace | S65: 1600 | T65: No | U65: waste gas recovery (coke oven gas) | V65: =IFERROR(K65+40,"") -> 2070
A66: P100000120511 | B66: =INDEX('Plant data'!D:D,MATCH($A66,'Plant data'!$A:$A,0)) -> Meramandali | C66: =INDEX('Plant data'!E:E,MATCH($A66,'Plant data'!$A:$A,0)) -> Odisha | D66: =INDEX('Plant data'!F:F,MATCH($A66,'Plant data'!$A:$A,0)) -> India | E66: U100001031050 | F66: unknown DRI (2) | G66: https://www.gem.wiki/Tata_Steel_BSL_Meramandali_steel_plant | H66: operating | I66: unknown | J66: unknown | K66: 2007 | L66: 18 | M66: unknown | N66: unknown | O66: unknown | P66: unknown | Q66: Lurgi | R66: rotary kiln | S66: 150 | T66: No | U66: coal | V66: =IFERROR(K66+40,"") -> 2047
A67: P100000120511 | B67: =INDEX('Plant data'!D:D,MATCH($A67,'Plant data'!$A:$A,0)) -> Meramandali | C67: =INDEX('Plant data'!E:E,MATCH($A67,'Plant data'!$A:$A,0)) -> Odisha | D67: =INDEX('Plant data'!F:F,MATCH($A67,'Plant data'!$A:$A,0)) -> India | E67: U100001031049 | F67: unknown DRI (3) | G67: https://www.gem.wiki/Tata_Steel_BSL_Meramandali_steel_plant | H67: operating | I67: unknown | J67: unknown | K67: 2007 | L67: 18 | M67: unknown | N67: unknown | O67: unknown | P67: unknown | Q67: Lurgi | R67: rotary kiln | S67: 150 | T67: No | U67: coal | V67: =IFERROR(K67+40,"") -> 2047
A68: P100000120511 | B68: =INDEX('Plant data'!D:D,MATCH($A68,'Plant data'!$A:$A,0)) -> Meramandali | C68: =INDEX('Plant data'!E:E,MATCH($A68,'Plant data'!$A:$A,0)) -> Odisha | D68: =INDEX('Plant data'!F:F,MATCH($A68,'Plant data'!$A:$A,0)) -> India | E68: U100001031051 | F68: unknown DRI (4) | G68: https://www.gem.wiki/Tata_Steel_BSL_Meramandali_steel_plant | H68: operating | I68: unknown | J68: unknown | K68: 2007 | L68: 18 | M68: unknown | N68: unknown | O68: unknown | P68: unknown | Q68: Lurgi | R68: rotary kiln | S68: 150 | T68: No | U68: coal | V68: =IFERROR(K68+40,"") -> 2047
A69: P100000120511 | B69: =INDEX('Plant data'!D:D,MATCH($A69,'Plant data'!$A:$A,0)) -> Meramandali | C69: =INDEX('Plant data'!E:E,MATCH($A69,'Plant data'!$A:$A,0)) -> Odisha | D69: =INDEX('Plant data'!F:F,MATCH($A69,'Plant data'!$A:$A,0)) -> India | E69: U100001031052 | F69: unknown DRI (5) | G69: https://www.gem.wiki/Tata_Steel_BSL_Meramandali_steel_plant | H69: operating | I69: unknown | J69: unknown | K69: 2007 | L69: 18 | M69: unknown | N69: unknown | O69: unknown | P69: unknown | Q69: Lurgi | R69: rotary kiln | S69: 150 | T69: No | U69: coal | V69: =IFERROR(K69+40,"") -> 2047
A70: P100000120511 | B70: =INDEX('Plant data'!D:D,MATCH($A70,'Plant data'!$A:$A,0)) -> Meramandali | C70: =INDEX('Plant data'!E:E,MATCH($A70,'Plant data'!$A:$A,0)) -> Odisha | D70: =INDEX('Plant data'!F:F,MATCH($A70,'Plant data'!$A:$A,0)) -> India | E70: U100001031053 | F70: unknown DRI (6) | G70: https://www.gem.wiki/Tata_Steel_BSL_Meramandali_steel_plant | H70: operating | I70: unknown | J70: unknown | K70: 2007 | L70: 18 | M70: unknown | N70: unknown | O70: unknown | P70: unknown | Q70: Lurgi | R70: rotary kiln | S70: 150 | T70: No | U70: coal | V70: =IFERROR(K70+40,"") -> 2047
A71: P100000120511 | B71: =INDEX('Plant data'!D:D,MATCH($A71,'Plant data'!$A:$A,0)) -> Meramandali | C71: =INDEX('Plant data'!E:E,MATCH($A71,'Plant data'!$A:$A,0)) -> Odisha | D71: =INDEX('Plant data'!F:F,MATCH($A71,'Plant data'!$A:$A,0)) -> India | E71: U100001031054 | F71: unknown DRI (7) | G71: https://www.gem.wiki/Tata_Steel_BSL_Meramandali_steel_plant | H71: operating | I71: unknown | J71: unknown | K71: 2007 | L71: 18 | M71: unknown | N71: unknown | O71: unknown | P71: unknown | Q71: Lurgi | R71: rotary kiln | S71: 150 | T71: No | U71: coal | V71: =IFERROR(K71+40,"") -> 2047
A72: P100000120511 | B72: =INDEX('Plant data'!D:D,MATCH($A72,'Plant data'!$A:$A,0)) -> Meramandali | C72: =INDEX('Plant data'!E:E,MATCH($A72,'Plant data'!$A:$A,0)) -> Odisha | D72: =INDEX('Plant data'!F:F,MATCH($A72,'Plant data'!$A:$A,0)) -> India | E72: U100001031055 | F72: unknown DRI (8) | G72: https://www.gem.wiki/Tata_Steel_BSL_Meramandali_steel_plant | H72: operating | I72: unknown | J72: unknown | K72: 2007 | L72: 18 | M72: unknown | N72: unknown | O72: unknown | P72: unknown | Q72: Lurgi | R72: rotary kiln | S72: 150 | T72: No | U72: coal | V72: =IFERROR(K72+40,"") -> 2047
A73: P100000120511 | B73: =INDEX('Plant data'!D:D,MATCH($A73,'Plant data'!$A:$A,0)) -> Meramandali | C73: =INDEX('Plant data'!E:E,MATCH($A73,'Plant data'!$A:$A,0)) -> Odisha | D73: =INDEX('Plant data'!F:F,MATCH($A73,'Plant data'!$A:$A,0)) -> India | E73: U100001031056 | F73: unknown DRI (9) | G73: https://www.gem.wiki/Tata_Steel_BSL_Meramandali_steel_plant | H73: operating | I73: unknown | J73: unknown | K73: 2007 | L73: 18 | M73: unknown | N73: unknown | O73: unknown | P73: unknown | Q73: Lurgi | R73: rotary kiln | S73: 150 | T73: No | U73: coal | V73: =IFERROR(K73+40,"") -> 2047
A74: P100000120512 | B74: =INDEX('Plant data'!D:D,MATCH($A74,'Plant data'!$A:$A,0)) -> Danapura | C74: =INDEX('Plant data'!E:E,MATCH($A74,'Plant data'!$A:$A,0)) -> Karnataka | D74: =INDEX('Plant data'!F:F,MATCH($A74,'Plant data'!$A:$A,0)) -> India | E74: U100000144443 | F74: DRI 1 | G74: https://www.gem.wiki/BMM_Ispat_Danapur_steel_plant | H74: operating | I74: unknown | J74: unknown | K74: 2011 | L74: 14 | M74: unknown | N74: unknown | O74: unknown | P74: unknown | Q74: unknown | R74: rotary kiln | S74: 175 | T74: No | U74: coal | V74: =IFERROR(K74+40,"") -> 2051
A75: P100000120512 | B75: =INDEX('Plant data'!D:D,MATCH($A75,'Plant data'!$A:$A,0)) -> Danapura | C75: =INDEX('Plant data'!E:E,MATCH($A75,'Plant data'!$A:$A,0)) -> Karnataka | D75: =INDEX('Plant data'!F:F,MATCH($A75,'Plant data'!$A:$A,0)) -> India | E75: U100000144444 | F75: DRI 2 | G75: https://www.gem.wiki/BMM_Ispat_Danapur_steel_plant | H75: operating | I75: unknown | J75: unknown | K75: 2011 | L75: 14 | M75: unknown | N75: unknown | O75: unknown | P75: unknown | Q75: unknown | R75: rotary kiln | S75: 175 | T75: No | U75: coal | V75: =IFERROR(K75+40,"") -> 2051
A76: P100000120512 | B76: =INDEX('Plant data'!D:D,MATCH($A76,'Plant data'!$A:$A,0)) -> Danapura | C76: =INDEX('Plant data'!E:E,MATCH($A76,'Plant data'!$A:$A,0)) -> Karnataka | D76: =INDEX('Plant data'!F:F,MATCH($A76,'Plant data'!$A:$A,0)) -> India | E76: U100000144445 | F76: DRI 3 | G76: https://www.gem.wiki/BMM_Ispat_Danapur_steel_plant | H76: operating | I76: unknown | J76: unknown | K76: 2011 | L76: 14 | M76: unknown | N76: unknown | O76: unknown | P76: unknown | Q76: unknown | R76: rotary kiln | S76: 175 | T76: No | U76: coal | V76: =IFERROR(K76+40,"") -> 2051
A77: P100000120512 | B77: =INDEX('Plant data'!D:D,MATCH($A77,'Plant data'!$A:$A,0)) -> Danapura | C77: =INDEX('Plant data'!E:E,MATCH($A77,'Plant data'!$A:$A,0)) -> Karnataka | D77: =INDEX('Plant data'!F:F,MATCH($A77,'Plant data'!$A:$A,0)) -> India | E77: U100000144446 | F77: DRI 4 | G77: https://www.gem.wiki/BMM_Ispat_Danapur_steel_plant | H77: operating | I77: unknown | J77: unknown | K77: 2011 | L77: 14 | M77: unknown | N77: unknown | O77: unknown | P77: unknown | Q77: unknown | R77: rotary kiln | S77: 175 | T77: No | U77: coal | V77: =IFERROR(K77+40,"") -> 2051
A78: P100000120512 | B78: =INDEX('Plant data'!D:D,MATCH($A78,'Plant data'!$A:$A,0)) -> Danapura | C78: =INDEX('Plant data'!E:E,MATCH($A78,'Plant data'!$A:$A,0)) -> Karnataka | D78: =INDEX('Plant data'!F:F,MATCH($A78,'Plant data'!$A:$A,0)) -> India | E78: U100000144447 | F78: unknown DRI (5) | G78: https://www.gem.wiki/BMM_Ispat_Danapur_steel_plant | H78: operating | I78: unknown | J78: unknown | K78: unknown | L78: unknown | M78: unknown | N78: unknown | O78: unknown | P78: unknown | Q78: unknown | R78: rotary kiln | S78: 30 | T78: No | U78: coal | V78: =IFERROR(K78+40,"")
A79: P100000120512 | B79: =INDEX('Plant data'!D:D,MATCH($A79,'Plant data'!$A:$A,0)) -> Danapura | C79: =INDEX('Plant data'!E:E,MATCH($A79,'Plant data'!$A:$A,0)) -> Karnataka | D79: =INDEX('Plant data'!F:F,MATCH($A79,'Plant data'!$A:$A,0)) -> India | E79: U100000144448 | F79: unknown DRI (6) | G79: https://www.gem.wiki/BMM_Ispat_Danapur_steel_plant | H79: operating | I79: unknown | J79: unknown | K79: unknown | L79: unknown | M79: unknown | N79: unknown | O79: unknown | P79: unknown | Q79: unknown | R79: rotary kiln | S79: 30 | T79: No | U79: coal | V79: =IFERROR(K79+40,"")
A80: P100000120513 | B80: =INDEX('Plant data'!D:D,MATCH($A80,'Plant data'!$A:$A,0)) -> Hazira | C80: =INDEX('Plant data'!E:E,MATCH($A80,'Plant data'!$A:$A,0)) -> Gujarat | D80: =INDEX('Plant data'!F:F,MATCH($A80,'Plant data'!$A:$A,0)) -> India | E80: U100000143318 | F80: DRI Mod I | G80: https://www.gem.wiki/ArcelorMittal_Nippon_Steel_Hazira_Plant | H80: operating | I80: unknown | J80: unknown | K80: 1990 | L80: 35 | M80: unknown | N80: unknown | O80: unknown | P80: unknown | Q80: Midrex | R80: shaft furnace | S80: 1000 | T80: No | U80: methane | V80: =IFERROR(K80+40,"") -> 2030
A81: P100000120513 | B81: =INDEX('Plant data'!D:D,MATCH($A81,'Plant data'!$A:$A,0)) -> Hazira | C81: =INDEX('Plant data'!E:E,MATCH($A81,'Plant data'!$A:$A,0)) -> Gujarat | D81: =INDEX('Plant data'!F:F,MATCH($A81,'Plant data'!$A:$A,0)) -> India | E81: U100000143319 | F81: DRI Mod II | G81: https://www.gem.wiki/ArcelorMittal_Nippon_Steel_Hazira_Plant | H81: operating | I81: unknown | J81: unknown | K81: 1990 | L81: 35 | M81: unknown | N81: unknown | O81: unknown | P81: unknown | Q81: Midrex | R81: shaft furnace | S81: 1000 | T81: No | U81: methane | V81: =IFERROR(K81+40,"") -> 2030
A82: P100000120513 | B82: =INDEX('Plant data'!D:D,MATCH($A82,'Plant data'!$A:$A,0)) -> Hazira | C82: =INDEX('Plant data'!E:E,MATCH($A82,'Plant data'!$A:$A,0)) -> Gujarat | D82: =INDEX('Plant data'!F:F,MATCH($A82,'Plant data'!$A:$A,0)) -> India | E82: U100000143320 | F82: DRI Mod III | G82: https://www.gem.wiki/ArcelorMittal_Nippon_Steel_Hazira_Plant | H82: operating | I82: unknown | J82: unknown | K82: 1992 | L82: 33 | M82: unknown | N82: unknown | O82: unknown | P82: unknown | Q82: Midrex | R82: shaft furnace | S82: 1000 | T82: No | U82: methane | V82: =IFERROR(K82+40,"") -> 2032
A83: P100000120513 | B83: =INDEX('Plant data'!D:D,MATCH($A83,'Plant data'!$A:$A,0)) -> Hazira | C83: =INDEX('Plant data'!E:E,MATCH($A83,'Plant data'!$A:$A,0)) -> Gujarat | D83: =INDEX('Plant data'!F:F,MATCH($A83,'Plant data'!$A:$A,0)) -> India | E83: U100000143321 | F83: DRI Mod IV | G83: https://www.gem.wiki/ArcelorMittal_Nippon_Steel_Hazira_Plant | H83: operating | I83: unknown | J83: unknown | K83: 2004 | L83: 21 | M83: unknown | N83: unknown | O83: unknown | P83: unknown | Q83: Midrex | R83: shaft furnace | S83: 1000 | T83: No | U83: methane | V83: =IFERROR(K83+40,"") -> 2044
A84: P100000120513 | B84: =INDEX('Plant data'!D:D,MATCH($A84,'Plant data'!$A:$A,0)) -> Hazira | C84: =INDEX('Plant data'!E:E,MATCH($A84,'Plant data'!$A:$A,0)) -> Gujarat | D84: =INDEX('Plant data'!F:F,MATCH($A84,'Plant data'!$A:$A,0)) -> India | E84: U100000143322 | F84: DRI Mod V | G84: https://www.gem.wiki/ArcelorMittal_Nippon_Steel_Hazira_Plant | H84: operating | I84: unknown | J84: unknown | K84: 2006 | L84: 19 | M84: unknown | N84: unknown | O84: unknown | P84: unknown | Q84: Midrex | R84: shaft furnace | S84: 1980 | T84: No | U84: methane | V84: =IFERROR(K84+40,"") -> 2046
A85: P100000120513 | B85: =INDEX('Plant data'!D:D,MATCH($A85,'Plant data'!$A:$A,0)) -> Hazira | C85: =INDEX('Plant data'!E:E,MATCH($A85,'Plant data'!$A:$A,0)) -> Gujarat | D85: =INDEX('Plant data'!F:F,MATCH($A85,'Plant data'!$A:$A,0)) -> India | E85: U100000144725 | F85: DRI Mod VI | G85: https://www.gem.wiki/ArcelorMittal_Nippon_Steel_Hazira_Plant | H85: operating | I85: unknown | J85: unknown | K85: 2010 | L85: 15 | M85: unknown | N85: unknown | O85: unknown | P85: unknown | Q85: Midrex | R85: shaft furnace | S85: 1850 | T85: No | U85: methane | V85: =IFERROR(K85+40,"") -> 2050
A86: P100000120515 | B86: =INDEX('Plant data'!D:D,MATCH($A86,'Plant data'!$A:$A,0)) -> Angul | C86: =INDEX('Plant data'!E:E,MATCH($A86,'Plant data'!$A:$A,0)) -> Odisha | D86: =INDEX('Plant data'!F:F,MATCH($A86,'Plant data'!$A:$A,0)) -> India | E86: U100000143325 | F86: DRI 1 | G86: https://www.gem.wiki/JSPL_Angul_steel_plant | H86: operating | I86: unknown | J86: unknown | K86: 2014 | L86: 11 | M86: unknown | N86: unknown | O86: unknown | P86: MIdrex technologies | Q86: Midrex | R86: shaft furnace | S86: 1800 | T86: No | U86: waste gas recovery (coke oven gas) | V86: =IFERROR(K86+40,"") -> 2054
A87: P100000120516 | B87: =INDEX('Plant data'!D:D,MATCH($A87,'Plant data'!$A:$A,0)) -> Raigarh | C87: =INDEX('Plant data'!E:E,MATCH($A87,'Plant data'!$A:$A,0)) -> Chhattisgarh | D87: =INDEX('Plant data'!F:F,MATCH($A87,'Plant data'!$A:$A,0)) -> India | E87: U100000143327 | F87: unknown DRI (1) | G87: https://www.gem.wiki/JSPL_Raigarh_steel_plant | H87: operating | I87: unknown | J87: unknown | K87: 1993 | L87: 32 | M87: unknown | N87: unknown | O87: unknown | P87: unknown | Q87: unknown | R87: rotary kiln | S87: 100 | T87: No | U87: coal | V87: =IFERROR(K87+40,"") -> 2033
A88: P100000120516 | B88: =INDEX('Plant data'!D:D,MATCH($A88,'Plant data'!$A:$A,0)) -> Raigarh | C88: =INDEX('Plant data'!E:E,MATCH($A88,'Plant data'!$A:$A,0)) -> Chhattisgarh | D88: =INDEX('Plant data'!F:F,MATCH($A88,'Plant data'!$A:$A,0)) -> India | E88: U100000144720 | F88: unknown DRI (10) | G88: https://www.gem.wiki/JSPL_Raigarh_steel_plant | H88: operating | I88: unknown | J88: unknown | K88: 2005 | L88: 20 | M88: unknown | N88: unknown | O88: unknown | P88: unknown | Q88: unknown | R88: rotary kiln | S88: 180 | T88: No | U88: coal | V88: =IFERROR(K88+40,"") -> 2045
A89: P100000120516 | B89: =INDEX('Plant data'!D:D,MATCH($A89,'Plant data'!$A:$A,0)) -> Raigarh | C89: =INDEX('Plant data'!E:E,MATCH($A89,'Plant data'!$A:$A,0)) -> Chhattisgarh | D89: =INDEX('Plant data'!F:F,MATCH($A89,'Plant data'!$A:$A,0)) -> India | E89: U100000144721 | F89: unknown DRI (11) | G89: https://www.gem.wiki/JSPL_Raigarh_steel_plant | H89: operating | I89: unknown | J89: unknown | K89: 2005 | L89: 20 | M89: unknown | N89: unknown | O89: unknown | P89: unknown | Q89: unknown | R89: rotary kiln | S89: 180 | T89: No | U89: coal | V89: =IFERROR(K89+40,"") -> 2045
A90: P100000120516 | B90: =INDEX('Plant data'!D:D,MATCH($A90,'Plant data'!$A:$A,0)) -> Raigarh | C90: =INDEX('Plant data'!E:E,MATCH($A90,'Plant data'!$A:$A,0)) -> Chhattisgarh | D90: =INDEX('Plant data'!F:F,MATCH($A90,'Plant data'!$A:$A,0)) -> India | E90: U100000143326 | F90: unknown DRI (2) | G90: https://www.gem.wiki/JSPL_Raigarh_steel_plant | H90: operating | I90: unknown | J90: unknown | K90: 2005 | L90: 20 | M90: unknown | N90: unknown | O90: unknown | P90: unknown | Q90: unknown | R90: rotary kiln | S90: 180 | T90: No | U90: coal | V90: =IFERROR(K90+40,"") -> 2045
A91: P100000120516 | B91: =INDEX(#REF!,MATCH($A91,#REF!,0)) -> #REF! | C91: =INDEX(#REF!,MATCH($A91,#REF!,0)) -> #REF! | D91: =INDEX(#REF!,MATCH($A91,#REF!,0)) -> #REF! | E91: U100000144421 | F91: unknown DRI (3) | G91: https://www.gem.wiki/JSPL_Raigarh_steel_plant | H91: announced | I91: 2021 | J91: unknown | K91: 2027 | M91: unknown | N91: unknown | O91: unknown | P91: unknown | Q91: unknown | R91: shaft furnace | S91: 2700 | T91: No | U91: waste gas recovery (coke oven gas) | V91: =IFERROR(K91+40,"") -> 2067
A92: P100000120516 | B92: =INDEX('Plant data'!D:D,MATCH($A92,'Plant data'!$A:$A,0)) -> Raigarh | C92: =INDEX('Plant data'!E:E,MATCH($A92,'Plant data'!$A:$A,0)) -> Chhattisgarh | D92: =INDEX('Plant data'!F:F,MATCH($A92,'Plant data'!$A:$A,0)) -> India | E92: U100000144714 | F92: unknown DRI (4) | G92: https://www.gem.wiki/JSPL_Raigarh_steel_plant | H92: operating | I92: unknown | J92: unknown | K92: 1994 | L92: 31 | M92: unknown | N92: unknown | O92: unknown | P92: unknown | Q92: unknown | R92: rotary kiln | S92: 100 | T92: No | U92: coal | V92: =IFERROR(K92+40,"") -> 2034
A93: P100000120516 | B93: =INDEX('Plant data'!D:D,MATCH($A93,'Plant data'!$A:$A,0)) -> Raigarh | C93: =INDEX('Plant data'!E:E,MATCH($A93,'Plant data'!$A:$A,0)) -> Chhattisgarh | D93: =INDEX('Plant data'!F:F,MATCH($A93,'Plant data'!$A:$A,0)) -> India | E93: U100000144715 | F93: unknown DRI (5) | G93: https://www.gem.wiki/JSPL_Raigarh_steel_plant | H93: operating | I93: unknown | J93: unknown | K93: 1995 | L93: 30 | M93: unknown | N93: unknown | O93: unknown | P93: unknown | Q93: unknown | R93: rotary kiln | S93: 100 | T93: No | U93: coal | V93: =IFERROR(K93+40,"") -> 2035
A94: P100000120516 | B94: =INDEX('Plant data'!D:D,MATCH($A94,'Plant data'!$A:$A,0)) -> Raigarh | C94: =INDEX('Plant data'!E:E,MATCH($A94,'Plant data'!$A:$A,0)) -> Chhattisgarh | D94: =INDEX('Plant data'!F:F,MATCH($A94,'Plant data'!$A:$A,0)) -> India | E94: U100000144716 | F94: unknown DRI (6) | G94: https://www.gem.wiki/JSPL_Raigarh_steel_plant | H94: operating | I94: unknown | J94: unknown | K94: 1996 | L94: 29 | M94: unknown | N94: unknown | O94: unknown | P94: unknown | Q94: unknown | R94: rotary kiln | S94: 100 | T94: No | U94: coal | V94: =IFERROR(K94+40,"") -> 2036
A95: P100000120516 | B95: =INDEX('Plant data'!D:D,MATCH($A95,'Plant data'!$A:$A,0)) -> Raigarh | C95: =INDEX('Plant data'!E:E,MATCH($A95,'Plant data'!$A:$A,0)) -> Chhattisgarh | D95: =INDEX('Plant data'!F:F,MATCH($A95,'Plant data'!$A:$A,0)) -> India | E95: U100000144717 | F95: unknown DRI (7) | G95: https://www.gem.wiki/JSPL_Raigarh_steel_plant | H95: operating | I95: unknown | J95: unknown | K95: 2000 | L95: 25 | M95: unknown | N95: unknown | O95: unknown | P95: unknown | Q95: unknown | R95: rotary kiln | S95: 100 | T95: No | U95: coal | V95: =IFERROR(K95+40,"") -> 2040
A96: P100000120516 | B96: =INDEX('Plant data'!D:D,MATCH($A96,'Plant data'!$A:$A,0)) -> Raigarh | C96: =INDEX('Plant data'!E:E,MATCH($A96,'Plant data'!$A:$A,0)) -> Chhattisgarh | D96: =INDEX('Plant data'!F:F,MATCH($A96,'Plant data'!$A:$A,0)) -> India | E96: U100000144718 | F96: unknown DRI (8) | G96: https://www.gem.wiki/JSPL_Raigarh_steel_plant | H96: operating | I96: unknown | J96: unknown | K96: 2000 | L96: 25 | M96: unknown | N96: unknown | O96: unknown | P96: unknown | Q96: unknown | R96: rotary kiln | S96: 100 | T96: No | U96: coal | V96: =IFERROR(K96+40,"") -> 2040
A97: P100000120516 | B97: =INDEX('Plant data'!D:D,MATCH($A97,'Plant data'!$A:$A,0)) -> Raigarh | C97: =INDEX('Plant data'!E:E,MATCH($A97,'Plant data'!$A:$A,0)) -> Chhattisgarh | D97: =INDEX('Plant data'!F:F,MATCH($A97,'Plant data'!$A:$A,0)) -> India | E97: U100000144719 | F97: unknown DRI (9) | G97: https://www.gem.wiki/JSPL_Raigarh_steel_plant | H97: operating | I97: unknown | J97: unknown | K97: 2005 | L97: 20 | M97: unknown | N97: unknown | O97: unknown | P97: unknown | Q97: unknown | R97: rotary kiln | S97: 180 | T97: No | U97: coal | V97: =IFERROR(K97+40,"") -> 2045
A98: P100000120517 | B98: =INDEX('Plant data'!D:D,MATCH($A98,'Plant data'!$A:$A,0)) -> Dolvi | C98: =INDEX('Plant data'!E:E,MATCH($A98,'Plant data'!$A:$A,0)) -> Maharashtra | D98: =INDEX('Plant data'!F:F,MATCH($A98,'Plant data'!$A:$A,0)) -> India | E98: U100000143328 | F98: unknown DRI (1) | G98: https://www.gem.wiki/JSW_Steel_Dolvi_steel_plant | H98: operating | I98: unknown | J98: unknown | K98: 1994 | L98: 31 | M98: unknown | N98: unknown | O98: unknown | P98: unknown | Q98: Midrex | R98: shaft furnace | S98: 2000 | T98: 100 tpd CCS | U98: methane | V98: =IFERROR(K98+40,"") -> 2034
A99: P100000120517 | B99: =INDEX(#REF!,MATCH($A99,#REF!,0)) -> #REF! | C99: =INDEX(#REF!,MATCH($A99,#REF!,0)) -> #REF! | D99: =INDEX(#REF!,MATCH($A99,#REF!,0)) -> #REF! | E99: U100001028181 | F99: unknown DRI (2) | G99: https://www.gem.wiki/JSW_Steel_Dolvi_steel_plant | H99: cancelled | I99: 2014 | J99: unknown | K99: unknown | L99: unknown | M99: unknown | N99: unknown | O99: unknown | P99: unknown | Q99: unknown | R99: shaft furnace | S99: 2000 | T99: No | U99: unknown | V99: =IFERROR(K99+40,"")
A100: P100000120519 | B100: =INDEX('Plant data'!D:D,MATCH($A100,'Plant data'!$A:$A,0)) -> Toranagallu | C100: =INDEX('Plant data'!E:E,MATCH($A100,'Plant data'!$A:$A,0)) -> Karnataka | D100: =INDEX('Plant data'!F:F,MATCH($A100,'Plant data'!$A:$A,0)) -> India | E100: U100000143329 | F100: unknown DRI (1) | G100: https://www.gem.wiki/JSW_Steel_Vijayanagar_steel_plant | H100: operating | I100: unknown | J100: unknown | K100: 2014 | L100: 11 | M100: unknown | N100: unknown | O100: unknown | P100: unknown | Q100: Midrex | R100: shaft furnace | S100: 1200 | T100: No | U100: methane | V100: =IFERROR(K100+40,"") -> 2054
A101: P100000120520 | B101: =INDEX(#REF!,MATCH($A101,#REF!,0)) -> #REF! | C101: =INDEX(#REF!,MATCH($A101,#REF!,0)) -> #REF! | D101: =INDEX(#REF!,MATCH($A101,#REF!,0)) -> #REF! | E101: U100000144393 | F101: unknown DRI (1) | G101: https://www.gem.wiki/JSW_Steel_Jharkhand_steel_plant | H101: announced | I101: 2014 | J101: unknown | K101: unknown | L101: unknown | M101: unknown | N101: unknown | O101: unknown | P101: unknown | Q101: unknown | R101: rotary kiln | S101: 1200 | T101: No | U101: coal | V101: =IFERROR(K101+40,"")
...

Sheet Electric arc furnaces
A1: GEM Plant ID | B1: Municipality | C1: Subnational unit (province/state) | D1: Country/Area | E1: GEM Unit ID | F1: Unit Name | G1: GEM Wiki Page | H1: Unit Status | I1: Announced Date | J1: Construction Date | K1: Start Date | L1: Unit Age | M1: Pre-retirement Announcement Date | N1: Idled Date | O1: Retired Date | P1: Current Capacity (ttpa) | Q1: Current Size (tonne) | R1: Scrap-based | S1: Retirement date
A2: P100000120001 | B2: =INDEX('Plant data'!D:D,MATCH($A2,'Plant data'!$A:$A,0)) -> Abu Dhabi Industrial City | C2: =INDEX('Plant data'!E:E,MATCH($A2,'Plant data'!$A:$A,0)) -> Abu Dhabi | D2: =INDEX('Plant data'!F:F,MATCH($A2,'Plant data'!$A:$A,0)) -> United Arab Emirates | E2: U100000144022 | F2: EAF SMP-1 | G2: https://www.gem.wiki/Emsteel_Abu_Dhabi_plant | H2: operating | I2: unknown | J2: unknown | K2: unknown | L2: unknown | M2: unknown | N2: unknown | O2: unknown | P2: 1200 | Q2: 150 | R2: Yes | S2: =IFERROR(K2+40,"")
A3: P100000120001 | B3: =INDEX('Plant data'!D:D,MATCH($A3,'Plant data'!$A:$A,0)) -> Abu Dhabi Industrial City | C3: =INDEX('Plant data'!E:E,MATCH($A3,'Plant data'!$A:$A,0)) -> Abu Dhabi | D3: =INDEX('Plant data'!F:F,MATCH($A3,'Plant data'!$A:$A,0)) -> United Arab Emirates | E3: U100000144023 | F3: EAF SMP-2 | G3: https://www.gem.wiki/Emsteel_Abu_Dhabi_plant | H3: operating | I3: unknown | J3: unknown | K3: unknown | L3: unknown | M3: unknown | N3: unknown | O3: unknown | P3: 1200 | Q3: unknown | R3: Yes | S3: =IFERROR(K3+40,"")
A4: P100000120001 | B4: =INDEX('Plant data'!D:D,MATCH($A4,'Plant data'!$A:$A,0)) -> Abu Dhabi Industrial City | C4: =INDEX('Plant data'!E:E,MATCH($A4,'Plant data'!$A:$A,0)) -> Abu Dhabi | D4: =INDEX('Plant data'!F:F,MATCH($A4,'Plant data'!$A:$A,0)) -> United Arab Emirates | E4: U100000144024 | F4: EAF SMP-3 | G4: https://www.gem.wiki/Emsteel_Abu_Dhabi_plant | H4: operating | I4: unknown | J4: unknown | K4: unknown | L4: unknown | M4: unknown | N4: unknown | O4: unknown | P4: 1200 | Q4: unknown | R4: Yes | S4: =IFERROR(K4+40,"")
A5: P100000120002 | B5: =INDEX('Plant data'!D:D,MATCH($A5,'Plant data'!$A:$A,0)) -> Musaffah Industrial Zone | C5: =INDEX('Plant data'!E:E,MATCH($A5,'Plant data'!$A:$A,0)) -> Abu Dhabi | D5: =INDEX('Plant data'!F:F,MATCH($A5,'Plant data'!$A:$A,0)) -> United Arab Emirates | E5: U100000144945 | F5: unknown EAF (1) | G5: https://www.gem.wiki/BILDCO_Abu_Dhabi_steel_plant | H5: cancelled | I5: unknown | J5: unknown | K5: unknown | L5: unknown | M5: unknown | N5: unknown | O5: unknown | P5: 1000 | Q5: unknown | R5: unknown | S5: =IFERROR(K5+40,"")
A6: P100000120004 | B6: =INDEX('Plant data'!D:D,MATCH($A6,'Plant data'!$A:$A,0)) -> Bradashesh | C6: =INDEX('Plant data'!E:E,MATCH($A6,'Plant data'!$A:$A,0)) -> Elbasan | D6: =INDEX('Plant data'!F:F,MATCH($A6,'Plant data'!$A:$A,0)) -> Albania | E6: U100000144025 | F6: unknown EAF (1) | G6: https://www.gem.wiki/Kurum_International_Elbasan_steel_plant | H6: mothballed | I6: unknown | J6: unknown | K6: 2010 | L6: 15 | M6: unknown | N6: 45505 | O6: unknown | P6: 700 | Q6: unknown | R6: Yes | S6: =IFERROR(K6+40,"") -> 2050
A7: P100000120006 | B7: =INDEX('Plant data'!D:D,MATCH($A7,'Plant data'!$A:$A,0)) -> Villa Constitución | C7: =INDEX('Plant data'!E:E,MATCH($A7,'Plant data'!$A:$A,0)) -> Santa Fe | D7: =INDEX('Plant data'!F:F,MATCH($A7,'Plant data'!$A:$A,0)) -> Argentina | E7: U100000144026 | F7: EAF 1 | G7: https://www.gem.wiki/ArcelorMittal_Acindar_Villa_Constitución_steel_plant | H7: operating | I7: unknown | J7: unknown | K7: 2007 | L7: 18 | M7: unknown | N7: unknown | O7: unknown | P7: 1000 | Q7: 110 | R7: Yes | S7: =IFERROR(K7+40,"") -> 2047
A8: P100000120006 | B8: =INDEX('Plant data'!D:D,MATCH($A8,'Plant data'!$A:$A,0)) -> Villa Constitución | C8: =INDEX('Plant data'!E:E,MATCH($A8,'Plant data'!$A:$A,0)) -> Santa Fe | D8: =INDEX('Plant data'!F:F,MATCH($A8,'Plant data'!$A:$A,0)) -> Argentina | E8: U100000144027 | F8: EAF 2 | G8: https://www.gem.wiki/ArcelorMittal_Acindar_Villa_Constitución_steel_plant | H8: operating | I8: unknown | J8: unknown | K8: 2007 | L8: 18 | M8: unknown | N8: unknown | O8: unknown | P8: 1000 | Q8: 110 | R8: Yes | S8: =IFERROR(K8+40,"") -> 2047
A9: P100000120007 | B9: =INDEX('Plant data'!D:D,MATCH($A9,'Plant data'!$A:$A,0)) -> Campana | C9: =INDEX('Plant data'!E:E,MATCH($A9,'Plant data'!$A:$A,0)) -> Buenos Aires | D9: =INDEX('Plant data'!F:F,MATCH($A9,'Plant data'!$A:$A,0)) -> Argentina | E9: U100000144028 | F9: EAF 4 | G9: https://www.gem.wiki/TenarisSiderca_Campana_steel_plant | H9: retired | I9: unknown | J9: unknown | K9: unknown | L9: unknown | M9: 2023 | N9: unknown | O9: 45505 | P9: 530 | Q9: unknown | R9: Yes | S9: =IFERROR(K9+40,"")
A10: P100000120007 | B10: =INDEX('Plant data'!D:D,MATCH($A10,'Plant data'!$A:$A,0)) -> Campana | C10: =INDEX('Plant data'!E:E,MATCH($A10,'Plant data'!$A:$A,0)) -> Buenos Aires | D10: =INDEX('Plant data'!F:F,MATCH($A10,'Plant data'!$A:$A,0)) -> Argentina | E10: U100000141478 | F10: EAF 5 | G10: https://www.gem.wiki/TenarisSiderca_Campana_steel_plant | H10: operating | I10: unknown | J10: unknown | K10: unknown | L10: unknown | M10: unknown | N10: unknown | O10: unknown | P10: 770 | Q10: unknown | R10: Yes | S10: =IFERROR(K10+40,"")
A11: P100000120007 | B11: =INDEX('Plant data'!D:D,MATCH($A11,'Plant data'!$A:$A,0)) -> Campana | C11: =INDEX('Plant data'!E:E,MATCH($A11,'Plant data'!$A:$A,0)) -> Buenos Aires | D11: =INDEX('Plant data'!F:F,MATCH($A11,'Plant data'!$A:$A,0)) -> Argentina | E11: U100001027806 | F11: EAF 6 | G11: https://www.gem.wiki/TenarisSiderca_Campana_steel_plant | H11: operating | I11: 45006 | J11: unknown | K11: 2024 | L11: 1 | M11: unknown | N11: unknown | O11: unknown | P11: 950 | Q11: unknown | R11: Yes | S11: =IFERROR(K11+40,"") -> 2064
A12: P100000120009 | B12: =INDEX('Plant data'!D:D,MATCH($A12,'Plant data'!$A:$A,0)) -> Pérez | C12: =INDEX('Plant data'!E:E,MATCH($A12,'Plant data'!$A:$A,0)) -> Santa Fe | D12: =INDEX('Plant data'!F:F,MATCH($A12,'Plant data'!$A:$A,0)) -> Argentina | E12: U100000141479 | F12: unknown EAF (1) | G12: https://www.gem.wiki/Gerdau_Sipar_Pérez_steel_plant | H12: operating | I12: unknown | J12: unknown | K12: 2017 | L12: 8 | M12: unknown | N12: unknown | O12: unknown | P12: 650 | Q12: 75 | R12: Yes | S12: =IFERROR(K12+40,"") -> 2057
A13: P100000120010 | B13: =INDEX('Plant data'!D:D,MATCH($A13,'Plant data'!$A:$A,0)) -> Linz | C13: =INDEX('Plant data'!E:E,MATCH($A13,'Plant data'!$A:$A,0)) -> Upper Austria | D13: =INDEX('Plant data'!F:F,MATCH($A13,'Plant data'!$A:$A,0)) -> Austria | E13: U100000141480 | F13: unknown EAF (1) | G13: https://www.gem.wiki/Voestalpine_Stahl_Linz_steel_plant | H13: construction | I13: 2023 | J13: 2024 | K13: 2027 | M13: unknown | N13: unknown | O13: unknown | P13: 1600 | Q13: 180 | R13: Yes | S13: =IFERROR(K13+40,"") -> 2067
A14: P100000120011 | B14: =INDEX('Plant data'!D:D,MATCH($A14,'Plant data'!$A:$A,0)) -> Leoben | C14: =INDEX('Plant data'!E:E,MATCH($A14,'Plant data'!$A:$A,0)) -> Styria | D14: =INDEX('Plant data'!F:F,MATCH($A14,'Plant data'!$A:$A,0)) -> Austria | E14: U100000141481 | F14: unknown EAF (1) | G14: https://www.gem.wiki/Voestalpine_Stahl_Donawitz_steel_plant | H14: construction | I14: 2023 | J14: 2024 | K14: 2027 | M14: unknown | N14: unknown | O14: unknown | P14: 850 | Q14: 65 | R14: Yes | S14: =IFERROR(K14+40,"") -> 2067
A15: P100000120011 | B15: =INDEX('Plant data'!D:D,MATCH($A15,'Plant data'!$A:$A,0)) -> Leoben | C15: =INDEX('Plant data'!E:E,MATCH($A15,'Plant data'!$A:$A,0)) -> Styria | D15: =INDEX('Plant data'!F:F,MATCH($A15,'Plant data'!$A:$A,0)) -> Austria | E15: U100000144755 | F15: unknown EAF (2) | G15: https://www.gem.wiki/Voestalpine_Stahl_Donawitz_steel_plant | H15: construction | I15: 2023 | J15: 45170 | K15: 2027 | M15: unknown | N15: unknown | O15: unknown | P15: 850 | Q15: 65 | R15: Yes | S15: =IFERROR(K15+40,"") -> 2067
A16: P100000120013 | B16: =INDEX('Plant data'!D:D,MATCH($A16,'Plant data'!$A:$A,0)) -> Whyalla | C16: =INDEX('Plant data'!E:E,MATCH($A16,'Plant data'!$A:$A,0)) -> South Australia | D16: =INDEX('Plant data'!F:F,MATCH($A16,'Plant data'!$A:$A,0)) -> Australia | E16: U100000141482 | F16: unknown EAF (1) | G16: https://www.gem.wiki/GFG_Liberty_Steel_Australia_Whyalla_steel_plant | H16: announced | I16: 2020 | J16: 2025 | K16: 2027 | M16: unknown | N16: unknown | O16: unknown | P16: 1500 | Q16: 160 | R16: Yes | S16: =IFERROR(K16+40,"") -> 2067
A17: P100000120014 | B17: =INDEX('Plant data'!D:D,MATCH($A17,'Plant data'!$A:$A,0)) -> Laverton | C17: =INDEX('Plant data'!E:E,MATCH($A17,'Plant data'!$A:$A,0)) -> Victoria | D17: =INDEX('Plant data'!F:F,MATCH($A17,'Plant data'!$A:$A,0)) -> Australia | E17: U100000141483 | F17: unknown EAF (1) | G17: https://www.gem.wiki/GFG_Liberty_Laverton_Steel_Mill | H17: operating | I17: unknown | J17: unknown | K17: unknown | L17: unknown | M17: unknown | N17: unknown | O17: unknown | P17: 780 | Q17: 83 | R17: Yes | S17: =IFERROR(K17+40,"")
A18: P100000120015 | B18: =INDEX('Plant data'!D:D,MATCH($A18,'Plant data'!$A:$A,0)) -> Rooty Hill | C18: =INDEX('Plant data'!E:E,MATCH($A18,'Plant data'!$A:$A,0)) -> New South Wales | D18: =INDEX('Plant data'!F:F,MATCH($A18,'Plant data'!$A:$A,0)) -> Australia | E18: U100000141484 | F18: unknown EAF (1) | G18: https://www.gem.wiki/GFG_Liberty_Sydney_Steel_Mill | H18: operating | I18: unknown | J18: unknown | K18: unknown | L18: unknown | M18: unknown | N18: unknown | O18: unknown | P18: 750 | Q18: 84 | R18: Yes | S18: =IFERROR(K18+40,"")
A19: P100000120016 | B19: =INDEX('Plant data'!D:D,MATCH($A19,'Plant data'!$A:$A,0)) -> Baku | C19: =INDEX('Plant data'!E:E,MATCH($A19,'Plant data'!$A:$A,0)) -> Narimanov | D19: =INDEX('Plant data'!F:F,MATCH($A19,'Plant data'!$A:$A,0)) -> Azerbaijan | E19: U100000141485 | F19: EAF 1 | G19: https://www.gem.wiki/Baku_Steel_Company_steel_plant | H19: operating | I19: unknown | J19: unknown | K19: 2013 | L19: 12 | M19: unknown | N19: unknown | O19: unknown | P19: 534 | Q19: 60 | R19: Yes | S19: =IFERROR(K19+40,"") -> 2053
A20: P100000120016 | B20: =INDEX('Plant data'!D:D,MATCH($A20,'Plant data'!$A:$A,0)) -> Baku | C20: =INDEX('Plant data'!E:E,MATCH($A20,'Plant data'!$A:$A,0)) -> Narimanov | D20: =INDEX('Plant data'!F:F,MATCH($A20,'Plant data'!$A:$A,0)) -> Azerbaijan | E20: U100000141486 | F20: EAF 2 | G20: https://www.gem.wiki/Baku_Steel_Company_steel_plant | H20: operating | I20: unknown | J20: unknown | K20: unknown | L20: unknown | M20: unknown | N20: unknown | O20: unknown | P20: 266 | Q20: 30 | R20: Yes | S20: =IFERROR(K20+40,"")
A21: P100000120017 | B21: =INDEX('Plant data'!D:D,MATCH($A21,'Plant data'!$A:$A,0)) -> Zenica | C21: =INDEX('Plant data'!E:E,MATCH($A21,'Plant data'!$A:$A,0)) -> Zenica-Doboj | D21: =INDEX('Plant data'!F:F,MATCH($A21,'Plant data'!$A:$A,0)) -> Bosnia and Herzegovina | E21: U100000141487 | F21: unknown EAF (1) | G21: https://www.gem.wiki/ArcelorMittal_Zenica_steel_plant | H21: operating | I21: unknown | J21: unknown | K21: 2005 | L21: 20 | M21: unknown | N21: unknown | O21: unknown | P21: 800 | Q21: 100 | R21: Yes | S21: =IFERROR(K21+40,"") -> 2045
A22: P100000120018 | B22: =INDEX('Plant data'!D:D,MATCH($A22,'Plant data'!$A:$A,0)) -> Kumira | C22: =INDEX('Plant data'!E:E,MATCH($A22,'Plant data'!$A:$A,0)) -> Chittagong | D22: =INDEX('Plant data'!F:F,MATCH($A22,'Plant data'!$A:$A,0)) -> Bangladesh | E22: U100000141488 | F22: unknown EAF (1) | G22: https://www.gem.wiki/GPH_Steel_Sitakunda_plant | H22: operating | I22: 2016 | J22: 2017 | K22: 2021 | L22: 4 | M22: unknown | N22: unknown | O22: unknown | P22: 840 | Q22: 80 | R22: Yes | S22: =IFERROR(K22+40,"") -> 2061
A23: P100000120019 | B23: =INDEX('Plant data'!D:D,MATCH($A23,'Plant data'!$A:$A,0)) -> Mirsarai | C23: =INDEX('Plant data'!E:E,MATCH($A23,'Plant data'!$A:$A,0)) -> Chittagong | D23: =INDEX('Plant data'!F:F,MATCH($A23,'Plant data'!$A:$A,0)) -> Bangladesh | E23: U100000141489 | F23: unknown EAF (1) | G23: https://www.gem.wiki/Bashundhara_Steel_Mirsarai_plant | H23: construction | I23: unknown | J23: 2021 | K23: 2026 | M23: unknown | N23: unknown | O23: unknown | P23: 1250 | Q23: 100 | R23: Yes | S23: =IFERROR(K23+40,"") -> 2066
A24: P100000120020 | B24: =INDEX('Plant data'!D:D,MATCH($A24,'Plant data'!$A:$A,0)) -> Sitakunda | C24: =INDEX('Plant data'!E:E,MATCH($A24,'Plant data'!$A:$A,0)) -> Chittagong | D24: =INDEX('Plant data'!F:F,MATCH($A24,'Plant data'!$A:$A,0)) -> Bangladesh | E24: U100000141490 | F24: unknown EAF (1) | G24: https://www.gem.wiki/Abul_Khair_Steel_Sitakunda_plant | H24: operating | I24: unknown | J24: unknown | K24: 2015 | L24: 10 | M24: unknown | N24: unknown | O24: unknown | P24: 700 | Q24: unknown | R24: Yes | S24: =IFERROR(K24+40,"") -> 2055
A25: P100000120020 | B25: =INDEX('Plant data'!D:D,MATCH($A25,'Plant data'!$A:$A,0)) -> Sitakunda | C25: =INDEX('Plant data'!E:E,MATCH($A25,'Plant data'!$A:$A,0)) -> Chittagong | D25: =INDEX('Plant data'!F:F,MATCH($A25,'Plant data'!$A:$A,0)) -> Bangladesh | E25: U100001048537 | F25: unknown EAF (2) | G25: https://www.gem.wiki/Abul_Khair_Steel_Sitakunda_plant | H25: operating | I25: unknown | J25: unknown | K25: 2015 | L25: 10 | M25: unknown | N25: unknown | O25: unknown | P25: 700 | Q25: unknown | R25: Yes | S25: =IFERROR(K25+40,"") -> 2055
A26: P100000120024 | B26: =INDEX('Plant data'!D:D,MATCH($A26,'Plant data'!$A:$A,0)) -> Sitakunda | C26: =INDEX('Plant data'!E:E,MATCH($A26,'Plant data'!$A:$A,0)) -> Chittagong | D26: =INDEX('Plant data'!F:F,MATCH($A26,'Plant data'!$A:$A,0)) -> Bangladesh | E26: U100000144259 | F26: unknown EAF (1) | G26: https://www.gem.wiki/KSRM_Sitakunda_steel_plant | H26: operating | I26: unknown | J26: unknown | K26: unknown | L26: unknown | M26: unknown | N26: unknown | O26: unknown | P26: 400 | Q26: unknown | R26: Yes | S26: =IFERROR(K26+40,"")
