Workbook

Sheet About
A1: BEbIC BAU Employment by ISIC Code
A3: Sources: | B3: Nonfarm employment by industry (2024)
B4: U.S. Bureau of Labor Statistics
B5: Current Employment Statistics, Table B-1a
B6: 2024
B7: https://www.bls.gov/ces/data/employment-and-earnings/2024/table1a_2024
B8: Tab 'BLS Employment', pasted verbatim from the stock workbook including its hand-split blocks (CES categories straddling ISIC boundaries, split by gross output). Column A holds the editable ISIC assignment; rows under the six split parents are re-labeled to their 52-code children by NAICS (column C). NAICS 5415 computer systems design is assigned to ISIC 62T63 (consistent deviation).
B10: Farm-sector employment (incl. self-employed)
B11: U.S. Bureau of Labor Statistics
B12: CPS, Table cpsaat15 (cell B5 of the BLS Employment tab)
B13: 2024
B14: https://www.bls.gov/cps/cpsaat15.htm
B15: Added to agriculture and split ISIC 01/02/03 by BLS Table 2.11 matrix shares of farming (111+112) / forestry (1131-2) / fishing (114000) — tab 'BLS 2.11 ag excerpt'. CES rows already cover logging and agricultural support.
B17: Private household employment
B18: IPUMS SDA (2024 ACS)
B19: empstat x ind crosstab (cell B9 of the BLS Employment tab)
B20: 2024
B21: https://sda.usa.ipums.org/sdaweb/analysis/?dataset=all_usa_samples
B22: Added to ISIC 97T98.
A25: Notes:
A26: Export | B26: BEbIC.csv = tab BEbIC values; canonical 52-code column order (positional Vensim read).

Sheet BLS Employment
A2: Other data
B4: ISIC 01T03 | C4: agriculture and related activities
B5: 2254000
B6: https://www.bls.gov/cps/cpsaat15.htm | C6: accessed 1/8/26
B8: ISIC 97T98 | C8: private households
B9: 608254
B10: https://sda.usa.ipums.org/sdaweb/analysis/?dataset=all_usa_samples
A13: Data split to assign to proper EPS ISIC Categories
A14: uses gross output data from io-model/BObIC
B16: Other miscellaneous nondurable goods manufacturing(1) | C16: 3122,60 | D16: 36.2 | E16: 35.2 | F16: 35.4 | G16: 35 | H16: 35.6 | I16: - | J16: -
A18: 312200 | B18: Tobacco manufacturing | C18: 69178 | D18: ISIC 10T12 | F18: 0.87351474 | G18: ISIC 10T12
A19: 316000 | B19: Leather and allied product manufacturing | C19: 10017 | D19: ISIC 13T15 | F19: 0.12648526 | G19: ISIC 13T15
A21: ISIC 10T12 | D21: 31.621234 | E21: 30.747719 | F21: 30.922422 | G21: 30.573016 | H21: 31.097125
A22: ISIC 13T15 | D22: 4.5787663 | E22: 4.4522811 | F22: 4.4775781 | G22: 4.426984 | H22: 4.5028752
B24: Asphalt paving, roofing, saturated materials, and other petroleum and coal products manufacturing(1) | C24: 32412,9 | D24: 46.8 | E24: 45.9 | F24: 46.1 | G24: 45.8 | H24: 45.8 | I24: - | J24: -
A26: 324121 | B26: Asphalt paving mixture and block manufacturing | C26: 18352 | D26: ISIC 19 | F26: 0.57650226 | G26: ISIC 19
A27: 324122 | B27: Asphalt shingle and coating materials manufacturing | C27: 15265 | D27: ISIC 19 | F27: 0.42349774 | G27: ISIC 241
A28: 324190 | B28: Other petroleum and coal products manufacturing | C28: 24695 | D28: ISIC 241
A30: ISIC 19 | D30: 26.980306 | E30: 26.461454 | F30: 26.576754 | G30: 26.403804 | H30: 26.403804
A31: ISIC 241 | D31: 19.819694 | E31: 19.438546 | F31: 19.523246 | G31: 19.396196 | H31: 19.396196
A34: All data from BLS
B36: ESTABLISHMENT DATA | C36: https://www.bls.gov/ces/data/employment-and-earnings/2024/table1a_202411.htm
B37: Table B-1a. Employees on nonfarm payrolls by industry sector and selected industry detail, seasonally adjusted
B38: [In thousands]
B39: Industry | C39: 2022 NAICS code | D39: Seasonally adjusted | J39: Change from:
D40: Nov. | E40: July | F40: Aug. | G40: Sept. | H40: Oct. | I40: Nov. | J40: Oct. 2024 - Nov. 2024(p)
D41: 2023 | E41: 2024 | F41: 2024 | G41: 2024 | H41: 2024(p) | I41: 2024(p)
B42: Total nonfarm | D42: 157014 | E42: 158692 | F42: 158770 | G42: 159025 | H42: 159061 | I42: 159288 | J42: 227
B44: Total private | D44: 134014 | E44: 135347 | F44: 135384 | G44: 135606 | H44: 135604 | I44: 135798 | J44: 194
B46: Goods-producing | D46: 21690 | E46: 21833 | F46: 21835 | G46: 21850 | H46: 21806 | I46: 21840 | J46: 34
B48: Mining and logging | D48: 640 | E48: 635 | F48: 635 | G48: 636 | H48: 638 | I48: 640 | J48: 2
A49: ISIC 02 | B49: Logging | C49: 1133 | D49: 43.4 | E49: 38.5 | F49: 38 | G49: 38.2 | H49: 38.2 | I49: 38.2 | J49: 0
B50: Mining, quarrying, and oil and gas extraction | C50: 21 | D50: 596.2 | E50: 596.7 | F50: 596.7 | G50: 598.2 | H50: 599.3 | I50: 601.5 | J50: 2.2
A51: ISIC 06 | B51: Oil and gas extraction | C51: 211 | D51: 117.4 | E51: 120 | F51: 119 | G51: 119.6 | H51: 119.6 | I51: 119.7 | J51: 0.1
B52: Mining (except oil and gas) | C52: 212 | D52: 187.1 | E52: 188.8 | F52: 188.6 | G52: 189 | H52: 189.3 | I52: 190 | J52: 0.7
A53: ISIC 05 | B53: Coal mining | C53: 2121 | D53: 42.7 | E53: 43.6 | F53: 43.2 | G53: 43.2 | H53: 42.8 | I53: 43.4 | J53: 0.6
B54: Surface coal mining(1) | C54: 212114 | D54: 19.6 | E54: 19.7 | F54: 19.2 | G54: 19.1 | H54: 18.6 | I54: - | J54: -
B55: Underground coal mining(1) | C55: 212115 | D55: 23 | E55: 23.9 | F55: 23.9 | G55: 24 | H55: 24.2 | I55: - | J55: -
A56: ISIC 07 | B56: Metal ore mining | C56: 2122 | D56: 43.7 | E56: 43.5 | F56: 43.6 | G56: 43.6 | H56: 43.6 | I56: 43.7 | J56: 0.1
A57: ISIC 08 | B57: Nonmetallic mineral mining and quarrying | C57: 2123 | D57: 100.7 | E57: 101.7 | F57: 101.8 | G57: 102.3 | H57: 102.9 | I57: 102.9 | J57: 0
B58: Stone mining and quarrying(1) | C58: 21231 | D58: 44.5 | E58: 45.4 | F58: 45.6 | G58: 45.5 | H58: 45.6 | I58: - | J58: -
B59: Crushed and broken limestone mining and quarrying(1) | C59: 212312 | D59: 23 | E59: 23.6 | F59: 23.5 | G59: 23.5 | H59: 23.5 | I59: - | J59: -
B60: Dimension stone, crushed and broken granite, and other crushed and broken stone mining and quarrying(1) | C60: 212311,3,9 | D60: 21.3 | E60: 21.9 | F60: 22.1 | G60: 21.9 | H60: 22 | I60: - | J60: -
B61: Sand, gravel, clay, and ceramic and refractory minerals mining and quarrying(1) | C61: 21232 | D61: 44.2 | E61: 44 | F61: 43.4 | G61: 44.4 | H61: 44.3 | I61: - | J61: -
B62: Construction sand and gravel mining(1) | C62: 212321 | D62: 30 | E62: 29.1 | F62: 28.5 | G62: 29.2 | H62: 29.4 | I62: - | J62: -
B63: Other nonmetallic mineral mining and quarrying(1) | C63: 21239 | D63: 12.2 | E63: 12.4 | F63: 12.7 | G63: 12.6 | H63: 13 | I63: - | J63: -
A64: ISIC 09 | B64: Support activities for mining | C64: 213 | D64: 291.7 | E64: 287.9 | F64: 289.1 | G64: 289.6 | H64: 290.4 | I64: 291.8 | J64: 1.4
B65: Support activities for oil and gas operations(1) | C65: 213112 | D65: 228.4 | E65: 226.7 | F65: 227.3 | G65: 227.6 | H65: 228.8 | I65: - | J65: -
A67: ISIC 41T43 | B67: Construction | C67: 23 | D67: 8102 | E67: 8247 | F67: 8275 | G67: 8301 | H67: 8303 | I67: 8313 | J67: 10
B68: Construction of buildings | C68: 236 | D68: 1829.8 | E68: 1876.2 | F68: 1882.7 | G68: 1884.1 | H68: 1883.8 | I68: 1883.5 | J68: -0.3
B69: Residential building construction | C69: 2361 | D69: 931.4 | E69: 945.9 | F69: 951.6 | G69: 955.4 | H69: 956.2 | I69: 957.6 | J69: 1.4
B70: New single-family housing construction (except for-sale builders) | C70: 236115 | D70: 378.2 | E70: 386.7 | F70: 387.5 | G70: 388 | H70: 389 | I70: - | J70: -
B71: New multifamily housing construction (except for-sale builders) | C71: 236116 | D71: 48.5 | E71: 47.5 | F71: 47.1 | G71: 47.9 | H71: 48.1 | I71: - | J71: -
B72: New housing for-sale builders | C72: 236117 | D72: 53.8 | E72: 54.3 | F72: 54.8 | G72: 55 | H72: 55.5 | I72: - | J72: -
B73: Residential remodelers | C73: 236118 | D73: 450.9 | E73: 457.4 | F73: 462.2 | G73: 464.4 | H73: 463.7 | I73: - | J73: -
B74: Nonresidential building construction | C74: 2362 | D74: 898.4 | E74: 930.3 | F74: 931.1 | G74: 928.7 | H74: 927.6 | I74: 925.9 | J74: -1.7
B75: Industrial building construction | C75: 23621 | D75: 159.4 | E75: 166.4 | F75: 167.2 | G75: 169.4 | H75: 170.8 | I75: - | J75: -
B76: Commercial and institutional building construction | C76: 23622 | D76: 738.9 | E76: 763.9 | F76: 763.8 | G76: 759.3 | H76: 756.8 | I76: - | J76: -
B77: Heavy and civil engineering construction | C77: 237 | D77: 1131.5 | E77: 1141.3 | F77: 1152.5 | G77: 1160.8 | H77: 1159.8 | I77: 1161.3 | J77: 1.5
B78: Utility system construction(1) | C78: 2371 | D78: 582.4 | E78: 583.7 | F78: 593.4 | G78: 596.6 | H78: 596.9 | I78: - | J78: -
B79: Water and sewer line and related structures construction(1) | C79: 23711 | D79: 204.3 | E79: 206.1 | F79: 206.5 | G79: 208.1 | H79: 208.5 | I79: - | J79: -
B80: Oil and gas pipeline and related structures construction(1) | C80: 23712 | D80: 139.9 | E80: 141.4 | F80: 146.6 | G80: 147.8 | H80: 149.3 | I80: - | J80: -
B81: Power and communication line and related structures construction(1) | C81: 23713 | D81: 238.4 | E81: 238.3 | F81: 241.4 | G81: 240.2 | H81: 239.1 | I81: - | J81: -
B82: Land subdivision(1) | C82: 2372 | D82: 40 | E82: 40.8 | F82: 40.5 | G82: 40.3 | H82: 40.1 | I82: - | J82: -
B83: Highway, street, and bridge construction(1) | C83: 2373 | D83: 379.8 | E83: 382.5 | F83: 384.2 | G83: 385.9 | H83: 386.2 | I83: - | J83: -
B84: Other heavy and civil engineering construction(1) | C84: 2379 | D84: 131.4 | E84: 134.2 | F84: 134.2 | G84: 134.9 | H84: 135.2 | I84: - | J84: -
B85: Specialty trade contractors | C85: 238 | D85: 5140.3 | E85: 5229.7 | F85: 5239.3 | G85: 5256.2 | H85: 5259.4 | I85: 5268.1 | J85: 8.7
B86: Residential specialty trade contractors | C86: part 238 | D86: 2390 | E86: 2416.6 | F86: 2414.3 | G86: 2421.5 | H86: 2414.5 | I86: 2416.2 | J86: 1.7
B87: Nonresidential specialty trade contractors | C87: part 238 | D87: 2750.3 | E87: 2813.1 | F87: 2825 | G87: 2834.7 | H87: 2844.9 | I87: 2851.9 | J87: 7
B88: Foundation, structure, and building exterior contractors(1) | C88: 2381 | D88: 1003.5 | E88: 998.3 | F88: 999.3 | G88: 1002.4 | H88: 999.8 | I88: - | J88: -
B89: Poured concrete foundation and structure contractors | C89: 23811 | D89: 253.1 | E89: 249.8 | F89: 250.3 | G89: 251 | H89: 249.3 | I89: - | J89: -
B90: Structural steel and precast concrete contractors | C90: 23812 | D90: 83.5 | E90: 84 | F90: 83.4 | G90: 82.9 | H90: 81.9 | I90: - | J90: -
B91: Framing contractors | C91: 23813 | D91: 85.8 | E91: 81.1 | F91: 82.4 | G91: 80.9 | H91: 81.3 | I91: - | J91: -
B92: Masonry contractors | C92: 23814 | D92: 146.6 | E92: 151.7 | F92: 150.4 | G92: 151.2 | H92: 152.5 | I92: - | J92: -
B93: Glass and glazing contractors | C93: 23815 | D93: 75.9 | E93: 72.5 | F93: 72.8 | G93: 74.2 | H93: 74 | I93: - | J93: -
B94: Roofing contractors | C94: 23816 | D94: 250.5 | E94: 256.1 | F94: 255 | G94: 258.1 | H94: 255.9 | I94: - | J94: -
B95: Siding contractors | C95: 23817 | D95: 42.4 | E95: 41.5 | F95: 41 | G95: 41.2 | H95: 41 | I95: - | J95: -
B96: Other foundation, structure, and building exterior contractors | C96: 23819 | D96: 63.7 | E96: 62.5 | F96: 63.6 | G96: 64 | H96: 64.6 | I96: - | J96: -
B97: Building equipment contractors(1) | C97: 2382 | D97: 2519.2 | E97: 2583.7 | F97: 2588.1 | G97: 2590.5 | H97: 2593.3 | I97: - | J97: -
B98: Electrical contractors and other wiring installation contractors | C98: 23821 | D98: 1088.1 | E98: 1112.1 | F98: 1111.5 | G98: 1112.4 | H98: 1115.6 | I98: - | J98: -
B99: Plumbing, heating, and air-conditioning contractors | C99: 23822 | D99: 1276 | E99: 1308.7 | F99: 1315.1 | G99: 1315.4 | H99: 1316 | I99: - | J99: -
... B110: All other specialty trade contractors | C110: 23899 | D110: 388.1 | E110: 406.2 | F110: 408.5 | G110: 409.9 | H110: 411.2 | I110: - | J110: -
B112: Manufacturing | D112: 12948 | E112: 12951 | F112: 12925 | G112: 12913 | H112: 12865 | I112: 12887 | J112: 22
B114: Durable goods | D114: 8129 | E114: 8130 | F114: 8100 | G114: 8096 | H114: 8052 | I114: 8078 | J114: 26
A115: ISIC 16 | B115: Wood product manufacturing | C115: 321 | D115: 415.1 | E115: 416.3 | F115: 414.6 | G115: 413.6 | H115: 412.8 | I115: 412.5 | J115: -0.3
B116: Sawmills and wood preservation(1) | C116: 3211 | D116: 89.9 | E116: 88.7 | F116: 88 | G116: 87.5 | H116: 87.5 | I116: - | J116: -
B117: Veneer, plywood, and engineered wood product manufacturing(1) | C117: 3212 | D117: 83 | E117: 82.3 | F117: 82 | G117: 81.9 | H117: 81 | I117: - | J117: -
B118: Other wood product manufacturing(1) | C118: 3219 | D118: 242.1 | E118: 245.7 | F118: 245 | G118: 244 | H118: 244 | I118: - | J118: -
B119: Millwork(1) | C119: 32191 | D119: 102 | E119: 102.2 | F119: 102.2 | G119: 101.4 | H119: 101.9 | I119: - | J119: -
B120: Wood window and door manufacturing(1) | C120: 321911 | D120: 56.9 | E120: 56.4 | F120: 56.6 | G120: 56.6 | H120: 56.5 | I120: - | J120: -
B121: Cut stock, resawing lumber, planing, and other millwork (including flooring)(1) | C121: 321912,8 | D121: 45.1 | E121: 45.9 | F121: 45.6 | G121: 44.8 | H121: 45.4 | I121: - | J121: -
B122: Wood container and pallet manufacturing(1) | C122: 32192 | D122: 64.5 | E122: 65.7 | F122: 65.5 | G122: 64.5 | H122: 64.7 | I122: - | J122: -
B123: All other wood product manufacturing(1) | C123: 32199 | D123: 75.7 | E123: 77.7 | F123: 77 | G123: 77.3 | H123: 77.2 | I123: - | J123: -
B124: Nonmetallic mineral product manufacturing | C124: 327 | D124: 422.5 | E124: 423.3 | F124: 423 | G124: 424.8 | H124: 428.2 | I124: 426.7 | J124: -1.5
A125: ISIC 239 | B125: Clay product and refractory manufacturing(1) | C125: 3271 | D125: 35.5 | E125: 35.6 | F125: 35.6 | G125: 35.5 | H125: 35.5 | I125: - | J125: -
A126: ISIC 231 | B126: Glass and glass product manufacturing(1) | C126: 3272 | D126: 81.7 | E126: 78.9 | F126: 77.4 | G126: 77.6 | H126: 78.2 | I126: - | J126: -
A127: ISIC 239 | B127: Cement and concrete product manufacturing(1) | C127: 3273 | D127: 206.9 | E127: 207.1 | F127: 206.7 | G127: 208.2 | H127: 209.5 | I127: - | J127: -
B128: Ready-mix concrete manufacturing(1) | C128: 32732 | D128: 106.1 | E128: 107.4 | F128: 106.8 | G128: 107.1 | H128: 107.5 | I128: - | J128: -
B129: Cement and concrete pipe, brick, block, and other concrete product manufacturing(1) | C129: 32731,3,9 | D129: 100.9 | E129: 99.7 | F129: 100.1 | G129: 101.3 | H129: 102.1 | I129: - | J129: -
A130: ISIC 239 | B130: Lime, gypsum, and other nonmetallic mineral product manufacturing(1) | C130: 3274,9 | D130: 97.9 | E130: 101.7 | F130: 103.2 | G130: 103.5 | H130: 105.1 | I130: - | J130: -
...

Sheet BLS 2.11 ag excerpt
A1: BLS Employment Projections Table 2.11 (2024 matrix) — agriculture-block employment, for splitting the CPS farm-sector total across ISIC 01/02/03 (CES rows already cover logging & ag support)
A2: Matrix code | B2: Industry | C2: Employment 2024 (000s)
A3: 111000 | B3: Crop production | C3: 863.9
A4: 112000 | B4: Animal production and aquaculture | C4: 442.4
A5: 1131-2 | B5: Forestry | C5: 7
A6: 114000 | B6: Fishing, hunting and trapping | C6: 20.9
A9: Share to ISIC 01 (farming) | B9: =($C$3+$C$4)/($C$3+$C$4+$C$5+$C$6)
A10: Share to ISIC 02 (forestry) | B10: =$C$5/($C$3+$C$4+$C$5+$C$6)
A11: Share to ISIC 03 (fishing) | B11: =$C$6/($C$3+$C$4+$C$5+$C$6)
A13: Transport modes (for splitting the CES 'Transportation and warehousing' supersector row)
A14: 482000 | C14: 156.4
A15: 484000 | C15: 1522.1
A16: 485000 | C16: 472.6
A17: 483000 | C17: 70
A18: 481000 | C18: 564.4
A19: 48A000 | C19: 0
A20: 493000 | C20: 1849.1
A21: 492000 | C21: 1096.4
A22: 486000 | C22: 55.4
A23: Share to ISIC 49 | B23: =($C$14+$C$15+$C$16)/($C$14+$C$15+$C$16+$C$17+$C$18+$C$19+$C$20+$C$21+$C$22)
A24: Share to ISIC 50 | B24: =($C$17)/($C$14+$C$15+$C$16+$C$17+$C$18+$C$19+$C$20+$C$21+$C$22)
A25: Share to ISIC 51 | B25: =($C$18)/($C$14+$C$15+$C$16+$C$17+$C$18+$C$19+$C$20+$C$21+$C$22)
A26: Share to ISIC 52 | B26: =($C$19+$C$20)/($C$14+$C$15+$C$16+$C$17+$C$18+$C$19+$C$20+$C$21+$C$22)
A27: Share to ISIC 53 | B27: =($C$21)/($C$14+$C$15+$C$16+$C$17+$C$18+$C$19+$C$20+$C$21+$C$22)
A28: Share to ISIC 352T353 | B28: =($C$22)/($C$14+$C$15+$C$16+$C$17+$C$18+$C$19+$C$20+$C$21+$C$22)

Sheet BLS Table 2.11
A1: Table 2.11 Employment and output by industry (Employment in thousands; Output in billion of chained 2017 dollars)
A2: 2024 National Employment Matrix title | B2: 2024 National Employment Matrix code | C2: Industry type | D2: Employment, 2024 | E2: Employment, 2034 | F2: Employment change, numeric, 2024–34 | G2: Employment change, percent, 2024–34 | H2: Compound annual rate of change, employment, 2024–34 | I2: Output, 2024 | J2: Output, 2034 | K2: Compound annual rate of change, output, 2024–34 | L2: Assigned ISIC Code (editable)
A3: Total, all industries | B3: TE1000 | C3: Summary | D3: 169956.1 | E3: 175167.9 | F3: 5211.8 | G3: 3.1 | H3: 0.3 | I3: 40174.8 | J3: 48622.4 | K3: 1.9
A4: Self-employed workers | B4: TE1100 | C4: Line item | D4: 9906.4 | E4: 10122.8 | F4: 216.4 | G4: 2.2 | H4: 0.2 | I4: — | J4: — | K4: —
A5: Total wage and salary employment | B5: TE1200 | C5: Summary | D5: 160049.7 | E5: 165045.1 | F5: 4995.4 | G5: 3.1 | H5: 0.3 | I5: — | J5: — | K5: —
A6: Agriculture, forestry, fishing, and hunting | B6: 110000 | C6: Summary | D6: 1480.7 | E6: 1482.1 | F6: 1.4 | G6: 0.1 | H6: 0 | I6: 447.9 | J6: 538.8 | K6: 1.9
A7: Crop production | B7: 111000 | C7: Line item | D7: 863.9 | E7: 881.2 | F7: 17.3 | G7: 2 | H7: 0.2 | I7: 175.8 | J7: 201.8 | K7: 1.4 | L7: ISIC 01
A8: Animal production and aquaculture | B8: 112000 | C8: Line item | D8: 442.4 | E8: 427.6 | F8: -14.8 | G8: -3.3 | H8: -0.3 | I8: 220 | J8: 277.6 | K8: 2.4 | L8: ISIC 01
A9: Forestry and logging | B9: 113000 | C9: Summary | D9: 47.2 | E9: 45.1 | F9: -2.1 | G9: -4.4 | H9: -0.5 | I9: — | J9: — | K9: —
A10: Forestry | B10: 1131-2 | C10: Line item | D10: 7 | E10: 6.9 | F10: -0.1 | G10: -2 | H10: -0.1 | I10: 3.9 | J10: 4.6 | K10: 1.6 | L10: ISIC 02
A11: Logging | B11: 113300 | C11: Line item | D11: 40.2 | E11: 38.2 | F11: -2 | G11: -4.9 | H11: -0.5 | I11: 18.9 | J11: 22.1 | K11: 1.6 | L11: ISIC 02
A12: Fishing, hunting and trapping | B12: 114000 | C12: Line item | D12: 20.9 | E12: 20.8 | F12: -0.1 | G12: -0.3 | H12: 0 | I12: 7.4 | J12: 8.6 | K12: 1.5 | L12: ISIC 03
A13: Support activities for agriculture and forestry | B13: 115000 | C13: Line item | D13: 106.2 | E13: 107.3 | F13: 1.1 | G13: 1 | H13: 0.1 | I13: 23.6 | J13: 27.6 | K13: 1.6 | L13: ISIC 01
A14: Mining, quarrying, and oil and gas extraction | B14: 210000 | C14: Summary | D14: 586.1 | E14: 576.8 | F14: -9.3 | G14: -1.6 | H14: -0.2 | I14: 564.6 | J14: 634.5 | K14: 1.2
A15: Oil and gas extraction | B15: 211000 | C15: Line item | D15: 122.5 | E15: 115.7 | F15: -6.8 | G15: -5.5 | H15: -0.6 | I15: 383.8 | J15: 450.7 | K15: 1.6 | L15: ISIC 06
A16: Mining (except oil and gas) | B16: 212000 | C16: Summary | D16: 191.7 | E16: 182.6 | F16: -9.1 | G16: -4.7 | H16: -0.5 | I16: 92.8 | J16: 99.9 | K16: 0.7
A17: Coal mining | B17: 212100 | C17: Line item | D17: 42.5 | E17: 23.2 | F17: -19.3 | G17: -45.3 | H17: -5.9 | I17: 29.8 | J17: 24.6 | K17: -1.9 | L17: ISIC 05
A18: Metal ore mining | B18: 212200 | C18: Line item | D18: 44.9 | E18: 48.4 | F18: 3.5 | G18: 7.9 | H18: 0.8 | I18: 26 | J18: 33.5 | K18: 2.6 | L18: ISIC 07
A19: Nonmetallic mineral mining and quarrying | B19: 212300 | C19: Line item | D19: 104.3 | E19: 111 | F19: 6.7 | G19: 6.4 | H19: 0.6 | I19: 36.9 | J19: 41.5 | K19: 1.2 | L19: ISIC 08
A20: Support activities for mining | B20: 213000 | C20: Line item | D20: 271.9 | E20: 278.4 | F20: 6.5 | G20: 2.4 | H20: 0.2 | I20: 95.6 | J20: 90.6 | K20: -0.5 | L20: ISIC 09
A21: Utilities | B21: 220000 | C21: Summary | D21: 591.3 | E21: 620 | F21: 28.7 | G21: 4.9 | H21: 0.5 | I21: 507.1 | J21: 602.2 | K21: 1.7
A22: Utilities | B22: 221000 | C22: Summary | D22: 591.3 | E22: 620 | F22: 28.7 | G22: 4.9 | H22: 0.5 | I22: 507.1 | J22: 602.2 | K22: 1.7
A23: Electric power generation, transmission and distribution | B23: 221100 | C23: Summary | D23: 413.1 | E23: 445.6 | F23: 32.5 | G23: 7.9 | H23: 0.8 | I23: 411.4 | J23: 501.2 | K23: 2 | L23: ISIC 351
A24: Electric power generation | B24: 221110 | C24: Summary | D24: 157.3 | E24: 169.2 | F24: 11.9 | G24: 7.6 | H24: 0.7 | I24: — | J24: — | K24: —
A25: Hydroelectric power generation | B25: 221111 | C25: Line item | D25: 8.2 | E25: 8.2 | F25: 0 | G25: 0.4 | H25: 0 | I25: — | J25: — | K25: —
A26: Fossil fuel electric power generation | B26: 221112 | C26: Line item | D26: 74.5 | E26: 51.5 | F26: -23 | G26: -30.9 | H26: -3.6 | I26: — | J26: — | K26: —
A27: Nuclear electric power generation | B27: 221113 | C27: Line item | D27: 38.2 | E27: 31.5 | F27: -6.7 | G27: -17.6 | H27: -1.9 | I27: — | J27: — | K27: —
A28: Solar electric power generation | B28: 221114 | C28: Line item | D28: 16.9 | E28: 47.2 | F28: 30.4 | G28: 180.2 | H28: 10.8 | I28: — | J28: — | K28: —
A29: Wind electric power generation | B29: 221115 | C29: Line item | D29: 11.2 | E29: 20.4 | F29: 9.2 | G29: 81.4 | H29: 6.2 | I29: — | J29: — | K29: —
A30: Geothermal electric power generation | B30: 221116 | C30: Line item | D30: 1.2 | E30: 1.6 | F30: 0.5 | G30: 41.4 | H30: 2.9 | I30: — | J30: — | K30: —
A31: Biomass electric power generation | B31: 221117 | C31: Line item | D31: 2.4 | E31: 2.5 | F31: 0 | G31: 1.9 | H31: 0.4 | I31: — | J31: — | K31: —
A32: Other electric power generation | B32: 221118 | C32: Line item | D32: 4.7 | E32: 6.2 | F32: 1.5 | G32: 32.9 | H32: 2.8 | I32: — | J32: — | K32: —
A33: Natural gas distribution | B33: 221200 | C33: Line item | D33: 116.1 | E33: 112.4 | F33: -3.7 | G33: -3.2 | H33: -0.3 | I33: 80.4 | J33: 86.5 | K33: 0.7 | L33: ISIC 352T353
A34: Water, sewage and other systems | B34: 221300 | C34: Line item | D34: 62.1 | E34: 62 | F34: -0.1 | G34: -0.1 | H34: 0 | I34: 15.6 | J34: 16.3 | K34: 0.5 | L34: ISIC 36T39
A35: Construction | B35: 230000 | C35: Summary | D35: 8211.7 | E35: 8572.2 | F35: 360.5 | G35: 4.4 | H35: 0.4 | I35: 1720.9 | J35: 1874.7 | K35: 0.9 | L35: ISIC 41T43
A36: Construction of buildings | B36: 236000 | C36: Summary | D36: 1853.6 | E36: 1938.2 | F36: 84.6 | G36: 4.6 | H36: 0.4 | I36: — | J36: — | K36: —
A37: Residential building construction | B37: 236100 | C37: Line item | D37: 943.1 | E37: 982.4 | F37: 39.3 | G37: 4.2 | H37: 0.4 | I37: — | J37: — | K37: —
A38: Nonresidential building construction | B38: 236200 | C38: Line item | D38: 910.5 | E38: 955.8 | F38: 45.3 | G38: 5 | H38: 0.5 | I38: — | J38: — | K38: —
A39: Heavy and civil engineering construction | B39: 237000 | C39: Summary | D39: 1154.4 | E39: 1206.1 | F39: 51.7 | G39: 4.5 | H39: 0.4 | I39: — | J39: — | K39: —
A40: Utility system construction | B40: 237100 | C40: Summary | D40: 602.8 | E40: 634.3 | F40: 31.5 | G40: 5.2 | H40: 0.5 | I40: — | J40: — | K40: —
A41: Power and communication line and related structures construction | B41: 237130 | C41: Line item | D41: 238.4 | E41: 257.2 | F41: 18.8 | G41: 7.9 | H41: 0.8 | I41: — | J41: — | K41: —
A42: Land subdivision | B42: 237200 | C42: Line item | D42: 37.1 | E42: 37.7 | F42: 0.6 | G42: 1.7 | H42: 0.2 | I42: — | J42: — | K42: —
A43: Highway, street, and bridge construction | B43: 237300 | C43: Line item | D43: 377.9 | E43: 390.9 | F43: 13 | G43: 3.4 | H43: 0.3 | I43: — | J43: — | K43: —
A44: Other heavy and civil engineering construction | B44: 237900 | C44: Line item | D44: 136.6 | E44: 143.2 | F44: 6.6 | G44: 4.8 | H44: 0.5 | I44: — | J44: — | K44: —
A45: Specialty trade contractors | B45: 238000 | C45: Summary | D45: 5203.7 | E45: 5427.9 | F45: 224.2 | G45: 4.3 | H45: 0.4 | I45: — | J45: — | K45: —
A46: Foundation, structure, and building exterior contractors | B46: 238100 | C46: Summary | D46: 992.5 | E46: 1032.1 | F46: 39.6 | G46: 4 | H46: 0.4 | I46: — | J46: — | K46: —
A47: Poured concrete foundation and structure contractors | B47: 238110 | C47: Line item | D47: 258.2 | E47: 273.5 | F47: 15.3 | G47: 5.9 | H47: 0.6 | I47: — | J47: — | K47: —
... A57: Other specialty trade contractors | B57: 238900 | C57: Line item | D57: 805.6 | E57: 848.6 | F57: 43 | G57: 5.3 | H57: 0.5 | I57: — | J57: — | K57: —
A58: Manufacturing | B58: 31-330 | C58: Summary | D58: 12817.2 | E58: 12816.8 | F58: -0.4 | G58: 0 | H58: 0 | I58: 5696.8 | J58: 6486.2 | K58: 1.3
A59: Food manufacturing | B59: 311000 | C59: Summary | D59: 1767.6 | E59: 1860.1 | F59: 92.5 | G59: 5.2 | H59: 0.5 | I59: 757.1 | J59: 910.3 | K59: 1.9 | L59: ISIC 10T12
A60: Animal food manufacturing | B60: 311100 | C60: Line item | D60: 75.4 | E60: 80.6 | F60: 5.2 | G60: 6.9 | H60: 0.7 | I60: 50.8 | J60: 60.7 | K60: 1.8
A61: Grain and oilseed milling | B61: 311200 | C61: Line item | D61: 67.4 | E61: 67.7 | F61: 0.3 | G61: 0.5 | H61: 0 | I61: 81.2 | J61: 93.9 | K61: 1.5
A62: Sugar and confectionery product manufacturing | B62: 311300 | C62: Line item | D62: 82.2 | E62: 84.2 | F62: 2 | G62: 2.4 | H62: 0.2 | I62: 32.6 | J62: 35.8 | K62: 0.9
A63: Fruit and vegetable preserving and specialty food manufacturing | B63: 311400 | C63: Line item | D63: 173.8 | E63: 172.6 | F63: -1.2 | G63: -0.7 | H63: -0.1 | I63: 57.1 | J63: 65.9 | K63: 1.4
A64: Dairy product manufacturing | B64: 311500 | C64: Line item | D64: 168 | E64: 178.8 | F64: 10.8 | G64: 6.4 | H64: 0.6 | I64: 130.4 | J64: 171.1 | K64: 2.8
A65: Animal slaughtering and processing | B65: 311600 | C65: Line item | D65: 556.4 | E65: 591.8 | F65: 35.4 | G65: 6.4 | H65: 0.6 | I65: 221.4 | J65: 265.1 | K65: 1.8
A66: Seafood product preparation and packaging | B66: 311700 | C66: Line item | D66: 31.5 | E66: 30.7 | F66: -0.8 | G66: -2.5 | H66: -0.3 | I66: 12.2 | J66: 14 | K66: 1.3
A67: Bakeries and tortilla manufacturing | B67: 311800 | C67: Line item | D67: 350.4 | E67: 369.2 | F67: 18.8 | G67: 5.4 | H67: 0.5 | I67: 62.1 | J67: 74.4 | K67: 1.8
A68: Other food manufacturing | B68: 311900 | C68: Line item | D68: 262.5 | E68: 284.4 | F68: 21.9 | G68: 8.4 | H68: 0.8 | I68: 109 | J68: 131 | K68: 1.9
A69: Beverage and tobacco product manufacturing | B69: 312000 | C69: Summary | D69: 343.4 | E69: 379.7 | F69: 36.3 | G69: 10.6 | H69: 1 | I69: 181.9 | J69: 203 | K69: 1.1 | L69: ISIC 10T12
A70: Beverage manufacturing | B70: 312100 | C70: Line item | D70: 333 | E70: 370.8 | F70: 37.8 | G70: 11.4 | H70: 1.1 | I70: 115.7 | J70: 150.5 | K70: 2.7
A71: Tobacco manufacturing | B71: 312200 | C71: Line item | D71: 10.4 | E71: 8.8 | F71: -1.6 | G71: -15 | H71: -1.7 | I71: 65.2 | J71: 54.6 | K71: -1.8
A72: Textile mills | B72: 313000 | C72: Line item | D72: 86.6 | E72: 78.3 | F72: -8.3 | G72: -9.5 | H72: -1 | I72: 19.4 | J72: 20 | K72: 0.3 | L72: ISIC 13T15
A73: Textile product mills | B73: 314000 | C73: Line item | D73: 99.5 | E73: 89 | F73: -10.5 | G73: -10.5 | H73: -1.1 | I73: 21 | J73: 21.9 | K73: 0.4 | L73: ISIC 13T15
A74: Apparel manufacturing | B74: 315000 | C74: Line item | D74: 84.5 | E74: 58.8 | F74: -25.7 | G74: -30.4 | H74: -3.6 | I74: 12.3 | J74: 10.1 | K74: -1.9 | L74: ISIC 13T15
A75: Leather and allied product manufacturing | B75: 316000 | C75: Line item | D75: 25.1 | E75: 23.8 | F75: -1.3 | G75: -5.2 | H75: -0.5 | I75: 11.9 | J75: 14.2 | K75: 1.8 | L75: ISIC 13T15
A76: Wood product manufacturing | B76: 321000 | C76: Summary | D76: 417 | E76: 417.6 | F76: 0.6 | G76: 0.1 | H76: 0 | I76: 126.5 | J76: 150.1 | K76: 1.7 | L76: ISIC 16
A77: Sawmills and wood preservation | B77: 321100 | C77: Line item | D77: 90.6 | E77: 89.2 | F77: -1.4 | G77: -1.6 | H77: -0.2 | I77: 47.2 | J77: 56.4 | K77: 1.8
A78: Veneer, plywood, and engineered wood product manufacturing | B78: 321200 | C78: Line item | D78: 82.2 | E78: 81.3 | F78: -0.9 | G78: -1.1 | H78: -0.1 | I78: 24.3 | J78: 28.6 | K78: 1.7
A79: Other wood product manufacturing | B79: 321900 | C79: Line item | D79: 244.2 | E79: 247.1 | F79: 2.9 | G79: 1.2 | H79: 0.1 | I79: 56.8 | J79: 67.3 | K79: 1.7
A80: Paper manufacturing | B80: 322000 | C80: Summary | D80: 354.6 | E80: 328.9 | F80: -25.7 | G80: -7.3 | H80: -0.7 | I80: 163 | J80: 180.2 | K80: 1 | L80: ISIC 17T18
A81: Pulp, paper, and paperboard mills | B81: 322100 | C81: Line item | D81: 84.7 | E81: 73.6 | F81: -11.1 | G81: -13.1 | H81: -1.4 | I81: 63.9 | J81: 63.1 | K81: -0.1
A82: Converted paper product manufacturing | B82: 322200 | C82: Line item | D82: 269.9 | E82: 255.3 | F82: -14.6 | G82: -5.4 | H82: -0.6 | I82: 99 | J82: 116.9 | K82: 1.7
A83: Printing and related support activities | B83: 323000 | C83: Line item | D83: 357.2 | E83: 301.9 | F83: -55.3 | G83: -15.5 | H83: -1.7 | I83: 67 | J83: 71.1 | K83: 0.6 | L83: ISIC 17T18
A84: Petroleum and coal products manufacturing | B84: 324000 | C84: Line item | D84: 109.4 | E84: 106.2 | F84: -3.2 | G84: -3 | H84: -0.3 | I84: 483.5 | J84: 535 | K84: 1 | L84: ISIC 19
A85: Chemical manufacturing | B85: 325000 | C85: Summary | D85: 897.9 | E85: 928.9 | F85: 31 | G85: 3.5 | H85: 0.3 | I85: 849.6 | J85: 1004 | K85: 1.7
A86: Chemical manufacturing (3251,2,3,9) | B86: 3250A1 | C86: Line item | D86: 368.7 | E86: 376.7 | F86: 8 | G86: 2.2 | H86: 0.2 | I86: 390.8 | J86: 431.5 | K86: 1 | L86: ISIC 20
A87: Chemical manufacturing (3255,6) | B87: 3250A2 | C87: Line item | D87: 178.7 | E87: 182.7 | F87: 4 | G87: 2.3 | H87: 0.2 | I87: 114.5 | J87: 139.5 | K87: 2 | L87: ISIC 20
A88: Pharmaceutical and medicine manufacturing | B88: 325400 | C88: Line item | D88: 350.5 | E88: 369.5 | F88: 19 | G88: 5.4 | H88: 0.5 | I88: 346.7 | J88: 438.5 | K88: 2.4 | L88: ISIC 21
A89: Plastics and rubber products manufacturing | B89: 326000 | C89: Summary | D89: 725.1 | E89: 753.4 | F89: 28.3 | G89: 3.9 | H89: 0.4 | I89: 229.7 | J89: 252.1 | K89: 0.9 | L89: ISIC 22
A90: Plastics product manufacturing | B90: 326100 | C90: Line item | D90: 592.5 | E90: 618.8 | F90: 26.3 | G90: 4.4 | H90: 0.4 | I90: 190.7 | J90: 212.4 | K90: 1.1
A91: Rubber product manufacturing | B91: 326200 | C91: Line item | D91: 132.6 | E91: 134.6 | F91: 2 | G91: 1.5 | H91: 0.1 | I91: 39.1 | J91: 39.7 | K91: 0.2
A92: Nonmetallic mineral product manufacturing | B92: 327000 | C92: Line item | D92: 422.3 | E92: 429 | F92: 6.7 | G92: 1.6 | H92: 0.2 | I92: 113.5 | J92: 132.3 | K92: 1.5 | L92: ISIC 239
A93: Primary metal manufacturing | B93: 331000 | C93: Summary | D93: 373.2 | E93: 360.2 | F93: -13 | G93: -3.5 | H93: -0.4 | I93: 246.6 | J93: 287.3 | K93: 1.5
A94: Iron and steel mills and ferroalloy manufacturing | B94: 331100 | C94: Line item | D94: 85.6 | E94: 86.9 | F94: 1.3 | G94: 1.5 | H94: 0.2 | I94: 103.9 | J94: 124.3 | K94: 1.8 | L94: ISIC 241
A95: Steel product manufacturing from purchased steel | B95: 331200 | C95: Line item | D95: 59.8 | E95: 60.9 | F95: 1.1 | G95: 1.9 | H95: 0.2 | I95: 25.6 | J95: 30.9 | K95: 1.9 | L95: ISIC 241
A96: Alumina and aluminum production and processing | B96: 331300 | C96: Line item | D96: 59.3 | E96: 58.4 | F96: -0.9 | G96: -1.5 | H96: -0.2 | I96: 38.1 | J96: 39.9 | K96: 0.5 | L96: ISIC 242
A97: Nonferrous metal (except aluminum) production and processing | B97: 331400 | C97: Line item | D97: 62.5 | E97: 63.6 | F97: 1.1 | G97: 1.8 | H97: 0.2 | I97: 50.3 | J97: 64.1 | K97: 2.4 | L97: ISIC 242
A98: Foundries | B98: 331500 | C98: Line item | D98: 106 | E98: 90.4 | F98: -15.6 | G98: -14.7 | H98: -1.6 | I98: 26.9 | J98: 24.8 | K98: -0.8
A99: Fabricated metal product manufacturing | B99: 332000 | C99: Summary | D99: 1442.1 | E99: 1385.3 | F99: -56.8 | G99: -3.9 | H99: -0.4 | I99: 303.5 | J99: 329.5 | K99: 0.8 | L99: ISIC 25
A100: Fabricated metal product manufacturing (3321,2,5,6,9) | B100: 3320A1 | C100: Line item | D100: 467.8 | E100: 423.2 | F100: -44.6 | G100: -9.5 | H100: -1 | I100: 123.8 | J100: 129.6 | K100: 0.5
A101: Fabricated metal product manufacturing (3323,4) | B101: 3320A2 | C101: Line item | D101: 511.5 | E101: 526.3 | F101: 14.8 | G101: 2.9 | H101: 0.3 | I101: 97.4 | J101: 109.1 | K101: 1.1
A102: Machine shops; turned product; and screw, nut, and bolt manufacturing | B102: 332700 | C102: Summary | D102: 333.2 | E102: 319.8 | F102: -13.4 | G102: -4 | H102: -0.4 | I102: 59.1 | J102: 65.9 | K102: 1.1
A103: Machine shops | B103: 332710 | C103: Line item | D103: 259 | E103: 260.1 | F103: 1.1 | G103: 0.4 | H103: 0 | I103: 37.1 | J103: 41.3 | K103: 1.1
A104: Turned product and screw, nut, and bolt manufacturing | B104: 332720 | C104: Line item | D104: 74.2 | E104: 59.8 | F104: -14.4 | G104: -19.5 | H104: -2.1 | I104: 22.2 | J104: 24.7 | K104: 1.1
A105: Coating, engraving, heat treating, and allied activities | B105: 332800 | C105: Line item | D105: 129.6 | E105: 115.9 | F105: -13.7 | G105: -10.6 | H105: -1.1 | I105: 25.1 | J105: 26.1 | K105: 0.4
A106: Machinery manufacturing | B106: 333000 | C106: Summary | D106: 1118.8 | E106: 1108.2 | F106: -10.6 | G106: -0.9 | H106: -0.1 | I106: 330.1 | J106: 366.9 | K106: 1.1 | L106: ISIC 28
A107: Machinery manufacturing (3331,2,4,9) | B107: 3330A1 | C107: Line item | D107: 780.2 | E107: 782.8 | F107: 2.6 | G107: 0.3 | H107: 0 | I107: 241.2 | J107: 266.8 | K107: 1
A108: Commercial and service industry machinery manufacturing | B108: 333300 | C108: Line item | D108: 88.7 | E108: 89.6 | F108: 0.9 | G108: 1 | H108: 0.1 | I108: 23.5 | J108: 26.4 | K108: 1.2
A109: Metalworking machinery manufacturing | B109: 333500 | C109: Line item | D109: 157.1 | E109: 147.4 | F109: -9.7 | G109: -6.2 | H109: -0.6 | I109: 27.3 | J109: 30.6 | K109: 1.1
...

Sheet AEO25 Table 23
C1: Table 23. Industrial Sector Macroeconomic Indicators
C2: https://www.eia.gov/outlooks/aeo/data/browser/#/?id=34-AEO2025&cases=highZTC&sourcekey=0
C3: Tue Dec 02 2025 13:21:59 GMT-0800 (Pacific Standard Time)
C4: Source: U.S. Energy Information Administration
B5: ISIC assignment (editable) | D5: full name | E5: api key | F5: units | G5: 2023 | H5: 2024 | I5: 2025 | J5: 2026 | K5: 2027 | L5: 2028 | M5: 2029 | N5: 2030 | O5: 2031 | P5: 2032 | Q5: 2033 | R5: 2034 | S5: 2035 | T5: 2036 | U5: 2037 | V5: 2038 | W5: 2039 | X5: 2040 | Y5: 2041 | Z5: 2042 | AA5: 2043 | AB5: 2044 | AC5: 2045 | AD5: 2046 | AE5: 2047 | AF5: 2048 | AG5: 2049 | AH5: 2050 | AI5: Growth (2024-2050)
A6: ISM000:ba_GDP(billionm_ | C6: Gross Domestic Product (billion 2012 dollars) | D6: Industrial Macroeconomic: Gross Domestic Product: High Zero-Carbon Technology Cost | E6: AEO.2025.HIGHZTC.ECI_GDP_NA_NA_NA_NA_NA_BLNY09DLR.A | F6: billion 2012 $ | H6: 21699.672 | I6: 22171.93 | J6: 22685.953 | K6: 23162.596 | L6: 23590.016 | M6: 24042.869 | N6: 24479.318 | O6: 24877.939 | P6: 25299.824 | Q6: 25731.902 | R6: 26166.297 | S6: 26621.836 | T6: 27077.875 | U6: 27546.342 | V6: 28018.711 | W6: 28503.035 | X6: 29003.939 | Y6: 29486.92 | Z6: 29991.914 | AA6: 30494.672 | AB6: 30998.293 | AC6: 31501.85 | AD6: 32021.367 | AE6: 32546.51 | AF6: 33074.625 | AG6: 33617.656 | AH6: 34162.723 | AI6: 0.018
A7: ISM000:ca_NonfarmEmploy | C7: Nonfarm Employment (millions) | D7: Industrial Macroeconomic: Employment, Nonfarm: High Zero-Carbon Technology Cost | E7: AEO.2025.HIGHZTC.ECI_NFE_NA_NA_NA_NA_NA_MILL.A | F7: millions | H7: 159.5452 | I7: 160.89847 | J7: 161.43066 | K7: 161.69711 | L7: 161.99791 | M7: 162.5314 | N7: 163.24155 | O7: 163.92671 | P7: 164.54892 | Q7: 164.98477 | R7: 165.29776 | S7: 165.56593 | T7: 166.08339 | U7: 166.7914 | V7: 167.5314 | W7: 168.18655 | X7: 169.00385 | Y7: 169.65865 | Z7: 170.29732 | AA7: 170.74045 | AB7: 171.20613 | AC7: 171.65497 | AD7: 172.12753 | AE7: 172.64163 | AF7: 173.16328 | AG7: 173.71744 | AH7: 174.28783 | AI7: 0.003
C8: Value of Shipments (billion 2012 dollars)
C9: Nonmanufacturing Sector
A10: ISM000:ea_Agricultural | B10: ,ISIC 01, | C10: Agriculture/Forestry/Fishing/Hunting | D10: Industrial Macroeconomic: Nonmanufacturing: Agriculture/Forestry/Fishing/Hunting: High Zero-Carbon Technology Cost | E10: AEO.2025.HIGHZTC.ECI_VOS_NMFG_AFF_NA_NA_NA_BLNY09DLR.A | F10: billion 2012 $ | H10: 538.8266 | I10: 544.76807 | J10: 552.01935 | K10: 559.25311 | L10: 565.51892 | M10: 573.79547 | N10: 581.47052 | O10: 587.56146 | P10: 593.56909 | Q10: 599.28235 | R10: 606.56781 | S10: 614.13873 | T10: 623.17743 | U10: 630.44727 | V10: 636.67987 | W10: 643.48901 | X10: 649.69403 | Y10: 654.328 | Z10: 659.78339 | AA10: 665.28345 | AB10: 671.34363 | AC10: 678.96008 | AD10: 686.82513 | AE10: 694.61627 | AF10: 702.28125 | AG10: 710.2558 | AH10: 718.01489 | AI10: 0.011
A11: ISM000:ea_Mining | B11: ,ISIC 05,ISIC 06,ISIC 08, | C11: Mining | D11: Industrial Macroeconomic: Nonmanufacturing: Mining: High Zero-Carbon Technology Cost | E11: AEO.2025.HIGHZTC.ECI_VOS_NMFG_MING_NA_NA_NA_BLNY09DLR.A | F11: billion 2012 $ | H11: 738.6261 | I11: 800.09271 | J11: 807.26276 | K11: 812.87158 | L11: 822.88531 | M11: 830.664 | N11: 837.44684 | O11: 834.11847 | P11: 842.65662 | Q11: 842.87884 | R11: 843.77454 | S11: 839.43475 | T11: 833.55817 | U11: 824.76233 | V11: 820.58246 | W11: 815.21143 | X11: 817.20264 | Y11: 820.17926 | Z11: 823.91998 | AA11: 823.77704 | AB11: 825.68115 | AC11: 828.09149 | AD11: 834.33093 | AE11: 835.11914 | AF11: 834.69672 | AG11: 836.80615 | AH11: 839.41028 | AI11: 0.005
A12: ISM000:ea_Construction | B12: ,ISIC 41T43, | C12: Construction | D12: Industrial Macroeconomic: Nonmanufacturing: Construction: High Zero-Carbon Technology Cost | E12: AEO.2025.HIGHZTC.ECI_VOS_NMFG_CNS_NA_NA_NA_BLNY09DLR.A | F12: billion 2012 $ | H12: 1440.7977 | I12: 1433.0573 | J12: 1444.2264 | K12: 1467.1532 | L12: 1502.7834 | M12: 1544.0198 | N12: 1573.1925 | O12: 1598.66 | P12: 1617.2603 | Q12: 1624.0387 | R12: 1624.3893 | S12: 1639.5165 | T12: 1660.5125 | U12: 1673.6357 | V12: 1687.7023 | W12: 1700.454 | X12: 1710.2748 | Y12: 1717.3003 | Z12: 1728.8163 | AA12: 1737.1105 | AB12: 1744.9568 | AC12: 1762.099 | AD12: 1781.2562 | AE12: 1803.2469 | AF12: 1826.4515 | AG12: 1851.1388 | AH12: 1872.7469 | AI12: 0.01
C13: Manufacturing Sector
A14: ISM000:fa_FoodandKindre | B14: ,ISIC 10T12, | C14: Food Products | D14: Industrial Macroeconomic: Manufacturing: Food Products: High Zero-Carbon Technology Cost | E14: AEO.2025.HIGHZTC.ECI_VOS_MANF_FPA_NA_NA_NA_BLNY09DLR.A | F14: billion 2012 $ | H14: 821.565 | I14: 826.25629 | J14: 829.60242 | K14: 837.90674 | L14: 844.65008 | M14: 853.04797 | N14: 861.58227 | O14: 869.4892 | P14: 877.76154 | Q14: 885.73114 | R14: 894.01611 | S14: 901.54547 | T14: 911.37494 | U14: 920.41272 | V14: 929.09497 | W14: 938.25281 | X14: 947.32989 | Y14: 956.4433 | Z14: 965.737 | AA14: 974.68512 | AB14: 983.68793 | AC14: 992.50006 | AD14: 1001.4976 | AE14: 1010.5715 | AF14: 1019.6702 | AG14: 1029.1584 | AH14: 1038.4718 | AI14: 0.009
A15: ISM000:fa_BeveragesandT | B15: ,ISIC 10T12, | C15: Beverages and Tobacco Products | D15: Industrial Macroeconomic: Manufacturing: Beverages and Tobacco Products: High Zero-Carbon Technology Cost | E15: AEO.2025.HIGHZTC.ECI_VOS_MANF_BVTP_NA_NA_NA_BLNY09DLR.A | F15: billion 2012 $ | H15: 141.90608 | I15: 139.8526 | J15: 138.7114 | K15: 138.03377 | L15: 137.52714 | M15: 136.83862 | N15: 136.09837 | O15: 135.32722 | P15: 134.48689 | Q15: 133.75133 | R15: 133.0681 | S15: 132.55055 | T15: 131.98662 | U15: 131.44885 | V15: 130.93477 | W15: 130.42633 | X15: 129.9326 | Y15: 129.43793 | Z15: 128.93127 | AA15: 128.3781 | AB15: 127.79433 | AC15: 127.17438 | AD15: 126.60002 | AE15: 126.07458 | AF15: 125.57433 | AG15: 125.09577 | AH15: 124.58905 | AI15: -0.005
A16: ISM000:fa_TextileMillPr | B16: ,ISIC 13T15, | C16: Textile Mills and Products | D16: Industrial Macroeconomic: Manufacturing: Textile Mills and Products: High Zero-Carbon Technology Cost | E16: AEO.2025.HIGHZTC.ECI_VOS_MANF_TMP_NA_NA_NA_BLNY09DLR.A | F16: billion 2012 $ | H16: 66.089165 | I16: 66.538513 | J16: 65.8992 | K16: 65.924271 | L16: 64.83783 | M16: 64.166801 | N16: 63.704239 | O16: 63.158009 | P16: 62.414116 | Q16: 61.727993 | R16: 61.319778 | S16: 60.568184 | T16: 59.831409 | U16: 59.532326 | V16: 59.14883 | W16: 58.90044 | X16: 58.791424 | Y16: 58.565128 | Z16: 58.345596 | AA16: 57.977749 | AB16: 57.632816 | AC16: 57.247356 | AD16: 56.93322 | AE16: 56.724243 | AF16: 56.464836 | AG16: 56.23605 | AH16: 55.887161 | AI16: -0.006
A17: ISM000:fa_LumberandWood | B17: ,ISIC 16, | C17: Wood Products | D17: Industrial Macroeconomic: Manufacturing: Wood Products: High Zero-Carbon Technology Cost | E17: AEO.2025.HIGHZTC.ECI_VOS_MANF_WDP_NA_NA_NA_BLNY09DLR.A | F17: billion 2012 $ | H17: 98.40712 | I17: 99.04071 | J17: 101.04065 | K17: 102.24693 | L17: 103.98792 | M17: 107.2435 | N17: 109.76388 | O17: 111.44402 | P17: 112.56998 | Q17: 112.37907 | R17: 113.57045 | S17: 115.05647 | T17: 118.32752 | U17: 120.52498 | V17: 121.29505 | W17: 122.2 | X17: 122.0394 | Y17: 119.66293 | Z17: 118.0938 | AA17: 115.15807 | AB17: 113.1279 | AC17: 113.01455 | AD17: 113.40658 | AE17: 114.63775 | AF17: 115.77583 | AG17: 117.22973 | AH17: 118.1262 | AI17: 0.007
A18: ISM000:fa_FurnitureandF | B18: ,ISIC 31T33, | C18: Furniture and Related Products | D18: Industrial Macroeconomic: Manufacturing: Furniture and Related Products: High Zero-Carbon Technology Cost | E18: AEO.2025.HIGHZTC.ECI_VOS_MANF_FRP_NA_NA_NA_BLNY09DLR.A | F18: billion 2012 $ | H18: 53.271854 | I18: 52.269444 | J18: 53.980427 | K18: 55.926292 | L18: 56.093472 | M18: 56.599045 | N18: 58.34198 | O18: 58.92627 | P18: 59.556118 | Q18: 59.890476 | R18: 61.148804 | S18: 61.658676 | T18: 62.141407 | U18: 63.414036 | V18: 64.388123 | W18: 65.334251 | X18: 66.700745 | Y18: 67.731552 | Z18: 68.640739 | AA18: 69.677574 | AB18: 70.932808 | AC18: 71.805748 | AD18: 72.815346 | AE18: 74.188431 | AF18: 74.879402 | AG18: 76.066422 | AH18: 76.886627 | AI18: 0.014
A19: ISM000:fa_PaperandAllie | B19: ,ISIC 17T18, | C19: Paper Products | D19: Industrial Macroeconomic: Manufacturing: Paper Products: High Zero-Carbon Technology Cost | E19: AEO.2025.HIGHZTC.ECI_VOS_MANF_PPM_NA_NA_NA_BLNY09DLR.A | F19: billion 2012 $ | H19: 161.46919 | I19: 162.7692 | J19: 164.02576 | K19: 162.47028 | L19: 161.55638 | M19: 161.47072 | N19: 161.8098 | O19: 162.97775 | P19: 163.75282 | Q19: 164.06697 | R19: 165.19106 | S19: 166.25287 | T19: 167.39653 | U19: 168.34885 | V19: 169.4716 | W19: 171.07837 | X19: 172.76543 | Y19: 174.02237 | Z19: 175.34892 | AA19: 176.49817 | AB19: 178.14328 | AC19: 179.31845 | AD19: 180.70677 | AE19: 182.0945 | AF19: 183.34045 | AG19: 184.40793 | AH19: 185.49396 | AI19: 0.005
A20: ISM000:fa_PrintingandPu | B20: ,ISIC 17T18, | C20: Printing | D20: Industrial Macroeconomic: Manufacturing: Printing: High Zero-Carbon Technology Cost | E20: AEO.2025.HIGHZTC.ECI_VOS_MANF_PRN_NA_NA_NA_BLNY09DLR.A | F20: billion 2012 $ | H20: 60.525852 | I20: 57.448959 | J20: 56.292637 | K20: 54.877972 | L20: 53.651821 | M20: 52.613571 | N20: 51.594307 | O20: 50.581692 | P20: 49.633221 | Q20: 48.66946 | R20: 47.801643 | S20: 46.996117 | T20: 46.399475 | U20: 45.814659 | V20: 45.239269 | W20: 44.861446 | X20: 44.471886 | Y20: 44.081989 | Z20: 43.735256 | AA20: 43.354687 | AB20: 43.027943 | AC20: 42.731819 | AD20: 42.579571 | AE20: 42.327194 | AF20: 42.10128 | AG20: 41.857502 | AH20: 41.633499 | AI20: -0.014
A21: ISM000:fa_ChemicalandAl | B21: ,ISIC 20, | C21: Chemical Manufacturing | D21: Industrial Macroeconomic: Manufacturing: Chemical Manufacturing: High Zero-Carbon Technology Cost | E21: AEO.2025.HIGHZTC.ECI_VOS_MANF_CHE_NA_NA_NA_BLNY09DLR.A | F21: billion 2012 $ | H21: 808.21368 | I21: 812.38934 | J21: 806.69074 | K21: 804.93176 | L21: 803.34943 | M21: 806.09863 | N21: 813.56812 | O21: 823.25134 | P21: 834.16455 | Q21: 843.79175 | R21: 855.42957 | S21: 865.72815 | T21: 874.20136 | U21: 885.51782 | V21: 896.98572 | W21: 909.44946 | X21: 923.43683 | Y21: 936.80664 | Z21: 950.84143 | AA21: 963.14319 | AB21: 974.9859 | AC21: 984.60706 | AD21: 994.83899 | AE21: 1008.811 | AF21: 1020.662 | AG21: 1031.7502 | AH21: 1041.1604 | AI21: 0.01
A22: ISM000:fa_BulkChemicals | C22: Bulk Chemicals | D22: Industrial Macroeconomic: Manufacturing: Chemicals: Bulk Chemicals: High Zero-Carbon Technology Cost | E22: AEO.2025.HIGHZTC.ECI_VOS_MANF_BCH_NA_NA_NA_BLNY09DLR.A | F22: billion 2012 $ | H22: 367.32217 | I22: 372.95435 | J22: 365.47006 | K22: 360.02753 | L22: 354.24496 | M22: 352.82477 | N22: 355.28152 | O22: 359.69891 | P22: 364.24594 | Q22: 367.19061 | R22: 373.40387 | S22: 379.88586 | T22: 384.06592 | U22: 389.13483 | V22: 394.53491 | W22: 400.9906 | X22: 408.14343 | Y22: 414.30145 | Z22: 420.51334 | AA22: 425.35037 | AB22: 430.8327 | AC22: 435.23618 | AD22: 439.59573 | AE22: 446.34097 | AF22: 451.72757 | AG22: 456.2446 | AH22: 460.80216 | AI22: 0.009
A23: ISM000:fa_Inorganic | C23: Inorganic | D23: Industrial Macroeconomic: Manufacturing: Chemicals: Bulk Chemicals: Inorganic: High Zero-Carbon Technology Cost | E23: AEO.2025.HIGHZTC.ECI_VOS_MANF_CHEIN_NA_NA_NA_BLNY09DLR.A | F23: billion 2012 $ | H23: 50.760822 | I23: 51.478336 | J23: 52.328194 | K23: 52.508663 | L23: 52.006046 | M23: 51.169857 | N23: 51.473831 | O23: 51.551136 | P23: 51.466038 | Q23: 51.676189 | R23: 51.725769 | S23: 52.104076 | T23: 52.200466 | U23: 51.96347 | V23: 52.269703 | W23: 52.373104 | X23: 52.339554 | Y23: 52.473537 | Z23: 52.384289 | AA23: 52.293137 | AB23: 52.097511 | AC23: 51.880245 | AD23: 51.748787 | AE23: 51.814064 | AF23: 51.907967 | AG23: 51.836624 | AH23: 51.954746 | AI23: 0.001
A24: ISM000:fa_Organic | C24: Organic | D24: Industrial Macroeconomic: Manufacturing: Chemicals: Bulk Chemicals: Organic: High Zero-Carbon Technology Cost | E24: AEO.2025.HIGHZTC.ECI_VOS_MANF_CHEOR_NA_NA_NA_BLNY09DLR.A | F24: billion 2012 $ | H24: 179.6485 | I24: 184.1534 | J24: 172.36072 | K24: 167.71588 | L24: 163.97459 | M24: 162.34164 | N24: 162.01833 | O24: 164.70097 | P24: 167.63568 | Q24: 169.28833 | R24: 172.1774 | S24: 176.19098 | T24: 179.03477 | U24: 181.7184 | V24: 185.00465 | W24: 189.10175 | X24: 193.48135 | Y24: 197.50008 | Z24: 201.28572 | AA24: 205.21362 | AB24: 209.58937 | AC24: 213.81535 | AD24: 216.95627 | AE24: 221.06383 | AF24: 224.53114 | AG24: 227.09778 | AH24: 230.2061 | AI24: 0.01
A25: ISM000:fa_Resins | C25: Resin | D25: Synthetic Rubber | E25: and Fibers | F25: Industrial Macroeconomic: Manufacturing: Chemicals: Bulk Chemicals: Resin, Synthetic Rubber, and Fibers: High Zero-Carbon Technology Cost | G25: AEO.2025.HIGHZTC.ECI_VOS_MANF_CHEBR_NA_NA_NA_BLNY09DLR.A | H25: 98.834442 | I25: 97.966858 | J25: 99.326225 | K25: 97.665497 | L25: 95.804192 | M25: 96.423264 | N25: 98.262207 | O25: 99.258095 | P25: 100.285 | Q25: 100.9119 | R25: 103.31385 | S25: 104.717 | T25: 105.34988 | U25: 107.17442 | V25: 108.3623 | W25: 110.00505 | X25: 112.15402 | Y25: 113.5902 | Z25: 115.5398 | AA25: 116.0079 | AB25: 116.68415 | AC25: 116.62328 | AD25: 117.465 | AE25: 119.5488 | AF25: 120.94505 | AG25: 122.55138 | AH25: 123.52005 | AI25: 0.009
A26: ISM000:fa_AgriculturalC | C26: Agricultural Chemicals | D26: Industrial Macroeconomic: Manufacturing: Chemicals: Bulk Chemicals: Agricultural Chemicals: High Zero-Carbon Technology Cost | E26: AEO.2025.HIGHZTC.ECI_VOS_MANF_AGC_NA_NA_NA_BLNY09DLR.A | F26: billion 2012 $ | H26: 38.078388 | I26: 39.355778 | J26: 41.454929 | K26: 42.137497 | L26: 42.460148 | M26: 42.890003 | N26: 43.527168 | O26: 44.188728 | P26: 44.859222 | Q26: 45.314175 | R26: 46.186852 | S26: 46.873821 | T26: 47.480816 | U26: 48.278534 | V26: 48.898262 | W26: 49.510666 | X26: 50.168533 | Y26: 50.737656 | Z26: 51.303539 | AA26: 51.835686 | AB26: 52.461685 | AC26: 52.917336 | AD26: 53.425697 | AE26: 53.914276 | AF26: 54.343407 | AG26: 54.758823 | AH26: 55.121239 | AI26: 0.014
A27: ISM000:fa_OtherChemical | C27: Other Chemical Products | D27: Industrial Macroeconomic: Manufacturing: Chemicals: Other Chemical Products: High Zero-Carbon Technology Cost | E27: AEO.2025.HIGHZTC.ECI_VOS_MANF_CHEO_NA_NA_NA_BLNY09DLR.A | F27: billion 2012 $ | H27: 440.89151 | I27: 439.435 | J27: 441.22067 | K27: 444.9042 | L27: 449.10446 | M27: 453.27383 | N27: 458.28656 | O27: 463.5524 | P27: 469.91864 | Q27: 476.60113 | R27: 482.02567 | S27: 485.84226 | T27: 490.13544 | U27: 496.383 | V27: 502.45084 | W27: 508.45886 | X27: 515.2934 | Y27: 522.50519 | Z27: 530.32806 | AA27: 537.79279 | AB27: 544.1532 | AC27: 549.37085 | AD27: 555.24323 | AE27: 562.47003 | AF27: 568.93445 | AG27: 575.50562 | AH27: 580.35828 | AI27: 0.011
A28: ISM000:fa_PetroleumandC | C28: Petroleum and Coal Products | D28: Industrial Macroeconomic: Manufacturing: Petroleum and Coal Products: High Zero-Carbon Technology Cost | E28: AEO.2025.HIGHZTC.ECI_VOS_MANF_PCL_NA_NA_NA_BLNY09DLR.A | F28: billion 2012 $ | H28: 816.09601 | I28: 829.73065 | J28: 826.35809 | K28: 822.63525 | L28: 818.11365 | M28: 811.7898 | N28: 801.87268 | O28: 790.94 | P28: 777.92773 | Q28: 764.57977 | R28: 753.02173 | S28: 741.50934 | T28: 729.7876 | U28: 718.6405 | V28: 709.41724 | W28: 702.5293 | X28: 697.51465 | Y28: 692.16034 | Z28: 686.87671 | AA28: 682.12921 | AB28: 678.85687 | AC28: 674.4317 | AD28: 672.45917 | AE28: 673.33466 | AF28: 671.36792 | AG28: 672.13104 | AH28: 673.04504 | AI28: -0.007
A29: ISM000:fa_PetroleumRefi | B29: ,ISIC 19, | C29: Petroleum Refineries | D29: Industrial Macroeconomic: Manufacturing: Petroleum and Coal: Petroleum Refineries: High Zero-Carbon Technology Cost | E29: AEO.2025.HIGHZTC.ECI_VOS_MANF_REF_NA_NA_NA_BLNY09DLR.A | F29: billion 2012 $ | H29: 773.8219 | I29: 786.61841 | J29: 783.18323 | K29: 779.68903 | L29: 775.45001 | M29: 769.39807 | N29: 759.90216 | O29: 749.35315 | P29: 736.87854 | Q29: 724.18066 | R29: 713.24438 | S29: 702.289 | T29: 691.01855 | U29: 680.32849 | V29: 671.50891 | W29: 664.93426 | X29: 660.10657 | Y29: 654.97394 | Z29: 650.02429 | AA29: 645.57031 | AB29: 642.4895 | AC29: 638.2727 | AD29: 636.51154 | AE29: 637.53351 | AF29: 635.75726 | AG29: 636.62994 | AH29: 637.6333 | AI29: -0.007
A30: ISM000:fa_OtherPetroleu | B30: ,ISIC 241, | C30: Other Petroleum and Coal Products | D30: Industrial Macroeconomic: Manufacturing: Petroleum and Coal: Other Petroleum & Coal Products: High Zero-Carbon Technology Cost | E30: AEO.2025.HIGHZTC.ECI_VOS_MANF_PCLO_NA_NA_NA_BLNY09DLR.A | F30: billion 2012 $ | H30: 42.27409 | I30: 43.112217 | J30: 43.174866 | K30: 42.94622 | L30: 42.663628 | M30: 42.391701 | N30: 41.970547 | O30: 41.586861 | P30: 41.049202 | Q30: 40.399086 | R30: 39.777332 | S30: 39.220341 | T30: 38.769024 | U30: 38.312031 | V30: 37.90834 | W30: 37.595055 | X30: 37.408058 | Y30: 37.186394 | Z30: 36.85239 | AA30: 36.558922 | AB30: 36.367348 | AC30: 36.158981 | AD30: 35.947632 | AE30: 35.801125 | AF30: 35.610645 | AG30: 35.501125 | AH30: 35.411743 | AI30: -0.007
A31: ISM000:fa_RubberandMisc | B31: ,ISIC 22, | C31: Plastics and Rubber Products | D31: Industrial Macroeconomic: Manufacturing: Plastics and Rubber Products: High Zero-Carbon Technology Cost | E31: AEO.2025.HIGHZTC.ECI_VOS_MANF_PRP_NA_NA_NA_BLNY09DLR.A | F31: billion 2012 $ | H31: 212.32913 | I31: 217.69611 | J31: 224.71417 | K31: 228.99838 | L31: 231.00073 | M31: 233.92827 | N31: 237.69215 | O31: 241.49115 | P31: 245.09897 | Q31: 248.24377 | R31: 252.30617 | S31: 255.40613 | T31: 257.66836 | U31: 260.66455 | V31: 263.21542 | W31: 265.90036 | X31: 268.94296 | Y31: 271.58008 | Z31: 274.43543 | AA31: 276.42465 | AB31: 278.5116 | AC31: 280.17221 | AD31: 282.02731 | AE31: 284.19464 | AF31: 286.12378 | AG31: 288.19809 | AH31: 289.85263 | AI31: 0.012
A32: ISM000:fa_Stone,Clay,an | C32: Non-metallic minerals | D32: Industrial Macroeconomic: Manufacturing: Stone, Clay, and Glass Products: High Zero-Carbon Technology Cost | E32: AEO.2025.HIGHZTC.ECI_VOS_MANF_SCG_NA_NA_NA_BLNY09DLR.A | F32: billion 2012 $ | H32: 111.54769 | I32: 111.64612 | J32: 111.83931 | K32: 112.53001 | L32: 113.1917 | M32: 113.50225 | N32: 114.45515 | O32: 115.9222 | P32: 117.23323 | Q32: 118.13599 | R32: 118.88231 | S32: 119.85504 | T32: 120.86804 | U32: 121.95155 | V32: 123.17243 | W32: 124.29541 | X32: 125.05119 | Y32: 125.54099 | Z32: 125.83267 | AA32: 125.66972 | AB32: 125.18317 | AC32: 125.38245 | AD32: 126.04735 | AE32: 126.8273 | AF32: 127.72215 | AG32: 128.63948 | AH32: 129.61243 | AI32: 0.006
A33: ISM000:fa_GlassandGlass | B33: ,ISIC 231, | C33: Glass and Glass Products | D33: Industrial Macroeconomic: Manufacturing: Stone, Clay, and Glass: Glass and Glass Products: High Zero-Carbon Technology Cost | E33: AEO.2025.HIGHZTC.ECI_VOS_MANF_SCGG_NA_NA_NA_BLNY09DLR.A | F33: billion 2012 $ | H33: 21.45093 | I33: 21.290245 | J33: 21.242983 | K33: 21.230724 | L33: 21.263985 | M33: 21.310061 | N33: 21.371811 | O33: 21.476692 | P33: 21.61256 | Q33: 21.745703 | R33: 21.89089 | S33: 22.055412 | T33: 22.216677 | U33: 22.39768 | V33: 22.595711 | W33: 22.798956 | X33: 23.015873 | Y33: 23.23588 | Z33: 23.452274 | AA33: 23.653669 | AB33: 23.834209 | AC33: 23.998465 | AD33: 24.153 | AE33: 24.320282 | AF33: 24.498272 | AG33: 24.677088 | AH33: 24.843611 | AI33: 0.006
A34: ISM000:fa_CementandHydr | B34: ,ISIC 239, | C34: Cement and Lime | D34: Industrial Macroeconomic: Manufacturing: Stone, Clay, and Glass: Cement and Lime: High Zero-Carbon Technology Cost | E34: AEO.2025.HIGHZTC.ECI_VOS_MANF_SCGCL_NA_NA_NA_BLNY09DLR.A | F34: billion 2012 $ | H34: 9.305412 | I34: 9.341552 | J34: 9.271192 | K34: 9.279629 | L34: 9.351248 | M34: 9.433073 | N34: 9.557519 | O34: 9.703686 | P34: 9.855732 | Q34: 9.999584 | R34: 10.13154 | S34: 10.260571 | T34: 10.38773 | U34: 10.523909 | V34: 10.673493 | W34: 10.821849 | X34: 10.946848 | Y34: 11.046646 | Z34: 11.118332 | AA34: 11.14825 | AB34: 11.14453 | AC34: 11.16645 | AD34: 11.222955 | AE34: 11.310638 | AF34: 11.422865 | AG34: 11.550447 | AH34: 11.685319 | AI34: 0.009
A35: ISM000:fa_OtherStone,Cl | B35: ,ISIC 239, | C35: Other Nonmetallic Mineral Products | D35: Industrial Macroeconomic: Manufacturing: Stone, Clay, and Glass: Other Nonmetallic Mineral Products: High Zero-Carbon Technology Cost | E35: AEO.2025.HIGHZTC.ECI_VOS_MANF_SCGOM_NA_NA_NA_BLNY09DLR.A | F35: billion 2012 $ | H35: 80.791351 | I35: 81.01432 | J35: 81.325134 | K35: 82.019653 | L35: 82.576469 | M35: 82.759117 | N35: 83.525826 | O35: 84.741814 | P35: 85.764938 | Q35: 86.390701 | R35: 86.859879 | S35: 87.539062 | T35: 88.263634 | U35: 89.029968 | V35: 89.903229 | W35: 90.674606 | X35: 91.088463 | Y35: 91.258469 | Z35: 91.26207 | AA35: 90.867805 | AB35: 90.204437 | AC35: 90.217529 | AD35: 90.671394 | AE35: 91.196381 | AF35: 91.801018 | AG35: 92.411949 | AH35: 93.083488 | AI35: 0.005
A36: ISM000:ga_PrimaryMetals | C36: Primary Metals Industry | D36: Industrial Macroeconomic: Manufacturing: Primary Metals Industry: High Zero-Carbon Technology Cost | E36: AEO.2025.HIGHZTC.ECI_VOS_MANF_PMM_NA_NA_NA_BLNY09DLR.A | F36: billion 2012 $ | H36: 244.86504 | I36: 248.52803 | J36: 255.5425 | K36: 258.2749 | L36: 258.45053 | M36: 259.36414 | N36: 262.41397 | O36: 266.26843 | P36: 270.27884 | Q36: 271.53186 | R36: 274.66315 | S36: 277.69369 | T36: 280.42725 | U36: 284.75626 | V36: 288.45294 | W36: 292.01385 | X36: 297.0069 | Y36: 300.80423 | Z36: 303.9722 | AA36: 308.31238 | AB36: 311.88547 | AC36: 314.56079 | AD36: 316.64414 | AE36: 319.67554 | AF36: 321.56711 | AG36: 322.92242 | AH36: 324.23212 | AI36: 0.011
A37: ISM000:ga_BlastFurnacea | B37: ,ISIC 241, | C37: Iron and Steel Mills and Products | D37: Industrial Macroeconomic: Manufacturing: Primary Metals: Iron and Steel Mills and Products: High Zero-Carbon Technology Cost | E37: AEO.2025.HIGHZTC.ECI_VOS_MANF_ISM_NA_NA_NA_BLNY09DLR.A | F37: billion 2012 $ | H37: 131.32573 | I37: 134.93411 | J37: 141.45989 | K37: 142.77377 | L37: 141.88794 | M37: 141.74979 | N37: 143.73824 | O37: 146.53499 | P37: 149.38496 | Q37: 149.45511 | R37: 151.37814 | S37: 153.10629 | T37: 154.5363 | U37: 157.53503 | V37: 159.87338 | W37: 162.08472 | X37: 165.73244 | Y37: 168.19681 | Z37: 170.0643 | AA37: 173.14265 | AB37: 175.5089 | AC37: 177.0495 | AD37: 178.07887 | AE37: 180.09767 | AF37: 181.03627 | AG37: 181.49979 | AH37: 181.98811 | AI37: 0.013
A38: ISM000:ga_Aluminum | B38: ,ISIC 242, | C38: Alumina and Aluminum Products | D38: Industrial Macroeconomic: Manufacturing: Primary Metals: Alumina and Aluminum Products: High Zero-Carbon Technology Cost | E38: AEO.2025.HIGHZTC.ECI_VOS_MANF_AAP_NA_NA_NA_BLNY09DLR.A | F38: billion 2012 $ | H38: 34.597599 | I38: 34.167324 | J38: 34.714939 | K38: 35.325741 | L38: 35.804806 | M38: 36.362534 | N38: 36.869461 | O38: 37.424278 | P38: 38.041748 | Q38: 38.662601 | R38: 39.322857 | S38: 40.049435 | T38: 40.793427 | U38: 41.567074 | V38: 42.354301 | W38: 43.131817 | X38: 43.905979 | Y38: 44.671326 | Z38: 45.415844 | AA38: 46.116341 | AB38: 46.751091 | AC38: 47.299404 | AD38: 47.767883 | AE38: 48.191673 | AF38: 48.568092 | AG38: 48.904499 | AH38: 49.198971 | AI38: 0.014
A39: ISM000:ga_OtherPrimaryM | B39: ,ISIC 242, | C39: Other Primary Metal Products | D39: Industrial Macroeconomic: Manufacturing: Primary Metals: Other Primary Metal Products: High Zero-Carbon Technology Cost | E39: AEO.2025.HIGHZTC.ECI_VOS_MANF_PMO_NA_NA_NA_BLNY09DLR.A | F39: billion 2012 $ | H39: 78.941711 | I39: 79.426582 | J39: 79.367668 | K39: 80.175369 | L39: 80.75779 | M39: 81.251801 | N39: 81.806282 | O39: 82.309166 | P39: 82.852135 | Q39: 83.414146 | R39: 83.962135 | S39: 84.537956 | T39: 85.097519 | U39: 85.654175 | V39: 86.225258 | W39: 86.797302 | X39: 87.368469 | Y39: 87.936096 | Z39: 88.492043 | AA39: 89.053383 | AB39: 89.625504 | AC39: 90.211868 | AD39: 90.797394 | AE39: 91.3862 | AF39: 91.962723 | AG39: 92.518127 | AH39: 93.045013 | AI39: 0.006
A40: ISM000:ga_FabricatedMet | B40: ,ISIC 25, | C40: Fabricated Metal Products | D40: Industrial Macroeconomic: Manufacturing: Fabricated Metal Products: High Zero-Carbon Technology Cost | E40: AEO.2025.HIGHZTC.ECI_VOS_MANF_FBP_NA_NA_NA_BLNY09DLR.A | F40: billion 2012 $ | H40: 302.45358 | I40: 308.42365 | J40: 320.7533 | K40: 328.51697 | L40: 329.17981 | M40: 329.98978 | N40: 332.51956 | O40: 335.4873 | P40: 338.85028 | Q40: 339.64154 | R40: 343.30469 | S40: 344.99402 | T40: 347.50638 | U40: 351.45007 | V40: 354.34689 | W40: 357.36279 | X40: 361.16931 | Y40: 363.91495 | Z40: 366.68784 | AA40: 368.30096 | AB40: 371.01907 | AC40: 372.19131 | AD40: 374.32022 | AE40: 376.14328 | AF40: 377.55277 | AG40: 379.67996 | AH40: 379.72183 | AI40: 0.009
A41: ISM000:ga_IndustrialMac | B41: ,ISIC 28, | C41: Machinery | D41: Industrial Macroeconomic: Manufacturing: Machinery: High Zero-Carbon Technology Cost | E41: AEO.2025.HIGHZTC.ECI_VOS_MANF_MCHI_NA_NA_NA_BLNY09DLR.A | F41: billion 2012 $ | H41: 298.00757 | I41: 301.46787 | J41: 307.617 | K41: 319.3667 | L41: 326.12961 | M41: 331.91284 | N41: 338.64636 | O41: 343.72708 | P41: 348.29407 | Q41: 349.59146 | R41: 352.93121 | S41: 355.55087 | T41: 358.41681 | U41: 361.28418 | V41: 362.44919 | W41: 363.33536 | X41: 364.77499 | Y41: 365.61197 | Z41: 366.47958 | AA41: 366.93137 | AB41: 367.69513 | AC41: 367.91858 | AD41: 368.88498 | AE41: 370.44449 | AF41: 370.69086 | AG41: 371.66428 | AH41: 371.93857 | AI41: 0.009
A42: ISM000:ga_Electronicand | B42: ,ISIC 26, | C42: Computers and Electronics | D42: Industrial Macroeconomic: Manufacturing: Computers and Electronics: High Zero-Carbon Technology Cost | E42: AEO.2025.HIGHZTC.ECI_VOS_MANF_CMPEL_NA_NA_NA_BLNY09DLR.A | F42: billion 2012 $ | H42: 440.02228 | I42: 457.77365 | J42: 467.24835 | K42: 485.61023 | L42: 505.60599 | M42: 521.77954 | N42: 537.289 | O42: 552.02997 | P42: 567.71088 | Q42: 579.98846 | R42: 593.50488 | S42: 608.81079 | T42: 626.12176 | U42: 643.88788 | V42: 661.97846 | W42: 681.56665 | X42: 702.5965 | Y42: 724.23218 | Z42: 746.66785 | AA42: 768.78619 | AB42: 792.41302 | AC42: 815.7619 | AD42: 841.44476 | AE42: 868.17761 | AF42: 895.31726 | AG42: 922.96326 | AH42: 950.84961 | AI42: 0.03
A43: ISM000:ga_Transportatio | B43: ,ISIC 29,ISIC 302T309, | C43: Transportation Equipment | D43: Industrial Macroeconomic: Manufacturing: Transportation Equipment: High Zero-Carbon Technology Cost | E43: AEO.2025.HIGHZTC.ECI_VOS_MANF_TEQ_NA_NA_NA_BLNY09DLR.A | F43: billion 2012 $ | H43: 1067.6899 | I43: 1135.0959 | J43: 1211.5575 | K43: 1234.714 | L43: 1260.626 | M43: 1284.1858 | N43: 1298.3617 | O43: 1299.6274 | P43: 1310.2197 | Q43: 1323.2843 | R43: 1352.7478 | S43: 1371.8915 | T43: 1384.062 | U43: 1398.4255 | V43: 1415.8612 | W43: 1434.6405 | X43: 1452.1932 | Y43: 1466.6412 | Z43: 1482.1952 | AA43: 1494.6827 | AB43: 1508.6281 | AC43: 1524.235 | AD43: 1539.3557 | AE43: 1554.1062 | AF43: 1568.6698 | AG43: 1581.3815 | AH43: 1589.3907 | AI43: 0.015
A44: ISM000:ga_Instrumentsan | B44: ,ISIC 27, | C44: Electrical Equipment | D44: Industrial Macroeconomic: Manufacturing: Electrical Equipment: High Zero-Carbon Technology Cost | E44: AEO.2025.HIGHZTC.ECI_VOS_MANF_EEQ_NA_NA_NA_BLNY09DLR.A | F44: billion 2012 $ | H44: 117.17452 | I44: 117.89025 | J44: 117.05665 | K44: 118.63743 | L44: 121.1516 | M44: 122.9899 | N44: 124.64062 | O44: 125.65285 | P44: 126.7785 | Q44: 126.76083 | R44: 126.97958 | S44: 127.5349 | T44: 128.18622 | U44: 128.97725 | V44: 129.6022 | W44: 130.39653 | X44: 131.37585 | Y44: 132.2148 | Z44: 133.01923 | AA44: 133.66067 | AB44: 134.38882 | AC44: 134.90305 | AD44: 135.61032 | AE44: 136.45515 | AF44: 137.00888 | AG44: 137.57597 | AH44: 137.9623 | AI44: 0.006
A45: ISM000:ga_Miscellaneous | B45: ,ISIC 31T33, | C45: Miscellaneous Manufacturing | D45: Industrial Macroeconomic: Manufacturing: Miscellaneous Manufacturing: High Zero-Carbon Technology Cost | E45: AEO.2025.HIGHZTC.ECI_VOS_MANF_MISC_NA_NA_NA_BLNY09DLR.A | F45: billion 2012 $ | H45: 153.33037 | I45: 157.28622 | J45: 161.45157 | K45: 166.08694 | L45: 170.00337 | M45: 172.20496 | N45: 174.9388 | O45: 177.68588 | P45: 181.15735 | Q45: 182.86475 | R45: 184.45093 | S45: 186.48675 | T45: 188.98085 | U45: 191.5983 | V45: 193.246 | W45: 194.85245 | X45: 196.92516 | Y45: 199.0097 | Z45: 201.02315 | AA45: 202.8374 | AB45: 204.95595 | AC45: 206.37453 | AD45: 208.37825 | AE45: 210.46848 | AF45: 211.74797 | AG45: 214.56938 | AH45: 214.75027 | AI45: 0.013
A46: ISM000:ha_TotalIndustri | C46: Total Industrial Value of Shipments | D46: Industrial Macroeconomic: Total Industrial Value of Shipments: High Zero-Carbon Technology Cost | E46: AEO.2025.HIGHZTC.ECI_VOS_IDAL_NA_NA_NA_NA_BLNY09DLR.A | F46: billion 2012 $ | H46: 8693.2158 | I46: 8880.0215 | J46: 9023.8906 | K46: 9136.9668 | L46: 9250.2939 | M46: 9368.2061 | N46: 9471.4023 | O46: 9544.3271 | P46: 9631.375 | Q46: 9680.8301 | R46: 9759.0693 | S46: 9833.1797 | T46: 9910.9326 | U46: 9985.4961 | V46: 10063.266 | W46: 10146.551 | X46: 10240.19 | Y46: 10320.271 | Z46: 10409.384 | AA46: 10482.779 | AB46: 10564.851 | AC46: 10653.482 | AD46: 10756.961 | AE46: 10868.238 | AF46: 10969.666 | AG46: 11079.728 | AH46: 11173.775 | AI46: 0.01

Sheet AEO 2026 Table 23 
C1: Table 23. Industrial Sector Macroeconomic Indicators
C2: https://www.eia.gov/outlooks/aeo/data/browser/#/?id=34-AEO2026&cases=electrnp&sourcekey=0
C3: Thu Apr 23 2026 15:01:03 GMT-0700 (Pacific Daylight Time)
C4: Source: U.S. Energy Information Administration
B5: ISIC assignment (editable) | D5: full name | E5: api key | F5: units | G5: 2025 | H5: 2026 | I5: 2027 | J5: 2028 | K5: 2029 | L5: 2030 | M5: 2031 | N5: 2032 | O5: 2033 | P5: 2034 | Q5: 2035 | R5: 2036 | S5: 2037 | T5: 2038 | U5: 2039 | V5: 2040 | W5: 2041 | X5: 2042 | Y5: 2043 | Z5: 2044 | AA5: 2045 | AB5: 2046 | AC5: 2047 | AD5: 2048 | AE5: 2049 | AF5: 2050 | AG5: Growth (2025-2050)
A6: ISM000:ba_GDP(billionm_ | C6: Gross Domestic Product (billion 2012 dollars) | D6: Industrial Macroeconomic: Gross Domestic Product: Alternative Electricity and Transportation | E6: AEO.2026.ELECTRNP.ECI_GDP_NA_NA_NA_NA_NA_BLNY09DLR.A | F6: billion 2012 $ | G6: 22086.084 | H6: 22669.975 | I6: 23095.641 | J6: 23390.617 | K6: 23750.76 | L6: 24166.652 | M6: 24572.645 | N6: 25034.145 | O6: 25522.301 | P6: 26041.154 | Q6: 26595.578 | R6: 27063.66 | S6: 27531.34 | T6: 28000.277 | U6: 28461.051 | V6: 28925.545 | W6: 29375.912 | X6: 29841.965 | Y6: 30321.672 | Z6: 30806.215 | AA6: 31294.172 | AB6: 31769.938 | AC6: 32226.467 | AD6: 32681.023 | AE6: 33125.082 | AF6: 33582.949 | AG6: 0.017
A7: ISM000:ca_NonfarmEmploy | C7: Nonfarm Employment (millions) | D7: Industrial Macroeconomic: Employment, Nonfarm: Alternative Electricity and Transportation | E7: AEO.2026.ELECTRNP.ECI_NFE_NA_NA_NA_NA_NA_MILL.A | F7: millions | G7: 160.34007 | H7: 161.28101 | I7: 162.17047 | J7: 162.60861 | K7: 163.08629 | L7: 163.62587 | M7: 164.11606 | N7: 164.78729 | O7: 165.46202 | P7: 166.1698 | Q7: 166.88487 | R7: 167.66199 | S7: 168.56576 | T7: 169.43977 | U7: 170.1514 | V7: 170.95247 | W7: 171.58038 | X7: 172.17842 | Y7: 172.70612 | Z7: 173.32774 | AA7: 174.0012 | AB7: 174.60243 | AC7: 175.09766 | AD7: 175.47995 | AE7: 175.77896 | AF7: 176.12506 | AG7: 0.004
C8: Value of Shipments (billion 2012 dollars)
C9: Nonmanufacturing Sector
A10: ISM000:ea_Agricultural | B10: ,ISIC 01, | C10: Agriculture/Forestry/Fishing/Hunting | D10: Industrial Macroeconomic: Nonmanufacturing: Agriculture/Forestry/Fishing/Hunting: Alternative Electricity and Transportation | E10: AEO.2026.ELECTRNP.ECI_VOS_NMFG_AFF_NA_NA_NA_BLNY09DLR.A | F10: billion 2012 $ | G10: 485.34998 | H10: 486.52557 | I10: 493.37537 | J10: 503.25858 | K10: 509.90396 | L10: 516.43335 | M10: 522.85254 | N10: 529.38611 | O10: 532.95337 | P10: 539.97076 | Q10: 547.71857 | R10: 555.45874 | S10: 562.9729 | T10: 570.92297 | U10: 579.125 | V10: 586.07172 | W10: 592.65619 | X10: 599.99512 | Y10: 606.93585 | Z10: 614.49286 | AA10: 623.08154 | AB10: 632.104 | AC10: 641.20709 | AD10: 650.44 | AE10: 659.60828 | AF10: 668.85413 | AG10: 0.013
A11: ISM000:ea_Mining | B11: ,ISIC 05,ISIC 06,ISIC 08, | C11: Mining | D11: Industrial Macroeconomic: Nonmanufacturing: Mining: Alternative Electricity and Transportation | E11: AEO.2026.ELECTRNP.ECI_VOS_NMFG_MING_NA_NA_NA_BLNY09DLR.A | F11: billion 2012 $ | G11: 791.22412 | H11: 863.60974 | I11: 857.47864 | J11: 862.24182 | K11: 867.37317 | L11: 886.0852 | M11: 900.35944 | N11: 913.71997 | O11: 923.65027 | P11: 935.96826 | Q11: 939.37109 | R11: 943.46912 | S11: 948.6922 | T11: 953.50342 | U11: 959.69214 | V11: 971.02344 | W11: 984.75244 | X11: 992.50195 | Y11: 1001.0425 | Z11: 1006.1229 | AA11: 1009.7766 | AB11: 1013.5451 | AC11: 1019.1384 | AD11: 1021.3472 | AE11: 1021.3635 | AF11: 1019.4868 | AG11: 0.01
A12: ISM000:ea_Construction | B12: ,ISIC 41T43, | C12: Construction | D12: Industrial Macroeconomic: Nonmanufacturing: Construction: Alternative Electricity and Transportation | E12: AEO.2026.ELECTRNP.ECI_VOS_NMFG_CNS_NA_NA_NA_BLNY09DLR.A | F12: billion 2012 $ | G12: 1526.77 | H12: 1521.3313 | I12: 1530.4597 | J12: 1540.0048 | K12: 1565.4055 | L12: 1591.653 | M12: 1615.953 | N12: 1640.3335 | O12: 1660.85 | P12: 1674.0291 | Q12: 1692.3223 | R12: 1708.3278 | S12: 1722.0208 | T12: 1733.7163 | U12: 1743.8199 | V12: 1750.1165 | W12: 1754.2722 | X12: 1764.618 | Y12: 1772.1407 | Z12: 1781.1648 | AA12: 1798.493 | AB12: 1816.6458 | AC12: 1833.3215 | AD12: 1850.2052 | AE12: 1869.444 | AF12: 1891.599 | AG12: 0.009
C13: Manufacturing Sector
A14: ISM000:fa_FoodandKindre | B14: ,ISIC 10T12, | C14: Food Products | D14: Industrial Macroeconomic: Manufacturing: Food Products: Alternative Electricity and Transportation | E14: AEO.2026.ELECTRNP.ECI_VOS_MANF_FPA_NA_NA_NA_BLNY09DLR.A | F14: billion 2012 $ | G14: 762.71002 | H14: 766.6488 | I14: 776.75324 | J14: 786.11645 | K14: 792.97131 | L14: 801.68433 | M14: 810.93811 | N14: 819.74689 | O14: 828.72485 | P14: 838.03882 | Q14: 846.84888 | R14: 856.58661 | S14: 866.08649 | T14: 875.84137 | U14: 885.78131 | V14: 894.87964 | W14: 903.73852 | X14: 912.51666 | Y14: 921.0224 | Z14: 929.5047 | AA14: 937.15027 | AB14: 945.1366 | AC14: 953.13153 | AD14: 961.09613 | AE14: 969.4184 | AF14: 977.19104 | AG14: 0.01
A15: ISM000:fa_BeveragesandT | B15: ,ISIC 10T12, | C15: Beverages and Tobacco Products | D15: Industrial Macroeconomic: Manufacturing: Beverages and Tobacco Products: Alternative Electricity and Transportation | E15: AEO.2026.ELECTRNP.ECI_VOS_MANF_BVTP_NA_NA_NA_BLNY09DLR.A | F15: billion 2012 $ | G15: 145.14 | H15: 143.29698 | I15: 141.07892 | J15: 139.88065 | K15: 138.8069 | L15: 137.82715 | M15: 136.89218 | N15: 136.1991 | O15: 135.47145 | P15: 134.65437 | Q15: 133.95633 | R15: 133.1942 | S15: 132.51904 | T15: 131.79112 | U15: 130.83189 | V15: 130.09213 | W15: 129.5887 | X15: 129.14653 | Y15: 128.57558 | Z15: 128.06078 | AA15: 127.7637 | AB15: 127.40795 | AC15: 126.8901 | AD15: 126.3991 | AE15: 125.8749 | AF15: 125.28133 | AG15: -0.006
A16: ISM000:fa_TextileMillPr | B16: ,ISIC 13T15, | C16: Textile Mills and Products | D16: Industrial Macroeconomic: Manufacturing: Textile Mills and Products: Alternative Electricity and Transportation | E16: AEO.2026.ELECTRNP.ECI_VOS_MANF_TMP_NA_NA_NA_BLNY09DLR.A | F16: billion 2012 $ | G16: 58.60323 | H16: 59.344818 | I16: 60.159962 | J16: 58.416599 | K16: 56.206123 | L16: 55.21006 | M16: 54.903446 | N16: 54.746746 | O16: 54.889694 | P16: 55.283863 | Q16: 55.522114 | R16: 55.493893 | S16: 55.565697 | T16: 55.676113 | U16: 55.728962 | V16: 55.944988 | W16: 56.146873 | X16: 56.280396 | Y16: 56.407085 | Z16: 56.575737 | AA16: 56.78751 | AB16: 56.890766 | AC16: 56.785236 | AD16: 56.510384 | AE16: 56.437035 | AF16: 56.381992 | AG16: -0.002
A17: ISM000:fa_LumberandWood | B17: ,ISIC 16, | C17: Wood Products | D17: Industrial Macroeconomic: Manufacturing: Wood Products: Alternative Electricity and Transportation | E17: AEO.2026.ELECTRNP.ECI_VOS_MANF_WDP_NA_NA_NA_BLNY09DLR.A | F17: billion 2012 $ | G17: 118.725 | H17: 99.63253 | I17: 93.661903 | J17: 98.211769 | K17: 105.91305 | L17: 107.0631 | M17: 104.34275 | N17: 104.02138 | O17: 106.39807 | P17: 110.546 | Q17: 113.7761 | R17: 117.1022 | S17: 119.56847 | T17: 122.23325 | U17: 124.19093 | V17: 124.83405 | W17: 122.58537 | X17: 121.28372 | Y17: 118.8681 | Z17: 117.27795 | AA17: 118.01935 | AB17: 118.72787 | AC17: 119.79555 | AD17: 120.763 | AE17: 122.42195 | AF17: 123.7975 | AG17: 0.002
A18: ISM000:fa_FurnitureandF | B18: ,ISIC 31T33, | C18: Furniture and Related Products | D18: Industrial Macroeconomic: Manufacturing: Furniture and Related Products: Alternative Electricity and Transportation | E18: AEO.2026.ELECTRNP.ECI_VOS_MANF_FRP_NA_NA_NA_BLNY09DLR.A | F18: billion 2012 $ | G18: 58.322498 | H18: 59.011951 | I18: 60.173313 | J18: 59.152695 | K18: 59.48531 | L18: 60.807999 | M18: 61.878868 | N18: 63.159161 | O18: 64.566895 | P18: 65.938286 | Q18: 68.118446 | R18: 69.331093 | S18: 70.475876 | T18: 72.192848 | U18: 73.151497 | V18: 74.659355 | W18: 76.165657 | X18: 77.674377 | Y18: 79.193832 | Z18: 80.946732 | AA18: 83.448448 | AB18: 84.887985 | AC18: 86.415627 | AD18: 87.191368 | AE18: 88.336067 | AF18: 89.970726 | AG18: 0.017
A19: ISM000:fa_PaperandAllie | B19: ,ISIC 17T18, | C19: Paper Products | D19: Industrial Macroeconomic: Manufacturing: Paper Products: Alternative Electricity and Transportation | E19: AEO.2026.ELECTRNP.ECI_VOS_MANF_PPM_NA_NA_NA_BLNY09DLR.A | F19: billion 2012 $ | G19: 146.52499 | H19: 146.30009 | I19: 148.3551 | J19: 148.39004 | K19: 148.27515 | L19: 148.2298 | M19: 149.00885 | N19: 149.76033 | O19: 150.41437 | P19: 151.04452 | Q19: 151.76538 | R19: 152.44345 | S19: 152.84227 | T19: 153.86858 | U19: 155.21448 | V19: 156.88922 | W19: 158.34563 | X19: 159.91808 | Y19: 161.62904 | Z19: 163.46222 | AA19: 165.47505 | AB19: 167.21362 | AC19: 169.04817 | AD19: 170.64967 | AE19: 172.45003 | AF19: 174.19078 | AG19: 0.007
A20: ISM000:fa_PrintingandPu | B20: ,ISIC 17T18, | C20: Printing | D20: Industrial Macroeconomic: Manufacturing: Printing: Alternative Electricity and Transportation | E20: AEO.2026.ELECTRNP.ECI_VOS_MANF_PRN_NA_NA_NA_BLNY09DLR.A | F20: billion 2012 $ | G20: 64.357498 | H20: 62.670582 | I20: 60.88274 | J20: 59.342823 | K20: 58.132961 | L20: 56.884991 | M20: 55.614899 | N20: 54.24551 | O20: 52.755295 | P20: 51.431721 | Q20: 50.014038 | R20: 48.692402 | S20: 47.663521 | T20: 46.690609 | U20: 46.016659 | V20: 45.447735 | W20: 44.834614 | X20: 44.365486 | Y20: 43.841122 | Z20: 43.243725 | AA20: 42.610481 | AB20: 42.079239 | AC20: 41.707779 | AD20: 41.560303 | AE20: 41.430828 | AF20: 41.002571 | AG20: -0.018
A21: ISM000:fa_ChemicalandAl | B21: ,ISIC 20, | C21: Chemical Manufacturing | D21: Industrial Macroeconomic: Manufacturing: Chemical Manufacturing: Alternative Electricity and Transportation | E21: AEO.2026.ELECTRNP.ECI_VOS_MANF_CHE_NA_NA_NA_BLNY09DLR.A | F21: billion 2012 $ | G21: 866.14447 | H21: 854.60504 | I21: 844.64343 | J21: 841.27881 | K21: 834.1626 | L21: 833.86487 | M21: 837.70923 | N21: 842.62769 | O21: 851.86352 | P21: 861.18933 | Q21: 871.22015 | R21: 881.64966 | S21: 893.15485 | T21: 904.77008 | U21: 918.34717 | V21: 932.80969 | W21: 949.00275 | X21: 967.69165 | Y21: 985.70813 | Z21: 1004.382 | AA21: 1024.8037 | AB21: 1046.9314 | AC21: 1070.0601 | AD21: 1091.0392 | AE21: 1111.1675 | AF21: 1133.6318 | AG21: 0.011
A22: ISM000:fa_BulkChemicals | C22: Bulk Chemicals | D22: Industrial Macroeconomic: Manufacturing: Chemicals: Bulk Chemicals: Alternative Electricity and Transportation | E22: AEO.2026.ELECTRNP.ECI_VOS_MANF_BCH_NA_NA_NA_BLNY09DLR.A | F22: billion 2012 $ | G22: 389.91446 | H22: 374.33463 | I22: 368.80945 | J22: 367.27594 | K22: 361.54742 | L22: 361.8844 | M22: 365.39737 | N22: 366.77454 | O22: 369.9859 | P22: 373.71805 | Q22: 378.38687 | R22: 383.46777 | S22: 388.05298 | T22: 392.6192 | U22: 399.43426 | V22: 406.02402 | W22: 412.86163 | X22: 420.91342 | Y22: 427.61038 | Z22: 434.30237 | AA22: 442.08344 | AB22: 450.44989 | AC22: 459.5007 | AD22: 467.66095 | AE22: 474.06464 | AF22: 482.12265 | AG22: 0.009
A23: ISM000:fa_Inorganic | C23: Inorganic | D23: Industrial Macroeconomic: Manufacturing: Chemicals: Bulk Chemicals: Inorganic: Alternative Electricity and Transportation | E23: AEO.2026.ELECTRNP.ECI_VOS_MANF_CHEIN_NA_NA_NA_BLNY09DLR.A | F23: billion 2012 $ | G23: 51.491623 | H23: 52.255329 | I23: 51.697498 | J23: 51.97789 | K23: 51.210506 | L23: 50.927029 | M23: 51.219692 | N23: 51.075771 | O23: 51.268539 | P23: 51.611919 | Q23: 51.78804 | R23: 51.978779 | S23: 51.913784 | T23: 51.978077 | U23: 52.200249 | V23: 52.240593 | W23: 52.3074 | X23: 52.404572 | Y23: 52.432655 | Z23: 52.335209 | AA23: 52.231144 | AB23: 52.381222 | AC23: 52.576962 | AD23: 52.698147 | AE23: 52.773537 | AF23: 52.96476 | AG23: 0.001
A24: ISM000:fa_Organic | C24: Organic | D24: Industrial Macroeconomic: Manufacturing: Chemicals: Bulk Chemicals: Organic: Alternative Electricity and Transportation | E24: AEO.2026.ELECTRNP.ECI_VOS_MANF_CHEOR_NA_NA_NA_BLNY09DLR.A | F24: billion 2012 $ | G24: 184.63533 | H24: 169.54507 | I24: 162.99795 | J24: 163.28098 | K24: 159.4751 | L24: 158.51843 | M24: 160.61568 | N24: 162.61992 | O24: 165.4667 | P24: 168.74754 | Q24: 171.98885 | R24: 176.30659 | S24: 178.54918 | T24: 181.37653 | U24: 186.22255 | V24: 190.33916 | W24: 194.99503 | X24: 200.03682 | Y24: 205.30133 | Z24: 211.08353 | AA24: 217.31682 | AB24: 223.62242 | AC24: 229.46664 | AD24: 235.0215 | AE24: 239.40428 | AF24: 244.6778 | AG24: 0.011
A25: ISM000:fa_Resins | C25: Resin | D25: Synthetic Rubber | E25: and Fibers | F25: Industrial Macroeconomic: Manufacturing: Chemicals: Bulk Chemicals: Resin, Synthetic Rubber, and Fibers: Alternative Electricity and Transportation | G25: AEO.2026.ELECTRNP.ECI_VOS_MANF_CHEBR_NA_NA_NA_BLNY09DLR.A | H25: billion 2012 $ | I25: 112.3475 | J25: 111.06512 | K25: 112.16788 | L25: 110.21043 | M25: 109.01678 | N25: 110.27058 | O25: 111.02355 | P25: 110.38338 | Q25: 110.30038 | R25: 110.13205 | S25: 110.97907 | T25: 111.197 | U25: 113.11678 | V25: 114.37852 | W25: 115.73042 | X25: 117.6879 | Y25: 119.25335 | Z25: 121.62275 | AA25: 122.51125 | AB25: 123.04223 | AC25: 123.99895 | AD25: 125.265 | AE25: 127.58845 | AF25: 129.46645 | AG25: 130.94455 | AH25: 132.97212 | AI25: 0.007
A26: ISM000:fa_AgriculturalC | C26: Agricultural Chemicals | D26: Industrial Macroeconomic: Manufacturing: Chemicals: Bulk Chemicals: Agricultural Chemicals: Alternative Electricity and Transportation | E26: AEO.2026.ELECTRNP.ECI_VOS_MANF_AGC_NA_NA_NA_BLNY09DLR.A | F26: billion 2012 $ | G26: 41.439999 | H26: 41.469086 | I26: 41.946102 | J26: 41.806648 | K26: 41.845043 | L26: 42.168369 | M26: 42.538464 | N26: 42.695454 | O26: 42.950291 | P26: 43.226524 | Q26: 43.630913 | R26: 43.985401 | S26: 44.473221 | T26: 44.886093 | U26: 45.281067 | V26: 45.756378 | W26: 46.305859 | X26: 46.84927 | Y26: 47.365139 | Z26: 47.841415 | AA26: 48.536507 | AB26: 49.181259 | AC26: 49.868652 | AD26: 50.474846 | AE26: 50.942249 | AF26: 51.507961 | AG26: 0.009
A27: ISM000:fa_OtherChemical | C27: Other Chemical Products | D27: Industrial Macroeconomic: Manufacturing: Chemicals: Other Chemical Products: Alternative Electricity and Transportation | E27: AEO.2026.ELECTRNP.ECI_VOS_MANF_CHEO_NA_NA_NA_BLNY09DLR.A | F27: billion 2012 $ | G27: 476.23001 | H27: 480.27042 | I27: 475.83402 | J27: 474.00284 | K27: 472.61517 | L27: 471.9805 | M27: 472.31189 | N27: 475.85318 | O27: 481.87759 | P27: 487.47125 | Q27: 492.83328 | R27: 498.18185 | S27: 505.10187 | T27: 512.15088 | U27: 518.9129 | V27: 526.78571 | W27: 536.14111 | X27: 546.7782 | Y27: 558.09772 | Z27: 570.07965 | AA27: 582.72028 | AB27: 596.48151 | AC27: 610.55933 | AD27: 623.37824 | AE27: 637.10284 | AF27: 651.50915 | AG27: 0.013
A28: ISM000:fa_PetroleumandC | C28: Petroleum and Coal Products | D28: Industrial Macroeconomic: Manufacturing: Petroleum and Coal Products: Alternative Electricity and Transportation | E28: AEO.2026.ELECTRNP.ECI_VOS_MANF_PCL_NA_NA_NA_BLNY09DLR.A | F28: billion 2012 $ | G28: 812.46875 | H28: 815.59912 | I28: 814.62958 | J28: 812.44067 | K28: 805.56982 | L28: 801.77545 | M28: 797.0885 | N28: 795.29706 | O28: 793.849 | P28: 794.52423 | Q28: 795.7514 | R28: 793.12036 | S28: 787.33997 | T28: 781.7132 | U28: 778.87054 | V28: 777.97797 | W28: 779.20483 | X28: 777.89734 | Y28: 774.04761 | Z28: 769.80383 | AA28: 765.90613 | AB28: 766.34454 | AC28: 767.62952 | AD28: 764.87122 | AE28: 763.11072 | AF28: 762.69849 | AG28: -0.003
A29: ISM000:fa_PetroleumRefi | B29: ,ISIC 19, | C29: Petroleum Refineries | D29: Industrial Macroeconomic: Manufacturing: Petroleum and Coal: Petroleum Refineries: Alternative Electricity and Transportation | E29: AEO.2026.ELECTRNP.ECI_VOS_MANF_REF_NA_NA_NA_BLNY09DLR.A | F29: billion 2012 $ | G29: 774.53998 | H29: 777.53735 | I29: 776.06775 | J29: 773.3844 | K29: 766.23871 | L29: 762.01086 | M29: 756.96893 | N29: 754.9978 | O29: 753.4519 | P29: 754.0094 | Q29: 755.11731 | R29: 752.42364 | S29: 746.49103 | T29: 740.76801 | U29: 737.8125 | V29: 736.7052 | W29: 737.79657 | X29: 736.50989 | Y29: 732.66779 | Z29: 728.45471 | AA29: 724.67084 | AB29: 725.17279 | AC29: 726.47797 | AD29: 723.81842 | AE29: 722.17981 | AF29: 721.8551 | AG29: -0.003
A30: ISM000:fa_OtherPetroleu | B30: ,ISIC 241, | C30: Other Petroleum and Coal Products | D30: Industrial Macroeconomic: Manufacturing: Petroleum and Coal: Other Petroleum & Coal Products: Alternative Electricity and Transportation | E30: AEO.2026.ELECTRNP.ECI_VOS_MANF_PCLO_NA_NA_NA_BLNY09DLR.A | F30: billion 2012 $ | G30: 37.928802 | H30: 38.061752 | I30: 38.561806 | J30: 39.056305 | K30: 39.331112 | L30: 39.764568 | M30: 40.11956 | N30: 40.299236 | O30: 40.397125 | P30: 40.514839 | Q30: 40.634068 | R30: 40.696747 | S30: 40.848927 | T30: 40.945206 | U30: 41.058052 | V30: 41.272781 | W30: 41.408283 | X30: 41.387432 | Y30: 41.379841 | Z30: 41.349102 | AA30: 41.235302 | AB30: 41.17173 | AC30: 41.151543 | AD30: 41.052803 | AE30: 40.930908 | AF30: 40.843361 | AG30: 0.003
A31: ISM000:fa_RubberandMisc | B31: ,ISIC 22, | C31: Plastics and Rubber Products | D31: Industrial Macroeconomic: Manufacturing: Plastics and Rubber Products: Alternative Electricity and Transportation | E31: AEO.2026.ELECTRNP.ECI_VOS_MANF_PRP_NA_NA_NA_BLNY09DLR.A | F31: billion 2012 $ | G31: 216.0925 | H31: 214.8234 | I31: 219.6775 | J31: 222.33086 | K31: 223.29581 | L31: 225.64897 | M31: 228.33862 | N31: 229.98912 | O31: 231.52588 | P31: 232.55505 | Q31: 234.36923 | R31: 237.0793 | S31: 240.29485 | T31: 243.16901 | U31: 245.56535 | V31: 248.44893 | W31: 251.36266 | X31: 254.49283 | Y31: 257.41254 | Z31: 260.39548 | AA31: 263.66223 | AB31: 266.49383 | AC31: 269.10242 | AD31: 271.19577 | AE31: 274.12976 | AF31: 277.05692 | AG31: 0.01
A32: ISM000:fa_Stone,Clay,an | C32: Non-metallic minerals | D32: Industrial Macroeconomic: Manufacturing: Stone, Clay, and Glass Products: Alternative Electricity and Transportation | E32: AEO.2026.ELECTRNP.ECI_VOS_MANF_SCG_NA_NA_NA_BLNY09DLR.A | F32: billion 2012 $ | G32: 111.71762 | H32: 110.27509 | I32: 108.78667 | J32: 108.49378 | K32: 108.21488 | L32: 108.48045 | M32: 109.16854 | N32: 109.853 | O32: 110.82516 | P32: 111.88461 | Q32: 112.97219 | R32: 114.1003 | S32: 115.13226 | T32: 116.23027 | U32: 117.29462 | V32: 117.99434 | W32: 118.39089 | X32: 118.60862 | Y32: 118.44074 | Z32: 118.10147 | AA32: 118.49583 | AB32: 119.35685 | AC32: 120.24088 | AD32: 121.14365 | AE32: 122.01753 | AF32: 122.99197 | AG32: 0.004
A33: ISM000:fa_GlassandGlass | B33: ,ISIC 231, | C33: Glass and Glass Products | D33: Industrial Macroeconomic: Manufacturing: Stone, Clay, and Glass: Glass and Glass Products: Alternative Electricity and Transportation | E33: AEO.2026.ELECTRNP.ECI_VOS_MANF_SCGG_NA_NA_NA_BLNY09DLR.A | F33: billion 2012 $ | G33: 21.317434 | H33: 21.330378 | I33: 21.382898 | J33: 21.358 | K33: 21.324633 | L33: 21.333778 | M33: 21.370119 | N33: 21.456921 | O33: 21.599215 | P33: 21.778683 | Q33: 22.004484 | R33: 22.229578 | S33: 22.444937 | T33: 22.672058 | U33: 22.897127 | V33: 23.127674 | W33: 23.370462 | X33: 23.622248 | Y33: 23.883127 | Z33: 24.140699 | AA33: 24.406715 | AB33: 24.67695 | AC33: 24.94762 | AD33: 25.221365 | AE33: 25.484995 | AF33: 25.749542 | AG33: 0.008
A34: ISM000:fa_CementandHydr | B34: ,ISIC 239, | C34: Cement and Lime | D34: Industrial Macroeconomic: Manufacturing: Stone, Clay, and Glass: Cement and Lime: Alternative Electricity and Transportation | E34: AEO.2026.ELECTRNP.ECI_VOS_MANF_SCGCL_NA_NA_NA_BLNY09DLR.A | F34: billion 2012 $ | G34: 9.336027 | H34: 9.138749 | I34: 8.976787 | J34: 8.899744 | K34: 8.858376 | L34: 8.879111 | M34: 8.939971 | N34: 9.02407 | O34: 9.135289 | P34: 9.258553 | Q34: 9.389754 | R34: 9.524654 | S34: 9.657454 | T34: 9.793234 | U34: 9.925656 | V34: 10.036542 | W34: 10.121435 | X34: 10.178687 | Y34: 10.198941 | Z34: 10.195507 | AA34: 10.222628 | AB34: 10.289026 | AC34: 10.381219 | AD34: 10.489734 | AE34: 10.605895 | AF34: 10.7287 | AG34: 0.006
A35: ISM000:fa_OtherStone,Cl | B35: ,ISIC 239, | C35: Other Nonmetallic Mineral Products | D35: Industrial Macroeconomic: Manufacturing: Stone, Clay, and Glass: Other Nonmetallic Mineral Products: Alternative Electricity and Transportation | E35: AEO.2026.ELECTRNP.ECI_VOS_MANF_SCGOM_NA_NA_NA_BLNY09DLR.A | F35: billion 2012 $ | G35: 81.064156 | H35: 79.805962 | I35: 78.426987 | J35: 78.236038 | K35: 78.031876 | L35: 78.267563 | M35: 78.858452 | N35: 79.372017 | O35: 80.090652 | P35: 80.847382 | Q35: 81.57795 | R35: 82.346069 | S35: 83.029869 | T35: 83.764977 | U35: 84.47184 | V35: 84.830124 | W35: 84.898994 | X35: 84.807686 | Y35: 84.358673 | Z35: 83.765266 | AA35: 83.866486 | AB35: 84.390877 | AC35: 84.912033 | AD35: 85.432556 | AE35: 85.926636 | AF35: 86.513733 | AG35: 0.003
A36: ISM000:ga_PrimaryMetals | C36: Primary Metals Industry | D36: Industrial Macroeconomic: Manufacturing: Primary Metals Industry: Alternative Electricity and Transportation | E36: AEO.2026.ELECTRNP.ECI_VOS_MANF_PMM_NA_NA_NA_BLNY09DLR.A | F36: billion 2012 $ | G36: 246.75572 | H36: 250.08716 | I36: 255.74016 | J36: 255.59541 | K36: 257.12192 | L36: 260.64471 | M36: 263.58637 | N36: 267.5704 | O36: 271.29825 | P36: 273.56982 | Q36: 276.89011 | R36: 279.22003 | S36: 281.90106 | T36: 284.14255 | U36: 286.10419 | V36: 289.0296 | W36: 292.31088 | X36: 295.6189 | Y36: 298.47379 | Z36: 301.26617 | AA36: 305.13907 | AB36: 308.23111 | AC36: 311.82584 | AD36: 314.93536 | AE36: 316.96918 | AF36: 319.74112 | AG36: 0.01
A37: ISM000:ga_BlastFurnacea | B37: ,ISIC 241, | C37: Iron and Steel Mills and Products | D37: Industrial Macroeconomic: Manufacturing: Primary Metals: Iron and Steel Mills and Products: Alternative Electricity and Transportation | E37: AEO.2026.ELECTRNP.ECI_VOS_MANF_ISM_NA_NA_NA_BLNY09DLR.A | F37: billion 2012 $ | G37: 133.18527 | H37: 136.57104 | I37: 141.48924 | J37: 140.72696 | K37: 141.82077 | L37: 144.79961 | M37: 147.15262 | N37: 150.40752 | O37: 153.23759 | P37: 154.47896 | Q37: 156.599 | R37: 157.66631 | S37: 159.09126 | T37: 160.06988 | U37: 160.77774 | V37: 162.43938 | W37: 164.43352 | X37: 166.44513 | Y37: 168.00439 | Z37: 169.521 | AA37: 172.14064 | AB37: 174.01265 | AC37: 176.44012 | AD37: 178.45138 | AE37: 179.46309 | AF37: 181.26073 | AG37: 0.012
A38: ISM000:ga_Aluminum | B38: ,ISIC 242, | C38: Alumina and Aluminum Products | D38: Industrial Macroeconomic: Manufacturing: Primary Metals: Alumina and Aluminum Products: Alternative Electricity and Transportation | E38: AEO.2026.ELECTRNP.ECI_VOS_MANF_AAP_NA_NA_NA_BLNY09DLR.A | F38: billion 2012 $ | G38: 34.303463 | H38: 34.704796 | I38: 35.137936 | J38: 35.538319 | K38: 35.894688 | L38: 36.223057 | M38: 36.590855 | N38: 37.023113 | O38: 37.529774 | P38: 38.114296 | Q38: 38.792519 | R38: 39.503159 | S38: 40.215851 | T38: 40.931011 | U38: 41.635021 | V38: 42.331554 | W38: 43.032452 | X38: 43.73204 | Y38: 44.414871 | Z38: 45.054203 | AA38: 45.637836 | AB38: 46.167351 | AC38: 46.650509 | AD38: 47.085503 | AE38: 47.473671 | AF38: 47.835384 | AG38: 0.013
A39: ISM000:ga_OtherPrimaryM | B39: ,ISIC 242, | C39: Other Primary Metal Products | D39: Industrial Macroeconomic: Manufacturing: Primary Metals: Other Primary Metal Products: Alternative Electricity and Transportation | E39: AEO.2026.ELECTRNP.ECI_VOS_MANF_PMO_NA_NA_NA_BLNY09DLR.A | F39: billion 2012 $ | G39: 79.266983 | H39: 78.811302 | I39: 79.112976 | J39: 79.330147 | K39: 79.406471 | L39: 79.622047 | M39: 79.842896 | N39: 80.139786 | O39: 80.530861 | P39: 80.976562 | Q39: 81.498573 | R39: 82.050552 | S39: 82.593948 | T39: 83.141647 | U39: 83.691399 | V39: 84.258675 | W39: 84.844894 | X39: 85.441742 | Y39: 86.05452 | Z39: 86.690979 | AA39: 87.360611 | AB39: 88.051102 | AC39: 88.735176 | AD39: 89.398453 | AE39: 90.03241 | AF39: 90.644989 | AG39: 0.005
A40: ISM000:ga_FabricatedMet | B40: ,ISIC 25, | C40: Fabricated Metal Products | D40: Industrial Macroeconomic: Manufacturing: Fabricated Metal Products: Alternative Electricity and Transportation | E40: AEO.2026.ELECTRNP.ECI_VOS_MANF_FBP_NA_NA_NA_BLNY09DLR.A | F40: billion 2012 $ | G40: 310.26749 | H40: 316.87705 | I40: 322.38943 | J40: 319.58441 | K40: 318.39221 | L40: 318.3259 | M40: 318.72214 | N40: 321.75366 | O40: 324.08569 | P40: 328.129 | Q40: 332.0043 | R40: 334.63113 | S40: 337.58502 | T40: 341.10525 | U40: 343.53482 | V40: 346.93414 | W40: 350.07004 | X40: 353.55838 | Y40: 357.13855 | Z40: 362.2135 | AA40: 367.13599 | AB40: 371.48428 | AC40: 373.76889 | AD40: 375.0892 | AE40: 379.121 | AF40: 382.78116 | AG40: 0.008
A41: ISM000:ga_IndustrialMac | B41: ,ISIC 28, | C41: Machinery | D41: Industrial Macroeconomic: Manufacturing: Machinery: Alternative Electricity and Transportation | E41: AEO.2026.ELECTRNP.ECI_VOS_MANF_MCHI_NA_NA_NA_BLNY09DLR.A | F41: billion 2012 $ | G41: 305.26001 | H41: 299.01385 | I41: 306.22296 | J41: 311.98895 | K41: 318.05756 | L41: 322.15585 | M41: 328.44147 | N41: 333.77564 | O41: 334.12036 | P41: 336.71985 | Q41: 341.10483 | R41: 344.25717 | S41: 346.36883 | T41: 347.21533 | U41: 347.32306 | V41: 348.83164 | W41: 350.16537 | X41: 351.42816 | Y41: 352.08035 | Z41: 352.5993 | AA41: 353.70801 | AB41: 355.37061 | AC41: 357.26349 | AD41: 358.30631 | AE41: 358.59338 | AF41: 358.35907 | AG41: 0.006
A42: ISM000:ga_Electronicand | B42: ,ISIC 26, | C42: Computers and Electronics | D42: Industrial Macroeconomic: Manufacturing: Computers and Electronics: Alternative Electricity and Transportation | E42: AEO.2026.ELECTRNP.ECI_VOS_MANF_CMPEL_NA_NA_NA_BLNY09DLR.A | F42: billion 2012 $ | G42: 411.20252 | H42: 415.517 | I42: 431.08682 | J42: 441.41235 | K42: 452.64929 | L42: 461.90463 | M42: 469.32001 | N42: 478.32999 | O42: 484.94519 | P42: 493.50339 | Q42: 503.60901 | R42: 513.61682 | S42: 524.40851 | T42: 535.19141 | U42: 546.87024 | V42: 559.02667 | W42: 570.98047 | X42: 583.86047 | Y42: 597.45813 | Z42: 612.4939 | AA42: 628.37769 | AB42: 645.09314 | AC42: 661.21069 | AD42: 677.41119 | AE42: 693.93957 | AF42: 708.70209 | AG42: 0.022
A43: ISM000:ga_Transportatio | B43: ,ISIC 29,ISIC 302T309, | C43: Transportation Equipment | D43: Industrial Macroeconomic: Manufacturing: Transportation Equipment: Alternative Electricity and Transportation | E43: AEO.2026.ELECTRNP.ECI_VOS_MANF_TEQ_NA_NA_NA_BLNY09DLR.A | F43: billion 2012 $ | G43: 1002.355 | H43: 1005.3 | I43: 1068.975 | J43: 1089.9318 | K43: 1107.297 | L43: 1125.724 | M43: 1133.2688 | N43: 1151.2688 | O43: 1159.2283 | P43: 1162.537 | Q43: 1167.0085 | R43: 1179.002 | S43: 1203.2567 | T43: 1225.7577 | U43: 1248.693 | V43: 1269.9425 | W43: 1288.6895 | X43: 1307.5587 | Y43: 1324.1825 | Z43: 1341.2595 | AA43: 1359.183 | AB43: 1376.2032 | AC43: 1391.7977 | AD43: 1407.7498 | AE43: 1422.3308 | AF43: 1434.1357 | AG43: 0.014
A44: ISM000:ga_Instrumentsan | B44: ,ISIC 27, | C44: Electrical Equipment | D44: Industrial Macroeconomic: Manufacturing: Electrical Equipment: Alternative Electricity and Transportation | E44: AEO.2026.ELECTRNP.ECI_VOS_MANF_EEQ_NA_NA_NA_BLNY09DLR.A | F44: billion 2012 $ | G44: 118.2975 | H44: 116.73825 | I44: 116.09667 | J44: 114.2786 | K44: 113.85622 | L44: 115.90938 | M44: 117.77843 | N44: 119.75828 | O44: 120.4133 | P44: 120.94665 | Q44: 122.24272 | R44: 123.16823 | S44: 124.02395 | T44: 124.64645 | U44: 125.23923 | V44: 126.064 | W44: 126.7776 | X44: 127.61202 | Y44: 128.32378 | Z44: 129.0089 | AA44: 129.82159 | AB44: 130.85539 | AC44: 131.88008 | AD44: 132.77362 | AE44: 133.50012 | AF44: 134.00803 | AG44: 0.005
A45: ISM000:ga_Miscellaneous | B45: ,ISIC 31T33, | C45: Miscellaneous Manufacturing | D45: Industrial Macroeconomic: Manufacturing: Miscellaneous Manufacturing: Alternative Electricity and Transportation | E45: AEO.2026.ELECTRNP.ECI_VOS_MANF_MISC_NA_NA_NA_BLNY09DLR.A | F45: billion 2012 $ | G45: 144.9075 | H45: 145.35612 | I45: 149.45869 | J45: 152.8595 | K45: 155.88032 | L45: 159.69968 | M45: 164.2225 | N45: 165.36556 | O45: 164.92943 | P45: 163.96925 | Q45: 163.58032 | R45: 164.35375 | S45: 165.49033 | T45: 166.50532 | U45: 166.7278 | V45: 167.80901 | W45: 168.99103 | X45: 169.76718 | Y45: 170.3938 | Z45: 171.00638 | AA45: 171.54739 | AB45: 172.19408 | AC45: 172.57062 | AD45: 172.60996 | AE45: 174.43875 | AF45: 173.48642 | AG45: 0.007
A46: ISM000:ha_TotalIndustri | C46: Total Industrial Value of Shipments | D46: Industrial Macroeconomic: Total Industrial Value of Shipments: Alternative Electricity and Transportation | E46: AEO.2026.ELECTRNP.ECI_VOS_IDAL_NA_NA_NA_NA_BLNY09DLR.A | F46: billion 2012 $ | G46: 8703.1973 | H46: 8752.5645 | I46: 8860.0869 | J46: 8925.21 | K46: 8996.9707 | L46: 9096.0107 | M46: 9180.3877 | N46: 9280.9062 | O46: 9357.7588 | P46: 9436.4336 | Q46: 9520.167 | R46: 9604.2969 | S46: 9697.3643 | T46: 9786.8838 | U46: 9878.123 | V46: 9974.8262 | W46: 10069.032 | X46: 10166.396 | Y46: 10253.317 | Z46: 10343.383 | AA46: 10450.387 | AB46: 10563.197 | AC46: 10674.791 | AD46: 10773.288 | AE46: 10876.104 | AF46: 10975.349 | AG46: 0.009

Sheet g2025 derivation
A1: 2024->2025 output growth per code, derived LIVE from the raw sources (same machinery as the BPCiObIC workbook). Row 4 = BLS compound rate; row 5 = AEO 2025 rate (2026-edition ELECTRNP vs 2025-edition HIGHZTC base-year splice); row 6 = g2025.
A2: f2025 (2025 GDP-fit factor — the ONE imported number; from the BPCiObIC workbook 'Rescale to Fit GDP Proj' row 5, col D. Repaste on BPCiObIC source updates.) | B2: 0.91504425
A3: ISIC | B3: ISIC 01 | C3: ISIC 02 | D3: ISIC 03 | E3: ISIC 05 | F3: ISIC 06 | G3: ISIC 07 | H3: ISIC 08 | I3: ISIC 09 | J3: ISIC 10T12 | K3: ISIC 13T15 | L3: ISIC 16 | M3: ISIC 17T18 | N3: ISIC 19 | O3: ISIC 20 | P3: ISIC 21 | Q3: ISIC 22 | R3: ISIC 231 | S3: ISIC 239 | T3: ISIC 241 | U3: ISIC 242 | V3: ISIC 25 | W3: ISIC 26 | X3: ISIC 27 | Y3: ISIC 28 | Z3: ISIC 29 | AA3: ISIC 301 | AB3: ISIC 302T309 | AC3: ISIC 31T33 | AD3: ISIC 351 | AE3: ISIC 352T353 | AF3: ISIC 36T39 | AG3: ISIC 41T43 | AH3: ISIC 45T47 | AI3: ISIC 49 | AJ3: ISIC 50 | AK3: ISIC 51 | AL3: ISIC 52 | AM3: ISIC 53 | AN3: ISIC 55T56 | AO3: ISIC 58T60 | AP3: ISIC 61 | AQ3: ISIC 62T63 | AR3: ISIC 64T66 | AS3: ISIC 68 | AT3: ISIC 69T75 | AU3: ISIC 77T82 | AV3: ISIC 84 | AW3: ISIC 85 | AX3: ISIC 86T88 | AY3: ISIC 90T93 | AZ3: ISIC 94T96 | BA3: ISIC 97T98
A4: BLS compound rate | B4: =IFERROR(SUMPRODUCT(--('BLS Table 2.11'!$L$1:$L$426=B$3),'BLS Table 2.11'!$J$1:$J$426,'BLS Table 2.11'!$K$1:$K$426)/SUMIFS('BLS Table 2.11'!$J$1:$J$426,'BLS Table 2.11'!$L$1:$L$426,B$3)/100,0) | C4: =IFERROR(SUMPRODUCT(--('BLS Table 2.11'!$L$1:$L$426=C$3),'BLS Table 2.11'!$J$1:$J$426,'BLS Table 2.11'!$K$1:$K$426)/SUMIFS('BLS Table 2.11'!$J$1:$J$426,'BLS Table 2.11'!$L$1:$L$426,C$3)/100,0) | D4: =IFERROR(SUMPRODUCT(--('BLS Table 2.11'!$L$1:$L$426=D$3),'BLS Table 2.11'!$J$1:$J$426,'BLS Table 2.11'!$K$1:$K$426)/SUMIFS('BLS Table 2.11'!$J$1:$J$426,'BLS Table 2.11'!$L$1:$L$426,D$3)/100,0) | E4: =IFERROR(SUMPRODUCT(--('BLS Table 2.11'!$L$1:$L$426=E$3),'BLS Table 2.11'!$J$1:$J$426,'BLS Table 2.11'!$K$1:$K$426)/SUMIFS('BLS Table 2.11'!$J$1:$J$426,'BLS Table 2.11'!$L$1:$L$426,E$3)/100,0) | F4: =IFERROR(SUMPRODUCT(--('BLS Table 2.11'!$L$1:$L$426=F$3),'BLS Table 2.11'!$J$1:$J$426,'BLS Table 2.11'!$K$1:$K$426)/SUMIFS('BLS Table 2.11'!$J$1:$J$426,'BLS Table 2.11'!$L$1:$L$426,F$3)/100,0) | G4: =IFERROR(SUMPRODUCT(--('BLS Table 2.11'!$L$1:$L$426=G$3),'BLS Table 2.11'!$J$1:$J$426,'BLS Table 2.11'!$K$1:$K$426)/SUMIFS('BLS Table 2.11'!$J$1:$J$426,'BLS Table 2.11'!$L$1:$L$426,G$3)/100,0) | H4: =IFERROR(SUMPRODUCT(--('BLS Table 2.11'!$L$1:$L$426=H$3),'BLS Table 2.11'!$J$1:$J$426,'BLS Table 2.11'!$K$1:$K$426)/SUMIFS('BLS Table 2.11'!$J$1:$J$426,'BLS Table 2.11'!$L$1:$L$426,H$3)/100,0) | I4: =IFERROR(SUMPRODUCT(--('BLS Table 2.11'!$L$1:$L$426=I$3),'BLS Table 2.11'!$J$1:$J$426,'BLS Table 2.11'!$K$1:$K$426)/SUMIFS('BLS Table 2.11'!$J$1:$J$426,'BLS Table 2.11'!$L$1:$L$426,I$3)/100,0) | ... BA4: =IFERROR(SUMPRODUCT(--('BLS Table 2.11'!$L$1:$L$426=BA$3),'BLS Table 2.11'!$J$1:$J$426,'BLS Table 2.11'!$K$1:$K$426)/SUMIFS('BLS Table 2.11'!$J$1:$J$426,'BLS Table 2.11'!$L$1:$L$426,BA$3)/100,0)
A5: AEO 2025 rate | B5: =IFERROR((SUMIFS('AEO 2026 Table 23 '!G:G,'AEO 2026 Table 23 '!$B:$B,"*,"&B$3&",*")-SUMIFS('AEO25 Table 23'!H:H,'AEO25 Table 23'!$B:$B,"*,"&B$3&",*"))/SUMIFS('AEO25 Table 23'!H:H,'AEO25 Table 23'!$B:$B,"*,"&B$3&",*"),"") | C5: =IFERROR((SUMIFS('AEO 2026 Table 23 '!G:G,'AEO 2026 Table 23 '!$B:$B,"*,"&C$3&",*")-SUMIFS('AEO25 Table 23'!H:H,'AEO25 Table 23'!$B:$B,"*,"&C$3&",*"))/SUMIFS('AEO25 Table 23'!H:H,'AEO25 Table 23'!$B:$B,"*,"&C$3&",*"),"") | D5: =IFERROR((SUMIFS('AEO 2026 Table 23 '!G:G,'AEO 2026 Table 23 '!$B:$B,"*,"&D$3&",*")-SUMIFS('AEO25 Table 23'!H:H,'AEO25 Table 23'!$B:$B,"*,"&D$3&",*"))/SUMIFS('AEO25 Table 23'!H:H,'AEO25 Table 23'!$B:$B,"*,"&D$3&",*"),"") | E5: =IFERROR((SUMIFS('AEO 2026 Table 23 '!G:G,'AEO 2026 Table 23 '!$B:$B,"*,"&E$3&",*")-SUMIFS('AEO25 Table 23'!H:H,'AEO25 Table 23'!$B:$B,"*,"&E$3&",*"))/SUMIFS('AEO25 Table 23'!H:H,'AEO25 Table 23'!$B:$B,"*,"&E$3&",*"),"") | F5: =IFERROR((SUMIFS('AEO 2026 Table 23 '!G:G,'AEO 2026 Table 23 '!$B:$B,"*,"&F$3&",*")-SUMIFS('AEO25 Table 23'!H:H,'AEO25 Table 23'!$B:$B,"*,"&F$3&",*"))/SUMIFS('AEO25 Table 23'!H:H,'AEO25 Table 23'!$B:$B,"*,"&F$3&",*"),"") | G5: =IFERROR((SUMIFS('AEO 2026 Table 23 '!G:G,'AEO 2026 Table 23 '!$B:$B,"*,"&G$3&",*")-SUMIFS('AEO25 Table 23'!H:H,'AEO25 Table 23'!$B:$B,"*,"&G$3&",*"))/SUMIFS('AEO25 Table 23'!H:H,'AEO25 Table 23'!$B:$B,"*,"&G$3&",*"),"") | H5: =IFERROR((SUMIFS('AEO 2026 Table 23 '!G:G,'AEO 2026 Table 23 '!$B:$B,"*,"&H$3&",*")-SUMIFS('AEO25 Table 23'!H:H,'AEO25 Table 23'!$B:$B,"*,"&H$3&",*"))/SUMIFS('AEO25 Table 23'!H:H,'AEO25 Table 23'!$B:$B,"*,"&H$3&",*"),"") | I5: =IFERROR((SUMIFS('AEO 2026 Table 23 '!G:G,'AEO 2026 Table 23 '!$B:$B,"*,"&I$3&",*")-SUMIFS('AEO25 Table 23'!H:H,'AEO25 Table 23'!$B:$B,"*,"&I$3&",*"))/SUMIFS('AEO25 Table 23'!H:H,'AEO25 Table 23'!$B:$B,"*,"&I$3&",*"),"") | ... BA5: =IFERROR((SUMIFS('AEO 2026 Table 23 '!G:G,'AEO 2026 Table 23 '!$B:$B,"*,"&BA$3&",*")-SUMIFS('AEO25 Table 23'!H:H,'AEO25 Table 23'!$B:$B,"*,"&BA$3&",*"))/SUMIFS('AEO25 Table 23'!H:H,'AEO25 Table 23'!$B:$B,"*,"&BA$3&",*"),"")
A6: g2025 | B6: =IF(B5="",B4*$B$2,B5) | C6: =IF(C5="",C4*$B$2,C5) | D6: =IF(D5="",D4*$B$2,D5) | E6: =IF(E5="",E4*$B$2,E5) | F6: =IF(F5="",F4*$B$2,F5) | G6: =IF(G5="",G4*$B$2,G5) | H6: =IF(H5="",H4*$B$2,H5) | I6: =IF(I5="",I4*$B$2,I5) | ... BA6: =IF(BA5="",BA4*$B$2,BA5)

Sheet OECD Mining & Utilities
A1: #NAME? | B1: <?xml version="1.0" encoding="utf-16"?><WebTableParameter xmlns:xsd="http://www.w3.org/2001/XMLSchema" xmlns:xsi="http://www.w3.org/2001/XMLSchema-instance" xmlns="http://stats.oecd.org/OECDStatWS/2004/03/01/"><DataTable Code="PDBI_I4" HasMetadata="true"><Name LocaleIsoCode="en">Productivity and ULC by main economic activity (ISIC Rev.4)</Name><Name LocaleIsoCode="fr">Productivité et CUM par principale activité économique (CITI Rev.4)</Name><Dimension Code="LOCATION" HasMetadata="false" CommonCode="LOCATION" Display="labels"><Name LocaleIsoCode="en">Country</Name><Name LocaleIsoCode="fr">Pays</Name><Member Code="AUS" HasMetadata="false" HasOnlyUnitMetadata="false" HasChild="0"><Name LocaleIsoCode="en">Australia</Name><Name LocaleIsoCode="fr">Australie</Name></Member><Member Code="AUT" HasMetadata="false" HasOnlyUnitMetadata="false" HasChild="0"><Name LocaleIsoCode="en">Austria</Name><Name LocaleIsoCode="fr">Autriche</Name></Member><Member Code="BEL" HasMetadata="false" HasOnlyUnitMetadata="false" HasChild="0"><Name LocaleIsoCode="en">Belgium</Name><Name LocaleIsoCode="fr">Belgique</Name></Member><Member Code="CAN" HasMetadata="false" HasOnlyUnitMetadata="false" HasChild="0"><Name LocaleIsoCode="en">Canada</Name><Name LocaleIsoCode="fr">Canada</Name></Member><Member Code="CHL" HasMetadata="false" HasOnlyUnitMetadata="false" HasChild="0"><Name LocaleIsoCode="en">Chile</Name><Name LocaleIsoCode="fr">Chili</Name></Member><Member Code="COL" HasMetadata="false" HasOnlyUnitMetadata="false" HasChild="0"><Name LocaleIsoCode="en">Colombia</Name><Name LocaleIsoCode="fr">Colombie</Name></Member><Member Code="CZE" HasMetadata="false" HasOnlyUnitMetadata="false" HasChild="0"><Name LocaleIsoCode="en">Czech Republic</Name><Name LocaleIsoCode="fr">République tchèque</Name></Member><Member Code="DNK" HasMetadata="false" HasOnlyUnitMetadata="false" HasChild="0"><Name LocaleIsoCode="en">Denmark</Name><Name LocaleIsoCode="fr">Danemark</Name></Member><Member Code="EST" HasMetadata="false" HasOnlyUnitMetadata="false" HasChild="0"><Name LocaleIsoCode="en">Estonia</Name><Name LocaleIsoCode="fr">Estonie</Name></Member><Member Code="FIN" HasMetadata="false" HasOnlyUnitMetadata="false" HasChild="0"><Name LocaleIsoCode="en">Finland</Name><Name LocaleIsoCode="fr">Finlande</Name></Member><Member Code="FRA" HasMetadata="false" HasOnlyUnitMetadata="false" HasChild="0"><Name LocaleIsoCode="en">France</Name><Name LocaleIsoCode="fr">France</Name></Member><Member Code="DEU" HasMetadata="true" HasOnlyUnitMetadata="false" HasChild="0"><Name LocaleIsoCode="en">Germany</Name><Name LocaleIsoCode="fr">Allemagne</Name></Member><Member Code="GRC" HasMetadata="false" HasOnlyUnitMetadata="false" HasChild="0"><Name LocaleIsoCode="en">Greece</Name><Name LocaleIsoCode="fr">Grèce</Name></Member><Member Code="HUN" HasMetadata="false" HasOnlyUnitMetadata="false" HasChild="0"><Name LocaleIsoCode="en">Hungary</Name><Name LocaleIsoCode="fr">Hongrie</Name></Member><Member Code="ISL" HasMetadata="false" HasOnlyUnitMetadata="false" HasChild="0"><Name LocaleIsoCode="en">Iceland</Name><Name LocaleIsoCode="fr">Islande</Name></Member><Member Code="IRL" HasMetadata="true" HasOnlyUnitMetadata="false" HasChild="0"><Name LocaleIsoCode="en">Ireland</Name><Name LocaleIsoCode="fr">Irlande</Name></Member><Member Code="ISR" HasMetadata="true" HasOnlyUnitMetadata="false" HasChild="0"><Name LocaleIsoCode="en">Israel</Name><Name LocaleIsoCode="fr">Israël</Name></Member><Member Code="ITA" HasMetadata="false" HasOnlyUnitMetadata="false" HasChild="0"><Name LocaleIsoCode="en">Italy</Name><Name LocaleIsoCode="fr">Italie</Name></Member><Member Code="JPN" HasMetadata="false" HasOnlyUnitMetadata="false" HasChild="0"><Name LocaleIsoCode="en">Japan</Name><Name LocaleIsoCode="fr">Japon</Name></Member><Member Code="KOR" HasMetadata="false" HasOnlyUnitMetadata="false" HasChild="0"><Name LocaleIsoCode="en">Korea</Name><Name LocaleIsoCode="fr">Corée</Name></Member><Member Code="LVA" HasMetadata="false" HasOnlyUnitMetadata="false" HasChild="0"><Name LocaleIsoCode="en">Latvia</Name><Name LocaleIsoCode="fr">Lettonie</Name></Member><Member Code="LTU" HasMetadata="false" HasOnlyUnitMetadata="false" HasChild="0"><Name LocaleIsoCode="en">Lithuania</Name><Name LocaleIsoCode="fr">Lituanie</Name></Member><Member Code="LUX" HasMetadata="false" HasOnlyUnitMetadata="false" HasChild="0"><Name LocaleIsoCode="en">Luxembourg</Name><Name LocaleIsoCode="fr">Luxembourg</Name></Member><Member Code="MEX" HasMetadata="false" HasOnlyUnitMetadata="false" HasChild="0"><Name LocaleIsoCode="en">Mexico</Name><Name LocaleIsoCode="fr">Mexique</Name></Member><Member Code="NLD" HasMetadata="false" HasOnlyUnitMetadata="false" HasChild="0"><Name LocaleIsoCode="en">Netherlands</Name><Name LocaleIsoCode="fr">Pays-Bas</Name></Member><Member Code="NZL" HasMetadata="false" HasOnlyUnitMetadata="false" HasChild="0"><Name LocaleIsoCode="en">New Zealand</Name><Name LocaleIsoCode="fr">Nouvelle-Zélande</Name></Member><Member Code="NOR" HasMetadata="false" HasOnlyUnitMetadata="false" HasChild="0"><Name LocaleIsoCode="en">Norway</Name><Name LocaleIsoCode="fr">Norvège</Name></Member><Member Code="POL" HasMetadata="false" HasOnlyUnitMetadata="false" HasChild="0"><Name LocaleIsoCode="en">Poland</Name><Name LocaleIsoCode="fr">Pologne</Name></Member><Member Code="PRT" HasMetadata="false" HasOnlyUnitMetadata="false" HasChild="0"><Name LocaleIsoCode="en">Portugal</Name><Name LocaleIsoCode="fr">Portugal</Name></Member><Member Code="SVK" HasMetadata="false" HasOnlyUnitMetadata="false" HasChild="0"><Name LocaleIsoCode="en">Slovak Republic</Name><Name LocaleIsoCode="fr">République slovaque</Name></Member><Member Code="SVN" HasMetadata="false" HasOnlyUnitMetadata="false" HasChild="0"><Name LocaleIsoCode="en">Slovenia</Name><Name LocaleIsoCode="fr">Slovénie</Name></Member><Member Code="ESP" HasMetadata="false" HasOnlyUnitMetadata="false" HasChild="0"><Name LocaleIsoCode="en">Spain</Name><Name LocaleIsoCode="fr">Espagne</Name></Member><Member Code="SWE" HasMetadata="false" HasOnlyUnitMetadata="false" HasChild="0"><Name LocaleIsoCode="en">Sweden</Name><Name LocaleIsoCode="fr">Suède</Name></Member><Member Code="CHE" HasMetadata="false" HasOnlyUnitMetadata="false" HasChild="0"><Name LocaleIsoCode="en">Switzerland</Name><Name LocaleIsoCode="fr">Suisse</Name></Member><Member Code="GBR" HasMetadata="false" HasOnlyUnitMetadata="false" HasChild="0"><Name LocaleIsoCode="en">United Kingdom</Name><Name LocaleIsoCode="fr">Royaume-Uni</Name></Member><Member Code="USA" HasMetadata="false" HasOnlyUnitMetadata="false" HasChild="0"><Name LocaleIsoCode="en">United States</Name><Name LocaleIsoCode="fr">États-Unis</Name></Member><Member Code="EA19" HasMetadata="false" HasOnlyUnitMetadata="false" HasChild="0"><Name LocaleIsoCode="en">Euro area (19 countries)</Name><Name LocaleIsoCode="fr">Zone euro (19 pays)</Name></Member><Member Code="EU28" HasMetadata="false" HasOnlyUnitMetadata="false" HasChild="0"><Name LocaleIsoCode="en">European Union (28 countries)</Name><Name LocaleIsoCode="fr">Union européenne (28 pays)</Name></Member><Member Code="NMEC" HasMetadata="false" HasOnlyUnitMetadata="false" HasChild="1"><Name LocaleIsoCode="en">Non-OECD Economies</Name><Name LocaleIsoCode="fr">Économies non-OCDE</Name><ChildMember Code="BRA" HasMetadata="false" HasOnlyUnitMetadata="false" HasChild="0"><Name LocaleIsoCode="en">Brazil</Name><Name LocaleIsoCode="fr">Brésil</Name></ChildMember><ChildMember Code="CRI" HasMetadata="false" HasOnlyUnitMetadata="false" HasChild="0"><Name LocaleIsoCode="en">Costa Rica</Name><Name LocaleIsoCode="fr">Costa Rica</Name></ChildMember><ChildMember Code="RUS" HasMetadata="false" HasOnlyUnitMetadata="false" HasChild="0"><Name LocaleIsoCode="en">Russia</Name><Name LocaleIsoCode="fr">Russie</Name></ChildMember><ChildMember Code="ZAF" HasMetadata="false" HasOnlyUnitMetadata="false" HasChild="0"><Name LocaleIsoCode="en">South Africa</Name><Name LocaleIsoCode="fr">Afrique du Sud</Name></ChildMember></Member></Dimension><Dimension Code="SUBJECT" HasMetadata="false" Display="labels"><Name LocaleIsoCode="en">Subject</Name><Name LocaleIsoCode="fr">Sujet</Name><Member Code="I4_ANA_GVAHRS" HasMetadata="false" HasOnlyUnitMetadata="false" HasChild="0"><Name LocaleIsoCode="en">Gross value added per hour worked, constant prices</Name><Name LocaleIsoCode="fr">Valeur ajoutée brute par heure travaillée, prix constants</Name></Member><Member Code="I4_ANA_GVAEMP" HasMetadata="false" HasOnlyUnitMetadata="false" HasChild="0" IsDisplayed="true"><Name LocaleIsoCode="en">Gross value added per person employed, constant prices</Name><Name LocaleIsoCode="fr">Valeur ajoutée brute par actif occupé, prix constants</Name></Member><Member Code="I4_ANA_GVA" HasMetadata="false" HasOnlyUnitMetadata="false" HasChild="0"><Name LocaleIsoCode="en">Gross value added, constant prices</Name><Name LocaleIsoCode="fr">Valeur ajoutée brute, prix constants</Name></Member><Member Code="I4_ANA_EMPTO" HasMetadata="false" HasOnlyUnitMetadata="false" HasChild="0"><Name LocaleIsoCode="en">Total employment (number of persons employed)</Name><Name LocaleIsoCode="fr">Emploi total (nombre d'actifs occupés)</Name></Member><Member Code="I4_ANA_HRSTO" HasMetadata="true" HasOnlyUnitMetadata="false" HasChild="0"><Name LocaleIsoCode="en">Total hours worked</Name><Name LocaleIsoCode="fr">Heures travaillées totales</Name></Member><Member Code="I4_ANA_HRSAV" HasMetadata="true" HasOnlyUnitMetadata="false" HasChild="0"><Name LocaleIsoCode="en">Average hours worked per person employed</Name><Name LocaleIsoCode="fr">Heures travaillées moyennes par actif occupé</Name></Member><Member Code="I4_ANA_CONILPHRS" HasMetadata="false" HasOnlyUnitMetadata="false" HasChild="0"><Name LocaleIsoCode="en">Industry contribution to business sector labour productivity</Name><Name LocaleIsoCode="fr">Contribution par industrie à la productivité du travail du secteur marchand</Name></Member><Member Code="I4_ANA_CONILPEMP" HasMetadata="false" HasOnlyUnitMetadata="false" HasChild="0"><Name LocaleIsoCode="en">Industry contribution to business sector labour productivity; employment based</Name><Name LocaleIsoCode="fr">Contribution par industrie à la productivité du travail du secteur marchand (basée sur l'emploi)</Name></Member><Member Code="I4_ANA_ULCH" HasMetadata="true" HasOnlyUnitMetadata="false" HasChild="0"><Name LocaleIsoCode="en">Unit Labour Costs</Name><Name LocaleIsoCode="fr">Coûts unitaires de la main d'œuvre</Name></Member><Member Code="I4_ANA_LCHRS" HasMetadata="true" HasOnlyUnitMetadata="false" HasChild="0"><Name LocaleIsoCode="en">Labour compensation per hour worked</Name><Name LocaleIsoCode="fr">Rémunération de la main d'oeuvre par heure travaillée</Name></Member><Member Code="I4_ANA_ULCE" HasMetadata="true" HasOnlyUnitMetadata="false" HasChild="0"><Name LocaleIsoCode="en">Unit Labour Costs, employment based</Name><Name LocaleIsoCode="fr">Coûts unitaires de la main d'œuvre, basés sur l'emploi </Name></Member><Member Code="I4_ANA_LCEMP" HasMetadata="false" HasOnlyUnitMetadata="false" HasChild="0"><Name LocaleIsoCode="en">Labour compensation per employee</Name><Name LocaleIsoCode="fr">Rémunération de la main d'oeuvre par salarié </Name></Member></Dimension><Dimension Code="MEASURE" HasMetadata="false" Display="labels"><Name LocaleIsoCode="en">Measure</Name><Name LocaleIsoCode="fr">Mesure</Name><Member Code="GRW" HasMetadata="true" HasOnlyUnitMetadata="false" HasChild="0"><Name LocaleIsoCode="en">Annual growth/change</Name><Name LocaleIsoCode="fr">Croissance/variation annuelle</Name></Member></Dimension><Dimension Code="ACTIVITY" HasMetadata="false" Display="codesandlabels"><Name LocaleIsoCode="en">Activity</Name><Name LocaleIsoCode="fr">Activité</Name><Member Code="A_U" HasMetadata="false" HasOnlyUnitMetadata="false" HasChild="1"><Name LocaleIsoCode="en">Total </Name><Name LocaleIsoCode="fr">Total</Name><ChildMember Code="BNEXCL" HasMetadata="false" HasOnlyUnitMetadata="false" HasChild="1"><Name LocaleIsoCode="en">Non-agriculture business sector excluding real estate</Name><Name LocaleIsoCode="fr">Secteur marchand non-agricole, hors activités immobilières</Name><ChildMember Code="B_E" HasMetadata="false" HasOnlyUnitMetadata="false" HasChild="1"><Name LocaleIsoCode="en">Industry including energy</Name><Name LocaleIsoCode="fr">Industrie, y compris l’énergie</Name><ChildMember Code="BDE" HasMetadata="false" HasOnlyUnitMetadata="false" HasChild="0" IsDisplayed="true"><Name LocaleIsoCode="en">Mining and utilities</Name><Name LocaleIsoCode="fr">Industries extractives , électricité et gaz , eau et déchets</Name></ChildMember><ChildMember Code="C" HasMetadata="false" HasOnlyUnitMetadata="false" HasChild="0"><Name LocaleIsoCode="en">Manufacturing</Name><Name LocaleIsoCode="fr">Activités de fabrication</Name></ChildMember></ChildMember><ChildMember Code="F" HasMetadata="false" HasOnlyUnitMetadata="false" HasChild="0"><Name LocaleIsoCode="en">Construction</Name><Name LocaleIsoCode="fr">Construction</Name></ChildMember><ChildMember Code="GNEXCL" HasMetadata="false" HasOnlyUnitMetadata="false" HasChild="1"><Name LocaleIsoCode="en">Business sector services excluding real estate</Name><Name LocaleIsoCode="fr">Services marchands, hors activités immobilières</Name><ChildMember Code="G_I" HasMetadata="false" HasOnlyUnitMetadata="false" HasChild="0"><Name LocaleIsoCode="en">Wholesale retail trade accommodation food services, transportation and storage</Name><Name LocaleIsoCode="fr">Commerce de gros et de détail, réparations , transport et entreposage , hébergement et restauration</Name></ChildMember><ChildMember Code="J" HasMetadata="false" HasOnlyUnitMetadata="false" HasChild="0"><Name LocaleIsoCode="en">Information and communication</Name><Name LocaleIsoCode="fr">Information et communication</Name></ChildMember><ChildMember Code="K" HasMetadata="false" HasOnlyUnitMetadata="false" HasChild="0"><Name LocaleIsoCode="en">Financial and insurance activities</Name><Name LocaleIsoCode="fr">Activités financières et d'assurances</Name></ChildMember><ChildMember Code="MN" HasMetadata="false" HasOnlyUnitMetadata="false" HasChild="0"><Name LocaleIsoCode="en">Professional, scientific and technical activities, Administrative and support service activities</Name><Name LocaleIsoCode="fr">Activités professionnelles, scientifiques et techniques , activités de services administratifs et d’appui</Name></ChildMember></ChildMember></ChildMember></Member></Dimension><Dimension Code="TIME" HasMetadata="false" CommonCode="TIME" Display="labels"><Name LocaleIsoCode="en">Time</Name><Name LocaleIsoCode="fr">Temps</Name><Member Code="1995" HasMetadata="false"><Name LocaleIsoCode="en">1995</Name><Name LocaleIsoCode="fr">1995</Name></Member><Member Code="1996" HasMetadata="false"><Name LocaleIsoCode="en">1996</Name><Name LocaleIsoCode="fr">1996</Name></Member><Member Code="1997" HasMetadata="false"><Name LocaleIsoCode="en">1997</Name><Name LocaleIsoCode="fr">1997</Name></Member><Member Code="1998" HasMetadata="false"><Name LocaleIsoCode="en">1998</Name><Name LocaleIsoCode="fr">1998</Name></Member><Member Code="1999" HasMetadata="false"><Name LocaleIsoCode="en">1999</Name><Name LocaleIsoCode="fr">1999</Name></Member><Member Code="2000" HasMetadata="false"><Name LocaleIsoCode="en">2000</Name><Name LocaleIsoCode="fr">2000</Name></Member><Member Code="2001" HasMetadata="false"><Name LocaleIsoCode="en">2001</Name><Name LocaleIsoCode="fr">2001</Name></Member><Member Code="2002" HasMetadata="false"><Name LocaleIsoCode="en">2002</Name><Name LocaleIsoCode="fr">2002</Name></Member><Member Code="2003" HasMetadata="false"><Name LocaleIsoCode="en">2003</Name><Name LocaleIsoCode="fr">2003</Name></Member><Member Code="2004" HasMetadata="false"><Name LocaleIsoCode="en">2004</Name><Name LocaleIsoCode="fr">2004</Name></Member><Member Code="2005" HasMetadata="false"><Name LocaleIsoCode="en">2005</Name><Name LocaleIsoCode="fr">2005</Name></Member><Member Code="2006" HasMetadata="false"><Name LocaleIsoCode="en">2006</Name><Name LocaleIsoCode="fr">2006</Name></Member><Member Code="2007" HasMetadata="false"><Name LocaleIsoCode="en">2007</Name><Name LocaleIsoCode="fr">2007</Name></Member><Member Code="2008" HasMetadata="false"><Name LocaleIsoCode="en">2008</Name><Name LocaleIsoCode="fr">2008</Name></Member><Member Code="2009" HasMetadata="false"><Name LocaleIsoCode="en">2009</Name><Name LocaleIsoCode="fr">2009</Name></Member><Member Code="2010" HasMetadata="false"><Name LocaleIsoCode="en">2010</Name><Name LocaleIsoCode="fr">2010</Name></Member><Member Code="2011" HasMetadata="false"><Name LocaleIsoCode="en">2011</Name><Name LocaleIsoCode="fr">2011</Name></Member><Member Code="2012" HasMetadata="false"><Name LocaleIsoCode="en">2012</Name><Name LocaleIsoCode="fr">2012</Name></Member><Member Code="2013" HasMetadata="false"><Name LocaleIsoCode="en">2013</Name><Name LocaleIsoCode="fr">2013</Name></Member><Member Code="2014" HasMetadata="false"><Name LocaleIsoCode="en">2014</Name><Name LocaleIsoCode="fr">2014</Name></Member><Member Code="2015" HasMetadata="false"><Name LocaleIsoCode="en">2015</Name><Name LocaleIsoCode="fr">2015</Name></Member><Member Code="2016" HasMetadata="false"><Name LocaleIsoCode="en">2016</Name><Name LocaleIsoCode="fr">2016</Name></Member><Member Code="2017" HasMetadata="false"><Name LocaleIsoCode="en">2017</Name><Name LocaleIsoCode="fr">2017</Name></Member><Member Code="2018" HasMetadata="false"><Name LocaleIsoCode="en">2018</Name><Name LocaleIsoCode="fr">2018</Name></Member><Member Code="2019" HasMetadata="false"><Name LocaleIsoCode="en">2019</Name><Name LocaleIsoCode="fr">2019</Name></Member></Dimension><WBOSInformations><TimeDimension WebTreeWasUsed="false"><StartCodes Annual="1995" /></TimeDimension></WBOSInformations><Tabulation Axis="horizontal"><Dimension Code="TIME" CommonCode="TIME" /><Dimension Code="MEASURE" /></Tabulation><Tabulation Axis="vertical"><Dimension Code="LOCATION" CommonCode="LOCATION" /></Tabulation><Tabulation Axis="page"><Dimension Code="SUBJECT" /><Dimension Code="ACTIVITY" /></Tabulation><Formatting><Labels LocaleIsoCode="en" /><Power>0</Power><Decimals>1</Decimals><SkipEmptyLines>true</SkipEmptyLines><SkipEmptyCols>true</SkipEmptyCols><SkipLineHierarchy>false</SkipLineHierarchy><SkipColHierarchy>false</SkipColHierarchy><Page>1</Page></Formatting></DataTable><Format><ShowEmptyAxes>true</ShowEmptyAxes><Page>1</Page><EnableSort>true</EnableSort><IncludeFlagColumn>false</IncludeFlagColumn><IncludeTimeSeriesId>false</IncludeTimeSeriesId><DoBarChart>false</DoBarChart><FreezePanes>true</FreezePanes><MaxBarChartLen>65</MaxBarChartLen></Format><Query><AbsoluteUri>http://stats.oecd.org//View.aspx?QueryId=&amp;QueryType=Public&amp;Lang=en</AbsoluteUri></Query></WebTableParameter>
A2: Dataset: Productivity and ULC by main economic activity (ISIC Rev.4)
A3: Subject | D3: Gross value added per person employed, constant prices
A4: Activity | D4: BDE: Mining and utilities
A5: Time | D5: 1995 | E5: 1996 | F5: 1997 | G5: 1998 | H5: 1999 | I5: 2000 | J5: 2001 | K5: 2002 | L5: 2003 | M5: 2004 | N5: 2005 | O5: 2006 | P5: 2007 | Q5: 2008 | R5: 2009 | S5: 2010 | T5: 2011 | U5: 2012 | V5: 2013 | W5: 2014 | X5: 2015 | Y5: 2016 | Z5: 2017 | AA5: 2018 | AB5: 2019
A6: Measure | D6: Annual growth/change
A7: Unit | D7: Percentage
A8: Country
A9: Australia | D9: 11.873586 | E9: 6.088949 | F9: 2.288617 | G9: 5.10491 | H9: 3.997186 | I9: 4.571828 | J9: -1.012654 | K9: -9.732628 | L9: -9.157785 | M9: -2.953357 | N9: -11.436768 | O9: 7.969507 | P9: -14.931679 | Q9: 3.332895 | R9: -3.231112 | S9: -11.033688 | T9: -10.348459 | U9: 13.894619 | V9: 7.940694 | W9: 17.890128 | X9: 7.683832 | Y9: 0.252948 | Z9: -3.845343 | AA9: .. | AB9: ..
A10: Austria | D10: -1.546396 | E10: 9.363747 | F10: 15.753046 | G10: 2.775991 | H10: 1.823979 | I10: 2.875089 | J10: 12.161994 | K10: 2.230702 | L10: 2.595379 | M10: 7.597743 | N10: -5.568574 | O10: -3.23471 | P10: -6.894449 | Q10: -6.661671 | R10: 1.724534 | S10: -4.247534 | T10: -3.167372 | U10: 1.467974 | V10: 4.799095 | W10: -6.842314 | X10: 0.988539 | Y10: 0.786397 | Z10: 4.59613 | AA10: 3.390284 | AB10: -0.412305
A11: Belgium | D11: .. | E11: 7.517088 | F11: 5.996845 | G11: -1.589094 | H11: 2.720623 | I11: 7.469734 | J11: -2.837806 | K11: -1.411397 | L11: 0.750408 | M11: 2.233061 | N11: -2.810107 | O11: 0.260458 | P11: 0.826721 | Q11: -3.069942 | R11: -5.381659 | S11: 5.166339 | T11: -2.490368 | U11: -7.761356 | V11: -3.428911 | W11: 5.385587 | X11: 3.270525 | Y11: 1.794065 | Z11: -4.684154 | AA11: -7.897528 | AB11: 5.457855
A12: Canada | D12: .. | E12: .. | F12: .. | G12: .. | H12: .. | I12: .. | J12: .. | K12: .. | L12: .. | M12: .. | N12: .. | O12: .. | P12: .. | Q12: -4.292483 | R12: -4.4655 | S12: 4.472325 | T12: -0.868338 | U12: -4.749713 | V12: 6.949534 | W12: 8.603134 | X12: 4.001319 | Y12: 4.799091 | Z12: .. | AA12: .. | AB12: ..
A13: Chile | D13: .. | E13: .. | F13: .. | G13: .. | H13: .. | I13: .. | J13: .. | K13: .. | L13: .. | M13: .. | N13: .. | O13: .. | P13: .. | Q13: .. | R13: .. | S13: .. | T13: -9.001167 | U13: -3.690479 | V13: -0.72716 | W13: 4.00942 | X13: 1.932009 | Y13: 6.746163 | Z13: -0.93511 | AA13: 4.853767 | AB13: ..
A14: Czech Republic | D14: 0.313677 | E14: 6.194056 | F14: -8.358839 | G14: -5.970458 | H14: 3.011932 | I14: 12.586877 | J14: 3.945138 | K14: 0.487365 | L14: 6.025132 | M14: 8.118094 | N14: -1.358181 | O14: 6.759318 | P14: 0.288457 | Q14: 3.51447 | R14: -5.605263 | S14: -6.368269 | T14: -6.239754 | U14: -1.18776 | V14: -10.984609 | W14: -1.527691 | X14: -1.063912 | Y14: -4.891502 | Z14: 0.725628 | AA14: -1.887684 | AB14: -0.780418
A15: Denmark | D15: -1.768692 | E15: 11.435703 | F15: 2.514266 | G15: -1.785373 | H15: 10.048712 | I15: 11.009505 | J15: 0.426375 | K15: -3.7636 | L15: 5.203032 | M15: 8.676066 | N15: -0.829578 | O15: -4.627215 | P15: -12.921944 | Q15: -11.920372 | R15: -11.5951 | S15: 11.051004 | T15: -4.666773 | U15: -7.218486 | V15: -4.530635 | W15: -8.234517 | X15: 0.601688 | Y15: 0.383103 | Z15: 0.770204 | AA15: -5.694433 | AB15: -7.306692
A16: Estonia | D16: .. | E16: 3.460238 | F16: -6.469462 | G16: -12.101695 | H16: -5.735049 | I16: 19.965544 | J16: 41.775537 | K16: 10.558097 | L16: -3.179847 | M16: -15.828024 | N16: 9.171683 | O16: 17.697576 | P16: 22.591983 | Q16: -10.085885 | R16: -3.342421 | S16: -0.187378 | T16: 2.194092 | U16: 2.597062 | V16: 24.511463 | W16: 1.10102 | X16: 5.388496 | Y16: 16.330131 | Z16: -1.376873 | AA16: 1.137516 | AB16: -7.568445
A17: Finland | D17: -0.320626 | E17: 7.683036 | F17: 1.560278 | G17: 2.036624 | H17: 3.473273 | I17: 0.96778 | J17: 7.76818 | K17: 4.34748 | L17: 2.85674 | M17: 3.227639 | N17: -2.14416 | O17: -3.389321 | P17: 5.59208 | Q17: -5.772629 | R17: -3.809533 | S17: 5.92266 | T17: -4.597803 | U17: 4.457955 | V17: -4.170962 | W17: 3.977176 | X17: -0.682826 | Y17: -4.108035 | Z17: 8.158292 | AA17: -1.11491 | AB17: -3.787532
A18: France | D18: 2.912629 | E18: 4.427758 | F18: -4.023798 | G18: 8.329017 | H18: 2.615878 | I18: -1.526661 | J18: 3.702651 | K18: 7.090026 | L18: -0.071788 | M18: 1.955156 | N18: -4.826257 | O18: -3.347164 | P18: 1.015735 | Q18: -3.040014 | R18: -8.694356 | S18: -2.70556 | T18: -3.419425 | U18: 4.639222 | V18: 3.334735 | W18: -4.351586 | X18: -1.33744 | Y18: -2.238763 | Z18: -0.412454 | AA18: 0.223351 | AB18: 1.633324
A19: Germany | D19: 5.41956 | E19: 4.505107 | F19: 1.437396 | G19: 3.418507 | H19: 2.405949 | I19: 2.905706 | J19: -0.056199 | K19: 5.250798 | L19: 0.482348 | M19: 6.712238 | N19: 0.062429 | O19: -10.288199 | P19: 6.676465 | Q19: 4.477033 | R19: 8.36395 | S19: 0.991573 | T19: -13.619595 | U19: 12.770582 | V19: -3.900447 | W19: 1.064307 | X19: 5.174721 | Y19: 5.315592 | Z19: 2.377673 | AA19: -1.853942 | AB19: -5.681453
A20: Greece | D20: .. | E20: 1.587273 | F20: 3.686176 | G20: 3.261943 | H20: 13.438178 | I20: 6.04415 | J20: 0.261305 | K20: 15.145181 | L20: 11.802811 | M20: 3.713035 | N20: 10.753412 | O20: -3.012638 | P20: -2.619989 | Q20: -11.28055 | R20: 10.877668 | S20: -20.273712 | T20: 5.356289 | U20: 4.949858 | V20: 1.004045 | W20: -9.279329 | X20: 0.565475 | Y20: -3.342473 | Z20: 2.231103 | AA20: -0.920301 | AB20: -5.226245
A21: Hungary | D21: .. | E21: 7.960043 | F21: -1.113895 | G21: -1.243444 | H21: 6.470719 | I21: 7.653605 | J21: 0.440593 | K21: 2.544605 | L21: -4.936725 | M21: 7.596589 | N21: -9.601811 | O21: 1.106706 | P21: 14.217207 | Q21: -5.853186 | R21: 15.066384 | S21: -6.742348 | T21: 1.429645 | U21: -11.129456 | V21: 5.465079 | W21: -2.363632 | X21: 6.33911 | Y21: 15.855646 | Z21: -9.152489 | AA21: -14.297116 | AB21: 5.053416
A22: Iceland | D22: .. | E22: .. | F22: .. | G22: .. | H22: .. | I22: .. | J22: .. | K22: .. | L22: .. | M22: .. | N22: .. | O22: .. | P22: .. | Q22: .. | R22: 4.825455 | S22: 2.598179 | T22: -3.509106 | U22: 4.137846 | V22: 4.21829 | W22: 2.354476 | X22: -7.526525 | Y22: -1.029861 | Z22: -5.159464 | AA22: 5.116339 | AB22: -2.043677
A23: Ireland | D23: .. | E23: 4.534052 | F23: -11.238584 | G23: -29.653587 | H23: 2.929208 | I23: 6.591884 | J23: -2.502287 | K23: 1.309861 | L23: 7.590391 | M23: -5.566177 | N23: -8.29259 | O23: -7.131645 | P23: -2.32746 | Q23: -0.014251 | R23: 4.739159 | S23: 38.160963 | T23: 8.371079 | U23: 4.305298 | V23: -7.318323 | W23: 12.185413 | X23: -6.986328 | Y23: 8.680748 | Z23: -7.647998 | AA23: 12.576849 | AB23: 9.076879
A24: Israel | D24: .. | E24: 13.273392 | F24: 3.597204 | G24: 5.801782 | H24: 1.125644 | I24: -10.944419 | J24: 12.780901 | K24: 4.933661 | L24: -3.134365 | M24: 0.870981 | N24: -3.321872 | O24: 27.745038 | P24: 18.40048 | Q24: -9.374201 | R24: 18.080629 | S24: -2.912385 | T24: -11.409545 | U24: -30.877564 | V24: 37.797234 | W24: 5.903407 | X24: 0.198014 | Y24: -2.68509 | Z24: -0.680012 | AA24: 13.21943 | AB24: ..
A25: Italy | D25: 4.979503 | E25: 1.111713 | F25: -2.247086 | G25: -0.816026 | H25: -0.992707 | I25: -3.024995 | J25: -3.576337 | K25: 0.800428 | L25: -3.209369 | M25: 5.385149 | N25: -3.836933 | O25: -10.001097 | P25: -2.813036 | Q25: 3.54111 | R25: -4.738485 | S25: -5.575893 | T25: -1.771335 | U25: -3.366479 | V25: -3.33526 | W25: -4.694767 | X25: -5.709701 | Y25: 3.223328 | Z25: 2.502153 | AA25: -2.704173 | AB25: -1.472878
A26: Japan | D26: 2.166222 | E26: 6.845657 | F26: 2.337818 | G26: 3.259744 | H26: 2.49272 | I26: 3.225027 | J26: 4.234384 | K26: 0.673704 | L26: 0.905097 | M26: 2.841677 | N26: 6.684469 | O26: 0.056294 | P26: -5.576707 | Q26: 3.324335 | R26: -17.886451 | S26: 9.335254 | T26: -11.901994 | U26: -18.96975 | V26: 7.531598 | W26: 1.285135 | X26: -9.702073 | Y26: 2.487589 | Z26: 9.695931 | AA26: 1.304384 | AB26: ..
A27: Korea | D27: .. | E27: .. | F27: .. | G27: .. | H27: .. | I27: .. | J27: .. | K27: .. | L27: .. | M27: .. | N27: 1.491051 | O27: -4.76068 | P27: -2.92113 | Q27: -6.046729 | R27: -1.934596 | S27: 18.880967 | T27: -1.282203 | U27: 1.580081 | V27: -10.158043 | W27: 0.300637 | X27: -3.139843 | Y27: -5.704622 | Z27: 4.760081 | AA27: -0.43063 | AB27: ..
A28: Latvia | D28: .. | E28: -1.327651 | F28: 1.533642 | G28: 5.060643 | H28: 0.978461 | I28: -12.549176 | J28: -6.023307 | K28: 12.047142 | L28: 10.569282 | M28: -0.18883 | N28: 3.928578 | O28: 11.190673 | P28: 2.168787 | Q28: -7.42531 | R28: 14.875845 | S28: 3.811378 | T28: -5.932077 | U28: -6.985968 | V28: -7.299629 | W28: -5.60929 | X28: 13.669806 | Y28: 10.746515 | Z28: -0.44219 | AA28: -5.120607 | AB28: -0.433495
A29: Lithuania | D29: .. | E29: 21.824559 | F29: -3.635378 | G29: -5.886605 | H29: 2.265821 | I29: -6.819954 | J29: 15.075973 | K29: 12.041481 | L29: 23.350683 | M29: 5.758286 | N29: 8.19192 | O29: 23.23022 | P29: -18.840457 | Q29: -1.965783 | R29: 9.661387 | S29: 12.410469 | T29: -3.538629 | U29: -10.74441 | V29: -6.320117 | W29: 10.422525 | X29: -1.038637 | Y29: -0.549218 | Z29: -10.91166 | AA29: 2.391043 | AB29: 3.938811
A30: Luxembourg | D30: .. | E30: 1.112422 | F30: 0.958269 | G30: -1.878657 | H30: 5.827297 | I30: 4.186087 | J30: -0.931011 | K30: -1.997096 | L30: 5.149328 | M30: 3.208835 | N30: 2.003029 | O30: -7.771555 | P30: -5.878089 | Q30: -15.099298 | R30: -3.773577 | S30: -13.481219 | T30: 8.809167 | U30: -3.971256 | V30: 20.997412 | W30: 1.053736 | X30: -0.069732 | Y30: -7.412186 | Z30: 0.935009 | AA30: 9.70932 | AB30: ..
A31: Mexico | D31: .. | E31: .. | F31: .. | G31: .. | H31: .. | I31: .. | J31: .. | K31: .. | L31: .. | M31: .. | N31: .. | O31: .. | P31: .. | Q31: .. | R31: .. | S31: .. | T31: 6.530792 | U31: -10.985498 | V31: -3.514781 | W31: .. | X31: .. | Y31: .. | Z31: .. | AA31: .. | AB31: ..
A32: Netherlands | D32: .. | E32: 11.961538 | F32: -5.093802 | G32: -2.161804 | H32: 0.114699 | I32: 0.11718 | J32: -3.374147 | K32: -0.873768 | L32: 1.342277 | M32: 6.414377 | N32: -3.117919 | O32: 2.879708 | P32: -3.385559 | Q32: 5.661918 | R32: -7.743811 | S32: 6.470906 | T32: -5.770865 | U32: 1.077356 | V32: 3.624677 | W32: -7.996717 | X32: -8.126945 | Y32: -1.249571 | Z32: -4.928834 | AA32: -6.66592 | AB32: -6.150804
A33: New Zealand | D33: .. | E33: .. | F33: .. | G33: .. | H33: .. | I33: .. | J33: .. | K33: .. | L33: .. | M33: .. | N33: .. | O33: .. | P33: .. | Q33: .. | R33: .. | S33: .. | T33: -5.978809 | U33: -1.377467 | V33: -2.085516 | W33: -10.11784 | X33: 1.977225 | Y33: 13.412285 | Z33: -9.861481 | AA33: .. | AB33: ..
A34: Norway | D34: 8.771992 | E34: 9.045979 | F34: 0.499594 | G34: -3.456103 | H34: 1.311167 | I34: 8.979312 | J34: -2.281448 | K34: -1.937102 | L34: -1.583996 | M34: 0.636016 | N34: -5.97373 | O34: -9.544428 | P34: -15.393925 | Q34: -9.489652 | R34: -3.010655 | S34: -6.52989 | T34: -6.533186 | U34: -5.850019 | V34: -5.521349 | W34: -2.120758 | X34: 9.358313 | Y34: 9.287979 | Z34: 6.844346 | AA34: -2.869437 | AB34: ..
A35: Poland | D35: .. | E35: -1.1551 | F35: -0.999324 | G35: -6.011004 | H35: 8.225339 | I35: 2.853149 | J35: 12.114806 | K35: 0.074594 | L35: 4.795219 | M35: -3.710822 | N35: -1.045122 | O35: -8.665955 | P35: 2.023942 | Q35: -1.130033 | R35: -1.107901 | S35: 10.232594 | T35: 4.368156 | U35: -0.117409 | V35: -1.347582 | W35: -7.626757 | X35: -0.236605 | Y35: 3.56025 | Z35: 11.067976 | AA35: 7.085827 | AB35: -12.157479
A36: Portugal | D36: .. | E36: 5.690579 | F36: -0.495519 | G36: 10.075939 | H36: 7.00295 | I36: 7.335367 | J36: 5.572138 | K36: 1.958481 | L36: 7.258778 | M36: 6.454423 | N36: -3.147472 | O36: 4.277469 | P36: 3.68056 | Q36: -1.255198 | R36: 6.952342 | S36: -3.071075 | T36: -3.357853 | U36: 1.572065 | V36: -4.255268 | W36: 2.703294 | X36: -0.224261 | Y36: -3.340032 | Z36: -5.828878 | AA36: 3.621351 | AB36: -3.190311
A37: Slovak Republic | D37: .. | E37: 36.993765 | F37: -17.039729 | G37: -5.934634 | H37: 31.46442 | I37: -9.71801 | J37: -23.455606 | K37: 33.065576 | L37: 32.092987 | M37: 14.711516 | N37: -13.883164 | O37: 34.821141 | P37: 20.771701 | Q37: -4.867613 | R37: -23.784513 | S37: -0.302465 | T37: 11.064369 | U37: 0.770673 | V37: -6.175271 | W37: 4.863676 | X37: -6.084349 | Y37: -3.325198 | Z37: -2.667099 | AA37: -6.310776 | AB37: 3.51406
A38: Slovenia | D38: .. | E38: 5.016008 | F38: 8.829721 | G38: 3.219138 | H38: -1.215605 | I38: 8.067515 | J38: -1.936127 | K38: 2.428169 | L38: 1.55858 | M38: 7.779298 | N38: 2.680255 | O38: 6.435189 | P38: 0.637735 | Q38: 5.8296 | R38: -7.109528 | S38: 3.526052 | T38: -1.373022 | U38: -1.870571 | V38: 1.581675 | W38: 0.195987 | X38: -4.973449 | Y38: 4.901538 | Z38: 5.14532 | AA38: 2.71458 | AB38: -4.351921
A39: Spain | D39: .. | E39: 2.537465 | F39: 0.460575 | G39: 0.67189 | H39: 2.003927 | I39: 2.599922 | J39: 4.34247 | K39: 3.078721 | L39: -0.7414 | M39: -0.168458 | N39: 0.910952 | O39: -0.185636 | P39: 1.292281 | Q39: 7.296289 | R39: -6.279951 | S39: 9.941465 | T39: 0.423131 | U39: -1.954385 | V39: -11.361386 | W39: -0.354357 | X39: -3.513248 | Y39: 6.742195 | Z39: -2.084163 | AA39: -5.338407 | AB39: 0.071949
A40: Sweden | D40: 6.533834 | E40: -0.783759 | F40: 1.660212 | G40: -2.295396 | H40: 2.840144 | I40: 3.85486 | J40: 4.709315 | K40: -4.260887 | L40: -10.421898 | M40: 9.76908 | N40: 2.062625 | O40: -13.932637 | P40: 7.743529 | Q40: -6.91219 | R40: -3.851432 | S40: 2.895263 | T40: -3.008885 | U40: 7.757074 | V40: -7.21792 | W40: 0.00598 | X40: 2.960254 | Y40: -2.313146 | Z40: -3.629622 | AA40: -0.491042 | AB40: 1.619569
A41: Switzerland | D41: .. | E41: -5.230728 | F41: 2.032599 | G41: -3.273897 | H41: 0.230223 | I41: 0.52093 | J41: 1.822724 | K41: -12.062864 | L41: -8.70262 | M41: -7.224966 | N41: 4.076028 | O41: 5.193394 | P41: -0.156211 | Q41: 6.965124 | R41: -8.568686 | S41: -4.996206 | T41: -9.677607 | U41: 3.626925 | V41: 0.854374 | W41: -14.866067 | X41: -15.680926 | Y41: -15.67215 | Z41: 6.925909 | AA41: 8.375918 | AB41: ..
A42: United Kingdom | D42: 8.461808 | E42: 3.863878 | F42: -1.477893 | G42: 3.163873 | H42: 7.834504 | I42: 1.010544 | J42: -1.975139 | K42: 3.718123 | L42: 2.225655 | M42: 1.626732 | N42: -4.067744 | O42: -6.093378 | P42: -3.944873 | Q42: -5.160115 | R42: -4.108502 | S42: -4.369326 | T42: -10.76256 | U42: -9.834171 | V42: -0.648738 | W42: 0.885528 | X42: 0.144142 | Y42: 5.192699 | Z42: -1.33391 | AA42: -5.632805 | AB42: 0.405239
A43: United States | D43: .. | E43: .. | F43: .. | G43: .. | H43: .. | I43: .. | J43: -6.233793 | K43: 3.968667 | L43: -4.200909 | M43: 3.412422 | N43: -6.282222 | O43: 6.170482 | P43: 2.872622 | Q43: -5.004498 | R43: 10.290607 | S43: -3.847729 | T43: 0.130174 | U43: 0.976581 | V43: -3.145911 | W43: 1.782306 | X43: 7.783318 | Y43: 2.947527 | Z43: 2.718879 | AA43: .. | AB43: ..
A44: Euro area (19 countries) | D44: .. | E44: 5.125663 | F44: -0.358056 | G44: 2.072951 | H44: 2.677887 | I44: 1.599316 | J44: 1.81693 | K44: 4.810453 | L44: 0.872171 | M44: 4.163464 | N44: -1.755048 | O44: -4.444534 | P44: 1.190549 | Q44: 1.990555 | R44: -0.444918 | S44: 1.50734 | T44: -5.278243 | U44: 3.300928 | V44: -1.799418 | W44: -1.833053 | X44: -0.769856 | Y44: 2.005384 | Z44: -0.151164 | AA44: -2.145689 | AB44: -2.485085
A45: European Union (28 countries) | D45: .. | E45: 4.057267 | F45: -0.355025 | G45: 2.717568 | H45: 5.063199 | I45: 3.500409 | J45: 3.231278 | K45: 3.795817 | L45: 2.220198 | M45: 2.125712 | N45: -1.836652 | O45: -4.842417 | P45: 1.597302 | Q45: 0.844681 | R45: -0.562435 | S45: 1.739286 | T45: -4.844454 | U45: 0.150173 | V45: -2.203673 | W45: -2.391557 | X45: 1.0436 | Y45: 2.760208 | Z45: 1.166606 | AA45: -1.922713 | AB45: -3.728092
A46: Non-OECD Economies | B46: Brazil | D46: .. | E46: .. | F46: .. | G46: .. | H46: .. | I46: .. | J46: -6.981844 | K46: 10.00204 | L46: 0.659419 | M46: -2.982182 | N46: 3.152489 | O46: 3.491201 | P46: 0.727252 | Q46: -1.321898 | R46: -2.105425 | S46: 4.003585 | T46: -0.946402 | U46: -1.655982 | V46: -4.961436 | W46: 13.581931 | X46: 5.994085 | Y46: 8.776481 | Z46: 0.794308 | AA46: .. | AB46: ..
B47: Costa Rica | D47: 30.867186 | E47: 3.433863 | F47: 9.155865 | G47: 8.94245 | H47: 10.288788 | I47: -3.370857 | J47: -7.068732 | K47: -9.857027 | L47: 0.256675 | M47: -2.299954 | N47: 16.222261 | O47: -4.795952 | P47: 11.321653 | Q47: -21.028767 | R47: 10.33822 | S47: -29.009999 | T47: 18.480387 | U47: 9.070695 | V47: -16.149921 | W47: 14.761359 | X47: 20.380864 | Y47: -10.161287 | Z47: 23.553897 | AA47: 11.606146 | AB47: ..
A48: Data extracted on 04 Jun 2020 21:30 UTC (GMT) from OECD.Stat

Sheet OECD Manufacturing
A1: #NAME? | B1: <?xml version="1.0" encoding="utf-16"?><WebTableParameter xmlns:xsd="http://www.w3.org/2001/XMLSchema" xmlns:xsi="http://www.w3.org/2001/XMLSchema-instance" xmlns="http://stats.oecd.org/OECDStatWS/2004/03/01/"><DataTable Code="PDBI_I4" HasMetadata="true"><Name LocaleIsoCode="en">Productivity and ULC by main economic activity (ISIC Rev.4)</Name><Name LocaleIsoCode="fr">Productivité et CUM par principale activité économique (CITI Rev.4)</Name><Dimension Code="LOCATION" HasMetadata="false" CommonCode="LOCATION" Display="labels"><Name LocaleIsoCode="en">Country</Name><Name LocaleIsoCode="fr">Pays</Name><Member Code="AUS" HasMetadata="false" HasOnlyUnitMetadata="false" HasChild="0"><Name LocaleIsoCode="en">Australia</Name><Name LocaleIsoCode="fr">Australie</Name></Member><Member Code="AUT" HasMetadata="false" HasOnlyUnitMetadata="false" HasChild="0"><Name LocaleIsoCode="en">Austria</Name><Name LocaleIsoCode="fr">Autriche</Name></Member><Member Code="BEL" HasMetadata="false" HasOnlyUnitMetadata="false" HasChild="0"><Name LocaleIsoCode="en">Belgium</Name><Name LocaleIsoCode="fr">Belgique</Name></Member><Member Code="CAN" HasMetadata="false" HasOnlyUnitMetadata="false" HasChild="0"><Name LocaleIsoCode="en">Canada</Name><Name LocaleIsoCode="fr">Canada</Name></Member><Member Code="CHL" HasMetadata="false" HasOnlyUnitMetadata="false" HasChild="0"><Name LocaleIsoCode="en">Chile</Name><Name LocaleIsoCode="fr">Chili</Name></Member><Member Code="COL" HasMetadata="false" HasOnlyUnitMetadata="false" HasChild="0"><Name LocaleIsoCode="en">Colombia</Name><Name LocaleIsoCode="fr">Colombie</Name></Member><Member Code="CZE" HasMetadata="false" HasOnlyUnitMetadata="false" HasChild="0"><Name LocaleIsoCode="en">Czech Republic</Name><Name LocaleIsoCode="fr">République tchèque</Name></Member><Member Code="DNK" HasMetadata="false" HasOnlyUnitMetadata="false" HasChild="0"><Name LocaleIsoCode="en">Denmark</Name><Name LocaleIsoCode="fr">Danemark</Name></Member><Member Code="EST" HasMetadata="false" HasOnlyUnitMetadata="false" HasChild="0"><Name LocaleIsoCode="en">Estonia</Name><Name LocaleIsoCode="fr">Estonie</Name></Member><Member Code="FIN" HasMetadata="false" HasOnlyUnitMetadata="false" HasChild="0"><Name LocaleIsoCode="en">Finland</Name><Name LocaleIsoCode="fr">Finlande</Name></Member><Member Code="FRA" HasMetadata="false" HasOnlyUnitMetadata="false" HasChild="0"><Name LocaleIsoCode="en">France</Name><Name LocaleIsoCode="fr">France</Name></Member><Member Code="DEU" HasMetadata="true" HasOnlyUnitMetadata="false" HasChild="0"><Name LocaleIsoCode="en">Germany</Name><Name LocaleIsoCode="fr">Allemagne</Name></Member><Member Code="GRC" HasMetadata="false" HasOnlyUnitMetadata="false" HasChild="0"><Name LocaleIsoCode="en">Greece</Name><Name LocaleIsoCode="fr">Grèce</Name></Member><Member Code="HUN" HasMetadata="false" HasOnlyUnitMetadata="false" HasChild="0"><Name LocaleIsoCode="en">Hungary</Name><Name LocaleIsoCode="fr">Hongrie</Name></Member><Member Code="ISL" HasMetadata="false" HasOnlyUnitMetadata="false" HasChild="0"><Name LocaleIsoCode="en">Iceland</Name><Name LocaleIsoCode="fr">Islande</Name></Member><Member Code="IRL" HasMetadata="true" HasOnlyUnitMetadata="false" HasChild="0"><Name LocaleIsoCode="en">Ireland</Name><Name LocaleIsoCode="fr">Irlande</Name></Member><Member Code="ISR" HasMetadata="true" HasOnlyUnitMetadata="false" HasChild="0"><Name LocaleIsoCode="en">Israel</Name><Name LocaleIsoCode="fr">Israël</Name></Member><Member Code="ITA" HasMetadata="false" HasOnlyUnitMetadata="false" HasChild="0"><Name LocaleIsoCode="en">Italy</Name><Name LocaleIsoCode="fr">Italie</Name></Member><Member Code="JPN" HasMetadata="false" HasOnlyUnitMetadata="false" HasChild="0"><Name LocaleIsoCode="en">Japan</Name><Name LocaleIsoCode="fr">Japon</Name></Member><Member Code="KOR" HasMetadata="false" HasOnlyUnitMetadata="false" HasChild="0"><Name LocaleIsoCode="en">Korea</Name><Name LocaleIsoCode="fr">Corée</Name></Member><Member Code="LVA" HasMetadata="false" HasOnlyUnitMetadata="false" HasChild="0"><Name LocaleIsoCode="en">Latvia</Name><Name LocaleIsoCode="fr">Lettonie</Name></Member><Member Code="LTU" HasMetadata="false" HasOnlyUnitMetadata="false" HasChild="0"><Name LocaleIsoCode="en">Lithuania</Name><Name LocaleIsoCode="fr">Lituanie</Name></Member><Member Code="LUX" HasMetadata="false" HasOnlyUnitMetadata="false" HasChild="0"><Name LocaleIsoCode="en">Luxembourg</Name><Name LocaleIsoCode="fr">Luxembourg</Name></Member><Member Code="MEX" HasMetadata="false" HasOnlyUnitMetadata="false" HasChild="0"><Name LocaleIsoCode="en">Mexico</Name><Name LocaleIsoCode="fr">Mexique</Name></Member><Member Code="NLD" HasMetadata="false" HasOnlyUnitMetadata="false" HasChild="0"><Name LocaleIsoCode="en">Netherlands</Name><Name LocaleIsoCode="fr">Pays-Bas</Name></Member><Member Code="NZL" HasMetadata="false" HasOnlyUnitMetadata="false" HasChild="0"><Name LocaleIsoCode="en">New Zealand</Name><Name LocaleIsoCode="fr">Nouvelle-Zélande</Name></Member><Member Code="NOR" HasMetadata="false" HasOnlyUnitMetadata="false" HasChild="0"><Name LocaleIsoCode="en">Norway</Name><Name LocaleIsoCode="fr">Norvège</Name></Member><Member Code="POL" HasMetadata="false" HasOnlyUnitMetadata="false" HasChild="0"><Name LocaleIsoCode="en">Poland</Name><Name LocaleIsoCode="fr">Pologne</Name></Member><Member Code="PRT" HasMetadata="false" HasOnlyUnitMetadata="false" HasChild="0"><Name LocaleIsoCode="en">Portugal</Name><Name LocaleIsoCode="fr">Portugal</Name></Member><Member Code="SVK" HasMetadata="false" HasOnlyUnitMetadata="false" HasChild="0"><Name LocaleIsoCode="en">Slovak Republic</Name><Name LocaleIsoCode="fr">République slovaque</Name></Member><Member Code="SVN" HasMetadata="false" HasOnlyUnitMetadata="false" HasChild="0"><Name LocaleIsoCode="en">Slovenia</Name><Name LocaleIsoCode="fr">Slovénie</Name></Member><Member Code="ESP" HasMetadata="false" HasOnlyUnitMetadata="false" HasChild="0"><Name LocaleIsoCode="en">Spain</Name><Name LocaleIsoCode="fr">Espagne</Name></Member><Member Code="SWE" HasMetadata="false" HasOnlyUnitMetadata="false" HasChild="0"><Name LocaleIsoCode="en">Sweden</Name><Name LocaleIsoCode="fr">Suède</Name></Member><Member Code="CHE" HasMetadata="false" HasOnlyUnitMetadata="false" HasChild="0"><Name LocaleIsoCode="en">Switzerland</Name><Name LocaleIsoCode="fr">Suisse</Name></Member><Member Code="GBR" HasMetadata="false" HasOnlyUnitMetadata="false" HasChild="0"><Name LocaleIsoCode="en">United Kingdom</Name><Name LocaleIsoCode="fr">Royaume-Uni</Name></Member><Member Code="USA" HasMetadata="false" HasOnlyUnitMetadata="false" HasChild="0"><Name LocaleIsoCode="en">United States</Name><Name LocaleIsoCode="fr">États-Unis</Name></Member><Member Code="EA19" HasMetadata="false" HasOnlyUnitMetadata="false" HasChild="0"><Name LocaleIsoCode="en">Euro area (19 countries)</Name><Name LocaleIsoCode="fr">Zone euro (19 pays)</Name></Member><Member Code="EU28" HasMetadata="false" HasOnlyUnitMetadata="false" HasChild="0"><Name LocaleIsoCode="en">European Union (28 countries)</Name><Name LocaleIsoCode="fr">Union européenne (28 pays)</Name></Member><Member Code="NMEC" HasMetadata="false" HasOnlyUnitMetadata="false" HasChild="1"><Name LocaleIsoCode="en">Non-OECD Economies</Name><Name LocaleIsoCode="fr">Économies non-OCDE</Name><ChildMember Code="BRA" HasMetadata="false" HasOnlyUnitMetadata="false" HasChild="0"><Name LocaleIsoCode="en">Brazil</Name><Name LocaleIsoCode="fr">Brésil</Name></ChildMember><ChildMember Code="CRI" HasMetadata="false" HasOnlyUnitMetadata="false" HasChild="0"><Name LocaleIsoCode="en">Costa Rica</Name><Name LocaleIsoCode="fr">Costa Rica</Name></ChildMember><ChildMember Code="RUS" HasMetadata="false" HasOnlyUnitMetadata="false" HasChild="0"><Name LocaleIsoCode="en">Russia</Name><Name LocaleIsoCode="fr">Russie</Name></ChildMember><ChildMember Code="ZAF" HasMetadata="false" HasOnlyUnitMetadata="false" HasChild="0"><Name LocaleIsoCode="en">South Africa</Name><Name LocaleIsoCode="fr">Afrique du Sud</Name></ChildMember></Member></Dimension><Dimension Code="SUBJECT" HasMetadata="false" Display="labels"><Name LocaleIsoCode="en">Subject</Name><Name LocaleIsoCode="fr">Sujet</Name><Member Code="I4_ANA_GVAHRS" HasMetadata="false" HasOnlyUnitMetadata="false" HasChild="0"><Name LocaleIsoCode="en">Gross value added per hour worked, constant prices</Name><Name LocaleIsoCode="fr">Valeur ajoutée brute par heure travaillée, prix constants</Name></Member><Member Code="I4_ANA_GVAEMP" HasMetadata="false" HasOnlyUnitMetadata="false" HasChild="0" IsDisplayed="true"><Name LocaleIsoCode="en">Gross value added per person employed, constant prices</Name><Name LocaleIsoCode="fr">Valeur ajoutée brute par actif occupé, prix constants</Name></Member><Member Code="I4_ANA_GVA" HasMetadata="false" HasOnlyUnitMetadata="false" HasChild="0"><Name LocaleIsoCode="en">Gross value added, constant prices</Name><Name LocaleIsoCode="fr">Valeur ajoutée brute, prix constants</Name></Member><Member Code="I4_ANA_EMPTO" HasMetadata="false" HasOnlyUnitMetadata="false" HasChild="0"><Name LocaleIsoCode="en">Total employment (number of persons employed)</Name><Name LocaleIsoCode="fr">Emploi total (nombre d'actifs occupés)</Name></Member><Member Code="I4_ANA_HRSTO" HasMetadata="true" HasOnlyUnitMetadata="false" HasChild="0"><Name LocaleIsoCode="en">Total hours worked</Name><Name LocaleIsoCode="fr">Heures travaillées totales</Name></Member><Member Code="I4_ANA_HRSAV" HasMetadata="true" HasOnlyUnitMetadata="false" HasChild="0"><Name LocaleIsoCode="en">Average hours worked per person employed</Name><Name LocaleIsoCode="fr">Heures travaillées moyennes par actif occupé</Name></Member><Member Code="I4_ANA_CONILPHRS" HasMetadata="false" HasOnlyUnitMetadata="false" HasChild="0"><Name LocaleIsoCode="en">Industry contribution to business sector labour productivity</Name><Name LocaleIsoCode="fr">Contribution par industrie à la productivité du travail du secteur marchand</Name></Member><Member Code="I4_ANA_CONILPEMP" HasMetadata="false" HasOnlyUnitMetadata="false" HasChild="0"><Name LocaleIsoCode="en">Industry contribution to business sector labour productivity; employment based</Name><Name LocaleIsoCode="fr">Contribution par industrie à la productivité du travail du secteur marchand (basée sur l'emploi)</Name></Member><Member Code="I4_ANA_ULCH" HasMetadata="true" HasOnlyUnitMetadata="false" HasChild="0"><Name LocaleIsoCode="en">Unit Labour Costs</Name><Name LocaleIsoCode="fr">Coûts unitaires de la main d'œuvre</Name></Member><Member Code="I4_ANA_LCHRS" HasMetadata="true" HasOnlyUnitMetadata="false" HasChild="0"><Name LocaleIsoCode="en">Labour compensation per hour worked</Name><Name LocaleIsoCode="fr">Rémunération de la main d'oeuvre par heure travaillée</Name></Member><Member Code="I4_ANA_ULCE" HasMetadata="true" HasOnlyUnitMetadata="false" HasChild="0"><Name LocaleIsoCode="en">Unit Labour Costs, employment based</Name><Name LocaleIsoCode="fr">Coûts unitaires de la main d'œuvre, basés sur l'emploi </Name></Member><Member Code="I4_ANA_LCEMP" HasMetadata="false" HasOnlyUnitMetadata="false" HasChild="0"><Name LocaleIsoCode="en">Labour compensation per employee</Name><Name LocaleIsoCode="fr">Rémunération de la main d'oeuvre par salarié </Name></Member></Dimension><Dimension Code="MEASURE" HasMetadata="false" Display="labels"><Name LocaleIsoCode="en">Measure</Name><Name LocaleIsoCode="fr">Mesure</Name><Member Code="GRW" HasMetadata="true" HasOnlyUnitMetadata="false" HasChild="0"><Name LocaleIsoCode="en">Annual growth/change</Name><Name LocaleIsoCode="fr">Croissance/variation annuelle</Name></Member></Dimension><Dimension Code="ACTIVITY" HasMetadata="false" Display="codesandlabels"><Name LocaleIsoCode="en">Activity</Name><Name LocaleIsoCode="fr">Activité</Name><Member Code="A_U" HasMetadata="false" HasOnlyUnitMetadata="false" HasChild="1"><Name LocaleIsoCode="en">Total </Name><Name LocaleIsoCode="fr">Total</Name><ChildMember Code="BNEXCL" HasMetadata="false" HasOnlyUnitMetadata="false" HasChild="1"><Name LocaleIsoCode="en">Non-agriculture business sector excluding real estate</Name><Name LocaleIsoCode="fr">Secteur marchand non-agricole, hors activités immobilières</Name><ChildMember Code="B_E" HasMetadata="false" HasOnlyUnitMetadata="false" HasChild="1"><Name LocaleIsoCode="en">Industry including energy</Name><Name LocaleIsoCode="fr">Industrie, y compris l’énergie</Name><ChildMember Code="BDE" HasMetadata="false" HasOnlyUnitMetadata="false" HasChild="0"><Name LocaleIsoCode="en">Mining and utilities</Name><Name LocaleIsoCode="fr">Industries extractives , électricité et gaz , eau et déchets</Name></ChildMember><ChildMember Code="C" HasMetadata="false" HasOnlyUnitMetadata="false" HasChild="0" IsDisplayed="true"><Name LocaleIsoCode="en">Manufacturing</Name><Name LocaleIsoCode="fr">Activités de fabrication</Name></ChildMember></ChildMember><ChildMember Code="F" HasMetadata="false" HasOnlyUnitMetadata="false" HasChild="0"><Name LocaleIsoCode="en">Construction</Name><Name LocaleIsoCode="fr">Construction</Name></ChildMember><ChildMember Code="GNEXCL" HasMetadata="false" HasOnlyUnitMetadata="false" HasChild="1"><Name LocaleIsoCode="en">Business sector services excluding real estate</Name><Name LocaleIsoCode="fr">Services marchands, hors activités immobilières</Name><ChildMember Code="G_I" HasMetadata="false" HasOnlyUnitMetadata="false" HasChild="0"><Name LocaleIsoCode="en">Wholesale retail trade accommodation food services, transportation and storage</Name><Name LocaleIsoCode="fr">Commerce de gros et de détail, réparations , transport et entreposage , hébergement et restauration</Name></ChildMember><ChildMember Code="J" HasMetadata="false" HasOnlyUnitMetadata="false" HasChild="0"><Name LocaleIsoCode="en">Information and communication</Name><Name LocaleIsoCode="fr">Information et communication</Name></ChildMember><ChildMember Code="K" HasMetadata="false" HasOnlyUnitMetadata="false" HasChild="0"><Name LocaleIsoCode="en">Financial and insurance activities</Name><Name LocaleIsoCode="fr">Activités financières et d'assurances</Name></ChildMember><ChildMember Code="MN" HasMetadata="false" HasOnlyUnitMetadata="false" HasChild="0"><Name LocaleIsoCode="en">Professional, scientific and technical activities, Administrative and support service activities</Name><Name LocaleIsoCode="fr">Activités professionnelles, scientifiques et techniques , activités de services administratifs et d’appui</Name></ChildMember></ChildMember></ChildMember></Member></Dimension><Dimension Code="TIME" HasMetadata="false" CommonCode="TIME" Display="labels"><Name LocaleIsoCode="en">Time</Name><Name LocaleIsoCode="fr">Temps</Name><Member Code="1995" HasMetadata="false"><Name LocaleIsoCode="en">1995</Name><Name LocaleIsoCode="fr">1995</Name></Member><Member Code="1996" HasMetadata="false"><Name LocaleIsoCode="en">1996</Name><Name LocaleIsoCode="fr">1996</Name></Member><Member Code="1997" HasMetadata="false"><Name LocaleIsoCode="en">1997</Name><Name LocaleIsoCode="fr">1997</Name></Member><Member Code="1998" HasMetadata="false"><Name LocaleIsoCode="en">1998</Name><Name LocaleIsoCode="fr">1998</Name></Member><Member Code="1999" HasMetadata="false"><Name LocaleIsoCode="en">1999</Name><Name LocaleIsoCode="fr">1999</Name></Member><Member Code="2000" HasMetadata="false"><Name LocaleIsoCode="en">2000</Name><Name LocaleIsoCode="fr">2000</Name></Member><Member Code="2001" HasMetadata="false"><Name LocaleIsoCode="en">2001</Name><Name LocaleIsoCode="fr">2001</Name></Member><Member Code="2002" HasMetadata="false"><Name LocaleIsoCode="en">2002</Name><Name LocaleIsoCode="fr">2002</Name></Member><Member Code="2003" HasMetadata="false"><Name LocaleIsoCode="en">2003</Name><Name LocaleIsoCode="fr">2003</Name></Member><Member Code="2004" HasMetadata="false"><Name LocaleIsoCode="en">2004</Name><Name LocaleIsoCode="fr">2004</Name></Member><Member Code="2005" HasMetadata="false"><Name LocaleIsoCode="en">2005</Name><Name LocaleIsoCode="fr">2005</Name></Member><Member Code="2006" HasMetadata="false"><Name LocaleIsoCode="en">2006</Name><Name LocaleIsoCode="fr">2006</Name></Member><Member Code="2007" HasMetadata="false"><Name LocaleIsoCode="en">2007</Name><Name LocaleIsoCode="fr">2007</Name></Member><Member Code="2008" HasMetadata="false"><Name LocaleIsoCode="en">2008</Name><Name LocaleIsoCode="fr">2008</Name></Member><Member Code="2009" HasMetadata="false"><Name LocaleIsoCode="en">2009</Name><Name LocaleIsoCode="fr">2009</Name></Member><Member Code="2010" HasMetadata="false"><Name LocaleIsoCode="en">2010</Name><Name LocaleIsoCode="fr">2010</Name></Member><Member Code="2011" HasMetadata="false"><Name LocaleIsoCode="en">2011</Name><Name LocaleIsoCode="fr">2011</Name></Member><Member Code="2012" HasMetadata="false"><Name LocaleIsoCode="en">2012</Name><Name LocaleIsoCode="fr">2012</Name></Member><Member Code="2013" HasMetadata="false"><Name LocaleIsoCode="en">2013</Name><Name LocaleIsoCode="fr">2013</Name></Member><Member Code="2014" HasMetadata="false"><Name LocaleIsoCode="en">2014</Name><Name LocaleIsoCode="fr">2014</Name></Member><Member Code="2015" HasMetadata="false"><Name LocaleIsoCode="en">2015</Name><Name LocaleIsoCode="fr">2015</Name></Member><Member Code="2016" HasMetadata="false"><Name LocaleIsoCode="en">2016</Name><Name LocaleIsoCode="fr">2016</Name></Member><Member Code="2017" HasMetadata="false"><Name LocaleIsoCode="en">2017</Name><Name LocaleIsoCode="fr">2017</Name></Member><Member Code="2018" HasMetadata="false"><Name LocaleIsoCode="en">2018</Name><Name LocaleIsoCode="fr">2018</Name></Member><Member Code="2019" HasMetadata="false"><Name LocaleIsoCode="en">2019</Name><Name LocaleIsoCode="fr">2019</Name></Member></Dimension><WBOSInformations><TimeDimension WebTreeWasUsed="false"><StartCodes Annual="1995" /></TimeDimension></WBOSInformations><Tabulation Axis="horizontal"><Dimension Code="TIME" CommonCode="TIME" /><Dimension Code="MEASURE" /></Tabulation><Tabulation Axis="vertical"><Dimension Code="LOCATION" CommonCode="LOCATION" /></Tabulation><Tabulation Axis="page"><Dimension Code="SUBJECT" /><Dimension Code="ACTIVITY" /></Tabulation><Formatting><Labels LocaleIsoCode="en" /><Power>0</Power><Decimals>1</Decimals><SkipEmptyLines>true</SkipEmptyLines><SkipEmptyCols>true</SkipEmptyCols><SkipLineHierarchy>false</SkipLineHierarchy><SkipColHierarchy>false</SkipColHierarchy><Page>1</Page></Formatting></DataTable><Format><ShowEmptyAxes>true</ShowEmptyAxes><Page>1</Page><EnableSort>true</EnableSort><IncludeFlagColumn>false</IncludeFlagColumn><IncludeTimeSeriesId>false</IncludeTimeSeriesId><DoBarChart>false</DoBarChart><FreezePanes>true</FreezePanes><MaxBarChartLen>65</MaxBarChartLen></Format><Query><AbsoluteUri>http://stats.oecd.org//View.aspx?QueryId=&amp;QueryType=Public&amp;Lang=en</AbsoluteUri></Query></WebTableParameter>
A2: Dataset: Productivity and ULC by main economic activity (ISIC Rev.4)
A3: Subject | D3: Gross value added per person employed, constant prices
A4: Activity | D4: C: Manufacturing
A5: Time | D5: 1995 | E5: 1996 | F5: 1997 | G5: 1998 | H5: 1999 | I5: 2000 | J5: 2001 | K5: 2002 | L5: 2003 | M5: 2004 | N5: 2005 | O5: 2006 | P5: 2007 | Q5: 2008 | R5: 2009 | S5: 2010 | T5: 2011 | U5: 2012 | V5: 2013 | W5: 2014 | X5: 2015 | Y5: 2016 | Z5: 2017 | AA5: 2018 | AB5: 2019
A6: Measure | D6: Annual growth/change
A7: Unit | D7: Percentage
A8: Country
A9: Australia | D9: 2.877152 | E9: -0.437182 | F9: 6.925454 | G9: 3.941735 | H9: -5.271467 | I9: 6.829335 | J9: 2.988234 | K9: 4.083924 | L9: 1.145228 | M9: 1.662998 | N9: -0.221015 | O9: -0.561053 | P9: 1.894252 | Q9: 1.181449 | R9: 2.000234 | S9: 1.457994 | T9: 1.212276 | U9: 0.289287 | V9: -2.583693 | W9: -0.981908 | X9: 0.159597 | Y9: 0.574867 | Z9: -4.087587 | AA9: .. | AB9: ..
A10: Austria | D10: 7.705436 | E10: 3.493053 | F10: 3.292483 | G10: 2.595522 | H10: 4.163498 | I10: 6.632105 | J10: 2.626684 | K10: 1.006394 | L10: 1.046575 | M10: 4.432717 | N10: 5.37147 | O10: 7.815195 | P10: 5.284663 | Q10: 0.339338 | R10: -11.499369 | S10: 9.724944 | T10: 5.698102 | U10: 1.050482 | V10: 0.518423 | W10: 2.292879 | X10: 0.365581 | Y10: 4.053353 | Z10: 3.436715 | AA10: 2.237175 | AB10: -0.994405
A11: Belgium | D11: .. | E11: 4.51491 | F11: 7.811887 | G11: 3.135033 | H11: 2.008268 | I11: 4.562902 | J11: -0.324927 | K11: 3.919185 | L11: 2.921187 | M11: 7.146003 | N11: 3.532121 | O11: -1.389192 | P11: 7.005714 | Q11: -3.259667 | R11: -3.801312 | S11: 9.639978 | T11: -0.072425 | U11: -0.127424 | V11: 3.419362 | W11: 5.814642 | X11: 5.269344 | Y11: -1.68215 | Z11: 2.10481 | AA11: -1.641767 | AB11: -1.411345
A12: Canada | D12: .. | E12: .. | F12: .. | G12: .. | H12: .. | I12: .. | J12: .. | K12: .. | L12: .. | M12: .. | N12: .. | O12: .. | P12: .. | Q12: 0.756356 | R12: -6.632876 | S12: 4.675547 | T12: 2.662676 | U12: 1.601607 | V12: 1.461275 | W12: 3.614952 | X12: 2.494138 | Y12: 0.493211 | Z12: 1.341579 | AA12: 3.295354 | AB12: ..
A13: Chile | D13: .. | E13: .. | F13: .. | G13: .. | H13: .. | I13: .. | J13: .. | K13: .. | L13: .. | M13: .. | N13: .. | O13: .. | P13: .. | Q13: .. | R13: .. | S13: .. | T13: 0.699817 | U13: 0.852607 | V13: 1.484854 | W13: -1.545053 | X13: -0.062231 | Y13: 0.58484 | Z13: 0.672461 | AA13: 6.654373 | AB13: ..
A14: Czech Republic | D14: 15.179769 | E14: 5.955778 | F14: 2.772376 | G14: 2.979016 | H14: 11.764993 | I14: 11.506966 | J14: 3.707167 | K14: 4.163683 | L14: 4.896261 | M14: 7.548584 | N14: 12.384002 | O14: 19.629625 | P14: 3.748556 | Q14: 7.644393 | R14: -4.651129 | S14: 14.854004 | T14: 6.273789 | U14: -4.164557 | V14: -2.581784 | W14: 4.828515 | X14: 1.629772 | Y14: 0.794843 | Z14: 9.134912 | AA14: 0.453179 | AB14: 1.134908
A15: Denmark | D15: 2.997019 | E15: -2.476895 | F15: 10.248718 | G15: 2.778432 | H15: 3.772773 | I15: 5.109124 | J15: 1.024163 | K15: 0.202722 | L15: 1.367069 | M15: 6.10414 | N15: 0.182604 | O15: 5.744203 | P15: -1.497398 | Q15: -1.080567 | R15: 0.984099 | S15: 13.897588 | T15: 6.311803 | U15: 6.109113 | V15: 4.668684 | W15: 0.83242 | X15: -1.757864 | Y15: 4.768126 | Z15: 1.392662 | AA15: 3.586482 | AB15: 3.929962
A16: Estonia | D16: .. | E16: 5.621851 | F16: 33.148203 | G16: 7.54828 | H16: 4.928195 | I16: 13.942669 | J16: 11.913045 | K16: 10.623074 | L16: 4.221689 | M16: 0.453299 | N16: 8.501816 | O16: 14.462205 | P16: 7.743162 | Q16: -6.1536 | R16: -8.04544 | S16: 26.637252 | T16: 2.046678 | U16: 5.5884 | V16: 1.82867 | W16: 8.109892 | X16: -3.260692 | Y16: 1.378728 | Z16: 0.609862 | AA16: 8.430832 | AB16: 6.135737
A17: Finland | D17: 2.099219 | E17: 2.962716 | F17: 6.312201 | G17: 7.32059 | H17: 7.38725 | I17: 12.023002 | J17: 2.732008 | K17: 5.531139 | L17: 5.798619 | M17: 7.671276 | N17: 3.614621 | O17: 10.597878 | P17: 8.830745 | Q17: -3.935844 | R17: -14.666509 | S17: 12.793638 | T17: -1.058548 | U17: -11.247675 | V17: 4.654448 | W17: 1.983434 | X17: 1.934009 | Y17: 6.424549 | Z17: 8.241985 | AA17: -1.96388 | AB17: 3.66559
A18: France | D18: 3.881426 | E18: 1.97208 | F18: 5.272113 | G18: 5.30705 | H18: 4.219528 | I18: 4.654493 | J18: 0.546195 | K18: 1.630609 | L18: 4.442896 | M18: 5.917035 | N18: 3.900278 | O18: 4.61004 | P18: 3.113068 | Q18: -2.092645 | R18: -0.80626 | S18: 7.268691 | T18: 4.693002 | U18: 0.30863 | V18: 1.121108 | W18: 2.114379 | X18: 2.75819 | Y18: 1.441948 | Z18: 1.610533 | AA18: -0.037193 | AB18: 0.825923
A19: Germany | D19: 1.896956 | E19: -0.255454 | F19: 5.667756 | G19: 0.335543 | H19: 1.328584 | I19: 5.952502 | J19: 1.171387 | K19: -0.273416 | L19: 3.74955 | M19: 5.2614 | N19: 3.423305 | O19: 9.83118 | P19: 2.659715 | Q19: -4.514812 | R19: -17.304466 | S19: 21.386322 | T19: 6.183521 | U19: -3.482249 | V19: -0.386107 | W19: 4.371561 | X19: 0.58589 | Y19: 3.84571 | Z19: 2.260952 | AA19: -0.231436 | AB19: -4.177958
A20: Greece | D20: .. | E20: -4.660338 | F20: 3.888999 | G20: 1.168789 | H20: 11.016985 | I20: 4.848225 | J20: 5.494402 | K20: 4.826936 | L20: 4.119358 | M20: -2.484748 | N20: -2.117331 | O20: -0.507066 | P20: 5.28081 | Q20: -10.015307 | R20: -0.539478 | S20: -4.312438 | T20: 2.763837 | U20: 0.924254 | V20: 6.236906 | W20: 0.924434 | X20: -4.766769 | Y20: 6.985381 | Z20: 0.199306 | AA20: 1.829916 | AB20: -4.296867
A21: Hungary | D21: .. | E21: 3.817712 | F21: 11.634315 | G21: 4.824087 | H21: 3.769794 | I21: 4.382831 | J21: 4.121496 | K21: 7.488165 | L21: 9.707483 | M21: 12.9604 | N21: 7.08638 | O21: 7.272483 | P21: 7.666027 | Q21: -0.808974 | R21: -9.855074 | S21: 13.009081 | T21: 0.65336 | U21: -3.816026 | V21: 0.720322 | W21: 5.189904 | X21: 9.165862 | Y21: -4.116739 | Z21: 0.013012 | AA21: -3.180077 | AB21: 4.51973
A22: Iceland | D22: .. | E22: .. | F22: .. | G22: .. | H22: .. | I22: .. | J22: .. | K22: .. | L22: .. | M22: .. | N22: .. | O22: .. | P22: .. | Q22: .. | R22: 4.158634 | S22: 1.786292 | T22: 4.655006 | U22: 0.297068 | V22: 3.888527 | W22: 0.949255 | X22: 4.826348 | Y22: -3.553727 | Z22: 1.344594 | AA22: 0.926935 | AB22: 3.967939
A23: Ireland | D23: .. | E23: 5.163144 | F23: 9.141816 | G23: 10.764463 | H23: 10.839184 | I23: 12.125246 | J23: 4.903034 | K23: 16.540445 | L23: 1.895172 | M23: 1.415979 | N23: 7.984373 | O23: 2.276714 | P23: 5.670164 | Q23: -5.946036 | R23: 4.999164 | S23: 23.44115 | T23: 5.756747 | U23: -0.069587 | V23: -7.937671 | W23: 9.203132 | X23: 81.716927 | Y23: -2.324732 | Z23: 6.079895 | AA23: 11.103363 | AB23: 1.147543
A24: Israel | D24: .. | E24: 6.111496 | F24: 7.734169 | G24: 7.042873 | H24: 6.280738 | I24: 11.600257 | J24: -2.538526 | K24: -0.870108 | L24: 9.287118 | M24: -0.295354 | N24: 4.7787 | O24: 2.252166 | P24: 1.748734 | Q24: -5.773355 | R24: -4.660401 | S24: 13.791247 | T24: -2.177027 | U24: -0.000539 | V24: -2.658127 | W24: 5.191755 | X24: -1.754445 | Y24: -5.83826 | Z24: 2.043933 | AA24: 1.794008 | AB24: ..
A25: Italy | D25: 5.518118 | E25: 0.912931 | F25: 1.4662 | G25: -0.477872 | H25: 0.981869 | I25: 3.642401 | J25: -0.249607 | K25: -0.563611 | L25: -2.617443 | M25: 2.731975 | N25: 1.567153 | O25: 3.530651 | P25: 2.518474 | Q25: -2.252459 | R25: -14.283585 | S25: 13.6791 | T25: 2.373485 | U25: -2.161976 | V25: 1.568052 | W25: 2.118623 | X25: 3.490194 | Y25: 2.0841 | Z25: 2.821248 | AA25: 1.231045 | AB25: -0.780711
A26: Japan | D26: 7.790366 | E26: 5.729171 | F26: 2.598852 | G26: 0.193866 | H26: 2.199998 | I26: 7.737904 | J26: -2.82594 | K26: 3.310746 | L26: 6.34109 | M26: 7.20048 | N26: 7.172565 | O26: 1.273185 | P26: 3.454607 | Q26: 0.305001 | R26: -13.582816 | S26: 17.383656 | T26: -1.88124 | U26: 3.995957 | V26: 2.130797 | W26: 2.963392 | X26: 4.867826 | Y26: -0.644741 | Z26: 3.821635 | AA26: 0.394821 | AB26: ..
A27: Korea | D27: .. | E27: .. | F27: .. | G27: .. | H27: .. | I27: .. | J27: .. | K27: .. | L27: .. | M27: .. | N27: 6.921421 | O27: 9.405207 | P27: 8.816479 | Q27: 4.554449 | R27: 0.975744 | S27: 7.997037 | T27: 3.267244 | U27: 1.061326 | V27: 1.361157 | W27: -0.34012 | X27: -1.541685 | Y27: 2.765318 | Z27: 4.114829 | AA27: 4.655856 | AB27: ..
A28: Latvia | D28: .. | E28: 3.161789 | F28: 11.685756 | G28: 5.329991 | H28: -2.31394 | I28: 10.538687 | J28: 2.526784 | K28: 7.487936 | L28: 0.899877 | M28: 9.087912 | N28: 6.347284 | O28: 6.671419 | P28: 1.95969 | Q28: -5.171165 | R28: 0.650204 | S28: 14.955712 | T28: 2.023007 | U28: -0.673012 | V28: -1.748321 | W28: 4.741714 | X28: 2.306066 | Y28: 2.235628 | Z28: 6.860267 | AA28: 1.650901 | AB28: 1.551619
A29: Lithuania | D29: .. | E29: 4.027709 | F29: 8.457082 | G29: 13.879875 | H29: -0.875329 | I29: 17.399102 | J29: 19.500439 | K29: -2.382216 | L29: 11.324269 | M29: 17.026792 | N29: 3.999444 | O29: 13.861747 | P29: 5.846923 | Q29: 2.101917 | R29: -2.028409 | S29: 18.425931 | T29: 8.359496 | U29: 2.171314 | V29: 5.076131 | W29: 4.799995 | X29: 0.911325 | Y29: -0.475967 | Z29: 6.415212 | AA29: -0.367898 | AB29: 2.741656
A30: Luxembourg | D30: .. | E30: -0.959531 | F30: 3.339399 | G30: -0.068646 | H30: 6.909648 | I30: 5.08036 | J30: -6.144863 | K30: 6.328526 | L30: 7.469488 | M30: -0.738356 | N30: -1.358351 | O30: -11.995574 | P30: 18.5604 | Q30: -23.222078 | R30: -18.469312 | S30: 10.800619 | T30: -12.95189 | U30: 5.714149 | V30: 15.105317 | W30: -7.79786 | X30: 13.69972 | Y30: 16.378265 | Z30: -1.753907 | AA30: -2.186402 | AB30: ..
A31: Mexico | D31: .. | E31: .. | F31: .. | G31: .. | H31: .. | I31: .. | J31: .. | K31: .. | L31: .. | M31: .. | N31: .. | O31: .. | P31: .. | Q31: .. | R31: .. | S31: .. | T31: 0.859362 | U31: 2.50305 | V31: -2.261108 | W31: .. | X31: .. | Y31: .. | Z31: .. | AA31: .. | AB31: ..
A32: Netherlands | D32: .. | E32: 3.253337 | F32: 1.091587 | G32: 4.03287 | H32: 4.010078 | I32: 5.079856 | J32: 2.759486 | K32: 1.823954 | L32: 2.361457 | M32: 7.341767 | N32: 5.175859 | O32: 3.016995 | P32: 5.696035 | Q32: -0.962648 | R32: -7.436968 | S32: 7.476887 | T32: 5.321827 | U32: 0.208004 | V32: 0.880918 | W32: 3.054164 | X32: 0.581787 | Y32: 1.617239 | Z32: 5.120485 | AA32: 2.662951 | AB32: -1.246047
A33: New Zealand | D33: .. | E33: .. | F33: .. | G33: .. | H33: .. | I33: .. | J33: .. | K33: .. | L33: .. | M33: .. | N33: .. | O33: .. | P33: .. | Q33: .. | R33: .. | S33: .. | T33: -1.417398 | U33: 4.21337 | V33: -0.614986 | W33: 0.122284 | X33: 0.366685 | Y33: 6.07644 | Z33: 1.258843 | AA33: 3.502279 | AB33: ..
A34: Norway | D34: -2.273591 | E34: 2.905781 | F34: 0.533547 | G34: -2.763806 | H34: 4.392672 | I34: 2.621226 | J34: 3.362147 | K34: 2.046837 | L34: 9.072935 | M34: 9.965663 | N34: 3.386095 | O34: -3.039585 | P34: 1.915661 | Q34: 1.889207 | R34: -3.101376 | S34: 6.193105 | T34: 2.19481 | U34: 1.218241 | V34: 2.045109 | W34: 3.000597 | X34: -1.727102 | Y34: 0.13548 | Z34: 2.188477 | AA34: -0.497078 | AB34: ..
A35: Poland | D35: .. | E35: -2.013926 | F35: -1.280349 | G35: -0.367215 | H35: 8.091064 | I35: 4.643551 | J35: 1.804927 | K35: 12.699261 | L35: 11.165105 | M35: 10.201479 | N35: 1.309144 | O35: 11.135069 | P35: 7.949408 | Q35: 3.544436 | R35: 6.928152 | S35: 15.966618 | T35: 6.518287 | U35: 3.728964 | V35: -1.709587 | W35: 5.64892 | X35: 3.880528 | Y35: -0.841437 | Z35: -1.985066 | AA35: 3.816654 | AB35: 7.653566
A36: Portugal | D36: .. | E36: 9.908204 | F36: 5.005955 | G36: 1.625951 | H36: 1.199534 | I36: 3.232852 | J36: 2.070293 | K36: 2.592315 | L36: 3.007534 | M36: 4.987599 | N36: 3.120375 | O36: 2.713252 | P36: 4.600811 | Q36: 0.51075 | R36: -2.425379 | S36: 9.95741 | T36: 2.56677 | U36: 0.336933 | V36: 2.653449 | W36: 0.443511 | X36: -0.301288 | Y36: 0.322545 | Z36: 2.33027 | AA36: -1.635948 | AB36: -1.369007
A37: Slovak Republic | D37: .. | E37: -0.24307 | F37: 6.647531 | G37: 22.11148 | H37: 4.917042 | I37: 16.485758 | J37: 15.693181 | K37: 4.937094 | L37: 14.118964 | M37: 22.937835 | N37: 12.80769 | O37: 10.089337 | P37: 8.037215 | Q37: -0.887346 | R37: -4.541923 | S37: 34.087683 | T37: -0.145735 | U37: 1.810801 | V37: -0.018281 | W37: 17.232306 | X37: 9.256193 | Y37: -4.341234 | Z37: -2.485247 | AA37: 14.651058 | AB37: -0.024122
A38: Slovenia | D38: .. | E38: 11.27747 | F38: 11.706909 | G38: 3.124903 | H38: 3.71674 | I38: 9.11201 | J38: 5.045442 | K38: 7.016761 | L38: 8.156665 | M38: 6.522296 | N38: 5.817577 | O38: 8.779226 | P38: 7.885038 | Q38: 1.578624 | R38: -6.705308 | S38: 12.937383 | T38: 3.670239 | U38: -1.276375 | V38: 1.403921 | W38: 4.298813 | X38: 1.051328 | Y38: 1.935491 | Z38: 4.682686 | AA38: -0.977587 | AB38: 0.961565
A39: Spain | D39: .. | E39: -0.827205 | F39: 1.227364 | G39: 1.360805 | H39: 1.507957 | I39: 1.972768 | J39: 4.290586 | K39: 1.677872 | L39: 2.162051 | M39: 0.684031 | N39: 1.89256 | O39: 4.210732 | P39: 3.505098 | Q39: -1.275128 | R39: 2.094289 | S39: 4.412722 | T39: 3.325735 | U39: 1.789021 | V39: 4.646536 | W39: 3.208613 | X39: 2.375671 | Y39: -1.165555 | Z39: 1.46043 | AA39: -0.853151 | AB39: -1.138253
A40: Sweden | D40: 6.931454 | E40: 3.991661 | F40: 8.668141 | G40: 6.385032 | H40: 8.619998 | I40: 9.230896 | J40: -2.564051 | K40: 7.406 | L40: 8.432443 | M40: 10.454931 | N40: 4.318741 | O40: 8.35342 | P40: 1.73557 | Q40: -3.832795 | R40: -15.171641 | S40: 25.691432 | T40: 3.282949 | U40: -5.608376 | V40: -1.57264 | W40: 0.590578 | X40: 7.423645 | Y40: 4.153808 | Z40: 0.301991 | AA40: 2.39386 | AB40: 1.128836
A41: Switzerland | D41: .. | E41: 3.272533 | F41: 6.056693 | G41: 2.535994 | H41: 2.882838 | I41: 2.2604 | J41: 3.768763 | K41: 4.627659 | L41: 2.559842 | M41: 3.187053 | N41: 3.176906 | O41: 3.703835 | P41: 2.046521 | Q41: 1.418866 | R41: -8.308133 | S41: 9.452917 | T41: 6.013929 | U41: -0.999984 | V41: 1.935725 | W41: 0.032286 | X41: 1.296116 | Y41: 5.208667 | Z41: 5.761961 | AA41: 3.337963 | AB41: ..
A42: United Kingdom | D42: -0.324548 | E42: -0.582784 | F42: 1.53714 | G42: 0.841625 | H42: 4.252694 | I42: 5.468434 | J42: 3.522867 | K42: 2.518288 | L42: 5.455203 | M42: 6.234396 | N42: 4.822299 | O42: 5.099777 | P42: 3.253707 | Q42: -0.087469 | R42: -2.346768 | S42: 7.066202 | T42: 2.813412 | U42: -1.920998 | V42: -0.39821 | W42: 2.290566 | X42: -1.043332 | Y42: 0.593225 | Z42: 0.711963 | AA42: -0.986271 | AB42: -1.623668
A43: United States | D43: .. | E43: .. | F43: .. | G43: .. | H43: .. | I43: .. | J43: 1.805953 | K43: 8.119128 | L43: 7.580201 | M43: 9.734039 | N43: 4.396405 | O43: 4.871733 | P43: 3.822985 | Q43: 0.480536 | R43: 1.465929 | S43: 6.423005 | T43: -1.458286 | U43: -2.94131 | V43: 1.670437 | W43: -0.417373 | X43: -1.025633 | Y43: -1.620591 | Z43: 2.432879 | AA43: .. | AB43: ..
A44: Euro area (19 countries) | D44: .. | E44: 0.755006 | F44: 4.144894 | G44: 1.948635 | H44: 2.519749 | I44: 5.36015 | J44: 1.502908 | K44: 1.015989 | L44: 2.220651 | M44: 4.521744 | N44: 3.14278 | O44: 6.021629 | P44: 3.741624 | Q44: -2.962448 | R44: -9.554592 | S44: 13.74985 | T44: 4.542432 | U44: -1.336092 | V44: 1.087736 | W44: 3.652729 | X44: 3.90938 | Y44: 2.208812 | Z44: 2.553 | AA44: 0.749248 | AB44: -1.865662
A45: European Union (28 countries) | D45: .. | E45: 0.393082 | F45: 3.874038 | G45: 2.563446 | H45: 4.039736 | I45: 6.016901 | J45: 1.799445 | K45: 1.458634 | L45: 2.829298 | M45: 4.949841 | N45: 3.129531 | O45: 5.64401 | P45: 3.098286 | Q45: -2.135422 | R45: -7.731972 | S45: 13.797117 | T45: 4.287155 | U45: -1.642635 | V45: 0.596149 | W45: 3.040444 | X45: 3.253089 | Y45: 1.375056 | Z45: 1.888184 | AA45: 0.742406 | AB45: -0.778787
A46: Non-OECD Economies | B46: Brazil | D46: .. | E46: .. | F46: .. | G46: .. | H46: .. | I46: .. | J46: 2.011289 | K46: -1.402613 | L46: -1.147798 | M46: 0.64361 | N46: -5.33156 | O46: 1.079232 | P46: 1.915326 | Q46: 0.966478 | R46: -8.087234 | S46: 2.939225 | T46: 0.803293 | U46: -3.806925 | V46: 1.529008 | W46: -3.048924 | X46: -2.752547 | Y46: 0.762018 | Z46: 0.96783 | AA46: .. | AB46: ..
B47: Costa Rica | D47: 7.36211 | E47: -0.563026 | F47: 7.062496 | G47: -0.600789 | H47: 0.60781 | I47: 7.928501 | J47: -6.340634 | K47: 8.582963 | L47: 0.847212 | M47: 2.648201 | N47: -0.803899 | O47: 3.339334 | P47: 0.047523 | Q47: 4.093534 | R47: -3.073663 | S47: 16.896221 | T47: 2.317882 | U47: 5.170845 | V47: 9.887746 | W47: -5.387985 | X47: -17.701619 | Y47: 14.636363 | Z47: 1.445159 | AA47: -8.075843 | AB47: ..
A48: Data extracted on 04 Jun 2020 21:28 UTC (GMT) from OECD.Stat

Sheet OECD Construction
A1: #NAME? | B1: <?xml version="1.0" encoding="utf-16"?><WebTableParameter xmlns:xsd="http://www.w3.org/2001/XMLSchema" xmlns:xsi="http://www.w3.org/2001/XMLSchema-instance" xmlns="http://stats.oecd.org/OECDStatWS/2004/03/01/"><DataTable Code="PDBI_I4" HasMetadata="true"><Name LocaleIsoCode="en">Productivity and ULC by main economic activity (ISIC Rev.4)</Name><Name LocaleIsoCode="fr">Productivité et CUM par principale activité économique (CITI Rev.4)</Name><Dimension Code="LOCATION" HasMetadata="false" CommonCode="LOCATION" Display="labels"><Name LocaleIsoCode="en">Country</Name><Name LocaleIsoCode="fr">Pays</Name><Member Code="AUS" HasMetadata="false" HasOnlyUnitMetadata="false" HasChild="0"><Name LocaleIsoCode="en">Australia</Name><Name LocaleIsoCode="fr">Australie</Name></Member><Member Code="AUT" HasMetadata="false" HasOnlyUnitMetadata="false" HasChild="0"><Name LocaleIsoCode="en">Austria</Name><Name LocaleIsoCode="fr">Autriche</Name></Member><Member Code="BEL" HasMetadata="false" HasOnlyUnitMetadata="false" HasChild="0"><Name LocaleIsoCode="en">Belgium</Name><Name LocaleIsoCode="fr">Belgique</Name></Member><Member Code="CAN" HasMetadata="false" HasOnlyUnitMetadata="false" HasChild="0"><Name LocaleIsoCode="en">Canada</Name><Name LocaleIsoCode="fr">Canada</Name></Member><Member Code="CHL" HasMetadata="false" HasOnlyUnitMetadata="false" HasChild="0"><Name LocaleIsoCode="en">Chile</Name><Name LocaleIsoCode="fr">Chili</Name></Member><Member Code="COL" HasMetadata="false" HasOnlyUnitMetadata="false" HasChild="0"><Name LocaleIsoCode="en">Colombia</Name><Name LocaleIsoCode="fr">Colombie</Name></Member><Member Code="CZE" HasMetadata="false" HasOnlyUnitMetadata="false" HasChild="0"><Name LocaleIsoCode="en">Czech Republic</Name><Name LocaleIsoCode="fr">République tchèque</Name></Member><Member Code="DNK" HasMetadata="false" HasOnlyUnitMetadata="false" HasChild="0"><Name LocaleIsoCode="en">Denmark</Name><Name LocaleIsoCode="fr">Danemark</Name></Member><Member Code="EST" HasMetadata="false" HasOnlyUnitMetadata="false" HasChild="0"><Name LocaleIsoCode="en">Estonia</Name><Name LocaleIsoCode="fr">Estonie</Name></Member><Member Code="FIN" HasMetadata="false" HasOnlyUnitMetadata="false" HasChild="0"><Name LocaleIsoCode="en">Finland</Name><Name LocaleIsoCode="fr">Finlande</Name></Member><Member Code="FRA" HasMetadata="false" HasOnlyUnitMetadata="false" HasChild="0"><Name LocaleIsoCode="en">France</Name><Name LocaleIsoCode="fr">France</Name></Member><Member Code="DEU" HasMetadata="true" HasOnlyUnitMetadata="false" HasChild="0"><Name LocaleIsoCode="en">Germany</Name><Name LocaleIsoCode="fr">Allemagne</Name></Member><Member Code="GRC" HasMetadata="false" HasOnlyUnitMetadata="false" HasChild="0"><Name LocaleIsoCode="en">Greece</Name><Name LocaleIsoCode="fr">Grèce</Name></Member><Member Code="HUN" HasMetadata="false" HasOnlyUnitMetadata="false" HasChild="0"><Name LocaleIsoCode="en">Hungary</Name><Name LocaleIsoCode="fr">Hongrie</Name></Member><Member Code="ISL" HasMetadata="false" HasOnlyUnitMetadata="false" HasChild="0"><Name LocaleIsoCode="en">Iceland</Name><Name LocaleIsoCode="fr">Islande</Name></Member><Member Code="IRL" HasMetadata="true" HasOnlyUnitMetadata="false" HasChild="0"><Name LocaleIsoCode="en">Ireland</Name><Name LocaleIsoCode="fr">Irlande</Name></Member><Member Code="ISR" HasMetadata="true" HasOnlyUnitMetadata="false" HasChild="0"><Name LocaleIsoCode="en">Israel</Name><Name LocaleIsoCode="fr">Israël</Name></Member><Member Code="ITA" HasMetadata="false" HasOnlyUnitMetadata="false" HasChild="0"><Name LocaleIsoCode="en">Italy</Name><Name LocaleIsoCode="fr">Italie</Name></Member><Member Code="JPN" HasMetadata="false" HasOnlyUnitMetadata="false" HasChild="0"><Name LocaleIsoCode="en">Japan</Name><Name LocaleIsoCode="fr">Japon</Name></Member><Member Code="KOR" HasMetadata="false" HasOnlyUnitMetadata="false" HasChild="0"><Name LocaleIsoCode="en">Korea</Name><Name LocaleIsoCode="fr">Corée</Name></Member><Member Code="LVA" HasMetadata="false" HasOnlyUnitMetadata="false" HasChild="0"><Name LocaleIsoCode="en">Latvia</Name><Name LocaleIsoCode="fr">Lettonie</Name></Member><Member Code="LTU" HasMetadata="false" HasOnlyUnitMetadata="false" HasChild="0"><Name LocaleIsoCode="en">Lithuania</Name><Name LocaleIsoCode="fr">Lituanie</Name></Member><Member Code="LUX" HasMetadata="false" HasOnlyUnitMetadata="false" HasChild="0"><Name LocaleIsoCode="en">Luxembourg</Name><Name LocaleIsoCode="fr">Luxembourg</Name></Member><Member Code="MEX" HasMetadata="false" HasOnlyUnitMetadata="false" HasChild="0"><Name LocaleIsoCode="en">Mexico</Name><Name LocaleIsoCode="fr">Mexique</Name></Member><Member Code="NLD" HasMetadata="false" HasOnlyUnitMetadata="false" HasChild="0"><Name LocaleIsoCode="en">Netherlands</Name><Name LocaleIsoCode="fr">Pays-Bas</Name></Member><Member Code="NZL" HasMetadata="false" HasOnlyUnitMetadata="false" HasChild="0"><Name LocaleIsoCode="en">New Zealand</Name><Name LocaleIsoCode="fr">Nouvelle-Zélande</Name></Member><Member Code="NOR" HasMetadata="false" HasOnlyUnitMetadata="false" HasChild="0"><Name LocaleIsoCode="en">Norway</Name><Name LocaleIsoCode="fr">Norvège</Name></Member><Member Code="POL" HasMetadata="false" HasOnlyUnitMetadata="false" HasChild="0"><Name LocaleIsoCode="en">Poland</Name><Name LocaleIsoCode="fr">Pologne</Name></Member><Member Code="PRT" HasMetadata="false" HasOnlyUnitMetadata="false" HasChild="0"><Name LocaleIsoCode="en">Portugal</Name><Name LocaleIsoCode="fr">Portugal</Name></Member><Member Code="SVK" HasMetadata="false" HasOnlyUnitMetadata="false" HasChild="0"><Name LocaleIsoCode="en">Slovak Republic</Name><Name LocaleIsoCode="fr">République slovaque</Name></Member><Member Code="SVN" HasMetadata="false" HasOnlyUnitMetadata="false" HasChild="0"><Name LocaleIsoCode="en">Slovenia</Name><Name LocaleIsoCode="fr">Slovénie</Name></Member><Member Code="ESP" HasMetadata="false" HasOnlyUnitMetadata="false" HasChild="0"><Name LocaleIsoCode="en">Spain</Name><Name LocaleIsoCode="fr">Espagne</Name></Member><Member Code="SWE" HasMetadata="false" HasOnlyUnitMetadata="false" HasChild="0"><Name LocaleIsoCode="en">Sweden</Name><Name LocaleIsoCode="fr">Suède</Name></Member><Member Code="CHE" HasMetadata="false" HasOnlyUnitMetadata="false" HasChild="0"><Name LocaleIsoCode="en">Switzerland</Name><Name LocaleIsoCode="fr">Suisse</Name></Member><Member Code="GBR" HasMetadata="false" HasOnlyUnitMetadata="false" HasChild="0"><Name LocaleIsoCode="en">United Kingdom</Name><Name LocaleIsoCode="fr">Royaume-Uni</Name></Member><Member Code="USA" HasMetadata="false" HasOnlyUnitMetadata="false" HasChild="0"><Name LocaleIsoCode="en">United States</Name><Name LocaleIsoCode="fr">États-Unis</Name></Member><Member Code="EA19" HasMetadata="false" HasOnlyUnitMetadata="false" HasChild="0"><Name LocaleIsoCode="en">Euro area (19 countries)</Name><Name LocaleIsoCode="fr">Zone euro (19 pays)</Name></Member><Member Code="EU28" HasMetadata="false" HasOnlyUnitMetadata="false" HasChild="0"><Name LocaleIsoCode="en">European Union (28 countries)</Name><Name LocaleIsoCode="fr">Union européenne (28 pays)</Name></Member><Member Code="NMEC" HasMetadata="false" HasOnlyUnitMetadata="false" HasChild="1"><Name LocaleIsoCode="en">Non-OECD Economies</Name><Name LocaleIsoCode="fr">Économies non-OCDE</Name><ChildMember Code="BRA" HasMetadata="false" HasOnlyUnitMetadata="false" HasChild="0"><Name LocaleIsoCode="en">Brazil</Name><Name LocaleIsoCode="fr">Brésil</Name></ChildMember><ChildMember Code="CRI" HasMetadata="false" HasOnlyUnitMetadata="false" HasChild="0"><Name LocaleIsoCode="en">Costa Rica</Name><Name LocaleIsoCode="fr">Costa Rica</Name></ChildMember><ChildMember Code="RUS" HasMetadata="false" HasOnlyUnitMetadata="false" HasChild="0"><Name LocaleIsoCode="en">Russia</Name><Name LocaleIsoCode="fr">Russie</Name></ChildMember><ChildMember Code="ZAF" HasMetadata="false" HasOnlyUnitMetadata="false" HasChild="0"><Name LocaleIsoCode="en">South Africa</Name><Name LocaleIsoCode="fr">Afrique du Sud</Name></ChildMember></Member></Dimension><Dimension Code="SUBJECT" HasMetadata="false" Display="labels"><Name LocaleIsoCode="en">Subject</Name><Name LocaleIsoCode="fr">Sujet</Name><Member Code="I4_ANA_GVAHRS" HasMetadata="false" HasOnlyUnitMetadata="false" HasChild="0"><Name LocaleIsoCode="en">Gross value added per hour worked, constant prices</Name><Name LocaleIsoCode="fr">Valeur ajoutée brute par heure travaillée, prix constants</Name></Member><Member Code="I4_ANA_GVAEMP" HasMetadata="false" HasOnlyUnitMetadata="false" HasChild="0" IsDisplayed="true"><Name LocaleIsoCode="en">Gross value added per person employed, constant prices</Name><Name LocaleIsoCode="fr">Valeur ajoutée brute par actif occupé, prix constants</Name></Member><Member Code="I4_ANA_GVA" HasMetadata="false" HasOnlyUnitMetadata="false" HasChild="0"><Name LocaleIsoCode="en">Gross value added, constant prices</Name><Name LocaleIsoCode="fr">Valeur ajoutée brute, prix constants</Name></Member><Member Code="I4_ANA_EMPTO" HasMetadata="false" HasOnlyUnitMetadata="false" HasChild="0"><Name LocaleIsoCode="en">Total employment (number of persons employed)</Name><Name LocaleIsoCode="fr">Emploi total (nombre d'actifs occupés)</Name></Member><Member Code="I4_ANA_HRSTO" HasMetadata="true" HasOnlyUnitMetadata="false" HasChild="0"><Name LocaleIsoCode="en">Total hours worked</Name><Name LocaleIsoCode="fr">Heures travaillées totales</Name></Member><Member Code="I4_ANA_HRSAV" HasMetadata="true" HasOnlyUnitMetadata="false" HasChild="0"><Name LocaleIsoCode="en">Average hours worked per person employed</Name><Name LocaleIsoCode="fr">Heures travaillées moyennes par actif occupé</Name></Member><Member Code="I4_ANA_CONILPHRS" HasMetadata="false" HasOnlyUnitMetadata="false" HasChild="0"><Name LocaleIsoCode="en">Industry contribution to business sector labour productivity</Name><Name LocaleIsoCode="fr">Contribution par industrie à la productivité du travail du secteur marchand</Name></Member><Member Code="I4_ANA_CONILPEMP" HasMetadata="false" HasOnlyUnitMetadata="false" HasChild="0"><Name LocaleIsoCode="en">Industry contribution to business sector labour productivity; employment based</Name><Name LocaleIsoCode="fr">Contribution par industrie à la productivité du travail du secteur marchand (basée sur l'emploi)</Name></Member><Member Code="I4_ANA_ULCH" HasMetadata="true" HasOnlyUnitMetadata="false" HasChild="0"><Name LocaleIsoCode="en">Unit Labour Costs</Name><Name LocaleIsoCode="fr">Coûts unitaires de la main d'œuvre</Name></Member><Member Code="I4_ANA_LCHRS" HasMetadata="true" HasOnlyUnitMetadata="false" HasChild="0"><Name LocaleIsoCode="en">Labour compensation per hour worked</Name><Name LocaleIsoCode="fr">Rémunération de la main d'oeuvre par heure travaillée</Name></Member><Member Code="I4_ANA_ULCE" HasMetadata="true" HasOnlyUnitMetadata="false" HasChild="0"><Name LocaleIsoCode="en">Unit Labour Costs, employment based</Name><Name LocaleIsoCode="fr">Coûts unitaires de la main d'œuvre, basés sur l'emploi </Name></Member><Member Code="I4_ANA_LCEMP" HasMetadata="false" HasOnlyUnitMetadata="false" HasChild="0"><Name LocaleIsoCode="en">Labour compensation per employee</Name><Name LocaleIsoCode="fr">Rémunération de la main d'oeuvre par salarié </Name></Member></Dimension><Dimension Code="MEASURE" HasMetadata="false" Display="labels"><Name LocaleIsoCode="en">Measure</Name><Name LocaleIsoCode="fr">Mesure</Name><Member Code="GRW" HasMetadata="true" HasOnlyUnitMetadata="false" HasChild="0"><Name LocaleIsoCode="en">Annual growth/change</Name><Name LocaleIsoCode="fr">Croissance/variation annuelle</Name></Member></Dimension><Dimension Code="ACTIVITY" HasMetadata="false" Display="codesandlabels"><Name LocaleIsoCode="en">Activity</Name><Name LocaleIsoCode="fr">Activité</Name><Member Code="A_U" HasMetadata="false" HasOnlyUnitMetadata="false" HasChild="1"><Name LocaleIsoCode="en">Total </Name><Name LocaleIsoCode="fr">Total</Name><ChildMember Code="BNEXCL" HasMetadata="false" HasOnlyUnitMetadata="false" HasChild="1"><Name LocaleIsoCode="en">Non-agriculture business sector excluding real estate</Name><Name LocaleIsoCode="fr">Secteur marchand non-agricole, hors activités immobilières</Name><ChildMember Code="B_E" HasMetadata="false" HasOnlyUnitMetadata="false" HasChild="1"><Name LocaleIsoCode="en">Industry including energy</Name><Name LocaleIsoCode="fr">Industrie, y compris l’énergie</Name><ChildMember Code="BDE" HasMetadata="false" HasOnlyUnitMetadata="false" HasChild="0"><Name LocaleIsoCode="en">Mining and utilities</Name><Name LocaleIsoCode="fr">Industries extractives , électricité et gaz , eau et déchets</Name></ChildMember><ChildMember Code="C" HasMetadata="false" HasOnlyUnitMetadata="false" HasChild="0"><Name LocaleIsoCode="en">Manufacturing</Name><Name LocaleIsoCode="fr">Activités de fabrication</Name></ChildMember></ChildMember><ChildMember Code="F" HasMetadata="false" HasOnlyUnitMetadata="false" HasChild="0" IsDisplayed="true"><Name LocaleIsoCode="en">Construction</Name><Name LocaleIsoCode="fr">Construction</Name></ChildMember><ChildMember Code="GNEXCL" HasMetadata="false" HasOnlyUnitMetadata="false" HasChild="1"><Name LocaleIsoCode="en">Business sector services excluding real estate</Name><Name LocaleIsoCode="fr">Services marchands, hors activités immobilières</Name><ChildMember Code="G_I" HasMetadata="false" HasOnlyUnitMetadata="false" HasChild="0"><Name LocaleIsoCode="en">Wholesale retail trade accommodation food services, transportation and storage</Name><Name LocaleIsoCode="fr">Commerce de gros et de détail, réparations , transport et entreposage , hébergement et restauration</Name></ChildMember><ChildMember Code="J" HasMetadata="false" HasOnlyUnitMetadata="false" HasChild="0"><Name LocaleIsoCode="en">Information and communication</Name><Name LocaleIsoCode="fr">Information et communication</Name></ChildMember><ChildMember Code="K" HasMetadata="false" HasOnlyUnitMetadata="false" HasChild="0"><Name LocaleIsoCode="en">Financial and insurance activities</Name><Name LocaleIsoCode="fr">Activités financières et d'assurances</Name></ChildMember><ChildMember Code="MN" HasMetadata="false" HasOnlyUnitMetadata="false" HasChild="0"><Name LocaleIsoCode="en">Professional, scientific and technical activities, Administrative and support service activities</Name><Name LocaleIsoCode="fr">Activités professionnelles, scientifiques et techniques , activités de services administratifs et d’appui</Name></ChildMember></ChildMember></ChildMember></Member></Dimension><Dimension Code="TIME" HasMetadata="false" CommonCode="TIME" Display="labels"><Name LocaleIsoCode="en">Time</Name><Name LocaleIsoCode="fr">Temps</Name><Member Code="1995" HasMetadata="false"><Name LocaleIsoCode="en">1995</Name><Name LocaleIsoCode="fr">1995</Name></Member><Member Code="1996" HasMetadata="false"><Name LocaleIsoCode="en">1996</Name><Name LocaleIsoCode="fr">1996</Name></Member><Member Code="1997" HasMetadata="false"><Name LocaleIsoCode="en">1997</Name><Name LocaleIsoCode="fr">1997</Name></Member><Member Code="1998" HasMetadata="false"><Name LocaleIsoCode="en">1998</Name><Name LocaleIsoCode="fr">1998</Name></Member><Member Code="1999" HasMetadata="false"><Name LocaleIsoCode="en">1999</Name><Name LocaleIsoCode="fr">1999</Name></Member><Member Code="2000" HasMetadata="false"><Name LocaleIsoCode="en">2000</Name><Name LocaleIsoCode="fr">2000</Name></Member><Member Code="2001" HasMetadata="false"><Name LocaleIsoCode="en">2001</Name><Name LocaleIsoCode="fr">2001</Name></Member><Member Code="2002" HasMetadata="false"><Name LocaleIsoCode="en">2002</Name><Name LocaleIsoCode="fr">2002</Name></Member><Member Code="2003" HasMetadata="false"><Name LocaleIsoCode="en">2003</Name><Name LocaleIsoCode="fr">2003</Name></Member><Member Code="2004" HasMetadata="false"><Name LocaleIsoCode="en">2004</Name><Name LocaleIsoCode="fr">2004</Name></Member><Member Code="2005" HasMetadata="false"><Name LocaleIsoCode="en">2005</Name><Name LocaleIsoCode="fr">2005</Name></Member><Member Code="2006" HasMetadata="false"><Name LocaleIsoCode="en">2006</Name><Name LocaleIsoCode="fr">2006</Name></Member><Member Code="2007" HasMetadata="false"><Name LocaleIsoCode="en">2007</Name><Name LocaleIsoCode="fr">2007</Name></Member><Member Code="2008" HasMetadata="false"><Name LocaleIsoCode="en">2008</Name><Name LocaleIsoCode="fr">2008</Name></Member><Member Code="2009" HasMetadata="false"><Name LocaleIsoCode="en">2009</Name><Name LocaleIsoCode="fr">2009</Name></Member><Member Code="2010" HasMetadata="false"><Name LocaleIsoCode="en">2010</Name><Name LocaleIsoCode="fr">2010</Name></Member><Member Code="2011" HasMetadata="false"><Name LocaleIsoCode="en">2011</Name><Name LocaleIsoCode="fr">2011</Name></Member><Member Code="2012" HasMetadata="false"><Name LocaleIsoCode="en">2012</Name><Name LocaleIsoCode="fr">2012</Name></Member><Member Code="2013" HasMetadata="false"><Name LocaleIsoCode="en">2013</Name><Name LocaleIsoCode="fr">2013</Name></Member><Member Code="2014" HasMetadata="false"><Name LocaleIsoCode="en">2014</Name><Name LocaleIsoCode="fr">2014</Name></Member><Member Code="2015" HasMetadata="false"><Name LocaleIsoCode="en">2015</Name><Name LocaleIsoCode="fr">2015</Name></Member><Member Code="2016" HasMetadata="false"><Name LocaleIsoCode="en">2016</Name><Name LocaleIsoCode="fr">2016</Name></Member><Member Code="2017" HasMetadata="false"><Name LocaleIsoCode="en">2017</Name><Name LocaleIsoCode="fr">2017</Name></Member><Member Code="2018" HasMetadata="false"><Name LocaleIsoCode="en">2018</Name><Name LocaleIsoCode="fr">2018</Name></Member><Member Code="2019" HasMetadata="false"><Name LocaleIsoCode="en">2019</Name><Name LocaleIsoCode="fr">2019</Name></Member></Dimension><WBOSInformations><TimeDimension WebTreeWasUsed="false"><StartCodes Annual="1995" /></TimeDimension></WBOSInformations><Tabulation Axis="horizontal"><Dimension Code="TIME" CommonCode="TIME" /><Dimension Code="MEASURE" /></Tabulation><Tabulation Axis="vertical"><Dimension Code="LOCATION" CommonCode="LOCATION" /></Tabulation><Tabulation Axis="page"><Dimension Code="SUBJECT" /><Dimension Code="ACTIVITY" /></Tabulation><Formatting><Labels LocaleIsoCode="en" /><Power>0</Power><Decimals>1</Decimals><SkipEmptyLines>true</SkipEmptyLines><SkipEmptyCols>true</SkipEmptyCols><SkipLineHierarchy>false</SkipLineHierarchy><SkipColHierarchy>false</SkipColHierarchy><Page>1</Page></Formatting></DataTable><Format><ShowEmptyAxes>true</ShowEmptyAxes><Page>1</Page><EnableSort>true</EnableSort><IncludeFlagColumn>false</IncludeFlagColumn><IncludeTimeSeriesId>false</IncludeTimeSeriesId><DoBarChart>false</DoBarChart><FreezePanes>true</FreezePanes><MaxBarChartLen>65</MaxBarChartLen></Format><Query><AbsoluteUri>http://stats.oecd.org//View.aspx?QueryId=&amp;QueryType=Public&amp;Lang=en</AbsoluteUri></Query></WebTableParameter>
A2: Dataset: Productivity and ULC by main economic activity (ISIC Rev.4)
A3: Subject | D3: Gross value added per person employed, constant prices
A4: Activity | D4: F: Construction
A5: Time | D5: 1995 | E5: 1996 | F5: 1997 | G5: 1998 | H5: 1999 | I5: 2000 | J5: 2001 | K5: 2002 | L5: 2003 | M5: 2004 | N5: 2005 | O5: 2006 | P5: 2007 | Q5: 2008 | R5: 2009 | S5: 2010 | T5: 2011 | U5: 2012 | V5: 2013 | W5: 2014 | X5: 2015 | Y5: 2016 | Z5: 2017 | AA5: 2018 | AB5: 2019
A6: Measure | D6: Annual growth/change
A7: Unit | D7: Percentage
A8: Country
A9: Australia | D9: 2.974009 | E9: 6.498595 | F9: 3.196412 | G9: 5.389301 | H9: -2.042104 | I9: -9.148021 | J9: 4.458558 | K9: 14.101563 | L9: -2.255771 | M9: -1.274738 | N9: 2.4044 | O9: -0.05105 | P9: 2.106906 | Q9: 2.910813 | R9: -0.837631 | S9: 0.099023 | T9: 16.668638 | U9: 2.947607 | V9: 0.724632 | W9: -3.64791 | X9: -6.149064 | Y9: -6.841658 | Z9: 0.601141 | AA9: .. | AB9: ..
A10: Austria | D10: -0.606296 | E10: 2.149555 | F10: -2.175402 | G10: 3.988638 | H10: 1.182618 | I10: 1.283334 | J10: 0.708777 | K10: 2.993425 | L10: 6.461489 | M10: 1.452768 | N10: 0.566588 | O10: -2.332121 | P10: -0.046696 | Q10: -4.106258 | R10: -9.047185 | S10: -4.043741 | T10: -2.489348 | U10: -1.582719 | V10: -0.043159 | W10: -3.529531 | X10: -2.199637 | Y10: -0.822163 | Z10: 1.798922 | AA10: 1.317015 | AB10: -1.236554
A11: Belgium | D11: .. | E11: -0.901014 | F11: 4.461712 | G11: -1.931134 | H11: 3.35565 | I11: 4.62691 | J11: -0.62767 | K11: 0.50614 | L11: 3.260896 | M11: 7.343765 | N11: 3.105407 | O11: 5.259401 | P11: -2.143441 | Q11: -1.502677 | R11: -2.032154 | S11: -0.429394 | T11: 3.917224 | U11: 0.388188 | V11: -0.148739 | W11: 3.784164 | X11: 4.210787 | Y11: 0.710677 | Z11: 0.396745 | AA11: 2.559774 | AB11: 2.221692
A12: Canada | D12: .. | E12: .. | F12: .. | G12: .. | H12: .. | I12: .. | J12: .. | K12: .. | L12: .. | M12: .. | N12: .. | O12: .. | P12: .. | Q12: -5.039763 | R12: -1.053532 | S12: 0.996057 | T12: 0.688422 | U12: -0.059517 | V12: -4.48877 | W12: 0.485167 | X12: -0.928378 | Y12: -3.726894 | Z12: 3.003809 | AA12: -2.146471 | AB12: ..
A13: Chile | D13: .. | E13: .. | F13: .. | G13: .. | H13: .. | I13: .. | J13: .. | K13: .. | L13: .. | M13: .. | N13: .. | O13: .. | P13: .. | Q13: .. | R13: .. | S13: .. | T13: -0.910844 | U13: 3.592036 | V13: -1.843218 | W13: -0.948158 | X13: 0.640422 | Y13: 0.823989 | Z13: -1.181616 | AA13: 1.189512 | AB13: ..
A14: Czech Republic | D14: 3.500974 | E14: 5.076341 | F14: -8.426118 | G14: -2.945298 | H14: -9.284242 | I14: -2.004594 | J14: 0.993682 | K14: -0.757609 | L14: 2.504973 | M14: 7.223912 | N14: 0.143778 | O14: -0.591091 | P14: 5.565523 | Q14: -2.364932 | R14: -7.560854 | S14: 2.276985 | T14: -1.598003 | U14: -1.867084 | V14: 3.72891 | W14: 6.836729 | X14: 4.402568 | Y14: -2.038901 | Z14: -2.664827 | AA14: 3.248524 | AB14: 2.048237
A15: Denmark | D15: 4.292799 | E15: 4.203138 | F15: -7.141867 | G15: 5.553316 | H15: 4.609195 | I15: -0.885083 | J15: -7.7034 | K15: 2.393187 | L15: 5.021941 | M15: 1.57068 | N15: -5.408267 | O15: 1.112767 | P15: -6.574002 | Q15: 3.163487 | R15: 1.446747 | S15: -3.992226 | T15: 3.678157 | U15: 3.630219 | V15: 3.622066 | W15: 0.810878 | X15: 7.5488 | Y15: 5.158203 | Z15: -2.169261 | AA15: 5.614128 | AB15: -1.843931
A16: Estonia | D16: .. | E16: 5.236933 | F16: -12.054018 | G16: 24.847241 | H16: -5.010311 | I16: 27.02752 | J16: 2.274756 | K16: 11.57558 | L16: -1.541214 | M16: 1.973374 | N16: 18.705735 | O16: -13.638989 | P16: -11.974587 | Q16: 8.661575 | R16: -5.130793 | S16: 28.989426 | T16: 3.445357 | U16: 5.747797 | V16: -4.298275 | W16: -7.631162 | X16: -7.173774 | Y16: 28.585767 | Z16: 8.234496 | AA16: 12.166594 | AB16: -4.366085
A17: Finland | D17: -10.949181 | E17: 7.015556 | F17: -2.049494 | G17: 0.933135 | H17: -7.347887 | I17: -3.188159 | J17: -6.806376 | K17: -0.064149 | L17: 4.798939 | M17: 2.995416 | N17: -0.441562 | O17: -1.147395 | P17: -2.063322 | Q17: -5.926026 | R17: -1.55106 | S17: 10.351763 | T17: -0.737176 | U17: -4.463133 | V17: -0.606794 | W17: -2.022299 | X17: 1.155245 | Y17: 0.836188 | Z17: -2.531749 | AA17: -2.203158 | AB17: 0.032391
A18: France | D18: 1.444311 | E18: -1.839324 | F18: -0.805768 | G18: 0.696442 | H18: 2.135759 | I18: 2.143887 | J18: 1.067543 | K18: -2.685644 | L18: -0.849299 | M18: 0.191749 | N18: -1.330659 | O18: -1.928303 | P18: -0.121508 | Q18: -4.319446 | R18: -5.793237 | S18: -0.906521 | T18: -1.889118 | U18: -4.769427 | V18: 0.962429 | W18: -1.959605 | X18: 1.971969 | Y18: 1.382748 | Z18: 3.147101 | AA18: -1.193818 | AB18: 1.112011
A19: Germany | D19: -5.174975 | E19: -2.327933 | F19: 1.49274 | G19: -0.016818 | H19: 0.792394 | I19: 0.479009 | J19: 0.539228 | K19: 1.255212 | L19: 0.074373 | M19: 0.310273 | N19: -0.777486 | O19: 0.133963 | P19: -2.44409 | Q19: -0.101997 | R19: -3.680519 | S19: 6.773197 | T19: 1.582728 | U19: -2.585945 | V19: -3.0426 | W19: 3.477531 | X19: -0.258007 | Y19: 0.929911 | Z19: -1.691852 | AA19: 1.91286 | AB19: 2.34814
A20: Greece | D20: .. | E20: 3.876495 | F20: 7.941791 | G20: 0.185117 | H20: 10.210143 | I20: -0.051471 | J20: 4.338455 | K20: -4.124772 | L20: 22.6137 | M20: 9.915065 | N20: -28.161049 | O20: 50.890081 | P20: -21.153179 | Q20: -26.381243 | R20: 5.841738 | S20: 6.722643 | T20: -4.366654 | U20: 9.900768 | V20: -16.798864 | W20: -14.133265 | X20: -0.244013 | Y20: 22.805495 | Z20: -1.104515 | AA20: 6.824231 | AB20: 14.606758
A21: Hungary | D21: .. | E21: -7.900669 | F21: 4.996726 | G21: 6.784171 | H21: -2.214428 | I21: 10.239893 | J21: 6.704477 | K21: 12.15522 | L21: -12.741247 | M21: -1.980948 | N21: 10.405774 | O21: -5.166098 | P21: -10.487229 | Q21: -8.970912 | R21: 6.031045 | S21: -3.009048 | T21: 3.857949 | U21: -6.667666 | V21: 9.78501 | W21: 4.999391 | X21: 7.853915 | Y21: -20.572313 | Z21: 11.614066 | AA21: 7.950713 | AB21: 10.282043
A22: Iceland | D22: .. | E22: .. | F22: .. | G22: .. | H22: .. | I22: .. | J22: .. | K22: .. | L22: .. | M22: .. | N22: .. | O22: .. | P22: .. | Q22: .. | R22: -7.302574 | S22: 3.242438 | T22: 3.672265 | U22: 1.370329 | V22: 2.234996 | W22: 4.402672 | X22: 3.672189 | Y22: 12.471402 | Z22: -4.865017 | AA22: -1.681843 | AB22: -0.774155
A23: Ireland | D23: .. | E23: 12.298314 | F23: 4.395533 | G23: -3.950723 | H23: -1.582726 | I23: -7.891351 | J23: -3.424946 | K23: 0.495922 | L23: 2.983341 | M23: -1.56215 | N23: -3.888129 | O23: -6.175526 | P23: -2.934259 | Q23: 6.351276 | R23: 10.039562 | S23: 10.146447 | T23: -3.093115 | U23: 3.942223 | V23: 6.442329 | W23: -1.99586 | X23: -8.26698 | Y23: 1.295926 | Z23: 4.531384 | AA23: -0.362916 | AB23: 3.067865
A24: Israel | D24: .. | E24: 2.180811 | F24: -2.007166 | G24: -5.672231 | H24: -2.322196 | I24: 1.053368 | J24: 1.456462 | K24: 4.010852 | L24: -2.925088 | M24: 2.518864 | N24: -0.367403 | O24: 5.166219 | P24: -5.397523 | Q24: 0.384478 | R24: 6.457538 | S24: 0.988269 | T24: 11.222332 | U24: 3.115157 | V24: -1.800214 | W24: -1.485885 | X24: -3.056862 | Y24: 3.594021 | Z24: 1.031545 | AA24: 3.447858 | AB24: ..
A25: Italy | D25: 2.954769 | E25: 2.190822 | F25: -3.631484 | G25: 0.302372 | H25: -1.330632 | I25: 1.578846 | J25: -2.031478 | K25: 0.582991 | L25: -0.418613 | M25: -0.812701 | N25: -3.066474 | O25: 0.454401 | P25: -3.248615 | Q25: -3.070745 | R25: -7.954666 | S25: -4.088651 | T25: -1.338094 | U25: -4.871597 | V25: 0.625262 | W25: -3.871214 | X25: -1.28953 | Y25: 0.71159 | Z25: 1.774982 | AA25: 2.110511 | AB25: 1.021649
A26: Japan | D26: -2.943534 | E26: 3.123626 | F26: -7.511581 | G26: 2.531607 | H26: 0.342844 | I26: -1.212138 | J26: -0.535817 | K26: -3.564041 | L26: -3.534565 | M26: -1.33575 | N26: -3.430252 | O26: 1.448706 | P26: -5.121009 | Q26: -3.721578 | R26: 3.044617 | S26: -0.805399 | T26: 1.446281 | U26: 1.73346 | V26: 10.085884 | W26: 2.629808 | X26: 1.930123 | Y26: 2.960638 | Z26: 2.976392 | AA26: -2.349416 | AB26: ..
A27: Korea | D27: .. | E27: .. | F27: .. | G27: .. | H27: .. | I27: .. | J27: .. | K27: .. | L27: .. | M27: .. | N27: 0.94167 | O27: -0.576565 | P27: 0.975564 | Q27: -1.40424 | R27: 6.844769 | S27: -5.795393 | T27: -4.994031 | U27: -1.823847 | V27: 5.342674 | W27: -1.230562 | X27: 4.789794 | Y27: 8.92014 | Z27: -0.456505 | AA27: -6.227153 | AB27: ..
A28: Latvia | D28: .. | E28: 5.434525 | F28: 5.408879 | G28: 14.983223 | H28: 12.108254 | I28: 11.806442 | J28: -13.567988 | K28: 27.540763 | L28: 1.353084 | M28: 9.042065 | N28: 11.626275 | O28: -4.970826 | P28: 5.646413 | Q28: -2.824047 | R28: -7.118337 | S28: -21.540322 | T28: 29.904292 | U28: 8.987207 | V28: -3.452136 | W28: 2.584588 | X28: -0.639967 | Y28: -7.440187 | Z28: 8.422522 | AA28: 7.530031 | AB28: 0.51915
A29: Lithuania | D29: .. | E29: 5.021092 | F29: 8.225443 | G29: 17.779761 | H29: -8.415685 | I29: -10.575375 | J29: 9.157101 | K29: 5.988975 | L29: 7.580996 | M29: 4.48943 | N29: 3.621627 | O29: 2.692458 | P29: 25.086075 | Q29: 7.705851 | R29: -25.874905 | S29: 23.502484 | T29: 22.281107 | U29: -8.723805 | V29: -1.559489 | W29: 13.245018 | X29: -5.829595 | Y29: -5.609979 | Z29: 10.94905 | AA29: 8.179021 | AB29: 0.052213
A30: Luxembourg | D30: .. | E30: -2.131969 | F30: 6.002147 | G30: 2.421864 | H30: 3.804837 | I30: -2.536752 | J30: -5.640058 | K30: 0.706287 | L30: -1.742565 | M30: 1.69849 | N30: -3.873977 | O30: 2.042886 | P30: 14.25349 | Q30: -9.095905 | R30: -2.426759 | S30: 0.652689 | T30: 4.732984 | U30: -9.72424 | V30: 0.714109 | W30: 10.595368 | X30: -1.581741 | Y30: 0.596895 | Z30: -0.584985 | AA30: 7.416838 | AB30: ..
A31: Mexico | D31: .. | E31: .. | F31: .. | G31: .. | H31: .. | I31: .. | J31: .. | K31: .. | L31: .. | M31: .. | N31: .. | O31: .. | P31: .. | Q31: .. | R31: .. | S31: .. | T31: 2.830562 | U31: 4.323102 | V31: -2.979653 | W31: .. | X31: .. | Y31: .. | Z31: .. | AA31: .. | AB31: ..
A32: Netherlands | D32: .. | E32: -3.350648 | F32: -2.522961 | G32: 2.205074 | H32: 4.500659 | I32: 0.029095 | J32: -0.208297 | K32: -1.210462 | L32: -0.019814 | M32: 0.251247 | N32: 4.047064 | O32: 2.035649 | P32: 3.417063 | Q32: 2.288286 | R32: -3.313213 | S32: -7.313153 | T32: 1.188546 | U32: -5.670986 | V32: 0.418516 | W32: 6.13661 | X32: 7.880179 | Y32: 7.909749 | Z32: 5.183226 | AA32: 4.785881 | AB32: 1.257098
A33: New Zealand | D33: .. | E33: .. | F33: .. | G33: .. | H33: .. | I33: .. | J33: .. | K33: .. | L33: .. | M33: .. | N33: .. | O33: .. | P33: .. | Q33: .. | R33: .. | S33: .. | T33: 1.09106 | U33: 8.336702 | V33: -2.120418 | W33: -5.164408 | X33: -2.992988 | Y33: 5.101874 | Z33: 0.694593 | AA33: 5.576943 | AB33: ..
A34: Norway | D34: -0.784766 | E34: -2.206145 | F34: 0.393749 | G34: -1.509883 | H34: -3.007419 | I34: 1.203981 | J34: -2.735746 | K34: -0.483949 | L34: -2.386106 | M34: 1.40019 | N34: -0.363801 | O34: -0.496844 | P34: 0.825023 | Q34: -1.246832 | R34: -3.192668 | S34: -1.001396 | T34: -1.063825 | U34: 1.317573 | V34: -0.787714 | W34: -0.490841 | X34: -0.457864 | Y34: 0.981728 | Z34: -0.859931 | AA34: -0.107024 | AB34: ..
A35: Poland | D35: .. | E35: -5.360252 | F35: -3.425826 | G35: 1.037692 | H35: 2.705756 | I35: 12.767595 | J35: -30.037108 | K35: 4.687195 | L35: 3.233956 | M35: 0.927003 | N35: -0.064305 | O35: -1.814178 | P35: -10.307713 | Q35: -11.445093 | R35: 4.254678 | S35: 10.097316 | T35: 11.125905 | U35: -1.171023 | V35: 0.528115 | W35: 9.952079 | X35: 4.36766 | Y35: -9.643236 | Z35: 6.996754 | AA35: 9.514806 | AB35: -1.094258
A36: Portugal | D36: .. | E36: -0.336951 | F36: 0.821971 | G36: -4.361223 | H36: -2.221442 | I36: -3.51066 | J36: 4.617018 | K36: -8.607229 | L36: -2.73055 | M36: 4.362408 | N36: -0.670679 | O36: -0.403415 | P36: 0.769939 | Q36: -1.523659 | R36: -2.095507 | S36: -2.390449 | T36: 3.119177 | U36: 6.359006 | V36: 4.03564 | W36: -3.703865 | X36: -1.254631 | Y36: 0.650288 | Z36: 0.68973 | AA36: 0.837034 | AB36: 5.62728
A37: Slovak Republic | D37: .. | E37: 33.776481 | F37: -0.3749 | G37: 10.399611 | H37: -17.220938 | I37: 11.106035 | J37: 1.768085 | K37: 12.351895 | L37: -9.253201 | M37: 7.072339 | N37: -2.6073 | O37: 12.88177 | P37: 5.420101 | Q37: 12.658382 | R37: -5.235158 | S37: -4.218135 | T37: 9.915744 | U37: 9.409303 | V37: -12.284716 | W37: 9.097507 | X37: 1.288647 | Y37: -2.142341 | Z37: 7.61806 | AA37: -4.420937 | AB37: -3.324804
A38: Slovenia | D38: .. | E38: 9.724919 | F38: 3.382789 | G38: 0.478047 | H38: 6.483305 | I38: -6.262903 | J38: -0.964052 | K38: 2.044906 | L38: 5.766362 | M38: 2.159815 | N38: -0.087817 | O38: 7.536062 | P38: 4.509559 | Q38: -6.529629 | R38: -12.968293 | S38: -10.001764 | T38: 2.461405 | U38: -0.290656 | V38: -2.381731 | W38: 11.015694 | X38: -3.779002 | Y38: -2.573228 | Z38: 5.912996 | AA38: 1.420905 | AB38: -3.524045
A39: Spain | D39: .. | E39: -2.233915 | F39: -5.845765 | G39: -3.132914 | H39: -4.881762 | I39: -6.188149 | J39: -0.281837 | K39: -0.698083 | L39: -1.989234 | M39: -3.844074 | N39: -3.494057 | O39: -3.47626 | P39: -4.186324 | Q39: 11.760608 | R39: 18.452133 | S39: -3.007928 | T39: 1.856124 | U39: 8.184444 | V39: 1.990374 | W39: 1.691688 | X39: -1.226258 | Y39: 2.400954 | Z39: -0.017858 | AA39: -1.694152 | AB39: -1.659033
A40: Sweden | D40: 1.513346 | E40: 5.177892 | F40: 0.620687 | G40: -0.146984 | H40: -0.714059 | I40: -0.763057 | J40: -0.681149 | K40: 1.156686 | L40: 1.406735 | M40: 4.857182 | N40: -1.346352 | O40: 4.122003 | P40: -1.454646 | Q40: -12.531257 | R40: 1.653809 | S40: -2.643668 | T40: -2.002605 | U40: -2.327441 | V40: -4.507731 | W40: 0.976867 | X40: 3.593104 | Y40: -2.121839 | Z40: -0.409759 | AA40: -0.17836 | AB40: 0.903966
A41: Switzerland | D41: .. | E41: -1.033356 | F41: -4.507043 | G41: 3.56811 | H41: 0.119989 | I41: -0.699371 | J41: -1.254025 | K41: 5.911196 | L41: 1.884842 | M41: -1.07265 | N41: 1.103714 | O41: -4.122941 | P41: -4.398443 | Q41: 0.646275 | R41: 2.332655 | S41: 4.315725 | T41: -1.842604 | U41: -0.209781 | V41: 0.700079 | W41: 0.932 | X41: -1.048895 | Y41: 0.955137 | Z41: 0.423764 | AA41: 1.466768 | AB41: ..
A42: United Kingdom | D42: 1.427535 | E42: 2.77835 | F42: 1.591321 | G42: -1.03185 | H42: 0.339949 | I42: -0.147992 | J42: -0.131773 | K42: 3.820358 | L42: 1.753357 | M42: 2.237251 | N42: -4.748677 | O42: -0.737784 | P42: -0.844388 | Q42: -2.856721 | R42: -9.764747 | S42: 14.617552 | T42: 2.71436 | U42: -6.539331 | V42: 1.711427 | W42: 6.425615 | X42: 1.402433 | Y42: 0.123038 | Z42: 2.201701 | AA42: -0.33239 | AB42: 2.839913
A43: United States | D43: .. | E43: .. | F43: .. | G43: .. | H43: .. | I43: .. | J43: -4.225882 | K43: -1.573179 | L43: 0.050535 | M43: -2.492552 | N43: -3.41007 | O43: -6.695059 | P43: -3.964294 | Q43: -2.502413 | R43: -2.885665 | S43: 1.376478 | T43: -1.199903 | U43: 3.601184 | V43: -0.908689 | W43: -4.264238 | X43: 2.910644 | Y43: -0.583458 | Z43: -2.649279 | AA43: .. | AB43: ..
