Workbook
Name dollars_2018_to_2012: #REF!
Name dollars_2020_2012: About!$A$85
Name dollars_2021_2012: #REF!
Name dollars_2022_2012: #REF!
Name lignite_multiplier: #REF!
Name nonlignite_multiplier: #REF!

Sheet About
A1: BS BAU Subsidy for Thermal Fuels per Energy Unit Produced
A2: BS BAU Subsidy per Unit Electricity Output
A3: BS BAU Subsidy per Unit Electricity Output for Exisiting Plants
A4: BS BAU Subsidy per Unit Electricity Capacity Built
A5: BS Duration of Subsidies per Unit Electricity Output
A7: Source: | B7: Tax Expenditures
B8: Joint Committee on Taxation, 113th Congress, 2nd Session
B9: 2014
B10: Estimates of Federal Tax Expenditures for Fiscal Years 2014-2018
B11: https://www.jct.gov/publications.html?func=download&id=4663&chk=4663&no_html=1
B12: Pages 22-34, Table 1
B14: Investment Tax Credit
B15: Database of State Incentives for Renewables & Efficiency (DSIRE)
B16: 2015
B17: Business Energy Investment Tax Credit
B18: http://programs.dsireusa.org/system/program/detail/658
B20: Production Tax Credit
B21: Congressional Research Service
B22: 2020
B23: The Renewable Electricity Production Tax Credit: In Brief
B24: https://fas.org/sgp/crs/misc/R43453.pdf
B26: Tax Credit for Qualifying Advanced Coal Projects
B27: Legal Information Institute, Cornell University Law School
B28: 2015
B29: 26 U.S. Code § 48A - Qualifying advanced coal project credit
B30: https://www.law.cornell.edu/uscode/text/26/48A
B32: Capital Gains Treatment for Royalties of Coal; Inclusion of Coal in Expensing of Exploration and Development Costs for Hard Mineral Fuels; Deductions for Tertiary Injections
B33: U.S. Treasury
B34: 2015
B35: Progress Report on Fossil Fuel Subsidies
B36: http://www.treasury.gov/open/Documents/USA%20FFSR%20progress%20report%20to%20G20%202014%20Final.pdf
B37: p.5
B39: Energy Production
B40: Energy Information Administration
B41: 2021, 2022, 2025, 2026
B42: Annual Energy Outlook 2021, Annual Energy Outlook 2022, Annual Energy Outlook 2025 (AEO 2025 High Zero-Carbon Technology Cost), Annual Energy Outlook 2026 (Alternative Electricity and Transportation)
B43: https://www.eia.gov/outlooks/aeo/tables_side.php
B44: Table 1, Table 8, Table 11
B46: 2020 Tax Credit Expansions
B47: Jeff St. John
B48: 2020
B49: Congress Passes Spending Bill With Solar, Wind Tax Credit Extensions and Energy R&D Package
B50: https://www.greentechmedia.com/articles/read/solar-and-wind-tax-credit-extensions-energy-rd-package-in-spending-bill-before-congress#:~:text=According%20to%20a%20summary%20shared,would%20have%20under%20existing%20law.
B52: Penalty for Monetizing Tax Credit Incentives
B53: NREL
B54: 2020
B55: Regional Energy Deployment System (ReEDS) Model Documentation: Version 2019
B56: https://www.nrel.gov/docs/fy20osti/74111.pdf
B57: Section 9.2.2; Section 9.2.1, second paragraph
A60: Notes
A61: The duration of subsidies per unit electricity output variable should specify the number of years
A62: generators will qualify for electricity production tax credits/incentives.
A64: Electricity tax credits follow the One Big Beautiful Bill Act (Public Law 119-21, sections 70512-70513), calculated on the "45Y48E Credits" tab.
A65: Wind and solar placed in service after 2027 qualify for 45Y/48E only if construction began by July 4, 2026. The CSVs give new onshore wind and solar PV
A66: the full credit for plants entering service through 2028, about two thirds in 2029 and one third in 2030 as the stock of safe-harbored projects
A67: runs out, and none from 2031; solar PV takes the investment credit through 2025 and the production credit after that, and offshore wind and solar thermal investment credits taper the same way.
A68: Geothermal and nuclear (including small modular reactors) keep the investment credit until the emissions-based phase-out (from 2036 for geothermal, 2040 for nuclear, in the CSVs).
A70: Tax expenditure data is only available for years 2014-2018.
A71: We assume 2013 to be like 2014 in terms of rate (tax expenditure per unit energy).
A73: We use the elements of the "All Fuels" subscript on the "ForCSV-ThermalFuels" tab and
A74: elements of the "Electricity Source" subscript on the "ForCSV-NonThermalElec" tab.
... A81: We adjust 2014 dollars to 2012 dollars using the following conversion factor:
A82: 0.971
A83: See "cpi.xlsx" in the InputData folder for source information.
A85: We adjust 2019 dollars to 2012 dollars using the following conversion factor:
A86: 0.89805482
A87: See "cpi.xlsx" in the InputData folder for source information.
A88: 0.88711067 | B88: dollars_2020_2012
A89: 0.78452102 | B89: dollars_2022_2012
A90: 0.75350342 | B90: 2023 to 2012

Sheet 45Y48E Credits
A1: Methodology:
A2: First, we calculate the percentage of new plants that will qualify for a) the prevailing wage and apprenticeship requirements and b) the domestic content requirements. For part a, we only calculate the share of plants that would meet the apprenticeship requirement and assume all these plants would also meet the prevailing wage requirement (varying assumptions on the share of qualifying plants across scenarios based on data for the construction industry from the ACP Labor Supply Report). For part a, we assume this requirement can be met in every year (which would represent union representation grows by roughly 20% by 2025. For part b, we calculate the domestic content share for each power plant type. For onshore and offshore wind, we assume 100% of plants qualify for the bonus credit, based on a Net Zero America analysis, which lists domestic content shares for various wind components at well over the 55% domestic content requirement. For solar, we use the cited domestic content values for cells, modules, and inverters to calculate a weighted domestic content share, given the percentage of solar capital costs by component from the JEDI model. We assume the domestic content share can increase to meet half the difference between current levels and the 55% requirement by 2026. Next, we add in the energy community bonus, assuming that 50% of capacity additions qualify. We then calculate what the total credit value would be for each technology in each year for both the ITC and the PTC. Here, we assume credits start in 2023 and run at their full value through 2032. For the PTC values, we also adjust the calculated credit by the present value over 10 years divided by the present value over the plant lifetime, because the PTC is only available for the first 10 years of a plant's lifetime. Finally, we apply a transferability multiplier of 7.5%. This value reduces the credit value available to developers to account for the fact tax credits are transferable. We limit our analysis to onshore and offshore wind, solar PV, solar thermal, geothermal, municipal solid waste, and battery storage. We do not model credits for qualifying hydro or biogas plants. For solar PV, we calculate a LCOE for both the ITC and PTC settings to determine whether that resource elects the ITC or the PTC in each year (the result is that solar PV opts for the PTC in every year of IRA tax credits).
A4: Phase-Out:
A5: The IRA tax credits will begin to phase out the later of either when electricity sector emissions fall 75% below 2022 values or after 2032.
A6: According to the EPA Greenhouse Gas Inventory, electricity sector CO2 emissions were 1554.4 MMT in 2022.
A7: Therefore, we evaluate when EPS electricity sector emissions fall below:
A8: =1554.4*0.25 -> 388.6 | B8: MMT
A9: Latest calibration year target passed: 2036
A10: https://www.nrel.gov/docs/fy25osti/92256.pdf
A12: First year after applicable year | B12: Second year following applicable year | C12: Third year following applicable year | D12: All years thereafter
A13: 1 | B13: 0.75 | C13: 0.5 | D13: 0
P14: threshold reached | Q14: first year | R14: second year | S14: third year
A15: Phaseout Timeline (without commenced construction provisions, covered below)
B16: 2019 | C16: 2020 | D16: 2021 | E16: 2022 | F16: 2023 | G16: 2024 | H16: 2025 | I16: 2026 | J16: 2027 | K16: 2028 | L16: 2029 | M16: 2030 | N16: 2031 | O16: 2032 | P16: 2033 | Q16: 2034 | R16: 2035 | S16: 2036 | T16: 2037 | U16: 2038 | V16: 2039 | W16: 2040 | X16: 2041 | Y16: 2042 | Z16: 2043 | AA16: 2044 | AB16: 2045 | AC16: 2046 | AD16: 2047 | AE16: 2048 | AF16: 2049 | AG16: 2050
A17: geothermal/nuclear/other | B17: 1 | C17: 1 | D17: 1 | E17: 1 | F17: 1 | G17: 1 | H17: 1 | I17: 1 | J17: 1 | K17: 1 | L17: 1 | M17: 1 | N17: 1 | O17: 1 | P17: =A13 -> 1 | Q17: =B13 -> 0.75 | R17: =C13 -> 0.5 | S17: =D13 -> 0 | T17: =E13 -> 0 | U17: =F13 -> 0 | V17: =G13 -> 0 | W17: =H13 -> 0 | ... AG17: =R13 -> 0
A18: wind/solar* | B18: 1 | C18: 1 | D18: 1 | E18: 1 | F18: 1 | G18: 1 | H18: 0.667 | I18: 0.333 | J18: 0 | K18: 0 | L18: 0 | M18: 0 | N18: 0 | O18: 0 | P18: 0 | Q18: 0 | R18: 0 | S18: 0 | T18: 0 | U18: 0 | V18: 0 | W18: 0 | X18: 0 | Y18: 0 | Z18: 0 | AA18: 0 | AB18: 0 | AC18: 0 | AD18: 0 | AE18: 0 | AF18: 0 | AG18: 0
A19: *the safe harbor deadline to qualify for the more relaxed safe harbor restrictions is July 4, 2026. We use reduced values here to represent lower qualifying shares of deployment
A20: in 2029 and 2030 as the stock of safe-harbored power plants is depleted and new, unsubsidized power plants take over.
A21: Calculations:
A22: Union Representation Calculations:
A23: Union membership
A24: https://cleanpower.org/wp-content/uploads/2021/06/ACP-Labor-Supply-Report.pdf
A43: Used union membership value for the construction industry to approximate. The apprenticeship provision applies to
A44: "each contractor and subcontractor who employs 4 or more individuals to perform construction, alteration,
A45: or repair work."
A46: We assume that the rate of union membership can increase by 20% by 2025 in response to the tax credit incentives.
A47: Current Value | B47: 0.127
A48: Value if Increased by 20% | B48: =B47*1.2 -> 0.1524
B50: 2022 | C50: 2023 | D50: 2024 | E50: 2025 | F50: 2026 | G50: 2027 | H50: 2028 | I50: 2029 | J50: 2030 | K50: 2031 | L50: 2032 | M50: 2033 | N50: 2034 | O50: 2035 | P50: 2036 | Q50: 2037 | R50: 2038 | S50: 2039 | T50: 2040 | U50: 2041 | V50: 2042 | W50: 2043 | X50: 2044 | Y50: 2045 | Z50: 2046 | AA50: 2047 | AB50: 2048 | AC50: 2049 | AD50: 2050
A51: Percentage of total labor hours that must be from qualified apprentices | B51: 0 | C51: 0.05 | D51: 0.1 | E51: 0.15 | F51: 0.15 | G51: 0.15 | H51: 0.15 | I51: 0.15 | J51: 0.15 | K51: 0.15 | L51: 0.15 | M51: 0.15 | N51: 0.15 | O51: 0.15 | P51: 0.15 | Q51: 0.15 | R51: 0.15 | S51: 0.15 | T51: 0.15 | U51: 0.15 | V51: 0.15 | W51: 0.15 | X51: 0.15 | Y51: 0.15 | Z51: 0.15 | AA51: 0.15 | AB51: 0.15 | AC51: 0.15 | AD51: 0.15
A52: Percent multiplier for bonus credit | B52: =B51 -> 0 | C52: 1 | D52: 1 | E52: 1 | F52: 1 | G52: 1 | H52: 1 | I52: 1 | J52: 1 | K52: 1 | L52: 1 | M52: 1 | N52: 1 | O52: 1 | P52: 1 | Q52: 1 | R52: 1 | S52: 1 | T52: 1 | U52: 1 | V52: 1 | W52: 1 | X52: 1 | Y52: 1 | Z52: 1 | AA52: 1 | AB52: 1 | AC52: 1 | AD52: 1
A54: Domestic Content Calculations
A55: Assumed that wind fully qualifies for domestic content credit, because weighted domestic content share is ~70%
A56: Source: https://netzeroamerica.princeton.edu/img/Working_Paper-High_Road_Labor_and_Renewable_Energy-PUBLIC_RELEASE-4-13-21.pdf
A58: Solar PV Capital Costs | B58: Percent | D58: Net Zero America: Domestic Content Share
A59: Construction Costs | B59: of Cost
A60: Module | B60: 0.412 | D60: 0.11
A61: Inverter | B61: 0.132 | D61: 0.37
A62: Electrical BOS | B62: 0.114 | D62: 0.15
A63: Structural BOS | B63: 0.07
A64: Install Labor and Equipment | B64: 0.088
A65: EPC Overhead | B65: 0.053
A66: Sales Tax | B66: 0.044
A67: Developer Overhead | B67: 0.018
A68: Contingency | B68: 0.026
A69: EPC/Developer Net Profit | B69: 0.044
A71: Current Weighted Domestic Content Share | B71: =SUMPRODUCT(B60:B62,D60:D62)/SUM(B60:B62) -> 0.16908815
A72: Assumed Domestic Content Share in 2028 (year in which maximum domestic content requirement of 55% begins) | B72: =AVERAGE(H80,B71) -> 0.35954407
B74: 2022 | C74: 2023 | D74: 2024 | E74: 2025 | F74: 2026 | G74: 2027 | H74: 2028
A75: Weighted Domestic Content Share | B75: =B71 -> 0.16908815 | C75: =B75 -> 0.16908815 | D75: =($H$75-$B$75)/5+C75 -> 0.20717933 | E75: =($H$75-$B$75)/5+D75 -> 0.24527052 | F75: =($H$75-$B$75)/5+E75 -> 0.2833617 | G75: =($H$75-$B$75)/5+F75 -> 0.32145289 | H75: =AVERAGE(B75,H80) -> 0.35954407
A77: Sources: JEDI, https://netzeroamerica.princeton.edu/img/Working_Paper-High_Road_Labor_and_Renewable_Energy-PUBLIC_RELEASE-4-13-21.pdf
B79: 2022 | C79: 2023 | D79: 2024 | E79: 2025 | F79: 2026 | G79: 2027 | H79: 2028 | I79: 2029 | J79: 2030 | K79: 2031 | L79: 2032 | M79: 2033 | N79: 2034 | O79: 2035 | P79: 2036 | Q79: 2037 | R79: 2038 | S79: 2039 | T79: 2040 | U79: 2041 | V79: 2042 | W79: 2043 | X79: 2044 | Y79: 2045 | Z79: 2046 | AA79: 2047 | AB79: 2048 | AC79: 2049 | AD79: 2050
A80: Required Domestic Content Share | B80: 0.4 | C80: 0.4 | D80: 0.4 | E80: 0.4 | F80: 0.45 | G80: 0.5 | H80: 0.55 | I80: 0.55 | J80: 0.55 | K80: 0.55 | L80: 0.55 | M80: 0.55 | N80: 0.55 | O80: 0.55 | P80: 0.55 | Q80: 0.55 | R80: 0.55 | S80: 0.55 | T80: 0.55 | U80: 0.55 | V80: 0.55 | W80: 0.55 | X80: 0.55 | Y80: 0.55 | Z80: 0.55 | AA80: 0.55 | AB80: 0.55 | AC80: 0.55 | AD80: 0.55
A81: Assumed Domestic Content Share This Year | B81: =B71 -> 0.16908815 | C81: =($H$81-$B$81)/COUNT($C$79:$H$79)+B81 -> 0.2008308 | D81: =($H$81-$B$81)/COUNT($C$79:$H$79)+C81 -> 0.23257345 | E81: =($H$81-$B$81)/COUNT($C$79:$H$79)+D81 -> 0.26431611 | F81: =($H$81-$B$81)/COUNT($C$79:$H$79)+E81 -> 0.29605876 | G81: =($H$81-$B$81)/COUNT($C$79:$H$79)+F81 -> 0.32780142 | H81: =B72 -> 0.35954407 | I81: =$H$81 -> 0.35954407 | J81: =$H$81 -> 0.35954407 | K81: =$H$81 -> 0.35954407 | L81: =$H$81 -> 0.35954407 | M81: =$H$81 -> 0.35954407 | N81: =$H$81 -> 0.35954407 | O81: =$H$81 -> 0.35954407 | P81: =$H$81 -> 0.35954407 | ... AD81: =$H$81 -> 0.35954407
A82: Multiplier for Solar Bonus Credit | B82: =B81/B80 -> 0.42272036 | C82: =C81/C80 -> 0.502077 | D82: =D81/D80 -> 0.58143364 | E82: =E81/E80 -> 0.66079027 | F82: =F81/F80 -> 0.65790836 | G82: =G81/G80 -> 0.65560284 | H82: =H81/H80 -> 0.6537165 | I82: =I81/I80 -> 0.6537165 | ... AD82: =AD81/AD80 -> 0.6537165
A84: Multiplier for Non-Solar Bonus Credit (assumed that domestic content requirements are only a limiting factor for solar PV) | B84: 1 | C84: 1 | D84: 1 | E84: 1 | F84: 1 | G84: 1 | H84: 1 | I84: 1 | J84: 1 | K84: 1 | L84: 1 | M84: 1 | N84: 1 | O84: 1 | P84: 1 | Q84: 1 | R84: 1 | S84: 1 | T84: 1 | U84: 1 | V84: 1 | W84: 1 | X84: 1 | Y84: 1 | Z84: 1 | AA84: 1 | AB84: 1 | AC84: 1 | AD84: 1
A86: Notes:
A87: The ITC/PTC values are extended by 3 years for wind and 2 years for solar PV to account for the commenced-construction provision (NREL's
A88: ReEDS modeling assumes a 3-year construction period for wind plants and 2-year period for solar PV plants, but the EPS deploys plants in a single annual timestep; the credits
A89: apply for any plant that begins construction in the applicable year rather than when plants come online).
A90: The PTC applies to the first 10 years of a project's lifetime. Therefore, the BAU PTC values are multiplied by 10 and divided by the average
A91: plant lifetime, which is 30 years.
A93: Computed Tax Credits
A95: Base credit | B95: 3
A96: Bonus credit | B96: 15
A97: 1992 to 2020 calendar year adjustment | B97: 1.6687 | C97: Source: https://www.govinfo.gov/content/pkg/FR-2020-05-13/pdf/2020-10273.pdf
A98: 2020 to 2012 USD | B98: 0.88711067
A99: Duration of PTC (years) | B99: 10
A101: Base Credit (2012 USD) | B101: =B95*B97*B98 -> 4.4409647
A102: Bonus Credit (2012 USD) | B102: =B96*B97*B98 -> 22.204824
A103: Domestic content bonus, bonus | B103: 0.1
A104: Discount rate | B104: 0 | C104: We don't use a discount rate, in line with other factors that are part of the cost per unit new elec output
A105: Transferability penalty | B105: 0.075 | C105: https://www.utilitydive.com/news/duke-avangrid-bank-of-america-ira-tax-credit-finance-clean-energy-wind-solar/696069/?s=09
A106: Energy community bonus | B106: 0.1
A107: Fraction of capacity qualifying for energy community bonus | B107: 0.5
A109: PTC
B110: wind | C110: solar | D110: safe harbor timeline
A111: construction period (source: NREL ATB) | B111: 3 | C111: 1 | D111: 4
B113: 2023 | C113: 2024 | D113: 2025 | E113: 2026 | F113: 2027 | G113: 2028 | H113: 2029 | I113: 2030 | J113: 2031 | K113: 2032 | L113: 2033 | M113: 2034 | N113: 2035 | O113: 2036 | P113: 2037 | Q113: 2038 | R113: 2039 | S113: 2040 | T113: 2041 | U113: 2042 | V113: 2043 | W113: 2044 | X113: 2045 | Y113: 2046 | Z113: 2047 | AA113: 2048 | AB113: 2049 | AC113: 2050
A114: PTC Phase-out Schedule, onshore wind | B114: =INDEX(18:18,MATCH(B113-$D$111,16:16,0)) -> 1 | C114: =INDEX(18:18,MATCH(C113-$D$111,16:16,0)) -> 1 | D114: =INDEX(18:18,MATCH(D113-$D$111,16:16,0)) -> 1 | E114: =INDEX(18:18,MATCH(E113-$D$111,16:16,0)) -> 1 | F114: =INDEX(18:18,MATCH(F113-$D$111,16:16,0)) -> 1 | G114: =INDEX(18:18,MATCH(G113-$D$111,16:16,0)) -> 1 | H114: =INDEX(18:18,MATCH(H113-$D$111,16:16,0)) -> 0.667 | I114: =INDEX(18:18,MATCH(I113-$D$111,16:16,0)) -> 0.333 | ... AC114: =INDEX(18:18,MATCH(AC113-$D$111,16:16,0)) -> 0
A115: PTC Phase-out Schedule, solar PV | B115: =INDEX(18:18,MATCH(B113-$D$111,16:16,0)) -> 1 | C115: =INDEX(18:18,MATCH(C113-$D$111,16:16,0)) -> 1 | D115: =INDEX(18:18,MATCH(D113-$D$111,16:16,0)) -> 1 | E115: =INDEX(18:18,MATCH(E113-$D$111,16:16,0)) -> 1 | F115: =INDEX(18:18,MATCH(F113-$D$111,16:16,0)) -> 1 | G115: =INDEX(18:18,MATCH(G113-$D$111,16:16,0)) -> 1 | H115: =INDEX(18:18,MATCH(H113-$D$111,16:16,0)) -> 0.667 | I115: =INDEX(18:18,MATCH(I113-$D$111,16:16,0)) -> 0.333 | ... AC115: =INDEX(18:18,MATCH(AC113-$D$111,16:16,0)) -> 0
B118: 2023 | C118: 2024 | D118: 2025 | E118: 2026 | F118: 2027 | G118: 2028 | H118: 2029 | I118: 2030 | J118: 2031 | K118: 2032 | L118: 2033 | M118: 2034 | N118: 2035 | O118: 2036 | P118: 2037 | Q118: 2038 | R118: 2039 | S118: 2040 | T118: 2041 | U118: 2042 | V118: 2043 | W118: 2044 | X118: 2045 | Y118: 2046 | Z118: 2047 | AA118: 2048 | AB118: 2049 | AC118: 2050
A119: Onshore Wind Credit Value 2012 $ / MWh | B119: =((($B$102*C52+$B$101*(1-C52))*(1+($B$103*C84)))+(($B$102*C52+$B$101*(1-C52))*$B$106*$B$107))*B114*(1-$B$105) -> 23.620381 | C119: =((($B$102*D52+$B$101*(1-D52))*(1+($B$103*D84)))+(($B$102*D52+$B$101*(1-D52))*$B$106*$B$107))*C114*(1-$B$105) -> 23.620381 | D119: =((($B$102*E52+$B$101*(1-E52))*(1+($B$103*E84)))+(($B$102*E52+$B$101*(1-E52))*$B$106*$B$107))*D114*(1-$B$105) -> 23.620381 | E119: =((($B$102*F52+$B$101*(1-F52))*(1+($B$103*F84)))+(($B$102*F52+$B$101*(1-F52))*$B$106*$B$107))*E114*(1-$B$105) -> 23.620381 | F119: =((($B$102*G52+$B$101*(1-G52))*(1+($B$103*G84)))+(($B$102*G52+$B$101*(1-G52))*$B$106*$B$107))*F114*(1-$B$105) -> 23.620381 | G119: =((($B$102*H52+$B$101*(1-H52))*(1+($B$103*H84)))+(($B$102*H52+$B$101*(1-H52))*$B$106*$B$107))*G114*(1-$B$105) -> 23.620381 | H119: =((($B$102*I52+$B$101*(1-I52))*(1+($B$103*I84)))+(($B$102*I52+$B$101*(1-I52))*$B$106*$B$107))*H114*(1-$B$105) -> 15.754794 | I119: =((($B$102*J52+$B$101*(1-J52))*(1+($B$103*J84)))+(($B$102*J52+$B$101*(1-J52))*$B$106*$B$107))*I114*(1-$B$105) -> 7.8655869 | ... AC119: =((($B$102*AD52+$B$101*(1-AD52))*(1+($B$103*AD84)))+(($B$102*AD52+$B$101*(1-AD52))*$B$106*$B$107))*AC114*(1-$B$105) -> 0
A121: Solar PV Credit Value (2020 $ / MWh) | B121: 0 | C121: 0 | D121: 0 | E121: =((($B$102*F52+$B$101*(1-F52))*(1+($B$103*F82)))+(($B$102*F52+$B$101*(1-F52))*$B$106*$B$107))*E115*(1-$B$105) -> 22.917743 | F121: =((($B$102*G52+$B$101*(1-G52))*(1+($B$103*G82)))+(($B$102*G52+$B$101*(1-G52))*$B$106*$B$107))*F115*(1-$B$105) -> 22.913008 | G121: =((($B$102*H52+$B$101*(1-H52))*(1+($B$103*H82)))+(($B$102*H52+$B$101*(1-H52))*$B$106*$B$107))*G115*(1-$B$105) -> 22.909133 | H121: =((($B$102*I52+$B$101*(1-I52))*(1+($B$103*I82)))+(($B$102*I52+$B$101*(1-I52))*$B$106*$B$107))*H115*(1-$B$105) -> 15.280392 | I121: =((($B$102*J52+$B$101*(1-J52))*(1+($B$103*J82)))+(($B$102*J52+$B$101*(1-J52))*$B$106*$B$107))*I115*(1-$B$105) -> 7.6287415 | J121: =((($B$102*K52+$B$101*(1-K52))*(1+($B$103*K82)))+(($B$102*K52+$B$101*(1-K52))*$B$106*$B$107))*J115*(1-$B$105) -> 0 | K121: =((($B$102*L52+$B$101*(1-L52))*(1+($B$103*L82)))+(($B$102*L52+$B$101*(1-L52))*$B$106*$B$107))*K115*(1-$B$105) -> 0 | L121: =((($B$102*M52+$B$101*(1-M52))*(1+($B$103*M82)))+(($B$102*M52+$B$101*(1-M52))*$B$106*$B$107))*L115*(1-$B$105) -> 0 | ... AC121: =((($B$102*AD52+$B$101*(1-AD52))*(1+($B$103*AD82)))+(($B$102*AD52+$B$101*(1-AD52))*$B$106*$B$107))*AC115*(1-$B$105) -> 0
A122: *see solar ITC vs. PTC determination below
A124: Nuclear Credit Value (2020 $ / MWh) | B124: =15*$B$98 -> 13.30666 | C124: =15*$B$98 -> 13.30666 | D124: =15*$B$98 -> 13.30666 | E124: =15*$B$98 -> 13.30666 | F124: =15*$B$98 -> 13.30666 | G124: =15*$B$98 -> 13.30666 | H124: =15*$B$98 -> 13.30666 | I124: =15*$B$98 -> 13.30666 | ... K124: =15*$B$98 -> 13.30666 | L124: 0 | M124: 0 | N124: 0 | O124: 0 | P124: 0 | Q124: 0 | R124: 0 | S124: 0 | T124: 0 | U124: 0 | V124: 0 | W124: 0 | X124: 0 | Y124: 0 | Z124: 0 | AA124: 0 | AB124: 0 | AC124: 0
A126: ITC
B127: solar PV | C127: solar thermal | D127: geothermal | E127: offshore wind | F127: nuclear: https://www.eia.gov/outlooks/aeo/assumptions/pdf/EMM_Assumptions.pdf | G127: safe harbor timeline
A128: construction period (source: NREL ATB) | B128: 1 | C128: 3 | D128: 2 | E128: 3 | F128: 6 | G128: 4
A130: ITC Phase-out Schedule | B130: 2023 | C130: 2024 | D130: 2025 | E130: 2026 | F130: 2027 | G130: 2028 | H130: 2029 | I130: 2030 | J130: 2031 | K130: 2032 | L130: 2033 | M130: 2034 | N130: 2035 | O130: 2036 | P130: 2037 | Q130: 2038 | R130: 2039 | S130: 2040 | T130: 2041 | U130: 2042 | V130: 2043 | W130: 2044 | X130: 2045 | Y130: 2046 | Z130: 2047 | AA130: 2048 | AB130: 2049 | AC130: 2050
A131: ITC Phase-out Scheulde, solar PV | B131: =B115 -> 1 | C131: =C115 -> 1 | D131: =D115 -> 1 | E131: =E115 -> 1 | F131: =F115 -> 1 | G131: =G115 -> 1 | H131: =H115 -> 0.667 | I131: =I115 -> 0.333 | ... AC131: =AC115 -> 0
A132: ITC Phase-out Scheulde, solar thermal | B132: =B115 -> 1 | C132: =C115 -> 1 | D132: =D115 -> 1 | E132: =E115 -> 1 | F132: =F115 -> 1 | G132: =G115 -> 1 | H132: =H115 -> 0.667 | I132: =I115 -> 0.333 | ... AC132: =AC115 -> 0
A133: ITC Phase-out Scheulde, geothermal | B133: =INDEX(17:17,MATCH(B130-$D$128,16:16,0)) -> 1 | C133: =INDEX(17:17,MATCH(C130-$D$128,16:16,0)) -> 1 | D133: =INDEX(17:17,MATCH(D130-$D$128,16:16,0)) -> 1 | E133: =INDEX(17:17,MATCH(E130-$D$128,16:16,0)) -> 1 | F133: =INDEX(17:17,MATCH(F130-$D$128,16:16,0)) -> 1 | G133: =INDEX(17:17,MATCH(G130-$D$128,16:16,0)) -> 1 | H133: =INDEX(17:17,MATCH(H130-$D$128,16:16,0)) -> 1 | I133: =INDEX(17:17,MATCH(I130-$D$128,16:16,0)) -> 1 | ... AC133: =INDEX(17:17,MATCH(AC130-$D$128,16:16,0)) -> 0
A134: ITC Phase-out Scheulde, nuclear | B134: =B133 -> 1 | C134: =C133 -> 1 | D134: =D133 -> 1 | E134: =INDEX(17:17,MATCH(E130-$F$128,16:16,0)) -> 1 | F134: =INDEX(17:17,MATCH(F130-$F$128,16:16,0)) -> 1 | G134: =INDEX(17:17,MATCH(G130-$F$128,16:16,0)) -> 1 | H134: =INDEX(17:17,MATCH(H130-$F$128,16:16,0)) -> 1 | I134: =INDEX(17:17,MATCH(I130-$F$128,16:16,0)) -> 1 | J134: =INDEX(17:17,MATCH(J130-$F$128,16:16,0)) -> 1 | K134: =INDEX(17:17,MATCH(K130-$F$128,16:16,0)) -> 1 | L134: =INDEX(17:17,MATCH(L130-$F$128,16:16,0)) -> 1 | ... AC134: =INDEX(17:17,MATCH(AC130-$F$128,16:16,0)) -> 0
A135: ITC Phase-out Scheulde, offshore wind | B135: =B114 -> 1 | C135: =C114 -> 1 | D135: =D114 -> 1 | E135: =E114 -> 1 | F135: =F114 -> 1 | G135: =G114 -> 1 | H135: =H114 -> 0.667 | I135: =I114 -> 0.333 | ... AC135: =AC114 -> 0
A136: * geothermal and nuclear - OBBBA phaseout timeline now implemented starting in 2034
A138: Base Credit | B138: 0.06
A139: Bonus Credit | B139: 0.3
A140: Domestic content bonus, bonus | B140: 0.1
A141: Transferability penalty | B141: 0.075
...

Sheet Tax Credits
A1: LEGACY REFERENCE: IRA-era NREL ATB tax credit assumptions. Nothing in this workbook reads this tab; the CSVs follow the 45Y48E Credits tab (see About).
C2: 2021 | D2: 2022 | E2: 2023 | F2: 2024 | G2: 2025 | H2: 2026 | I2: 2027 | J2: 2028 | K2: 2029 | L2: 2030 | M2: 2031 | N2: 2032 | O2: 2033 | P2: 2034 | Q2: 2035 | R2: 2036 | S2: 2037 | T2: 2038 | U2: 2039 | V2: 2040 | W2: 2041 | X2: 2042 | Y2: 2043 | Z2: 2044 | AA2: 2045 | AB2: 2046 | AC2: 2047 | AD2: 2048 | AE2: 2049 | AF2: 2050
A3: R&D ITC (%) | B3: R&D Scenario | C3: 0 | D3: 0 | E3: 0 | F3: 0 | G3: 0 | H3: 0 | I3: 0 | J3: 0 | K3: 0 | L3: 0 | M3: 0 | N3: 0 | O3: 0 | P3: 0 | Q3: 0 | R3: 0 | S3: 0 | T3: 0 | U3: 0 | V3: 0 | W3: 0 | X3: 0 | Y3: 0 | Z3: 0 | AA3: 0 | AB3: 0 | AC3: 0 | AD3: 0 | AE3: 0 | AF3: 0
A4: R&D PTC ($/MWh) | C4: 0 | D4: 0 | E4: 0 | F4: 0 | G4: 0 | H4: 0 | I4: 0 | J4: 0 | K4: 0 | L4: 0 | M4: 0 | N4: 0 | O4: 0 | P4: 0 | Q4: 0 | R4: 0 | S4: 0 | T4: 0 | U4: 0 | V4: 0 | W4: 0 | X4: 0 | Y4: 0 | Z4: 0 | AA4: 0 | AB4: 0 | AC4: 0 | AD4: 0 | AE4: 0 | AF4: 0
B6: Market and Policies Scenario
C7: Note that changing tax credit assumptions has implications for project financing. If you change numbers here, we strongly recommend changing debt fractions on the WACC Calc sheet as well.
A9: ITC (%) | B9: Offshore Wind | C9: 0.30000001 | D9: 0.30000001 | E9: 0.30000001 | F9: 0.30000001 | G9: 0.30000001 | H9: 0.30000001 | I9: 0.30000001 | J9: 0.30000001 | K9: 0.30000001 | L9: 0.30000001 | M9: 0.30000001 | N9: 0.30000001 | O9: 0.30000001 | P9: 0.30000001 | Q9: 0.30000001 | R9: 0.30000001 | S9: 0.30000001 | T9: 0.30000001 | U9: 0.30000001 | V9: 0.30000001 | W9: 0.30000001 | X9: 0.30000001 | Y9: 0.30000001 | Z9: 0.30000001 | AA9: 0.30000001 | AB9: 0.30000001 | AC9: 0.30000001 | AD9: 0.30000001 | AE9: 0.30000001 | AF9: 0.22500001 | AH9: 10 Year Safe Harbor
B10: Land-Based Wind | C10: 0 | D10: 0 | E10: 0 | F10: 0 | G10: 0 | H10: 0 | I10: 0 | J10: 0 | K10: 0 | L10: 0 | M10: 0 | N10: 0 | O10: 0 | P10: 0 | Q10: 0 | R10: 0 | S10: 0 | T10: 0 | U10: 0 | V10: 0 | W10: 0 | X10: 0 | Y10: 0 | Z10: 0 | AA10: 0 | AB10: 0 | AC10: 0 | AD10: 0 | AE10: 0 | AF10: 0
B11: Distributed Wind | C11: 0 | D11: 0 | E11: 0.30000001 | F11: 0.30000001 | G11: 0.30000001 | H11: 0.30000001 | I11: 0.30000001 | J11: 0.30000001 | K11: 0.30000001 | L11: 0.30000001 | M11: 0.30000001 | N11: 0.30000001 | O11: 0.30000001 | P11: 0.30000001 | Q11: 0.30000001 | R11: 0.30000001 | S11: 0.30000001 | T11: 0.30000001 | U11: 0.30000001 | V11: 0.30000001 | W11: 0.30000001 | X11: 0.30000001 | Y11: 0.30000001 | Z11: 0.22500001 | AA11: 0.15000001 | AB11: 0 | AC11: 0 | AD11: 0 | AE11: 0 | AF11: 0 | AH11: 4 Year Safe Harbor
B12: Solar - Utility PV | C12: 0.30000001 | D12: 0.30000001 | E12: 0 | F12: 0 | G12: 0 | H12: 0 | I12: 0 | J12: 0 | K12: 0 | L12: 0 | M12: 0 | N12: 0 | O12: 0 | P12: 0 | Q12: 0 | R12: 0 | S12: 0 | T12: 0 | U12: 0 | V12: 0 | W12: 0 | X12: 0 | Y12: 0 | Z12: 0 | AA12: 0 | AB12: 0 | AC12: 0 | AD12: 0 | AE12: 0 | AF12: 0
B13: Solar - PV Dist. Comm | C13: 0.30000001 | D13: 0.30000001 | E13: 0.30000001 | F13: 0.30000001 | G13: 0.30000001 | H13: 0.30000001 | I13: 0.30000001 | J13: 0.30000001 | K13: 0.30000001 | L13: 0.30000001 | M13: 0.30000001 | N13: 0.30000001 | O13: 0.30000001 | P13: 0.30000001 | Q13: 0.30000001 | R13: 0.30000001 | S13: 0.30000001 | T13: 0.30000001 | U13: 0.30000001 | V13: 0.30000001 | W13: 0.30000001 | X13: 0.30000001 | Y13: 0.30000001 | Z13: 0.22500001 | AA13: 0.15000001 | AB13: 0 | AC13: 0 | AD13: 0 | AE13: 0 | AF13: 0 | AH13: 4 Year Safe Harbor
B14: Solar - PV Dist. Res | C14: 0.30000001 | D14: 0.30000001 | E14: 0.30000001 | F14: 0.30000001 | G14: 0.30000001 | H14: 0.30000001 | I14: 0.30000001 | J14: 0.30000001 | K14: 0.30000001 | L14: 0.30000001 | M14: 0.30000001 | N14: 0.30000001 | O14: 0.26 | P14: 0.22 | Q14: 0 | R14: 0 | S14: 0 | T14: 0 | U14: 0 | V14: 0 | W14: 0 | X14: 0 | Y14: 0 | Z14: 0 | AA14: 0 | AB14: 0 | AC14: 0 | AD14: 0 | AE14: 0 | AF14: 0
B15: Solar - CSP | C15: 0.30000001 | D15: 0.30000001 | E15: 0.30000001 | F15: 0.30000001 | G15: 0.30000001 | H15: 0.30000001 | I15: 0.30000001 | J15: 0.30000001 | K15: 0.30000001 | L15: 0.30000001 | M15: 0.30000001 | N15: 0.30000001 | O15: 0.30000001 | P15: 0.30000001 | Q15: 0.30000001 | R15: 0.30000001 | S15: 0.30000001 | T15: 0.30000001 | U15: 0.30000001 | V15: 0.30000001 | W15: 0.30000001 | X15: 0.30000001 | Y15: 0.30000001 | Z15: 0.22500001 | AA15: 0.15000001 | AB15: 0 | AC15: 0 | AD15: 0 | AE15: 0 | AF15: 0 | AH15: 25D specifies credit by date, not CO2 emissions
B16: Geothermal | C16: 0 | D16: 0 | E16: 0.30000001 | F16: 0.30000001 | G16: 0.30000001 | H16: 0.30000001 | I16: 0.30000001 | J16: 0.30000001 | K16: 0.30000001 | L16: 0.30000001 | M16: 0.30000001 | N16: 0.30000001 | O16: 0.30000001 | P16: 0.30000001 | Q16: 0.30000001 | R16: 0.30000001 | S16: 0.30000001 | T16: 0.30000001 | U16: 0.30000001 | V16: 0.30000001 | W16: 0.30000001 | X16: 0.30000001 | Y16: 0.30000001 | Z16: 0.22500001 | AA16: 0.15000001 | AB16: 0 | AC16: 0 | AD16: 0 | AE16: 0 | AF16: 0 | AH16: 4 Year Safe Harbor
B17: Hydropower | C17: 0 | D17: 0 | E17: 0.30000001 | F17: 0.30000001 | G17: 0.30000001 | H17: 0.30000001 | I17: 0.30000001 | J17: 0.30000001 | K17: 0.30000001 | L17: 0.30000001 | M17: 0.30000001 | N17: 0.30000001 | O17: 0.30000001 | P17: 0.30000001 | Q17: 0.30000001 | R17: 0.30000001 | S17: 0.30000001 | T17: 0.30000001 | U17: 0.30000001 | V17: 0.30000001 | W17: 0.30000001 | X17: 0.30000001 | Y17: 0.30000001 | Z17: 0.22500001 | AA17: 0.15000001 | AB17: 0 | AC17: 0 | AD17: 0 | AE17: 0 | AF17: 0 | AH17: 4 Year Safe Harbor
B18: Nuclear | C18: 0 | D18: 0 | E18: 0 | F18: 0 | G18: 0.30000001 | H18: 0.30000001 | I18: 0.30000001 | J18: 0.30000001 | K18: 0.30000001 | L18: 0.30000001 | M18: 0.30000001 | N18: 0.30000001 | O18: 0.30000001 | P18: 0.30000001 | Q18: 0.30000001 | R18: 0.30000001 | S18: 0.30000001 | T18: 0.30000001 | U18: 0.30000001 | V18: 0.30000001 | W18: 0.30000001 | X18: 0.30000001 | Y18: 0.30000001 | Z18: 0.22500001 | AA18: 0.15000001 | AB18: 0 | AC18: 0 | AD18: 0 | AE18: 0 | AF18: 0 | AH18: 4 Year Safe Harbor
B19: Biopower | C19: 0 | D19: 0 | E19: 0 | F19: 0 | G19: 0 | H19: 0 | I19: 0 | J19: 0 | K19: 0 | L19: 0 | M19: 0 | N19: 0 | O19: 0 | P19: 0 | Q19: 0 | R19: 0 | S19: 0 | T19: 0 | U19: 0 | V19: 0 | W19: 0 | X19: 0 | Y19: 0 | Z19: 0 | AA19: 0 | AB19: 0 | AC19: 0 | AD19: 0 | AE19: 0 | AF19: 0
B20: Utility-Scale PV-Plus-Battery | C20: 0.30000001 | D20: 0.30000001 | E20: 0.30000001 | F20: 0.30000001 | G20: 0.30000001 | H20: 0.30000001 | I20: 0.30000001 | J20: 0.30000001 | K20: 0.30000001 | L20: 0.30000001 | M20: 0.30000001 | N20: 0.30000001 | O20: 0.30000001 | P20: 0.30000001 | Q20: 0.30000001 | R20: 0.30000001 | S20: 0.30000001 | T20: 0.30000001 | U20: 0.30000001 | V20: 0.30000001 | W20: 0.30000001 | X20: 0.30000001 | Y20: 0.30000001 | Z20: 0.22500001 | AA20: 0.15000001 | AB20: 0 | AC20: 0 | AD20: 0 | AE20: 0 | AF20: 0 | AH20: 4 Year Safe Harbor
B21: Utility-Scale Battery Storage | C21: 0.30000001 | D21: 0.30000001 | E21: 0.30000001 | F21: 0.30000001 | G21: 0.30000001 | H21: 0.30000001 | I21: 0.30000001 | J21: 0.30000001 | K21: 0.30000001 | L21: 0.30000001 | M21: 0.30000001 | N21: 0.30000001 | O21: 0.30000001 | P21: 0.30000001 | Q21: 0.30000001 | R21: 0.30000001 | S21: 0.30000001 | T21: 0.30000001 | U21: 0.30000001 | V21: 0.30000001 | W21: 0.30000001 | X21: 0.30000001 | Y21: 0.30000001 | Z21: 0.22500001 | AA21: 0.15000001 | AB21: 0 | AC21: 0 | AD21: 0 | AE21: 0 | AF21: 0 | AH21: 4 Year Safe Harbor
B22: Commercial Battery Storage | C22: 0.30000001 | D22: 0.30000001 | E22: 0.30000001 | F22: 0.30000001 | G22: 0.30000001 | H22: 0.30000001 | I22: 0.30000001 | J22: 0.30000001 | K22: 0.30000001 | L22: 0.30000001 | M22: 0.30000001 | N22: 0.30000001 | O22: 0.30000001 | P22: 0.30000001 | Q22: 0.30000001 | R22: 0.30000001 | S22: 0.30000001 | T22: 0.30000001 | U22: 0.30000001 | V22: 0.30000001 | W22: 0.30000001 | X22: 0.30000001 | Y22: 0.30000001 | Z22: 0.22500001 | AA22: 0.15000001 | AB22: 0 | AC22: 0 | AD22: 0 | AE22: 0 | AF22: 0 | AH22: 4 Year Safe Harbor
B23: Residential Battery Storage | C23: 0.30000001 | D23: 0.30000001 | E23: 0.30000001 | F23: 0.30000001 | G23: 0.30000001 | H23: 0.30000001 | I23: 0.30000001 | J23: 0.30000001 | K23: 0.30000001 | L23: 0.30000001 | M23: 0.30000001 | N23: 0.30000001 | O23: 0.26 | P23: 0.22 | Q23: 0 | R23: 0 | S23: 0 | T23: 0 | U23: 0 | V23: 0 | W23: 0 | X23: 0 | Y23: 0 | Z23: 0 | AA23: 0 | AB23: 0 | AC23: 0 | AD23: 0 | AE23: 0 | AF23: 0 | AH23: 25D specifies credit by date, not CO2 emissions
B24: Pumped Storage Hydropower | C24: 0.30000001 | D24: 0.30000001 | E24: 0.30000001 | F24: 0.30000001 | G24: 0.30000001 | H24: 0.30000001 | I24: 0.30000001 | J24: 0.30000001 | K24: 0.30000001 | L24: 0.30000001 | M24: 0.30000001 | N24: 0.30000001 | O24: 0.30000001 | P24: 0.30000001 | Q24: 0.30000001 | R24: 0.30000001 | S24: 0.30000001 | T24: 0.30000001 | U24: 0.30000001 | V24: 0.30000001 | W24: 0.30000001 | X24: 0.30000001 | Y24: 0.30000001 | Z24: 0.22500001 | AA24: 0.15000001 | AB24: 0 | AC24: 0 | AD24: 0 | AE24: 0 | AF24: 0 | AH24: 4 Year Safe Harbor
A26: PTC ($/MWh) | B26: Offshore Wind | C26: 0 | D26: 0 | E26: 0 | F26: 0 | G26: 0 | H26: 0 | I26: 0 | J26: 0 | K26: 0 | L26: 0 | M26: 0 | N26: 0 | O26: 0 | P26: 0 | Q26: 0 | R26: 0 | S26: 0 | T26: 0 | U26: 0 | V26: 0 | W26: 0 | X26: 0 | Y26: 0 | Z26: 0 | AA26: 0 | AB26: 0 | AC26: 0 | AD26: 0 | AE26: 0 | AF26: 0
B27: Land-Based Wind | C27: 19.2 | D27: 25.46 | E27: 25.46 | F27: 25.46 | G27: 25.46 | H27: 25.46 | I27: 25.46 | J27: 25.46 | K27: 25.46 | L27: 25.46 | M27: 25.46 | N27: 25.46 | O27: 25.46 | P27: 25.46 | Q27: 25.46 | R27: 25.46 | S27: 25.46 | T27: 25.46 | U27: 25.46 | V27: 25.46 | W27: 25.46 | X27: 25.46 | Y27: 25.46 | Z27: 19.095 | AA27: 12.73 | AB27: 0 | AC27: 0 | AD27: 0 | AE27: 0 | AF27: 0 | AH27: 4 Year Safe Harbor
B28: Distributed Wind | C28: 19.2 | D28: 25.46 | E28: 0 | F28: 0 | G28: 0 | H28: 0 | I28: 0 | J28: 0 | K28: 0 | L28: 0 | M28: 0 | N28: 0 | O28: 0 | P28: 0 | Q28: 0 | R28: 0 | S28: 0 | T28: 0 | U28: 0 | V28: 0 | W28: 0 | X28: 0 | Y28: 0 | Z28: 0 | AA28: 0 | AB28: 0 | AC28: 0 | AD28: 0 | AE28: 0 | AF28: 0
B29: Solar - Utility PV | C29: 0 | D29: 0 | E29: 25.46 | F29: 25.46 | G29: 25.46 | H29: 25.46 | I29: 25.46 | J29: 25.46 | K29: 25.46 | L29: 25.46 | M29: 25.46 | N29: 25.46 | O29: 25.46 | P29: 25.46 | Q29: 25.46 | R29: 25.46 | S29: 25.46 | T29: 25.46 | U29: 25.46 | V29: 25.46 | W29: 25.46 | X29: 25.46 | Y29: 25.46 | Z29: 19.095 | AA29: 12.73 | AB29: 0 | AC29: 0 | AD29: 0 | AE29: 0 | AF29: 0 | AH29: 4 Year Safe Harbor
B30: Solar - PV Dist. Comm | C30: 0 | D30: 0 | E30: 0 | F30: 0 | G30: 0 | H30: 0 | I30: 0 | J30: 0 | K30: 0 | L30: 0 | M30: 0 | N30: 0 | O30: 0 | P30: 0 | Q30: 0 | R30: 0 | S30: 0 | T30: 0 | U30: 0 | V30: 0 | W30: 0 | X30: 0 | Y30: 0 | Z30: 0 | AA30: 0 | AB30: 0 | AC30: 0 | AD30: 0 | AE30: 0 | AF30: 0
B31: Solar - PV Dist. Res | C31: 0 | D31: 0 | E31: 0 | F31: 0 | G31: 0 | H31: 0 | I31: 0 | J31: 0 | K31: 0 | L31: 0 | M31: 0 | N31: 0 | O31: 0 | P31: 0 | Q31: 0 | R31: 0 | S31: 0 | T31: 0 | U31: 0 | V31: 0 | W31: 0 | X31: 0 | Y31: 0 | Z31: 0 | AA31: 0 | AB31: 0 | AC31: 0 | AD31: 0 | AE31: 0 | AF31: 0
B32: Solar - CSP | C32: 0 | D32: 0 | E32: 0 | F32: 0 | G32: 0 | H32: 0 | I32: 0 | J32: 0 | K32: 0 | L32: 0 | M32: 0 | N32: 0 | O32: 0 | P32: 0 | Q32: 0 | R32: 0 | S32: 0 | T32: 0 | U32: 0 | V32: 0 | W32: 0 | X32: 0 | Y32: 0 | Z32: 0 | AA32: 0 | AB32: 0 | AC32: 0 | AD32: 0 | AE32: 0 | AF32: 0
B33: Geothermal | C33: 24 | D33: 24 | E33: 0 | F33: 0 | G33: 0 | H33: 0 | I33: 0 | J33: 0 | K33: 0 | L33: 0 | M33: 0 | N33: 0 | O33: 0 | P33: 0 | Q33: 0 | R33: 0 | S33: 0 | T33: 0 | U33: 0 | V33: 0 | W33: 0 | X33: 0 | Y33: 0 | Z33: 0 | AA33: 0 | AB33: 0 | AC33: 0 | AD33: 0 | AE33: 0 | AF33: 0
B34: Hydropower | C34: 6 | D34: 6 | E34: 0 | F34: 0 | G34: 0 | H34: 0 | I34: 0 | J34: 0 | K34: 0 | L34: 0 | M34: 0 | N34: 0 | O34: 0 | P34: 0 | Q34: 0 | R34: 0 | S34: 0 | T34: 0 | U34: 0 | V34: 0 | W34: 0 | X34: 0 | Y34: 0 | Z34: 0 | AA34: 0 | AB34: 0 | AC34: 0 | AD34: 0 | AE34: 0 | AF34: 0
B35: Nuclear | C35: 0 | D35: 0 | E35: 0 | F35: 0 | G35: 0 | H35: 0 | I35: 0 | J35: 0 | K35: 0 | L35: 0 | M35: 0 | N35: 0 | O35: 0 | P35: 0 | Q35: 0 | R35: 0 | S35: 0 | T35: 0 | U35: 0 | V35: 0 | W35: 0 | X35: 0 | Y35: 0 | Z35: 0 | AA35: 0 | AB35: 0 | AC35: 0 | AD35: 0 | AE35: 0 | AF35: 0
B36: Biopower | C36: 0 | D36: 0 | E36: 25.46 | F36: 25.46 | G36: 25.46 | H36: 25.46 | I36: 25.46 | J36: 25.46 | K36: 25.46 | L36: 25.46 | M36: 25.46 | N36: 25.46 | O36: 25.46 | P36: 25.46 | Q36: 25.46 | R36: 25.46 | S36: 25.46 | T36: 25.46 | U36: 25.46 | V36: 25.46 | W36: 25.46 | X36: 25.46 | Y36: 25.46 | Z36: 19.095 | AA36: 12.73 | AB36: 0 | AC36: 0 | AD36: 0 | AE36: 0 | AF36: 0 | AH36: 4 Year Safe Harbor
B37: Utility-Scale PV-Plus-Battery | C37: 0 | D37: 0 | E37: 0 | F37: 0 | G37: 0 | H37: 0 | I37: 0 | J37: 0 | K37: 0 | L37: 0 | M37: 0 | N37: 0 | O37: 0 | P37: 0 | Q37: 0 | R37: 0 | S37: 0 | T37: 0 | U37: 0 | V37: 0 | W37: 0 | X37: 0 | Y37: 0 | Z37: 0 | AA37: 0 | AB37: 0 | AC37: 0 | AD37: 0 | AE37: 0 | AF37: 0
B38: Utility-Scale Battery Storage | C38: 0 | D38: 0 | E38: 0 | F38: 0 | G38: 0 | H38: 0 | I38: 0 | J38: 0 | K38: 0 | L38: 0 | M38: 0 | N38: 0 | O38: 0 | P38: 0 | Q38: 0 | R38: 0 | S38: 0 | T38: 0 | U38: 0 | V38: 0 | W38: 0 | X38: 0 | Y38: 0 | Z38: 0 | AA38: 0 | AB38: 0 | AC38: 0 | AD38: 0 | AE38: 0 | AF38: 0
B39: Commercial Battery Storage | C39: 0 | D39: 0 | E39: 0 | F39: 0 | G39: 0 | H39: 0 | I39: 0 | J39: 0 | K39: 0 | L39: 0 | M39: 0 | N39: 0 | O39: 0 | P39: 0 | Q39: 0 | R39: 0 | S39: 0 | T39: 0 | U39: 0 | V39: 0 | W39: 0 | X39: 0 | Y39: 0 | Z39: 0 | AA39: 0 | AB39: 0 | AC39: 0 | AD39: 0 | AE39: 0 | AF39: 0
B40: Residential Battery Storage | C40: 0 | D40: 0 | E40: 0 | F40: 0 | G40: 0 | H40: 0 | I40: 0 | J40: 0 | K40: 0 | L40: 0 | M40: 0 | N40: 0 | O40: 0 | P40: 0 | Q40: 0 | R40: 0 | S40: 0 | T40: 0 | U40: 0 | V40: 0 | W40: 0 | X40: 0 | Y40: 0 | Z40: 0 | AA40: 0 | AB40: 0 | AC40: 0 | AD40: 0 | AE40: 0 | AF40: 0
B41: Pumped Storage Hydropower | C41: 0 | D41: 0 | E41: 0 | F41: 0 | G41: 0 | H41: 0 | I41: 0 | J41: 0 | K41: 0 | L41: 0 | M41: 0 | N41: 0 | O41: 0 | P41: 0 | Q41: 0 | R41: 0 | S41: 0 | T41: 0 | U41: 0 | V41: 0 | W41: 0 | X41: 0 | Y41: 0 | Z41: 0 | AA41: 0 | AB41: 0 | AC41: 0 | AD41: 0 | AE41: 0 | AF41: 0
A43: Notes and References | B43: PTC Amounts from https://www.irs.gov/pub/irs-drop/a-22-23.pdf, deflated to 2021 dollars
B44: Tax credits for storage technologies are included here for reference, but do not affect project costs since the ATB does not calculate LCOS
B45: Some plants represented in the ATB may qualify for additional tax credits such as 45Q. These credits are not represented here because the ATB does not calculate LCOE for these technologies
B46: For more details see: https://www.whitehouse.gov/wp-content/uploads/2022/12/Inflation-Reduction-Act-Guidebook.pdf

Sheet Solar - Utility PV
A1: Solar Utility PV | M1: https://atb.nrel.gov/electricity/2023/utility-scale_pv
U2: Inputs
U3: Calculated
U4: Input from other tab
B7: X | G7: Assumptions
H9: Technology | J9: Base Year: | M9: 2021
J10: All values are given in 2021 U.S. dollars, see references at the bottom of this worksheet for dollar year conversions where source dollar years don't match 2021.
J11: Utility Scale Solar Photovoltaic
J12: Representative plant is single-axis tracking with capacity of 100 MW DC
J13: Overnight Capital Cost, Capacity Factor, Fixed O&M, and Variable O&M costs represent
J14: $/kW AC, unlike the commercial and residential PV cases which are represented in $/kW DC.
J15: Capacity factors chosen here to reflect range across the continental U.S. in ReEDS.
J16: Available Capacity (GW)
J19: 118918
M20: ATB values reflect annual average capacity factor over life of plant including estimated degradation, starting at 0.7% per year, reducing to 0.2%, 0.5%, and 0.5% annual degradation by 2050 for the advanced, moderate, and conservative scenarios, respectively. Capacity factors also assume an energy yield gain of 20%, 10%, and 0% for advanced, moderate, and conservatives scenarios in 2035.
J26: Technology Classification | K26: Name | L26: Tech | M26: Resource | N26: Scale | O26: Maturity
K27: Utility PV - Class 1 | L27: Tracking PV | M27: Class1 | N27: Utility | O27: Y
K28: Utility PV - Class 2 | L28: Tracking PV | M28: Class2 | N28: Utility | O28: Y
K29: Utility PV - Class 3 | L29: Tracking PV | M29: Class3 | N29: Utility | O29: Y
K30: Utility PV - Class 4 | L30: Tracking PV | M30: Class4 | N30: Utility | O30: Y
K31: Utility PV - Class 5 | L31: Tracking PV | M31: Class5 | N31: Utility | O31: Y
K32: Utility PV - Class 6 | L32: Tracking PV | M32: Class6 | N32: Utility | O32: Y
K33: Utility PV - Class 7 | L33: Tracking PV | M33: Class7 | N33: Utility | O33: Y
K34: Utility PV - Class 8 | L34: Tracking PV | M34: Class8 | N34: Utility | O34: Y
K35: Utility PV - Class 9 | L35: Tracking PV | M35: Class9 | N35: Utility | O35: Y
K36: Utility PV - Class 10 | L36: Tracking PV | M36: Class10 | N36: Utility | O36: Y
H38: Finance | J38: Financial Assumptions:
J39: Capital Recovery Period (Years) | O39: 20 | Q39: Financial Case | S39: Market
J40: Depreciation Period | O40: 5 | Q40: Capital Recovery Period | S40: 20
J41: Equity Premium During Construction | O41: 0.02
J42: Construction Duration yrs | O42: 1
J43: Year | K43: Capital | L43: Percent of Leverage During Construction | M43: Percent of Equity During Construction
J44: Index | K44: Fraction
J47: 0 | K47: 1 | L47: 0.8 | M47: 0.2
J48: 1 | K48: 0 | L48: 0.8 | M48: 0.2
J49: 2 | K49: 0 | L49: 0.8 | M49: 0.2
M51: 2021 | N51: 2022 | O51: 2023 | P51: 2024 | Q51: 2025 | R51: 2026 | S51: 2027 | T51: 2028 | U51: 2029 | V51: 2030 | W51: 2031 | X51: 2032 | Y51: 2033 | Z51: 2034 | AA51: 2035 | AB51: 2036 | AC51: 2037 | AD51: 2038 | AE51: 2039 | AF51: 2040 | AG51: 2041 | AH51: 2042 | AI51: 2043 | AJ51: 2044 | AK51: 2045 | AL51: 2046 | AM51: 2047 | AN51: 2048 | AO51: 2049 | AP51: 2050
J52: Assumptions | K52: Inflation Rate | L52: * | M52: 0.0279 | N52: 0.0272 | O52: 0.0253 | P52: 0.025 | Q52: 0.025 | R52: 0.025 | S52: 0.025 | T52: 0.025 | U52: 0.025 | V52: 0.025 | W52: 0.025 | X52: 0.025 | Y52: 0.025 | Z52: 0.025 | AA52: 0.025 | AB52: 0.025 | AC52: 0.025 | AD52: 0.025 | AE52: 0.025 | AF52: 0.025 | AG52: 0.025 | AH52: 0.025 | AI52: 0.025 | AJ52: 0.025 | AK52: 0.025 | AL52: 0.025 | AM52: 0.025 | AN52: 0.025 | AO52: 0.025 | AP52: 0.025
K53: Interest Rate Nominal | L53: Advanced | M53: 0.07 | N53: 0.07 | O53: 0.07 | P53: 0.07 | Q53: 0.07 | R53: 0.07 | S53: 0.07 | T53: 0.07 | U53: 0.07 | V53: 0.07 | W53: 0.07 | X53: 0.07 | Y53: 0.07 | Z53: 0.07 | AA53: 0.07 | AB53: 0.07 | AC53: 0.07 | AD53: 0.07 | AE53: 0.07 | AF53: 0.07 | AG53: 0.07 | AH53: 0.07 | AI53: 0.07 | AJ53: 0.07 | AK53: 0.07 | AL53: 0.07 | AM53: 0.07 | AN53: 0.07 | AO53: 0.07 | AP53: 0.07
K54: Interest Rate Nominal | L54: Moderate | M54: 0.07 | N54: 0.07 | O54: 0.07 | P54: 0.07 | Q54: 0.07 | R54: 0.07 | S54: 0.07 | T54: 0.07 | U54: 0.07 | V54: 0.07 | W54: 0.07 | X54: 0.07 | Y54: 0.07 | Z54: 0.07 | AA54: 0.07 | AB54: 0.07 | AC54: 0.07 | AD54: 0.07 | AE54: 0.07 | AF54: 0.07 | AG54: 0.07 | AH54: 0.07 | AI54: 0.07 | AJ54: 0.07 | AK54: 0.07 | AL54: 0.07 | AM54: 0.07 | AN54: 0.07 | AO54: 0.07 | AP54: 0.07
K55: Interest Rate Nominal | L55: Conservative | M55: 0.07 | N55: 0.07 | O55: 0.07 | P55: 0.07 | Q55: 0.07 | R55: 0.07 | S55: 0.07 | T55: 0.07 | U55: 0.07 | V55: 0.07 | W55: 0.07 | X55: 0.07 | Y55: 0.07 | Z55: 0.07 | AA55: 0.07 | AB55: 0.07 | AC55: 0.07 | AD55: 0.07 | AE55: 0.07 | AF55: 0.07 | AG55: 0.07 | AH55: 0.07 | AI55: 0.07 | AJ55: 0.07 | AK55: 0.07 | AL55: 0.07 | AM55: 0.07 | AN55: 0.07 | AO55: 0.07 | AP55: 0.07
K56: Calculated Interest Rate Real | L56: Advanced | M56: 0.040957292 | N56: 0.041666667 | O56: 0.043596996 | P56: 0.043902439 | Q56: 0.043902439 | R56: 0.043902439 | S56: 0.043902439 | T56: 0.043902439 | U56: 0.043902439 | V56: 0.043902439 | W56: 0.043902439 | X56: 0.043902439 | Y56: 0.043902439 | Z56: 0.043902439 | AA56: 0.043902439 | AB56: 0.043902439 | AC56: 0.043902439 | AD56: 0.043902439 | AE56: 0.043902439 | AF56: 0.043902439 | AG56: 0.043902439 | AH56: 0.043902439 | AI56: 0.043902439 | AJ56: 0.043902439 | AK56: 0.043902439 | AL56: 0.043902439 | AM56: 0.043902439 | AN56: 0.043902439 | AO56: 0.043902439 | AP56: 0.043902439
K57: Calculated Interest Rate Real | L57: Moderate | M57: 0.040957292 | N57: 0.041666667 | O57: 0.043596996 | P57: 0.043902439 | Q57: 0.043902439 | R57: 0.043902439 | S57: 0.043902439 | T57: 0.043902439 | U57: 0.043902439 | V57: 0.043902439 | W57: 0.043902439 | X57: 0.043902439 | Y57: 0.043902439 | Z57: 0.043902439 | AA57: 0.043902439 | AB57: 0.043902439 | AC57: 0.043902439 | AD57: 0.043902439 | AE57: 0.043902439 | AF57: 0.043902439 | AG57: 0.043902439 | AH57: 0.043902439 | AI57: 0.043902439 | AJ57: 0.043902439 | AK57: 0.043902439 | AL57: 0.043902439 | AM57: 0.043902439 | AN57: 0.043902439 | AO57: 0.043902439 | AP57: 0.043902439
K58: Calculated Interest Rate Real | L58: Conservative | M58: 0.040957292 | N58: 0.041666667 | O58: 0.043596996 | P58: 0.043902439 | Q58: 0.043902439 | R58: 0.043902439 | S58: 0.043902439 | T58: 0.043902439 | U58: 0.043902439 | V58: 0.043902439 | W58: 0.043902439 | X58: 0.043902439 | Y58: 0.043902439 | Z58: 0.043902439 | AA58: 0.043902439 | AB58: 0.043902439 | AC58: 0.043902439 | AD58: 0.043902439 | AE58: 0.043902439 | AF58: 0.043902439 | AG58: 0.043902439 | AH58: 0.043902439 | AI58: 0.043902439 | AJ58: 0.043902439 | AK58: 0.043902439 | AL58: 0.043902439 | AM58: 0.043902439 | AN58: 0.043902439 | AO58: 0.043902439 | AP58: 0.043902439
K59: Interest During Construction - Nominal | L59: * | M59: 0.065 | N59: 0.065 | O59: 0.065 | P59: 0.065 | Q59: 0.065 | R59: 0.065 | S59: 0.065 | T59: 0.065 | U59: 0.065 | V59: 0.065 | W59: 0.065 | X59: 0.065 | Y59: 0.065 | Z59: 0.065 | AA59: 0.065 | AB59: 0.065 | AC59: 0.065 | AD59: 0.065 | AE59: 0.065 | AF59: 0.065 | AG59: 0.065 | AH59: 0.065 | AI59: 0.065 | AJ59: 0.065 | AK59: 0.065 | AL59: 0.065 | AM59: 0.065 | AN59: 0.065 | AO59: 0.065 | AP59: 0.065
K60: Rate of Return on Equity Nominal | L60: Advanced | M60: 0.088 | N60: 0.088 | O60: 0.088 | P60: 0.088 | Q60: 0.088 | R60: 0.088 | S60: 0.088 | T60: 0.088 | U60: 0.088 | V60: 0.088 | W60: 0.088 | X60: 0.088 | Y60: 0.088 | Z60: 0.088 | AA60: 0.088 | AB60: 0.088 | AC60: 0.088 | AD60: 0.088 | AE60: 0.088 | AF60: 0.088 | AG60: 0.088 | AH60: 0.088 | AI60: 0.088 | AJ60: 0.088 | AK60: 0.088 | AL60: 0.088 | AM60: 0.088 | AN60: 0.088 | AO60: 0.088 | AP60: 0.088
K61: Rate of Return on Equity Nominal | L61: Moderate | M61: 0.088 | N61: 0.088 | O61: 0.088 | P61: 0.088 | Q61: 0.088 | R61: 0.088 | S61: 0.088 | T61: 0.088 | U61: 0.088 | V61: 0.088 | W61: 0.088 | X61: 0.088 | Y61: 0.088 | Z61: 0.088 | AA61: 0.088 | AB61: 0.088 | AC61: 0.088 | AD61: 0.088 | AE61: 0.088 | AF61: 0.088 | AG61: 0.088 | AH61: 0.088 | AI61: 0.088 | AJ61: 0.088 | AK61: 0.088 | AL61: 0.088 | AM61: 0.088 | AN61: 0.088 | AO61: 0.088 | AP61: 0.088
K62: Rate of Return on Equity Nominal | L62: Conservative | M62: 0.088 | N62: 0.088 | O62: 0.088 | P62: 0.088 | Q62: 0.088 | R62: 0.088 | S62: 0.088 | T62: 0.088 | U62: 0.088 | V62: 0.088 | W62: 0.088 | X62: 0.088 | Y62: 0.088 | Z62: 0.088 | AA62: 0.088 | AB62: 0.088 | AC62: 0.088 | AD62: 0.088 | AE62: 0.088 | AF62: 0.088 | AG62: 0.088 | AH62: 0.088 | AI62: 0.088 | AJ62: 0.088 | AK62: 0.088 | AL62: 0.088 | AM62: 0.088 | AN62: 0.088 | AO62: 0.088 | AP62: 0.088
K63: Calculated Rate of Return on Equity Real | L63: Advanced | M63: 0.058468723 | N63: 0.059190031 | O63: 0.061152833 | P63: 0.061463415 | Q63: 0.061463415 | R63: 0.061463415 | S63: 0.061463415 | T63: 0.061463415 | U63: 0.061463415 | V63: 0.061463415 | W63: 0.061463415 | X63: 0.061463415 | Y63: 0.061463415 | Z63: 0.061463415 | AA63: 0.061463415 | AB63: 0.061463415 | AC63: 0.061463415 | AD63: 0.061463415 | AE63: 0.061463415 | AF63: 0.061463415 | AG63: 0.061463415 | AH63: 0.061463415 | AI63: 0.061463415 | AJ63: 0.061463415 | AK63: 0.061463415 | AL63: 0.061463415 | AM63: 0.061463415 | AN63: 0.061463415 | AO63: 0.061463415 | AP63: 0.061463415
K64: Calculated Rate of Return on Equity Real | L64: Moderate | M64: 0.058468723 | N64: 0.059190031 | O64: 0.061152833 | P64: 0.061463415 | Q64: 0.061463415 | R64: 0.061463415 | S64: 0.061463415 | T64: 0.061463415 | U64: 0.061463415 | V64: 0.061463415 | W64: 0.061463415 | X64: 0.061463415 | Y64: 0.061463415 | Z64: 0.061463415 | AA64: 0.061463415 | AB64: 0.061463415 | AC64: 0.061463415 | AD64: 0.061463415 | AE64: 0.061463415 | AF64: 0.061463415 | AG64: 0.061463415 | AH64: 0.061463415 | AI64: 0.061463415 | AJ64: 0.061463415 | AK64: 0.061463415 | AL64: 0.061463415 | AM64: 0.061463415 | AN64: 0.061463415 | AO64: 0.061463415 | AP64: 0.061463415
... K81: Capital Recovery Factor (CRF) Real | L81: Conservative | M81: 0.07394932 | N81: 0.07441553 | O81: 0.075637737 | P81: 0.076002521 | Q81: 0.076174206 | R81: 0.076355697 | S81: 0.076547857 | T81: 0.076751655 | U81: 0.076968181 | V81: 0.077198663 | W81: 0.077444496 | X81: 0.077707264 | Y81: 0.077988777 | Z81: 0.078291113 | AA81: 0.078616668 | AB81: 0.078725694 | AC81: 0.07883741 | AD81: 0.078951917 | AE81: 0.079069321 | AF81: 0.079189732 | AG81: 0.079313267 | AH81: 0.07944005 | AI81: 0.07957021 | AJ81: 0.077493305 | AK81: 0.075383018 | AL81: 0.070699204 | AM81: 0.070699127 | AN81: 0.070699048 | AO81: 0.070698967 | AP81: 0.070698883
D84: X | G84: Future Projections
M85: Base Year
M86: 2021 | N86: 2022 | O86: 2023 | P86: 2024 | Q86: 2025 | R86: 2026 | S86: 2027 | T86: 2028 | U86: 2029 | V86: 2030 | W86: 2031 | X86: 2032 | Y86: 2033 | Z86: 2034 | AA86: 2035 | AB86: 2036 | AC86: 2037 | AD86: 2038 | AE86: 2039 | AF86: 2040 | AG86: 2041 | AH86: 2042 | AI86: 2043 | AJ86: 2044 | AK86: 2045 | AL86: 2046 | AM86: 2047 | AN86: 2048 | AO86: 2049 | AP86: 2050
H87: Techno-Economic Cost and Performance Parameters | J87: Net Capacity Factor (%) | K87: Utility PV - Class 1 | L87: Advanced | M87: 0.33998841 | N87: 0.34180761 | O87: 0.34362682 | P87: 0.34544602 | Q87: 0.34726523 | R87: 0.34908443 | S87: 0.35090363 | T87: 0.35272284 | U87: 0.35454204 | V87: 0.35636125 | W87: 0.35818045 | X87: 0.35999965 | Y87: 0.36181886 | Z87: 0.36363806 | AA87: 0.36545727 | AB87: 0.36647925 | AC87: 0.36750123 | AD87: 0.36852322 | AE87: 0.3695452 | AF87: 0.37056718 | AG87: 0.37158917 | AH87: 0.37261115 | AI87: 0.37363313 | AJ87: 0.37465512 | AK87: 0.3756771 | AL87: 0.37669909 | AM87: 0.37772107 | AN87: 0.37874305 | AO87: 0.37976504 | AP87: 0.38078702
K88: Utility PV - Class 1 | L88: Moderate | M88: 0.33998841 | N88: 0.34131199 | O88: 0.34263557 | P88: 0.34395914 | Q88: 0.34528272 | R88: 0.3466063 | S88: 0.34792988 | T88: 0.34925345 | U88: 0.35057703 | V88: 0.35190061 | W88: 0.35322419 | X88: 0.35454776 | Y88: 0.35587134 | Z88: 0.35719492 | AA88: 0.3585185 | AB88: 0.35898108 | AC88: 0.35944367 | AD88: 0.35990625 | AE88: 0.36036884 | AF88: 0.36083142 | AG88: 0.361294 | AH88: 0.36175659 | AI88: 0.36221917 | AJ88: 0.36268176 | AK88: 0.36314434 | AL88: 0.36360693 | AM88: 0.36406951 | AN88: 0.3645321 | AO88: 0.36499468 | AP88: 0.36545727
K89: Utility PV - Class 1 | L89: Conservative | M89: 0.33998841 | N89: 0.33998841 | O89: 0.33998841 | P89: 0.33998841 | Q89: 0.33998841 | R89: 0.33998841 | S89: 0.33998841 | T89: 0.33998841 | U89: 0.33998841 | V89: 0.33998841 | W89: 0.33998841 | X89: 0.33998841 | Y89: 0.33998841 | Z89: 0.33998841 | AA89: 0.33998841 | AB89: 0.34122375 | AC89: 0.34245909 | AD89: 0.34369443 | AE89: 0.34492977 | AF89: 0.34616511 | AG89: 0.34740044 | AH89: 0.34863578 | AI89: 0.34987112 | AJ89: 0.35110646 | AK89: 0.3523418 | AL89: 0.35357714 | AM89: 0.35481248 | AN89: 0.35604782 | AO89: 0.35728316 | AP89: 0.3585185
K90: Utility PV - Class 2 | L90: Advanced | M90: 0.32891481 | N90: 0.33064457 | O90: 0.33237432 | P90: 0.33410407 | Q90: 0.33583383 | R90: 0.33756358 | S90: 0.33929333 | T90: 0.34102309 | U90: 0.34275284 | V90: 0.3444826 | W90: 0.34621235 | X90: 0.3479421 | Y90: 0.34967186 | Z90: 0.35140161 | AA90: 0.35313136 | AB90: 0.35414825 | AC90: 0.35516513 | AD90: 0.35618201 | AE90: 0.35719889 | AF90: 0.35821577 | AG90: 0.35923265 | AH90: 0.36024954 | AI90: 0.36126642 | AJ90: 0.3622833 | AK90: 0.36330018 | AL90: 0.36431706 | AM90: 0.36533395 | AN90: 0.36635083 | AO90: 0.36736771 | AP90: 0.36838459
K91: Utility PV - Class 2 | L91: Moderate | M91: 0.32891481 | N91: 0.33017206 | O91: 0.33142931 | P91: 0.33268655 | Q91: 0.3339438 | R91: 0.33520105 | S91: 0.33645829 | T91: 0.33771554 | U91: 0.33897279 | V91: 0.34023004 | W91: 0.34148728 | X91: 0.34274453 | Y91: 0.34400178 | Z91: 0.34525902 | AA91: 0.34651627 | AB91: 0.34695728 | AC91: 0.34739828 | AD91: 0.34783929 | AE91: 0.34828029 | AF91: 0.3487213 | AG91: 0.34916231 | AH91: 0.34960331 | AI91: 0.35004432 | AJ91: 0.35048533 | AK91: 0.35092633 | AL91: 0.35136734 | AM91: 0.35180834 | AN91: 0.35224935 | AO91: 0.35269036 | AP91: 0.35313136
K92: Utility PV - Class 2 | L92: Conservative | M92: 0.32891481 | N92: 0.32891481 | O92: 0.32891481 | P92: 0.32891481 | Q92: 0.32891481 | R92: 0.32891481 | S92: 0.32891481 | T92: 0.32891481 | U92: 0.32891481 | V92: 0.32891481 | W92: 0.32891481 | X92: 0.32891481 | Y92: 0.32891481 | Z92: 0.32891481 | AA92: 0.32891481 | AB92: 0.33008824 | AC92: 0.33126167 | AD92: 0.3324351 | AE92: 0.33360853 | AF92: 0.33478197 | AG92: 0.3359554 | AH92: 0.33712883 | AI92: 0.33830226 | AJ92: 0.33947569 | AK92: 0.34064912 | AL92: 0.34182255 | AM92: 0.34299598 | AN92: 0.34416941 | AO92: 0.34534284 | AP92: 0.34651627
K93: Utility PV - Class 3 | L93: Advanced | M93: 0.31323814 | N93: 0.31502678 | O93: 0.31681541 | P93: 0.31860405 | Q93: 0.32039269 | R93: 0.32218132 | S93: 0.32396996 | T93: 0.3257586 | U93: 0.32754724 | V93: 0.32933587 | W93: 0.33112451 | X93: 0.33291315 | Y93: 0.33470179 | Z93: 0.33649042 | AA93: 0.33827906 | AB93: 0.33911557 | AC93: 0.33995208 | AD93: 0.34078859 | AE93: 0.3416251 | AF93: 0.34246161 | AG93: 0.34329812 | AH93: 0.34413463 | AI93: 0.34497114 | AJ93: 0.34580765 | AK93: 0.34664416 | AL93: 0.34748067 | AM93: 0.34831718 | AN93: 0.34915369 | AO93: 0.3499902 | AP93: 0.35082671
K94: Utility PV - Class 3 | L94: Moderate | M94: 0.31323814 | N94: 0.31453518 | O94: 0.31583223 | P94: 0.31712927 | Q94: 0.31842631 | R94: 0.31972336 | S94: 0.3210204 | T94: 0.32231745 | U94: 0.32361449 | V94: 0.32491153 | W94: 0.32620858 | X94: 0.32750562 | Y94: 0.32880267 | Z94: 0.33009971 | AA94: 0.33139675 | AB94: 0.33185558 | AC94: 0.3323144 | AD94: 0.33277322 | AE94: 0.33323204 | AF94: 0.33369086 | AG94: 0.33414968 | AH94: 0.3346085 | AI94: 0.33506732 | AJ94: 0.33552614 | AK94: 0.33598496 | AL94: 0.33644378 | AM94: 0.3369026 | AN94: 0.33736142 | AO94: 0.33782024 | AP94: 0.33827906
K95: Utility PV - Class 3 | L95: Conservative | M95: 0.31323814 | N95: 0.31323814 | O95: 0.31323814 | P95: 0.31323814 | Q95: 0.31323814 | R95: 0.31323814 | S95: 0.31323814 | T95: 0.31323814 | U95: 0.31323814 | V95: 0.31323814 | W95: 0.31323814 | X95: 0.31323814 | Y95: 0.31323814 | Z95: 0.31323814 | AA95: 0.31323814 | AB95: 0.31444871 | AC95: 0.31565929 | AD95: 0.31686986 | AE95: 0.31808044 | AF95: 0.31929101 | AG95: 0.32050158 | AH95: 0.32171216 | AI95: 0.32292273 | AJ95: 0.32413331 | AK95: 0.32534388 | AL95: 0.32655446 | AM95: 0.32776503 | AN95: 0.32897561 | AO95: 0.33018618 | AP95: 0.33139675
K96: Utility PV - Class 4 | L96: Advanced | M96: 0.29822264 | N96: 0.30003451 | O96: 0.30184638 | P96: 0.30365824 | Q96: 0.30547011 | R96: 0.30728198 | S96: 0.30909385 | T96: 0.31090572 | U96: 0.31271759 | V96: 0.31452946 | W96: 0.31634133 | X96: 0.31815319 | Y96: 0.31996506 | Z96: 0.32177693 | AA96: 0.3235888 | AB96: 0.3242835 | AC96: 0.32497821 | AD96: 0.32567291 | AE96: 0.32636762 | AF96: 0.32706232 | AG96: 0.32775702 | AH96: 0.32845173 | AI96: 0.32914643 | AJ96: 0.32984113 | AK96: 0.33053584 | AL96: 0.33123054 | AM96: 0.33192524 | AN96: 0.33261995 | AO96: 0.33331465 | AP96: 0.33400935
K97: Utility PV - Class 4 | L97: Moderate | M97: 0.29822264 | N97: 0.29953314 | O97: 0.30084365 | P97: 0.30215416 | Q97: 0.30346466 | R97: 0.30477517 | S97: 0.30608567 | T97: 0.30739618 | U97: 0.30870668 | V97: 0.31001719 | W97: 0.3113277 | X97: 0.3126382 | Y97: 0.31394871 | Z97: 0.31525921 | AA97: 0.31656972 | AB97: 0.31703766 | AC97: 0.3175056 | AD97: 0.31797354 | AE97: 0.31844147 | AF97: 0.31890941 | AG97: 0.31937735 | AH97: 0.31984529 | AI97: 0.32031323 | AJ97: 0.32078117 | AK97: 0.32124911 | AL97: 0.32171705 | AM97: 0.32218498 | AN97: 0.32265292 | AO97: 0.32312086 | AP97: 0.3235888
K98: Utility PV - Class 4 | L98: Conservative | M98: 0.29822264 | N98: 0.29822264 | O98: 0.29822264 | P98: 0.29822264 | Q98: 0.29822264 | R98: 0.29822264 | S98: 0.29822264 | T98: 0.29822264 | U98: 0.29822264 | V98: 0.29822264 | W98: 0.29822264 | X98: 0.29822264 | Y98: 0.29822264 | Z98: 0.29822264 | AA98: 0.29822264 | AB98: 0.29944578 | AC98: 0.30066892 | AD98: 0.30189205 | AE98: 0.30311519 | AF98: 0.30433833 | AG98: 0.30556147 | AH98: 0.30678461 | AI98: 0.30800775 | AJ98: 0.30923089 | AK98: 0.31045403 | AL98: 0.31167716 | AM98: 0.3129003 | AN98: 0.31412344 | AO98: 0.31534658 | AP98: 0.31656972
K99: Utility PV - Class 5 | L99: Advanced | M99: 0.28327664 | N99: 0.28506567 | O99: 0.2868547 | P99: 0.28864373 | Q99: 0.29043276 | R99: 0.29222179 | S99: 0.29401082 | T99: 0.29579985 | U99: 0.29758888 | V99: 0.29937791 | W99: 0.30116694 | X99: 0.30295597 | Y99: 0.304745 | Z99: 0.30653403 | AA99: 0.30832306 | AB99: 0.30891951 | AC99: 0.30951596 | AD99: 0.31011241 | AE99: 0.31070887 | AF99: 0.31130532 | AG99: 0.31190177 | AH99: 0.31249822 | AI99: 0.31309467 | AJ99: 0.31369112 | AK99: 0.31428758 | AL99: 0.31488403 | AM99: 0.31548048 | AN99: 0.31607693 | AO99: 0.31667338 | AP99: 0.31726984
... K116: Utility PV - Class 10 | L116: Conservative | M116: 0.2137264 | N116: 0.2137264 | O116: 0.2137264 | P116: 0.2137264 | Q116: 0.2137264 | R116: 0.2137264 | S116: 0.2137264 | T116: 0.2137264 | U116: 0.2137264 | V116: 0.2137264 | W116: 0.2137264 | X116: 0.2137264 | Y116: 0.2137264 | Z116: 0.2137264 | AA116: 0.2137264 | AB116: 0.21476266 | AC116: 0.21579893 | AD116: 0.2168352 | AE116: 0.21787146 | AF116: 0.21890773 | AG116: 0.219944 | AH116: 0.22098026 | AI116: 0.22201653 | AJ116: 0.2230528 | AK116: 0.22408906 | AL116: 0.22512533 | AM116: 0.2261616 | AN116: 0.22719786 | AO116: 0.22823413 | AP116: 0.2292704
M118: 2021 | N118: 2022 | O118: 2023 | P118: 2024 | Q118: 2025 | R118: 2026 | S118: 2027 | T118: 2028 | U118: 2029 | V118: 2030 | W118: 2031 | X118: 2032 | Y118: 2033 | Z118: 2034 | AA118: 2035 | AB118: 2036 | AC118: 2037 | AD118: 2038 | AE118: 2039 | AF118: 2040 | AG118: 2041 | AH118: 2042 | AI118: 2043 | AJ118: 2044 | AK118: 2045 | AL118: 2046 | AM118: 2047 | AN118: 2048 | AO118: 2049 | AP118: 2050
J119: Annual Energy Production (kWh/kW) | K119: Utility PV - Class 1 | L119: Advanced | M119: 2978.2985 | N119: 2994.2347 | O119: 3010.1709 | P119: 3026.1072 | Q119: 3042.0434 | R119: 3057.9796 | S119: 3073.9158 | T119: 3089.8521 | U119: 3105.7883 | V119: 3121.7245 | W119: 3137.6607 | X119: 3153.597 | Y119: 3169.5332 | Z119: 3185.4694 | AA119: 3201.4057 | AB119: 3210.3582 | AC119: 3219.3108 | AD119: 3228.2634 | AE119: 3237.216 | AF119: 3246.1685 | AG119: 3255.1211 | AH119: 3264.0737 | AI119: 3273.0263 | AJ119: 3281.9788 | AK119: 3290.9314 | AL119: 3299.884 | AM119: 3308.8366 | AN119: 3317.7891 | AO119: 3326.7417 | AP119: 3335.6943
K120: Utility PV - Class 1 | L120: Moderate | M120: 2978.2985 | N120: 2989.893 | O120: 3001.4876 | P120: 3013.0821 | Q120: 3024.6766 | R120: 3036.2712 | S120: 3047.8657 | T120: 3059.4603 | U120: 3071.0548 | V120: 3082.6493 | W120: 3094.2439 | X120: 3105.8384 | Y120: 3117.433 | Z120: 3129.0275 | AA120: 3140.622 | AB120: 3144.6743 | AC120: 3148.7265 | AD120: 3152.7788 | AE120: 3156.831 | AF120: 3160.8832 | AG120: 3164.9355 | AH120: 3168.9877 | AI120: 3173.04 | AJ120: 3177.0922 | AK120: 3181.1444 | AL120: 3185.1967 | AM120: 3189.2489 | AN120: 3193.3012 | AO120: 3197.3534 | AP120: 3201.4057
K121: Utility PV - Class 1 | L121: Conservative | M121: 2978.2985 | N121: 2978.2985 | O121: 2978.2985 | P121: 2978.2985 | Q121: 2978.2985 | R121: 2978.2985 | S121: 2978.2985 | T121: 2978.2985 | U121: 2978.2985 | V121: 2978.2985 | W121: 2978.2985 | X121: 2978.2985 | Y121: 2978.2985 | Z121: 2978.2985 | AA121: 2978.2985 | AB121: 2989.12 | AC121: 2999.9416 | AD121: 3010.7632 | AE121: 3021.5848 | AF121: 3032.4063 | AG121: 3043.2279 | AH121: 3054.0495 | AI121: 3064.871 | AJ121: 3075.6926 | AK121: 3086.5142 | AL121: 3097.3357 | AM121: 3108.1573 | AN121: 3118.9789 | AO121: 3129.8005 | AP121: 3140.622
K122: Utility PV - Class 2 | L122: Advanced | M122: 2881.2938 | N122: 2896.4464 | O122: 2911.599 | P122: 2926.7517 | Q122: 2941.9043 | R122: 2957.057 | S122: 2972.2096 | T122: 2987.3623 | U122: 3002.5149 | V122: 3017.6675 | W122: 3032.8202 | X122: 3047.9728 | Y122: 3063.1255 | Z122: 3078.2781 | AA122: 3093.4307 | AB122: 3102.3386 | AC122: 3111.2465 | AD122: 3120.1544 | AE122: 3129.0623 | AF122: 3137.9702 | AG122: 3146.8781 | AH122: 3155.7859 | AI122: 3164.6938 | AJ122: 3173.6017 | AK122: 3182.5096 | AL122: 3191.4175 | AM122: 3200.3254 | AN122: 3209.2332 | AO122: 3218.1411 | AP122: 3227.049
K123: Utility PV - Class 2 | L123: Moderate | M123: 2881.2938 | N123: 2892.3072 | O123: 2903.3207 | P123: 2914.3342 | Q123: 2925.3477 | R123: 2936.3612 | S123: 2947.3747 | T123: 2958.3881 | U123: 2969.4016 | V123: 2980.4151 | W123: 2991.4286 | X123: 3002.4421 | Y123: 3013.4556 | Z123: 3024.469 | AA123: 3035.4825 | AB123: 3039.3457 | AC123: 3043.209 | AD123: 3047.0722 | AE123: 3050.9354 | AF123: 3054.7986 | AG123: 3058.6618 | AH123: 3062.525 | AI123: 3066.3882 | AJ123: 3070.2515 | AK123: 3074.1147 | AL123: 3077.9779 | AM123: 3081.8411 | AN123: 3085.7043 | AO123: 3089.5675 | AP123: 3093.4307
K124: Utility PV - Class 2 | L124: Conservative | M124: 2881.2938 | N124: 2881.2938 | O124: 2881.2938 | P124: 2881.2938 | Q124: 2881.2938 | R124: 2881.2938 | S124: 2881.2938 | T124: 2881.2938 | U124: 2881.2938 | V124: 2881.2938 | W124: 2881.2938 | X124: 2881.2938 | Y124: 2881.2938 | Z124: 2881.2938 | AA124: 2881.2938 | AB124: 2891.573 | AC124: 2901.8523 | AD124: 2912.1315 | AE124: 2922.4108 | AF124: 2932.69 | AG124: 2942.9693 | AH124: 2953.2485 | AI124: 2963.5278 | AJ124: 2973.807 | AK124: 2984.0863 | AL124: 2994.3655 | AM124: 3004.6448 | AN124: 3014.924 | AO124: 3025.2033 | AP124: 3035.4825
K125: Utility PV - Class 3 | L125: Advanced | M125: 2743.9661 | N125: 2759.6346 | O125: 2775.303 | P125: 2790.9715 | Q125: 2806.6399 | R125: 2822.3084 | S125: 2837.9769 | T125: 2853.6453 | U125: 2869.3138 | V125: 2884.9823 | W125: 2900.6507 | X125: 2916.3192 | Y125: 2931.9876 | Z125: 2947.6561 | AA125: 2963.3246 | AB125: 2970.6524 | AC125: 2977.9802 | AD125: 2985.3081 | AE125: 2992.6359 | AF125: 2999.9637 | AG125: 3007.2916 | AH125: 3014.6194 | AI125: 3021.9472 | AJ125: 3029.275 | AK125: 3036.6029 | AL125: 3043.9307 | AM125: 3051.2585 | AN125: 3058.5864 | AO125: 3065.9142 | AP125: 3073.242
K126: Utility PV - Class 3 | L126: Moderate | M126: 2743.9661 | N126: 2755.3282 | O126: 2766.6903 | P126: 2778.0524 | Q126: 2789.4145 | R126: 2800.7766 | S126: 2812.1387 | T126: 2823.5008 | U126: 2834.8629 | V126: 2846.225 | W126: 2857.5871 | X126: 2868.9493 | Y126: 2880.3114 | Z126: 2891.6735 | AA126: 2903.0356 | AB126: 2907.0548 | AC126: 2911.0741 | AD126: 2915.0934 | AE126: 2919.1126 | AF126: 2923.1319 | AG126: 2927.1512 | AH126: 2931.1704 | AI126: 2935.1897 | AJ126: 2939.209 | AK126: 2943.2282 | AL126: 2947.2475 | AM126: 2951.2668 | AN126: 2955.286 | AO126: 2959.3053 | AP126: 2963.3246
K127: Utility PV - Class 3 | L127: Conservative | M127: 2743.9661 | N127: 2743.9661 | O127: 2743.9661 | P127: 2743.9661 | Q127: 2743.9661 | R127: 2743.9661 | S127: 2743.9661 | T127: 2743.9661 | U127: 2743.9661 | V127: 2743.9661 | W127: 2743.9661 | X127: 2743.9661 | Y127: 2743.9661 | Z127: 2743.9661 | AA127: 2743.9661 | AB127: 2754.5707 | AC127: 2765.1754 | AD127: 2775.78 | AE127: 2786.3846 | AF127: 2796.9892 | AG127: 2807.5939 | AH127: 2818.1985 | AI127: 2828.8031 | AJ127: 2839.4078 | AK127: 2850.0124 | AL127: 2860.617 | AM127: 2871.2217 | AN127: 2881.8263 | AO127: 2892.4309 | AP127: 2903.0356
K128: Utility PV - Class 4 | L128: Advanced | M128: 2612.4303 | N128: 2628.3023 | O128: 2644.1743 | P128: 2660.0462 | Q128: 2675.9182 | R128: 2691.7902 | S128: 2707.6621 | T128: 2723.5341 | U128: 2739.4061 | V128: 2755.278 | W128: 2771.15 | X128: 2787.022 | Y128: 2802.894 | Z128: 2818.7659 | AA128: 2834.6379 | AB128: 2840.7235 | AC128: 2846.8091 | AD128: 2852.8947 | AE128: 2858.9803 | AF128: 2865.0659 | AG128: 2871.1515 | AH128: 2877.2371 | AI128: 2883.3227 | AJ128: 2889.4083 | AK128: 2895.4939 | AL128: 2901.5795 | AM128: 2907.6651 | AN128: 2913.7507 | AO128: 2919.8363 | AP128: 2925.9219
K129: Utility PV - Class 4 | L129: Moderate | M129: 2612.4303 | N129: 2623.9103 | O129: 2635.3904 | P129: 2646.8704 | Q129: 2658.3504 | R129: 2669.8305 | S129: 2681.3105 | T129: 2692.7905 | U129: 2704.2706 | V129: 2715.7506 | W129: 2727.2306 | X129: 2738.7106 | Y129: 2750.1907 | Z129: 2761.6707 | AA129: 2773.1507 | AB129: 2777.2499 | AC129: 2781.349 | AD129: 2785.4482 | AE129: 2789.5473 | AF129: 2793.6465 | AG129: 2797.7456 | AH129: 2801.8447 | AI129: 2805.9439 | AJ129: 2810.043 | AK129: 2814.1422 | AL129: 2818.2413 | AM129: 2822.3405 | AN129: 2826.4396 | AO129: 2830.5388 | AP129: 2834.6379
K130: Utility PV - Class 4 | L130: Conservative | M130: 2612.4303 | N130: 2612.4303 | O130: 2612.4303 | P130: 2612.4303 | Q130: 2612.4303 | R130: 2612.4303 | S130: 2612.4303 | T130: 2612.4303 | U130: 2612.4303 | V130: 2612.4303 | W130: 2612.4303 | X130: 2612.4303 | Y130: 2612.4303 | Z130: 2612.4303 | AA130: 2612.4303 | AB130: 2623.145 | AC130: 2633.8597 | AD130: 2644.5744 | AE130: 2655.2891 | AF130: 2666.0038 | AG130: 2676.7185 | AH130: 2687.4332 | AI130: 2698.1479 | AJ130: 2708.8626 | AK130: 2719.5773 | AL130: 2730.292 | AM130: 2741.0067 | AN130: 2751.7213 | AO130: 2762.436 | AP130: 2773.1507
K131: Utility PV - Class 5 | L131: Advanced | M131: 2481.5034 | N131: 2497.1753 | O131: 2512.8472 | P131: 2528.5191 | Q131: 2544.191 | R131: 2559.8629 | S131: 2575.5348 | T131: 2591.2067 | U131: 2606.8786 | V131: 2622.5505 | W131: 2638.2224 | X131: 2653.8943 | Y131: 2669.5662 | Z131: 2685.2381 | AA131: 2700.91 | AB131: 2706.1349 | AC131: 2711.3598 | AD131: 2716.5847 | AE131: 2721.8097 | AF131: 2727.0346 | AG131: 2732.2595 | AH131: 2737.4844 | AI131: 2742.7093 | AJ131: 2747.9342 | AK131: 2753.1592 | AL131: 2758.3841 | AM131: 2763.609 | AN131: 2768.8339 | AO131: 2774.0588 | AP131: 2779.2838
... K148: Utility PV - Class 10 | L148: Conservative | M148: 1872.2432 | N148: 1872.2432 | O148: 1872.2432 | P148: 1872.2432 | Q148: 1872.2432 | R148: 1872.2432 | S148: 1872.2432 | T148: 1872.2432 | U148: 1872.2432 | V148: 1872.2432 | W148: 1872.2432 | X148: 1872.2432 | Y148: 1872.2432 | Z148: 1872.2432 | AA148: 1872.2432 | AB148: 1881.3209 | AC148: 1890.3986 | AD148: 1899.4763 | AE148: 1908.554 | AF148: 1917.6317 | AG148: 1926.7094 | AH148: 1935.7871 | AI148: 1944.8648 | AJ148: 1953.9425 | AK148: 1963.0202 | AL148: 1972.0979 | AM148: 1981.1756 | AN148: 1990.2533 | AO148: 1999.331 | AP148: 2008.4087
M150: 2021 | N150: 2022 | O150: 2023 | P150: 2024 | Q150: 2025 | R150: 2026 | S150: 2027 | T150: 2028 | U150: 2029 | V150: 2030 | W150: 2031 | X150: 2032 | Y150: 2033 | Z150: 2034 | AA150: 2035 | AB150: 2036 | AC150: 2037 | AD150: 2038 | AE150: 2039 | AF150: 2040 | AG150: 2041 | AH150: 2042 | AI150: 2043 | AJ150: 2044 | AK150: 2045 | AL150: 2046 | AM150: 2047 | AN150: 2048 | AO150: 2049 | AP150: 2050
J151: CAPEX ($/kW) | K151: Utility PV - Class 1 | L151: Advanced | M151: 1290.8063 | N151: 1373.1982 | O151: 1316.219 | P151: 1259.2399 | Q151: 1202.2608 | R151: 1145.2817 | S151: 1088.3025 | T151: 1031.3234 | U151: 974.34429 | V151: 917.36516 | W151: 860.38604 | X151: 803.40692 | Y151: 746.42779 | Z151: 689.44867 | AA151: 632.46954 | AB151: 625.04006 | AC151: 617.61057 | AD151: 610.18108 | AE151: 602.75159 | AF151: 595.32211 | AG151: 587.89262 | AH151: 580.46313 | AI151: 573.03365 | AJ151: 565.60416 | AK151: 558.17467 | AL151: 550.74518 | AM151: 543.3157 | AN151: 535.88621 | AO151: 528.45672 | AP151: 521.02724
K152: Utility PV - Class 1 | L152: Moderate | M152: 1290.8063 | N152: 1373.1982 | O152: 1331.3528 | P152: 1289.5074 | Q152: 1247.662 | R152: 1205.8167 | S152: 1163.9713 | T152: 1122.1259 | U152: 1080.2806 | V152: 1038.4352 | W152: 996.58982 | X152: 954.74445 | Y152: 912.89908 | Z152: 871.05371 | AA152: 829.20834 | AB152: 816.09242 | AC152: 802.9765 | AD152: 789.86058 | AE152: 776.74466 | AF152: 763.62874 | AG152: 750.51282 | AH152: 737.3969 | AI152: 724.28098 | AJ152: 711.16506 | AK152: 698.04914 | AL152: 684.93322 | AM152: 671.8173 | AN152: 658.70138 | AO152: 645.58546 | AP152: 632.46954
K153: Utility PV - Class 1 | L153: Conservative | M153: 1290.8063 | N153: 1373.1982 | O153: 1352.2929 | P153: 1331.3877 | Q153: 1310.4824 | R153: 1289.5772 | S153: 1268.672 | T153: 1247.7667 | U153: 1226.8615 | V153: 1205.9562 | W153: 1185.051 | X153: 1164.1458 | Y153: 1143.2405 | Z153: 1122.3353 | AA153: 1101.43 | AB153: 1083.2819 | AC153: 1065.1338 | AD153: 1046.9857 | AE153: 1028.8376 | AF153: 1010.6895 | AG153: 992.54136 | AH153: 974.39325 | AI153: 956.24514 | AJ153: 938.09702 | AK153: 919.94891 | AL153: 901.8008 | AM153: 883.65268 | AN153: 865.50457 | AO153: 847.35646 | AP153: 829.20834
K154: Utility PV - Class 2 | L154: Advanced | M154: 1290.8063 | N154: 1373.1982 | O154: 1316.219 | P154: 1259.2399 | Q154: 1202.2608 | R154: 1145.2817 | S154: 1088.3025 | T154: 1031.3234 | U154: 974.34429 | V154: 917.36516 | W154: 860.38604 | X154: 803.40692 | Y154: 746.42779 | Z154: 689.44867 | AA154: 632.46954 | AB154: 625.04006 | AC154: 617.61057 | AD154: 610.18108 | AE154: 602.75159 | AF154: 595.32211 | AG154: 587.89262 | AH154: 580.46313 | AI154: 573.03365 | AJ154: 565.60416 | AK154: 558.17467 | AL154: 550.74518 | AM154: 543.3157 | AN154: 535.88621 | AO154: 528.45672 | AP154: 521.02724
K155: Utility PV - Class 2 | L155: Moderate | M155: 1290.8063 | N155: 1373.1982 | O155: 1331.3528 | P155: 1289.5074 | Q155: 1247.662 | R155: 1205.8167 | S155: 1163.9713 | T155: 1122.1259 | U155: 1080.2806 | V155: 1038.4352 | W155: 996.58982 | X155: 954.74445 | Y155: 912.89908 | Z155: 871.05371 | AA155: 829.20834 | AB155: 816.09242 | AC155: 802.9765 | AD155: 789.86058 | AE155: 776.74466 | AF155: 763.62874 | AG155: 750.51282 | AH155: 737.3969 | AI155: 724.28098 | AJ155: 711.16506 | AK155: 698.04914 | AL155: 684.93322 | AM155: 671.8173 | AN155: 658.70138 | AO155: 645.58546 | AP155: 632.46954
K156: Utility PV - Class 2 | L156: Conservative | M156: 1290.8063 | N156: 1373.1982 | O156: 1352.2929 | P156: 1331.3877 | Q156: 1310.4824 | R156: 1289.5772 | S156: 1268.672 | T156: 1247.7667 | U156: 1226.8615 | V156: 1205.9562 | W156: 1185.051 | X156: 1164.1458 | Y156: 1143.2405 | Z156: 1122.3353 | AA156: 1101.43 | AB156: 1083.2819 | AC156: 1065.1338 | AD156: 1046.9857 | AE156: 1028.8376 | AF156: 1010.6895 | AG156: 992.54136 | AH156: 974.39325 | AI156: 956.24514 | AJ156: 938.09702 | AK156: 919.94891 | AL156: 901.8008 | AM156: 883.65268 | AN156: 865.50457 | AO156: 847.35646 | AP156: 829.20834
K157: Utility PV - Class 3 | L157: Advanced | M157: 1290.8063 | N157: 1373.1982 | O157: 1316.219 | P157: 1259.2399 | Q157: 1202.2608 | R157: 1145.2817 | S157: 1088.3025 | T157: 1031.3234 | U157: 974.34429 | V157: 917.36516 | W157: 860.38604 | X157: 803.40692 | Y157: 746.42779 | Z157: 689.44867 | AA157: 632.46954 | AB157: 625.04006 | AC157: 617.61057 | AD157: 610.18108 | AE157: 602.75159 | AF157: 595.32211 | AG157: 587.89262 | AH157: 580.46313 | AI157: 573.03365 | AJ157: 565.60416 | AK157: 558.17467 | AL157: 550.74518 | AM157: 543.3157 | AN157: 535.88621 | AO157: 528.45672 | AP157: 521.02724
K158: Utility PV - Class 3 | L158: Moderate | M158: 1290.8063 | N158: 1373.1982 | O158: 1331.3528 | P158: 1289.5074 | Q158: 1247.662 | R158: 1205.8167 | S158: 1163.9713 | T158: 1122.1259 | U158: 1080.2806 | V158: 1038.4352 | W158: 996.58982 | X158: 954.74445 | Y158: 912.89908 | Z158: 871.05371 | AA158: 829.20834 | AB158: 816.09242 | AC158: 802.9765 | AD158: 789.86058 | AE158: 776.74466 | AF158: 763.62874 | AG158: 750.51282 | AH158: 737.3969 | AI158: 724.28098 | AJ158: 711.16506 | AK158: 698.04914 | AL158: 684.93322 | AM158: 671.8173 | AN158: 658.70138 | AO158: 645.58546 | AP158: 632.46954
K159: Utility PV - Class 3 | L159: Conservative | M159: 1290.8063 | N159: 1373.1982 | O159: 1352.2929 | P159: 1331.3877 | Q159: 1310.4824 | R159: 1289.5772 | S159: 1268.672 | T159: 1247.7667 | U159: 1226.8615 | V159: 1205.9562 | W159: 1185.051 | X159: 1164.1458 | Y159: 1143.2405 | Z159: 1122.3353 | AA159: 1101.43 | AB159: 1083.2819 | AC159: 1065.1338 | AD159: 1046.9857 | AE159: 1028.8376 | AF159: 1010.6895 | AG159: 992.54136 | AH159: 974.39325 | AI159: 956.24514 | AJ159: 938.09702 | AK159: 919.94891 | AL159: 901.8008 | AM159: 883.65268 | AN159: 865.50457 | AO159: 847.35646 | AP159: 829.20834
K160: Utility PV - Class 4 | L160: Advanced | M160: 1290.8063 | N160: 1373.1982 | O160: 1316.219 | P160: 1259.2399 | Q160: 1202.2608 | R160: 1145.2817 | S160: 1088.3025 | T160: 1031.3234 | U160: 974.34429 | V160: 917.36516 | W160: 860.38604 | X160: 803.40692 | Y160: 746.42779 | Z160: 689.44867 | AA160: 632.46954 | AB160: 625.04006 | AC160: 617.61057 | AD160: 610.18108 | AE160: 602.75159 | AF160: 595.32211 | AG160: 587.89262 | AH160: 580.46313 | AI160: 573.03365 | AJ160: 565.60416 | AK160: 558.17467 | AL160: 550.74518 | AM160: 543.3157 | AN160: 535.88621 | AO160: 528.45672 | AP160: 521.02724
K161: Utility PV - Class 4 | L161: Moderate | M161: 1290.8063 | N161: 1373.1982 | O161: 1331.3528 | P161: 1289.5074 | Q161: 1247.662 | R161: 1205.8167 | S161: 1163.9713 | T161: 1122.1259 | U161: 1080.2806 | V161: 1038.4352 | W161: 996.58982 | X161: 954.74445 | Y161: 912.89908 | Z161: 871.05371 | AA161: 829.20834 | AB161: 816.09242 | AC161: 802.9765 | AD161: 789.86058 | AE161: 776.74466 | AF161: 763.62874 | AG161: 750.51282 | AH161: 737.3969 | AI161: 724.28098 | AJ161: 711.16506 | AK161: 698.04914 | AL161: 684.93322 | AM161: 671.8173 | AN161: 658.70138 | AO161: 645.58546 | AP161: 632.46954
K162: Utility PV - Class 4 | L162: Conservative | M162: 1290.8063 | N162: 1373.1982 | O162: 1352.2929 | P162: 1331.3877 | Q162: 1310.4824 | R162: 1289.5772 | S162: 1268.672 | T162: 1247.7667 | U162: 1226.8615 | V162: 1205.9562 | W162: 1185.051 | X162: 1164.1458 | Y162: 1143.2405 | Z162: 1122.3353 | AA162: 1101.43 | AB162: 1083.2819 | AC162: 1065.1338 | AD162: 1046.9857 | AE162: 1028.8376 | AF162: 1010.6895 | AG162: 992.54136 | AH162: 974.39325 | AI162: 956.24514 | AJ162: 938.09702 | AK162: 919.94891 | AL162: 901.8008 | AM162: 883.65268 | AN162: 865.50457 | AO162: 847.35646 | AP162: 829.20834
K163: Utility PV - Class 5 | L163: Advanced | M163: 1290.8063 | N163: 1373.1982 | O163: 1316.219 | P163: 1259.2399 | Q163: 1202.2608 | R163: 1145.2817 | S163: 1088.3025 | T163: 1031.3234 | U163: 974.34429 | V163: 917.36516 | W163: 860.38604 | X163: 803.40692 | Y163: 746.42779 | Z163: 689.44867 | AA163: 632.46954 | AB163: 625.04006 | AC163: 617.61057 | AD163: 610.18108 | AE163: 602.75159 | AF163: 595.32211 | AG163: 587.89262 | AH163: 580.46313 | AI163: 573.03365 | AJ163: 565.60416 | AK163: 558.17467 | AL163: 550.74518 | AM163: 543.3157 | AN163: 535.88621 | AO163: 528.45672 | AP163: 521.02724
... K180: Utility PV - Class 10 | L180: Conservative | M180: 1290.8063 | N180: 1373.1982 | O180: 1352.2929 | P180: 1331.3877 | Q180: 1310.4824 | R180: 1289.5772 | S180: 1268.672 | T180: 1247.7667 | U180: 1226.8615 | V180: 1205.9562 | W180: 1185.051 | X180: 1164.1458 | Y180: 1143.2405 | Z180: 1122.3353 | AA180: 1101.43 | AB180: 1083.2819 | AC180: 1065.1338 | AD180: 1046.9857 | AE180: 1028.8376 | AF180: 1010.6895 | AG180: 992.54136 | AH180: 974.39325 | AI180: 956.24514 | AJ180: 938.09702 | AK180: 919.94891 | AL180: 901.8008 | AM180: 883.65268 | AN180: 865.50457 | AO180: 847.35646 | AP180: 829.20834
M182: 2021 | N182: 2022 | O182: 2023 | P182: 2024 | Q182: 2025 | R182: 2026 | S182: 2027 | T182: 2028 | U182: 2029 | V182: 2030 | W182: 2031 | X182: 2032 | Y182: 2033 | Z182: 2034 | AA182: 2035 | AB182: 2036 | AC182: 2037 | AD182: 2038 | AE182: 2039 | AF182: 2040 | AG182: 2041 | AH182: 2042 | AI182: 2043 | AJ182: 2044 | AK182: 2045 | AL182: 2046 | AM182: 2047 | AN182: 2048 | AO182: 2049 | AP182: 2050
J183: Construction Financing Cost ($/kW) | K183: Utility PV - Class 1 | L183: Advanced | M183: 44.991186 | N183: 47.862964 | O183: 45.87695 | P183: 43.890937 | Q183: 41.904924 | R183: 39.918911 | S183: 37.932897 | T183: 35.946884 | U183: 33.960871 | V183: 31.974858 | W183: 29.988844 | X183: 28.002831 | Y183: 26.016818 | Z183: 24.030805 | AA183: 22.044791 | AB183: 21.785836 | AC183: 21.52688 | AD183: 21.267925 | AE183: 21.008969 | AF183: 20.750014 | AG183: 20.491058 | AH183: 20.232102 | AI183: 19.973147 | AJ183: 19.714191 | AK183: 19.455236 | AL183: 19.19628 | AM183: 18.937325 | AN183: 18.678369 | AO183: 18.419414 | AP183: 18.160458
...

Sheet Land-Based Wind
A1: Land-Based Wind | M1: https://atb.nrel.gov/electricity/2023/land-based_wind
U2: Inputs
U3: Calculated
U4: Input from other tab
B7: X | G7: Assumptions
H9: Technology | J9: Base Year: | M9: 2021
J10: All values are given in 2021 U.S. dollars, see references at the bottom of this worksheet for dollar year conversions where source dollar years don't match 2021.
J11: Land-Based Wind Classes
J13: Technology Classification | K13: Name | L13: Tech | M13: Resource | N13: Scale | O13: Maturity | P13: Wind Classes | Q13: Wind Speed Range (m/s) | R13: Weighted Average Wind Speed (m/s)
K14: Land-Based Wind - Class 1 - Technology 1 | L14: Wind Turbine Technology 1 | M14: Class1 | N14: Utility | O14: Y | P14: Class1 | Q14: > 9.0 | R14: 9.5
K15: Land-Based Wind - Class 2 - Technology 1 | L15: Wind Turbine Technology 1 | M15: Class2 | N15: Utility | O15: Y | P15: Class2 | Q15: 8.8 - 9.0 | R15: 8.9
K16: Land-Based Wind - Class 3 - Technology 1 | L16: Wind Turbine Technology 1 | M16: Class3 | N16: Utility | O16: Y | P16: Class3 | Q16: 8.6 - 8.8 | R16: 8.7
K17: Land-Based Wind - Class 4 - Technology 1 | L17: Wind Turbine Technology 1 | M17: Class4 | N17: Utility | O17: Y | P17: Class4 | Q17: 8.4 - 8.6 | R17: 8.5
K18: Land-Based Wind - Class 5 - Technology 1 | L18: Wind Turbine Technology 1 | M18: Class5 | N18: Utility | O18: Y | P18: Class5 | Q18: 8.1 - 8.4 | R18: 8.2
K19: Land-Based Wind - Class 6 - Technology 1 | L19: Wind Turbine Technology 1 | M19: Class6 | N19: Utility | O19: Y | P19: Class6 | Q19: 7.6 - 8.1 | R19: 7.8
K20: Land-Based Wind - Class 7 - Technology 1 | L20: Wind Turbine Technology 1 | M20: Class7 | N20: Utility | O20: Y | P20: Class7 | Q20: 7.1 - 7.6 | R20: 7.4
K21: Land-Based Wind - Class 8 - Technology 2 | L21: Wind Turbine Technology 2 | M21: Class8 | N21: Utility | O21: Y | P21: Class8 | Q21: 6.5 - 7.1 | R21: 6.8
K22: Land-Based Wind - Class 9 - Technology 3 | L22: Wind Turbine Technology 3 | M22: Class9 | N22: Utility | O22: Y | P22: Class9 | Q22: 5.9 - 6.5 | R22: 6.2
K23: Land-Based Wind - Class 10 - Technology 4 | L23: Wind Turbine Technology 4 | M23: Class10 | N23: Utility | O23: Y | P23: Class10 | Q23: 1.7 - 5.9 | R23: 5.2
P25: Wind speeds presented in table are assumed to be 110 meters above the surface
Q27: Financial Case | S27: Market
H28: Finance | J28: Financial Assumptions: | Q28: Capital Recovery Period | S28: 20
J29: Capital Recovery Period (Years) | O29: 20
J30: Depreciation Period | O30: 5
J31: Equity Premium During Construction | O31: 0.02
J32: Construction Duration yrs | O32: 3
J33: Year | K33: Capital | L33: Percent of Leverage During Construction | M33: Percent of Equity During Construction
J34: Index | K34: Fraction
J35: 0 | K35: 0.8 | L35: 0.8 | M35: 0.2
J36: 1 | K36: 0.1 | L36: 0.8 | M36: 0.2
J37: 2 | K37: 0.1 | L37: 0.8 | M37: 0.2
M40: 2021 | N40: 2022 | O40: 2023 | P40: 2024 | Q40: 2025 | R40: 2026 | S40: 2027 | T40: 2028 | U40: 2029 | V40: 2030 | W40: 2031 | X40: 2032 | Y40: 2033 | Z40: 2034 | AA40: 2035 | AB40: 2036 | AC40: 2037 | AD40: 2038 | AE40: 2039 | AF40: 2040 | AG40: 2041 | AH40: 2042 | AI40: 2043 | AJ40: 2044 | AK40: 2045 | AL40: 2046 | AM40: 2047 | AN40: 2048 | AO40: 2049 | AP40: 2050
J41: Assumptions | K41: Inflation Rate | L41: * | M41: 0.0279 | N41: 0.0272 | O41: 0.0253 | P41: 0.025 | Q41: 0.025 | R41: 0.025 | S41: 0.025 | T41: 0.025 | U41: 0.025 | V41: 0.025 | W41: 0.025 | X41: 0.025 | Y41: 0.025 | Z41: 0.025 | AA41: 0.025 | AB41: 0.025 | AC41: 0.025 | AD41: 0.025 | AE41: 0.025 | AF41: 0.025 | AG41: 0.025 | AH41: 0.025 | AI41: 0.025 | AJ41: 0.025 | AK41: 0.025 | AL41: 0.025 | AM41: 0.025 | AN41: 0.025 | AO41: 0.025 | AP41: 0.025
K42: Interest Rate Nominal | L42: Advanced | M42: 0.07 | N42: 0.07 | O42: 0.07 | P42: 0.07 | Q42: 0.07 | R42: 0.07 | S42: 0.07 | T42: 0.07 | U42: 0.07 | V42: 0.07 | W42: 0.07 | X42: 0.07 | Y42: 0.07 | Z42: 0.07 | AA42: 0.07 | AB42: 0.07 | AC42: 0.07 | AD42: 0.07 | AE42: 0.07 | AF42: 0.07 | AG42: 0.07 | AH42: 0.07 | AI42: 0.07 | AJ42: 0.07 | AK42: 0.07 | AL42: 0.07 | AM42: 0.07 | AN42: 0.07 | AO42: 0.07 | AP42: 0.07
K43: Interest Rate Nominal | L43: Moderate | M43: 0.07 | N43: 0.07 | O43: 0.07 | P43: 0.07 | Q43: 0.07 | R43: 0.07 | S43: 0.07 | T43: 0.07 | U43: 0.07 | V43: 0.07 | W43: 0.07 | X43: 0.07 | Y43: 0.07 | Z43: 0.07 | AA43: 0.07 | AB43: 0.07 | AC43: 0.07 | AD43: 0.07 | AE43: 0.07 | AF43: 0.07 | AG43: 0.07 | AH43: 0.07 | AI43: 0.07 | AJ43: 0.07 | AK43: 0.07 | AL43: 0.07 | AM43: 0.07 | AN43: 0.07 | AO43: 0.07 | AP43: 0.07
K44: Interest Rate Nominal | L44: Conservative | M44: 0.07 | N44: 0.07 | O44: 0.07 | P44: 0.07 | Q44: 0.07 | R44: 0.07 | S44: 0.07 | T44: 0.07 | U44: 0.07 | V44: 0.07 | W44: 0.07 | X44: 0.07 | Y44: 0.07 | Z44: 0.07 | AA44: 0.07 | AB44: 0.07 | AC44: 0.07 | AD44: 0.07 | AE44: 0.07 | AF44: 0.07 | AG44: 0.07 | AH44: 0.07 | AI44: 0.07 | AJ44: 0.07 | AK44: 0.07 | AL44: 0.07 | AM44: 0.07 | AN44: 0.07 | AO44: 0.07 | AP44: 0.07
K45: Calculated Interest Rate Real | L45: Advanced | M45: 0.040957292 | N45: 0.041666667 | O45: 0.043596996 | P45: 0.043902439 | Q45: 0.043902439 | R45: 0.043902439 | S45: 0.043902439 | T45: 0.043902439 | U45: 0.043902439 | V45: 0.043902439 | W45: 0.043902439 | X45: 0.043902439 | Y45: 0.043902439 | Z45: 0.043902439 | AA45: 0.043902439 | AB45: 0.043902439 | AC45: 0.043902439 | AD45: 0.043902439 | AE45: 0.043902439 | AF45: 0.043902439 | AG45: 0.043902439 | AH45: 0.043902439 | AI45: 0.043902439 | AJ45: 0.043902439 | AK45: 0.043902439 | AL45: 0.043902439 | AM45: 0.043902439 | AN45: 0.043902439 | AO45: 0.043902439 | AP45: 0.043902439
K46: Calculated Interest Rate Real | L46: Moderate | M46: 0.040957292 | N46: 0.041666667 | O46: 0.043596996 | P46: 0.043902439 | Q46: 0.043902439 | R46: 0.043902439 | S46: 0.043902439 | T46: 0.043902439 | U46: 0.043902439 | V46: 0.043902439 | W46: 0.043902439 | X46: 0.043902439 | Y46: 0.043902439 | Z46: 0.043902439 | AA46: 0.043902439 | AB46: 0.043902439 | AC46: 0.043902439 | AD46: 0.043902439 | AE46: 0.043902439 | AF46: 0.043902439 | AG46: 0.043902439 | AH46: 0.043902439 | AI46: 0.043902439 | AJ46: 0.043902439 | AK46: 0.043902439 | AL46: 0.043902439 | AM46: 0.043902439 | AN46: 0.043902439 | AO46: 0.043902439 | AP46: 0.043902439
K47: Calculated Interest Rate Real | L47: Conservative | M47: 0.040957292 | N47: 0.041666667 | O47: 0.043596996 | P47: 0.043902439 | Q47: 0.043902439 | R47: 0.043902439 | S47: 0.043902439 | T47: 0.043902439 | U47: 0.043902439 | V47: 0.043902439 | W47: 0.043902439 | X47: 0.043902439 | Y47: 0.043902439 | Z47: 0.043902439 | AA47: 0.043902439 | AB47: 0.043902439 | AC47: 0.043902439 | AD47: 0.043902439 | AE47: 0.043902439 | AF47: 0.043902439 | AG47: 0.043902439 | AH47: 0.043902439 | AI47: 0.043902439 | AJ47: 0.043902439 | AK47: 0.043902439 | AL47: 0.043902439 | AM47: 0.043902439 | AN47: 0.043902439 | AO47: 0.043902439 | AP47: 0.043902439
K48: Interest During Construction - Nominal | L48: * | M48: 0.065 | N48: 0.065 | O48: 0.065 | P48: 0.065 | Q48: 0.065 | R48: 0.065 | S48: 0.065 | T48: 0.065 | U48: 0.065 | V48: 0.065 | W48: 0.065 | X48: 0.065 | Y48: 0.065 | Z48: 0.065 | AA48: 0.065 | AB48: 0.065 | AC48: 0.065 | AD48: 0.065 | AE48: 0.065 | AF48: 0.065 | AG48: 0.065 | AH48: 0.065 | AI48: 0.065 | AJ48: 0.065 | AK48: 0.065 | AL48: 0.065 | AM48: 0.065 | AN48: 0.065 | AO48: 0.065 | AP48: 0.065
K49: Rate of Return on Equity Nominal | L49: Advanced | M49: 0.1 | N49: 0.1 | O49: 0.1 | P49: 0.1 | Q49: 0.1 | R49: 0.1 | S49: 0.1 | T49: 0.1 | U49: 0.1 | V49: 0.1 | W49: 0.1 | X49: 0.1 | Y49: 0.1 | Z49: 0.1 | AA49: 0.1 | AB49: 0.1 | AC49: 0.1 | AD49: 0.1 | AE49: 0.1 | AF49: 0.1 | AG49: 0.1 | AH49: 0.1 | AI49: 0.1 | AJ49: 0.1 | AK49: 0.1 | AL49: 0.1 | AM49: 0.1 | AN49: 0.1 | AO49: 0.1 | AP49: 0.1
K50: Rate of Return on Equity Nominal | L50: Moderate | M50: 0.1 | N50: 0.1 | O50: 0.1 | P50: 0.1 | Q50: 0.1 | R50: 0.1 | S50: 0.1 | T50: 0.1 | U50: 0.1 | V50: 0.1 | W50: 0.1 | X50: 0.1 | Y50: 0.1 | Z50: 0.1 | AA50: 0.1 | AB50: 0.1 | AC50: 0.1 | AD50: 0.1 | AE50: 0.1 | AF50: 0.1 | AG50: 0.1 | AH50: 0.1 | AI50: 0.1 | AJ50: 0.1 | AK50: 0.1 | AL50: 0.1 | AM50: 0.1 | AN50: 0.1 | AO50: 0.1 | AP50: 0.1
K51: Rate of Return on Equity Nominal | L51: Conservative | M51: 0.1 | N51: 0.1 | O51: 0.1 | P51: 0.1 | Q51: 0.1 | R51: 0.1 | S51: 0.1 | T51: 0.1 | U51: 0.1 | V51: 0.1 | W51: 0.1 | X51: 0.1 | Y51: 0.1 | Z51: 0.1 | AA51: 0.1 | AB51: 0.1 | AC51: 0.1 | AD51: 0.1 | AE51: 0.1 | AF51: 0.1 | AG51: 0.1 | AH51: 0.1 | AI51: 0.1 | AJ51: 0.1 | AK51: 0.1 | AL51: 0.1 | AM51: 0.1 | AN51: 0.1 | AO51: 0.1 | AP51: 0.1
K52: Calculated Rate of Return on Equity Real | L52: Advanced | M52: 0.07014301 | N52: 0.070872274 | O52: 0.072856725 | P52: 0.073170732 | Q52: 0.073170732 | R52: 0.073170732 | S52: 0.073170732 | T52: 0.073170732 | U52: 0.073170732 | V52: 0.073170732 | W52: 0.073170732 | X52: 0.073170732 | Y52: 0.073170732 | Z52: 0.073170732 | AA52: 0.073170732 | AB52: 0.073170732 | AC52: 0.073170732 | AD52: 0.073170732 | AE52: 0.073170732 | AF52: 0.073170732 | AG52: 0.073170732 | AH52: 0.073170732 | AI52: 0.073170732 | AJ52: 0.073170732 | AK52: 0.073170732 | AL52: 0.073170732 | AM52: 0.073170732 | AN52: 0.073170732 | AO52: 0.073170732 | AP52: 0.073170732
K53: Calculated Rate of Return on Equity Real | L53: Moderate | M53: 0.07014301 | N53: 0.070872274 | O53: 0.072856725 | P53: 0.073170732 | Q53: 0.073170732 | R53: 0.073170732 | S53: 0.073170732 | T53: 0.073170732 | U53: 0.073170732 | V53: 0.073170732 | W53: 0.073170732 | X53: 0.073170732 | Y53: 0.073170732 | Z53: 0.073170732 | AA53: 0.073170732 | AB53: 0.073170732 | AC53: 0.073170732 | AD53: 0.073170732 | AE53: 0.073170732 | AF53: 0.073170732 | AG53: 0.073170732 | AH53: 0.073170732 | AI53: 0.073170732 | AJ53: 0.073170732 | AK53: 0.073170732 | AL53: 0.073170732 | AM53: 0.073170732 | AN53: 0.073170732 | AO53: 0.073170732 | AP53: 0.073170732
... K70: Capital Recovery Factor (CRF) Real | L70: Conservative | M70: 0.078798319 | N70: 0.08078028 | O70: 0.082682548 | P70: 0.083941635 | Q70: 0.084190851 | R70: 0.084448111 | S70: 0.084713809 | T70: 0.084988365 | U70: 0.085272229 | V70: 0.08556588 | W70: 0.085676421 | X70: 0.085788795 | Y70: 0.085903047 | Z70: 0.086019225 | AA70: 0.086137377 | AB70: 0.086257555 | AC70: 0.086379811 | AD70: 0.086504198 | AE70: 0.086630774 | AF70: 0.086759595 | AG70: 0.086890723 | AH70: 0.08702422 | AI70: 0.087160149 | AJ70: 0.083846539 | AK70: 0.080531244 | AL70: 0.073360169 | AM70: 0.073360149 | AN70: 0.07336013 | AO70: 0.073360109 | AP70: 0.073360089
D73: X | G73: Future Projections
M74: Base Year
M75: 2021 | N75: 2022 | O75: 2023 | P75: 2024 | Q75: 2025 | R75: 2026 | S75: 2027 | T75: 2028 | U75: 2029 | V75: 2030 | W75: 2031 | X75: 2032 | Y75: 2033 | Z75: 2034 | AA75: 2035 | AB75: 2036 | AC75: 2037 | AD75: 2038 | AE75: 2039 | AF75: 2040 | AG75: 2041 | AH75: 2042 | AI75: 2043 | AJ75: 2044 | AK75: 2045 | AL75: 2046 | AM75: 2047 | AN75: 2048 | AO75: 2049 | AP75: 2050
H76: Techno-Economic Cost and Performance Parameters | J76: Net Capacity Factor (%) | K76: Land-Based Wind - Class 1 - Technology 1 | L76: Advanced | M76: 0.49815 | N76: 0.50564216 | O76: 0.51317531 | P76: 0.52074944 | Q76: 0.52836457 | R76: 0.53602068 | S76: 0.54371778 | T76: 0.55145586 | U76: 0.55923494 | V76: 0.567055 | W76: 0.56754343 | X76: 0.568032 | Y76: 0.56852071 | Z76: 0.56900957 | AA76: 0.56949858 | AB76: 0.56998773 | AC76: 0.57047702 | AD76: 0.57096646 | AE76: 0.57145604 | AF76: 0.57194577 | AG76: 0.57243563 | AH76: 0.57292565 | AI76: 0.57341581 | AJ76: 0.57390611 | AK76: 0.57439656 | AL76: 0.57488715 | AM76: 0.57537788 | AN76: 0.57586876 | AO76: 0.57635979 | AP76: 0.57685096
K77: Land-Based Wind - Class 1 - Technology 1 | L77: Moderate | M77: 0.49815 | N77: 0.50197667 | O77: 0.50580333 | P77: 0.50963 | Q77: 0.51345667 | R77: 0.51728333 | S77: 0.52111 | T77: 0.52493667 | U77: 0.52876333 | V77: 0.53259 | W77: 0.5330205 | X77: 0.533451 | Y77: 0.5338815 | Z77: 0.534312 | AA77: 0.5347425 | AB77: 0.535173 | AC77: 0.5356035 | AD77: 0.536034 | AE77: 0.5364645 | AF77: 0.536895 | AG77: 0.5373255 | AH77: 0.537756 | AI77: 0.5381865 | AJ77: 0.538617 | AK77: 0.5390475 | AL77: 0.539478 | AM77: 0.5399085 | AN77: 0.540339 | AO77: 0.5407695 | AP77: 0.5412
K78: Land-Based Wind - Class 1 - Technology 1 | L78: Conservative | M78: 0.49815 | N78: 0.49883333 | O78: 0.49951667 | P78: 0.5002 | Q78: 0.50088333 | R78: 0.50156667 | S78: 0.50225 | T78: 0.50293333 | U78: 0.50361667 | V78: 0.5043 | W78: 0.504915 | X78: 0.50553 | Y78: 0.506145 | Z78: 0.50676 | AA78: 0.507375 | AB78: 0.50799 | AC78: 0.508605 | AD78: 0.50922 | AE78: 0.509835 | AF78: 0.51045 | AG78: 0.511065 | AH78: 0.51168 | AI78: 0.512295 | AJ78: 0.51291 | AK78: 0.513525 | AL78: 0.51414 | AM78: 0.514755 | AN78: 0.51537 | AO78: 0.515985 | AP78: 0.5166
K79: Land-Based Wind - Class 2 - Technology 1 | L79: Advanced | M79: 0.46737 | N79: 0.47451172 | O79: 0.48169442 | P79: 0.48891811 | Q79: 0.49618279 | R79: 0.50348846 | S79: 0.51083511 | T79: 0.51822275 | U79: 0.52565138 | V79: 0.533121 | W79: 0.53352478 | X79: 0.53392861 | Y79: 0.53433251 | Z79: 0.53473647 | AA79: 0.53514049 | AB79: 0.53554457 | AC79: 0.53594871 | AD79: 0.53635292 | AE79: 0.53675718 | AF79: 0.53716151 | AG79: 0.53756589 | AH79: 0.53797034 | AI79: 0.53837485 | AJ79: 0.53877942 | AK79: 0.53918405 | AL79: 0.53958875 | AM79: 0.5399935 | AN79: 0.54039832 | AO79: 0.54080319 | AP79: 0.54120813
K80: Land-Based Wind - Class 2 - Technology 1 | L80: Moderate | M80: 0.46737 | N80: 0.47096022 | O80: 0.47455044 | P80: 0.47814067 | Q80: 0.48173089 | R80: 0.48532111 | S80: 0.48891133 | T80: 0.49250156 | U80: 0.49609178 | V80: 0.499682 | W80: 0.5000859 | X80: 0.5004898 | Y80: 0.5008937 | Z80: 0.5012976 | AA80: 0.5017015 | AB80: 0.5021054 | AC80: 0.5025093 | AD80: 0.5029132 | AE80: 0.5033171 | AF80: 0.503721 | AG80: 0.5041249 | AH80: 0.5045288 | AI80: 0.5049327 | AJ80: 0.5053366 | AK80: 0.5057405 | AL80: 0.5061444 | AM80: 0.5065483 | AN80: 0.5069522 | AO80: 0.5073561 | AP80: 0.50776
K81: Land-Based Wind - Class 2 - Technology 1 | L81: Conservative | M81: 0.46737 | N81: 0.46801111 | O81: 0.46865222 | P81: 0.46929333 | Q81: 0.46993444 | R81: 0.47057556 | S81: 0.47121667 | T81: 0.47185778 | U81: 0.47249889 | V81: 0.47314 | W81: 0.473717 | X81: 0.474294 | Y81: 0.474871 | Z81: 0.475448 | AA81: 0.476025 | AB81: 0.476602 | AC81: 0.477179 | AD81: 0.477756 | AE81: 0.478333 | AF81: 0.47891 | AG81: 0.479487 | AH81: 0.480064 | AI81: 0.480641 | AJ81: 0.481218 | AK81: 0.481795 | AL81: 0.482372 | AM81: 0.482949 | AN81: 0.483526 | AO81: 0.484103 | AP81: 0.48468
K82: Land-Based Wind - Class 3 - Technology 1 | L82: Advanced | M82: 0.45684 | N82: 0.46386183 | O82: 0.47092464 | P82: 0.47802844 | Q82: 0.48517323 | R82: 0.49235901 | S82: 0.49958578 | T82: 0.50685353 | U82: 0.51416227 | V82: 0.521512 | W82: 0.52188682 | X82: 0.52226166 | Y82: 0.52263654 | Z82: 0.52301146 | AA82: 0.5233864 | AB82: 0.52376138 | AC82: 0.5241364 | AD82: 0.52451144 | AE82: 0.52488652 | AF82: 0.52526163 | AG82: 0.52563677 | AH82: 0.52601195 | AI82: 0.52638716 | AJ82: 0.5267624 | AK82: 0.52713767 | AL82: 0.52751298 | AM82: 0.52788832 | AN82: 0.52826369 | AO82: 0.5286391 | AP82: 0.52901454
K83: Land-Based Wind - Class 3 - Technology 1 | L83: Moderate | M83: 0.45684 | N83: 0.46034933 | O83: 0.46385867 | P83: 0.467368 | Q83: 0.47087733 | R83: 0.47438667 | S83: 0.477896 | T83: 0.48140533 | U83: 0.48491467 | V83: 0.488424 | W83: 0.4888188 | X83: 0.4892136 | Y83: 0.4896084 | Z83: 0.4900032 | AA83: 0.490398 | AB83: 0.4907928 | AC83: 0.4911876 | AD83: 0.4915824 | AE83: 0.4919772 | AF83: 0.492372 | AG83: 0.4927668 | AH83: 0.4931616 | AI83: 0.4935564 | AJ83: 0.4939512 | AK83: 0.494346 | AL83: 0.4947408 | AM83: 0.4951356 | AN83: 0.4955304 | AO83: 0.4959252 | AP83: 0.49632
K84: Land-Based Wind - Class 3 - Technology 1 | L84: Conservative | M84: 0.45684 | N84: 0.45746667 | O84: 0.45809333 | P84: 0.45872 | Q84: 0.45934667 | R84: 0.45997333 | S84: 0.4606 | T84: 0.46122667 | U84: 0.46185333 | V84: 0.46248 | W84: 0.463044 | X84: 0.463608 | Y84: 0.464172 | Z84: 0.464736 | AA84: 0.4653 | AB84: 0.465864 | AC84: 0.466428 | AD84: 0.466992 | AE84: 0.467556 | AF84: 0.46812 | AG84: 0.468684 | AH84: 0.469248 | AI84: 0.469812 | AJ84: 0.470376 | AK84: 0.47094 | AL84: 0.471504 | AM84: 0.472068 | AN84: 0.472632 | AO84: 0.473196 | AP84: 0.47376
K85: Land-Based Wind - Class 4 - Technology 1 | L85: Advanced | M85: 0.44469 | N85: 0.45157349 | O85: 0.45849798 | P85: 0.46546344 | Q85: 0.4724699 | R85: 0.47951735 | S85: 0.48660578 | T85: 0.4937352 | U85: 0.5009056 | V85: 0.508117 | W85: 0.5084584 | X85: 0.5087998 | Y85: 0.5091412 | Z85: 0.5094826 | AA85: 0.509824 | AB85: 0.5101654 | AC85: 0.5105068 | AD85: 0.5108482 | AE85: 0.5111896 | AF85: 0.511531 | AG85: 0.5118724 | AH85: 0.5122138 | AI85: 0.5125552 | AJ85: 0.5128966 | AK85: 0.513238 | AL85: 0.5135794 | AM85: 0.5139208 | AN85: 0.5142622 | AO85: 0.5146036 | AP85: 0.514945
K86: Land-Based Wind - Class 4 - Technology 1 | L86: Moderate | M86: 0.44469 | N86: 0.448106 | O86: 0.451522 | P86: 0.454938 | Q86: 0.458354 | R86: 0.46177 | S86: 0.465186 | T86: 0.468602 | U86: 0.472018 | V86: 0.475434 | W86: 0.4758183 | X86: 0.4762026 | Y86: 0.4765869 | Z86: 0.4769712 | AA86: 0.4773555 | AB86: 0.4777398 | AC86: 0.4781241 | AD86: 0.4785084 | AE86: 0.4788927 | AF86: 0.479277 | AG86: 0.4796613 | AH86: 0.4800456 | AI86: 0.4804299 | AJ86: 0.4808142 | AK86: 0.4811985 | AL86: 0.4815828 | AM86: 0.4819671 | AN86: 0.4823514 | AO86: 0.4827357 | AP86: 0.48312
K87: Land-Based Wind - Class 4 - Technology 1 | L87: Conservative | M87: 0.44469 | N87: 0.4453 | O87: 0.44591 | P87: 0.44652 | Q87: 0.44713 | R87: 0.44774 | S87: 0.44835 | T87: 0.44896 | U87: 0.44957 | V87: 0.45018 | W87: 0.450729 | X87: 0.451278 | Y87: 0.451827 | Z87: 0.452376 | AA87: 0.452925 | AB87: 0.453474 | AC87: 0.454023 | AD87: 0.454572 | AE87: 0.455121 | AF87: 0.45567 | AG87: 0.456219 | AH87: 0.456768 | AI87: 0.457317 | AJ87: 0.457866 | AK87: 0.458415 | AL87: 0.458964 | AM87: 0.459513 | AN87: 0.460062 | AO87: 0.460611 | AP87: 0.46116
K88: Land-Based Wind - Class 5 - Technology 1 | L88: Advanced | M88: 0.43011 | N88: 0.43682749 | O88: 0.44358598 | P88: 0.45038544 | Q88: 0.4572259 | R88: 0.46410735 | S88: 0.47102978 | T88: 0.4779932 | U88: 0.4849976 | V88: 0.492043 | W88: 0.4923443 | X88: 0.49264556 | Y88: 0.49294679 | Z88: 0.49324797 | AA88: 0.49354911 | AB88: 0.49385022 | AC88: 0.49415129 | AD88: 0.49445231 | AE88: 0.4947533 | AF88: 0.49505425 | AG88: 0.49535515 | AH88: 0.49565602 | AI88: 0.49595685 | AJ88: 0.49625764 | AK88: 0.49655839 | AL88: 0.4968591 | AM88: 0.49715978 | AN88: 0.49746041 | AO88: 0.497761 | AP88: 0.49806156
... K105: Land-Based Wind - Class 10 - Technology 4 | L105: Conservative | M105: 0.25839 | N105: 0.25874444 | O105: 0.25909889 | P105: 0.25945333 | Q105: 0.25980778 | R105: 0.26016222 | S105: 0.26051667 | T105: 0.26087111 | U105: 0.26122556 | V105: 0.26158 | W105: 0.261899 | X105: 0.262218 | Y105: 0.262537 | Z105: 0.262856 | AA105: 0.263175 | AB105: 0.263494 | AC105: 0.263813 | AD105: 0.264132 | AE105: 0.264451 | AF105: 0.26477 | AG105: 0.265089 | AH105: 0.265408 | AI105: 0.265727 | AJ105: 0.266046 | AK105: 0.266365 | AL105: 0.266684 | AM105: 0.267003 | AN105: 0.267322 | AO105: 0.267641 | AP105: 0.26796
M107: 2021 | N107: 2022 | O107: 2023 | P107: 2024 | Q107: 2025 | R107: 2026 | S107: 2027 | T107: 2028 | U107: 2029 | V107: 2030 | W107: 2031 | X107: 2032 | Y107: 2033 | Z107: 2034 | AA107: 2035 | AB107: 2036 | AC107: 2037 | AD107: 2038 | AE107: 2039 | AF107: 2040 | AG107: 2041 | AH107: 2042 | AI107: 2043 | AJ107: 2044 | AK107: 2045 | AL107: 2046 | AM107: 2047 | AN107: 2048 | AO107: 2049 | AP107: 2050
J108: Annual Energy Production (kWh/kW) | K108: Land-Based Wind - Class 1 - Technology 1 | L108: Advanced | M108: 4363.794 | N108: 4429.4253 | O108: 4495.4157 | P108: 4561.7651 | Q108: 4628.4736 | R108: 4695.5411 | S108: 4762.9677 | T108: 4830.7534 | U108: 4898.8981 | V108: 4967.4018 | W108: 4971.6804 | X108: 4975.9603 | Y108: 4980.2415 | Z108: 4984.5239 | AA108: 4988.8076 | AB108: 4993.0925 | AC108: 4997.3787 | AD108: 5001.6662 | AE108: 5005.9549 | AF108: 5010.2449 | AG108: 5014.5362 | AH108: 5018.8287 | AI108: 5023.1225 | AJ108: 5027.4175 | AK108: 5031.7138 | AL108: 5036.0114 | AM108: 5040.3103 | AN108: 5044.6104 | AO108: 5048.9117 | AP108: 5053.2144
K109: Land-Based Wind - Class 1 - Technology 1 | L109: Moderate | M109: 4363.794 | N109: 4397.3156 | O109: 4430.8372 | P109: 4464.3588 | Q109: 4497.8804 | R109: 4531.402 | S109: 4564.9236 | T109: 4598.4452 | U109: 4631.9668 | V109: 4665.4884 | W109: 4669.2596 | X109: 4673.0308 | Y109: 4676.8019 | Z109: 4680.5731 | AA109: 4684.3443 | AB109: 4688.1155 | AC109: 4691.8867 | AD109: 4695.6578 | AE109: 4699.429 | AF109: 4703.2002 | AG109: 4706.9714 | AH109: 4710.7426 | AI109: 4714.5137 | AJ109: 4718.2849 | AK109: 4722.0561 | AL109: 4725.8273 | AM109: 4729.5985 | AN109: 4733.3696 | AO109: 4737.1408 | AP109: 4740.912
K110: Land-Based Wind - Class 1 - Technology 1 | L110: Conservative | M110: 4363.794 | N110: 4369.78 | O110: 4375.766 | P110: 4381.752 | Q110: 4387.738 | R110: 4393.724 | S110: 4399.71 | T110: 4405.696 | U110: 4411.682 | V110: 4417.668 | W110: 4423.0554 | X110: 4428.4428 | Y110: 4433.8302 | Z110: 4439.2176 | AA110: 4444.605 | AB110: 4449.9924 | AC110: 4455.3798 | AD110: 4460.7672 | AE110: 4466.1546 | AF110: 4471.542 | AG110: 4476.9294 | AH110: 4482.3168 | AI110: 4487.7042 | AJ110: 4493.0916 | AK110: 4498.479 | AL110: 4503.8664 | AM110: 4509.2538 | AN110: 4514.6412 | AO110: 4520.0286 | AP110: 4525.416
K111: Land-Based Wind - Class 2 - Technology 1 | L111: Advanced | M111: 4094.1612 | N111: 4156.7226 | O111: 4219.6431 | P111: 4282.9227 | Q111: 4346.5612 | R111: 4410.5589 | S111: 4474.9156 | T111: 4539.6313 | U111: 4604.7061 | V111: 4670.14 | W111: 4673.677 | X111: 4677.2146 | Y111: 4680.7528 | Z111: 4684.2915 | AA111: 4687.8307 | AB111: 4691.3704 | AC111: 4694.9107 | AD111: 4698.4515 | AE111: 4701.9929 | AF111: 4705.5348 | AG111: 4709.0772 | AH111: 4712.6202 | AI111: 4716.1637 | AJ111: 4719.7077 | AK111: 4723.2523 | AL111: 4726.7974 | AM111: 4730.3431 | AN111: 4733.8893 | AO111: 4737.436 | AP111: 4740.9832
K112: Land-Based Wind - Class 2 - Technology 1 | L112: Moderate | M112: 4094.1612 | N112: 4125.6115 | O112: 4157.0619 | P112: 4188.5122 | Q112: 4219.9626 | R112: 4251.4129 | S112: 4282.8633 | T112: 4314.3136 | U112: 4345.764 | V112: 4377.2143 | W112: 4380.7525 | X112: 4384.2906 | Y112: 4387.8288 | Z112: 4391.367 | AA112: 4394.9051 | AB112: 4398.4433 | AC112: 4401.9815 | AD112: 4405.5196 | AE112: 4409.0578 | AF112: 4412.596 | AG112: 4416.1341 | AH112: 4419.6723 | AI112: 4423.2105 | AJ112: 4426.7486 | AK112: 4430.2868 | AL112: 4433.8249 | AM112: 4437.3631 | AN112: 4440.9013 | AO112: 4444.4394 | AP112: 4447.9776
K113: Land-Based Wind - Class 2 - Technology 1 | L113: Conservative | M113: 4094.1612 | N113: 4099.7773 | O113: 4105.3935 | P113: 4111.0096 | Q113: 4116.6257 | R113: 4122.2419 | S113: 4127.858 | T113: 4133.4741 | U113: 4139.0903 | V113: 4144.7064 | W113: 4149.7609 | X113: 4154.8154 | Y113: 4159.87 | Z113: 4164.9245 | AA113: 4169.979 | AB113: 4175.0335 | AC113: 4180.088 | AD113: 4185.1426 | AE113: 4190.1971 | AF113: 4195.2516 | AG113: 4200.3061 | AH113: 4205.3606 | AI113: 4210.4152 | AJ113: 4215.4697 | AK113: 4220.5242 | AL113: 4225.5787 | AM113: 4230.6332 | AN113: 4235.6878 | AO113: 4240.7423 | AP113: 4245.7968
K114: Land-Based Wind - Class 3 - Technology 1 | L114: Advanced | M114: 4001.9184 | N114: 4063.4296 | O114: 4125.2999 | P114: 4187.5292 | Q114: 4250.1175 | R114: 4313.0649 | S114: 4376.3714 | T114: 4440.0369 | U114: 4504.0615 | V114: 4568.4451 | W114: 4571.7285 | X114: 4575.0122 | Y114: 4578.2961 | Z114: 4581.5804 | AA114: 4584.8649 | AB114: 4588.1497 | AC114: 4591.4348 | AD114: 4594.7202 | AE114: 4598.0059 | AF114: 4601.2919 | AG114: 4604.5781 | AH114: 4607.8647 | AI114: 4611.1515 | AJ114: 4614.4386 | AK114: 4617.726 | AL114: 4621.0137 | AM114: 4624.3017 | AN114: 4627.5899 | AO114: 4630.8785 | AP114: 4634.1673
K115: Land-Based Wind - Class 3 - Technology 1 | L115: Moderate | M115: 4001.9184 | N115: 4032.6602 | O115: 4063.4019 | P115: 4094.1437 | Q115: 4124.8854 | R115: 4155.6272 | S115: 4186.369 | T115: 4217.1107 | U115: 4247.8525 | V115: 4278.5942 | W115: 4282.0527 | X115: 4285.5111 | Y115: 4288.9696 | Z115: 4292.428 | AA115: 4295.8865 | AB115: 4299.3449 | AC115: 4302.8034 | AD115: 4306.2618 | AE115: 4309.7203 | AF115: 4313.1787 | AG115: 4316.6372 | AH115: 4320.0956 | AI115: 4323.5541 | AJ115: 4327.0125 | AK115: 4330.471 | AL115: 4333.9294 | AM115: 4337.3879 | AN115: 4340.8463 | AO115: 4344.3048 | AP115: 4347.7632
K116: Land-Based Wind - Class 3 - Technology 1 | L116: Conservative | M116: 4001.9184 | N116: 4007.408 | O116: 4012.8976 | P116: 4018.3872 | Q116: 4023.8768 | R116: 4029.3664 | S116: 4034.856 | T116: 4040.3456 | U116: 4045.8352 | V116: 4051.3248 | W116: 4056.2654 | X116: 4061.2061 | Y116: 4066.1467 | Z116: 4071.0874 | AA116: 4076.028 | AB116: 4080.9686 | AC116: 4085.9093 | AD116: 4090.8499 | AE116: 4095.7906 | AF116: 4100.7312 | AG116: 4105.6718 | AH116: 4110.6125 | AI116: 4115.5531 | AJ116: 4120.4938 | AK116: 4125.4344 | AL116: 4130.375 | AM116: 4135.3157 | AN116: 4140.2563 | AO116: 4145.197 | AP116: 4150.1376
K117: Land-Based Wind - Class 4 - Technology 1 | L117: Advanced | M117: 3895.4844 | N117: 3955.7838 | O117: 4016.4423 | P117: 4077.4598 | Q117: 4138.8363 | R117: 4200.5719 | S117: 4262.6666 | T117: 4325.1203 | U117: 4387.9331 | V117: 4451.1049 | W117: 4454.0956 | X117: 4457.0862 | Y117: 4460.0769 | Z117: 4463.0676 | AA117: 4466.0582 | AB117: 4469.0489 | AC117: 4472.0396 | AD117: 4475.0302 | AE117: 4478.0209 | AF117: 4481.0116 | AG117: 4484.0022 | AH117: 4486.9929 | AI117: 4489.9836 | AJ117: 4492.9742 | AK117: 4495.9649 | AL117: 4498.9555 | AM117: 4501.9462 | AN117: 4504.9369 | AO117: 4507.9275 | AP117: 4510.9182
K118: Land-Based Wind - Class 4 - Technology 1 | L118: Moderate | M118: 3895.4844 | N118: 3925.4086 | O118: 3955.3327 | P118: 3985.2569 | Q118: 4015.181 | R118: 4045.1052 | S118: 4075.0294 | T118: 4104.9535 | U118: 4134.8777 | V118: 4164.8018 | W118: 4168.1683 | X118: 4171.5348 | Y118: 4174.9012 | Z118: 4178.2677 | AA118: 4181.6342 | AB118: 4185.0006 | AC118: 4188.3671 | AD118: 4191.7336 | AE118: 4195.1001 | AF118: 4198.4665 | AG118: 4201.833 | AH118: 4205.1995 | AI118: 4208.5659 | AJ118: 4211.9324 | AK118: 4215.2989 | AL118: 4218.6653 | AM118: 4222.0318 | AN118: 4225.3983 | AO118: 4228.7647 | AP118: 4232.1312
K119: Land-Based Wind - Class 4 - Technology 1 | L119: Conservative | M119: 3895.4844 | N119: 3900.828 | O119: 3906.1716 | P119: 3911.5152 | Q119: 3916.8588 | R119: 3922.2024 | S119: 3927.546 | T119: 3932.8896 | U119: 3938.2332 | V119: 3943.5768 | W119: 3948.386 | X119: 3953.1953 | Y119: 3958.0045 | Z119: 3962.8138 | AA119: 3967.623 | AB119: 3972.4322 | AC119: 3977.2415 | AD119: 3982.0507 | AE119: 3986.86 | AF119: 3991.6692 | AG119: 3996.4784 | AH119: 4001.2877 | AI119: 4006.0969 | AJ119: 4010.9062 | AK119: 4015.7154 | AL119: 4020.5246 | AM119: 4025.3339 | AN119: 4030.1431 | AO119: 4034.9524 | AP119: 4039.7616
K120: Land-Based Wind - Class 5 - Technology 1 | L120: Advanced | M120: 3767.7636 | N120: 3826.6088 | O120: 3885.8131 | P120: 3945.3765 | Q120: 4005.2989 | R120: 4065.5803 | S120: 4126.2209 | T120: 4187.2204 | U120: 4248.579 | V120: 4310.2967 | W120: 4312.9361 | X120: 4315.5751 | Y120: 4318.2139 | Z120: 4320.8522 | AA120: 4323.4902 | AB120: 4326.1279 | AC120: 4328.7653 | AD120: 4331.4022 | AE120: 4334.0389 | AF120: 4336.6752 | AG120: 4339.3111 | AH120: 4341.9468 | AI120: 4344.582 | AJ120: 4347.2169 | AK120: 4349.8515 | AL120: 4352.4858 | AM120: 4355.1196 | AN120: 4357.7532 | AO120: 4360.3864 | AP120: 4363.0192
... K137: Land-Based Wind - Class 10 - Technology 4 | L137: Conservative | M137: 2263.4964 | N137: 2266.6013 | O137: 2269.7063 | P137: 2272.8112 | Q137: 2275.9161 | R137: 2279.0211 | S137: 2282.126 | T137: 2285.2309 | U137: 2288.3359 | V137: 2291.4408 | W137: 2294.2352 | X137: 2297.0297 | Y137: 2299.8241 | Z137: 2302.6186 | AA137: 2305.413 | AB137: 2308.2074 | AC137: 2311.0019 | AD137: 2313.7963 | AE137: 2316.5908 | AF137: 2319.3852 | AG137: 2322.1796 | AH137: 2324.9741 | AI137: 2327.7685 | AJ137: 2330.563 | AK137: 2333.3574 | AL137: 2336.1518 | AM137: 2338.9463 | AN137: 2341.7407 | AO137: 2344.5352 | AP137: 2347.3296
M139: 2021 | N139: 2022 | O139: 2023 | P139: 2024 | Q139: 2025 | R139: 2026 | S139: 2027 | T139: 2028 | U139: 2029 | V139: 2030 | W139: 2031 | X139: 2032 | Y139: 2033 | Z139: 2034 | AA139: 2035 | AB139: 2036 | AC139: 2037 | AD139: 2038 | AE139: 2039 | AF139: 2040 | AG139: 2041 | AH139: 2042 | AI139: 2043 | AJ139: 2044 | AK139: 2045 | AL139: 2046 | AM139: 2047 | AN139: 2048 | AO139: 2049 | AP139: 2050
J140: CAPEX ($/kW) | K140: Land-Based Wind - Class 1 - Technology 1 | L140: Advanced | M140: 1363 | N140: 1533.3167 | O140: 1434.0015 | P140: 1273.9566 | Q140: 1244.2755 | R140: 1214.5944 | S140: 1184.9133 | T140: 1155.2322 | U140: 1125.5511 | V140: 1095.8699 | W140: 1083.5552 | X140: 1071.2404 | Y140: 1058.9257 | Z140: 1046.6109 | AA140: 1034.2961 | AB140: 1021.9814 | AC140: 1009.6666 | AD140: 997.35186 | AE140: 985.0371 | AF140: 972.72234 | AG140: 960.40758 | AH140: 948.09282 | AI140: 935.77806 | AJ140: 923.46331 | AK140: 911.14855 | AL140: 898.83379 | AM140: 886.51903 | AN140: 874.20427 | AO140: 861.88951 | AP140: 849.57475
K141: Land-Based Wind - Class 1 - Technology 1 | L141: Moderate | M141: 1363 | N141: 1540.2333 | O141: 1447.2333 | P141: 1292 | Q141: 1268.3333 | R141: 1244.6667 | S141: 1221 | T141: 1197.3333 | U141: 1173.6667 | V141: 1150 | W141: 1138.6766 | X141: 1127.3532 | Y141: 1116.0298 | Z141: 1104.7064 | AA141: 1093.383 | AB141: 1082.0596 | AC141: 1070.7362 | AD141: 1059.4129 | AE141: 1048.0895 | AF141: 1036.7661 | AG141: 1025.4427 | AH141: 1014.1193 | AI141: 1002.7959 | AJ141: 991.47249 | AK141: 980.1491 | AL141: 968.8257 | AM141: 957.50231 | AN141: 946.17892 | AO141: 934.85552 | AP141: 923.53213
K142: Land-Based Wind - Class 1 - Technology 1 | L142: Conservative | M142: 1363 | N142: 1556.0722 | O142: 1477.5338 | P142: 1333.3189 | Q142: 1323.4252 | R142: 1313.5315 | S142: 1303.6378 | T142: 1293.7441 | U142: 1283.8504 | V142: 1273.9566 | W142: 1265.3665 | X142: 1256.7764 | Y142: 1248.1862 | Z142: 1239.5961 | AA142: 1231.0059 | AB142: 1222.4158 | AC142: 1213.8257 | AD142: 1205.2355 | AE142: 1196.6454 | AF142: 1188.0552 | AG142: 1179.4651 | AH142: 1170.875 | AI142: 1162.2848 | AJ142: 1153.6947 | AK142: 1145.1045 | AL142: 1136.5144 | AM142: 1127.9243 | AN142: 1119.3341 | AO142: 1110.744 | AP142: 1102.1538
K143: Land-Based Wind - Class 2 - Technology 1 | L143: Advanced | M143: 1363 | N143: 1533.3167 | O143: 1434.0015 | P143: 1273.9566 | Q143: 1244.2755 | R143: 1214.5944 | S143: 1184.9133 | T143: 1155.2322 | U143: 1125.5511 | V143: 1095.8699 | W143: 1083.5552 | X143: 1071.2404 | Y143: 1058.9257 | Z143: 1046.6109 | AA143: 1034.2961 | AB143: 1021.9814 | AC143: 1009.6666 | AD143: 997.35186 | AE143: 985.0371 | AF143: 972.72234 | AG143: 960.40758 | AH143: 948.09282 | AI143: 935.77806 | AJ143: 923.46331 | AK143: 911.14855 | AL143: 898.83379 | AM143: 886.51903 | AN143: 874.20427 | AO143: 861.88951 | AP143: 849.57475
K144: Land-Based Wind - Class 2 - Technology 1 | L144: Moderate | M144: 1363 | N144: 1540.2333 | O144: 1447.2333 | P144: 1292 | Q144: 1268.3333 | R144: 1244.6667 | S144: 1221 | T144: 1197.3333 | U144: 1173.6667 | V144: 1150 | W144: 1138.6766 | X144: 1127.3532 | Y144: 1116.0298 | Z144: 1104.7064 | AA144: 1093.383 | AB144: 1082.0596 | AC144: 1070.7362 | AD144: 1059.4129 | AE144: 1048.0895 | AF144: 1036.7661 | AG144: 1025.4427 | AH144: 1014.1193 | AI144: 1002.7959 | AJ144: 991.47249 | AK144: 980.1491 | AL144: 968.8257 | AM144: 957.50231 | AN144: 946.17892 | AO144: 934.85552 | AP144: 923.53213
K145: Land-Based Wind - Class 2 - Technology 1 | L145: Conservative | M145: 1363 | N145: 1556.0722 | O145: 1477.5338 | P145: 1333.3189 | Q145: 1323.4252 | R145: 1313.5315 | S145: 1303.6378 | T145: 1293.7441 | U145: 1283.8504 | V145: 1273.9566 | W145: 1265.3665 | X145: 1256.7764 | Y145: 1248.1862 | Z145: 1239.5961 | AA145: 1231.0059 | AB145: 1222.4158 | AC145: 1213.8257 | AD145: 1205.2355 | AE145: 1196.6454 | AF145: 1188.0552 | AG145: 1179.4651 | AH145: 1170.875 | AI145: 1162.2848 | AJ145: 1153.6947 | AK145: 1145.1045 | AL145: 1136.5144 | AM145: 1127.9243 | AN145: 1119.3341 | AO145: 1110.744 | AP145: 1102.1538
K146: Land-Based Wind - Class 3 - Technology 1 | L146: Advanced | M146: 1363 | N146: 1533.3167 | O146: 1434.0015 | P146: 1273.9566 | Q146: 1244.2755 | R146: 1214.5944 | S146: 1184.9133 | T146: 1155.2322 | U146: 1125.5511 | V146: 1095.8699 | W146: 1083.5552 | X146: 1071.2404 | Y146: 1058.9257 | Z146: 1046.6109 | AA146: 1034.2961 | AB146: 1021.9814 | AC146: 1009.6666 | AD146: 997.35186 | AE146: 985.0371 | AF146: 972.72234 | AG146: 960.40758 | AH146: 948.09282 | AI146: 935.77806 | AJ146: 923.46331 | AK146: 911.14855 | AL146: 898.83379 | AM146: 886.51903 | AN146: 874.20427 | AO146: 861.88951 | AP146: 849.57475
K147: Land-Based Wind - Class 3 - Technology 1 | L147: Moderate | M147: 1363 | N147: 1540.2333 | O147: 1447.2333 | P147: 1292 | Q147: 1268.3333 | R147: 1244.6667 | S147: 1221 | T147: 1197.3333 | U147: 1173.6667 | V147: 1150 | W147: 1138.6766 | X147: 1127.3532 | Y147: 1116.0298 | Z147: 1104.7064 | AA147: 1093.383 | AB147: 1082.0596 | AC147: 1070.7362 | AD147: 1059.4129 | AE147: 1048.0895 | AF147: 1036.7661 | AG147: 1025.4427 | AH147: 1014.1193 | AI147: 1002.7959 | AJ147: 991.47249 | AK147: 980.1491 | AL147: 968.8257 | AM147: 957.50231 | AN147: 946.17892 | AO147: 934.85552 | AP147: 923.53213
K148: Land-Based Wind - Class 3 - Technology 1 | L148: Conservative | M148: 1363 | N148: 1556.0722 | O148: 1477.5338 | P148: 1333.3189 | Q148: 1323.4252 | R148: 1313.5315 | S148: 1303.6378 | T148: 1293.7441 | U148: 1283.8504 | V148: 1273.9566 | W148: 1265.3665 | X148: 1256.7764 | Y148: 1248.1862 | Z148: 1239.5961 | AA148: 1231.0059 | AB148: 1222.4158 | AC148: 1213.8257 | AD148: 1205.2355 | AE148: 1196.6454 | AF148: 1188.0552 | AG148: 1179.4651 | AH148: 1170.875 | AI148: 1162.2848 | AJ148: 1153.6947 | AK148: 1145.1045 | AL148: 1136.5144 | AM148: 1127.9243 | AN148: 1119.3341 | AO148: 1110.744 | AP148: 1102.1538
K149: Land-Based Wind - Class 4 - Technology 1 | L149: Advanced | M149: 1363 | N149: 1533.3167 | O149: 1434.0015 | P149: 1273.9566 | Q149: 1244.2755 | R149: 1214.5944 | S149: 1184.9133 | T149: 1155.2322 | U149: 1125.5511 | V149: 1095.8699 | W149: 1083.5552 | X149: 1071.2404 | Y149: 1058.9257 | Z149: 1046.6109 | AA149: 1034.2961 | AB149: 1021.9814 | AC149: 1009.6666 | AD149: 997.35186 | AE149: 985.0371 | AF149: 972.72234 | AG149: 960.40758 | AH149: 948.09282 | AI149: 935.77806 | AJ149: 923.46331 | AK149: 911.14855 | AL149: 898.83379 | AM149: 886.51903 | AN149: 874.20427 | AO149: 861.88951 | AP149: 849.57475
K150: Land-Based Wind - Class 4 - Technology 1 | L150: Moderate | M150: 1363 | N150: 1540.2333 | O150: 1447.2333 | P150: 1292 | Q150: 1268.3333 | R150: 1244.6667 | S150: 1221 | T150: 1197.3333 | U150: 1173.6667 | V150: 1150 | W150: 1138.6766 | X150: 1127.3532 | Y150: 1116.0298 | Z150: 1104.7064 | AA150: 1093.383 | AB150: 1082.0596 | AC150: 1070.7362 | AD150: 1059.4129 | AE150: 1048.0895 | AF150: 1036.7661 | AG150: 1025.4427 | AH150: 1014.1193 | AI150: 1002.7959 | AJ150: 991.47249 | AK150: 980.1491 | AL150: 968.8257 | AM150: 957.50231 | AN150: 946.17892 | AO150: 934.85552 | AP150: 923.53213
K151: Land-Based Wind - Class 4 - Technology 1 | L151: Conservative | M151: 1363 | N151: 1556.0722 | O151: 1477.5338 | P151: 1333.3189 | Q151: 1323.4252 | R151: 1313.5315 | S151: 1303.6378 | T151: 1293.7441 | U151: 1283.8504 | V151: 1273.9566 | W151: 1265.3665 | X151: 1256.7764 | Y151: 1248.1862 | Z151: 1239.5961 | AA151: 1231.0059 | AB151: 1222.4158 | AC151: 1213.8257 | AD151: 1205.2355 | AE151: 1196.6454 | AF151: 1188.0552 | AG151: 1179.4651 | AH151: 1170.875 | AI151: 1162.2848 | AJ151: 1153.6947 | AK151: 1145.1045 | AL151: 1136.5144 | AM151: 1127.9243 | AN151: 1119.3341 | AO151: 1110.744 | AP151: 1102.1538
K152: Land-Based Wind - Class 5 - Technology 1 | L152: Advanced | M152: 1363 | N152: 1533.3167 | O152: 1434.0015 | P152: 1273.9566 | Q152: 1244.2755 | R152: 1214.5944 | S152: 1184.9133 | T152: 1155.2322 | U152: 1125.5511 | V152: 1095.8699 | W152: 1083.5552 | X152: 1071.2404 | Y152: 1058.9257 | Z152: 1046.6109 | AA152: 1034.2961 | AB152: 1021.9814 | AC152: 1009.6666 | AD152: 997.35186 | AE152: 985.0371 | AF152: 972.72234 | AG152: 960.40758 | AH152: 948.09282 | AI152: 935.77806 | AJ152: 923.46331 | AK152: 911.14855 | AL152: 898.83379 | AM152: 886.51903 | AN152: 874.20427 | AO152: 861.88951 | AP152: 849.57475
... K169: Land-Based Wind - Class 10 - Technology 4 | L169: Conservative | M169: 1961 | N169: 2233.3238 | O169: 2115.3456 | P169: 1904.0622 | Q169: 1885.0829 | R169: 1866.1037 | S169: 1847.1244 | T169: 1828.1451 | U169: 1809.1659 | V169: 1790.1866 | W169: 1778.626 | X169: 1767.0654 | Y169: 1755.5048 | Z169: 1743.9442 | AA169: 1732.3837 | AB169: 1720.8231 | AC169: 1709.2625 | AD169: 1697.7019 | AE169: 1686.1413 | AF169: 1674.5807 | AG169: 1663.0201 | AH169: 1651.4596 | AI169: 1639.899 | AJ169: 1628.3384 | AK169: 1616.7778 | AL169: 1605.2172 | AM169: 1593.6566 | AN169: 1582.096 | AO169: 1570.5355 | AP169: 1558.9749
M171: 2021 | N171: 2022 | O171: 2023 | P171: 2024 | Q171: 2025 | R171: 2026 | S171: 2027 | T171: 2028 | U171: 2029 | V171: 2030 | W171: 2031 | X171: 2032 | Y171: 2033 | Z171: 2034 | AA171: 2035 | AB171: 2036 | AC171: 2037 | AD171: 2038 | AE171: 2039 | AF171: 2040 | AG171: 2041 | AH171: 2042 | AI171: 2043 | AJ171: 2044 | AK171: 2045 | AL171: 2046 | AM171: 2047 | AN171: 2048 | AO171: 2049 | AP171: 2050
J172: Construction Financing Cost ($/kW) | K172: Land-Based Wind - Class 1 - Technology 1 | L172: Advanced | M172: 79.116965 | N172: 89.003202 | O172: 83.238334 | P172: 73.948337 | Q172: 72.225461 | R172: 70.502585 | S172: 68.779709 | T172: 67.056833 | U172: 65.333957 | V172: 63.611081 | W172: 62.896256 | X172: 62.181431 | Y172: 61.466607 | Z172: 60.751782 | AA172: 60.036957 | AB172: 59.322132 | AC172: 58.607307 | AD172: 57.892482 | AE172: 57.177657 | AF172: 56.462832 | AG172: 55.748007 | AH172: 55.033182 | AI172: 54.318357 | AJ172: 53.603532 | AK172: 52.888707 | AL172: 52.173882 | AM172: 51.459057 | AN172: 50.744232 | AO172: 50.029407 | AP172: 49.314582
K173: Land-Based Wind - Class 1 - Technology 1 | L173: Moderate | M173: 79.116965 | N173: 89.404686 | O173: 84.00639 | P173: 74.995685 | Q173: 73.621925 | R173: 72.248165 | S173: 70.874405 | T173: 69.500645 | U173: 68.126885 | V173: 66.753125 | W173: 66.095845 | X173: 65.438565 | Y173: 64.781286 | Z173: 64.124006 | AA173: 63.466726 | AB173: 62.809446 | AC173: 62.152166 | AD173: 61.494886 | AE173: 60.837606 | AF173: 60.180326 | AG173: 59.523046 | AH173: 58.865766 | AI173: 58.208486 | AJ173: 57.551206 | AK173: 56.893926 | AL173: 56.236647 | AM173: 55.579367 | AN173: 54.922087 | AO173: 54.264807 | AP173: 53.607527
K174: Land-Based Wind - Class 1 - Technology 1 | L174: Conservative | M174: 79.116965 | N174: 90.324074 | O174: 85.765219 | P174: 77.394089 | Q174: 76.819797 | R174: 76.245505 | S174: 75.671213 | T174: 75.096921 | U174: 74.522629 | V174: 73.948337 | W174: 73.449712 | X174: 72.951087 | Y174: 72.452462 | Z174: 71.953837 | AA174: 71.455212 | AB174: 70.956587 | AC174: 70.457962 | AD174: 69.959337 | AE174: 69.460712 | AF174: 68.962087 | AG174: 68.463462 | AH174: 67.964837 | AI174: 67.466212 | AJ174: 66.967587 | AK174: 66.468962 | AL174: 65.970337 | AM174: 65.471712 | AN174: 64.973087 | AO174: 64.474462 | AP174: 63.975837
K175: Land-Based Wind - Class 2 - Technology 1 | L175: Advanced | M175: 79.116965 | N175: 89.003202 | O175: 83.238334 | P175: 73.948337 | Q175: 72.225461 | R175: 70.502585 | S175: 68.779709 | T175: 67.056833 | U175: 65.333957 | V175: 63.611081 | W175: 62.896256 | X175: 62.181431 | Y175: 61.466607 | Z175: 60.751782 | AA175: 60.036957 | AB175: 59.322132 | AC175: 58.607307 | AD175: 57.892482 | AE175: 57.177657 | AF175: 56.462832 | AG175: 55.748007 | AH175: 55.033182 | AI175: 54.318357 | AJ175: 53.603532 | AK175: 52.888707 | AL175: 52.173882 | AM175: 51.459057 | AN175: 50.744232 | AO175: 50.029407 | AP175: 49.314582
K176: Land-Based Wind - Class 2 - Technology 1 | L176: Moderate | M176: 79.116965 | N176: 89.404686 | O176: 84.00639 | P176: 74.995685 | Q176: 73.621925 | R176: 72.248165 | S176: 70.874405 | T176: 69.500645 | U176: 68.126885 | V176: 66.753125 | W176: 66.095845 | X176: 65.438565 | Y176: 64.781286 | Z176: 64.124006 | AA176: 63.466726 | AB176: 62.809446 | AC176: 62.152166 | AD176: 61.494886 | AE176: 60.837606 | AF176: 60.180326 | AG176: 59.523046 | AH176: 58.865766 | AI176: 58.208486 | AJ176: 57.551206 | AK176: 56.893926 | AL176: 56.236647 | AM176: 55.579367 | AN176: 54.922087 | AO176: 54.264807 | AP176: 53.607527
K177: Land-Based Wind - Class 2 - Technology 1 | L177: Conservative | M177: 79.116965 | N177: 90.324074 | O177: 85.765219 | P177: 77.394089 | Q177: 76.819797 | R177: 76.245505 | S177: 75.671213 | T177: 75.096921 | U177: 74.522629 | V177: 73.948337 | W177: 73.449712 | X177: 72.951087 | Y177: 72.452462 | Z177: 71.953837 | AA177: 71.455212 | AB177: 70.956587 | AC177: 70.457962 | AD177: 69.959337 | AE177: 69.460712 | AF177: 68.962087 | AG177: 68.463462 | AH177: 67.964837 | AI177: 67.466212 | AJ177: 66.967587 | AK177: 66.468962 | AL177: 65.970337 | AM177: 65.471712 | AN177: 64.973087 | AO177: 64.474462 | AP177: 63.975837
...

Sheet Subsidies Paid
A1: Model Energy Source | B1: Subsidy Name | C1: Source | D1: Fuel/Electricity | E1: Unit | F1: 2013 | G1: 2014 | H1: 2015 | I1: 2016 | J1: 2017 | K1: 2018 | L1: 2019 | M1: 2020 | N1: 2021 | O1: 2022 | P1: 2023 | Q1: 2024 | R1: 2025 | S1: 2026 | T1: 2027 | U1: 2028 | V1: 2029 | W1: 2030
A2: biomass | B2: Section 45: PTC | C2: http://programs.dsireusa.org/system/program/detail/734 | D2: Electricity | E2: $/kWh (2014) | F2: 0.011 | G2: 0.012 | H2: 0.012 | I2: 0.012 | J2: 0 | K2: 0 | L2: 0 | M2: 0 | N2: 0 | O2: 0 | P2: 0 | Q2: 0 | R2: 0 | S2: 0 | T2: 0 | U2: 0 | V2: 0 | W2: 0 | X2: <expires in 2016
A3: coal | B3: IRC Section 48A Tax Credit for IGCC and ACBGT | C3: https://www.law.cornell.edu/uscode/text/26/48A | D3: Electricity | E3: % of investments costs | F3: 0 | G3: 0 | H3: 0 | I3: 0 | J3: 0 | K3: 0 | L3: 0 | M3: 0 | N3: 0 | O3: 0 | P3: 0 | Q3: 0 | R3: 0 | S3: 0 | T3: 0 | U3: 0 | V3: 0 | W3: 0 | X3: <We assign this zero because no unit in our model can meet the heat rate requirements to be elgible and we assume no new IGCC units
A4: coal | B4: Amortization of air pollution control facilities | C4: https://www.jct.gov/publications.html?func=download&id=4663&chk=4663&no_html=1 | D4: Electricity | E4: Billion $ | F4: n/a | G4: 0.4 | H4: 0.4 | I4: 0.4 | J4: 0.3 | K4: 0.3 | L4: n/a | M4: n/a | N4: n/a | O4: n/a | P4: n/a | Q4: n/a | R4: n/a | S4: n/a | T4: n/a | U4: n/a | V4: n/a | W4: n/a | X4: <use same methodology as before
A5: hydro | B5: Section 45: PTC | C5: http://programs.dsireusa.org/system/program/detail/734 | D5: Electricity | E5: $/kWh (2014) | F5: 0.011 | G5: 0.012 | H5: 0.012 | I5: 0.012 | J5: 0 | K5: 0 | L5: 0 | M5: 0 | N5: 0 | O5: 0 | P5: 0 | Q5: 0 | R5: 0 | S5: 0 | T5: 0 | U5: 0 | V5: 0 | W5: 0 | X5: <expires in 2016
A6: nuclear | B6: Special rules for nuclear decommissioning costs | C6: https://www.jct.gov/publications.html?func=download&id=4663&chk=4663&no_html=1 | D6: Electricity | E6: Billion $ | F6: 0 | G6: 0.2 | H6: 0.2 | I6: 0.2 | J6: 0.3 | K6: 0.3 | L6: 0 | M6: 0 | N6: 0 | O6: 0 | P6: 0 | Q6: 0 | R6: 0 | S6: 0 | T6: 0 | U6: 0 | V6: 0 | W6: 0 | X6: <use same methodology as before
A7: nuclear | B7: Civil Nuclear Credit Program | C7: https://www.energy.gov/ne/civil-nuclear-credit-program | D7: Electricity | E7: Billion $ | F7: 0 | G7: 0 | H7: 0 | I7: 0 | J7: 0 | K7: 0 | L7: 0 | M7: 0 | N7: 0 | O7: =6/5 -> 1.2 | P7: =6/5 -> 1.2 | Q7: =6/5 -> 1.2 | R7: =6/5 -> 1.2 | S7: =6/5 -> 1.2 | T7: 0 | U7: 0 | V7: 0 | W7: 0 | X7: <we use the assumption in the 2022 AEO, which is that funds are used between 2022-2026
A8: solar pv, solar thermal | B8: Section 48: ITC | C8: https://www.greentechmedia.com/articles/read/solar-and-wind-tax-credit-extensions-energy-rd-package-in-spending-bill-before-congress#:~:text=According%20to%20a%20summary%20shared,would%20have%20under%20existing%20law. | D8: Electricity | E8: % of investment costs | F8: 0.3 | G8: 0.3 | H8: 0.3 | I8: 0.3 | J8: 0.3 | K8: 0.3 | L8: 0.3 | M8: 0.26 | N8: 0.26 | O8: 0.26 | P8: 0.22 | Q8: 0.1 | R8: 0.1 | S8: 0.1 | T8: 0.1 | U8: 0.1 | V8: 0.1 | W8: 0.1 | X8: <extended with ramp down and no phase out
A9: offshore wind | B9: Section 48: ITC | C9: https://www.greentechmedia.com/articles/read/solar-and-wind-tax-credit-extensions-energy-rd-package-in-spending-bill-before-congress#:~:text=According%20to%20a%20summary%20shared,would%20have%20under%20existing%20law. | D9: Electricity | E9: % of investment costs | F9: 0 | G9: 0 | H9: 0 | I9: 0 | J9: 0 | K9: 0 | L9: 0 | M9: 0 | N9: 0.3 | O9: 0.3 | P9: 0.3 | Q9: 0.3 | R9: 0.3 | S9: 0 | T9: 0 | U9: 0 | V9: 0 | W9: 0 | X9: <assumed offshore wind will use the ITC starting in 2021 based on a lower calculated LCOE
A10: onshore wind | B10: Section 45: PTC | C10: https://fas.org/sgp/crs/misc/R43453.pdf; https://www.greentechmedia.com/articles/read/solar-and-wind-tax-credit-extensions-energy-rd-package-in-spending-bill-before-congress#:~:text=According%20to%20a%20summary%20shared,would%20have%20under%20existing%20law. | D10: Electricity | E10: $/kWh (2019) | F10: 0.023 | G10: 0.023 | H10: 0.023 | I10: 0.023 | J10: =I10*0.8 -> 0.0184 | K10: =I10*0.6 -> 0.0138 | L10: =0.025*0.4 -> 0.01 | M10: =0.025*0.6 -> 0.015 | N10: =0.025*0.6 -> 0.015 | O10: 0 | P10: 0 | Q10: 0 | R10: 0 | S10: 0 | T10: 0 | U10: 0 | V10: 0 | W10: 0 | X10: <extending with ramp down, expiring in 2021
A11: offshore wind | B11: Section 45: PTC | C11: https://fas.org/sgp/crs/misc/R43453.pdf; https://www.greentechmedia.com/articles/read/solar-and-wind-tax-credit-extensions-energy-rd-package-in-spending-bill-before-congress#:~:text=According%20to%20a%20summary%20shared,would%20have%20under%20existing%20law. | D11: Electricity | E11: $/kWh (2019) | F11: =F10 -> 0.023 | G11: =G10 -> 0.023 | H11: =H10 -> 0.023 | I11: =I10 -> 0.023 | J11: =J10 -> 0.0184 | K11: =K10 -> 0.0138 | L11: =L10 -> 0.01 | M11: =M10 -> 0.015 | N11: 0 | O11: 0 | P11: 0 | Q11: 0 | R11: 0 | S11: 0 | T11: 0 | U11: 0 | V11: 0 | W11: 0 | X11: <extended through 2020, but assumes offshore wind will use the ITC starting in 2021 based on a lower calculated LCOE
A12: geothermal | B12: Section 45: PTC | C12: http://programs.dsireusa.org/system/program/detail/734 | D12: Electricity | E12: $/kWh (2019) | F12: =0.023 -> 0.023 | G12: =0.023 -> 0.023 | H12: =0.023 -> 0.023 | I12: =0.023 -> 0.023 | J12: 0 | K12: 0 | L12: 0 | M12: 0 | N12: 0 | O12: 0 | P12: 0 | Q12: 0 | R12: 0 | S12: 0 | T12: 0 | U12: 0 | V12: 0 | W12: 0 | X12: <expires in 2016
A13: geothermal | B13: Section 48: ITC | C13: http://programs.dsireusa.org/system/program/detail/658 | D13: Electricity | E13: % of investment costs | F13: 0.1 | G13: 0.1 | H13: 0.1 | I13: 0.1 | J13: 0.1 | K13: 0.1 | L13: 0.1 | M13: 0.1 | N13: 0.1 | O13: 0.1 | P13: 0.1 | Q13: 0.1 | R13: 0.1 | S13: 0.1 | T13: 0.1 | U13: 0.1 | V13: 0.1 | W13: 0.1 | X13: <no expiration; can be taken in lieu of PTC
A14: coal | B14: Capital gains treatment for royalties of coal | C14: http://www.treasury.gov/open/Documents/USA%20FFSR%20progress%20report%20to%20G20%202014%20Final.pdf | D14: Fuel | E14: $ | F14: n/a | G14: n/a | H14: 53000000 | I14: n/a | J14: n/a | K14: n/a | L14: n/a | M14: n/a | N14: n/a | O14: n/a | P14: n/a | Q14: n/a | R14: n/a | S14: n/a | T14: n/a | U14: n/a | V14: n/a | W14: n/a | X14: <need to estimate based on this
A15: coal | B15: Expensing of exploration and development costs for hard mineral fuels | C15: http://www.treasury.gov/open/Documents/USA%20FFSR%20progress%20report%20to%20G20%202014%20Final.pdf; https://www.jct.gov/publications.html?func=download&id=4663&chk=4663&no_html=1 | D15: Fuel | E15: Billion $ | F15: n/a | G15: 0.1 | H15: 0.1 | I15: 0.1 | J15: 0.1 | K15: 0.1 | L15: n/a | M15: n/a | N15: n/a | O15: n/a | P15: n/a | Q15: n/a | R15: n/a | S15: n/a | T15: n/a | U15: n/a | V15: n/a | W15: n/a
A16: petroleum gasoline, petroleum diesel, jet fuel | B16: Expensing of exploration and development costs for hard mineral fuels | C16: http://www.treasury.gov/open/Documents/USA%20FFSR%20progress%20report%20to%20G20%202014%20Final.pdf; https://www.jct.gov/publications.html?func=download&id=4663&chk=4663&no_html=1 | D16: Fuel | E16: Billion $ | F16: n/a | G16: 1.1 | H16: 1.1 | I16: 1.2 | J16: 1.3 | K16: 1.3 | L16: n/a | M16: n/a | N16: n/a | O16: n/a | P16: n/a | Q16: n/a | R16: n/a | S16: n/a | T16: n/a | U16: n/a | V16: n/a | W16: n/a | X16: <use same methodology as before
A17: natural gas, petroleum gasoline, petroleum diesel, jet fuel | B17: Excess of percentage over cost depletion, fuels: Oil and gas | C17: http://www.treasury.gov/open/Documents/USA%20FFSR%20progress%20report%20to%20G20%202014%20Final.pdf | D17: Fuel | E17: Billion $ | F17: n/a | G17: 1.02 | H17: 1.52 | I17: 1.62 | J17: 1.62 | K17: 1.62 | L17: n/a | M17: n/a | N17: n/a | O17: n/a | P17: n/a | Q17: n/a | R17: n/a | S17: n/a | T17: n/a | U17: n/a | V17: n/a | W17: n/a | X17: <use same methodology as before
A18: natural gas, petroleum gasoline, petroleum diesel, jet fuel | B18: Amortization of geological and geophysical expenditures associated with oil and gas exploration | C18: http://www.treasury.gov/open/Documents/USA%20FFSR%20progress%20report%20to%20G20%202014%20Final.pdf | D18: Fuel | E18: Billion $ | F18: n/a | G18: 0.14 | H18: 0.14 | I18: 0.14 | J18: 0.14 | K18: 0.14 | L18: n/a | M18: n/a | N18: n/a | O18: n/a | P18: n/a | Q18: n/a | R18: n/a | S18: n/a | T18: n/a | U18: n/a | V18: n/a | W18: n/a | X18: <use same methodology as before
A19: natural gas, petroleum gasoline, petroleum diesel, jet fuel | B19: Exceptions for publicly traded partnership with qualified income derived from certain energy-related activities | C19: https://www.fas.org/sgp/crs/misc/R41769.pdf | D19: Fuel | E19: Billion $ | F19: n/a | G19: 1.1 | H19: 1.1 | I19: 1.2 | J19: 1.2 | K19: 1.2 | L19: n/a | M19: n/a | N19: n/a | O19: n/a | P19: n/a | Q19: n/a | R19: n/a | S19: n/a | T19: n/a | U19: n/a | V19: n/a | W19: n/a | X19: <use same methodology as before
A20: petroleum gasoline, petroleum diesel, jet fuel | B20: Deduction for tertiary injectants | C20: http://www.treasury.gov/open/Documents/USA%20FFSR%20progress%20report%20to%20G20%202014%20Final.pdf | D20: Fuel | E20: $ | F20: n/a | G20: n/a | H20: 10000000 | I20: n/a | J20: n/a | K20: n/a | L20: n/a | M20: n/a | N20: n/a | O20: n/a | P20: n/a | Q20: n/a | R20: n/a | S20: n/a | T20: n/a | U20: n/a | V20: n/a | W20: n/a | X20: <need to estimate based on this

Sheet AEO 2022 Table 1
B1: ref2022.d011222a | C1: 2021 | D1: 2022 | E1: 2023 | F1: 2024 | G1: 2025 | H1: 2026 | I1: 2027 | J1: 2028 | K1: 2029 | L1: 2030 | M1: 2031 | N1: 2032 | O1: 2033 | P1: 2034 | Q1: 2035 | R1: 2036 | S1: 2037 | T1: 2038 | U1: 2039 | V1: 2040 | W1: 2041 | X1: 2042 | Y1: 2043 | Z1: 2044 | AA1: 2045 | AB1: 2046 | AC1: 2047 | AD1: 2048 | AE1: 2049 | AF1: 2050
C3: Report | D3: Annual Energy Outlook 2022
C4: Scenario | D4: ref2022 | G4: Reference
C5: Datekey | D5: d011222a
C6: Release Date | E6: March 2022
A10: SUP000 | B10: 1. Total Energy Supply, Disposition, and Price Summary | AG10: Average
B11: (quadrillion Btu, unless otherwise noted) | AG11: Annual
AG12: Change
B13: Supply, Disposition, and Prices | C13: 2021 | D13: 2022 | E13: 2023 | F13: 2024 | G13: 2025 | H13: 2026 | I13: 2027 | J13: 2028 | K13: 2029 | L13: 2030 | M13: 2031 | N13: 2032 | O13: 2033 | P13: 2034 | Q13: 2035 | R13: 2036 | S13: 2037 | T13: 2038 | U13: 2039 | V13: 2040 | W13: 2041 | X13: 2042 | Y13: 2043 | Z13: 2044 | AA13: 2045 | AB13: 2046 | AC13: 2047 | AD13: 2048 | AE13: 2049 | AF13: 2050 | AG13: 2021–2050
B15: Production
A16: SUP000:ba_CrudeOilLease | B16: Crude Oil and Lease Condensate | C16: 23.173487 | D16: 24.717472 | E16: 25.494104 | F16: 26.154642 | G16: 27.054277 | H16: 27.435596 | I16: 27.342155 | J16: 27.686852 | K16: 27.633852 | L16: 27.555265 | M16: 27.280258 | N16: 27.009712 | O16: 27.003248 | P16: 26.646475 | Q16: 26.47743 | R16: 26.305445 | S16: 26.016472 | T16: 25.819599 | U16: 25.821352 | V16: 25.902487 | W16: 25.722721 | X16: 25.635948 | Y16: 25.63641 | Z16: 25.47831 | AA16: 25.779816 | AB16: 25.951448 | AC16: 25.981897 | AD16: 25.859144 | AE16: 25.553583 | AF16: 26.234585 | AG16: 0.004287
A17: SUP000:ba_NaturalGasPla | B17: Natural Gas Plant Liquids | C17: 7.006215 | D17: 7.552815 | E17: 7.883783 | F17: 8.023396 | G17: 8.163991 | H17: 8.108202 | I17: 8.041482 | J17: 8.029618 | K17: 8.082181 | L17: 8.155948 | M17: 8.184832 | N17: 8.259987 | O17: 8.235239 | P17: 8.250072 | Q17: 8.27844 | R17: 8.210117 | S17: 8.17472 | T17: 8.172275 | U17: 8.222511 | V17: 8.267702 | W17: 8.281703 | X17: 8.384741 | Y17: 8.490253 | Z17: 8.476263 | AA17: 8.579662 | AB17: 8.612893 | AC17: 8.634458 | AD17: 8.644827 | AE17: 8.650251 | AF17: 8.701235 | AG17: 0.007499
A18: SUP000:ba_DryNaturalGas | B18: Dry Natural Gas | C18: 35.682777 | D18: 36.629646 | E18: 36.922058 | F18: 37.131554 | G18: 37.233967 | H18: 37.210548 | I18: 37.134987 | J18: 37.74691 | K18: 38.012238 | L18: 38.079895 | M18: 38.334229 | N18: 38.609394 | O18: 38.861305 | P18: 38.688675 | Q18: 38.547447 | R18: 38.495739 | S18: 38.611137 | T18: 38.832619 | U18: 39.095234 | V18: 39.377579 | W18: 39.502232 | X18: 39.69487 | Y18: 40.037334 | Z18: 40.361305 | AA18: 40.596077 | AB18: 40.848938 | AC18: 41.134644 | AD18: 41.335979 | AE18: 41.513866 | AF18: 41.894924 | AG18: 0.00555
A19: SUP000:ba_Coal | B19: Coal 1/ | C19: 13.089978 | D19: 12.741252 | E19: 12.812081 | F19: 11.346849 | G19: 10.919338 | H19: 10.890395 | I19: 10.594276 | J19: 10.517385 | K19: 10.477952 | L19: 10.320335 | M19: 10.278054 | N19: 10.186623 | O19: 10.161192 | P19: 9.840708 | Q19: 9.568752 | R19: 9.414873 | S19: 9.287329 | T19: 9.301336 | U19: 9.227633 | V19: 9.145965 | W19: 9.122682 | X19: 9.086012 | Y19: 8.961373 | Z19: 8.89466 | AA19: 8.785145 | AB19: 8.720604 | AC19: 8.623024 | AD19: 8.544412 | AE19: 8.507181 | AF19: 8.572097 | AG19: -0.014492
A20: SUP000:ba_NuclearPower | B20: Nuclear / Uranium 2/ | C20: 8.12115 | D20: 8.183111 | E20: 8.202579 | F20: 8.239058 | G20: 8.163899 | H20: 8.075755 | I20: 7.930267 | J20: 7.368946 | K20: 7.299504 | L20: 7.307006 | M20: 7.318423 | N20: 7.326343 | O20: 6.808416 | P20: 6.815667 | Q20: 6.747447 | R20: 6.758354 | S20: 6.760554 | T20: 6.762659 | U20: 6.762759 | V20: 6.766273 | W20: 6.77936 | X20: 6.788805 | Y20: 6.797936 | Z20: 6.805902 | AA20: 6.814445 | AB20: 6.818903 | AC20: 6.823349 | AD20: 6.826119 | AE20: 6.829472 | AF20: 6.834313 | AG20: -0.005931
A21: SUP000:ba_Hydropower | B21: Conventional Hydroelectric Power | C21: 2.288529 | D21: 2.39653 | E21: 2.520376 | F21: 2.607582 | G21: 2.562303 | H21: 2.533515 | I21: 2.5148 | J21: 2.494481 | K21: 2.48263 | L21: 2.471396 | M21: 2.456771 | N21: 2.450083 | O21: 2.436512 | P21: 2.4271 | Q21: 2.410605 | R21: 2.397023 | S21: 2.392663 | T21: 2.381657 | U21: 2.376802 | V21: 2.37014 | W21: 2.362096 | X21: 2.354189 | Y21: 2.3427 | Z21: 2.33699 | AA21: 2.32513 | AB21: 2.318443 | AC21: 2.309026 | AD21: 2.304834 | AE21: 2.295233 | AF21: 2.274688 | AG21: -0.000209
A22: SUP000:ba_Biomass | B22: Biomass 3/ | C22: 4.70119 | D22: 4.833665 | E22: 4.736951 | F22: 4.731843 | G22: 4.751482 | H22: 4.740038 | I22: 4.728146 | J22: 4.706775 | K22: 4.708263 | L22: 4.6997 | M22: 4.688527 | N22: 4.681827 | O22: 4.666749 | P22: 4.654086 | Q22: 4.648972 | R22: 4.641438 | S22: 4.63418 | T22: 4.638316 | U22: 4.647457 | V22: 4.683486 | W22: 4.705445 | X22: 4.722157 | Y22: 4.748343 | Z22: 4.791994 | AA22: 4.814004 | AB22: 4.843565 | AC22: 4.876688 | AD22: 4.909999 | AE22: 4.942437 | AF22: 4.984637 | AG22: 0.002021
A23: SUP000:ba_RenewableEner | B23: Other Renewable Energy 4/ | C23: 4.839005 | D23: 5.544484 | E23: 6.085557 | F23: 6.989227 | G23: 7.561359 | H23: 7.846316 | I23: 8.347466 | J23: 8.5777 | K23: 8.787159 | L23: 9.155986 | M23: 9.41178 | N23: 9.649215 | O23: 9.910384 | P23: 10.464489 | Q23: 11.17978 | R23: 11.560812 | S23: 11.709242 | T23: 11.735645 | U23: 11.787336 | V23: 11.864063 | W23: 11.965893 | X23: 12.084974 | Y23: 12.202391 | Z23: 12.369851 | AA23: 12.586577 | AB23: 12.70438 | AC23: 12.871214 | AD23: 13.03612 | AE23: 13.182046 | AF23: 13.273847 | AG23: 0.035408
A24: SUP000:ba_Other | B24: Other 5/ | C24: 2.133576 | D24: 1.012973 | E24: 0.879855 | F24: 0.894946 | G24: 0.774271 | H24: 0.88321 | I24: 0.8699 | J24: 0.796129 | K24: 0.770551 | L24: 0.770231 | M24: 0.768565 | N24: 0.632673 | O24: 0.631935 | P24: 0.640565 | Q24: 0.637551 | R24: 0.647367 | S24: 0.651814 | T24: 0.653633 | U24: 0.651491 | V24: 0.642037 | W24: 0.639621 | X24: 0.634056 | Y24: 0.627797 | Z24: 0.632698 | AA24: 0.626717 | AB24: 0.618566 | AC24: 0.61455 | AD24: 0.621078 | AE24: 0.628376 | AF24: 0.623335 | AG24: -0.041542
A25: SUP000:ba_Total | B25: Total | C25: 101.0359 | D25: 103.61195 | E25: 105.53733 | F25: 106.1191 | G25: 107.18489 | H25: 107.72357 | I25: 107.50348 | J25: 107.9248 | K25: 108.25434 | L25: 108.51576 | M25: 108.72144 | N25: 108.80585 | O25: 108.71499 | P25: 108.42783 | Q25: 108.49642 | R25: 108.43117 | S25: 108.23811 | T25: 108.29774 | U25: 108.59257 | V25: 109.01973 | W25: 109.08175 | X25: 109.38576 | Y25: 109.84454 | Z25: 110.14797 | AA25: 110.90757 | AB25: 111.43774 | AC25: 111.86885 | AD25: 112.08251 | AE25: 112.10244 | AF25: 113.39367 | AG25: 0.003987
B27: Imports
A28: SUP000:ca_CrudeOil | B28: Crude Oil | C28: 13.849983 | D28: 16.37085 | E28: 16.629141 | F28: 15.971055 | G28: 15.230758 | H28: 14.679036 | I28: 14.643375 | J28: 14.357627 | K28: 14.264916 | L28: 14.200821 | M28: 14.399286 | N28: 14.778255 | O28: 14.611301 | P28: 14.955673 | Q28: 15.036996 | R28: 15.363056 | S28: 15.527345 | T28: 15.740888 | U28: 15.813135 | V28: 15.458242 | W28: 15.443821 | X28: 15.243117 | Y28: 14.882616 | Z28: 15.204732 | AA28: 14.507174 | AB28: 14.091373 | AC28: 13.903984 | AD28: 14.131474 | AE28: 14.48548 | AF28: 13.759513 | AG28: -0.000226
A29: SUP000:ca_PetroleumProd | B29: Petroleum and Other Liquids 6/ | C29: 4.715964 | D29: 4.470991 | E29: 3.845002 | F29: 3.923882 | G29: 4.01288 | H29: 3.965475 | I29: 3.914824 | J29: 3.83206 | K29: 3.720322 | L29: 3.693734 | M29: 3.634232 | N29: 3.635437 | O29: 3.59495 | P29: 3.562899 | Q29: 3.543973 | R29: 3.497625 | S29: 3.494834 | T29: 3.505317 | U29: 3.501205 | V29: 3.483078 | W29: 3.503401 | X29: 3.506699 | Y29: 3.514882 | Z29: 3.52966 | AA29: 3.55301 | AB29: 3.566257 | AC29: 3.599412 | AD29: 3.686488 | AE29: 3.677653 | AF29: 3.64243 | AG29: -0.008867
A30: SUP000:ca_NaturalGas | B30: Natural Gas | C30: 2.798295 | D30: 2.540921 | E30: 2.459869 | F30: 2.356853 | G30: 2.282891 | H30: 2.256741 | I30: 2.221225 | J30: 2.170627 | K30: 2.036805 | L30: 1.983411 | M30: 1.890747 | N30: 1.878801 | O30: 1.924771 | P30: 1.886512 | Q30: 1.844462 | R30: 1.839028 | S30: 1.873339 | T30: 1.870136 | U30: 1.839986 | V30: 1.805083 | W30: 1.780095 | X30: 1.772161 | Y30: 1.710783 | Z30: 1.587325 | AA30: 1.509457 | AB30: 1.489166 | AC30: 1.460802 | AD30: 1.464388 | AE30: 1.431648 | AF30: 1.387205 | AG30: -0.023907
A31: SUP000:ca_OtherImports | B31: Other 7/ | C31: 0.290388 | D31: 0.22012 | E31: 0.1165 | F31: 0.120814 | G31: 0.110212 | H31: 0.115351 | I31: 0.128298 | J31: 0.136961 | K31: 0.138309 | L31: 0.145788 | M31: 0.137366 | N31: 0.141914 | O31: 0.134995 | P31: 0.140072 | Q31: 0.137182 | R31: 0.136788 | S31: 0.131592 | T31: 0.13375 | U31: 0.134478 | V31: 0.136204 | W31: 0.131303 | X31: 0.131657 | Y31: 0.139108 | Z31: 0.138671 | AA31: 0.134569 | AB31: 0.134666 | AC31: 0.134403 | AD31: 0.13461 | AE31: 0.13483 | AF31: 0.135472 | AG31: -0.025949
A32: SUP000:ca_Total | B32: Total | C32: 21.654629 | D32: 23.602882 | E32: 23.05051 | F32: 22.372604 | G32: 21.63674 | H32: 21.016602 | I32: 20.907722 | J32: 20.497274 | K32: 20.160353 | L32: 20.023756 | M32: 20.06163 | N32: 20.434408 | O32: 20.266016 | P32: 20.545156 | Q32: 20.562613 | R32: 20.836498 | S32: 21.027109 | T32: 21.250092 | U32: 21.288803 | V32: 20.882607 | W32: 20.85862 | X32: 20.653633 | Y32: 20.247391 | Z32: 20.460388 | AA32: 19.70421 | AB32: 19.281464 | AC32: 19.098602 | AD32: 19.41696 | AE32: 19.729612 | AF32: 18.92462 | AG32: -0.004636
B34: Exports
A35: SUP000:da_Petroleum | B35: Petroleum and Other Liquids 8/ | C35: 16.73385 | D35: 18.356298 | E35: 19.182388 | F35: 19.602926 | G35: 19.941938 | H35: 19.903315 | I35: 19.849981 | J35: 19.863663 | K35: 19.811287 | L35: 19.834377 | M35: 19.808157 | N35: 19.842936 | O35: 19.662491 | P35: 19.775711 | Q35: 19.81488 | R35: 19.950239 | S35: 19.816631 | T35: 19.884661 | U35: 19.983006 | V35: 19.83169 | W35: 19.682125 | X35: 19.486174 | Y35: 19.221823 | Z35: 19.413261 | AA35: 19.138691 | AB35: 18.841377 | AC35: 18.655954 | AD35: 18.810968 | AE35: 18.771133 | AF35: 18.527115 | AG35: 0.003517
A36: SUP000:da_NaturalGas | B36: Natural Gas | C36: 6.809672 | D36: 7.579476 | E36: 7.788739 | F36: 7.875538 | G36: 8.095082 | H36: 8.109738 | I36: 8.24765 | J36: 8.540207 | K36: 8.791788 | L36: 9.023255 | M36: 9.300149 | N36: 9.552501 | O36: 9.670875 | P36: 9.714972 | Q36: 9.777483 | R36: 9.799871 | S36: 9.798469 | T36: 9.820782 | U36: 9.84569 | V36: 9.881186 | W36: 9.868215 | X36: 9.885421 | Y36: 9.895191 | Z36: 9.93121 | AA36: 9.928005 | AB36: 9.911631 | AC36: 9.899729 | AD36: 9.904961 | AE36: 9.876596 | AF36: 9.8705 | AG36: 0.012882
A37: SUP000:da_Coal | B37: Coal | C37: 2.253399 | D37: 2.300418 | E37: 2.924233 | F37: 2.806449 | G37: 2.745555 | H37: 2.878079 | I37: 2.822221 | J37: 2.814723 | K37: 2.789355 | L37: 2.781176 | M37: 2.809537 | N37: 2.864769 | O37: 2.790718 | P37: 2.767172 | Q37: 2.793478 | R37: 2.759903 | S37: 2.751223 | T37: 2.785581 | U37: 2.726024 | V37: 2.735147 | W37: 2.71931 | X37: 2.734332 | Y37: 2.698877 | Z37: 2.698676 | AA37: 2.712163 | AB37: 2.696237 | AC37: 2.690248 | AD37: 2.71199 | AE37: 2.722844 | AF37: 2.737185 | AG37: 0.006729
A38: SUP000:da_Total | B38: Total | C38: 25.796921 | D38: 28.236191 | E38: 29.895359 | F38: 30.284914 | G38: 30.782578 | H38: 30.891132 | I38: 30.919853 | J38: 31.218594 | K38: 31.392429 | L38: 31.638807 | M38: 31.917843 | N38: 32.260204 | O38: 32.124084 | P38: 32.257858 | Q38: 32.385841 | R38: 32.510014 | S38: 32.366325 | T38: 32.491024 | U38: 32.554718 | V38: 32.448021 | W38: 32.26965 | X38: 32.105927 | Y38: 31.815891 | Z38: 32.043148 | AA38: 31.778858 | AB38: 31.449245 | AC38: 31.245932 | AD38: 31.427919 | AE38: 31.370575 | AF38: 31.1348 | AG38: 0.006506
A40: SUP000:ea_Discrepancy | B40: Discrepancy 9/ | C40: -0.09956 | D40: 1.014343 | E40: 0.351906 | F40: 0.371489 | G40: 0.341177 | H40: 0.382046 | I40: 0.381279 | J40: 0.35734 | K40: 0.386271 | L40: 0.381487 | M40: 0.400639 | N40: 0.433743 | O40: 0.415009 | P40: 0.413139 | Q40: 0.417732 | R40: 0.407967 | S40: 0.411499 | T40: 0.408596 | U40: 0.402512 | V40: 0.377655 | W40: 0.373608 | X40: 0.358025 | Y40: 0.344402 | Z40: 0.348759 | AA40: 0.320744 | AB40: 0.279781 | AC40: 0.300562 | AD40: 0.304501 | AE40: 0.307432 | AF40: 0.309587 | AG40: --
B42: Consumption
A43: SUP000:fa_PetroleumProd | B43: Petroleum and Other Liquids 10/ | C43: 36.03891 | D43: 36.753876 | E43: 37.164867 | F43: 37.008743 | G43: 36.993271 | H43: 36.890812 | I43: 36.698307 | J43: 36.579685 | K43: 36.420643 | L43: 36.309967 | M43: 36.218292 | N43: 36.215271 | O43: 36.163837 | P43: 36.030983 | Q43: 35.914291 | R43: 35.832382 | S43: 35.810936 | T43: 35.784924 | U43: 35.813648 | V43: 35.779423 | W43: 35.801689 | X43: 35.841454 | Y43: 35.887527 | Z43: 35.903362 | AA43: 35.944035 | AB43: 36.088379 | AC43: 36.201035 | AD43: 36.273766 | AE43: 36.392872 | AF43: 36.628178 | AG43: 0.000559
A44: SUP000:fa_NaturalGas | B44: Natural Gas | C44: 31.361422 | D44: 31.199945 | E44: 31.177605 | F44: 31.16921 | G44: 30.965534 | H44: 30.880772 | I44: 30.613737 | J44: 30.871202 | K44: 30.754141 | L44: 30.537725 | M44: 30.416206 | N44: 30.414434 | O44: 30.607912 | P44: 30.353966 | Q44: 30.106274 | R44: 30.03334 | S44: 30.184532 | T44: 30.381096 | U44: 30.592625 | V44: 30.803253 | W44: 30.909266 | X44: 31.077223 | Y44: 31.346886 | Z44: 31.509253 | AA44: 31.678867 | AB44: 31.934574 | AC44: 32.173542 | AD44: 32.373512 | AE44: 32.546021 | AF44: 32.886066 | AG44: 0.001638
A45: SUP000:fa_Coal | B45: Coal 11/ | C45: 10.883375 | D45: 10.484755 | E45: 9.873912 | F45: 8.510278 | G45: 8.140191 | H45: 7.937951 | I45: 7.705096 | J45: 7.669232 | K45: 7.61521 | L45: 7.464706 | M45: 7.393437 | N45: 7.246166 | O45: 7.293676 | P45: 6.99925 | Q45: 6.700851 | R45: 6.583507 | S45: 6.461794 | T45: 6.44173 | U45: 6.426641 | V45: 6.337152 | W45: 6.326757 | X45: 6.277361 | Y45: 6.194617 | Z45: 6.127982 | AA45: 6.00381 | AB45: 5.957881 | AC45: 5.866497 | AD45: 5.765072 | AE45: 5.717658 | AF45: 5.766378 | AG45: -0.021665
A46: SUP000:fa_NuclearPower | B46: Nuclear / Uranium 2/ | C46: 8.12115 | D46: 8.183111 | E46: 8.202579 | F46: 8.239058 | G46: 8.163899 | H46: 8.075755 | I46: 7.930267 | J46: 7.368946 | K46: 7.299504 | L46: 7.307006 | M46: 7.318423 | N46: 7.326343 | O46: 6.808416 | P46: 6.815667 | Q46: 6.747447 | R46: 6.758354 | S46: 6.760554 | T46: 6.762659 | U46: 6.762759 | V46: 6.766273 | W46: 6.77936 | X46: 6.788805 | Y46: 6.797936 | Z46: 6.805902 | AA46: 6.814445 | AB46: 6.818903 | AC46: 6.823349 | AD46: 6.826119 | AE46: 6.829472 | AF46: 6.834313 | AG46: -0.005931
A47: SUP000:fa_Hydropower | B47: Conventional Hydroelectric Power | C47: 2.288529 | D47: 2.39653 | E47: 2.520376 | F47: 2.607582 | G47: 2.562303 | H47: 2.533515 | I47: 2.5148 | J47: 2.494481 | K47: 2.48263 | L47: 2.471396 | M47: 2.456771 | N47: 2.450083 | O47: 2.436512 | P47: 2.4271 | Q47: 2.410605 | R47: 2.397023 | S47: 2.392663 | T47: 2.381657 | U47: 2.376802 | V47: 2.37014 | W47: 2.362096 | X47: 2.354189 | Y47: 2.3427 | Z47: 2.33699 | AA47: 2.32513 | AB47: 2.318443 | AC47: 2.309026 | AD47: 2.304834 | AE47: 2.295233 | AF47: 2.274688 | AG47: -0.000209
A48: SUP000:fa_Biomass | B48: Biomass 12/ | C48: 3.124412 | D48: 3.124567 | E48: 3.05355 | F48: 3.045954 | G48: 3.05583 | H48: 3.041447 | I48: 3.026574 | J48: 3.002259 | K48: 2.992482 | L48: 2.980528 | M48: 2.965883 | N48: 2.956268 | O48: 2.939253 | P48: 2.923384 | Q48: 2.911871 | R48: 2.900167 | S48: 2.888609 | T48: 2.879169 | U48: 2.882052 | V48: 2.872139 | W48: 2.872755 | X48: 2.872178 | Y48: 2.879459 | Z48: 2.883198 | AA48: 2.883371 | AB48: 2.891699 | AC48: 2.900502 | AD48: 2.911157 | AE48: 2.913831 | AF48: 2.933004 | AG48: -0.002178
A49: SUP000:fa_RenewableEner | B49: Other Renewable Energy 4/ | C49: 4.839005 | D49: 5.544484 | E49: 6.085557 | F49: 6.989227 | G49: 7.561359 | H49: 7.846316 | I49: 8.347466 | J49: 8.5777 | K49: 8.787159 | L49: 9.155986 | M49: 9.41178 | N49: 9.649215 | O49: 9.910384 | P49: 10.464489 | Q49: 11.17978 | R49: 11.560812 | S49: 11.709242 | T49: 11.735645 | U49: 11.787336 | V49: 11.864063 | W49: 11.965893 | X49: 12.084974 | Y49: 12.202391 | Z49: 12.369851 | AA49: 12.586577 | AB49: 12.70438 | AC49: 12.871214 | AD49: 13.03612 | AE49: 13.182046 | AF49: 13.273847 | AG49: 0.035408
A50: SUP000:fa_Other | B50: Other 13/ | C50: 0.336373 | D50: 0.277024 | E50: 0.26214 | F50: 0.265242 | G50: 0.255492 | H50: 0.260431 | I50: 0.273827 | J50: 0.282621 | K50: 0.284219 | L50: 0.291907 | M50: 0.28379 | N50: 0.288546 | O50: 0.281913 | P50: 0.287158 | Q50: 0.284342 | R50: 0.284106 | S50: 0.279065 | T50: 0.281331 | U50: 0.282285 | V50: 0.284222 | W50: 0.2793 | X50: 0.27926 | Y50: 0.280125 | Z50: 0.279916 | AA50: 0.275945 | AB50: 0.27593 | AC50: 0.275795 | AD50: 0.276476 | AE50: 0.276908 | AF50: 0.27742 | AG50: -0.006622
A51: SUP000:fa_Total | B51: Total | C51: 96.993172 | D51: 97.964294 | E51: 98.340576 | F51: 97.835297 | G51: 97.697876 | H51: 97.466995 | I51: 97.110069 | J51: 96.846138 | K51: 96.635994 | L51: 96.519226 | M51: 96.464584 | N51: 96.546318 | O51: 96.44191 | P51: 96.301994 | Q51: 96.255463 | R51: 96.349693 | S51: 96.487396 | T51: 96.648209 | U51: 96.924149 | V51: 97.07666 | W51: 97.297112 | X51: 97.575439 | Y51: 97.931641 | Z51: 98.216454 | AA51: 98.512177 | AB51: 98.990181 | AC51: 99.420959 | AD51: 99.767052 | AE51: 100.15404 | AF51: 100.8739 | AG51: 0.001354
B53: Prices (2021 dollars per unit)
A54: SUP000:ha_WorldOilPrice | B54: Brent Spot Price (dollars per barrel) | C54: 71.587997 | D54: 69.66571 | E54: 60.115009 | F54: 65.487526 | G54: 66.944946 | H54: 68.336487 | I54: 70.188248 | J54: 71.247108 | K54: 72.276756 | L54: 73.089027 | M54: 74.201714 | N54: 75.693771 | O54: 76.516808 | P54: 77.011726 | Q54: 77.511917 | R54: 77.914551 | S54: 79.12043 | T54: 79.949265 | U54: 80.107307 | V54: 81.746223 | W54: 82.892479 | X54: 83.244728 | Y54: 84.953598 | Z54: 86.823944 | AA54: 87.048103 | AB54: 88.261673 | AC54: 88.154121 | AD54: 88.15358 | AE54: 88.626503 | AF54: 88.049568 | AG54: 0.007163
A55: SUP000:ha_ForLowSulfLit | B55: West Texas Intermediate Spot Price (dollars per barrel | C55: 69.023003 | D55: 66.150894 | E55: 58.565804 | F55: 63.481312 | G55: 64.71344 | H55: 65.889473 | I55: 67.33989 | J55: 68.79483 | K55: 69.806862 | L55: 70.71656 | M55: 71.664322 | N55: 73.149719 | O55: 74.028023 | P55: 74.299271 | Q55: 74.585869 | R55: 74.74485 | S55: 75.858505 | T55: 76.686295 | U55: 76.795464 | V55: 78.57148 | W55: 79.729446 | X55: 80.188103 | Y55: 81.850861 | Z55: 83.591797 | AA55: 84.018883 | AB55: 85.136871 | AC55: 85.34671 | AD55: 85.364227 | AE55: 85.855141 | AF55: 85.23468 | AG55: 0.007301
A56: SUP000:ha_GasPriceHenry | B56: Natural Gas at Henry Hub (dollars per mmBtu) | C56: 4.115437 | D56: 3.837557 | E56: 3.471147 | F56: 3.126585 | G56: 2.953741 | H56: 2.906966 | I56: 2.954549 | J56: 3.136157 | K56: 3.292231 | L56: 3.388971 | M56: 3.454448 | N56: 3.491858 | O56: 3.59329 | P56: 3.594153 | Q56: 3.524364 | R56: 3.485305 | S56: 3.48693 | T56: 3.51827 | U56: 3.545613 | V56: 3.577658 | W56: 3.63465 | X56: 3.652029 | Y56: 3.589562 | Z56: 3.561126 | AA56: 3.469676 | AB56: 3.425366 | AC56: 3.400315 | AD56: 3.392432 | AE56: 3.403568 | AF56: 3.409512 | AG56: -0.006468
A57: SUP000:ha_CoalMinemouth | B57: Coal, Minemouth (dollars per ton) 14/ | C57: 36.126965 | D57: 33.048691 | E57: 33.697308 | F57: 34.915207 | G57: 33.191757 | H57: 31.716324 | I57: 31.066441 | J57: 30.505335 | K57: 30.725069 | L57: 30.714941 | M57: 30.711941 | N57: 30.82056 | O57: 31.028635 | P57: 31.325903 | Q57: 31.308147 | R57: 31.61187 | S57: 32.129681 | T57: 32.22797 | U57: 32.280781 | V57: 32.69191 | W57: 32.910851 | X57: 32.751488 | Y57: 33.197136 | Z57: 33.294754 | AA57: 33.901966 | AB57: 34.154438 | AC57: 34.402786 | AD57: 34.352524 | AE57: 34.457165 | AF57: 34.526253 | AG57: -0.001562
A58: SUP000:ha_CoalMineBtu | B58: Coal, Minemouth (dollars per million Btu) 14/ | C58: 1.753047 | D58: 1.605396 | E58: 1.612716 | F58: 1.644811 | G58: 1.57868 | H58: 1.524597 | I58: 1.498204 | J58: 1.483403 | K58: 1.4923 | L58: 1.492875 | M58: 1.493347 | N58: 1.493653 | O58: 1.496539 | P58: 1.510248 | Q58: 1.511186 | R58: 1.522797 | S58: 1.536004 | T58: 1.543051 | U58: 1.547495 | V58: 1.564056 | W58: 1.574198 | X58: 1.569195 | Y58: 1.586313 | Z58: 1.590278 | AA58: 1.607756 | AB58: 1.618476 | AC58: 1.629431 | AD58: 1.629268 | AE58: 1.634834 | AF58: 1.639391 | AG58: -0.002309
A59: SUP000:ha_CoalDelivered | B59: Coal, Delivered (dollars per million Btu) 15/ | C59: 2.229239 | D59: 2.108559 | E59: 2.109313 | F59: 2.118861 | G59: 2.072601 | H59: 2.05201 | I59: 2.039511 | J59: 2.031738 | K59: 2.042039 | L59: 2.041963 | M59: 2.03813 | N59: 2.033941 | O59: 2.027794 | P59: 2.031424 | Q59: 2.01707 | R59: 2.01048 | S59: 2.012397 | T59: 2.00864 | U59: 2.008059 | V59: 2.010775 | W59: 2.014587 | X59: 2.002263 | Y59: 2.00309 | Z59: 2.000369 | AA59: 2.000631 | AB59: 2.001826 | AC59: 1.997227 | AD59: 1.985802 | AE59: 1.98377 | AF59: 1.981437 | AG59: -0.004055
A60: SUP000:ha_Electricity(c | B60: Electricity (cents per kilowatthour) | C60: 11.09206 | D60: 10.975097 | E60: 10.752557 | F60: 10.540874 | G60: 10.475073 | H60: 10.501468 | I60: 10.507842 | J60: 10.52357 | K60: 10.553371 | L60: 10.551203 | M60: 10.580885 | N60: 10.611277 | O60: 10.653981 | P60: 10.67311 | Q60: 10.574654 | R60: 10.500532 | S60: 10.454601 | T60: 10.40737 | U60: 10.364239 | V60: 10.379671 | W60: 10.349372 | X60: 10.349371 | Y60: 10.292791 | Z60: 10.252166 | AA60: 10.25128 | AB60: 10.175208 | AC60: 10.157688 | AD60: 10.123593 | AE60: 10.092719 | AF60: 10.021296 | AG60: -0.003494
B63: Prices (nominal dollars per unit)
A64: SUP000:nom_ImportRACost | B64: Brent Spot Price (dollars per barrel) | C64: 71.587997 | D64: 71.908997 | E64: 63.61998 | F64: 71.373055 | G64: 75.273743 | H64: 79.457573 | I64: 84.49556 | J64: 88.816948 | K64: 93.240852 | L64: 97.461693 | M64: 102.24275 | N64: 107.67736 | O64: 112.40005 | P64: 116.90786 | Q64: 121.68389 | R64: 126.52406 | S64: 132.93751 | T64: 138.98383 | U64: 144.0029 | V64: 152.01515 | W64: 159.44214 | X64: 165.62906 | Y64: 174.78682 | Z64: 184.65153 | AA64: 191.32927 | AB64: 200.49499 | AC64: 206.9554 | AD64: 213.82344 | AE64: 221.99219 | AF64: 227.62056 | AG64: 0.040694
A65: SUP000:nom_ForLowSulfLi | B65: West Texas Intermediate Spot Price (dollars per barrel | C65: 69.023003 | D65: 68.280998 | E65: 61.980446 | F65: 69.186539 | G65: 72.76461 | H65: 76.612328 | I65: 81.066589 | J65: 85.759926 | K65: 90.05455 | L65: 94.298096 | M65: 98.746475 | N65: 104.05834 | O65: 108.74414 | P65: 112.79021 | Q65: 117.09036 | R65: 121.37684 | S65: 127.45686 | T65: 133.31148 | U65: 138.04945 | V65: 146.11139 | W65: 153.35812 | X65: 159.54741 | Y65: 168.40314 | Z65: 177.7776 | AA65: 184.67111 | AB65: 193.3967 | AC65: 200.36456 | AD65: 207.05765 | AE65: 215.05046 | AF65: 220.34367 | AG65: 0.040838
A66: SUP000:nom_Gas@HenryHub | B66: Natural Gas at Henry Hub (dollars per mmBtu) | C66: 4.115437 | D66: 3.961129 | E66: 3.67353 | F66: 3.407579 | G66: 3.321223 | H66: 3.380046 | I66: 3.55681 | J66: 3.909547 | K66: 4.247153 | L66: 4.519075 | M66: 4.759894 | N66: 4.967306 | O66: 5.278396 | P66: 5.456114 | Q66: 5.532805 | R66: 5.659725 | S66: 5.858712 | T66: 6.116162 | U66: 6.373682 | V66: 6.653007 | W66: 6.991181 | X66: 7.266311 | Y66: 7.385303 | Z66: 7.573573 | AA66: 7.62625 | AB66: 7.781052 | AC66: 7.982764 | AD66: 8.228611 | AE66: 8.525277 | AF66: 8.814068 | AG66: 0.02661
A67: SUP000:nom_CoalMinemout | B67: Coal, Minemouth (dollars per ton) 14/ | C67: 36.126965 | D67: 34.112881 | E67: 35.66201 | F67: 38.053123 | G67: 37.321236 | H67: 36.877842 | I67: 37.399086 | J67: 38.02808 | K67: 39.636967 | L67: 40.957314 | M67: 42.318069 | N67: 43.843456 | O67: 45.579796 | P67: 47.554371 | Q67: 49.149826 | R67: 51.333954 | S67: 53.984035 | T67: 56.025112 | U67: 58.02874 | V67: 60.793827 | W67: 63.30341 | X67: 65.164467 | Y67: 68.301071 | Z67: 70.80912 | AA67: 74.515556 | AB67: 77.585136 | AC67: 80.765846 | AD67: 83.324745 | AE67: 86.30851 | AF67: 89.255226 | AG67: 0.03168
A68: SUP000:nom_CoalMineBtu | B68: Coal, Minemouth (dollars per million Btu) 14/ | C68: 1.753047 | D68: 1.65709 | E68: 1.706745 | F68: 1.792635 | G68: 1.775088 | H68: 1.77271 | I68: 1.803601 | J68: 1.849217 | K68: 1.925146 | L68: 1.990697 | M68: 2.057687 | N68: 2.124779 | O68: 2.198354 | P68: 2.292636 | Q68: 2.37237 | R68: 2.472843 | S68: 2.580781 | T68: 2.68244 | U68: 2.781816 | V68: 2.908517 | W68: 3.02794 | X68: 3.122171 | Y68: 3.263741 | Z68: 3.3821 | AA68: 3.533802 | AB68: 3.676526 | AC68: 3.825341 | AD68: 3.951918 | AE68: 4.094942 | AF68: 4.238058 | AG68: 0.030908
A69: SUP000:nom_CoalDeliverd | B69: Coal, Delivered (dollars per million Btu) 15/ | C69: 2.229239 | D69: 2.176456 | E69: 2.232296 | F69: 2.309288 | G69: 2.330459 | H69: 2.385954 | I69: 2.455249 | J69: 2.532773 | K69: 2.634339 | L69: 2.722887 | M69: 2.808344 | N69: 2.89336 | O69: 2.978747 | P69: 3.083808 | Q69: 3.166544 | R69: 3.264783 | S69: 3.381214 | T69: 3.491821 | U69: 3.609737 | V69: 3.739234 | W69: 3.875021 | X69: 3.98383 | Y69: 4.121235 | Z69: 4.254254 | AA69: 4.397331 | AB69: 4.547344 | AC69: 4.688799 | AD69: 4.81672 | AE69: 4.968959 | AF69: 5.122294 | AG69: 0.029103
A70: SUP000:nom_Electricity | B70: Electricity (cents per kilowatthour) | C70: 11.09206 | D70: 11.328503 | E70: 11.379478 | F70: 11.48821 | G70: 11.778304 | H70: 12.210477 | I70: 12.649781 | J70: 13.118728 | K70: 13.614408 | L70: 14.069665 | M70: 14.579432 | N70: 15.094956 | O70: 15.650263 | P70: 16.202343 | Q70: 16.600866 | R70: 17.051628 | S70: 17.565737 | T70: 18.092175 | U70: 18.631014 | V70: 19.302019 | W70: 19.906824 | X70: 20.591772 | Y70: 21.176786 | Z70: 21.803642 | AA70: 22.532022 | AB70: 23.113977 | AC70: 23.846741 | AD70: 24.555573 | AE70: 25.280302 | AF70: 25.906462 | AG70: 0.029682
B72: 1/ Includes waste coal.
B73: 2/ These values represent the energy obtained from uranium when it is used in light water reactors. The total energy content of uranium
B74: is much larger, but alternative processes are required to take advantage of it.
B75: 3/ Includes grid-connected electricity from wood and wood waste; biomass, such as corn, used for liquid fuels production; and nonelectric
B76: energy demand from wood. Refer to Table 17 for details.
B77: 4/ Includes grid-connected electricity from landfill gas; biogenic municipal waste; wind; photovoltaic and solar thermal sources; and
B78: nonelectric energy from renewable sources, such as active and passive solar systems. Excludes electricity imports using renewable sources
B79: and nonmarketed renewable energy. See Table 17 for selected nonmarketed residential and commercial renewable energy data.
B80: 5/ Includes non-biogenic municipal waste, hydrogen, methanol, and some domestic inputs to refineries.
B81: 6/ Includes imports of finished petroleum products, unfinished oils, alcohols, ethers, blending components, and renewable fuels such as ethanol.
B82: 7/ Includes coal, coal coke (net), and electricity (net). Excludes imports of fuel used in nuclear power plants.
B83: 8/ Includes crude oil, petroleum products, ethanol, and biodiesel.
... B100: National Energy Modeling System run ref2022.d011222a. Projections: EIA, AEO2022 National Energy Modeling System run ref2022.d011222a.

Sheet AEO 2023 Table 1
B1: ref2023.d020623a | C1: 2022 | D1: 2023 | E1: 2024 | F1: 2025 | G1: 2026 | H1: 2027 | I1: 2028 | J1: 2029 | K1: 2030 | L1: 2031 | M1: 2032 | N1: 2033 | O1: 2034 | P1: 2035 | Q1: 2036 | R1: 2037 | S1: 2038 | T1: 2039 | U1: 2040 | V1: 2041 | W1: 2042 | X1: 2043 | Y1: 2044 | Z1: 2045 | AA1: 2046 | AB1: 2047 | AC1: 2048 | AD1: 2049 | AE1: 2050
C3: Report | D3: Annual Energy Outlook 2023
C4: Scenario | D4: ref2023 | G4: Reference
C5: Datekey | D5: d020623a
C6: Release Date | E6: March 2023
A10: SUP000 | B10: 1. Total Energy Supply, Disposition, and Price Summary | AF10: Average
B11: (quadrillion Btu, unless otherwise noted) | AF11: Annual
AF12: Change
B13: Supply, Disposition, and Prices | C13: 2022 | D13: 2023 | E13: 2024 | F13: 2025 | G13: 2026 | H13: 2027 | I13: 2028 | J13: 2029 | K13: 2030 | L13: 2031 | M13: 2032 | N13: 2033 | O13: 2034 | P13: 2035 | Q13: 2036 | R13: 2037 | S13: 2038 | T13: 2039 | U13: 2040 | V13: 2041 | W13: 2042 | X13: 2043 | Y13: 2044 | Z13: 2045 | AA13: 2046 | AB13: 2047 | AC13: 2048 | AD13: 2049 | AE13: 2050 | AF13: 2022–2050
B15: Production
A16: SUP000:ba_CrudeOilLease | B16: Crude Oil and Lease Condensate | C16: 24.586992 | D16: 25.571161 | E16: 26.28504 | F16: 26.689157 | G16: 27.061613 | H16: 27.276854 | I16: 27.645002 | J16: 27.607613 | K16: 27.657637 | L16: 27.504726 | M16: 27.566185 | N16: 27.626516 | O16: 27.525274 | P16: 27.454479 | Q16: 27.324806 | R16: 27.286285 | S16: 27.180134 | T16: 27.06955 | U16: 26.857201 | V16: 26.565493 | W16: 26.618496 | X16: 26.76222 | Y16: 27.042204 | Z16: 27.108969 | AA16: 27.167717 | AB16: 26.948446 | AC16: 27.031092 | AD16: 27.320032 | AE16: 27.390823 | AF16: 0.003864
A17: SUP000:ba_NaturalGasPla | B17: Natural Gas Plant Liquids | C17: 7.768493 | D17: 8.169656 | E17: 8.33212 | F17: 8.311151 | G17: 8.472385 | H17: 8.339916 | I17: 8.228629 | J17: 8.126106 | K17: 8.05903 | L17: 8.040661 | M17: 8.113167 | N17: 8.167894 | O17: 8.280707 | P17: 8.339736 | Q17: 8.463762 | R17: 8.517173 | S17: 8.518053 | T17: 8.645661 | U17: 8.632603 | V17: 8.691146 | W17: 8.843096 | X17: 8.967008 | Y17: 9.032116 | Z17: 9.079972 | AA17: 9.143809 | AB17: 9.19521 | AC17: 9.236042 | AD17: 9.282736 | AE17: 9.310446 | AF17: 0.006487
A18: SUP000:ba_DryNaturalGas | B18: Dry Natural Gas | C18: 37.814274 | D18: 37.835823 | E18: 36.882996 | F18: 37.047318 | G18: 37.522251 | H18: 37.473186 | I18: 37.786018 | J18: 38.036835 | K18: 38.406055 | L18: 38.853168 | M18: 39.378105 | N18: 39.977421 | O18: 40.490608 | P18: 40.958794 | Q18: 41.332081 | R18: 41.707432 | S18: 41.989216 | T18: 42.240601 | U18: 42.38311 | V18: 42.506451 | W18: 42.687958 | X18: 42.804451 | Y18: 42.884609 | Z18: 43.041492 | AA18: 42.870251 | AB18: 43.082157 | AC18: 43.152935 | AD18: 43.235588 | AE18: 43.621796 | AF18: 0.005116
A19: SUP000:ba_Coal | B19: Coal 1/ | C19: 11.789563 | D19: 11.071955 | E19: 12.067057 | F19: 11.332017 | G19: 10.370732 | H19: 9.303524 | I19: 8.355421 | J19: 7.463985 | K19: 7.094864 | L19: 7.063365 | M19: 7.113411 | N19: 7.082268 | O19: 7.01697 | P19: 7.068785 | Q19: 6.985933 | R19: 6.801968 | S19: 6.692012 | T19: 6.533113 | U19: 6.437759 | V19: 6.442639 | W19: 6.454122 | X19: 6.36397 | Y19: 6.262532 | Z19: 6.188755 | AA19: 6.119871 | AB19: 6.087613 | AC19: 6.069883 | AD19: 6.032045 | AE19: 5.945596 | AF19: -0.024152
A20: SUP000:ba_NuclearPower | B20: Nuclear / Uranium 2/ | C20: 8.064654 | D20: 8.187211 | E20: 8.246629 | F20: 8.171966 | G20: 8.092857 | H20: 8.092719 | I20: 7.997469 | J20: 7.99734 | K20: 7.918744 | L20: 7.918797 | M20: 7.918885 | N20: 7.47281 | O20: 7.403218 | P20: 7.313933 | Q20: 7.145817 | R20: 7.031636 | S20: 6.837198 | T20: 6.734248 | U20: 6.533641 | V20: 6.535408 | W20: 6.538529 | X20: 6.541202 | Y20: 6.544166 | Z20: 6.544192 | AA20: 6.541663 | AB20: 6.539629 | AC20: 6.530636 | AD20: 6.531871 | AE20: 6.527707 | AF20: -0.007523
A21: SUP000:ba_Hydropower | B21: Conventional Hydroelectric Power | C21: 2.453454 | D21: 2.458462 | E21: 2.502563 | F21: 2.588684 | G21: 2.579723 | H21: 2.556826 | I21: 2.515381 | J21: 2.486196 | K21: 2.457424 | L21: 2.43646 | M21: 2.419676 | N21: 2.422381 | O21: 2.426406 | P21: 2.429998 | Q21: 2.435315 | R21: 2.423512 | S21: 2.41015 | T21: 2.386208 | U21: 2.381421 | V21: 2.366141 | W21: 2.369409 | X21: 2.362637 | Y21: 2.357599 | Z21: 2.354464 | AA21: 2.343242 | AB21: 2.336414 | AC21: 2.334075 | AD21: 2.320942 | AE21: 2.309024 | AF21: -0.002164
A22: SUP000:ba_Biomass | B22: Biomass 3/ | C22: 4.838805 | D22: 5.032741 | E22: 4.964215 | F22: 4.912142 | G22: 4.886052 | H22: 4.875721 | I22: 4.769737 | J22: 4.767001 | K22: 4.765035 | L22: 4.767915 | M22: 4.773014 | N22: 4.782948 | O22: 4.793034 | P22: 4.817472 | Q22: 4.818559 | R22: 4.826615 | S22: 4.834418 | T22: 4.844079 | U22: 4.857975 | V22: 4.892778 | W22: 4.909179 | X22: 4.92593 | Y22: 4.924026 | Z22: 4.93202 | AA22: 4.970815 | AB22: 5.019265 | AC22: 5.10552 | AD22: 5.154455 | AE22: 5.188916 | AF22: 0.002498
A23: SUP000:ba_RenewableEner | B23: Other Renewable Energy 4/ | C23: 5.622848 | D23: 6.12555 | E23: 6.742159 | F23: 8.173244 | G23: 9.907674 | H23: 11.653165 | I23: 13.154488 | J23: 14.209772 | K23: 15.128234 | L23: 15.78889 | M23: 16.442295 | N23: 17.189573 | O23: 17.791294 | P23: 18.262888 | Q23: 18.746868 | R23: 19.110622 | S23: 19.414564 | T23: 19.60931 | U23: 19.90523 | V23: 20.063116 | W23: 20.302187 | X23: 20.584305 | Y23: 20.993839 | Z23: 21.370592 | AA23: 21.805227 | AB23: 22.17202 | AC23: 22.539532 | AD23: 22.84026 | AE23: 23.283979 | AF23: 0.052057
A24: SUP000:ba_Other | B24: Other 5/ | C24: 1.82513 | D24: 1.234037 | E24: 0.928669 | F24: 0.803857 | G24: 0.909898 | H24: 0.90237 | I24: 0.841003 | J24: 0.828401 | K24: 0.836635 | L24: 0.837526 | M24: 0.71289 | N24: 0.708538 | O24: 0.71509 | P24: 0.709654 | Q24: 0.706237 | R24: 0.703952 | S24: 0.704838 | T24: 0.704036 | U24: 0.700627 | V24: 0.702727 | W24: 0.700445 | X24: 0.699926 | Y24: 0.700781 | Z24: 0.700645 | AA24: 0.677574 | AB24: 0.674621 | AC24: 0.677692 | AD24: 0.678272 | AE24: 0.675773 | AF24: -0.034862
A25: SUP000:ba_Total | B25: Total | C25: 104.76421 | D25: 105.6866 | E25: 106.95145 | F25: 108.02953 | G25: 109.80318 | H25: 110.47428 | I25: 111.29315 | J25: 111.52324 | K25: 112.32366 | L25: 113.21151 | M25: 114.43762 | N25: 115.43036 | O25: 116.4426 | P25: 117.35574 | Q25: 117.95938 | R25: 118.4092 | S25: 118.58059 | T25: 118.76679 | U25: 118.68956 | V25: 118.76591 | W25: 119.42342 | X25: 120.01164 | Y25: 120.74187 | Z25: 121.3211 | AA25: 121.64017 | AB25: 122.05538 | AC25: 122.67742 | AD25: 123.39619 | AE25: 124.25407 | AF25: 0.006112
B27: Imports
A28: SUP000:ca_CrudeOil | B28: Crude Oil | C28: 13.824968 | D28: 14.777425 | E28: 15.446031 | F28: 15.30518 | G28: 15.0045 | H28: 15.261106 | I28: 15.230433 | J28: 15.49168 | K28: 15.589063 | L28: 15.686406 | M28: 15.720078 | N28: 15.538974 | O28: 15.709466 | P28: 15.851457 | Q28: 15.843707 | R28: 15.807153 | S28: 15.874156 | T28: 15.984639 | U28: 16.045517 | V28: 16.390509 | W28: 16.327881 | X28: 16.155361 | Y28: 15.890744 | Z28: 15.766374 | AA28: 15.490686 | AB28: 15.523278 | AC28: 15.392778 | AD28: 15.059613 | AE28: 14.806977 | AF28: 0.002454
A29: SUP000:ca_PetroleumProd | B29: Petroleum and Other Liquids 6/ | C29: 4.758858 | D29: 4.839342 | E29: 4.030089 | F29: 4.034095 | G29: 4.035874 | H29: 3.992856 | I29: 3.913863 | J29: 3.837766 | K29: 3.804423 | L29: 3.806296 | M29: 3.740932 | N29: 3.718116 | O29: 3.68477 | P29: 3.681871 | Q29: 3.670537 | R29: 3.681304 | S29: 3.685072 | T29: 3.692872 | U29: 3.702409 | V29: 3.723368 | W29: 3.718675 | X29: 3.725362 | Y29: 3.717126 | Z29: 3.747543 | AA29: 3.722438 | AB29: 3.744125 | AC29: 3.816768 | AD29: 3.836668 | AE29: 3.767644 | AF29: -0.008307
A30: SUP000:ca_NaturalGas | B30: Natural Gas | C30: 2.981649 | D30: 2.808482 | E30: 2.461069 | F30: 2.35087 | G30: 2.25211 | H30: 2.184048 | I30: 2.073739 | J30: 2.040553 | K30: 2.072865 | L30: 2.06794 | M30: 2.11868 | N30: 2.137902 | O30: 2.141702 | P30: 2.125696 | Q30: 2.080384 | R30: 2.079351 | S30: 2.136969 | T30: 2.11006 | U30: 2.231398 | V30: 2.256781 | W30: 2.269709 | X30: 2.318002 | Y30: 2.40196 | Z30: 2.477401 | AA30: 2.508059 | AB30: 2.53545 | AC30: 2.582582 | AD30: 2.599269 | AE30: 2.627204 | AF30: -0.00451
A31: SUP000:ca_OtherImports | B31: Other 7/ | C31: 0.25367 | D31: 0.337121 | E31: 0.14549 | F31: 0.130841 | G31: 0.141319 | H31: 0.155275 | I31: 0.177303 | J31: 0.169148 | K31: 0.176284 | L31: 0.166932 | M31: 0.170314 | N31: 0.169336 | O31: 0.170398 | P31: 0.165942 | Q31: 0.164005 | R31: 0.163859 | S31: 0.167017 | T31: 0.16908 | U31: 0.170614 | V31: 0.166044 | W31: 0.165721 | X31: 0.163252 | Y31: 0.161465 | Z31: 0.158517 | AA31: 0.155057 | AB31: 0.154695 | AC31: 0.157649 | AD31: 0.15918 | AE31: 0.157261 | AF31: -0.016931
A32: SUP000:ca_Total | B32: Total | C32: 21.819145 | D32: 22.762371 | E32: 22.08268 | F32: 21.820986 | G32: 21.433804 | H32: 21.593285 | I32: 21.395336 | J32: 21.539146 | K32: 21.642633 | L32: 21.727573 | M32: 21.750002 | N32: 21.564329 | O32: 21.706337 | P32: 21.824965 | Q32: 21.758633 | R32: 21.731667 | S32: 21.863213 | T32: 21.956652 | U32: 22.149939 | V32: 22.536701 | W32: 22.481985 | X32: 22.361977 | Y32: 22.171295 | Z32: 22.149836 | AA32: 21.876242 | AB32: 21.957548 | AC32: 21.949778 | AD32: 21.654732 | AE32: 21.359085 | AF32: -0.000761
B34: Exports
A35: SUP000:da_Petroleum | B35: Petroleum and Other Liquids 8/ | C35: 18.53616 | D35: 19.04047 | E35: 20.328047 | F35: 20.57988 | G35: 21.071783 | H35: 21.489708 | I35: 21.636562 | J35: 21.880472 | K35: 22.202881 | L35: 22.327625 | M35: 22.464676 | N35: 22.515352 | O35: 22.756023 | P35: 22.978777 | Q35: 23.076605 | R35: 23.112068 | S35: 23.121672 | T35: 23.267797 | U35: 23.053844 | V35: 23.139196 | W35: 23.210157 | X35: 23.236942 | Y35: 23.218386 | Z35: 23.136253 | AA35: 22.799206 | AB35: 22.53091 | AC35: 22.513948 | AD35: 22.402639 | AE35: 21.931286 | AF35: 0.006025
A36: SUP000:da_NaturalGas | B36: Natural Gas | C36: 7.157014 | D36: 7.945881 | E36: 7.943815 | F36: 8.33703 | G36: 8.842743 | H36: 9.263846 | I36: 9.664758 | J36: 10.022476 | K36: 10.671082 | L36: 11.372363 | M36: 12.069704 | N36: 12.747917 | O36: 13.325287 | P36: 13.720263 | Q36: 13.973807 | R36: 14.186524 | S36: 14.301539 | T36: 14.335634 | U36: 14.360343 | V36: 14.349729 | W36: 14.358644 | X36: 14.365799 | Y36: 14.408306 | Z36: 14.392715 | AA36: 14.375298 | AB36: 14.355018 | AC36: 14.358721 | AD36: 14.323404 | AE36: 14.304577 | AF36: 0.02504
A37: SUP000:da_Coal | B37: Coal | C37: 2.154573 | D37: 2.143556 | E37: 2.779966 | F37: 2.715976 | G37: 2.848135 | H37: 2.810707 | I37: 2.822736 | J37: 2.808787 | K37: 2.810107 | L37: 2.838428 | M37: 2.89129 | N37: 2.819009 | O37: 2.79456 | P37: 2.821391 | Q37: 2.784587 | R37: 2.726998 | S37: 2.770777 | T37: 2.712615 | U37: 2.722989 | V37: 2.708216 | W37: 2.723382 | X37: 2.690624 | Y37: 2.694831 | Z37: 2.703859 | AA37: 2.688675 | AB37: 2.682404 | AC37: 2.70565 | AD37: 2.707865 | AE37: 2.723995 | AF37: 0.00841
A38: SUP000:da_Total | B38: Total | C38: 27.847746 | D38: 29.129908 | E38: 31.051828 | F38: 31.632887 | G38: 32.762661 | H38: 33.564262 | I38: 34.124054 | J38: 34.711735 | K38: 35.684071 | L38: 36.538418 | M38: 37.425667 | N38: 38.082275 | O38: 38.87587 | P38: 39.520432 | Q38: 39.834999 | R38: 40.025589 | S38: 40.193985 | T38: 40.316048 | U38: 40.137177 | V38: 40.197144 | W38: 40.292183 | X38: 40.293365 | Y38: 40.321526 | Z38: 40.232826 | AA38: 39.863178 | AB38: 39.568333 | AC38: 39.57832 | AD38: 39.43391 | AE38: 38.959858 | AF38: 0.012064
A40: SUP000:ea_Discrepancy | B40: Discrepancy 9/ | C40: -0.457861 | D40: 0.97529 | E40: 0.423643 | F40: 0.464403 | G40: 0.459312 | H40: 0.424484 | I40: 0.430447 | J40: 0.294971 | K40: 0.325535 | L40: 0.400856 | M40: 0.449509 | N40: 0.447327 | O40: 0.453705 | P40: 0.532143 | Q40: 0.48624 | R40: 0.46405 | S40: 0.455482 | T40: 0.450829 | U40: 0.450035 | V40: 0.45557 | W40: 0.44809 | X40: 0.438515 | Y40: 0.440971 | Z40: 0.547066 | AA40: 0.476925 | AB40: 0.612675 | AC40: 0.563404 | AD40: 0.513699 | AE40: 0.713924 | AF40: --
B42: Consumption
A43: SUP000:fa_PetroleumProd | B43: Petroleum and Other Liquids 10/ | C43: 36.816776 | D43: 36.981636 | E43: 36.540516 | F43: 36.38258 | G43: 36.236435 | H43: 36.093872 | I43: 35.925087 | J43: 35.71246 | K43: 35.460438 | L43: 35.244152 | M43: 35.085304 | N43: 34.948364 | O43: 34.86829 | P43: 34.774864 | Q43: 34.660748 | R43: 34.614304 | S43: 34.581387 | T43: 34.574551 | U43: 34.635841 | V43: 34.700855 | W43: 34.772816 | X43: 34.84396 | Y43: 34.938004 | Z43: 35.050571 | AA43: 35.202904 | AB43: 35.394215 | AC43: 35.548607 | AD43: 35.727844 | AE43: 35.995079 | AF43: -0.000806
A44: SUP000:fa_NaturalGas | B44: Natural Gas | C44: 33.183849 | D44: 31.975372 | E44: 30.744192 | F44: 30.454859 | G44: 30.362862 | H44: 29.860353 | I44: 29.690903 | J44: 29.540802 | K44: 29.285072 | L44: 29.002975 | M44: 28.86751 | N44: 28.778568 | O44: 28.707445 | P44: 28.712893 | Q44: 28.819685 | R44: 28.978542 | S44: 29.210226 | T44: 29.397072 | U44: 29.632147 | V44: 29.788446 | W44: 29.983868 | X44: 30.153929 | Y44: 30.279633 | Z44: 30.429348 | AA44: 30.410452 | AB44: 30.539183 | AC44: 30.747511 | AD44: 30.902693 | AE44: 31.130543 | AF44: -0.002279
A45: SUP000:fa_Coal | B45: Coal 11/ | C45: 9.694483 | D45: 9.040522 | E45: 9.411029 | F45: 8.647058 | G45: 7.516863 | H45: 6.501535 | I45: 5.529372 | J45: 4.801684 | K45: 4.396944 | L45: 4.30778 | M45: 4.272085 | N45: 4.338585 | O45: 4.299617 | P45: 4.302522 | Q45: 4.260971 | R45: 4.161004 | S45: 4.002717 | T45: 3.909357 | U45: 3.806856 | V45: 3.824085 | W45: 3.815112 | X45: 3.763251 | Y45: 3.645989 | Z45: 3.548136 | AA45: 3.463649 | AB45: 3.422932 | AC45: 3.33322 | AD45: 3.31122 | AE45: 3.208326 | AF45: -0.038723
A46: SUP000:fa_NuclearPower | B46: Nuclear / Uranium 2/ | C46: 8.064654 | D46: 8.187211 | E46: 8.246629 | F46: 8.171966 | G46: 8.092857 | H46: 8.092719 | I46: 7.997469 | J46: 7.99734 | K46: 7.918744 | L46: 7.918797 | M46: 7.918885 | N46: 7.47281 | O46: 7.403218 | P46: 7.313933 | Q46: 7.145817 | R46: 7.031636 | S46: 6.837198 | T46: 6.734248 | U46: 6.533641 | V46: 6.535408 | W46: 6.538529 | X46: 6.541202 | Y46: 6.544166 | Z46: 6.544192 | AA46: 6.541663 | AB46: 6.539629 | AC46: 6.530636 | AD46: 6.531871 | AE46: 6.527707 | AF46: -0.007523
A47: SUP000:fa_Hydropower | B47: Conventional Hydroelectric Power | C47: 2.453454 | D47: 2.458462 | E47: 2.502563 | F47: 2.588684 | G47: 2.579723 | H47: 2.556826 | I47: 2.515381 | J47: 2.486196 | K47: 2.457424 | L47: 2.43646 | M47: 2.419676 | N47: 2.422381 | O47: 2.426406 | P47: 2.429998 | Q47: 2.435315 | R47: 2.423512 | S47: 2.41015 | T47: 2.386208 | U47: 2.381421 | V47: 2.366141 | W47: 2.369409 | X47: 2.362637 | Y47: 2.357599 | Z47: 2.354464 | AA47: 2.343242 | AB47: 2.336414 | AC47: 2.334075 | AD47: 2.320942 | AE47: 2.309024 | AF47: -0.002164
A48: SUP000:fa_Biomass | B48: Biomass 12/ | C48: 3.086376 | D48: 3.275092 | E48: 3.097149 | F48: 3.077337 | G48: 3.057139 | H48: 3.045216 | I48: 3.037763 | J48: 3.031368 | K48: 3.025933 | L48: 3.025459 | M48: 3.027686 | N48: 3.034011 | O48: 3.040862 | P48: 3.052712 | Q48: 3.050264 | R48: 3.054543 | S48: 3.058388 | T48: 3.063898 | U48: 3.073415 | V48: 3.092868 | W48: 3.104291 | X48: 3.115824 | Y48: 3.11755 | Z48: 3.122586 | AA48: 3.141141 | AB48: 3.159971 | AC48: 3.182918 | AD48: 3.200994 | AE48: 3.21923 | AF48: 0.001506
A49: SUP000:fa_RenewableEner | B49: Other Renewable Energy 4/ | C49: 5.622848 | D49: 6.12555 | E49: 6.742159 | F49: 8.173244 | G49: 9.907674 | H49: 11.653165 | I49: 13.154488 | J49: 14.209772 | K49: 15.128234 | L49: 15.78889 | M49: 16.442295 | N49: 17.189573 | O49: 17.791294 | P49: 18.262888 | Q49: 18.746868 | R49: 19.110622 | S49: 19.414564 | T49: 19.60931 | U49: 19.90523 | V49: 20.063116 | W49: 20.302187 | X49: 20.584305 | Y49: 20.993839 | Z49: 21.370592 | AA49: 21.805227 | AB49: 22.17202 | AC49: 22.539532 | AD49: 22.84026 | AE49: 23.283979 | AF49: 0.052057
A50: SUP000:fa_Other | B50: Other 13/ | C50: 0.271036 | D50: 0.299924 | E50: 0.274433 | F50: 0.257492 | G50: 0.26147 | H50: 0.275129 | I50: 0.283526 | J50: 0.276055 | K50: 0.28389 | L50: 0.275291 | M50: 0.27901 | N50: 0.280792 | O50: 0.282222 | P50: 0.278324 | Q50: 0.277099 | R50: 0.277055 | S50: 0.279712 | T50: 0.281933 | U50: 0.283737 | V50: 0.278974 | W50: 0.278928 | X50: 0.276634 | Y50: 0.273885 | Z50: 0.271158 | AA50: 0.268038 | AB50: 0.26756 | AC50: 0.268972 | AD50: 0.267478 | AE50: 0.265471 | AF50: -0.000741
A51: SUP000:fa_Total | B51: Total | C51: 99.193466 | D51: 98.343773 | E51: 97.558655 | F51: 97.75322 | G51: 98.015015 | H51: 98.078819 | I51: 98.133987 | J51: 98.055679 | K51: 97.956688 | L51: 97.999809 | M51: 98.312447 | N51: 98.465088 | O51: 98.819359 | P51: 99.128128 | Q51: 99.396774 | R51: 99.65123 | S51: 99.794334 | T51: 99.956566 | U51: 100.25229 | V51: 100.6499 | W51: 101.16514 | X51: 101.64174 | Y51: 102.15067 | Z51: 102.69104 | AA51: 103.17632 | AB51: 103.83192 | AC51: 104.48547 | AD51: 105.10331 | AE51: 105.93937 | AF51: 0.002353
B53: Prices (2022 dollars per unit)
A54: SUP000:ha_WorldOilPrice | B54: Brent Spot Price (dollars per barrel) | C54: 102.13 | D54: 91.544693 | E54: 92.531395 | F54: 87.048607 | G54: 87.88282 | H54: 88.306427 | I54: 88.879097 | J54: 89.470894 | K54: 90.163071 | L54: 90.724144 | M54: 91.546387 | N54: 92.007187 | O54: 92.694916 | P54: 93.55275 | Q54: 94.142883 | R54: 94.796173 | S54: 95.331741 | T54: 95.867317 | U54: 96.392181 | V54: 96.938461 | W54: 97.381508 | X54: 97.758682 | Y54: 98.241776 | Z54: 98.596687 | AA54: 99.377373 | AB54: 99.794151 | AC54: 100.38441 | AD54: 101.06876 | AE54: 101.34071 | AF54: -0.000277
A55: SUP000:ha_ForLowSulfLit | B55: West Texas Intermediate Spot Price (dollars per barrel) | C55: 95.875999 | D55: 85.782883 | E55: 91.164047 | F55: 85.233162 | G55: 85.255096 | H55: 85.532898 | I55: 86.264732 | J55: 86.738144 | K55: 87.188271 | L55: 87.748749 | M55: 88.512123 | N55: 88.937447 | O55: 89.608727 | P55: 90.03215 | Q55: 90.825806 | R55: 91.434029 | S55: 91.807198 | T55: 92.341896 | U55: 92.759918 | V55: 93.263626 | W55: 93.719948 | X55: 94.111893 | Y55: 94.517479 | Z55: 94.856956 | AA55: 95.591454 | AB55: 96.024887 | AC55: 96.717949 | AD55: 97.444786 | AE55: 97.681374 | AF55: 0.000666
A56: SUP000:ha_GasPriceHenry | B56: Natural Gas at Henry Hub (dollars per mmBtu) | C56: 6.523997 | D56: 5.266376 | E56: 4.072381 | F56: 3.489514 | G56: 3.065508 | H56: 2.853001 | I56: 2.799904 | J56: 2.825097 | K56: 2.91248 | L56: 3.043758 | M56: 3.208004 | N56: 3.416918 | O56: 3.56943 | P56: 3.681824 | Q56: 3.694155 | R56: 3.737596 | S56: 3.866561 | T56: 3.78878 | U56: 3.938065 | V56: 4.022155 | W56: 4.014737 | X56: 3.950616 | Y56: 3.913768 | Z56: 3.910706 | AA56: 3.907083 | AB56: 3.870706 | AC56: 3.849094 | AD56: 3.783895 | AE56: 3.771015 | AF56: -0.019386
A57: SUP000:ha_CoalMinemouth | B57: Coal, Minemouth (dollars per ton) 14/ | C57: 37.847488 | D57: 37.282368 | E57: 40.075565 | F57: 40.7808 | G57: 43.636292 | H57: 47.361679 | I57: 49.855022 | J57: 50.434628 | K57: 52.797508 | L57: 55.776047 | M57: 53.310043 | N57: 53.457973 | O57: 53.443798 | P57: 53.327934 | Q57: 54.118721 | R57: 55.130642 | S57: 57.305939 | T57: 57.80991 | U57: 59.124004 | V57: 58.977062 | W57: 59.08213 | X57: 60.30798 | Y57: 61.433601 | Z57: 62.543072 | AA57: 63.485416 | AB57: 63.976109 | AC57: 64.145096 | AD57: 64.784264 | AE57: 65.411858 | AF57: 0.019733
A58: SUP000:ha_CoalMineBtu | B58: Coal, Minemouth (dollars per million Btu) 14/ | C58: 1.853989 | D58: 1.835992 | E58: 1.949069 | F58: 1.971774 | G58: 2.075296 | H58: 2.208372 | I58: 2.306122 | J58: 2.357656 | K58: 2.457956 | L58: 2.593634 | M58: 2.477518 | N58: 2.476679 | O58: 2.486898 | P58: 2.488834 | Q58: 2.523628 | R58: 2.575216 | S58: 2.63626 | T58: 2.656385 | U58: 2.708991 | V58: 2.70876 | W58: 2.716106 | X58: 2.761281 | Y58: 2.804768 | Z58: 2.847011 | AA58: 2.88458 | AB58: 2.905447 | AC58: 2.918446 | AD58: 2.943681 | AE58: 2.976179 | AF58: 0.017047
A59: SUP000:ha_CoalDelivered | B59: Coal, Delivered (dollars per million Btu) 15/ | C59: 2.326422 | D59: 2.26747 | E59: 2.266108 | F59: 2.271228 | G59: 2.283574 | H59: 2.312538 | I59: 2.349293 | J59: 2.399381 | K59: 2.446105 | L59: 2.451144 | M59: 2.441114 | N59: 2.425828 | O59: 2.431217 | P59: 2.429012 | Q59: 2.432617 | R59: 2.450752 | S59: 2.493669 | T59: 2.501265 | U59: 2.519032 | V59: 2.516981 | W59: 2.520107 | X59: 2.529351 | Y59: 2.54457 | Z59: 2.558418 | AA59: 2.576957 | AB59: 2.584111 | AC59: 2.597035 | AD59: 2.60517 | AE59: 2.631093 | AF59: 0.004405
A60: SUP000:ha_Electricity(c | B60: Electricity (cents per kilowatthour) | C60: 12.224998 | D60: 11.913273 | E60: 11.471824 | F60: 11.030275 | G60: 10.768831 | H60: 10.582514 | I60: 10.45016 | J60: 10.399552 | K60: 10.413742 | L60: 10.447019 | M60: 10.475133 | N60: 10.629589 | O60: 10.729555 | P60: 10.73074 | Q60: 10.793545 | R60: 10.871433 | S60: 10.987963 | T60: 11.078531 | U60: 11.155383 | V60: 11.217563 | W60: 11.243109 | X60: 11.258493 | Y60: 11.271253 | Z60: 11.281693 | AA60: 11.247436 | AB60: 11.196383 | AC60: 11.178801 | AD60: 11.117008 | AE60: 11.024078 | AF60: -0.003686
B63: Prices (nominal dollars per unit)
A64: SUP000:nom_ImportRACost | B64: Brent Spot Price (dollars per barrel) | C64: 102.13 | D64: 95.329002 | E64: 98.708405 | F64: 94.878891 | G64: 97.830475 | H64: 100.42555 | I64: 103.26054 | J64: 106.22783 | K64: 109.43919 | L64: 112.63979 | M64: 116.26587 | N64: 119.61838 | O64: 123.39955 | P64: 127.45785 | Q64: 131.21597 | R64: 135.08392 | S64: 138.85072 | T64: 142.6973 | U64: 146.67824 | V64: 150.81691 | W64: 154.92827 | X64: 159.09348 | Y64: 163.57149 | Z64: 167.98759 | AA64: 173.31236 | AB64: 178.17406 | AC64: 183.52431 | AD64: 189.21034 | AE64: 194.29927 | AF64: 0.023236
A65: SUP000:nom_ForLowSulfLi | B65: West Texas Intermediate Spot Price (dollars per barrel) | C65: 95.875999 | D65: 89.329002 | E65: 97.249779 | F65: 92.900146 | G65: 94.905304 | H65: 97.271385 | I65: 100.22316 | J65: 102.98327 | K65: 105.82841 | L65: 108.94564 | M65: 112.41229 | N65: 115.62741 | O65: 119.29108 | P65: 122.66132 | Q65: 126.59264 | R65: 130.29289 | S65: 133.71722 | T65: 137.44975 | U65: 141.15109 | V65: 145.09961 | W65: 149.10294 | X65: 153.15866 | Y65: 157.37058 | Z65: 161.61589 | AA65: 166.70979 | AB65: 171.44435 | AC65: 176.82123 | AD65: 182.42593 | AE65: 187.28326 | AF65: 0.024201
A66: SUP000:nom_Gas@HenryHub | B66: Natural Gas at Henry Hub (dollars per mmBtu) | C66: 6.523997 | D66: 5.48408 | E66: 4.344237 | F66: 3.803406 | G66: 3.4125 | H66: 3.244545 | I66: 3.252955 | J66: 3.354208 | K66: 3.535144 | L66: 3.779019 | M66: 4.074234 | N66: 4.442329 | O66: 4.751782 | P66: 5.016179 | Q66: 5.148898 | R66: 5.326049 | S66: 5.631648 | T66: 5.639552 | U66: 5.992483 | V66: 6.257671 | W66: 6.387211 | X66: 6.429273 | Y66: 6.516381 | Z66: 6.663004 | AA66: 6.813882 | AB66: 6.910819 | AC66: 7.036972 | AD66: 7.083812 | AE66: 7.230118 | AF66: 0.003677
A67: SUP000:nom_CoalMinemout | B67: Coal, Minemouth (dollars per ton) 14/ | C67: 37.847488 | D67: 38.823559 | E67: 42.750843 | F67: 44.449158 | G67: 48.575581 | H67: 53.861572 | I67: 57.92202 | J67: 59.880493 | K67: 64.085182 | L67: 69.249504 | M67: 67.704903 | N67: 69.50061 | O67: 71.146736 | P67: 72.654884 | Q67: 75.430458 | R67: 78.560806 | S67: 83.466125 | T67: 86.049324 | U67: 89.967934 | V67: 91.756546 | W67: 93.996201 | X67: 98.145828 | Y67: 102.28628 | Z67: 106.55997 | AA67: 110.71743 | AB67: 114.22395 | AC67: 117.27104 | AD67: 121.28231 | AE67: 125.41332 | AF67: 0.043716
A68: SUP000:nom_CoalMineBtu | B68: Coal, Minemouth (dollars per million Btu) 14/ | C68: 1.853989 | D68: 1.911889 | E68: 2.079181 | F68: 2.149142 | G68: 2.310204 | H68: 2.511448 | I68: 2.679273 | J68: 2.799219 | K68: 2.983446 | L68: 3.220161 | M68: 3.146501 | N68: 3.219926 | O68: 3.310668 | P68: 3.39083 | Q68: 3.517423 | R68: 3.669666 | S68: 3.839715 | T68: 3.953995 | U68: 4.122222 | V68: 4.21429 | W68: 4.321165 | X68: 4.493738 | Y68: 4.669909 | Z68: 4.850696 | AA68: 5.030655 | AB68: 5.187432 | AC68: 5.335547 | AD68: 5.51085 | AE68: 5.70619 | AF68: 0.040967
A69: SUP000:nom_CoalDeliverd | B69: Coal, Delivered (dollars per million Btu) 15/ | C69: 2.326422 | D69: 2.361203 | E69: 2.417383 | F69: 2.475532 | G69: 2.542057 | H69: 2.62991 | I69: 2.72943 | J69: 2.848759 | K69: 2.969062 | L69: 3.043251 | M69: 3.100267 | N69: 3.153815 | O69: 3.236543 | P69: 3.309328 | Q69: 3.390572 | R69: 3.492306 | S69: 3.63203 | T69: 3.723102 | U69: 3.833166 | V69: 3.915921 | W69: 4.009342 | X69: 4.116291 | Y69: 4.236682 | Z69: 4.358995 | AA69: 4.494166 | AB69: 4.613713 | AC69: 4.74794 | AD69: 4.877126 | AE69: 5.044562 | AF69: 0.028028
A70: SUP000:nom_Electricity | B70: Electricity (cents per kilowatthour) | C70: 12.224998 | D70: 12.405747 | E70: 12.237636 | F70: 12.022483 | G70: 11.987779 | H70: 12.034852 | I70: 12.141092 | J70: 12.347277 | K70: 12.640115 | L70: 12.970637 | M70: 13.303643 | N70: 13.81951 | O70: 14.283655 | P70: 14.619742 | Q70: 15.044 | R70: 15.49172 | S70: 16.003973 | T70: 16.490255 | U70: 16.974945 | V70: 17.452291 | W70: 17.887127 | X70: 18.322187 | Y70: 18.766512 | Z70: 19.221584 | AA70: 19.615328 | AB70: 19.990198 | AC70: 20.437254 | AD70: 20.812099 | AE70: 21.136326 | AF70: 0.019746
B72: 1/ Includes waste coal.
B73: 2/ These values represent the energy obtained from uranium when it is used in light water reactors. The total energy content of uranium
B74: is much larger, but alternative processes are required to take advantage of it.
B75: 3/ Includes grid-connected electricity from wood and wood waste; biomass, such as corn, used for liquid fuels production; and non-electric
B76: energy demand from wood. Refer to Table 17 for details on biomass use by sector.
B77: 4/ Includes grid-connected electricity from landfill gas; biogenic municipal waste; wind; photovoltaic and solar thermal sources; and
B78: non-electric energy from renewable sources, such as active and passive solar systems. Excludes electricity imports using renewable sources
B79: and nonmarketed renewable energy. See Table 17 for selected nonmarketed residential and commercial renewable energy data.
B80: 5/ Includes non-biogenic municipal waste, hydrogen, methanol, and some domestic inputs to refineries.
B81: 6/ Includes imports of finished petroleum products, unfinished oils, alcohols, ethers, blending components, and renewable fuels such as ethanol.
B82: 7/ Includes coal, coal coke (net), and electricity (net). Excludes imports of fuel used in nuclear power plants.
B83: 8/ Includes crude oil, petroleum products, ethanol, and biodiesel.
... B100: National Energy Modeling System run ref2023.d020623a. Projections: EIA, AEO2023 National Energy Modeling System run ref2023.d020623a.

Sheet AEO 2025 Table 1
A1: Table 1. Total Energy Supply, Disposition, and Price Summary
A2: https://www.eia.gov/outlooks/aeo/data/browser/#/?id=1-AEO2025&region=0-0&cases=highZTC&start=2023&end=2050&f=A&sourcekey=0
A3: Tue Dec 02 2025 13:12:41 GMT-0800 (Pacific Standard Time)
A4: Source: U.S. Energy Information Administration
B5: full name | C5: api key | D5: units | E5: 2023 | F5: 2024 | G5: 2025 | H5: 2026 | I5: 2027 | J5: 2028 | K5: 2029 | L5: 2030 | M5: 2031 | N5: 2032 | O5: 2033 | P5: 2034 | Q5: 2035 | R5: 2036 | S5: 2037 | T5: 2038 | U5: 2039 | V5: 2040 | W5: 2041 | X5: 2042 | Y5: 2043 | Z5: 2044 | AA5: 2045 | AB5: 2046 | AC5: 2047 | AD5: 2048 | AE5: 2049 | AF5: 2050 | AG5: Growth (2024-2050)
A6: Production
A7: Crude Oil and Lease Condensate | B7: Total Energy: Production: Crude Oil and Lease Condensate: High Zero-Carbon Technology Cost | C7: AEO.2025.HIGHZTC.SUP_PRD_TEN_NA_CLC_NA_USA_QBTU.A | D7: quads | F7: 27.464071 | G7: 28.262268 | H7: 28.541277 | I7: 28.920042 | J7: 28.912859 | K7: 28.885859 | L7: 28.679308 | M7: 28.304096 | N7: 27.836266 | O7: 27.61907 | P7: 27.394928 | Q7: 26.821156 | R7: 26.303026 | S7: 25.84412 | T7: 25.384386 | U7: 25.005167 | V7: 24.713476 | W7: 24.388079 | X7: 24.236376 | Y7: 23.936176 | Z7: 23.837074 | AA7: 23.875832 | AB7: 23.736609 | AC7: 23.543898 | AD7: 23.332935 | AE7: 23.274858 | AF7: 23.1695 | AG7: -0.007
A8: Natural Gas Plant Liquids | B8: Total Energy: Production: Natural Gas Plant Liquids: High Zero-Carbon Technology Cost | C8: AEO.2025.HIGHZTC.SUP_PRD_TEN_NA_NGP_NA_USA_QBTU.A | D8: quads | F8: 8.944769 | G8: 9.05181 | H8: 9.60171 | I8: 9.876178 | J8: 9.871415 | K8: 9.926223 | L8: 10.00989 | M8: 9.89515 | N8: 9.990735 | O8: 10.111237 | P8: 10.230657 | Q8: 10.516375 | R8: 10.493037 | S8: 10.495532 | T8: 10.641144 | U8: 10.687873 | V8: 10.727968 | W8: 10.720901 | X8: 10.776079 | Y8: 10.805953 | Z8: 10.850081 | AA8: 10.89747 | AB8: 10.976542 | AC8: 11.038014 | AD8: 11.041052 | AE8: 11.063836 | AF8: 11.13463 | AG8: 0.008
A9: Dry Natural Gas | B9: Total Energy: Production: Dry Natural Gas: High Zero-Carbon Technology Cost | C9: AEO.2025.HIGHZTC.SUP_PRD_TEN_NA_DNG_NA_USA_QBTU.A | D9: quads | F9: 39.777958 | G9: 39.964314 | H9: 40.376175 | I9: 40.612423 | J9: 41.816151 | K9: 42.651703 | L9: 43.563282 | M9: 43.656242 | N9: 45.521187 | O9: 45.501274 | P9: 45.491352 | Q9: 45.081741 | R9: 44.722286 | S9: 44.078888 | T9: 43.848736 | U9: 43.464912 | V9: 43.734524 | W9: 44.301231 | X9: 44.546783 | Y9: 44.735222 | Z9: 44.901123 | AA9: 45.16296 | AB9: 45.552685 | AC9: 45.824455 | AD9: 45.987713 | AE9: 46.20248 | AF9: 46.360294 | AG9: 0.006
A10: Coal | B10: Total Energy: Production: Coal: High Zero-Carbon Technology Cost | C10: AEO.2025.HIGHZTC.SUP_PRD_TEN_NA_CL_NA_USA_QBTU.A | D10: quads | F10: 10.26485 | G10: 10.131456 | H10: 9.293497 | I10: 8.276928 | J10: 8.234891 | K10: 7.890815 | L10: 7.08404 | M10: 6.787313 | N10: 4.313393 | O10: 4.312983 | P10: 4.267705 | Q10: 4.298421 | R10: 4.226029 | S10: 4.238231 | T10: 4.161532 | U10: 3.857612 | V10: 3.892832 | W10: 3.849295 | X10: 3.853676 | Y10: 3.865084 | Z10: 3.875777 | AA10: 3.917226 | AB10: 3.78107 | AC10: 3.81519 | AD10: 3.824779 | AE10: 3.842716 | AF10: 3.797269 | AG10: -0.038
A11: Nuclear / Uranium | B11: Total Energy: Production: Nuclear: High Zero-Carbon Technology Cost | C11: AEO.2025.HIGHZTC.SUP_PRD_TEN_NA_NUC_NA_USA_QBTU.A | D11: quads | F11: 8.122566 | G11: 8.281053 | H11: 8.359651 | I11: 8.340639 | J11: 8.340502 | K11: 8.340389 | L11: 8.247139 | M11: 8.160346 | N11: 8.160302 | O11: 8.160461 | P11: 8.160461 | Q11: 8.139178 | R11: 8.087199 | S11: 8.127986 | T11: 8.12495 | U11: 8.1107 | V11: 8.109373 | W11: 8.110039 | X11: 8.110383 | Y11: 8.110783 | Z11: 8.108737 | AA11: 8.110209 | AB11: 8.106524 | AC11: 8.109944 | AD11: 8.109 | AE11: 8.107161 | AF11: 8.107944 | AG11: 0
A12: Conventional Hydroelectric Power | B12: Total Energy: Production: Hydropower: High Zero-Carbon Technology Cost | C12: AEO.2025.HIGHZTC.SUP_PRD_TEN_NA_HYD_CNV_USA_QBTU.A | D12: quads | F12: 0.826728 | G12: 0.897152 | H12: 0.931477 | I12: 0.9659 | J12: 0.966652 | K12: 0.966602 | L12: 0.968512 | M12: 0.968752 | N12: 0.969003 | O12: 0.969075 | P12: 0.969638 | Q12: 0.967771 | R12: 0.964381 | S12: 0.960529 | T12: 0.958948 | U12: 0.951818 | V12: 0.950544 | W12: 0.95869 | X12: 0.949528 | Y12: 0.936356 | Z12: 0.934708 | AA12: 0.932852 | AB12: 0.919088 | AC12: 0.934345 | AD12: 0.921085 | AE12: 0.936604 | AF12: 0.935078 | AG12: 0.005
A13: Biomass | B13: Total Energy: Production: Biomass: High Zero-Carbon Technology Cost | C13: AEO.2025.HIGHZTC.SUP_PRD_TEN_NA_BMS_NA_USA_QBTU.A | D13: quads | F13: 4.716752 | G13: 4.804474 | H13: 4.818114 | I13: 4.744431 | J13: 4.579154 | K13: 4.598478 | L13: 4.623134 | M13: 4.630532 | N13: 4.646151 | O13: 4.635807 | P13: 4.636226 | Q13: 4.63634 | R13: 4.661358 | S13: 4.661342 | T13: 4.658323 | U13: 4.66623 | V13: 4.688058 | W13: 4.674701 | X13: 4.667527 | Y13: 4.655848 | Z13: 4.66567 | AA13: 4.684711 | AB13: 4.70013 | AC13: 4.723889 | AD13: 4.744252 | AE13: 4.772791 | AF13: 4.801425 | AG13: 0.001
A14: Other Renewable Energy | B14: Total Energy: Production: Other Renewable Energy: High Zero-Carbon Technology Cost | C14: AEO.2025.HIGHZTC.SUP_PRD_TEN_NA_PRE_NA_USA_QBTU.A | D14: quads | F14: 2.569243 | G14: 2.896151 | H14: 3.433188 | I14: 3.727581 | J14: 3.892466 | K14: 4.120078 | L14: 4.468548 | M14: 4.851171 | N14: 5.28144 | O14: 5.732325 | P14: 6.271772 | Q14: 6.915045 | R14: 7.522262 | S14: 8.246304 | T14: 8.732141 | U14: 9.419082 | V14: 9.742584 | W14: 9.889035 | X14: 10.072232 | Y14: 10.301825 | Z14: 10.495997 | AA14: 10.674304 | AB14: 10.906047 | AC14: 11.059608 | AD14: 11.247785 | AE14: 11.391186 | AF14: 11.62299 | AG14: 0.06
A15: Other | B15: Total Energy: Production: Other: High Zero-Carbon Technology Cost | C15: AEO.2025.HIGHZTC.SUP_PRD_TEN_NA_OTH_NA_USA_QBTU.A | D15: quads | F15: 1.700421 | G15: 1.771321 | H15: 0.824013 | I15: 0.822489 | J15: 0.749478 | K15: 0.725554 | L15: 0.728704 | M15: 0.728677 | N15: 0.60499 | O15: 0.60499 | P15: 0.60499 | Q15: 0.60499 | R15: 0.60499 | S15: 0.60499 | T15: 0.60499 | U15: 0.60499 | V15: 0.60499 | W15: 0.60499 | X15: 0.60499 | Y15: 0.60499 | Z15: 0.60499 | AA15: 0.60499 | AB15: 0.60499 | AC15: 0.60499 | AD15: 0.60499 | AE15: 0.60499 | AF15: 0.60499 | AG15: -0.039
A16: Total | B16: Total Energy: Production: Total: High Zero-Carbon Technology Cost | C16: AEO.2025.HIGHZTC.SUP_PRD_TEN_NA_TOT_NA_USA_QBTU.A | D16: quads | F16: 104.38736 | G16: 106.06001 | H16: 106.17911 | I16: 106.28661 | J16: 107.36357 | K16: 108.10571 | L16: 108.37256 | M16: 107.98228 | N16: 107.32346 | O16: 107.64722 | P16: 108.02773 | Q16: 107.98102 | R16: 107.58456 | S16: 107.25791 | T16: 107.11515 | U16: 106.76839 | V16: 107.16434 | W16: 107.49696 | X16: 107.81757 | Y16: 107.95223 | Z16: 108.27415 | AA16: 108.86055 | AB16: 109.28368 | AC16: 109.65434 | AD16: 109.81359 | AE16: 110.19662 | AF16: 110.53412 | AG16: 0.002
A17: Imports
A18: Crude Oil | B18: Total Energy: Imports: Crude Oil: High Zero-Carbon Technology Cost | C18: AEO.2025.HIGHZTC.TRAD_IMP_TEN_NA_CR_NA_USA_QBTU.A | D18: quads | F18: 14.511203 | G18: 13.426377 | H18: 14.170196 | I18: 13.641159 | J18: 13.656388 | K18: 13.334659 | L18: 13.681565 | M18: 14.299134 | N18: 14.391166 | O18: 14.434647 | P18: 14.614406 | Q18: 14.994991 | R18: 15.286606 | S18: 15.385403 | T18: 15.587898 | U18: 15.946284 | V18: 16.18852 | W18: 16.484674 | X18: 16.65641 | Y18: 17.139084 | Z18: 17.287809 | AA18: 17.219873 | AB18: 17.294519 | AC18: 17.580736 | AD18: 17.53945 | AE18: 17.701067 | AF18: 17.778273 | AG18: 0.008
A19: Petroleum and Other Liquids | B19: Total Energy: Imports: Liquid Fuels: High Zero-Carbon Technology Cost | C19: AEO.2025.HIGHZTC.TRAD_IMP_TEN_NA_LFL_NA_USA_QBTU.A | D19: quads | F19: 4.051471 | G19: 3.947032 | H19: 4.106811 | I19: 4.007668 | J19: 3.907186 | K19: 3.795186 | L19: 3.787237 | M19: 3.75431 | N19: 3.683765 | O19: 3.660914 | P19: 3.621716 | Q19: 3.589755 | R19: 3.575656 | S19: 3.579068 | T19: 3.569711 | U19: 3.558779 | V19: 3.560091 | W19: 3.54757 | X19: 3.539692 | Y19: 3.528108 | Z19: 3.537213 | AA19: 3.579826 | AB19: 3.540157 | AC19: 3.544324 | AD19: 3.610859 | AE19: 3.612013 | AF19: 3.561888 | AG19: -0.005
A20: Natural Gas | B20: Total Energy: Imports: Natural Gas: High Zero-Carbon Technology Cost | C20: AEO.2025.HIGHZTC.TRAD_IMP_TEN_NA_NG_NA_USA_QBTU.A | D20: quads | F20: 3.087353 | G20: 2.928516 | H20: 2.44861 | I20: 2.691667 | J20: 2.635259 | K20: 2.685839 | L20: 2.755344 | M20: 2.765631 | N20: 2.761101 | O20: 2.626046 | P20: 2.477881 | Q20: 2.476447 | R20: 2.511924 | S20: 2.541484 | T20: 2.574915 | U20: 2.597797 | V20: 2.555126 | W20: 2.424842 | X20: 2.428653 | Y20: 2.495061 | Z20: 2.561628 | AA20: 2.54905 | AB20: 2.381193 | AC20: 2.363839 | AD20: 2.427631 | AE20: 2.517868 | AF20: 2.607521 | AG20: -0.006
A21: Other | B21: Total Energy: Imports: Other: High Zero-Carbon Technology Cost | C21: AEO.2025.HIGHZTC.TRAD_IMP_TEN_NA_OTH_NA_USA_QBTU.A | D21: quads | F21: 0.091886 | G21: 0.13382 | H21: 0.159464 | I21: 0.21491 | J21: 0.256195 | K21: 0.274823 | L21: 0.301232 | M21: 0.308272 | N21: 0.315313 | O21: 0.323256 | P21: 0.32607 | Q21: 0.330338 | R21: 0.322584 | S21: 0.318855 | T21: 0.317105 | U21: 0.309224 | V21: 0.314087 | W21: 0.315513 | X21: 0.31305 | Y21: 0.293137 | Z21: 0.291691 | AA21: 0.289309 | AB21: 0.273181 | AC21: 0.262254 | AD21: 0.255587 | AE21: 0.245526 | AF21: 0.236449 | AG21: 0.037
A22: Total | B22: Total Energy: Imports: Total: High Zero-Carbon Technology Cost | C22: AEO.2025.HIGHZTC.TRAD_IMP_TEN_NA_TOT_NA_USA_QBTU.A | D22: quads | F22: 21.741913 | G22: 20.435745 | H22: 20.88508 | I22: 20.555405 | J22: 20.455029 | K22: 20.090506 | L22: 20.525377 | M22: 21.127346 | N22: 21.151344 | O22: 21.044861 | P22: 21.040073 | Q22: 21.391531 | R22: 21.696772 | S22: 21.824812 | T22: 22.049629 | U22: 22.412086 | V22: 22.617825 | W22: 22.772602 | X22: 22.937805 | Y22: 23.455391 | Z22: 23.678341 | AA22: 23.638058 | AB22: 23.489052 | AC22: 23.751154 | AD22: 23.833527 | AE22: 24.076473 | AF22: 24.18413 | AG22: 0.004
A23: Exports
A24: Petroleum and Other Liquids | B24: Total Energy: Exports: Petroleum: High Zero-Carbon Technology Cost | C24: AEO.2025.HIGHZTC.TRAD_EXP_TEN_NA_PET_NA_USA_QBTU.A | D24: quads | F24: 20.660601 | G24: 20.339432 | H24: 21.727066 | I24: 21.978756 | J24: 21.857641 | K24: 21.781075 | L24: 22.423283 | M24: 22.928905 | N24: 23.090502 | O24: 23.653084 | P24: 24.25209 | Q24: 24.863869 | R24: 25.149168 | S24: 25.315872 | T24: 25.662657 | U24: 26.044285 | V24: 26.331007 | W24: 26.577488 | X24: 26.932499 | Y24: 27.351252 | Z24: 27.591288 | AA24: 27.74062 | AB24: 27.845409 | AC24: 28.038736 | AD24: 27.964088 | AE24: 28.088184 | AF24: 28.047884 | AG24: 0.012
A25: Natural Gas | B25: Total Energy: Exports: Natural Gas: High Zero-Carbon Technology Cost | C25: AEO.2025.HIGHZTC.TRAD_EXP_TEN_NA_NG_NA_USA_QBTU.A | D25: quads | F25: 7.818752 | G25: 8.591709 | H25: 9.108819 | I25: 9.009503 | J25: 10.029778 | K25: 10.658371 | L25: 11.299662 | M25: 11.562331 | N25: 11.83005 | O25: 12.097961 | P25: 12.369316 | Q25: 12.509456 | R25: 12.687962 | S25: 12.821247 | T25: 12.877399 | U25: 12.941127 | V25: 13.047361 | W25: 13.099333 | X25: 13.132851 | Y25: 13.117587 | Z25: 13.110284 | AA25: 13.128943 | AB25: 13.158234 | AC25: 13.197891 | AD25: 13.21223 | AE25: 13.199548 | AF25: 13.252179 | AG25: 0.021
A26: Coal | B26: Total Energy: Exports: Coal: High Zero-Carbon Technology Cost | C26: AEO.2025.HIGHZTC.TRAD_EXP_TEN_NA_CL_NA_USA_QBTU.A | D26: quads | F26: 2.725175 | G26: 2.605518 | H26: 2.710523 | I26: 2.810207 | J26: 2.943514 | K26: 2.881355 | L26: 2.820419 | M26: 2.803875 | N26: 2.825913 | O26: 2.818362 | P26: 2.800367 | Q26: 2.880848 | R26: 2.851437 | S26: 2.91902 | T26: 2.896337 | U26: 2.971976 | V26: 3.015071 | W26: 2.979697 | X26: 2.995062 | Y26: 3.01593 | Z26: 3.040822 | AA26: 3.113441 | AB26: 3.132786 | AC26: 3.176474 | AD26: 3.196385 | AE26: 3.227969 | AF26: 3.194277 | AG26: 0.006
A27: Total | B27: Total Energy: Exports: Total: High Zero-Carbon Technology Cost | C27: AEO.2025.HIGHZTC.TRAD_EXP_TEN_NA_TOT_NA_USA_QBTU.A | D27: quads | F27: 31.204529 | G27: 31.536659 | H27: 33.546406 | I27: 33.798466 | J27: 34.830933 | K27: 35.320801 | L27: 36.543365 | M27: 37.295113 | N27: 37.746464 | O27: 38.569408 | P27: 39.421772 | Q27: 40.254173 | R27: 40.688564 | S27: 41.056141 | T27: 41.43639 | U27: 41.95739 | V27: 42.39344 | W27: 42.656517 | X27: 43.06041 | Y27: 43.484768 | Z27: 43.742393 | AA27: 43.983006 | AB27: 44.136429 | AC27: 44.413101 | AD27: 44.372704 | AE27: 44.515701 | AF27: 44.494339 | AG27: 0.014
A28: Discrepancy | B28: Total Energy: Discrepancy: High Zero-Carbon Technology Cost | C28: AEO.2025.HIGHZTC.UNC_NA_TEN_NA_DESCR_NA_USA_QBTU.A | D28: quads | F28: 1.414474 | G28: 0.693565 | H28: 0.055897 | I28: -0.015652 | J28: 0.066837 | K28: 0.105583 | L28: 0.220062 | M28: 0.224979 | N28: 0.177616 | O28: 0.194424 | P28: 0.208023 | Q28: 0.238838 | R28: 0.181911 | S28: 0.250698 | T28: 0.230839 | U28: 0.308479 | V28: 0.364468 | W28: 0.369488 | X28: 0.241982 | Y28: 0.262257 | Z28: 0.269756 | AA28: 0.331047 | AB28: 0.246117 | AC28: 0.221275 | AD28: 0.20118 | AE28: 0.247356 | AF28: 0.382828 | AG28: -0.049
A29: Consumption
A30: Petroleum and Other Liquids | B30: Total Energy: Use: Liquid Fuels: High Zero-Carbon Technology Cost | C30: AEO.2025.HIGHZTC.CNSM_USE_TEN_NA_LFL_NA_USA_QBTU.A | D30: quads | F30: 37.196278 | G30: 37.598106 | H30: 37.679672 | I30: 37.519691 | J30: 37.305046 | K30: 36.974751 | L30: 36.565708 | M30: 36.099148 | N30: 35.465519 | O30: 34.827679 | P30: 34.257473 | Q30: 33.691135 | R30: 33.140713 | S30: 32.601837 | T30: 32.143185 | U30: 31.759447 | V30: 31.460081 | W30: 31.157518 | X30: 30.861813 | Y30: 30.642817 | Z30: 30.493799 | AA30: 30.396223 | AB30: 30.278259 | AC30: 30.253607 | AD30: 30.158323 | AE30: 30.176685 | AF30: 30.205194 | AG30: -0.008
A31: Natural Gas | B31: Total Energy: Use: Natural Gas: High Zero-Carbon Technology Cost | C31: AEO.2025.HIGHZTC.CNSM_USE_TEN_NA_NG_NA_USA_QBTU.A | D31: quads | F31: 34.247383 | G31: 33.971241 | H31: 33.337524 | I31: 33.851017 | J31: 33.922363 | K31: 34.094196 | L31: 34.339489 | M31: 34.235748 | N31: 35.867371 | O31: 35.444721 | P31: 35.016048 | Q31: 34.454063 | R31: 34.016273 | S31: 33.218056 | T31: 32.987907 | U31: 32.505821 | V31: 32.587852 | W31: 32.979076 | X31: 33.33342 | Y31: 33.587589 | Z31: 33.842003 | AA31: 34.02898 | AB31: 34.300522 | AC31: 34.535992 | AD31: 34.761581 | AE31: 35.023502 | AF31: 35.093433 | AG31: 0.001
A32: Coal | B32: Total Energy: Use: Coal: High Zero-Carbon Technology Cost | C32: AEO.2025.HIGHZTC.CNSM_USE_TEN_NA_CL_NA_USA_QBTU.A | D32: quads | F32: 7.531142 | G32: 7.540981 | H32: 6.612533 | I32: 5.497371 | J32: 5.306551 | K32: 5.055994 | L32: 4.287706 | M32: 4.004857 | N32: 1.526352 | O32: 1.519729 | P32: 1.490149 | Q32: 1.437609 | R32: 1.398837 | S32: 1.344788 | T32: 1.280926 | U32: 0.900582 | V32: 0.893456 | W32: 0.884383 | X32: 0.874039 | Y32: 0.865476 | Z32: 0.851125 | AA32: 0.821714 | AB32: 0.665149 | AC32: 0.655488 | AD32: 0.644758 | AE32: 0.630765 | AF32: 0.619131 | AG32: -0.092
A33: Nuclear / Uranium | B33: Total Energy: Use: Nuclear: High Zero-Carbon Technology Cost | C33: AEO.2025.HIGHZTC.CNSM_USE_TEN_NA_NUC_NA_USA_QBTU.A | D33: quads | F33: 8.122566 | G33: 8.281053 | H33: 8.359651 | I33: 8.340639 | J33: 8.340502 | K33: 8.340389 | L33: 8.247139 | M33: 8.160346 | N33: 8.160302 | O33: 8.160461 | P33: 8.160461 | Q33: 8.139178 | R33: 8.087199 | S33: 8.127986 | T33: 8.12495 | U33: 8.1107 | V33: 8.109373 | W33: 8.110039 | X33: 8.110383 | Y33: 8.110783 | Z33: 8.108737 | AA33: 8.110209 | AB33: 8.106524 | AC33: 8.109944 | AD33: 8.109 | AE33: 8.107161 | AF33: 8.107944 | AG33: 0
A34: Conventional Hydroelectric Power | B34: Total Energy: Use: Hydropower: High Zero-Carbon Technology Cost | C34: AEO.2025.HIGHZTC.CNSM_USE_TEN_NA_HYD_CNV_USA_QBTU.A | D34: quads | F34: 0.826728 | G34: 0.897152 | H34: 0.931477 | I34: 0.9659 | J34: 0.966652 | K34: 0.966602 | L34: 0.968512 | M34: 0.968752 | N34: 0.969003 | O34: 0.969075 | P34: 0.969638 | Q34: 0.967771 | R34: 0.964381 | S34: 0.960529 | T34: 0.958948 | U34: 0.951818 | V34: 0.950544 | W34: 0.95869 | X34: 0.949528 | Y34: 0.936356 | Z34: 0.934708 | AA34: 0.932852 | AB34: 0.919088 | AC34: 0.934345 | AD34: 0.921085 | AE34: 0.936604 | AF34: 0.935078 | AG34: 0.005
A35: Biomass | B35: Total Energy: Use: Biomass: High Zero-Carbon Technology Cost | C35: AEO.2025.HIGHZTC.CNSM_USE_TEN_NA_BMS_NA_USA_QBTU.A | D35: quads | F35: 2.827603 | G35: 2.873342 | H35: 2.876137 | I35: 2.864724 | J35: 2.854348 | K35: 2.867029 | L35: 2.880749 | M35: 2.886152 | N35: 2.89081 | O35: 2.875911 | P35: 2.872308 | Q35: 2.870189 | R35: 2.88414 | S35: 2.88274 | T35: 2.877328 | U35: 2.882768 | V35: 2.891253 | W35: 2.874173 | X35: 2.86325 | Y35: 2.847385 | Z35: 2.846941 | AA35: 2.855452 | AB35: 2.865723 | AC35: 2.884223 | AD35: 2.899275 | AE35: 2.922654 | AF35: 2.944951 | AG35: 0.002
A36: Other Renewable Energy | B36: Total Energy: Use: Other Renewable Energy: High Zero-Carbon Technology Cost | C36: AEO.2025.HIGHZTC.CNSM_USE_TEN_NA_PRE_NA_USA_QBTU.A | D36: quads | F36: 2.569243 | G36: 2.896151 | H36: 3.433188 | I36: 3.727581 | J36: 3.892466 | K36: 4.120078 | L36: 4.468548 | M36: 4.851171 | N36: 5.28144 | O36: 5.732325 | P36: 6.271772 | Q36: 6.915045 | R36: 7.522262 | S36: 8.246304 | T36: 8.732141 | U36: 9.419082 | V36: 9.742584 | W36: 9.889035 | X36: 10.072232 | Y36: 10.301825 | Z36: 10.495997 | AA36: 10.674304 | AB36: 10.906047 | AC36: 11.059608 | AD36: 11.247785 | AE36: 11.391186 | AF36: 11.62299 | AG36: 0.06
A37: Other | B37: Total Energy: Use: Other: High Zero-Carbon Technology Cost | C37: AEO.2025.HIGHZTC.CNSM_USE_TEN_NA_OTH_NA_USA_QBTU.A | D37: quads | F37: 0.189315 | G37: 0.207495 | H37: 0.231698 | I37: 0.292279 | J37: 0.332907 | K37: 0.35079 | L37: 0.376656 | M37: 0.383346 | N37: 0.389936 | O37: 0.398346 | P37: 0.400153 | Q37: 0.404547 | R37: 0.397064 | S37: 0.393637 | T37: 0.392163 | U37: 0.384382 | V37: 0.389118 | W37: 0.390634 | X37: 0.388311 | Y37: 0.368371 | Z37: 0.367046 | AA37: 0.364825 | AB37: 0.348878 | AC37: 0.337916 | AD37: 0.331416 | AE37: 0.321471 | AF37: 0.312351 | AG37: 0.019
