Workbook

Sheet About
A1: SoDSCbRIC Share of Distriuted Solar Costs by Recipient ISIC Code
A3: Source: | B3: NREL
B4: 2018
B5: U.S. Solar Photovoltaic System Cost Benchmark: Q1 2018
B6: https://www.nrel.gov/docs/fy19osti/72399.pdf
B7: Figures 14 and 20
A9: Notes
A10: As taxes (except fuel taxes) are handled separately (on the "Cross-Sector Totals" sheet), not within
A11: each sector, we reallocate the "sales tax" share in this variable to the equipment portions
A12: of the costs.
A14: 52-code expansion (2026-07-17):
A15: The output tabs produce the 52-code ISIC list. The derivation above is unchanged and live; output-tab formulas reference the derivation tabs
A16: directly, with the original header-label criteria written as literals (the derivation tabs still use the pre-split 42-code labels).
A18: Children of split parents multiply the parent's allocation by the factors on the 'Factors applied' tab (editable; defaults = BEA 2024 gross-
A19: output shares from io-model/BObIC; semantic overrides documented per row with rationale).
A21: Data centers | B21: Data centers are a separate building type. They copy the commercial cost shares so the values are defined; data centers have no distributed solar.

Sheet Factors applied
A1: Child factors applied inline in the output-tab formulas (editable). Defaults = BEA 2024 output shares; semantic overrides and fuel reroutes noted per row.
A2: File | B2: Row context | C2: Child | D2: Parent | E2: Factor | F2: Rationale | G2: BEA 2024 output share
A3: SoDSCbRIC.csv | B3: commercial | C3: ISIC 01 | D3: ISIC 01T03 | E3: 0.94299868 | F3: BEA 2024 output share (default) | G3: 0.94299868
A4: SoDSCbRIC.csv | B4: commercial | C4: ISIC 02 | D4: ISIC 01T03 | E4: 0.041765731 | F4: BEA 2024 output share (default) | G4: 0.041765731
A5: SoDSCbRIC.csv | B5: commercial | C5: ISIC 03 | D5: ISIC 01T03 | E5: 0.015235586 | F5: BEA 2024 output share (default) | G5: 0.015235586
A6: SoDSCbRIC.csv | B6: commercial | C6: ISIC 07 | D6: ISIC 07T08 | E6: 0.43273688 | F6: BEA 2024 output share (default) | G6: 0.43273688
A7: SoDSCbRIC.csv | B7: commercial | C7: ISIC 08 | D7: ISIC 07T08 | E7: 0.56726312 | F7: BEA 2024 output share (default) | G7: 0.56726312
A8: SoDSCbRIC.csv | B8: commercial | C8: ISIC 301 | D8: ISIC 30 | E8: 0.11713687 | F8: BEA 2024 output share (default) | G8: 0.11713687
A9: SoDSCbRIC.csv | B9: commercial | C9: ISIC 302T309 | D9: ISIC 30 | E9: 0.88286313 | F9: BEA 2024 output share (default) | G9: 0.88286313
A10: SoDSCbRIC.csv | B10: commercial | C10: ISIC 49 | D10: ISIC 49T53 | E10: 0.69 | F10: semantic override | G10: 0.45630816
A11: SoDSCbRIC.csv | B11: commercial | C11: ISIC 50 | D11: ISIC 49T53 | E11: 0 | F11: semantic override | G11: 0.044370048
A12: SoDSCbRIC.csv | B12: commercial | C12: ISIC 51 | D12: ISIC 49T53 | E12: 0 | F12: semantic override | G12: 0.18837505
A13: SoDSCbRIC.csv | B13: commercial | C13: ISIC 52 | D13: ISIC 49T53 | E13: 0.31 | F13: semantic override | G13: 0.22286512
A14: SoDSCbRIC.csv | B14: commercial | C14: ISIC 53 | D14: ISIC 49T53 | E14: 0 | F14: semantic override | G14: 0.088081621
... A50: SoDSCbRIC.csv | B50: urban residential | C50: ISIC 94T96 | D50: ISIC 90T96 | E50: 0.57837505 | F50: BEA 2024 output share (default) | G50: 0.57837505

Sheet Data
A1: Residential | G1: ISIC Code | H1: Meaning
A2: 2018 USD/W-DC, mixed weighted average, 6.2 kW | B2: Pre-Tax Reallocation | C2: Pre-Tax Reallocation | D2: Share | E2: ISIC Code | G2: ISIC 01T03 | H2: Agriculture, forestry and fishing
A3: Net Profit | B3: 0.33 | C3: =B3 -> 0.33 | D3: =C3/SUM($C$3:$C$13) -> 0.11115463 | E3: ISIC 41T43 | G3: ISIC 05 | H3: Coal mining
A4: Overhead | B4: 0.32 | C4: =B4 -> 0.32 | D4: =C4/SUM($C$3:$C$13) -> 0.10778631 | E4: ISIC 41T43 | G4: ISIC 06 | H4: Oil and gas extraction
A5: Sales and Marketing | B5: 0.35 | C5: =B5 -> 0.35 | D5: =C5/SUM($C$3:$C$13) -> 0.11789127 | E5: ISIC 69T82 | G5: ISIC 07T08 | H5: Mining and quarrying of non-energy producing products
A6: Permitting, Inspection, Interconnection | B6: 0.06 | C6: =B6 -> 0.06 | D6: =C6/SUM($C$3:$C$13) -> 0.020209933 | E6: ISIC 69T82 | G6: ISIC 09 | H6: Mining support service activities
A7: Install Labor | B7: 0.27 | C7: =B7 -> 0.27 | D7: =C7/SUM($C$3:$C$13) -> 0.090944697 | E7: ISIC 41T43 | G7: ISIC 10T12 | H7: Food products, beverages and tobacco
A8: Sales Tax | B8: 0.09 | C8: 0 | D8: =C8/SUM($C$3:$C$13) -> 0 | G8: ISIC 13T15 | H8: Textiles, wearing apparel, leather and related products
A9: Supply Chain Costs | B9: 0.3 | C9: =B9+(B$8/SUM(B$9:B$13)) -> 0.36976744 | D9: =C9/SUM($C$3:$C$13) -> 0.12454958 | E9: ISIC 49T53 | G9: ISIC 16 | H9: Wood and of products of wood and cork (except furniture)
A10: Electrical BOS | B10: 0.21 | C10: =B10+(B$8/SUM(B$9:B$13)) -> 0.27976744 | D10: =C10/SUM($C$3:$C$13) -> 0.094234686 | E10: ISIC 27 | G10: ISIC 17T18 | H10: Paper products and printing
A11: Structrual BOS | B11: 0.1 | C11: =B11+(B$8/SUM(B$9:B$13)) -> 0.16976744 | D11: =C11/SUM($C$3:$C$13) -> 0.057183143 | E11: ISIC 25 | G11: ISIC 19 | H11: Coke and refined petroleum products
A12: Inverter | B12: 0.21 | C12: =B12+(B$8/SUM(B$9:B$13)) -> 0.27976744 | D12: =C12/SUM($C$3:$C$13) -> 0.094234686 | E12: ISIC 27 | G12: ISIC 20 | H12: Chemicals
A13: Module | B13: 0.47 | C13: =B13+(B$8/SUM(B$9:B$13)) -> 0.53976744 | D13: =C13/SUM($C$3:$C$13) -> 0.18181106 | E13: ISIC 26 | G13: ISIC 21 | H13: Pharmaceuticals
G14: ISIC 22 | H14: Rubber and plastics products
A15: Commercial | G15: ISIC 231 | H15: Glass
A16: 2018 USD/W-DC, 200 kW | B16: Pre-Tax Reallocation | C16: Pre-Tax Reallocation | D16: Share | E16: ISIC Code | G16: ISIC 239 | H16: Cement and other nonmetallic minerals
A17: EPC/Developer Net Profit | B17: 0.12 | C17: =B17 -> 0.12 | D17: =C17/SUM($C$17:$C$27) -> 0.059203313 | E17: ISIC 41T43 | G17: ISIC 241 | H17: Iron and steel
A18: Contingency | B18: 0.05 | C18: =B18 -> 0.05 | D18: =C18/SUM($C$17:$C$27) -> 0.024668047 | E18: ISIC 41T43 | G18: ISIC 242 | H18: Other metals
A19: Developer Overhead | B19: 0.36 | C19: =B19 -> 0.36 | D19: =C19/SUM($C$17:$C$27) -> 0.17760994 | E19: ISIC 41T43 | G19: ISIC 25 | H19: Fabricated metal products, except machinery and equipment
A20: Sales Tax | B20: 0.05 | C20: 0 | D20: =C20/SUM($C$17:$C$27) -> 0 | G20: ISIC 26 | H20: Computer, electronic and optical products
A21: PII | B21: 0.1 | C21: =B21 -> 0.1 | D21: =C21/SUM($C$17:$C$27) -> 0.049336095 | E21: ISIC 69T82 | G21: ISIC 27 | H21: Electrical equipment
A22: EPC Overhead | B22: 0.18 | C22: =B22 -> 0.18 | D22: =C22/SUM($C$17:$C$27) -> 0.08880497 | E22: ISIC 41T43 | G22: ISIC 28 | H22: Machinery and equipment n.e.c.
A23: Install Labor and Equipment | B23: 0.16 | C23: =B23 -> 0.16 | D23: =C23/SUM($C$17:$C$27) -> 0.078937751 | E23: ISIC 41T43 | G23: ISIC 29 | H23: Motor vehicles, trailers and semi-trailers
A24: Electrical BOS | B24: 0.14 | C24: =B24+(B$20/SUM(B$24:B$27)) -> 0.2017284 | D24: =C24/SUM($C$17:$C$27) -> 0.099524912 | E24: ISIC 27 | G24: ISIC 30 | H24: Other transport equipment
A25: Structural BOS | B25: 0.12 | C25: =B25+(B$20/SUM(B$24:B$27)) -> 0.1817284 | D25: =C25/SUM($C$17:$C$27) -> 0.089657693 | E25: ISIC 25 | G25: ISIC 31T33 | H25: Other manufacturing; repair and installation of machinery and equipment
A26: Inverter Only | B26: 0.08 | C26: =B26+(B$20/SUM(B$24:B$27)) -> 0.1417284 | D26: =C26/SUM($C$17:$C$27) -> 0.069923255 | E26: ISIC 27 | G26: ISIC 351 | H26: Electricity generation and distribution
A27: Module | B27: 0.47 | C27: =B27+(B$20/SUM(B$24:B$27)) -> 0.5317284 | D27: =C27/SUM($C$17:$C$27) -> 0.26233402 | E27: ISIC 26 | G27: ISIC 352T353 | H27: Energy pipelines and gas processing
G28: ISIC 36T39 | H28: Water and waste
G29: ISIC 41T43 | H29: Construction
G30: ISIC 45T47 | H30: Wholesale and retail trade; repair of motor vehicles
G31: ISIC 49T53 | H31: Transportation and storage
G32: ISIC 55T56 | H32: Accomodation and food services
G33: ISIC 58T60 | H33: Publishing, audiovisual and broadcasting activities
G34: ISIC 61 | H34: Telecommunications
G35: ISIC 62T63 | H35: IT and other information services
G36: ISIC 64T66 | H36: Financial and insurance activities
G37: ISIC 68 | H37: Real estate activities
G38: ISIC 69T82 | H38: Other business sector services
G39: ISIC 84 | H39: Public administration and defence; compulsory social security
... G43: ISIC 97T98 | H43: Private households with employed persons

Sheet Checks
A1: Validation checks
A3: Child-factor groups sum to 1 (per file/context/parent; rate-file reroutes excluded)
A4: SoDSCbRIC.csv | commercial | ISIC 01T03 | B4: =('Factors applied'!$E$3+'Factors applied'!$E$4+'Factors applied'!$E$5) -> 1 | C4: =IF(ABS(B4-1)<0.000000001,"PASS","FAIL") -> PASS
A5: SoDSCbRIC.csv | commercial | ISIC 07T08 | B5: =('Factors applied'!$E$6+'Factors applied'!$E$7) -> 1 | C5: =IF(ABS(B5-1)<0.000000001,"PASS","FAIL") -> PASS
A6: SoDSCbRIC.csv | commercial | ISIC 30 | B6: =('Factors applied'!$E$8+'Factors applied'!$E$9) -> 1 | C6: =IF(ABS(B6-1)<0.000000001,"PASS","FAIL") -> PASS
A7: SoDSCbRIC.csv | commercial | ISIC 49T53 | B7: =('Factors applied'!$E$10+'Factors applied'!$E$11+'Factors applied'!$E$12+'Factors applied'!$E$13+'Factors applied'!$E$14) -> 1 | C7: =IF(ABS(B7-1)<0.000000001,"PASS","FAIL") -> PASS
A8: SoDSCbRIC.csv | commercial | ISIC 69T82 | B8: =('Factors applied'!$E$15+'Factors applied'!$E$16) -> 1 | C8: =IF(ABS(B8-1)<0.000000001,"PASS","FAIL") -> PASS
A9: SoDSCbRIC.csv | commercial | ISIC 90T96 | B9: =('Factors applied'!$E$17+'Factors applied'!$E$18) -> 1 | C9: =IF(ABS(B9-1)<0.000000001,"PASS","FAIL") -> PASS
A10: SoDSCbRIC.csv | rural residential | ISIC 01T03 | B10: =('Factors applied'!$E$19+'Factors applied'!$E$20+'Factors applied'!$E$21) -> 1 | C10: =IF(ABS(B10-1)<0.000000001,"PASS","FAIL") -> PASS
A11: SoDSCbRIC.csv | rural residential | ISIC 07T08 | B11: =('Factors applied'!$E$22+'Factors applied'!$E$23) -> 1 | C11: =IF(ABS(B11-1)<0.000000001,"PASS","FAIL") -> PASS
A12: SoDSCbRIC.csv | rural residential | ISIC 30 | B12: =('Factors applied'!$E$24+'Factors applied'!$E$25) -> 1 | C12: =IF(ABS(B12-1)<0.000000001,"PASS","FAIL") -> PASS
A13: SoDSCbRIC.csv | rural residential | ISIC 49T53 | B13: =('Factors applied'!$E$26+'Factors applied'!$E$27+'Factors applied'!$E$28+'Factors applied'!$E$29+'Factors applied'!$E$30) -> 1 | C13: =IF(ABS(B13-1)<0.000000001,"PASS","FAIL") -> PASS
A14: SoDSCbRIC.csv | rural residential | ISIC 69T82 | B14: =('Factors applied'!$E$31+'Factors applied'!$E$32) -> 1 | C14: =IF(ABS(B14-1)<0.000000001,"PASS","FAIL") -> PASS
A15: SoDSCbRIC.csv | rural residential | ISIC 90T96 | B15: =('Factors applied'!$E$33+'Factors applied'!$E$34) -> 1 | C15: =IF(ABS(B15-1)<0.000000001,"PASS","FAIL") -> PASS
A16: SoDSCbRIC.csv | urban residential | ISIC 01T03 | B16: =('Factors applied'!$E$35+'Factors applied'!$E$36+'Factors applied'!$E$37) -> 1 | C16: =IF(ABS(B16-1)<0.000000001,"PASS","FAIL") -> PASS
A17: SoDSCbRIC.csv | urban residential | ISIC 07T08 | B17: =('Factors applied'!$E$38+'Factors applied'!$E$39) -> 1 | C17: =IF(ABS(B17-1)<0.000000001,"PASS","FAIL") -> PASS
A18: SoDSCbRIC.csv | urban residential | ISIC 30 | B18: =('Factors applied'!$E$40+'Factors applied'!$E$41) -> 1 | C18: =IF(ABS(B18-1)<0.000000001,"PASS","FAIL") -> PASS
A19: SoDSCbRIC.csv | urban residential | ISIC 49T53 | B19: =('Factors applied'!$E$42+'Factors applied'!$E$43+'Factors applied'!$E$44+'Factors applied'!$E$45+'Factors applied'!$E$46) -> 1 | C19: =IF(ABS(B19-1)<0.000000001,"PASS","FAIL") -> PASS
A20: SoDSCbRIC.csv | urban residential | ISIC 69T82 | B20: =('Factors applied'!$E$47+'Factors applied'!$E$48) -> 1 | C20: =IF(ABS(B20-1)<0.000000001,"PASS","FAIL") -> PASS
A21: SoDSCbRIC.csv | urban residential | ISIC 90T96 | B21: =('Factors applied'!$E$49+'Factors applied'!$E$50) -> 1 | C21: =IF(ABS(B21-1)<0.000000001,"PASS","FAIL") -> PASS

Sheet SoDSCbRIC
B1: ISIC 01 | C1: ISIC 02 | D1: ISIC 03 | E1: ISIC 05 | F1: ISIC 06 | G1: ISIC 07 | H1: ISIC 08 | I1: ISIC 09 | J1: ISIC 10T12 | K1: ISIC 13T15 | L1: ISIC 16 | M1: ISIC 17T18 | N1: ISIC 19 | O1: ISIC 20 | P1: ISIC 21 | Q1: ISIC 22 | R1: ISIC 231 | S1: ISIC 239 | T1: ISIC 241 | U1: ISIC 242 | V1: ISIC 25 | W1: ISIC 26 | X1: ISIC 27 | Y1: ISIC 28 | Z1: ISIC 29 | AA1: ISIC 301 | AB1: ISIC 302T309 | AC1: ISIC 31T33 | AD1: ISIC 351 | AE1: ISIC 352T353 | AF1: ISIC 36T39 | AG1: ISIC 41T43 | AH1: ISIC 45T47 | AI1: ISIC 49 | AJ1: ISIC 50 | AK1: ISIC 51 | AL1: ISIC 52 | AM1: ISIC 53 | AN1: ISIC 55T56 | AO1: ISIC 58T60 | AP1: ISIC 61 | AQ1: ISIC 62T63 | AR1: ISIC 64T66 | AS1: ISIC 68 | AT1: ISIC 69T75 | AU1: ISIC 77T82 | AV1: ISIC 84 | AW1: ISIC 85 | AX1: ISIC 86T88 | AY1: ISIC 90T93 | AZ1: ISIC 94T96 | BA1: ISIC 97T98
A2: urban residential | B2: =(SUMIF(Data!$E$3:$E$13,"ISIC 01T03",Data!$D$3:$D$13))*'Factors applied'!$E$35 -> 0 | C2: =(SUMIF(Data!$E$3:$E$13,"ISIC 01T03",Data!$D$3:$D$13))*'Factors applied'!$E$36 -> 0 | D2: =(SUMIF(Data!$E$3:$E$13,"ISIC 01T03",Data!$D$3:$D$13))*'Factors applied'!$E$37 -> 0 | E2: =(SUMIF(Data!$E$3:$E$13,"ISIC 05",Data!$D$3:$D$13)) -> 0 | F2: =(SUMIF(Data!$E$3:$E$13,"ISIC 06",Data!$D$3:$D$13)) -> 0 | G2: =(SUMIF(Data!$E$3:$E$13,"ISIC 07T08",Data!$D$3:$D$13))*'Factors applied'!$E$38 -> 0 | H2: =(SUMIF(Data!$E$3:$E$13,"ISIC 07T08",Data!$D$3:$D$13))*'Factors applied'!$E$39 -> 0 | I2: =(SUMIF(Data!$E$3:$E$13,"ISIC 09",Data!$D$3:$D$13)) -> 0 | J2: =(SUMIF(Data!$E$3:$E$13,"ISIC 10T12",Data!$D$3:$D$13)) -> 0 | K2: =(SUMIF(Data!$E$3:$E$13,"ISIC 13T15",Data!$D$3:$D$13)) -> 0 | L2: =(SUMIF(Data!$E$3:$E$13,"ISIC 16",Data!$D$3:$D$13)) -> 0 | M2: =(SUMIF(Data!$E$3:$E$13,"ISIC 17T18",Data!$D$3:$D$13)) -> 0 | N2: =(SUMIF(Data!$E$3:$E$13,"ISIC 19",Data!$D$3:$D$13)) -> 0 | O2: =(SUMIF(Data!$E$3:$E$13,"ISIC 20",Data!$D$3:$D$13)) -> 0 | P2: =(SUMIF(Data!$E$3:$E$13,"ISIC 21",Data!$D$3:$D$13)) -> 0 | Q2: =(SUMIF(Data!$E$3:$E$13,"ISIC 22",Data!$D$3:$D$13)) -> 0 | R2: =(SUMIF(Data!$E$3:$E$13,"ISIC 231",Data!$D$3:$D$13)) -> 0 | S2: =(SUMIF(Data!$E$3:$E$13,"ISIC 239",Data!$D$3:$D$13)) -> 0 | T2: =(SUMIF(Data!$E$3:$E$13,"ISIC 241",Data!$D$3:$D$13)) -> 0 | U2: =(SUMIF(Data!$E$3:$E$13,"ISIC 242",Data!$D$3:$D$13)) -> 0 | V2: =(SUMIF(Data!$E$3:$E$13,"ISIC 25",Data!$D$3:$D$13)) -> 0.057183143 | W2: =(SUMIF(Data!$E$3:$E$13,"ISIC 26",Data!$D$3:$D$13)) -> 0.18181106 | X2: =(SUMIF(Data!$E$3:$E$13,"ISIC 27",Data!$D$3:$D$13)) -> 0.18846937 | Y2: =(SUMIF(Data!$E$3:$E$13,"ISIC 28",Data!$D$3:$D$13)) -> 0 | Z2: =(SUMIF(Data!$E$3:$E$13,"ISIC 29",Data!$D$3:$D$13)) -> 0 | AA2: =(SUMIF(Data!$E$3:$E$13,"ISIC 30",Data!$D$3:$D$13))*'Factors applied'!$E$40 -> 0 | AB2: =(SUMIF(Data!$E$3:$E$13,"ISIC 30",Data!$D$3:$D$13))*'Factors applied'!$E$41 -> 0 | AC2: =(SUMIF(Data!$E$3:$E$13,"ISIC 31T33",Data!$D$3:$D$13)) -> 0 | AD2: =(SUMIF(Data!$E$3:$E$13,"ISIC 351",Data!$D$3:$D$13)) -> 0 | AE2: =(SUMIF(Data!$E$3:$E$13,"ISIC 352T353",Data!$D$3:$D$13)) -> 0 | AF2: =(SUMIF(Data!$E$3:$E$13,"ISIC 36T39",Data!$D$3:$D$13)) -> 0 | AG2: =(SUMIF(Data!$E$3:$E$13,"ISIC 41T43",Data!$D$3:$D$13)) -> 0.30988563 | AH2: =(SUMIF(Data!$E$3:$E$13,"ISIC 45T47",Data!$D$3:$D$13)) -> 0 | AI2: =(SUMIF(Data!$E$3:$E$13,"ISIC 49T53",Data!$D$3:$D$13))*'Factors applied'!$E$42 -> 0.085939214 | AJ2: =(SUMIF(Data!$E$3:$E$13,"ISIC 49T53",Data!$D$3:$D$13))*'Factors applied'!$E$43 -> 0 | AK2: =(SUMIF(Data!$E$3:$E$13,"ISIC 49T53",Data!$D$3:$D$13))*'Factors applied'!$E$44 -> 0 | AL2: =(SUMIF(Data!$E$3:$E$13,"ISIC 49T53",Data!$D$3:$D$13))*'Factors applied'!$E$45 -> 0.038610371 | AM2: =(SUMIF(Data!$E$3:$E$13,"ISIC 49T53",Data!$D$3:$D$13))*'Factors applied'!$E$46 -> 0 | AN2: =(SUMIF(Data!$E$3:$E$13,"ISIC 55T56",Data!$D$3:$D$13)) -> 0 | AO2: =(SUMIF(Data!$E$3:$E$13,"ISIC 58T60",Data!$D$3:$D$13)) -> 0 | AP2: =(SUMIF(Data!$E$3:$E$13,"ISIC 61",Data!$D$3:$D$13)) -> 0 | AQ2: =(SUMIF(Data!$E$3:$E$13,"ISIC 62T63",Data!$D$3:$D$13)) -> 0 | AR2: =(SUMIF(Data!$E$3:$E$13,"ISIC 64T66",Data!$D$3:$D$13)) -> 0 | AS2: =(SUMIF(Data!$E$3:$E$13,"ISIC 68",Data!$D$3:$D$13)) -> 0 | AT2: =(SUMIF(Data!$E$3:$E$13,"ISIC 69T82",Data!$D$3:$D$13))*'Factors applied'!$E$47 -> 0.13810121 | AU2: =(SUMIF(Data!$E$3:$E$13,"ISIC 69T82",Data!$D$3:$D$13))*'Factors applied'!$E$48 -> 0 | AV2: =(SUMIF(Data!$E$3:$E$13,"ISIC 84",Data!$D$3:$D$13)) -> 0 | AW2: =(SUMIF(Data!$E$3:$E$13,"ISIC 85",Data!$D$3:$D$13)) -> 0 | AX2: =(SUMIF(Data!$E$3:$E$13,"ISIC 86T88",Data!$D$3:$D$13)) -> 0 | AY2: =(SUMIF(Data!$E$3:$E$13,"ISIC 90T96",Data!$D$3:$D$13))*'Factors applied'!$E$49 -> 0 | AZ2: =(SUMIF(Data!$E$3:$E$13,"ISIC 90T96",Data!$D$3:$D$13))*'Factors applied'!$E$50 -> 0 | BA2: =(SUMIF(Data!$E$3:$E$13,"ISIC 97T98",Data!$D$3:$D$13)) -> 0
A3: rural residential | B3: =((SUMIF(Data!$E$3:$E$13,"ISIC 01T03",Data!$D$3:$D$13)))*'Factors applied'!$E$19 -> 0 | C3: =((SUMIF(Data!$E$3:$E$13,"ISIC 01T03",Data!$D$3:$D$13)))*'Factors applied'!$E$20 -> 0 | D3: =((SUMIF(Data!$E$3:$E$13,"ISIC 01T03",Data!$D$3:$D$13)))*'Factors applied'!$E$21 -> 0 | E3: =((SUMIF(Data!$E$3:$E$13,"ISIC 05",Data!$D$3:$D$13))) -> 0 | F3: =((SUMIF(Data!$E$3:$E$13,"ISIC 06",Data!$D$3:$D$13))) -> 0 | G3: =((SUMIF(Data!$E$3:$E$13,"ISIC 07T08",Data!$D$3:$D$13)))*'Factors applied'!$E$22 -> 0 | H3: =((SUMIF(Data!$E$3:$E$13,"ISIC 07T08",Data!$D$3:$D$13)))*'Factors applied'!$E$23 -> 0 | I3: =((SUMIF(Data!$E$3:$E$13,"ISIC 09",Data!$D$3:$D$13))) -> 0 | J3: =((SUMIF(Data!$E$3:$E$13,"ISIC 10T12",Data!$D$3:$D$13))) -> 0 | K3: =((SUMIF(Data!$E$3:$E$13,"ISIC 13T15",Data!$D$3:$D$13))) -> 0 | L3: =((SUMIF(Data!$E$3:$E$13,"ISIC 16",Data!$D$3:$D$13))) -> 0 | M3: =((SUMIF(Data!$E$3:$E$13,"ISIC 17T18",Data!$D$3:$D$13))) -> 0 | N3: =((SUMIF(Data!$E$3:$E$13,"ISIC 19",Data!$D$3:$D$13))) -> 0 | O3: =((SUMIF(Data!$E$3:$E$13,"ISIC 20",Data!$D$3:$D$13))) -> 0 | P3: =((SUMIF(Data!$E$3:$E$13,"ISIC 21",Data!$D$3:$D$13))) -> 0 | Q3: =((SUMIF(Data!$E$3:$E$13,"ISIC 22",Data!$D$3:$D$13))) -> 0 | R3: =((SUMIF(Data!$E$3:$E$13,"ISIC 231",Data!$D$3:$D$13))) -> 0 | S3: =((SUMIF(Data!$E$3:$E$13,"ISIC 239",Data!$D$3:$D$13))) -> 0 | T3: =((SUMIF(Data!$E$3:$E$13,"ISIC 241",Data!$D$3:$D$13))) -> 0 | U3: =((SUMIF(Data!$E$3:$E$13,"ISIC 242",Data!$D$3:$D$13))) -> 0 | V3: =((SUMIF(Data!$E$3:$E$13,"ISIC 25",Data!$D$3:$D$13))) -> 0.057183143 | W3: =((SUMIF(Data!$E$3:$E$13,"ISIC 26",Data!$D$3:$D$13))) -> 0.18181106 | X3: =((SUMIF(Data!$E$3:$E$13,"ISIC 27",Data!$D$3:$D$13))) -> 0.18846937 | Y3: =((SUMIF(Data!$E$3:$E$13,"ISIC 28",Data!$D$3:$D$13))) -> 0 | Z3: =((SUMIF(Data!$E$3:$E$13,"ISIC 29",Data!$D$3:$D$13))) -> 0 | AA3: =((SUMIF(Data!$E$3:$E$13,"ISIC 30",Data!$D$3:$D$13)))*'Factors applied'!$E$24 -> 0 | AB3: =((SUMIF(Data!$E$3:$E$13,"ISIC 30",Data!$D$3:$D$13)))*'Factors applied'!$E$25 -> 0 | AC3: =((SUMIF(Data!$E$3:$E$13,"ISIC 31T33",Data!$D$3:$D$13))) -> 0 | AD3: =((SUMIF(Data!$E$3:$E$13,"ISIC 351",Data!$D$3:$D$13))) -> 0 | AE3: =((SUMIF(Data!$E$3:$E$13,"ISIC 352T353",Data!$D$3:$D$13))) -> 0 | AF3: =((SUMIF(Data!$E$3:$E$13,"ISIC 36T39",Data!$D$3:$D$13))) -> 0 | AG3: =((SUMIF(Data!$E$3:$E$13,"ISIC 41T43",Data!$D$3:$D$13))) -> 0.30988563 | AH3: =((SUMIF(Data!$E$3:$E$13,"ISIC 45T47",Data!$D$3:$D$13))) -> 0 | AI3: =((SUMIF(Data!$E$3:$E$13,"ISIC 49T53",Data!$D$3:$D$13)))*'Factors applied'!$E$26 -> 0.085939214 | AJ3: =((SUMIF(Data!$E$3:$E$13,"ISIC 49T53",Data!$D$3:$D$13)))*'Factors applied'!$E$27 -> 0 | AK3: =((SUMIF(Data!$E$3:$E$13,"ISIC 49T53",Data!$D$3:$D$13)))*'Factors applied'!$E$28 -> 0 | AL3: =((SUMIF(Data!$E$3:$E$13,"ISIC 49T53",Data!$D$3:$D$13)))*'Factors applied'!$E$29 -> 0.038610371 | AM3: =((SUMIF(Data!$E$3:$E$13,"ISIC 49T53",Data!$D$3:$D$13)))*'Factors applied'!$E$30 -> 0 | AN3: =((SUMIF(Data!$E$3:$E$13,"ISIC 55T56",Data!$D$3:$D$13))) -> 0 | AO3: =((SUMIF(Data!$E$3:$E$13,"ISIC 58T60",Data!$D$3:$D$13))) -> 0 | AP3: =((SUMIF(Data!$E$3:$E$13,"ISIC 61",Data!$D$3:$D$13))) -> 0 | AQ3: =((SUMIF(Data!$E$3:$E$13,"ISIC 62T63",Data!$D$3:$D$13))) -> 0 | AR3: =((SUMIF(Data!$E$3:$E$13,"ISIC 64T66",Data!$D$3:$D$13))) -> 0 | AS3: =((SUMIF(Data!$E$3:$E$13,"ISIC 68",Data!$D$3:$D$13))) -> 0 | AT3: =((SUMIF(Data!$E$3:$E$13,"ISIC 69T82",Data!$D$3:$D$13)))*'Factors applied'!$E$31 -> 0.13810121 | AU3: =((SUMIF(Data!$E$3:$E$13,"ISIC 69T82",Data!$D$3:$D$13)))*'Factors applied'!$E$32 -> 0 | AV3: =((SUMIF(Data!$E$3:$E$13,"ISIC 84",Data!$D$3:$D$13))) -> 0 | AW3: =((SUMIF(Data!$E$3:$E$13,"ISIC 85",Data!$D$3:$D$13))) -> 0 | AX3: =((SUMIF(Data!$E$3:$E$13,"ISIC 86T88",Data!$D$3:$D$13))) -> 0 | AY3: =((SUMIF(Data!$E$3:$E$13,"ISIC 90T96",Data!$D$3:$D$13)))*'Factors applied'!$E$33 -> 0 | AZ3: =((SUMIF(Data!$E$3:$E$13,"ISIC 90T96",Data!$D$3:$D$13)))*'Factors applied'!$E$34 -> 0 | BA3: =((SUMIF(Data!$E$3:$E$13,"ISIC 97T98",Data!$D$3:$D$13))) -> 0
A4: commercial | B4: =(SUMIF(Data!$E$17:$E$27,"ISIC 01T03",Data!$D$17:$D$27))*'Factors applied'!$E$3 -> 0 | C4: =(SUMIF(Data!$E$17:$E$27,"ISIC 01T03",Data!$D$17:$D$27))*'Factors applied'!$E$4 -> 0 | D4: =(SUMIF(Data!$E$17:$E$27,"ISIC 01T03",Data!$D$17:$D$27))*'Factors applied'!$E$5 -> 0 | E4: =(SUMIF(Data!$E$17:$E$27,"ISIC 05",Data!$D$17:$D$27)) -> 0 | F4: =(SUMIF(Data!$E$17:$E$27,"ISIC 06",Data!$D$17:$D$27)) -> 0 | G4: =(SUMIF(Data!$E$17:$E$27,"ISIC 07T08",Data!$D$17:$D$27))*'Factors applied'!$E$6 -> 0 | H4: =(SUMIF(Data!$E$17:$E$27,"ISIC 07T08",Data!$D$17:$D$27))*'Factors applied'!$E$7 -> 0 | I4: =(SUMIF(Data!$E$17:$E$27,"ISIC 09",Data!$D$17:$D$27)) -> 0 | J4: =(SUMIF(Data!$E$17:$E$27,"ISIC 10T12",Data!$D$17:$D$27)) -> 0 | K4: =(SUMIF(Data!$E$17:$E$27,"ISIC 13T15",Data!$D$17:$D$27)) -> 0 | L4: =(SUMIF(Data!$E$17:$E$27,"ISIC 16",Data!$D$17:$D$27)) -> 0 | M4: =(SUMIF(Data!$E$17:$E$27,"ISIC 17T18",Data!$D$17:$D$27)) -> 0 | N4: =(SUMIF(Data!$E$17:$E$27,"ISIC 19",Data!$D$17:$D$27)) -> 0 | O4: =(SUMIF(Data!$E$17:$E$27,"ISIC 20",Data!$D$17:$D$27)) -> 0 | P4: =(SUMIF(Data!$E$17:$E$27,"ISIC 21",Data!$D$17:$D$27)) -> 0 | Q4: =(SUMIF(Data!$E$17:$E$27,"ISIC 22",Data!$D$17:$D$27)) -> 0 | R4: =(SUMIF(Data!$E$17:$E$27,"ISIC 231",Data!$D$17:$D$27)) -> 0 | S4: =(SUMIF(Data!$E$17:$E$27,"ISIC 239",Data!$D$17:$D$27)) -> 0 | T4: =(SUMIF(Data!$E$17:$E$27,"ISIC 241",Data!$D$17:$D$27)) -> 0 | U4: =(SUMIF(Data!$E$17:$E$27,"ISIC 242",Data!$D$17:$D$27)) -> 0 | V4: =(SUMIF(Data!$E$17:$E$27,"ISIC 25",Data!$D$17:$D$27)) -> 0.089657693 | W4: =(SUMIF(Data!$E$17:$E$27,"ISIC 26",Data!$D$17:$D$27)) -> 0.26233402 | X4: =(SUMIF(Data!$E$17:$E$27,"ISIC 27",Data!$D$17:$D$27)) -> 0.16944817 | Y4: =(SUMIF(Data!$E$17:$E$27,"ISIC 28",Data!$D$17:$D$27)) -> 0 | Z4: =(SUMIF(Data!$E$17:$E$27,"ISIC 29",Data!$D$17:$D$27)) -> 0 | AA4: =(SUMIF(Data!$E$17:$E$27,"ISIC 30",Data!$D$17:$D$27))*'Factors applied'!$E$8 -> 0 | AB4: =(SUMIF(Data!$E$17:$E$27,"ISIC 30",Data!$D$17:$D$27))*'Factors applied'!$E$9 -> 0 | AC4: =(SUMIF(Data!$E$17:$E$27,"ISIC 31T33",Data!$D$17:$D$27)) -> 0 | AD4: =(SUMIF(Data!$E$17:$E$27,"ISIC 351",Data!$D$17:$D$27)) -> 0 | AE4: =(SUMIF(Data!$E$17:$E$27,"ISIC 352T353",Data!$D$17:$D$27)) -> 0 | AF4: =(SUMIF(Data!$E$17:$E$27,"ISIC 36T39",Data!$D$17:$D$27)) -> 0 | AG4: =(SUMIF(Data!$E$17:$E$27,"ISIC 41T43",Data!$D$17:$D$27)) -> 0.42922402 | AH4: =(SUMIF(Data!$E$17:$E$27,"ISIC 45T47",Data!$D$17:$D$27)) -> 0 | AI4: =(SUMIF(Data!$E$17:$E$27,"ISIC 49T53",Data!$D$17:$D$27))*'Factors applied'!$E$10 -> 0 | AJ4: =(SUMIF(Data!$E$17:$E$27,"ISIC 49T53",Data!$D$17:$D$27))*'Factors applied'!$E$11 -> 0 | AK4: =(SUMIF(Data!$E$17:$E$27,"ISIC 49T53",Data!$D$17:$D$27))*'Factors applied'!$E$12 -> 0 | AL4: =(SUMIF(Data!$E$17:$E$27,"ISIC 49T53",Data!$D$17:$D$27))*'Factors applied'!$E$13 -> 0 | AM4: =(SUMIF(Data!$E$17:$E$27,"ISIC 49T53",Data!$D$17:$D$27))*'Factors applied'!$E$14 -> 0 | AN4: =(SUMIF(Data!$E$17:$E$27,"ISIC 55T56",Data!$D$17:$D$27)) -> 0 | AO4: =(SUMIF(Data!$E$17:$E$27,"ISIC 58T60",Data!$D$17:$D$27)) -> 0 | AP4: =(SUMIF(Data!$E$17:$E$27,"ISIC 61",Data!$D$17:$D$27)) -> 0 | AQ4: =(SUMIF(Data!$E$17:$E$27,"ISIC 62T63",Data!$D$17:$D$27)) -> 0 | AR4: =(SUMIF(Data!$E$17:$E$27,"ISIC 64T66",Data!$D$17:$D$27)) -> 0 | AS4: =(SUMIF(Data!$E$17:$E$27,"ISIC 68",Data!$D$17:$D$27)) -> 0 | AT4: =(SUMIF(Data!$E$17:$E$27,"ISIC 69T82",Data!$D$17:$D$27))*'Factors applied'!$E$15 -> 0.049336095 | AU4: =(SUMIF(Data!$E$17:$E$27,"ISIC 69T82",Data!$D$17:$D$27))*'Factors applied'!$E$16 -> 0 | AV4: =(SUMIF(Data!$E$17:$E$27,"ISIC 84",Data!$D$17:$D$27)) -> 0 | AW4: =(SUMIF(Data!$E$17:$E$27,"ISIC 85",Data!$D$17:$D$27)) -> 0 | AX4: =(SUMIF(Data!$E$17:$E$27,"ISIC 86T88",Data!$D$17:$D$27)) -> 0 | AY4: =(SUMIF(Data!$E$17:$E$27,"ISIC 90T96",Data!$D$17:$D$27))*'Factors applied'!$E$17 -> 0 | AZ4: =(SUMIF(Data!$E$17:$E$27,"ISIC 90T96",Data!$D$17:$D$27))*'Factors applied'!$E$18 -> 0 | BA4: =(SUMIF(Data!$E$17:$E$27,"ISIC 97T98",Data!$D$17:$D$27)) -> 0
A5: data centers | B5: =B4 -> 0 | C5: =C4 -> 0 | D5: =D4 -> 0 | E5: =E4 -> 0 | F5: =F4 -> 0 | G5: =G4 -> 0 | H5: =H4 -> 0 | I5: =I4 -> 0 | ... BA5: =BA4 -> 0
