Workbook
Name a: #REF!
Name AsphaltStore: [1]Control!$D$50
Name base.year: #REF!
Name BaseYear: 2018
Name BTV11_15: #REF!
Name BVT17_15: #REF!
Name CAAGR_tolerance: 200
Name CH4_to_CO2e: '[2]Cross-Page Data'!$C$12
Name CH4GWP: #REF!
Name CO2_T4_APS: #REF!
Name CO2_T4_NZE: #REF!
Name CO2_T4_STEPS: #REF!
Name CO2_T5_APS: #REF!
Name CO2_T5_CPS: #REF!
Name CO2_T5_NZE: #REF!
Name CO2_T5_STEPS: #REF!
Name coal.past: #REF!
Name COAL_PRODUCTION: #REF!
Name Coal_trade: #REF!
Name coaldemand: #REF!
Name CokeCoalStore: [1]Control!$D$63
Name Constants.Density.Diesel: #REF!
Name Constants.Density.Ethanol: #REF!
Name Constants.Density.JetFuel: #REF!
Name Constants.Density.MotorSpirit: #REF!
Name ConsumeBlock1: '[1]Default State Energy Data Table'!$A$6:$AM$67
Name Conversion.to.average.power: #REF!
Name Conversion.water.L: #REF!
Name Conversion.water.units: #REF!
Name Conversions.Area.m2: #REF!
Name Conversions.Area.Units: #REF!
Name Conversions.Energy.Joules: #REF!
Name Conversions.Energy.Units: #REF!
Name Conversions.Money.GBP: #REF!
Name Conversions.Money.Units: #REF!
Name Conversions.Power.Units: #REF!
Name Conversions.Power.Watts: #REF!
Name Cost.Capital.Scenario: #REF!
Name Cost.Finance.Scenario: #REF!
Name Cost.Fuel.Scenario: #REF!
Name Cost.Infrastructure.Scenario: #REF!
Name cpi_2010to2012: #REF!
Name cpi_2013to2012: #REF!
Name cpi_2014to2012: #REF!
Name cpi_2016to2012: #REF!
Name CreateRegions: #REF!
Name csp.capacity: #REF!
Name CSVfilepath: #REF!
Name D: #REF!
Name dd: #REF!
Name ddd: #REF!
Name ddddd: #REF!
Name dddddd: #REF!
Name deflator_year: "$2018"
Name DeflatorYear: "$2018"
Name discount_factors: #REF!
Name DistillStore: [1]Control!$D$51
Name DW_EDO_022WV: #REF!
Name DW_EDO_023WV: #REF!
Name DW_EDO_024WV: #REF!

Sheet About
A1: PEaWHRP Process Efficiency and Waste Heat Recovery Parameters
A4: Sources: | B4: Recovery Costs | D4: Waste Heat Recovery Equipment Costs
B5: Kermeli et al. | D5: U.S. DOE Advanced Manufacturing Office / BCS Inc.; EPRI; Case Studies in Thermal Engineering
B6: 2022 | D6: 2008-2025
B7: Energy efficiency potentials in the EU industry: impacts of deep decarbonization technologies | D7: Steam Tip Sheets #3 and #26A; Waste Heat Recovery: Technology and Opportunities in U.S. Industry; EPRI report 1020134; industrial ORC capex survey
B8: https://link.springer.com/article/10.1007/s12053-022-10071-8#Sec15 | D8: https://www.energy.gov/sites/prod/files/2014/05/f16/steam26a_condensing.pdf ; https://www.epri.com/research/products/1020134
B9: Supplementary Information | D9: Basis for gap-fill technology assumptions (blue inputs); evidence table on tab 'summary'
B11: Specific Energy Consumption | D11: Fuel Carbon Intensity
B12: Fleiter et al. (via Kermeli et al. Table 1) | D12: U.S. Environmental Protection Agency
B13: 2017 | D13: 2022-2024
B14: Baseline scenario of the heating and cooling demand in buildings and industry in the 14 MSs until 2050 | D14: GHG Emission Factors Hub (stationary combustion); eGRID (US average grid intensity)
B15: https://link.springer.com/article/10.1007/s12053-022-10071-8/tables/1 | D15: https://www.epa.gov/climateleadership/ghg-emission-factors-hub
B16: Pasted to tab 'Kermeli SEC' | D16: Used for the $/MMBtu -> $/tCO2 equivalence table on tab 'summary'
B18: US Production Tonnages | D18: Industry Cost of Capital
B19: USGS; AISI / worldsteel; U.S. EIA; FAO; American Foundry Society | D19: EPS input data folder: indst / BCoISC
B20: 2018-2025 | D20: as of 2026-07-29
B21: Mineral Commodity Summaries (aluminum, soda ash, ammonia, cement, clinker); crude steel by route; coke; paper & pulp; aluminum castings | D21: Real weighted average cost of capital by EPS industry (no hurdle premium included)
B22: https://pubs.usgs.gov/periodicals/mcs2025/ ; https://www.eia.gov/todayinenergy/detail.php?id=67385 | D22: Tab 'BCoISC-WACCbI'
B23: Eight products ESTIMATED (no official source found) - see 'product map' cols I/J | D23: Real WACC by EPS industry from the EPS input-data folder (indst / BCoISC), as of 2026-07-29.
B25: Industry Energy Base | D25: Waste Heat Potential & Temperature Splits
B26: U.S. Energy Information Administration, Manufacturing Energy Consumption Survey (MECS) | D26: Imported from 'Waste Heat Recovery Potl by Indst' file (Bianchi-derived)
B27: 2018 | D27: -
B28: Table 3.1 Fuel Consumption, by NAICS code | D28: Industry waste-heat potential (dimensionless) and low / medium / high temperature shares
B29: https://www.eia.gov/consumption/manufacturing/data/2018/pdf/Table3_1.pdf | D29: External links now broken; cached values retained
B30: Mapped to EPS industries on tab 'energy base (MECS)' | D30: Tabs: 'WHRPbI', 'EU Data', 'heat share (src)'. The source file's 'BPFUbIP-Summed Data by Industry' tab is no longer in this workbook; its values are cached where used.
B32: Industry Heat Temperature Bands | D32: Zero-Savings & Zero-Cost Corrections (rounding recovery)
B33: Derived from the industry / BPFUbIP source file | D33: Worrell, Kermeli & Galitsky (2013) ENERGY STAR Cement Guide; Fleiter et al. (2012) Energy 40(1); Worrell et al. (2010) LBNL-4779E; Zhang et al. (2021) J. Cleaner Production
B34: - | D34: 2010-2021
B35: Share of each industry's boiler and non-boiler heat falling in five temperature bands (<100C, 100-200C, 200-500C, 500-1000C, >1000C) | D35: Kermeli's published tables round savings to 0.1 GJ/t and costs to whole euros, zeroing 12 small measures and 5 costs. True values recovered from the primary sources and wired into 'Kermeli Data' (green cells) via tab 'src review'.
B36: - | D36: https://www.energystar.gov/sites/default/files/buildings/tools/ENERGY%20STAR%20Guide%20for%20the%20Cement%20Industry%2028_08_2013%20Final.pdf ; https://www.osti.gov/servlets/purl/1026806 ; doi 10.1016/j.energy.2012.02.025 ; Zhang et al. (2021) via https://pure.iiasa.ac.at/id/eprint/16625 (Elsevier PII S0959652620333801)
B37: Tab 'indst heat consumption'; used to deduct already-credited burner-integral recovery band by band | D37: Clinker-to-cement ratio 76% (GNR 2019, via Kermeli et al. 2022) used for basis conversions; full audit trail, verdicts and open items on tab 'src review'.
A40: Notes:
A41: Purpose | B41: Converts the single-average WHR capital cost into measure-level cost data and cost-binned energy-savings supply curves for EPS. (The LEGACY Calcs and WHRCC tabs that held the original single-average calculation were validated against the new outputs and removed 2026-07-29.)
A42: Outputs | B42: PEaWHRP-WMD / PEaWHRP-PMD = measure-level data (25 EPS industries x 7 waste-heat / 17 efficiency measure slots; savings as % of industry fuel or electricity, capital and operating intensities per unit of annual savings capacity, lifetime). PEaWHRP-WM / PEaWHRP-PM = subscript element lists. Efficiency slots reduced 18 -> 17 on 2026-07-29 by re-packing the chemicals list after an equipment-replacement exclusion.
A43: Master table | B43: Kermeli Data' - extended with added columns (classification, EPS industry, carrier shares, temperature band); source values never retyped.
A44: Classification | B44: Three buckets: (1) unit WHR = burner-integral recovery, excluded (handled in the unit-efficiency files); (2) system WHR = process-level recovery -> waste-heat outputs; (3) other process efficiency -> efficiency outputs.
A45: Classification rulings (G0.1) | B45: Scrap preheat = system WHR; ammonia air preheat = system WHR; glass low-NOx burners = unit (excluded); optimized burning = process; CHP and cogeneration = excluded; top-gas recovery turbine = system WHR; top-gas recycling = process; clinker substitution = excluded; the fuel-switching and electrification block = excluded. Row-by-row map on tab 'reconciliation'.
A46: Do-not-double-count | B46: Recovery already credited in unit-efficiency files is never re-credited: glass regenerative furnaces; blast-furnace hot-blast stoves and coke-oven regenerators; cement preheater/precalciner; recuperative/regenerative burners generally.
A47: Burner-integral credits | B47: Start-year penetrations already credited by temperature band: <100C 0%; 100-200C 0%; 200-500C 5%; 500-1000C 17.4%; >1000C 58.7%. Deducted when sizing gap-fill.
A48: Energy base (G0.6) | B48: Fuel savings are expressed as a percentage of industry TOTAL COMBUSTION FUEL (MECS total less electricity); electricity savings as a percentage of total net electricity. Kermeli Table 1 reports a heating share of 1.0 for fuels in every product, so fuel savings draw on total fuel. The heat-share column on 'energy base (MECS)' is retained for reference only.
A49: Discount rate | B49: Industry real WACC (tab 'BCoISC-WACCbI') + hurdle premium of 7 percentage points (input cell economics!AE4) => approx. 10.6-12.6% for covered industries. A flat 15% sensitivity is retained in economics column Y.
A50: Cost of conserved energy | B50: CCE = (investment annualised over technical lifetime + annual O&M) / annual energy saved, in 2012$/MMBtu, gross of the fuel-savings benefit. Mixed-carrier measures allocate investment and O&M in proportion to carrier savings shares. Negative-O&M measures may return negative CCE and are retained.
A51: Cost dispersion | B51: Each measure's CCE is treated as the mean of a normal distribution with sigma = 0.30 x |CCE|; tail mass below the bottom edge pools into the bottom bin and above the top edge into the top bin. Applied on the binned tabs ('dist engine'); left endogenous to EPS/Vensim for the measure-level tables.
A52: Bins | B52: Approved edges: <= $0 (bottom), $0.25 steps to $20, > $20 (top) = 82 bins per carrier. (The former 'bins proposal' tab has been removed; this line is the record.)
... A59: Temperature bands | B59: Gap-fill and Bianchi-fill targets are reduced by the burner-integral penetration already credited in the unit-efficiency files, applied band by band using each industry's five-band heat split (tab 'indst heat consumption', columns D-H) and the credited penetrations on tab 'summary' (cells B93:F93). Bands below 500C are filled with the economizer/condensing class, bands above 500C with the recuperator/air-preheater class.
A61: Conversions: | C61: Source / verification (primary)
A62: =1/cpi!B12 | B62: 2021 EUR to 2021 USD | C62: Live link: = 1 / cpi!B12 (ECB 2021 annual avg 1.1827 USD/EUR). Replaces hardcoded 0.8458 (which matched neither ECB 0.8455 nor IRS 0.846 exactly); applied as divisor: EUR/GJ / rate = USD/GJ.
A63: =cpi!B10 | B63: 2021 USD to 2012 USD | C63: Live link: = cpi!B10 = CPI2012/CPI2021, computed from the full BLS CPI-U series on tab 'Data' (229.594 / 270.970 = 0.8473). Replaces hardcoded 0.847.
A64: =cpi!B13 | B64: GJ to BTU | C64: NIST: 1 Btu(IT) = 1055.05585 J -> 1 GJ = 1e9 / 1055.05585 = 947,817 Btu. Value verified.
A65: ='src review'!B9 | B65: clinker-to-cement ratio (2015) | C65: GNR (2019) via Kermeli et al. (2022). Input cell: 'src review'!B9 - used to convert per-tonne-cement source figures onto Kermeli's per-tonne-clinker basis and vice versa.

Sheet hand-maintained inputs
A1: Hand-maintained model input CSVs (not produced by ExportPEaWHRP.py)
A2: Documented 2026-07-31. These four CSVs live beside this workbook and are read directly by EPS.mdl. Edit them in a text editor; keep this tab in sync.
A4: File | B4: Contents & units | C4: Methodology & sources
A5: PEaWHRP-PAC.csv | B5: Payback acceptance curve: share of firms accepting a simple payback of N years (survivor curve), rows = Measure Set (waste heat / process efficiency, currently identical), cols = payback grid 0-10 yr. Read as Vensim lookups (PAC Payback Acceptance Curve). | C5: Anchored on revealed adoption in DOE IAC audit data: Anderson & Newell (2004), RFF/Resources for the Future - implicit threshold 1.25-1.5 yr payback (65-80% hurdle rate), ~half of recommendations rejected; Muthulingam, Corbett, Benartzi & Oppenheim (2013), M&SOM 15(4) - 89,299 recommendations, mean payback 1.06 yr, adoption 50.16%. Shape ~lognormal(median 1 yr, sigma 0.9); S(0)=0.85 reflects incomplete adoption even at instant payback. Same construct as EIA NEMS IDM 'AcceptFrac' payback acceptance curve (kept as optimistic sensitivity bound, NOT adopted - it is a CHP engineering assumption, 100% acceptance at 1 yr). Full derivation: PEaWHRP_PaybackAcceptance_Plan.md at repo root.
A6: PEaWHRP-MCL-mult.csv | B6: Measure Cost Level multipliers scaling levelized cost / payback across 5 cost variants per measure. Decision-only: cash flows use unadjusted input costs. | C6: Equal-probability quintile midpoints of Normal(mean 1, sigma 0.30): 0.62/0.84/1.00/1.16/1.38. The +/-30% sigma spread was specified in the project brief (Dan O'Brien); discretization documented in WHR_EfficiencyMeasures_Restructure_Plan.md sec 4.5. Note: for measures with negative O&M cost the multiplier amplifies the benefit at high cost levels - flagged for review.
A7: PEaWHRP-MCL-share.csv | B7: Share of each measure's potential assigned to each cost level; must sum to 1. | C7: Equal 20% shares by construction (quintile discretization, same source as multipliers).
A8: PEaWHRP-SoCEMDSiaY.csv | B8: Share of each cost-effective tranche's remaining potential that begins deployment per year (0.2). | C8: Mirrors the industrial CCS convention SoCECRCSiaY (InputData/ccs/SoCECRCSiaY/SoCECRCSiaY.csv = 0.2/yr), adopted for consistency across EPS endogenous-deployment structures.
A10: Retired: | B10: PEaWHRP-MHRP.csv (hurdle premium; superseded by the PAC curve 2026-07-31), PEaWHRP-PSUS.csv (price-signal unlock sensitivity; superseded by the PAC curve 2026-07-31). Kept as .retired files for history.

Sheet Data
A1: Historical Consumer Price Index for All Urban Consumers (CPI-U): U.S. city average, all items, index
A2: averages — Continued
A3: [1982-84=100, unless otherwise noted]
A5: Source: | B5: U.S. Bureau of Labor Statistics
B6: 2024
B7: Historical CPI-U
B8: https://data.bls.gov/pdq/SurveyOutputServlet
A10: Year | B10: Semiannual averages | D10: Annual avg. | E10: Percent change from previous | G10: Multiply by to get 2012 Dollars
B11: 1st half | C11: 2nd half | E11: Dec. | F11: Annual avg.
A12: 1968............................................................................. . | B12: – | C12: – | D12: 34.8 | E12: 4.7 | F12: 4.2
A13: 1969............................................................................. . | B13: – | C13: – | D13: 36.7 | E13: 6.2 | F13: 5.5
A14: 1970............................................................................. . | B14: – | C14: – | D14: 38.8 | E14: 5.6 | F14: 5.7
A15: 1971............................................................................. . | B15: – | C15: – | D15: 40.5 | E15: 3.3 | F15: 4.4
A16: 1972............................................................................. . | B16: – | C16: – | D16: 41.8 | E16: 3.4 | F16: 3.2
A17: 1973............................................................................. . | B17: – | C17: – | D17: 44.4 | E17: 8.7 | F17: 6.2
A18: 1974............................................................................. . | B18: – | C18: – | D18: 49.3 | E18: 12.3 | F18: 11
A19: 1975............................................................................. . | B19: – | C19: – | D19: 53.8 | E19: 6.9 | F19: 9.1
A20: 1976............................................................................. . | B20: – | C20: – | D20: 56.9 | E20: 4.9 | F20: 5.8
A21: 1977............................................................................. . | B21: – | C21: – | D21: 60.6 | E21: 6.7 | F21: 6.5
A22: 1978............................................................................. . | B22: – | C22: – | D22: 65.2 | E22: 9 | F22: 7.6
A23: 1979............................................................................. . | B23: – | C23: – | D23: 72.6 | E23: 13.3 | F23: 11.3
... A27: 1983............................................................................. . | B27: – | C27: – | D27: 99.6 | E27: 3.8 | F27: 3.2
A28: 1984............................................................................. . | B28: 102.9 | C28: 104.9 | D28: 103.9 | E28: 3.9 | F28: 4.3
A29: 1985............................................................................. . | B29: 106.6 | C29: 108.5 | D29: 107.6 | E29: 3.8 | F29: 3.6
A30: 1986............................................................................. . | B30: 109.1 | C30: 110.1 | D30: 109.6 | E30: 1.1 | F30: 1.9
A31: 1987............................................................................. . | B31: 112.4 | C31: 114.9 | D31: 113.6 | E31: 4.4 | F31: 3.6
A32: 1988............................................................................. . | B32: 116.8 | C32: 119.7 | D32: 118.3 | E32: 4.4 | F32: 4.1
A33: 1989............................................................................. . | B33: 122.7 | C33: 125.3 | D33: 124 | E33: 4.6 | F33: 4.8
A34: 1990............................................................................. . | B34: 128.7 | C34: 132.6 | D34: 130.7 | E34: 6.1 | F34: 5.4 | G34: =$D$56/D34
A35: 1991............................................................................. . | B35: 135.2 | C35: 137.2 | D35: 136.2 | E35: 3.1 | F35: 4.2 | G35: =$D$56/D35
A36: 1992............................................................................. . | B36: 139.2 | C36: 141.4 | D36: 140.3 | E36: 2.9 | F36: 3 | G36: =$D$56/D36
A37: 1993............................................................................. . | B37: 143.7 | C37: 145.3 | D37: 144.5 | E37: 2.7 | F37: 3 | G37: =$D$56/D37
A38: 1994............................................................................. . | B38: 147.2 | C38: 149.3 | D38: 148.2 | E38: 2.7 | F38: 2.6 | G38: =$D$56/D38
A39: 1995............................................................................. . | B39: 151.5 | C39: 153.2 | D39: 152.4 | E39: 2.5 | F39: 2.8 | G39: =$D$56/D39
A40: 1996............................................................................. . | B40: 155.8 | C40: 157.9 | D40: 156.9 | E40: 3.3 | F40: 3 | G40: =$D$56/D40
A41: 1997............................................................................. . | B41: 159.9 | C41: 161.2 | D41: 160.5 | E41: 1.7 | F41: 2.3 | G41: =$D$56/D41
A42: 1998............................................................................. . | B42: 162.3 | C42: 163.7 | D42: 163 | E42: 1.6 | F42: 1.6 | G42: =$D$56/D42
A43: 1999............................................................................. . | B43: 165.4 | C43: 167.8 | D43: 166.6 | E43: 2.7 | F43: 2.2 | G43: =$D$56/D43
A44: 2000............................................................................. . | B44: 170.8 | C44: 173.6 | D44: 172.2 | E44: 3.4 | F44: 3.4 | G44: =$D$56/D44
A45: 2001............................................................................. . | B45: 176.6 | C45: 177.5 | D45: 177.1 | E45: 1.6 | F45: 2.8 | G45: =$D$56/D45
... A66: 2022............................................................................. . | B66: 288.347 | C66: 296.963 | D66: 292.655 | E66: 6.5 | F66: 8 | G66: =$D$56/D66
A67: 2023............................................................................. . | B67: 302.408 | C67: 306.996 | D67: 304.702 | G67: =$D$56/D67
A68: 2024............................................................................. . | B68: 312.145 | C68: 315.233 | D68: 313.689 | G68: =$D$56/D68
A69: 2025............................................................................. . | B69: 320.13 | C69: 324.16 | D69: 321.962 | G69: =$D$56/D69

Sheet cpi
A1: CPI-U deflators & unit conversions
A2: US CPI-U, all items, U.S. city average, not seasonally adjusted, annual average (1982-84=100). Source: BLS series CUUR0000SA0. Values now pulled live from the 'Data' sheet, which holds the full 1968-2025 series.
A3: Used to deflate Kermeli 2021-EUR costs to 2012 USD (the model's reporting-year basis, matching LEGACY Calcs).
A5: Year | B5: CPI-U (annual avg) | C5: Deflator to 2012$
A6: 2012 | B6: =Data!D56 | C6: =$B$6/B6
A7: 2015 | B7: =Data!D59 | C7: =$B$6/B7
A8: 2021 | B8: =Data!D65 | C8: =$B$6/B8
A10: Key deflator (2021 -> 2012 USD) | B10: =C8 | C10: = CPI2012 / CPI2021. LEGACY About!A18 uses 0.847 (hardcoded); this cell recomputes it live = 0.8473.
A12: EUR->USD (2021 average) | B12: 1.1827 | C12: USD per EUR. LEGACY About!A17 stores the inverse 0.8458 (EUR per USD) and divides.
A13: GJ -> BTU | B13: 947817 | C13: BTU per GJ. Matches LEGACY About!A19.
A15: 2012$/MMBtu conversion helper | B15: =B13/1000000 | C15: BTU per GJ / 1e6 = MMBtu per GJ (0.947817).

Sheet summary
A1: Summary — supply curves, gap-fill assumptions, review flags
A2: Curves = cumulative % reduction of industry carrier energy vs CCE (2012$/MMBtu, @10% real). Covered industries from Kermeli measures; 19 uncovered industries carry the Bianchi fill (fuel-whr only, assumed cost $4.95/MMBtu).
A4: Proposed gap-fill technology assumptions (generic heat recovery, covered sectors) — before applying to curves
A5: Technology | B5: Temp band | C5: Capex $/kW | D5: Life (yr) | E5: O&M %capex/yr | F5: Load (h/yr) | G5: CCE @10% ($/MMBtu)
A6: Plug-in recuperator / fired-heater APH (gas-gas, eps~0.4) | B6: 200-1000C | C6: 300 | D6: 20 | E6: 0.02 | F6: 8000 | G6: 1.5107667
A7: Economizer (boiler feedwater, <200C) | B7: 100-200C | C7: 250 | D7: 20 | E7: 0.02 | F7: 8000 | G7: 1.2589722
A8: Condensing HX (deep <100C latent recovery) | B8: <100C | C8: 300 | D8: 20 | E8: 0.025 | F8: 8000 | G8: 1.5657198
A9: Waste-heat ORC (heat-to-power, $/kWe) | B9: 200-500C | C9: 2500 | D9: 20 | E9: 0.02 | F9: 8000 | G9: 12.589722
A10: Generic Bianchi-fill recovery (uncovered industries) | B10: mixed | C10: 275 | D10: 20 | E10: 0.02 | F10: 8000 | G10: 1.3848695
A11: Sizing rule (double-count-safe): gap-fill applies to COVERED industries only, sized to the RESIDUAL = Bianchi potential − existing curve capture − burner-integral credit already taken in unit files (by temp band: 200-500C 5%, 500-1000C 17.4%, >1000C 58.7%). Recuperator/APH fill only the un-credited band share; economizer/condensing HX fill <500C where unit files credit 0-5% (this file's declared scope); NO ORC fill in cement (clinker ORC measure already in curve). Uncovered industries already carry the full Bianchi fill — no gap-fill there.
A12: Do-not-double-count guard: glass regenerative furnaces, BF hot-blast stoves/coke regenerators, cement preheater/precalciner are inside the >1000C burner-integral credit — the 58.7% deduction above prevents re-crediting them.
A13: Review flags
A14: 1. GUESSED TONNAGES: glass, pulp grades, methanol, carbon black are industry ballparks (tagged); Al foundries has none (contributes 0); ethylene is 2019. Curves scale 1:1 with these.
A15: 2. GAP-FILL PRICES ARE PROPOSALS: the 4 blue rows above are DOE/EPRI-anchored picks, not data; not yet in curves. subject to review, then inject per the sizing rule (A11).
A16: 3. RESOLVED — bottom-up vs MECS check complete (validation F13:I19); ratios 0.12-0.89, all < 1, shortfalls explainable.
A17: 4. CURVES UNDERSHOOT LITERATURE POTENTIAL (e.g. steel ~2% found vs ~14% recoverable) because Kermeli omits generic bolt-on HX — closing flag 2 closes this.
A18: 5. DISCOUNT RATE = industry WACC (BCoISC-WACCbI tab) + hurdle premium (economics!AE4, blue, = +7pp per G0.1 ruling) => covered industries ~10.6-12.6%. Rationale: owners don't invest at break-even (legacy Calcs: 'hurdle = WACC + risk premium'). Flat-15% sensitivity retained (economics col Y). Tune AE4 to change every CCE at once.
A19: 6. JUDGMENT CALLS: ammonia reactor cooling + clinker grate cooler counted as system WHR; arguable overlap with unit-file high-temp credit. If reversed, cement/ammonia whr shrink modestly.
A20: 7. BAKED-IN BASES (documented in-cell, swappable): MECS 2018; heat-share fractions from imported potential file; ammonia N->NH3 conversion; pig iron = BOF-route proxy.
A22: Cost curves — rows 11-18 of each output tab (pulp&paper, refining, chemicals, rubber&plastic, glass, cement, iron&steel, other metals)
A60: CCE $/MMBtu -> $/tCO2 (carbon-price equivalence by displaced fuel)
A61: Fuel displaced | B61: kg CO2 / MMBtu | C61: $/tCO2 per $1/MMBtu | D61: Bulk curve $1/MMBtu -> | E61: $4/MMBtu ->
A62: Natural gas | B62: 53.06 | C62: 18.846589 | D62: 18.846589 | E62: 75.386355
A63: Distillate fuel oil (No.2) | B63: 73.96 | C63: 13.520822 | D63: 13.520822 | E63: 54.083288
A64: Bituminous coal | B64: 93.28 | C64: 10.720412 | D64: 10.720412 | E64: 42.881647
A65: Coal coke | B65: 113.67 | C65: 8.797396 | D65: 8.797396 | E65: 35.189584
A66: Grid electricity (US avg) | B66: 109.4 | C66: 9.1407678 | D66: 9.1407678 | E66: 36.563071
A68: Gap-fill techs vs NG carbon price ($/tCO2): | B68: 28.472798 | C68: 23.727332 | D68: 29.508477 | E68: 115.07973 | F68: (recuperator / economizer / condensing HX / ORC-vs-grid)
A70: Published cost evidence behind the gap-fill assumptions
A71: Source | B71: Technology | C71: Published figure | D71: Implied $/kW | E71: Our assumption
A72: Case Studies in Thermal Engineering (Dec 2023, peer-reviewed) | B72: Fired-heater air preheater (gas-gas HX) | C72: $71,631 capex for 286 kW_th recovered; 0.77-yr payback | D72: $250/kW_th | E72: $300/kW_th (recuperator/APH, +20% conservative)
A73: U.S. DOE research range (WHR systems, all classes) | B73: Industrial WHR generally | C73: $500-$4,500 per kW of waste heat recovered | D73: brackets all four rows | E73: economizer $200 / condensing $250 sit at-to-below the floor: flag as weakest two
A74: EPRI report 1020134 (2010) | B74: Waste-heat-driven CHP (heat-to-power) | C74: $2,000-2,500/kW (>5 MW); $3,500-4,500/kW (<400 kW) | D74: $2,000-4,500/kWe | E74: $2,500/kWe (ORC, large-system end)
A75: ORC market survey (2024-25) | B75: Industrial ORC 1-10 MWe | C75: $1.8M-$3.2M per MWe installed | D75: $1,800-3,200/kWe | E75: $2,500/kWe (midpoint)
A76: U.S. DOE / BCS Inc. (2008), Waste Heat Recovery: Technology and Opportunities | B76: Recuperators, economizers (canonical study) | C76: Canonical DOE cost study underpinning the economizer and recuperator classes | D76: - | E76: backstops recuperator/economizer rows
A77: DOE AMO Steam Tip Sheets #3 / #26A / #26B | B77: Feedwater + condensing economizers | C77: payback < 2 years' at $8/MMBtu fuel; worked examples 4.6-7.55 MMBtu/hr recovered | D77: implied ~$200-550/kW_th | E77: economizer raised to $250; condensing to $300 (mid-range)
A78: Weakest links: economizer ($200) and condensing HX ($250) rest on the DOE range floor, not a specific study.
A80: Capital cost of equipment at full 2050 potential (2012$ millions) — for EPS investment accounting
A81: Industry | B81: whr measures $M | C81: gap-fill HX $M | D81: process measures $M | E81: TOTAL $M
A82: pulp paper and printing 17T18 | B82: 314.52017 | C82: 889.28203 | D82: 625.47585 | E82: 1829.2781
A83: chemicals 20 | B83: 117.45691 | C83: 2258.6598 | D83: 1223.2244 | E83: 3599.3412
A84: glass and glass products 231 | B84: 138.79176 | C84: 0 | D84: 204.9308 | E84: 343.72256
A85: cement and other nonmetallic minerals 239 | B85: 1702.7795 | C85: 228.46485 | D85: 1597.9592 | E85: 3529.2035
A86: iron and steel 241 | B86: 1389.6934 | C86: 491.92683 | D86: 793.66355 | E86: 2675.2838
A87: other metals 242 | B87: 0 | C87: 50.454557 | D87: 374.8039 | E87: 425.25846
A88: TOTAL (covered) | B88: 3663.2418 | C88: 3918.7881 | D88: 4820.0577 | E88: 12402.088
A89: Notes: gap-fill capex = residual energy x tech capex ($/kW / 28.8 GJ-yr per kW at 8,000 h). Per-measure capital intensity (2012$/MMBtu-yr) in economics col AM; per-bin capex matrices available on request. Elec-side measures' capex included in whr/process columns.
A91: Burner-integral penetration already credited in unit-efficiency files, by temperature band (deducted from all gap-fill / Bianchi-fill targets)
A92: Band | B92: < 100C | C92: 100-200C | D92: 200-500C | E92: 500-1000C | F92: > 1000C
A93: Credited penetration | B93: 0 | C93: 0 | D93: 0.05 | E93: 0.174 | F93: 0.587
A94: Available share (1 - credit) | B94: 1 | C94: 1 | D94: 0.95 | E94: 0.826 | F94: 0.413
A95: Band shares per industry from tab 'indst heat consumption' (cols D-H). Low+medium bands (<500C) are filled with the economizer/condensing class; high bands (>500C) with the recuperator/APH class.

Sheet Kermeli Data
A1: Calculations | W1: Exclusion note
A2: Data from Kermeli et al. (SM) | B2: https://link.springer.com/article/10.1007/s12053-022-10071-8#Sec10
A3: NPV =CF0 + CF1/(1+r)1 + CF2/(1+r)2 + … + CFn/(1+r)n
A4: r = hurdle rate = WACC + risk premium
A5: https://capitalgains.thediff.co/p/hurdle-rates
A7: Energy Savings & Cost of Measures from Kermeli et al.
A8: Product / Process | B8: Technology / Measure | C8: 2015 Diffusion | D8: 2030 Implementation | E8: 2050 Implementation | F8: Fuel Savings (GJ/t) | G8: Elec. Savings (GJ/t) | H8: H2 Savings (GJ/t) | I8: Investment (€/t) | J8: Technical lifetime (years) | K8: Annual O&M Costs (€/t) | L8: Temp band | M8: Burner-integral penetration | N8: EPS/heat-share industry | O8: Heat share | P8: Bucket | Q8: Bucket justification / tag | R8: Fuel save share | S8: Elec save share | T8: H2 save share | U8: 2015+2050 sum | V8: Diffusion flag
A9: Primary aluminum | B9: PFPBa | C9: 0.9 | D9: 0.1 | E9: 0.1 | F9: 0 | G9: 2.8 | H9: 0 | I9: 2340 | J9: 20 | K9: 0 | L9: >1000C | M9: 0.587 | N9: Other metals (242) | O9: 0.6089 | P9: 3 proc | Q9: Smelter electrical efficiency (point-feed prebake). Not recovery. | R9: 0 | S9: 1 | T9: 0 | U9: 1
A10: Primary aluminum | B10: Optimization electrolysis controlc | C10: 0.55 | D10: 0.35 | E10: 0.45 | F10: 0 | G10: 3.6 | H10: 0 | I10: 188 | J10: 5 | K10: -65 | L10: >1000C | M10: 0.587 | N10: Other metals (242) | O10: 0.6089 | P10: 3 proc | Q10: Electrolysis control optimization. Not recovery. | R10: 0 | S10: 1 | T10: 0 | U10: 1
A11: Primary aluminum | B11: Optimization cell designc | C11: 0.55 | D11: 0.35 | E11: 0.45 | F11: 0 | G11: 2.5 | H11: 0 | I11: 236 | J11: 6 | K11: 0 | L11: >1000C | M11: 0.587 | N11: Other metals (242) | O11: 0.6089 | P11: 3 proc | Q11: Cell design optimization. Not recovery. | R11: 0 | S11: 1 | T11: 0 | U11: 1
A12: Secondary aluminum | B12: Regenerative or recuperative burnerd | C12: 0.3 | D12: 0.25 | E12: 0.5 | F12: 2 | G12: 0 | H12: 0 | I12: 14 | J12: 20 | K12: 0.4 | L12: 500-1000C | M12: 0.174 | N12: Other metals (242) | O12: 0.6089 | P12: 1 unit | Q12: unit WHR — handled in unit-efficiency files (recup/regen burner; do-not-double-count). | R12: 1 | S12: 0 | T12: 0 | U12: 0.8
A13: Secondary aluminum | B13: New decoating equipmentd | C13: 0 | D13: 0.15 | E13: 0.6 | F13: 0.4 | G13: 0 | H13: 0 | I13: 40 | J13: 10 | K13: 40 | L13: 500-1000C | M13: 0.174 | N13: Other metals (242) | O13: 0.6089 | P13: X equip-replace | Q13: Decoating/delacquering process improvement. | R13: 1 | S13: 0 | T13: 0 | U13: 0.6 | W13: Excluded 2026-07-28: discrete furnace replacement - VFM 'in place of a gas reverberatory furnace' (DOE Aluminum Report 2016). Carried by stock turnover / standards channel.
A14: Aluminum foundries | B14: Improved process schedulinge | C14: 0.6 | D14: 0.39 | E14: 0.4 | F14: 1.8 | G14: 0 | H14: 0 | I14: 25 | J14: 20 | K14: 0 | L14: 500-1000C | M14: 0.174 | N14: Other metals (242) | O14: 0.6089 | P14: 3 proc | Q14: Process scheduling. Not recovery. | R14: 1 | S14: 0 | T14: 0 | U14: 1
A15: Aluminum foundries | B15: Regenerative or recuperative burnere | C15: 0.5 | D15: 0.05 | E15: 0.3 | F15: 4.8 | G15: 0 | H15: 0 | I15: 10 | J15: 20 | K15: 0.7 | L15: 500-1000C | M15: 0.174 | N15: Other metals (242) | O15: 0.6089 | P15: 1 unit | Q15: unit WHR — handled in unit-efficiency files (recup/regen burner; do-not-double-count). | R15: 1 | S15: 0 | T15: 0 | U15: 0.8
A16: Aluminum foundries | B16: Liquid metal as feedstocke | C16: 0.05 | D16: 0.2 | E16: 0.45 | F16: 8.7 | G16: 0 | H16: 0 | I16: 25 | J16: 20 | K16: 0 | L16: 500-1000C | M16: 0.174 | N16: Other metals (242) | O16: 0.6089 | P16: 3 proc | Q16: Liquid-metal feedstock avoids remelt. Process/material. | R16: 1 | S16: 0 | T16: 0 | U16: 0.5
A17: Coke oven | B17: Programmed heatinga | C17: 0.3 | D17: 0.5 | E17: 0.7 | F17: 0.2 | G17: 0 | H17: 0 | I17: 0.2 | J17: 10 | K17: 0 | L17: >1000C | M17: 0.587 | N17: Iron & steel (241) | O17: 0.6516 | P17: 3 proc | Q17: Programmed heating (control). Not recovery. | R17: 1 | S17: 0 | T17: 0 | U17: 1
A18: Coke oven | B18: Variable speed drive on compressorsa | C18: 0.3 | D18: 0.5 | E18: 0.7 | F18: ='src review'!H97 | G18: ='src review'!I97 | H18: 0 | I18: 0.3 | J18: 15 | K18: 0 | L18: >1000C | M18: 0.587 | N18: Iron & steel (241) | O18: 0.6516 | P18: 3 proc | Q18: VSD on compressors (motor efficiency). | R18: 0 | S18: 0 | T18: 0 | U18: 1
A19: Coke oven | B19: Coal moisture controla | C19: 0.3 | D19: 0.5 | E19: 0.7 | F19: 0.3 | G19: 0 | H19: 0 | I19: 6.5 | J19: 10 | K19: 0 | L19: >1000C | M19: 0.587 | N19: Iron & steel (241) | O19: 0.6516 | P19: 3 proc | Q19: Coal moisture control (charge prep). | R19: 1 | S19: 0 | T19: 0 | U19: 1
A20: Pig iron | B20: Waste heat recovery blast furnace slagb | C20: 0 | D20: 0.43 | E20: 0.8 | F20: 0.4 | G20: 0 | H20: 0 | I20: 54.5 | J20: 20 | K20: 0 | L20: >1000C | M20: 0.587 | N20: Iron & steel (241) | O20: 0.6516 | P20: 2 whr | Q20: System WHR: blast-furnace slag sensible-heat recovery. Not on do-not-double-count list. | R20: 1 | S20: 0 | T20: 0 | U20: 0.8
A21: Pig iron | B21: Top gas recovery turbineb | C21: 0.7 | D21: 0.21 | E21: 0.29 | F21: 0 | G21: 0.1 | H21: 0 | I21: 3.3 | J21: 15 | K21: 0.5 | L21: >1000C | M21: 0.587 | N21: Iron & steel (241) | O21: 0.6516 | P21: 2 whr | Q21: System WHR: top-gas recovery turbine (pressure/sensible heat). G0.1 ruling; no overlap with hot-blast-stove credit. | R21: 0 | S21: 1 | T21: 0 | U21: 0.99
A22: Pig iron | B22: Moisture Removing Blowing Technique in Blast Furnacec | C22: 0.05 | D22: 0.65 | E22: 0.75 | F22: 0.2 | G22: 0 | H22: 0 | I22: 2 | J22: 15 | K22: 0 | L22: >1000C | M22: 0.587 | N22: Iron & steel (241) | O22: 0.6516 | P22: 3 proc | Q22: Blast dehumidification (process). | R22: 1 | S22: 0 | T22: 0 | U22: 0.8
A23: Pig iron | B23: Injection of pulverized coal in BFc | C23: 0.05 | D23: 0.45 | E23: 0.95 | F23: 0.6 | G23: 0 | H23: 0 | I23: 5.4 | J23: 20 | K23: 1.6 | L23: >1000C | M23: 0.587 | N23: Iron & steel (241) | O23: 0.6516 | P23: 3 proc | Q23: Pulverized-coal injection (reductant substitution). | R23: 1 | S23: 0 | T23: 0 | U23: 1
A24: Pig iron | B24: Cogeneration (for the use of untapped coke oven gas, blast furnace gas, and basic oxygen furnace-gas in integrated steel mills)c | C24: 0.05 | D24: 0.2 | E24: 0.5 | F24: 0.2 | G24: 0 | H24: 0 | I24: 2.8 | J24: 20 | K24: 0 | L24: >1000C | M24: 0.587 | N24: Iron & steel (241) | O24: 0.6516 | P24: X CHP | Q24: CHP/cogen — excluded per G0.1 ruling. | R24: 1 | S24: 0 | T24: 0 | U24: 0.55
A25: Pig iron | B25: Recovery of blast furnace gas | C25: 0.05 | D25: 0.03 | E25: 0.05 | F25: 0.1 | G25: 0 | H25: 0 | I25: 1.3 | J25: 15 | K25: 0 | L25: >1000C | M25: 0.587 | N25: Iron & steel (241) | O25: 0.6516 | P25: 3 proc | Q25: Off-gas recovery (BF gas capture). Bucket 3 per G0.1 ruling: gas/feedstock recovery, not waste heat. | R25: 1 | S25: 0 | T25: 0 | U25: 0.1
A26: Pig iron | B26: Improved hot blast stove controlc | C26: 0.25 | D26: 0.3 | E26: 0.45 | F26: 0.3 | G26: 0 | H26: 0 | I26: 0.3 | J26: 5 | K26: 0 | L26: >1000C | M26: 0.587 | N26: Iron & steel (241) | O26: 0.6516 | P26: 3 proc | Q26: Hot-blast-stove CONTROL efficiency (not recovery; stove recovery itself is do-not-double-count). | R26: 1 | S26: 0 | T26: 0 | U26: 0.7
A27: Pig iron | B27: Improved blast furnace controlc | C27: 0.5 | D27: 0.25 | E27: 0.5 | F27: 0.3 | G27: 0 | H27: 0 | I27: 0.6 | J27: 5 | K27: 0 | L27: >1000C | M27: 0.587 | N27: Iron & steel (241) | O27: 0.6516 | P27: 3 proc | Q27: Blast furnace control. Not recovery. | R27: 1 | S27: 0 | T27: 0 | U27: 1
A28: BF/BOF steel | B28: Recovery of BOF and sensible heatc | C28: 0.7 | D28: 0.1 | E28: 0.2 | F28: 0.6 | G28: 0 | H28: 0 | I28: 25.6 | J28: 10 | K28: 0 | L28: >1000C | M28: 0.587 | N28: Iron & steel (241) | O28: 0.6516 | P28: 2 whr | Q28: System WHR: BOF gas + sensible heat recovery. | R28: 1 | S28: 0 | T28: 0 | U28: 0.9
A29: BF/BOF steel | B29: Scrap preheatingc | C29: 0.3 | D29: 0.25 | E29: 0.7 | F29: 0.2 | G29: 0.4 | H29: 0 | I29: 17.4 | J29: 30 | K29: 0 | L29: >1000C | M29: 0.587 | N29: Iron & steel (241) | O29: 0.6516 | P29: 2 whr | Q29: System WHR: scrap preheating. G0.1 ruling (EAF floor at no-preheat value; no double count). | R29: 0.33333333 | S29: 0.66666667 | T29: 0 | U29: 1
A30: BF/BOF steel | B30: Variable speed drives for flue gas control, pumps, fans in integrated steel millsc | C30: 0.85 | D30: 0.15 | E30: 0.15 | F30: 0 | G30: 0.03 | H30: 0 | I30: 1.5 | J30: 10 | K30: 0 | L30: >1000C | M30: 0.587 | N30: Iron & steel (241) | O30: 0.6516 | P30: 3 proc | Q30: VSD flue-gas/pumps/fans (motor efficiency). | R30: 0 | S30: 1 | T30: 0 | U30: 1
... A34: Rolled steel | B34: Recuperative or regenerative burnerc | C34: 0.4 | D34: 0.5 | E34: 0.6 | F34: 0.6 | G34: 0 | H34: 0 | I34: 2.9 | J34: 10 | K34: 0 | L34: 500-1000C | M34: 0.174 | N34: Iron & steel (241) | O34: 0.6516 | P34: 1 unit | Q34: unit WHR — handled in unit-efficiency files (recup/regen burner; do-not-double-count). | R34: 1 | S34: 0 | T34: 0 | U34: 1
A35: Rolled steel | B35: Endless Hot Rolling of Steel Sheetsc | C35: 0.01 | D35: 0.14 | E35: 0.19 | F35: 0.4 | G35: 0 | H35: 0 | I35: 7.3 | J35: 20 | K35: 0 | L35: 500-1000C | M35: 0.174 | N35: Iron & steel (241) | O35: 0.6516 | P35: X equip-replace | Q35: Endless hot rolling (process). | R35: 1 | S35: 0 | T35: 0 | U35: 0.2 | W35: Excluded 2026-07-28: new-build casting-rolling line - 'construction of an ESP plant' (Worrell et al. 2010, LBNL-4779E). Enters via new equipment stock, not retrofit.
A36: Rolled steel | B36: Process control in hot rollingc | C36: 0.3 | D36: 0.5 | E36: 0.7 | F36: 0.3 | G36: 0 | H36: 0 | I36: 0.8 | J36: 10 | K36: 0 | L36: 500-1000C | M36: 0.174 | N36: Iron & steel (241) | O36: 0.6516 | P36: 3 proc | Q36: Hot-rolling process control. | R36: 1 | S36: 0 | T36: 0 | U36: 1
A37: Container glass | B37: Batch/cullet preheatinga | C37: 0.4 | D37: 0.2 | E37: 0.38 | F37: 0.7 | G37: 0 | H37: 0 | I37: 20 | J37: 20 | K37: 0 | L37: >1000C | M37: 0.587 | N37: Glass (231) | O37: 0.7514 | P37: 2 whr | Q37: System WHR: flue-gas heat to preheat batch/cullet (bolt-on downstream of regenerator; not double-counted). | R37: 1 | S37: 0 | T37: 0 | U37: 0.78
A38: Container glass | B38: Increase of culletsb | C38: 0.55 | D38: 0.27 | E38: 0.3 | F38: 1.2 | G38: 0 | H38: 0 | I38: 28 | J38: 20 | K38: 0.8 | L38: >1000C | M38: 0.587 | N38: Glass (231) | O38: 0.7514 | P38: 3 proc | Q38: Increased cullet (raw-material substitution). | R38: 1 | S38: 0 | T38: 0 | U38: 0.85
A39: Container glass | B39: Low NOx burnersa | C39: 0.25 | D39: 0.21 | E39: 0.37 | F39: 0.3 | G39: 0 | H39: 0 | I39: 3 | J39: 20 | K39: 0 | L39: >1000C | M39: 0.587 | N39: Glass (231) | O39: 0.7514 | P39: 1 unit | Q39: unit WHR — handled in unit-efficiency files (low-NOx burner). G0.1 ruling. | R39: 1 | S39: 0 | T39: 0 | U39: 0.62
A40: Container glass | B40: Optimized burningc | C40: 0.3 | D40: 0.39 | E40: 0.65 | F40: 0.5 | G40: 0 | H40: 0 | I40: 10 | J40: 20 | K40: 0 | L40: >1000C | M40: 0.587 | N40: Glass (231) | O40: 0.7514 | P40: 3 proc | Q40: Optimized burning (process efficiency). G0.1 ruling. | R40: 1 | S40: 0 | T40: 0 | U40: 0.95
A41: Container glass | B41: Process Control-Software and Image based controla | C41: 0.5 | D41: 0.3 | E41: 0.5 | F41: 0.2 | G41: 0 | H41: 0 | I41: 3 | J41: 10 | K41: 0 | L41: >1000C | M41: 0.587 | N41: Glass (231) | O41: 0.7514 | P41: 3 proc | Q41: Process control / image-based control. | R41: 1 | S41: 0 | T41: 0 | U41: 1
A42: Flat glass | B42: Waste heat recoveryd | C42: 0.7 | D42: 0.05 | E42: 0.25 | F42: 0 | G42: 0.3 | H42: 0 | I42: 10 | J42: 20 | K42: 0 | L42: >1000C | M42: 0.587 | N42: Glass (231) | O42: 0.7514 | P42: 2 whr | Q42: System WHR: flat-glass waste heat recovery (offsets electricity). | R42: 0 | S42: 1 | T42: 0 | U42: 0.95
A43: Flat glass | B43: Batch/cullet preheatinge | C43: 0 | D43: 0.2 | E43: 0.5 | F43: 1.1 | G43: 0 | H43: 0 | I43: 20 | J43: 20 | K43: 0 | L43: >1000C | M43: 0.587 | N43: Glass (231) | O43: 0.7514 | P43: 2 whr | Q43: System WHR: flue-gas heat to preheat batch/cullet. | R43: 1 | S43: 0 | T43: 0 | U43: 0.5
A44: Flat glass | B44: Low NOx burnersa | C44: 0.25 | D44: 0.21 | E44: 0.37 | F44: 0.4 | G44: 0 | H44: 0 | I44: 3 | J44: 20 | K44: 0 | L44: >1000C | M44: 0.587 | N44: Glass (231) | O44: 0.7514 | P44: 1 unit | Q44: unit WHR — handled in unit-efficiency files (low-NOx burner). G0.1 ruling. | R44: 1 | S44: 0 | T44: 0 | U44: 0.62
A45: Flat glass | B45: Optimized burningc | C45: 0.3 | D45: 0.41 | E45: 0.66 | F45: 1 | G45: 0 | H45: 0 | I45: 10 | J45: 20 | K45: 0 | L45: >1000C | M45: 0.587 | N45: Glass (231) | O45: 0.7514 | P45: 3 proc | Q45: Optimized burning (process efficiency). G0.1 ruling. | R45: 1 | S45: 0 | T45: 0 | U45: 0.96
A46: Flat glass | B46: Process Control-Software and Image based controla | C46: 0.5 | D46: 0.3 | E46: 0.5 | F46: 0.4 | G46: 0 | H46: 0 | I46: 3 | J46: 10 | K46: 0 | L46: >1000C | M46: 0.587 | N46: Glass (231) | O46: 0.7514 | P46: 3 proc | Q46: Process control / image-based control. | R46: 1 | S46: 0 | T46: 0 | U46: 1
A47: Mechanical pulp | B47: Heat recovery (TMP, GW)a | C47: 0.95 | D47: 0.05 | E47: 0.05 | F47: 3.5 | G47: 0 | H47: 0 | I47: 41 | J47: 20 | K47: 0 | L47: 100-200C | M47: 0 | N47: Pulp & paper (17T18) | O47: 0.8551 | P47: 2 whr | Q47: System WHR: heat recovery from TMP/GW refiners. | R47: 1 | S47: 0 | T47: 0 | U47: 1
A48: Mechanical pulp | B48: Efficient refiner and pretreatment (TMP)a | C48: 0.15 | D48: 0.13 | E48: 0.65 | F48: 0 | G48: 1.6 | H48: 0 | I48: 122 | J48: 20 | K48: 0 | L48: 100-200C | M48: 0 | N48: Pulp & paper (17T18) | O48: 0.8551 | P48: 3 proc | Q48: Efficient refiner & pretreatment. | R48: 0 | S48: 1 | T48: 0 | U48: 0.8
A49: Recovered fibre pulp | B49: High consistency pulpingb | C49: 0.6 | D49: 0.25 | E49: 0.4 | F49: ='src review'!L65 | G49: ='src review'!M65 | H49: 0 | I49: 3 | J49: 20 | K49: 0 | L49: 100-200C | M49: 0 | N49: Pulp & paper (17T18) | O49: 0.8551 | P49: 3 proc | Q49: High-consistency pulping (process). | R49: 0 | S49: 0 | T49: 0 | U49: 1
A50: Recovered fibre pulp | B50: Efficient screeningb | C50: 0.7 | D50: 0.08 | E50: 0.3 | F50: 0 | G50: 0.1 | H50: 0 | I50: 6 | J50: 20 | K50: 0 | L50: 100-200C | M50: 0 | N50: Pulp & paper (17T18) | O50: 0.8551 | P50: 3 proc | Q50: Efficient screening (motor/process). | R50: 0 | S50: 1 | T50: 0 | U50: 1
A51: Recovered fibre pulp | B51: Heat recovery from bleachingb | C51: 0.7 | D51: 0.08 | E51: 0.3 | F51: ='src review'!L66 | G51: ='src review'!M66 | H51: 0 | I51: 2 | J51: 20 | K51: 0 | L51: 100-200C | M51: 0 | N51: Pulp & paper (17T18) | O51: 0.8551 | P51: 2 whr | Q51: System WHR: heat recovery from bleaching. | R51: 0 | S51: 0 | T51: 0 | U51: 1
A52: Recovered fibre pulp | B52: Efficient disperserb | C52: 0.7 | D52: 0.22 | E52: 0.3 | F52: ='src review'!L67 | G52: ='src review'!M67 | H52: 0 | I52: 1 | J52: 15 | K52: 0 | L52: 100-200C | M52: 0 | N52: Pulp & paper (17T18) | O52: 0.8551 | P52: 3 proc | Q52: Efficient disperser (process). | R52: 0 | S52: 0 | T52: 0 | U52: 1
A53: Tissue paper | B53: Efficient refinersa | C53: 0.1 | D53: 0.18 | E53: 0.23 | F53: 0 | G53: 0.1 | H53: 0 | I53: 16 | J53: 20 | K53: 0 | L53: 100-200C | M53: 0 | N53: Pulp & paper (17T18) | O53: 0.8551 | P53: X equip-replace | Q53: Efficient refiners (process). | R53: 0 | S53: 1 | T53: 0 | U53: 0.33 | W53: Excluded 2026-07-28: 'technology replacement option' requiring substantial process change (Rutten et al. 2017, HRE background report). Like-for-like refiner replacement carried by stock turnover / standards channel.
A54: Tissue paper | B54: Optimization of refininga | C54: 0.4 | D54: 0.5 | E54: 0.6 | F54: 0 | G54: 0.1 | H54: 0 | I54: 1 | J54: 20 | K54: 0 | L54: 100-200C | M54: 0 | N54: Pulp & paper (17T18) | O54: 0.8551 | P54: 3 proc | Q54: Optimization of refining. | R54: 0 | S54: 1 | T54: 0 | U54: 1
A55: Tissue paper | B55: Steamboxa | C55: 0.75 | D55: 0.02 | E55: 0.05 | F55: 0.2 | G55: 0 | H55: 0 | I55: 5 | J55: 15 | K55: 0 | L55: 100-200C | M55: 0 | N55: Pulp & paper (17T18) | O55: 0.8551 | P55: 3 proc | Q55: Steambox (dewatering/drying aid). | R55: 1 | S55: 0 | T55: 0 | U55: 0.8
A56: Tissue paper | B56: Shoepressa | C56: 0.7 | D56: 0.06 | E56: 0.1 | F56: 0.5 | G56: 0 | H56: 0 | I56: 32 | J56: 20 | K56: 0 | L56: 100-200C | M56: 0 | N56: Pulp & paper (17T18) | O56: 0.8551 | P56: X equip-replace | Q56: Shoepress (mechanical dewatering). | R56: 1 | S56: 0 | T56: 0 | U56: 0.8 | W56: Excluded 2026-07-28: equipment replacement - 'a large concave shoe instead of one of the rotating cylinders' (LBNL-2268E). Carried by stock turnover / standards channel.
A57: Tissue paper | B57: Heat recovery and integrationa | C57: 0.65 | D57: 0.18 | E57: 0.32 | F57: 0 | G57: 1.1 | H57: 0 | I57: 16 | J57: 20 | K57: 0 | L57: 100-200C | M57: 0 | N57: Pulp & paper (17T18) | O57: 0.8551 | P57: 2 whr | Q57: System WHR: heat recovery and process integration. | R57: 0 | S57: 1 | T57: 0 | U57: 0.97
A58: Graphic paper | B58: Efficient refinersa | C58: 0.1 | D58: 0.18 | E58: 0.23 | F58: 0 | G58: 0.1 | H58: 0 | I58: 16 | J58: 20 | K58: 0 | L58: 100-200C | M58: 0 | N58: Pulp & paper (17T18) | O58: 0.8551 | P58: X equip-replace | Q58: Efficient refiners (process). | R58: 0 | S58: 1 | T58: 0 | U58: 0.33 | W58: Excluded 2026-07-28: 'technology replacement option' requiring substantial process change (Rutten et al. 2017, HRE background report). Like-for-like refiner replacement carried by stock turnover / standards channel.
A59: Graphic paper | B59: Optimization of refining | C59: 0.4 | D59: 0.5 | E59: 0.6 | F59: 0 | G59: 0.1 | H59: 0 | I59: 1 | J59: 20 | K59: 0 | L59: 100-200C | M59: 0 | N59: Pulp & paper (17T18) | O59: 0.8551 | P59: 3 proc | Q59: Optimization of refining. | R59: 0 | S59: 1 | T59: 0 | U59: 1
A60: Graphic paper | B60: Steamboxa | C60: 0.75 | D60: 0.02 | E60: 0.05 | F60: 0.2 | G60: 0 | H60: 0 | I60: 5 | J60: 15 | K60: 0 | L60: 100-200C | M60: 0 | N60: Pulp & paper (17T18) | O60: 0.8551 | P60: 3 proc | Q60: Steambox (dewatering/drying aid). | R60: 1 | S60: 0 | T60: 0 | U60: 0.8
A61: Graphic paper | B61: Shoepressa | C61: 0.7 | D61: 0.06 | E61: 0.1 | F61: 0.5 | G61: 0 | H61: 0 | I61: 32 | J61: 20 | K61: 0 | L61: 100-200C | M61: 0 | N61: Pulp & paper (17T18) | O61: 0.8551 | P61: X equip-replace | Q61: Shoepress (mechanical dewatering). | R61: 1 | S61: 0 | T61: 0 | U61: 0.8 | W61: Excluded 2026-07-28: equipment replacement - 'a large concave shoe instead of one of the rotating cylinders' (LBNL-2268E). Carried by stock turnover / standards channel.
A62: Graphic paper | B62: Heat recovery and integrationa | C62: 0.65 | D62: 0.18 | E62: 0.32 | F62: 0 | G62: 1.1 | H62: 0 | I62: 16 | J62: 20 | K62: 0 | L62: 100-200C | M62: 0 | N62: Pulp & paper (17T18) | O62: 0.8551 | P62: 2 whr | Q62: System WHR: heat recovery and process integration. | R62: 0 | S62: 1 | T62: 0 | U62: 0.97
A63: Board and packaging paper | B63: Efficient refinersa | C63: 0.1 | D63: 0.18 | E63: 0.23 | F63: 0 | G63: 0.1 | H63: 0 | I63: 16 | J63: 20 | K63: 0 | L63: 100-200C | M63: 0 | N63: Pulp & paper (17T18) | O63: 0.8551 | P63: X equip-replace | Q63: Efficient refiners (process). | R63: 0 | S63: 1 | T63: 0 | U63: 0.33 | W63: Excluded 2026-07-28: 'technology replacement option' requiring substantial process change (Rutten et al. 2017, HRE background report). Like-for-like refiner replacement carried by stock turnover / standards channel.
A64: Board and packaging paper | B64: Optimization of refininga | C64: 0.4 | D64: 0.5 | E64: 0.6 | F64: 0 | G64: 0.1 | H64: 0 | I64: 1 | J64: 20 | K64: 0 | L64: 100-200C | M64: 0 | N64: Pulp & paper (17T18) | O64: 0.8551 | P64: 3 proc | Q64: Optimization of refining. | R64: 0 | S64: 1 | T64: 0 | U64: 1
A65: Board and packaging paper | B65: Steamboxa | C65: 0.75 | D65: 0.02 | E65: 0.05 | F65: 0.2 | G65: 0 | H65: 0 | I65: 5 | J65: 15 | K65: 0 | L65: 100-200C | M65: 0 | N65: Pulp & paper (17T18) | O65: 0.8551 | P65: 3 proc | Q65: Steambox (dewatering/drying aid). | R65: 1 | S65: 0 | T65: 0 | U65: 0.8
A66: Board and packaging paper | B66: Shoepressa | C66: 0.7 | D66: 0.06 | E66: 0.1 | F66: 0.5 | G66: 0 | H66: 0 | I66: 32 | J66: 20 | K66: 0 | L66: 100-200C | M66: 0 | N66: Pulp & paper (17T18) | O66: 0.8551 | P66: X equip-replace | Q66: Shoepress (mechanical dewatering). | R66: 1 | S66: 0 | T66: 0 | U66: 0.8 | W66: Excluded 2026-07-28: equipment replacement - 'a large concave shoe instead of one of the rotating cylinders' (LBNL-2268E). Carried by stock turnover / standards channel.
A67: Board and packaging paper | B67: Heat recovery and integrationa | C67: 0.65 | D67: 0.18 | E67: 0.32 | F67: 0 | G67: 1.1 | H67: 0 | I67: 16 | J67: 20 | K67: 0 | L67: 100-200C | M67: 0 | N67: Pulp & paper (17T18) | O67: 0.8551 | P67: 2 whr | Q67: System WHR: heat recovery and process integration. | R67: 0 | S67: 1 | T67: 0 | U67: 0.97
A68: Ethylene | B68: Advanced furnace materialsa | C68: 0.2 | D68: 0.3 | E68: 0.55 | F68: 1.7 | G68: 0 | H68: 0 | I68: 2 | J68: 20 | K68: 0 | L68: 500-1000C | M68: 0.174 | N68: Chemicals (20) | O68: 0.7161 | P68: 3 proc | Q68: Advanced furnace materials (loss reduction). | R68: 1 | S68: 0 | T68: 0 | U68: 0.75
A69: Ethylene | B69: Improving compression and separation sectionb | C69: 0.2 | D69: 0.18 | E69: 0.28 | F69: 1 | G69: 0 | H69: 0 | I69: 1 | J69: 20 | K69: 0 | L69: 500-1000C | M69: 0.174 | N69: Chemicals (20) | O69: 0.7161 | P69: 3 proc | Q69: Compression & separation section improvement. | R69: 1 | S69: 0 | T69: 0 | U69: 0.48
A70: Ethylene | B70: Integration of a gas turbinec | C70: 0.05 | D70: 0.12 | E70: 0.15 | F70: 2.6 | G70: 0 | H70: 0 | I70: 58 | J70: 20 | K70: 0 | L70: 500-1000C | M70: 0.174 | N70: Chemicals (20) | O70: 0.7161 | P70: X CHP | Q70: CHP/cogen — excluded per G0.1 ruling. Gas-turbine cogen; elec booked 0. | R70: 1 | S70: 0 | T70: 0 | U70: 0.2
A71: Ethylene | B71: Improved compressorsd | C71: 0.85 | D71: 0.08 | E71: 0.1 | F71: 0.8 | G71: 0 | H71: 0 | I71: 22 | J71: 20 | K71: 0 | L71: 500-1000C | M71: 0.174 | N71: Chemicals (20) | O71: 0.7161 | P71: 3 proc | Q71: Improved compressors (process). | R71: 1 | S71: 0 | T71: 0 | U71: 0.95
A72: Ethylene | B72: Utilization of flare gase | C72: 0.85 | D72: 0.09 | E72: 0.1 | F72: 2 | G72: 0 | H72: 0 | I72: 60 | J72: 20 | K72: 0 | L72: 500-1000C | M72: 0.174 | N72: Chemicals (20) | O72: 0.7161 | P72: 3 proc | Q72: Flare-gas utilization. Bucket 3 per G0.1 ruling: gas recovery, not waste heat. | R72: 1 | S72: 0 | T72: 0 | U72: 0.95
A73: Ethylene | B73: Modern control systeme | C73: 0.85 | D73: 0.09 | E73: 0.1 | F73: 1.5 | G73: 0 | H73: 0 | I73: 29 | J73: 20 | K73: 0 | L73: 500-1000C | M73: 0.174 | N73: Chemicals (20) | O73: 0.7161 | P73: 3 proc | Q73: Modern control system. | R73: 1 | S73: 0 | T73: 0 | U73: 0.95
A74: Soda ash | B74: Integrated design and operationf | C74: 0.5 | D74: 0.25 | E74: 0.4 | F74: 2 | G74: 0.1 | H74: 0 | I74: 40 | J74: 20 | K74: 0 | L74: 200-500C | M74: 0.05 | N74: Chemicals (20) | O74: 0.7161 | P74: 3 proc | Q74: Integrated design & operation (distinct from Heat integration row). | R74: 0.95238095 | S74: 0.047619048 | T74: 0 | U74: 0.9
A75: Soda ash | B75: Vertical shaft kiln for concentrated CO2 gas and reactive limef | C75: 0.7 | D75: 0.2 | E75: 0.3 | F75: 0.3 | G75: 0 | H75: 0 | I75: 16 | J75: 20 | K75: 0 | L75: 200-500C | M75: 0.05 | N75: Chemicals (20) | O75: 0.7161 | P75: X equip-replace | Q75: Vertical shaft kiln (process technology). | R75: 1 | S75: 0 | T75: 0 | U75: 1 | W75: Excluded 2026-07-28: kiln technology choice - 'the choice of vertical shaft kiln, instead of the other types available' (Boulamanti & Moya 2017, JRC EUR 28471). Equipment replacement channel.
A76: Soda ash | B76: Heat integratione | C76: 0.65 | D76: 0.15 | E76: 0.19 | F76: 1 | G76: 0 | H76: 0 | I76: 20 | J76: 20 | K76: 0 | L76: 200-500C | M76: 0.05 | N76: Chemicals (20) | O76: 0.7161 | P76: 2 whr | Q76: System WHR: process heat integration. | R76: 1 | S76: 0 | T76: 0 | U76: 0.84
A77: Soda ash | B77: Modern control systeme | C77: 0.65 | D77: 0.16 | E77: 0.19 | F77: 0.4 | G77: 0 | H77: 0 | I77: 10 | J77: 20 | K77: 0 | L77: 200-500C | M77: 0.05 | N77: Chemicals (20) | O77: 0.7161 | P77: 3 proc | Q77: Modern control system. | R77: 1 | S77: 0 | T77: 0 | U77: 0.84
A78: Soda ash | B78: Usage of CHPe | C78: 0.7 | D78: 0.27 | E78: 0.3 | F78: 1.8 | G78: 0 | H78: 0 | I78: 36 | J78: 30 | K78: 0 | L78: 200-500C | M78: 0.05 | N78: Chemicals (20) | O78: 0.7161 | P78: X CHP | Q78: CHP/cogen — excluded per G0.1 ruling. | R78: 1 | S78: 0 | T78: 0 | U78: 1
A79: Soda ash | B79: Efficiency packagee | C79: 0.55 | D79: 0.23 | E79: 0.29 | F79: 1 | G79: 0 | H79: 0 | I79: 22 | J79: 20 | K79: 0 | L79: 200-500C | M79: 0.05 | N79: Chemicals (20) | O79: 0.7161 | P79: 3 proc | Q79: Efficiency package (process). | R79: 1 | S79: 0 | T79: 0 | U79: 0.84
A80: Soda ash | B80: Usage of purer feede | C80: 0.55 | D80: 0.27 | E80: 0.3 | F80: 0.3 | G80: 0 | H80: 0 | I80: 1 | J80: 10 | K80: 0 | L80: 200-500C | M80: 0.05 | N80: Chemicals (20) | O80: 0.7161 | P80: 3 proc | Q80: Purer feed (process/material). | R80: 1 | S80: 0 | T80: 0 | U80: 0.85
A81: Carbon black | B81: Usage of CHPe | C81: 0.9 | D81: 0.1 | E81: 0.1 | F81: 6.5 | G81: 0 | H81: 0 | I81: 130 | J81: 20 | K81: 0 | L81: >1000C | M81: 0.587 | N81: Chemicals (20) | O81: 0.7161 | P81: X CHP | Q81: CHP/cogen — excluded per G0.1 ruling. | R81: 1 | S81: 0 | T81: 0 | U81: 1
A82: Carbon black | B82: Modern control systeme | C82: 0.8 | D82: 0.08 | E82: 0.14 | F82: 6.5 | G82: 0.2 | H82: 0 | I82: 139 | J82: 10 | K82: 0 | L82: >1000C | M82: 0.587 | N82: Chemicals (20) | O82: 0.7161 | P82: 3 proc | Q82: Modern control system. | R82: 0.97014925 | S82: 0.029850746 | T82: 0 | U82: 0.94
A83: Carbon black | B83: Optimization of black carbon separatione | C83: 0.7 | D83: 0.14 | E83: 0.23 | F83: 6.5 | G83: 0.3 | H83: 0 | I83: 142 | J83: 20 | K83: 0 | L83: >1000C | M83: 0.587 | N83: Chemicals (20) | O83: 0.7161 | P83: 3 proc | Q83: Optimization of carbon-black separation. | R83: 0.95588235 | S83: 0.044117647 | T83: 0 | U83: 0.93
A84: Methanol | B84: Efficiency package, synthesis gas sectione | C84: 0.5 | D84: 0.21 | E84: 0.3 | F84: 1.8 | G84: 0.1 | H84: 0 | I84: 39 | J84: 20 | K84: 0 | L84: 500-1000C | M84: 0.174 | N84: Chemicals (20) | O84: 0.7161 | P84: 3 proc | Q84: Efficiency package, syngas section. | R84: 0.94736842 | S84: 0.052631579 | T84: 0 | U84: 0.8
A85: Methanol | B85: Efficiency package, methanol synthesis sectione | C85: 0.5 | D85: 0.27 | E85: 0.37 | F85: 1.1 | G85: 0 | H85: 0 | I85: 24 | J85: 20 | K85: 0 | L85: 500-1000C | M85: 0.174 | N85: Chemicals (20) | O85: 0.7161 | P85: 3 proc | Q85: Efficiency package, methanol synthesis section. | R85: 1 | S85: 0 | T85: 0 | U85: 0.87
A86: Ammonia | B86: Improved CO2 removal sectionf | C86: 0.55 | D86: 0.2 | E86: 0.31 | F86: 1 | G86: 0 | H86: 0 | I86: 15 | J86: 20 | K86: 0 | L86: 500-1000C | M86: 0.174 | N86: Chemicals (20) | O86: 0.7161 | P86: 3 proc | Q86: Improved CO2 removal (process). | R86: 1 | S86: 0 | T86: 0 | U86: 0.86
A87: Ammonia | B87: Indirect cooling of the ammonia synthesis reactorf | C87: 0.55 | D87: 0.2 | E87: 0.31 | F87: 0.6 | G87: 0 | H87: 0 | I87: 7 | J87: 20 | K87: 0 | L87: 500-1000C | M87: 0.174 | N87: Chemicals (20) | O87: 0.7161 | P87: 2 whr | Q87: System WHR: recovers exothermic synthesis-reactor heat (indirect cooling). | R87: 1 | S87: 0 | T87: 0 | U87: 0.86
... A91: Ammonia | B91: Advanced process control | C91: 0.3 | D91: 0.3 | E91: 0.55 | F91: 0.7 | G91: 0 | H91: 0 | I91: 6 | J91: 10 | K91: 0 | L91: 500-1000C | M91: 0.174 | N91: Chemicals (20) | O91: 0.7161 | P91: 3 proc | Q91: Advanced process control. | R91: 1 | S91: 0 | T91: 0 | U91: 0.85
A92: Clinker | B92: Improved raw Mill Blendinga | C92: 0.3 | D92: 0.4 | E92: 0.7 | F92: ='src review'!Q11 | G92: ='src review'!R11 | H92: 0 | I92: 4 | J92: 20 | K92: 0 | L92: >1000C | M92: 0.587 | N92: Cement (239) | O92: 0.8492 | P92: 3 proc | Q92: Raw mill blending (process). | R92: 0 | S92: 0 | T92: 0 | U92: 1
A93: Clinker | B93: Use of High-Pressure Roller Pressesa | C93: 0.3 | D93: 0.4 | E93: 0.7 | F93: 0 | G93: 0.1 | H93: 0 | I93: 11 | J93: 20 | K93: 0 | L93: >1000C | M93: 0.587 | N93: Cement (239) | O93: 0.8492 | P93: 3 proc | Q93: High-pressure roller presses (grinding efficiency). | R93: 0 | S93: 1 | T93: 0 | U93: 1
A94: Clinker | B94: High Efficiency Classifiersb | C94: 0.5 | D94: 0.3 | E94: 0.5 | F94: ='src review'!Q12 | G94: ='src review'!R12 | H94: 0 | I94: 4 | J94: 20 | K94: 0 | L94: >1000C | M94: 0.587 | N94: Cement (239) | O94: 0.8492 | P94: 3 proc | Q94: High-efficiency classifiers. | R94: 0 | S94: 0 | T94: 0 | U94: 1
A95: Clinker | B95: Raw Meal Process Controlb | C95: 0.5 | D95: 0.3 | E95: 0.5 | F95: ='src review'!Q13 | G95: ='src review'!R13 | H95: 0 | I95: 0 | J95: 20 | K95: 0.1 | L95: >1000C | M95: 0.587 | N95: Cement (239) | O95: 0.8492 | P95: 3 proc | Q95: Raw meal process control. | R95: 0 | S95: 0 | T95: 0 | U95: 1
A96: Clinker | B96: Energy Management and Control Systemsc | C96: 0.8 | D96: 0.15 | E96: 0.2 | F96: 0.2 | G96: 0 | H96: 0 | I96: ='src review'!H160 | J96: 10 | K96: 0 | L96: >1000C | M96: 0.587 | N96: Cement (239) | O96: 0.8492 | P96: 3 proc | Q96: Energy management & control. | R96: 1 | S96: 0 | T96: 0 | U96: 1
A97: Clinker | B97: Kiln Combustion System Improvementsc | C97: 0.95 | D97: 0.05 | E97: 0.05 | F97: 0.4 | G97: 0 | H97: 0 | I97: ='src review'!H161 | J97: 30 | K97: 0 | L97: >1000C | M97: 0.587 | N97: Cement (239) | O97: 0.8492 | P97: 3 proc | Q97: Kiln combustion system improvements. | R97: 1 | S97: 0 | T97: 0 | U97: 1
A98: Clinker | B98: Indirect Firingc | C98: 0.95 | D98: 0.05 | E98: 0.05 | F98: 0.2 | G98: 0 | H98: 0 | I98: 10 | J98: 20 | K98: 0 | L98: >1000C | M98: 0.587 | N98: Cement (239) | O98: 0.8492 | P98: 3 proc | Q98: Indirect firing (combustion system). | R98: 1 | S98: 0 | T98: 0 | U98: 1
A99: Clinker | B99: Oxygen Enrichment technologyc | C99: 0.95 | D99: 0.05 | E99: 0.05 | F99: 0.2 | G99: -0.1 | H99: 0 | I99: 6 | J99: 20 | K99: 0 | L99: >1000C | M99: 0.587 | N99: Cement (239) | O99: 0.8492 | P99: 3 proc | Q99: Oxygen enrichment (process). | R99: 1 | S99: 0 | T99: 0 | U99: 1
A100: Clinker | B100: Kiln Shell Heat Loss Reductionc | C100: 0.95 | D100: 0.05 | E100: 0.05 | F100: 0.4 | G100: 0 | H100: 0 | I100: ='src review'!H162 | J100: 5 | K100: 0 | L100: >1000C | M100: 0.587 | N100: Cement (239) | O100: 0.8492 | P100: 3 proc | Q100: Preheater shell heat-loss reduction (insulation, not recovery; preheater recovery itself is do-not-double-count). | R100: 1 | S100: 0 | T100: 0 | U100: 1
A101: Clinker | B101: Conversion to Grate Coolerc | C101: 0.8 | D101: 0.15 | E101: 0.2 | F101: 0.3 | G101: 0 | H101: 0 | I101: 15 | J101: 30 | K101: 0.1 | L101: >1000C | M101: 0.587 | N101: Cement (239) | O101: 0.8492 | P101: 2 whr | Q101: System WHR: clinker grate-cooler heat recovery to combustion air (not burner-integral; not on DC list). | R101: 1 | S101: 0 | T101: 0 | U101: 1
A102: Clinker | B102: Optimize Grate Coolerc | C102: 0.7 | D102: 0.3 | E102: 0.3 | F102: 0.1 | G102: 0 | H102: 0 | I102: 2 | J102: 30 | K102: 0.1 | L102: >1000C | M102: 0.587 | N102: Cement (239) | O102: 0.8492 | P102: 2 whr | Q102: System WHR: optimize grate cooler (clinker heat recovery). | R102: 1 | S102: 0 | T102: 0 | U102: 1
A103: Clinker | B103: Low-Pressure Drop Suspension Preheatersc | C103: 0.75 | D103: 0.2 | E103: 0.25 | F103: ='src review'!Q14 | G103: ='src review'!R14 | H103: 0 | I103: 6 | J103: 30 | K103: 0 | L103: >1000C | M103: 0.587 | N103: Cement (239) | O103: 0.8492 | P103: 3 proc | Q103: Low-pressure-drop preheaters (fan-power/pressure drop, not recovery). | R103: 0 | S103: 0 | T103: 0 | U103: 1
A104: Clinker | B104: Heat Recovery for Power Generation (ORC)d | C104: 0 | D104: 0.58 | E104: 1 | F104: 0 | G104: 0.1 | H104: 0 | I104: 20 | J104: 20 | K104: 1 | L104: >1000C | M104: 0.587 | N104: Cement (239) | O104: 0.8492 | P104: 2 whr | Q104: System WHR: heat-to-power (ORC). Per taxonomy. | R104: 0 | S104: 1 | T104: 0 | U104: 1
A105: Clinker | B105: Increase Preheater Stages (from 5 to 6)c | C105: 0.9 | D105: 0.08 | E105: 0.1 | F105: 0.1 | G105: 0 | H105: 0 | I105: 11 | J105: 30 | K105: 0 | L105: >1000C | M105: 0.587 | N105: Cement (239) | O105: 0.8492 | P105: X DC | Q105: Do-not-double-count: increases preheater recovery, already credited in unit-efficiency files. | R105: 1 | S105: 0 | T105: 0 | U105: 1
A106: Clinker | B106: Addition of Precalciner or Upgradeb | C106: 0.49 | D106: 0.17 | E106: 0.33 | F106: 0.6 | G106: 0 | H106: 0 | I106: 93 | J106: 40 | K106: -1.2 | L106: >1000C | M106: 0.587 | N106: Cement (239) | O106: 0.8492 | P106: X DC | Q106: Do-not-double-count: precalciner recovery already credited in unit-efficiency files. | R106: 1 | S106: 0 | T106: 0 | U106: 0.82
A107: Clinker | B107: Conversion of Long Dry Kiln to Preheater Precalcinerb | C107: 0 | D107: 0.03 | E107: 0.05 | F107: 1.2 | G107: 0 | H107: 0 | I107: 93 | J107: 40 | K107: 0 | L107: >1000C | M107: 0.587 | N107: Cement (239) | O107: 0.8492 | P107: X DC | Q107: Do-not-double-count: preheater/precalciner recovery already credited in unit-efficiency files. | R107: 1 | S107: 0 | T107: 0 | U107: 0.05
...

Sheet Kermeli SEC
B3: Products | C3: Specific energy consumption (SEC) | E3: Share for heating | G3: Share for cooling
C5: (in GJ/t product)
C6: Fuels | D6: Electricity | E6: Fuels | F6: Electricity | G6: Fuels | H6: Electricity
B7: Chemicals
B8: Carbon black | C8: 52.7a | D8: 1.8 | E8: 1 | F8: 0 | G8: 0 | H8: 0.06
B9: Ethylene | C9: 31.8a | D9: 0 | E9: 1 | F9: 0 | G9: 0 | H9: 0
B10: Methanol | C10: 15 | D10: 0.5 | E10: 1 | F10: 0 | G10: 0 | H10: 0.04
B11: Ammonia | C11: 11.3 | D11: 0.5 | E11: 1 | F11: 0 | G11: 0 | H11: 0.06
B12: Soda ash | C12: 11.3 | D12: 0.3 | E12: 1 | F12: 0 | G12: 0 | H12: 0
B13: All rest chemicals | E13: 1 | F13: 0 | G13: 0 | H13: 0.03
B14: Iron and steel
B15: Blast furnace | C15: 11.6 | D15: 0.6 | E15: 1 | F15: 0 | G15: 0 | H15: 0
B16: Rolled steel | C16: 1.8b | D16: 0.4b | E16: 1 | F16: 0.1 | G16: 0 | H16: 0
B17: Electric arc furnace | C17: 1 | D17: 2.3 | E17: 1 | F17: 0.95 | G17: 0 | H17: 0
B18: Coke oven | C18: 3.2 | D18: 0.1 | E18: 1 | F18: 0 | G18: 0 | H18: 0
B19: All rest iron and steel | E19: 1 | F19: 0 | G19: 0 | H19: 0
B20: Non-ferrous metals
B21: Primary aluminium | C21: 0 | D21: 55.8 | E21: 1 | F21: 0.05 | G21: 0 | H21: 0
B22: All rest non-ferrous metals | E22: 1 | F22: 0.05 | G22: 0 | H22: 0
B23: Non-metallic minerals
B24: Cement | C24: 3.7c | D24: 0.5c | E24: 1 | F24: 0 | G24: 0 | H24: 0
B25: Flat glass | C25: 10.9 | D25: 3.3 | E25: 1 | F25: 0 | G25: 0 | H25: 0.06
B26: Container glass | C26: 5.8 | D26: 1.4 | E26: 1 | F26: 0.04 | G26: 0 | H26: 0.06
B27: All rest non-metallic minerals | E27: 1 | F27: 0 | G27: 0 | H27: 0.02
B28: Pulp and paper
B29: Paper | C29: 5.5 | D29: 1.9 | E29: 1 | F29: 0.01 | G29: 0 | H29: 0.01
B30: Chemical pulp | C30: 12.7 | D30: 2.3 | E30: 1 | F30: 0.01 | G30: 0 | H30: 0
B31: All rest pulp and paper | E31: 1 | F31: 0.01 | G31: 0 | H31: 0.005
B32: Others
B33: All rest others | E33: 1 | F33: 0.05 | G33: 0 | H33: 0.15

Sheet product map
A1: Product map & source data
A2: Per-product attributes referenced by Kermeli Data (XLOOKUP). Temp band & burner-integral penetration per G0.1 ruling-approved mapping. Heat-share links to 'heat share (src)'. US tonnages added in T4.2.
A4: Band -> burner-integral penetration (start-year, already credited in unit files)
A5: Band | B5: Penetration
A6: <100C | B6: 0
A7: 100-200C | B7: 0
A8: 200-500C | B8: 0.05
A9: 500-1000C | B9: 0.174
A10: >1000C | B10: 0.587
A13: Product | B13: EPS / heat-share industry | C13: Heat-share code | D13: Heat share (link) | E13: Temp band (dominant) | F13: Burner-integral penetration | G13: US production (Mt/yr) | H13: Basis year | I13: Source (primary) | J13: Split method / notes | K13: SEC total (GJ/t) — Kermeli Table 1 | L13: Steel split inputs | N13: SEC x prod (TBtu)
A14: Primary aluminum | B14: Other metals (242) | C14: 242 | D14: 0.6089 | E14: >1000C | F14: 0.587 | G14: 0.67 | H14: 2024e | I14: USGS MCS 2025 Aluminum | K14: 55.8 | L14: US crude steel total (Mt) | M14: 79.5 | N14: 35.435086
A15: Secondary aluminum | B15: Other metals (242) | C15: 242 | D15: 0.6089 | E15: 500-1000C | F15: 0.174 | G15: 1.6 | H15: 2024e | I15: USGS MCS 2025 Aluminum (old scrap) | K15: pending | L15: EAF share | M15: 0.718 | N15: 0
A16: Aluminum foundries | B16: Other metals (242) | C16: 242 | D16: 0.6089 | E16: 500-1000C | F16: 0.174 | G16: 2.4 | H16: ~2023 est | I16: ESTIMATED (AFS census basis) | J16: estimated split | K16: pending | L16: Note | M16: EAF/BOF split = total x EAF share; rolled ≈ total crude steel; pig iron proxy ≈ BOF-route crude steel. | N16: 0
A17: Coke oven | B17: Iron & steel (241) | C17: 241 | D17: 0.6516 | E17: >1000C | F17: 0.587 | G17: 9.07 | H17: 2025 | I17: EIA Today in Energy / Quarterly Coal Report | K17: 3.3 | L17: US paper total (Mt, 2023 FAO) | M17: 60.7 | N17: 28.369111
A18: Pig iron | B18: Iron & steel (241) | C18: 241 | D18: 0.6516 | E18: >1000C | F18: 0.587 | G18: 22.419 | H18: 2024 (proxy) | I18: Proxy from crude-steel split (see L13:M16) | K18: 12.2 | N18: 259.23913
A19: BF/BOF steel | B19: Iron & steel (241) | C19: 241 | D19: 0.6516 | E19: >1000C | F19: 0.587 | G19: 22.419 | H19: 2024 | I19: worldsteel/AISI x (1 - EAF share) | K19: pending | N19: 0
A20: EAF steel | B20: Iron & steel (241) | C20: 241 | D20: 0.6516 | E20: >1000C | F20: 0.587 | G20: 57.081 | H20: 2024 | I20: worldsteel/AISI x EAF share | K20: 3.3 | N20: 178.53773
A21: Rolled steel | B21: Iron & steel (241) | C21: 241 | D21: 0.6516 | E21: 500-1000C | F21: 0.174 | G21: 79.5 | H21: 2024 | I21: ≈ total crude steel (worldsteel/AISI) | K21: 2.2 | N21: 165.77319
A22: Container glass | B22: Glass (231) | C22: 231 | D22: 0.7514 | E22: >1000C | F22: 0.587 | G22: 10 | H22: ~2024 est | I22: ESTIMATED (market research) | J22: estimated split | K22: 7.2 | N22: 68.242824
A23: Flat glass | B23: Glass (231) | C23: 231 | D23: 0.7514 | E23: >1000C | F23: 0.587 | G23: 5 | H23: ~2024 est | I23: ESTIMATED (market research) | J23: estimated split | K23: 14.2 | N23: 67.295007
A24: Mechanical pulp | B24: Pulp & paper (17T18) | C24: 17T18 | D24: 0.8551 | E24: 100-200C | F24: 0 | G24: 1.5 | H24: ~2023 est | I24: ESTIMATED (FAO-anchored) | J24: estimated split | K24: pending | N24: 0
A25: Recovered fibre pulp | B25: Pulp & paper (17T18) | C25: 17T18 | D25: 0.8551 | E25: 100-200C | F25: 0 | G25: 20 | H25: ~2023 est | I25: ESTIMATED (FAO-anchored) | J25: estimated split | K25: pending | N25: 0
A26: Chemical pulp | B26: Pulp & paper (17T18) | C26: 17T18 | D26: 0.8551 | E26: 100-200C | F26: 0 | G26: 40 | H26: ~2023 est | I26: ESTIMATED (FAO-anchored) | J26: estimated split | K26: 15 | N26: 568.6902
A27: Tissue paper | B27: Pulp & paper (17T18) | C27: 17T18 | D27: 0.8551 | E27: 100-200C | F27: 0 | G27: 7.1 | H27: 2023 | I27: FAOSTAT (household & sanitary) | J27: direct | K27: 7.4 | N27: 49.798305
A28: Graphic paper | B28: Pulp & paper (17T18) | C28: 17T18 | D28: 0.8551 | E28: 100-200C | F28: 0 | G28: 7.37 | H28: 2023 | I28: FAOSTAT residual (total - tissue - packaging) | J28: estimated split (residual) | K28: 7.4 | N28: 51.692044
A29: Board and packaging paper | B29: Pulp & paper (17T18) | C29: 17T18 | D29: 0.8551 | E29: 100-200C | F29: 0 | G29: 46.23 | H29: 2023 | I29: FAOSTAT (packaging paper & board) | J29: direct | K29: 7.4 | N29: 324.25009
A30: Ethylene | B30: Chemicals (20) | C30: 20 | D30: 0.7161 | E30: 500-1000C | F30: 0.174 | G30: 31.4 | H30: 2019 | I30: US DOE Ethane Report (2019; refine to recent yr) | J30: direct (dated) | K30: 31.8 | N30: 946.41423
A31: Soda ash | B31: Chemicals (20) | C31: 20 | D31: 0.7161 | E31: 200-500C | F31: 0.05 | G31: 12 | H31: 2024e | I31: USGS MCS 2025 Soda Ash | K31: 11.6 | N31: 131.93613
A32: Carbon black | B32: Chemicals (20) | C32: 20 | D32: 0.7161 | E32: >1000C | F32: 0.587 | G32: 1.3 | H32: ~2023 est | I32: ESTIMATED | J32: estimated split | K32: 54.5 | N32: 67.152834
A33: Methanol | B33: Chemicals (20) | C33: 20 | D33: 0.7161 | E33: 500-1000C | F33: 0.174 | G33: 9 | H33: ~2023 est | I33: ESTIMATED (ACC-anchored) | J33: estimated split | K33: 15.5 | N33: 132.22047
A34: Ammonia | B34: Chemicals (20) | C34: 20 | D34: 0.7161 | E34: 500-1000C | F34: 0.174 | G34: 16.5 | H34: 2024 | I34: USGS MCS 2026 Nitrogen (N content /0.8235 -> NH3) | K34: 11.8 | N34: 184.53997
A35: Clinker | B35: Cement (239) | C35: 239 | D35: 0.8492 | E35: >1000C | F35: 0.587 | G35: 72 | H35: 2024e | I35: USGS MCS 2026 Cement (clinker line) | K35: pending | N35: 0
A36: Cement | B36: Cement (239) | C36: 239 | D36: 0.8492 | E36: >1000C | F36: 0.587 | G36: 85 | H36: 2024e | I36: USGS MCS 2026 Cement | K36: 4.2 | N36: 338.37067

Sheet energy base (MECS)
A1: Industry energy base — EIA MECS 2018 Table 3.1 (denominator for % reduction curves)
A2: Fuel-curve base = combustion fuel x heat share (G0.6 Option B). Elec-curve base = net electricity. Elec TBtu = MkWh x 0.003412 (3,412 Btu/kWh). Only the 6 covered manufacturing industries need this; uncovered industries take the Bianchi fraction directly.
A3: EPS industry | B3: NAICS | C3: Total fuel (TBtu) | D3: Net elec (MkWh) | E3: Elec (TBtu) | F3: Combustion fuel (TBtu) | G3: Heat share | H3: Fuel-for-heat base (TBtu) | I3: Elec base (TBtu) | K3: code
A4: pulp paper and printing 17T18 | B4: 322+323 | C4: 2098 | D4: 61038 | E4: =D4*0.003412 | F4: =C4-E4 | G4: ='heat share (src)'!C10 | H4: =F4*G4 | I4: =E4 | K4: 17T18
A5: chemicals 20 | B5: 325 | C5: 3813 | D5: 146846 | E5: =D5*0.003412 | F5: =C5-E5 | G5: ='heat share (src)'!C12 | H5: =F5*G5 | I5: =E5 | K5: 20
A6: glass and glass products 231 | B6: 3272 | C6: 153 | D6: 10676 | E6: =D6*0.003412 | F6: =C6-E6 | G6: ='heat share (src)'!C14 | H6: =F6*G6 | I6: =E6 | K6: 231
A7: cement and other nonmetallic 239 | B7: 327 less 3272 | C7: 668 | D7: 27277 | E7: =D7*0.003412 | F7: =C7-E7 | G7: ='heat share (src)'!C15 | H7: =F7*G7 | I7: =E7 | K7: 239
A8: iron and steel 241 | B8: 331110 | C8: 1141 | D8: 55633 | E8: =D8*0.003412 | F8: =C8-E8 | G8: ='heat share (src)'!C16 | H8: =F8*G8 | I8: =E8 | K8: 241
A9: other metals 242 | B9: 3313+3314 | C9: 302 | D9: 39534 | E9: =D9*0.003412 | F9: =C9-E9 | G9: ='heat share (src)'!C17 | H9: =F9*G9 | I9: =E9 | K9: 242
A11: Bianchi assumed cost mu (savings-wtd avg CCE of covered whr, $/MMBtu) | F11: {=SUMPRODUCT((economics!$D$2:$D$167="whr")*economics!$AK$2:$AK$167*economics!$AH$2:$AH$167)/SUMPRODUCT((economics!$D$2:$D$167="whr")*economics!$AH$2:$AH$167)}

Sheet EU Data
B22: Indst | C22: Potential (TWh) | D22: Potential (%) | E22: LT | F22: MT | G22: HT | H22: EPS ISIC 1 | I22: EPS ISIC 2 | J22: EPS ISIC 3
B23: NS | C23: 19.9 | D23: 0.033 | E23: 35.4 | F23: 17.9 | G23: 46.7 | H23: other manufacturing 31T33 | I23: metal products except machinery and vehicles 25 | J23: rubber and plastic products 22
B24: C | C24: 9.6 | D24: 0.016 | E24: 15.2 | F24: 33.2 | G24: 51.6 | H24: construction 41T43
B25: W&WP | C25: 4.8 | D25: 0.008 | E25: 73.9 | F25: 4 | G25: 22.1 | H25: wood products 16
B26: M | C26: 19.6 | D26: 0.033 | E26: 36.8 | F26: 6.2 | G26: 57 | H26: other machinery 28 | I26: computers and electronics 26 | J26: appliances and electrical equipment 27
B27: TE | C27: 7.9 | D27: 0.013 | E27: 40.7 | F27: 5.8 | G27: 53.5 | H27: road vehicles 29 | I27: nonroad vehicles 30
B28: PPP | C28: 27 | D28: 0.045 | E28: 43.8 | F28: 6.8 | G28: 49.4 | H28: pulp paper and printing 17T18
B29: T&L | C29: 5.5 | D29: 0.009 | E29: 26.2 | F29: 5.9 | G29: 67.9 | H29: textiles apparel and leather 13T15
B30: F&T | C30: 35.1 | D30: 0.059 | E30: 25.1 | F30: 9.1 | G30: 65.8 | H30: food beverage and tobacco 10T12
B31: M&Q | C31: 3.3 | D31: 0.005 | E31: 27 | F31: 20.6 | G31: 52.4 | H31: other mining and quarrying 07T08
B32: NMM | C32: 43.8 | D32: 0.074 | E32: 0.6 | F32: 15 | G32: 84.4 | H32: cement and other nonmetallic minerals 239 | I32: glass and glass products 231
B33: C&P | C33: 33.9 | D33: 0.057 | E33: 37.1 | F33: 62.9 | G33: 0 | H33: chemicals 20
B34: NFM | C34: 14.1 | D34: 0.024 | E34: 1.8 | F34: 4.5 | G34: 93.7 | H34: other metals 242
B35: I&S | C35: 54.3 | D35: 0.091 | E35: 11.1 | F35: 29.8 | G35: 59.1 | H35: iron and steel 241

Sheet economics
A1: Product | B1: Measure | C1: Bucket | D1: Curve | E1: 2050 add'l diffusion | F1: Fuel GJ/t | G1: Elec GJ/t | H1: Invest EUR/t | I1: Life (yr) | J1: O&M EUR/t | K1: US tonnage (Mt) | L1: Invest 2012$/t | M1: O&M 2012$/t | N1: CRF@10% | O1: Ann cost 2012$/t | P1: Tot pos GJ/t | Q1: Fuel share | R1: Elec share | S1: CCE@10% $/GJ | T1: CCE@10% $/MMBtu | U1: CCE fuel@10% | V1: CCE elec@10% | W1: CRF@15% | X1: Ann cost@15% $/t | Y1: CCE@15% $/MMBtu | Z1: Ann fuel saved GJ/yr | AA1: Ann elec saved GJ/yr | AB1: Flags | AD1: Real discount rate | AE1: 0.1 | AG1: Industry code | AH1: Fuel %pot | AI1: Elec %pot | AJ1: sigma | AK1: mu | AL1: WACC (industry) | AM1: Cap intensity 2012$/MMBtu-yr | AN1: Total capex 2012$
A2: ='Kermeli Data'!A9 | B2: ='Kermeli Data'!B9 | C2: ='Kermeli Data'!P9 | D2: =IF(C2="2 whr","whr",IF(C2="3 proc","process","EXCLUDED")) | E2: ='Kermeli Data'!E9 | F2: ='Kermeli Data'!F9 | G2: ='Kermeli Data'!G9 | H2: ='Kermeli Data'!I9 | I2: ='Kermeli Data'!J9 | J2: ='Kermeli Data'!K9 | K2: =IFERROR(_xlfn.XLOOKUP(A2,'product map'!$A$14:$A$36,'product map'!$G$14:$G$36),"pending") | L2: =H2*cpi!$B$12*cpi!$B$10 | M2: =J2*cpi!$B$12*cpi!$B$10 | N2: =IF(I2>0,AL2/(1-(1+AL2)^-I2),"") | O2: =L2*N2+M2 | P2: =MAX(F2,0)+MAX(G2,0) | Q2: =IF(P2>0,MAX(F2,0)/P2,0) | R2: =IF(P2>0,MAX(G2,0)/P2,0) | S2: =IF(P2>0,O2/P2,"") | T2: =IF(P2>0,S2/$AE$3,"") | U2: =IF(AND(P2>0,Q2>0),T2,"") | V2: =IF(AND(P2>0,R2>0),T2,"") | W2: =IF(I2>0,$AE$2/(1-(1+$AE$2)^-I2),"") | X2: =L2*W2+M2 | Y2: =IF(P2>0,(X2/P2)/$AE$3,"") | Z2: =IF(AND(ISNUMBER(K2),Q2>0),MAX(F2,0)*K2*1000000*E2,"pending") | AA2: =IF(AND(ISNUMBER(K2),R2>0),MAX(G2,0)*K2*1000000*E2,"pending") | AB2: =IF(AND(ISNUMBER(S2),S2<0),"NEG-CCE","")&IF(NOT(ISNUMBER(K2)),"|pending tonnage","") | AD2: Hurdle rate (sensitivity) | AE2: 0.15 | AG2: =IFERROR(_xlfn.XLOOKUP(A2,'product map'!$A$14:$A$36,'product map'!$C$14:$C$36),"?") | AH2: =IFERROR((Z2*0.000000947817)/_xlfn.XLOOKUP(AG2,'energy base (MECS)'!$K$4:$K$9,'energy base (MECS)'!$F$4:$F$9),0) | AI2: =IFERROR((AA2*0.000000947817)/_xlfn.XLOOKUP(AG2,'energy base (MECS)'!$K$4:$K$9,'energy base (MECS)'!$I$4:$I$9),0) | AJ2: =MAX(0.3*ABS(AK2),0.000001) | AK2: =IF(ISNUMBER(T2),T2,0) | AL2: =IFERROR(_xlfn.XLOOKUP(AG2,'BCoISC-WACCbI'!$C$2:$C$26,'BCoISC-WACCbI'!$B$2:$B$26)+$AE$4,0.1) | AM2: =IF(P2>0,L2/P2/0.947817,0) | AN2: =IF(AND(P2>0,ISNUMBER(K2)),L2*K2*1000000*E2,0)
A3: ='Kermeli Data'!A10 | B3: ='Kermeli Data'!B10 | C3: ='Kermeli Data'!P10 | D3: =IF(C3="2 whr","whr",IF(C3="3 proc","process","EXCLUDED")) | E3: ='Kermeli Data'!E10 | F3: ='Kermeli Data'!F10 | G3: ='Kermeli Data'!G10 | H3: ='Kermeli Data'!I10 | I3: ='Kermeli Data'!J10 | J3: ='Kermeli Data'!K10 | K3: =IFERROR(_xlfn.XLOOKUP(A3,'product map'!$A$14:$A$36,'product map'!$G$14:$G$36),"pending") | L3: =H3*cpi!$B$12*cpi!$B$10 | M3: =J3*cpi!$B$12*cpi!$B$10 | N3: =IF(I3>0,AL3/(1-(1+AL3)^-I3),"") | O3: =L3*N3+M3 | P3: =MAX(F3,0)+MAX(G3,0) | Q3: =IF(P3>0,MAX(F3,0)/P3,0) | R3: =IF(P3>0,MAX(G3,0)/P3,0) | S3: =IF(P3>0,O3/P3,"") | T3: =IF(P3>0,S3/$AE$3,"") | U3: =IF(AND(P3>0,Q3>0),T3,"") | V3: =IF(AND(P3>0,R3>0),T3,"") | W3: =IF(I3>0,$AE$2/(1-(1+$AE$2)^-I3),"") | X3: =L3*W3+M3 | Y3: =IF(P3>0,(X3/P3)/$AE$3,"") | Z3: =IF(AND(ISNUMBER(K3),Q3>0),MAX(F3,0)*K3*1000000*E3,"pending") | AA3: =IF(AND(ISNUMBER(K3),R3>0),MAX(G3,0)*K3*1000000*E3,"pending") | AB3: =IF(AND(ISNUMBER(S3),S3<0),"NEG-CCE","")&IF(NOT(ISNUMBER(K3)),"|pending tonnage","") | AD3: MMBtu per GJ (from cpi!B15) | AE3: =cpi!B15 | AG3: =IFERROR(_xlfn.XLOOKUP(A3,'product map'!$A$14:$A$36,'product map'!$C$14:$C$36),"?") | AH3: =IFERROR((Z3*0.000000947817)/_xlfn.XLOOKUP(AG3,'energy base (MECS)'!$K$4:$K$9,'energy base (MECS)'!$F$4:$F$9),0) | AI3: =IFERROR((AA3*0.000000947817)/_xlfn.XLOOKUP(AG3,'energy base (MECS)'!$K$4:$K$9,'energy base (MECS)'!$I$4:$I$9),0) | AJ3: =MAX(0.3*ABS(AK3),0.000001) | AK3: =IF(ISNUMBER(T3),T3,0) | AL3: =IFERROR(_xlfn.XLOOKUP(AG3,'BCoISC-WACCbI'!$C$2:$C$26,'BCoISC-WACCbI'!$B$2:$B$26)+$AE$4,0.1) | AM3: =IF(P3>0,L3/P3/0.947817,0) | AN3: =IF(AND(P3>0,ISNUMBER(K3)),L3*K3*1000000*E3,0)
A4: ='Kermeli Data'!A11 | B4: ='Kermeli Data'!B11 | C4: ='Kermeli Data'!P11 | D4: =IF(C4="2 whr","whr",IF(C4="3 proc","process","EXCLUDED")) | E4: ='Kermeli Data'!E11 | F4: ='Kermeli Data'!F11 | G4: ='Kermeli Data'!G11 | H4: ='Kermeli Data'!I11 | I4: ='Kermeli Data'!J11 | J4: ='Kermeli Data'!K11 | K4: =IFERROR(_xlfn.XLOOKUP(A4,'product map'!$A$14:$A$36,'product map'!$G$14:$G$36),"pending") | L4: =H4*cpi!$B$12*cpi!$B$10 | M4: =J4*cpi!$B$12*cpi!$B$10 | N4: =IF(I4>0,AL4/(1-(1+AL4)^-I4),"") | O4: =L4*N4+M4 | P4: =MAX(F4,0)+MAX(G4,0) | Q4: =IF(P4>0,MAX(F4,0)/P4,0) | R4: =IF(P4>0,MAX(G4,0)/P4,0) | S4: =IF(P4>0,O4/P4,"") | T4: =IF(P4>0,S4/$AE$3,"") | U4: =IF(AND(P4>0,Q4>0),T4,"") | V4: =IF(AND(P4>0,R4>0),T4,"") | W4: =IF(I4>0,$AE$2/(1-(1+$AE$2)^-I4),"") | X4: =L4*W4+M4 | Y4: =IF(P4>0,(X4/P4)/$AE$3,"") | Z4: =IF(AND(ISNUMBER(K4),Q4>0),MAX(F4,0)*K4*1000000*E4,"pending") | AA4: =IF(AND(ISNUMBER(K4),R4>0),MAX(G4,0)*K4*1000000*E4,"pending") | AB4: =IF(AND(ISNUMBER(S4),S4<0),"NEG-CCE","")&IF(NOT(ISNUMBER(K4)),"|pending tonnage","") | AD4: Hurdle premium (added to industry WACC) | AE4: 0.07 | AG4: =IFERROR(_xlfn.XLOOKUP(A4,'product map'!$A$14:$A$36,'product map'!$C$14:$C$36),"?") | AH4: =IFERROR((Z4*0.000000947817)/_xlfn.XLOOKUP(AG4,'energy base (MECS)'!$K$4:$K$9,'energy base (MECS)'!$F$4:$F$9),0) | AI4: =IFERROR((AA4*0.000000947817)/_xlfn.XLOOKUP(AG4,'energy base (MECS)'!$K$4:$K$9,'energy base (MECS)'!$I$4:$I$9),0) | AJ4: =MAX(0.3*ABS(AK4),0.000001) | AK4: =IF(ISNUMBER(T4),T4,0) | AL4: =IFERROR(_xlfn.XLOOKUP(AG4,'BCoISC-WACCbI'!$C$2:$C$26,'BCoISC-WACCbI'!$B$2:$B$26)+$AE$4,0.1) | AM4: =IF(P4>0,L4/P4/0.947817,0) | AN4: =IF(AND(P4>0,ISNUMBER(K4)),L4*K4*1000000*E4,0)
A5: ='Kermeli Data'!A12 | B5: ='Kermeli Data'!B12 | C5: ='Kermeli Data'!P12 | D5: =IF(C5="2 whr","whr",IF(C5="3 proc","process","EXCLUDED")) | E5: ='Kermeli Data'!E12 | F5: ='Kermeli Data'!F12 | G5: ='Kermeli Data'!G12 | H5: ='Kermeli Data'!I12 | I5: ='Kermeli Data'!J12 | J5: ='Kermeli Data'!K12 | K5: =IFERROR(_xlfn.XLOOKUP(A5,'product map'!$A$14:$A$36,'product map'!$G$14:$G$36),"pending") | L5: =H5*cpi!$B$12*cpi!$B$10 | M5: =J5*cpi!$B$12*cpi!$B$10 | N5: =IF(I5>0,AL5/(1-(1+AL5)^-I5),"") | O5: =L5*N5+M5 | P5: =MAX(F5,0)+MAX(G5,0) | Q5: =IF(P5>0,MAX(F5,0)/P5,0) | R5: =IF(P5>0,MAX(G5,0)/P5,0) | S5: =IF(P5>0,O5/P5,"") | T5: =IF(P5>0,S5/$AE$3,"") | U5: =IF(AND(P5>0,Q5>0),T5,"") | V5: =IF(AND(P5>0,R5>0),T5,"") | W5: =IF(I5>0,$AE$2/(1-(1+$AE$2)^-I5),"") | X5: =L5*W5+M5 | Y5: =IF(P5>0,(X5/P5)/$AE$3,"") | Z5: =IF(AND(ISNUMBER(K5),Q5>0),MAX(F5,0)*K5*1000000*E5,"pending") | AA5: =IF(AND(ISNUMBER(K5),R5>0),MAX(G5,0)*K5*1000000*E5,"pending") | AB5: =IF(AND(ISNUMBER(S5),S5<0),"NEG-CCE","")&IF(NOT(ISNUMBER(K5)),"|pending tonnage","") | AG5: =IFERROR(_xlfn.XLOOKUP(A5,'product map'!$A$14:$A$36,'product map'!$C$14:$C$36),"?") | AH5: =IFERROR((Z5*0.000000947817)/_xlfn.XLOOKUP(AG5,'energy base (MECS)'!$K$4:$K$9,'energy base (MECS)'!$F$4:$F$9),0) | AI5: =IFERROR((AA5*0.000000947817)/_xlfn.XLOOKUP(AG5,'energy base (MECS)'!$K$4:$K$9,'energy base (MECS)'!$I$4:$I$9),0) | AJ5: =MAX(0.3*ABS(AK5),0.000001) | AK5: =IF(ISNUMBER(T5),T5,0) | AL5: =IFERROR(_xlfn.XLOOKUP(AG5,'BCoISC-WACCbI'!$C$2:$C$26,'BCoISC-WACCbI'!$B$2:$B$26)+$AE$4,0.1) | AM5: =IF(P5>0,L5/P5/0.947817,0) | AN5: =IF(AND(P5>0,ISNUMBER(K5)),L5*K5*1000000*E5,0)
A6: ='Kermeli Data'!A13 | B6: ='Kermeli Data'!B13 | C6: ='Kermeli Data'!P13 | D6: =IF(C6="2 whr","whr",IF(C6="3 proc","process","EXCLUDED")) | E6: ='Kermeli Data'!E13 | F6: ='Kermeli Data'!F13 | G6: ='Kermeli Data'!G13 | H6: ='Kermeli Data'!I13 | I6: ='Kermeli Data'!J13 | J6: ='Kermeli Data'!K13 | K6: =IFERROR(_xlfn.XLOOKUP(A6,'product map'!$A$14:$A$36,'product map'!$G$14:$G$36),"pending") | L6: =H6*cpi!$B$12*cpi!$B$10 | M6: =J6*cpi!$B$12*cpi!$B$10 | N6: =IF(I6>0,AL6/(1-(1+AL6)^-I6),"") | O6: =L6*N6+M6 | P6: =MAX(F6,0)+MAX(G6,0) | Q6: =IF(P6>0,MAX(F6,0)/P6,0) | R6: =IF(P6>0,MAX(G6,0)/P6,0) | S6: =IF(P6>0,O6/P6,"") | T6: =IF(P6>0,S6/$AE$3,"") | U6: =IF(AND(P6>0,Q6>0),T6,"") | V6: =IF(AND(P6>0,R6>0),T6,"") | W6: =IF(I6>0,$AE$2/(1-(1+$AE$2)^-I6),"") | X6: =L6*W6+M6 | Y6: =IF(P6>0,(X6/P6)/$AE$3,"") | Z6: =IF(AND(ISNUMBER(K6),Q6>0),MAX(F6,0)*K6*1000000*E6,"pending") | AA6: =IF(AND(ISNUMBER(K6),R6>0),MAX(G6,0)*K6*1000000*E6,"pending") | AB6: =IF(AND(ISNUMBER(S6),S6<0),"NEG-CCE","")&IF(NOT(ISNUMBER(K6)),"|pending tonnage","") | AG6: =IFERROR(_xlfn.XLOOKUP(A6,'product map'!$A$14:$A$36,'product map'!$C$14:$C$36),"?") | AH6: =IFERROR((Z6*0.000000947817)/_xlfn.XLOOKUP(AG6,'energy base (MECS)'!$K$4:$K$9,'energy base (MECS)'!$F$4:$F$9),0) | AI6: =IFERROR((AA6*0.000000947817)/_xlfn.XLOOKUP(AG6,'energy base (MECS)'!$K$4:$K$9,'energy base (MECS)'!$I$4:$I$9),0) | AJ6: =MAX(0.3*ABS(AK6),0.000001) | AK6: =IF(ISNUMBER(T6),T6,0) | AL6: =IFERROR(_xlfn.XLOOKUP(AG6,'BCoISC-WACCbI'!$C$2:$C$26,'BCoISC-WACCbI'!$B$2:$B$26)+$AE$4,0.1) | AM6: =IF(P6>0,L6/P6/0.947817,0) | AN6: =IF(AND(P6>0,ISNUMBER(K6)),L6*K6*1000000*E6,0)
A7: ='Kermeli Data'!A14 | B7: ='Kermeli Data'!B14 | C7: ='Kermeli Data'!P14 | D7: =IF(C7="2 whr","whr",IF(C7="3 proc","process","EXCLUDED")) | E7: ='Kermeli Data'!E14 | F7: ='Kermeli Data'!F14 | G7: ='Kermeli Data'!G14 | H7: ='Kermeli Data'!I14 | I7: ='Kermeli Data'!J14 | J7: ='Kermeli Data'!K14 | K7: =IFERROR(_xlfn.XLOOKUP(A7,'product map'!$A$14:$A$36,'product map'!$G$14:$G$36),"pending") | L7: =H7*cpi!$B$12*cpi!$B$10 | M7: =J7*cpi!$B$12*cpi!$B$10 | N7: =IF(I7>0,AL7/(1-(1+AL7)^-I7),"") | O7: =L7*N7+M7 | P7: =MAX(F7,0)+MAX(G7,0) | Q7: =IF(P7>0,MAX(F7,0)/P7,0) | R7: =IF(P7>0,MAX(G7,0)/P7,0) | S7: =IF(P7>0,O7/P7,"") | T7: =IF(P7>0,S7/$AE$3,"") | U7: =IF(AND(P7>0,Q7>0),T7,"") | V7: =IF(AND(P7>0,R7>0),T7,"") | W7: =IF(I7>0,$AE$2/(1-(1+$AE$2)^-I7),"") | X7: =L7*W7+M7 | Y7: =IF(P7>0,(X7/P7)/$AE$3,"") | Z7: =IF(AND(ISNUMBER(K7),Q7>0),MAX(F7,0)*K7*1000000*E7,"pending") | AA7: =IF(AND(ISNUMBER(K7),R7>0),MAX(G7,0)*K7*1000000*E7,"pending") | AB7: =IF(AND(ISNUMBER(S7),S7<0),"NEG-CCE","")&IF(NOT(ISNUMBER(K7)),"|pending tonnage","") | AG7: =IFERROR(_xlfn.XLOOKUP(A7,'product map'!$A$14:$A$36,'product map'!$C$14:$C$36),"?") | AH7: =IFERROR((Z7*0.000000947817)/_xlfn.XLOOKUP(AG7,'energy base (MECS)'!$K$4:$K$9,'energy base (MECS)'!$F$4:$F$9),0) | AI7: =IFERROR((AA7*0.000000947817)/_xlfn.XLOOKUP(AG7,'energy base (MECS)'!$K$4:$K$9,'energy base (MECS)'!$I$4:$I$9),0) | AJ7: =MAX(0.3*ABS(AK7),0.000001) | AK7: =IF(ISNUMBER(T7),T7,0) | AL7: =IFERROR(_xlfn.XLOOKUP(AG7,'BCoISC-WACCbI'!$C$2:$C$26,'BCoISC-WACCbI'!$B$2:$B$26)+$AE$4,0.1) | AM7: =IF(P7>0,L7/P7/0.947817,0) | AN7: =IF(AND(P7>0,ISNUMBER(K7)),L7*K7*1000000*E7,0)
A8: ='Kermeli Data'!A15 | B8: ='Kermeli Data'!B15 | C8: ='Kermeli Data'!P15 | D8: =IF(C8="2 whr","whr",IF(C8="3 proc","process","EXCLUDED")) | E8: ='Kermeli Data'!E15 | F8: ='Kermeli Data'!F15 | G8: ='Kermeli Data'!G15 | H8: ='Kermeli Data'!I15 | I8: ='Kermeli Data'!J15 | J8: ='Kermeli Data'!K15 | K8: =IFERROR(_xlfn.XLOOKUP(A8,'product map'!$A$14:$A$36,'product map'!$G$14:$G$36),"pending") | L8: =H8*cpi!$B$12*cpi!$B$10 | M8: =J8*cpi!$B$12*cpi!$B$10 | N8: =IF(I8>0,AL8/(1-(1+AL8)^-I8),"") | O8: =L8*N8+M8 | P8: =MAX(F8,0)+MAX(G8,0) | Q8: =IF(P8>0,MAX(F8,0)/P8,0) | R8: =IF(P8>0,MAX(G8,0)/P8,0) | S8: =IF(P8>0,O8/P8,"") | T8: =IF(P8>0,S8/$AE$3,"") | U8: =IF(AND(P8>0,Q8>0),T8,"") | V8: =IF(AND(P8>0,R8>0),T8,"") | W8: =IF(I8>0,$AE$2/(1-(1+$AE$2)^-I8),"") | X8: =L8*W8+M8 | Y8: =IF(P8>0,(X8/P8)/$AE$3,"") | Z8: =IF(AND(ISNUMBER(K8),Q8>0),MAX(F8,0)*K8*1000000*E8,"pending") | AA8: =IF(AND(ISNUMBER(K8),R8>0),MAX(G8,0)*K8*1000000*E8,"pending") | AB8: =IF(AND(ISNUMBER(S8),S8<0),"NEG-CCE","")&IF(NOT(ISNUMBER(K8)),"|pending tonnage","") | AG8: =IFERROR(_xlfn.XLOOKUP(A8,'product map'!$A$14:$A$36,'product map'!$C$14:$C$36),"?") | AH8: =IFERROR((Z8*0.000000947817)/_xlfn.XLOOKUP(AG8,'energy base (MECS)'!$K$4:$K$9,'energy base (MECS)'!$F$4:$F$9),0) | AI8: =IFERROR((AA8*0.000000947817)/_xlfn.XLOOKUP(AG8,'energy base (MECS)'!$K$4:$K$9,'energy base (MECS)'!$I$4:$I$9),0) | AJ8: =MAX(0.3*ABS(AK8),0.000001) | AK8: =IF(ISNUMBER(T8),T8,0) | AL8: =IFERROR(_xlfn.XLOOKUP(AG8,'BCoISC-WACCbI'!$C$2:$C$26,'BCoISC-WACCbI'!$B$2:$B$26)+$AE$4,0.1) | AM8: =IF(P8>0,L8/P8/0.947817,0) | AN8: =IF(AND(P8>0,ISNUMBER(K8)),L8*K8*1000000*E8,0)
A9: ='Kermeli Data'!A16 | B9: ='Kermeli Data'!B16 | C9: ='Kermeli Data'!P16 | D9: =IF(C9="2 whr","whr",IF(C9="3 proc","process","EXCLUDED")) | E9: ='Kermeli Data'!E16 | F9: ='Kermeli Data'!F16 | G9: ='Kermeli Data'!G16 | H9: ='Kermeli Data'!I16 | I9: ='Kermeli Data'!J16 | J9: ='Kermeli Data'!K16 | K9: =IFERROR(_xlfn.XLOOKUP(A9,'product map'!$A$14:$A$36,'product map'!$G$14:$G$36),"pending") | L9: =H9*cpi!$B$12*cpi!$B$10 | M9: =J9*cpi!$B$12*cpi!$B$10 | N9: =IF(I9>0,AL9/(1-(1+AL9)^-I9),"") | O9: =L9*N9+M9 | P9: =MAX(F9,0)+MAX(G9,0) | Q9: =IF(P9>0,MAX(F9,0)/P9,0) | R9: =IF(P9>0,MAX(G9,0)/P9,0) | S9: =IF(P9>0,O9/P9,"") | T9: =IF(P9>0,S9/$AE$3,"") | U9: =IF(AND(P9>0,Q9>0),T9,"") | V9: =IF(AND(P9>0,R9>0),T9,"") | W9: =IF(I9>0,$AE$2/(1-(1+$AE$2)^-I9),"") | X9: =L9*W9+M9 | Y9: =IF(P9>0,(X9/P9)/$AE$3,"") | Z9: =IF(AND(ISNUMBER(K9),Q9>0),MAX(F9,0)*K9*1000000*E9,"pending") | AA9: =IF(AND(ISNUMBER(K9),R9>0),MAX(G9,0)*K9*1000000*E9,"pending") | AB9: =IF(AND(ISNUMBER(S9),S9<0),"NEG-CCE","")&IF(NOT(ISNUMBER(K9)),"|pending tonnage","") | AG9: =IFERROR(_xlfn.XLOOKUP(A9,'product map'!$A$14:$A$36,'product map'!$C$14:$C$36),"?") | AH9: =IFERROR((Z9*0.000000947817)/_xlfn.XLOOKUP(AG9,'energy base (MECS)'!$K$4:$K$9,'energy base (MECS)'!$F$4:$F$9),0) | AI9: =IFERROR((AA9*0.000000947817)/_xlfn.XLOOKUP(AG9,'energy base (MECS)'!$K$4:$K$9,'energy base (MECS)'!$I$4:$I$9),0) | AJ9: =MAX(0.3*ABS(AK9),0.000001) | AK9: =IF(ISNUMBER(T9),T9,0) | AL9: =IFERROR(_xlfn.XLOOKUP(AG9,'BCoISC-WACCbI'!$C$2:$C$26,'BCoISC-WACCbI'!$B$2:$B$26)+$AE$4,0.1) | AM9: =IF(P9>0,L9/P9/0.947817,0) | AN9: =IF(AND(P9>0,ISNUMBER(K9)),L9*K9*1000000*E9,0)
A10: ='Kermeli Data'!A17 | B10: ='Kermeli Data'!B17 | C10: ='Kermeli Data'!P17 | D10: =IF(C10="2 whr","whr",IF(C10="3 proc","process","EXCLUDED")) | E10: ='Kermeli Data'!E17 | F10: ='Kermeli Data'!F17 | G10: ='Kermeli Data'!G17 | H10: ='Kermeli Data'!I17 | I10: ='Kermeli Data'!J17 | J10: ='Kermeli Data'!K17 | K10: =IFERROR(_xlfn.XLOOKUP(A10,'product map'!$A$14:$A$36,'product map'!$G$14:$G$36),"pending") | L10: =H10*cpi!$B$12*cpi!$B$10 | M10: =J10*cpi!$B$12*cpi!$B$10 | N10: =IF(I10>0,AL10/(1-(1+AL10)^-I10),"") | O10: =L10*N10+M10 | P10: =MAX(F10,0)+MAX(G10,0) | Q10: =IF(P10>0,MAX(F10,0)/P10,0) | R10: =IF(P10>0,MAX(G10,0)/P10,0) | S10: =IF(P10>0,O10/P10,"") | T10: =IF(P10>0,S10/$AE$3,"") | U10: =IF(AND(P10>0,Q10>0),T10,"") | V10: =IF(AND(P10>0,R10>0),T10,"") | W10: =IF(I10>0,$AE$2/(1-(1+$AE$2)^-I10),"") | X10: =L10*W10+M10 | Y10: =IF(P10>0,(X10/P10)/$AE$3,"") | Z10: =IF(AND(ISNUMBER(K10),Q10>0),MAX(F10,0)*K10*1000000*E10,"pending") | AA10: =IF(AND(ISNUMBER(K10),R10>0),MAX(G10,0)*K10*1000000*E10,"pending") | AB10: =IF(AND(ISNUMBER(S10),S10<0),"NEG-CCE","")&IF(NOT(ISNUMBER(K10)),"|pending tonnage","") | AG10: =IFERROR(_xlfn.XLOOKUP(A10,'product map'!$A$14:$A$36,'product map'!$C$14:$C$36),"?") | AH10: =IFERROR((Z10*0.000000947817)/_xlfn.XLOOKUP(AG10,'energy base (MECS)'!$K$4:$K$9,'energy base (MECS)'!$F$4:$F$9),0) | AI10: =IFERROR((AA10*0.000000947817)/_xlfn.XLOOKUP(AG10,'energy base (MECS)'!$K$4:$K$9,'energy base (MECS)'!$I$4:$I$9),0) | AJ10: =MAX(0.3*ABS(AK10),0.000001) | AK10: =IF(ISNUMBER(T10),T10,0) | AL10: =IFERROR(_xlfn.XLOOKUP(AG10,'BCoISC-WACCbI'!$C$2:$C$26,'BCoISC-WACCbI'!$B$2:$B$26)+$AE$4,0.1) | AM10: =IF(P10>0,L10/P10/0.947817,0) | AN10: =IF(AND(P10>0,ISNUMBER(K10)),L10*K10*1000000*E10,0)
A11: ='Kermeli Data'!A18 | B11: ='Kermeli Data'!B18 | C11: ='Kermeli Data'!P18 | D11: =IF(C11="2 whr","whr",IF(C11="3 proc","process","EXCLUDED")) | E11: ='Kermeli Data'!E18 | F11: ='Kermeli Data'!F18 | G11: ='Kermeli Data'!G18 | H11: ='Kermeli Data'!I18 | I11: ='Kermeli Data'!J18 | J11: ='Kermeli Data'!K18 | K11: =IFERROR(_xlfn.XLOOKUP(A11,'product map'!$A$14:$A$36,'product map'!$G$14:$G$36),"pending") | L11: =H11*cpi!$B$12*cpi!$B$10 | M11: =J11*cpi!$B$12*cpi!$B$10 | N11: =IF(I11>0,AL11/(1-(1+AL11)^-I11),"") | O11: =L11*N11+M11 | P11: =MAX(F11,0)+MAX(G11,0) | Q11: =IF(P11>0,MAX(F11,0)/P11,0) | R11: =IF(P11>0,MAX(G11,0)/P11,0) | S11: =IF(P11>0,O11/P11,"") | T11: =IF(P11>0,S11/$AE$3,"") | U11: =IF(AND(P11>0,Q11>0),T11,"") | V11: =IF(AND(P11>0,R11>0),T11,"") | W11: =IF(I11>0,$AE$2/(1-(1+$AE$2)^-I11),"") | X11: =L11*W11+M11 | Y11: =IF(P11>0,(X11/P11)/$AE$3,"") | Z11: =IF(AND(ISNUMBER(K11),Q11>0),MAX(F11,0)*K11*1000000*E11,"pending") | AA11: =IF(AND(ISNUMBER(K11),R11>0),MAX(G11,0)*K11*1000000*E11,"pending") | AB11: =IF(AND(ISNUMBER(S11),S11<0),"NEG-CCE","")&IF(NOT(ISNUMBER(K11)),"|pending tonnage","") | AG11: =IFERROR(_xlfn.XLOOKUP(A11,'product map'!$A$14:$A$36,'product map'!$C$14:$C$36),"?") | AH11: =IFERROR((Z11*0.000000947817)/_xlfn.XLOOKUP(AG11,'energy base (MECS)'!$K$4:$K$9,'energy base (MECS)'!$F$4:$F$9),0) | AI11: =IFERROR((AA11*0.000000947817)/_xlfn.XLOOKUP(AG11,'energy base (MECS)'!$K$4:$K$9,'energy base (MECS)'!$I$4:$I$9),0) | AJ11: =MAX(0.3*ABS(AK11),0.000001) | AK11: =IF(ISNUMBER(T11),T11,0) | AL11: =IFERROR(_xlfn.XLOOKUP(AG11,'BCoISC-WACCbI'!$C$2:$C$26,'BCoISC-WACCbI'!$B$2:$B$26)+$AE$4,0.1) | AM11: =IF(P11>0,L11/P11/0.947817,0) | AN11: =IF(AND(P11>0,ISNUMBER(K11)),L11*K11*1000000*E11,0)
A12: ='Kermeli Data'!A19 | B12: ='Kermeli Data'!B19 | C12: ='Kermeli Data'!P19 | D12: =IF(C12="2 whr","whr",IF(C12="3 proc","process","EXCLUDED")) | E12: ='Kermeli Data'!E19 | F12: ='Kermeli Data'!F19 | G12: ='Kermeli Data'!G19 | H12: ='Kermeli Data'!I19 | I12: ='Kermeli Data'!J19 | J12: ='Kermeli Data'!K19 | K12: =IFERROR(_xlfn.XLOOKUP(A12,'product map'!$A$14:$A$36,'product map'!$G$14:$G$36),"pending") | L12: =H12*cpi!$B$12*cpi!$B$10 | M12: =J12*cpi!$B$12*cpi!$B$10 | N12: =IF(I12>0,AL12/(1-(1+AL12)^-I12),"") | O12: =L12*N12+M12 | P12: =MAX(F12,0)+MAX(G12,0) | Q12: =IF(P12>0,MAX(F12,0)/P12,0) | R12: =IF(P12>0,MAX(G12,0)/P12,0) | S12: =IF(P12>0,O12/P12,"") | T12: =IF(P12>0,S12/$AE$3,"") | U12: =IF(AND(P12>0,Q12>0),T12,"") | V12: =IF(AND(P12>0,R12>0),T12,"") | W12: =IF(I12>0,$AE$2/(1-(1+$AE$2)^-I12),"") | X12: =L12*W12+M12 | Y12: =IF(P12>0,(X12/P12)/$AE$3,"") | Z12: =IF(AND(ISNUMBER(K12),Q12>0),MAX(F12,0)*K12*1000000*E12,"pending") | AA12: =IF(AND(ISNUMBER(K12),R12>0),MAX(G12,0)*K12*1000000*E12,"pending") | AB12: =IF(AND(ISNUMBER(S12),S12<0),"NEG-CCE","")&IF(NOT(ISNUMBER(K12)),"|pending tonnage","") | AG12: =IFERROR(_xlfn.XLOOKUP(A12,'product map'!$A$14:$A$36,'product map'!$C$14:$C$36),"?") | AH12: =IFERROR((Z12*0.000000947817)/_xlfn.XLOOKUP(AG12,'energy base (MECS)'!$K$4:$K$9,'energy base (MECS)'!$F$4:$F$9),0) | AI12: =IFERROR((AA12*0.000000947817)/_xlfn.XLOOKUP(AG12,'energy base (MECS)'!$K$4:$K$9,'energy base (MECS)'!$I$4:$I$9),0) | AJ12: =MAX(0.3*ABS(AK12),0.000001) | AK12: =IF(ISNUMBER(T12),T12,0) | AL12: =IFERROR(_xlfn.XLOOKUP(AG12,'BCoISC-WACCbI'!$C$2:$C$26,'BCoISC-WACCbI'!$B$2:$B$26)+$AE$4,0.1) | AM12: =IF(P12>0,L12/P12/0.947817,0) | AN12: =IF(AND(P12>0,ISNUMBER(K12)),L12*K12*1000000*E12,0)
A13: ='Kermeli Data'!A20 | B13: ='Kermeli Data'!B20 | C13: ='Kermeli Data'!P20 | D13: =IF(C13="2 whr","whr",IF(C13="3 proc","process","EXCLUDED")) | E13: ='Kermeli Data'!E20 | F13: ='Kermeli Data'!F20 | G13: ='Kermeli Data'!G20 | H13: ='Kermeli Data'!I20 | I13: ='Kermeli Data'!J20 | J13: ='Kermeli Data'!K20 | K13: =IFERROR(_xlfn.XLOOKUP(A13,'product map'!$A$14:$A$36,'product map'!$G$14:$G$36),"pending") | L13: =H13*cpi!$B$12*cpi!$B$10 | M13: =J13*cpi!$B$12*cpi!$B$10 | N13: =IF(I13>0,AL13/(1-(1+AL13)^-I13),"") | O13: =L13*N13+M13 | P13: =MAX(F13,0)+MAX(G13,0) | Q13: =IF(P13>0,MAX(F13,0)/P13,0) | R13: =IF(P13>0,MAX(G13,0)/P13,0) | S13: =IF(P13>0,O13/P13,"") | T13: =IF(P13>0,S13/$AE$3,"") | U13: =IF(AND(P13>0,Q13>0),T13,"") | V13: =IF(AND(P13>0,R13>0),T13,"") | W13: =IF(I13>0,$AE$2/(1-(1+$AE$2)^-I13),"") | X13: =L13*W13+M13 | Y13: =IF(P13>0,(X13/P13)/$AE$3,"") | Z13: =IF(AND(ISNUMBER(K13),Q13>0),MAX(F13,0)*K13*1000000*E13,"pending") | AA13: =IF(AND(ISNUMBER(K13),R13>0),MAX(G13,0)*K13*1000000*E13,"pending") | AB13: =IF(AND(ISNUMBER(S13),S13<0),"NEG-CCE","")&IF(NOT(ISNUMBER(K13)),"|pending tonnage","") | AG13: =IFERROR(_xlfn.XLOOKUP(A13,'product map'!$A$14:$A$36,'product map'!$C$14:$C$36),"?") | AH13: =IFERROR((Z13*0.000000947817)/_xlfn.XLOOKUP(AG13,'energy base (MECS)'!$K$4:$K$9,'energy base (MECS)'!$F$4:$F$9),0) | AI13: =IFERROR((AA13*0.000000947817)/_xlfn.XLOOKUP(AG13,'energy base (MECS)'!$K$4:$K$9,'energy base (MECS)'!$I$4:$I$9),0) | AJ13: =MAX(0.3*ABS(AK13),0.000001) | AK13: =IF(ISNUMBER(T13),T13,0) | AL13: =IFERROR(_xlfn.XLOOKUP(AG13,'BCoISC-WACCbI'!$C$2:$C$26,'BCoISC-WACCbI'!$B$2:$B$26)+$AE$4,0.1) | AM13: =IF(P13>0,L13/P13/0.947817,0) | AN13: =IF(AND(P13>0,ISNUMBER(K13)),L13*K13*1000000*E13,0)
A14: ='Kermeli Data'!A21 | B14: ='Kermeli Data'!B21 | C14: ='Kermeli Data'!P21 | D14: =IF(C14="2 whr","whr",IF(C14="3 proc","process","EXCLUDED")) | E14: ='Kermeli Data'!E21 | F14: ='Kermeli Data'!F21 | G14: ='Kermeli Data'!G21 | H14: ='Kermeli Data'!I21 | I14: ='Kermeli Data'!J21 | J14: ='Kermeli Data'!K21 | K14: =IFERROR(_xlfn.XLOOKUP(A14,'product map'!$A$14:$A$36,'product map'!$G$14:$G$36),"pending") | L14: =H14*cpi!$B$12*cpi!$B$10 | M14: =J14*cpi!$B$12*cpi!$B$10 | N14: =IF(I14>0,AL14/(1-(1+AL14)^-I14),"") | O14: =L14*N14+M14 | P14: =MAX(F14,0)+MAX(G14,0) | Q14: =IF(P14>0,MAX(F14,0)/P14,0) | R14: =IF(P14>0,MAX(G14,0)/P14,0) | S14: =IF(P14>0,O14/P14,"") | T14: =IF(P14>0,S14/$AE$3,"") | U14: =IF(AND(P14>0,Q14>0),T14,"") | V14: =IF(AND(P14>0,R14>0),T14,"") | W14: =IF(I14>0,$AE$2/(1-(1+$AE$2)^-I14),"") | X14: =L14*W14+M14 | Y14: =IF(P14>0,(X14/P14)/$AE$3,"") | Z14: =IF(AND(ISNUMBER(K14),Q14>0),MAX(F14,0)*K14*1000000*E14,"pending") | AA14: =IF(AND(ISNUMBER(K14),R14>0),MAX(G14,0)*K14*1000000*E14,"pending") | AB14: =IF(AND(ISNUMBER(S14),S14<0),"NEG-CCE","")&IF(NOT(ISNUMBER(K14)),"|pending tonnage","") | AG14: =IFERROR(_xlfn.XLOOKUP(A14,'product map'!$A$14:$A$36,'product map'!$C$14:$C$36),"?") | AH14: =IFERROR((Z14*0.000000947817)/_xlfn.XLOOKUP(AG14,'energy base (MECS)'!$K$4:$K$9,'energy base (MECS)'!$F$4:$F$9),0) | AI14: =IFERROR((AA14*0.000000947817)/_xlfn.XLOOKUP(AG14,'energy base (MECS)'!$K$4:$K$9,'energy base (MECS)'!$I$4:$I$9),0) | AJ14: =MAX(0.3*ABS(AK14),0.000001) | AK14: =IF(ISNUMBER(T14),T14,0) | AL14: =IFERROR(_xlfn.XLOOKUP(AG14,'BCoISC-WACCbI'!$C$2:$C$26,'BCoISC-WACCbI'!$B$2:$B$26)+$AE$4,0.1) | AM14: =IF(P14>0,L14/P14/0.947817,0) | AN14: =IF(AND(P14>0,ISNUMBER(K14)),L14*K14*1000000*E14,0)
A15: ='Kermeli Data'!A22 | B15: ='Kermeli Data'!B22 | C15: ='Kermeli Data'!P22 | D15: =IF(C15="2 whr","whr",IF(C15="3 proc","process","EXCLUDED")) | E15: ='Kermeli Data'!E22 | F15: ='Kermeli Data'!F22 | G15: ='Kermeli Data'!G22 | H15: ='Kermeli Data'!I22 | I15: ='Kermeli Data'!J22 | J15: ='Kermeli Data'!K22 | K15: =IFERROR(_xlfn.XLOOKUP(A15,'product map'!$A$14:$A$36,'product map'!$G$14:$G$36),"pending") | L15: =H15*cpi!$B$12*cpi!$B$10 | M15: =J15*cpi!$B$12*cpi!$B$10 | N15: =IF(I15>0,AL15/(1-(1+AL15)^-I15),"") | O15: =L15*N15+M15 | P15: =MAX(F15,0)+MAX(G15,0) | Q15: =IF(P15>0,MAX(F15,0)/P15,0) | R15: =IF(P15>0,MAX(G15,0)/P15,0) | S15: =IF(P15>0,O15/P15,"") | T15: =IF(P15>0,S15/$AE$3,"") | U15: =IF(AND(P15>0,Q15>0),T15,"") | V15: =IF(AND(P15>0,R15>0),T15,"") | W15: =IF(I15>0,$AE$2/(1-(1+$AE$2)^-I15),"") | X15: =L15*W15+M15 | Y15: =IF(P15>0,(X15/P15)/$AE$3,"") | Z15: =IF(AND(ISNUMBER(K15),Q15>0),MAX(F15,0)*K15*1000000*E15,"pending") | AA15: =IF(AND(ISNUMBER(K15),R15>0),MAX(G15,0)*K15*1000000*E15,"pending") | AB15: =IF(AND(ISNUMBER(S15),S15<0),"NEG-CCE","")&IF(NOT(ISNUMBER(K15)),"|pending tonnage","") | AG15: =IFERROR(_xlfn.XLOOKUP(A15,'product map'!$A$14:$A$36,'product map'!$C$14:$C$36),"?") | AH15: =IFERROR((Z15*0.000000947817)/_xlfn.XLOOKUP(AG15,'energy base (MECS)'!$K$4:$K$9,'energy base (MECS)'!$F$4:$F$9),0) | AI15: =IFERROR((AA15*0.000000947817)/_xlfn.XLOOKUP(AG15,'energy base (MECS)'!$K$4:$K$9,'energy base (MECS)'!$I$4:$I$9),0) | AJ15: =MAX(0.3*ABS(AK15),0.000001) | AK15: =IF(ISNUMBER(T15),T15,0) | AL15: =IFERROR(_xlfn.XLOOKUP(AG15,'BCoISC-WACCbI'!$C$2:$C$26,'BCoISC-WACCbI'!$B$2:$B$26)+$AE$4,0.1) | AM15: =IF(P15>0,L15/P15/0.947817,0) | AN15: =IF(AND(P15>0,ISNUMBER(K15)),L15*K15*1000000*E15,0)
A16: ='Kermeli Data'!A23 | B16: ='Kermeli Data'!B23 | C16: ='Kermeli Data'!P23 | D16: =IF(C16="2 whr","whr",IF(C16="3 proc","process","EXCLUDED")) | E16: ='Kermeli Data'!E23 | F16: ='Kermeli Data'!F23 | G16: ='Kermeli Data'!G23 | H16: ='Kermeli Data'!I23 | I16: ='Kermeli Data'!J23 | J16: ='Kermeli Data'!K23 | K16: =IFERROR(_xlfn.XLOOKUP(A16,'product map'!$A$14:$A$36,'product map'!$G$14:$G$36),"pending") | L16: =H16*cpi!$B$12*cpi!$B$10 | M16: =J16*cpi!$B$12*cpi!$B$10 | N16: =IF(I16>0,AL16/(1-(1+AL16)^-I16),"") | O16: =L16*N16+M16 | P16: =MAX(F16,0)+MAX(G16,0) | Q16: =IF(P16>0,MAX(F16,0)/P16,0) | R16: =IF(P16>0,MAX(G16,0)/P16,0) | S16: =IF(P16>0,O16/P16,"") | T16: =IF(P16>0,S16/$AE$3,"") | U16: =IF(AND(P16>0,Q16>0),T16,"") | V16: =IF(AND(P16>0,R16>0),T16,"") | W16: =IF(I16>0,$AE$2/(1-(1+$AE$2)^-I16),"") | X16: =L16*W16+M16 | Y16: =IF(P16>0,(X16/P16)/$AE$3,"") | Z16: =IF(AND(ISNUMBER(K16),Q16>0),MAX(F16,0)*K16*1000000*E16,"pending") | AA16: =IF(AND(ISNUMBER(K16),R16>0),MAX(G16,0)*K16*1000000*E16,"pending") | AB16: =IF(AND(ISNUMBER(S16),S16<0),"NEG-CCE","")&IF(NOT(ISNUMBER(K16)),"|pending tonnage","") | AG16: =IFERROR(_xlfn.XLOOKUP(A16,'product map'!$A$14:$A$36,'product map'!$C$14:$C$36),"?") | AH16: =IFERROR((Z16*0.000000947817)/_xlfn.XLOOKUP(AG16,'energy base (MECS)'!$K$4:$K$9,'energy base (MECS)'!$F$4:$F$9),0) | AI16: =IFERROR((AA16*0.000000947817)/_xlfn.XLOOKUP(AG16,'energy base (MECS)'!$K$4:$K$9,'energy base (MECS)'!$I$4:$I$9),0) | AJ16: =MAX(0.3*ABS(AK16),0.000001) | AK16: =IF(ISNUMBER(T16),T16,0) | AL16: =IFERROR(_xlfn.XLOOKUP(AG16,'BCoISC-WACCbI'!$C$2:$C$26,'BCoISC-WACCbI'!$B$2:$B$26)+$AE$4,0.1) | AM16: =IF(P16>0,L16/P16/0.947817,0) | AN16: =IF(AND(P16>0,ISNUMBER(K16)),L16*K16*1000000*E16,0)
... A167: ='Kermeli Data'!A174 | B167: ='Kermeli Data'!B174 | C167: ='Kermeli Data'!P174 | D167: =IF(C167="2 whr","whr",IF(C167="3 proc","process","EXCLUDED")) | E167: ='Kermeli Data'!E174 | F167: ='Kermeli Data'!F174 | G167: ='Kermeli Data'!G174 | H167: ='Kermeli Data'!I174 | I167: ='Kermeli Data'!J174 | J167: ='Kermeli Data'!K174 | K167: =IFERROR(_xlfn.XLOOKUP(A167,'product map'!$A$14:$A$36,'product map'!$G$14:$G$36),"pending") | L167: =H167*cpi!$B$12*cpi!$B$10 | M167: =J167*cpi!$B$12*cpi!$B$10 | N167: =IF(I167>0,AL167/(1-(1+AL167)^-I167),"") | O167: =L167*N167+M167 | P167: =MAX(F167,0)+MAX(G167,0) | Q167: =IF(P167>0,MAX(F167,0)/P167,0) | R167: =IF(P167>0,MAX(G167,0)/P167,0) | S167: =IF(P167>0,O167/P167,"") | T167: =IF(P167>0,S167/$AE$3,"") | U167: =IF(AND(P167>0,Q167>0),T167,"") | V167: =IF(AND(P167>0,R167>0),T167,"") | W167: =IF(I167>0,$AE$2/(1-(1+$AE$2)^-I167),"") | X167: =L167*W167+M167 | Y167: =IF(P167>0,(X167/P167)/$AE$3,"") | Z167: =IF(AND(ISNUMBER(K167),Q167>0),MAX(F167,0)*K167*1000000*E167,"pending") | AA167: =IF(AND(ISNUMBER(K167),R167>0),MAX(G167,0)*K167*1000000*E167,"pending") | AB167: =IF(AND(ISNUMBER(S167),S167<0),"NEG-CCE","")&IF(NOT(ISNUMBER(K167)),"|pending tonnage","") | AG167: =IFERROR(_xlfn.XLOOKUP(A167,'product map'!$A$14:$A$36,'product map'!$C$14:$C$36),"?") | AH167: =IFERROR((Z167*0.000000947817)/_xlfn.XLOOKUP(AG167,'energy base (MECS)'!$K$4:$K$9,'energy base (MECS)'!$F$4:$F$9),0) | AI167: =IFERROR((AA167*0.000000947817)/_xlfn.XLOOKUP(AG167,'energy base (MECS)'!$K$4:$K$9,'energy base (MECS)'!$I$4:$I$9),0) | AJ167: =MAX(0.3*ABS(AK167),0.000001) | AK167: =IF(ISNUMBER(T167),T167,0) | AL167: =IFERROR(_xlfn.XLOOKUP(AG167,'BCoISC-WACCbI'!$C$2:$C$26,'BCoISC-WACCbI'!$B$2:$B$26)+$AE$4,0.1) | AM167: =IF(P167>0,L167/P167/0.947817,0) | AN167: =IF(AND(P167>0,ISNUMBER(K167)),L167*K167*1000000*E167,0)

Sheet fuel-whr
A1: fuel-whr — cumulative % reduction (system WHR, fuel carrier). Rows=canonical WHRPbI industries; cols=CCE bins ($/MMBtu, 2012$). Uncovered industries: Bianchi fill @ assumed cost.
A3: Industry | B3: code | C3: Bianchi pot. | D3: covered | E3: 0 | F3: 0.25 | G3: 0.5 | H3: 0.75 | I3: 1 | J3: 1.25 | K3: 1.5 | L3: 1.75 | M3: 2 | N3: 2.25 | O3: 2.5 | P3: 2.75 | Q3: 3 | R3: 3.25 | S3: 3.5 | T3: 3.75 | U3: 4 | V3: 4.25 | W3: 4.5 | X3: 4.75 | Y3: 5 | Z3: 5.25 | AA3: 5.5 | AB3: 5.75 | AC3: 6 | AD3: 6.25 | AE3: 6.5 | AF3: 6.75 | AG3: 7 | AH3: 7.25 | AI3: 7.5 | AJ3: 7.75 | AK3: 8 | AL3: 8.25 | AM3: 8.5 | AN3: 8.75 | AO3: 9 | AP3: 9.25 | AQ3: 9.5 | AR3: 9.75 | AS3: 10 | AT3: 10.25 | AU3: 10.5 | AV3: 10.75 | AW3: 11 | AX3: 11.25 | AY3: 11.5 | AZ3: 11.75 | BA3: 12 | BB3: 12.25 | BC3: 12.5 | BD3: 12.75 | BE3: 13 | BF3: 13.25 | BG3: 13.5 | BH3: 13.75 | BI3: 14 | BJ3: 14.25 | BK3: 14.5 | BL3: 14.75 | BM3: 15 | BN3: 15.25 | BO3: 15.5 | BP3: 15.75 | BQ3: 16 | BR3: 16.25 | BS3: 16.5 | BT3: 16.75 | BU3: 17 | BV3: 17.25 | BW3: 17.5 | BX3: 17.75 | BY3: 18 | BZ3: 18.25 | CA3: 18.5 | CB3: 18.75 | CC3: 19 | CD3: 19.25 | CE3: 19.5 | CF3: 19.75 | CG3: 20 | CH3: 99999 | CJ3: capture(meas) | CK3: b<100 | CL3: b100-200 | CM3: b200-500 | CN3: b500-1000 | CO3: b>1000 | CP3: adj LT+MT target | CQ3: adj HT target | CR3: resid LT+MT | CS3: resid HT | CT3: WACC | CU3: mu econ | CV3: mu recup | CW3: total fill
A4: =WHRPbI!A2 | B4: 01T03 | C4: =WHRPbI!B2 | D4: =ISNUMBER(MATCH($B4,'energy base (MECS)'!$K$4:$K$9,0)) | E4: {=IF($D4,SUMPRODUCT((economics!$AG$2:$AG$167=$B4)*(economics!$D$2:$D$167="whr")*economics!$AH$2:$AH$167*_xlfn.NORM.DIST(E$3,economics!$AK$2:$AK$167,economics!$AJ$2:$AJ$167,TRUE))+$CR4*_xlfn.NORM.DIST(E$3,$CU4,0.3*$CU4,TRUE)+$CS4*_xlfn.NORM.DIST(E$3,$CV4,0.3*$CV4,TRUE),$CW4*_xlfn.NORM.DIST(E$3,'energy base (MECS)'!$F$11,0.3*'energy base (MECS)'!$F$11,TRUE))} | F4: {=IF($D4,SUMPRODUCT((economics!$AG$2:$AG$167=$B4)*(economics!$D$2:$D$167="whr")*economics!$AH$2:$AH$167*_xlfn.NORM.DIST(F$3,economics!$AK$2:$AK$167,economics!$AJ$2:$AJ$167,TRUE))+$CR4*_xlfn.NORM.DIST(F$3,$CU4,0.3*$CU4,TRUE)+$CS4*_xlfn.NORM.DIST(F$3,$CV4,0.3*$CV4,TRUE),$CW4*_xlfn.NORM.DIST(F$3,'energy base (MECS)'!$F$11,0.3*'energy base (MECS)'!$F$11,TRUE))} | G4: {=IF($D4,SUMPRODUCT((economics!$AG$2:$AG$167=$B4)*(economics!$D$2:$D$167="whr")*economics!$AH$2:$AH$167*_xlfn.NORM.DIST(G$3,economics!$AK$2:$AK$167,economics!$AJ$2:$AJ$167,TRUE))+$CR4*_xlfn.NORM.DIST(G$3,$CU4,0.3*$CU4,TRUE)+$CS4*_xlfn.NORM.DIST(G$3,$CV4,0.3*$CV4,TRUE),$CW4*_xlfn.NORM.DIST(G$3,'energy base (MECS)'!$F$11,0.3*'energy base (MECS)'!$F$11,TRUE))} | H4: {=IF($D4,SUMPRODUCT((economics!$AG$2:$AG$167=$B4)*(economics!$D$2:$D$167="whr")*economics!$AH$2:$AH$167*_xlfn.NORM.DIST(H$3,economics!$AK$2:$AK$167,economics!$AJ$2:$AJ$167,TRUE))+$CR4*_xlfn.NORM.DIST(H$3,$CU4,0.3*$CU4,TRUE)+$CS4*_xlfn.NORM.DIST(H$3,$CV4,0.3*$CV4,TRUE),$CW4*_xlfn.NORM.DIST(H$3,'energy base (MECS)'!$F$11,0.3*'energy base (MECS)'!$F$11,TRUE))} | I4: {=IF($D4,SUMPRODUCT((economics!$AG$2:$AG$167=$B4)*(economics!$D$2:$D$167="whr")*economics!$AH$2:$AH$167*_xlfn.NORM.DIST(I$3,economics!$AK$2:$AK$167,economics!$AJ$2:$AJ$167,TRUE))+$CR4*_xlfn.NORM.DIST(I$3,$CU4,0.3*$CU4,TRUE)+$CS4*_xlfn.NORM.DIST(I$3,$CV4,0.3*$CV4,TRUE),$CW4*_xlfn.NORM.DIST(I$3,'energy base (MECS)'!$F$11,0.3*'energy base (MECS)'!$F$11,TRUE))} | J4: {=IF($D4,SUMPRODUCT((economics!$AG$2:$AG$167=$B4)*(economics!$D$2:$D$167="whr")*economics!$AH$2:$AH$167*_xlfn.NORM.DIST(J$3,economics!$AK$2:$AK$167,economics!$AJ$2:$AJ$167,TRUE))+$CR4*_xlfn.NORM.DIST(J$3,$CU4,0.3*$CU4,TRUE)+$CS4*_xlfn.NORM.DIST(J$3,$CV4,0.3*$CV4,TRUE),$CW4*_xlfn.NORM.DIST(J$3,'energy base (MECS)'!$F$11,0.3*'energy base (MECS)'!$F$11,TRUE))} | K4: {=IF($D4,SUMPRODUCT((economics!$AG$2:$AG$167=$B4)*(economics!$D$2:$D$167="whr")*economics!$AH$2:$AH$167*_xlfn.NORM.DIST(K$3,economics!$AK$2:$AK$167,economics!$AJ$2:$AJ$167,TRUE))+$CR4*_xlfn.NORM.DIST(K$3,$CU4,0.3*$CU4,TRUE)+$CS4*_xlfn.NORM.DIST(K$3,$CV4,0.3*$CV4,TRUE),$CW4*_xlfn.NORM.DIST(K$3,'energy base (MECS)'!$F$11,0.3*'energy base (MECS)'!$F$11,TRUE))} | L4: {=IF($D4,SUMPRODUCT((economics!$AG$2:$AG$167=$B4)*(economics!$D$2:$D$167="whr")*economics!$AH$2:$AH$167*_xlfn.NORM.DIST(L$3,economics!$AK$2:$AK$167,economics!$AJ$2:$AJ$167,TRUE))+$CR4*_xlfn.NORM.DIST(L$3,$CU4,0.3*$CU4,TRUE)+$CS4*_xlfn.NORM.DIST(L$3,$CV4,0.3*$CV4,TRUE),$CW4*_xlfn.NORM.DIST(L$3,'energy base (MECS)'!$F$11,0.3*'energy base (MECS)'!$F$11,TRUE))} | ... CH4: {=IF($D4,SUMPRODUCT((economics!$AG$2:$AG$167=$B4)*(economics!$D$2:$D$167="whr")*economics!$AH$2:$AH$167*_xlfn.NORM.DIST(CH$3,economics!$AK$2:$AK$167,economics!$AJ$2:$AJ$167,TRUE))+$CR4*_xlfn.NORM.DIST(CH$3,$CU4,0.3*$CU4,TRUE)+$CS4*_xlfn.NORM.DIST(CH$3,$CV4,0.3*$CV4,TRUE),$CW4*_xlfn.NORM.DIST(CH$3,'energy base (MECS)'!$F$11,0.3*'energy base (MECS)'!$F$11,TRUE))} | CJ4: {=SUMPRODUCT((economics!$AG$2:$AG$167=$B4)*(economics!$D$2:$D$167="whr")*economics!$AH$2:$AH$167)} | CK4: ='indst heat consumption'!D4 | CL4: ='indst heat consumption'!E4 | CM4: ='indst heat consumption'!F4 | CN4: ='indst heat consumption'!G4 | CO4: ='indst heat consumption'!H4 | CP4: =$C4*(CK4*summary!$B$94+CL4*summary!$C$94+CM4*summary!$D$94) | CQ4: =$C4*(CN4*summary!$E$94+CO4*summary!$F$94) | CR4: =IF(CP4+CQ4>0,CP4*MAX(0,CP4+CQ4-CJ4)/(CP4+CQ4),0) | CS4: =IF(CP4+CQ4>0,CQ4*MAX(0,CP4+CQ4-CJ4)/(CP4+CQ4),0) | CT4: =IFERROR(_xlfn.XLOOKUP($B4,'BCoISC-WACCbI'!$C$2:$C$26,'BCoISC-WACCbI'!$B$2:$B$26)+economics!$AE$4,0.1) | CU4: =(summary!$C$7*(CT4/(1-(1+CT4)^-summary!$D$7))+summary!$C$7*summary!$E$7)/(summary!$F$7*3412/1000000) | CV4: =(summary!$C$6*(CT4/(1-(1+CT4)^-summary!$D$6))+summary!$C$6*summary!$E$6)/(summary!$F$6*3412/1000000) | CW4: =CR4+CS4
A5: =WHRPbI!A3 | B5: 5 | C5: =WHRPbI!B3 | D5: =ISNUMBER(MATCH($B5,'energy base (MECS)'!$K$4:$K$9,0)) | E5: {=IF($D5,SUMPRODUCT((economics!$AG$2:$AG$167=$B5)*(economics!$D$2:$D$167="whr")*economics!$AH$2:$AH$167*_xlfn.NORM.DIST(E$3,economics!$AK$2:$AK$167,economics!$AJ$2:$AJ$167,TRUE))+$CR5*_xlfn.NORM.DIST(E$3,$CU5,0.3*$CU5,TRUE)+$CS5*_xlfn.NORM.DIST(E$3,$CV5,0.3*$CV5,TRUE),$CW5*_xlfn.NORM.DIST(E$3,'energy base (MECS)'!$F$11,0.3*'energy base (MECS)'!$F$11,TRUE))} | F5: {=IF($D5,SUMPRODUCT((economics!$AG$2:$AG$167=$B5)*(economics!$D$2:$D$167="whr")*economics!$AH$2:$AH$167*_xlfn.NORM.DIST(F$3,economics!$AK$2:$AK$167,economics!$AJ$2:$AJ$167,TRUE))+$CR5*_xlfn.NORM.DIST(F$3,$CU5,0.3*$CU5,TRUE)+$CS5*_xlfn.NORM.DIST(F$3,$CV5,0.3*$CV5,TRUE),$CW5*_xlfn.NORM.DIST(F$3,'energy base (MECS)'!$F$11,0.3*'energy base (MECS)'!$F$11,TRUE))} | G5: {=IF($D5,SUMPRODUCT((economics!$AG$2:$AG$167=$B5)*(economics!$D$2:$D$167="whr")*economics!$AH$2:$AH$167*_xlfn.NORM.DIST(G$3,economics!$AK$2:$AK$167,economics!$AJ$2:$AJ$167,TRUE))+$CR5*_xlfn.NORM.DIST(G$3,$CU5,0.3*$CU5,TRUE)+$CS5*_xlfn.NORM.DIST(G$3,$CV5,0.3*$CV5,TRUE),$CW5*_xlfn.NORM.DIST(G$3,'energy base (MECS)'!$F$11,0.3*'energy base (MECS)'!$F$11,TRUE))} | H5: {=IF($D5,SUMPRODUCT((economics!$AG$2:$AG$167=$B5)*(economics!$D$2:$D$167="whr")*economics!$AH$2:$AH$167*_xlfn.NORM.DIST(H$3,economics!$AK$2:$AK$167,economics!$AJ$2:$AJ$167,TRUE))+$CR5*_xlfn.NORM.DIST(H$3,$CU5,0.3*$CU5,TRUE)+$CS5*_xlfn.NORM.DIST(H$3,$CV5,0.3*$CV5,TRUE),$CW5*_xlfn.NORM.DIST(H$3,'energy base (MECS)'!$F$11,0.3*'energy base (MECS)'!$F$11,TRUE))} | I5: {=IF($D5,SUMPRODUCT((economics!$AG$2:$AG$167=$B5)*(economics!$D$2:$D$167="whr")*economics!$AH$2:$AH$167*_xlfn.NORM.DIST(I$3,economics!$AK$2:$AK$167,economics!$AJ$2:$AJ$167,TRUE))+$CR5*_xlfn.NORM.DIST(I$3,$CU5,0.3*$CU5,TRUE)+$CS5*_xlfn.NORM.DIST(I$3,$CV5,0.3*$CV5,TRUE),$CW5*_xlfn.NORM.DIST(I$3,'energy base (MECS)'!$F$11,0.3*'energy base (MECS)'!$F$11,TRUE))} | J5: {=IF($D5,SUMPRODUCT((economics!$AG$2:$AG$167=$B5)*(economics!$D$2:$D$167="whr")*economics!$AH$2:$AH$167*_xlfn.NORM.DIST(J$3,economics!$AK$2:$AK$167,economics!$AJ$2:$AJ$167,TRUE))+$CR5*_xlfn.NORM.DIST(J$3,$CU5,0.3*$CU5,TRUE)+$CS5*_xlfn.NORM.DIST(J$3,$CV5,0.3*$CV5,TRUE),$CW5*_xlfn.NORM.DIST(J$3,'energy base (MECS)'!$F$11,0.3*'energy base (MECS)'!$F$11,TRUE))} | K5: {=IF($D5,SUMPRODUCT((economics!$AG$2:$AG$167=$B5)*(economics!$D$2:$D$167="whr")*economics!$AH$2:$AH$167*_xlfn.NORM.DIST(K$3,economics!$AK$2:$AK$167,economics!$AJ$2:$AJ$167,TRUE))+$CR5*_xlfn.NORM.DIST(K$3,$CU5,0.3*$CU5,TRUE)+$CS5*_xlfn.NORM.DIST(K$3,$CV5,0.3*$CV5,TRUE),$CW5*_xlfn.NORM.DIST(K$3,'energy base (MECS)'!$F$11,0.3*'energy base (MECS)'!$F$11,TRUE))} | L5: {=IF($D5,SUMPRODUCT((economics!$AG$2:$AG$167=$B5)*(economics!$D$2:$D$167="whr")*economics!$AH$2:$AH$167*_xlfn.NORM.DIST(L$3,economics!$AK$2:$AK$167,economics!$AJ$2:$AJ$167,TRUE))+$CR5*_xlfn.NORM.DIST(L$3,$CU5,0.3*$CU5,TRUE)+$CS5*_xlfn.NORM.DIST(L$3,$CV5,0.3*$CV5,TRUE),$CW5*_xlfn.NORM.DIST(L$3,'energy base (MECS)'!$F$11,0.3*'energy base (MECS)'!$F$11,TRUE))} | ... CH5: {=IF($D5,SUMPRODUCT((economics!$AG$2:$AG$167=$B5)*(economics!$D$2:$D$167="whr")*economics!$AH$2:$AH$167*_xlfn.NORM.DIST(CH$3,economics!$AK$2:$AK$167,economics!$AJ$2:$AJ$167,TRUE))+$CR5*_xlfn.NORM.DIST(CH$3,$CU5,0.3*$CU5,TRUE)+$CS5*_xlfn.NORM.DIST(CH$3,$CV5,0.3*$CV5,TRUE),$CW5*_xlfn.NORM.DIST(CH$3,'energy base (MECS)'!$F$11,0.3*'energy base (MECS)'!$F$11,TRUE))} | CJ5: {=SUMPRODUCT((economics!$AG$2:$AG$167=$B5)*(economics!$D$2:$D$167="whr")*economics!$AH$2:$AH$167)} | CK5: ='indst heat consumption'!D5 | CL5: ='indst heat consumption'!E5 | CM5: ='indst heat consumption'!F5 | CN5: ='indst heat consumption'!G5 | CO5: ='indst heat consumption'!H5 | CP5: =$C5*(CK5*summary!$B$94+CL5*summary!$C$94+CM5*summary!$D$94) | CQ5: =$C5*(CN5*summary!$E$94+CO5*summary!$F$94) | CR5: =IF(CP5+CQ5>0,CP5*MAX(0,CP5+CQ5-CJ5)/(CP5+CQ5),0) | CS5: =IF(CP5+CQ5>0,CQ5*MAX(0,CP5+CQ5-CJ5)/(CP5+CQ5),0) | CT5: =IFERROR(_xlfn.XLOOKUP($B5,'BCoISC-WACCbI'!$C$2:$C$26,'BCoISC-WACCbI'!$B$2:$B$26)+economics!$AE$4,0.1) | CU5: =(summary!$C$7*(CT5/(1-(1+CT5)^-summary!$D$7))+summary!$C$7*summary!$E$7)/(summary!$F$7*3412/1000000) | CV5: =(summary!$C$6*(CT5/(1-(1+CT5)^-summary!$D$6))+summary!$C$6*summary!$E$6)/(summary!$F$6*3412/1000000) | CW5: =CR5+CS5
A6: =WHRPbI!A4 | B6: 6 | C6: =WHRPbI!B4 | D6: =ISNUMBER(MATCH($B6,'energy base (MECS)'!$K$4:$K$9,0)) | E6: {=IF($D6,SUMPRODUCT((economics!$AG$2:$AG$167=$B6)*(economics!$D$2:$D$167="whr")*economics!$AH$2:$AH$167*_xlfn.NORM.DIST(E$3,economics!$AK$2:$AK$167,economics!$AJ$2:$AJ$167,TRUE))+$CR6*_xlfn.NORM.DIST(E$3,$CU6,0.3*$CU6,TRUE)+$CS6*_xlfn.NORM.DIST(E$3,$CV6,0.3*$CV6,TRUE),$CW6*_xlfn.NORM.DIST(E$3,'energy base (MECS)'!$F$11,0.3*'energy base (MECS)'!$F$11,TRUE))} | F6: {=IF($D6,SUMPRODUCT((economics!$AG$2:$AG$167=$B6)*(economics!$D$2:$D$167="whr")*economics!$AH$2:$AH$167*_xlfn.NORM.DIST(F$3,economics!$AK$2:$AK$167,economics!$AJ$2:$AJ$167,TRUE))+$CR6*_xlfn.NORM.DIST(F$3,$CU6,0.3*$CU6,TRUE)+$CS6*_xlfn.NORM.DIST(F$3,$CV6,0.3*$CV6,TRUE),$CW6*_xlfn.NORM.DIST(F$3,'energy base (MECS)'!$F$11,0.3*'energy base (MECS)'!$F$11,TRUE))} | G6: {=IF($D6,SUMPRODUCT((economics!$AG$2:$AG$167=$B6)*(economics!$D$2:$D$167="whr")*economics!$AH$2:$AH$167*_xlfn.NORM.DIST(G$3,economics!$AK$2:$AK$167,economics!$AJ$2:$AJ$167,TRUE))+$CR6*_xlfn.NORM.DIST(G$3,$CU6,0.3*$CU6,TRUE)+$CS6*_xlfn.NORM.DIST(G$3,$CV6,0.3*$CV6,TRUE),$CW6*_xlfn.NORM.DIST(G$3,'energy base (MECS)'!$F$11,0.3*'energy base (MECS)'!$F$11,TRUE))} | H6: {=IF($D6,SUMPRODUCT((economics!$AG$2:$AG$167=$B6)*(economics!$D$2:$D$167="whr")*economics!$AH$2:$AH$167*_xlfn.NORM.DIST(H$3,economics!$AK$2:$AK$167,economics!$AJ$2:$AJ$167,TRUE))+$CR6*_xlfn.NORM.DIST(H$3,$CU6,0.3*$CU6,TRUE)+$CS6*_xlfn.NORM.DIST(H$3,$CV6,0.3*$CV6,TRUE),$CW6*_xlfn.NORM.DIST(H$3,'energy base (MECS)'!$F$11,0.3*'energy base (MECS)'!$F$11,TRUE))} | I6: {=IF($D6,SUMPRODUCT((economics!$AG$2:$AG$167=$B6)*(economics!$D$2:$D$167="whr")*economics!$AH$2:$AH$167*_xlfn.NORM.DIST(I$3,economics!$AK$2:$AK$167,economics!$AJ$2:$AJ$167,TRUE))+$CR6*_xlfn.NORM.DIST(I$3,$CU6,0.3*$CU6,TRUE)+$CS6*_xlfn.NORM.DIST(I$3,$CV6,0.3*$CV6,TRUE),$CW6*_xlfn.NORM.DIST(I$3,'energy base (MECS)'!$F$11,0.3*'energy base (MECS)'!$F$11,TRUE))} | J6: {=IF($D6,SUMPRODUCT((economics!$AG$2:$AG$167=$B6)*(economics!$D$2:$D$167="whr")*economics!$AH$2:$AH$167*_xlfn.NORM.DIST(J$3,economics!$AK$2:$AK$167,economics!$AJ$2:$AJ$167,TRUE))+$CR6*_xlfn.NORM.DIST(J$3,$CU6,0.3*$CU6,TRUE)+$CS6*_xlfn.NORM.DIST(J$3,$CV6,0.3*$CV6,TRUE),$CW6*_xlfn.NORM.DIST(J$3,'energy base (MECS)'!$F$11,0.3*'energy base (MECS)'!$F$11,TRUE))} | K6: {=IF($D6,SUMPRODUCT((economics!$AG$2:$AG$167=$B6)*(economics!$D$2:$D$167="whr")*economics!$AH$2:$AH$167*_xlfn.NORM.DIST(K$3,economics!$AK$2:$AK$167,economics!$AJ$2:$AJ$167,TRUE))+$CR6*_xlfn.NORM.DIST(K$3,$CU6,0.3*$CU6,TRUE)+$CS6*_xlfn.NORM.DIST(K$3,$CV6,0.3*$CV6,TRUE),$CW6*_xlfn.NORM.DIST(K$3,'energy base (MECS)'!$F$11,0.3*'energy base (MECS)'!$F$11,TRUE))} | L6: {=IF($D6,SUMPRODUCT((economics!$AG$2:$AG$167=$B6)*(economics!$D$2:$D$167="whr")*economics!$AH$2:$AH$167*_xlfn.NORM.DIST(L$3,economics!$AK$2:$AK$167,economics!$AJ$2:$AJ$167,TRUE))+$CR6*_xlfn.NORM.DIST(L$3,$CU6,0.3*$CU6,TRUE)+$CS6*_xlfn.NORM.DIST(L$3,$CV6,0.3*$CV6,TRUE),$CW6*_xlfn.NORM.DIST(L$3,'energy base (MECS)'!$F$11,0.3*'energy base (MECS)'!$F$11,TRUE))} | ... CH6: {=IF($D6,SUMPRODUCT((economics!$AG$2:$AG$167=$B6)*(economics!$D$2:$D$167="whr")*economics!$AH$2:$AH$167*_xlfn.NORM.DIST(CH$3,economics!$AK$2:$AK$167,economics!$AJ$2:$AJ$167,TRUE))+$CR6*_xlfn.NORM.DIST(CH$3,$CU6,0.3*$CU6,TRUE)+$CS6*_xlfn.NORM.DIST(CH$3,$CV6,0.3*$CV6,TRUE),$CW6*_xlfn.NORM.DIST(CH$3,'energy base (MECS)'!$F$11,0.3*'energy base (MECS)'!$F$11,TRUE))} | CJ6: {=SUMPRODUCT((economics!$AG$2:$AG$167=$B6)*(economics!$D$2:$D$167="whr")*economics!$AH$2:$AH$167)} | CK6: ='indst heat consumption'!D6 | CL6: ='indst heat consumption'!E6 | CM6: ='indst heat consumption'!F6 | CN6: ='indst heat consumption'!G6 | CO6: ='indst heat consumption'!H6 | CP6: =$C6*(CK6*summary!$B$94+CL6*summary!$C$94+CM6*summary!$D$94) | CQ6: =$C6*(CN6*summary!$E$94+CO6*summary!$F$94) | CR6: =IF(CP6+CQ6>0,CP6*MAX(0,CP6+CQ6-CJ6)/(CP6+CQ6),0) | CS6: =IF(CP6+CQ6>0,CQ6*MAX(0,CP6+CQ6-CJ6)/(CP6+CQ6),0) | CT6: =IFERROR(_xlfn.XLOOKUP($B6,'BCoISC-WACCbI'!$C$2:$C$26,'BCoISC-WACCbI'!$B$2:$B$26)+economics!$AE$4,0.1) | CU6: =(summary!$C$7*(CT6/(1-(1+CT6)^-summary!$D$7))+summary!$C$7*summary!$E$7)/(summary!$F$7*3412/1000000) | CV6: =(summary!$C$6*(CT6/(1-(1+CT6)^-summary!$D$6))+summary!$C$6*summary!$E$6)/(summary!$F$6*3412/1000000) | CW6: =CR6+CS6
A7: =WHRPbI!A5 | B7: 07T08 | C7: =WHRPbI!B5 | D7: =ISNUMBER(MATCH($B7,'energy base (MECS)'!$K$4:$K$9,0)) | E7: {=IF($D7,SUMPRODUCT((economics!$AG$2:$AG$167=$B7)*(economics!$D$2:$D$167="whr")*economics!$AH$2:$AH$167*_xlfn.NORM.DIST(E$3,economics!$AK$2:$AK$167,economics!$AJ$2:$AJ$167,TRUE))+$CR7*_xlfn.NORM.DIST(E$3,$CU7,0.3*$CU7,TRUE)+$CS7*_xlfn.NORM.DIST(E$3,$CV7,0.3*$CV7,TRUE),$CW7*_xlfn.NORM.DIST(E$3,'energy base (MECS)'!$F$11,0.3*'energy base (MECS)'!$F$11,TRUE))} | F7: {=IF($D7,SUMPRODUCT((economics!$AG$2:$AG$167=$B7)*(economics!$D$2:$D$167="whr")*economics!$AH$2:$AH$167*_xlfn.NORM.DIST(F$3,economics!$AK$2:$AK$167,economics!$AJ$2:$AJ$167,TRUE))+$CR7*_xlfn.NORM.DIST(F$3,$CU7,0.3*$CU7,TRUE)+$CS7*_xlfn.NORM.DIST(F$3,$CV7,0.3*$CV7,TRUE),$CW7*_xlfn.NORM.DIST(F$3,'energy base (MECS)'!$F$11,0.3*'energy base (MECS)'!$F$11,TRUE))} | G7: {=IF($D7,SUMPRODUCT((economics!$AG$2:$AG$167=$B7)*(economics!$D$2:$D$167="whr")*economics!$AH$2:$AH$167*_xlfn.NORM.DIST(G$3,economics!$AK$2:$AK$167,economics!$AJ$2:$AJ$167,TRUE))+$CR7*_xlfn.NORM.DIST(G$3,$CU7,0.3*$CU7,TRUE)+$CS7*_xlfn.NORM.DIST(G$3,$CV7,0.3*$CV7,TRUE),$CW7*_xlfn.NORM.DIST(G$3,'energy base (MECS)'!$F$11,0.3*'energy base (MECS)'!$F$11,TRUE))} | H7: {=IF($D7,SUMPRODUCT((economics!$AG$2:$AG$167=$B7)*(economics!$D$2:$D$167="whr")*economics!$AH$2:$AH$167*_xlfn.NORM.DIST(H$3,economics!$AK$2:$AK$167,economics!$AJ$2:$AJ$167,TRUE))+$CR7*_xlfn.NORM.DIST(H$3,$CU7,0.3*$CU7,TRUE)+$CS7*_xlfn.NORM.DIST(H$3,$CV7,0.3*$CV7,TRUE),$CW7*_xlfn.NORM.DIST(H$3,'energy base (MECS)'!$F$11,0.3*'energy base (MECS)'!$F$11,TRUE))} | I7: {=IF($D7,SUMPRODUCT((economics!$AG$2:$AG$167=$B7)*(economics!$D$2:$D$167="whr")*economics!$AH$2:$AH$167*_xlfn.NORM.DIST(I$3,economics!$AK$2:$AK$167,economics!$AJ$2:$AJ$167,TRUE))+$CR7*_xlfn.NORM.DIST(I$3,$CU7,0.3*$CU7,TRUE)+$CS7*_xlfn.NORM.DIST(I$3,$CV7,0.3*$CV7,TRUE),$CW7*_xlfn.NORM.DIST(I$3,'energy base (MECS)'!$F$11,0.3*'energy base (MECS)'!$F$11,TRUE))} | J7: {=IF($D7,SUMPRODUCT((economics!$AG$2:$AG$167=$B7)*(economics!$D$2:$D$167="whr")*economics!$AH$2:$AH$167*_xlfn.NORM.DIST(J$3,economics!$AK$2:$AK$167,economics!$AJ$2:$AJ$167,TRUE))+$CR7*_xlfn.NORM.DIST(J$3,$CU7,0.3*$CU7,TRUE)+$CS7*_xlfn.NORM.DIST(J$3,$CV7,0.3*$CV7,TRUE),$CW7*_xlfn.NORM.DIST(J$3,'energy base (MECS)'!$F$11,0.3*'energy base (MECS)'!$F$11,TRUE))} | K7: {=IF($D7,SUMPRODUCT((economics!$AG$2:$AG$167=$B7)*(economics!$D$2:$D$167="whr")*economics!$AH$2:$AH$167*_xlfn.NORM.DIST(K$3,economics!$AK$2:$AK$167,economics!$AJ$2:$AJ$167,TRUE))+$CR7*_xlfn.NORM.DIST(K$3,$CU7,0.3*$CU7,TRUE)+$CS7*_xlfn.NORM.DIST(K$3,$CV7,0.3*$CV7,TRUE),$CW7*_xlfn.NORM.DIST(K$3,'energy base (MECS)'!$F$11,0.3*'energy base (MECS)'!$F$11,TRUE))} | L7: {=IF($D7,SUMPRODUCT((economics!$AG$2:$AG$167=$B7)*(economics!$D$2:$D$167="whr")*economics!$AH$2:$AH$167*_xlfn.NORM.DIST(L$3,economics!$AK$2:$AK$167,economics!$AJ$2:$AJ$167,TRUE))+$CR7*_xlfn.NORM.DIST(L$3,$CU7,0.3*$CU7,TRUE)+$CS7*_xlfn.NORM.DIST(L$3,$CV7,0.3*$CV7,TRUE),$CW7*_xlfn.NORM.DIST(L$3,'energy base (MECS)'!$F$11,0.3*'energy base (MECS)'!$F$11,TRUE))} | ... CH7: {=IF($D7,SUMPRODUCT((economics!$AG$2:$AG$167=$B7)*(economics!$D$2:$D$167="whr")*economics!$AH$2:$AH$167*_xlfn.NORM.DIST(CH$3,economics!$AK$2:$AK$167,economics!$AJ$2:$AJ$167,TRUE))+$CR7*_xlfn.NORM.DIST(CH$3,$CU7,0.3*$CU7,TRUE)+$CS7*_xlfn.NORM.DIST(CH$3,$CV7,0.3*$CV7,TRUE),$CW7*_xlfn.NORM.DIST(CH$3,'energy base (MECS)'!$F$11,0.3*'energy base (MECS)'!$F$11,TRUE))} | CJ7: {=SUMPRODUCT((economics!$AG$2:$AG$167=$B7)*(economics!$D$2:$D$167="whr")*economics!$AH$2:$AH$167)} | CK7: ='indst heat consumption'!D7 | CL7: ='indst heat consumption'!E7 | CM7: ='indst heat consumption'!F7 | CN7: ='indst heat consumption'!G7 | CO7: ='indst heat consumption'!H7 | CP7: =$C7*(CK7*summary!$B$94+CL7*summary!$C$94+CM7*summary!$D$94) | CQ7: =$C7*(CN7*summary!$E$94+CO7*summary!$F$94) | CR7: =IF(CP7+CQ7>0,CP7*MAX(0,CP7+CQ7-CJ7)/(CP7+CQ7),0) | CS7: =IF(CP7+CQ7>0,CQ7*MAX(0,CP7+CQ7-CJ7)/(CP7+CQ7),0) | CT7: =IFERROR(_xlfn.XLOOKUP($B7,'BCoISC-WACCbI'!$C$2:$C$26,'BCoISC-WACCbI'!$B$2:$B$26)+economics!$AE$4,0.1) | CU7: =(summary!$C$7*(CT7/(1-(1+CT7)^-summary!$D$7))+summary!$C$7*summary!$E$7)/(summary!$F$7*3412/1000000) | CV7: =(summary!$C$6*(CT7/(1-(1+CT7)^-summary!$D$6))+summary!$C$6*summary!$E$6)/(summary!$F$6*3412/1000000) | CW7: =CR7+CS7
A8: =WHRPbI!A6 | B8: 10T12 | C8: =WHRPbI!B6 | D8: =ISNUMBER(MATCH($B8,'energy base (MECS)'!$K$4:$K$9,0)) | E8: {=IF($D8,SUMPRODUCT((economics!$AG$2:$AG$167=$B8)*(economics!$D$2:$D$167="whr")*economics!$AH$2:$AH$167*_xlfn.NORM.DIST(E$3,economics!$AK$2:$AK$167,economics!$AJ$2:$AJ$167,TRUE))+$CR8*_xlfn.NORM.DIST(E$3,$CU8,0.3*$CU8,TRUE)+$CS8*_xlfn.NORM.DIST(E$3,$CV8,0.3*$CV8,TRUE),$CW8*_xlfn.NORM.DIST(E$3,'energy base (MECS)'!$F$11,0.3*'energy base (MECS)'!$F$11,TRUE))} | F8: {=IF($D8,SUMPRODUCT((economics!$AG$2:$AG$167=$B8)*(economics!$D$2:$D$167="whr")*economics!$AH$2:$AH$167*_xlfn.NORM.DIST(F$3,economics!$AK$2:$AK$167,economics!$AJ$2:$AJ$167,TRUE))+$CR8*_xlfn.NORM.DIST(F$3,$CU8,0.3*$CU8,TRUE)+$CS8*_xlfn.NORM.DIST(F$3,$CV8,0.3*$CV8,TRUE),$CW8*_xlfn.NORM.DIST(F$3,'energy base (MECS)'!$F$11,0.3*'energy base (MECS)'!$F$11,TRUE))} | G8: {=IF($D8,SUMPRODUCT((economics!$AG$2:$AG$167=$B8)*(economics!$D$2:$D$167="whr")*economics!$AH$2:$AH$167*_xlfn.NORM.DIST(G$3,economics!$AK$2:$AK$167,economics!$AJ$2:$AJ$167,TRUE))+$CR8*_xlfn.NORM.DIST(G$3,$CU8,0.3*$CU8,TRUE)+$CS8*_xlfn.NORM.DIST(G$3,$CV8,0.3*$CV8,TRUE),$CW8*_xlfn.NORM.DIST(G$3,'energy base (MECS)'!$F$11,0.3*'energy base (MECS)'!$F$11,TRUE))} | H8: {=IF($D8,SUMPRODUCT((economics!$AG$2:$AG$167=$B8)*(economics!$D$2:$D$167="whr")*economics!$AH$2:$AH$167*_xlfn.NORM.DIST(H$3,economics!$AK$2:$AK$167,economics!$AJ$2:$AJ$167,TRUE))+$CR8*_xlfn.NORM.DIST(H$3,$CU8,0.3*$CU8,TRUE)+$CS8*_xlfn.NORM.DIST(H$3,$CV8,0.3*$CV8,TRUE),$CW8*_xlfn.NORM.DIST(H$3,'energy base (MECS)'!$F$11,0.3*'energy base (MECS)'!$F$11,TRUE))} | I8: {=IF($D8,SUMPRODUCT((economics!$AG$2:$AG$167=$B8)*(economics!$D$2:$D$167="whr")*economics!$AH$2:$AH$167*_xlfn.NORM.DIST(I$3,economics!$AK$2:$AK$167,economics!$AJ$2:$AJ$167,TRUE))+$CR8*_xlfn.NORM.DIST(I$3,$CU8,0.3*$CU8,TRUE)+$CS8*_xlfn.NORM.DIST(I$3,$CV8,0.3*$CV8,TRUE),$CW8*_xlfn.NORM.DIST(I$3,'energy base (MECS)'!$F$11,0.3*'energy base (MECS)'!$F$11,TRUE))} | J8: {=IF($D8,SUMPRODUCT((economics!$AG$2:$AG$167=$B8)*(economics!$D$2:$D$167="whr")*economics!$AH$2:$AH$167*_xlfn.NORM.DIST(J$3,economics!$AK$2:$AK$167,economics!$AJ$2:$AJ$167,TRUE))+$CR8*_xlfn.NORM.DIST(J$3,$CU8,0.3*$CU8,TRUE)+$CS8*_xlfn.NORM.DIST(J$3,$CV8,0.3*$CV8,TRUE),$CW8*_xlfn.NORM.DIST(J$3,'energy base (MECS)'!$F$11,0.3*'energy base (MECS)'!$F$11,TRUE))} | K8: {=IF($D8,SUMPRODUCT((economics!$AG$2:$AG$167=$B8)*(economics!$D$2:$D$167="whr")*economics!$AH$2:$AH$167*_xlfn.NORM.DIST(K$3,economics!$AK$2:$AK$167,economics!$AJ$2:$AJ$167,TRUE))+$CR8*_xlfn.NORM.DIST(K$3,$CU8,0.3*$CU8,TRUE)+$CS8*_xlfn.NORM.DIST(K$3,$CV8,0.3*$CV8,TRUE),$CW8*_xlfn.NORM.DIST(K$3,'energy base (MECS)'!$F$11,0.3*'energy base (MECS)'!$F$11,TRUE))} | L8: {=IF($D8,SUMPRODUCT((economics!$AG$2:$AG$167=$B8)*(economics!$D$2:$D$167="whr")*economics!$AH$2:$AH$167*_xlfn.NORM.DIST(L$3,economics!$AK$2:$AK$167,economics!$AJ$2:$AJ$167,TRUE))+$CR8*_xlfn.NORM.DIST(L$3,$CU8,0.3*$CU8,TRUE)+$CS8*_xlfn.NORM.DIST(L$3,$CV8,0.3*$CV8,TRUE),$CW8*_xlfn.NORM.DIST(L$3,'energy base (MECS)'!$F$11,0.3*'energy base (MECS)'!$F$11,TRUE))} | ... CH8: {=IF($D8,SUMPRODUCT((economics!$AG$2:$AG$167=$B8)*(economics!$D$2:$D$167="whr")*economics!$AH$2:$AH$167*_xlfn.NORM.DIST(CH$3,economics!$AK$2:$AK$167,economics!$AJ$2:$AJ$167,TRUE))+$CR8*_xlfn.NORM.DIST(CH$3,$CU8,0.3*$CU8,TRUE)+$CS8*_xlfn.NORM.DIST(CH$3,$CV8,0.3*$CV8,TRUE),$CW8*_xlfn.NORM.DIST(CH$3,'energy base (MECS)'!$F$11,0.3*'energy base (MECS)'!$F$11,TRUE))} | CJ8: {=SUMPRODUCT((economics!$AG$2:$AG$167=$B8)*(economics!$D$2:$D$167="whr")*economics!$AH$2:$AH$167)} | CK8: ='indst heat consumption'!D8 | CL8: ='indst heat consumption'!E8 | CM8: ='indst heat consumption'!F8 | CN8: ='indst heat consumption'!G8 | CO8: ='indst heat consumption'!H8 | CP8: =$C8*(CK8*summary!$B$94+CL8*summary!$C$94+CM8*summary!$D$94) | CQ8: =$C8*(CN8*summary!$E$94+CO8*summary!$F$94) | CR8: =IF(CP8+CQ8>0,CP8*MAX(0,CP8+CQ8-CJ8)/(CP8+CQ8),0) | CS8: =IF(CP8+CQ8>0,CQ8*MAX(0,CP8+CQ8-CJ8)/(CP8+CQ8),0) | CT8: =IFERROR(_xlfn.XLOOKUP($B8,'BCoISC-WACCbI'!$C$2:$C$26,'BCoISC-WACCbI'!$B$2:$B$26)+economics!$AE$4,0.1) | CU8: =(summary!$C$7*(CT8/(1-(1+CT8)^-summary!$D$7))+summary!$C$7*summary!$E$7)/(summary!$F$7*3412/1000000) | CV8: =(summary!$C$6*(CT8/(1-(1+CT8)^-summary!$D$6))+summary!$C$6*summary!$E$6)/(summary!$F$6*3412/1000000) | CW8: =CR8+CS8
A9: =WHRPbI!A7 | B9: 13T15 | C9: =WHRPbI!B7 | D9: =ISNUMBER(MATCH($B9,'energy base (MECS)'!$K$4:$K$9,0)) | E9: {=IF($D9,SUMPRODUCT((economics!$AG$2:$AG$167=$B9)*(economics!$D$2:$D$167="whr")*economics!$AH$2:$AH$167*_xlfn.NORM.DIST(E$3,economics!$AK$2:$AK$167,economics!$AJ$2:$AJ$167,TRUE))+$CR9*_xlfn.NORM.DIST(E$3,$CU9,0.3*$CU9,TRUE)+$CS9*_xlfn.NORM.DIST(E$3,$CV9,0.3*$CV9,TRUE),$CW9*_xlfn.NORM.DIST(E$3,'energy base (MECS)'!$F$11,0.3*'energy base (MECS)'!$F$11,TRUE))} | F9: {=IF($D9,SUMPRODUCT((economics!$AG$2:$AG$167=$B9)*(economics!$D$2:$D$167="whr")*economics!$AH$2:$AH$167*_xlfn.NORM.DIST(F$3,economics!$AK$2:$AK$167,economics!$AJ$2:$AJ$167,TRUE))+$CR9*_xlfn.NORM.DIST(F$3,$CU9,0.3*$CU9,TRUE)+$CS9*_xlfn.NORM.DIST(F$3,$CV9,0.3*$CV9,TRUE),$CW9*_xlfn.NORM.DIST(F$3,'energy base (MECS)'!$F$11,0.3*'energy base (MECS)'!$F$11,TRUE))} | G9: {=IF($D9,SUMPRODUCT((economics!$AG$2:$AG$167=$B9)*(economics!$D$2:$D$167="whr")*economics!$AH$2:$AH$167*_xlfn.NORM.DIST(G$3,economics!$AK$2:$AK$167,economics!$AJ$2:$AJ$167,TRUE))+$CR9*_xlfn.NORM.DIST(G$3,$CU9,0.3*$CU9,TRUE)+$CS9*_xlfn.NORM.DIST(G$3,$CV9,0.3*$CV9,TRUE),$CW9*_xlfn.NORM.DIST(G$3,'energy base (MECS)'!$F$11,0.3*'energy base (MECS)'!$F$11,TRUE))} | H9: {=IF($D9,SUMPRODUCT((economics!$AG$2:$AG$167=$B9)*(economics!$D$2:$D$167="whr")*economics!$AH$2:$AH$167*_xlfn.NORM.DIST(H$3,economics!$AK$2:$AK$167,economics!$AJ$2:$AJ$167,TRUE))+$CR9*_xlfn.NORM.DIST(H$3,$CU9,0.3*$CU9,TRUE)+$CS9*_xlfn.NORM.DIST(H$3,$CV9,0.3*$CV9,TRUE),$CW9*_xlfn.NORM.DIST(H$3,'energy base (MECS)'!$F$11,0.3*'energy base (MECS)'!$F$11,TRUE))} | I9: {=IF($D9,SUMPRODUCT((economics!$AG$2:$AG$167=$B9)*(economics!$D$2:$D$167="whr")*economics!$AH$2:$AH$167*_xlfn.NORM.DIST(I$3,economics!$AK$2:$AK$167,economics!$AJ$2:$AJ$167,TRUE))+$CR9*_xlfn.NORM.DIST(I$3,$CU9,0.3*$CU9,TRUE)+$CS9*_xlfn.NORM.DIST(I$3,$CV9,0.3*$CV9,TRUE),$CW9*_xlfn.NORM.DIST(I$3,'energy base (MECS)'!$F$11,0.3*'energy base (MECS)'!$F$11,TRUE))} | J9: {=IF($D9,SUMPRODUCT((economics!$AG$2:$AG$167=$B9)*(economics!$D$2:$D$167="whr")*economics!$AH$2:$AH$167*_xlfn.NORM.DIST(J$3,economics!$AK$2:$AK$167,economics!$AJ$2:$AJ$167,TRUE))+$CR9*_xlfn.NORM.DIST(J$3,$CU9,0.3*$CU9,TRUE)+$CS9*_xlfn.NORM.DIST(J$3,$CV9,0.3*$CV9,TRUE),$CW9*_xlfn.NORM.DIST(J$3,'energy base (MECS)'!$F$11,0.3*'energy base (MECS)'!$F$11,TRUE))} | K9: {=IF($D9,SUMPRODUCT((economics!$AG$2:$AG$167=$B9)*(economics!$D$2:$D$167="whr")*economics!$AH$2:$AH$167*_xlfn.NORM.DIST(K$3,economics!$AK$2:$AK$167,economics!$AJ$2:$AJ$167,TRUE))+$CR9*_xlfn.NORM.DIST(K$3,$CU9,0.3*$CU9,TRUE)+$CS9*_xlfn.NORM.DIST(K$3,$CV9,0.3*$CV9,TRUE),$CW9*_xlfn.NORM.DIST(K$3,'energy base (MECS)'!$F$11,0.3*'energy base (MECS)'!$F$11,TRUE))} | L9: {=IF($D9,SUMPRODUCT((economics!$AG$2:$AG$167=$B9)*(economics!$D$2:$D$167="whr")*economics!$AH$2:$AH$167*_xlfn.NORM.DIST(L$3,economics!$AK$2:$AK$167,economics!$AJ$2:$AJ$167,TRUE))+$CR9*_xlfn.NORM.DIST(L$3,$CU9,0.3*$CU9,TRUE)+$CS9*_xlfn.NORM.DIST(L$3,$CV9,0.3*$CV9,TRUE),$CW9*_xlfn.NORM.DIST(L$3,'energy base (MECS)'!$F$11,0.3*'energy base (MECS)'!$F$11,TRUE))} | ... CH9: {=IF($D9,SUMPRODUCT((economics!$AG$2:$AG$167=$B9)*(economics!$D$2:$D$167="whr")*economics!$AH$2:$AH$167*_xlfn.NORM.DIST(CH$3,economics!$AK$2:$AK$167,economics!$AJ$2:$AJ$167,TRUE))+$CR9*_xlfn.NORM.DIST(CH$3,$CU9,0.3*$CU9,TRUE)+$CS9*_xlfn.NORM.DIST(CH$3,$CV9,0.3*$CV9,TRUE),$CW9*_xlfn.NORM.DIST(CH$3,'energy base (MECS)'!$F$11,0.3*'energy base (MECS)'!$F$11,TRUE))} | CJ9: {=SUMPRODUCT((economics!$AG$2:$AG$167=$B9)*(economics!$D$2:$D$167="whr")*economics!$AH$2:$AH$167)} | CK9: ='indst heat consumption'!D9 | CL9: ='indst heat consumption'!E9 | CM9: ='indst heat consumption'!F9 | CN9: ='indst heat consumption'!G9 | CO9: ='indst heat consumption'!H9 | CP9: =$C9*(CK9*summary!$B$94+CL9*summary!$C$94+CM9*summary!$D$94) | CQ9: =$C9*(CN9*summary!$E$94+CO9*summary!$F$94) | CR9: =IF(CP9+CQ9>0,CP9*MAX(0,CP9+CQ9-CJ9)/(CP9+CQ9),0) | CS9: =IF(CP9+CQ9>0,CQ9*MAX(0,CP9+CQ9-CJ9)/(CP9+CQ9),0) | CT9: =IFERROR(_xlfn.XLOOKUP($B9,'BCoISC-WACCbI'!$C$2:$C$26,'BCoISC-WACCbI'!$B$2:$B$26)+economics!$AE$4,0.1) | CU9: =(summary!$C$7*(CT9/(1-(1+CT9)^-summary!$D$7))+summary!$C$7*summary!$E$7)/(summary!$F$7*3412/1000000) | CV9: =(summary!$C$6*(CT9/(1-(1+CT9)^-summary!$D$6))+summary!$C$6*summary!$E$6)/(summary!$F$6*3412/1000000) | CW9: =CR9+CS9
A10: =WHRPbI!A8 | B10: 16 | C10: =WHRPbI!B8 | D10: =ISNUMBER(MATCH($B10,'energy base (MECS)'!$K$4:$K$9,0)) | E10: {=IF($D10,SUMPRODUCT((economics!$AG$2:$AG$167=$B10)*(economics!$D$2:$D$167="whr")*economics!$AH$2:$AH$167*_xlfn.NORM.DIST(E$3,economics!$AK$2:$AK$167,economics!$AJ$2:$AJ$167,TRUE))+$CR10*_xlfn.NORM.DIST(E$3,$CU10,0.3*$CU10,TRUE)+$CS10*_xlfn.NORM.DIST(E$3,$CV10,0.3*$CV10,TRUE),$CW10*_xlfn.NORM.DIST(E$3,'energy base (MECS)'!$F$11,0.3*'energy base (MECS)'!$F$11,TRUE))} | F10: {=IF($D10,SUMPRODUCT((economics!$AG$2:$AG$167=$B10)*(economics!$D$2:$D$167="whr")*economics!$AH$2:$AH$167*_xlfn.NORM.DIST(F$3,economics!$AK$2:$AK$167,economics!$AJ$2:$AJ$167,TRUE))+$CR10*_xlfn.NORM.DIST(F$3,$CU10,0.3*$CU10,TRUE)+$CS10*_xlfn.NORM.DIST(F$3,$CV10,0.3*$CV10,TRUE),$CW10*_xlfn.NORM.DIST(F$3,'energy base (MECS)'!$F$11,0.3*'energy base (MECS)'!$F$11,TRUE))} | G10: {=IF($D10,SUMPRODUCT((economics!$AG$2:$AG$167=$B10)*(economics!$D$2:$D$167="whr")*economics!$AH$2:$AH$167*_xlfn.NORM.DIST(G$3,economics!$AK$2:$AK$167,economics!$AJ$2:$AJ$167,TRUE))+$CR10*_xlfn.NORM.DIST(G$3,$CU10,0.3*$CU10,TRUE)+$CS10*_xlfn.NORM.DIST(G$3,$CV10,0.3*$CV10,TRUE),$CW10*_xlfn.NORM.DIST(G$3,'energy base (MECS)'!$F$11,0.3*'energy base (MECS)'!$F$11,TRUE))} | H10: {=IF($D10,SUMPRODUCT((economics!$AG$2:$AG$167=$B10)*(economics!$D$2:$D$167="whr")*economics!$AH$2:$AH$167*_xlfn.NORM.DIST(H$3,economics!$AK$2:$AK$167,economics!$AJ$2:$AJ$167,TRUE))+$CR10*_xlfn.NORM.DIST(H$3,$CU10,0.3*$CU10,TRUE)+$CS10*_xlfn.NORM.DIST(H$3,$CV10,0.3*$CV10,TRUE),$CW10*_xlfn.NORM.DIST(H$3,'energy base (MECS)'!$F$11,0.3*'energy base (MECS)'!$F$11,TRUE))} | I10: {=IF($D10,SUMPRODUCT((economics!$AG$2:$AG$167=$B10)*(economics!$D$2:$D$167="whr")*economics!$AH$2:$AH$167*_xlfn.NORM.DIST(I$3,economics!$AK$2:$AK$167,economics!$AJ$2:$AJ$167,TRUE))+$CR10*_xlfn.NORM.DIST(I$3,$CU10,0.3*$CU10,TRUE)+$CS10*_xlfn.NORM.DIST(I$3,$CV10,0.3*$CV10,TRUE),$CW10*_xlfn.NORM.DIST(I$3,'energy base (MECS)'!$F$11,0.3*'energy base (MECS)'!$F$11,TRUE))} | J10: {=IF($D10,SUMPRODUCT((economics!$AG$2:$AG$167=$B10)*(economics!$D$2:$D$167="whr")*economics!$AH$2:$AH$167*_xlfn.NORM.DIST(J$3,economics!$AK$2:$AK$167,economics!$AJ$2:$AJ$167,TRUE))+$CR10*_xlfn.NORM.DIST(J$3,$CU10,0.3*$CU10,TRUE)+$CS10*_xlfn.NORM.DIST(J$3,$CV10,0.3*$CV10,TRUE),$CW10*_xlfn.NORM.DIST(J$3,'energy base (MECS)'!$F$11,0.3*'energy base (MECS)'!$F$11,TRUE))} | K10: {=IF($D10,SUMPRODUCT((economics!$AG$2:$AG$167=$B10)*(economics!$D$2:$D$167="whr")*economics!$AH$2:$AH$167*_xlfn.NORM.DIST(K$3,economics!$AK$2:$AK$167,economics!$AJ$2:$AJ$167,TRUE))+$CR10*_xlfn.NORM.DIST(K$3,$CU10,0.3*$CU10,TRUE)+$CS10*_xlfn.NORM.DIST(K$3,$CV10,0.3*$CV10,TRUE),$CW10*_xlfn.NORM.DIST(K$3,'energy base (MECS)'!$F$11,0.3*'energy base (MECS)'!$F$11,TRUE))} | L10: {=IF($D10,SUMPRODUCT((economics!$AG$2:$AG$167=$B10)*(economics!$D$2:$D$167="whr")*economics!$AH$2:$AH$167*_xlfn.NORM.DIST(L$3,economics!$AK$2:$AK$167,economics!$AJ$2:$AJ$167,TRUE))+$CR10*_xlfn.NORM.DIST(L$3,$CU10,0.3*$CU10,TRUE)+$CS10*_xlfn.NORM.DIST(L$3,$CV10,0.3*$CV10,TRUE),$CW10*_xlfn.NORM.DIST(L$3,'energy base (MECS)'!$F$11,0.3*'energy base (MECS)'!$F$11,TRUE))} | ... CH10: {=IF($D10,SUMPRODUCT((economics!$AG$2:$AG$167=$B10)*(economics!$D$2:$D$167="whr")*economics!$AH$2:$AH$167*_xlfn.NORM.DIST(CH$3,economics!$AK$2:$AK$167,economics!$AJ$2:$AJ$167,TRUE))+$CR10*_xlfn.NORM.DIST(CH$3,$CU10,0.3*$CU10,TRUE)+$CS10*_xlfn.NORM.DIST(CH$3,$CV10,0.3*$CV10,TRUE),$CW10*_xlfn.NORM.DIST(CH$3,'energy base (MECS)'!$F$11,0.3*'energy base (MECS)'!$F$11,TRUE))} | CJ10: {=SUMPRODUCT((economics!$AG$2:$AG$167=$B10)*(economics!$D$2:$D$167="whr")*economics!$AH$2:$AH$167)} | CK10: ='indst heat consumption'!D10 | CL10: ='indst heat consumption'!E10 | CM10: ='indst heat consumption'!F10 | CN10: ='indst heat consumption'!G10 | CO10: ='indst heat consumption'!H10 | CP10: =$C10*(CK10*summary!$B$94+CL10*summary!$C$94+CM10*summary!$D$94) | CQ10: =$C10*(CN10*summary!$E$94+CO10*summary!$F$94) | CR10: =IF(CP10+CQ10>0,CP10*MAX(0,CP10+CQ10-CJ10)/(CP10+CQ10),0) | CS10: =IF(CP10+CQ10>0,CQ10*MAX(0,CP10+CQ10-CJ10)/(CP10+CQ10),0) | CT10: =IFERROR(_xlfn.XLOOKUP($B10,'BCoISC-WACCbI'!$C$2:$C$26,'BCoISC-WACCbI'!$B$2:$B$26)+economics!$AE$4,0.1) | CU10: =(summary!$C$7*(CT10/(1-(1+CT10)^-summary!$D$7))+summary!$C$7*summary!$E$7)/(summary!$F$7*3412/1000000) | CV10: =(summary!$C$6*(CT10/(1-(1+CT10)^-summary!$D$6))+summary!$C$6*summary!$E$6)/(summary!$F$6*3412/1000000) | CW10: =CR10+CS10
A11: =WHRPbI!A9 | B11: 17T18 | C11: =WHRPbI!B9 | D11: =ISNUMBER(MATCH($B11,'energy base (MECS)'!$K$4:$K$9,0)) | E11: {=IF($D11,SUMPRODUCT((economics!$AG$2:$AG$167=$B11)*(economics!$D$2:$D$167="whr")*economics!$AH$2:$AH$167*_xlfn.NORM.DIST(E$3,economics!$AK$2:$AK$167,economics!$AJ$2:$AJ$167,TRUE))+$CR11*_xlfn.NORM.DIST(E$3,$CU11,0.3*$CU11,TRUE)+$CS11*_xlfn.NORM.DIST(E$3,$CV11,0.3*$CV11,TRUE),$CW11*_xlfn.NORM.DIST(E$3,'energy base (MECS)'!$F$11,0.3*'energy base (MECS)'!$F$11,TRUE))} | F11: {=IF($D11,SUMPRODUCT((economics!$AG$2:$AG$167=$B11)*(economics!$D$2:$D$167="whr")*economics!$AH$2:$AH$167*_xlfn.NORM.DIST(F$3,economics!$AK$2:$AK$167,economics!$AJ$2:$AJ$167,TRUE))+$CR11*_xlfn.NORM.DIST(F$3,$CU11,0.3*$CU11,TRUE)+$CS11*_xlfn.NORM.DIST(F$3,$CV11,0.3*$CV11,TRUE),$CW11*_xlfn.NORM.DIST(F$3,'energy base (MECS)'!$F$11,0.3*'energy base (MECS)'!$F$11,TRUE))} | G11: {=IF($D11,SUMPRODUCT((economics!$AG$2:$AG$167=$B11)*(economics!$D$2:$D$167="whr")*economics!$AH$2:$AH$167*_xlfn.NORM.DIST(G$3,economics!$AK$2:$AK$167,economics!$AJ$2:$AJ$167,TRUE))+$CR11*_xlfn.NORM.DIST(G$3,$CU11,0.3*$CU11,TRUE)+$CS11*_xlfn.NORM.DIST(G$3,$CV11,0.3*$CV11,TRUE),$CW11*_xlfn.NORM.DIST(G$3,'energy base (MECS)'!$F$11,0.3*'energy base (MECS)'!$F$11,TRUE))} | H11: {=IF($D11,SUMPRODUCT((economics!$AG$2:$AG$167=$B11)*(economics!$D$2:$D$167="whr")*economics!$AH$2:$AH$167*_xlfn.NORM.DIST(H$3,economics!$AK$2:$AK$167,economics!$AJ$2:$AJ$167,TRUE))+$CR11*_xlfn.NORM.DIST(H$3,$CU11,0.3*$CU11,TRUE)+$CS11*_xlfn.NORM.DIST(H$3,$CV11,0.3*$CV11,TRUE),$CW11*_xlfn.NORM.DIST(H$3,'energy base (MECS)'!$F$11,0.3*'energy base (MECS)'!$F$11,TRUE))} | I11: {=IF($D11,SUMPRODUCT((economics!$AG$2:$AG$167=$B11)*(economics!$D$2:$D$167="whr")*economics!$AH$2:$AH$167*_xlfn.NORM.DIST(I$3,economics!$AK$2:$AK$167,economics!$AJ$2:$AJ$167,TRUE))+$CR11*_xlfn.NORM.DIST(I$3,$CU11,0.3*$CU11,TRUE)+$CS11*_xlfn.NORM.DIST(I$3,$CV11,0.3*$CV11,TRUE),$CW11*_xlfn.NORM.DIST(I$3,'energy base (MECS)'!$F$11,0.3*'energy base (MECS)'!$F$11,TRUE))} | J11: {=IF($D11,SUMPRODUCT((economics!$AG$2:$AG$167=$B11)*(economics!$D$2:$D$167="whr")*economics!$AH$2:$AH$167*_xlfn.NORM.DIST(J$3,economics!$AK$2:$AK$167,economics!$AJ$2:$AJ$167,TRUE))+$CR11*_xlfn.NORM.DIST(J$3,$CU11,0.3*$CU11,TRUE)+$CS11*_xlfn.NORM.DIST(J$3,$CV11,0.3*$CV11,TRUE),$CW11*_xlfn.NORM.DIST(J$3,'energy base (MECS)'!$F$11,0.3*'energy base (MECS)'!$F$11,TRUE))} | K11: {=IF($D11,SUMPRODUCT((economics!$AG$2:$AG$167=$B11)*(economics!$D$2:$D$167="whr")*economics!$AH$2:$AH$167*_xlfn.NORM.DIST(K$3,economics!$AK$2:$AK$167,economics!$AJ$2:$AJ$167,TRUE))+$CR11*_xlfn.NORM.DIST(K$3,$CU11,0.3*$CU11,TRUE)+$CS11*_xlfn.NORM.DIST(K$3,$CV11,0.3*$CV11,TRUE),$CW11*_xlfn.NORM.DIST(K$3,'energy base (MECS)'!$F$11,0.3*'energy base (MECS)'!$F$11,TRUE))} | L11: {=IF($D11,SUMPRODUCT((economics!$AG$2:$AG$167=$B11)*(economics!$D$2:$D$167="whr")*economics!$AH$2:$AH$167*_xlfn.NORM.DIST(L$3,economics!$AK$2:$AK$167,economics!$AJ$2:$AJ$167,TRUE))+$CR11*_xlfn.NORM.DIST(L$3,$CU11,0.3*$CU11,TRUE)+$CS11*_xlfn.NORM.DIST(L$3,$CV11,0.3*$CV11,TRUE),$CW11*_xlfn.NORM.DIST(L$3,'energy base (MECS)'!$F$11,0.3*'energy base (MECS)'!$F$11,TRUE))} | ... CH11: {=IF($D11,SUMPRODUCT((economics!$AG$2:$AG$167=$B11)*(economics!$D$2:$D$167="whr")*economics!$AH$2:$AH$167*_xlfn.NORM.DIST(CH$3,economics!$AK$2:$AK$167,economics!$AJ$2:$AJ$167,TRUE))+$CR11*_xlfn.NORM.DIST(CH$3,$CU11,0.3*$CU11,TRUE)+$CS11*_xlfn.NORM.DIST(CH$3,$CV11,0.3*$CV11,TRUE),$CW11*_xlfn.NORM.DIST(CH$3,'energy base (MECS)'!$F$11,0.3*'energy base (MECS)'!$F$11,TRUE))} | CJ11: {=SUMPRODUCT((economics!$AG$2:$AG$167=$B11)*(economics!$D$2:$D$167="whr")*economics!$AH$2:$AH$167)} | CK11: ='indst heat consumption'!D11 | CL11: ='indst heat consumption'!E11 | CM11: ='indst heat consumption'!F11 | CN11: ='indst heat consumption'!G11 | CO11: ='indst heat consumption'!H11 | CP11: =$C11*(CK11*summary!$B$94+CL11*summary!$C$94+CM11*summary!$D$94) | CQ11: =$C11*(CN11*summary!$E$94+CO11*summary!$F$94) | CR11: =IF(CP11+CQ11>0,CP11*MAX(0,CP11+CQ11-CJ11)/(CP11+CQ11),0) | CS11: =IF(CP11+CQ11>0,CQ11*MAX(0,CP11+CQ11-CJ11)/(CP11+CQ11),0) | CT11: =IFERROR(_xlfn.XLOOKUP($B11,'BCoISC-WACCbI'!$C$2:$C$26,'BCoISC-WACCbI'!$B$2:$B$26)+economics!$AE$4,0.1) | CU11: =(summary!$C$7*(CT11/(1-(1+CT11)^-summary!$D$7))+summary!$C$7*summary!$E$7)/(summary!$F$7*3412/1000000) | CV11: =(summary!$C$6*(CT11/(1-(1+CT11)^-summary!$D$6))+summary!$C$6*summary!$E$6)/(summary!$F$6*3412/1000000) | CW11: =CR11+CS11
A12: =WHRPbI!A10 | B12: 19 | C12: =WHRPbI!B10 | D12: =ISNUMBER(MATCH($B12,'energy base (MECS)'!$K$4:$K$9,0)) | E12: {=IF($D12,SUMPRODUCT((economics!$AG$2:$AG$167=$B12)*(economics!$D$2:$D$167="whr")*economics!$AH$2:$AH$167*_xlfn.NORM.DIST(E$3,economics!$AK$2:$AK$167,economics!$AJ$2:$AJ$167,TRUE))+$CR12*_xlfn.NORM.DIST(E$3,$CU12,0.3*$CU12,TRUE)+$CS12*_xlfn.NORM.DIST(E$3,$CV12,0.3*$CV12,TRUE),$CW12*_xlfn.NORM.DIST(E$3,'energy base (MECS)'!$F$11,0.3*'energy base (MECS)'!$F$11,TRUE))} | F12: {=IF($D12,SUMPRODUCT((economics!$AG$2:$AG$167=$B12)*(economics!$D$2:$D$167="whr")*economics!$AH$2:$AH$167*_xlfn.NORM.DIST(F$3,economics!$AK$2:$AK$167,economics!$AJ$2:$AJ$167,TRUE))+$CR12*_xlfn.NORM.DIST(F$3,$CU12,0.3*$CU12,TRUE)+$CS12*_xlfn.NORM.DIST(F$3,$CV12,0.3*$CV12,TRUE),$CW12*_xlfn.NORM.DIST(F$3,'energy base (MECS)'!$F$11,0.3*'energy base (MECS)'!$F$11,TRUE))} | G12: {=IF($D12,SUMPRODUCT((economics!$AG$2:$AG$167=$B12)*(economics!$D$2:$D$167="whr")*economics!$AH$2:$AH$167*_xlfn.NORM.DIST(G$3,economics!$AK$2:$AK$167,economics!$AJ$2:$AJ$167,TRUE))+$CR12*_xlfn.NORM.DIST(G$3,$CU12,0.3*$CU12,TRUE)+$CS12*_xlfn.NORM.DIST(G$3,$CV12,0.3*$CV12,TRUE),$CW12*_xlfn.NORM.DIST(G$3,'energy base (MECS)'!$F$11,0.3*'energy base (MECS)'!$F$11,TRUE))} | H12: {=IF($D12,SUMPRODUCT((economics!$AG$2:$AG$167=$B12)*(economics!$D$2:$D$167="whr")*economics!$AH$2:$AH$167*_xlfn.NORM.DIST(H$3,economics!$AK$2:$AK$167,economics!$AJ$2:$AJ$167,TRUE))+$CR12*_xlfn.NORM.DIST(H$3,$CU12,0.3*$CU12,TRUE)+$CS12*_xlfn.NORM.DIST(H$3,$CV12,0.3*$CV12,TRUE),$CW12*_xlfn.NORM.DIST(H$3,'energy base (MECS)'!$F$11,0.3*'energy base (MECS)'!$F$11,TRUE))} | I12: {=IF($D12,SUMPRODUCT((economics!$AG$2:$AG$167=$B12)*(economics!$D$2:$D$167="whr")*economics!$AH$2:$AH$167*_xlfn.NORM.DIST(I$3,economics!$AK$2:$AK$167,economics!$AJ$2:$AJ$167,TRUE))+$CR12*_xlfn.NORM.DIST(I$3,$CU12,0.3*$CU12,TRUE)+$CS12*_xlfn.NORM.DIST(I$3,$CV12,0.3*$CV12,TRUE),$CW12*_xlfn.NORM.DIST(I$3,'energy base (MECS)'!$F$11,0.3*'energy base (MECS)'!$F$11,TRUE))} | J12: {=IF($D12,SUMPRODUCT((economics!$AG$2:$AG$167=$B12)*(economics!$D$2:$D$167="whr")*economics!$AH$2:$AH$167*_xlfn.NORM.DIST(J$3,economics!$AK$2:$AK$167,economics!$AJ$2:$AJ$167,TRUE))+$CR12*_xlfn.NORM.DIST(J$3,$CU12,0.3*$CU12,TRUE)+$CS12*_xlfn.NORM.DIST(J$3,$CV12,0.3*$CV12,TRUE),$CW12*_xlfn.NORM.DIST(J$3,'energy base (MECS)'!$F$11,0.3*'energy base (MECS)'!$F$11,TRUE))} | K12: {=IF($D12,SUMPRODUCT((economics!$AG$2:$AG$167=$B12)*(economics!$D$2:$D$167="whr")*economics!$AH$2:$AH$167*_xlfn.NORM.DIST(K$3,economics!$AK$2:$AK$167,economics!$AJ$2:$AJ$167,TRUE))+$CR12*_xlfn.NORM.DIST(K$3,$CU12,0.3*$CU12,TRUE)+$CS12*_xlfn.NORM.DIST(K$3,$CV12,0.3*$CV12,TRUE),$CW12*_xlfn.NORM.DIST(K$3,'energy base (MECS)'!$F$11,0.3*'energy base (MECS)'!$F$11,TRUE))} | L12: {=IF($D12,SUMPRODUCT((economics!$AG$2:$AG$167=$B12)*(economics!$D$2:$D$167="whr")*economics!$AH$2:$AH$167*_xlfn.NORM.DIST(L$3,economics!$AK$2:$AK$167,economics!$AJ$2:$AJ$167,TRUE))+$CR12*_xlfn.NORM.DIST(L$3,$CU12,0.3*$CU12,TRUE)+$CS12*_xlfn.NORM.DIST(L$3,$CV12,0.3*$CV12,TRUE),$CW12*_xlfn.NORM.DIST(L$3,'energy base (MECS)'!$F$11,0.3*'energy base (MECS)'!$F$11,TRUE))} | ... CH12: {=IF($D12,SUMPRODUCT((economics!$AG$2:$AG$167=$B12)*(economics!$D$2:$D$167="whr")*economics!$AH$2:$AH$167*_xlfn.NORM.DIST(CH$3,economics!$AK$2:$AK$167,economics!$AJ$2:$AJ$167,TRUE))+$CR12*_xlfn.NORM.DIST(CH$3,$CU12,0.3*$CU12,TRUE)+$CS12*_xlfn.NORM.DIST(CH$3,$CV12,0.3*$CV12,TRUE),$CW12*_xlfn.NORM.DIST(CH$3,'energy base (MECS)'!$F$11,0.3*'energy base (MECS)'!$F$11,TRUE))} | CJ12: {=SUMPRODUCT((economics!$AG$2:$AG$167=$B12)*(economics!$D$2:$D$167="whr")*economics!$AH$2:$AH$167)} | CK12: ='indst heat consumption'!D12 | CL12: ='indst heat consumption'!E12 | CM12: ='indst heat consumption'!F12 | CN12: ='indst heat consumption'!G12 | CO12: ='indst heat consumption'!H12 | CP12: =$C12*(CK12*summary!$B$94+CL12*summary!$C$94+CM12*summary!$D$94) | CQ12: =$C12*(CN12*summary!$E$94+CO12*summary!$F$94) | CR12: =IF(CP12+CQ12>0,CP12*MAX(0,CP12+CQ12-CJ12)/(CP12+CQ12),0) | CS12: =IF(CP12+CQ12>0,CQ12*MAX(0,CP12+CQ12-CJ12)/(CP12+CQ12),0) | CT12: =IFERROR(_xlfn.XLOOKUP($B12,'BCoISC-WACCbI'!$C$2:$C$26,'BCoISC-WACCbI'!$B$2:$B$26)+economics!$AE$4,0.1) | CU12: =(summary!$C$7*(CT12/(1-(1+CT12)^-summary!$D$7))+summary!$C$7*summary!$E$7)/(summary!$F$7*3412/1000000) | CV12: =(summary!$C$6*(CT12/(1-(1+CT12)^-summary!$D$6))+summary!$C$6*summary!$E$6)/(summary!$F$6*3412/1000000) | CW12: =CR12+CS12
A13: =WHRPbI!A11 | B13: 20 | C13: =WHRPbI!B11 | D13: =ISNUMBER(MATCH($B13,'energy base (MECS)'!$K$4:$K$9,0)) | E13: {=IF($D13,SUMPRODUCT((economics!$AG$2:$AG$167=$B13)*(economics!$D$2:$D$167="whr")*economics!$AH$2:$AH$167*_xlfn.NORM.DIST(E$3,economics!$AK$2:$AK$167,economics!$AJ$2:$AJ$167,TRUE))+$CR13*_xlfn.NORM.DIST(E$3,$CU13,0.3*$CU13,TRUE)+$CS13*_xlfn.NORM.DIST(E$3,$CV13,0.3*$CV13,TRUE),$CW13*_xlfn.NORM.DIST(E$3,'energy base (MECS)'!$F$11,0.3*'energy base (MECS)'!$F$11,TRUE))} | F13: {=IF($D13,SUMPRODUCT((economics!$AG$2:$AG$167=$B13)*(economics!$D$2:$D$167="whr")*economics!$AH$2:$AH$167*_xlfn.NORM.DIST(F$3,economics!$AK$2:$AK$167,economics!$AJ$2:$AJ$167,TRUE))+$CR13*_xlfn.NORM.DIST(F$3,$CU13,0.3*$CU13,TRUE)+$CS13*_xlfn.NORM.DIST(F$3,$CV13,0.3*$CV13,TRUE),$CW13*_xlfn.NORM.DIST(F$3,'energy base (MECS)'!$F$11,0.3*'energy base (MECS)'!$F$11,TRUE))} | G13: {=IF($D13,SUMPRODUCT((economics!$AG$2:$AG$167=$B13)*(economics!$D$2:$D$167="whr")*economics!$AH$2:$AH$167*_xlfn.NORM.DIST(G$3,economics!$AK$2:$AK$167,economics!$AJ$2:$AJ$167,TRUE))+$CR13*_xlfn.NORM.DIST(G$3,$CU13,0.3*$CU13,TRUE)+$CS13*_xlfn.NORM.DIST(G$3,$CV13,0.3*$CV13,TRUE),$CW13*_xlfn.NORM.DIST(G$3,'energy base (MECS)'!$F$11,0.3*'energy base (MECS)'!$F$11,TRUE))} | H13: {=IF($D13,SUMPRODUCT((economics!$AG$2:$AG$167=$B13)*(economics!$D$2:$D$167="whr")*economics!$AH$2:$AH$167*_xlfn.NORM.DIST(H$3,economics!$AK$2:$AK$167,economics!$AJ$2:$AJ$167,TRUE))+$CR13*_xlfn.NORM.DIST(H$3,$CU13,0.3*$CU13,TRUE)+$CS13*_xlfn.NORM.DIST(H$3,$CV13,0.3*$CV13,TRUE),$CW13*_xlfn.NORM.DIST(H$3,'energy base (MECS)'!$F$11,0.3*'energy base (MECS)'!$F$11,TRUE))} | I13: {=IF($D13,SUMPRODUCT((economics!$AG$2:$AG$167=$B13)*(economics!$D$2:$D$167="whr")*economics!$AH$2:$AH$167*_xlfn.NORM.DIST(I$3,economics!$AK$2:$AK$167,economics!$AJ$2:$AJ$167,TRUE))+$CR13*_xlfn.NORM.DIST(I$3,$CU13,0.3*$CU13,TRUE)+$CS13*_xlfn.NORM.DIST(I$3,$CV13,0.3*$CV13,TRUE),$CW13*_xlfn.NORM.DIST(I$3,'energy base (MECS)'!$F$11,0.3*'energy base (MECS)'!$F$11,TRUE))} | J13: {=IF($D13,SUMPRODUCT((economics!$AG$2:$AG$167=$B13)*(economics!$D$2:$D$167="whr")*economics!$AH$2:$AH$167*_xlfn.NORM.DIST(J$3,economics!$AK$2:$AK$167,economics!$AJ$2:$AJ$167,TRUE))+$CR13*_xlfn.NORM.DIST(J$3,$CU13,0.3*$CU13,TRUE)+$CS13*_xlfn.NORM.DIST(J$3,$CV13,0.3*$CV13,TRUE),$CW13*_xlfn.NORM.DIST(J$3,'energy base (MECS)'!$F$11,0.3*'energy base (MECS)'!$F$11,TRUE))} | K13: {=IF($D13,SUMPRODUCT((economics!$AG$2:$AG$167=$B13)*(economics!$D$2:$D$167="whr")*economics!$AH$2:$AH$167*_xlfn.NORM.DIST(K$3,economics!$AK$2:$AK$167,economics!$AJ$2:$AJ$167,TRUE))+$CR13*_xlfn.NORM.DIST(K$3,$CU13,0.3*$CU13,TRUE)+$CS13*_xlfn.NORM.DIST(K$3,$CV13,0.3*$CV13,TRUE),$CW13*_xlfn.NORM.DIST(K$3,'energy base (MECS)'!$F$11,0.3*'energy base (MECS)'!$F$11,TRUE))} | L13: {=IF($D13,SUMPRODUCT((economics!$AG$2:$AG$167=$B13)*(economics!$D$2:$D$167="whr")*economics!$AH$2:$AH$167*_xlfn.NORM.DIST(L$3,economics!$AK$2:$AK$167,economics!$AJ$2:$AJ$167,TRUE))+$CR13*_xlfn.NORM.DIST(L$3,$CU13,0.3*$CU13,TRUE)+$CS13*_xlfn.NORM.DIST(L$3,$CV13,0.3*$CV13,TRUE),$CW13*_xlfn.NORM.DIST(L$3,'energy base (MECS)'!$F$11,0.3*'energy base (MECS)'!$F$11,TRUE))} | ... CH13: {=IF($D13,SUMPRODUCT((economics!$AG$2:$AG$167=$B13)*(economics!$D$2:$D$167="whr")*economics!$AH$2:$AH$167*_xlfn.NORM.DIST(CH$3,economics!$AK$2:$AK$167,economics!$AJ$2:$AJ$167,TRUE))+$CR13*_xlfn.NORM.DIST(CH$3,$CU13,0.3*$CU13,TRUE)+$CS13*_xlfn.NORM.DIST(CH$3,$CV13,0.3*$CV13,TRUE),$CW13*_xlfn.NORM.DIST(CH$3,'energy base (MECS)'!$F$11,0.3*'energy base (MECS)'!$F$11,TRUE))} | CJ13: {=SUMPRODUCT((economics!$AG$2:$AG$167=$B13)*(economics!$D$2:$D$167="whr")*economics!$AH$2:$AH$167)} | CK13: ='indst heat consumption'!D13 | CL13: ='indst heat consumption'!E13 | CM13: ='indst heat consumption'!F13 | CN13: ='indst heat consumption'!G13 | CO13: ='indst heat consumption'!H13 | CP13: =$C13*(CK13*summary!$B$94+CL13*summary!$C$94+CM13*summary!$D$94) | CQ13: =$C13*(CN13*summary!$E$94+CO13*summary!$F$94) | CR13: =IF(CP13+CQ13>0,CP13*MAX(0,CP13+CQ13-CJ13)/(CP13+CQ13),0) | CS13: =IF(CP13+CQ13>0,CQ13*MAX(0,CP13+CQ13-CJ13)/(CP13+CQ13),0) | CT13: =IFERROR(_xlfn.XLOOKUP($B13,'BCoISC-WACCbI'!$C$2:$C$26,'BCoISC-WACCbI'!$B$2:$B$26)+economics!$AE$4,0.1) | CU13: =(summary!$C$7*(CT13/(1-(1+CT13)^-summary!$D$7))+summary!$C$7*summary!$E$7)/(summary!$F$7*3412/1000000) | CV13: =(summary!$C$6*(CT13/(1-(1+CT13)^-summary!$D$6))+summary!$C$6*summary!$E$6)/(summary!$F$6*3412/1000000) | CW13: =CR13+CS13
A14: =WHRPbI!A12 | B14: 22 | C14: =WHRPbI!B12 | D14: =ISNUMBER(MATCH($B14,'energy base (MECS)'!$K$4:$K$9,0)) | E14: {=IF($D14,SUMPRODUCT((economics!$AG$2:$AG$167=$B14)*(economics!$D$2:$D$167="whr")*economics!$AH$2:$AH$167*_xlfn.NORM.DIST(E$3,economics!$AK$2:$AK$167,economics!$AJ$2:$AJ$167,TRUE))+$CR14*_xlfn.NORM.DIST(E$3,$CU14,0.3*$CU14,TRUE)+$CS14*_xlfn.NORM.DIST(E$3,$CV14,0.3*$CV14,TRUE),$CW14*_xlfn.NORM.DIST(E$3,'energy base (MECS)'!$F$11,0.3*'energy base (MECS)'!$F$11,TRUE))} | F14: {=IF($D14,SUMPRODUCT((economics!$AG$2:$AG$167=$B14)*(economics!$D$2:$D$167="whr")*economics!$AH$2:$AH$167*_xlfn.NORM.DIST(F$3,economics!$AK$2:$AK$167,economics!$AJ$2:$AJ$167,TRUE))+$CR14*_xlfn.NORM.DIST(F$3,$CU14,0.3*$CU14,TRUE)+$CS14*_xlfn.NORM.DIST(F$3,$CV14,0.3*$CV14,TRUE),$CW14*_xlfn.NORM.DIST(F$3,'energy base (MECS)'!$F$11,0.3*'energy base (MECS)'!$F$11,TRUE))} | G14: {=IF($D14,SUMPRODUCT((economics!$AG$2:$AG$167=$B14)*(economics!$D$2:$D$167="whr")*economics!$AH$2:$AH$167*_xlfn.NORM.DIST(G$3,economics!$AK$2:$AK$167,economics!$AJ$2:$AJ$167,TRUE))+$CR14*_xlfn.NORM.DIST(G$3,$CU14,0.3*$CU14,TRUE)+$CS14*_xlfn.NORM.DIST(G$3,$CV14,0.3*$CV14,TRUE),$CW14*_xlfn.NORM.DIST(G$3,'energy base (MECS)'!$F$11,0.3*'energy base (MECS)'!$F$11,TRUE))} | H14: {=IF($D14,SUMPRODUCT((economics!$AG$2:$AG$167=$B14)*(economics!$D$2:$D$167="whr")*economics!$AH$2:$AH$167*_xlfn.NORM.DIST(H$3,economics!$AK$2:$AK$167,economics!$AJ$2:$AJ$167,TRUE))+$CR14*_xlfn.NORM.DIST(H$3,$CU14,0.3*$CU14,TRUE)+$CS14*_xlfn.NORM.DIST(H$3,$CV14,0.3*$CV14,TRUE),$CW14*_xlfn.NORM.DIST(H$3,'energy base (MECS)'!$F$11,0.3*'energy base (MECS)'!$F$11,TRUE))} | I14: {=IF($D14,SUMPRODUCT((economics!$AG$2:$AG$167=$B14)*(economics!$D$2:$D$167="whr")*economics!$AH$2:$AH$167*_xlfn.NORM.DIST(I$3,economics!$AK$2:$AK$167,economics!$AJ$2:$AJ$167,TRUE))+$CR14*_xlfn.NORM.DIST(I$3,$CU14,0.3*$CU14,TRUE)+$CS14*_xlfn.NORM.DIST(I$3,$CV14,0.3*$CV14,TRUE),$CW14*_xlfn.NORM.DIST(I$3,'energy base (MECS)'!$F$11,0.3*'energy base (MECS)'!$F$11,TRUE))} | J14: {=IF($D14,SUMPRODUCT((economics!$AG$2:$AG$167=$B14)*(economics!$D$2:$D$167="whr")*economics!$AH$2:$AH$167*_xlfn.NORM.DIST(J$3,economics!$AK$2:$AK$167,economics!$AJ$2:$AJ$167,TRUE))+$CR14*_xlfn.NORM.DIST(J$3,$CU14,0.3*$CU14,TRUE)+$CS14*_xlfn.NORM.DIST(J$3,$CV14,0.3*$CV14,TRUE),$CW14*_xlfn.NORM.DIST(J$3,'energy base (MECS)'!$F$11,0.3*'energy base (MECS)'!$F$11,TRUE))} | K14: {=IF($D14,SUMPRODUCT((economics!$AG$2:$AG$167=$B14)*(economics!$D$2:$D$167="whr")*economics!$AH$2:$AH$167*_xlfn.NORM.DIST(K$3,economics!$AK$2:$AK$167,economics!$AJ$2:$AJ$167,TRUE))+$CR14*_xlfn.NORM.DIST(K$3,$CU14,0.3*$CU14,TRUE)+$CS14*_xlfn.NORM.DIST(K$3,$CV14,0.3*$CV14,TRUE),$CW14*_xlfn.NORM.DIST(K$3,'energy base (MECS)'!$F$11,0.3*'energy base (MECS)'!$F$11,TRUE))} | L14: {=IF($D14,SUMPRODUCT((economics!$AG$2:$AG$167=$B14)*(economics!$D$2:$D$167="whr")*economics!$AH$2:$AH$167*_xlfn.NORM.DIST(L$3,economics!$AK$2:$AK$167,economics!$AJ$2:$AJ$167,TRUE))+$CR14*_xlfn.NORM.DIST(L$3,$CU14,0.3*$CU14,TRUE)+$CS14*_xlfn.NORM.DIST(L$3,$CV14,0.3*$CV14,TRUE),$CW14*_xlfn.NORM.DIST(L$3,'energy base (MECS)'!$F$11,0.3*'energy base (MECS)'!$F$11,TRUE))} | ... CH14: {=IF($D14,SUMPRODUCT((economics!$AG$2:$AG$167=$B14)*(economics!$D$2:$D$167="whr")*economics!$AH$2:$AH$167*_xlfn.NORM.DIST(CH$3,economics!$AK$2:$AK$167,economics!$AJ$2:$AJ$167,TRUE))+$CR14*_xlfn.NORM.DIST(CH$3,$CU14,0.3*$CU14,TRUE)+$CS14*_xlfn.NORM.DIST(CH$3,$CV14,0.3*$CV14,TRUE),$CW14*_xlfn.NORM.DIST(CH$3,'energy base (MECS)'!$F$11,0.3*'energy base (MECS)'!$F$11,TRUE))} | CJ14: {=SUMPRODUCT((economics!$AG$2:$AG$167=$B14)*(economics!$D$2:$D$167="whr")*economics!$AH$2:$AH$167)} | CK14: ='indst heat consumption'!D14 | CL14: ='indst heat consumption'!E14 | CM14: ='indst heat consumption'!F14 | CN14: ='indst heat consumption'!G14 | CO14: ='indst heat consumption'!H14 | CP14: =$C14*(CK14*summary!$B$94+CL14*summary!$C$94+CM14*summary!$D$94) | CQ14: =$C14*(CN14*summary!$E$94+CO14*summary!$F$94) | CR14: =IF(CP14+CQ14>0,CP14*MAX(0,CP14+CQ14-CJ14)/(CP14+CQ14),0) | CS14: =IF(CP14+CQ14>0,CQ14*MAX(0,CP14+CQ14-CJ14)/(CP14+CQ14),0) | CT14: =IFERROR(_xlfn.XLOOKUP($B14,'BCoISC-WACCbI'!$C$2:$C$26,'BCoISC-WACCbI'!$B$2:$B$26)+economics!$AE$4,0.1) | CU14: =(summary!$C$7*(CT14/(1-(1+CT14)^-summary!$D$7))+summary!$C$7*summary!$E$7)/(summary!$F$7*3412/1000000) | CV14: =(summary!$C$6*(CT14/(1-(1+CT14)^-summary!$D$6))+summary!$C$6*summary!$E$6)/(summary!$F$6*3412/1000000) | CW14: =CR14+CS14
A15: =WHRPbI!A13 | B15: 231 | C15: =WHRPbI!B13 | D15: =ISNUMBER(MATCH($B15,'energy base (MECS)'!$K$4:$K$9,0)) | E15: {=IF($D15,SUMPRODUCT((economics!$AG$2:$AG$167=$B15)*(economics!$D$2:$D$167="whr")*economics!$AH$2:$AH$167*_xlfn.NORM.DIST(E$3,economics!$AK$2:$AK$167,economics!$AJ$2:$AJ$167,TRUE))+$CR15*_xlfn.NORM.DIST(E$3,$CU15,0.3*$CU15,TRUE)+$CS15*_xlfn.NORM.DIST(E$3,$CV15,0.3*$CV15,TRUE),$CW15*_xlfn.NORM.DIST(E$3,'energy base (MECS)'!$F$11,0.3*'energy base (MECS)'!$F$11,TRUE))} | F15: {=IF($D15,SUMPRODUCT((economics!$AG$2:$AG$167=$B15)*(economics!$D$2:$D$167="whr")*economics!$AH$2:$AH$167*_xlfn.NORM.DIST(F$3,economics!$AK$2:$AK$167,economics!$AJ$2:$AJ$167,TRUE))+$CR15*_xlfn.NORM.DIST(F$3,$CU15,0.3*$CU15,TRUE)+$CS15*_xlfn.NORM.DIST(F$3,$CV15,0.3*$CV15,TRUE),$CW15*_xlfn.NORM.DIST(F$3,'energy base (MECS)'!$F$11,0.3*'energy base (MECS)'!$F$11,TRUE))} | G15: {=IF($D15,SUMPRODUCT((economics!$AG$2:$AG$167=$B15)*(economics!$D$2:$D$167="whr")*economics!$AH$2:$AH$167*_xlfn.NORM.DIST(G$3,economics!$AK$2:$AK$167,economics!$AJ$2:$AJ$167,TRUE))+$CR15*_xlfn.NORM.DIST(G$3,$CU15,0.3*$CU15,TRUE)+$CS15*_xlfn.NORM.DIST(G$3,$CV15,0.3*$CV15,TRUE),$CW15*_xlfn.NORM.DIST(G$3,'energy base (MECS)'!$F$11,0.3*'energy base (MECS)'!$F$11,TRUE))} | H15: {=IF($D15,SUMPRODUCT((economics!$AG$2:$AG$167=$B15)*(economics!$D$2:$D$167="whr")*economics!$AH$2:$AH$167*_xlfn.NORM.DIST(H$3,economics!$AK$2:$AK$167,economics!$AJ$2:$AJ$167,TRUE))+$CR15*_xlfn.NORM.DIST(H$3,$CU15,0.3*$CU15,TRUE)+$CS15*_xlfn.NORM.DIST(H$3,$CV15,0.3*$CV15,TRUE),$CW15*_xlfn.NORM.DIST(H$3,'energy base (MECS)'!$F$11,0.3*'energy base (MECS)'!$F$11,TRUE))} | I15: {=IF($D15,SUMPRODUCT((economics!$AG$2:$AG$167=$B15)*(economics!$D$2:$D$167="whr")*economics!$AH$2:$AH$167*_xlfn.NORM.DIST(I$3,economics!$AK$2:$AK$167,economics!$AJ$2:$AJ$167,TRUE))+$CR15*_xlfn.NORM.DIST(I$3,$CU15,0.3*$CU15,TRUE)+$CS15*_xlfn.NORM.DIST(I$3,$CV15,0.3*$CV15,TRUE),$CW15*_xlfn.NORM.DIST(I$3,'energy base (MECS)'!$F$11,0.3*'energy base (MECS)'!$F$11,TRUE))} | J15: {=IF($D15,SUMPRODUCT((economics!$AG$2:$AG$167=$B15)*(economics!$D$2:$D$167="whr")*economics!$AH$2:$AH$167*_xlfn.NORM.DIST(J$3,economics!$AK$2:$AK$167,economics!$AJ$2:$AJ$167,TRUE))+$CR15*_xlfn.NORM.DIST(J$3,$CU15,0.3*$CU15,TRUE)+$CS15*_xlfn.NORM.DIST(J$3,$CV15,0.3*$CV15,TRUE),$CW15*_xlfn.NORM.DIST(J$3,'energy base (MECS)'!$F$11,0.3*'energy base (MECS)'!$F$11,TRUE))} | K15: {=IF($D15,SUMPRODUCT((economics!$AG$2:$AG$167=$B15)*(economics!$D$2:$D$167="whr")*economics!$AH$2:$AH$167*_xlfn.NORM.DIST(K$3,economics!$AK$2:$AK$167,economics!$AJ$2:$AJ$167,TRUE))+$CR15*_xlfn.NORM.DIST(K$3,$CU15,0.3*$CU15,TRUE)+$CS15*_xlfn.NORM.DIST(K$3,$CV15,0.3*$CV15,TRUE),$CW15*_xlfn.NORM.DIST(K$3,'energy base (MECS)'!$F$11,0.3*'energy base (MECS)'!$F$11,TRUE))} | L15: {=IF($D15,SUMPRODUCT((economics!$AG$2:$AG$167=$B15)*(economics!$D$2:$D$167="whr")*economics!$AH$2:$AH$167*_xlfn.NORM.DIST(L$3,economics!$AK$2:$AK$167,economics!$AJ$2:$AJ$167,TRUE))+$CR15*_xlfn.NORM.DIST(L$3,$CU15,0.3*$CU15,TRUE)+$CS15*_xlfn.NORM.DIST(L$3,$CV15,0.3*$CV15,TRUE),$CW15*_xlfn.NORM.DIST(L$3,'energy base (MECS)'!$F$11,0.3*'energy base (MECS)'!$F$11,TRUE))} | ... CH15: {=IF($D15,SUMPRODUCT((economics!$AG$2:$AG$167=$B15)*(economics!$D$2:$D$167="whr")*economics!$AH$2:$AH$167*_xlfn.NORM.DIST(CH$3,economics!$AK$2:$AK$167,economics!$AJ$2:$AJ$167,TRUE))+$CR15*_xlfn.NORM.DIST(CH$3,$CU15,0.3*$CU15,TRUE)+$CS15*_xlfn.NORM.DIST(CH$3,$CV15,0.3*$CV15,TRUE),$CW15*_xlfn.NORM.DIST(CH$3,'energy base (MECS)'!$F$11,0.3*'energy base (MECS)'!$F$11,TRUE))} | CJ15: {=SUMPRODUCT((economics!$AG$2:$AG$167=$B15)*(economics!$D$2:$D$167="whr")*economics!$AH$2:$AH$167)} | CK15: ='indst heat consumption'!D15 | CL15: ='indst heat consumption'!E15 | CM15: ='indst heat consumption'!F15 | CN15: ='indst heat consumption'!G15 | CO15: ='indst heat consumption'!H15 | CP15: =$C15*(CK15*summary!$B$94+CL15*summary!$C$94+CM15*summary!$D$94) | CQ15: =$C15*(CN15*summary!$E$94+CO15*summary!$F$94) | CR15: =IF(CP15+CQ15>0,CP15*MAX(0,CP15+CQ15-CJ15)/(CP15+CQ15),0) | CS15: =IF(CP15+CQ15>0,CQ15*MAX(0,CP15+CQ15-CJ15)/(CP15+CQ15),0) | CT15: =IFERROR(_xlfn.XLOOKUP($B15,'BCoISC-WACCbI'!$C$2:$C$26,'BCoISC-WACCbI'!$B$2:$B$26)+economics!$AE$4,0.1) | CU15: =(summary!$C$7*(CT15/(1-(1+CT15)^-summary!$D$7))+summary!$C$7*summary!$E$7)/(summary!$F$7*3412/1000000) | CV15: =(summary!$C$6*(CT15/(1-(1+CT15)^-summary!$D$6))+summary!$C$6*summary!$E$6)/(summary!$F$6*3412/1000000) | CW15: =CR15+CS15
A16: =WHRPbI!A14 | B16: 239 | C16: =WHRPbI!B14 | D16: =ISNUMBER(MATCH($B16,'energy base (MECS)'!$K$4:$K$9,0)) | E16: {=IF($D16,SUMPRODUCT((economics!$AG$2:$AG$167=$B16)*(economics!$D$2:$D$167="whr")*economics!$AH$2:$AH$167*_xlfn.NORM.DIST(E$3,economics!$AK$2:$AK$167,economics!$AJ$2:$AJ$167,TRUE))+$CR16*_xlfn.NORM.DIST(E$3,$CU16,0.3*$CU16,TRUE)+$CS16*_xlfn.NORM.DIST(E$3,$CV16,0.3*$CV16,TRUE),$CW16*_xlfn.NORM.DIST(E$3,'energy base (MECS)'!$F$11,0.3*'energy base (MECS)'!$F$11,TRUE))} | F16: {=IF($D16,SUMPRODUCT((economics!$AG$2:$AG$167=$B16)*(economics!$D$2:$D$167="whr")*economics!$AH$2:$AH$167*_xlfn.NORM.DIST(F$3,economics!$AK$2:$AK$167,economics!$AJ$2:$AJ$167,TRUE))+$CR16*_xlfn.NORM.DIST(F$3,$CU16,0.3*$CU16,TRUE)+$CS16*_xlfn.NORM.DIST(F$3,$CV16,0.3*$CV16,TRUE),$CW16*_xlfn.NORM.DIST(F$3,'energy base (MECS)'!$F$11,0.3*'energy base (MECS)'!$F$11,TRUE))} | G16: {=IF($D16,SUMPRODUCT((economics!$AG$2:$AG$167=$B16)*(economics!$D$2:$D$167="whr")*economics!$AH$2:$AH$167*_xlfn.NORM.DIST(G$3,economics!$AK$2:$AK$167,economics!$AJ$2:$AJ$167,TRUE))+$CR16*_xlfn.NORM.DIST(G$3,$CU16,0.3*$CU16,TRUE)+$CS16*_xlfn.NORM.DIST(G$3,$CV16,0.3*$CV16,TRUE),$CW16*_xlfn.NORM.DIST(G$3,'energy base (MECS)'!$F$11,0.3*'energy base (MECS)'!$F$11,TRUE))} | H16: {=IF($D16,SUMPRODUCT((economics!$AG$2:$AG$167=$B16)*(economics!$D$2:$D$167="whr")*economics!$AH$2:$AH$167*_xlfn.NORM.DIST(H$3,economics!$AK$2:$AK$167,economics!$AJ$2:$AJ$167,TRUE))+$CR16*_xlfn.NORM.DIST(H$3,$CU16,0.3*$CU16,TRUE)+$CS16*_xlfn.NORM.DIST(H$3,$CV16,0.3*$CV16,TRUE),$CW16*_xlfn.NORM.DIST(H$3,'energy base (MECS)'!$F$11,0.3*'energy base (MECS)'!$F$11,TRUE))} | I16: {=IF($D16,SUMPRODUCT((economics!$AG$2:$AG$167=$B16)*(economics!$D$2:$D$167="whr")*economics!$AH$2:$AH$167*_xlfn.NORM.DIST(I$3,economics!$AK$2:$AK$167,economics!$AJ$2:$AJ$167,TRUE))+$CR16*_xlfn.NORM.DIST(I$3,$CU16,0.3*$CU16,TRUE)+$CS16*_xlfn.NORM.DIST(I$3,$CV16,0.3*$CV16,TRUE),$CW16*_xlfn.NORM.DIST(I$3,'energy base (MECS)'!$F$11,0.3*'energy base (MECS)'!$F$11,TRUE))} | J16: {=IF($D16,SUMPRODUCT((economics!$AG$2:$AG$167=$B16)*(economics!$D$2:$D$167="whr")*economics!$AH$2:$AH$167*_xlfn.NORM.DIST(J$3,economics!$AK$2:$AK$167,economics!$AJ$2:$AJ$167,TRUE))+$CR16*_xlfn.NORM.DIST(J$3,$CU16,0.3*$CU16,TRUE)+$CS16*_xlfn.NORM.DIST(J$3,$CV16,0.3*$CV16,TRUE),$CW16*_xlfn.NORM.DIST(J$3,'energy base (MECS)'!$F$11,0.3*'energy base (MECS)'!$F$11,TRUE))} | K16: {=IF($D16,SUMPRODUCT((economics!$AG$2:$AG$167=$B16)*(economics!$D$2:$D$167="whr")*economics!$AH$2:$AH$167*_xlfn.NORM.DIST(K$3,economics!$AK$2:$AK$167,economics!$AJ$2:$AJ$167,TRUE))+$CR16*_xlfn.NORM.DIST(K$3,$CU16,0.3*$CU16,TRUE)+$CS16*_xlfn.NORM.DIST(K$3,$CV16,0.3*$CV16,TRUE),$CW16*_xlfn.NORM.DIST(K$3,'energy base (MECS)'!$F$11,0.3*'energy base (MECS)'!$F$11,TRUE))} | L16: {=IF($D16,SUMPRODUCT((economics!$AG$2:$AG$167=$B16)*(economics!$D$2:$D$167="whr")*economics!$AH$2:$AH$167*_xlfn.NORM.DIST(L$3,economics!$AK$2:$AK$167,economics!$AJ$2:$AJ$167,TRUE))+$CR16*_xlfn.NORM.DIST(L$3,$CU16,0.3*$CU16,TRUE)+$CS16*_xlfn.NORM.DIST(L$3,$CV16,0.3*$CV16,TRUE),$CW16*_xlfn.NORM.DIST(L$3,'energy base (MECS)'!$F$11,0.3*'energy base (MECS)'!$F$11,TRUE))} | ... CH16: {=IF($D16,SUMPRODUCT((economics!$AG$2:$AG$167=$B16)*(economics!$D$2:$D$167="whr")*economics!$AH$2:$AH$167*_xlfn.NORM.DIST(CH$3,economics!$AK$2:$AK$167,economics!$AJ$2:$AJ$167,TRUE))+$CR16*_xlfn.NORM.DIST(CH$3,$CU16,0.3*$CU16,TRUE)+$CS16*_xlfn.NORM.DIST(CH$3,$CV16,0.3*$CV16,TRUE),$CW16*_xlfn.NORM.DIST(CH$3,'energy base (MECS)'!$F$11,0.3*'energy base (MECS)'!$F$11,TRUE))} | CJ16: {=SUMPRODUCT((economics!$AG$2:$AG$167=$B16)*(economics!$D$2:$D$167="whr")*economics!$AH$2:$AH$167)} | CK16: ='indst heat consumption'!D16 | CL16: ='indst heat consumption'!E16 | CM16: ='indst heat consumption'!F16 | CN16: ='indst heat consumption'!G16 | CO16: ='indst heat consumption'!H16 | CP16: =$C16*(CK16*summary!$B$94+CL16*summary!$C$94+CM16*summary!$D$94) | CQ16: =$C16*(CN16*summary!$E$94+CO16*summary!$F$94) | CR16: =IF(CP16+CQ16>0,CP16*MAX(0,CP16+CQ16-CJ16)/(CP16+CQ16),0) | CS16: =IF(CP16+CQ16>0,CQ16*MAX(0,CP16+CQ16-CJ16)/(CP16+CQ16),0) | CT16: =IFERROR(_xlfn.XLOOKUP($B16,'BCoISC-WACCbI'!$C$2:$C$26,'BCoISC-WACCbI'!$B$2:$B$26)+economics!$AE$4,0.1) | CU16: =(summary!$C$7*(CT16/(1-(1+CT16)^-summary!$D$7))+summary!$C$7*summary!$E$7)/(summary!$F$7*3412/1000000) | CV16: =(summary!$C$6*(CT16/(1-(1+CT16)^-summary!$D$6))+summary!$C$6*summary!$E$6)/(summary!$F$6*3412/1000000) | CW16: =CR16+CS16
A17: =WHRPbI!A15 | B17: 241 | C17: =WHRPbI!B15 | D17: =ISNUMBER(MATCH($B17,'energy base (MECS)'!$K$4:$K$9,0)) | E17: {=IF($D17,SUMPRODUCT((economics!$AG$2:$AG$167=$B17)*(economics!$D$2:$D$167="whr")*economics!$AH$2:$AH$167*_xlfn.NORM.DIST(E$3,economics!$AK$2:$AK$167,economics!$AJ$2:$AJ$167,TRUE))+$CR17*_xlfn.NORM.DIST(E$3,$CU17,0.3*$CU17,TRUE)+$CS17*_xlfn.NORM.DIST(E$3,$CV17,0.3*$CV17,TRUE),$CW17*_xlfn.NORM.DIST(E$3,'energy base (MECS)'!$F$11,0.3*'energy base (MECS)'!$F$11,TRUE))} | F17: {=IF($D17,SUMPRODUCT((economics!$AG$2:$AG$167=$B17)*(economics!$D$2:$D$167="whr")*economics!$AH$2:$AH$167*_xlfn.NORM.DIST(F$3,economics!$AK$2:$AK$167,economics!$AJ$2:$AJ$167,TRUE))+$CR17*_xlfn.NORM.DIST(F$3,$CU17,0.3*$CU17,TRUE)+$CS17*_xlfn.NORM.DIST(F$3,$CV17,0.3*$CV17,TRUE),$CW17*_xlfn.NORM.DIST(F$3,'energy base (MECS)'!$F$11,0.3*'energy base (MECS)'!$F$11,TRUE))} | G17: {=IF($D17,SUMPRODUCT((economics!$AG$2:$AG$167=$B17)*(economics!$D$2:$D$167="whr")*economics!$AH$2:$AH$167*_xlfn.NORM.DIST(G$3,economics!$AK$2:$AK$167,economics!$AJ$2:$AJ$167,TRUE))+$CR17*_xlfn.NORM.DIST(G$3,$CU17,0.3*$CU17,TRUE)+$CS17*_xlfn.NORM.DIST(G$3,$CV17,0.3*$CV17,TRUE),$CW17*_xlfn.NORM.DIST(G$3,'energy base (MECS)'!$F$11,0.3*'energy base (MECS)'!$F$11,TRUE))} | H17: {=IF($D17,SUMPRODUCT((economics!$AG$2:$AG$167=$B17)*(economics!$D$2:$D$167="whr")*economics!$AH$2:$AH$167*_xlfn.NORM.DIST(H$3,economics!$AK$2:$AK$167,economics!$AJ$2:$AJ$167,TRUE))+$CR17*_xlfn.NORM.DIST(H$3,$CU17,0.3*$CU17,TRUE)+$CS17*_xlfn.NORM.DIST(H$3,$CV17,0.3*$CV17,TRUE),$CW17*_xlfn.NORM.DIST(H$3,'energy base (MECS)'!$F$11,0.3*'energy base (MECS)'!$F$11,TRUE))} | I17: {=IF($D17,SUMPRODUCT((economics!$AG$2:$AG$167=$B17)*(economics!$D$2:$D$167="whr")*economics!$AH$2:$AH$167*_xlfn.NORM.DIST(I$3,economics!$AK$2:$AK$167,economics!$AJ$2:$AJ$167,TRUE))+$CR17*_xlfn.NORM.DIST(I$3,$CU17,0.3*$CU17,TRUE)+$CS17*_xlfn.NORM.DIST(I$3,$CV17,0.3*$CV17,TRUE),$CW17*_xlfn.NORM.DIST(I$3,'energy base (MECS)'!$F$11,0.3*'energy base (MECS)'!$F$11,TRUE))} | J17: {=IF($D17,SUMPRODUCT((economics!$AG$2:$AG$167=$B17)*(economics!$D$2:$D$167="whr")*economics!$AH$2:$AH$167*_xlfn.NORM.DIST(J$3,economics!$AK$2:$AK$167,economics!$AJ$2:$AJ$167,TRUE))+$CR17*_xlfn.NORM.DIST(J$3,$CU17,0.3*$CU17,TRUE)+$CS17*_xlfn.NORM.DIST(J$3,$CV17,0.3*$CV17,TRUE),$CW17*_xlfn.NORM.DIST(J$3,'energy base (MECS)'!$F$11,0.3*'energy base (MECS)'!$F$11,TRUE))} | K17: {=IF($D17,SUMPRODUCT((economics!$AG$2:$AG$167=$B17)*(economics!$D$2:$D$167="whr")*economics!$AH$2:$AH$167*_xlfn.NORM.DIST(K$3,economics!$AK$2:$AK$167,economics!$AJ$2:$AJ$167,TRUE))+$CR17*_xlfn.NORM.DIST(K$3,$CU17,0.3*$CU17,TRUE)+$CS17*_xlfn.NORM.DIST(K$3,$CV17,0.3*$CV17,TRUE),$CW17*_xlfn.NORM.DIST(K$3,'energy base (MECS)'!$F$11,0.3*'energy base (MECS)'!$F$11,TRUE))} | L17: {=IF($D17,SUMPRODUCT((economics!$AG$2:$AG$167=$B17)*(economics!$D$2:$D$167="whr")*economics!$AH$2:$AH$167*_xlfn.NORM.DIST(L$3,economics!$AK$2:$AK$167,economics!$AJ$2:$AJ$167,TRUE))+$CR17*_xlfn.NORM.DIST(L$3,$CU17,0.3*$CU17,TRUE)+$CS17*_xlfn.NORM.DIST(L$3,$CV17,0.3*$CV17,TRUE),$CW17*_xlfn.NORM.DIST(L$3,'energy base (MECS)'!$F$11,0.3*'energy base (MECS)'!$F$11,TRUE))} | ... CH17: {=IF($D17,SUMPRODUCT((economics!$AG$2:$AG$167=$B17)*(economics!$D$2:$D$167="whr")*economics!$AH$2:$AH$167*_xlfn.NORM.DIST(CH$3,economics!$AK$2:$AK$167,economics!$AJ$2:$AJ$167,TRUE))+$CR17*_xlfn.NORM.DIST(CH$3,$CU17,0.3*$CU17,TRUE)+$CS17*_xlfn.NORM.DIST(CH$3,$CV17,0.3*$CV17,TRUE),$CW17*_xlfn.NORM.DIST(CH$3,'energy base (MECS)'!$F$11,0.3*'energy base (MECS)'!$F$11,TRUE))} | CJ17: {=SUMPRODUCT((economics!$AG$2:$AG$167=$B17)*(economics!$D$2:$D$167="whr")*economics!$AH$2:$AH$167)} | CK17: ='indst heat consumption'!D17 | CL17: ='indst heat consumption'!E17 | CM17: ='indst heat consumption'!F17 | CN17: ='indst heat consumption'!G17 | CO17: ='indst heat consumption'!H17 | CP17: =$C17*(CK17*summary!$B$94+CL17*summary!$C$94+CM17*summary!$D$94) | CQ17: =$C17*(CN17*summary!$E$94+CO17*summary!$F$94) | CR17: =IF(CP17+CQ17>0,CP17*MAX(0,CP17+CQ17-CJ17)/(CP17+CQ17),0) | CS17: =IF(CP17+CQ17>0,CQ17*MAX(0,CP17+CQ17-CJ17)/(CP17+CQ17),0) | CT17: =IFERROR(_xlfn.XLOOKUP($B17,'BCoISC-WACCbI'!$C$2:$C$26,'BCoISC-WACCbI'!$B$2:$B$26)+economics!$AE$4,0.1) | CU17: =(summary!$C$7*(CT17/(1-(1+CT17)^-summary!$D$7))+summary!$C$7*summary!$E$7)/(summary!$F$7*3412/1000000) | CV17: =(summary!$C$6*(CT17/(1-(1+CT17)^-summary!$D$6))+summary!$C$6*summary!$E$6)/(summary!$F$6*3412/1000000) | CW17: =CR17+CS17
A18: =WHRPbI!A16 | B18: 242 | C18: =WHRPbI!B16 | D18: =ISNUMBER(MATCH($B18,'energy base (MECS)'!$K$4:$K$9,0)) | E18: {=IF($D18,SUMPRODUCT((economics!$AG$2:$AG$167=$B18)*(economics!$D$2:$D$167="whr")*economics!$AH$2:$AH$167*_xlfn.NORM.DIST(E$3,economics!$AK$2:$AK$167,economics!$AJ$2:$AJ$167,TRUE))+$CR18*_xlfn.NORM.DIST(E$3,$CU18,0.3*$CU18,TRUE)+$CS18*_xlfn.NORM.DIST(E$3,$CV18,0.3*$CV18,TRUE),$CW18*_xlfn.NORM.DIST(E$3,'energy base (MECS)'!$F$11,0.3*'energy base (MECS)'!$F$11,TRUE))} | F18: {=IF($D18,SUMPRODUCT((economics!$AG$2:$AG$167=$B18)*(economics!$D$2:$D$167="whr")*economics!$AH$2:$AH$167*_xlfn.NORM.DIST(F$3,economics!$AK$2:$AK$167,economics!$AJ$2:$AJ$167,TRUE))+$CR18*_xlfn.NORM.DIST(F$3,$CU18,0.3*$CU18,TRUE)+$CS18*_xlfn.NORM.DIST(F$3,$CV18,0.3*$CV18,TRUE),$CW18*_xlfn.NORM.DIST(F$3,'energy base (MECS)'!$F$11,0.3*'energy base (MECS)'!$F$11,TRUE))} | G18: {=IF($D18,SUMPRODUCT((economics!$AG$2:$AG$167=$B18)*(economics!$D$2:$D$167="whr")*economics!$AH$2:$AH$167*_xlfn.NORM.DIST(G$3,economics!$AK$2:$AK$167,economics!$AJ$2:$AJ$167,TRUE))+$CR18*_xlfn.NORM.DIST(G$3,$CU18,0.3*$CU18,TRUE)+$CS18*_xlfn.NORM.DIST(G$3,$CV18,0.3*$CV18,TRUE),$CW18*_xlfn.NORM.DIST(G$3,'energy base (MECS)'!$F$11,0.3*'energy base (MECS)'!$F$11,TRUE))} | H18: {=IF($D18,SUMPRODUCT((economics!$AG$2:$AG$167=$B18)*(economics!$D$2:$D$167="whr")*economics!$AH$2:$AH$167*_xlfn.NORM.DIST(H$3,economics!$AK$2:$AK$167,economics!$AJ$2:$AJ$167,TRUE))+$CR18*_xlfn.NORM.DIST(H$3,$CU18,0.3*$CU18,TRUE)+$CS18*_xlfn.NORM.DIST(H$3,$CV18,0.3*$CV18,TRUE),$CW18*_xlfn.NORM.DIST(H$3,'energy base (MECS)'!$F$11,0.3*'energy base (MECS)'!$F$11,TRUE))} | I18: {=IF($D18,SUMPRODUCT((economics!$AG$2:$AG$167=$B18)*(economics!$D$2:$D$167="whr")*economics!$AH$2:$AH$167*_xlfn.NORM.DIST(I$3,economics!$AK$2:$AK$167,economics!$AJ$2:$AJ$167,TRUE))+$CR18*_xlfn.NORM.DIST(I$3,$CU18,0.3*$CU18,TRUE)+$CS18*_xlfn.NORM.DIST(I$3,$CV18,0.3*$CV18,TRUE),$CW18*_xlfn.NORM.DIST(I$3,'energy base (MECS)'!$F$11,0.3*'energy base (MECS)'!$F$11,TRUE))} | J18: {=IF($D18,SUMPRODUCT((economics!$AG$2:$AG$167=$B18)*(economics!$D$2:$D$167="whr")*economics!$AH$2:$AH$167*_xlfn.NORM.DIST(J$3,economics!$AK$2:$AK$167,economics!$AJ$2:$AJ$167,TRUE))+$CR18*_xlfn.NORM.DIST(J$3,$CU18,0.3*$CU18,TRUE)+$CS18*_xlfn.NORM.DIST(J$3,$CV18,0.3*$CV18,TRUE),$CW18*_xlfn.NORM.DIST(J$3,'energy base (MECS)'!$F$11,0.3*'energy base (MECS)'!$F$11,TRUE))} | K18: {=IF($D18,SUMPRODUCT((economics!$AG$2:$AG$167=$B18)*(economics!$D$2:$D$167="whr")*economics!$AH$2:$AH$167*_xlfn.NORM.DIST(K$3,economics!$AK$2:$AK$167,economics!$AJ$2:$AJ$167,TRUE))+$CR18*_xlfn.NORM.DIST(K$3,$CU18,0.3*$CU18,TRUE)+$CS18*_xlfn.NORM.DIST(K$3,$CV18,0.3*$CV18,TRUE),$CW18*_xlfn.NORM.DIST(K$3,'energy base (MECS)'!$F$11,0.3*'energy base (MECS)'!$F$11,TRUE))} | L18: {=IF($D18,SUMPRODUCT((economics!$AG$2:$AG$167=$B18)*(economics!$D$2:$D$167="whr")*economics!$AH$2:$AH$167*_xlfn.NORM.DIST(L$3,economics!$AK$2:$AK$167,economics!$AJ$2:$AJ$167,TRUE))+$CR18*_xlfn.NORM.DIST(L$3,$CU18,0.3*$CU18,TRUE)+$CS18*_xlfn.NORM.DIST(L$3,$CV18,0.3*$CV18,TRUE),$CW18*_xlfn.NORM.DIST(L$3,'energy base (MECS)'!$F$11,0.3*'energy base (MECS)'!$F$11,TRUE))} | ... CH18: {=IF($D18,SUMPRODUCT((economics!$AG$2:$AG$167=$B18)*(economics!$D$2:$D$167="whr")*economics!$AH$2:$AH$167*_xlfn.NORM.DIST(CH$3,economics!$AK$2:$AK$167,economics!$AJ$2:$AJ$167,TRUE))+$CR18*_xlfn.NORM.DIST(CH$3,$CU18,0.3*$CU18,TRUE)+$CS18*_xlfn.NORM.DIST(CH$3,$CV18,0.3*$CV18,TRUE),$CW18*_xlfn.NORM.DIST(CH$3,'energy base (MECS)'!$F$11,0.3*'energy base (MECS)'!$F$11,TRUE))} | CJ18: {=SUMPRODUCT((economics!$AG$2:$AG$167=$B18)*(economics!$D$2:$D$167="whr")*economics!$AH$2:$AH$167)} | CK18: ='indst heat consumption'!D18 | CL18: ='indst heat consumption'!E18 | CM18: ='indst heat consumption'!F18 | CN18: ='indst heat consumption'!G18 | CO18: ='indst heat consumption'!H18 | CP18: =$C18*(CK18*summary!$B$94+CL18*summary!$C$94+CM18*summary!$D$94) | CQ18: =$C18*(CN18*summary!$E$94+CO18*summary!$F$94) | CR18: =IF(CP18+CQ18>0,CP18*MAX(0,CP18+CQ18-CJ18)/(CP18+CQ18),0) | CS18: =IF(CP18+CQ18>0,CQ18*MAX(0,CP18+CQ18-CJ18)/(CP18+CQ18),0) | CT18: =IFERROR(_xlfn.XLOOKUP($B18,'BCoISC-WACCbI'!$C$2:$C$26,'BCoISC-WACCbI'!$B$2:$B$26)+economics!$AE$4,0.1) | CU18: =(summary!$C$7*(CT18/(1-(1+CT18)^-summary!$D$7))+summary!$C$7*summary!$E$7)/(summary!$F$7*3412/1000000) | CV18: =(summary!$C$6*(CT18/(1-(1+CT18)^-summary!$D$6))+summary!$C$6*summary!$E$6)/(summary!$F$6*3412/1000000) | CW18: =CR18+CS18
A19: =WHRPbI!A17 | B19: 25 | C19: =WHRPbI!B17 | D19: =ISNUMBER(MATCH($B19,'energy base (MECS)'!$K$4:$K$9,0)) | E19: {=IF($D19,SUMPRODUCT((economics!$AG$2:$AG$167=$B19)*(economics!$D$2:$D$167="whr")*economics!$AH$2:$AH$167*_xlfn.NORM.DIST(E$3,economics!$AK$2:$AK$167,economics!$AJ$2:$AJ$167,TRUE))+$CR19*_xlfn.NORM.DIST(E$3,$CU19,0.3*$CU19,TRUE)+$CS19*_xlfn.NORM.DIST(E$3,$CV19,0.3*$CV19,TRUE),$CW19*_xlfn.NORM.DIST(E$3,'energy base (MECS)'!$F$11,0.3*'energy base (MECS)'!$F$11,TRUE))} | F19: {=IF($D19,SUMPRODUCT((economics!$AG$2:$AG$167=$B19)*(economics!$D$2:$D$167="whr")*economics!$AH$2:$AH$167*_xlfn.NORM.DIST(F$3,economics!$AK$2:$AK$167,economics!$AJ$2:$AJ$167,TRUE))+$CR19*_xlfn.NORM.DIST(F$3,$CU19,0.3*$CU19,TRUE)+$CS19*_xlfn.NORM.DIST(F$3,$CV19,0.3*$CV19,TRUE),$CW19*_xlfn.NORM.DIST(F$3,'energy base (MECS)'!$F$11,0.3*'energy base (MECS)'!$F$11,TRUE))} | G19: {=IF($D19,SUMPRODUCT((economics!$AG$2:$AG$167=$B19)*(economics!$D$2:$D$167="whr")*economics!$AH$2:$AH$167*_xlfn.NORM.DIST(G$3,economics!$AK$2:$AK$167,economics!$AJ$2:$AJ$167,TRUE))+$CR19*_xlfn.NORM.DIST(G$3,$CU19,0.3*$CU19,TRUE)+$CS19*_xlfn.NORM.DIST(G$3,$CV19,0.3*$CV19,TRUE),$CW19*_xlfn.NORM.DIST(G$3,'energy base (MECS)'!$F$11,0.3*'energy base (MECS)'!$F$11,TRUE))} | H19: {=IF($D19,SUMPRODUCT((economics!$AG$2:$AG$167=$B19)*(economics!$D$2:$D$167="whr")*economics!$AH$2:$AH$167*_xlfn.NORM.DIST(H$3,economics!$AK$2:$AK$167,economics!$AJ$2:$AJ$167,TRUE))+$CR19*_xlfn.NORM.DIST(H$3,$CU19,0.3*$CU19,TRUE)+$CS19*_xlfn.NORM.DIST(H$3,$CV19,0.3*$CV19,TRUE),$CW19*_xlfn.NORM.DIST(H$3,'energy base (MECS)'!$F$11,0.3*'energy base (MECS)'!$F$11,TRUE))} | I19: {=IF($D19,SUMPRODUCT((economics!$AG$2:$AG$167=$B19)*(economics!$D$2:$D$167="whr")*economics!$AH$2:$AH$167*_xlfn.NORM.DIST(I$3,economics!$AK$2:$AK$167,economics!$AJ$2:$AJ$167,TRUE))+$CR19*_xlfn.NORM.DIST(I$3,$CU19,0.3*$CU19,TRUE)+$CS19*_xlfn.NORM.DIST(I$3,$CV19,0.3*$CV19,TRUE),$CW19*_xlfn.NORM.DIST(I$3,'energy base (MECS)'!$F$11,0.3*'energy base (MECS)'!$F$11,TRUE))} | J19: {=IF($D19,SUMPRODUCT((economics!$AG$2:$AG$167=$B19)*(economics!$D$2:$D$167="whr")*economics!$AH$2:$AH$167*_xlfn.NORM.DIST(J$3,economics!$AK$2:$AK$167,economics!$AJ$2:$AJ$167,TRUE))+$CR19*_xlfn.NORM.DIST(J$3,$CU19,0.3*$CU19,TRUE)+$CS19*_xlfn.NORM.DIST(J$3,$CV19,0.3*$CV19,TRUE),$CW19*_xlfn.NORM.DIST(J$3,'energy base (MECS)'!$F$11,0.3*'energy base (MECS)'!$F$11,TRUE))} | K19: {=IF($D19,SUMPRODUCT((economics!$AG$2:$AG$167=$B19)*(economics!$D$2:$D$167="whr")*economics!$AH$2:$AH$167*_xlfn.NORM.DIST(K$3,economics!$AK$2:$AK$167,economics!$AJ$2:$AJ$167,TRUE))+$CR19*_xlfn.NORM.DIST(K$3,$CU19,0.3*$CU19,TRUE)+$CS19*_xlfn.NORM.DIST(K$3,$CV19,0.3*$CV19,TRUE),$CW19*_xlfn.NORM.DIST(K$3,'energy base (MECS)'!$F$11,0.3*'energy base (MECS)'!$F$11,TRUE))} | L19: {=IF($D19,SUMPRODUCT((economics!$AG$2:$AG$167=$B19)*(economics!$D$2:$D$167="whr")*economics!$AH$2:$AH$167*_xlfn.NORM.DIST(L$3,economics!$AK$2:$AK$167,economics!$AJ$2:$AJ$167,TRUE))+$CR19*_xlfn.NORM.DIST(L$3,$CU19,0.3*$CU19,TRUE)+$CS19*_xlfn.NORM.DIST(L$3,$CV19,0.3*$CV19,TRUE),$CW19*_xlfn.NORM.DIST(L$3,'energy base (MECS)'!$F$11,0.3*'energy base (MECS)'!$F$11,TRUE))} | ... CH19: {=IF($D19,SUMPRODUCT((economics!$AG$2:$AG$167=$B19)*(economics!$D$2:$D$167="whr")*economics!$AH$2:$AH$167*_xlfn.NORM.DIST(CH$3,economics!$AK$2:$AK$167,economics!$AJ$2:$AJ$167,TRUE))+$CR19*_xlfn.NORM.DIST(CH$3,$CU19,0.3*$CU19,TRUE)+$CS19*_xlfn.NORM.DIST(CH$3,$CV19,0.3*$CV19,TRUE),$CW19*_xlfn.NORM.DIST(CH$3,'energy base (MECS)'!$F$11,0.3*'energy base (MECS)'!$F$11,TRUE))} | CJ19: {=SUMPRODUCT((economics!$AG$2:$AG$167=$B19)*(economics!$D$2:$D$167="whr")*economics!$AH$2:$AH$167)} | CK19: ='indst heat consumption'!D19 | CL19: ='indst heat consumption'!E19 | CM19: ='indst heat consumption'!F19 | CN19: ='indst heat consumption'!G19 | CO19: ='indst heat consumption'!H19 | CP19: =$C19*(CK19*summary!$B$94+CL19*summary!$C$94+CM19*summary!$D$94) | CQ19: =$C19*(CN19*summary!$E$94+CO19*summary!$F$94) | CR19: =IF(CP19+CQ19>0,CP19*MAX(0,CP19+CQ19-CJ19)/(CP19+CQ19),0) | CS19: =IF(CP19+CQ19>0,CQ19*MAX(0,CP19+CQ19-CJ19)/(CP19+CQ19),0) | CT19: =IFERROR(_xlfn.XLOOKUP($B19,'BCoISC-WACCbI'!$C$2:$C$26,'BCoISC-WACCbI'!$B$2:$B$26)+economics!$AE$4,0.1) | CU19: =(summary!$C$7*(CT19/(1-(1+CT19)^-summary!$D$7))+summary!$C$7*summary!$E$7)/(summary!$F$7*3412/1000000) | CV19: =(summary!$C$6*(CT19/(1-(1+CT19)^-summary!$D$6))+summary!$C$6*summary!$E$6)/(summary!$F$6*3412/1000000) | CW19: =CR19+CS19
A20: =WHRPbI!A18 | B20: 26 | C20: =WHRPbI!B18 | D20: =ISNUMBER(MATCH($B20,'energy base (MECS)'!$K$4:$K$9,0)) | E20: {=IF($D20,SUMPRODUCT((economics!$AG$2:$AG$167=$B20)*(economics!$D$2:$D$167="whr")*economics!$AH$2:$AH$167*_xlfn.NORM.DIST(E$3,economics!$AK$2:$AK$167,economics!$AJ$2:$AJ$167,TRUE))+$CR20*_xlfn.NORM.DIST(E$3,$CU20,0.3*$CU20,TRUE)+$CS20*_xlfn.NORM.DIST(E$3,$CV20,0.3*$CV20,TRUE),$CW20*_xlfn.NORM.DIST(E$3,'energy base (MECS)'!$F$11,0.3*'energy base (MECS)'!$F$11,TRUE))} | F20: {=IF($D20,SUMPRODUCT((economics!$AG$2:$AG$167=$B20)*(economics!$D$2:$D$167="whr")*economics!$AH$2:$AH$167*_xlfn.NORM.DIST(F$3,economics!$AK$2:$AK$167,economics!$AJ$2:$AJ$167,TRUE))+$CR20*_xlfn.NORM.DIST(F$3,$CU20,0.3*$CU20,TRUE)+$CS20*_xlfn.NORM.DIST(F$3,$CV20,0.3*$CV20,TRUE),$CW20*_xlfn.NORM.DIST(F$3,'energy base (MECS)'!$F$11,0.3*'energy base (MECS)'!$F$11,TRUE))} | G20: {=IF($D20,SUMPRODUCT((economics!$AG$2:$AG$167=$B20)*(economics!$D$2:$D$167="whr")*economics!$AH$2:$AH$167*_xlfn.NORM.DIST(G$3,economics!$AK$2:$AK$167,economics!$AJ$2:$AJ$167,TRUE))+$CR20*_xlfn.NORM.DIST(G$3,$CU20,0.3*$CU20,TRUE)+$CS20*_xlfn.NORM.DIST(G$3,$CV20,0.3*$CV20,TRUE),$CW20*_xlfn.NORM.DIST(G$3,'energy base (MECS)'!$F$11,0.3*'energy base (MECS)'!$F$11,TRUE))} | H20: {=IF($D20,SUMPRODUCT((economics!$AG$2:$AG$167=$B20)*(economics!$D$2:$D$167="whr")*economics!$AH$2:$AH$167*_xlfn.NORM.DIST(H$3,economics!$AK$2:$AK$167,economics!$AJ$2:$AJ$167,TRUE))+$CR20*_xlfn.NORM.DIST(H$3,$CU20,0.3*$CU20,TRUE)+$CS20*_xlfn.NORM.DIST(H$3,$CV20,0.3*$CV20,TRUE),$CW20*_xlfn.NORM.DIST(H$3,'energy base (MECS)'!$F$11,0.3*'energy base (MECS)'!$F$11,TRUE))} | I20: {=IF($D20,SUMPRODUCT((economics!$AG$2:$AG$167=$B20)*(economics!$D$2:$D$167="whr")*economics!$AH$2:$AH$167*_xlfn.NORM.DIST(I$3,economics!$AK$2:$AK$167,economics!$AJ$2:$AJ$167,TRUE))+$CR20*_xlfn.NORM.DIST(I$3,$CU20,0.3*$CU20,TRUE)+$CS20*_xlfn.NORM.DIST(I$3,$CV20,0.3*$CV20,TRUE),$CW20*_xlfn.NORM.DIST(I$3,'energy base (MECS)'!$F$11,0.3*'energy base (MECS)'!$F$11,TRUE))} | J20: {=IF($D20,SUMPRODUCT((economics!$AG$2:$AG$167=$B20)*(economics!$D$2:$D$167="whr")*economics!$AH$2:$AH$167*_xlfn.NORM.DIST(J$3,economics!$AK$2:$AK$167,economics!$AJ$2:$AJ$167,TRUE))+$CR20*_xlfn.NORM.DIST(J$3,$CU20,0.3*$CU20,TRUE)+$CS20*_xlfn.NORM.DIST(J$3,$CV20,0.3*$CV20,TRUE),$CW20*_xlfn.NORM.DIST(J$3,'energy base (MECS)'!$F$11,0.3*'energy base (MECS)'!$F$11,TRUE))} | K20: {=IF($D20,SUMPRODUCT((economics!$AG$2:$AG$167=$B20)*(economics!$D$2:$D$167="whr")*economics!$AH$2:$AH$167*_xlfn.NORM.DIST(K$3,economics!$AK$2:$AK$167,economics!$AJ$2:$AJ$167,TRUE))+$CR20*_xlfn.NORM.DIST(K$3,$CU20,0.3*$CU20,TRUE)+$CS20*_xlfn.NORM.DIST(K$3,$CV20,0.3*$CV20,TRUE),$CW20*_xlfn.NORM.DIST(K$3,'energy base (MECS)'!$F$11,0.3*'energy base (MECS)'!$F$11,TRUE))} | L20: {=IF($D20,SUMPRODUCT((economics!$AG$2:$AG$167=$B20)*(economics!$D$2:$D$167="whr")*economics!$AH$2:$AH$167*_xlfn.NORM.DIST(L$3,economics!$AK$2:$AK$167,economics!$AJ$2:$AJ$167,TRUE))+$CR20*_xlfn.NORM.DIST(L$3,$CU20,0.3*$CU20,TRUE)+$CS20*_xlfn.NORM.DIST(L$3,$CV20,0.3*$CV20,TRUE),$CW20*_xlfn.NORM.DIST(L$3,'energy base (MECS)'!$F$11,0.3*'energy base (MECS)'!$F$11,TRUE))} | ... CH20: {=IF($D20,SUMPRODUCT((economics!$AG$2:$AG$167=$B20)*(economics!$D$2:$D$167="whr")*economics!$AH$2:$AH$167*_xlfn.NORM.DIST(CH$3,economics!$AK$2:$AK$167,economics!$AJ$2:$AJ$167,TRUE))+$CR20*_xlfn.NORM.DIST(CH$3,$CU20,0.3*$CU20,TRUE)+$CS20*_xlfn.NORM.DIST(CH$3,$CV20,0.3*$CV20,TRUE),$CW20*_xlfn.NORM.DIST(CH$3,'energy base (MECS)'!$F$11,0.3*'energy base (MECS)'!$F$11,TRUE))} | CJ20: {=SUMPRODUCT((economics!$AG$2:$AG$167=$B20)*(economics!$D$2:$D$167="whr")*economics!$AH$2:$AH$167)} | CK20: ='indst heat consumption'!D20 | CL20: ='indst heat consumption'!E20 | CM20: ='indst heat consumption'!F20 | CN20: ='indst heat consumption'!G20 | CO20: ='indst heat consumption'!H20 | CP20: =$C20*(CK20*summary!$B$94+CL20*summary!$C$94+CM20*summary!$D$94) | CQ20: =$C20*(CN20*summary!$E$94+CO20*summary!$F$94) | CR20: =IF(CP20+CQ20>0,CP20*MAX(0,CP20+CQ20-CJ20)/(CP20+CQ20),0) | CS20: =IF(CP20+CQ20>0,CQ20*MAX(0,CP20+CQ20-CJ20)/(CP20+CQ20),0) | CT20: =IFERROR(_xlfn.XLOOKUP($B20,'BCoISC-WACCbI'!$C$2:$C$26,'BCoISC-WACCbI'!$B$2:$B$26)+economics!$AE$4,0.1) | CU20: =(summary!$C$7*(CT20/(1-(1+CT20)^-summary!$D$7))+summary!$C$7*summary!$E$7)/(summary!$F$7*3412/1000000) | CV20: =(summary!$C$6*(CT20/(1-(1+CT20)^-summary!$D$6))+summary!$C$6*summary!$E$6)/(summary!$F$6*3412/1000000) | CW20: =CR20+CS20
A21: =WHRPbI!A19 | B21: 27 | C21: =WHRPbI!B19 | D21: =ISNUMBER(MATCH($B21,'energy base (MECS)'!$K$4:$K$9,0)) | E21: {=IF($D21,SUMPRODUCT((economics!$AG$2:$AG$167=$B21)*(economics!$D$2:$D$167="whr")*economics!$AH$2:$AH$167*_xlfn.NORM.DIST(E$3,economics!$AK$2:$AK$167,economics!$AJ$2:$AJ$167,TRUE))+$CR21*_xlfn.NORM.DIST(E$3,$CU21,0.3*$CU21,TRUE)+$CS21*_xlfn.NORM.DIST(E$3,$CV21,0.3*$CV21,TRUE),$CW21*_xlfn.NORM.DIST(E$3,'energy base (MECS)'!$F$11,0.3*'energy base (MECS)'!$F$11,TRUE))} | F21: {=IF($D21,SUMPRODUCT((economics!$AG$2:$AG$167=$B21)*(economics!$D$2:$D$167="whr")*economics!$AH$2:$AH$167*_xlfn.NORM.DIST(F$3,economics!$AK$2:$AK$167,economics!$AJ$2:$AJ$167,TRUE))+$CR21*_xlfn.NORM.DIST(F$3,$CU21,0.3*$CU21,TRUE)+$CS21*_xlfn.NORM.DIST(F$3,$CV21,0.3*$CV21,TRUE),$CW21*_xlfn.NORM.DIST(F$3,'energy base (MECS)'!$F$11,0.3*'energy base (MECS)'!$F$11,TRUE))} | G21: {=IF($D21,SUMPRODUCT((economics!$AG$2:$AG$167=$B21)*(economics!$D$2:$D$167="whr")*economics!$AH$2:$AH$167*_xlfn.NORM.DIST(G$3,economics!$AK$2:$AK$167,economics!$AJ$2:$AJ$167,TRUE))+$CR21*_xlfn.NORM.DIST(G$3,$CU21,0.3*$CU21,TRUE)+$CS21*_xlfn.NORM.DIST(G$3,$CV21,0.3*$CV21,TRUE),$CW21*_xlfn.NORM.DIST(G$3,'energy base (MECS)'!$F$11,0.3*'energy base (MECS)'!$F$11,TRUE))} | H21: {=IF($D21,SUMPRODUCT((economics!$AG$2:$AG$167=$B21)*(economics!$D$2:$D$167="whr")*economics!$AH$2:$AH$167*_xlfn.NORM.DIST(H$3,economics!$AK$2:$AK$167,economics!$AJ$2:$AJ$167,TRUE))+$CR21*_xlfn.NORM.DIST(H$3,$CU21,0.3*$CU21,TRUE)+$CS21*_xlfn.NORM.DIST(H$3,$CV21,0.3*$CV21,TRUE),$CW21*_xlfn.NORM.DIST(H$3,'energy base (MECS)'!$F$11,0.3*'energy base (MECS)'!$F$11,TRUE))} | I21: {=IF($D21,SUMPRODUCT((economics!$AG$2:$AG$167=$B21)*(economics!$D$2:$D$167="whr")*economics!$AH$2:$AH$167*_xlfn.NORM.DIST(I$3,economics!$AK$2:$AK$167,economics!$AJ$2:$AJ$167,TRUE))+$CR21*_xlfn.NORM.DIST(I$3,$CU21,0.3*$CU21,TRUE)+$CS21*_xlfn.NORM.DIST(I$3,$CV21,0.3*$CV21,TRUE),$CW21*_xlfn.NORM.DIST(I$3,'energy base (MECS)'!$F$11,0.3*'energy base (MECS)'!$F$11,TRUE))} | J21: {=IF($D21,SUMPRODUCT((economics!$AG$2:$AG$167=$B21)*(economics!$D$2:$D$167="whr")*economics!$AH$2:$AH$167*_xlfn.NORM.DIST(J$3,economics!$AK$2:$AK$167,economics!$AJ$2:$AJ$167,TRUE))+$CR21*_xlfn.NORM.DIST(J$3,$CU21,0.3*$CU21,TRUE)+$CS21*_xlfn.NORM.DIST(J$3,$CV21,0.3*$CV21,TRUE),$CW21*_xlfn.NORM.DIST(J$3,'energy base (MECS)'!$F$11,0.3*'energy base (MECS)'!$F$11,TRUE))} | K21: {=IF($D21,SUMPRODUCT((economics!$AG$2:$AG$167=$B21)*(economics!$D$2:$D$167="whr")*economics!$AH$2:$AH$167*_xlfn.NORM.DIST(K$3,economics!$AK$2:$AK$167,economics!$AJ$2:$AJ$167,TRUE))+$CR21*_xlfn.NORM.DIST(K$3,$CU21,0.3*$CU21,TRUE)+$CS21*_xlfn.NORM.DIST(K$3,$CV21,0.3*$CV21,TRUE),$CW21*_xlfn.NORM.DIST(K$3,'energy base (MECS)'!$F$11,0.3*'energy base (MECS)'!$F$11,TRUE))} | L21: {=IF($D21,SUMPRODUCT((economics!$AG$2:$AG$167=$B21)*(economics!$D$2:$D$167="whr")*economics!$AH$2:$AH$167*_xlfn.NORM.DIST(L$3,economics!$AK$2:$AK$167,economics!$AJ$2:$AJ$167,TRUE))+$CR21*_xlfn.NORM.DIST(L$3,$CU21,0.3*$CU21,TRUE)+$CS21*_xlfn.NORM.DIST(L$3,$CV21,0.3*$CV21,TRUE),$CW21*_xlfn.NORM.DIST(L$3,'energy base (MECS)'!$F$11,0.3*'energy base (MECS)'!$F$11,TRUE))} | ... CH21: {=IF($D21,SUMPRODUCT((economics!$AG$2:$AG$167=$B21)*(economics!$D$2:$D$167="whr")*economics!$AH$2:$AH$167*_xlfn.NORM.DIST(CH$3,economics!$AK$2:$AK$167,economics!$AJ$2:$AJ$167,TRUE))+$CR21*_xlfn.NORM.DIST(CH$3,$CU21,0.3*$CU21,TRUE)+$CS21*_xlfn.NORM.DIST(CH$3,$CV21,0.3*$CV21,TRUE),$CW21*_xlfn.NORM.DIST(CH$3,'energy base (MECS)'!$F$11,0.3*'energy base (MECS)'!$F$11,TRUE))} | CJ21: {=SUMPRODUCT((economics!$AG$2:$AG$167=$B21)*(economics!$D$2:$D$167="whr")*economics!$AH$2:$AH$167)} | CK21: ='indst heat consumption'!D21 | CL21: ='indst heat consumption'!E21 | CM21: ='indst heat consumption'!F21 | CN21: ='indst heat consumption'!G21 | CO21: ='indst heat consumption'!H21 | CP21: =$C21*(CK21*summary!$B$94+CL21*summary!$C$94+CM21*summary!$D$94) | CQ21: =$C21*(CN21*summary!$E$94+CO21*summary!$F$94) | CR21: =IF(CP21+CQ21>0,CP21*MAX(0,CP21+CQ21-CJ21)/(CP21+CQ21),0) | CS21: =IF(CP21+CQ21>0,CQ21*MAX(0,CP21+CQ21-CJ21)/(CP21+CQ21),0) | CT21: =IFERROR(_xlfn.XLOOKUP($B21,'BCoISC-WACCbI'!$C$2:$C$26,'BCoISC-WACCbI'!$B$2:$B$26)+economics!$AE$4,0.1) | CU21: =(summary!$C$7*(CT21/(1-(1+CT21)^-summary!$D$7))+summary!$C$7*summary!$E$7)/(summary!$F$7*3412/1000000) | CV21: =(summary!$C$6*(CT21/(1-(1+CT21)^-summary!$D$6))+summary!$C$6*summary!$E$6)/(summary!$F$6*3412/1000000) | CW21: =CR21+CS21
A22: =WHRPbI!A20 | B22: 28 | C22: =WHRPbI!B20 | D22: =ISNUMBER(MATCH($B22,'energy base (MECS)'!$K$4:$K$9,0)) | E22: {=IF($D22,SUMPRODUCT((economics!$AG$2:$AG$167=$B22)*(economics!$D$2:$D$167="whr")*economics!$AH$2:$AH$167*_xlfn.NORM.DIST(E$3,economics!$AK$2:$AK$167,economics!$AJ$2:$AJ$167,TRUE))+$CR22*_xlfn.NORM.DIST(E$3,$CU22,0.3*$CU22,TRUE)+$CS22*_xlfn.NORM.DIST(E$3,$CV22,0.3*$CV22,TRUE),$CW22*_xlfn.NORM.DIST(E$3,'energy base (MECS)'!$F$11,0.3*'energy base (MECS)'!$F$11,TRUE))} | F22: {=IF($D22,SUMPRODUCT((economics!$AG$2:$AG$167=$B22)*(economics!$D$2:$D$167="whr")*economics!$AH$2:$AH$167*_xlfn.NORM.DIST(F$3,economics!$AK$2:$AK$167,economics!$AJ$2:$AJ$167,TRUE))+$CR22*_xlfn.NORM.DIST(F$3,$CU22,0.3*$CU22,TRUE)+$CS22*_xlfn.NORM.DIST(F$3,$CV22,0.3*$CV22,TRUE),$CW22*_xlfn.NORM.DIST(F$3,'energy base (MECS)'!$F$11,0.3*'energy base (MECS)'!$F$11,TRUE))} | G22: {=IF($D22,SUMPRODUCT((economics!$AG$2:$AG$167=$B22)*(economics!$D$2:$D$167="whr")*economics!$AH$2:$AH$167*_xlfn.NORM.DIST(G$3,economics!$AK$2:$AK$167,economics!$AJ$2:$AJ$167,TRUE))+$CR22*_xlfn.NORM.DIST(G$3,$CU22,0.3*$CU22,TRUE)+$CS22*_xlfn.NORM.DIST(G$3,$CV22,0.3*$CV22,TRUE),$CW22*_xlfn.NORM.DIST(G$3,'energy base (MECS)'!$F$11,0.3*'energy base (MECS)'!$F$11,TRUE))} | H22: {=IF($D22,SUMPRODUCT((economics!$AG$2:$AG$167=$B22)*(economics!$D$2:$D$167="whr")*economics!$AH$2:$AH$167*_xlfn.NORM.DIST(H$3,economics!$AK$2:$AK$167,economics!$AJ$2:$AJ$167,TRUE))+$CR22*_xlfn.NORM.DIST(H$3,$CU22,0.3*$CU22,TRUE)+$CS22*_xlfn.NORM.DIST(H$3,$CV22,0.3*$CV22,TRUE),$CW22*_xlfn.NORM.DIST(H$3,'energy base (MECS)'!$F$11,0.3*'energy base (MECS)'!$F$11,TRUE))} | I22: {=IF($D22,SUMPRODUCT((economics!$AG$2:$AG$167=$B22)*(economics!$D$2:$D$167="whr")*economics!$AH$2:$AH$167*_xlfn.NORM.DIST(I$3,economics!$AK$2:$AK$167,economics!$AJ$2:$AJ$167,TRUE))+$CR22*_xlfn.NORM.DIST(I$3,$CU22,0.3*$CU22,TRUE)+$CS22*_xlfn.NORM.DIST(I$3,$CV22,0.3*$CV22,TRUE),$CW22*_xlfn.NORM.DIST(I$3,'energy base (MECS)'!$F$11,0.3*'energy base (MECS)'!$F$11,TRUE))} | J22: {=IF($D22,SUMPRODUCT((economics!$AG$2:$AG$167=$B22)*(economics!$D$2:$D$167="whr")*economics!$AH$2:$AH$167*_xlfn.NORM.DIST(J$3,economics!$AK$2:$AK$167,economics!$AJ$2:$AJ$167,TRUE))+$CR22*_xlfn.NORM.DIST(J$3,$CU22,0.3*$CU22,TRUE)+$CS22*_xlfn.NORM.DIST(J$3,$CV22,0.3*$CV22,TRUE),$CW22*_xlfn.NORM.DIST(J$3,'energy base (MECS)'!$F$11,0.3*'energy base (MECS)'!$F$11,TRUE))} | K22: {=IF($D22,SUMPRODUCT((economics!$AG$2:$AG$167=$B22)*(economics!$D$2:$D$167="whr")*economics!$AH$2:$AH$167*_xlfn.NORM.DIST(K$3,economics!$AK$2:$AK$167,economics!$AJ$2:$AJ$167,TRUE))+$CR22*_xlfn.NORM.DIST(K$3,$CU22,0.3*$CU22,TRUE)+$CS22*_xlfn.NORM.DIST(K$3,$CV22,0.3*$CV22,TRUE),$CW22*_xlfn.NORM.DIST(K$3,'energy base (MECS)'!$F$11,0.3*'energy base (MECS)'!$F$11,TRUE))} | L22: {=IF($D22,SUMPRODUCT((economics!$AG$2:$AG$167=$B22)*(economics!$D$2:$D$167="whr")*economics!$AH$2:$AH$167*_xlfn.NORM.DIST(L$3,economics!$AK$2:$AK$167,economics!$AJ$2:$AJ$167,TRUE))+$CR22*_xlfn.NORM.DIST(L$3,$CU22,0.3*$CU22,TRUE)+$CS22*_xlfn.NORM.DIST(L$3,$CV22,0.3*$CV22,TRUE),$CW22*_xlfn.NORM.DIST(L$3,'energy base (MECS)'!$F$11,0.3*'energy base (MECS)'!$F$11,TRUE))} | ... CH22: {=IF($D22,SUMPRODUCT((economics!$AG$2:$AG$167=$B22)*(economics!$D$2:$D$167="whr")*economics!$AH$2:$AH$167*_xlfn.NORM.DIST(CH$3,economics!$AK$2:$AK$167,economics!$AJ$2:$AJ$167,TRUE))+$CR22*_xlfn.NORM.DIST(CH$3,$CU22,0.3*$CU22,TRUE)+$CS22*_xlfn.NORM.DIST(CH$3,$CV22,0.3*$CV22,TRUE),$CW22*_xlfn.NORM.DIST(CH$3,'energy base (MECS)'!$F$11,0.3*'energy base (MECS)'!$F$11,TRUE))} | CJ22: {=SUMPRODUCT((economics!$AG$2:$AG$167=$B22)*(economics!$D$2:$D$167="whr")*economics!$AH$2:$AH$167)} | CK22: ='indst heat consumption'!D22 | CL22: ='indst heat consumption'!E22 | CM22: ='indst heat consumption'!F22 | CN22: ='indst heat consumption'!G22 | CO22: ='indst heat consumption'!H22 | CP22: =$C22*(CK22*summary!$B$94+CL22*summary!$C$94+CM22*summary!$D$94) | CQ22: =$C22*(CN22*summary!$E$94+CO22*summary!$F$94) | CR22: =IF(CP22+CQ22>0,CP22*MAX(0,CP22+CQ22-CJ22)/(CP22+CQ22),0) | CS22: =IF(CP22+CQ22>0,CQ22*MAX(0,CP22+CQ22-CJ22)/(CP22+CQ22),0) | CT22: =IFERROR(_xlfn.XLOOKUP($B22,'BCoISC-WACCbI'!$C$2:$C$26,'BCoISC-WACCbI'!$B$2:$B$26)+economics!$AE$4,0.1) | CU22: =(summary!$C$7*(CT22/(1-(1+CT22)^-summary!$D$7))+summary!$C$7*summary!$E$7)/(summary!$F$7*3412/1000000) | CV22: =(summary!$C$6*(CT22/(1-(1+CT22)^-summary!$D$6))+summary!$C$6*summary!$E$6)/(summary!$F$6*3412/1000000) | CW22: =CR22+CS22
A23: =WHRPbI!A21 | B23: 29 | C23: =WHRPbI!B21 | D23: =ISNUMBER(MATCH($B23,'energy base (MECS)'!$K$4:$K$9,0)) | E23: {=IF($D23,SUMPRODUCT((economics!$AG$2:$AG$167=$B23)*(economics!$D$2:$D$167="whr")*economics!$AH$2:$AH$167*_xlfn.NORM.DIST(E$3,economics!$AK$2:$AK$167,economics!$AJ$2:$AJ$167,TRUE))+$CR23*_xlfn.NORM.DIST(E$3,$CU23,0.3*$CU23,TRUE)+$CS23*_xlfn.NORM.DIST(E$3,$CV23,0.3*$CV23,TRUE),$CW23*_xlfn.NORM.DIST(E$3,'energy base (MECS)'!$F$11,0.3*'energy base (MECS)'!$F$11,TRUE))} | F23: {=IF($D23,SUMPRODUCT((economics!$AG$2:$AG$167=$B23)*(economics!$D$2:$D$167="whr")*economics!$AH$2:$AH$167*_xlfn.NORM.DIST(F$3,economics!$AK$2:$AK$167,economics!$AJ$2:$AJ$167,TRUE))+$CR23*_xlfn.NORM.DIST(F$3,$CU23,0.3*$CU23,TRUE)+$CS23*_xlfn.NORM.DIST(F$3,$CV23,0.3*$CV23,TRUE),$CW23*_xlfn.NORM.DIST(F$3,'energy base (MECS)'!$F$11,0.3*'energy base (MECS)'!$F$11,TRUE))} | G23: {=IF($D23,SUMPRODUCT((economics!$AG$2:$AG$167=$B23)*(economics!$D$2:$D$167="whr")*economics!$AH$2:$AH$167*_xlfn.NORM.DIST(G$3,economics!$AK$2:$AK$167,economics!$AJ$2:$AJ$167,TRUE))+$CR23*_xlfn.NORM.DIST(G$3,$CU23,0.3*$CU23,TRUE)+$CS23*_xlfn.NORM.DIST(G$3,$CV23,0.3*$CV23,TRUE),$CW23*_xlfn.NORM.DIST(G$3,'energy base (MECS)'!$F$11,0.3*'energy base (MECS)'!$F$11,TRUE))} | H23: {=IF($D23,SUMPRODUCT((economics!$AG$2:$AG$167=$B23)*(economics!$D$2:$D$167="whr")*economics!$AH$2:$AH$167*_xlfn.NORM.DIST(H$3,economics!$AK$2:$AK$167,economics!$AJ$2:$AJ$167,TRUE))+$CR23*_xlfn.NORM.DIST(H$3,$CU23,0.3*$CU23,TRUE)+$CS23*_xlfn.NORM.DIST(H$3,$CV23,0.3*$CV23,TRUE),$CW23*_xlfn.NORM.DIST(H$3,'energy base (MECS)'!$F$11,0.3*'energy base (MECS)'!$F$11,TRUE))} | I23: {=IF($D23,SUMPRODUCT((economics!$AG$2:$AG$167=$B23)*(economics!$D$2:$D$167="whr")*economics!$AH$2:$AH$167*_xlfn.NORM.DIST(I$3,economics!$AK$2:$AK$167,economics!$AJ$2:$AJ$167,TRUE))+$CR23*_xlfn.NORM.DIST(I$3,$CU23,0.3*$CU23,TRUE)+$CS23*_xlfn.NORM.DIST(I$3,$CV23,0.3*$CV23,TRUE),$CW23*_xlfn.NORM.DIST(I$3,'energy base (MECS)'!$F$11,0.3*'energy base (MECS)'!$F$11,TRUE))} | J23: {=IF($D23,SUMPRODUCT((economics!$AG$2:$AG$167=$B23)*(economics!$D$2:$D$167="whr")*economics!$AH$2:$AH$167*_xlfn.NORM.DIST(J$3,economics!$AK$2:$AK$167,economics!$AJ$2:$AJ$167,TRUE))+$CR23*_xlfn.NORM.DIST(J$3,$CU23,0.3*$CU23,TRUE)+$CS23*_xlfn.NORM.DIST(J$3,$CV23,0.3*$CV23,TRUE),$CW23*_xlfn.NORM.DIST(J$3,'energy base (MECS)'!$F$11,0.3*'energy base (MECS)'!$F$11,TRUE))} | K23: {=IF($D23,SUMPRODUCT((economics!$AG$2:$AG$167=$B23)*(economics!$D$2:$D$167="whr")*economics!$AH$2:$AH$167*_xlfn.NORM.DIST(K$3,economics!$AK$2:$AK$167,economics!$AJ$2:$AJ$167,TRUE))+$CR23*_xlfn.NORM.DIST(K$3,$CU23,0.3*$CU23,TRUE)+$CS23*_xlfn.NORM.DIST(K$3,$CV23,0.3*$CV23,TRUE),$CW23*_xlfn.NORM.DIST(K$3,'energy base (MECS)'!$F$11,0.3*'energy base (MECS)'!$F$11,TRUE))} | L23: {=IF($D23,SUMPRODUCT((economics!$AG$2:$AG$167=$B23)*(economics!$D$2:$D$167="whr")*economics!$AH$2:$AH$167*_xlfn.NORM.DIST(L$3,economics!$AK$2:$AK$167,economics!$AJ$2:$AJ$167,TRUE))+$CR23*_xlfn.NORM.DIST(L$3,$CU23,0.3*$CU23,TRUE)+$CS23*_xlfn.NORM.DIST(L$3,$CV23,0.3*$CV23,TRUE),$CW23*_xlfn.NORM.DIST(L$3,'energy base (MECS)'!$F$11,0.3*'energy base (MECS)'!$F$11,TRUE))} | ... CH23: {=IF($D23,SUMPRODUCT((economics!$AG$2:$AG$167=$B23)*(economics!$D$2:$D$167="whr")*economics!$AH$2:$AH$167*_xlfn.NORM.DIST(CH$3,economics!$AK$2:$AK$167,economics!$AJ$2:$AJ$167,TRUE))+$CR23*_xlfn.NORM.DIST(CH$3,$CU23,0.3*$CU23,TRUE)+$CS23*_xlfn.NORM.DIST(CH$3,$CV23,0.3*$CV23,TRUE),$CW23*_xlfn.NORM.DIST(CH$3,'energy base (MECS)'!$F$11,0.3*'energy base (MECS)'!$F$11,TRUE))} | CJ23: {=SUMPRODUCT((economics!$AG$2:$AG$167=$B23)*(economics!$D$2:$D$167="whr")*economics!$AH$2:$AH$167)} | CK23: ='indst heat consumption'!D23 | CL23: ='indst heat consumption'!E23 | CM23: ='indst heat consumption'!F23 | CN23: ='indst heat consumption'!G23 | CO23: ='indst heat consumption'!H23 | CP23: =$C23*(CK23*summary!$B$94+CL23*summary!$C$94+CM23*summary!$D$94) | CQ23: =$C23*(CN23*summary!$E$94+CO23*summary!$F$94) | CR23: =IF(CP23+CQ23>0,CP23*MAX(0,CP23+CQ23-CJ23)/(CP23+CQ23),0) | CS23: =IF(CP23+CQ23>0,CQ23*MAX(0,CP23+CQ23-CJ23)/(CP23+CQ23),0) | CT23: =IFERROR(_xlfn.XLOOKUP($B23,'BCoISC-WACCbI'!$C$2:$C$26,'BCoISC-WACCbI'!$B$2:$B$26)+economics!$AE$4,0.1) | CU23: =(summary!$C$7*(CT23/(1-(1+CT23)^-summary!$D$7))+summary!$C$7*summary!$E$7)/(summary!$F$7*3412/1000000) | CV23: =(summary!$C$6*(CT23/(1-(1+CT23)^-summary!$D$6))+summary!$C$6*summary!$E$6)/(summary!$F$6*3412/1000000) | CW23: =CR23+CS23
A24: =WHRPbI!A22 | B24: 30 | C24: =WHRPbI!B22 | D24: =ISNUMBER(MATCH($B24,'energy base (MECS)'!$K$4:$K$9,0)) | E24: {=IF($D24,SUMPRODUCT((economics!$AG$2:$AG$167=$B24)*(economics!$D$2:$D$167="whr")*economics!$AH$2:$AH$167*_xlfn.NORM.DIST(E$3,economics!$AK$2:$AK$167,economics!$AJ$2:$AJ$167,TRUE))+$CR24*_xlfn.NORM.DIST(E$3,$CU24,0.3*$CU24,TRUE)+$CS24*_xlfn.NORM.DIST(E$3,$CV24,0.3*$CV24,TRUE),$CW24*_xlfn.NORM.DIST(E$3,'energy base (MECS)'!$F$11,0.3*'energy base (MECS)'!$F$11,TRUE))} | F24: {=IF($D24,SUMPRODUCT((economics!$AG$2:$AG$167=$B24)*(economics!$D$2:$D$167="whr")*economics!$AH$2:$AH$167*_xlfn.NORM.DIST(F$3,economics!$AK$2:$AK$167,economics!$AJ$2:$AJ$167,TRUE))+$CR24*_xlfn.NORM.DIST(F$3,$CU24,0.3*$CU24,TRUE)+$CS24*_xlfn.NORM.DIST(F$3,$CV24,0.3*$CV24,TRUE),$CW24*_xlfn.NORM.DIST(F$3,'energy base (MECS)'!$F$11,0.3*'energy base (MECS)'!$F$11,TRUE))} | G24: {=IF($D24,SUMPRODUCT((economics!$AG$2:$AG$167=$B24)*(economics!$D$2:$D$167="whr")*economics!$AH$2:$AH$167*_xlfn.NORM.DIST(G$3,economics!$AK$2:$AK$167,economics!$AJ$2:$AJ$167,TRUE))+$CR24*_xlfn.NORM.DIST(G$3,$CU24,0.3*$CU24,TRUE)+$CS24*_xlfn.NORM.DIST(G$3,$CV24,0.3*$CV24,TRUE),$CW24*_xlfn.NORM.DIST(G$3,'energy base (MECS)'!$F$11,0.3*'energy base (MECS)'!$F$11,TRUE))} | H24: {=IF($D24,SUMPRODUCT((economics!$AG$2:$AG$167=$B24)*(economics!$D$2:$D$167="whr")*economics!$AH$2:$AH$167*_xlfn.NORM.DIST(H$3,economics!$AK$2:$AK$167,economics!$AJ$2:$AJ$167,TRUE))+$CR24*_xlfn.NORM.DIST(H$3,$CU24,0.3*$CU24,TRUE)+$CS24*_xlfn.NORM.DIST(H$3,$CV24,0.3*$CV24,TRUE),$CW24*_xlfn.NORM.DIST(H$3,'energy base (MECS)'!$F$11,0.3*'energy base (MECS)'!$F$11,TRUE))} | I24: {=IF($D24,SUMPRODUCT((economics!$AG$2:$AG$167=$B24)*(economics!$D$2:$D$167="whr")*economics!$AH$2:$AH$167*_xlfn.NORM.DIST(I$3,economics!$AK$2:$AK$167,economics!$AJ$2:$AJ$167,TRUE))+$CR24*_xlfn.NORM.DIST(I$3,$CU24,0.3*$CU24,TRUE)+$CS24*_xlfn.NORM.DIST(I$3,$CV24,0.3*$CV24,TRUE),$CW24*_xlfn.NORM.DIST(I$3,'energy base (MECS)'!$F$11,0.3*'energy base (MECS)'!$F$11,TRUE))} | J24: {=IF($D24,SUMPRODUCT((economics!$AG$2:$AG$167=$B24)*(economics!$D$2:$D$167="whr")*economics!$AH$2:$AH$167*_xlfn.NORM.DIST(J$3,economics!$AK$2:$AK$167,economics!$AJ$2:$AJ$167,TRUE))+$CR24*_xlfn.NORM.DIST(J$3,$CU24,0.3*$CU24,TRUE)+$CS24*_xlfn.NORM.DIST(J$3,$CV24,0.3*$CV24,TRUE),$CW24*_xlfn.NORM.DIST(J$3,'energy base (MECS)'!$F$11,0.3*'energy base (MECS)'!$F$11,TRUE))} | K24: {=IF($D24,SUMPRODUCT((economics!$AG$2:$AG$167=$B24)*(economics!$D$2:$D$167="whr")*economics!$AH$2:$AH$167*_xlfn.NORM.DIST(K$3,economics!$AK$2:$AK$167,economics!$AJ$2:$AJ$167,TRUE))+$CR24*_xlfn.NORM.DIST(K$3,$CU24,0.3*$CU24,TRUE)+$CS24*_xlfn.NORM.DIST(K$3,$CV24,0.3*$CV24,TRUE),$CW24*_xlfn.NORM.DIST(K$3,'energy base (MECS)'!$F$11,0.3*'energy base (MECS)'!$F$11,TRUE))} | L24: {=IF($D24,SUMPRODUCT((economics!$AG$2:$AG$167=$B24)*(economics!$D$2:$D$167="whr")*economics!$AH$2:$AH$167*_xlfn.NORM.DIST(L$3,economics!$AK$2:$AK$167,economics!$AJ$2:$AJ$167,TRUE))+$CR24*_xlfn.NORM.DIST(L$3,$CU24,0.3*$CU24,TRUE)+$CS24*_xlfn.NORM.DIST(L$3,$CV24,0.3*$CV24,TRUE),$CW24*_xlfn.NORM.DIST(L$3,'energy base (MECS)'!$F$11,0.3*'energy base (MECS)'!$F$11,TRUE))} | ... CH24: {=IF($D24,SUMPRODUCT((economics!$AG$2:$AG$167=$B24)*(economics!$D$2:$D$167="whr")*economics!$AH$2:$AH$167*_xlfn.NORM.DIST(CH$3,economics!$AK$2:$AK$167,economics!$AJ$2:$AJ$167,TRUE))+$CR24*_xlfn.NORM.DIST(CH$3,$CU24,0.3*$CU24,TRUE)+$CS24*_xlfn.NORM.DIST(CH$3,$CV24,0.3*$CV24,TRUE),$CW24*_xlfn.NORM.DIST(CH$3,'energy base (MECS)'!$F$11,0.3*'energy base (MECS)'!$F$11,TRUE))} | CJ24: {=SUMPRODUCT((economics!$AG$2:$AG$167=$B24)*(economics!$D$2:$D$167="whr")*economics!$AH$2:$AH$167)} | CK24: ='indst heat consumption'!D24 | CL24: ='indst heat consumption'!E24 | CM24: ='indst heat consumption'!F24 | CN24: ='indst heat consumption'!G24 | CO24: ='indst heat consumption'!H24 | CP24: =$C24*(CK24*summary!$B$94+CL24*summary!$C$94+CM24*summary!$D$94) | CQ24: =$C24*(CN24*summary!$E$94+CO24*summary!$F$94) | CR24: =IF(CP24+CQ24>0,CP24*MAX(0,CP24+CQ24-CJ24)/(CP24+CQ24),0) | CS24: =IF(CP24+CQ24>0,CQ24*MAX(0,CP24+CQ24-CJ24)/(CP24+CQ24),0) | CT24: =IFERROR(_xlfn.XLOOKUP($B24,'BCoISC-WACCbI'!$C$2:$C$26,'BCoISC-WACCbI'!$B$2:$B$26)+economics!$AE$4,0.1) | CU24: =(summary!$C$7*(CT24/(1-(1+CT24)^-summary!$D$7))+summary!$C$7*summary!$E$7)/(summary!$F$7*3412/1000000) | CV24: =(summary!$C$6*(CT24/(1-(1+CT24)^-summary!$D$6))+summary!$C$6*summary!$E$6)/(summary!$F$6*3412/1000000) | CW24: =CR24+CS24
A25: =WHRPbI!A23 | B25: 31T33 | C25: =WHRPbI!B23 | D25: =ISNUMBER(MATCH($B25,'energy base (MECS)'!$K$4:$K$9,0)) | E25: {=IF($D25,SUMPRODUCT((economics!$AG$2:$AG$167=$B25)*(economics!$D$2:$D$167="whr")*economics!$AH$2:$AH$167*_xlfn.NORM.DIST(E$3,economics!$AK$2:$AK$167,economics!$AJ$2:$AJ$167,TRUE))+$CR25*_xlfn.NORM.DIST(E$3,$CU25,0.3*$CU25,TRUE)+$CS25*_xlfn.NORM.DIST(E$3,$CV25,0.3*$CV25,TRUE),$CW25*_xlfn.NORM.DIST(E$3,'energy base (MECS)'!$F$11,0.3*'energy base (MECS)'!$F$11,TRUE))} | F25: {=IF($D25,SUMPRODUCT((economics!$AG$2:$AG$167=$B25)*(economics!$D$2:$D$167="whr")*economics!$AH$2:$AH$167*_xlfn.NORM.DIST(F$3,economics!$AK$2:$AK$167,economics!$AJ$2:$AJ$167,TRUE))+$CR25*_xlfn.NORM.DIST(F$3,$CU25,0.3*$CU25,TRUE)+$CS25*_xlfn.NORM.DIST(F$3,$CV25,0.3*$CV25,TRUE),$CW25*_xlfn.NORM.DIST(F$3,'energy base (MECS)'!$F$11,0.3*'energy base (MECS)'!$F$11,TRUE))} | G25: {=IF($D25,SUMPRODUCT((economics!$AG$2:$AG$167=$B25)*(economics!$D$2:$D$167="whr")*economics!$AH$2:$AH$167*_xlfn.NORM.DIST(G$3,economics!$AK$2:$AK$167,economics!$AJ$2:$AJ$167,TRUE))+$CR25*_xlfn.NORM.DIST(G$3,$CU25,0.3*$CU25,TRUE)+$CS25*_xlfn.NORM.DIST(G$3,$CV25,0.3*$CV25,TRUE),$CW25*_xlfn.NORM.DIST(G$3,'energy base (MECS)'!$F$11,0.3*'energy base (MECS)'!$F$11,TRUE))} | H25: {=IF($D25,SUMPRODUCT((economics!$AG$2:$AG$167=$B25)*(economics!$D$2:$D$167="whr")*economics!$AH$2:$AH$167*_xlfn.NORM.DIST(H$3,economics!$AK$2:$AK$167,economics!$AJ$2:$AJ$167,TRUE))+$CR25*_xlfn.NORM.DIST(H$3,$CU25,0.3*$CU25,TRUE)+$CS25*_xlfn.NORM.DIST(H$3,$CV25,0.3*$CV25,TRUE),$CW25*_xlfn.NORM.DIST(H$3,'energy base (MECS)'!$F$11,0.3*'energy base (MECS)'!$F$11,TRUE))} | I25: {=IF($D25,SUMPRODUCT((economics!$AG$2:$AG$167=$B25)*(economics!$D$2:$D$167="whr")*economics!$AH$2:$AH$167*_xlfn.NORM.DIST(I$3,economics!$AK$2:$AK$167,economics!$AJ$2:$AJ$167,TRUE))+$CR25*_xlfn.NORM.DIST(I$3,$CU25,0.3*$CU25,TRUE)+$CS25*_xlfn.NORM.DIST(I$3,$CV25,0.3*$CV25,TRUE),$CW25*_xlfn.NORM.DIST(I$3,'energy base (MECS)'!$F$11,0.3*'energy base (MECS)'!$F$11,TRUE))} | J25: {=IF($D25,SUMPRODUCT((economics!$AG$2:$AG$167=$B25)*(economics!$D$2:$D$167="whr")*economics!$AH$2:$AH$167*_xlfn.NORM.DIST(J$3,economics!$AK$2:$AK$167,economics!$AJ$2:$AJ$167,TRUE))+$CR25*_xlfn.NORM.DIST(J$3,$CU25,0.3*$CU25,TRUE)+$CS25*_xlfn.NORM.DIST(J$3,$CV25,0.3*$CV25,TRUE),$CW25*_xlfn.NORM.DIST(J$3,'energy base (MECS)'!$F$11,0.3*'energy base (MECS)'!$F$11,TRUE))} | K25: {=IF($D25,SUMPRODUCT((economics!$AG$2:$AG$167=$B25)*(economics!$D$2:$D$167="whr")*economics!$AH$2:$AH$167*_xlfn.NORM.DIST(K$3,economics!$AK$2:$AK$167,economics!$AJ$2:$AJ$167,TRUE))+$CR25*_xlfn.NORM.DIST(K$3,$CU25,0.3*$CU25,TRUE)+$CS25*_xlfn.NORM.DIST(K$3,$CV25,0.3*$CV25,TRUE),$CW25*_xlfn.NORM.DIST(K$3,'energy base (MECS)'!$F$11,0.3*'energy base (MECS)'!$F$11,TRUE))} | L25: {=IF($D25,SUMPRODUCT((economics!$AG$2:$AG$167=$B25)*(economics!$D$2:$D$167="whr")*economics!$AH$2:$AH$167*_xlfn.NORM.DIST(L$3,economics!$AK$2:$AK$167,economics!$AJ$2:$AJ$167,TRUE))+$CR25*_xlfn.NORM.DIST(L$3,$CU25,0.3*$CU25,TRUE)+$CS25*_xlfn.NORM.DIST(L$3,$CV25,0.3*$CV25,TRUE),$CW25*_xlfn.NORM.DIST(L$3,'energy base (MECS)'!$F$11,0.3*'energy base (MECS)'!$F$11,TRUE))} | ... CH25: {=IF($D25,SUMPRODUCT((economics!$AG$2:$AG$167=$B25)*(economics!$D$2:$D$167="whr")*economics!$AH$2:$AH$167*_xlfn.NORM.DIST(CH$3,economics!$AK$2:$AK$167,economics!$AJ$2:$AJ$167,TRUE))+$CR25*_xlfn.NORM.DIST(CH$3,$CU25,0.3*$CU25,TRUE)+$CS25*_xlfn.NORM.DIST(CH$3,$CV25,0.3*$CV25,TRUE),$CW25*_xlfn.NORM.DIST(CH$3,'energy base (MECS)'!$F$11,0.3*'energy base (MECS)'!$F$11,TRUE))} | CJ25: {=SUMPRODUCT((economics!$AG$2:$AG$167=$B25)*(economics!$D$2:$D$167="whr")*economics!$AH$2:$AH$167)} | CK25: ='indst heat consumption'!D25 | CL25: ='indst heat consumption'!E25 | CM25: ='indst heat consumption'!F25 | CN25: ='indst heat consumption'!G25 | CO25: ='indst heat consumption'!H25 | CP25: =$C25*(CK25*summary!$B$94+CL25*summary!$C$94+CM25*summary!$D$94) | CQ25: =$C25*(CN25*summary!$E$94+CO25*summary!$F$94) | CR25: =IF(CP25+CQ25>0,CP25*MAX(0,CP25+CQ25-CJ25)/(CP25+CQ25),0) | CS25: =IF(CP25+CQ25>0,CQ25*MAX(0,CP25+CQ25-CJ25)/(CP25+CQ25),0) | CT25: =IFERROR(_xlfn.XLOOKUP($B25,'BCoISC-WACCbI'!$C$2:$C$26,'BCoISC-WACCbI'!$B$2:$B$26)+economics!$AE$4,0.1) | CU25: =(summary!$C$7*(CT25/(1-(1+CT25)^-summary!$D$7))+summary!$C$7*summary!$E$7)/(summary!$F$7*3412/1000000) | CV25: =(summary!$C$6*(CT25/(1-(1+CT25)^-summary!$D$6))+summary!$C$6*summary!$E$6)/(summary!$F$6*3412/1000000) | CW25: =CR25+CS25
