Workbook
Name gal_per_barrel: [1]About!$A$63

Sheet About
A1: BIFUbC BAU Industrial Fuel Use before CCS
A3: Sources: | B3: All Subscripts Except Waste Management | D3: Properties of Hydrogen Fuel
B4: Energy Information Administration | D4: Pacific Northwest National Laboratory
B5: 2025 | D5: Accessed 2022
B6: Annual Energy Outlook 2025 (the High Zero-Carbon Technology Cost scenario for most industries and the Alternate Transportation scenario for refined petroleum and coke and chemicals) | D6: Hydrogen Analysis Resource Center
B7: https://www.eia.gov/outlooks/aeo/ | D7: https://h2tools.org/hyarc/hydrogen-data/lower-and-higher-heating-values-hydrogen-and-other-fuels
B8: See below for listing of which tables are used for which data | D8: Lower and Higher Heating Values.xlsx
B10: Waste Management
B11: Energy Information Administration
B12: 2021
B13: Miscellaneous Electric Load Consumption Characterization 2021 Update
B14: https://www.eia.gov/analysis/studies/demand/miscelectric/pdf/miscelectric.pdf
B16: Reallocating Portions of "Balance of Manufacturing" to Specific Industry Categories
B17: U.S. Bureau of Economic Analysis
B18: 2025 (with data for 2017)
B19: https://apps.bea.gov/iTable/?reqid=1602&step=2&Categories=AR&isURI=1&_gl=1*1mimqnw*_ga*MTQwODg4MjA3OC4xNzY2NDQ0MTUw*_ga_J4698JNNFT*czE3NjY0NDQxNDkkbzEkZzEkdDE3NjY0NDU2MDIkajU4JGwwJGgw#eyJhcHBpZCI6MTYwMiwic3RlcHMiOlsxLDIsM10sImRhdGEiOltbImNhdGVnb3JpZXMiLCJBUiJdLFsiVGFibGVfTGlzdCIsIlVzZUFSUHJvIl1dfQ==
B20: "Use of Commodities by Industry" table, 405-industry breakdown
A22: Note:
A23: The words "before CCS" in this variable name indicate that this is the fuel use by industry, excluding
A24: any fuel used to power the energy-intensive process of carbon capture and sequestration. If any CCS
A25: is performed by Industry in the BAU case, this is handled in CCS sector input variables, not here.
A27: EIA Data Source and Adjustments
A28: EIA provided a detailed industrial energy consumption file from the AEO that they run on request (titled indusa),
A29: which contains several more industry categories than available online. We use this file directly for most
A30: energy consumption. However, there are a few places where we supplement with the published AEO
A31: tables where they contain data not shown in the detailed table (e.g. some refining energy consumption).
A33: The following table provides a key to the AEO data sources available for each EPS Industry Category.
A34: The places where the indusa is supplemented by the main AEO tables is also noted by red color coding
A35: in the output tabs.
... A44: Note the special handling for the hydrogen output tab, discussed below.
B46: EPS Industry Category | C46: AEO Data Source
B47: agriculture and forestry 01T03 | C47: indusa
B48: coal mining 05 | C48: indusa
B49: oil and gas extraction 06 | C49: indusa, adds Lease and Plant Fuel from Table 34 into the natural gas category (this is mapped to production instead of the "energy pipelines and gas processing" category because of how changes in energy consumption and emissions in the EPS Industry sector are calculated, as processing enegy use/emissions are more correlated with the amount of domestic production rather than the amount of domestic demand)
B50: other mining and quarrying 07T08 | C50: indusa
B51: food beverage and tobacco 10T12 | C51: indusa
B52: textiles apparel and leather 13T15 | C52: indusa
B53: wood products 16 | C53: indusa
B54: pulp paper and printing 17T18 | C54: indusa
B55: refined petroleum and coke 19 | C55: indusa (Alt Trans case), plus several tabs include line items from Table 24 that are not included in the indusa file; crude oil inputs are calculated based on Tables 24 and 11
B56: chemicals 20 | C56: indusa (Alt Trans case)
B57: rubber and plastic products 22 | C57: indusa
... B71: construction 41T43 | C71: indusa
A73: In general, the AEO provides data for industries that map well onto the EPS's Industry Categories.
A74: However, there are some differences. Since U.S. economic data (from the U.S. BEA or BLS) map
A75: perfectly onto the EPS's Industry Categories (for example, output, value added, and employment),
A76: we cannot allow the energy use to be grouped differently. Therefore, we make the following
A77: adjustments to align AEO energy use data with the BLS/BEA economic data and the EPS industry
A78: categories:
B79: Remove this from AEO's "Miscellaneous Finished Goods" | C79: Add it to:
B80: beverages and tobacco | C80: food beverage and tobacco 10T12
B81: textiles, apparel, and leather | C81: textiles apparel and leather 13T15
B82: printing & support activities | C82: pulp paper and printing 17T18
B83: BEA other manufacturing (inc. furniture) | C83: other manufacturing 31T33
B84: asphalt paving mixture, block, shingle, coating materials | C84: refined petroleum and coke 19
A86: We also use BEA data to split out the AEO transport equipment category into road and nonroad equipment.
A88: This Variable Excludes All On-Site Energy Carrier Generation (Electricity, Heat, Hydrogen)
A89: This variable is for energy purchased and consumed by the Industry sector.
A90: Secondary energy, including electricity, heat, or hydrogen that is generated on-site and also consumed on-site
A91: (e.g. entirely within an industrial facility) should not be included in this variable.
A92: Any energy carrier (electricity, heat, hydrogen) demand entered here will be
A93: supplied by the electricity, district heat, or hydrogen supply sectors respectively.
A95: No information is provided on district heat usage for industry. We assume this usage is zero.
A96: (Heat generated on-site is not district heat.)
A98: Hydrogen Demand
A99: In line with the note above, we only want to report hydrogen demand for merchant hydrogen rather than
A100: by-product hydrogen. We use AEO Table 19 to find the total hydrogen demand by sector and convert to BTU
... A118: Petroleum Fuels Mapping (based on closest BTU Content)
B119: Fuel Used in AEO | C119: Corresponding EPS Fuel
B120: Crude Oil | C120: Crude Oil
B121: Propane Heat and Power | C121: LPG/propane/butane
B122: Liquefied Petroleum Gas and Other Feedstocks | C122: LPG/propane/butane
B123: Motor Gasoline | C123: Petroleum Diesel
B124: Distillate Fuel Oil | C124: Petroleum Diesel
B125: Residual Fuel Oil | C125: Heavy or Residual Oil
B126: Petrochemical Feedstocks | C126: LPG/propane/butane
B127: Petroleum Coke | C127: Petroleum Diesel
B128: Asphalt and Road Oil | C128: Petroleum Diesel
B129: Miscellaneous Petroleum 3/ | C129: Heavy or Residual Oil
B130: Other Petroleum | C130: Heavy or Residual Oil
A132: We assign "other petroleum" to Heavy or Residual Oil because it is noted as mostly lubricants, which
A133: are more similar to heavy fuel oil than diesel fuel.

Sheet AEO 2025 Table 11 Alt Trans
B1: alttrnp.d032125a | AE1: 2048 | AF1: 2049 | AG1: 2050
C3: Report | D3: Annual Energy Outlook 2025
C4: Scenario | D4: alttrnp | F4: Alternative Transportation
C5: Datekey | D5: d032125a
C6: Release Date | E6: April 2025
B7: 11. Petroleum and Other Liquids Supply and Disposition | AH7: Average
B8: (million barrels per day, unless otherwise noted) | AH8: Annual
AD9: Avg Annual Change | AH9: Change
B10: Supply and Disposition | C10: 2024 | D10: 2025 | E10: 2026 | F10: 2027 | G10: 2028 | H10: 2029 | I10: 2030 | J10: 2031 | K10: 2032 | L10: 2033 | M10: 2034 | N10: 2035 | O10: 2036 | P10: 2037 | Q10: 2038 | R10: 2039 | S10: 2040 | T10: 2041 | U10: 2042 | V10: 2043 | W10: 2044 | X10: 2045 | Y10: 2046 | Z10: 2047 | AA10: 2048 | AB10: 2049 | AC10: 2050 | AD10: 2024-2050 | AE10: 2048 | AF10: 2049 | AG10: 2050 | AH10: 2022–2050
B12: Crude Oil
A13: PSD000:ba_DomesticCrude | B13: Domestic Crude Production 1/ | C13: 13.266058 | D13: 13.693652 | E13: 13.839074 | F13: 14.038465 | G13: 14.011215 | H13: 14.015731 | I13: 13.940209 | J13: 13.756026 | K13: 13.561993 | L13: 13.430722 | M13: 13.346446 | N13: 13.136957 | O13: 12.949175 | P13: 12.84719 | Q13: 12.758718 | R13: 12.588844 | S13: 12.433366 | T13: 12.430215 | U13: 12.487457 | V13: 12.401797 | W13: 12.272331 | X13: 12.159727 | Y13: 12.08534 | Z13: 12.215338 | AA13: 12.170947 | AB13: 12.05266 | AC13: 11.838856 | AD13: -0.0043681915 | AE13: 13.064216 | AF13: 13.201051 | AG13: 13.238148 | AH13: 0.00403
A14: PSD000:ba_Alaska | B14: Alaska | C14: 0.41062087 | D14: 0.39963207 | E14: 0.40487066 | F14: 0.46422005 | G14: 0.56030095 | H14: 0.60315979 | I14: 0.60611278 | J14: 0.62792921 | K14: 0.66175401 | L14: 0.71722645 | M14: 0.71032172 | N14: 0.68120486 | O14: 0.64413589 | P14: 0.61198485 | Q14: 0.57338315 | R14: 0.53106153 | S14: 0.48933902 | T14: 0.45479003 | U14: 0.42676017 | V14: 0.4074499 | W14: 0.38954821 | X14: 0.37030914 | Y14: 0.35324398 | Z14: 0.338072 | AA14: 0.32455087 | AB14: 0.31247112 | AC14: 0.28727165 | AD14: -0.013646115 | AE14: 0.764543 | AF14: 0.759241 | AG14: 0.728145 | AH14: 0.018448
A15: PSD000:ba_Lower48States | B15: Lower 48 States | C15: 12.855437 | D15: 13.29402 | E15: 13.434203 | F15: 13.574244 | G15: 13.450914 | H15: 13.412571 | I15: 13.334097 | J15: 13.128097 | K15: 12.900238 | L15: 12.713495 | M15: 12.636125 | N15: 12.455752 | O15: 12.305039 | P15: 12.235205 | Q15: 12.185335 | R15: 12.057782 | S15: 11.944027 | T15: 11.975426 | U15: 12.060698 | V15: 11.994348 | W15: 11.882784 | X15: 11.789417 | Y15: 11.732097 | Z15: 11.877266 | AA15: 11.846396 | AB15: 11.740189 | AC15: 11.551584 | AD15: -0.0041047932 | AE15: 12.299672 | AF15: 12.441811 | AG15: 12.510002 | AH15: 0.003349
A16: PSD000:ba_NetImports | B16: Net Imports | C16: 2.4549999 | D16: 1.8920002 | E16: 2.1775162 | F16: 1.9933624 | G16: 2.1656954 | H16: 2.313693 | I16: 2.4252987 | J16: 2.7585728 | K16: 3.0392106 | L16: 3.0914676 | M16: 3.2355583 | N16: 3.3848877 | O16: 3.5184855 | P16: 3.5493448 | Q16: 3.6603484 | R16: 3.9512239 | S16: 4.0562949 | T16: 4.0106273 | U16: 3.7918098 | V16: 3.9335723 | W16: 4.0717936 | X16: 4.2653069 | Y16: 4.2957578 | Z16: 4.1539917 | AA16: 4.2179379 | AB16: 4.3336339 | AC16: 4.6391878 | AD16: 0.024779438 | AE16: 3.920272 | AF16: 3.804193 | AG16: 3.70923 | AH16: 0.009909
A17: PSD000:ba_GrossImports | B17: Gross Imports | C17: 6.585 | D17: 6.0910001 | E17: 6.3381681 | F17: 6.0013413 | G17: 6.2358308 | H17: 6.3450432 | I17: 6.356637 | J17: 6.5245132 | K17: 6.8713169 | L17: 6.8747983 | M17: 7.0884843 | N17: 7.1651192 | O17: 7.2640347 | P17: 7.1343379 | Q17: 7.1455827 | R17: 7.3101044 | S17: 7.3866124 | T17: 7.3212247 | U17: 7.1790562 | V17: 7.2514606 | W17: 7.3556213 | X17: 7.4329057 | Y17: 7.2070584 | Z17: 7.0455523 | AA17: 7.037344 | AB17: 7.2015338 | AC17: 7.427247 | AD17: 0.0046399982 | AE17: 6.913453 | AF17: 6.763233 | AG17: 6.649956 | AH17: 0.002081
A18: PSD000:ba_Exports | B18: Exports | C18: 4.1300001 | D18: 4.1989999 | E18: 4.1606517 | F18: 4.0079789 | G18: 4.0701356 | H18: 4.0313501 | I18: 3.9313383 | J18: 3.7659404 | K18: 3.8321061 | L18: 3.7833304 | M18: 3.852926 | N18: 3.7802315 | O18: 3.745549 | P18: 3.5849934 | Q18: 3.4852343 | R18: 3.3588803 | S18: 3.3303175 | T18: 3.3105974 | U18: 3.3872464 | V18: 3.3178883 | W18: 3.2838275 | X18: 3.167599 | Y18: 2.9113004 | Z18: 2.8915603 | AA18: 2.8194063 | AB18: 2.8678997 | AC18: 2.7880592 | AD18: -0.014999133 | AE18: 2.993181 | AF18: 2.95904 | AG18: 2.940725 | AH18: -0.005787
A19: PSD000:ba_OtherCrudeSup | B19: Other Crude Supply 2/ | C19: 0.53499997 | D19: 0.57100004 | E19: 0.10617 | F19: 0.10548 | G19: 0.070079997 | H19: 0.059999999 | I19: 0.059999999 | J19: 0.059999999 | K19: 0 | L19: 0 | M19: 0 | N19: 0 | O19: 0 | P19: 0 | Q19: 0 | R19: 0 | S19: 0 | T19: 0 | U19: 0 | V19: 0 | W19: 0 | X19: 0 | Y19: 0 | Z19: 0 | AA19: 0 | AB19: 0 | AC19: 0 | AD19: -- | AE19: 0 | AF19: 0 | AG19: 0 | AH19: --
A20: PSD000:ba_TotalCrudeSup | B20: Total Crude Supply | C20: 16.256058 | D20: 16.156652 | E20: 16.122761 | F20: 16.137306 | G20: 16.24699 | H20: 16.389423 | I20: 16.425508 | J20: 16.574598 | K20: 16.601204 | L20: 16.52219 | M20: 16.582005 | N20: 16.521845 | O20: 16.467661 | P20: 16.396534 | Q20: 16.419067 | R20: 16.540068 | S20: 16.48966 | T20: 16.440842 | U20: 16.279266 | V20: 16.335369 | W20: 16.344124 | X20: 16.425034 | Y20: 16.381098 | Z20: 16.369329 | AA20: 16.388885 | AB20: 16.386293 | AC20: 16.478043 | AD20: 0.00052179455 | AE20: 16.984488 | AF20: 17.005243 | AG20: 16.947378 | AH20: 0.003854
A22: PSD000:ca_NetProductImp | B22: Net Product Imports | C22: -4.7969999 | D22: -4.4340005 | E22: -5.3931117 | F22: -5.6637378 | G22: -5.8147402 | H22: -6.0862393 | I22: -6.3148069 | J22: -6.4986482 | K22: -6.7580967 | L22: -6.8829226 | M22: -7.1004648 | N22: -7.2989154 | O22: -7.3504176 | P22: -7.3862834 | Q22: -7.55582 | R22: -7.7120018 | S22: -7.6603565 | T22: -7.6474137 | U22: -7.5461054 | V22: -7.6730962 | W22: -7.7635083 | X22: -7.9331498 | Y22: -8.0228386 | Z22: -8.0455475 | AA22: -8.0462437 | AB22: -7.9991622 | AC22: -8.0336752 | AD22: 0.020030722 | AE22: -6.658555 | AF22: -6.624732 | AG22: -6.431421 | AH22: 0.017224
A23: PSD000:ca_GrossRefinedP | B23: Gross Refined Product Imports 3/ | C23: 0.66500002 | D23: 0.65899998 | E23: 0.74173576 | F23: 0.74009639 | G23: 0.73737037 | H23: 0.73435467 | I23: 0.74169171 | J23: 0.75268632 | K23: 0.75330985 | L23: 0.75508237 | M23: 0.75996852 | N23: 0.76140255 | O23: 0.76254404 | P23: 0.76617682 | Q23: 0.76701474 | R23: 0.76568347 | S23: 0.76656389 | T23: 0.77134937 | U23: 0.77358657 | V23: 0.77358884 | W23: 0.77418184 | X23: 0.78442264 | Y23: 0.7686832 | Z23: 0.76776731 | AA23: 0.79498076 | AB23: 0.79559314 | AC23: 0.77234918 | AD23: 0.0057723531 | AE23: 0.805134 | AF23: 0.810104 | AG23: 0.773733 | AH23: -0.009681
A24: PSD000:ca_UnfinishedOil | B24: Unfinished Oil Imports | C24: 0.59200001 | D24: 0.58200002 | E24: 0.59942865 | F24: 0.59710908 | G24: 0.59515744 | H24: 0.59320581 | I24: 0.58276296 | J24: 0.58930254 | K24: 0.5790931 | L24: 0.57725811 | M24: 0.57542318 | N24: 0.57395619 | O24: 0.57212126 | P24: 0.57028633 | Q24: 0.5684514 | R24: 0.55160463 | S24: 0.5497697 | T24: 0.54756814 | U24: 0.56073201 | V24: 0.55889708 | W24: 0.55706209 | X24: 0.54001164 | Y24: 0.55302429 | Z24: 0.55285913 | AA24: 0.55238223 | AB24: 0.5475902 | AC24: 0.53426778 | AD24: -0.0039387407 | AE24: 0.549354 | AF24: 0.54752 | AG24: 0.545493 | AH24: -0.009369
A25: PSD000:ca_BlendingCompo | B25: Blending Component Imports | C25: 0.60500002 | D25: 0.60500002 | E25: 0.53568333 | F25: 0.48372349 | G25: 0.4439463 | H25: 0.41017503 | I25: 0.37991047 | J25: 0.35651109 | K25: 0.33064896 | L25: 0.31053254 | M25: 0.29528698 | N25: 0.27803043 | O25: 0.27208009 | P25: 0.26686966 | Q25: 0.26301065 | R25: 0.26084292 | S25: 0.25915292 | T25: 0.25786659 | U25: 0.25322995 | V25: 0.25596577 | W25: 0.2564913 | X25: 0.25691581 | Y25: 0.25923806 | Z25: 0.261724 | AA25: 0.26749563 | AB25: 0.27378368 | AC25: 0.27946764 | AD25: -0.02926859 | AE25: 0.380901 | AF25: 0.387239 | AG25: 0.393548 | AH25: -0.004218
A26: PSD000:ca_Exports | B26: Exports | C26: 6.6589999 | D26: 6.2800002 | E26: 7.2699594 | F26: 7.4846668 | G26: 7.5912142 | H26: 7.8239746 | I26: 8.0191717 | J26: 8.1971483 | K26: 8.4211483 | L26: 8.5257959 | M26: 8.731144 | N26: 8.9123039 | O26: 8.9571629 | P26: 8.9896164 | Q26: 9.1542969 | R26: 9.2901335 | S26: 9.2358427 | T26: 9.2241983 | U26: 9.1336536 | V26: 9.261548 | W26: 9.351244 | X26: 9.5144997 | Y26: 9.6037836 | Z26: 9.6278982 | AA26: 9.6611023 | AB26: 9.6161289 | AC26: 9.6197605 | AD26: 0.014248637 | AE26: 8.393944 | AF26: 8.369595 | AG26: 8.144195 | AH26: 0.010046
A27: PSD000:ca_RefineryProce | B27: Refinery Processing Gain 4/ | C27: 0.98000002 | D27: 1.016 | E27: 0.90159047 | F27: 0.87853771 | G27: 0.91380489 | H27: 0.93051493 | I27: 0.93910778 | J27: 0.93981522 | K27: 0.9594422 | L27: 0.95770127 | M27: 0.96941692 | N27: 0.96152616 | O27: 0.97701991 | P27: 0.97750109 | Q27: 0.97359896 | R27: 0.98396575 | S27: 0.98303294 | T27: 0.98112708 | U27: 0.97470093 | V27: 0.97656184 | W27: 0.97273654 | X27: 0.97380805 | Y27: 0.96531028 | Z27: 0.96246451 | AA27: 0.96213937 | AB27: 0.95689845 | AC27: 0.96412009 | AD27: -0.00062813839 | AE27: 0.973956 | AF27: 0.974545 | AG27: 0.965124 | AH27: -0.001622
A28: PSD000:ProductStockDraw | B28: Product Stock Withdrawal | C28: 0.048 | D28: -0.011 | E28: 0 | F28: 0 | G28: 0 | H28: 0 | I28: 0 | J28: 0 | K28: 0 | L28: 0 | M28: 0 | N28: 0 | O28: 0 | P28: 0 | Q28: 0 | R28: 0 | S28: 0 | T28: 0 | U28: 0 | V28: 0 | W28: 0 | X28: 0 | Y28: 0 | Z28: 0 | AA28: 0 | AB28: 0 | AC28: 0 | AD28: -- | AE28: 0 | AF28: 0 | AG28: 0 | AH28: --
A29: PSD000:ca_NaturalGasPla | B29: Natural Gas Plant Liquids | C29: 6.8487673 | D29: 6.9222689 | E29: 7.4246435 | F29: 7.6437483 | G29: 7.6547918 | H29: 7.6884294 | I29: 7.7403307 | J29: 7.6810575 | K29: 7.7766018 | L29: 7.8726325 | M29: 7.9454503 | N29: 8.1236935 | O29: 8.1454334 | P29: 8.2023191 | Q29: 8.2853785 | R29: 8.2694407 | S29: 8.2659359 | T29: 8.2955713 | U29: 8.3512173 | V29: 8.4079313 | W29: 8.4561825 | X29: 8.518302 | Y29: 8.6038322 | Z29: 8.6799364 | AA29: 8.7107763 | AB29: 8.7141981 | AC29: 8.6905966 | AD29: 0.0092025823 | AE29: 7.166816 | AF29: 7.201195 | AG29: 7.223709 | AH29: 0.006831
A30: PSD000:ca_Hydrogeb | B30: Hydrogen 5/ | C30: 8.3062735 | D30: 8.3583136 | E30: 8.9121571 | F30: 9.1428165 | G30: 9.0858173 | H30: 9.1176319 | I30: 9.1689453 | J30: 9.1082878 | K30: 9.2017498 | L30: 9.2964916 | M30: 9.3937244 | N30: 9.5747032 | O30: 9.5822945 | P30: 9.6281366 | Q30: 9.7292938 | R30: 9.7108603 | S30: 9.7017021 | T30: 9.7291346 | U30: 9.7831783 | V30: 9.838479 | W30: 9.8863745 | X30: 9.9508924 | Y30: 10.044309 | Z30: 10.134096 | AA30: 10.167455 | AB30: 10.181632 | AC30: 10.171256 | AD30: 0.0078209885
A31: PSD000:from_Renewables | B31: Biofuels | C31: 1.2375062 | D31: 1.2160439 | E31: 1.2622174 | F31: 1.2737726 | G31: 1.2059509 | H31: 1.205182 | I31: 1.2033191 | J31: 1.2019346 | K31: 1.1998516 | L31: 1.1985633 | M31: 1.2229778 | N31: 1.2257136 | O31: 1.2115651 | P31: 1.2005217 | Q31: 1.2186189 | R31: 1.2161235 | S31: 1.2104707 | T31: 1.2082673 | U31: 1.2066653 | V31: 1.2052517 | W31: 1.204896 | X31: 1.2072945 | Y31: 1.2151804 | Z31: 1.2288632 | AA31: 1.2313821 | AB31: 1.2421379 | AC31: 1.2553636 | AD31: 0.00055119233 | AE31: 1.163749 | AF31: 1.181888 | AG31: 1.196141 | AH31: 0.001356
A32: PSD000:cb_TotalEthanol | B32: Ethanol (undenatured) | C32: 0.89962983 | D32: 0.90398222 | E32: 0.92223638 | F32: 0.9248206 | G32: 0.92163283 | H32: 0.91708481 | I32: 0.91132659 | J32: 0.90740526 | K32: 0.90213406 | L32: 0.898054 | M32: 0.89526153 | N32: 0.89227635 | O32: 0.88661826 | P32: 0.88121343 | Q32: 0.87751985 | R32: 0.87381512 | S32: 0.87144601 | T32: 0.86933738 | U32: 0.86621034 | V32: 0.86530417 | W32: 0.86331224 | X32: 0.86287463 | Y32: 0.86172152 | Z32: 0.86258709 | AA32: 0.86133522 | AB32: 0.86205858 | AC32: 0.8650347 | AD32: -0.0015070847 | AE32: 0.858167 | AF32: 0.86727 | AG32: 0.878013 | AH32: -0.000415
A33: PSD000:ca_DomesticEthan | B33: Domestic Production | C33: 1.0228798 | D33: 1.0248302 | E33: 1.0403882 | F33: 1.0419692 | G33: 1.0420033 | H33: 1.0426598 | I33: 1.0419941 | J33: 1.041517 | K33: 1.0413069 | L33: 1.0418068 | M33: 1.0419081 | N33: 1.0411739 | O33: 1.0428159 | P33: 1.0448785 | Q33: 1.0452884 | R33: 1.0493288 | S33: 1.055146 | T33: 1.0576329 | U33: 1.0592115 | V33: 1.0711412 | W33: 1.0752956 | X33: 1.0801607 | Y33: 1.0844382 | Z33: 1.0908749 | AA33: 1.0953219 | AB33: 1.1018975 | AC33: 1.1049199 | AD33: 0.0029717466 | AE33: 1.102327 | AF33: 1.113072 | AG33: 1.121086 | AH33: 0.004852
A34: PSD000:ca_EthanolImport | B34: Net Imports | C34: -0.12325 | D34: -0.120848 | E34: -0.11815185 | F34: -0.11714857 | G34: -0.12037047 | H34: -0.12557498 | I34: -0.13066749 | J34: -0.13411175 | K34: -0.13917278 | L34: -0.14375283 | M34: -0.14664665 | N34: -0.14889759 | O34: -0.15619764 | P34: -0.16366504 | Q34: -0.16776858 | R34: -0.1755137 | S34: -0.1837 | T34: -0.18829556 | U34: -0.19300112 | V34: -0.20583709 | W34: -0.21198334 | X34: -0.21728612 | Y34: -0.22271666 | Z34: -0.22828779 | AA34: -0.23398666 | AB34: -0.23983888 | AC34: -0.23988521 | AD34: 0.025944135 | AE34: -0.24416 | AF34: -0.245802 | AG34: -0.243073 | AH34: 0.035821
A35: PSD000:cb_TotalBiodiesl | B35: Biodiesel | C35: 0.12139644 | D35: 0.10103945 | E35: 0.10270155 | F35: 0.096831784 | G35: 0.059198756 | H35: 0.069466762 | I35: 0.07241486 | J35: 0.073744856 | K35: 0.074368209 | L35: 0.077496417 | M35: 0.084545314 | N35: 0.089571968 | O35: 0.088854894 | P35: 0.093317956 | Q35: 0.092993245 | R35: 0.091702439 | S35: 0.090348974 | T35: 0.088931568 | U35: 0.087448962 | V35: 0.085899837 | W35: 0.084543794 | X35: 0.082857601 | Y35: 0.081100821 | Z35: 0.079272017 | AA35: 0.077369772 | AB35: 0.075392589 | AC35: 0.073338971 | AD35: -0.019196788 | AE35: 0.060377 | AF35: 0.057682 | AG35: 0.054987 | AH35: --
A36: PSD000:cb_DomesticBiodi | B36: Domestic Production | C36: 0.108 | D36: 0.10557124 | E36: 0.094603211 | F36: 0.088692948 | G36: 0.051019225 | H36: 0.061246332 | I36: 0.064153329 | J36: 0.065442018 | K36: 0.066023856 | L36: 0.069110341 | M36: 0.076117307 | N36: 0.081101827 | O36: 0.080342397 | P36: 0.084762901 | Q36: 0.084395416 | R36: 0.083061621 | S36: 0.08166495 | T36: 0.080204122 | U36: 0.078677878 | V36: 0.077084899 | W36: 0.075684778 | X36: 0.073954292 | Y36: 0.072152995 | Z36: 0.070279457 | AA36: 0.068332247 | AB36: 0.066309877 | AC36: 0.064210847 | AD36: -0.019799782 | AE36: 0.051339 | AF36: 0.048599 | AG36: 0.045859 | AH36: -0.029806
A37: PSD000:cb_BiodieselImpo | B37: Net Imports | C37: 0.013396445 | D37: -0.0045317831 | E37: 0.0080983434 | F37: 0.0081388364 | G37: 0.0081795305 | H37: 0.0082204277 | I37: 0.0082615297 | J37: 0.0083028376 | K37: 0.0083443513 | L37: 0.0083860727 | M37: 0.0084280036 | N37: 0.0084701432 | O37: 0.0085124942 | P37: 0.0085550565 | Q37: 0.0085978322 | R37: 0.0086408211 | S37: 0.0086840251 | T37: 0.0087274453 | U37: 0.0087710833 | V37: 0.0088149374 | W37: 0.0088590123 | X37: 0.0089033078 | Y37: 0.0089478241 | Z37: 0.008992563 | AA37: 0.0090375263 | AB37: 0.0090827141 | AC37: 0.0091281272 | AD37: -0.014646633 | AE37: 0.009038 | AF37: 0.009083 | AG37: 0.009128 | AH37: --
A38: PSD000:cb_TotalRenewableBiodiesl | B38: Renewable Diesel | C38: 0.21056423 | D38: 0.20132892 | E38: 0.22745721 | F38: 0.22205755 | G38: 0.19547884 | H38: 0.18923268 | I38: 0.19006601 | J38: 0.19125785 | K38: 0.19378066 | L38: 0.19346045 | M38: 0.21322477 | N38: 0.21391486 | O38: 0.2063068 | P38: 0.19575992 | Q38: 0.21744311 | R38: 0.21990336 | S38: 0.21802208 | T38: 0.21932875 | U38: 0.22228675 | V38: 0.22331826 | W38: 0.22626144 | X38: 0.23070426 | Y38: 0.2412954 | Z38: 0.25565976 | AA38: 0.26123065 | AB38: 0.27301162 | AC38: 0.28508034 | AD38: 0.011721251 | AE38: 0.240211 | AF38: 0.251702 | AG38: 0.257954 | AH38: 0.017899
A39: PSD000:cb_DomesticBiodi | B39: Domestic Production | C39: 0.17383203 | D39: 0.17999749 | E39: 0.1864015 | F39: 0.18048865 | G39: 0.15926315 | H39: 0.15256429 | I39: 0.15293926 | J39: 0.15366702 | K39: 0.15571994 | L39: 0.15492398 | M39: 0.17420658 | N39: 0.17440894 | O39: 0.16630706 | P39: 0.15526019 | Q39: 0.17643712 | R39: 0.17838481 | S39: 0.17598455 | T39: 0.17676574 | U39: 0.17919171 | V39: 0.17968453 | W39: 0.18208228 | X39: 0.18597287 | Y39: 0.19600487 | Z39: 0.20980309 | AA39: 0.21480079 | AB39: 0.22600137 | AC39: 0.23748246 | AD39: 0.012072455 | AE39: 0.193781 | AF39: 0.204692 | AG39: 0.210356 | AH39: 0.015761
A40: PSD000:cb_BiodieselImpo | B40: Net Imports | C40: 0.036732204 | D40: 0.021331433 | E40: 0.041055705 | F40: 0.041568901 | G40: 0.036215696 | H40: 0.036668394 | I40: 0.037126746 | J40: 0.037590832 | K40: 0.038060717 | L40: 0.038536478 | M40: 0.03901818 | N40: 0.03950591 | O40: 0.039999735 | P40: 0.040499728 | Q40: 0.041005976 | R40: 0.04151855 | S40: 0.042037532 | T40: 0.042563003 | U40: 0.043095041 | V40: 0.043633729 | W40: 0.044179149 | X40: 0.04473139 | Y40: 0.04529053 | Z40: 0.045856662 | AA40: 0.046429869 | AB40: 0.047010247 | AC40: 0.047597874 | AD40: 0.010016534 | AE40: 0.04643 | AF40: 0.04701 | AG40: 0.047598 | AH40: 0.029306
A41: PSD000:Other_BM-derived | B41: Other Biomass-derived Liquids 6/ | C41: 0.0059156041 | D41: 0.0096933525 | E41: 0.0098222801 | F41: 0.030062634 | G41: 0.029640473 | H41: 0.02939764 | I41: 0.029511649 | J41: 0.029526625 | K41: 0.029568642 | L41: 0.029552519 | M41: 0.029946186 | N41: 0.029950442 | O41: 0.029785194 | P41: 0.03023036 | Q41: 0.030662647 | R41: 0.030702494 | S41: 0.030653605 | T41: 0.030669641 | U41: 0.030719234 | V41: 0.030729385 | W41: 0.030778408 | X41: 0.0308579 | Y41: 0.03106273 | Z41: 0.031344425 | AA41: 0.031446498 | AB41: 0.031675179 | AC41: 0.031909589 | AD41: 0.066966663 | AE41: 0.004994 | AF41: 0.005235 | AG41: 0.005188 | AH41: 0.016102
A42: PSD000:Other_BM_Dome | B42: Domestic Production | C42: 0.0059156041 | D42: 0.0096933525 | E42: 0.0098222801 | F42: 0.030062634 | G42: 0.029640473 | H42: 0.02939764 | I42: 0.029511649 | J42: 0.029526625 | K42: 0.029568642 | L42: 0.029552519 | M42: 0.029946186 | N42: 0.029950442 | O42: 0.029785194 | P42: 0.03023036 | Q42: 0.030662647 | R42: 0.030702494 | S42: 0.030653605 | T42: 0.030669641 | U42: 0.030719234 | V42: 0.030729385 | W42: 0.030778408 | X42: 0.0308579 | Y42: 0.03106273 | Z42: 0.031344425 | AA42: 0.031446498 | AB42: 0.031675179 | AC42: 0.031909589 | AD42: 0.066966663 | AE42: 0.004994 | AF42: 0.005235 | AG42: 0.005188 | AH42: 0.016102
A43: PSD000:Other_BM_NetImp | B43: Net Imports | C43: 0 | D43: 0 | E43: 0 | F43: 0 | G43: 0 | H43: 0 | I43: 0 | J43: 0 | K43: 0 | L43: 0 | M43: 0 | N43: 0 | O43: 0 | P43: 0 | Q43: 0 | R43: 0 | S43: 0 | T43: 0 | U43: 0 | V43: 0 | W43: 0 | X43: 0 | Y43: 0 | Z43: 0 | AA43: 0 | AB43: 0 | AC43: 0 | AD43: -- | AE43: 0 | AF43: 0 | AG43: 0 | AH43: --
A44: PSD000:Other_BM_Stock | B44: Stock Withdrawal | C44: 0 | D44: 0 | E44: 0 | F44: 0 | G44: 0 | H44: 0 | I44: 0 | J44: 0 | K44: 0 | L44: 0 | M44: 0 | N44: 0 | O44: 0 | P44: 0 | Q44: 0 | R44: 0 | S44: 0 | T44: 0 | U44: 0 | V44: 0 | W44: 0 | X44: 0 | Y44: 0 | Z44: 0 | AA44: 0 | AB44: 0 | AC44: 0 | AD44: -- | AE44: 0 | AF44: 0 | AG44: 0 | AH44: --
A45: PSD000:ca_OtherOther | B45: Other 7/ | C45: 0.22 | D45: 0.22 | E45: 0.2252962 | F45: 0.2252962 | G45: 0.22507462 | H45: 0.22402112 | I45: 0.2252962 | J45: 0.2252962 | K45: 0.2252962 | L45: 0.2252962 | M45: 0.2252962 | N45: 0.2252962 | O45: 0.2252962 | P45: 0.2252962 | Q45: 0.2252962 | R45: 0.2252962 | S45: 0.2252962 | T45: 0.2252962 | U45: 0.2252962 | V45: 0.2252962 | W45: 0.2252962 | X45: 0.2252962 | Y45: 0.2252962 | Z45: 0.2252962 | AA45: 0.2252962 | AB45: 0.2252962 | AC45: 0.2252962 | AD45: 0.00091535857 | AE45: 0.240915 | AF45: 0.241168 | AG45: 0.240079 | AH45: 0.002962
A47: PSD000:da_TotalPrimaryS | B47: Total Primary Supply 8/ | C47: 20.793331 | D47: 21.085964 | E47: 20.543396 | F47: 20.494923 | G47: 20.431873 | H47: 20.35133 | I47: 20.218754 | J47: 20.124054 | K47: 20.004299 | L47: 19.893459 | M47: 19.844681 | N47: 19.759159 | O47: 19.676558 | P47: 19.615887 | Q47: 19.566139 | R47: 19.522892 | S47: 19.514038 | T47: 19.503689 | U47: 19.491039 | V47: 19.477314 | W47: 19.439728 | X47: 19.416584 | Y47: 19.367878 | Z47: 19.420341 | AA47: 19.472237 | AB47: 19.525661 | AC47: 19.579742 | AD47: -0.0023102824 | AE47: 19.871368 | AF47: 19.979309 | AG47: 20.14101 | AH47: 0.000952
B50: Product Supplied
B51: by Fuel
A52: PSD000:ea_LiqPetGas | B52: Hydrocarbon Gas Liquids 9/ | C52: 3.585 | D52: 3.6140001 | E52: 3.6623759 | F52: 3.6664758 | G52: 3.6725259 | H52: 3.6765642 | I52: 3.6772616 | J52: 3.6769929 | K52: 3.6821861 | L52: 3.695914 | M52: 3.7182603 | N52: 3.730968 | O52: 3.7388787 | P52: 3.7566409 | Q52: 3.7727873 | R52: 3.7857547 | S52: 3.8296173 | T52: 3.871742 | U52: 3.920011 | V52: 3.9323568 | W52: 3.9418168 | X52: 3.9448662 | Y52: 3.9323759 | Z52: 3.9832308 | AA52: 4.0516658 | AB52: 4.1095324 | AC52: 4.150485 | AD52: 0.0056492324 | AE52: 4.868012 | AF52: 4.905651 | AG52: 4.97313 | AH52: 0.013366
A53: PSD000:ea_MotorGasoline | B53: Motor Gasoline 10/ | C53: 8.9420004 | D53: 8.9469995 | E53: 8.9520025 | F53: 8.9171867 | G53: 8.8273106 | H53: 8.7263632 | I53: 8.6153345 | J53: 8.5229397 | K53: 8.4195929 | L53: 8.3285732 | M53: 8.2501879 | N53: 8.1708698 | O53: 8.0772905 | P53: 7.9869614 | Q53: 7.9140239 | R53: 7.8417883 | S53: 7.7821794 | T53: 7.7291451 | U53: 7.6671958 | V53: 7.627224 | W53: 7.5769868 | X53: 7.5407166 | Y53: 7.4987454 | Z53: 7.4744277 | AA53: 7.4319081 | AB53: 7.406528 | AC53: 7.3997025 | AD53: -0.0072550739 | AE53: 7.329745 | AF53: 7.374018 | AG53: 7.431168 | AH53: -0.005967
A54: PSD000:ea_E85E85E85E85 | B54: of which: E85 11/ | C54: 0.0025753288 | D54: 0.0023798347 | E54: 0.0021791055 | F54: 0.0019500109 | G54: 0.0018875961 | H54: 0.0018430116 | I54: 0.0017648952 | J54: 0.001620793 | K54: 0.0015140732 | L54: 0.0014075681 | M54: 0.0013184585 | N54: 0.0012381718 | O54: 0.0011641728 | P54: 0.0011242828 | Q54: 0.0010379453 | R54: 0.0010100839 | S54: 0.00098976342 | T54: 0.00097242161 | U54: 0.0009507194 | V54: 0.00092851085 | W54: 0.00093115406 | X54: 0.00090255542 | Y54: 0.00089443865 | Z54: 0.00091116154 | AA54: 0.0009048974 | AB54: 0.00089826382 | AC54: 0.00088356755 | AD54: -0.040309841 | AE54: 0.013778 | AF54: 0.013969 | AG54: 0.01415 | AH54: -0.017487
A55: PSD000:ea_JetFuel | B55: Jet Fuel 12/ | C55: 1.696 | D55: 1.726 | E55: 1.7317746 | F55: 1.7386062 | G55: 1.7517883 | H55: 1.7667621 | I55: 1.779703 | J55: 1.7888781 | K55: 1.8001851 | L55: 1.8119309 | M55: 1.8232173 | N55: 1.8377693 | O55: 1.8537691 | P55: 1.8726456 | Q55: 1.8928964 | R55: 1.9136384 | S55: 1.9340479 | T55: 1.9533651 | U55: 1.9749453 | V55: 1.9950753 | W55: 2.0127919 | X55: 2.0297608 | Y55: 2.0456357 | Z55: 2.0651824 | AA55: 2.0861969 | AB55: 2.1050286 | AC55: 2.1236806 | AD55: 0.0086866731 | AE55: 2.145059 | AF55: 2.172902 | AG55: 2.203979 | AH55: 0.012698
A56: PSD000:ea_DistillateFue | B56: Distillate Fuel Oil 13/ | C56: 4.1020002 | D56: 4.2579999 | E56: 4.249269 | F56: 4.213994 | G56: 4.1928124 | H56: 4.1705971 | I56: 4.1381207 | J56: 4.1059275 | K56: 4.0634823 | L56: 4.0309052 | M56: 3.9984694 | N56: 3.9677703 | O56: 3.9446568 | P56: 3.9243164 | Q56: 3.9079809 | R56: 3.8860016 | S56: 3.8676162 | T56: 3.848937 | U56: 3.8344526 | V56: 3.8198125 | W56: 3.8043528 | X56: 3.7924743 | Y56: 3.7803826 | Z56: 3.780797 | AA56: 3.7818596 | AB56: 3.7823682 | AC56: 3.7786644 | AD56: -0.0031528699 | AE56: 3.479365 | AF56: 3.476026 | AG56: 3.481913 | AH56: -0.004602
A57: PSD000:eb_DieselAllSect | B57: of which: Diesel | C57: 3.523 | D57: 3.6760001 | E57: 3.8272917 | F57: 3.7983267 | G57: 3.7818236 | H57: 3.7637734 | I57: 3.7369032 | J57: 3.7095008 | K57: 3.6745825 | L57: 3.6445544 | M57: 3.6147056 | N57: 3.5865676 | O57: 3.5651877 | P57: 3.5468953 | Q57: 3.5327046 | R57: 3.5126729 | S57: 3.4965434 | T57: 3.4802442 | U57: 3.4680882 | V57: 3.4555838 | W57: 3.4427137 | X57: 3.4328263 | Y57: 3.4223754 | Z57: 3.4240305 | AA57: 3.4261856 | AB57: 3.4276762 | AC57: 3.4250884 | AD57: -0.0010834748 | AE57: 3.197692 | AF57: 3.196416 | AG57: 3.204183 | AH57: -0.004855
A58: PSD000:ea_ResidualFuel | B58: Residual Fuel Oil | C58: 0.28799999 | D58: 0.27000001 | E58: 0.25959659 | F58: 0.26330677 | G58: 0.26424536 | H58: 0.26735225 | I58: 0.27011693 | J58: 0.27228391 | K58: 0.27413416 | L58: 0.27579799 | M58: 0.27777702 | N58: 0.28046942 | O58: 0.2821885 | P58: 0.28426203 | Q58: 0.28560576 | R58: 0.28713161 | S58: 0.28836259 | T58: 0.28849226 | U58: 0.28863305 | V58: 0.28878129 | W58: 0.28881848 | X58: 0.28892857 | Y58: 0.2906782 | Z58: 0.29254425 | AA58: 0.29472464 | AB58: 0.29664636 | AC58: 0.29849967 | AD58: 0.0013781951 | AE58: 0.212655 | AF58: 0.21106 | AG58: 0.209144 | AH58: -0.018817
A59: PSD000:ea_Other | B59: Other 14/ | C59: 1.665 | D59: 1.691 | E59: 1.6829168 | F59: 1.6890352 | G59: 1.7210267 | H59: 1.7333032 | I59: 1.7397866 | J59: 1.7537948 | K59: 1.7654152 | L59: 1.7655158 | M59: 1.7785542 | N59: 1.7805166 | O59: 1.7891765 | P59: 1.794718 | Q59: 1.7962399 | R59: 1.8051701 | S59: 1.808767 | T59: 1.8088677 | U59: 1.8028208 | V59: 1.8106033 | W59: 1.810539 | X59: 1.8160582 | Y59: 1.8157229 | Z59: 1.8156441 | AA59: 1.8174932 | AB59: 1.8173676 | AC59: 1.8217478 | AD59: 0.0034664272 | AE59: 1.857642 | AF59: 1.862096 | AG59: 1.863454 | AH59: 0.000784
B60: by Sector
A61: PSD000:fa_Residentialan | B61: Residential and Commercial | C61: 1.0578766 | D61: 1.1055152 | E61: 1.1091573 | F61: 1.1105212 | G61: 1.1111432 | H61: 1.1101173 | I61: 1.108466 | J61: 1.1069376 | K61: 1.106403 | L61: 1.1067103 | M61: 1.1065373 | N61: 1.1068175 | O61: 1.1080761 | P61: 1.1096965 | Q61: 1.1115468 | R61: 1.113495 | S61: 1.1156408 | T61: 1.1179688 | U61: 1.1206185 | V61: 1.1232225 | W61: 1.1259025 | X61: 1.1285496 | Y61: 1.1314036 | Z61: 1.1346115 | AA61: 1.1381208 | AB61: 1.1417665 | AC61: 1.1452484 | AD61: 0.0030568893 | AE61: 0.907139 | AF61: 0.905504 | AG61: 0.904027 | AH61: -0.005139
A62: PSD000:fa_Industrial | B62: Industrial 15/ | C62: 5.3582535 | D62: 5.4138851 | E62: 5.4991713 | F62: 5.5169783 | G62: 5.5650744 | H62: 5.5920291 | I62: 5.611187 | J62: 5.6337376 | K62: 5.6598506 | L62: 5.6795545 | M62: 5.7199502 | N62: 5.740766 | O62: 5.7637734 | P62: 5.7924986 | Q62: 5.8153481 | R62: 5.8412023 | S62: 5.8915052 | T62: 5.936296 | U62: 5.9818602 | V62: 6.0046272 | W62: 6.0159054 | X62: 6.0282092 | Y62: 6.0194693 | Z62: 6.0753498 | AA62: 6.1502838 | AB62: 6.2133803 | AC62: 6.2632518 | AD62: 0.0060204128 | AE62: 6.893939 | AF62: 6.935251 | AG62: 7.006616 | AH62: 0.008412
A63: PSD000:fa_Transportatio | B63: Transportation | C63: 14.17246 | D63: 14.200508 | E63: 14.104213 | F63: 13.967547 | G63: 13.861677 | H63: 13.744924 | I63: 13.609481 | J63: 13.489232 | K63: 13.351422 | L63: 13.233884 | M63: 13.130118 | N63: 13.029602 | O63: 12.921593 | P63: 12.82407 | Q63: 12.748586 | R63: 12.669785 | S63: 12.607664 | T63: 12.551304 | U63: 12.491521 | V63: 12.452889 | W63: 12.40123 | X63: 12.364955 | Y63: 12.320742 | Z63: 12.309518 | AA63: 12.282042 | AB63: 12.268525 | AC63: 12.270431 | AD63: -0.0055272937 | AE63: 12.124934 | AF63: 12.19198 | AG63: 12.283104 | AH63: -0.003884
A64: PSD000:fa_ElectricPower | B64: Electric Power 16/ | C64: 0.050709266 | D64: 0.049653932 | E64: 0.046516303 | F64: 0.042606272 | G64: 0.039803367 | H64: 0.037977554 | I64: 0.035263076 | J64: 0.033313729 | K64: 0.028180882 | L64: 0.027659336 | M64: 0.027588576 | N64: 0.027343418 | O64: 0.027135337 | P64: 0.026587836 | Q64: 0.025942029 | R64: 0.025805572 | S64: 0.025434891 | T64: 0.023855295 | U64: 0.022129456 | V64: 0.02059391 | W64: 0.018528806 | X64: 0.017087439 | Y64: 0.01689123 | Z64: 0.016788838 | AA64: 0.016874954 | AB64: 0.01689315 | AC64: 0.017059783 | AD64: -0.041033769 | AE64: 0.020744 | AF64: 0.020784 | AG64: 0.02068 | AH64: -0.032277
A65: PSD000:fa_balancesector | B65: Unspecified Sector 17/ | C65: -0.38510609 | D65: -0.29773566 | E65: -0.22555155 | F65: -0.15393811 | G65: -0.15241364 | H65: -0.15070929 | I65: -0.1487985 | J65: -0.14714091 | K65: -0.14524759 | L65: -0.14360699 | M65: -0.14214374 | N65: -0.14067933 | O65: -0.13910362 | P65: -0.13762243 | Q65: -0.13641717 | R65: -0.1351648 | S65: -0.13413209 | T65: -0.13318872 | U65: -0.13217194 | V65: -0.13144383 | W65: -0.13057496 | X65: -0.12990949 | Y65: -0.12915219 | Z65: -0.12876694 | AA65: -0.1281518 | AB65: -0.12774548 | AC65: -0.12754411 | AD65: -0.041611622 | AE65: -0.05684 | AF65: -0.055819 | AG65: -0.055094 | AH65: -0.062201
A66: PSD000:fa_Total | B66: Total | C66: 20.278 | D66: 20.506001 | E66: 20.537933 | F66: 20.488605 | G66: 20.42971 | H66: 20.340942 | I66: 20.220322 | J66: 20.120817 | K66: 20.004995 | L66: 19.908638 | M66: 19.846466 | N66: 19.768364 | O66: 19.685961 | P66: 19.619545 | Q66: 19.569536 | R66: 19.519484 | S66: 19.51059 | T66: 19.500551 | U66: 19.488058 | V66: 19.473854 | W66: 19.435307 | X66: 19.412804 | Y66: 19.363541 | Z66: 19.411825 | AA66: 19.46385 | AB66: 19.517469 | AC66: 19.572781 | AD66: -0.0013604849 | AE66: 19.892477 | AF66: 20.001751 | AG66: 20.162788 | AH66: 0.00046
A68: PSD000:ga_Discrepancy | B68: Discrepancy 18/ | C68: 0.51533127 | D68: 0.57996368 | E68: 0.0054626465 | F68: 0.0063171387 | G68: 0.0021629333 | H68: 0.010387421 | I68: -0.0015678406 | J68: 0.0032367706 | K68: -0.00069618225 | L68: -0.01517868 | M68: -0.0017852783 | N68: -0.0092048645 | O68: -0.0094032288 | P68: -0.0036582947 | Q68: -0.0033969879 | R68: 0.003408432 | S68: 0.0034484863 | T68: 0.0031375885 | U68: 0.0029811859 | V68: 0.0034599304 | W68: 0.0044212341 | X68: 0.003780365 | Y68: 0.0043373108 | Z68: 0.0085163116 | AA68: 0.0083866119 | AB68: 0.0081920624 | AC68: 0.0069618225 | AD68: -0.15257475 | AE68: -0.021109 | AF68: -0.022442 | AG68: -0.021778 | AH68: -0.088724
A70: PSD000:ha_DomesticRefin | B70: Domestic Refinery Distillation Capacity 19/ | C70: 18.347 | D70: 18.087999 | E70: 17.997711 | F70: 18.072172 | G70: 18.146631 | H70: 18.221092 | I70: 18.221092 | J70: 18.221092 | K70: 18.221092 | L70: 18.221092 | M70: 18.221092 | N70: 18.221092 | O70: 18.221092 | P70: 18.221092 | Q70: 18.221092 | R70: 18.221092 | S70: 18.221092 | T70: 18.221092 | U70: 18.221092 | V70: 18.221092 | W70: 18.221092 | X70: 18.221092 | Y70: 18.221092 | Z70: 18.221092 | AA70: 18.221092 | AB70: 18.221092 | AC70: 18.221092 | AD70: -0.00026482045 | AE70: 18.664671 | AF70: 18.664671 | AG70: 18.664671 | AH70: 0.001391
A71: PSD000:ha_CapacityUtili | B71: Capacity Utilization Rate (percentage) 20/ | C71: 90.436996 | D71: 90.696999 | E71: 90.684219 | F71: 90.385918 | G71: 90.633942 | H71: 90.985527 | I71: 91.239304 | J71: 92.043198 | K71: 92.192162 | L71: 91.834076 | M71: 92.089714 | N71: 91.79673 | O71: 91.494415 | P71: 91.066872 | Q71: 91.188919 | R71: 91.784683 | S71: 91.50351 | T71: 91.232399 | U71: 90.3703 | V71: 90.67067 | W71: 90.709312 | X71: 91.126129 | Y71: 90.907059 | Z71: 90.822334 | AA71: 90.929321 | AB71: 90.909378 | AC71: 91.397987 | AD71: 0.00040662194 | AE71: 91.983101 | AF71: 92.092339 | AG71: 91.78006 | AH71: 0.000125
A72: PSD000:total_gross_imp | B72: Total Gross Imports | C72: 8.4827805 | D72: 7.941853 | E72: 8.2701168 | F72: 7.8782454 | G72: 8.0630817 | H72: 8.1341734 | I72: 8.1127005 | J72: 8.2752028 | K72: 8.5870247 | L72: 8.5709839 | M72: 8.7731533 | N72: 8.833168 | O72: 8.9262381 | P72: 8.7936459 | Q72: 8.800746 | R72: 8.9420948 | S72: 9.0128202 | T72: 8.9492998 | U72: 8.8184719 | V72: 8.8923607 | W72: 8.9963951 | X72: 9.0678902 | Y72: 8.8422422 | Z72: 8.6827526 | AA72: 8.7076702 | AB72: 8.8745937 | AC72: 9.0700579 | AD72: 0.0025779466 | AE72: 8.70431 | AF72: 8.564189 | AG72: 8.419456 | AH72: -0.000283
A73: PSD000:total_gross_exp | B73: Total Gross Exports | C73: 10.897901 | D73: 10.587901 | E73: 11.554709 | F73: 11.616061 | G73: 11.788102 | H73: 11.987405 | I73: 12.087488 | J73: 12.103498 | K73: 12.398677 | L73: 12.459269 | M73: 12.737261 | N73: 12.848117 | O73: 12.865855 | P73: 12.745195 | Q73: 12.814383 | R73: 12.828228 | S73: 12.74986 | T73: 12.723091 | U73: 12.713901 | V73: 12.785274 | W73: 12.847055 | X73: 12.899384 | Y73: 12.737801 | Z73: 12.747746 | AA73: 12.714496 | AB73: 12.723867 | AC73: 12.647705 | AD73: 0.0057435706 | AE73: 11.631284 | AF73: 11.574436 | AG73: 11.327992 | AH73: 0.005436
A74: PSD000:total_net_import | B74: Total Net Imports | C74: -2.4151201 | D74: -2.6460481 | E74: -3.2845926 | F74: -3.7378159 | G74: -3.7250204 | H74: -3.8532314 | I74: -3.9747877 | J74: -3.8282948 | K74: -3.8116522 | L74: -3.8882847 | M74: -3.9641075 | N74: -4.0149488 | O74: -3.9396172 | P74: -3.9515495 | Q74: -4.0136366 | R74: -3.8861332 | S74: -3.7370396 | T74: -3.7737913 | U74: -3.8954287 | V74: -3.8929129 | W74: -3.8506603 | X74: -3.8314943 | Y74: -3.8955584 | Z74: -4.0649939 | AA74: -4.0068254 | AB74: -3.8492737 | AC74: -3.5776472 | AD74: 0.015228496 | AE74: -2.926973 | AF74: -3.010247 | AG74: -2.908536 | AH74: 0.030735
A75: PSD000:ha_ImportShareof | B75: Net Import Share of Product Supplied (percentage) | C75: -11.614884 | D75: -12.548862 | E75: -15.98856 | F75: -18.237766 | G75: -18.231417 | H75: -18.933565 | I75: -19.658915 | J75: -19.02347 | K75: -19.054173 | L75: -19.545546 | M75: -19.975666 | N75: -20.319433 | O75: -20.021883 | P75: -20.144636 | Q75: -20.513174 | R75: -19.905516 | S75: -19.15052 | T75: -19.349117 | U75: -19.98575 | V75: -19.986906 | W75: -19.808199 | X75: -19.733103 | Y75: -20.113506 | Z75: -20.931631 | AA75: -20.577118 | AB75: -19.713924 | AC75: -18.272184 | AD75: 0.017579365 | AE75: -14.72961 | AF75: -15.066828 | AG75: -14.440868 | AH75: 0.029755
B76: Expenditures for Imported Crude Oil and
A77: PSD000:ha_PetroleumProd | B77: Petroleum Products (billion 2024 dollars) | C77: 211.22293 | D77: 212.18256 | E77: 204.16765 | F77: 191.45808 | G77: 196.5358 | H77: 199.82175 | I77: 200.4895 | J77: 207.08952 | K77: 214.84694 | L77: 218.71115 | M77: 228.42351 | N77: 232.47325 | O77: 237.21016 | P77: 235.403 | Q77: 237.79829 | R77: 245.40245 | S77: 250.19363 | T77: 249.71602 | U77: 246.61725 | V77: 250.14815 | W77: 254.63794 | X77: 258.9238 | Y77: 259.93024 | Z77: 254.88451 | AA77: 256.84747 | AB77: 264.4585 | AC77: 274.17441 | AD77: 0.0100832 | AE77: 262.36072 | AF77: 259.06534 | AG77: 255.76141 | AH77: -0.013231
B79: Data source: 2024: U.S. Energy Information Administration (EIA), Short-Term Energy Outlook, December 2024 and EIA,
B80: National Energy Modeling System run alttrnp.d032125a. Projections: EIA, AEO2025 National Energy Modeling System run alttrnp.d032125a.
B81: Note: Totals may not equal sum of components due to independent rounding.
B82: 1/ Includes lease condensate.
B83: 2/ Strategic petroleum reserve stock additions plus unaccounted for crude oil and crude oil stock withdrawals.
B84: 3/ Includes other hydrocarbons and alcohols.
B85: 4/ The volumetric amount by which total output is greater than input due to the processing of crude oil into products which, in total,
B86: have a lower specific gravity than the crude oil processed.
B87: 5/ Hydrogen includes both hydrogen produced from steam methane reforming hydrogen plants located at refineries and hydrogen
B88: purchased from third-party suppliers.
B89: 6/ Includes pyrolysis oils and renewable feedstocks used for the on-site production of
B90: diesel, gasoline, and aviation fuel.
... B109: - - = Not applicable

Sheet AEO 2025 Table 19 Alt Trans
B1: alttrnp.d032125a
C3: Report | D3: Annual Energy Outlook 2025
C4: Scenario | D4: alttrnp | F4: Alternative Transportation
C5: Datekey | D5: d032125a
C6: Release Date | E6: April 2025
B7: 19. Hydrogen Supply, Disposition, and Prices
B8: (million metric tons unless otherwise noted)
AD9: Avg Annual Change
C10: 2024 | D10: 2025 | E10: 2026 | F10: 2027 | G10: 2028 | H10: 2029 | I10: 2030 | J10: 2031 | K10: 2032 | L10: 2033 | M10: 2034 | N10: 2035 | O10: 2036 | P10: 2037 | Q10: 2038 | R10: 2039 | S10: 2040 | T10: 2041 | U10: 2042 | V10: 2043 | W10: 2044 | X10: 2045 | Y10: 2046 | Z10: 2047 | AA10: 2048 | AB10: 2049 | AC10: 2050 | AD10: 2024-2050
B12: Supply 1/
B13: Production By Technology
A14: HMM000:ba_smr | B14: Steam Methane Reforming 2/ | C14: 5.5051384 | D14: 5.5889602 | E14: 5.5451565 | F14: 5.5703378 | G14: 5.5628238 | H14: 5.5745244 | I14: 5.6207018 | J14: 5.6625314 | K14: 5.707273 | L14: 5.7308187 | M14: 5.749361 | N14: 5.7707858 | O14: 5.8204174 | P14: 6.0551076 | Q14: 6.2393594 | R14: 6.2594314 | S14: 6.2611084 | T14: 6.2733102 | U14: 6.2780075 | V14: 6.3645296 | W14: 6.3972588 | X14: 6.432919 | Y14: 6.4609509 | Z14: 6.4699512 | AA14: 6.4801841 | AB14: 6.4801397 | AC14: 6.5980368 | AD14: 0.0069893211
A15: HMM000:ba_smrccs | B15: Steam Methane Reforming with CCS 2/ | C15: 0.2306924 | D15: 0.230692 | E15: 0.39994362 | F15: 0.41354027 | G15: 0.41889471 | H15: 0.4279497 | I15: 0.43944368 | J15: 0.45007727 | K15: 0.46119824 | L15: 0.47170499 | M15: 0.48237947 | N15: 0.48959753 | O15: 0.4892351 | P15: 0.28911802 | Q15: 0.14359674 | R15: 0.15727676 | S15: 0.1627091 | T15: 0.16618843 | U15: 0.17135538 | V15: 0.11807384 | W15: 0.11751097 | X15: 0.11735085 | Y15: 0.11717795 | Z15: 0.11653521 | AA15: 0.11577284 | AB15: 0.11521158 | AC15: 0 | AD15: --
A16: HMM000:ba_electrolysis | B16: Electrolysis | C16: 6.3908135e-07 | D16: 6.1730128e-07 | E16: 3.8930702e-07 | F16: 3.628117e-07 | G16: 3.327601e-07 | H16: 2.985829e-07 | I16: 2.6217054e-07 | J16: 0.00012001424 | K16: 0.00092720776 | L16: 0.00067770947 | M16: 0.0024563787 | N16: 0.004181481 | O16: 0.0060350928 | P16: 0.0060992041 | Q16: 0.0060373452 | R16: 0.005953365 | S16: 0.005953365 | T16: 0.0056725019 | U16: 0.004532469 | V16: 0.0036667839 | W16: 0.0026680494 | X16: 0.0012990754 | Y16: 6.6363667e-05 | Z16: 0.00011060611 | AA16: 0.00010507581 | AB16: 7.189397e-05 | AC16: 6.6363667e-05 | AD16: 0.19550901
A17: HMM000:ba_byproduct | B17: Byproduct Hydrogen Supply to Market 3/ | C17: 2.0956628 | D17: 2.1142423 | E17: 2.1277764 | F17: 2.1292381 | G17: 2.1321261 | H17: 2.1337104 | I17: 2.1338773 | J17: 2.1338718 | K17: 2.1376319 | L17: 2.148906 | M17: 2.1672626 | N17: 2.1772437 | O17: 2.1832345 | P17: 2.1968148 | Q17: 2.2088783 | R17: 2.2192264 | S17: 2.2451625 | T17: 2.2696211 | U17: 2.2976239 | V17: 2.3018119 | W17: 2.3032181 | X17: 2.3003263 | Y17: 2.2891886 | Z17: 2.3190982 | AA17: 2.3579726 | AB17: 2.392503 | AC17: 2.4160314 | AD17: 0.0054863943
A18: HMM000:ba_tothydrogen | B18: Total Hydrogen Supply | C18: 7.8314943 | D18: 7.9338951 | E18: 8.0728769 | F18: 8.1131172 | G18: 8.1138449 | H18: 8.1361847 | I18: 8.1940231 | J18: 8.2466002 | K18: 8.3070297 | L18: 8.352107 | M18: 8.4014587 | N18: 8.4418087 | O18: 8.4989223 | P18: 8.5471392 | Q18: 8.5978718 | R18: 8.6418877 | S18: 8.6749334 | T18: 8.7147923 | U18: 8.7515192 | V18: 8.7880821 | W18: 8.8206558 | X18: 8.8518953 | Y18: 8.867384 | Z18: 8.905695 | AA18: 8.9540348 | AB18: 8.9879265 | AC18: 9.0141344 | AD18: 0.0054239063
A20: HMM000:ca_totconsumption | B20: Consumption | C20: 7.7855921 | D20: 7.892333 | E20: 8.0292177 | F20: 8.084693 | G20: 8.0735922 | H20: 8.0833263 | I20: 8.1592484 | J20: 8.210845 | K20: 8.2659883 | L20: 8.3113127 | M20: 8.3615227 | N20: 8.4006357 | O20: 8.4577017 | P20: 8.5056267 | Q20: 8.5566587 | R20: 8.5998325 | S20: 8.6340618 | T20: 8.6736765 | U20: 8.7099237 | V20: 8.7465868 | W20: 8.7804031 | X20: 8.8126745 | Y20: 8.8281441 | Z20: 8.8652754 | AA20: 8.9119902 | AB20: 8.9451675 | AC20: 8.9719315 | AD20: 0.0054697556
A21: HMM000:ca_industrial | B21: Industrial feedstock 4/ | C21: 7.7823462 | D21: 7.8888826 | E21: 8.0256901 | F21: 8.0811338 | G21: 8.0700436 | H21: 8.079875 | I21: 8.1558905 | J21: 8.2075968 | K21: 8.2623367 | L21: 8.3077421 | M21: 8.358736 | N21: 8.3978758 | O21: 8.4545679 | P21: 8.5026684 | Q21: 8.553874 | R21: 8.5972147 | S21: 8.6316042 | T21: 8.6713753 | U21: 8.7077494 | V21: 8.744525 | W21: 8.7784281 | X21: 8.8107958 | Y21: 8.8263378 | Z21: 8.8635216 | AA21: 8.9102688 | AB21: 8.9434757 | AC21: 8.9702616 | AD21: 0.005478683
A22: HMM000:ca_bulkchemical | B22: Bulk Chemicals 5/ | C22: 3.9304557 | D22: 4.0369473 | E22: 4.1736989 | F22: 4.2290726 | G22: 4.2216926 | H22: 4.2494364 | I22: 4.3035359 | J22: 4.3551092 | K22: 4.4096913 | L22: 4.4549131 | M22: 4.5057025 | N22: 4.5446177 | O22: 4.6010561 | P22: 4.6488757 | Q22: 4.6998014 | R22: 4.7428293 | S22: 4.776876 | T22: 4.8162756 | U22: 4.852252 | V22: 4.8885646 | W22: 4.9219723 | X22: 4.9538069 | Y22: 4.96878 | Z22: 5.0053468 | AA22: 5.0514383 | AB22: 5.08394 | AC22: 5.1098895 | AD22: 0.010144278
A23: HMM000:ca_refinery | B23: Refinery 6/ | C23: 3.8516364 | D23: 3.8516364 | E23: 3.8516364 | F23: 3.8516364 | G23: 3.8478487 | H23: 3.8298378 | I23: 3.8516364 | J23: 3.8516364 | K23: 3.8516364 | L23: 3.8516364 | M23: 3.8516364 | N23: 3.8516364 | O23: 3.8516364 | P23: 3.8516364 | Q23: 3.8516364 | R23: 3.8516364 | S23: 3.8516364 | T23: 3.8516364 | U23: 3.8516364 | V23: 3.8516364 | W23: 3.8516364 | X23: 3.8516364 | Y23: 3.8516364 | Z23: 3.8516364 | AA23: 3.8516364 | AB23: 3.8516364 | AC23: 3.8516364 | AD23: 0
A24: HMM000:ca_othercons | B24: Other Industrial 7/ | C24: 0.00025415421 | D24: 0.0002989769 | E24: 0.00035476685 | F24: 0.00042486191 | G24: 0.00050234795 | H24: 0.00060081482 | I24: 0.00071811676 | J24: 0.00085115433 | K24: 0.0010089874 | L24: 0.0011925697 | M24: 0.0013971329 | N24: 0.0016217232 | O24: 0.0018754005 | P24: 0.0021562576 | Q24: 0.002436161 | R24: 0.0027489662 | S24: 0.0030918121 | T24: 0.0034632683 | U24: 0.0038609505 | V24: 0.0043239594 | W24: 0.0048193932 | X24: 0.0053524971 | Y24: 0.0059213638 | Z24: 0.0065383911 | AA24: 0.0071940422 | AB24: 0.0078992844 | AC24: 0.0087356567 | AD24: 0.14573597
A25: HMM000:ca_transportation | B25: Transportation | C25: 0.0032457646 | D25: 0.0034504062 | E25: 0.0035280678 | F25: 0.0035593058 | G25: 0.0035486633 | H25: 0.003451298 | I25: 0.0033582149 | J25: 0.0032481444 | K25: 0.0031163597 | L25: 0.0029525768 | M25: 0.0027863262 | N25: 0.0026168041 | O25: 0.0024430808 | P25: 0.0022680461 | Q25: 0.0020939324 | R25: 0.0019270121 | S25: 0.0017670685 | T25: 0.0016111071 | U25: 0.0014840551 | V25: 0.0013711945 | W25: 0.0012841554 | X25: 0.0011884088 | Y25: 0.0011161857 | Z25: 0.0010638197 | AA25: 0.0010311647 | AB25: 0.0010016119 | AC25: 0.00097954215 | AD25: -0.04503227
A26: HMM000:ca_transportationldv | B26: Light-Duty Vehicles | C26: 0.003000132 | D26: 0.0031928055 | E26: 0.0032669876 | F26: 0.0032981676 | G26: 0.0032883768 | H26: 0.0031925521 | I26: 0.00310094 | J26: 0.0029922982 | K26: 0.0028639704 | L26: 0.0027039882 | M26: 0.002540295 | N26: 0.0023743205 | O26: 0.0022043486 | P26: 0.0020332623 | Q26: 0.0018629252 | R26: 0.0016997308 | S26: 0.0015439068 | T26: 0.0013922079 | U26: 0.0012697311 | V26: 0.0011609823 | W26: 0.0010781866 | X26: 0.00098615105 | Y26: 0.0009180202 | Z26: 0.00087024301 | AA26: 0.00084183092 | AB26: 0.0008162384 | AC26: 0.00079701416 | AD26: -0.049704485
A27: HMM000:ca_transportationclt | B27: Commercial Light Trucks | C27: 0 | D27: 0 | E27: 0 | F27: 0 | G27: 0 | H27: 0 | I27: 0 | J27: 0 | K27: 0 | L27: 0 | M27: 0 | N27: 0 | O27: 0 | P27: 0 | Q27: 0 | R27: 0 | S27: 0 | T27: 0 | U27: 0 | V27: 0 | W27: 0 | X27: 0 | Y27: 0 | Z27: 0 | AA27: 0 | AB27: 0 | AC27: 0 | AD27: --
A28: HMM000:ca_transportationft | B28: Freight Trucks | C28: 0 | D28: 0 | E28: 0 | F28: 0 | G28: 0 | H28: 0 | I28: 0 | J28: 0 | K28: 0 | L28: 0 | M28: 0 | N28: 0 | O28: 0 | P28: 0 | Q28: 0 | R28: 0 | S28: 0 | T28: 0 | U28: 0 | V28: 0 | W28: 0 | X28: 0 | Y28: 0 | Z28: 0 | AA28: 0 | AB28: 0 | AC28: 0 | AD28: --
A29: HMM000:ca_transportationbt | B29: Bus Transportation | C29: 0.00024563243 | D29: 0.00025760106 | E29: 0.0002610801 | F29: 0.0002611379 | G29: 0.00026028638 | H29: 0.00025874595 | I29: 0.00025727504 | J29: 0.00025584645 | K29: 0.00025238932 | L29: 0.000248589 | M29: 0.00024603124 | N29: 0.00024248399 | O29: 0.00023873204 | P29: 0.00023478399 | Q29: 0.00023100717 | R29: 0.00022728153 | S29: 0.00022316181 | T29: 0.00021889906 | U29: 0.00021432411 | V29: 0.00021021221 | W29: 0.0002059689 | X29: 0.00020225787 | Y29: 0.00019816554 | Z29: 0.00019357671 | AA29: 0.0001893336 | AB29: 0.00018537347 | AC29: 0.00018252793 | AD29: -0.011355534
A30: HMM000:ca_electric | B30: Electric Power | C30: 0 | D30: 0 | E30: 0 | F30: 0 | G30: 0 | H30: 0 | I30: 0 | J30: 0 | K30: 0.00053505629 | L30: 0.00061796914 | M30: 0 | N30: 0.0001431947 | O30: 0.00069062994 | P30: 0.00069062994 | Q30: 0.00069062994 | R30: 0.00069062994 | S30: 0.00069062994 | T30: 0.00069062994 | U30: 0.00069062994 | V30: 0.00069062994 | W30: 0.00069062994 | X30: 0.00069062994 | Y30: 0.00069062994 | Z30: 0.00069062994 | AA30: 0.00069062994 | AB30: 0.00069062994 | AC30: 0.00069062994 | AD30: --
A32: HMM000:da_disc | B32: Discrepancy 8/ | C32: 0.045902252 | D32: 0.04156208 | E32: 0.04365921 | F32: 0.028424263 | G32: 0.040252686 | H32: 0.052858353 | I32: 0.03477478 | J32: 0.035755157 | K32: 0.041041374 | L32: 0.040794373 | M32: 0.039936066 | N32: 0.041172981 | O32: 0.041220665 | P32: 0.041512489 | Q32: 0.041213036 | R32: 0.04205513 | S32: 0.04087162 | T32: 0.041115761 | U32: 0.041595459 | V32: 0.041495323 | W32: 0.040252686 | X32: 0.03922081 | Y32: 0.039239883 | Z32: 0.040419579 | AA32: 0.04204464 | AB32: 0.042758942 | AC32: 0.04220295 | AD32: -0.0032264787
B34: Prices ($/MMBtu)
A35: HMM000:ea_spotprice | B35: Hydrogen average market spot price 9/ | C35: 7.0623779 | D35: 8.1772223 | E35: 8.0545816 | F35: 7.9175053 | G35: 8.0400534 | H35: 8.1602316 | I35: 8.3440771 | J35: 8.5184183 | K35: 8.94697 | L35: 9.3011131 | M35: 9.5776072 | N35: 9.6891594 | O35: 9.6014671 | P35: 9.5438509 | Q35: 9.6702099 | R35: 9.5780802 | S35: 9.621891 | T35: 9.7619715 | U35: 9.9076681 | V35: 9.856391 | W35: 9.917922 | X35: 9.9243517 | Y35: 9.9192829 | Z35: 9.8394737 | AA35: 9.8236074 | AB35: 9.8260241 | AC35: 9.6644516 | AD35: 0.012137397
B37: Delivered End-Use Prices ($/MMBtu)
A38: HMM000:fa_indprice | B38: Industrial 10/ | C38: 9.5251846 | D38: 10.640075 | E38: 10.517506 | F38: 10.380456 | G38: 10.503005 | H38: 10.623157 | I38: 10.806981 | J38: 10.981338 | K38: 11.409804 | L38: 11.764016 | M38: 12.040632 | N38: 12.152257 | O38: 12.064539 | P38: 12.006973 | Q38: 12.133413 | R38: 12.041291 | S38: 12.085117 | T38: 12.225208 | U38: 12.370907 | V38: 12.319608 | W38: 12.38115 | X38: 12.38759 | Y38: 12.382531 | Z38: 12.302726 | AA38: 12.286866 | AB38: 12.289292 | AC38: 12.127695 | AD38: 0.0093337667
A39: HMM000:fa_transprice | B39: Transportation 11/ | C39: 61.324638 | D39: 62.25843 | E39: 61.971077 | F39: 61.767258 | G39: 61.892784 | H39: 62.113873 | I39: 62.39904 | J39: 62.600948 | K39: 63.057625 | L39: 63.294518 | M39: 63.625202 | N39: 63.53323 | O39: 63.365929 | P39: 63.24189 | Q39: 63.203316 | R39: 63.148933 | S39: 63.206013 | T39: 63.394558 | U39: 63.590591 | V39: 63.686977 | W39: 63.750324 | X39: 63.777321 | Y39: 63.778011 | Z39: 63.728878 | AA39: 63.706928 | AB39: 63.682514 | AC39: 63.668934 | AD39: 0.0014439282
A40: HMM000:fa_epprice | B40: Electric Power 10/ | C40: 9.5251846 | D40: 10.640075 | E40: 10.517506 | F40: 10.380456 | G40: 10.503005 | H40: 10.623157 | I40: 10.806981 | J40: 10.981338 | K40: 12.995852 | L40: 13.232461 | M40: 12.040632 | N40: 13.472548 | O40: 13.305155 | P40: 13.177244 | Q40: 13.113541 | R40: 13.064906 | S40: 13.120963 | T40: 13.31252 | U40: 13.512442 | V40: 13.66419 | W40: 13.733344 | X40: 13.768576 | Y40: 13.772696 | Z40: 13.729864 | AA40: 13.708858 | AB40: 13.6861 | AC40: 13.695667 | AD40: 0.014064925
B42: Data source: 2024: U.S. Energy Information Administration (EIA), Short-Term Energy Outlook, December 2024 and EIA,
B43: AEO2025 National Energy Modeling System run alttrnp.d032125a. Projections: EIA, AEO2025 National Energy Modeling System run alttrnp.d032125a.
B44: 1/ Supply is defined as hydrogen production from an industrial process that converts an energy feedstock of water
B45: into hydrogen gas as its primary output, plus byproduct hydrogen delivered to an end user (that is, not self-consumed for heat
B46: and power onsite).
B47: 2/ Includes volumes produced for delivery to end users in the market as well as production at facilities that may be adjacent
B48: to/producing hydrogen for a specific industrial facility that requires hydrogen feedstock. Specifically, dedicated hydrogen
B49: associated with nitrogenous fertilizer plants, refineries, and other chemical industrial are included in this total.
B50: 3/ Sources include the petrochemical industry, where hydrogen is a byproduct of ethane cracking. Byproduct supply does not
B51: include self-consumed hydrogen from other industrial subsectors; that is, byproduct supply here only includes byproduct hydrogen
B52: that is sold or transferred to another facility. Also excluded is hydrogen produced by refiners as a byproduct of catalytic cracking,
B53: where we assume it is used for heat and power and not further purified for input as a refinery feed during crude oil processing.
... B69: dispensing stations, building and operating hydrogen dispensing stations, and state and federal taxes

Sheet AEO 2025 Table 24 Alt Trans
A1: Table 24. Refining Industry Energy Consumption
A2: https://www.eia.gov/outlooks/aeo/data/browser/#/?id=35-AEO2025&cases=alttrnp&sourcekey=0
A3: Mon Dec 22 2025 12:10:08 GMT-0800 (Pacific Standard Time)
A4: Source: U.S. Energy Information Administration
B5: full name | C5: api key | D5: units | E5: 2023 | F5: 2024 | G5: 2025 | H5: 2026 | I5: 2027 | J5: 2028 | K5: 2029 | L5: 2030 | M5: 2031 | N5: 2032 | O5: 2033 | P5: 2034 | Q5: 2035 | R5: 2036 | S5: 2037 | T5: 2038 | U5: 2039 | V5: 2040 | W5: 2041 | X5: 2042 | Y5: 2043 | Z5: 2044 | AA5: 2045 | AB5: 2046 | AC5: 2047 | AD5: 2048 | AE5: 2049 | AF5: 2050 | AG5: Growth (2024-2050)
A6: Value of Shipments (billion 2012 dollars) | B6: Refining Industry: Value of Shipments: Alternative Transportation | C6: AEO.2025.ALTTRNP.ECI_VOS_IDAL_REF_NA_NA_NA_BLNY09DLR.A | D6: billion 2012 $ | F6: 773.8219 | G6: 786.61841 | H6: 783.81787 | I6: 782.10388 | J6: 779.7373 | K6: 776.40668 | L6: 771.18811 | M6: 766.94324 | N6: 762.13257 | O6: 758.32636 | P6: 755.69568 | Q6: 752.53565 | R6: 749.16858 | S6: 746.45282 | T6: 744.5329 | U6: 742.69019 | V6: 742.33783 | W6: 741.48614 | X6: 740.88788 | Y6: 740.5517 | Z6: 739.12549 | AA6: 737.6637 | AB6: 736.20465 | AC6: 737.94757 | AD6: 738.86261 | AE6: 741.01337 | AF6: 744.24585 | AG6: -0.001
A7: Inputs to Distillation Units
A8: (million barrels per day) | B8: Refining Industry: Inputs to Distillation Units: Alternative Transportation | C8: AEO.2025.ALTTRNP.IN_DIST_IDAL_REF_CR_NA_NA_MILLBRLPDY.A | D8: MMb/d | F8: 16.848057 | G8: 16.738653 | H8: 16.722189 | I8: 16.734415 | J8: 16.842148 | K8: 16.98263 | L8: 17.008272 | M8: 17.1639 | N8: 17.180298 | O8: 17.099449 | P8: 17.157427 | Q8: 17.0958 | R8: 17.039782 | S8: 16.96682 | T8: 16.987518 | U8: 17.091673 | V8: 17.039431 | W8: 16.988409 | X8: 16.839998 | Y8: 16.894266 | Z8: 16.901186 | AA8: 16.965046 | AB8: 16.934122 | AC8: 16.922188 | AD8: 16.941267 | AE8: 16.933884 | AF8: 17.01231 | AG8: 0
A9: Total Energy Consumption (trillion Btu)
A10: Residual Fuel Oil | B10: Refining Industry: Total Energy Use: Residual Fuel Oil: Alternative Transportation | C10: AEO.2025.ALTTRNP.CNSM_NA_IDAL_REFLIQ_RFO_NA_NA_TRLBTU.A | D10: trillion Btu | F10: 0.288 | G10: 0.288 | H10: 0 | I10: 0 | J10: 0 | K10: 0 | L10: 0 | M10: 0 | N10: 0 | O10: 0 | P10: 0 | Q10: 0 | R10: 0 | S10: 0 | T10: 0 | U10: 0 | V10: 0 | W10: 0 | X10: 0 | Y10: 0 | Z10: 0 | AA10: 0 | AB10: 0 | AC10: 0 | AD10: 0 | AE10: 0 | AF10: 0 | AG10: -1
A11: Distillate Fuel Oil | B11: Refining Industry: Total Energy Use: Distillate Fuel Oil: Alternative Transportation | C11: AEO.2025.ALTTRNP.CNSM_NA_IDAL_REFLIQ_DFO_NA_NA_TRLBTU.A | D11: trillion Btu | F11: 1.574 | G11: 1.574 | H11: 0 | I11: 0 | J11: 0 | K11: 0 | L11: 0 | M11: 0 | N11: 0 | O11: 0 | P11: 0 | Q11: 0 | R11: 0 | S11: 0 | T11: 0 | U11: 0 | V11: 0 | W11: 0 | X11: 0 | Y11: 0 | Z11: 0 | AA11: 0 | AB11: 0 | AC11: 0 | AD11: 0 | AE11: 0 | AF11: 0 | AG11: -1
A12: Liquefied Petroleum Gas Heat and Power | B12: Refining Industry: Total Energy Use: Liquefied Petroleum Gases: Alternative Transportation | C12: AEO.2025.ALTTRNP.CNSM_NA_IDAL_REFLIQ_LPG_NA_NA_TRLBTU.A | D12: trillion Btu | F12: 6.789 | G12: 6.789 | H12: 0 | I12: 0 | J12: 0 | K12: 0 | L12: 0 | M12: 0 | N12: 0 | O12: 0 | P12: 0 | Q12: 0 | R12: 0 | S12: 0 | T12: 0 | U12: 0 | V12: 0 | W12: 0 | X12: 0 | Y12: 0 | Z12: 0 | AA12: 0 | AB12: 0 | AC12: 0 | AD12: 0 | AE12: 0 | AF12: 0 | AG12: -1
A13: Petroleum Coke | B13: Refining Industry: Total Energy Use: Petroleum Coke: Alternative Transportation | C13: AEO.2025.ALTTRNP.CNSM_NA_IDAL_REFLIQ_PCK_NA_NA_TRLBTU.A | D13: trillion Btu | F13: 451 | G13: 474 | H13: 486.20065 | I13: 483.74756 | J13: 490.34976 | K13: 492.25888 | L13: 492.62241 | M13: 494.92432 | N13: 490.86194 | O13: 489.46631 | P13: 496.12726 | Q13: 491.00287 | R13: 493.41675 | S13: 493.38968 | T13: 492.19797 | U13: 493.08524 | V13: 491.63504 | W13: 491.6618 | X13: 489.4292 | Y13: 489.91248 | Z13: 488.48138 | AA13: 489.76041 | AB13: 490.83139 | AC13: 492.59686 | AD13: 494.7594 | AE13: 490.1915 | AF13: 493.41516 | AG13: 0.003
A14: Still Gas | B14: Refining Industry: Total Energy Use: Still Gas: Alternative Transportation | C14: AEO.2025.ALTTRNP.CNSM_NA_IDAL_REFLIQ_SLG_NA_NA_TRLBTU.A | D14: trillion Btu | F14: 1391.026 | G14: 1391.026 | H14: 1323.4628 | I14: 1310.1118 | J14: 1363.3091 | K14: 1370.7123 | L14: 1371.5575 | M14: 1385.0876 | N14: 1409.2587 | O14: 1400.8381 | P14: 1415.644 | Q14: 1414.0172 | R14: 1423.7493 | S14: 1432.6365 | T14: 1431.3408 | U14: 1442.8116 | V14: 1444.0347 | W14: 1438.6699 | X14: 1421.8981 | Y14: 1434.576 | Z14: 1433.7826 | AA14: 1440.428 | AB14: 1431.8506 | AC14: 1425.0454 | AD14: 1420.5372 | AE14: 1419.891 | AF14: 1425.0227 | AG14: 0.001
A15: Other Petroleum | B15: Refining Industry: Total Energy Use: Other Petroleum: Alternative Transportation | C15: AEO.2025.ALTTRNP.CNSM_NA_IDAL_REFLIQ_ONP_NA_NA_TRLBTU.A | D15: trillion Btu | F15: 6.113 | G15: 6.113 | H15: 5.833968 | I15: 5.877283 | J15: 5.681673 | K15: 4.229258 | L15: 3.376377 | M15: 2.924395 | N15: 2.586175 | O15: 2.354666 | P15: 2.210732 | Q15: 4.678841 | R15: 5.126453 | S15: 4.315352 | T15: 4.291104 | U15: 4.816897 | V15: 6.522789 | W15: 6.297829 | X15: 6.574095 | Y15: 6.753811 | Z15: 5.457685 | AA15: 5.868826 | AB15: 6.885268 | AC15: 7.422028 | AD15: 8.089056 | AE15: 8.451115 | AF15: 8.151185 | AG15: 0.011
A16: Petroleum and Other Liquids Subtotal | B16: Refining Industry: Total Energy Use: Petroleum Subtotal: Alternative Transportation | C16: AEO.2025.ALTTRNP.CNSM_NA_IDAL_REFLIQ_PET_NA_NA_TRLBTU.A | D16: trillion Btu | F16: 1856.79 | G16: 1879.79 | H16: 1815.4974 | I16: 1799.7367 | J16: 1859.3405 | K16: 1867.2004 | L16: 1867.5563 | M16: 1882.9364 | N16: 1902.7068 | O16: 1892.6591 | P16: 1913.9819 | Q16: 1909.6989 | R16: 1922.2925 | S16: 1930.3414 | T16: 1927.83 | U16: 1940.7137 | V16: 1942.1925 | W16: 1936.6296 | X16: 1917.9014 | Y16: 1931.2423 | Z16: 1927.7216 | AA16: 1936.0571 | AB16: 1929.5673 | AC16: 1925.0643 | AD16: 1923.3857 | AE16: 1918.5337 | AF16: 1926.5891 | AG16: 0.001
A17: Natural Gas | B17: Refining Industry: Total Energy Use: Natural Gas: Alternative Transportation | C17: AEO.2025.ALTTRNP.CNSM_NA_IDAL_REFLIQ_NG_NA_NA_TRLBTU.A | D17: trillion Btu | F17: 1323.9661 | G17: 1323.9661 | H17: 1062.9296 | I17: 1073.686 | J17: 1047.1814 | K17: 1061.3569 | L17: 1071.8081 | M17: 1069.7634 | N17: 1067.0209 | O17: 1071.188 | P17: 1061.9846 | Q17: 1059.5316 | R17: 1048.5593 | S17: 1039.0363 | T17: 1045.0566 | U17: 1050.2699 | V17: 1048.0364 | W17: 1050.7719 | X17: 1058.4512 | Y17: 1059.9369 | Z17: 1065.2886 | AA17: 1072.6115 | AB17: 1079.2428 | AC17: 1090.7336 | AD17: 1102.186 | AE17: 1105.8815 | AF17: 1117.6824 | AG17: -0.006
A18: of which: Heat and Power | B18: Refining Industry: Total Energy Use: Natural Gas: Heat and Power: Alternative Transportation | C18: AEO.2025.ALTTRNP.CNSM_NA_IDAL_REFLIQ_NG_HAP_NA_TRLBTU.A | D18: trillion Btu | F18: 1323.9661 | G18: 1323.9661 | H18: 1062.9296 | I18: 1073.686 | J18: 1047.1814 | K18: 1061.3569 | L18: 1071.8081 | M18: 1069.7634 | N18: 1067.0209 | O18: 1071.188 | P18: 1061.9846 | Q18: 1059.5316 | R18: 1048.5593 | S18: 1039.0363 | T18: 1045.0566 | U18: 1050.2699 | V18: 1048.0364 | W18: 1050.7719 | X18: 1058.4512 | Y18: 1059.9369 | Z18: 1065.2886 | AA18: 1072.6115 | AB18: 1079.2428 | AC18: 1090.7336 | AD18: 1102.186 | AE18: 1105.8815 | AF18: 1117.6824 | AG18: -0.006
A19: of which: Feedstocks | B19: Refining Industry: Total Energy Use: Natural Gas: Feedstocks: Alternative Transportation | C19: AEO.2025.ALTTRNP.CNSM_NA_IDAL_REFLIQ_NG_FSK_NA_TRLBTU.A | D19: trillion Btu | F19: 0 | G19: 0 | H19: 0 | I19: 0 | J19: 0 | K19: 0 | L19: 0 | M19: 0 | N19: 0 | O19: 0 | P19: 0 | Q19: 0 | R19: 0 | S19: 0 | T19: 0 | U19: 0 | V19: 0 | W19: 0 | X19: 0 | Y19: 0 | Z19: 0 | AA19: 0 | AB19: 0 | AC19: 0 | AD19: 0 | AE19: 0 | AF19: 0 | AG19: - -
A20: Steam Coal | B20: Refining Industry: Total Energy Use: Steam Coal: Alternative Transportation | C20: AEO.2025.ALTTRNP.CNSM_NA_IDAL_REFLIQ_STC_NA_NA_TRLBTU.A | D20: trillion Btu | F20: 124.711 | G20: 124.711 | H20: 124.711 | I20: 124.711 | J20: 124.711 | K20: 124.711 | L20: 124.711 | M20: 124.711 | N20: 124.711 | O20: 124.711 | P20: 124.711 | Q20: 124.711 | R20: 124.711 | S20: 124.711 | T20: 124.711 | U20: 124.711 | V20: 124.711 | W20: 124.711 | X20: 124.711 | Y20: 124.711 | Z20: 124.711 | AA20: 124.711 | AB20: 124.711 | AC20: 124.711 | AD20: 124.711 | AE20: 124.711 | AF20: 124.711 | AG20: 0
A21: Biofuels Heat and Coproducts | B21: Refining Industry: Total Energy Use: Biofuels Heat and Coproducts: Alternative Transportation | C21: AEO.2025.ALTTRNP.CNSM_NA_IDAL_REFLIQ_BFH_NA_NA_TRLBTU.A | D21: trillion Btu | F21: 893.86113 | G21: 915.74153 | H21: 915.86486 | I21: 917.10213 | J21: 916.26924 | K21: 917.41387 | L21: 916.96018 | M21: 916.783 | N21: 916.89136 | O21: 917.63763 | P21: 918.07899 | Q21: 917.75251 | R21: 919.55857 | S21: 921.86931 | T21: 922.41843 | U21: 926.1476 | V21: 931.41394 | W21: 933.78431 | X21: 935.36781 | Y21: 946.35736 | Z21: 950.26712 | AA21: 954.73333 | AB21: 958.18237 | AC21: 963.57021 | AD21: 967.55059 | AE21: 972.35691 | AF21: 972.75927 | AG21: 0.003
A22: Purchased Electricity | B22: Refining Industry: Total Energy Use: Purchased Electricity: Alternative Transportation | C22: AEO.2025.ALTTRNP.CNSM_NA_IDAL_REFLIQ_PRC_NA_NA_TRLBTU.A | D22: trillion Btu | F22: 178.51601 | G22: 178.51601 | H22: 176.31662 | I22: 176.67641 | J22: 177.57729 | K22: 179.42639 | L22: 180.81592 | M22: 181.62707 | N22: 182.19148 | O22: 182.16025 | P22: 183.53548 | Q22: 182.82712 | R22: 183.36214 | S22: 183.30934 | T22: 183.43364 | U22: 185.23369 | V22: 185.59866 | W22: 185.28073 | X22: 184.56509 | Y22: 185.9061 | Z22: 185.97168 | AA22: 187.55859 | AB22: 187.8275 | AC22: 189.00555 | AD22: 189.93939 | AE22: 189.67049 | AF22: 191.38377 | AG22: 0.003
A23: Total | B23: Refining Industry: Total Energy Use: Total: Alternative Transportation | C23: AEO.2025.ALTTRNP.CNSM_NA_IDAL_REFLIQ_NA_NA_NA_TRLBTU.A | D23: trillion Btu | F23: 4377.8443 | G23: 4422.7247 | H23: 4095.3194 | I23: 4091.9124 | J23: 4125.0795 | K23: 4150.1087 | L23: 4161.8513 | M23: 4175.8206 | N23: 4193.5212 | O23: 4188.3559 | P23: 4202.2919 | Q23: 4194.5211 | R23: 4198.4834 | S23: 4199.2673 | T23: 4203.4497 | U23: 4227.0758 | V23: 4231.9525 | W23: 4231.1774 | X23: 4220.9965 | Y23: 4248.1535 | Z23: 4253.96 | AA23: 4275.6713 | AB23: 4279.5308 | AC23: 4293.0846 | AD23: 4307.7728 | AE23: 4311.1533 | AF23: 4333.1255 | AG23: 0
A24: Carbon Dioxide Emissions
A25: (million metric tons CO2) | B25: Refining Industry: Carbon Dioxide Emissions: Alternative Transportation | C25: AEO.2025.ALTTRNP.EMI_CO2_IDAL_REFLIQ_NA_NA_NA_METNCO2.A | D25: MMmt carbon dioxide | F25: 238.31757 | G25: 240.10014 | H25: 220.16097 | I25: 218.22972 | J25: 220.64476 | K25: 221.38361 | L25: 220.7097 | M25: 220.6656 | N25: 218.89671 | O25: 217.65579 | P25: 218.09587 | Q25: 216.93048 | R25: 216.64603 | S25: 216.21854 | T25: 216.14064 | U25: 216.95471 | V25: 216.80495 | W25: 216.58307 | X25: 215.66394 | Y25: 216.72922 | Z25: 216.78101 | AA25: 217.76518 | AB25: 217.64328 | AC25: 217.95607 | AD25: 218.4511 | AE25: 218.16045 | AF25: 219.48138 | AG25: -0.003
A26: Energy Related to Refining Activity Only
A27: Energy Consumption
A28: Residual Fuel Oil | B28: Refining Industry: Refinery Only Energy: Use: Residual Fuel Oil: Alternative Transportation | C28: AEO.2025.ALTTRNP.CNSM_NA_IDAL_REF_RFO_NA_NA_TRLBTU.A | D28: trillion Btu | F28: 0.288 | G28: 0.288 | H28: 0 | I28: 0 | J28: 0 | K28: 0 | L28: 0 | M28: 0 | N28: 0 | O28: 0 | P28: 0 | Q28: 0 | R28: 0 | S28: 0 | T28: 0 | U28: 0 | V28: 0 | W28: 0 | X28: 0 | Y28: 0 | Z28: 0 | AA28: 0 | AB28: 0 | AC28: 0 | AD28: 0 | AE28: 0 | AF28: 0 | AG28: -1
A29: Distillate Fuel Oil | B29: Refining Industry: Refinery Only Energy: Use: Distillate Fuel Oil: Alternative Transportation | C29: AEO.2025.ALTTRNP.CNSM_NA_IDAL_REF_DFO_NA_NA_TRLBTU.A | D29: trillion Btu | F29: 1.574 | G29: 1.574 | H29: 0 | I29: 0 | J29: 0 | K29: 0 | L29: 0 | M29: 0 | N29: 0 | O29: 0 | P29: 0 | Q29: 0 | R29: 0 | S29: 0 | T29: 0 | U29: 0 | V29: 0 | W29: 0 | X29: 0 | Y29: 0 | Z29: 0 | AA29: 0 | AB29: 0 | AC29: 0 | AD29: 0 | AE29: 0 | AF29: 0 | AG29: -1
A30: Liquefied Petroleum Gas Heat and Power | B30: Refining Industry: Refinery Only Energy: Use: Liquefied Petroleum Gases: Alternative Transportation | C30: AEO.2025.ALTTRNP.CNSM_NA_IDAL_REF_LPG_NA_NA_TRLBTU.A | D30: trillion Btu | F30: 6.789 | G30: 6.789 | H30: 0 | I30: 0 | J30: 0 | K30: 0 | L30: 0 | M30: 0 | N30: 0 | O30: 0 | P30: 0 | Q30: 0 | R30: 0 | S30: 0 | T30: 0 | U30: 0 | V30: 0 | W30: 0 | X30: 0 | Y30: 0 | Z30: 0 | AA30: 0 | AB30: 0 | AC30: 0 | AD30: 0 | AE30: 0 | AF30: 0 | AG30: -1
A31: Petroleum Coke | B31: Refining Industry: Refinery Only Energy: Use: Petroleum Coke: Alternative Transportation | C31: AEO.2025.ALTTRNP.CNSM_NA_IDAL_REF_PCK_NA_NA_TRLBTU.A | D31: trillion Btu | F31: 449.26001 | G31: 472.26001 | H31: 486.20065 | I31: 483.74756 | J31: 490.34976 | K31: 492.25888 | L31: 492.62241 | M31: 494.92432 | N31: 490.86194 | O31: 489.46631 | P31: 496.12726 | Q31: 491.00287 | R31: 493.41675 | S31: 493.38968 | T31: 492.19797 | U31: 493.08524 | V31: 491.63504 | W31: 491.6618 | X31: 489.4292 | Y31: 489.91248 | Z31: 488.48138 | AA31: 489.76041 | AB31: 490.83139 | AC31: 492.59686 | AD31: 494.7594 | AE31: 490.1915 | AF31: 493.41516 | AG31: 0.004
A32: Still Gas | B32: Refining Industry: Refinery Only Energy: Use: Still Gas: Alternative Transportation | C32: AEO.2025.ALTTRNP.CNSM_NA_IDAL_REF_SLG_NA_NA_TRLBTU.A | D32: trillion Btu | F32: 1366.646 | G32: 1366.7061 | H32: 1274.4293 | I32: 1260.9409 | J32: 1314.0837 | K32: 1321.4869 | L32: 1322.3322 | M32: 1335.8623 | N32: 1360.0353 | O32: 1351.7081 | P32: 1366.4187 | Q32: 1364.9149 | R32: 1374.5624 | S32: 1383.4111 | T32: 1382.1155 | U32: 1393.5863 | V32: 1394.8093 | W32: 1389.4446 | X32: 1372.6727 | Y32: 1385.3507 | Z32: 1384.5573 | AA32: 1391.2026 | AB32: 1382.6252 | AC32: 1375.8201 | AD32: 1371.3119 | AE32: 1370.6656 | AF32: 1375.7974 | AG32: 0
A33: Other Petroleum | B33: Refining Industry: Refinery Only Energy: Use: Other Petroleum: Alternative Transportation | C33: AEO.2025.ALTTRNP.CNSM_NA_IDAL_REF_ONP_NA_NA_TRLBTU.A | D33: trillion Btu | F33: 6.113 | G33: 6.113 | H33: 5.833968 | I33: 5.877283 | J33: 5.681673 | K33: 4.229258 | L33: 3.376377 | M33: 2.924395 | N33: 2.586175 | O33: 2.354666 | P33: 2.210732 | Q33: 4.678841 | R33: 5.126453 | S33: 4.315352 | T33: 4.291104 | U33: 4.816897 | V33: 6.522789 | W33: 6.297829 | X33: 6.574095 | Y33: 6.753811 | Z33: 5.457685 | AA33: 5.868826 | AB33: 6.885268 | AC33: 7.422028 | AD33: 8.089056 | AE33: 8.451115 | AF33: 8.151185 | AG33: 0.011
A34: Petroleum and Other Liquids Subtotal | B34: Refining Industry: Refinery Only Energy: Use: Petroleum Subtotal: Alternative Transportation | C34: AEO.2025.ALTTRNP.CNSM_NA_IDAL_REF_PET_NA_NA_TRLBTU.A | D34: trillion Btu | F34: 1830.67 | G34: 1853.7301 | H34: 1766.464 | I34: 1750.5658 | J34: 1810.1151 | K34: 1817.9751 | L34: 1818.3309 | M34: 1833.7111 | N34: 1853.4834 | O34: 1843.5291 | P34: 1864.7566 | Q34: 1860.5966 | R34: 1873.1056 | S34: 1881.1161 | T34: 1878.6046 | U34: 1891.4884 | V34: 1892.9672 | W34: 1887.4043 | X34: 1868.676 | Y34: 1882.017 | Z34: 1878.4962 | AA34: 1886.8318 | AB34: 1880.3419 | AC34: 1875.839 | AD34: 1874.1604 | AE34: 1869.3084 | AF34: 1877.3638 | AG34: 0.001
A35: Natural Gas | B35: Refining Industry: Refinery Only Energy: Use: Natural Gas: Alternative Transportation | C35: AEO.2025.ALTTRNP.CNSM_NA_IDAL_REF_NG_NA_NA_TRLBTU.A | D35: trillion Btu | F35: 808.56604 | G35: 808.56604 | H35: 427.22208 | I35: 436.82562 | J35: 410.0712 | K35: 424.00134 | L35: 434.68335 | M35: 432.75714 | N35: 430.05325 | O35: 434.41937 | P35: 424.8028 | Q35: 423.08664 | R35: 411.42645 | S35: 401.33829 | T35: 407.19852 | U35: 411.71152 | V35: 408.42349 | W35: 410.69241 | X35: 418.06561 | Y35: 417.27274 | Z35: 421.862 | AA35: 428.28018 | AB35: 432.82687 | AC35: 441.98639 | AD35: 452.26132 | AE35: 454.82437 | AF35: 465.87308 | AG35: -0.021
A36: Steam Coal | B36: Refining Industry: Refinery Only Energy: Use: Steam Coal: Alternative Transportation | C36: AEO.2025.ALTTRNP.CNSM_NA_IDAL_REF_STC_NA_NA_TRLBTU.A | D36: trillion Btu | F36: 0 | G36: 0 | H36: 0 | I36: 0 | J36: 0 | K36: 0 | L36: 0 | M36: 0 | N36: 0 | O36: 0 | P36: 0 | Q36: 0 | R36: 0 | S36: 0 | T36: 0 | U36: 0 | V36: 0 | W36: 0 | X36: 0 | Y36: 0 | Z36: 0 | AA36: 0 | AB36: 0 | AC36: 0 | AD36: 0 | AE36: 0 | AF36: 0 | AG36: - -
A37: Purchased Electricity | B37: Refining Industry: Refinery Only Energy: Use: Purchased Electricity: Alternative Transportation | C37: AEO.2025.ALTTRNP.CNSM_NA_IDAL_REF_PRC_NA_NA_TRLBTU.A | D37: trillion Btu | F37: 141.51601 | G37: 141.51601 | H37: 134.14038 | I37: 134.43617 | J37: 135.33226 | K37: 137.14908 | L37: 138.56081 | M37: 139.388 | N37: 139.95592 | O37: 139.89941 | P37: 141.26739 | Q37: 140.50139 | R37: 140.96152 | S37: 140.81674 | T37: 140.91992 | U37: 142.55022 | V37: 142.67261 | W37: 142.24824 | X37: 141.46324 | Y37: 142.30307 | Z37: 142.19241 | AA37: 143.57486 | AB37: 143.66319 | AC37: 144.57217 | AD37: 145.31825 | AE37: 144.79637 | AF37: 146.42419 | AG37: 0.001
A38: Total | B38: Refining Industry: Refinery Only Energy: Use: Total: Alternative Transportation | C38: AEO.2025.ALTTRNP.CNSM_NA_IDAL_REF_TOT_NA_NA_TRLBTU.A | D38: trillion Btu | F38: 2780.7522 | G38: 2803.8123 | H38: 2327.8264 | I38: 2321.8276 | J38: 2355.5186 | K38: 2379.1257 | L38: 2391.575 | M38: 2405.8562 | N38: 2423.4924 | O38: 2417.8479 | P38: 2430.8267 | Q38: 2424.1846 | R38: 2425.4934 | S38: 2423.271 | T38: 2426.7231 | U38: 2445.7502 | V38: 2444.0632 | W38: 2440.345 | X38: 2428.2048 | Y38: 2441.5928 | Z38: 2442.5505 | AA38: 2458.687 | AB38: 2456.8318 | AC38: 2462.3977 | AD38: 2471.74 | AE38: 2468.9292 | AF38: 2489.6611 | AG38: -0.004
A39: Carbon Dioxide Emissions
A40: (million metric tons CO2) | B40: Refining Industry: Refinery Only Energy: Carbon Dioxide Emissions: Alternative Transportation | C40: AEO.2025.ALTTRNP.EMI_CO2_IDAL_REF_NA_NA_NA_METNCO2.A | D40: MMmt carbon dioxide | F40: 193.35005 | G40: 195.12502 | H40: 167.3913 | I40: 165.72898 | J40: 168.22646 | K40: 169.14714 | L40: 168.8363 | M40: 169.06985 | N40: 168.00544 | O40: 166.94281 | P40: 167.54579 | Q40: 166.53698 | R40: 166.35403 | S40: 165.99975 | T40: 165.95673 | U40: 166.82062 | V40: 166.61604 | W40: 166.3658 | X40: 165.41694 | Y40: 166.33234 | Z40: 166.33766 | AA40: 167.27556 | AB40: 167.05114 | AC40: 167.24423 | AD40: 167.6849 | AE40: 167.33479 | AF40: 168.60823 | AG40: -0.005
A41: Energy Consumption per Unit of Refinery Input
A42: (thousand Btu per barrel)
A43: Residual Fuel Oil | B43: Refining Industry: Refinery Only Energy: Use per Unit of Refinery Input: Residual Fuel Oil: Alternative Transportation | C43: AEO.2025.ALTTRNP.INY_NA_IDAL_REF_RFO_NA_NA_THBTUPBRL.A | D43: thousand Btu/b | F43: 0.046833 | G43: 0.047139 | H43: 0 | I43: 0 | J43: 0 | K43: 0 | L43: 0 | M43: 0 | N43: 0 | O43: 0 | P43: 0 | Q43: 0 | R43: 0 | S43: 0 | T43: 0 | U43: 0 | V43: 0 | W43: 0 | X43: 0 | Y43: 0 | Z43: 0 | AA43: 0 | AB43: 0 | AC43: 0 | AD43: 0 | AE43: 0 | AF43: 0 | AG43: -1
A44: Distillate Fuel Oil | B44: Refining Industry: Refinery Only Energy: Use per Unit of Refinery Input: Distillate Fuel Oil: Alternative Transportation | C44: AEO.2025.ALTTRNP.INY_NA_IDAL_REF_DFO_NA_NA_THBTUPBRL.A | D44: thousand Btu/b | F44: 0.255954 | G44: 0.257627 | H44: 0 | I44: 0 | J44: 0 | K44: 0 | L44: 0 | M44: 0 | N44: 0 | O44: 0 | P44: 0 | Q44: 0 | R44: 0 | S44: 0 | T44: 0 | U44: 0 | V44: 0 | W44: 0 | X44: 0 | Y44: 0 | Z44: 0 | AA44: 0 | AB44: 0 | AC44: 0 | AD44: 0 | AE44: 0 | AF44: 0 | AG44: -1
A45: Liquefied Petroleum Gas Heat and Power | B45: Refining Industry: Refinery Only Energy: Use per Unit of Refinery Input: Liquefied Petroleum Gases: Alternative Transportation | C45: AEO.2025.ALTTRNP.INY_NA_IDAL_REF_LPG_NA_NA_THBTUPBRL.A | D45: thousand Btu/b | F45: 1.103985 | G45: 1.111201 | H45: 0 | I45: 0 | J45: 0 | K45: 0 | L45: 0 | M45: 0 | N45: 0 | O45: 0 | P45: 0 | Q45: 0 | R45: 0 | S45: 0 | T45: 0 | U45: 0 | V45: 0 | W45: 0 | X45: 0 | Y45: 0 | Z45: 0 | AA45: 0 | AB45: 0 | AC45: 0 | AD45: 0 | AE45: 0 | AF45: 0 | AG45: -1
A46: Petroleum Coke | B46: Refining Industry: Refinery Only Energy: Use per Unit of Refinery Input: Petroleum Coke: Alternative Transportation | C46: AEO.2025.ALTTRNP.INY_NA_IDAL_REF_PCK_NA_NA_THBTUPBRL.A | D46: thousand Btu/b | F46: 73.05587 | G46: 77.29792 | H46: 79.658028 | I46: 79.198219 | J46: 79.765602 | K46: 79.413757 | L46: 79.352585 | M46: 79.000519 | N46: 78.277298 | O46: 78.42379 | P46: 79.222412 | Q46: 78.686768 | R46: 79.333565 | S46: 79.670357 | T46: 79.381081 | U46: 79.039566 | V46: 79.048729 | W46: 79.290451 | X46: 79.626015 | Y46: 79.448608 | Z46: 79.184097 | AA46: 79.092583 | AB46: 79.410294 | AC46: 79.752129 | AD46: 80.012032 | AE46: 79.307877 | AF46: 79.461426 | AG46: 0.003
A47: Still Gas | B47: Refining Industry: Refinery Only Energy: Use per Unit of Refinery Input: Still Gas: Alternative Transportation | C47: AEO.2025.ALTTRNP.INY_NA_IDAL_REF_SLG_NA_NA_THBTUPBRL.A | D47: thousand Btu/b | F47: 222.23547 | G47: 223.69783 | H47: 208.79965 | I47: 206.43881 | J47: 213.76309 | K47: 213.18913 | L47: 213.00386 | M47: 213.23222 | N47: 216.88356 | O47: 216.57481 | P47: 218.19199 | Q47: 218.7375 | R47: 221.00777 | S47: 223.38702 | T47: 222.90588 | U47: 223.38625 | V47: 224.26778 | W47: 224.07616 | X47: 223.32231 | Y47: 224.66092 | Z47: 224.44032 | AA47: 224.66866 | AB47: 223.69122 | AC47: 222.74721 | AD47: 221.7673 | AE47: 221.75943 | AF47: 221.56355 | AG47: 0
A48: Other Petroleum | B48: Refining Industry: Refinery Only Energy: Use per Unit of Refinery Input: Other Petroleum: Alternative Transportation | C48: AEO.2025.ALTTRNP.INY_NA_IDAL_REF_ONP_NA_NA_THBTUPBRL.A | D48: thousand Btu/b | F48: 0.994058 | G48: 1.000555 | H48: 0.955824 | I48: 0.962217 | J48: 0.924242 | K48: 0.682286 | L48: 0.543873 | M48: 0.466796 | N48: 0.412415 | O48: 0.377272 | P48: 0.353013 | Q48: 0.749818 | R48: 0.824252 | S48: 0.696824 | T48: 0.692064 | U48: 0.772129 | V48: 1.048782 | W48: 1.015653 | X48: 1.06955 | Y48: 1.095259 | Z48: 0.884705 | AA48: 0.947771 | AB48: 1.113949 | AC48: 1.201637 | AD48: 1.308155 | AE48: 1.367302 | AF48: 1.312697 | AG48: 0.011
A49: Petroleum and Other Liquids Subtotal | B49: Refining Industry: Refinery Only Energy: Use per Unit of Refinery Input: Petroleum Subtotal: Alternative Transportation | C49: AEO.2025.ALTTRNP.INY_NA_IDAL_REF_PET_NA_NA_THBTUPBRL.A | D49: thousand Btu/b | F49: 297.69217 | G49: 303.41226 | H49: 289.41348 | I49: 286.59924 | J49: 294.45294 | K49: 293.28519 | L49: 292.90033 | M49: 292.69952 | N49: 295.57327 | O49: 295.37585 | P49: 297.76743 | Q49: 298.17407 | R49: 301.16559 | S49: 303.75421 | T49: 302.97903 | U49: 303.19794 | V49: 304.3653 | W49: 304.38226 | X49: 304.01788 | Y49: 305.20477 | Z49: 304.50912 | AA49: 304.70902 | AB49: 304.21545 | AC49: 303.70096 | AD49: 303.08749 | AE49: 302.43463 | AF49: 302.33765 | AG49: 0.001
A50: Natural Gas | B50: Refining Industry: Refinery Only Energy: Use per Unit of Refinery Input: Natural Gas: Alternative Transportation | C50: AEO.2025.ALTTRNP.INY_NA_IDAL_REF_NG_NA_NA_THBTUPBRL.A | D50: thousand Btu/b | F50: 131.48398 | G50: 132.34335 | H50: 69.99511 | I50: 71.516251 | J50: 66.706619 | K50: 68.4021 | L50: 70.019646 | M50: 69.077301 | N50: 68.580193 | O50: 69.604004 | P50: 67.833206 | Q50: 67.802704 | R50: 66.150833 | S50: 64.806305 | T50: 65.672478 | U50: 65.995689 | V50: 65.669357 | W50: 66.232491 | X50: 68.015755 | Y50: 67.668694 | Z50: 68.384926 | AA50: 69.163994 | AB50: 70.025894 | AC50: 71.55822 | AD50: 73.139282 | AE50: 73.585846 | AF50: 75.02594 | AG50: -0.021
A51: Steam Coal | B51: Refining Industry: Refinery Only Energy: Use per Unit of Refinery Input: Steam Coal: Alternative Transportation | C51: AEO.2025.ALTTRNP.INY_NA_IDAL_REF_STC_NA_NA_THBTUPBRL.A | D51: thousand Btu/b | F51: 0 | G51: 0 | H51: 0 | I51: 0 | J51: 0 | K51: 0 | L51: 0 | M51: 0 | N51: 0 | O51: 0 | P51: 0 | Q51: 0 | R51: 0 | S51: 0 | T51: 0 | U51: 0 | V51: 0 | W51: 0 | X51: 0 | Y51: 0 | Z51: 0 | AA51: 0 | AB51: 0 | AC51: 0 | AD51: 0 | AE51: 0 | AF51: 0 | AG51: - -
A52: Purchased Electricity | B52: Refining Industry: Refinery Only Energy: Use per Unit of Refinery Input: Purchased Electricity: Alternative Transportation | C52: AEO.2025.ALTTRNP.INY_NA_IDAL_REF_PRC_NA_NA_THBTUPBRL.A | D52: thousand Btu/b | F52: 23.012453 | G52: 23.162861 | H52: 21.977259 | I52: 22.00963 | J52: 22.01461 | K52: 22.125601 | L52: 22.319647 | M52: 22.249308 | N52: 22.31864 | O52: 22.415113 | P52: 22.55781 | Q52: 22.516365 | R52: 22.66437 | S52: 22.738457 | T52: 22.727392 | U52: 22.850224 | V52: 22.939959 | W52: 22.940418 | X52: 23.014879 | Y52: 23.077145 | Z52: 23.049759 | AA52: 23.186249 | AB52: 23.242882 | AC52: 23.406439 | AD52: 23.500734 | AE52: 23.426544 | AF52: 23.5807 | AG52: 0.001
A53: Total | B53: Refining Industry: Refinery Only Energy: Use per Unit of Refinery Input: Total: Alternative Transportation | C53: AEO.2025.ALTTRNP.INY_NA_IDAL_REF_TOT_NA_NA_THBTUPBRL.A | D53: thousand Btu/b | F53: 452.1886 | G53: 458.91849 | H53: 381.38586 | I53: 380.12512 | J53: 383.17416 | K53: 383.8129 | L53: 385.23962 | M53: 384.02612 | N53: 386.47211 | O53: 387.39496 | P53: 388.15845 | Q53: 388.49313 | R53: 389.98077 | S53: 391.29898 | T53: 391.37891 | U53: 392.04385 | V53: 392.97464 | W53: 393.55518 | X53: 395.04852 | Y53: 395.95062 | Z53: 395.94379 | AA53: 397.05926 | AB53: 397.48422 | AC53: 398.66562 | AD53: 399.72751 | AE53: 399.44702 | AF53: 400.94428 | AG53: -0.005
A54: Combined Heat and Power
A55: Generating Capacity (gigawatts)
A56: Petroleum | B56: Refining Industry: Combined Heat and Power: Generating Capacity: Petroleum: Alternative Transportation | C56: AEO.2025.ALTTRNP.CAP_CHP_IDAL_REFLIQ_PET_NA_NA_GW.A | D56: GW | F56: 0.1079 | G56: 0.1079 | H56: 0.1079 | I56: 0.1079 | J56: 0.1079 | K56: 0.1079 | L56: 0.1079 | M56: 0.1079 | N56: 0.1079 | O56: 0.1079 | P56: 0.1079 | Q56: 0.1079 | R56: 0.1079 | S56: 0.1079 | T56: 0.1079 | U56: 0.1079 | V56: 0.1079 | W56: 0.1079 | X56: 0.1079 | Y56: 0.1079 | Z56: 0.1079 | AA56: 0.1079 | AB56: 0.1079 | AC56: 0.1079 | AD56: 0.1079 | AE56: 0.1079 | AF56: 0.1079 | AG56: 0
A57: Natural Gas | B57: Refining Industry: Combined Heat and Power: Generating Capacity: Natural Gas: Alternative Transportation | C57: AEO.2025.ALTTRNP.CAP_CHP_IDAL_REFLIQ_NG_NA_NA_GW.A | D57: GW | F57: 3.5964 | G57: 3.5964 | H57: 3.5964 | I57: 3.5964 | J57: 3.5964 | K57: 3.5964 | L57: 3.5964 | M57: 3.5964 | N57: 3.5964 | O57: 3.5964 | P57: 3.5964 | Q57: 3.5964 | R57: 3.5964 | S57: 3.5964 | T57: 3.5964 | U57: 3.5964 | V57: 3.5964 | W57: 3.5964 | X57: 3.5964 | Y57: 3.5964 | Z57: 3.5964 | AA57: 3.5964 | AB57: 3.5964 | AC57: 3.5964 | AD57: 3.5964 | AE57: 3.5964 | AF57: 3.5964 | AG57: 0
A58: Coal | B58: Refining Industry: Combined Heat and Power: Generating Capacity: Coal: Alternative Transportation | C58: AEO.2025.ALTTRNP.CAP_CHP_IDAL_REFLIQ_CL_NA_NA_GW.A | D58: GW | F58: 0 | G58: 0 | H58: 0 | I58: 0 | J58: 0 | K58: 0 | L58: 0 | M58: 0 | N58: 0 | O58: 0 | P58: 0 | Q58: 0 | R58: 0 | S58: 0 | T58: 0 | U58: 0 | V58: 0 | W58: 0 | X58: 0 | Y58: 0 | Z58: 0 | AA58: 0 | AB58: 0 | AC58: 0 | AD58: 0 | AE58: 0 | AF58: 0 | AG58: - -
A59: Other | B59: Refining Industry: Combined Heat and Power: Generating Capacity: Other: Alternative Transportation | C59: AEO.2025.ALTTRNP.CAP_CHP_IDAL_REFLIQ_OTH_NA_NA_GW.A | D59: GW | F59: 0.8112 | G59: 0.8112 | H59: 0.8112 | I59: 0.8112 | J59: 0.8112 | K59: 0.8112 | L59: 0.8112 | M59: 0.8112 | N59: 0.8112 | O59: 0.8112 | P59: 0.8112 | Q59: 0.8112 | R59: 0.8112 | S59: 0.8112 | T59: 0.8112 | U59: 0.8112 | V59: 0.8112 | W59: 0.8112 | X59: 0.8112 | Y59: 0.8112 | Z59: 0.8112 | AA59: 0.8112 | AB59: 0.8112 | AC59: 0.8112 | AD59: 0.8112 | AE59: 0.8112 | AF59: 0.8112 | AG59: 0
A60: Total | B60: Refining Industry: Combined Heat and Power: Generating Capacity: Total: Alternative Transportation | C60: AEO.2025.ALTTRNP.CAP_CHP_IDAL_REFLIQ_TOT_NA_NA_GW.A | D60: GW | F60: 4.5155 | G60: 4.5155 | H60: 4.5155 | I60: 4.5155 | J60: 4.5155 | K60: 4.5155 | L60: 4.5155 | M60: 4.5155 | N60: 4.5155 | O60: 4.5155 | P60: 4.5155 | Q60: 4.5155 | R60: 4.5155 | S60: 4.5155 | T60: 4.5155 | U60: 4.5155 | V60: 4.5155 | W60: 4.5155 | X60: 4.5155 | Y60: 4.5155 | Z60: 4.5155 | AA60: 4.5155 | AB60: 4.5155 | AC60: 4.5155 | AD60: 4.5155 | AE60: 4.5155 | AF60: 4.5155 | AG60: 0
A61: Net Generation (billion kilowatthours)
A62: Petroleum | B62: Refining Industry: Combined Heat and Power: Net Generation: Petroleum: Alternative Transportation | C62: AEO.2025.ALTTRNP.GEN_CHP_IDAL_REFLIQ_PET_NA_NA_BLNKWH.A | D62: BkWh | F62: 0.25214 | G62: 0.25214 | H62: 0 | I62: 0 | J62: 0 | K62: 0 | L62: 0 | M62: 0 | N62: 0 | O62: 0 | P62: 0 | Q62: 0 | R62: 0 | S62: 0 | T62: 0 | U62: 0 | V62: 0 | W62: 0 | X62: 0 | Y62: 0 | Z62: 0 | AA62: 0 | AB62: 0 | AC62: 0 | AD62: 0 | AE62: 0 | AF62: 0 | AG62: -1
A63: Natural Gas | B63: Refining Industry: Combined Heat and Power: Net Generation: Natural Gas: Alternative Transportation | C63: AEO.2025.ALTTRNP.GEN_CHP_IDAL_REFLIQ_NG_NA_NA_BLNKWH.A | D63: BkWh | F63: 23.696951 | G63: 23.696951 | H63: 22.524042 | I63: 22.587189 | J63: 22.612188 | K63: 22.612188 | L63: 22.612188 | M63: 22.612188 | N63: 22.611286 | O63: 22.568405 | P63: 22.612188 | Q63: 22.555649 | R63: 22.594526 | S63: 22.612188 | T63: 22.612188 | U63: 22.612188 | V63: 22.612188 | W63: 22.612188 | X63: 22.612188 | Y63: 22.612188 | Z63: 22.612188 | AA63: 22.612188 | AB63: 22.612188 | AC63: 22.612188 | AD63: 22.612188 | AE63: 22.612188 | AF63: 22.612188 | AG63: -0.002
A64: Coal | B64: Refining Industry: Combined Heat and Power: Net Generation: Coal: Alternative Transportation | C64: AEO.2025.ALTTRNP.GEN_CHP_IDAL_REFLIQ_CL_NA_NA_BLNKWH.A | D64: BkWh | F64: 0 | G64: 0 | H64: 0 | I64: 0 | J64: 0 | K64: 0 | L64: 0 | M64: 0 | N64: 0 | O64: 0 | P64: 0 | Q64: 0 | R64: 0 | S64: 0 | T64: 0 | U64: 0 | V64: 0 | W64: 0 | X64: 0 | Y64: 0 | Z64: 0 | AA64: 0 | AB64: 0 | AC64: 0 | AD64: 0 | AE64: 0 | AF64: 0 | AG64: - -
A65: Other | B65: Refining Industry: Combined Heat and Power: Net Generation: Other: Alternative Transportation | C65: AEO.2025.ALTTRNP.GEN_CHP_IDAL_REFLIQ_OTH_NA_NA_BLNKWH.A | D65: BkWh | F65: 4.34482 | G65: 4.34482 | H65: 5.682563 | I65: 5.697982 | J65: 5.704946 | K65: 5.704954 | L65: 5.704961 | M65: 5.704969 | N65: 5.704751 | O65: 5.694039 | P65: 5.704994 | Q65: 5.690867 | R65: 5.700593 | S65: 5.705014 | T65: 5.705021 | U65: 5.705027 | V65: 5.705033 | W65: 5.70504 | X65: 5.705045 | Y65: 5.705051 | Z65: 5.705056 | AA65: 5.705063 | AB65: 5.705069 | AC65: 5.705075 | AD65: 5.705081 | AE65: 5.705087 | AF65: 5.705093 | AG65: 0.011
A66: Total | B66: Refining Industry: Combined Heat and Power: Net Generation: Total: Alternative Transportation | C66: AEO.2025.ALTTRNP.GEN_CHP_IDAL_REFLIQ_TOT_NA_NA_BLNKWH.A | D66: BkWh | F66: 28.293911 | G66: 28.293911 | H66: 28.206604 | I66: 28.285172 | J66: 28.317135 | K66: 28.317142 | L66: 28.31715 | M66: 28.317158 | N66: 28.316036 | O66: 28.262444 | P66: 28.317183 | Q66: 28.246517 | R66: 28.29512 | S66: 28.317202 | T66: 28.317209 | U66: 28.317215 | V66: 28.317223 | W66: 28.317228 | X66: 28.317234 | Y66: 28.31724 | Z66: 28.317245 | AA66: 28.317251 | AB66: 28.317257 | AC66: 28.317263 | AD66: 28.317268 | AE66: 28.317276 | AF66: 28.317282 | AG66: 0
A67: Disposition
A68: Sales to the Grid | B68: Refining Industry: Combined Heat and Power: Net Generation: Sales to the Grid: Alternative Transportation | C68: AEO.2025.ALTTRNP.GEN_CHP_IDAL_REFLIQ_STG_NA_NA_BLNKWH.A | D68: BkWh | F68: 9.03193 | G68: 9.03193 | H68: 0.135588 | I68: 0.254935 | J68: 0.018426 | K68: 0.018428 | L68: 0.018431 | M68: 0.018434 | N68: 0.018437 | O68: 0.018439 | P68: 0.018443 | Q68: 0.018446 | R68: 0.018448 | S68: 0.01845 | T68: 0.018452 | U68: 0.018454 | V68: 0.018457 | W68: 0.018459 | X68: 0.018461 | Y68: 0.018463 | Z68: 0.018465 | AA68: 0.018467 | AB68: 0.018469 | AC68: 0.018471 | AD68: 0.018473 | AE68: 0.018476 | AF68: 0.018478 | AG68: -0.212
A69: Generation for Own Use | B69: Refining Industry: Combined Heat and Power: Net Generation: Generation for Own Use: Alternative Transportation | C69: AEO.2025.ALTTRNP.GEN_CHP_IDAL_REFLIQ_GFO_NA_NA_BLNKWH.A | D69: BkWh | F69: 19.261982 | G69: 19.261982 | H69: 28.071016 | I69: 28.030235 | J69: 28.298708 | K69: 28.298714 | L69: 28.298717 | M69: 28.298723 | N69: 28.297604 | O69: 28.244005 | P69: 28.29874 | Q69: 28.228071 | R69: 28.27667 | S69: 28.298754 | T69: 28.298758 | U69: 28.298761 | V69: 28.298765 | W69: 28.298769 | X69: 28.298773 | Y69: 28.298777 | Z69: 28.29878 | AA69: 28.298784 | AB69: 28.298788 | AC69: 28.298792 | AD69: 28.298796 | AE69: 28.2988 | AF69: 28.298803 | AG69: 0.015
A70: Energy Consumed at Ethanol Plants
A71: (trillion Btu)
A72: Natural Gas | B72: Refining Industry: Energy Consumed at Ethanol Plants: Natural Gas: Alternative Transportation | C72: AEO.2025.ALTTRNP.CNSM_NA_IDAL_ETHPLT_NG_NA_NA_TRLBTU.A | D72: trillion Btu | F72: 368 | G72: 368 | H72: 439.57364 | I72: 440.1767 | J72: 440.20877 | K72: 440.45416 | L72: 440.22333 | M72: 440.10486 | N72: 440.07407 | O72: 440.24847 | P72: 440.2804 | Q72: 440.03592 | R72: 440.38525 | S72: 440.79654 | T72: 440.9567 | U72: 441.65695 | V72: 442.71146 | W72: 443.17801 | X72: 443.48413 | Y72: 445.76273 | Z72: 446.52515 | AA72: 447.42984 | AB72: 449.5145 | AC72: 451.84582 | AD72: 453.02328 | AE72: 454.15567 | AF72: 454.90787 | AG72: 0.008
A73: Coal | B73: Refining Industry: Energy Consumed at Ethanol Plants: Coal: Alternative Transportation | C73: AEO.2025.ALTTRNP.CNSM_NA_IDAL_ETHPLT_CL_NA_NA_TRLBTU.A | D73: trillion Btu | F73: 124.711 | G73: 124.711 | H73: 124.711 | I73: 124.711 | J73: 124.711 | K73: 124.711 | L73: 124.711 | M73: 124.711 | N73: 124.711 | O73: 124.711 | P73: 124.711 | Q73: 124.711 | R73: 124.711 | S73: 124.711 | T73: 124.711 | U73: 124.711 | V73: 124.711 | W73: 124.711 | X73: 124.711 | Y73: 124.711 | Z73: 124.711 | AA73: 124.711 | AB73: 124.711 | AC73: 124.711 | AD73: 124.711 | AE73: 124.711 | AF73: 124.711 | AG73: 0
A74: Electricity | B74: Refining Industry: Energy Consumed at Ethanol Plants: Electricity: Alternative Transportation | C74: AEO.2025.ALTTRNP.CNSM_NA_IDAL_ETHPLT_ELC_NA_NA_TRLBTU.A | D74: trillion Btu | F74: 37 | G74: 37 | H74: 42.176247 | I74: 42.240231 | J74: 42.245022 | K74: 42.277313 | L74: 42.255108 | M74: 42.239067 | N74: 42.235569 | O74: 42.260826 | P74: 42.268085 | Q74: 42.325733 | R74: 42.40062 | S74: 42.492599 | T74: 42.513721 | U74: 42.683468 | V74: 42.926048 | W74: 43.032482 | X74: 43.101856 | Y74: 43.603035 | Z74: 43.779266 | AA74: 43.98373 | AB74: 44.16431 | AC74: 44.433372 | AD74: 44.62114 | AE74: 44.874119 | AF74: 44.959576 | AG74: 0.008
A75: Total | B75: Refining Industry: Energy Consumed at Ethanol Plants: Total: Alternative Transportation | C75: AEO.2025.ALTTRNP.CNSM_NA_IDAL_ETHPLT_TOT_NA_NA_TRLBTU.A | D75: trillion Btu | F75: 529.711 | G75: 529.711 | H75: 606.46094 | I75: 607.12793 | J75: 607.1648 | K75: 607.4425 | L75: 607.18945 | M75: 607.05493 | N75: 607.02063 | O75: 607.22028 | P75: 607.25946 | Q75: 607.07269 | R75: 607.49689 | S75: 608.00018 | T75: 608.18146 | U75: 609.05139 | V75: 610.34851 | W75: 610.92151 | X75: 611.297 | Y75: 614.07678 | Z75: 615.01538 | AA75: 616.12457 | AB75: 618.38977 | AC75: 620.99017 | AD75: 622.35541 | AE75: 623.74085 | AF75: 624.57849 | AG75: 0.006

Sheet AEO 2025 Table 34 High Cost
A1: Table 34. Nonmanufacturing Sector Energy Consumption
A2: https://www.eia.gov/outlooks/aeo/data/browser/#/?id=43-AEO2025&region=0-0&cases=highZTC&start=2023&end=2050&f=A&sourcekey=0
A3: Mon Dec 22 2025 13:49:03 GMT-0800 (Pacific Standard Time)
A4: Source: U.S. Energy Information Administration
B5: full name | C5: api key | D5: units | E5: 2023 | F5: 2024 | G5: 2025 | H5: 2026 | I5: 2027 | J5: 2028 | K5: 2029 | L5: 2030 | M5: 2031 | N5: 2032 | O5: 2033 | P5: 2034 | Q5: 2035 | R5: 2036 | S5: 2037 | T5: 2038 | U5: 2039 | V5: 2040 | W5: 2041 | X5: 2042 | Y5: 2043 | Z5: 2044 | AA5: 2045 | AB5: 2046 | AC5: 2047 | AD5: 2048 | AE5: 2049 | AF5: 2050 | AG5: Growth (2024-2050)
A6: Energy Consumption (trillion Btu)
A7: Agriculture
A8: Residual Fuel Oil | B8: Nonmanufacturing: Energy Use: Agriculture: Residual Fuel Oil: High Zero-Carbon Technology Cost | C8: AEO.2025.HIGHZTC.CNSM_NA_IDAL_AGG_RFO_NA_NA_TRLBTU.A | D8: trillion Btu | F8: 0.007151 | G8: 0.007195 | H8: 0.007237 | I8: 0.007279 | J8: 0.007318 | K8: 0.007354 | L8: 0.007386 | M8: 0.007415 | N8: 0.007439 | O8: 0.007458 | P8: 0.007472 | Q8: 0.007481 | R8: 0.007484 | S8: 0.007484 | T8: 0.007484 | U8: 0.007484 | V8: 0.007484 | W8: 0.007484 | X8: 0.007484 | Y8: 0.007484 | Z8: 0.007484 | AA8: 0.007484 | AB8: 0.007484 | AC8: 0.007484 | AD8: 0.007484 | AE8: 0.007484 | AF8: 0.007484 | AG8: 0.002
A9: Distillate Fuel Oil | B9: Nonmanufacturing: Energy Use: Agriculture: Distillate Fuel Oil: High Zero-Carbon Technology Cost | C9: AEO.2025.HIGHZTC.CNSM_NA_IDAL_AGG_DFO_NA_NA_TRLBTU.A | D9: trillion Btu | F9: 452.83762 | G9: 458.29614 | H9: 465.19879 | I9: 471.97595 | J9: 477.90424 | K9: 485.47 | L9: 492.16901 | M9: 497.75558 | N9: 505.66394 | O9: 509.75311 | P9: 515.32288 | Q9: 520.79834 | R9: 526.69922 | S9: 532.43048 | T9: 537.54034 | U9: 542.58954 | V9: 547.11218 | W9: 550.05554 | X9: 553.27753 | Y9: 556.7544 | Z9: 560.48663 | AA9: 564.7442 | AB9: 569.61731 | AC9: 574.45471 | AD9: 578.8053 | AE9: 583.81451 | AF9: 588.63025 | AG9: 0.01
A10: Propane | B10: Nonmanufacturing: Energy Use: Agriculture: Propane: High Zero-Carbon Technology Cost | C10: AEO.2025.HIGHZTC.CNSM_NA_IDAL_AGG_PROP_NA_NA_TRLBTU.A | D10: trillion Btu | F10: 41.404037 | G10: 80.855927 | H10: 81.774956 | I10: 82.713669 | J10: 83.310661 | K10: 84.381516 | L10: 85.223122 | M10: 85.808968 | N10: 87.626282 | O10: 87.947159 | P10: 88.669144 | Q10: 89.425743 | R10: 90.341187 | S10: 91.51889 | T10: 92.626541 | U10: 93.642433 | V10: 94.467255 | W10: 94.872864 | X10: 95.377594 | Y10: 95.886169 | Z10: 96.424637 | AA10: 97.057343 | AB10: 97.74086 | AC10: 98.410957 | AD10: 99.036865 | AE10: 99.719421 | AF10: 100.34543 | AG10: 0.035
A11: Motor Gasoline | B11: Nonmanufacturing: Energy Use: Agriculture: Motor Gasoline: High Zero-Carbon Technology Cost | C11: AEO.2025.HIGHZTC.CNSM_NA_IDAL_AGG_MGS_NA_NA_TRLBTU.A | D11: trillion Btu | F11: 112.12957 | G11: 113.45358 | H11: 115.07301 | I11: 116.68591 | J11: 118.0397 | K11: 119.8076 | L11: 121.4303 | M11: 122.7054 | N11: 123.95003 | O11: 125.09918 | P11: 126.50211 | Q11: 127.9128 | R11: 129.52899 | S11: 130.81549 | T11: 131.93413 | U11: 133.15097 | V11: 134.23576 | W11: 135.05588 | X11: 136.03784 | Y11: 137.02133 | Z11: 138.10562 | AA11: 139.44562 | AB11: 140.83327 | AC11: 142.20737 | AD11: 143.56061 | AE11: 144.97232 | AF11: 146.34283 | AG11: 0.01
A12: Other Petroleum | B12: Nonmanufacturing: Energy Use: Agriculture: Other Petroleum: High Zero-Carbon Technology Cost | C12: AEO.2025.HIGHZTC.CNSM_NA_IDAL_AGG_ONP_NA_NA_TRLBTU.A | D12: trillion Btu | F12: 9.245264 | G12: 9.737392 | H12: 10.261007 | I12: 10.781988 | J12: 11.256981 | K12: 11.763462 | L12: 12.234728 | M12: 12.626682 | N12: 12.98722 | O12: 13.298818 | P12: 13.589292 | Q12: 13.836977 | R12: 14.059357 | S12: 14.21764 | T12: 14.362858 | U12: 14.516664 | V12: 14.650713 | W12: 14.75922 | X12: 14.889067 | Y12: 15.018761 | Z12: 15.158793 | AA12: 15.323853 | AB12: 15.493307 | AC12: 15.660235 | AD12: 15.825542 | AE12: 15.997446 | AF12: 16.165174 | AG12: 0.022
A13: Petroleum and Other Liquids Subtotal | B13: Nonmanufacturing: Energy Use: Agriculture: Petroleum Subtotal: High Zero-Carbon Technology Cost | C13: AEO.2025.HIGHZTC.CNSM_NA_IDAL_AGG_PET_NA_NA_TRLBTU.A | D13: trillion Btu | F13: 615.6236 | G13: 662.35022 | H13: 672.315 | I13: 682.1648 | J13: 690.51886 | K13: 701.42993 | L13: 711.06457 | M13: 718.90405 | N13: 730.23492 | O13: 736.10571 | P13: 744.09088 | Q13: 751.98132 | R13: 760.63629 | S13: 768.98999 | T13: 776.47137 | U13: 783.9071 | V13: 790.47345 | W13: 794.75098 | X13: 799.58954 | Y13: 804.68811 | Z13: 810.18317 | AA13: 816.57849 | AB13: 823.6922 | AC13: 830.74072 | AD13: 837.23584 | AE13: 844.51117 | AF13: 851.49121 | AG13: 0.013
A14: Natural Gas | B14: Nonmanufacturing: Energy Use: Agriculture: Natural Gas: High Zero-Carbon Technology Cost | C14: AEO.2025.HIGHZTC.CNSM_NA_IDAL_AGG_NG_NA_NA_TRLBTU.A | D14: trillion Btu | F14: 122.34796 | G14: 124.1658 | H14: 126.29595 | I14: 128.44269 | J14: 130.17386 | K14: 132.43704 | L14: 134.40065 | M14: 135.93582 | N14: 138.45021 | O14: 139.04538 | P14: 139.77579 | Q14: 140.38768 | R14: 141.17102 | S14: 142.14377 | T14: 143.08174 | U14: 144.08902 | V14: 144.83972 | W14: 145.03836 | X14: 145.33452 | Y14: 145.54581 | Z14: 145.77357 | AA14: 146.16974 | AB14: 146.59885 | AC14: 147.03268 | AD14: 147.46091 | AE14: 147.89938 | AF14: 148.26309 | AG14: 0.007
A15: Steam Coal | B15: Nonmanufacturing: Energy Use: Agriculture: Steam Coal: High Zero-Carbon Technology Cost | C15: AEO.2025.HIGHZTC.CNSM_NA_IDAL_AGG_STC_NA_NA_TRLBTU.A | D15: trillion Btu | F15: 0 | G15: 0 | H15: 0 | I15: 0 | J15: 0 | K15: 0 | L15: 0 | M15: 0 | N15: 0 | O15: 0 | P15: 0 | Q15: 0 | R15: 0 | S15: 0 | T15: 0 | U15: 0 | V15: 0 | W15: 0 | X15: 0 | Y15: 0 | Z15: 0 | AA15: 0 | AB15: 0 | AC15: 0 | AD15: 0 | AE15: 0 | AF15: 0 | AG15: - -
A16: Renewables | B16: Nonmanufacturing: Energy Use: Agriculture: Renewables: High Zero-Carbon Technology Cost | C16: AEO.2025.HIGHZTC.CNSM_NA_IDAL_AGG_REB_NA_NA_TRLBTU.A | D16: trillion Btu | F16: 154.06143 | G16: 157.97572 | H16: 162.51143 | I16: 167.14265 | J16: 171.16118 | K16: 175.48122 | L16: 179.54721 | M16: 183.05507 | N16: 186.32358 | O16: 189.23309 | P16: 192.04016 | Q16: 194.48589 | R16: 196.59807 | S16: 198.36169 | T16: 200.09322 | U16: 201.9218 | V16: 203.61675 | W16: 205.27649 | X16: 207.04697 | Y16: 208.73186 | Z16: 210.41885 | AA16: 212.09283 | AB16: 213.80112 | AC16: 215.50011 | AD16: 217.20622 | AE16: 218.97884 | AF16: 220.71374 | AG16: 0.014
A17: Purchased Electricity | B17: Nonmanufacturing: Energy Use: Agriculture: Purchased Electricity: High Zero-Carbon Technology Cost | C17: AEO.2025.HIGHZTC.CNSM_NA_IDAL_AGG_PRC_NA_NA_TRLBTU.A | D17: trillion Btu | F17: 262.05255 | G17: 263.62152 | H17: 266.06168 | I17: 268.54468 | J17: 270.33459 | K17: 273.19244 | L17: 275.82172 | M17: 277.62625 | N17: 279.95923 | O17: 281.78656 | P17: 284.33527 | Q17: 287.16293 | R17: 290.6701 | S17: 293.69983 | T17: 296.43674 | U17: 299.33496 | V17: 301.858 | W17: 303.77884 | X17: 306.08929 | Y17: 308.39804 | Z17: 310.90631 | AA17: 313.92621 | AB17: 317.03345 | AC17: 320.09821 | AD17: 323.12454 | AE17: 326.271 | AF17: 329.32242 | AG17: 0.009
A18: Total | B18: Nonmanufacturing: Energy Use: Agriculture: Total: High Zero-Carbon Technology Cost | C18: AEO.2025.HIGHZTC.CNSM_NA_IDAL_AGG_NA_NA_NA_TRLBTU.A | D18: trillion Btu | F18: 1154.0854 | G18: 1208.1133 | H18: 1227.1841 | I18: 1246.2948 | J18: 1262.1885 | K18: 1282.5405 | L18: 1300.8342 | M18: 1315.5211 | N18: 1334.9679 | O18: 1346.1709 | P18: 1360.2422 | Q18: 1374.0178 | R18: 1389.0754 | S18: 1403.1953 | T18: 1416.0831 | U18: 1429.2528 | V18: 1440.788 | W18: 1448.8446 | X18: 1458.0603 | Y18: 1467.3638 | Z18: 1477.282 | AA18: 1488.7673 | AB18: 1501.1256 | AC18: 1513.3718 | AD18: 1525.0275 | AE18: 1537.6604 | AF18: 1549.7904 | AG18: 0.011
A19: Construction
A20: Distillate Fuel Oil | B20: Nonmanufacturing: Energy Use: Construction: Distillate Fuel Oil: High Zero-Carbon Technology Cost | C20: AEO.2025.HIGHZTC.CNSM_NA_IDAL_CNS_DFO_NA_NA_TRLBTU.A | D20: trillion Btu | F20: 419.76849 | G20: 419.17923 | H20: 423.67413 | I20: 431.17426 | J20: 441.86273 | K20: 454.02328 | L20: 463.11707 | M20: 471.16321 | N20: 477.27676 | O20: 480.05225 | P20: 480.74609 | Q20: 484.97327 | R20: 490.35501 | S20: 493.50403 | T20: 496.9227 | U20: 499.88867 | V20: 501.94858 | W20: 503.22253 | X20: 505.73303 | Y20: 507.32175 | Z20: 508.61276 | AA20: 512.31744 | AB20: 516.49432 | AC20: 521.40173 | AD20: 526.63287 | AE20: 532.22131 | AF20: 536.91437 | AG20: 0.01
A21: Propane | B21: Nonmanufacturing: Energy Use: Construction: Propane: High Zero-Carbon Technology Cost | C21: AEO.2025.HIGHZTC.CNSM_NA_IDAL_CNS_PROP_NA_NA_TRLBTU.A | D21: trillion Btu | F21: 12.307419 | G21: 27.315939 | H21: 27.598486 | I21: 28.083321 | J21: 28.782772 | K21: 29.588707 | L21: 30.186295 | M21: 30.754942 | N21: 31.212793 | O21: 31.439442 | P21: 31.526323 | Q21: 31.876596 | R21: 32.342094 | S21: 32.682552 | T21: 33.0326 | U21: 33.349995 | V21: 33.602657 | W21: 33.804405 | X21: 34.104683 | Y21: 34.348549 | Z21: 34.584919 | AA21: 34.991879 | AB21: 35.439442 | AC21: 35.942875 | AD21: 36.472069 | AE21: 37.034397 | AF21: 37.540482 | AG21: 0.044
A22: Motor Gasoline | B22: Nonmanufacturing: Energy Use: Construction: Motor Gasoline: High Zero-Carbon Technology Cost | C22: AEO.2025.HIGHZTC.CNSM_NA_IDAL_CNS_MGS_NA_NA_TRLBTU.A | D22: trillion Btu | F22: 121.57278 | G22: 121.13708 | H22: 122.21139 | I22: 124.16063 | J22: 127.06473 | K22: 130.39542 | L22: 132.79503 | M22: 134.87865 | N22: 136.40195 | O22: 136.98132 | P22: 137.01158 | Q22: 138.15793 | R22: 139.69083 | S22: 140.58964 | T22: 141.5685 | U22: 142.44072 | V22: 143.08028 | W22: 143.50456 | X22: 144.28355 | Y22: 144.81291 | Z22: 145.30769 | AA22: 146.51964 | AB22: 147.8857 | AC22: 149.47032 | AD22: 151.1497 | AE22: 152.94296 | AF22: 154.49802 | AG22: 0.009
A23: Asphalt and Road Oil | B23: Nonmanufacturing: Energy Use: Construction: Asphalt and Road Oil: High Zero-Carbon Technology Cost | C23: AEO.2025.HIGHZTC.CNSM_NA_IDAL_CNS_ARO_NA_NA_TRLBTU.A | D23: trillion Btu | F23: 120.14117 | G23: 119.94123 | H23: 121.3371 | I23: 125.0684 | J23: 127.80494 | K23: 131.69115 | L23: 134.4605 | M23: 137.05617 | N23: 137.71544 | O23: 138.74452 | P23: 138.93977 | Q23: 140.67961 | R23: 142.68559 | S23: 143.5733 | T23: 144.87567 | U23: 146.0303 | V23: 146.64436 | W23: 146.98863 | X23: 147.55704 | Y23: 148.13567 | Z23: 148.37125 | AA23: 149.74322 | AB23: 151.30231 | AC23: 152.40837 | AD23: 153.91064 | AE23: 155.02138 | AF23: 156.44511 | AG23: 0.01
A24: Other Petroleum | B24: Nonmanufacturing: Energy Use: Construction: Other Petroleum: High Zero-Carbon Technology Cost | C24: AEO.2025.HIGHZTC.CNSM_NA_IDAL_CNS_ONP_NA_NA_TRLBTU.A | D24: trillion Btu | F24: 16.23967 | G24: 16.857174 | H24: 17.704321 | I24: 18.688671 | J24: 19.82263 | K24: 21.022797 | L24: 22.033899 | M24: 22.964468 | N24: 23.740353 | O24: 24.255016 | P24: 24.568413 | Q24: 25.00882 | R24: 25.443253 | S24: 25.716419 | T24: 26.000772 | U24: 26.256672 | V24: 26.454756 | W24: 26.609751 | X24: 26.849916 | Y24: 27.04084 | Z24: 27.225008 | AA24: 27.552948 | AB24: 27.911907 | AC24: 28.316233 | AD24: 28.743046 | AE24: 29.194395 | AF24: 29.598223 | AG24: 0.023
A25: Petroleum and Other Liquids Subtotal | B25: Nonmanufacturing: Energy Use: Construction: Petroleum Subtotal: High Zero-Carbon Technology Cost | C25: AEO.2025.HIGHZTC.CNSM_NA_IDAL_CNS_PET_NA_NA_TRLBTU.A | D25: trillion Btu | F25: 690.02954 | G25: 704.43066 | H25: 712.52545 | I25: 727.17529 | J25: 745.33777 | K25: 766.72144 | L25: 782.59277 | M25: 796.81744 | N25: 806.34729 | O25: 811.47253 | P25: 812.79218 | Q25: 820.69629 | R25: 830.51679 | S25: 836.06598 | T25: 842.40027 | U25: 847.96637 | V25: 851.73059 | W25: 854.12988 | X25: 858.52826 | Y25: 861.65973 | Z25: 864.10162 | AA25: 871.12512 | AB25: 879.03369 | AC25: 887.53955 | AD25: 896.90832 | AE25: 906.41449 | AF25: 914.99622 | AG25: 0.011
A26: Natural Gas | B26: Nonmanufacturing: Energy Use: Construction: Natural Gas: High Zero-Carbon Technology Cost | C26: AEO.2025.HIGHZTC.CNSM_NA_IDAL_CNS_NG_NA_NA_TRLBTU.A | D26: trillion Btu | F26: 245.00238 | G26: 245.13113 | H26: 247.61883 | I26: 251.41577 | J26: 256.62997 | K26: 262.49716 | L26: 266.84134 | M26: 270.69763 | N26: 273.24936 | O26: 273.25919 | P26: 271.4259 | Q26: 270.91968 | R26: 270.94867 | S26: 270.17819 | T26: 269.7226 | U26: 269.3096 | V26: 268.40628 | W26: 266.94116 | X26: 265.84152 | Y26: 264.08127 | Z26: 262.01776 | AA26: 260.82214 | AB26: 259.79495 | AC26: 259.11102 | AD26: 258.54974 | AE26: 257.94745 | AF26: 256.83411 | AG26: 0.002
A27: Purchased Electricity | B27: Nonmanufacturing: Energy Use: Construction: Purchased Electricity: High Zero-Carbon Technology Cost | C27: AEO.2025.HIGHZTC.CNSM_NA_IDAL_CNS_PRC_NA_NA_TRLBTU.A | D27: trillion Btu | F27: 282.75815 | G27: 280.70007 | H27: 282.28598 | I27: 285.96384 | J27: 291.86291 | K27: 298.83804 | L27: 303.75226 | M27: 308.2341 | N27: 311.62149 | O27: 312.9101 | P27: 313.00482 | Q27: 315.86893 | R27: 319.92416 | S27: 322.71317 | T27: 325.65283 | U27: 328.28406 | V27: 330.27838 | W27: 331.76929 | X27: 334.20966 | Y27: 336.06912 | Z27: 337.84415 | AA27: 341.29993 | AB27: 345.11279 | AC27: 349.45135 | AD27: 354.03561 | AE27: 358.89059 | AF27: 363.17361 | AG27: 0.01
A28: Total | B28: Nonmanufacturing: Energy Use: Construction: Total: High Zero-Carbon Technology Cost | C28: AEO.2025.HIGHZTC.CNSM_NA_IDAL_CNS_NA_NA_NA_TRLBTU.A | D28: trillion Btu | F28: 1217.79 | G28: 1230.2618 | H28: 1242.4303 | I28: 1264.5549 | J28: 1293.8307 | K28: 1328.0566 | L28: 1353.1863 | M28: 1375.7493 | N28: 1391.2181 | O28: 1397.6418 | P28: 1397.2229 | Q28: 1407.4849 | R28: 1421.3896 | S28: 1428.9573 | T28: 1437.7756 | U28: 1445.5601 | V28: 1450.4153 | W28: 1452.8403 | X28: 1458.5793 | Y28: 1461.8101 | Z28: 1463.9635 | AA28: 1473.2472 | AB28: 1483.9414 | AC28: 1496.1021 | AD28: 1509.4937 | AE28: 1523.2526 | AF28: 1535.0039 | AG28: 0.009
A29: Mining
A30: Residual Fuel Oil | B30: Nonmanufacturing: Energy Use: Mining: Residual Fuel Oil: High Zero-Carbon Technology Cost | C30: AEO.2025.HIGHZTC.CNSM_NA_IDAL_MING_RFO_NA_NA_TRLBTU.A | D30: trillion Btu | F30: 2.334118 | G30: 2.573152 | H30: 2.580975 | I30: 2.620793 | J30: 2.667965 | K30: 2.702149 | L30: 2.735261 | M30: 2.727485 | N30: 2.771352 | O30: 2.767373 | P30: 2.765793 | Q30: 2.746739 | R30: 2.7179 | S30: 2.678733 | T30: 2.656598 | U30: 2.634772 | V30: 2.63657 | W30: 2.642482 | X30: 2.650714 | Y30: 2.645197 | Z30: 2.646671 | AA30: 2.649994 | AB30: 2.66645 | AC30: 2.661613 | AD30: 2.645908 | AE30: 2.650129 | AF30: 2.638282 | AG30: 0.005
A31: Distillate Fuel Oil | B31: Nonmanufacturing: Energy Use: Mining: Distillate Fuel Oil: High Zero-Carbon Technology Cost | C31: AEO.2025.HIGHZTC.CNSM_NA_IDAL_MING_DFO_NA_NA_TRLBTU.A | D31: trillion Btu | F31: 237.76035 | G31: 244.47708 | H31: 246.28226 | I31: 245.7854 | J31: 247.3326 | K31: 248.51724 | L31: 249.27962 | M31: 249.60577 | N31: 249.33414 | O31: 250.6879 | P31: 252.93906 | Q31: 253.71124 | R31: 253.36824 | S31: 253.10919 | T31: 253.523 | U31: 252.89659 | V31: 254.04691 | W31: 255.14717 | X31: 255.79062 | Y31: 256.65064 | Z31: 257.90366 | AA31: 258.31918 | AB31: 259.74008 | AC31: 260.24515 | AD31: 259.74698 | AE31: 260.32584 | AF31: 260.91363 | AG31: 0.004
A32: Motor Gasoline | B32: Nonmanufacturing: Energy Use: Mining: Motor Gasoline: High Zero-Carbon Technology Cost | C32: AEO.2025.HIGHZTC.CNSM_NA_IDAL_MING_MGS_NA_NA_TRLBTU.A | D32: trillion Btu | F32: 47.588776 | G32: 50.656647 | H32: 51.102974 | I32: 51.392719 | J32: 52.004646 | K32: 52.454712 | L32: 52.890091 | M32: 52.820072 | N32: 53.092056 | O32: 53.239243 | P32: 53.405106 | Q32: 53.2799 | R32: 53.015045 | S32: 52.584839 | T32: 52.396976 | U32: 52.099373 | V32: 52.269695 | W32: 52.479782 | X32: 52.725075 | Y32: 52.77182 | Z32: 52.929951 | AA32: 53.113861 | AB32: 53.479111 | AC32: 53.549644 | AD32: 53.553421 | AE32: 53.695675 | AF32: 53.858719 | AG32: 0.005
A33: Other Petroleum | B33: Nonmanufacturing: Energy Use: Mining: Other Petroleum: High Zero-Carbon Technology Cost | C33: AEO.2025.HIGHZTC.CNSM_NA_IDAL_MING_ONP_NA_NA_TRLBTU.A | D33: trillion Btu | F33: 8.863046 | G33: 9.781559 | H33: 10.11577 | I33: 10.400723 | J33: 10.852774 | K33: 11.202106 | L33: 11.43539 | M33: 11.569921 | N33: 11.493596 | O33: 11.625751 | P33: 11.700925 | Q33: 11.681952 | R33: 11.578305 | S33: 11.416384 | T33: 11.308599 | U33: 11.152623 | V33: 11.15838 | W33: 11.167107 | X33: 11.194284 | Y33: 11.163399 | Z33: 11.152832 | AA33: 11.168379 | AB33: 11.219541 | AC33: 11.196096 | AD33: 11.167583 | AE33: 11.173761 | AF33: 11.178327 | AG33: 0.009
A34: Petroleum and Other Liquids Subtotal | B34: Nonmanufacturing: Energy Use: Mining: Petroleum Subtotal: High Zero-Carbon Technology Cost | C34: AEO.2025.HIGHZTC.CNSM_NA_IDAL_MING_PET_NA_NA_TRLBTU.A | D34: trillion Btu | F34: 296.54627 | G34: 307.48843 | H34: 310.082 | I34: 310.19965 | J34: 312.858 | K34: 314.87622 | L34: 316.34036 | M34: 316.72324 | N34: 316.69113 | O34: 318.32028 | P34: 320.81088 | Q34: 321.41983 | R34: 320.6795 | S34: 319.78912 | T34: 319.88516 | U34: 318.78336 | V34: 320.11154 | W34: 321.43652 | X34: 322.36069 | Y34: 323.23105 | Z34: 324.63312 | AA34: 325.2514 | AB34: 327.10516 | AC34: 327.65253 | AD34: 327.11386 | AE34: 327.8454 | AF34: 328.58896 | AG34: 0.004
A35: Natural Gas | B35: Nonmanufacturing: Energy Use: Mining: Natural Gas: High Zero-Carbon Technology Cost | C35: AEO.2025.HIGHZTC.CNSM_NA_IDAL_MING_NG_NA_NA_TRLBTU.A | D35: trillion Btu | F35: 643.42297 | G35: 668.29993 | H35: 674.88641 | I35: 678.3421 | J35: 682.97449 | K35: 687.26111 | L35: 691.51331 | M35: 692.0022 | N35: 697.62152 | O35: 699.09857 | P35: 700.99097 | Q35: 699.20007 | R35: 695.62909 | S35: 691.09595 | T35: 689.02747 | U35: 686.40607 | V35: 686.80359 | W35: 687.32257 | X35: 686.96399 | Y35: 685.70136 | Z35: 685.33014 | AA35: 684.83423 | AB35: 685.68555 | AC35: 684.71533 | AD35: 683.10352 | AE35: 682.5838 | AF35: 682.18744 | AG35: 0.002
A36: Lease and Plant Fuel | B36: Nonmanufacturing: Energy Use: Mining: Lease and Plant Fuel: High Zero-Carbon Technology Cost | C36: AEO.2025.HIGHZTC.CNSM_NA_IDAL_MING_LSAPFL_NA_NA_TRLBTU.A | D36: trillion Btu | F36: 2045.2953 | G36: 2052.198 | H36: 2151.5581 | I36: 2160.4229 | J36: 2206.0051 | K36: 2226.782 | L36: 2238.0469 | M36: 2232.5896 | N36: 2285.5608 | O36: 2298.938 | P36: 2313.5833 | Q36: 2305.0078 | R36: 2296.3169 | S36: 2271.6519 | T36: 2265.6467 | U36: 2246.52 | V36: 2250.1501 | W36: 2260.5295 | X36: 2271.1816 | Y36: 2275.6582 | Z36: 2278.6611 | AA36: 2282.2698 | AB36: 2291.5203 | AC36: 2301.0574 | AD36: 2305.6938 | AE36: 2311.2717 | AF36: 2318.1809 | AG36: 0.005
A37: Steam Coal | B37: Nonmanufacturing: Energy Use: Mining: Steam Coal: High Zero-Carbon Technology Cost | C37: AEO.2025.HIGHZTC.CNSM_NA_IDAL_MING_STC_NA_NA_TRLBTU.A | D37: trillion Btu | F37: 0 | G37: 0 | H37: 0 | I37: 0 | J37: 0 | K37: 0 | L37: 0 | M37: 0 | N37: 0 | O37: 0 | P37: 0 | Q37: 0 | R37: 0 | S37: 0 | T37: 0 | U37: 0 | V37: 0 | W37: 0 | X37: 0 | Y37: 0 | Z37: 0 | AA37: 0 | AB37: 0 | AC37: 0 | AD37: 0 | AE37: 0 | AF37: 0 | AG37: - -
A38: Renewables | B38: Nonmanufacturing: Energy Use: Mining: Renewables: High Zero-Carbon Technology Cost | C38: AEO.2025.HIGHZTC.CNSM_NA_IDAL_MING_REB_NA_NA_TRLBTU.A | D38: trillion Btu | F38: 0 | G38: 0 | H38: 0 | I38: 0 | J38: 0 | K38: 0 | L38: 0 | M38: 0 | N38: 0 | O38: 0 | P38: 0 | Q38: 0 | R38: 0 | S38: 0 | T38: 0 | U38: 0 | V38: 0 | W38: 0 | X38: 0 | Y38: 0 | Z38: 0 | AA38: 0 | AB38: 0 | AC38: 0 | AD38: 0 | AE38: 0 | AF38: 0 | AG38: - -
A39: Purchased Electricity Excluding Oil Shale | B39: Nonmanufacturing: Energy Use: Mining: Purchased Electricity excluding Oil Shale: High Zero-Carbon Technology Cost | C39: AEO.2025.HIGHZTC.CNSM_NA_IDAL_MING_PEO_NA_NA_TRLBTU.A | D39: trillion Btu | F39: 282.85733 | G39: 290.87442 | H39: 290.87546 | I39: 289.55035 | J39: 289.88937 | K39: 289.83847 | L39: 289.30405 | M39: 288.08926 | N39: 286.78217 | O39: 287.62405 | P39: 289.41559 | Q39: 289.86078 | R39: 289.50659 | S39: 289.16836 | T39: 289.71048 | U39: 289.33185 | V39: 290.86072 | W39: 292.27185 | X39: 293.75757 | Y39: 294.77801 | Z39: 296.36615 | AA39: 297.86789 | AB39: 299.73462 | AC39: 300.47177 | AD39: 300.79892 | AE39: 301.54904 | AF39: 301.87964 | AG39: 0.003
A40: Purchased Electricity for Oil Shale | B40: Nonmanufacturing: Energy Use: Mining: Purchased Electricity for Oil Shale: High Zero-Carbon Technology Cost | C40: AEO.2025.HIGHZTC.CNSM_NA_IDAL_MING_PES_NA_NA_TRLBTU.A | D40: trillion Btu | F40: 0 | G40: 0 | H40: 0 | I40: 0 | J40: 0 | K40: 0 | L40: 0 | M40: 0 | N40: 0 | O40: 0 | P40: 0 | Q40: 0 | R40: 0 | S40: 0 | T40: 0 | U40: 0 | V40: 0 | W40: 0 | X40: 0 | Y40: 0 | Z40: 0 | AA40: 0 | AB40: 0 | AC40: 0 | AD40: 0 | AE40: 0 | AF40: 0 | AG40: - -
A41: Total | B41: Nonmanufacturing: Energy Use: Mining: Total: High Zero-Carbon Technology Cost | C41: AEO.2025.HIGHZTC.CNSM_NA_IDAL_MING_NA_NA_NA_TRLBTU.A | D41: trillion Btu | F41: 3268.1221 | G41: 3318.8608 | H41: 3427.4019 | I41: 3438.5149 | J41: 3491.7271 | K41: 3518.7578 | L41: 3535.2043 | M41: 3529.4043 | N41: 3586.6558 | O41: 3603.981 | P41: 3624.8008 | Q41: 3615.4885 | R41: 3602.1321 | S41: 3571.7053 | T41: 3564.2698 | U41: 3541.0413 | V41: 3547.9263 | W41: 3561.5605 | X41: 3574.2639 | Y41: 3579.3687 | Z41: 3584.9907 | AA41: 3590.2234 | AB41: 3604.0457 | AC41: 3613.897 | AD41: 3616.71 | AE41: 3623.25 | AF41: 3630.8369 | AG41: 0.004
A42: Value of Shipments (billion 2012 dollars)
A43: Agriculture | B43: Nonmanufacturing: Value of Shipments: Agriculture: High Zero-Carbon Technology Cost | C43: AEO.2025.HIGHZTC.ECI_VOS_IDAL_AGG_NA_NA_NA_BLNY09DLR.A | D43: billion 2012 $ | F43: 538.8266 | G43: 544.76807 | H43: 552.01935 | I43: 559.25311 | J43: 565.51892 | K43: 573.79547 | L43: 581.47052 | M43: 587.56146 | N43: 593.56909 | O43: 599.28235 | P43: 606.56781 | Q43: 614.13873 | R43: 623.17743 | S43: 630.44727 | T43: 636.67987 | U43: 643.48901 | V43: 649.69403 | W43: 654.328 | X43: 659.78339 | Y43: 665.28345 | Z43: 671.34363 | AA43: 678.96008 | AB43: 686.82513 | AC43: 694.61627 | AD43: 702.28125 | AE43: 710.2558 | AF43: 718.01489 | AG43: 0.011
A44: Construction | B44: Nonmanufacturing: Value of Shipments: Construction: High Zero-Carbon Technology Cost | C44: AEO.2025.HIGHZTC.ECI_VOS_IDAL_CNS_NA_NA_NA_BLNY09DLR.A | D44: billion 2012 $ | F44: 1440.7977 | G44: 1433.0573 | H44: 1444.2264 | I44: 1467.1532 | J44: 1502.7834 | K44: 1544.0198 | L44: 1573.1925 | M44: 1598.66 | N44: 1617.2603 | O44: 1624.0387 | P44: 1624.3893 | Q44: 1639.5165 | R44: 1660.5125 | S44: 1673.6357 | T44: 1687.7023 | U44: 1700.454 | V44: 1710.2748 | W44: 1717.3003 | X44: 1728.8163 | Y44: 1737.1105 | Z44: 1744.9568 | AA44: 1762.099 | AB44: 1781.2562 | AC44: 1803.2469 | AD44: 1826.4515 | AE44: 1851.1388 | AF44: 1872.7469 | AG44: 0.01
A45: Mining | B45: Nonmanufacturing: Value of Shipments: Mining: High Zero-Carbon Technology Cost | C45: AEO.2025.HIGHZTC.ECI_VOS_IDAL_MING_NA_NA_NA_BLNY09DLR.A | D45: billion 2012 $ | F45: 738.6261 | G45: 800.09271 | H45: 807.26276 | I45: 812.87158 | J45: 822.88531 | K45: 830.664 | L45: 837.44684 | M45: 834.11847 | N45: 842.65662 | O45: 842.87884 | P45: 843.77454 | Q45: 839.43475 | R45: 833.55817 | S45: 824.76233 | T45: 820.58246 | U45: 815.21143 | V45: 817.20264 | W45: 820.17926 | X45: 823.91998 | Y45: 823.77704 | Z45: 825.68115 | AA45: 828.09149 | AB45: 834.33093 | AC45: 835.11914 | AD45: 834.69672 | AE45: 836.80615 | AF45: 839.41028 | AG45: 0.005
A46: Energy Consumption per Unit of Output
A47: (thousand Btu per 2012 dollar shipments)
A48: Agriculture | B48: Nonmanufacturing: Energy Use per Unit of Output: Agriculture: High Zero-Carbon Technology Cost | C48: AEO.2025.HIGHZTC.INY_NA_IDAL_AGG_NA_NA_NA_THBTUPY05DLR.A | D48: thousand Btu/2012 $ | F48: 2.14185 | G48: 2.217665 | H48: 2.223082 | I48: 2.228499 | J48: 2.231912 | K48: 2.235188 | L48: 2.237146 | M48: 2.238951 | N48: 2.249052 | O48: 2.246305 | P48: 2.242523 | Q48: 2.237309 | R48: 2.229021 | S48: 2.225714 | T48: 2.224168 | U48: 2.221099 | V48: 2.217641 | W48: 2.214248 | X48: 2.209908 | Y48: 2.205622 | Z48: 2.200486 | AA48: 2.192717 | AB48: 2.185601 | AC48: 2.178716 | AD48: 2.171534 | AE48: 2.164939 | AF48: 2.158438 | AG48: 0
A49: Construction | B49: Nonmanufacturing: Energy Use per Unit of Output: Construction: High Zero-Carbon Technology Cost | C49: AEO.2025.HIGHZTC.INY_NA_IDAL_CNS_NA_NA_NA_THBTUPY05DLR.A | D49: thousand Btu/2012 $ | F49: 0.845219 | G49: 0.858488 | H49: 0.860274 | I49: 0.861911 | J49: 0.860956 | K49: 0.860129 | L49: 0.860153 | M49: 0.860564 | N49: 0.860231 | O49: 0.860596 | P49: 0.860153 | Q49: 0.858476 | R49: 0.855995 | S49: 0.853804 | T49: 0.851913 | U49: 0.850102 | V49: 0.84806 | W49: 0.846003 | X49: 0.843687 | Y49: 0.841518 | Z49: 0.838968 | AA49: 0.836075 | AB49: 0.833087 | AC49: 0.829671 | AD49: 0.826462 | AE49: 0.822873 | AF49: 0.819654 | AG49: -0.001
A50: Mining | B50: Nonmanufacturing: Energy Use per Unit of Output: Mining: High Zero-Carbon Technology Cost | C50: AEO.2025.HIGHZTC.INY_NA_IDAL_MING_NA_NA_NA_THBTUPY05DLR.A | D50: thousand Btu/2012 $ | F50: 4.424596 | G50: 4.148095 | H50: 4.245708 | I50: 4.230084 | J50: 4.243273 | K50: 4.236078 | L50: 4.221407 | M50: 4.231298 | N50: 4.256367 | O50: 4.2758 | P50: 4.295935 | Q50: 4.307051 | R50: 4.321393 | S50: 4.330587 | T50: 4.343585 | U50: 4.343709 | V50: 4.34155 | W50: 4.342417 | X50: 4.33812 | Y50: 4.34507 | Z50: 4.341858 | AA50: 4.335539 | AB50: 4.319684 | AC50: 4.327403 | AD50: 4.332963 | AE50: 4.329856 | AF50: 4.325461 | AG50: -0.001
A51: Carbon Dioxide Emissions
A52: (million metric tons CO2)
A53: Agriculture | B53: Nonmanufacturing: Carbon Dioxide Emissions: Agriculture: High Zero-Carbon Technology Cost | C53: AEO.2025.HIGHZTC.EMI_CO2_IDAL_AGG_NA_NA_NA_METNCO2.A | D53: MMmt carbon dioxide | F53: 78.382301 | G53: 80.615349 | H53: 78.628204 | I53: 77.503716 | J53: 77.697411 | K53: 78.412224 | L53: 77.689354 | M53: 77.455978 | N53: 74.967728 | O53: 74.795258 | P53: 74.616066 | Q53: 74.299164 | R53: 74.291687 | S53: 74.112839 | T53: 74.245338 | U53: 73.770882 | V53: 74.196396 | W53: 74.665421 | X53: 75.199448 | Y53: 75.70636 | Z53: 76.245735 | AA53: 76.822029 | AB53: 77.526459 | AC53: 78.194504 | AD53: 78.852882 | AE53: 79.58902 | AF53: 80.193016 | AG53: 0.001
A54: Construction | B54: Nonmanufacturing: Carbon Dioxide Emissions: Construction: High Zero-Carbon Technology Cost | C54: AEO.2025.HIGHZTC.EMI_CO2_IDAL_CNS_NA_NA_NA_METNCO2.A | D54: MMmt carbon dioxide | F54: 83.53215 | G54: 83.032433 | H54: 80.545547 | I54: 79.531601 | J54: 80.6791 | K54: 82.332726 | L54: 81.981239 | M54: 82.209213 | N54: 79.220596 | O54: 78.771767 | P54: 77.723236 | Q54: 77.096703 | R54: 76.92337 | S54: 76.309967 | T54: 76.145393 | U54: 75.285522 | V54: 75.345276 | W54: 75.546753 | X54: 75.93457 | Y54: 76.140427 | Z54: 76.295166 | AA54: 76.736397 | AB54: 77.333496 | AC54: 78.015381 | AD54: 78.776131 | AE54: 79.594963 | AF54: 80.174736 | AG54: -0.002
A55: Mining | B55: Nonmanufacturing: Carbon Dioxide Emissions: Mining: High Zero-Carbon Technology Cost | C55: AEO.2025.HIGHZTC.EMI_CO2_IDAL_MING_NA_NA_NA_METNCO2.A | D55: MMmt carbon dioxide | F55: 85.075089 | G55: 86.739349 | H55: 83.92485 | I55: 81.649559 | J55: 81.4235 | K55: 81.366768 | L55: 79.868851 | M55: 78.799446 | N55: 75.356148 | O55: 74.863373 | P55: 74.2883 | Q55: 73.186478 | R55: 72.111885 | S55: 70.888924 | T55: 70.27227 | U55: 68.951286 | V55: 68.96402 | W55: 69.214828 | X55: 69.399628 | Y55: 69.48542 | Z55: 69.671265 | AA55: 69.733604 | AB55: 70.043793 | AC55: 70.102249 | AD55: 70.058647 | AE55: 70.190651 | AF55: 70.232864 | AG55: -0.007
A56: Agriculture | B56: Construction | C56: and Mining:
A57: Combined Heat and Power
A58: Generating Capacity (gigawatts)
A59: Petroleum | B59: Nonmanufacturing: Combined Heat and Power: Generating Capacity: Petroleum: High Zero-Carbon Technology Cost | C59: AEO.2025.HIGHZTC.CAP_CHP_IDAL_NMFG_PET_NA_NA_GW.A | D59: GW | F59: 0.0324 | G59: 0.0324 | H59: 0.0324 | I59: 0.0324 | J59: 0.0324 | K59: 0.0324 | L59: 0.0324 | M59: 0.0324 | N59: 0.0324 | O59: 0.0324 | P59: 0.0324 | Q59: 0.0324 | R59: 0.0324 | S59: 0.0324 | T59: 0.0324 | U59: 0.0324 | V59: 0.0324 | W59: 0.0324 | X59: 0.0324 | Y59: 0.0324 | Z59: 0.0324 | AA59: 0.0324 | AB59: 0.0324 | AC59: 0.0324 | AD59: 0.0324 | AE59: 0.0324 | AF59: 0.0324 | AG59: 0
A60: Natural Gas | B60: Nonmanufacturing: Combined Heat and Power: Generating Capacity: Natural Gas: High Zero-Carbon Technology Cost | C60: AEO.2025.HIGHZTC.CAP_CHP_IDAL_NMFG_NG_NA_NA_GW.A | D60: GW | F60: 0.22225 | G60: 0.22225 | H60: 0.22225 | I60: 0.22225 | J60: 0.22225 | K60: 0.22225 | L60: 0.22225 | M60: 0.22225 | N60: 0.22225 | O60: 0.22225 | P60: 0.22225 | Q60: 0.22225 | R60: 0.22225 | S60: 0.22225 | T60: 0.22225 | U60: 0.22225 | V60: 0.22225 | W60: 0.22225 | X60: 0.22225 | Y60: 0.22225 | Z60: 0.22225 | AA60: 0.22225 | AB60: 0.22225 | AC60: 0.22225 | AD60: 0.22225 | AE60: 0.22225 | AF60: 0.22225 | AG60: 0
A61: Coal | B61: Nonmanufacturing: Combined Heat and Power: Generating Capacity: Coal: High Zero-Carbon Technology Cost | C61: AEO.2025.HIGHZTC.CAP_CHP_IDAL_NMFG_CL_NA_NA_GW.A | D61: GW | F61: 0 | G61: 0 | H61: 0 | I61: 0 | J61: 0 | K61: 0 | L61: 0 | M61: 0 | N61: 0 | O61: 0 | P61: 0 | Q61: 0 | R61: 0 | S61: 0 | T61: 0 | U61: 0 | V61: 0 | W61: 0 | X61: 0 | Y61: 0 | Z61: 0 | AA61: 0 | AB61: 0 | AC61: 0 | AD61: 0 | AE61: 0 | AF61: 0 | AG61: - -
A62: Other | B62: Nonmanufacturing: Combined Heat and Power: Generating Capacity: Other: High Zero-Carbon Technology Cost | C62: AEO.2025.HIGHZTC.CAP_CHP_IDAL_NMFG_OTH_NA_NA_GW.A | D62: GW | F62: 0.1753 | G62: 0.1753 | H62: 0.1753 | I62: 0.1753 | J62: 0.1753 | K62: 0.1753 | L62: 0.1753 | M62: 0.1753 | N62: 0.1753 | O62: 0.1753 | P62: 0.1753 | Q62: 0.1753 | R62: 0.1753 | S62: 0.1753 | T62: 0.1753 | U62: 0.1753 | V62: 0.1753 | W62: 0.1753 | X62: 0.1753 | Y62: 0.1753 | Z62: 0.1753 | AA62: 0.1753 | AB62: 0.1753 | AC62: 0.1753 | AD62: 0.1753 | AE62: 0.1753 | AF62: 0.1753 | AG62: 0
A63: Total | B63: Nonmanufacturing: Combined Heat and Power: Generating Capacity: Total: High Zero-Carbon Technology Cost | C63: AEO.2025.HIGHZTC.CAP_CHP_IDAL_NMFG_TOT_NA_NA_GW.A | D63: GW | F63: 0.42995 | G63: 0.42995 | H63: 0.42995 | I63: 0.42995 | J63: 0.42995 | K63: 0.42995 | L63: 0.42995 | M63: 0.42995 | N63: 0.42995 | O63: 0.42995 | P63: 0.42995 | Q63: 0.42995 | R63: 0.42995 | S63: 0.42995 | T63: 0.42995 | U63: 0.42995 | V63: 0.42995 | W63: 0.42995 | X63: 0.42995 | Y63: 0.42995 | Z63: 0.42995 | AA63: 0.42995 | AB63: 0.42995 | AC63: 0.42995 | AD63: 0.42995 | AE63: 0.42995 | AF63: 0.42995 | AG63: 0
A64: Net Generation (billion kilowatthours)
A65: Petroleum | B65: Nonmanufacturing: Combined Heat and Power: Net Generation: Petroleum: High Zero-Carbon Technology Cost | C65: AEO.2025.HIGHZTC.GEN_CHP_IDAL_NMFG_PET_NA_NA_BLNKWH.A | D65: BkWh | F65: 0.000477 | G65: 0.000477 | H65: 0.000477 | I65: 0.000477 | J65: 0.000477 | K65: 0.000477 | L65: 0.000477 | M65: 0.000477 | N65: 0.000477 | O65: 0.000477 | P65: 0.000477 | Q65: 0.000477 | R65: 0.000477 | S65: 0.000477 | T65: 0.000477 | U65: 0.000477 | V65: 0.000477 | W65: 0.000477 | X65: 0.000477 | Y65: 0.000477 | Z65: 0.000477 | AA65: 0.000477 | AB65: 0.000477 | AC65: 0.000477 | AD65: 0.000477 | AE65: 0.000477 | AF65: 0.000477 | AG65: 0
A66: Natural Gas | B66: Nonmanufacturing: Combined Heat and Power: Net Generation: Natural Gas: High Zero-Carbon Technology Cost | C66: AEO.2025.HIGHZTC.GEN_CHP_IDAL_NMFG_NG_NA_NA_BLNKWH.A | D66: BkWh | F66: 0.995144 | G66: 0.995144 | H66: 0.995144 | I66: 0.995144 | J66: 0.995144 | K66: 0.995144 | L66: 0.995144 | M66: 0.995144 | N66: 0.995144 | O66: 0.995144 | P66: 0.995144 | Q66: 0.995144 | R66: 0.995144 | S66: 0.995144 | T66: 0.995144 | U66: 0.995144 | V66: 0.995144 | W66: 0.995144 | X66: 0.995144 | Y66: 0.995144 | Z66: 0.995144 | AA66: 0.995144 | AB66: 0.995144 | AC66: 0.995144 | AD66: 0.995144 | AE66: 0.995144 | AF66: 0.995144 | AG66: 0
A67: Coal | B67: Nonmanufacturing: Combined Heat and Power: Net Generation: Coal: High Zero-Carbon Technology Cost | C67: AEO.2025.HIGHZTC.GEN_CHP_IDAL_NMFG_CL_NA_NA_BLNKWH.A | D67: BkWh | F67: 0 | G67: 0 | H67: 0 | I67: 0 | J67: 0 | K67: 0 | L67: 0 | M67: 0 | N67: 0 | O67: 0 | P67: 0 | Q67: 0 | R67: 0 | S67: 0 | T67: 0 | U67: 0 | V67: 0 | W67: 0 | X67: 0 | Y67: 0 | Z67: 0 | AA67: 0 | AB67: 0 | AC67: 0 | AD67: 0 | AE67: 0 | AF67: 0 | AG67: - -
A68: Other | B68: Nonmanufacturing: Combined Heat and Power: Net Generation: Other: High Zero-Carbon Technology Cost | C68: AEO.2025.HIGHZTC.GEN_CHP_IDAL_NMFG_OTH_NA_NA_BLNKWH.A | D68: BkWh | F68: 0.581405 | G68: 0.581405 | H68: 0.581405 | I68: 0.581405 | J68: 0.581405 | K68: 0.581405 | L68: 0.581405 | M68: 0.581405 | N68: 0.581405 | O68: 0.581405 | P68: 0.581405 | Q68: 0.581405 | R68: 0.581405 | S68: 0.581405 | T68: 0.581405 | U68: 0.581405 | V68: 0.581405 | W68: 0.581405 | X68: 0.581405 | Y68: 0.581405 | Z68: 0.581405 | AA68: 0.581405 | AB68: 0.581405 | AC68: 0.581405 | AD68: 0.581405 | AE68: 0.581405 | AF68: 0.581405 | AG68: 0
A69: Total | B69: Nonmanufacturing: Combined Heat and Power: Net Generation: Total: High Zero-Carbon Technology Cost | C69: AEO.2025.HIGHZTC.GEN_CHP_IDAL_NMFG_TOT_NA_NA_BLNKWH.A | D69: BkWh | F69: 1.577025 | G69: 1.577025 | H69: 1.577025 | I69: 1.577025 | J69: 1.577025 | K69: 1.577025 | L69: 1.577025 | M69: 1.577025 | N69: 1.577025 | O69: 1.577025 | P69: 1.577025 | Q69: 1.577025 | R69: 1.577025 | S69: 1.577025 | T69: 1.577025 | U69: 1.577025 | V69: 1.577025 | W69: 1.577025 | X69: 1.577025 | Y69: 1.577025 | Z69: 1.577025 | AA69: 1.577025 | AB69: 1.577025 | AC69: 1.577025 | AD69: 1.577025 | AE69: 1.577025 | AF69: 1.577025 | AG69: 0
A70: Disposition
A71: Sales to the Grid | B71: Nonmanufacturing: Combined Heat and Power: Net Generation: Sales to the Grid: High Zero-Carbon Technology Cost | C71: AEO.2025.HIGHZTC.GEN_CHP_IDAL_NMFG_STG_NA_NA_BLNKWH.A | D71: BkWh | F71: 0.723958 | G71: 0.723958 | H71: 0.723958 | I71: 0.723958 | J71: 0.723958 | K71: 0.723958 | L71: 0.723958 | M71: 0.723958 | N71: 0.723958 | O71: 0.723958 | P71: 0.723958 | Q71: 0.723958 | R71: 0.723958 | S71: 0.723958 | T71: 0.723958 | U71: 0.723958 | V71: 0.723958 | W71: 0.723958 | X71: 0.723958 | Y71: 0.723958 | Z71: 0.723958 | AA71: 0.723958 | AB71: 0.723958 | AC71: 0.723958 | AD71: 0.723958 | AE71: 0.723958 | AF71: 0.723958 | AG71: 0
A72: Generation for Own Use | B72: Nonmanufacturing: Combined Heat and Power: Net Generation: Generation for Own Use: High Zero-Carbon Technology Cost | C72: AEO.2025.HIGHZTC.GEN_CHP_IDAL_NMFG_GFO_NA_NA_BLNKWH.A | D72: BkWh | F72: 0.853067 | G72: 0.853067 | H72: 0.853067 | I72: 0.853067 | J72: 0.853067 | K72: 0.853067 | L72: 0.853067 | M72: 0.853067 | N72: 0.853067 | O72: 0.853067 | P72: 0.853067 | Q72: 0.853067 | R72: 0.853067 | S72: 0.853067 | T72: 0.853067 | U72: 0.853067 | V72: 0.853067 | W72: 0.853067 | X72: 0.853067 | Y72: 0.853067 | Z72: 0.853067 | AA72: 0.853067 | AB72: 0.853067 | AC72: 0.853067 | AD72: 0.853067 | AE72: 0.853067 | AF72: 0.853067 | AG72: 0

Sheet AEO 2025 Table 36 High Cost
A1: Table 36. Transportation Sector Energy Use by Fuel Type Within a Mode
A2: https://www.eia.gov/outlooks/aeo/data/browser/#/?id=46-AEO2025&cases=highZTC&sourcekey=0
A3: Mon Dec 22 2025 13:58:33 GMT-0800 (Pacific Standard Time)
A4: Source: U.S. Energy Information Administration
B5: full name | C5: api key | D5: units | E5: 2023 | F5: 2024 | G5: 2025 | H5: 2026 | I5: 2027 | J5: 2028 | K5: 2029 | L5: 2030 | M5: 2031 | N5: 2032 | O5: 2033 | P5: 2034 | Q5: 2035 | R5: 2036 | S5: 2037 | T5: 2038 | U5: 2039 | V5: 2040 | W5: 2041 | X5: 2042 | Y5: 2043 | Z5: 2044 | AA5: 2045 | AB5: 2046 | AC5: 2047 | AD5: 2048 | AE5: 2049 | AF5: 2050 | AG5: Growth (2024-2050)
A6: Light-Duty Vehicle | B6: Transportation Energy Use: Light-Duty Vehicle: Total: High Zero-Carbon Technology Cost | C6: AEO.2025.HIGHZTC.CNSM_NA_TRN_LDTY_NA_NA_NA_TRLBTU.A | D6: trillion Btu | F6: 15260.489 | G6: 15307.431 | H6: 15238.966 | I6: 15083.636 | J6: 14873.955 | K6: 14611.554 | L6: 14289.963 | M6: 13974.275 | N6: 13603.419 | O6: 13225.382 | P6: 12866.434 | Q6: 12504.122 | R6: 12122.051 | S6: 11748.685 | T6: 11411.939 | U6: 11092.792 | V6: 10813.671 | W6: 10563.53 | X6: 10311.565 | Y6: 10117.454 | Z6: 9919.0898 | AA6: 9765.2021 | AB6: 9620.5322 | AC6: 9512.2793 | AD6: 9365.8779 | AE6: 9277.5 | AF6: 9214.2656 | AG6: -0.019
A7: Motor Gasoline excluding E85 | B7: Transportation Energy Use: Light-Duty Vehicle: Motor Gasoline: High Zero-Carbon Technology Cost | C7: AEO.2025.HIGHZTC.CNSM_NA_TRN_LDTY_MGS_NA_NA_TRLBTU.A | D7: trillion Btu | F7: 15078.713 | G7: 15090.714 | H7: 14977.662 | I7: 14765.493 | J7: 14485.53 | K7: 14138.418 | L7: 13716.037 | M7: 13296.651 | N7: 12807.512 | O7: 12309.446 | P7: 11826.313 | Q7: 11342.058 | R7: 10838.905 | S7: 10345.961 | T7: 9893.7236 | U7: 9464.3945 | V7: 9080.8389 | W7: 8732.6758 | X7: 8389.8271 | Y7: 8112.9824 | Z7: 7840.5776 | AA7: 7619.9771 | AB7: 7413.1279 | AC7: 7247.8564 | AD7: 7051.585 | AE7: 6918.0991 | AF7: 6814.1104 | AG7: -0.03
A8: E85 | B8: Transportation Energy Use: Light-Duty Vehicle: Ethanol: High Zero-Carbon Technology Cost | C8: AEO.2025.HIGHZTC.CNSM_NA_TRN_LDTY_ETH_NA_NA_TRLBTU.A | D8: trillion Btu | F8: 36.427429 | G8: 35.33992 | H8: 32.52599 | I8: 30.218664 | J8: 29.038832 | K8: 28.717287 | L8: 26.841259 | M8: 24.55201 | N8: 22.677277 | O8: 20.779903 | P8: 19.1008 | Q8: 17.373703 | R8: 15.723388 | S8: 14.361159 | T8: 13.034491 | U8: 11.983353 | V8: 11.309345 | W8: 10.702095 | X8: 10.176045 | Y8: 9.851645 | Z8: 9.759826 | AA8: 9.177158 | AB8: 8.97878 | AC8: 9.107712 | AD8: 8.877073 | AE8: 8.722369 | AF8: 8.491708 | AG8: -0.054
A9: Distillate Fuel Oil (diesel) | B9: Transportation Energy Use: Light-Duty Vehicle: Distillate Fuel Oil: High Zero-Carbon Technology Cost | C9: AEO.2025.HIGHZTC.CNSM_NA_TRN_LDTY_DFO_NA_NA_TRLBTU.A | D9: trillion Btu | F9: 87.078362 | G9: 94.655159 | H9: 99.703285 | I9: 102.33607 | J9: 103.3842 | K9: 103.42925 | L9: 101.74048 | M9: 99.507736 | N9: 96.852959 | O9: 93.000244 | P9: 90.178574 | Q9: 86.818474 | R9: 83.923294 | S9: 80.940491 | T9: 77.986107 | U9: 74.975311 | V9: 71.960983 | W9: 69.296875 | X9: 67.447365 | Y9: 65.66642 | Z9: 63.63406 | AA9: 61.847984 | AB9: 60.775646 | AC9: 59.869881 | AD9: 58.850166 | AE9: 58.236065 | AF9: 58.000553 | AG9: -0.016
A10: Compressed/Liquefied Natural Gas | B10: Transportation Energy Use: Light-Duty Vehicle: Natural Gas: High Zero-Carbon Technology Cost | C10: AEO.2025.HIGHZTC.CNSM_NA_TRN_LDTY_NG_NA_NA_TRLBTU.A | D10: trillion Btu | F10: 0.660398 | G10: 0.605187 | H10: 0.549156 | I10: 0.494681 | J10: 0.45459 | K10: 0.428993 | L10: 0.391201 | M10: 0.353882 | N10: 0.320976 | O10: 0.292745 | P10: 0.26519 | Q10: 0.203169 | R10: 0.180924 | S10: 0.166969 | T10: 0.153304 | U10: 0.142682 | V10: 0.13393 | W10: 0.125458 | X10: 0.117764 | Y10: 0.110541 | Z10: 0.103651 | AA10: 0.09727 | AB10: 0.091329 | AC10: 0.085745 | AD10: 0.080504 | AE10: 0.075585 | AF10: 0.070976 | AG10: -0.082
A11: Propane | B11: Transportation Energy Use: Light-Duty Vehicle: Propane: High Zero-Carbon Technology Cost | C11: AEO.2025.HIGHZTC.CNSM_NA_TRN_LDTY_PROP_NA_NA_TRLBTU.A | D11: trillion Btu | F11: 0.638988 | G11: 0.579102 | H11: 0.519557 | I11: 0.478708 | J11: 0.445294 | K11: 0.413929 | L11: 0.385055 | M11: 0.359241 | N11: 0.330938 | O11: 0.304559 | P11: 0.28307 | Q11: 0.263566 | R11: 0.247379 | S11: 0.231383 | T11: 0.216316 | U11: 0.202113 | V11: 0.188224 | W11: 0.176138 | X11: 0.165441 | Y11: 0.154884 | Z11: 0.142988 | AA11: 0.133255 | AB11: 0.125299 | AC11: 0.117805 | AD11: 0.110695 | AE11: 0.103744 | AF11: 0.097175 | AG11: -0.07
A12: Electricity | B12: Transportation Energy Use: Light-Duty Vehicle: Electricity: High Zero-Carbon Technology Cost | C12: AEO.2025.HIGHZTC.CNSM_NA_TRN_LDTY_ELC_NA_NA_TRLBTU.A | D12: trillion Btu | F12: 56.56958 | G12: 85.110336 | H12: 127.56996 | I12: 184.17648 | J12: 254.66922 | K12: 339.72858 | L12: 444.16895 | M12: 552.47022 | N12: 675.36536 | O12: 801.22229 | P12: 929.98206 | Q12: 1057.1216 | R12: 1182.8118 | S12: 1306.7878 | T12: 1426.6125 | U12: 1540.9023 | V12: 1649.0675 | W12: 1750.402 | X12: 1843.6935 | Y12: 1928.5625 | Z12: 2004.7559 | AA12: 2073.8643 | AB12: 2137.3345 | AC12: 2195.1475 | AD12: 2246.2832 | AE12: 2292.175 | AF12: 2333.4087 | AG12: 0.154
A13: Hydrogen | B13: Transportation Energy Use: Light-Duty Vehicle: Hydrogen: High Zero-Carbon Technology Cost | C13: AEO.2025.HIGHZTC.CNSM_NA_TRN_LDTY_HDG_NA_NA_TRLBTU.A | D13: trillion Btu | F13: 0.402034 | G13: 0.42671 | H13: 0.435438 | I13: 0.437203 | J13: 0.432748 | K13: 0.416944 | L13: 0.39986 | M13: 0.381109 | N13: 0.359524 | O13: 0.334596 | P13: 0.309507 | Q13: 0.284196 | R13: 0.259672 | S13: 0.235695 | T13: 0.212713 | U13: 0.191256 | V13: 0.171422 | W13: 0.152797 | X13: 0.138189 | Y13: 0.125538 | Z13: 0.116014 | AA13: 0.105783 | AB13: 0.098423 | AC13: 0.093399 | AD13: 0.090682 | AE13: 0.088052 | AF13: 0.085931 | AG13: -0.058
A14: Commercial Light Trucks | B14: Transportation Energy Use: Commercial Light Trucks: Total: High Zero-Carbon Technology Cost | C14: AEO.2025.HIGHZTC.CNSM_NA_TRN_CLTR_NA_NA_NA_TRLBTU.A | D14: trillion Btu | F14: 873.99145 | G14: 855.034 | H14: 838.43176 | I14: 826.88806 | J14: 814.09418 | K14: 801.67993 | L14: 787.84528 | M14: 772.20612 | N14: 754.61365 | O14: 737.16205 | P14: 719.35858 | Q14: 701.14941 | R14: 682.76044 | S14: 664.43939 | T14: 646.4209 | U14: 629.03162 | V14: 612.79901 | W14: 596.2243 | X14: 580.9588 | Y14: 566.11743 | Z14: 552.3678 | AA14: 539.45007 | AB14: 527.50915 | AC14: 516.43762 | AD14: 506.17914 | AE14: 496.6521 | AF14: 487.62674 | AG14: -0.022
A15: Motor Gasoline excluding E85 | B15: Transportation Energy Use: Commercial Light Trucks: Motor Gasoline: High Zero-Carbon Technology Cost | C15: AEO.2025.HIGHZTC.CNSM_NA_TRN_CLTR_MGS_NA_NA_TRLBTU.A | D15: trillion Btu | F15: 608.42578 | G15: 601.5625 | H15: 597.14856 | I15: 595.61444 | J15: 593.96979 | K15: 592.66351 | L15: 588.24194 | M15: 582.69812 | N15: 574.72473 | O15: 566.65491 | P15: 558.28509 | Q15: 548.98895 | R15: 538.86938 | S15: 528.01648 | T15: 516.63263 | U15: 505.15448 | V15: 493.7569 | W15: 482.04581 | X15: 470.77185 | Y15: 459.41434 | Z15: 448.79602 | AA15: 438.68729 | AB15: 429.27118 | AC15: 420.47049 | AD15: 412.40582 | AE15: 404.90088 | AF15: 397.87622 | AG15: -0.016
A16: E85 | B16: Transportation Energy Use: Commercial Light Trucks: E85: High Zero-Carbon Technology Cost | C16: AEO.2025.HIGHZTC.CNSM_NA_TRN_CLTR_E85_NA_NA_TRLBTU.A | D16: trillion Btu | F16: 3.353461 | G16: 3.405243 | H16: 3.281574 | I16: 3.272549 | J16: 3.374837 | K16: 3.642771 | L16: 3.690603 | M16: 3.669209 | N16: 3.684026 | O16: 3.705997 | P16: 3.674337 | Q16: 3.63798 | R16: 3.594924 | S16: 3.569052 | T16: 3.545904 | U16: 3.526858 | V16: 3.523842 | W16: 3.508153 | X16: 3.504537 | Y16: 3.498338 | Z16: 3.507572 | AA16: 3.493911 | AB16: 3.481594 | AC16: 3.460819 | AD16: 3.442074 | AE16: 3.424428 | AF16: 3.403273 | AG16: 0.001
A17: Distillate Fuel Oil (diesel) | B17: Transportation Energy Use: Commercial Light Trucks: Distillate Fuel Oil: High Zero-Carbon Technology Cost | C17: AEO.2025.HIGHZTC.CNSM_NA_TRN_CLTR_DFO_NA_NA_TRLBTU.A | D17: trillion Btu | F17: 259.75577 | G17: 246.74863 | H17: 233.57419 | I17: 222.29999 | J17: 209.64484 | K17: 196.53175 | L17: 184.30652 | M17: 171.4337 | N17: 158.46571 | O17: 146.06552 | P17: 133.62692 | Q17: 121.53496 | R17: 110.14775 | S17: 99.745972 | T17: 90.231766 | U17: 81.570694 | V17: 73.941185 | W17: 66.454643 | X17: 59.917336 | Y17: 54.022701 | Z17: 48.577 | AA17: 43.623192 | AB17: 39.106979 | AC17: 35.029881 | AD17: 31.169085 | AE17: 27.599089 | AF17: 24.198015 | AG17: -0.087
... A20: Electricity | B20: Transportation Energy Use: Commercial Light Trucks: Electricity: High Zero-Carbon Technology Cost | C20: AEO.2025.HIGHZTC.CNSM_NA_TRN_CLTR_ELC_NA_NA_TRLBTU.A | D20: trillion Btu | F20: 1.06976 | G20: 1.601877 | H20: 2.295563 | I20: 3.130169 | J20: 4.117538 | K20: 5.325387 | L20: 7.648943 | M20: 10.108873 | N20: 13.100485 | O20: 15.851048 | P20: 18.554623 | Q20: 21.379025 | R20: 24.083881 | S20: 26.527243 | T20: 28.83213 | U20: 30.924461 | V20: 32.939304 | W20: 34.787857 | X20: 36.498371 | Y20: 38.075539 | Z20: 39.528816 | AA20: 40.846691 | AB20: 42.019699 | AC20: 43.050621 | AD20: 43.943878 | AE20: 44.713509 | AF20: 45.360718 | AG20: 0.155
A21: Hydrogen | B21: Transportation Energy Use: Commercial Light Trucks: Hydrogen: High Zero-Carbon Technology Cost | C21: AEO.2025.HIGHZTC.CNSM_NA_TRN_CLTR_HDG_NA_NA_TRLBTU.A | D21: trillion Btu | F21: 0 | G21: 0 | H21: 0 | I21: 0 | J21: 0 | K21: 0 | L21: 0 | M21: 0 | N21: 0 | O21: 0 | P21: 0 | Q21: 0 | R21: 0 | S21: 0 | T21: 0 | U21: 0 | V21: 0 | W21: 0 | X21: 0 | Y21: 0.001212 | Z21: 0.009263 | AA21: 0.020546 | AB21: 0.041574 | AC21: 0.071093 | AD21: 0.127834 | AE21: 0.217564 | AF21: 0.356829 | AG21: - -
A22: Freight Trucks | B22: Transportation Energy Use: Freight Trucks: Total: High Zero-Carbon Technology Cost | C22: AEO.2025.HIGHZTC.CNSM_NA_TRN_FRTT_NA_NA_NA_TRLBTU.A | D22: trillion Btu | F22: 6001.4731 | G22: 6050.2676 | H22: 6053.9404 | I22: 6031.1089 | J22: 5994.9873 | K22: 5954.3574 | L22: 5902.2236 | M22: 5836.5996 | N22: 5757.7109 | O22: 5672.3013 | P22: 5612.856 | Q22: 5558.0103 | R22: 5514.4033 | S22: 5480.4556 | T22: 5449.1079 | U22: 5425.2842 | V22: 5415.7944 | W22: 5402.21 | X22: 5396.6211 | Y22: 5391.2021 | Z22: 5394.5547 | AA22: 5402.7178 | AB22: 5420.5317 | AC22: 5444.748 | AD22: 5463.7939 | AE22: 5489.8696 | AF22: 5510.6143 | AG22: -0.003
A23: Motor Gasoline | B23: Transportation Energy Use: Freight Trucks: Motor Gasoline: High Zero-Carbon Technology Cost | C23: AEO.2025.HIGHZTC.CNSM_NA_TRN_FRTT_MGS_NA_NA_TRLBTU.A | D23: trillion Btu | F23: 682.4906 | G23: 695.90741 | H23: 704.94104 | I23: 711.28308 | J23: 719.72559 | K23: 730.81122 | L23: 738.69678 | M23: 746.79218 | N23: 748.73218 | O23: 751.41028 | P23: 759.10693 | Q23: 767.61896 | R23: 777.10248 | S23: 787.45099 | T23: 797.2608 | U23: 808.04626 | V23: 820.60492 | W23: 831.64282 | X23: 843.08344 | Y23: 853.50049 | Z23: 864.48114 | AA23: 875.80878 | AB23: 888.27637 | AC23: 901.37817 | AD23: 913.26483 | AE23: 925.93494 | AF23: 937.04437 | AG23: 0.012
A24: Distillate Fuel Oil (diesel) | B24: Transportation Energy Use: Freight Trucks: Distillate Fuel Oil: High Zero-Carbon Technology Cost | C24: AEO.2025.HIGHZTC.CNSM_NA_TRN_FRTT_DFO_NA_NA_TRLBTU.A | D24: trillion Btu | F24: 5257.6699 | G24: 5284.0142 | H24: 5267.7407 | I24: 5225.6382 | J24: 5165.8057 | K24: 5096.4736 | L24: 5013.9595 | M24: 4896.1763 | N24: 4729.1665 | O24: 4557.5889 | P24: 4412.6309 | Q24: 4278.0908 | R24: 4158.9648 | S24: 4053.2153 | T24: 3955.3257 | U24: 3867.5049 | V24: 3793.1143 | W24: 3720.6106 | X24: 3658.8506 | Y24: 3602.6099 | Z24: 3557.1406 | AA24: 3518.7932 | AB24: 3490.781 | AC24: 3470.6499 | AD24: 3449.8669 | AE24: 3436.2156 | AF24: 3421.4976 | AG24: -0.016
A25: Compressed/Liquefied Natural Gas | B25: Transportation Energy Use: Freight Trucks: Natural Gas: High Zero-Carbon Technology Cost | C25: AEO.2025.HIGHZTC.CNSM_NA_TRN_FRTT_NG_NA_NA_TRLBTU.A | D25: trillion Btu | F25: 55.607025 | G25: 61.286621 | H25: 66.512894 | I25: 70.746414 | J25: 73.719643 | K25: 76.223946 | L25: 77.844803 | M25: 78.784286 | N25: 78.480484 | O25: 77.958153 | P25: 77.938934 | Q25: 78.406151 | R25: 79.31675 | S25: 80.993866 | T25: 83.580132 | U25: 87.354393 | V25: 93.074173 | W25: 99.738602 | X25: 107.46339 | Y25: 116.10664 | Z25: 125.44911 | AA25: 135.2171 | AB25: 145.73639 | AC25: 156.81 | AD25: 168.02614 | AE25: 179.7695 | AF25: 191.95842 | AG25: 0.049
A26: Propane | B26: Transportation Energy Use: Freight Trucks: Propane: High Zero-Carbon Technology Cost | C26: AEO.2025.HIGHZTC.CNSM_NA_TRN_FRTT_LPG_NA_NA_TRLBTU.A | D26: trillion Btu | F26: 1.636492 | G26: 1.801557 | H26: 1.951411 | I26: 2.084738 | J26: 2.188121 | K26: 2.252767 | L26: 2.307956 | M26: 2.332778 | N26: 2.341018 | O26: 2.337155 | P26: 2.332596 | Q26: 2.318546 | R26: 2.303517 | S26: 2.287126 | T26: 2.27201 | U26: 2.259797 | V26: 2.25367 | W26: 2.242332 | X26: 2.232503 | Y26: 2.222283 | Z26: 2.216636 | AA26: 2.215415 | AB26: 2.21933 | AC26: 2.226755 | AD26: 2.227245 | AE26: 2.224462 | AF26: 2.222812 | AG26: 0.012
A27: E85 | B27: Transportation Energy Use: Freight Trucks: E85: High Zero-Carbon Technology Cost | C27: AEO.2025.HIGHZTC.CNSM_NA_TRN_FRTT_E85_NA_NA_TRLBTU.A | D27: trillion Btu | F27: 1.423929 | G27: 1.318955 | H27: 1.146513 | I27: 1.021841 | J27: 0.946846 | K27: 0.931149 | L27: 0.862054 | M27: 0.786396 | N27: 0.730176 | O27: 0.679167 | P27: 0.626373 | Q27: 0.57731 | R27: 0.529053 | S27: 0.485149 | T27: 0.442946 | U27: 0.404136 | V27: 0.370378 | W27: 0.338337 | X27: 0.310206 | Y27: 0.285105 | Z27: 0.261264 | AA27: 0.236446 | AB27: 0.211961 | AC27: 0.188605 | AD27: 0.162717 | AE27: 0.136932 | AF27: 0.110914 | AG27: -0.094
A28: Electricity | B28: Transportation Energy Use: Freight Trucks: Electricity: High Zero-Carbon Technology Cost | C28: AEO.2025.HIGHZTC.CNSM_NA_TRN_FRTT_ELC_NA_NA_TRLBTU.A | D28: trillion Btu | F28: 2.266414 | G28: 3.433411 | H28: 5.599921 | I28: 8.880999 | J28: 12.972794 | K28: 18.272411 | L28: 27.942268 | M28: 45.792831 | N28: 74.49781 | O28: 105.26667 | P28: 133.8157 | Q28: 159.0761 | R28: 180.93138 | S28: 199.40852 | T28: 214.66609 | U28: 227.2757 | V28: 237.93591 | W28: 245.96394 | X28: 252.02275 | Y28: 255.97452 | Z28: 258.67361 | AA28: 260.44653 | AB28: 261.64618 | AC28: 262.22531 | AD28: 262.02826 | AE28: 261.76526 | AF28: 260.92081 | AG28: 0.2
A29: Hydrogen | B29: Transportation Energy Use: Freight Trucks: Hydrogen: High Zero-Carbon Technology Cost | C29: AEO.2025.HIGHZTC.CNSM_NA_TRN_FRTT_HDG_NA_NA_TRLBTU.A | D29: trillion Btu | F29: 0.378578 | G29: 2.505357 | H29: 6.048138 | I29: 11.453158 | J29: 19.628872 | K29: 29.392036 | L29: 40.610481 | M29: 65.934532 | N29: 123.7632 | O29: 177.06161 | P29: 226.4043 | Q29: 271.92246 | R29: 315.25488 | S29: 356.61429 | T29: 395.5607 | U29: 432.4386 | V29: 468.44046 | W29: 501.67319 | X29: 532.65796 | Y29: 560.5033 | Z29: 586.33203 | AA29: 610 | AB29: 631.66052 | AC29: 651.26977 | AD29: 668.21777 | AE29: 683.82318 | AF29: 696.85938 | AG29: 0.335
A30: Freight Rail | B30: Transportation Energy Use: Freight Rail: Total: High Zero-Carbon Technology Cost | C30: AEO.2025.HIGHZTC.CNSM_NA_TRN_FRAIL_NA_NA_NA_TRLBTU.A | D30: trillion Btu | F30: 434.06409 | G30: 444.38675 | H30: 432.66199 | I30: 416.25888 | J30: 415.83365 | K30: 419.08118 | L30: 406.80212 | M30: 407.73685 | N30: 387.07651 | O30: 388.41467 | P30: 385.07489 | Q30: 384.40488 | R30: 385.70474 | S30: 386.56387 | T30: 389.65802 | U30: 383.65881 | V30: 385.24612 | W30: 384.97702 | X30: 386.4035 | Y30: 388.01605 | Z30: 389.36176 | AA30: 391.8663 | AB30: 393.15125 | AC30: 394.18994 | AD30: 396.63806 | AE30: 398.89523 | AF30: 399.70093 | AG30: -0.003
A31: Distillate Fuel Oil (diesel) | B31: Transportation Energy Use: Freight Rail: Distillate Fuel Oil: High Zero-Carbon Technology Cost | C31: AEO.2025.HIGHZTC.CNSM_NA_TRN_FRAIL_DFO_NA_NA_TRLBTU.A | D31: trillion Btu | F31: 434.06409 | G31: 444.38675 | H31: 432.66199 | I31: 416.25888 | J31: 415.83365 | K31: 419.08118 | L31: 406.80212 | M31: 407.73685 | N31: 387.07651 | O31: 388.41467 | P31: 385.07489 | Q31: 384.40488 | R31: 385.70474 | S31: 386.56387 | T31: 389.65802 | U31: 383.65881 | V31: 385.24612 | W31: 384.97702 | X31: 386.4035 | Y31: 388.01605 | Z31: 389.36176 | AA31: 391.8663 | AB31: 393.15125 | AC31: 394.18994 | AD31: 396.63806 | AE31: 398.89523 | AF31: 399.70093 | AG31: -0.003
A32: Residual Fuel Oil | B32: Transportation Energy Use: Freight Rail: Residual Fuel Oil: High Zero-Carbon Technology Cost | C32: AEO.2025.HIGHZTC.CNSM_NA_TRN_FRAIL_RFO_NA_NA_TRLBTU.A | D32: trillion Btu | F32: 0 | G32: 0 | H32: 0 | I32: 0 | J32: 0 | K32: 0 | L32: 0 | M32: 0 | N32: 0 | O32: 0 | P32: 0 | Q32: 0 | R32: 0 | S32: 0 | T32: 0 | U32: 0 | V32: 0 | W32: 0 | X32: 0 | Y32: 0 | Z32: 0 | AA32: 0 | AB32: 0 | AC32: 0 | AD32: 0 | AE32: 0 | AF32: 0 | AG32: - -
A33: Compressed Natural Gas | B33: Transportation Energy Use: Freight Rail: CNG: High Zero-Carbon Technology Cost | C33: AEO.2025.HIGHZTC.CNSM_NA_TRN_FRAIL_CNG_NA_NA_TRLBTU.A | D33: trillion Btu | F33: 0 | G33: 0 | H33: 0 | I33: 0 | J33: 0 | K33: 0 | L33: 0 | M33: 0 | N33: 0 | O33: 0 | P33: 0 | Q33: 0 | R33: 0 | S33: 0 | T33: 0 | U33: 0 | V33: 0 | W33: 0 | X33: 0 | Y33: 0 | Z33: 0 | AA33: 0 | AB33: 0 | AC33: 0 | AD33: 0 | AE33: 0 | AF33: 0 | AG33: - -
A34: Liquefied Natural Gas | B34: Transportation Energy Use: Freight Rail: LNG: High Zero-Carbon Technology Cost | C34: AEO.2025.HIGHZTC.CNSM_NA_TRN_FRAIL_LNG_NA_NA_TRLBTU.A | D34: trillion Btu | F34: 0 | G34: 0 | H34: 0 | I34: 0 | J34: 0 | K34: 0 | L34: 0 | M34: 0 | N34: 0 | O34: 0 | P34: 0 | Q34: 0 | R34: 0 | S34: 0 | T34: 0 | U34: 0 | V34: 0 | W34: 0 | X34: 0 | Y34: 0 | Z34: 0 | AA34: 0 | AB34: 0 | AC34: 0 | AD34: 0 | AE34: 0 | AF34: 0 | AG34: - -
A35: Domestic Shipping | B35: Transportation Energy Use: Domestic Shipping: Total: High Zero-Carbon Technology Cost | C35: AEO.2025.HIGHZTC.CNSM_NA_TRN_DMT_NA_NA_NA_TRLBTU.A | D35: trillion Btu | F35: 94.44101 | G35: 95.27887 | H35: 94.586136 | I35: 93.708351 | J35: 93.004196 | K35: 92.223045 | L35: 91.304771 | M35: 90.212555 | N35: 88.847214 | O35: 87.756058 | P35: 86.901985 | Q35: 85.969269 | R35: 84.990311 | S35: 84.006584 | T35: 83.086525 | U35: 82.232483 | V35: 81.614235 | W35: 80.902916 | X35: 80.232147 | Y35: 79.5196 | Z35: 78.892044 | AA35: 78.27169 | AB35: 77.757919 | AC35: 77.264191 | AD35: 76.642616 | AE35: 76.132912 | AF35: 75.601562 | AG35: -0.009
A36: Distillate Fuel Oil (diesel) | B36: Transportation Energy Use: Domestic Shipping: Distillate Fuel Oil: High Zero-Carbon Technology Cost | C36: AEO.2025.HIGHZTC.CNSM_NA_TRN_DMT_DFO_NA_NA_TRLBTU.A | D36: trillion Btu | F36: 92.332253 | G36: 93.229027 | H36: 92.558723 | I36: 91.707336 | J36: 91.024765 | K36: 90.266647 | L36: 89.374756 | M36: 88.312607 | N36: 86.983078 | O36: 85.921478 | P36: 85.091591 | Q36: 84.18441 | R36: 83.23098 | S36: 82.273125 | T36: 81.378265 | U36: 80.54834 | V36: 79.906387 | W36: 79.115509 | X36: 78.359489 | Y36: 77.557571 | Z36: 76.833122 | AA36: 76.10984 | AB36: 75.48381 | AC36: 74.870232 | AD36: 74.125595 | AE36: 73.481552 | AF36: 72.808403 | AG36: -0.009
A37: Residual Oil | B37: Transportation Energy Use: Domestic Shipping: Residual Oil: High Zero-Carbon Technology Cost | C37: AEO.2025.HIGHZTC.CNSM_NA_TRN_DMT_RFO_NA_NA_TRLBTU.A | D37: trillion Btu | F37: 1.38224 | G37: 1.262424 | H37: 1.198125 | I37: 1.1297 | J37: 1.065997 | K37: 1.002686 | L37: 0.935397 | M37: 0.864924 | N37: 0.794553 | O37: 0.726979 | P37: 0.66444 | Q37: 0.60409 | R37: 0.551972 | S37: 0.496411 | T37: 0.435091 | U37: 0.370942 | V37: 0.315153 | W37: 0.312295 | X37: 0.309586 | Y37: 0.306732 | Z37: 0.304215 | AA37: 0.301702 | AB37: 0.299605 | AC37: 0.297626 | AD37: 0.295128 | AE37: 0.293075 | AF37: 0.290938 | AG37: -0.058
A38: Compressed Natural Gas | B38: Transportation Energy Use: Domestic Shipping: CNG: High Zero-Carbon Technology Cost | C38: AEO.2025.HIGHZTC.CNSM_NA_TRN_DMT_CNG_NA_NA_TRLBTU.A | D38: trillion Btu | F38: 0 | G38: 0 | H38: 0 | I38: 0 | J38: 0 | K38: 0 | L38: 0 | M38: 0 | N38: 0 | O38: 0 | P38: 0 | Q38: 0 | R38: 0 | S38: 0 | T38: 0 | U38: 0 | V38: 0 | W38: 0 | X38: 0 | Y38: 0 | Z38: 0 | AA38: 0 | AB38: 0 | AC38: 0 | AD38: 0 | AE38: 0 | AF38: 0 | AG38: - -
A39: Liquefied Natural Gas | B39: Transportation Energy Use: Domestic Shipping: LNG: High Zero-Carbon Technology Cost | C39: AEO.2025.HIGHZTC.CNSM_NA_TRN_DMT_LNG_NA_NA_TRLBTU.A | D39: trillion Btu | F39: 0.726514 | G39: 0.787423 | H39: 0.829282 | I39: 0.871314 | J39: 0.913439 | K39: 0.953713 | L39: 0.99462 | M39: 1.035029 | N39: 1.069581 | O39: 1.107598 | P39: 1.14596 | Q39: 1.180773 | R39: 1.20736 | S39: 1.237043 | T39: 1.273172 | U39: 1.313204 | V39: 1.392694 | W39: 1.47511 | X39: 1.563072 | Y39: 1.655294 | Z39: 1.754708 | AA39: 1.860145 | AB39: 1.9745 | AC39: 2.096337 | AD39: 2.221896 | AE39: 2.358284 | AF39: 2.502217 | AG39: 0.049
A40: International Shipping | B40: Transportation Energy Use: International Shipping: Total: High Zero-Carbon Technology Cost | C40: AEO.2025.HIGHZTC.CNSM_NA_TRN_INTS_NA_NA_NA_TRLBTU.A | D40: trillion Btu | F40: 752.13025 | G40: 733.3067 | H40: 742.06049 | I40: 754.56427 | J40: 766.50555 | K40: 778.03467 | L40: 789.80176 | M40: 800.87366 | N40: 812.74347 | O40: 823.2041 | P40: 836.37293 | Q40: 846.20081 | R40: 853.59204 | S40: 861.87116 | T40: 868.49695 | U40: 875.62793 | V40: 882.57135 | W40: 888.73053 | X40: 895.35602 | Y40: 901.50629 | Z40: 908.52472 | AA40: 913.87469 | AB40: 919.83179 | AC40: 927.04059 | AD40: 933.39648 | AE40: 940.06476 | AF40: 945.89783 | AG40: 0.009
A41: Distillate Fuel Oil (diesel) | B41: Transportation Energy Use: International Shipping: Distillate Fuel Oil: High Zero-Carbon Technology Cost | C41: AEO.2025.HIGHZTC.CNSM_NA_TRN_INTS_DFO_NA_NA_TRLBTU.A | D41: trillion Btu | F41: 195.75676 | G41: 212.58131 | H41: 224.52464 | I41: 227.93929 | J41: 233.25775 | K41: 236.12277 | L41: 239.11221 | M41: 243.18715 | N41: 249.75525 | O41: 255.75678 | P41: 262.03488 | Q41: 265.78299 | R41: 268.34146 | S41: 270.24402 | T41: 272.47406 | U41: 273.81439 | V41: 275.54227 | W41: 277.35568 | X41: 279.3913 | Y41: 281.28842 | Z41: 280.65305 | AA41: 282.3649 | AB41: 285.01282 | AC41: 287.12247 | AD41: 289.21393 | AE41: 292.17453 | AF41: 295.77689 | AG41: 0.016
A42: Residual Oil | B42: Transportation Energy Use: International Shipping: Residual Oil: High Zero-Carbon Technology Cost | C42: AEO.2025.HIGHZTC.CNSM_NA_TRN_INTS_RFO_NA_NA_TRLBTU.A | D42: trillion Btu | F42: 550.43884 | G42: 514.18426 | H42: 510.8992 | I42: 519.96149 | J42: 526.24042 | K42: 534.55054 | L42: 542.92639 | M42: 549.45734 | N42: 554.50519 | O42: 558.63245 | P42: 565.22852 | Q42: 571.00024 | R42: 575.61383 | S42: 581.75073 | T42: 585.95453 | U42: 591.57178 | V42: 596.58789 | W42: 600.78863 | X42: 605.23956 | Y42: 609.3794 | Z42: 616.91864 | AA42: 620.51691 | AB42: 623.70618 | AC42: 628.71411 | AD42: 632.90594 | AE42: 636.49347 | AF42: 638.4978 | AG42: 0.006
A43: Compressed Natural Gas | B43: Transportation Energy Use: International Shipping: CNG: High Zero-Carbon Technology Cost | C43: AEO.2025.HIGHZTC.CNSM_NA_TRN_INTS_CNG_NA_NA_TRLBTU.A | D43: trillion Btu | F43: 0 | G43: 0 | H43: 0 | I43: 0 | J43: 0 | K43: 0 | L43: 0 | M43: 0 | N43: 0 | O43: 0 | P43: 0 | Q43: 0 | R43: 0 | S43: 0 | T43: 0 | U43: 0 | V43: 0 | W43: 0 | X43: 0 | Y43: 0 | Z43: 0 | AA43: 0 | AB43: 0 | AC43: 0 | AD43: 0 | AE43: 0 | AF43: 0 | AG43: - -
A44: Liquefied Natural Gas | B44: Transportation Energy Use: International Shipping: LNG: High Zero-Carbon Technology Cost | C44: AEO.2025.HIGHZTC.CNSM_NA_TRN_INTS_LNG_NA_NA_TRLBTU.A | D44: trillion Btu | F44: 5.93466 | G44: 6.541157 | H44: 6.636672 | I44: 6.663532 | J44: 7.007362 | K44: 7.361353 | L44: 7.763188 | M44: 8.229191 | N44: 8.483017 | O44: 8.814903 | P44: 9.109492 | Q44: 9.417616 | R44: 9.636709 | S44: 9.876389 | T44: 10.068367 | U44: 10.241791 | V44: 10.441242 | W44: 10.58622 | X44: 10.725135 | Y44: 10.838467 | Z44: 10.953075 | AA44: 10.992849 | AB44: 11.112764 | AC44: 11.204041 | AD44: 11.276592 | AE44: 11.396806 | AF44: 11.623198 | AG44: 0.026
A45: Air Transportation | B45: Transportation Energy Use: Air: Total: High Zero-Carbon Technology Cost | C45: AEO.2025.HIGHZTC.CNSM_NA_TRN_AIR_NA_NA_NA_TRLBTU.A | D45: trillion Btu | F45: 3268.3242 | G45: 3261.9939 | H45: 3288.9993 | I45: 3324.144 | J45: 3351.9536 | K45: 3387.1174 | L45: 3417.8857 | M45: 3438.6223 | N45: 3463.2673 | O45: 3487.4619 | P45: 3511.9185 | Q45: 3545.7239 | R45: 3578.2483 | S45: 3614.8806 | T45: 3653.8213 | U45: 3694.3792 | V45: 3737.8083 | W45: 3776.9478 | X45: 3818.4766 | Y45: 3857.0522 | Z45: 3896.0488 | AA45: 3933.9158 | AB45: 3972.8289 | AC45: 4011.6816 | AD45: 4050.0459 | AE45: 4089.4229 | AF45: 4128.4189 | AG45: 0.009
A46: Jet Fuel | B46: Transportation Energy Use: Air: Jet Fuel: High Zero-Carbon Technology Cost | C46: AEO.2025.HIGHZTC.CNSM_NA_TRN_AIR_JFL_NA_NA_TRLBTU.A | D46: trillion Btu | F46: 3245.9226 | G46: 3239.5999 | H46: 3266.6116 | I46: 3301.7615 | J46: 3329.5752 | K46: 3364.7424 | L46: 3395.5137 | M46: 3416.2527 | N46: 3440.8997 | O46: 3465.0959 | P46: 3489.554 | Q46: 3523.3604 | R46: 3555.8857 | S46: 3592.5188 | T46: 3631.4602 | U46: 3672.0186 | V46: 3715.4482 | W46: 3754.5881 | X46: 3796.1172 | Y46: 3834.6931 | Z46: 3873.6899 | AA46: 3911.5569 | AB46: 3950.4702 | AC46: 3989.323 | AD46: 4027.6875 | AE46: 4067.0645 | AF46: 4106.0605 | AG46: 0.009
A47: Aviation Gasoline | B47: Transportation Energy Use: Air: Aviation Gasoline: High Zero-Carbon Technology Cost | C47: AEO.2025.HIGHZTC.CNSM_NA_TRN_AIR_AVGA_NA_NA_TRLBTU.A | D47: trillion Btu | F47: 22.401548 | G47: 22.394032 | H47: 22.387812 | I47: 22.382666 | J47: 22.378407 | K47: 22.374884 | L47: 22.371969 | M47: 22.369558 | N47: 22.367563 | O47: 22.365911 | P47: 22.364546 | Q47: 22.363417 | R47: 22.36248 | S47: 22.361708 | T47: 22.361067 | U47: 22.360538 | V47: 22.3601 | W47: 22.359737 | X47: 22.359438 | Y47: 22.35919 | Z47: 22.358984 | AA47: 22.358814 | AB47: 22.358673 | AC47: 22.358557 | AD47: 22.358461 | AE47: 22.358381 | AF47: 22.358315 | AG47: 0
A48: Military Use | B48: Transportation Energy Use: Military: Total: High Zero-Carbon Technology Cost | C48: AEO.2025.HIGHZTC.CNSM_NA_TRN_MILT_NA_NA_NA_TRLBTU.A | D48: trillion Btu | F48: 444.78882 | G48: 449.84467 | H48: 452.96936 | I48: 454.89594 | J48: 455.76202 | K48: 455.59357 | L48: 455.3775 | M48: 455.84168 | N48: 456.21741 | O48: 456.60962 | P48: 456.93198 | Q48: 457.18359 | R48: 457.63098 | S48: 458.2178 | T48: 458.78357 | U48: 459.33374 | V48: 459.8689 | W48: 460.39087 | X48: 460.90399 | Y48: 461.41101 | Z48: 461.91266 | AA48: 462.40851 | AB48: 462.90356 | AC48: 463.39795 | AD48: 463.88965 | AE48: 464.38208 | AF48: 464.87579 | AG48: 0.002
A49: Jet Fuel and Aviation Gasoline | B49: Transportation Energy Use: Military: Jet Fuel: High Zero-Carbon Technology Cost | C49: AEO.2025.HIGHZTC.CNSM_NA_TRN_MILT_JFL_NA_NA_TRLBTU.A | D49: trillion Btu | F49: 335.94638 | G49: 339.76504 | H49: 342.12509 | I49: 343.58023 | J49: 344.23438 | K49: 344.10715 | L49: 343.94397 | M49: 344.29456 | N49: 344.57834 | O49: 344.87457 | P49: 345.11804 | Q49: 345.30811 | R49: 345.646 | S49: 346.08923 | T49: 346.51654 | U49: 346.9321 | V49: 347.33627 | W49: 347.73053 | X49: 348.1181 | Y49: 348.50104 | Z49: 348.87991 | AA49: 349.25446 | AB49: 349.62836 | AC49: 350.00177 | AD49: 350.37314 | AE49: 350.74509 | AF49: 351.11795 | AG49: 0.002
A50: Residual Fuel Oil | B50: Transportation Energy Use: Military: Residual Fuel Oil: High Zero-Carbon Technology Cost | C50: AEO.2025.HIGHZTC.CNSM_NA_TRN_MILT_RFO_NA_NA_TRLBTU.A | D50: trillion Btu | F50: 0 | G50: 0 | H50: 0 | I50: 0 | J50: 0 | K50: 0 | L50: 0 | M50: 0 | N50: 0 | O50: 0 | P50: 0 | Q50: 0 | R50: 0 | S50: 0 | T50: 0 | U50: 0 | V50: 0 | W50: 0 | X50: 0 | Y50: 0 | Z50: 0 | AA50: 0 | AB50: 0 | AC50: 0 | AD50: 0 | AE50: 0 | AF50: 0 | AG50: - -
A51: Distillates and Diesel | B51: Transportation Energy Use: Military: Distillate Fuel Oil: High Zero-Carbon Technology Cost | C51: AEO.2025.HIGHZTC.CNSM_NA_TRN_MILT_DFO_NA_NA_TRLBTU.A | D51: trillion Btu | F51: 108.84243 | G51: 110.07963 | H51: 110.84426 | I51: 111.31572 | J51: 111.52764 | K51: 111.48642 | L51: 111.43355 | M51: 111.54713 | N51: 111.63908 | O51: 111.73505 | P51: 111.81393 | Q51: 111.8755 | R51: 111.98498 | S51: 112.12857 | T51: 112.26702 | U51: 112.40166 | V51: 112.53262 | W51: 112.66032 | X51: 112.7859 | Y51: 112.90997 | Z51: 113.03274 | AA51: 113.15407 | AB51: 113.27522 | AC51: 113.39619 | AD51: 113.51651 | AE51: 113.63701 | AF51: 113.75784 | AG51: 0.002
A52: Bus Transportation | B52: Transportation Energy Use: Bus: High Zero-Carbon Technology Cost | C52: AEO.2025.HIGHZTC.CNSM_NA_TRN_BUS_NA_NA_NA_TRLBTU.A | D52: trillion Btu | F52: 207.86243 | G52: 213.54208 | H52: 215.9906 | I52: 216.63992 | J52: 216.57369 | K52: 215.75391 | L52: 214.79817 | M52: 212.57156 | N52: 209.5369 | O52: 206.2919 | P52: 203.21616 | Q52: 199.88687 | R52: 196.78232 | S52: 193.77222 | T52: 190.58655 | U52: 187.49443 | V52: 184.37126 | W52: 181.43538 | X52: 178.59711 | Y52: 175.79675 | Z52: 172.36633 | AA52: 169.69446 | AB52: 167.52806 | AC52: 165.4205 | AD52: 163.3414 | AE52: 161.30496 | AF52: 159.47977 | AG52: -0.01
A53: Transit Bus | B53: Transportation Energy Use: Bus: Transit Bus: High Zero-Carbon Technology Cost | C53: AEO.2025.HIGHZTC.CNSM_NA_TRN_TBUS_NA_NA_NA_TRLBTU.A | D53: trillion Btu | F53: 76.713676 | G53: 81.340424 | H53: 83.945221 | I53: 85.538612 | J53: 86.718315 | K53: 87.466774 | L53: 88.35804 | M53: 88.470428 | N53: 88.173332 | O53: 87.581596 | P53: 87.076767 | Q53: 86.256851 | R53: 85.611046 | S53: 84.879425 | T53: 84.100143 | U53: 83.310959 | V53: 82.433357 | W53: 81.646797 | X53: 80.873589 | Y53: 80.10347 | Z53: 78.494415 | AA53: 77.453468 | AB53: 76.728394 | AC53: 75.947868 | AD53: 75.172005 | AE53: 74.390259 | AF53: 73.757797 | AG53: -0.002
A54: Motor Gasoline | B54: Transportation Energy Use: Bus: Transit Bus: Motor Gasoline: High Zero-Carbon Technology Cost | C54: AEO.2025.HIGHZTC.CNSM_NA_TRN_TBUS_MGS_NA_NA_TRLBTU.A | D54: trillion Btu | F54: 9.147728 | G54: 9.642467 | H54: 9.883402 | I54: 9.981477 | J54: 10.010757 | K54: 9.948858 | L54: 9.929296 | M54: 9.781315 | N54: 9.534733 | O54: 9.246647 | P54: 8.946321 | Q54: 8.631692 | R54: 8.38075 | S54: 8.09886 | T54: 7.86342 | U54: 7.604629 | V54: 7.390038 | W54: 7.158372 | X54: 6.949068 | Y54: 6.759976 | Z54: 6.48781 | AA54: 6.31827 | AB54: 6.219316 | AC54: 6.066014 | AD54: 5.923258 | AE54: 5.827044 | AF54: 5.671556 | AG54: -0.018
A55: E85 | B55: Transportation Energy Use: Bus: Transit Bus: E85: High Zero-Carbon Technology Cost | C55: AEO.2025.HIGHZTC.CNSM_NA_TRN_TBUS_E85_NA_NA_TRLBTU.A | D55: trillion Btu | F55: 0 | G55: 0 | H55: 0 | I55: 0 | J55: 0 | K55: 0 | L55: 0 | M55: 0 | N55: 0 | O55: 0 | P55: 0 | Q55: 0 | R55: 0 | S55: 0 | T55: 0 | U55: 0 | V55: 0 | W55: 0 | X55: 0 | Y55: 0 | Z55: 0 | AA55: 0 | AB55: 0 | AC55: 0 | AD55: 0 | AE55: 0 | AF55: 0 | AG55: - -
A56: Distillate Fuel Oil (diesel) | B56: Transportation Energy Use: Bus: Transit Bus: Distillate Fuel Oil: High Zero-Carbon Technology Cost | C56: AEO.2025.HIGHZTC.CNSM_NA_TRN_TBUS_DFO_NA_NA_TRLBTU.A | D56: trillion Btu | F56: 40.627388 | G56: 42.872288 | H56: 44.088909 | I56: 44.716587 | J56: 45.00478 | K56: 44.906284 | L56: 44.98534 | M56: 44.458988 | N56: 43.456772 | O56: 42.279755 | P56: 41.047626 | Q56: 39.683052 | R56: 38.550735 | S56: 37.340832 | T56: 36.306938 | U56: 35.190861 | V56: 34.226418 | W56: 33.203209 | X56: 32.304462 | Y56: 31.44088 | Z56: 30.262665 | AA56: 29.476738 | AB56: 28.988014 | AC56: 28.394573 | AD56: 27.780321 | AE56: 27.350904 | AF56: 26.737988 | AG56: -0.016
A57: Compressed/Liquefied Natural Gas | B57: Transportation Energy Use: Bus: Transit Bus: Natural Gas: High Zero-Carbon Technology Cost | C57: AEO.2025.HIGHZTC.CNSM_NA_TRN_TBUS_NG_NA_NA_TRLBTU.A | D57: trillion Btu | F57: 23.265272 | G57: 24.381159 | H57: 24.767448 | I57: 24.779255 | J57: 24.708263 | K57: 24.42313 | L57: 24.169113 | M57: 23.815048 | N57: 23.317387 | O57: 22.69585 | P57: 22.093412 | Q57: 21.511358 | R57: 21.066313 | S57: 20.511549 | T57: 20.054729 | U57: 19.574566 | V57: 19.189419 | W57: 18.803814 | X57: 18.386913 | Y57: 18.147205 | Z57: 17.600431 | AA57: 17.348394 | AB57: 17.209435 | AC57: 16.792492 | AD57: 16.58194 | AE57: 16.347504 | AF57: 16.025608 | AG57: -0.014
A58: Propane | B58: Transportation Energy Use: Bus: Transit Bus: Propane: High Zero-Carbon Technology Cost | C58: AEO.2025.HIGHZTC.CNSM_NA_TRN_TBUS_LPG_NA_NA_TRLBTU.A | D58: trillion Btu | F58: 0.88137 | G58: 0.944928 | H58: 0.985149 | I58: 1.012938 | J58: 1.03505 | K58: 1.051444 | L58: 1.074973 | M58: 1.076987 | N58: 1.071976 | O58: 1.06367 | P58: 1.057564 | Q58: 1.047655 | R58: 1.041594 | S58: 1.033986 | T58: 1.025559 | U58: 1.017277 | V58: 1.007476 | W58: 0.999086 | X58: 0.991319 | Y58: 0.982627 | Z58: 0.962228 | AA58: 0.950182 | AB58: 0.943532 | AC58: 0.935979 | AD58: 0.92851 | AE58: 0.92102 | AF58: 0.914876 | AG58: 0.001
A59: Electricity | B59: Transportation Energy Use: Bus: Transit Bus: Electricity: High Zero-Carbon Technology Cost | C59: AEO.2025.HIGHZTC.CNSM_NA_TRN_TBUS_ELC_NA_NA_TRLBTU.A | D59: trillion Btu | F59: 2.758943 | G59: 3.464991 | H59: 4.185267 | I59: 5.013327 | J59: 5.924563 | K59: 7.10243 | L59: 8.164955 | M59: 9.303988 | N59: 10.758839 | O59: 12.262644 | P59: 13.899314 | Q59: 15.351219 | R59: 16.540325 | S59: 17.863461 | T59: 18.81938 | U59: 19.894112 | V59: 20.591154 | W59: 21.45405 | X59: 22.214142 | Y59: 22.745682 | Z59: 23.155113 | AA59: 23.334368 | AB59: 23.343084 | AC59: 23.734314 | AD59: 23.933989 | AE59: 23.920307 | AF59: 24.384747 | AG59: 0.087
A60: Hydrogen | B60: Transportation Energy Use: Bus: Transit Bus: Hydrogen: High Zero-Carbon Technology Cost | C60: AEO.2025.HIGHZTC.CNSM_NA_TRN_TBUS_HDG_NA_NA_TRLBTU.A | D60: trillion Btu | F60: 0.032973 | G60: 0.034595 | H60: 0.035048 | I60: 0.035029 | J60: 0.034907 | K60: 0.034625 | L60: 0.034362 | M60: 0.034102 | N60: 0.033624 | O60: 0.033036 | P60: 0.032528 | Q60: 0.031873 | R60: 0.031331 | S60: 0.030734 | T60: 0.030119 | U60: 0.029512 | V60: 0.028853 | W60: 0.028264 | X60: 0.027687 | Y60: 0.0271 | Z60: 0.026172 | AA60: 0.025512 | AB60: 0.025014 | AC60: 0.024496 | AD60: 0.023989 | AE60: 0.023483 | AF60: 0.023022 | AG60: -0.014
A61: Intercity Bus | B61: Transportation Energy Use: Bus: Intercity Bus: High Zero-Carbon Technology Cost | C61: AEO.2025.HIGHZTC.CNSM_NA_TRN_IBUS_NA_NA_NA_TRLBTU.A | D61: trillion Btu | F61: 30.108593 | G61: 31.32419 | H61: 32.204422 | I61: 32.814705 | J61: 33.257591 | K61: 33.581924 | L61: 33.814713 | M61: 33.975029 | N61: 34.077873 | O61: 34.13052 | P61: 34.142056 | Q61: 34.121861 | R61: 34.075111 | S61: 34.006035 | T61: 33.934147 | U61: 33.851566 | V61: 33.760597 | W61: 33.660355 | X61: 33.555733 | Y61: 33.445522 | Z61: 33.331009 | AA61: 33.212841 | AB61: 33.09325 | AC61: 32.971729 | AD61: 32.849072 | AE61: 32.72522 | AF61: 32.600166 | AG61: 0.003
A62: Motor Gasoline | B62: Transportation Energy Use: Bus: Intercity Bus: Motor Gasoline: High Zero-Carbon Technology Cost | C62: AEO.2025.HIGHZTC.CNSM_NA_TRN_IBUS_MGS_NA_NA_TRLBTU.A | D62: trillion Btu | F62: 0 | G62: 0 | H62: 0 | I62: 0 | J62: 0 | K62: 0 | L62: 0 | M62: 0 | N62: 0 | O62: 0 | P62: 0 | Q62: 0 | R62: 0 | S62: 0 | T62: 0 | U62: 0 | V62: 0 | W62: 0 | X62: 0 | Y62: 0 | Z62: 0 | AA62: 0 | AB62: 0 | AC62: 0 | AD62: 0 | AE62: 0 | AF62: 0 | AG62: - -
A63: E85 | B63: Transportation Energy Use: Bus: Intercity Bus: E85: High Zero-Carbon Technology Cost | C63: AEO.2025.HIGHZTC.CNSM_NA_TRN_IBUS_E85_NA_NA_TRLBTU.A | D63: trillion Btu | F63: 0 | G63: 0 | H63: 0 | I63: 0 | J63: 0 | K63: 0 | L63: 0 | M63: 0 | N63: 0 | O63: 0 | P63: 0 | Q63: 0 | R63: 0 | S63: 0 | T63: 0 | U63: 0 | V63: 0 | W63: 0 | X63: 0 | Y63: 0 | Z63: 0 | AA63: 0 | AB63: 0 | AC63: 0 | AD63: 0 | AE63: 0 | AF63: 0 | AG63: - -
A64: Distillate Fuel Oil (diesel) | B64: Transportation Energy Use: Bus: Intercity Bus: Distillate Fuel Oil: High Zero-Carbon Technology Cost | C64: AEO.2025.HIGHZTC.CNSM_NA_TRN_IBUS_DFO_NA_NA_TRLBTU.A | D64: trillion Btu | F64: 30.108593 | G64: 31.32419 | H64: 32.204422 | I64: 32.814705 | J64: 33.257591 | K64: 33.581924 | L64: 33.814713 | M64: 33.975029 | N64: 34.077873 | O64: 34.13052 | P64: 34.142056 | Q64: 34.121861 | R64: 34.075111 | S64: 34.006035 | T64: 33.934147 | U64: 33.851566 | V64: 33.760597 | W64: 33.660355 | X64: 33.555733 | Y64: 33.445522 | Z64: 33.331009 | AA64: 33.212841 | AB64: 33.09325 | AC64: 32.971729 | AD64: 32.849072 | AE64: 32.72522 | AF64: 32.600166 | AG64: 0.003
A65: Compressed/Liquefied Natural Gas | B65: Transportation Energy Use: Bus: Intercity Bus: Natural Gas: High Zero-Carbon Technology Cost | C65: AEO.2025.HIGHZTC.CNSM_NA_TRN_IBUS_NG_NA_NA_TRLBTU.A | D65: trillion Btu | F65: 0 | G65: 0 | H65: 0 | I65: 0 | J65: 0 | K65: 0 | L65: 0 | M65: 0 | N65: 0 | O65: 0 | P65: 0 | Q65: 0 | R65: 0 | S65: 0 | T65: 0 | U65: 0 | V65: 0 | W65: 0 | X65: 0 | Y65: 0 | Z65: 0 | AA65: 0 | AB65: 0 | AC65: 0 | AD65: 0 | AE65: 0 | AF65: 0 | AG65: - -
A66: Propane | B66: Transportation Energy Use: Bus: Intercity Bus: Propane: High Zero-Carbon Technology Cost | C66: AEO.2025.HIGHZTC.CNSM_NA_TRN_IBUS_LPG_NA_NA_TRLBTU.A | D66: trillion Btu | F66: 0 | G66: 0 | H66: 0 | I66: 0 | J66: 0 | K66: 0 | L66: 0 | M66: 0 | N66: 0 | O66: 0 | P66: 0 | Q66: 0 | R66: 0 | S66: 0 | T66: 0 | U66: 0 | V66: 0 | W66: 0 | X66: 0 | Y66: 0 | Z66: 0 | AA66: 0 | AB66: 0 | AC66: 0 | AD66: 0 | AE66: 0 | AF66: 0 | AG66: - -
A67: Electricity | B67: Transportation Energy Use: Bus: Intercity Bus: Electricity: High Zero-Carbon Technology Cost | C67: AEO.2025.HIGHZTC.CNSM_NA_TRN_IBUS_ELC_NA_NA_TRLBTU.A | D67: trillion Btu | F67: 0 | G67: 0 | H67: 0 | I67: 0 | J67: 0 | K67: 0 | L67: 0 | M67: 0 | N67: 0 | O67: 0 | P67: 0 | Q67: 0 | R67: 0 | S67: 0 | T67: 0 | U67: 0 | V67: 0 | W67: 0 | X67: 0 | Y67: 0 | Z67: 0 | AA67: 0 | AB67: 0 | AC67: 0 | AD67: 0 | AE67: 0 | AF67: 0 | AG67: - -
A68: Hydrogen | B68: Transportation Energy Use: Bus: Intercity Bus: Hydrogen: High Zero-Carbon Technology Cost | C68: AEO.2025.HIGHZTC.CNSM_NA_TRN_IBUS_HDG_NA_NA_TRLBTU.A | D68: trillion Btu | F68: 0 | G68: 0 | H68: 0 | I68: 0 | J68: 0 | K68: 0 | L68: 0 | M68: 0 | N68: 0 | O68: 0 | P68: 0 | Q68: 0 | R68: 0 | S68: 0 | T68: 0 | U68: 0 | V68: 0 | W68: 0 | X68: 0 | Y68: 0 | Z68: 0 | AA68: 0 | AB68: 0 | AC68: 0 | AD68: 0 | AE68: 0 | AF68: 0 | AG68: - -
A69: School Bus | B69: Transportation Energy Use: Bus: School Bus: High Zero-Carbon Technology Cost | C69: AEO.2025.HIGHZTC.CNSM_NA_TRN_LSRC_NA_NA_NA_TRLBTU.A | D69: trillion Btu | F69: 101.04017 | G69: 100.87746 | H69: 99.84095 | I69: 98.286613 | J69: 96.597778 | K69: 94.705215 | L69: 92.62542 | M69: 90.126106 | N69: 87.285683 | O69: 84.579781 | P69: 81.997322 | Q69: 79.508171 | R69: 77.096169 | S69: 74.886749 | T69: 72.552269 | U69: 70.331909 | V69: 68.177307 | W69: 66.128227 | X69: 64.167786 | Y69: 62.247749 | Z69: 60.540901 | AA69: 59.028156 | AB69: 57.706417 | AC69: 56.500896 | AD69: 55.32032 | AE69: 54.189476 | AF69: 53.121811 | AG69: -0.024
A70: Motor Gasoline | B70: Transportation Energy Use: Bus: School Bus: Motor Gasoline: High Zero-Carbon Technology Cost | C70: AEO.2025.HIGHZTC.CNSM_NA_TRN_LSRC_MGS_NA_NA_TRLBTU.A | D70: trillion Btu | F70: 10.011436 | G70: 9.964176 | H70: 9.821723 | I70: 9.614322 | J70: 9.38471 | K70: 9.121292 | L70: 8.827079 | M70: 8.456922 | N70: 8.017527 | O70: 7.593064 | P70: 7.182855 | Q70: 6.785142 | R70: 6.397426 | S70: 6.04143 | T70: 5.676151 | U70: 5.333529 | V70: 5.004425 | W70: 4.696619 | X70: 4.408235 | Y70: 4.129229 | Z70: 3.891798 | AA70: 3.692005 | AB70: 3.530134 | AC70: 3.391419 | AD70: 3.25913 | AE70: 3.136157 | AF70: 3.025429 | AG70: -0.045
A71: E85 | B71: Transportation Energy Use: Bus: School Bus: E85: High Zero-Carbon Technology Cost | C71: AEO.2025.HIGHZTC.CNSM_NA_TRN_LSRC_E85_NA_NA_TRLBTU.A | D71: trillion Btu | F71: 0 | G71: 0 | H71: 0 | I71: 0 | J71: 0 | K71: 0 | L71: 0 | M71: 0 | N71: 0 | O71: 0 | P71: 0 | Q71: 0 | R71: 0 | S71: 0 | T71: 0 | U71: 0 | V71: 0 | W71: 0 | X71: 0 | Y71: 0 | Z71: 0 | AA71: 0 | AB71: 0 | AC71: 0 | AD71: 0 | AE71: 0 | AF71: 0 | AG71: - -
A72: Distillate Fuel Oil (diesel) | B72: Transportation Energy Use: Bus: School Bus: Distillate Fuel Oil: High Zero-Carbon Technology Cost | C72: AEO.2025.HIGHZTC.CNSM_NA_TRN_LSRC_DFO_NA_NA_TRLBTU.A | D72: trillion Btu | F72: 81.477959 | G72: 81.093323 | H72: 79.93396 | I72: 78.246048 | J72: 76.377357 | K72: 74.233505 | L72: 71.839066 | M72: 68.826538 | N72: 65.250526 | O72: 61.796055 | P72: 58.457565 | Q72: 55.220787 | R72: 52.065376 | S72: 49.168098 | T72: 46.195282 | U72: 43.40686 | V72: 40.728447 | W72: 38.22337 | X72: 35.876366 | Y72: 33.605675 | Z72: 31.673342 | AA72: 30.047331 | AB72: 28.729946 | AC72: 27.601021 | AD72: 26.524384 | AE72: 25.523575 | AF72: 24.622414 | AG72: -0.045
A73: Compressed/Liquefied Natural Gas | B73: Transportation Energy Use: Bus: School Bus: Natural Gas: High Zero-Carbon Technology Cost | C73: AEO.2025.HIGHZTC.CNSM_NA_TRN_LSRC_NG_NA_NA_TRLBTU.A | D73: trillion Btu | F73: 1.080427 | G73: 1.108989 | H73: 1.124032 | I73: 1.133449 | J73: 1.142681 | K73: 1.151834 | L73: 1.160827 | M73: 1.169465 | N73: 1.178296 | O73: 1.186917 | P73: 1.196398 | Q73: 1.206272 | R73: 1.217246 | S73: 1.229459 | T73: 1.240311 | U73: 1.251236 | V73: 1.262401 | W73: 1.273438 | X73: 1.284112 | Y73: 1.294395 | Z73: 1.304595 | AA73: 1.315723 | AB73: 1.325555 | AC73: 1.334555 | AD73: 1.342887 | AE73: 1.350569 | AF73: 1.357745 | AG73: 0.009
A74: Propane | B74: Transportation Energy Use: Bus: School Bus: Propane: High Zero-Carbon Technology Cost | C74: AEO.2025.HIGHZTC.CNSM_NA_TRN_LSRC_LPG_NA_NA_TRLBTU.A | D74: trillion Btu | F74: 8.036844 | G74: 7.998907 | H74: 7.884549 | I74: 7.718054 | J74: 7.533731 | K74: 7.322266 | L74: 7.086082 | M74: 6.788931 | N74: 6.436201 | O74: 6.095457 | P74: 5.766154 | Q74: 5.446883 | R74: 5.135638 | S74: 4.849856 | T74: 4.556623 | U74: 4.281578 | V74: 4.017384 | W74: 3.770288 | X74: 3.538783 | Y74: 3.314806 | Z74: 3.124204 | AA74: 2.963817 | AB74: 2.833873 | AC74: 2.722517 | AD74: 2.61632 | AE74: 2.517601 | AF74: 2.428712 | AG74: -0.045
A75: Electricity | B75: Transportation Energy Use: Bus: School Bus: Electricity: High Zero-Carbon Technology Cost | C75: AEO.2025.HIGHZTC.CNSM_NA_TRN_LSRC_ELC_NA_NA_TRLBTU.A | D75: trillion Btu | F75: 0.433501 | G75: 0.712075 | H75: 1.07668 | I75: 1.574746 | J75: 2.159298 | K75: 2.876319 | L75: 3.712366 | M75: 4.88425 | N75: 6.403127 | O75: 7.908282 | P75: 9.394354 | Q75: 10.84909 | R75: 12.280479 | S75: 13.597902 | T75: 14.883904 | U75: 16.058702 | V75: 17.164646 | W75: 18.164515 | X75: 19.060289 | Y75: 19.90365 | Z75: 20.546963 | AA75: 21.009281 | AB75: 21.286911 | AC75: 21.451382 | AD75: 21.5776 | AE75: 21.661572 | AF75: 21.687511 | AG75: 0.162
A76: Hydrogen | B76: Transportation Energy Use: Bus: School Bus: Hydrogen: High Zero-Carbon Technology Cost | C76: AEO.2025.HIGHZTC.CNSM_NA_TRN_LSRC_HDG_NA_NA_TRLBTU.A | D76: trillion Btu | F76: 0 | G76: 0 | H76: 0 | I76: 0 | J76: 0 | K76: 0 | L76: 0 | M76: 0 | N76: 0 | O76: 0 | P76: 0 | Q76: 0 | R76: 0 | S76: 0 | T76: 0 | U76: 0 | V76: 0 | W76: 0 | X76: 0 | Y76: 0 | Z76: 0 | AA76: 0 | AB76: 0 | AC76: 0 | AD76: 0 | AE76: 0 | AF76: 0 | AG76: - -
A77: Rail Transportation | B77: Transportation Energy Use: Rail: High Zero-Carbon Technology Cost | C77: AEO.2025.HIGHZTC.CNSM_NA_TRN_RAIL_NA_NA_NA_TRLBTU.A | D77: trillion Btu | F77: 43.892979 | G77: 46.494804 | H77: 47.930431 | I77: 48.7127 | J77: 49.23811 | K77: 49.779125 | L77: 50.407837 | M77: 50.881531 | N77: 51.293755 | O77: 51.621185 | P77: 51.909443 | Q77: 52.169571 | R77: 52.53038 | S77: 52.945206 | T77: 53.364662 | U77: 53.755737 | V77: 54.128273 | W77: 54.482323 | X77: 54.85173 | Y77: 55.162514 | Z77: 55.416405 | AA77: 55.730747 | AB77: 56.11055 | AC77: 56.487953 | AD77: 56.863499 | AE77: 57.250282 | AF77: 57.64875 | AG77: 0.011
A78: Intercity Rail | B78: Transportation Energy Use: Rail: Intercity Rail: High Zero-Carbon Technology Cost | C78: AEO.2025.HIGHZTC.CNSM_NA_TRN_IRAIL_NA_NA_NA_TRLBTU.A | D78: trillion Btu | F78: 8.742382 | G78: 9.380059 | H78: 9.837832 | I78: 10.165743 | J78: 10.415087 | K78: 10.611311 | L78: 10.771235 | M78: 10.905774 | N78: 11.020588 | O78: 11.119541 | P78: 11.206322 | Q78: 11.283692 | R78: 11.353813 | S78: 11.417555 | T78: 11.481839 | U78: 11.543387 | V78: 11.602665 | W78: 11.660023 | X78: 11.716012 | Y78: 11.770653 | Z78: 11.824216 | AA78: 11.876847 | AB78: 11.928874 | AC78: 11.980318 | AD78: 12.031491 | AE78: 12.082007 | AF78: 12.132166 | AG78: 0.013
A79: Electricity | B79: Transportation Energy Use: Rail: Intercity Rail: Electricity: High Zero-Carbon Technology Cost | C79: AEO.2025.HIGHZTC.CNSM_NA_TRN_IRAIL_ELC_NA_NA_TRLBTU.A | D79: trillion Btu | F79: 1.06266 | G79: 1.140172 | H79: 1.195815 | I79: 1.235674 | J79: 1.265982 | K79: 1.289834 | L79: 1.309273 | M79: 1.325626 | N79: 1.339582 | O79: 1.35161 | P79: 1.362159 | Q79: 1.371563 | R79: 1.380087 | S79: 1.387835 | T79: 1.395649 | U79: 1.40313 | V79: 1.410336 | W79: 1.417307 | X79: 1.424113 | Y79: 1.430755 | Z79: 1.437265 | AA79: 1.443663 | AB79: 1.449986 | AC79: 1.45624 | AD79: 1.462461 | AE79: 1.4686 | AF79: 1.474698 | AG79: 0.013
A80: Diesel | B80: Transportation Energy Use: Rail: Intercity Rail: Diesel: High Zero-Carbon Technology Cost | C80: AEO.2025.HIGHZTC.CNSM_NA_TRN_IRAIL_DSL_NA_NA_TRLBTU.A | D80: trillion Btu | F80: 7.679722 | G80: 8.239887 | H80: 8.642017 | I80: 8.930069 | J80: 9.149105 | K80: 9.321477 | L80: 9.461963 | M80: 9.580148 | N80: 9.681005 | O80: 9.767931 | P80: 9.844163 | Q80: 9.912129 | R80: 9.973726 | S80: 10.02972 | T80: 10.08619 | U80: 10.140258 | V80: 10.192329 | W80: 10.242716 | X80: 10.291899 | Y80: 10.339898 | Z80: 10.38695 | AA80: 10.433185 | AB80: 10.478888 | AC80: 10.524078 | AD80: 10.569031 | AE80: 10.613407 | AF80: 10.657468 | AG80: 0.013
A81: Compressed Natural Gas | B81: Transportation Energy Use: Rail: Intercity Rail: CNG: High Zero-Carbon Technology Cost | C81: AEO.2025.HIGHZTC.CNSM_NA_TRN_IRAIL_CNG_NA_NA_TRLBTU.A | D81: trillion Btu | F81: 0 | G81: 0 | H81: 0 | I81: 0 | J81: 0 | K81: 0 | L81: 0 | M81: 0 | N81: 0 | O81: 0 | P81: 0 | Q81: 0 | R81: 0 | S81: 0 | T81: 0 | U81: 0 | V81: 0 | W81: 0 | X81: 0 | Y81: 0 | Z81: 0 | AA81: 0 | AB81: 0 | AC81: 0 | AD81: 0 | AE81: 0 | AF81: 0 | AG81: - -
A82: Liquefied Natural Gas | B82: Transportation Energy Use: Rail: Intercity Rail: LNG: High Zero-Carbon Technology Cost | C82: AEO.2025.HIGHZTC.CNSM_NA_TRN_IRAIL_LNG_NA_NA_TRLBTU.A | D82: trillion Btu | F82: 0 | G82: 0 | H82: 0 | I82: 0 | J82: 0 | K82: 0 | L82: 0 | M82: 0 | N82: 0 | O82: 0 | P82: 0 | Q82: 0 | R82: 0 | S82: 0 | T82: 0 | U82: 0 | V82: 0 | W82: 0 | X82: 0 | Y82: 0 | Z82: 0 | AA82: 0 | AB82: 0 | AC82: 0 | AD82: 0 | AE82: 0 | AF82: 0 | AG82: - -
A83: Transit Rail | B83: Transportation Energy Use: Rail: Transit Rail: High Zero-Carbon Technology Cost | C83: AEO.2025.HIGHZTC.CNSM_NA_TRN_TRAIL_NA_NA_NA_TRLBTU.A | D83: trillion Btu | F83: 14.508802 | G83: 15.423924 | H83: 16.004051 | I83: 16.428049 | J83: 16.873972 | K83: 17.277363 | L83: 17.596182 | M83: 17.825174 | N83: 18.030691 | O83: 18.172157 | P83: 18.297941 | Q83: 18.37661 | R83: 18.550228 | S83: 18.707918 | T83: 18.836727 | U83: 18.951267 | V83: 19.052519 | W83: 19.14823 | X83: 19.248808 | Y83: 19.321045 | Z83: 19.244219 | AA83: 19.261974 | AB83: 19.350773 | AC83: 19.42939 | AD83: 19.507893 | AE83: 19.592464 | AF83: 19.69496 | AG83: 0.012
A84: Electricity | B84: Transportation Energy Use: Rail: Transit Rail: Electricity: High Zero-Carbon Technology Cost | C84: AEO.2025.HIGHZTC.CNSM_NA_TRN_TRAIL_ELC_NA_NA_TRLBTU.A | D84: trillion Btu | F84: 14.508802 | G84: 15.423924 | H84: 16.004051 | I84: 16.428049 | J84: 16.873972 | K84: 17.277363 | L84: 17.596182 | M84: 17.825174 | N84: 18.030691 | O84: 18.172157 | P84: 18.297941 | Q84: 18.37661 | R84: 18.550228 | S84: 18.707918 | T84: 18.836727 | U84: 18.951267 | V84: 19.052519 | W84: 19.14823 | X84: 19.248808 | Y84: 19.321045 | Z84: 19.244219 | AA84: 19.261974 | AB84: 19.350773 | AC84: 19.42939 | AD84: 19.507893 | AE84: 19.592464 | AF84: 19.69496 | AG84: 0.012
A85: Commuter Rail | B85: Transportation Energy Use: Rail: Commuter Rail: High Zero-Carbon Technology Cost | C85: AEO.2025.HIGHZTC.CNSM_NA_TRN_CRAIL_NA_NA_NA_TRLBTU.A | D85: trillion Btu | F85: 20.641792 | G85: 21.690823 | H85: 22.088547 | I85: 22.118906 | J85: 21.949051 | K85: 21.890451 | L85: 22.040421 | M85: 22.150585 | N85: 22.242476 | O85: 22.329487 | P85: 22.405182 | Q85: 22.50927 | R85: 22.626337 | S85: 22.819733 | T85: 23.046093 | U85: 23.261082 | V85: 23.473091 | W85: 23.674068 | X85: 23.886911 | Y85: 24.070816 | Z85: 24.347973 | AA85: 24.591925 | AB85: 24.830904 | AC85: 25.078247 | AD85: 25.324118 | AE85: 25.575806 | AF85: 25.821625 | AG85: 0.009
A86: Electricity | B86: Transportation Energy Use: Rail: Commuter Rail: Electricity: High Zero-Carbon Technology Cost | C86: AEO.2025.HIGHZTC.CNSM_NA_TRN_CRAIL_ELC_NA_NA_TRLBTU.A | D86: trillion Btu | F86: 7.511251 | G86: 7.856135 | H86: 8.014301 | I86: 8.056931 | J86: 8.029058 | K86: 8.083075 | L86: 8.127502 | M86: 8.139222 | N86: 8.151962 | O86: 8.170964 | P86: 8.180331 | Q86: 8.20938 | R86: 8.23822 | S86: 8.306414 | T86: 8.392798 | U86: 8.472018 | V86: 8.555479 | W86: 8.630824 | X86: 8.707513 | Y86: 8.77251 | Z86: 8.913724 | AA86: 9.014948 | AB86: 9.095682 | AC86: 9.182542 | AD86: 9.267992 | AE86: 9.355288 | AF86: 9.435994 | AG86: 0.009
A87: Diesel | B87: Transportation Energy Use: Rail: Commuter Rail: Diesel: High Zero-Carbon Technology Cost | C87: AEO.2025.HIGHZTC.CNSM_NA_TRN_CRAIL_DSL_NA_NA_TRLBTU.A | D87: trillion Btu | F87: 13.130542 | G87: 13.834688 | H87: 14.074244 | I87: 14.061975 | J87: 13.919993 | K87: 13.807377 | L87: 13.912918 | M87: 14.011362 | N87: 14.090513 | O87: 14.158524 | P87: 14.224851 | Q87: 14.299891 | R87: 14.388117 | S87: 14.513319 | T87: 14.653296 | U87: 14.789064 | V87: 14.917612 | W87: 15.043245 | X87: 15.179399 | Y87: 15.298307 | Z87: 15.434248 | AA87: 15.576977 | AB87: 15.735222 | AC87: 15.895704 | AD87: 16.056126 | AE87: 16.220518 | AF87: 16.385632 | AG87: 0.009
A88: Compressed Natural Gas | B88: Transportation Energy Use: Rail: Commuter Rail: CNG: High Zero-Carbon Technology Cost | C88: AEO.2025.HIGHZTC.CNSM_NA_TRN_CRAIL_CNG_NA_NA_TRLBTU.A | D88: trillion Btu | F88: 0 | G88: 0 | H88: 0 | I88: 0 | J88: 0 | K88: 0 | L88: 0 | M88: 0 | N88: 0 | O88: 0 | P88: 0 | Q88: 0 | R88: 0 | S88: 0 | T88: 0 | U88: 0 | V88: 0 | W88: 0 | X88: 0 | Y88: 0 | Z88: 0 | AA88: 0 | AB88: 0 | AC88: 0 | AD88: 0 | AE88: 0 | AF88: 0 | AG88: - -
A89: Liquefied Natural Gas | B89: Transportation Energy Use: Rail: Commuter Rail: LNG: High Zero-Carbon Technology Cost | C89: AEO.2025.HIGHZTC.CNSM_NA_TRN_CRAIL_LNG_NA_NA_TRLBTU.A | D89: trillion Btu | F89: 0 | G89: 0 | H89: 0 | I89: 0 | J89: 0 | K89: 0 | L89: 0 | M89: 0 | N89: 0 | O89: 0 | P89: 0 | Q89: 0 | R89: 0 | S89: 0 | T89: 0 | U89: 0 | V89: 0 | W89: 0 | X89: 0 | Y89: 0 | Z89: 0 | AA89: 0 | AB89: 0 | AC89: 0 | AD89: 0 | AE89: 0 | AF89: 0 | AG89: - -
A90: Recreational Boats | B90: Transportation Energy Use: Recreation Boats: High Zero-Carbon Technology Cost | C90: AEO.2025.HIGHZTC.CNSM_NA_TRN_RCB_NA_NA_NA_TRLBTU.A | D90: trillion Btu | F90: 207.60503 | G90: 206.04599 | H90: 205.27014 | I90: 204.48312 | J90: 203.24808 | K90: 202.19612 | L90: 200.96423 | M90: 199.40019 | N90: 198.04327 | O90: 196.8064 | P90: 195.62358 | Q90: 194.62672 | R90: 193.6503 | S90: 192.78343 | T90: 191.86041 | U90: 191.0006 | V90: 190.22939 | W90: 189.31865 | X90: 188.52251 | Y90: 187.6864 | Z90: 186.82878 | AA90: 185.94426 | AB90: 185.12283 | AC90: 184.30211 | AD90: 183.46287 | AE90: 182.67705 | AF90: 181.86838 | AG90: -0.005
A91: Gasoline | B91: Transportation Energy Use: Recreation Boats: Motor Gasoline: High Zero-Carbon Technology Cost | C91: AEO.2025.HIGHZTC.CNSM_NA_TRN_RCB_GSL_NA_NA_TRLBTU.A | D91: trillion Btu | F91: 166.9146 | G91: 165.39096 | H91: 164.49768 | I91: 163.59615 | J91: 162.33752 | K91: 161.22684 | L91: 159.9744 | M91: 158.45999 | N91: 157.11281 | O91: 155.86308 | P91: 154.65817 | Q91: 153.60199 | R91: 152.56335 | S91: 151.6123 | T91: 150.61832 | U91: 149.67517 | V91: 148.80249 | W91: 147.82179 | X91: 146.93173 | Y91: 146.0116 | Z91: 145.07593 | AA91: 144.12064 | AB91: 143.2155 | AC91: 142.31206 | AD91: 141.39554 | AE91: 140.52135 | AF91: 139.63074 | AG91: -0.007
A92: Distillate Fuel Oil (diesel) | B92: Transportation Energy Use: Recreation Boats: Distillate Fuel Oil: High Zero-Carbon Technology Cost | C92: AEO.2025.HIGHZTC.CNSM_NA_TRN_RCB_DFO_NA_NA_TRLBTU.A | D92: trillion Btu | F92: 40.690426 | G92: 40.655025 | H92: 40.772465 | I92: 40.886971 | J92: 40.910557 | K92: 40.969288 | L92: 40.989838 | M92: 40.940205 | N92: 40.930458 | O92: 40.943306 | P92: 40.965408 | Q92: 41.024738 | R92: 41.086941 | S92: 41.171127 | T92: 41.242096 | U92: 41.325428 | V92: 41.426895 | W92: 41.496861 | X92: 41.590778 | Y92: 41.674797 | Z92: 41.752853 | AA92: 41.823624 | AB92: 41.907333 | AC92: 41.990051 | AD92: 42.067337 | AE92: 42.155701 | AF92: 42.23764 | AG92: 0.001
A93: Lubricants | B93: Transportation Energy Use: Lubricants: High Zero-Carbon Technology Cost | C93: AEO.2025.HIGHZTC.CNSM_NA_TRN_NA_LBC_NA_NA_TRLBTU.A | D93: trillion Btu | F93: 134.2615 | G93: 134.659 | H93: 135.33812 | I93: 135.81798 | J93: 136.04903 | K93: 136.17673 | L93: 136.24362 | M93: 136.16698 | N93: 136.04956 | O93: 136.00752 | P93: 136.02983 | Q93: 136.03761 | R93: 136.0283 | S93: 136.02759 | T93: 136.0531 | U93: 136.11911 | V93: 136.18365 | W93: 136.1859 | X93: 136.17905 | Y93: 136.15538 | Z93: 136.12061 | AA93: 136.08847 | AB93: 136.05507 | AC93: 135.99182 | AD93: 135.91403 | AE93: 135.82387 | AF93: 135.7079 | AG93: 0
A94: Pipeline Fuel Natural Gas | B94: Transportation Energy Use: Pipeline Fuel Natural Gas: High Zero-Carbon Technology Cost | C94: AEO.2025.HIGHZTC.CNSM_NA_TRN_PIPL_NG_NA_NA_TRLBTU.A | D94: trillion Btu | F94: 924.18793 | G94: 870.45642 | H94: 864.42304 | I94: 836.05847 | J94: 796.98029 | K94: 765.96509 | L94: 728.79102 | M94: 715.77008 | N94: 724.21405 | O94: 717.66333 | P94: 716.69464 | Q94: 718.06836 | R94: 719.89661 | S94: 718.30798 | T94: 719.70441 | U94: 722.53784 | V94: 730.92743 | W94: 740.04352 | X94: 751.18921 | Y94: 764.55859 | Z94: 780.26044 | AA94: 795.53528 | AB94: 807.06793 | AC94: 819.466 | AD94: 833.34381 | AE94: 848.64667 | AF94: 866.41681 | AG94: -0.002
A95: Natural Gas Liquefaction for Export | B95: Transportation Energy Use: Natural Gas for Liquefaction: High Zero-Carbon Technology Cost | C95: AEO.2025.HIGHZTC.CNSM_NA_NMFG_LQFCT_DELE_NA_NA_TRLBTU.A | D95: trillion Btu | F95: 367.99011 | G95: 420.41077 | H95: 447.69333 | I95: 448.49335 | J95: 534.99713 | K95: 595.5882 | L95: 658.57672 | M95: 675.61273 | N95: 693.99408 | O95: 709.17914 | P95: 725.92346 | Q95: 734.3147 | R95: 744.34363 | S95: 751.13715 | T95: 751.13715 | U95: 751.13715 | V95: 752.73523 | W95: 751.13715 | X95: 751.05316 | Y95: 747.79608 | Z95: 745.88696 | AA95: 744.06097 | AB95: 741.29364 | AC95: 741.68195 | AD95: 740.83313 | AE95: 738.8512 | AF95: 741.92645 | AG95: 0.027
A96: Total Consumption | B96: Transportation Energy Use: Total Use: High Zero-Carbon Technology Cost | C96: AEO.2025.HIGHZTC.CNSM_NA_TRN_NA_NA_NA_NA_TRLBTU.A | D96: trillion Btu | F96: 29015.502 | G96: 29089.152 | H96: 29059.262 | I96: 28875.412 | J96: 28703.182 | K96: 28465.1 | L96: 28130.986 | M96: 27766.773 | N96: 27337.027 | O96: 26895.859 | P96: 26505.246 | Q96: 26117.867 | R96: 25722.613 | S96: 25344.094 | T96: 25004.021 | U96: 24684.383 | V96: 24437.947 | W96: 24206.516 | X96: 23990.91 | Y96: 23829.436 | Z96: 23677.633 | AA96: 23574.762 | AB96: 23488.223 | AC96: 23450.389 | AD96: 23370.225 | AE96: 23357.477 | AF96: 23370.049 | AG96: -0.008

Sheet AEO Table 69 Alt Trans
A1: Table 69. Conversion Factors
A2: https://www.eia.gov/outlooks/aeo/data/browser/#/?id=20-AEO2025&cases=alttrnp&sourcekey=0
A3: Mon Dec 22 2025 12:22:16 GMT-0800 (Pacific Standard Time)
A4: Source: U.S. Energy Information Administration
B5: full name | C5: api key | D5: units | E5: 2023 | F5: 2024 | G5: 2025 | H5: 2026 | I5: 2027 | J5: 2028 | K5: 2029 | L5: 2030 | M5: 2031 | N5: 2032 | O5: 2033 | P5: 2034 | Q5: 2035 | R5: 2036 | S5: 2037 | T5: 2038 | U5: 2039 | V5: 2040 | W5: 2041 | X5: 2042 | Y5: 2043 | Z5: 2044 | AA5: 2045 | AB5: 2046 | AC5: 2047 | AD5: 2048 | AE5: 2049 | AF5: 2050 | AG5: Growth (2024-2050)
A6: Petroleum and Other Liquids
A7: (MMBtu per barrel)
A8: Asphalt and Road Oil | B8: Conversion Factors: Petroleum Products: Asphalt and Road Oil: Alternative Transportation | C8: AEO.2025.ALTTRNP.CNF_NA_NA_NA_PET_ARO_NA_MILLBTUPBRL.A | D8: MMBtu/b | F8: 6.636 | G8: 6.636 | H8: 6.636 | I8: 6.636 | J8: 6.636 | K8: 6.636 | L8: 6.636 | M8: 6.636 | N8: 6.636 | O8: 6.636 | P8: 6.636 | Q8: 6.636 | R8: 6.636 | S8: 6.636 | T8: 6.636 | U8: 6.636 | V8: 6.636 | W8: 6.636 | X8: 6.636 | Y8: 6.636 | Z8: 6.636 | AA8: 6.636 | AB8: 6.636 | AC8: 6.636 | AD8: 6.636 | AE8: 6.636 | AF8: 6.636 | AG8: 0
A9: Aviation Gasoline | B9: Conversion Factors: Petroleum Products: Aviation Gasoline: Alternative Transportation | C9: AEO.2025.ALTTRNP.CNF_NA_NA_NA_PET_AVGA_NA_MILLBTUPBRL.A | D9: MMBtu/b | F9: 5.048 | G9: 5.048 | H9: 5.048 | I9: 5.048 | J9: 5.048 | K9: 5.048 | L9: 5.048 | M9: 5.048 | N9: 5.048 | O9: 5.048 | P9: 5.048 | Q9: 5.048 | R9: 5.048 | S9: 5.048 | T9: 5.048 | U9: 5.048 | V9: 5.048 | W9: 5.048 | X9: 5.048 | Y9: 5.048 | Z9: 5.048 | AA9: 5.048 | AB9: 5.048 | AC9: 5.048 | AD9: 5.048 | AE9: 5.048 | AF9: 5.048 | AG9: 0
A10: Biodiesel | B10: Conversion Factors: Liquids: Biodiesel: Alternative Transportation | C10: AEO.2025.ALTTRNP.CNF_NA_NA_NA_BDL_BDL_NA_MILLBTUPBRL.A | D10: MMBtu/b | F10: 5.359 | G10: 5.359 | H10: 5.359 | I10: 5.359 | J10: 5.359 | K10: 5.359 | L10: 5.359 | M10: 5.359 | N10: 5.359 | O10: 5.359 | P10: 5.359 | Q10: 5.359 | R10: 5.359 | S10: 5.359 | T10: 5.359 | U10: 5.359 | V10: 5.359 | W10: 5.359 | X10: 5.359 | Y10: 5.359 | Z10: 5.359 | AA10: 5.359 | AB10: 5.359 | AC10: 5.359 | AD10: 5.359 | AE10: 5.359 | AF10: 5.359 | AG10: 0
A11: Distillate Fuel Oil | B11: Conversion Factors: Petroleum Products: Distillate Fuel Oil: Alternative Transportation | C11: AEO.2025.ALTTRNP.CNF_NA_NA_NA_PET_DFO_NA_MILLBTUPBRL.A | D11: MMBtu/b | F11: 5.825 | G11: 5.825 | H11: 5.825 | I11: 5.825 | J11: 5.825 | K11: 5.825 | L11: 5.825 | M11: 5.825 | N11: 5.825 | O11: 5.825 | P11: 5.825 | Q11: 5.825 | R11: 5.825 | S11: 5.825 | T11: 5.825 | U11: 5.825 | V11: 5.825 | W11: 5.825 | X11: 5.825 | Y11: 5.825 | Z11: 5.825 | AA11: 5.825 | AB11: 5.825 | AC11: 5.825 | AD11: 5.825 | AE11: 5.825 | AF11: 5.825 | AG11: 0
A12: Residential | B12: Conversion Factors: Petroleum Products: Distillate Fuel Oil: Residential: Alternative Transportation | C12: AEO.2025.ALTTRNP.CNF_NA_RESD_NA_NA_DFO_NA_MILLBTUPBRL.A | D12: MMBtu/b | F12: 5.775605 | G12: 5.77577 | H12: 5.776321 | I12: 5.776855 | J12: 5.776533 | K12: 5.776544 | L12: 5.776433 | M12: 5.776507 | N12: 5.776567 | O12: 5.776566 | P12: 5.776496 | Q12: 5.776568 | R12: 5.776513 | S12: 5.776423 | T12: 5.776426 | U12: 5.776364 | V12: 5.776304 | W12: 5.776344 | X12: 5.776352 | Y12: 5.776368 | Z12: 5.776289 | AA12: 5.776322 | AB12: 5.776204 | AC12: 5.776111 | AD12: 5.776162 | AE12: 5.776204 | AF12: 5.776156 | AG12: 0
A13: Commercial | B13: Conversion Factors: Petroleum Products: Distillate Fuel Oil: Commercial: Alternative Transportation | C13: AEO.2025.ALTTRNP.CNF_NA_COMM_NA_NA_DFO_NA_MILLBTUPBRL.A | D13: MMBtu/b | F13: 5.775605 | G13: 5.77577 | H13: 5.776321 | I13: 5.776855 | J13: 5.776533 | K13: 5.776544 | L13: 5.776433 | M13: 5.776507 | N13: 5.776567 | O13: 5.776566 | P13: 5.776496 | Q13: 5.776568 | R13: 5.776513 | S13: 5.776423 | T13: 5.776426 | U13: 5.776364 | V13: 5.776304 | W13: 5.776344 | X13: 5.776352 | Y13: 5.776368 | Z13: 5.776289 | AA13: 5.776322 | AB13: 5.776204 | AC13: 5.776111 | AD13: 5.776162 | AE13: 5.776204 | AF13: 5.776156 | AG13: 0
A14: Transportation | B14: Conversion Factors: Petroleum Products: Distillate Fuel Oil: Transportation: Alternative Transportation | C14: AEO.2025.ALTTRNP.CNF_NA_TRN_NA_NA_DFO_NA_MILLBTUPBRL.A | D14: MMBtu/b | F14: 5.775605 | G14: 5.77577 | H14: 5.776321 | I14: 5.776855 | J14: 5.776533 | K14: 5.776544 | L14: 5.776433 | M14: 5.776507 | N14: 5.776567 | O14: 5.776566 | P14: 5.776496 | Q14: 5.776568 | R14: 5.776513 | S14: 5.776423 | T14: 5.776426 | U14: 5.776364 | V14: 5.776304 | W14: 5.776344 | X14: 5.776352 | Y14: 5.776368 | Z14: 5.776289 | AA14: 5.776322 | AB14: 5.776204 | AC14: 5.776111 | AD14: 5.776162 | AE14: 5.776204 | AF14: 5.776156 | AG14: 0
A15: Industrial | B15: Conversion Factors: Petroleum Products: Distillate Fuel Oil: Industrial: Alternative Transportation | C15: AEO.2025.ALTTRNP.CNF_NA_IDAL_NA_NA_DFO_NA_MILLBTUPBRL.A | D15: MMBtu/b | F15: 5.775605 | G15: 5.77577 | H15: 5.776321 | I15: 5.776855 | J15: 5.776533 | K15: 5.776544 | L15: 5.776433 | M15: 5.776507 | N15: 5.776567 | O15: 5.776566 | P15: 5.776496 | Q15: 5.776568 | R15: 5.776513 | S15: 5.776423 | T15: 5.776426 | U15: 5.776364 | V15: 5.776304 | W15: 5.776344 | X15: 5.776352 | Y15: 5.776368 | Z15: 5.776289 | AA15: 5.776322 | AB15: 5.776204 | AC15: 5.776111 | AD15: 5.776162 | AE15: 5.776204 | AF15: 5.776156 | AG15: 0
A16: Electric Power | B16: Conversion Factors: Petroleum Products: Distillate Fuel Oil: Electric Power: Alternative Transportation | C16: AEO.2025.ALTTRNP.CNF_NA_ELEP_NA_NA_DFO_NA_MILLBTUPBRL.A | D16: MMBtu/b | F16: 5.775605 | G16: 5.77577 | H16: 5.776321 | I16: 5.776855 | J16: 5.776533 | K16: 5.776544 | L16: 5.776433 | M16: 5.776507 | N16: 5.776567 | O16: 5.776566 | P16: 5.776496 | Q16: 5.776568 | R16: 5.776513 | S16: 5.776423 | T16: 5.776426 | U16: 5.776364 | V16: 5.776304 | W16: 5.776344 | X16: 5.776352 | Y16: 5.776368 | Z16: 5.776289 | AA16: 5.776322 | AB16: 5.776204 | AC16: 5.776111 | AD16: 5.776162 | AE16: 5.776204 | AF16: 5.776156 | AG16: 0
A17: Total Distillate | B17: Conversion Factors: Petroleum Products: Distillate Fuel Oil: Total Distillate: Alternative Transportation | C17: AEO.2025.ALTTRNP.CNF_NA_NA_NA_NA_DFO_NA_MILLBTUPBRL.A | D17: MMBtu/b | F17: 5.775605 | G17: 5.77577 | H17: 5.776321 | I17: 5.776855 | J17: 5.776533 | K17: 5.776544 | L17: 5.776433 | M17: 5.776507 | N17: 5.776568 | O17: 5.776566 | P17: 5.776496 | Q17: 5.776568 | R17: 5.776513 | S17: 5.776423 | T17: 5.776426 | U17: 5.776365 | V17: 5.776304 | W17: 5.776344 | X17: 5.776353 | Y17: 5.776369 | Z17: 5.776289 | AA17: 5.776322 | AB17: 5.776204 | AC17: 5.776111 | AD17: 5.776162 | AE17: 5.776203 | AF17: 5.776156 | AG17: 0
A18: Distillate Fuel Oil - Low Sulfur Diesel | B18: Conversion Factors: Petroleum Products: Distillate Fuel Oil - Low Sulfur Diesel: Alternative Transportation | C18: AEO.2025.ALTTRNP.CNF_NA_NA_NA_PET_DFOLSD_NA_MILLBTUPBRL.A | D18: MMBtu/b | F18: 5.817 | G18: 5.817 | H18: 5.817 | I18: 5.817 | J18: 5.817 | K18: 5.817 | L18: 5.817 | M18: 5.817 | N18: 5.817 | O18: 5.817 | P18: 5.817 | Q18: 5.817 | R18: 5.817 | S18: 5.817 | T18: 5.817 | U18: 5.817 | V18: 5.817 | W18: 5.817 | X18: 5.817 | Y18: 5.817 | Z18: 5.817 | AA18: 5.817 | AB18: 5.817 | AC18: 5.817 | AD18: 5.817 | AE18: 5.817 | AF18: 5.817 | AG18: 0
A19: Distillate Fuel Oil - Ultra Low Sulfur Diesel | B19: Conversion Factors: Petroleum Products: Distillate Fuel Oil - Ultra Low Sulfur Diesel: Alternative Transportation | C19: AEO.2025.ALTTRNP.CNF_NA_NA_NA_PET_DFOULSD_NA_MILLBTUPBRL.A | D19: MMBtu/b | F19: 5.77 | G19: 5.77 | H19: 5.77 | I19: 5.77 | J19: 5.77 | K19: 5.77 | L19: 5.77 | M19: 5.77 | N19: 5.77 | O19: 5.77 | P19: 5.77 | Q19: 5.77 | R19: 5.77 | S19: 5.77 | T19: 5.77 | U19: 5.77 | V19: 5.77 | W19: 5.77 | X19: 5.77 | Y19: 5.77 | Z19: 5.77 | AA19: 5.77 | AB19: 5.77 | AC19: 5.77 | AD19: 5.77 | AE19: 5.77 | AF19: 5.77 | AG19: 0
... A38: Petroleum Product Exports | B38: Conversion Factors: Petroleum Products: Petroleum Product Exports: Alternative Transportation | C38: AEO.2025.ALTTRNP.CNF_NA_EXP_NA_PET_PPE_NA_MILLBTUPBRL.A | D38: MMBtu/b | F38: 4.976242 | G38: 5.067001 | H38: 4.864438 | I38: 4.819191 | J38: 4.811352 | K38: 4.814482 | L38: 4.812219 | M38: 4.833379 | N38: 4.838005 | O38: 4.826646 | P38: 4.82654 | Q38: 4.815027 | R38: 4.800422 | S38: 4.799081 | T38: 4.809628 | U38: 4.826902 | V38: 4.833848 | W38: 4.837827 | X38: 4.828389 | Y38: 4.824518 | Z38: 4.818137 | AA38: 4.809884 | AB38: 4.784757 | AC38: 4.783411 | AD38: 4.797252 | AE38: 4.813817 | AF38: 4.828918 | AG38: -0.001
A39: Crude Oil
A40: Production | B40: Conversion Factors: Petroleum Products: Crude Oil: Production: Alternative Transportation | C40: AEO.2025.ALTTRNP.CNF_SUP_PRD_NA_CR_NA_NA_MILLBTUPBRL.A | D40: MMBtu/b | F40: 5.671918 | G40: 5.654488 | H40: 5.65189 | I40: 5.649252 | J40: 5.648753 | K40: 5.649007 | L40: 5.649159 | M40: 5.647911 | N40: 5.646112 | O40: 5.644947 | P40: 5.642896 | Q40: 5.639985 | R40: 5.63804 | S40: 5.637438 | T40: 5.637084 | U40: 5.635664 | V40: 5.633886 | W40: 5.633715 | X40: 5.63414 | Y40: 5.633895 | Z40: 5.632653 | AA40: 5.631763 | AB40: 5.630982 | AC40: 5.630935 | AD40: 5.630385 | AE40: 5.629236 | AF40: 5.62682 | AG40: 0
A41: Imports | B41: Conversion Factors: Petroleum Products: Crude Oil: Imports: Alternative Transportation | C41: AEO.2025.ALTTRNP.CNF_TRAD_IMP_NA_CR_NA_NA_MILLBTUPBRL.A | D41: MMBtu/b | F41: 6.040502 | G41: 6.038667 | H41: 6.057796 | I41: 6.048572 | J41: 6.062667 | K41: 6.063107 | L41: 6.058156 | M41: 6.070844 | N41: 6.082986 | O41: 6.07884 | P41: 6.075884 | Q41: 6.077944 | R41: 6.082214 | S41: 6.095512 | T41: 6.092415 | U41: 6.091714 | V41: 6.086824 | W41: 6.08998 | X41: 6.087101 | Y41: 6.090764 | Z41: 6.090205 | AA41: 6.087873 | AB41: 6.081349 | AC41: 6.080957 | AD41: 6.081051 | AE41: 6.080932 | AF41: 6.079495 | AG41: 0
A42: Exports | B42: Conversion Factors: Petroleum Products: Crude Oil: Exports: Alternative Transportation | C42: AEO.2025.ALTTRNP.CNF_TRAD_EXP_NA_CR_NA_NA_MILLBTUPBRL.A | D42: MMBtu/b | F42: 5.579841 | G42: 5.59565 | H42: 5.589642 | I42: 5.591691 | J42: 5.578902 | K42: 5.579348 | L42: 5.589793 | M42: 5.59424 | N42: 5.594057 | O42: 5.594067 | P42: 5.593933 | Q42: 5.593907 | R42: 5.593852 | S42: 5.593891 | T42: 5.593883 | U42: 5.593896 | V42: 5.593824 | W42: 5.593742 | X42: 5.593582 | Y42: 5.593536 | Z42: 5.59346 | AA42: 5.593442 | AB42: 5.59354 | AC42: 5.593438 | AD42: 5.593375 | AE42: 5.593212 | AF42: 5.593147 | AG42: 0
A43: Natural Gas Plant Liquids | B43: Conversion Factors: Petroleum Products: Natural Gas Plant Liquids: Alternative Transportation | C43: AEO.2025.ALTTRNP.CNF_NA_PRD_NA_PET_NGP_NA_MILLBTUPBRL.A | D43: MMBtu/b | F43: 3.578193 | G43: 3.582565 | H43: 3.552518 | I43: 3.543889 | J43: 3.531261 | K43: 3.525285 | L43: 3.526774 | M43: 3.514866 | N43: 3.517446 | O43: 3.514235 | P43: 3.502977 | Q43: 3.506538 | R43: 3.495856 | S43: 3.494517 | T43: 3.500052 | U43: 3.498715 | V43: 3.49738 | W43: 3.496238 | X43: 3.494922 | Y43: 3.493768 | Z43: 3.492053 | AA43: 3.490428 | AB43: 3.48999 | AC43: 3.489597 | AD43: 3.488538 | AE43: 3.48744 | AF43: 3.486252 | AG43: -0.001
A44: Natural Gas (thousand Btu per cubic foot)
A45: Consumption | B45: Conversion Factors: Natural Gas: Use: Alternative Transportation | C45: AEO.2025.ALTTRNP.CNF_NA_NA_NA_NG_NA_NA_BTUPCUFT.A | D45: thousand Btu/cu ft | F45: 1.036 | G45: 1.036 | H45: 1.036 | I45: 1.036 | J45: 1.036 | K45: 1.036 | L45: 1.036 | M45: 1.036 | N45: 1.036 | O45: 1.036 | P45: 1.036 | Q45: 1.036 | R45: 1.036 | S45: 1.036 | T45: 1.036 | U45: 1.036 | V45: 1.036 | W45: 1.036 | X45: 1.036 | Y45: 1.036 | Z45: 1.036 | AA45: 1.036 | AB45: 1.036 | AC45: 1.036 | AD45: 1.036 | AE45: 1.036 | AF45: 1.036 | AG45: 0
A46: Electric Power Sector | B46: Conversion Factors: Natural Gas: Use: Electric Power Sector: Alternative Transportation | C46: AEO.2025.ALTTRNP.CNF_NA_ELEP_NA_NG_NA_NA_BTUPCUFT.A | D46: thousand Btu/cu ft | F46: 1.033 | G46: 1.033 | H46: 1.033 | I46: 1.033 | J46: 1.033 | K46: 1.033 | L46: 1.033 | M46: 1.033 | N46: 1.033 | O46: 1.033 | P46: 1.033 | Q46: 1.033 | R46: 1.033 | S46: 1.033 | T46: 1.033 | U46: 1.033 | V46: 1.033 | W46: 1.033 | X46: 1.033 | Y46: 1.033 | Z46: 1.033 | AA46: 1.033 | AB46: 1.033 | AC46: 1.033 | AD46: 1.033 | AE46: 1.033 | AF46: 1.033 | AG46: 0
A47: End-use Sector | B47: Conversion Factors: Natural Gas: Use: End-use Sector: Alternative Transportation | C47: AEO.2025.ALTTRNP.CNF_NA_ENUS_NA_NG_NA_NA_BTUPCUFT.A | D47: thousand Btu/cu ft | F47: 1.038 | G47: 1.038 | H47: 1.038 | I47: 1.038 | J47: 1.038 | K47: 1.038 | L47: 1.038 | M47: 1.038 | N47: 1.038 | O47: 1.038 | P47: 1.038 | Q47: 1.038 | R47: 1.038 | S47: 1.038 | T47: 1.038 | U47: 1.038 | V47: 1.038 | W47: 1.038 | X47: 1.038 | Y47: 1.038 | Z47: 1.038 | AA47: 1.038 | AB47: 1.038 | AC47: 1.038 | AD47: 1.038 | AE47: 1.038 | AF47: 1.038 | AG47: 0
A48: Production | B48: Conversion Factors: Natural Gas: Production: Alternative Transportation | C48: AEO.2025.ALTTRNP.CNF_NA_PRD_NA_NG_NA_NA_BTUPCUFT.A | D48: thousand Btu/cu ft | F48: 1.036 | G48: 1.036 | H48: 1.036 | I48: 1.036 | J48: 1.036 | K48: 1.036 | L48: 1.036 | M48: 1.036 | N48: 1.036 | O48: 1.036 | P48: 1.036 | Q48: 1.036 | R48: 1.036 | S48: 1.036 | T48: 1.036 | U48: 1.036 | V48: 1.036 | W48: 1.036 | X48: 1.036 | Y48: 1.036 | Z48: 1.036 | AA48: 1.036 | AB48: 1.036 | AC48: 1.036 | AD48: 1.036 | AE48: 1.036 | AF48: 1.036 | AG48: 0
A49: Imports | B49: Conversion Factors: Natural Gas: Imports: Alternative Transportation | C49: AEO.2025.ALTTRNP.CNF_NA_IMP_NA_NG_NA_NA_BTUPCUFT.A | D49: thousand Btu/cu ft | F49: 1.025 | G49: 1.025 | H49: 1.025 | I49: 1.025 | J49: 1.025 | K49: 1.025 | L49: 1.025 | M49: 1.025 | N49: 1.025 | O49: 1.025 | P49: 1.025 | Q49: 1.025 | R49: 1.025 | S49: 1.025 | T49: 1.025 | U49: 1.025 | V49: 1.025 | W49: 1.025 | X49: 1.025 | Y49: 1.025 | Z49: 1.025 | AA49: 1.025 | AB49: 1.025 | AC49: 1.025 | AD49: 1.025 | AE49: 1.025 | AF49: 1.025 | AG49: 0
A50: Exports | B50: Conversion Factors: Natural Gas: Exports: Alternative Transportation | C50: AEO.2025.ALTTRNP.CNF_NA_EXP_NA_NG_NA_NA_BTUPCUFT.A | D50: thousand Btu/cu ft | F50: 1.009 | G50: 1.009 | H50: 1.009 | I50: 1.009 | J50: 1.009 | K50: 1.009 | L50: 1.009 | M50: 1.009 | N50: 1.009 | O50: 1.009 | P50: 1.009 | Q50: 1.009 | R50: 1.009 | S50: 1.009 | T50: 1.009 | U50: 1.009 | V50: 1.009 | W50: 1.009 | X50: 1.009 | Y50: 1.009 | Z50: 1.009 | AA50: 1.009 | AB50: 1.009 | AC50: 1.009 | AD50: 1.009 | AE50: 1.009 | AF50: 1.009 | AG50: 0
A51: Compressed/Liquefied Natural Gas | B51: Conversion Factors: Natural Gas: Compressed/Liquefied Natural Gas: Alternative Transportation | C51: AEO.2025.ALTTRNP.CNF_NA_NA_NA_CMPORLQFNG_NA_NA_BTUPCUFT.A | D51: thousand Btu/cu ft | F51: 0.96 | G51: 0.96 | H51: 0.96 | I51: 0.96 | J51: 0.96 | K51: 0.96 | L51: 0.96 | M51: 0.96 | N51: 0.96 | O51: 0.96 | P51: 0.96 | Q51: 0.96 | R51: 0.96 | S51: 0.96 | T51: 0.96 | U51: 0.96 | V51: 0.96 | W51: 0.96 | X51: 0.96 | Y51: 0.96 | Z51: 0.96 | AA51: 0.96 | AB51: 0.96 | AC51: 0.96 | AD51: 0.96 | AE51: 0.96 | AF51: 0.96 | AG51: 0
A52: Coal (MMBtu per short ton)
A53: Production | B53: Conversion Factors: Coal: Production: Alternative Transportation | C53: AEO.2025.ALTTRNP.CNF_NA_NA_NA_PRD_NA_NA_MILLBTUPTON.A | D53: MMBtu/ton | F53: 21.115574 | G53: 21.038376 | H53: 21.114906 | I53: 21.532087 | J53: 21.674246 | K53: 21.752199 | L53: 22.250534 | M53: 22.31806 | N53: 24.293774 | O53: 24.271925 | P53: 24.36586 | Q53: 24.671024 | R53: 24.742714 | S53: 24.83272 | T53: 24.546293 | U53: 25.168102 | V53: 25.294571 | W53: 25.491381 | X53: 25.510672 | Y53: 25.473606 | Z53: 25.545614 | AA53: 25.494932 | AB53: 25.811268 | AC53: 25.688904 | AD53: 25.626335 | AE53: 25.617619 | AF53: 25.735912 | AG53: 0.008
A54: East of the Mississippi | B54: Conversion Factors: Coal: Production: East of the Mississippi: Alternative Transportation | C54: AEO.2025.ALTTRNP.CNF_NA_NA_NA_PRD_NA_EOM_MILLBTUPTON.A | D54: MMBtu/ton | F54: 24.224154 | G54: 24.311584 | H54: 24.096188 | I54: 24.03693 | J54: 24.164139 | K54: 24.050213 | L54: 24.11488 | M54: 24.141878 | N54: 26.863497 | O54: 26.865271 | P54: 26.709299 | Q54: 26.769547 | R54: 26.763245 | S54: 26.754742 | T54: 26.820023 | U54: 26.787138 | V54: 26.773607 | W54: 26.723829 | X54: 26.705944 | Y54: 26.656021 | Z54: 26.638067 | AA54: 26.612169 | AB54: 26.644041 | AC54: 26.64337 | AD54: 26.657051 | AE54: 26.685377 | AF54: 26.705746 | AG54: 0.004
A55: West of the Mississippi | B55: Conversion Factors: Coal: Production: West of the Mississippi: Alternative Transportation | C55: AEO.2025.ALTTRNP.CNF_NA_NA_NA_PRD_NA_WOM_MILLBTUPTON.A | D55: MMBtu/ton | F55: 17.676613 | G55: 17.635162 | H55: 17.57864 | I55: 17.936699 | J55: 17.939032 | K55: 18.300385 | L55: 18.582584 | M55: 18.614046 | N55: 19.335278 | O55: 19.240191 | P55: 17.758957 | Q55: 17.801657 | R55: 17.832256 | S55: 17.845358 | T55: 17.721239 | U55: 17.862076 | V55: 17.905554 | W55: 18.002266 | X55: 18.018427 | Y55: 18.018173 | Z55: 18.066101 | AA55: 18.040119 | AB55: 18.271677 | AC55: 18.337481 | AD55: 18.298412 | AE55: 18.29674 | AF55: 18.422411 | AG55: 0.002
A56: Consumption | B56: Conversion Factors: Coal: Use: Alternative Transportation | C56: AEO.2025.ALTTRNP.CNF_NA_NA_NA_CNSM_NA_NA_MILLBTUPTON.A | D56: MMBtu/ton | F56: 19.940289 | G56: 19.973602 | H56: 19.830999 | I56: 19.935202 | J56: 19.764484 | K56: 19.87011 | L56: 20.262617 | M56: 20.367182 | N56: 22.370853 | O56: 22.354103 | P56: 22.417408 | Q56: 22.383223 | R56: 22.555441 | S56: 22.630484 | T56: 22.757643 | U56: 23.438261 | V56: 23.415792 | W56: 23.387712 | X56: 23.388384 | Y56: 23.364775 | Z56: 23.524065 | AA56: 23.487206 | AB56: 24.318295 | AC56: 24.279192 | AD56: 24.249689 | AE56: 24.378206 | AF56: 24.406179 | AG56: 0.008
