Workbook
Name billion_kw_to_MW: About!$B$30
Name CH4_to_CO2e: '[1]Cross-Page Data'!$C$12
Name cpi_2010to2012: #REF!
Name cpi_2013to2012: #REF!
Name cpi_2014to2012: #REF!
Name cpi_2016to2012: #REF!
Name dollars_2020_2012: [2]About!$A$113
Name dollars_2022_2012: [2]About!$A$111
Name gigwatt_to_megawatt: About!$B$31
Name gigwatts_to_megawatts: [3]About!$A$31
Name N2O_to_CO2e: '[1]Cross-Page Data'!$C$13
Name Percent_rural: About!$A$28
Name Percent_Urban: About!$A$27
Name unit_conv: [4]About!$A$123

Sheet About
A1: CiDESCTY Change in Distributed Electricity Source Capacities This Year
A3: Sources: | B3: Distributed Generation and Capacity - 2021-2050
B4: Energy Information Administration
B5: 2023, 2025
B6: Annual Energy Outlook 2023
B7: Annual Energy Outlook 2025
B8: Scenario: High zero-carbon technology cost
B9: https://www.eia.gov/outlooks/aeo/tables_side_xls.php
B10: Table 21 and Table 22
B12: Urban vs. Rural Residential Households
B13: Energy Information Administration
B14: 2020
B15: Residential Energy Consumption Survey (RECS)
B16: https://www.eia.gov/consumption/residential/data/2020/?src=%E2%80%B9%20Consumption%20%20%20%20%20%20Residential%20Energy%20Consumption%20Survey%20(RECS)-f1
B17: https://www.eia.gov/consumption/residential/data/2020/hc/xls/HC%202.1.xlsx
B18: Table HC2.1
A20: Notes
A21: This file can be used to test an alternate distributed solar additions schedule.
A22: We use it to incorporate additional distributed solar capacity associated with the
A23: Solar for All campaign of the Inflation Reduction Act.
A26: Urban Rural Split
A27: ='RECS HC2.1'!B24/SUM('RECS HC2.1'!B24,'RECS HC2.1'!B27) -> 0.81308184 | B27: Urban
A28: ='RECS HC2.1'!B27/SUM('RECS HC2.1'!B24,'RECS HC2.1'!B27) -> 0.18691816 | B28: Rural
A30: Conversion from billion kilowatthours to megawatthours | B30: =10^6 -> 1000000
A31: Conversion from gigawatts to megawatts | B31: 1000
A33: Data centers | B33: Data centers are a separate building type. There are no policy-mandated changes in distributed capacity at data centers, so their export tab is zero.

Sheet Source Data>

Sheet AEO23_Table_21._Residential
A1: Table 21. Residential Sector Equipment Stock and Efficiency, and Distributed Generation
A2: https://www.eia.gov/outlooks/aeo/data/browser/#/?id=30-AEO2023&sourcekey=0
A3: Sun May 04 2025 20:12:23 GMT-0700 (Pacific Daylight Time)
A4: Source: U.S. Energy Information Administration
B5: full name | C5: api key | D5: units | E5: 2021 | F5: 2022 | G5: 2023 | H5: 2024 | I5: 2025 | J5: 2026 | K5: 2027 | L5: 2028 | M5: 2029 | N5: 2030 | O5: 2031 | P5: 2032 | Q5: 2033 | R5: 2034 | S5: 2035 | T5: 2036 | U5: 2037 | V5: 2038 | W5: 2039 | X5: 2040 | Y5: 2041 | Z5: 2042 | AA5: 2043 | AB5: 2044 | AC5: 2045 | AD5: 2046 | AE5: 2047 | AF5: 2048 | AG5: 2049 | AH5: 2050 | AI5: Growth (2022-2050)
A6: Equipment Stock (million units)
A7: Main Space Heaters
A8: Electric Heat Pumps | B8: Residential Equipment: Equipment Stock: Main Space Heaters: Electric Heat Pumps: Reference case | C8: AEO.2023.REF2023.EQNR_STK_RESD_MSHR_EHP_NA_NA_MILL.A | D8: millions | F8: 13.315578 | G8: 13.570746 | H8: 13.822851 | I8: 14.081017 | J8: 14.338543 | K8: 14.596683 | L8: 14.856007 | M8: 15.113205 | N8: 15.364176 | O8: 15.610795 | P8: 15.855648 | Q8: 16.095499 | R8: 16.328896 | S8: 16.560501 | T8: 16.79364 | U8: 17.026976 | V8: 17.2586 | W8: 17.487827 | X8: 17.718792 | Y8: 17.949728 | Z8: 18.178337 | AA8: 18.406141 | AB8: 18.633221 | AC8: 18.859972 | AD8: 19.086086 | AE8: 19.312725 | AF8: 19.538191 | AG8: 19.762444 | AH8: 19.985924 | AI8: 0.015
A9: Electric Other | B9: Residential Equipment: Equipment Stock: Main Space Heaters: Electric Other: Reference case | C9: AEO.2023.REF2023.EQNR_STK_RESD_MSHR_ELO_NA_NA_MILL.A | D9: millions | F9: 31.010973 | G9: 31.191193 | H9: 31.367004 | I9: 31.545937 | J9: 31.728054 | K9: 31.914146 | L9: 32.103336 | M9: 32.291443 | N9: 32.472885 | O9: 32.650379 | P9: 32.828148 | Q9: 33.003277 | R9: 33.172894 | S9: 33.339802 | T9: 33.508488 | U9: 33.676701 | V9: 33.844833 | W9: 34.012619 | X9: 34.183968 | Y9: 34.355839 | Z9: 34.525658 | AA9: 34.694195 | AB9: 34.861164 | AC9: 35.026974 | AD9: 35.191212 | AE9: 35.356567 | AF9: 35.521111 | AG9: 35.685036 | AH9: 35.849113 | AI9: 0.005
A10: Natural Gas Heat Pumps | B10: Residential Equipment: Equipment Stock: Main Space Heaters: Natural Gas Heat Pumps: Reference case | C10: AEO.2023.REF2023.EQNR_STK_RESD_MSHR_NHU_NA_NA_MILL.A | D10: millions | F10: 1.321198 | G10: 1.319243 | H10: 1.317296 | I10: 1.315357 | J10: 1.313426 | K10: 1.311503 | L10: 1.309587 | M10: 1.307679 | N10: 1.30578 | O10: 1.303886 | P10: 1.302001 | Q10: 1.300122 | R10: 1.298251 | S10: 1.296387 | T10: 1.29453 | U10: 1.29268 | V10: 1.290837 | W10: 1.289001 | X10: 1.287171 | Y10: 1.285348 | Z10: 1.283531 | AA10: 1.281721 | AB10: 1.279918 | AC10: 1.27812 | AD10: 1.27633 | AE10: 1.274545 | AF10: 1.272766 | AG10: 1.270993 | AH10: 1.269227 | AI10: -0.001
A11: Natural Gas Other | B11: Residential Equipment: Equipment Stock: Main Space Heaters: Natural Gas Other: Reference case | C11: AEO.2023.REF2023.EQNR_STK_RESD_MSHR_NGO_NA_NA_MILL.A | D11: millions | F11: 62.066788 | G11: 62.86874 | H11: 63.678131 | I11: 64.503296 | J11: 65.32177 | K11: 66.136948 | L11: 66.951584 | M11: 67.756226 | N11: 68.541176 | O11: 69.310356 | P11: 70.070587 | Q11: 70.812531 | R11: 71.531357 | S11: 72.239449 | T11: 72.944847 | U11: 73.64325 | V11: 74.338699 | W11: 75.029205 | X11: 75.724937 | Y11: 76.420006 | Z11: 77.106728 | AA11: 77.789856 | AB11: 78.469795 | AC11: 79.146408 | AD11: 79.816353 | AE11: 80.482452 | AF11: 81.140999 | AG11: 81.790314 | AH11: 82.431442 | AI11: 0.01
A12: Distillate Fuel Oil | B12: Residential Equipment: Equipment Stock: Main Space Heaters: Distillate Fuel Oil: Reference case | C12: AEO.2023.REF2023.EQNR_STK_RESD_MSHR_DFO_NA_NA_MILL.A | D12: millions | F12: 5.454962 | G12: 5.405786 | H12: 5.357452 | I12: 5.309505 | J12: 5.261883 | K12: 5.215992 | L12: 5.1721 | M12: 5.130489 | N12: 5.09118 | O12: 5.053465 | P12: 5.01742 | Q12: 4.982733 | R12: 4.949076 | S12: 4.916341 | T12: 4.884336 | U12: 4.853684 | V12: 4.824137 | W12: 4.795379 | X12: 4.767413 | Y12: 4.739604 | Z12: 4.710267 | AA12: 4.679461 | AB12: 4.647407 | AC12: 4.614363 | AD12: 4.580481 | AE12: 4.545176 | AF12: 4.508846 | AG12: 4.471894 | AH12: 4.43473 | AI12: -0.007
A13: Propane | B13: Residential Equipment: Equipment Stock: Main Space Heaters: Propane: Reference case | C13: AEO.2023.REF2023.EQNR_STK_RESD_MSHR_PROP_NA_NA_MILL.A | D13: millions | F13: 5.292898 | G13: 5.283106 | H13: 5.272407 | I13: 5.26181 | J13: 5.251935 | K13: 5.245102 | L13: 5.240705 | M13: 5.238044 | N13: 5.235492 | O13: 5.233078 | P13: 5.23132 | Q13: 5.229799 | R13: 5.228008 | S13: 5.225996 | T13: 5.224109 | U13: 5.221475 | V13: 5.218017 | W13: 5.213948 | X13: 5.210232 | Y13: 5.207039 | Z13: 5.202483 | AA13: 5.196987 | AB13: 5.190924 | AC13: 5.184589 | AD13: 5.177998 | AE13: 5.171618 | AF13: 5.165352 | AG13: 5.159314 | AH13: 5.153788 | AI13: -0.001
A14: Kerosene | B14: Residential Equipment: Equipment Stock: Main Space Heaters: Kerosene: Reference case | C14: AEO.2023.REF2023.EQNR_STK_RESD_MSHR_KRS_NA_NA_MILL.A | D14: millions | F14: 0.003901 | G14: 0.00709 | H14: 0.009997 | I14: 0.012783 | J14: 0.015616 | K14: 0.01846 | L14: 0.021282 | M14: 0.024013 | N14: 0.026531 | O14: 0.028897 | P14: 0.031215 | Q14: 0.033522 | R14: 0.035761 | S14: 0.037892 | T14: 0.039987 | U14: 0.041972 | V14: 0.043841 | W14: 0.045631 | X14: 0.047425 | Y14: 0.049189 | Z14: 0.050905 | AA14: 0.052555 | AB14: 0.05413 | AC14: 0.055631 | AD14: 0.057045 | AE14: 0.058409 | AF14: 0.059716 | AG14: 0.060958 | AH14: 0.062151 | AI14: 0.104
A15: Wood Stoves | B15: Residential Equipment: Equipment Stock: Main Space Heaters: Wood Stoves: Reference case | C15: AEO.2023.REF2023.EQNR_STK_RESD_MSHR_WDS_NA_NA_MILL.A | D15: millions | F15: 3.297239 | G15: 3.265615 | H15: 3.237753 | I15: 3.211385 | J15: 3.186906 | K15: 3.163538 | L15: 3.140653 | M15: 3.117714 | N15: 3.094777 | O15: 3.071414 | P15: 3.047546 | Q15: 3.023053 | R15: 2.997959 | S15: 2.972195 | T15: 2.94591 | U15: 2.920416 | V15: 2.895695 | W15: 2.871994 | X15: 2.848303 | Y15: 2.825649 | Z15: 2.804177 | AA15: 2.783932 | AB15: 2.765052 | AC15: 2.747301 | AD15: 2.730428 | AE15: 2.713511 | AF15: 2.69659 | AG15: 2.679538 | AH15: 2.662318 | AI15: -0.008
A16: Geothermal Heat Pumps | B16: Residential Equipment: Equipment Stock: Main Space Heaters: Geothermal Heat Pumps: Reference case | C16: AEO.2023.REF2023.EQNR_STK_RESD_MSHR_GEHP_NA_NA_MILL.A | D16: millions | F16: 0.716036 | G16: 0.778759 | H16: 0.840134 | I16: 0.901506 | J16: 0.960455 | K16: 1.018172 | L16: 1.07555 | M16: 1.132757 | N16: 1.189252 | O16: 1.245527 | P16: 1.301907 | Q16: 1.358019 | R16: 1.41364 | S16: 1.469565 | T16: 1.525942 | U16: 1.581249 | V16: 1.635567 | W16: 1.68851 | X16: 1.741698 | Y16: 1.793962 | Z16: 1.844503 | AA16: 1.893613 | AB16: 1.941229 | AC16: 1.987597 | AD16: 2.03283 | AE16: 2.077793 | AF16: 2.122324 | AG16: 2.166456 | AH16: 2.210309 | AI16: 0.041
A17: Total | B17: Residential Equipment: Equipment Stock: Main Space Heaters: Total: Reference case | C17: AEO.2023.REF2023.EQNR_STK_RESD_MSHR_TOT_NA_NA_MILL.A | D17: millions | F17: 122.47958 | G17: 123.69027 | H17: 124.90303 | I17: 126.14259 | J17: 127.3786 | K17: 128.62054 | L17: 129.87079 | M17: 131.11156 | N17: 132.32124 | O17: 133.5078 | P17: 134.68579 | Q17: 135.83856 | R17: 136.95584 | S17: 138.05812 | T17: 139.16179 | U17: 140.25841 | V17: 141.35023 | W17: 142.4341 | X17: 143.52994 | Y17: 144.62639 | Z17: 145.70659 | AA17: 146.77846 | AB17: 147.8428 | AC17: 148.90096 | AD17: 149.94875 | AE17: 150.9928 | AF17: 152.02593 | AG17: 153.04695 | AH17: 154.05901 | AI17: 0.008
A18: Space Cooling (million units)
A19: Electric Heat Pumps | B19: Residential Equipment: Equipment Stock: Space Cooling: Electric Heat Pumps: Reference case | C19: AEO.2023.REF2023.EQNR_STK_RESD_SPC_EHP_NA_NA_MILL.A | D19: millions | F19: 13.315581 | G19: 13.570746 | H19: 13.82285 | I19: 14.081021 | J19: 14.338547 | K19: 14.596686 | L19: 14.856006 | M19: 15.113201 | N19: 15.364179 | O19: 15.610802 | P19: 15.855643 | Q19: 16.095505 | R19: 16.328897 | S19: 16.560503 | T19: 16.793638 | U19: 17.026976 | V19: 17.258608 | W19: 17.487829 | X19: 17.718796 | Y19: 17.949732 | Z19: 18.178335 | AA19: 18.406145 | AB19: 18.633224 | AC19: 18.859974 | AD19: 19.086088 | AE19: 19.312731 | AF19: 19.538191 | AG19: 19.762447 | AH19: 19.985924 | AI19: 0.015
A20: Natural Gas Heat Pumps | B20: Residential Equipment: Equipment Stock: Space Cooling: Natural Gas Heat Pumps: Reference case | C20: AEO.2023.REF2023.EQNR_STK_RESD_SPC_NHU_NA_NA_MILL.A | D20: millions | F20: 1.321198 | G20: 1.319242 | H20: 1.317296 | I20: 1.315357 | J20: 1.313426 | K20: 1.311503 | L20: 1.309587 | M20: 1.307679 | N20: 1.305779 | O20: 1.303886 | P20: 1.302001 | Q20: 1.300122 | R20: 1.298251 | S20: 1.296387 | T20: 1.29453 | U20: 1.29268 | V20: 1.290837 | W20: 1.289001 | X20: 1.287171 | Y20: 1.285348 | Z20: 1.283531 | AA20: 1.281721 | AB20: 1.279918 | AC20: 1.27812 | AD20: 1.276329 | AE20: 1.274545 | AF20: 1.272766 | AG20: 1.270993 | AH20: 1.269227 | AI20: -0.001
A21: Geothermal Heat Pumps | B21: Residential Equipment: Equipment Stock: Space Cooling: Geothermal Heat Pumps: Reference case | C21: AEO.2023.REF2023.EQNR_STK_RESD_SPC_GEHP_NA_NA_MILL.A | D21: millions | F21: 0.716036 | G21: 0.778759 | H21: 0.840134 | I21: 0.901506 | J21: 0.960454 | K21: 1.018172 | L21: 1.075549 | M21: 1.132756 | N21: 1.189252 | O21: 1.245526 | P21: 1.301908 | Q21: 1.35802 | R21: 1.41364 | S21: 1.469566 | T21: 1.525942 | U21: 1.581248 | V21: 1.635567 | W21: 1.688511 | X21: 1.741697 | Y21: 1.793962 | Z21: 1.844503 | AA21: 1.893613 | AB21: 1.941229 | AC21: 1.987596 | AD21: 2.03283 | AE21: 2.077794 | AF21: 2.122325 | AG21: 2.166455 | AH21: 2.210309 | AI21: 0.041
A22: Central Air Conditioners | B22: Residential Equipment: Equipment Stock: Space Cooling: Central Air Conditioners: Reference case | C22: AEO.2023.REF2023.EQNR_STK_RESD_SPC_CAC_NA_NA_MILL.A | D22: millions | F22: 65.952873 | G22: 67.531487 | H22: 69.112846 | I22: 70.710129 | J22: 72.30307 | K22: 73.89785 | L22: 75.496254 | M22: 77.087234 | N22: 78.657112 | O22: 80.210655 | P22: 81.756866 | Q22: 83.285324 | R22: 84.789772 | S22: 86.282951 | T22: 87.774986 | U22: 89.260513 | V22: 90.740982 | W22: 92.214447 | X22: 93.693588 | Y22: 95.171677 | Z22: 96.63768 | AA22: 98.096832 | AB22: 99.549744 | AC22: 100.99702 | AD22: 102.43625 | AE22: 103.87109 | AF22: 105.29724 | AG22: 106.71379 | AH22: 108.12277 | AI22: 0.018
A23: Room Air Conditioners | B23: Residential Equipment: Equipment Stock: Space Cooling: Room Air Conditioners: Reference case | C23: AEO.2023.REF2023.EQNR_STK_RESD_SPC_RAC_NA_NA_MILL.A | D23: millions | F23: 58.086197 | G23: 58.099602 | H23: 58.113243 | I23: 58.130096 | J23: 58.148983 | K23: 58.170322 | L23: 58.193909 | M23: 58.21701 | N23: 58.235847 | O23: 58.251923 | P23: 58.267937 | Q23: 58.282757 | R23: 58.294533 | S23: 58.304741 | T23: 58.315868 | U23: 58.326084 | V23: 58.335472 | W23: 58.3442 | X23: 58.355373 | Y23: 58.36763 | Z23: 58.379017 | AA23: 58.390129 | AB23: 58.400814 | AC23: 58.41119 | AD23: 58.42065 | AE23: 58.430313 | AF23: 58.439327 | AG23: 58.447399 | AH23: 58.45509 | AI23: 0
A24: Total | B24: Residential Equipment: Equipment Stock: Space Cooling: Total: Reference case | C24: AEO.2023.REF2023.EQNR_STK_RESD_SPC_TOT_NA_NA_MILL.A | D24: millions | F24: 139.39188 | G24: 141.29984 | H24: 143.20636 | I24: 145.13811 | J24: 147.06448 | K24: 148.99454 | L24: 150.93131 | M24: 152.85788 | N24: 154.75217 | O24: 156.62279 | P24: 158.48434 | Q24: 160.32173 | R24: 162.12509 | S24: 163.91415 | T24: 165.70497 | U24: 167.4875 | V24: 169.26147 | W24: 171.02399 | X24: 172.79663 | Y24: 174.56834 | Z24: 176.32306 | AA24: 178.06845 | AB24: 179.80493 | AC24: 181.53391 | AD24: 183.25215 | AE24: 184.96646 | AF24: 186.66986 | AG24: 188.36108 | AH24: 190.04332 | AI24: 0.011
A25: Water Heaters (million units)
A26: Electric | B26: Residential Equipment: Equipment Stock: Water Heaters: Electric: Reference case | C26: AEO.2023.REF2023.EQNR_STK_RESD_WHT_ELE_NA_NA_MILL.A | D26: millions | F26: 60.580669 | G26: 60.983253 | H26: 61.337627 | I26: 61.675991 | J26: 61.982437 | K26: 62.286163 | L26: 62.581848 | M26: 62.861568 | N26: 63.111282 | O26: 63.367752 | P26: 63.636322 | Q26: 63.985218 | R26: 64.382027 | S26: 64.897079 | T26: 65.400185 | U26: 65.903778 | V26: 66.40728 | W26: 66.89624 | X26: 67.381805 | Y26: 67.859169 | Z26: 68.323227 | AA26: 68.776733 | AB26: 69.220825 | AC26: 69.659088 | AD26: 70.099632 | AE26: 70.538925 | AF26: 70.972908 | AG26: 71.406891 | AH26: 71.842628 | AI26: 0.006
A27: Natural Gas | B27: Residential Equipment: Equipment Stock: Water Heaters: Natural Gas: Reference case | C27: AEO.2023.REF2023.EQNR_STK_RESD_WHT_NG_NA_NA_MILL.A | D27: millions | F27: 61.25243 | G27: 61.855328 | H27: 62.501675 | I27: 63.183994 | J27: 63.881008 | K27: 64.589165 | L27: 65.313995 | M27: 66.041458 | N27: 66.761238 | O27: 67.455582 | P27: 68.133423 | Q27: 68.80352 | R27: 69.458298 | S27: 70.120712 | T27: 70.7752 | U27: 71.421005 | V27: 72.060173 | W27: 72.70253 | X27: 73.355804 | Y27: 74.013893 | Z27: 74.66552 | AA27: 75.31604 | AB27: 75.965561 | AC27: 76.611816 | AD27: 77.243378 | AE27: 77.870567 | AF27: 78.490524 | AG27: 79.097527 | AH27: 79.692604 | AI27: 0.009
A28: Distillate Fuel Oil | B28: Residential Equipment: Equipment Stock: Water Heaters: Distillate Fuel Oil: Reference case | C28: AEO.2023.REF2023.EQNR_STK_RESD_WHT_DFO_NA_NA_MILL.A | D28: millions | F28: 2.542532 | G28: 2.484457 | H28: 2.431864 | I28: 2.385705 | J28: 2.343567 | K28: 2.305742 | L28: 2.272055 | M28: 2.242364 | N28: 2.216697 | O28: 2.188768 | P28: 2.159277 | Q28: 2.128753 | R28: 2.098122 | S28: 2.066852 | T28: 2.036216 | U28: 2.006083 | V28: 1.976985 | W28: 1.948926 | X28: 1.922033 | Y28: 1.896241 | Z28: 1.871523 | AA28: 1.847718 | AB28: 1.824666 | AC28: 1.80236 | AD28: 1.780556 | AE28: 1.759241 | AF28: 1.738419 | AG28: 1.717659 | AH28: 1.697292 | AI28: -0.014
A29: Propane | B29: Residential Equipment: Equipment Stock: Water Heaters: Propane: Reference case | C29: AEO.2023.REF2023.EQNR_STK_RESD_WHT_PROP_NA_NA_MILL.A | D29: millions | F29: 3.944016 | G29: 3.844217 | H29: 3.754283 | I29: 3.67485 | J29: 3.605606 | K29: 3.545926 | L29: 3.495781 | M29: 3.454613 | N29: 3.421728 | O29: 3.383463 | P29: 3.341427 | Q29: 3.296932 | R29: 3.250626 | S29: 3.203295 | T29: 3.156687 | U29: 3.1109 | V29: 3.066498 | W29: 3.024202 | X29: 2.984899 | Y29: 2.94847 | Z29: 2.914493 | AA29: 2.882922 | AB29: 2.853478 | AC29: 2.825944 | AD29: 2.799708 | AE29: 2.775011 | AF29: 2.751561 | AG29: 2.729004 | AH29: 2.707524 | AI29: -0.013
A30: Solar Thermal | B30: Residential Equipment: Equipment Stock: Water Heaters: Solar Thermal: Reference case | C30: AEO.2023.REF2023.EQNR_STK_RESD_WHT_SLR_THERM_NA_MILL.A | D30: millions | F30: 2.232774 | G30: 2.576883 | H30: 2.912508 | I30: 3.238233 | J30: 3.563558 | K30: 3.872656 | L30: 4.167933 | M30: 4.454165 | N30: 4.734822 | O30: 5.018878 | P30: 5.304139 | Q30: 5.495253 | R30: 5.620392 | S30: 5.606394 | T30: 5.612399 | U30: 5.618275 | V30: 5.623932 | W30: 5.629901 | X30: 5.636178 | Y30: 5.642672 | Z30: 5.649299 | AA30: 5.656049 | AB30: 5.662947 | AC30: 5.670003 | AD30: 5.677579 | AE30: 5.685092 | AF30: 5.692599 | AG30: 5.700052 | AH30: 5.707356 | AI30: 0.034
A31: Total | B31: Residential Equipment: Equipment Stock: Water Heaters: Total: Reference case | C31: AEO.2023.REF2023.EQNR_STK_RESD_WHT_TOT_NA_NA_MILL.A | D31: millions | F31: 130.55243 | G31: 131.74414 | H31: 132.93796 | I31: 134.15877 | J31: 135.37617 | K31: 136.59966 | L31: 137.8316 | M31: 139.05418 | N31: 140.24576 | O31: 141.41444 | P31: 142.57459 | Q31: 143.70969 | R31: 144.80948 | S31: 145.89433 | T31: 146.98068 | U31: 148.06004 | V31: 149.13487 | W31: 150.2018 | X31: 151.28072 | Y31: 152.36044 | Z31: 153.42404 | AA31: 154.47946 | AB31: 155.52748 | AC31: 156.5692 | AD31: 157.60088 | AE31: 158.62883 | AF31: 159.64601 | AG31: 160.65115 | AH31: 161.6474 | AI31: 0.008
A32: Cooking Equipment (million units)
A33: Electric | B33: Residential Equipment: Equipment Stock: Cooking Equipment: Electric: Reference case | C33: AEO.2023.REF2023.EQNR_STK_RESD_CER_ELE_NA_NA_MILL.A | D33: millions | F33: 98.268684 | G33: 98.918465 | H33: 99.554741 | I33: 100.19855 | J33: 100.82862 | K33: 101.44907 | L33: 102.06017 | M33: 102.62416 | N33: 103.12352 | O33: 103.55598 | P33: 103.92822 | Q33: 104.31216 | R33: 104.7261 | S33: 105.18793 | T33: 105.71883 | U33: 106.31783 | V33: 106.90277 | W33: 107.47091 | X33: 108.03522 | Y33: 108.58673 | Z33: 109.11317 | AA33: 109.61954 | AB33: 110.10674 | AC33: 110.57737 | AD33: 111.03217 | AE33: 111.47945 | AF33: 111.91858 | AG33: 112.35443 | AH33: 112.79388 | AI33: 0.005
A34: Natural Gas | B34: Residential Equipment: Equipment Stock: Cooking Equipment: Natural Gas: Reference case | C34: AEO.2023.REF2023.EQNR_STK_RESD_CER_NG_NA_NA_MILL.A | D34: millions | F34: 48.883518 | G34: 49.409149 | H34: 49.952679 | I34: 50.517521 | J34: 51.095181 | K34: 51.691891 | L34: 52.309582 | M34: 52.968777 | N34: 53.66621 | O34: 54.41114 | P34: 55.209866 | Q34: 55.967617 | R34: 56.656403 | S34: 57.278698 | T34: 57.828838 | U34: 58.300526 | V34: 58.784473 | W34: 59.280293 | X34: 59.794044 | Y34: 60.32373 | Z34: 60.864475 | AA34: 61.418552 | AB34: 61.984871 | AC34: 62.561092 | AD34: 63.141663 | AE34: 63.723984 | AF34: 64.30146 | AG34: 64.868683 | AH34: 65.422531 | AI34: 0.01
A35: Propane | B35: Residential Equipment: Equipment Stock: Cooking Equipment: Propane: Reference case | C35: AEO.2023.REF2023.EQNR_STK_RESD_CER_PROP_NA_NA_MILL.A | D35: millions | F35: 7.251641 | G35: 7.235342 | H35: 7.217015 | I35: 7.196943 | J35: 7.174531 | K35: 7.148907 | L35: 7.120317 | M35: 7.088118 | N35: 7.051433 | O35: 7.011372 | P35: 6.969453 | Q35: 6.931829 | R35: 6.898018 | S35: 6.868111 | T35: 6.842745 | U35: 6.821068 | V35: 6.79666 | W35: 6.769514 | X35: 6.740311 | Y35: 6.708988 | Z35: 6.67562 | AA35: 6.640938 | AB35: 6.605863 | AC35: 6.571425 | AD35: 6.53839 | AE35: 6.507637 | AF35: 6.479108 | AG35: 6.452258 | AH35: 6.426418 | AI35: -0.004
A36: Total | B36: Residential Equipment: Equipment Stock: Cooking Equipment: Total: Reference case | C36: AEO.2023.REF2023.EQNR_STK_RESD_CER_TOT_NA_NA_MILL.A | D36: millions | F36: 154.40385 | G36: 155.56294 | H36: 156.72443 | I36: 157.91303 | J36: 159.09833 | K36: 160.28987 | L36: 161.49007 | M36: 162.68106 | N36: 163.84117 | O36: 164.97849 | P36: 166.10754 | Q36: 167.21159 | R36: 168.28052 | S36: 169.33475 | T36: 170.39041 | U36: 171.43942 | V36: 172.4839 | W36: 173.52072 | X36: 174.56958 | Y36: 175.61945 | Z36: 176.65326 | AA36: 177.67902 | AB36: 178.69748 | AC36: 179.70989 | AD36: 180.71222 | AE36: 181.71106 | AF36: 182.69914 | AG36: 183.67537 | AH36: 184.64282 | AI36: 0.006
A37: Clothes Dryers (million units)
A38: Electric | B38: Residential Equipment: Equipment Stock: Clothes Dryers: Electric: Reference case | C38: AEO.2023.REF2023.EQNR_STK_RESD_CDR_ELE_NA_NA_MILL.A | D38: millions | F38: 86.664726 | G38: 88.297852 | H38: 89.928329 | I38: 91.593002 | J38: 93.232185 | K38: 94.86705 | L38: 96.512413 | M38: 98.151497 | N38: 99.765617 | O38: 101.36159 | P38: 102.95294 | Q38: 104.52692 | R38: 106.11953 | S38: 107.71137 | T38: 109.31779 | U38: 110.90412 | V38: 112.47349 | W38: 114.02781 | X38: 115.58364 | Y38: 117.13265 | Z38: 118.66014 | AA38: 120.17596 | AB38: 121.68253 | AC38: 123.18261 | AD38: 124.6744 | AE38: 126.16296 | AF38: 127.6415 | AG38: 129.10883 | AH38: 130.56717 | AI38: 0.015
A39: Natural Gas | B39: Residential Equipment: Equipment Stock: Clothes Dryers: Natural Gas: Reference case | C39: AEO.2023.REF2023.EQNR_STK_RESD_CDR_NG_NA_NA_MILL.A | D39: millions | F39: 20.076683 | G39: 20.41683 | H39: 20.774427 | I39: 21.150564 | J39: 21.546068 | K39: 21.964548 | L39: 22.379805 | M39: 22.792025 | N39: 23.198757 | O39: 23.600092 | P39: 23.995813 | Q39: 24.382277 | R39: 24.755445 | S39: 25.112667 | T39: 25.454254 | U39: 25.806086 | V39: 26.167633 | W39: 26.537321 | X39: 26.915823 | Y39: 27.30057 | Z39: 27.687328 | AA39: 28.075541 | AB39: 28.46377 | AC39: 28.850496 | AD39: 29.233149 | AE39: 29.61228 | AF39: 29.987488 | AG39: 30.358225 | AH39: 30.725327 | AI39: 0.015
A40: Total | B40: Residential Equipment: Equipment Stock: Clothes Dryers: Total: Reference case | C40: AEO.2023.REF2023.EQNR_STK_RESD_CDR_TOT_NA_NA_MILL.A | D40: millions | F40: 106.74141 | G40: 108.71468 | H40: 110.70276 | I40: 112.74357 | J40: 114.77825 | K40: 116.8316 | L40: 118.89222 | M40: 120.94352 | N40: 122.96437 | O40: 124.96168 | P40: 126.94875 | Q40: 128.9092 | R40: 130.87497 | S40: 132.82404 | T40: 134.77203 | U40: 136.71021 | V40: 138.64113 | W40: 140.56512 | X40: 142.49947 | Y40: 144.43323 | Z40: 146.34747 | AA40: 148.25151 | AB40: 150.1463 | AC40: 152.03311 | AD40: 153.90755 | AE40: 155.77524 | AF40: 157.629 | AG40: 159.46706 | AH40: 161.2925 | AI40: 0.015
A41: Other Appliances (million units)
A42: Refrigerators | B42: Residential Equipment: Equipment Stock: Other Appliances: Refrigerators: Reference case | C42: AEO.2023.REF2023.EQNR_STK_RESD_OTAR_RFG_NA_NA_MILL.A | D42: millions | F42: 172.81052 | G42: 174.53036 | H42: 176.2757 | I42: 178.06526 | J42: 179.84724 | K42: 181.6357 | L42: 183.43623 | M42: 185.22487 | N42: 186.97124 | O42: 188.68539 | P42: 190.38591 | Q42: 192.05006 | R42: 193.66389 | S42: 195.25655 | T42: 196.84982 | U42: 198.43115 | V42: 200.00401 | W42: 201.56328 | X42: 203.13881 | Y42: 204.7164 | Z42: 206.27017 | AA42: 207.8128 | AB42: 209.34547 | AC42: 210.86969 | AD42: 212.37984 | AE42: 213.88214 | AF42: 215.3678 | AG42: 216.83412 | AH42: 218.28552 | AI42: 0.008
A43: Freezers | B43: Residential Equipment: Equipment Stock: Other Appliances: Freezers: Reference case | C43: AEO.2023.REF2023.EQNR_STK_RESD_OTAR_FRZ_NA_NA_MILL.A | D43: millions | F43: 45.411747 | G43: 45.797165 | H43: 46.196087 | I43: 46.606503 | J43: 47.016159 | K43: 47.427891 | L43: 47.84296 | M43: 48.255486 | N43: 48.656849 | O43: 49.049393 | P43: 49.438591 | Q43: 49.820274 | R43: 50.190594 | S43: 50.555218 | T43: 50.919407 | U43: 51.278885 | V43: 51.634022 | W43: 51.984623 | X43: 52.339035 | Y43: 52.69482 | Z43: 53.045345 | AA43: 53.39328 | AB43: 53.739021 | AC43: 54.08271 | AD43: 54.422565 | AE43: 54.759823 | AF43: 55.092644 | AG43: 55.419907 | AH43: 55.742943 | AI43: 0.007
A44: Stock Average Equipment Efficiency
A45: Main Space Heaters
A46: Electric Heat Pumps (HSPF) | B46: Residential Equipment: Stock Average Efficiency: Main Space Heaters: Electric Heat Pumps: Reference case | C46: AEO.2023.REF2023.EFI_STK_RESD_SPHR_EHP_NA_NA_HSPF.A | D46: HSPF | F46: 8.210587 | G46: 8.304102 | H46: 8.388268 | I46: 8.46823 | J46: 8.543405 | K46: 8.61423 | L46: 8.680594 | M46: 8.742821 | N46: 8.800603 | O46: 8.854053 | P46: 8.903027 | Q46: 8.946011 | R46: 8.983779 | S46: 9.015677 | T46: 9.040678 | U46: 9.057808 | V46: 9.073445 | W46: 9.087294 | X46: 9.099171 | Y46: 9.109041 | Z46: 9.117004 | AA46: 9.123222 | AB46: 9.127919 | AC46: 9.131365 | AD46: 9.133833 | AE46: 9.13556 | AF46: 9.136773 | AG46: 9.137641 | AH46: 9.138287 | AI46: 0.004
A47: Natural Gas Heat Pumps (GCOP) | B47: Residential Equipment: Stock Average Efficiency: Main Space Heaters: Natural Gas Heat Pumps: Reference case | C47: AEO.2023.REF2023.EFI_STK_RESD_SPHR_NHU_NA_NA_GCOP.A | D47: GCOP | F47: 1.3 | G47: 1.3 | H47: 1.3 | I47: 1.3 | J47: 1.3 | K47: 1.3 | L47: 1.3 | M47: 1.3 | N47: 1.3 | O47: 1.3 | P47: 1.3 | Q47: 1.3 | R47: 1.3 | S47: 1.3 | T47: 1.3 | U47: 1.3 | V47: 1.3 | W47: 1.3 | X47: 1.3 | Y47: 1.3 | Z47: 1.3 | AA47: 1.3 | AB47: 1.3 | AC47: 1.3 | AD47: 1.3 | AE47: 1.3 | AF47: 1.3 | AG47: 1.3 | AH47: 1.3 | AI47: 0
A48: Geothermal Heat Pumps (COP) | B48: Residential Equipment: Stock Average Efficiency: Main Space Heaters: Geothermal Heat Pumps: Reference case | C48: AEO.2023.REF2023.EFI_STK_RESD_SPHR_GEHP_NA_NA_COP.A | D48: COP | F48: 3.504604 | G48: 3.556369 | H48: 3.59844 | I48: 3.634681 | J48: 3.666291 | K48: 3.693115 | L48: 3.716257 | M48: 3.736611 | N48: 3.754611 | O48: 3.770766 | P48: 3.785425 | Q48: 3.796584 | R48: 3.805493 | S48: 3.796041 | T48: 3.785444 | U48: 3.774951 | V48: 3.764537 | W48: 3.754287 | X48: 3.744015 | Y48: 3.733937 | Z48: 3.724154 | AA48: 3.714635 | AB48: 3.705535 | AC48: 3.696872 | AD48: 3.688707 | AE48: 3.681581 | AF48: 3.675506 | AG48: 3.670432 | AH48: 3.666301 | AI48: 0.002
A49: Natural Gas Furnace (AFUE) | B49: Residential Equipment: Stock Average Efficiency: Main Space Heaters: Natural Gas Furnace: Reference case | C49: AEO.2023.REF2023.EFI_STK_RESD_SPHR_NFR_NA_NA_AFUE.A | D49: AFUE | F49: 0.832511 | G49: 0.839042 | H49: 0.845284 | I49: 0.851464 | J49: 0.857598 | K49: 0.863234 | L49: 0.868416 | M49: 0.873145 | N49: 0.877414 | O49: 0.881295 | P49: 0.884778 | Q49: 0.886197 | R49: 0.887271 | S49: 0.88805 | T49: 0.888509 | U49: 0.888666 | V49: 0.888505 | W49: 0.888013 | X49: 0.887169 | Y49: 0.885984 | Z49: 0.884725 | AA49: 0.883386 | AB49: 0.88197 | AC49: 0.880496 | AD49: 0.879007 | AE49: 0.877502 | AF49: 0.876014 | AG49: 0.87458 | AH49: 0.873234 | AI49: 0.002
A50: Distillate Furnace (AFUE) | B50: Residential Equipment: Stock Average Efficiency: Main Space Heaters: Distillate Furnace: Reference case | C50: AEO.2023.REF2023.EFI_STK_RESD_SPHR_DFR_NA_NA_AFUE.A | D50: AFUE | F50: 0.83698 | G50: 0.839296 | H50: 0.840969 | I50: 0.842509 | J50: 0.844005 | K50: 0.845546 | L50: 0.846945 | M50: 0.848229 | N50: 0.849376 | O50: 0.850423 | P50: 0.851347 | Q50: 0.851875 | R50: 0.85233 | S50: 0.852715 | T50: 0.853026 | U50: 0.853266 | V50: 0.853428 | W50: 0.853509 | X50: 0.853498 | Y50: 0.853403 | Z50: 0.853276 | AA50: 0.85311 | AB50: 0.852896 | AC50: 0.852628 | AD50: 0.8523 | AE50: 0.851906 | AF50: 0.851443 | AG50: 0.850915 | AH50: 0.850327 | AI50: 0.001
A51: Space Cooling
A52: Electric Heat Pumps (SEER) | B52: Residential Equipment: Stock Average Efficiency: Space Cooling: Electric Heat Pumps: Reference case | C52: AEO.2023.REF2023.EFI_STK_RESD_SPC_EHP_NA_NA_SEER.A | D52: SEER | F52: 14.11839 | G52: 14.361896 | H52: 14.581603 | I52: 14.788684 | J52: 14.981616 | K52: 15.161526 | L52: 15.328118 | M52: 15.482331 | N52: 15.623494 | O52: 15.752029 | P52: 15.867741 | Q52: 15.967607 | R52: 16.05327 | S52: 16.123375 | T52: 16.175518 | U52: 16.207474 | V52: 16.236523 | W52: 16.262094 | X52: 16.28384 | Y52: 16.301706 | Z52: 16.315929 | AA52: 16.326824 | AB52: 16.334866 | AC52: 16.340574 | AD52: 16.344492 | AE52: 16.347061 | AF52: 16.34874 | AG52: 16.349838 | AH52: 16.35058 | AI52: 0.005
A53: Natural Gas Heat Pumps (GCOP) | B53: Residential Equipment: Stock Average Efficiency: Space Cooling: Natural Gas Heat Pumps: Reference case | C53: AEO.2023.REF2023.EFI_STK_RESD_SPC_NHU_NA_NA_GCOP.A | D53: GCOP | F53: 0.617709 | G53: 0.624238 | H53: 0.630573 | I53: 0.636707 | J53: 0.642617 | K53: 0.648374 | L53: 0.654042 | M53: 0.659783 | N53: 0.665711 | O53: 0.671927 | P53: 0.678372 | Q53: 0.684735 | R53: 0.690509 | S53: 0.695105 | T53: 0.698073 | U53: 0.699293 | V53: 0.699814 | W53: 0.699968 | X53: 0.699997 | Y53: 0.7 | Z53: 0.7 | AA53: 0.7 | AB53: 0.7 | AC53: 0.7 | AD53: 0.7 | AE53: 0.7 | AF53: 0.7 | AG53: 0.7 | AH53: 0.7 | AI53: 0.004
A54: Geothermal Heat Pumps (EER) | B54: Residential Equipment: Stock Average Efficiency: Space Cooling: Geothermal Heat Pumps: Reference case | C54: AEO.2023.REF2023.EFI_STK_RESD_SPC_GEHP_NA_NA_EER.A | D54: EER | F54: 16.046894 | G54: 16.408232 | H54: 16.704948 | I54: 16.961611 | J54: 17.185707 | K54: 17.376514 | L54: 17.541615 | M54: 17.686884 | N54: 17.815271 | O54: 17.930159 | P54: 18.034073 | Q54: 18.113184 | R54: 18.175549 | S54: 18.107792 | T54: 18.027935 | U54: 17.949612 | V54: 17.872522 | W54: 17.797092 | X54: 17.72201 | Y54: 17.648726 | Z54: 17.577887 | AA54: 17.509315 | AB54: 17.444035 | AC54: 17.382135 | AD54: 17.324015 | AE54: 17.27326 | AF54: 17.22991 | AG54: 17.193609 | AH54: 17.163919 | AI54: 0.002
A55: Central Air Conditioners (SEER) | B55: Residential Equipment: Stock Average Efficiency: Space Cooling: Central Air Conditioners: Reference case | C55: AEO.2023.REF2023.EFI_STK_RESD_SPC_CAC_NA_NA_SEER.A | D55: SEER | F55: 13.652026 | G55: 13.912424 | H55: 14.154226 | I55: 14.378797 | J55: 14.584899 | K55: 14.773286 | L55: 14.944267 | M55: 15.10037 | N55: 15.240844 | O55: 15.365807 | P55: 15.47662 | Q55: 15.542378 | R55: 15.594194 | S55: 15.634286 | T55: 15.661597 | U55: 15.6744 | V55: 15.685153 | W55: 15.693208 | X55: 15.698021 | Y55: 15.699372 | Z55: 15.697274 | AA55: 15.69194 | AB55: 15.683793 | AC55: 15.673481 | AD55: 15.661708 | AE55: 15.649206 | AF55: 15.636743 | AG55: 15.624902 | AH55: 15.614152 | AI55: 0.005
A56: Room Air Conditioners (EER) | B56: Residential Equipment: Stock Average Efficiency: Space Cooling: Room Air Conditioners: Reference case | C56: AEO.2023.REF2023.EFI_STK_RESD_SPC_RAC_NA_NA_EER.A | D56: EER | F56: 11.294298 | G56: 11.378965 | H56: 11.470779 | I56: 11.555712 | J56: 11.63078 | K56: 11.69559 | L56: 11.751351 | M56: 11.797001 | N56: 11.849714 | O56: 11.886739 | P56: 11.908359 | Q56: 11.930096 | R56: 11.951797 | S56: 11.972926 | T56: 11.993067 | U56: 12.011563 | V56: 12.027761 | W56: 12.0411 | X56: 12.063248 | Y56: 12.082109 | Z56: 12.098355 | AA56: 12.112704 | AB56: 12.125787 | AC56: 12.138025 | AD56: 12.149449 | AE56: 12.159873 | AF56: 12.168983 | AG56: 12.17645 | AH56: 12.18211 | AI56: 0.003
A57: Water Heaters
A58: Electric (EF) | B58: Residential Equipment: Stock Average Efficiency: Water Heaters: Electric: Reference case | C58: AEO.2023.REF2023.EFI_STK_RESD_WHT_ELE_NA_NA_EF.A | D58: EF | F58: 0.932231 | G58: 0.943999 | H58: 0.954985 | I58: 0.966586 | J58: 0.978653 | K58: 0.990484 | L58: 1.001943 | M58: 1.012981 | N58: 1.023422 | O58: 1.033579 | P58: 1.043442 | Q58: 1.043284 | R58: 1.03752 | S58: 1.032037 | T58: 1.026696 | U58: 1.021409 | V58: 1.016134 | W58: 1.011338 | X58: 1.006963 | Y58: 1.003034 | Z58: 0.999559 | AA58: 0.996529 | AB58: 0.993921 | AC58: 0.991708 | AD58: 0.989854 | AE58: 0.988325 | AF58: 0.987083 | AG58: 0.986091 | AH58: 0.98531 | AI58: 0.002
A59: Natural Gas (EF) | B59: Residential Equipment: Stock Average Efficiency: Water Heaters: Natural Gas: Reference case | C59: AEO.2023.REF2023.EFI_STK_RESD_WHT_NG_NA_NA_EF.A | D59: EF | F59: 0.618654 | G59: 0.622229 | H59: 0.625105 | I59: 0.627324 | J59: 0.628953 | K59: 0.63006 | L59: 0.630623 | M59: 0.630691 | N59: 0.630318 | O59: 0.629944 | P59: 0.629577 | Q59: 0.628701 | R59: 0.627765 | S59: 0.626858 | T59: 0.625995 | U59: 0.62519 | V59: 0.62445 | W59: 0.62378 | X59: 0.623184 | Y59: 0.622661 | Z59: 0.622209 | AA59: 0.621823 | AB59: 0.621499 | AC59: 0.62123 | AD59: 0.621015 | AE59: 0.620843 | AF59: 0.620707 | AG59: 0.620602 | AH59: 0.620522 | AI59: 0
A60: Distillate Fuel Oil (EF) | B60: Residential Equipment: Stock Average Efficiency: Water Heaters: Distillate Fuel Oil: Reference case | C60: AEO.2023.REF2023.EFI_STK_RESD_WHT_DFO_NA_NA_EF.A | D60: EF | F60: 0.612026 | G60: 0.624824 | H60: 0.636098 | I60: 0.645684 | J60: 0.653606 | K60: 0.659701 | L60: 0.663876 | M60: 0.666014 | N60: 0.66605 | O60: 0.666088 | P60: 0.666126 | Q60: 0.666164 | R60: 0.6662 | S60: 0.666235 | T60: 0.666267 | U60: 0.666297 | V60: 0.666323 | W60: 0.666346 | X60: 0.666367 | Y60: 0.666385 | Z60: 0.666401 | AA60: 0.666415 | AB60: 0.666427 | AC60: 0.666438 | AD60: 0.666451 | AE60: 0.666462 | AF60: 0.666473 | AG60: 0.666484 | AH60: 0.666495 | AI60: 0.003
A61: Propane (EF) | B61: Residential Equipment: Stock Average Efficiency: Water Heaters: Propane: Reference case | C61: AEO.2023.REF2023.EFI_STK_RESD_WHT_PROP_NA_NA_EF.A | D61: EF | F61: 0.607499 | G61: 0.611083 | H61: 0.614302 | I61: 0.616901 | J61: 0.618938 | K61: 0.620442 | L61: 0.621421 | M61: 0.621887 | N61: 0.621842 | O61: 0.621805 | P61: 0.621799 | Q61: 0.621477 | R61: 0.621127 | S61: 0.620762 | T61: 0.620385 | U61: 0.620003 | V61: 0.619628 | W61: 0.619264 | X61: 0.618919 | Y61: 0.6186 | Z61: 0.618312 | AA61: 0.618055 | AB61: 0.617832 | AC61: 0.617643 | AD61: 0.617488 | AE61: 0.617364 | AF61: 0.617266 | AG61: 0.617193 | AH61: 0.617138 | AI61: 0.001
A62: Other Appliances (kilowatthours per year)
A63: Refrigerators | B63: Residential Equipment: Stock Average Efficiency: Other Appliances: Refrigerators: Reference case | C63: AEO.2023.REF2023.EFI_STK_RESD_OTAR_RFG_NA_NA_KWH.A | D63: kWh | F63: 601.62268 | G63: 591.79913 | H63: 582.51691 | I63: 573.78015 | J63: 565.58649 | K63: 557.91095 | L63: 550.7345 | M63: 544.04511 | N63: 537.87042 | O63: 532.28186 | P63: 527.24188 | Q63: 522.7456 | R63: 518.78699 | S63: 515.33673 | T63: 512.38696 | U63: 509.90985 | V63: 507.92584 | W63: 506.40897 | X63: 505.38199 | Y63: 504.86813 | Z63: 504.85422 | AA63: 504.83514 | AB63: 504.81171 | AC63: 504.78409 | AD63: 504.75421 | AE63: 504.72391 | AF63: 504.69354 | AG63: 504.66638 | AH63: 504.64325 | AI63: -0.006
A64: Freezers | B64: Residential Equipment: Stock Average Efficiency: Other Appliances: Freezers: Reference case | C64: AEO.2023.REF2023.EFI_STK_RESD_OTAR_FRZ_NA_NA_KWH.A | D64: kWh | F64: 448.44434 | G64: 443.66037 | H64: 438.78305 | I64: 433.82999 | J64: 428.81097 | K64: 423.76276 | L64: 418.95932 | M64: 414.39859 | N64: 410.09692 | O64: 406.03284 | P64: 402.1857 | Q64: 398.57709 | R64: 395.21826 | S64: 392.09049 | T64: 389.22845 | U64: 386.60855 | V64: 384.2406 | W64: 382.10922 | X64: 380.19821 | Y64: 378.55283 | Z64: 377.15033 | AA64: 376.0249 | AB64: 375.1943 | AC64: 374.65906 | AD64: 374.4122 | AE64: 374.40713 | AF64: 374.40103 | AG64: 374.39468 | AH64: 374.38818 | AI64: -0.006
A65: Building Shell Efficiency Index
A66: Space Heating
A67: Pre-2015 Homes | B67: Residential Equipment: Building Shell Efficiency Index: Space Heating: Pre-2015 Homes: Reference case | C67: AEO.2023.REF2023.EFI_BSE_RESD_SPH_OLD_NA_NA_Y15EQ1.A | D67: 2015=1.00 | F67: 0.949531 | G67: 0.941271 | H67: 0.935547 | I67: 0.931025 | J67: 0.926384 | K67: 0.921287 | L67: 0.915757 | M67: 0.90954 | N67: 0.902871 | O67: 0.895915 | P67: 0.8889 | Q67: 0.881681 | R67: 0.874436 | S67: 0.867313 | T67: 0.860338 | U67: 0.853362 | V67: 0.846267 | W67: 0.839304 | X67: 0.832365 | Y67: 0.825437 | Z67: 0.818606 | AA67: 0.811915 | AB67: 0.80533 | AC67: 0.798658 | AD67: 0.791662 | AE67: 0.784823 | AF67: 0.778197 | AG67: 0.771682 | AH67: 0.765165 | AI67: -0.008
A68: New Construction | B68: Residential Equipment: Building Shell Efficiency Index: Space Heating: New Construction: Reference case | C68: AEO.2023.REF2023.EFI_BSE_RESD_SPH_NCO_NA_NA_Y15EQ1.A | D68: 2015=1.00 | F68: 0.838603 | G68: 0.784996 | H68: 0.777509 | I68: 0.774892 | J68: 0.77626 | K68: 0.776751 | L68: 0.776031 | M68: 0.773863 | N68: 0.771326 | O68: 0.76938 | P68: 0.767984 | Q68: 0.882591 | R68: 0.881587 | S68: 0.882601 | T68: 0.882229 | U68: 0.882226 | V68: 0.882243 | W68: 0.882296 | X68: 0.881293 | Y68: 0.879356 | Z68: 0.878537 | AA68: 0.877424 | AB68: 0.876082 | AC68: 0.874815 | AD68: 0.873478 | AE68: 0.873823 | AF68: 0.87376 | AG68: 0.874249 | AH68: 0.874747 | AI68: 0.002
A69: All Homes | B69: Residential Equipment: Building Shell Efficiency Index: Space Heating: All Homes: Reference case | C69: AEO.2023.REF2023.EFI_BSE_RESD_SPH_AHM_NA_NA_Y15EQ1.A | D69: 2015=1.00 | F69: 0.941702 | G69: 0.932327 | H69: 0.925351 | I69: 0.919533 | J69: 0.913762 | K69: 0.907725 | L69: 0.901436 | M69: 0.894692 | N69: 0.887717 | O69: 0.880652 | P69: 0.873678 | Q69: 0.867923 | R69: 0.862235 | S69: 0.856766 | T69: 0.851519 | U69: 0.846373 | V69: 0.841234 | W69: 0.836294 | X69: 0.83146 | Y69: 0.826709 | Z69: 0.822107 | AA69: 0.81768 | AB69: 0.813395 | AC69: 0.809113 | AD69: 0.80466 | AE69: 0.800399 | AF69: 0.796357 | AG69: 0.792461 | AH69: 0.78863 | AI69: -0.006
A70: Space Cooling
A71: Pre-2015 Homes | B71: Residential Equipment: Building Shell Efficiency Index: Space Cooling: Pre-2015 Homes: Reference case | C71: AEO.2023.REF2023.EFI_BSE_RESD_SPC_OLD_NA_NA_Y15EQ1.A | D71: 2015=1.00 | F71: 0.982053 | G71: 0.979071 | H71: 0.977092 | I71: 0.975571 | J71: 0.973951 | K71: 0.972134 | L71: 0.970146 | M71: 0.967898 | N71: 0.965495 | O71: 0.962988 | P71: 0.960457 | Q71: 0.957868 | R71: 0.95527 | S71: 0.952708 | T71: 0.95019 | U71: 0.947673 | V71: 0.945107 | W71: 0.94258 | X71: 0.940056 | Y71: 0.937522 | Z71: 0.935024 | AA71: 0.932571 | AB71: 0.930163 | AC71: 0.927714 | AD71: 0.925119 | AE71: 0.922588 | AF71: 0.920137 | AG71: 0.91773 | AH71: 0.915312 | AI71: -0.003
A72: New Construction | B72: Residential Equipment: Building Shell Efficiency Index: Space Cooling: New Construction: Reference case | C72: AEO.2023.REF2023.EFI_BSE_RESD_SPC_NCO_NA_NA_Y15EQ1.A | D72: 2015=1.00 | F72: 0.981704 | G72: 0.96699 | H72: 0.960888 | I72: 0.958751 | J72: 0.959902 | K72: 0.960768 | L72: 0.960538 | M72: 0.959561 | N72: 0.958217 | O72: 0.957406 | P72: 0.957186 | Q72: 0.999057 | R72: 0.998953 | S72: 0.999541 | T72: 0.99967 | U72: 0.999815 | V72: 0.99998 | W72: 1.0003 | X72: 1.000248 | Y72: 0.999571 | Z72: 0.999605 | AA72: 0.999285 | AB72: 0.998766 | AC72: 0.998304 | AD72: 0.997878 | AE72: 0.998472 | AF72: 0.998787 | AG72: 0.999431 | AH72: 1.000114 | AI72: 0.001
A73: All Homes | B73: Residential Equipment: Building Shell Efficiency Index: Space Cooling: All Homes: Reference case | C73: AEO.2023.REF2023.EFI_BSE_RESD_SPC_AHM_NA_NA_Y15EQ1.A | D73: 2015=1.00 | F73: 0.982549 | G73: 0.979629 | H73: 0.977618 | I73: 0.976033 | J73: 0.974401 | K73: 0.972632 | L73: 0.970741 | M73: 0.968648 | N73: 0.966445 | O73: 0.964185 | P73: 0.961937 | Q73: 0.960043 | R73: 0.958152 | S73: 0.956315 | T73: 0.954538 | U73: 0.952782 | V73: 0.951005 | W73: 0.949281 | X73: 0.947581 | Y73: 0.945886 | Z73: 0.944233 | AA73: 0.942628 | AB73: 0.941067 | AC73: 0.939484 | AD73: 0.937796 | AE73: 0.936177 | AF73: 0.934631 | AG73: 0.933132 | AH73: 0.931638 | AI73: -0.002
A74: Distributed Generation and
A75: Combined Heat and Power
A76: Generating Capacity (gigawatts)
A77: Natural Gas Fuel Cells | B77: Residential: Combined Heat and Power: Generating Capacity: Fuel Cells: Reference case | C77: AEO.2023.REF2023.CAP_NA_COMM_CHP_FCL_NA_NA_MW.A | D77: GW | F77: 0 | G77: 0 | H77: 0 | I77: 0 | J77: 0 | K77: 0 | L77: 0 | M77: 0 | N77: 0 | O77: 0 | P77: 0 | Q77: 0 | R77: 2e-06 | S77: 5e-06 | T77: 1.1e-05 | U77: 2.2e-05 | V77: 4.4e-05 | W77: 8.3e-05 | X77: 0.000155 | Y77: 0.000286 | Z77: 0.000417 | AA77: 0.00055 | AB77: 0.000682 | AC77: 0.000816 | AD77: 0.00095 | AE77: 0.001084 | AF77: 0.001219 | AG77: 0.001353 | AH77: 0.001488 | AI77: - -
A78: Solar Photovoltaic | B78: Residential: Combined Heat and Power: Generating Capacity: Solar Photovoltaic: Reference case | C78: AEO.2023.REF2023.CAP_NA_RESD_CHP_SLR_PHTVL_NA_MW.A | D78: GW | F78: 25.940821 | G78: 28.426916 | H78: 31.31752 | I78: 34.213085 | J78: 37.102398 | K78: 40.088001 | L78: 43.162285 | M78: 46.379025 | N78: 49.715115 | O78: 53.221054 | P78: 56.974155 | Q78: 60.782734 | R78: 64.698021 | S78: 68.113708 | T78: 71.713646 | U78: 75.468544 | V78: 79.508545 | W78: 83.846107 | X78: 88.482719 | Y78: 93.406563 | Z78: 98.617554 | AA78: 104.15289 | AB78: 109.90788 | AC78: 115.97617 | AD78: 122.2729 | AE78: 128.79648 | AF78: 135.66493 | AG78: 142.69435 | AH78: 149.97357 | AI78: 0.065
A79: Wind | B79: Residential: Combined Heat and Power: Generating Capacity: Wind: Reference case | C79: AEO.2023.REF2023.CAP_NA_RESD_CHP_WND_NA_NA_MW.A | D79: GW | F79: 0.063448 | G79: 0.069112 | H79: 0.075193 | I79: 0.081515 | J79: 0.087961 | K79: 0.094482 | L79: 0.101025 | M79: 0.10757 | N79: 0.11409 | O79: 0.120587 | P79: 0.12707 | Q79: 0.133309 | R79: 0.133312 | S79: 0.133318 | T79: 0.133331 | U79: 0.133353 | V79: 0.133396 | W79: 0.133474 | X79: 0.133618 | Y79: 0.13388 | Z79: 0.134143 | AA79: 0.134408 | AB79: 0.134673 | AC79: 0.13494 | AD79: 0.135207 | AE79: 0.135476 | AF79: 0.135745 | AG79: 0.136015 | AH79: 0.136285 | AI79: 0.028
A80: Total | B80: Residential: Combined Heat and Power: Generating Capacity: Total: Reference case | C80: AEO.2023.REF2023.CAP_NA_RESD_CHP_TOT_NA_NA_MW.A | D80: GW | F80: 26.004269 | G80: 28.496029 | H80: 31.392714 | I80: 34.294601 | J80: 37.190361 | K80: 40.182484 | L80: 43.263309 | M80: 46.486595 | N80: 49.829205 | O80: 53.34164 | P80: 57.101227 | Q80: 60.916042 | R80: 64.831337 | S80: 68.247032 | T80: 71.846985 | U80: 75.601921 | V80: 79.641983 | W80: 83.979668 | X80: 88.616493 | Y80: 93.540726 | Z80: 98.752113 | AA80: 104.28785 | AB80: 110.04324 | AC80: 116.11193 | AD80: 122.40906 | AE80: 128.93304 | AF80: 135.8019 | AG80: 142.83173 | AH80: 150.11136 | AI80: 0.065
A81: Net Generation (billion kilowatthours)
A82: Natural Gas Fuel Cells | B82: Residential: Combined Heat and Power: Net Generation: Fuel Cells: Reference case | C82: AEO.2023.REF2023.GEN_NA_COMM_CHP_FCL_NA_NA_MILLKWH.A | D82: billion kWh | F82: 0 | G82: 0 | H82: 0 | I82: 0 | J82: 0 | K82: 0 | L82: 0 | M82: 0 | N82: 0 | O82: 0 | P82: 0 | Q82: 1e-06 | R82: 6e-06 | S82: 1.4e-05 | T82: 3.1e-05 | U82: 6.2e-05 | V82: 0.000122 | W82: 0.00023 | X82: 0.000431 | Y82: 0.000798 | Z82: 0.001165 | AA82: 0.001534 | AB82: 0.001904 | AC82: 0.002276 | AD82: 0.002649 | AE82: 0.003024 | AF82: 0.0034 | AG82: 0.003776 | AH82: 0.004152 | AI82: - -
A83: Solar Photovoltaic | B83: Residential: Combined Heat and Power: Net Generation: Solar Photovoltaic: Reference case | C83: AEO.2023.REF2023.GEN_NA_COMM_CHP_SLR_PHTVL_NA_MILLKWH.A | D83: billion kWh | F83: 38.879559 | G83: 43.125973 | H83: 47.972565 | I83: 52.818501 | J83: 57.647594 | K83: 62.611156 | L83: 67.696831 | M83: 72.98391 | N83: 78.436142 | O83: 84.134567 | P83: 90.184685 | Q83: 96.308403 | R83: 102.5744 | S83: 108.09508 | T83: 113.88322 | U83: 119.88541 | V83: 126.29795 | W83: 133.13672 | X83: 140.40329 | Y83: 148.07901 | Z83: 156.16257 | AA83: 164.70763 | AB83: 173.56131 | AC83: 182.85916 | AD83: 192.47685 | AE83: 202.41138 | AF83: 212.83244 | AG83: 223.47301 | AH83: 234.46117 | AI83: 0.066
A84: Wind | B84: Residential: Combined Heat and Power: Net Generation: Wind: Reference case | C84: AEO.2023.REF2023.GEN_NA_COMM_CHP_WND_NA_NA_MILLKWH.A | D84: billion kWh | F84: 0.069007 | G84: 0.074813 | H84: 0.081044 | I84: 0.087524 | J84: 0.094131 | K84: 0.100814 | L84: 0.107521 | M84: 0.114228 | N84: 0.120911 | O84: 0.12757 | P84: 0.134214 | Q84: 0.140609 | R84: 0.140612 | S84: 0.140619 | T84: 0.140631 | U84: 0.140654 | V84: 0.140698 | W84: 0.140778 | X84: 0.140925 | Y84: 0.141195 | Z84: 0.141465 | AA84: 0.141736 | AB84: 0.142007 | AC84: 0.14228 | AD84: 0.142554 | AE84: 0.142829 | AF84: 0.143104 | AG84: 0.143379 | AH84: 0.143655 | AI84: 0.027
A85: Total | B85: Residential: Combined Heat and Power: Net Generation: Total: Reference case | C85: AEO.2023.REF2023.GEN_NA_COMM_CHP_TOT_NA_NA_MILLKWH.A | D85: billion kWh | F85: 38.948566 | G85: 43.200787 | H85: 48.053608 | I85: 52.906025 | J85: 57.741726 | K85: 62.711971 | L85: 67.804352 | M85: 73.098137 | N85: 78.557053 | O85: 84.262138 | P85: 90.318901 | Q85: 96.449013 | R85: 102.71502 | S85: 108.23572 | T85: 114.02388 | U85: 120.02612 | V85: 126.43877 | W85: 133.27773 | X85: 140.54465 | Y85: 148.22099 | Z85: 156.30519 | AA85: 164.85091 | AB85: 173.70523 | AC85: 183.00371 | AD85: 192.62205 | AE85: 202.55722 | AF85: 212.97894 | AG85: 223.62015 | AH85: 234.60898 | AI85: 0.066
A86: Disposition
A87: Sales to the Grid | B87: Residential: Combined Heat and Power: Net Generation: Sales to the Grid: Reference case | C87: AEO.2023.REF2023.GEN_NA_COMM_CHP_STG_NA_NA_MILLKWH.A | D87: billion kWh | F87: 6.116397 | G87: 7.017288 | H87: 8.039189 | I87: 9.009025 | J87: 9.966662 | K87: 10.957931 | L87: 11.963233 | M87: 13.032094 | N87: 14.131605 | O87: 15.315522 | P87: 16.611361 | Q87: 17.921099 | R87: 19.288816 | S87: 20.464827 | T87: 21.72669 | U87: 23.024828 | V87: 24.442295 | W87: 25.954372 | X87: 27.590239 | Y87: 29.314402 | Z87: 31.122248 | AA87: 33.063015 | AB87: 35.056107 | AC87: 37.173237 | AD87: 39.340511 | AE87: 41.550514 | AF87: 43.885693 | AG87: 46.226215 | AH87: 48.640495 | AI87: 0.077
A88: Generation for Own Use | B88: Residential: Combined Heat and Power: Net Generation: Generation for Own Use: Reference case | C88: AEO.2023.REF2023.GEN_NA_COMM_CHP_GFO_NA_NA_MILLKWH.A | D88: billion kWh | F88: 32.832169 | G88: 36.183495 | H88: 40.014423 | I88: 43.896996 | J88: 47.775063 | K88: 51.75404 | L88: 55.841122 | M88: 60.066036 | N88: 64.425438 | O88: 68.946617 | P88: 73.707542 | Q88: 78.527916 | R88: 83.426201 | S88: 87.770882 | T88: 92.297188 | U88: 97.001289 | V88: 101.99648 | W88: 107.32336 | X88: 112.95441 | Y88: 118.9066 | Z88: 125.18295 | AA88: 131.78787 | AB88: 138.64912 | AC88: 145.83049 | AD88: 153.28155 | AE88: 161.0067 | AF88: 169.09323 | AG88: 177.39394 | AH88: 185.96849 | AI88: 0.064
A89: Energy Input (trillion Btu)
A90: Natural Gas Fuel Cells | B90: Residential: Combined Heat and Power: Energy Input: Fuel Cells: Reference case | C90: AEO.2023.REF2023.CNSM_NA_COMM_CHP_FCL_NA_NA_TRLBTU.A | D90: trillion Btu | F90: 0 | G90: 0 | H90: 0 | I90: 0 | J90: 0 | K90: 0 | L90: 0 | M90: 0 | N90: 0 | O90: 0 | P90: 3e-06 | Q90: 9e-06 | R90: 4.3e-05 | S90: 0.000108 | T90: 0.000237 | U90: 0.000474 | V90: 0.000928 | W90: 0.001755 | X90: 0.003277 | Y90: 0.00605 | Z90: 0.008821 | AA90: 0.011598 | AB90: 0.014381 | AC90: 0.017171 | AD90: 0.019964 | AE90: 0.022764 | AF90: 0.025563 | AG90: 0.028357 | AH90: 0.031149 | AI90: - -
A91: Solar Photovoltaic | B91: Residential: Combined Heat and Power: Energy Input: Solar Photovoltaic: Reference case | C91: AEO.2023.REF2023.CNSM_NA_COMM_CHP_SLR_PHTVL_NA_TRLBTU.A | D91: trillion Btu | F91: 320.74207 | G91: 353.17841 | H91: 397.25159 | I91: 434.42645 | J91: 470.73334 | K91: 509.77789 | L91: 548.17249 | M91: 589.55798 | N91: 635.00909 | O91: 682.9519 | P91: 733.30017 | Q91: 781.92981 | R91: 835.91406 | S91: 883.02222 | T91: 929.25885 | U91: 974.57056 | V91: 1022.5746 | W91: 1077.0762 | X91: 1132.4678 | Y91: 1197.6093 | Z91: 1261.7703 | AA91: 1330.9084 | AB91: 1405.4312 | AC91: 1483.5311 | AD91: 1559.2985 | AE91: 1639.5164 | AF91: 1720.6675 | AG91: 1808.1606 | AH91: 1890.2471 | AI91: 0.065
A92: Wind | B92: Residential: Combined Heat and Power: Energy Input: Wind: Reference case | C92: AEO.2023.REF2023.CNSM_NA_COMM_CHP_WND_NA_NA_TRLBTU.A | D92: trillion Btu | F92: 0.5612 | G92: 0.603398 | H92: 0.658638 | I92: 0.704729 | J92: 0.747767 | K92: 0.800745 | L92: 0.853856 | M92: 0.906597 | N92: 0.96025 | O92: 1.016923 | P92: 1.071568 | Q92: 1.121735 | R92: 1.122288 | S92: 1.12683 | T92: 1.126382 | U92: 1.127776 | V92: 1.128401 | W92: 1.130486 | X92: 1.13545 | Y92: 1.143631 | Z92: 1.145825 | AA92: 1.154219 | AB92: 1.16212 | AC92: 1.170447 | AD92: 1.177325 | AE92: 1.183087 | AF92: 1.186864 | AG92: 1.193909 | AH92: 1.191869 | AI92: 0.027
A93: Total | B93: Residential: Combined Heat and Power: Energy Input: Total: Reference case | C93: AEO.2023.REF2023.CNSM_NA_COMM_CHP_TOT_NA_NA_TRLBTU.A | D93: trillion Btu | F93: 321.30325 | G93: 353.7818 | H93: 397.91022 | I93: 435.13119 | J93: 471.48111 | K93: 510.57864 | L93: 549.02637 | M93: 590.4646 | N93: 635.96936 | O93: 683.96881 | P93: 734.37176 | Q93: 783.05157 | R93: 837.03644 | S93: 884.14917 | T93: 930.3855 | U93: 975.69879 | V93: 1023.7039 | W93: 1078.2084 | X93: 1133.6066 | Y93: 1198.759 | Z93: 1262.9249 | AA93: 1332.0742 | AB93: 1406.6077 | AC93: 1484.7188 | AD93: 1560.4959 | AE93: 1640.7222 | AF93: 1721.8799 | AG93: 1809.3829 | AH93: 1891.4701 | AI93: 0.065

Sheet AEO25_Table_21._Residential
A1: Table 21. Residential Sector Equipment Stock and Efficiency, and Distributed Generation
A2: https://www.eia.gov/outlooks/aeo/data/browser/#/?id=30-AEO2025&cases=highZTC&sourcekey=0
A3: Tue Dec 02 2025 13:21:44 GMT-0800 (Pacific Standard Time)
A4: Source: U.S. Energy Information Administration
B5: full name | C5: api key | D5: units | E5: 2023 | F5: 2024 | G5: 2025 | H5: 2026 | I5: 2027 | J5: 2028 | K5: 2029 | L5: 2030 | M5: 2031 | N5: 2032 | O5: 2033 | P5: 2034 | Q5: 2035 | R5: 2036 | S5: 2037 | T5: 2038 | U5: 2039 | V5: 2040 | W5: 2041 | X5: 2042 | Y5: 2043 | Z5: 2044 | AA5: 2045 | AB5: 2046 | AC5: 2047 | AD5: 2048 | AE5: 2049 | AF5: 2050 | AG5: Growth (2024-2050)
A6: Equipment Stock (million units)
A7: Main Space Heaters
A8: Electric Heat Pumps | B8: Residential Equipment: Equipment Stock: Main Space Heaters: Electric Heat Pumps: High Zero-Carbon Technology Cost | C8: AEO.2025.HIGHZTC.EQNR_STK_RESD_MSHR_EHP_NA_NA_MILL.A | D8: millions | F8: 16.645529 | G8: 16.962238 | H8: 17.297937 | I8: 17.63735 | J8: 17.975958 | K8: 18.323191 | L8: 18.671122 | M8: 19.020292 | N8: 19.366976 | O8: 19.701832 | P8: 20.022341 | Q8: 20.338335 | R8: 20.648127 | S8: 20.94591 | T8: 21.232155 | U8: 21.506626 | V8: 21.772039 | W8: 22.026169 | X8: 22.27137 | Y8: 22.506741 | Z8: 22.737045 | AA8: 22.966516 | AB8: 23.194811 | AC8: 23.422667 | AD8: 23.650106 | AE8: 23.877323 | AF8: 24.103533 | AG8: 0.014
A9: Electric Other | B9: Residential Equipment: Equipment Stock: Main Space Heaters: Electric Other: High Zero-Carbon Technology Cost | C9: AEO.2025.HIGHZTC.EQNR_STK_RESD_MSHR_ELO_NA_NA_MILL.A | D9: millions | F9: 26.605318 | G9: 26.78159 | H9: 26.987282 | I9: 27.200581 | J9: 27.420454 | K9: 27.653374 | L9: 27.889208 | M9: 28.127293 | N9: 28.362696 | O9: 28.587048 | P9: 28.798485 | Q9: 29.005108 | R9: 29.206934 | S9: 29.397682 | T9: 29.579088 | U9: 29.751591 | V9: 29.918131 | W9: 30.076429 | X9: 30.228321 | Y9: 30.375742 | Z9: 30.522755 | AA9: 30.670509 | AB9: 30.818306 | AC9: 30.9662 | AD9: 31.114233 | AE9: 31.262747 | AF9: 31.41095 | AG9: 0.006
A10: Natural Gas Heat Pumps | B10: Residential Equipment: Equipment Stock: Main Space Heaters: Natural Gas Heat Pumps: High Zero-Carbon Technology Cost | C10: AEO.2025.HIGHZTC.EQNR_STK_RESD_MSHR_NHU_NA_NA_MILL.A | D10: millions | F10: 1.335856 | G10: 1.335485 | H10: 1.335121 | I10: 1.334763 | J10: 1.334411 | K10: 1.334067 | L10: 1.333728 | M10: 1.333394 | N10: 1.333067 | O10: 1.332746 | P10: 1.332431 | Q10: 1.33212 | R10: 1.331816 | S10: 1.331517 | T10: 1.331223 | U10: 1.330934 | V10: 1.330651 | W10: 1.330373 | X10: 1.330099 | Y10: 1.329831 | Z10: 1.329567 | AA10: 1.329308 | AB10: 1.329053 | AC10: 1.328804 | AD10: 1.328558 | AE10: 1.328316 | AF10: 1.328079 | AG10: 0
A11: Natural Gas Other | B11: Residential Equipment: Equipment Stock: Main Space Heaters: Natural Gas Other: High Zero-Carbon Technology Cost | C11: AEO.2025.HIGHZTC.EQNR_STK_RESD_MSHR_NGO_NA_NA_MILL.A | D11: millions | F11: 65.614693 | G11: 66.503311 | H11: 67.422646 | I11: 68.347206 | J11: 69.275345 | K11: 70.215851 | L11: 71.155624 | M11: 72.095222 | N11: 73.022018 | O11: 73.917961 | P11: 74.776138 | Q11: 75.619469 | R11: 76.443016 | S11: 77.232452 | T11: 77.991676 | U11: 78.71611 | V11: 79.412209 | W11: 80.076683 | X11: 80.717903 | Y11: 81.333214 | Z11: 81.934601 | AA11: 82.534103 | AB11: 83.129738 | AC11: 83.72612 | AD11: 84.322975 | AE11: 84.920403 | AF11: 85.516907 | AG11: 0.01
A12: Distillate Fuel Oil | B12: Residential Equipment: Equipment Stock: Main Space Heaters: Distillate Fuel Oil: High Zero-Carbon Technology Cost | C12: AEO.2025.HIGHZTC.EQNR_STK_RESD_MSHR_DFO_NA_NA_MILL.A | D12: millions | F12: 4.76794 | G12: 4.7259 | H12: 4.684821 | I12: 4.644579 | J12: 4.60502 | K12: 4.565969 | L12: 4.526826 | M12: 4.487612 | N12: 4.449521 | O12: 4.412687 | P12: 4.377314 | Q12: 4.343427 | R12: 4.310317 | S12: 4.277948 | T12: 4.246086 | U12: 4.214488 | V12: 4.183174 | W12: 4.152061 | X12: 4.122024 | Y12: 4.093054 | Z12: 4.065121 | AA12: 4.0385 | AB12: 4.012821 | AC12: 3.986746 | AD12: 3.960447 | AE12: 3.934162 | AF12: 3.908093 | AG12: -0.008
A13: Propane | B13: Residential Equipment: Equipment Stock: Main Space Heaters: Propane: High Zero-Carbon Technology Cost | C13: AEO.2025.HIGHZTC.EQNR_STK_RESD_MSHR_PROP_NA_NA_MILL.A | D13: millions | F13: 5.242597 | G13: 5.231007 | H13: 5.222726 | I13: 5.213856 | J13: 5.201762 | K13: 5.192317 | L13: 5.180441 | M13: 5.167188 | N13: 5.155312 | O13: 5.143894 | P13: 5.132373 | Q13: 5.121347 | R13: 5.111237 | S13: 5.101963 | T13: 5.09299 | U13: 5.084504 | V13: 5.077328 | W13: 5.070891 | X13: 5.064682 | Y13: 5.058537 | Z13: 5.052648 | AA13: 5.047476 | AB13: 5.043245 | AC13: 5.03766 | AD13: 5.030745 | AE13: 5.022702 | AF13: 5.01332 | AG13: -0.002
A14: Kerosene | B14: Residential Equipment: Equipment Stock: Main Space Heaters: Kerosene: High Zero-Carbon Technology Cost | C14: AEO.2025.HIGHZTC.EQNR_STK_RESD_MSHR_KRS_NA_NA_MILL.A | D14: millions | F14: 0.004925 | G14: 0.007897 | H14: 0.011523 | I14: 0.015072 | J14: 0.018269 | K14: 0.02133 | L14: 0.02419 | M14: 0.027018 | N14: 0.029863 | O14: 0.032679 | P14: 0.035394 | Q14: 0.038013 | R14: 0.040598 | S14: 0.043115 | T14: 0.045557 | U14: 0.047931 | V14: 0.050323 | W14: 0.052708 | X14: 0.055048 | Y14: 0.057337 | Z14: 0.059592 | AA14: 0.06182 | AB14: 0.063984 | AC14: 0.066125 | AD14: 0.068224 | AE14: 0.0703 | AF14: 0.072325 | AG14: 0.109
A15: Wood Stoves | B15: Residential Equipment: Equipment Stock: Main Space Heaters: Wood Stoves: High Zero-Carbon Technology Cost | C15: AEO.2025.HIGHZTC.EQNR_STK_RESD_MSHR_WDS_NA_NA_MILL.A | D15: millions | F15: 2.220637 | G15: 2.212639 | H15: 2.204829 | I15: 2.197059 | J15: 2.189375 | K15: 2.181753 | L15: 2.174187 | M15: 2.166692 | N15: 2.159028 | O15: 2.151248 | P15: 2.1434 | Q15: 2.135421 | R15: 2.127357 | S15: 2.119169 | T15: 2.11095 | U15: 2.102684 | V15: 2.094329 | W15: 2.085804 | X15: 2.077575 | Y15: 2.069646 | Z15: 2.062065 | AA15: 2.054862 | AB15: 2.048036 | AC15: 2.041663 | AD15: 2.035719 | AE15: 2.030173 | AF15: 2.025021 | AG15: -0.004
A16: Geothermal Heat Pumps | B16: Residential Equipment: Equipment Stock: Main Space Heaters: Geothermal Heat Pumps: High Zero-Carbon Technology Cost | C16: AEO.2025.HIGHZTC.EQNR_STK_RESD_MSHR_GEHP_NA_NA_MILL.A | D16: millions | F16: 1.360675 | G16: 1.408181 | H16: 1.455492 | I16: 1.50272 | J16: 1.549133 | K16: 1.595817 | L16: 1.642325 | M16: 1.688836 | N16: 1.73555 | O16: 1.781672 | P16: 1.826767 | Q16: 1.871948 | R16: 1.916753 | S16: 1.960757 | T16: 2.003791 | U16: 2.045475 | V16: 2.086105 | W16: 2.125625 | X16: 2.164013 | Y16: 2.200763 | Z16: 2.236357 | AA16: 2.271668 | AB16: 2.306613 | AC16: 2.34118 | AD16: 2.37536 | AE16: 2.409184 | AF16: 2.442582 | AG16: 0.023
A17: Total | B17: Residential Equipment: Equipment Stock: Main Space Heaters: Total: High Zero-Carbon Technology Cost | C17: AEO.2025.HIGHZTC.EQNR_STK_RESD_MSHR_TOT_NA_NA_MILL.A | D17: millions | F17: 123.79816 | G17: 125.16825 | H17: 126.62237 | I17: 128.09319 | J17: 129.56972 | K17: 131.08366 | L17: 132.59764 | M17: 134.11356 | N17: 135.61403 | O17: 137.06177 | P17: 138.44466 | Q17: 139.80519 | R17: 141.13614 | S17: 142.41052 | T17: 143.6335 | U17: 144.80035 | V17: 145.9243 | W17: 146.99674 | X17: 148.03105 | Y17: 149.02486 | Z17: 149.99976 | AA17: 150.97473 | AB17: 151.94659 | AC17: 152.91716 | AD17: 153.88637 | AE17: 154.8553 | AF17: 155.82082 | AG17: 0.009
A18: Space Cooling (million units)
A19: Electric Heat Pumps | B19: Residential Equipment: Equipment Stock: Space Cooling: Electric Heat Pumps: High Zero-Carbon Technology Cost | C19: AEO.2025.HIGHZTC.EQNR_STK_RESD_SPC_EHP_NA_NA_MILL.A | D19: millions | F19: 16.645529 | G19: 16.962236 | H19: 17.297932 | I19: 17.637352 | J19: 17.975958 | K19: 18.323191 | L19: 18.671116 | M19: 19.02029 | N19: 19.36697 | O19: 19.701841 | P19: 20.022339 | Q19: 20.338339 | R19: 20.648117 | S19: 20.945915 | T19: 21.232161 | U19: 21.506636 | V19: 21.772034 | W19: 22.026175 | X19: 22.271376 | Y19: 22.506746 | Z19: 22.737047 | AA19: 22.966528 | AB19: 23.194815 | AC19: 23.422672 | AD19: 23.650103 | AE19: 23.87734 | AF19: 24.103531 | AG19: 0.014
A20: Natural Gas Heat Pumps | B20: Residential Equipment: Equipment Stock: Space Cooling: Natural Gas Heat Pumps: High Zero-Carbon Technology Cost | C20: AEO.2025.HIGHZTC.EQNR_STK_RESD_SPC_NHU_NA_NA_MILL.A | D20: millions | F20: 1.335856 | G20: 1.335485 | H20: 1.335121 | I20: 1.334763 | J20: 1.334412 | K20: 1.334066 | L20: 1.333727 | M20: 1.333394 | N20: 1.333067 | O20: 1.332746 | P20: 1.33243 | Q20: 1.33212 | R20: 1.331816 | S20: 1.331517 | T20: 1.331223 | U20: 1.330934 | V20: 1.330651 | W20: 1.330372 | X20: 1.330099 | Y20: 1.329831 | Z20: 1.329567 | AA20: 1.329308 | AB20: 1.329053 | AC20: 1.328803 | AD20: 1.328558 | AE20: 1.328316 | AF20: 1.32808 | AG20: 0
A21: Geothermal Heat Pumps | B21: Residential Equipment: Equipment Stock: Space Cooling: Geothermal Heat Pumps: High Zero-Carbon Technology Cost | C21: AEO.2025.HIGHZTC.EQNR_STK_RESD_SPC_GEHP_NA_NA_MILL.A | D21: millions | F21: 1.360675 | G21: 1.40818 | H21: 1.455491 | I21: 1.50272 | J21: 1.549134 | K21: 1.595817 | L21: 1.642326 | M21: 1.688836 | N21: 1.73555 | O21: 1.781671 | P21: 1.826768 | Q21: 1.871948 | R21: 1.916753 | S21: 1.960756 | T21: 2.00379 | U21: 2.045475 | V21: 2.086105 | W21: 2.125626 | X21: 2.164013 | Y21: 2.200764 | Z21: 2.236356 | AA21: 2.271667 | AB21: 2.306613 | AC21: 2.341179 | AD21: 2.37536 | AE21: 2.409185 | AF21: 2.442581 | AG21: 0.023
A22: Central Air Conditioners | B22: Residential Equipment: Equipment Stock: Space Cooling: Central Air Conditioners: High Zero-Carbon Technology Cost | C22: AEO.2025.HIGHZTC.EQNR_STK_RESD_SPC_CAC_NA_NA_MILL.A | D22: millions | F22: 79.649452 | G22: 80.900047 | H22: 82.197365 | I22: 83.50415 | J22: 84.811256 | K22: 86.135658 | L22: 87.457458 | M22: 88.779007 | N22: 90.091568 | O22: 91.374115 | P22: 92.619194 | Q22: 93.851295 | R22: 95.065895 | S22: 96.248184 | T22: 97.400749 | U22: 98.520065 | V22: 99.614029 | W22: 100.67795 | X22: 101.7196 | Y22: 102.7365 | Z22: 103.74096 | AA22: 104.74514 | AB22: 105.74709 | AC22: 106.74812 | AD22: 107.74809 | AE22: 108.7477 | AF22: 109.74496 | AG22: 0.012
A23: Room Air Conditioners | B23: Residential Equipment: Equipment Stock: Space Cooling: Room Air Conditioners: High Zero-Carbon Technology Cost | C23: AEO.2025.HIGHZTC.EQNR_STK_RESD_SPC_RAC_NA_NA_MILL.A | D23: millions | F23: 43.140507 | G23: 43.232368 | H23: 43.345276 | I23: 43.46328 | J23: 43.586712 | K23: 43.719509 | L23: 43.854378 | M23: 43.990795 | N23: 44.124844 | O23: 44.250751 | P23: 44.367279 | Q23: 44.480221 | R23: 44.589432 | S23: 44.690407 | T23: 44.784588 | U23: 44.872437 | V23: 44.956017 | W23: 45.033756 | X23: 45.107018 | Y23: 45.177341 | Z23: 45.247604 | AA23: 45.318493 | AB23: 45.389637 | AC23: 45.461102 | AD23: 45.53299 | AE23: 45.605553 | AF23: 45.678272 | AG23: 0.002
A24: Total | B24: Residential Equipment: Equipment Stock: Space Cooling: Total: High Zero-Carbon Technology Cost | C24: AEO.2025.HIGHZTC.EQNR_STK_RESD_SPC_TOT_NA_NA_MILL.A | D24: millions | F24: 142.13202 | G24: 143.83832 | H24: 145.63118 | I24: 147.44226 | J24: 149.25748 | K24: 151.10825 | L24: 152.95901 | M24: 154.81233 | N24: 156.65199 | O24: 158.44113 | P24: 160.16801 | Q24: 161.87393 | R24: 163.55202 | S24: 165.17679 | T24: 166.75252 | U24: 168.27554 | V24: 169.75884 | W24: 171.19388 | X24: 172.5921 | Y24: 173.95119 | Z24: 175.29153 | AA24: 176.63113 | AB24: 177.96719 | AC24: 179.30188 | AD24: 180.6351 | AE24: 181.96808 | AF24: 183.29742 | AG24: 0.01
A25: Water Heaters (million units)
A26: Electric | B26: Residential Equipment: Equipment Stock: Water Heaters: Electric: High Zero-Carbon Technology Cost | C26: AEO.2025.HIGHZTC.EQNR_STK_RESD_WHT_ELE_NA_NA_MILL.A | D26: millions | F26: 62.064091 | G26: 62.296463 | H26: 62.600315 | I26: 62.92688 | J26: 63.228168 | K26: 64.053841 | L26: 64.829208 | M26: 65.567513 | N26: 66.280678 | O26: 66.984314 | P26: 67.653503 | Q26: 68.314453 | R26: 68.97834 | S26: 69.632027 | T26: 70.273941 | U26: 70.902107 | V26: 71.522514 | W26: 72.129929 | X26: 72.728317 | Y26: 73.317879 | Z26: 73.899185 | AA26: 74.478477 | AB26: 75.054726 | AC26: 75.626358 | AD26: 76.193161 | AE26: 76.757141 | AF26: 77.316254 | AG26: 0.008
A27: Natural Gas | B27: Residential Equipment: Equipment Stock: Water Heaters: Natural Gas: High Zero-Carbon Technology Cost | C27: AEO.2025.HIGHZTC.EQNR_STK_RESD_WHT_NG_NA_NA_MILL.A | D27: millions | F27: 64.896248 | G27: 65.896965 | H27: 66.916298 | I27: 67.939789 | J27: 68.981888 | K27: 69.718719 | L27: 70.479591 | M27: 71.256226 | N27: 72.025871 | O27: 72.786705 | P27: 73.528267 | Q27: 74.274551 | R27: 74.990112 | S27: 75.663231 | T27: 76.299583 | U27: 76.895554 | V27: 77.45697 | W27: 77.980125 | X27: 78.47403 | Y27: 78.935936 | Z27: 79.385979 | AA27: 79.836296 | AB27: 80.28476 | AC27: 80.734146 | AD27: 81.184738 | AE27: 81.635727 | AF27: 82.086113 | AG27: 0.009
A28: Distillate Fuel Oil | B28: Residential Equipment: Equipment Stock: Water Heaters: Distillate Fuel Oil: High Zero-Carbon Technology Cost | C28: AEO.2025.HIGHZTC.EQNR_STK_RESD_WHT_DFO_NA_NA_MILL.A | D28: millions | F28: 2.328812 | G28: 2.229761 | H28: 2.137233 | I28: 2.050461 | J28: 1.970477 | K28: 1.896038 | L28: 1.830604 | M28: 1.773455 | N28: 1.724959 | O28: 1.685178 | P28: 1.65441 | Q28: 1.632862 | R28: 1.610081 | S28: 1.586346 | T28: 1.561976 | U28: 1.537204 | V28: 1.512282 | W28: 1.487386 | X28: 1.462679 | Y28: 1.438287 | Z28: 1.414327 | AA28: 1.390946 | AB28: 1.368182 | AC28: 1.346109 | AD28: 1.32476 | AE28: 1.304158 | AF28: 1.284297 | AG28: -0.023
A29: Propane | B29: Residential Equipment: Equipment Stock: Water Heaters: Propane: High Zero-Carbon Technology Cost | C29: AEO.2025.HIGHZTC.EQNR_STK_RESD_WHT_PROP_NA_NA_MILL.A | D29: millions | F29: 3.994673 | G29: 3.890314 | H29: 3.796247 | I29: 3.708011 | J29: 3.626368 | K29: 3.531686 | L29: 3.447552 | M29: 3.374222 | N29: 3.31144 | O29: 3.259597 | P29: 3.218467 | Q29: 3.18944 | R29: 3.157171 | S29: 3.122084 | T29: 3.084893 | U29: 3.04617 | V29: 3.007124 | W29: 2.967928 | X29: 2.928841 | Y29: 2.889926 | Z29: 2.851814 | AA29: 2.814927 | AB29: 2.779243 | AC29: 2.745224 | AD29: 2.712765 | AE29: 2.681901 | AF29: 2.652292 | AG29: -0.016
A30: Solar Thermal | B30: Residential Equipment: Equipment Stock: Water Heaters: Solar Thermal: High Zero-Carbon Technology Cost | C30: AEO.2025.HIGHZTC.EQNR_STK_RESD_WHT_SLR_THERM_NA_MILL.A | D30: millions | F30: 1.564945 | G30: 1.899681 | H30: 2.211646 | I30: 2.501981 | J30: 2.791456 | K30: 2.906761 | L30: 3.028901 | M30: 3.155326 | N30: 3.279312 | O30: 3.349281 | P30: 3.38851 | Q30: 3.387712 | R30: 3.389602 | S30: 3.391462 | T30: 3.393306 | U30: 3.395105 | V30: 3.396857 | W30: 3.398571 | X30: 3.400233 | Y30: 3.401839 | Z30: 3.403495 | AA30: 3.405192 | AB30: 3.40693 | AC30: 3.408704 | AD30: 3.410507 | AE30: 3.412341 | AF30: 3.414205 | AG30: 0.03
A31: Total | B31: Residential Equipment: Equipment Stock: Water Heaters: Total: High Zero-Carbon Technology Cost | C31: AEO.2025.HIGHZTC.EQNR_STK_RESD_WHT_TOT_NA_NA_MILL.A | D31: millions | F31: 134.84877 | G31: 136.21318 | H31: 137.66174 | I31: 139.12712 | J31: 140.59836 | K31: 142.10706 | L31: 143.61586 | M31: 145.12672 | N31: 146.62227 | O31: 148.06508 | P31: 149.44313 | Q31: 150.79901 | R31: 152.12529 | S31: 153.39516 | T31: 154.61371 | U31: 155.77615 | V31: 156.89575 | W31: 157.96393 | X31: 158.99411 | Y31: 159.98387 | Z31: 160.95477 | AA31: 161.92584 | AB31: 162.89384 | AC31: 163.86055 | AD31: 164.82593 | AE31: 165.79126 | AF31: 166.75317 | AG31: 0.008
A32: Cooking Equipment (million units)
A33: Electric | B33: Residential Equipment: Equipment Stock: Cooking Equipment: Electric: High Zero-Carbon Technology Cost | C33: AEO.2025.HIGHZTC.EQNR_STK_RESD_CER_ELE_NA_NA_MILL.A | D33: millions | F33: 100.27812 | G33: 101.10259 | H33: 101.98053 | I33: 102.8632 | J33: 103.74537 | K33: 104.65044 | L33: 105.55076 | M33: 106.44516 | N33: 107.31894 | O33: 108.1434 | P33: 108.88472 | Q33: 109.57114 | R33: 110.1867 | S33: 110.70435 | T33: 111.20811 | U33: 111.71865 | V33: 112.24985 | W33: 112.80871 | X33: 113.41383 | Y33: 113.98341 | Z33: 114.53365 | AA33: 115.07655 | AB33: 115.60883 | AC33: 116.13017 | AD33: 116.6391 | AE33: 117.13462 | AF33: 117.61186 | AG33: 0.006
A34: Natural Gas | B34: Residential Equipment: Equipment Stock: Cooking Equipment: Natural Gas: High Zero-Carbon Technology Cost | C34: AEO.2025.HIGHZTC.EQNR_STK_RESD_CER_NG_NA_NA_MILL.A | D34: millions | F34: 53.97237 | G34: 54.503727 | H34: 55.061764 | I34: 55.632816 | J34: 56.213551 | K34: 56.80965 | L34: 57.412582 | M34: 58.02486 | N34: 58.644409 | O34: 59.262939 | P34: 59.903133 | Q34: 60.579704 | R34: 61.301079 | S34: 62.067856 | T34: 62.795506 | U34: 63.458031 | V34: 64.053505 | W34: 64.565849 | X34: 64.989624 | Y34: 65.410423 | Z34: 65.83329 | AA34: 66.264915 | AB34: 66.705818 | AC34: 67.157867 | AD34: 67.622643 | AE34: 68.102386 | AF34: 68.598465 | AG34: 0.009
A35: Propane | B35: Residential Equipment: Equipment Stock: Cooking Equipment: Propane: High Zero-Carbon Technology Cost | C35: AEO.2025.HIGHZTC.EQNR_STK_RESD_CER_PROP_NA_NA_MILL.A | D35: millions | F35: 6.249792 | G35: 6.24914 | H35: 6.252706 | I35: 6.255498 | J35: 6.255161 | K35: 6.254043 | L35: 6.251281 | M35: 6.247181 | N35: 6.241242 | O35: 6.233177 | P35: 6.221874 | Q35: 6.207108 | R35: 6.1889 | S35: 6.166887 | T35: 6.14676 | U35: 6.128918 | V35: 6.114851 | W35: 6.104977 | X35: 6.099405 | Y35: 6.092152 | Z35: 6.083468 | AA35: 6.07354 | AB35: 6.062016 | AC35: 6.049131 | AD35: 6.034698 | AE35: 6.018864 | AF35: 6.001561 | AG35: -0.002
A36: Total | B36: Residential Equipment: Equipment Stock: Cooking Equipment: Total: High Zero-Carbon Technology Cost | C36: AEO.2025.HIGHZTC.EQNR_STK_RESD_CER_TOT_NA_NA_MILL.A | D36: millions | F36: 160.50027 | G36: 161.85547 | H36: 163.295 | I36: 164.75151 | J36: 166.21408 | K36: 167.71414 | L36: 169.21463 | M36: 170.71719 | N36: 172.20459 | O36: 173.63953 | P36: 175.00974 | Q36: 176.35796 | R36: 177.67668 | S36: 178.93909 | T36: 180.15037 | U36: 181.3056 | V36: 182.41821 | W36: 183.47954 | X36: 184.50285 | Y36: 185.48598 | Z36: 186.45041 | AA36: 187.41501 | AB36: 188.37665 | AC36: 189.33717 | AD36: 190.29645 | AE36: 191.25586 | AF36: 192.21188 | AG36: 0.007
A37: Clothes Dryers (million units)
A38: Electric | B38: Residential Equipment: Equipment Stock: Clothes Dryers: Electric: High Zero-Carbon Technology Cost | C38: AEO.2025.HIGHZTC.EQNR_STK_RESD_CDR_ELE_NA_NA_MILL.A | D38: millions | F38: 92.221107 | G38: 94.908974 | H38: 97.661568 | I38: 100.4443 | J38: 103.24648 | K38: 106.05999 | L38: 108.87318 | M38: 111.66229 | N38: 114.41385 | O38: 117.12387 | P38: 119.78091 | Q38: 122.4272 | R38: 125.05272 | S38: 127.63446 | T38: 130.17616 | U38: 132.67476 | V38: 135.14604 | W38: 137.59196 | X38: 139.98711 | Y38: 142.33012 | Z38: 144.64094 | AA38: 146.94054 | AB38: 149.23036 | AC38: 151.51019 | AD38: 153.78226 | AE38: 156.04994 | AF38: 158.30891 | AG38: 0.021
A39: Natural Gas | B39: Residential Equipment: Equipment Stock: Clothes Dryers: Natural Gas: High Zero-Carbon Technology Cost | C39: AEO.2025.HIGHZTC.EQNR_STK_RESD_CDR_NG_NA_NA_MILL.A | D39: millions | F39: 20.353802 | G39: 20.727465 | H39: 21.108976 | I39: 21.498468 | J39: 21.905369 | K39: 22.331652 | L39: 22.776669 | M39: 23.24667 | N39: 23.740404 | O39: 24.225313 | P39: 24.699818 | Q39: 25.166246 | R39: 25.623446 | S39: 26.068548 | T39: 26.501984 | U39: 26.919897 | V39: 27.319826 | W39: 27.699757 | X39: 28.090372 | Y39: 28.489046 | Z39: 28.897078 | AA39: 29.31538 | AB39: 29.741957 | AC39: 30.175976 | AD39: 30.615866 | AE39: 31.060276 | AF39: 31.508205 | AG39: 0.017
A40: Total | B40: Residential Equipment: Equipment Stock: Clothes Dryers: Total: High Zero-Carbon Technology Cost | C40: AEO.2025.HIGHZTC.EQNR_STK_RESD_CDR_TOT_NA_NA_MILL.A | D40: millions | F40: 112.57491 | G40: 115.63644 | H40: 118.77055 | I40: 121.94276 | J40: 125.15185 | K40: 128.39165 | L40: 131.64984 | M40: 134.90897 | N40: 138.15425 | O40: 141.34918 | P40: 144.48073 | Q40: 147.59345 | R40: 150.67616 | S40: 153.703 | T40: 156.67815 | U40: 159.59465 | V40: 162.46587 | W40: 165.29172 | X40: 168.07748 | Y40: 170.81917 | Z40: 173.53803 | AA40: 176.25592 | AB40: 178.97232 | AC40: 181.68617 | AD40: 184.39812 | AE40: 187.11021 | AF40: 189.81712 | AG40: 0.02
A41: Other Appliances (million units)
A42: Refrigerators | B42: Residential Equipment: Equipment Stock: Other Appliances: Refrigerators: High Zero-Carbon Technology Cost | C42: AEO.2025.HIGHZTC.EQNR_STK_RESD_OTAR_RFG_NA_NA_MILL.A | D42: millions | F42: 185.51213 | G42: 187.57016 | H42: 189.72298 | I42: 191.89264 | J42: 194.05687 | K42: 196.26173 | L42: 198.46158 | M42: 200.66261 | N42: 202.84566 | O42: 204.9603 | P42: 206.98817 | Q42: 208.9885 | R42: 210.94859 | S42: 212.83372 | T42: 214.6485 | U42: 216.38301 | V42: 218.05542 | W42: 219.65475 | X42: 221.20091 | Y42: 222.68465 | Z42: 224.13631 | AA42: 225.58777 | AB42: 227.03429 | AC42: 228.47902 | AD42: 229.9216 | AE42: 231.36346 | AF42: 232.79994 | AG42: 0.009
A43: Freezers | B43: Residential Equipment: Equipment Stock: Other Appliances: Freezers: High Zero-Carbon Technology Cost | C43: AEO.2025.HIGHZTC.EQNR_STK_RESD_OTAR_FRZ_NA_NA_MILL.A | D43: millions | F43: 48.421524 | G43: 48.897556 | H43: 49.389957 | I43: 49.883247 | J43: 50.367458 | K43: 50.854794 | L43: 51.338001 | M43: 51.821068 | N43: 52.302494 | O43: 52.772449 | P43: 53.225803 | Q43: 53.674511 | R43: 54.115623 | S43: 54.542957 | T43: 54.956287 | U43: 55.352367 | V43: 55.735516 | W43: 56.103615 | X43: 56.460857 | Y43: 56.802979 | Z43: 57.136333 | AA43: 57.469646 | AB43: 57.801506 | AC43: 58.133106 | AD43: 58.464127 | AE43: 58.794895 | AF43: 59.124157 | AG43: 0.008
A44: Stock Average Equipment Efficiency
A45: Main Space Heaters
A46: Electric Heat Pumps (HSPF) | B46: Residential Equipment: Stock Average Efficiency: Main Space Heaters: Electric Heat Pumps: High Zero-Carbon Technology Cost | C46: AEO.2025.HIGHZTC.EFI_STK_RESD_SPHR_EHP_NA_NA_HSPF.A | D46: HSPF | F46: 8.301575 | G46: 8.411783 | H46: 8.524261 | I46: 8.639673 | J46: 8.759115 | K46: 8.870728 | L46: 8.974126 | M46: 9.069015 | N46: 9.155725 | O46: 9.226506 | P46: 9.289591 | Q46: 9.344809 | R46: 9.392457 | S46: 9.432801 | T46: 9.465774 | U46: 9.491529 | V46: 9.511662 | W46: 9.523355 | X46: 9.525758 | Y46: 9.528441 | Z46: 9.531271 | AA46: 9.534098 | AB46: 9.536915 | AC46: 9.539699 | AD46: 9.542423 | AE46: 9.545066 | AF46: 9.547633 | AG46: 0.005
A47: Natural Gas Heat Pumps (GCOP) | B47: Residential Equipment: Stock Average Efficiency: Main Space Heaters: Natural Gas Heat Pumps: High Zero-Carbon Technology Cost | C47: AEO.2025.HIGHZTC.EFI_STK_RESD_SPHR_NHU_NA_NA_GCOP.A | D47: GCOP | F47: 1.3 | G47: 1.3 | H47: 1.3 | I47: 1.3 | J47: 1.3 | K47: 1.3 | L47: 1.3 | M47: 1.3 | N47: 1.3 | O47: 1.3 | P47: 1.3 | Q47: 1.3 | R47: 1.3 | S47: 1.3 | T47: 1.3 | U47: 1.3 | V47: 1.3 | W47: 1.3 | X47: 1.3 | Y47: 1.3 | Z47: 1.3 | AA47: 1.3 | AB47: 1.3 | AC47: 1.3 | AD47: 1.3 | AE47: 1.3 | AF47: 1.3 | AG47: 0
A48: Geothermal Heat Pumps (COP) | B48: Residential Equipment: Stock Average Efficiency: Main Space Heaters: Geothermal Heat Pumps: High Zero-Carbon Technology Cost | C48: AEO.2025.HIGHZTC.EFI_STK_RESD_SPHR_GEHP_NA_NA_COP.A | D48: COP | F48: 3.198018 | G48: 3.229836 | H48: 3.260657 | I48: 3.290383 | J48: 3.318929 | K48: 3.346405 | L48: 3.372804 | M48: 3.398271 | N48: 3.421792 | O48: 3.4418 | P48: 3.459232 | Q48: 3.469077 | R48: 3.477528 | S48: 3.485055 | T48: 3.491715 | U48: 3.497602 | V48: 3.502827 | W48: 3.507296 | X48: 3.511081 | Y48: 3.514184 | Z48: 3.516665 | AA48: 3.51842 | AB48: 3.519624 | AC48: 3.520261 | AD48: 3.520312 | AE48: 3.519931 | AF48: 3.519072 | AG48: 0.004
A49: Natural Gas Furnace (AFUE) | B49: Residential Equipment: Stock Average Efficiency: Main Space Heaters: Natural Gas Furnace: High Zero-Carbon Technology Cost | C49: AEO.2025.HIGHZTC.EFI_STK_RESD_SPHR_NFR_NA_NA_AFUE.A | D49: AFUE | F49: 0.81869 | G49: 0.823765 | H49: 0.828838 | I49: 0.833879 | J49: 0.838906 | K49: 0.847897 | L49: 0.857558 | M49: 0.867226 | N49: 0.876317 | O49: 0.884643 | P49: 0.8924 | Q49: 0.899578 | R49: 0.906261 | S49: 0.912422 | T49: 0.918101 | U49: 0.923289 | V49: 0.928013 | W49: 0.932266 | X49: 0.936086 | Y49: 0.939438 | Z49: 0.942309 | AA49: 0.944658 | AB49: 0.946467 | AC49: 0.948268 | AD49: 0.950024 | AE49: 0.951704 | AF49: 0.953277 | AG49: 0.006
A50: Distillate Furnace (AFUE) | B50: Residential Equipment: Stock Average Efficiency: Main Space Heaters: Distillate Furnace: High Zero-Carbon Technology Cost | C50: AEO.2025.HIGHZTC.EFI_STK_RESD_SPHR_DFR_NA_NA_AFUE.A | D50: AFUE | F50: 0.835821 | G50: 0.83737 | H50: 0.838934 | I50: 0.840479 | J50: 0.841988 | K50: 0.843465 | L50: 0.844934 | M50: 0.846412 | N50: 0.847821 | O50: 0.849073 | P50: 0.850235 | Q50: 0.851286 | R50: 0.852252 | S50: 0.85311 | T50: 0.853878 | U50: 0.854555 | V50: 0.855138 | W50: 0.855625 | X50: 0.856018 | Y50: 0.856314 | Z50: 0.856506 | AA50: 0.856586 | AB50: 0.856572 | AC50: 0.856558 | AD50: 0.856545 | AE50: 0.856532 | AF50: 0.856519 | AG50: 0.001
A51: Space Cooling
A52: Electric Heat Pumps (SEER) | B52: Residential Equipment: Stock Average Efficiency: Space Cooling: Electric Heat Pumps: High Zero-Carbon Technology Cost | C52: AEO.2025.HIGHZTC.EFI_STK_RESD_SPC_EHP_NA_NA_SEER.A | D52: SEER | F52: 13.990335 | G52: 14.225822 | H52: 14.465521 | I52: 14.710986 | J52: 14.964726 | K52: 15.201395 | L52: 15.42023 | M52: 15.62071 | N52: 15.803606 | O52: 15.951933 | P52: 16.083612 | Q52: 16.198576 | R52: 16.297474 | S52: 16.380913 | T52: 16.448742 | U52: 16.501339 | V52: 16.546972 | W52: 16.574265 | X52: 16.58153 | Y52: 16.589703 | Z52: 16.598383 | AA52: 16.607206 | AB52: 16.616085 | AC52: 16.624941 | AD52: 16.633642 | AE52: 16.642115 | AF52: 16.650322 | AG52: 0.007
A53: Natural Gas Heat Pumps (GCOP) | B53: Residential Equipment: Stock Average Efficiency: Space Cooling: Natural Gas Heat Pumps: High Zero-Carbon Technology Cost | C53: AEO.2025.HIGHZTC.EFI_STK_RESD_SPC_NHU_NA_NA_GCOP.A | D53: GCOP | F53: 0.623339 | G53: 0.628984 | H53: 0.634922 | I53: 0.641268 | J53: 0.64812 | K53: 0.654681 | L53: 0.660912 | M53: 0.666764 | N53: 0.672238 | O53: 0.677284 | P53: 0.681912 | Q53: 0.686074 | R53: 0.689759 | S53: 0.692949 | T53: 0.695604 | U53: 0.697704 | V53: 0.699202 | W53: 0.7 | X53: 0.7 | Y53: 0.7 | Z53: 0.7 | AA53: 0.7 | AB53: 0.7 | AC53: 0.7 | AD53: 0.7 | AE53: 0.7 | AF53: 0.7 | AG53: 0.004
A54: Geothermal Heat Pumps (EER) | B54: Residential Equipment: Stock Average Efficiency: Space Cooling: Geothermal Heat Pumps: High Zero-Carbon Technology Cost | C54: AEO.2025.HIGHZTC.EFI_STK_RESD_SPC_GEHP_NA_NA_EER.A | D54: EER | F54: 13.993668 | G54: 14.221729 | H54: 14.442514 | I54: 14.655156 | J54: 14.858943 | K54: 15.054792 | L54: 15.24262 | M54: 15.423491 | N54: 15.590322 | O54: 15.732929 | P54: 15.857524 | Q54: 15.92991 | R54: 15.991646 | S54: 16.046743 | T54: 16.095617 | U54: 16.138885 | V54: 16.177298 | W54: 16.210196 | X54: 16.238113 | Y54: 16.261044 | Z54: 16.279423 | AA54: 16.292555 | AB54: 16.301682 | AC54: 16.306694 | AD54: 16.307491 | AE54: 16.305126 | AF54: 16.299299 | AG54: 0.006
A55: Central Air Conditioners (SEER) | B55: Residential Equipment: Stock Average Efficiency: Space Cooling: Central Air Conditioners: High Zero-Carbon Technology Cost | C55: AEO.2025.HIGHZTC.EFI_STK_RESD_SPC_CAC_NA_NA_SEER.A | D55: SEER | F55: 13.469368 | G55: 13.76048 | H55: 14.051945 | I55: 14.34586 | J55: 14.645688 | K55: 14.925357 | L55: 15.18473 | M55: 15.422161 | N55: 15.637525 | O55: 15.709616 | P55: 15.752591 | Q55: 15.78285 | R55: 15.799917 | S55: 15.80462 | T55: 15.79846 | U55: 15.781046 | V55: 15.75336 | W55: 15.715132 | X55: 15.665411 | Y55: 15.616528 | Z55: 15.568357 | AA55: 15.521166 | AB55: 15.475282 | AC55: 15.430945 | AD55: 15.388376 | AE55: 15.347758 | AF55: 15.309222 | AG55: 0.005
A56: Room Air Conditioners (EER) | B56: Residential Equipment: Stock Average Efficiency: Space Cooling: Room Air Conditioners: High Zero-Carbon Technology Cost | C56: AEO.2025.HIGHZTC.EFI_STK_RESD_SPC_RAC_NA_NA_EER.A | D56: EER | F56: 11.448732 | G56: 11.644737 | H56: 11.847325 | I56: 12.298437 | J56: 12.757018 | K56: 13.272966 | L56: 13.771557 | M56: 14.233994 | N56: 14.651569 | O56: 15.024332 | P56: 15.341799 | Q56: 15.580716 | R56: 15.738295 | S56: 15.813057 | T56: 15.872056 | U56: 15.916222 | V56: 15.947607 | W56: 15.968753 | X56: 15.982252 | Y56: 15.990417 | Z56: 15.995095 | AA56: 15.997622 | AB56: 15.998911 | AC56: 15.999532 | AD56: 15.999801 | AE56: 15.999924 | AF56: 15.999976 | AG56: 0.013
A57: Water Heaters
A58: Electric (EF) | B58: Residential Equipment: Stock Average Efficiency: Water Heaters: Electric: High Zero-Carbon Technology Cost | C58: AEO.2025.HIGHZTC.EFI_STK_RESD_WHT_ELE_NA_NA_EF.A | D58: EF | F58: 1.089594 | G58: 1.142516 | H58: 1.194647 | I58: 1.245785 | J58: 1.296718 | K58: 1.427567 | L58: 1.530845 | M58: 1.640694 | N58: 1.744714 | O58: 1.833205 | P58: 1.91778 | Q58: 1.995061 | R58: 2.064635 | S58: 2.126171 | T58: 2.179694 | U58: 2.225028 | V58: 2.262446 | W58: 2.291731 | X58: 2.312705 | Y58: 2.325641 | Z58: 2.33766 | AA58: 2.348729 | AB58: 2.358847 | AC58: 2.368028 | AD58: 2.376319 | AE58: 2.383758 | AF58: 2.390381 | AG58: 0.031
A59: Natural Gas (EF) | B59: Residential Equipment: Stock Average Efficiency: Water Heaters: Natural Gas: High Zero-Carbon Technology Cost | C59: AEO.2025.HIGHZTC.EFI_STK_RESD_WHT_NG_NA_NA_EF.A | D59: EF | F59: 0.605986 | G59: 0.613774 | H59: 0.620732 | I59: 0.626879 | J59: 0.632248 | K59: 0.640281 | L59: 0.647174 | M59: 0.653142 | N59: 0.658141 | O59: 0.660803 | P59: 0.662594 | Q59: 0.663523 | R59: 0.664392 | S59: 0.665197 | T59: 0.665936 | U59: 0.666609 | V59: 0.667216 | W59: 0.667758 | X59: 0.668238 | Y59: 0.66866 | Z59: 0.669028 | AA59: 0.669346 | AB59: 0.669618 | AC59: 0.669849 | AD59: 0.670043 | AE59: 0.670204 | AF59: 0.670337 | AG59: 0.004
A60: Distillate Fuel Oil (EF) | B60: Residential Equipment: Stock Average Efficiency: Water Heaters: Distillate Fuel Oil: High Zero-Carbon Technology Cost | C60: AEO.2025.HIGHZTC.EFI_STK_RESD_WHT_DFO_NA_NA_EF.A | D60: EF | F60: 0.547698 | G60: 0.559994 | H60: 0.572179 | I60: 0.583994 | J60: 0.59521 | K60: 0.60664 | L60: 0.616759 | M60: 0.625502 | N60: 0.632547 | O60: 0.637645 | P60: 0.640544 | Q60: 0.641082 | R60: 0.641634 | S60: 0.642193 | T60: 0.642754 | U60: 0.643312 | V60: 0.643862 | W60: 0.644401 | X60: 0.644925 | Y60: 0.64543 | Z60: 0.645913 | AA60: 0.646374 | AB60: 0.646809 | AC60: 0.647219 | AD60: 0.647602 | AE60: 0.647957 | AF60: 0.648285 | AG60: 0.007
A61: Propane (EF) | B61: Residential Equipment: Stock Average Efficiency: Water Heaters: Propane: High Zero-Carbon Technology Cost | C61: AEO.2025.HIGHZTC.EFI_STK_RESD_WHT_PROP_NA_NA_EF.A | D61: EF | F61: 0.609399 | G61: 0.618704 | H61: 0.627502 | I61: 0.635687 | J61: 0.643129 | K61: 0.650474 | L61: 0.656896 | M61: 0.662416 | N61: 0.666918 | O61: 0.669209 | P61: 0.670362 | Q61: 0.670312 | R61: 0.670217 | S61: 0.670084 | T61: 0.669917 | U61: 0.669723 | V61: 0.669505 | W61: 0.66927 | X61: 0.669022 | Y61: 0.668766 | Z61: 0.668508 | AA61: 0.668249 | AB61: 0.667995 | AC61: 0.667748 | AD61: 0.667511 | AE61: 0.667286 | AF61: 0.667075 | AG61: 0.003
A62: Other Appliances (kilowatthours per year)
A63: Refrigerators | B63: Residential Equipment: Stock Average Efficiency: Other Appliances: Refrigerators: High Zero-Carbon Technology Cost | C63: AEO.2025.HIGHZTC.EFI_STK_RESD_OTAR_RFG_NA_NA_KWH.A | D63: kWh | F63: 605.32141 | G63: 596.56372 | H63: 587.74408 | I63: 578.85461 | J63: 569.90594 | K63: 561.435 | L63: 548.93573 | M63: 536.88129 | N63: 525.27539 | O63: 514.09534 | P63: 503.3385 | Q63: 493.03497 | R63: 483.48178 | S63: 474.76013 | T63: 466.87344 | U63: 459.84949 | V63: 453.64551 | W63: 448.24676 | X63: 443.6087 | Y63: 439.75659 | Z63: 436.64328 | AA63: 434.2933 | AB63: 432.73151 | AC63: 431.93127 | AD63: 431.20816 | AE63: 430.55432 | AF63: 429.9595 | AG63: -0.013
A64: Freezers | B64: Residential Equipment: Stock Average Efficiency: Other Appliances: Freezers: High Zero-Carbon Technology Cost | C64: AEO.2025.HIGHZTC.EFI_STK_RESD_OTAR_FRZ_NA_NA_KWH.A | D64: kWh | F64: 463.55093 | G64: 458.8902 | H64: 454.28131 | I64: 449.72031 | J64: 445.12622 | K64: 440.45502 | L64: 433.68933 | M64: 426.78296 | N64: 419.79501 | O64: 413.10068 | P64: 406.70032 | Q64: 400.59753 | R64: 394.77927 | S64: 389.23379 | T64: 383.98914 | U64: 379.0647 | V64: 374.43823 | W64: 370.16132 | X64: 366.20215 | Y64: 362.57892 | Z64: 359.272 | AA64: 356.2627 | AB64: 353.61423 | AC64: 351.29883 | AD64: 349.36639 | AE64: 347.84357 | AF64: 346.73441 | AG64: -0.011
A65: Building Shell Efficiency Index
A66: Space Heating
A67: Pre-2020 Homes | B67: Residential Equipment: Building Shell Efficiency Index: Space Heating: Pre-2015 Homes: High Zero-Carbon Technology Cost | C67: AEO.2025.HIGHZTC.EFI_BSE_RESD_SPH_OLD_NA_NA_Y15EQ1.A | D67: 2015=1.00 | F67: 0.962499 | G67: 0.958293 | H67: 0.953861 | I67: 0.948976 | J67: 0.94338 | K67: 0.937139 | L67: 0.930514 | M67: 0.923414 | N67: 0.915817 | O67: 0.907954 | P67: 0.900289 | Q67: 0.89305 | R67: 0.886269 | S67: 0.879715 | T67: 0.873158 | U67: 0.86666 | V67: 0.860093 | W67: 0.853337 | X67: 0.846504 | Y67: 0.83967 | Z67: 0.83285 | AA67: 0.826026 | AB67: 0.819144 | AC67: 0.81229 | AD67: 0.805503 | AE67: 0.798702 | AF67: 0.791856 | AG67: -0.007
A68: New Construction | B68: Residential Equipment: Building Shell Efficiency Index: Space Heating: New Construction: High Zero-Carbon Technology Cost | C68: AEO.2025.HIGHZTC.EFI_BSE_RESD_SPH_NCO_NA_NA_Y15EQ1.A | D68: 2015=1.00 | F68: 0.777795 | G68: 0.777804 | H68: 0.788456 | I68: 0.791936 | J68: 0.797173 | K68: 0.796403 | L68: 0.797131 | M68: 0.795607 | N68: 0.791438 | O68: 0.90783 | P68: 0.903509 | Q68: 0.903332 | R68: 0.901356 | S68: 0.896882 | T68: 0.893279 | U68: 0.890833 | V68: 0.88829 | W68: 0.884528 | X68: 0.881262 | Y68: 0.880932 | Z68: 0.881812 | AA68: 0.880657 | AB68: 0.879689 | AC68: 0.87822 | AD68: 0.877219 | AE68: 0.876159 | AF68: 0.875121 | AG68: 0.005
A69: All Homes | B69: Residential Equipment: Building Shell Efficiency Index: Space Heating: All Homes: High Zero-Carbon Technology Cost | C69: AEO.2025.HIGHZTC.EFI_BSE_RESD_SPH_AHM_NA_NA_Y15EQ1.A | D69: 2015=1.00 | F69: 0.955143 | G69: 0.949095 | H69: 0.943004 | I69: 0.936667 | J69: 0.929901 | K69: 0.922678 | L69: 0.9153 | M69: 0.907667 | N69: 0.899751 | O69: 0.893162 | P69: 0.88683 | Q69: 0.880983 | R69: 0.87561 | S69: 0.870475 | T69: 0.865393 | U69: 0.860418 | V69: 0.855445 | W69: 0.850361 | X69: 0.845263 | Y69: 0.840229 | Z69: 0.83528 | AA69: 0.830391 | AB69: 0.82552 | AC69: 0.820726 | AD69: 0.816043 | AE69: 0.811407 | AF69: 0.806791 | AG69: -0.006
A70: Space Cooling
A71: Pre-2020 Homes | B71: Residential Equipment: Building Shell Efficiency Index: Space Cooling: Pre-2015 Homes: High Zero-Carbon Technology Cost | C71: AEO.2025.HIGHZTC.EFI_BSE_RESD_SPC_OLD_NA_NA_Y15EQ1.A | D71: 2015=1.00 | F71: 0.987064 | G71: 0.985772 | H71: 0.98427 | I71: 0.982508 | J71: 0.980458 | K71: 0.978187 | L71: 0.975783 | M71: 0.973246 | N71: 0.970565 | O71: 0.967795 | P71: 0.965096 | Q71: 0.962539 | R71: 0.960132 | S71: 0.957803 | T71: 0.955471 | U71: 0.953172 | V71: 0.950855 | W71: 0.948457 | X71: 0.946022 | Y71: 0.943575 | Z71: 0.941128 | AA71: 0.938696 | AB71: 0.936247 | AC71: 0.933813 | AD71: 0.931396 | AE71: 0.928972 | AF71: 0.92653 | AG71: -0.002
A72: New Construction | B72: Residential Equipment: Building Shell Efficiency Index: Space Cooling: New Construction: High Zero-Carbon Technology Cost | C72: AEO.2025.HIGHZTC.EFI_BSE_RESD_SPC_NCO_NA_NA_Y15EQ1.A | D72: 2015=1.00 | F72: 0.962238 | G72: 0.963735 | H72: 0.972506 | I72: 0.975369 | J72: 0.97906 | K72: 0.982037 | L72: 0.982878 | M72: 0.982742 | N72: 0.980868 | O72: 1.020371 | P72: 1.018169 | Q72: 1.017907 | R72: 1.016993 | S72: 1.014689 | T72: 1.012976 | U72: 1.012075 | V72: 1.01144 | W72: 1.010168 | X72: 1.008936 | Y72: 1.00961 | Z72: 1.010903 | AA72: 1.010773 | AB72: 1.010664 | AC72: 1.010374 | AD72: 1.010311 | AE72: 1.010293 | AF72: 1.0102 | AG72: 0.002
A73: All Homes | B73: Residential Equipment: Building Shell Efficiency Index: Space Cooling: All Homes: High Zero-Carbon Technology Cost | C73: AEO.2025.HIGHZTC.EFI_BSE_RESD_SPC_AHM_NA_NA_Y15EQ1.A | D73: 2015=1.00 | F73: 0.987118 | G73: 0.985658 | H73: 0.98411 | I73: 0.982377 | J73: 0.980453 | K73: 0.978394 | L73: 0.976264 | M73: 0.974055 | N73: 0.971739 | O73: 0.969759 | P73: 0.96783 | Q73: 0.966045 | R73: 0.964396 | S73: 0.9628 | T73: 0.961193 | U73: 0.959611 | V73: 0.958014 | W73: 0.956344 | X73: 0.954641 | Y73: 0.952937 | Z73: 0.951251 | AA73: 0.949591 | AB73: 0.947931 | AC73: 0.946295 | AD73: 0.944687 | AE73: 0.943085 | AF73: 0.941481 | AG73: -0.002
A74: Distributed Generation and
A75: Combined Heat and Power
A76: Generating Capacity (gigawatts)
A77: Natural Gas Fuel Cells | B77: Residential: Combined Heat and Power: Generating Capacity: Fuel Cells: High Zero-Carbon Technology Cost | C77: AEO.2025.HIGHZTC.CAP_NA_COMM_CHP_FCL_NA_NA_MW.A | D77: GW | F77: 0.001725 | G77: 0.003088 | H77: 0.003101 | I77: 0.003114 | J77: 0.003127 | K77: 0.00314 | L77: 0.003153 | M77: 0.003166 | N77: 0.003179 | O77: 0.003192 | P77: 0.003205 | Q77: 0.003218 | R77: 0.003231 | S77: 0.003244 | T77: 0.003257 | U77: 0.00327 | V77: 0.003285 | W77: 0.003301 | X77: 0.003322 | Y77: 0.003352 | Z77: 0.003399 | AA77: 0.003478 | AB77: 0.003618 | AC77: 0.003759 | AD77: 0.0039 | AE77: 0.004042 | AF77: 0.004185 | AG77: 0.035
A78: Solar Photovoltaic | B78: Residential: Combined Heat and Power: Generating Capacity: Solar Photovoltaic: High Zero-Carbon Technology Cost | C78: AEO.2025.HIGHZTC.CAP_NA_RESD_CHP_SLR_PHTVL_NA_MW.A | D78: GW | F78: 41.307827 | G78: 47.377987 | H78: 53.527718 | I78: 59.344631 | J78: 65.296082 | K78: 71.340698 | L78: 77.804955 | M78: 84.770462 | N78: 91.686966 | O78: 98.871689 | P78: 105.99403 | Q78: 111.56861 | R78: 117.32034 | S78: 123.13393 | T78: 129.23361 | U78: 135.37601 | V78: 141.64864 | W78: 147.97232 | X78: 154.48625 | Y78: 161.0881 | Z78: 167.79971 | AA78: 174.75017 | AB78: 181.85144 | AC78: 189.17082 | AD78: 196.66997 | AE78: 204.34807 | AF78: 212.12654 | AG78: 0.065
A79: Wind | B79: Residential: Combined Heat and Power: Generating Capacity: Wind: High Zero-Carbon Technology Cost | C79: AEO.2025.HIGHZTC.CAP_NA_RESD_CHP_WND_NA_NA_MW.A | D79: GW | F79: 0.308179 | G79: 0.560921 | H79: 0.806044 | I79: 0.908432 | J79: 1.022869 | K79: 1.146172 | L79: 1.390895 | M79: 1.690819 | N79: 1.994769 | O79: 2.108177 | P79: 2.161123 | Q79: 2.162338 | R79: 2.163817 | S79: 2.165545 | T79: 2.167536 | U79: 2.169726 | V79: 2.172139 | W79: 2.1748 | X79: 2.177634 | Y79: 2.18058 | Z79: 2.183634 | AA79: 2.186825 | AB79: 2.190188 | AC79: 2.193648 | AD79: 2.197246 | AE79: 2.200986 | AF79: 2.20487 | AG79: 0.079
A80: Total | B80: Residential: Combined Heat and Power: Generating Capacity: Total: High Zero-Carbon Technology Cost | C80: AEO.2025.HIGHZTC.CAP_NA_RESD_CHP_TOT_NA_NA_MW.A | D80: GW | F80: 41.617729 | G80: 47.941998 | H80: 54.336864 | I80: 60.256176 | J80: 66.322075 | K80: 72.490013 | L80: 79.198997 | M80: 86.464447 | N80: 93.684914 | O80: 100.98305 | P80: 108.15836 | Q80: 113.73417 | R80: 119.4874 | S80: 125.30272 | T80: 131.4044 | U80: 137.549 | V80: 143.82405 | W80: 150.15042 | X80: 156.66721 | Y80: 163.27203 | Z80: 169.98675 | AA80: 176.94047 | AB80: 184.04524 | AC80: 191.36822 | AD80: 198.87112 | AE80: 206.5531 | AF80: 214.33559 | AG80: 0.065
A81: Net Generation (billion kilowatthours)
A82: Natural Gas Fuel Cells | B82: Residential: Combined Heat and Power: Net Generation: Fuel Cells: High Zero-Carbon Technology Cost | C82: AEO.2025.HIGHZTC.GEN_NA_COMM_CHP_FCL_NA_NA_MILLKWH.A | D82: billion kWh | F82: 0.006833 | G82: 0.01223 | H82: 0.012281 | I82: 0.012333 | J82: 0.012384 | K82: 0.012436 | L82: 0.012487 | M82: 0.012539 | N82: 0.01259 | O82: 0.012642 | P82: 0.012693 | Q82: 0.012744 | R82: 0.012796 | S82: 0.012847 | T82: 0.012899 | U82: 0.012951 | V82: 0.013007 | W82: 0.013071 | X82: 0.013154 | Y82: 0.013272 | Z82: 0.013459 | AA82: 0.013774 | AB82: 0.014328 | AC82: 0.014885 | AD82: 0.015444 | AE82: 0.016007 | AF82: 0.016572 | AG82: 0.035
A83: Solar Photovoltaic | B83: Residential: Combined Heat and Power: Net Generation: Solar Photovoltaic: High Zero-Carbon Technology Cost | C83: AEO.2025.HIGHZTC.GEN_NA_COMM_CHP_SLR_PHTVL_NA_MILLKWH.A | D83: billion kWh | F83: 62.697704 | G83: 71.294235 | H83: 79.992973 | I83: 88.17804 | J83: 96.523483 | K83: 104.96889 | L83: 113.99036 | M83: 123.68132 | N83: 133.25902 | O83: 143.18649 | P83: 153.01392 | Q83: 160.67247 | R83: 168.56346 | S83: 176.51448 | T83: 184.85332 | U83: 193.22803 | V83: 201.7585 | W83: 210.33153 | X83: 219.14546 | Y83: 228.05829 | Z83: 237.09641 | AA83: 246.437 | AB83: 255.9633 | AC83: 265.76538 | AD83: 275.78906 | AE83: 286.03299 | AF83: 296.38397 | AG83: 0.062
A84: Wind | B84: Residential: Combined Heat and Power: Net Generation: Wind: High Zero-Carbon Technology Cost | C84: AEO.2025.HIGHZTC.GEN_NA_COMM_CHP_WND_NA_NA_MILLKWH.A | D84: billion kWh | F84: 0.36942 | G84: 0.627201 | H84: 0.879623 | I84: 0.996866 | J84: 1.127979 | K84: 1.269903 | L84: 1.541979 | M84: 1.900119 | N84: 2.263994 | O84: 2.387514 | P84: 2.444973 | Q84: 2.446357 | R84: 2.448035 | S84: 2.44999 | T84: 2.452236 | U84: 2.4547 | V84: 2.457409 | W84: 2.460389 | X84: 2.463559 | Y84: 2.466848 | Z84: 2.470254 | AA84: 2.473806 | AB84: 2.477537 | AC84: 2.481375 | AD84: 2.485367 | AE84: 2.489517 | AF84: 2.493827 | AG84: 0.076
A85: Total | B85: Residential: Combined Heat and Power: Net Generation: Total: High Zero-Carbon Technology Cost | C85: AEO.2025.HIGHZTC.GEN_NA_COMM_CHP_TOT_NA_NA_MILLKWH.A | D85: billion kWh | F85: 63.073956 | G85: 71.933662 | H85: 80.88488 | I85: 89.187233 | J85: 97.663849 | K85: 106.25123 | L85: 115.54483 | M85: 125.59397 | N85: 135.5356 | O85: 145.58664 | P85: 155.47159 | Q85: 163.13156 | R85: 171.02429 | S85: 178.97733 | T85: 187.31845 | U85: 195.69568 | V85: 204.22891 | W85: 212.80499 | X85: 221.62218 | Y85: 230.53841 | Z85: 239.58012 | AA85: 248.92458 | AB85: 258.45517 | AC85: 268.26166 | AD85: 278.28989 | AE85: 288.53851 | AF85: 298.89438 | AG85: 0.062
A86: Disposition
A87: Sales to the Grid | B87: Residential: Combined Heat and Power: Net Generation: Sales to the Grid: High Zero-Carbon Technology Cost | C87: AEO.2025.HIGHZTC.GEN_NA_COMM_CHP_STG_NA_NA_MILLKWH.A | D87: billion kWh | F87: 11.527926 | G87: 13.327675 | H87: 15.115705 | I87: 16.711512 | J87: 18.336744 | K87: 19.964907 | L87: 21.847279 | M87: 23.999292 | N87: 26.07505 | O87: 28.288122 | P87: 30.488134 | Q87: 32.147984 | R87: 33.877605 | S87: 35.58342 | T87: 37.42905 | U87: 39.226177 | V87: 41.04538 | W87: 42.813847 | X87: 44.644409 | Y87: 46.466736 | Z87: 48.275852 | AA87: 50.168255 | AB87: 52.062748 | AC87: 54.058846 | AD87: 56.059513 | AE87: 58.126335 | AF87: 60.175503 | AG87: 0.066
A88: Generation for Own Use | B88: Residential: Combined Heat and Power: Net Generation: Generation for Own Use: High Zero-Carbon Technology Cost | C88: AEO.2025.HIGHZTC.GEN_NA_COMM_CHP_GFO_NA_NA_MILLKWH.A | D88: billion kWh | F88: 51.546032 | G88: 58.605991 | H88: 65.769173 | I88: 72.475723 | J88: 79.32711 | K88: 86.286324 | L88: 93.697556 | M88: 101.59469 | N88: 109.46055 | O88: 117.29853 | P88: 124.98345 | Q88: 130.98358 | R88: 137.14668 | S88: 143.39391 | T88: 149.88939 | U88: 156.4695 | V88: 163.18352 | W88: 169.99115 | X88: 176.97777 | Y88: 184.07167 | Z88: 191.30428 | AA88: 198.75633 | AB88: 206.39241 | AC88: 214.20282 | AD88: 222.23038 | AE88: 230.41217 | AF88: 238.71884 | AG88: 0.061
A89: Energy Input (trillion Btu)
A90: Natural Gas Fuel Cells | B90: Residential: Combined Heat and Power: Energy Input: Fuel Cells: High Zero-Carbon Technology Cost | C90: AEO.2025.HIGHZTC.CNSM_NA_COMM_CHP_FCL_NA_NA_TRLBTU.A | D90: trillion Btu | F90: 0.052159 | G90: 0.093352 | H90: 0.093745 | I90: 0.094138 | J90: 0.094531 | K90: 0.094924 | L90: 0.095317 | M90: 0.09571 | N90: 0.096103 | O90: 0.096496 | P90: 0.096889 | Q90: 0.097282 | R90: 0.097675 | S90: 0.098068 | T90: 0.098461 | U90: 0.09886 | V90: 0.099284 | W90: 0.099774 | X90: 0.100407 | Y90: 0.101309 | Z90: 0.102735 | AA90: 0.105142 | AB90: 0.109371 | AC90: 0.113619 | AD90: 0.117891 | AE90: 0.122184 | AF90: 0.126495 | AG90: 0.035
A91: Solar Photovoltaic | B91: Residential: Combined Heat and Power: Energy Input: Solar Photovoltaic: High Zero-Carbon Technology Cost | C91: AEO.2025.HIGHZTC.CNSM_NA_COMM_CHP_SLR_PHTVL_NA_TRLBTU.A | D91: trillion Btu | F91: 213.92456 | G91: 243.25592 | H91: 272.93601 | I91: 300.86346 | J91: 329.3381 | K91: 358.15387 | L91: 388.93512 | M91: 422.00061 | N91: 454.67975 | O91: 488.55231 | P91: 522.08344 | Q91: 548.21448 | R91: 575.13855 | S91: 602.26739 | T91: 630.71948 | U91: 659.29395 | V91: 688.3999 | W91: 717.65118 | X91: 747.72437 | Y91: 778.13477 | Z91: 808.97296 | AA91: 840.84302 | AB91: 873.34674 | AC91: 906.7915 | AD91: 940.99225 | AE91: 975.94446 | AF91: 1011.262 | AG91: 0.062
A92: Wind | B92: Residential: Combined Heat and Power: Energy Input: Wind: High Zero-Carbon Technology Cost | C92: AEO.2025.HIGHZTC.CNSM_NA_COMM_CHP_WND_NA_NA_TRLBTU.A | D92: trillion Btu | F92: 1.26046 | G92: 2.140008 | H92: 3.001273 | I92: 3.401307 | J92: 3.848665 | K92: 4.332908 | L92: 5.261231 | M92: 6.483206 | N92: 7.724746 | O92: 8.146197 | P92: 8.342248 | Q92: 8.34697 | R92: 8.352695 | S92: 8.359365 | T92: 8.367029 | U92: 8.375438 | V92: 8.38468 | W92: 8.394847 | X92: 8.405662 | Y92: 8.416884 | Z92: 8.428505 | AA92: 8.440624 | AB92: 8.453354 | AC92: 8.46645 | AD92: 8.480072 | AE92: 8.494232 | AF92: 8.508938 | AG92: 0.076
A93: Total | B93: Residential: Combined Heat and Power: Energy Input: Total: High Zero-Carbon Technology Cost | C93: AEO.2025.HIGHZTC.CNSM_NA_COMM_CHP_TOT_NA_NA_TRLBTU.A | D93: trillion Btu | F93: 215.23717 | G93: 245.48929 | H93: 276.03104 | I93: 304.35892 | J93: 333.28131 | K93: 362.5817 | L93: 394.29166 | M93: 428.57953 | N93: 462.50058 | O93: 496.79501 | P93: 530.52252 | Q93: 556.65875 | R93: 583.58893 | S93: 610.72485 | T93: 639.18494 | U93: 667.76825 | V93: 696.88391 | W93: 726.14581 | X93: 756.23041 | Y93: 786.65295 | Z93: 817.50421 | AA93: 849.38879 | AB93: 881.90949 | AC93: 915.37158 | AD93: 949.59021 | AE93: 984.56091 | AF93: 1019.8973 | AG93: 0.062

Sheet AEO23_table_22._Comm
A1: Table 22. Commercial Sector Energy Consumption, Floorspace, Equipment Efficiency, and Distributed Generation
A2: https://www.eia.gov/outlooks/aeo/data/browser/#/?id=32-AEO2023&cases=ref2023&sourcekey=0
A3: Sun May 04 2025 20:16:27 GMT-0700 (Pacific Daylight Time)
A4: Source: U.S. Energy Information Administration
B5: full name | C5: api key | D5: units | E5: 2021 | F5: 2022 | G5: 2023 | H5: 2024 | I5: 2025 | J5: 2026 | K5: 2027 | L5: 2028 | M5: 2029 | N5: 2030 | O5: 2031 | P5: 2032 | Q5: 2033 | R5: 2034 | S5: 2035 | T5: 2036 | U5: 2037 | V5: 2038 | W5: 2039 | X5: 2040 | Y5: 2041 | Z5: 2042 | AA5: 2043 | AB5: 2044 | AC5: 2045 | AD5: 2046 | AE5: 2047 | AF5: 2048 | AG5: 2049 | AH5: 2050 | AI5: Growth (2022-2050)
A6: Commercial Building Delivered
A7: Energy Consumption (quadrillion Btu)
A8: Assembly | B8: Commercial: Gross End-use: Assembly: Reference case | C8: AEO.2023.REF2023.#N/A.A | D8: quads | F8: 0.645733 | G8: 0.628144 | H8: 0.62174 | I8: 0.627551 | J8: 0.631386 | K8: 0.633341 | L8: 0.634329 | M8: 0.634228 | N8: 0.633376 | O8: 0.632204 | P8: 0.631712 | Q8: 0.629789 | R8: 0.62738 | S8: 0.624869 | T8: 0.622415 | U8: 0.619707 | V8: 0.616438 | W8: 0.613268 | X8: 0.609889 | Y8: 0.60662 | Z8: 0.603497 | AA8: 0.600765 | AB8: 0.598298 | AC8: 0.595616 | AD8: 0.592323 | AE8: 0.589637 | AF8: 0.587393 | AG8: 0.585342 | AH8: 0.583169 | AI8: -0.004
A9: Education | B9: Commercial: Gross End-use: Education: Reference case | C9: AEO.2023.REF2023.#N/A.A | D9: quads | F9: 1.023192 | G9: 1.003815 | H9: 1.000211 | I9: 1.013541 | J9: 1.024501 | K9: 1.032973 | L9: 1.040353 | M9: 1.045932 | N9: 1.049982 | O9: 1.053062 | P9: 1.057371 | Q9: 1.059303 | R9: 1.060372 | S9: 1.061235 | T9: 1.06226 | U9: 1.062465 | V9: 1.061857 | W9: 1.061067 | X9: 1.060739 | Y9: 1.060583 | Z9: 1.06075 | AA9: 1.061631 | AB9: 1.062934 | AC9: 1.064115 | AD9: 1.065007 | AE9: 1.066551 | AF9: 1.06862 | AG9: 1.070613 | AH9: 1.072455 | AI9: 0.002
A10: Food Sales | B10: Commercial: Gross End-use: Food Sales: Reference case | C10: AEO.2023.REF2023.#N/A.A | D10: quads | F10: 0.376753 | G10: 0.374265 | H10: 0.375342 | I10: 0.378536 | J10: 0.381119 | K10: 0.382864 | L10: 0.384441 | M10: 0.385803 | N10: 0.386818 | O10: 0.388211 | P10: 0.389563 | Q10: 0.39031 | R10: 0.390741 | S10: 0.391055 | T10: 0.391202 | U10: 0.391069 | V10: 0.39059 | W10: 0.389942 | X10: 0.389324 | Y10: 0.389086 | Z10: 0.388913 | AA10: 0.388801 | AB10: 0.388769 | AC10: 0.388698 | AD10: 0.388394 | AE10: 0.388341 | AF10: 0.388475 | AG10: 0.388726 | AH10: 0.388975 | AI10: 0.001
A11: Food Service | B11: Commercial: Gross End-use: Food Service: Reference case | C11: AEO.2023.REF2023.#N/A.A | D11: quads | F11: 0.559557 | G11: 0.551407 | H11: 0.557413 | I11: 0.565627 | J11: 0.572108 | K11: 0.576674 | L11: 0.580489 | M11: 0.583597 | N11: 0.585853 | O11: 0.588401 | P11: 0.590744 | Q11: 0.592037 | R11: 0.592774 | S11: 0.593398 | T11: 0.594019 | U11: 0.594302 | V11: 0.593912 | W11: 0.593581 | X11: 0.59289 | Y11: 0.592554 | Z11: 0.592391 | AA11: 0.592601 | AB11: 0.593097 | AC11: 0.593406 | AD11: 0.592836 | AE11: 0.592862 | AF11: 0.593445 | AG11: 0.594274 | AH11: 0.595011 | AI11: 0.002
A12: Health Care | B12: Commercial: Gross End-use: Health Care: Reference case | C12: AEO.2023.REF2023.#N/A.A | D12: quads | F12: 0.537446 | G12: 0.525337 | H12: 0.528509 | I12: 0.538635 | J12: 0.547313 | K12: 0.554273 | L12: 0.560439 | M12: 0.56541 | N12: 0.569363 | O12: 0.573106 | P12: 0.576964 | Q12: 0.579783 | R12: 0.582157 | S12: 0.584465 | T12: 0.586925 | U12: 0.589071 | V12: 0.590614 | W12: 0.592249 | X12: 0.593927 | Y12: 0.595674 | Z12: 0.597665 | AA12: 0.600155 | AB12: 0.603081 | AC12: 0.605845 | AD12: 0.608112 | AE12: 0.610984 | AF12: 0.614403 | AG12: 0.617943 | AH12: 0.621364 | AI12: 0.005
A13: Lodging | B13: Commercial: Gross End-use: Lodging: Reference case | C13: AEO.2023.REF2023.#N/A.A | D13: quads | F13: 0.596199 | G13: 0.589345 | H13: 0.595147 | I13: 0.604807 | J13: 0.613311 | K13: 0.620434 | L13: 0.627071 | M13: 0.633023 | N13: 0.63844 | O13: 0.643374 | P13: 0.649181 | Q13: 0.65363 | R13: 0.657586 | S13: 0.661524 | T13: 0.66545 | U13: 0.669019 | V13: 0.67191 | W13: 0.674736 | X13: 0.677333 | Y13: 0.679942 | Z13: 0.68261 | AA13: 0.685634 | AB13: 0.688987 | AC13: 0.691996 | AD13: 0.694103 | AE13: 0.696796 | AF13: 0.699991 | AG13: 0.703246 | AH13: 0.706087 | AI13: 0.006
A14: Office - Large | B14: Commercial: Gross End-use: Office - Large: Reference case | C14: AEO.2023.REF2023.#N/A.A | D14: quads | F14: 0.906171 | G14: 0.890402 | H14: 0.889829 | I14: 0.899311 | J14: 0.907485 | K14: 0.913852 | L14: 0.919879 | M14: 0.924673 | N14: 0.928521 | O14: 0.932099 | P14: 0.936194 | Q14: 0.938945 | R14: 0.941428 | S14: 0.944112 | T14: 0.947333 | U14: 0.950204 | V14: 0.952675 | W14: 0.955222 | X14: 0.958763 | Y14: 0.962846 | Z14: 0.967718 | AA14: 0.97365 | AB14: 0.98056 | AC14: 0.987933 | AD14: 0.995871 | AE14: 1.005302 | AF14: 1.016063 | AG14: 1.027597 | AH14: 1.039765 | AI14: 0.005
A15: Office - Small | B15: Commercial: Gross End-use: Office - Small: Reference case | C15: AEO.2023.REF2023.#N/A.A | D15: quads | F15: 0.620077 | G15: 0.609582 | H15: 0.607109 | I15: 0.613284 | J15: 0.618099 | K15: 0.621356 | L15: 0.624245 | M15: 0.626456 | N15: 0.62797 | O15: 0.628755 | P15: 0.630648 | Q15: 0.63105 | R15: 0.631021 | S15: 0.630952 | T15: 0.630982 | U15: 0.630597 | V15: 0.629736 | W15: 0.628835 | X15: 0.628013 | Y15: 0.627388 | Z15: 0.62698 | AA15: 0.6269 | AB15: 0.626923 | AC15: 0.626934 | AD15: 0.626788 | AE15: 0.626966 | AF15: 0.627466 | AG15: 0.62805 | AH15: 0.628609 | AI15: 0
A16: Mercantile/Service | B16: Commercial: Gross End-use: Mercantile/Service: Reference case | C16: AEO.2023.REF2023.#N/A.A | D16: quads | F16: 1.411627 | G16: 1.386703 | H16: 1.377442 | I16: 1.392811 | J16: 1.404702 | K16: 1.412897 | L16: 1.419597 | M16: 1.424017 | N16: 1.425929 | O16: 1.427025 | P16: 1.429976 | Q16: 1.429622 | R16: 1.428147 | S16: 1.426421 | T16: 1.424619 | U16: 1.421674 | V16: 1.417378 | W16: 1.412856 | X16: 1.408803 | Y16: 1.405292 | Z16: 1.402139 | AA16: 1.399782 | AB16: 1.398019 | AC16: 1.395774 | AD16: 1.3922 | AE16: 1.389886 | AF16: 1.388586 | AG16: 1.387521 | AH16: 1.386141 | AI16: -0.001
A17: Warehouse | B17: Commercial: Gross End-use: Warehouse: Reference case | C17: AEO.2023.REF2023.#N/A.A | D17: quads | F17: 0.450864 | G17: 0.451145 | H17: 0.454155 | I17: 0.463089 | J17: 0.471026 | K17: 0.478129 | L17: 0.485102 | M17: 0.491822 | N17: 0.497912 | O17: 0.50345 | P17: 0.510037 | Q17: 0.515355 | R17: 0.520313 | S17: 0.525204 | T17: 0.53007 | U17: 0.534572 | V17: 0.538516 | W17: 0.542437 | X17: 0.546601 | Y17: 0.550947 | Z17: 0.555398 | AA17: 0.56006 | AB17: 0.564801 | AC17: 0.569487 | AD17: 0.573914 | AE17: 0.578711 | AF17: 0.583712 | AG17: 0.58879 | AH17: 0.593861 | AI17: 0.01
A18: Other | B18: Commercial: Gross End-use: Other: Reference case | C18: AEO.2023.REF2023.#N/A.A | D18: quads | F18: 0.403793 | G18: 0.400096 | H18: 0.395901 | I18: 0.402047 | J18: 0.407493 | K18: 0.412239 | L18: 0.41679 | M18: 0.420545 | N18: 0.423651 | O18: 0.426308 | P18: 0.429258 | Q18: 0.431418 | R18: 0.433246 | S18: 0.434947 | T18: 0.436626 | U18: 0.438 | V18: 0.439043 | W18: 0.439929 | X18: 0.441081 | Y18: 0.442205 | Z18: 0.443411 | AA18: 0.444822 | AB18: 0.446439 | AC18: 0.448004 | AD18: 0.449416 | AE18: 0.451156 | AF18: 0.453161 | AG18: 0.455199 | AH18: 0.457203 | AI18: 0.004
A19: Total | B19: Commercial: Gross End-use: Total: Reference case | C19: AEO.2023.REF2023.#N/A.A | D19: quads | F19: 7.531413 | G19: 7.410243 | H19: 7.4028 | I19: 7.499238 | J19: 7.578544 | K19: 7.639032 | L19: 7.692736 | M19: 7.735506 | N19: 7.767814 | O19: 7.795995 | P19: 7.831648 | Q19: 7.851241 | R19: 7.865163 | S19: 7.878181 | T19: 7.891899 | U19: 7.900681 | V19: 7.902669 | W19: 7.904121 | X19: 7.907362 | Y19: 7.913136 | Z19: 7.92147 | AA19: 7.934801 | AB19: 7.951907 | AC19: 7.96781 | AD19: 7.978965 | AE19: 7.997193 | AF19: 8.021315 | AG19: 8.047301 | AH19: 8.07264 | AI19: 0.002
A20: Commercial Building Floorspace
A21: (billion square feet)
A22: Assembly | B22: Commercial: Floorspace: Assembly: Reference case | C22: AEO.2023.REF2023.KEI_FLR_COMM_ASB_NA_NA_NA_BLNSQFT.A | D22: billion sq ft | F22: 10.400917 | G22: 10.436387 | H22: 10.496305 | I22: 10.57352 | J22: 10.640577 | K22: 10.701997 | L22: 10.772717 | M22: 10.853343 | N22: 10.941223 | O22: 11.033052 | P22: 11.121057 | Q22: 11.20028 | R22: 11.270812 | S22: 11.332419 | T22: 11.38581 | U22: 11.432502 | V22: 11.472919 | W22: 11.507771 | X22: 11.538272 | Y22: 11.565514 | Z22: 11.59073 | AA22: 11.615142 | AB22: 11.639624 | AC22: 11.664806 | AD22: 11.691126 | AE22: 11.718759 | AF22: 11.747728 | AG22: 11.777931 | AH22: 11.809135 | AI22: 0.005
A23: Education | B23: Commercial: Floorspace: Education: Reference case | C23: AEO.2023.REF2023.KEI_FLR_COMM_EDD_NA_NA_NA_BLNSQFT.A | D23: billion sq ft | F23: 13.515454 | G23: 13.643662 | H23: 13.780691 | I23: 13.941533 | J23: 14.090282 | K23: 14.232786 | L23: 14.388822 | M23: 14.559372 | N23: 14.74106 | O23: 14.929582 | P23: 15.114496 | Q23: 15.289021 | R23: 15.453143 | S23: 15.606402 | T23: 15.749625 | U23: 15.884776 | V23: 16.012333 | W23: 16.133186 | X23: 16.24894 | Y23: 16.361061 | Z23: 16.471249 | AA23: 16.581207 | AB23: 16.692177 | AC23: 16.80508 | AD23: 16.920567 | AE23: 17.038923 | AF23: 17.160229 | AG23: 17.28437 | AH23: 17.411037 | AI23: 0.009
A24: Food Sales | B24: Commercial: Floorspace: Food Sales: Reference case | C24: AEO.2023.REF2023.KEI_FLR_COMM_FDSA_NA_NA_NA_BLNSQFT.A | D24: billion sq ft | F24: 1.291462 | G24: 1.296816 | H24: 1.305836 | I24: 1.317039 | J24: 1.32701 | K24: 1.336312 | L24: 1.346806 | M24: 1.358573 | N24: 1.371286 | O24: 1.384535 | P24: 1.397346 | Q24: 1.409095 | R24: 1.419791 | S24: 1.429398 | T24: 1.438004 | U24: 1.445796 | V24: 1.452825 | W24: 1.459178 | X24: 1.465006 | Y24: 1.470445 | Z24: 1.475653 | AA24: 1.480783 | AB24: 1.485946 | AC24: 1.491223 | AD24: 1.496672 | AE24: 1.502314 | AF24: 1.508155 | AG24: 1.514183 | AH24: 1.520367 | AI24: 0.006
A25: Food Service | B25: Commercial: Floorspace: Food Service: Reference case | C25: AEO.2023.REF2023.KEI_FLR_COMM_FSC_NA_NA_NA_BLNSQFT.A | D25: billion sq ft | F25: 1.888346 | G25: 1.896453 | H25: 1.909625 | I25: 1.925987 | J25: 1.940549 | K25: 1.954131 | L25: 1.969456 | M25: 1.986643 | N25: 2.005212 | O25: 2.024564 | P25: 2.043276 | Q25: 2.060434 | R25: 2.07605 | S25: 2.090076 | T25: 2.102637 | U25: 2.114007 | V25: 2.124261 | W25: 2.133526 | X25: 2.142023 | Y25: 2.149953 | Z25: 2.157542 | AA25: 2.165018 | AB25: 2.172542 | AC25: 2.180233 | AD25: 2.188173 | AE25: 2.196398 | AF25: 2.204911 | AG25: 2.213697 | AH25: 2.222713 | AI25: 0.006
A26: Health Care | B26: Commercial: Floorspace: Health Care: Reference case | C26: AEO.2023.REF2023.KEI_FLR_COMM_HLC_NA_NA_NA_BLNSQFT.A | D26: billion sq ft | F26: 2.701855 | G26: 2.733213 | H26: 2.769319 | I26: 2.81037 | J26: 2.849174 | K26: 2.886892 | L26: 2.927522 | M26: 2.971289 | N26: 3.017531 | O26: 3.065386 | P26: 3.112723 | Q26: 3.15814 | R26: 3.201612 | S26: 3.243025 | T26: 3.282532 | U26: 3.320521 | V26: 3.357078 | W26: 3.392376 | X26: 3.426738 | Y26: 3.460464 | Z26: 3.493907 | AA26: 3.527425 | AB26: 3.561281 | AC26: 3.595673 | AD26: 3.630744 | AE26: 3.66656 | AF26: 3.70314 | AG26: 3.740469 | AH26: 3.778483 | AI26: 0.012
A27: Lodging | B27: Commercial: Floorspace: Lodging: Reference case | C27: AEO.2023.REF2023.KEI_FLR_COMM_LGC_NA_NA_NA_BLNSQFT.A | D27: billion sq ft | F27: 6.687417 | G27: 6.7613 | H27: 6.851435 | I27: 6.953804 | J27: 7.050617 | K27: 7.144745 | L27: 7.246084 | M27: 7.35519 | N27: 7.470426 | O27: 7.589662 | P27: 7.707621 | Q27: 7.820828 | R27: 7.929226 | S27: 8.032525 | T27: 8.131104 | U27: 8.225924 | V27: 8.317192 | W27: 8.405338 | X27: 8.491166 | Y27: 8.575415 | Z27: 8.658957 | AA27: 8.742681 | AB27: 8.827238 | AC27: 8.91312 | AD27: 9.000679 | AE27: 9.090082 | AF27: 9.181379 | AG27: 9.274526 | AH27: 9.369368 | AI27: 0.012
A28: Office - Large | B28: Commercial: Floorspace: Office - Large: Reference case | C28: AEO.2023.REF2023.KEI_FLR_COMM_OFLC_NA_NA_NA_BLNSQFT.A | D28: billion sq ft | F28: 9.603739 | G28: 9.659845 | H28: 9.72727 | I28: 9.810922 | J28: 9.885389 | K28: 9.954844 | L28: 10.033158 | M28: 10.120936 | N28: 10.215735 | O28: 10.314505 | P28: 10.409986 | Q28: 10.497533 | R28: 10.577204 | S28: 10.648745 | T28: 10.712796 | U28: 10.770758 | V28: 10.823006 | W28: 10.870186 | X28: 10.913433 | Y28: 10.953755 | Z28: 10.99232 | AA28: 11.030277 | AB28: 11.068451 | AC28: 11.107449 | AD28: 11.147686 | AE28: 11.189342 | AF28: 11.232442 | AG28: 11.276896 | AH28: 11.322491 | AI28: 0.006
A29: Office - Small | B29: Commercial: Floorspace: Office - Small: Reference case | C29: AEO.2023.REF2023.KEI_FLR_COMM_OFSC_NA_NA_NA_BLNSQFT.A | D29: billion sq ft | F29: 9.134697 | G29: 9.196621 | H29: 9.27128 | I29: 9.361578 | J29: 9.443316 | K29: 9.52045 | L29: 9.606236 | M29: 9.70128 | N29: 9.803274 | O29: 9.909311 | P29: 10.012436 | Q29: 10.108168 | R29: 10.196538 | S29: 10.277281 | T29: 10.350986 | U29: 10.418979 | V29: 10.481609 | W29: 10.539486 | X29: 10.593686 | Y29: 10.645185 | Z29: 10.6951 | AA29: 10.744549 | AB29: 10.794334 | AC29: 10.84505 | AD29: 10.897103 | AE29: 10.950674 | AF29: 11.005796 | AG29: 11.062386 | AH29: 11.120239 | AI29: 0.007
A30: Mercantile/Service | B30: Commercial: Floorspace: Mercantile/Service: Reference case | C30: AEO.2023.REF2023.KEI_FLR_COMM_MCSC_NA_NA_NA_BLNSQFT.A | D30: billion sq ft | F30: 17.156851 | G30: 17.261364 | H30: 17.402252 | I30: 17.572483 | J30: 17.726637 | K30: 17.872143 | L30: 18.033882 | M30: 18.21299 | N30: 18.405138 | O30: 18.60487 | P30: 18.799126 | Q30: 18.979485 | R30: 19.146017 | S30: 19.29821 | T30: 19.437168 | U30: 19.565395 | V30: 19.683525 | W30: 19.792713 | X30: 19.894976 | Y30: 19.992142 | Z30: 20.086315 | AA30: 20.179588 | AB30: 20.273474 | AC30: 20.36908 | AD30: 20.467176 | AE30: 20.568098 | AF30: 20.671907 | AG30: 20.778452 | AH30: 20.887339 | AI30: 0.007
A31: Warehouse | B31: Commercial: Floorspace: Warehouse: Reference case | C31: AEO.2023.REF2023.KEI_FLR_COMM_WHRC_NA_NA_NA_BLNSQFT.A | D31: billion sq ft | F31: 15.59821 | G31: 15.909663 | H31: 16.170263 | I31: 16.460665 | J31: 16.739002 | K31: 17.01198 | L31: 17.303083 | M31: 17.613777 | N31: 17.940296 | O31: 18.277628 | P31: 18.613136 | Q31: 18.938387 | R31: 19.253145 | S31: 19.556597 | T31: 19.849546 | U31: 20.134249 | V31: 20.411131 | W31: 20.68116 | X31: 20.946251 | Y31: 21.208176 | Z31: 21.469057 | AA31: 21.731073 | AB31: 21.995848 | AC31: 22.264605 | AD31: 22.538246 | AE31: 22.817213 | AF31: 23.101664 | AG31: 23.3915 | AH31: 23.686375 | AI31: 0.015
A32: Other | B32: Commercial: Floorspace: Other: Reference case | C32: AEO.2023.REF2023.KEI_FLR_COMM_OTHU_NA_NA_NA_BLNSQFT.A | D32: billion sq ft | F32: 7.492591 | G32: 7.58013 | H32: 7.672274 | I32: 7.77797 | J32: 7.877273 | K32: 7.973412 | L32: 8.07744 | M32: 8.189959 | N32: 8.309116 | O32: 8.432521 | P32: 8.554302 | Q32: 8.670608 | R32: 8.781395 | S32: 8.886363 | T32: 8.985946 | U32: 9.08123 | V32: 9.172462 | W32: 9.260121 | X32: 9.345108 | Y32: 9.428247 | Z32: 9.510506 | AA32: 9.592859 | AB32: 9.676027 | AC32: 9.760542 | AD32: 9.84679 | AE32: 9.934951 | AF32: 10.025074 | AG32: 10.117102 | AH32: 10.210867 | AI32: 0.011
A33: Total | B33: Commercial: Floorspace: Total: Reference case | C33: AEO.2023.REF2023.KEI_FLR_COMM_NA_NA_NA_NA_BLNSQFT.A | D33: billion sq ft | F33: 95.471542 | G33: 96.37545 | H33: 97.356552 | I33: 98.505859 | J33: 99.569824 | K33: 100.58969 | L33: 101.7052 | M33: 102.92335 | N33: 104.22029 | O33: 105.56561 | P33: 106.88551 | Q33: 108.13197 | R33: 109.30492 | S33: 110.40104 | T33: 111.42615 | U33: 112.39414 | V33: 113.30834 | W33: 114.17503 | X33: 115.0056 | Y33: 115.81035 | Z33: 116.60134 | AA33: 117.3906 | AB33: 118.18694 | AC33: 118.99686 | AD33: 119.82497 | AE33: 120.67332 | AF33: 121.54242 | AG33: 122.43151 | AH33: 123.33842 | AI33: 0.009
A34: Stock Average Equipment Efficiency
A35: Space Heating
A36: Electricity | B36: Commercial: Stock Average Efficiency: Space Heating: Electricity: Reference case | C36: AEO.2023.REF2023.EFF_STKE_COMM_SPH_ELC_NA_NA_BTUOTPBTUIN.A | D36: Btu Out/Btu In | F36: 1.600274 | G36: 1.594243 | H36: 1.587098 | I36: 1.578912 | J36: 1.570767 | K36: 1.563012 | L36: 1.555431 | M36: 1.548036 | N36: 1.540515 | O36: 1.532912 | P36: 1.525505 | Q36: 1.517811 | R36: 1.510503 | S36: 1.503626 | T36: 1.496855 | U36: 1.49042 | V36: 1.48431 | W36: 1.478547 | X36: 1.47299 | Y36: 1.467513 | Z36: 1.462165 | AA36: 1.456975 | AB36: 1.451967 | AC36: 1.447101 | AD36: 1.442009 | AE36: 1.437024 | AF36: 1.43215 | AG36: 1.427428 | AH36: 1.422603 | AI36: -0.004
A37: Natural Gas | B37: Commercial: Stock Average Efficiency: Space Heating: Natural Gas: Reference case | C37: AEO.2023.REF2023.EFF_STKE_COMM_SPH_NG_NA_NA_BTUOTPBTUIN.A | D37: Btu Out/Btu In | F37: 0.790325 | G37: 0.791603 | H37: 0.792499 | I37: 0.793097 | J37: 0.793588 | K37: 0.794002 | L37: 0.794402 | M37: 0.794797 | N37: 0.795166 | O37: 0.795518 | P37: 0.795851 | Q37: 0.796166 | R37: 0.796463 | S37: 0.796747 | T37: 0.797016 | U37: 0.797268 | V37: 0.797498 | W37: 0.797719 | X37: 0.797928 | Y37: 0.798139 | Z37: 0.798332 | AA37: 0.798496 | AB37: 0.798634 | AC37: 0.798766 | AD37: 0.798905 | AE37: 0.799021 | AF37: 0.799131 | AG37: 0.799225 | AH37: 0.799317 | AI37: 0
A38: Distillate Fuel Oil | B38: Commercial: Stock Average Efficiency: Space Heating: Distillate Fuel Oil: Reference case | C38: AEO.2023.REF2023.EFF_STKE_COMM_SPH_DFO_NA_NA_BTUOTPBTUIN.A | D38: Btu Out/Btu In | F38: 0.811075 | G38: 0.811913 | H38: 0.812663 | I38: 0.813233 | J38: 0.813739 | K38: 0.814214 | L38: 0.81467 | M38: 0.815112 | N38: 0.815656 | O38: 0.816172 | P38: 0.816661 | Q38: 0.81712 | R38: 0.817553 | S38: 0.817961 | T38: 0.818347 | U38: 0.818712 | V38: 0.819057 | W38: 0.819381 | X38: 0.81994 | Y38: 0.820468 | Z38: 0.820969 | AA38: 0.821409 | AB38: 0.82182 | AC38: 0.822211 | AD38: 0.822579 | AE38: 0.822928 | AF38: 0.823258 | AG38: 0.823571 | AH38: 0.823868 | AI38: 0.001
A39: Space Cooling
A40: Electricity | B40: Commercial: Stock Average Efficiency: Space Cooling: Electricity: Reference case | C40: AEO.2023.REF2023.EFF_STKE_COMM_SPC_ELC_NA_NA_BTUOTPBTUIN.A | D40: Btu Out/Btu In | F40: 3.631937 | G40: 3.670844 | H40: 3.705795 | I40: 3.741041 | J40: 3.773756 | K40: 3.804141 | L40: 3.833991 | M40: 3.863452 | N40: 3.894044 | O40: 3.923628 | P40: 3.951355 | Q40: 3.978105 | R40: 4.003486 | S40: 4.02747 | T40: 4.049935 | U40: 4.071064 | V40: 4.091231 | W40: 4.110403 | X40: 4.132566 | Y40: 4.153564 | Z40: 4.173704 | AA40: 4.193167 | AB40: 4.21193 | AC40: 4.229976 | AD40: 4.247146 | AE40: 4.263546 | AF40: 4.279475 | AG40: 4.294493 | AH40: 4.308665 | AI40: 0.006
A41: Natural Gas | B41: Commercial: Stock Average Efficiency: Space Cooling: Natural Gas: Reference case | C41: AEO.2023.REF2023.EFF_STKE_COMM_SPC_NG_NA_NA_BTUOTPBTUIN.A | D41: Btu Out/Btu In | F41: 0.79191 | G41: 0.815889 | H41: 0.801778 | I41: 0.811522 | J41: 0.820885 | K41: 0.829966 | L41: 0.839108 | M41: 0.848253 | N41: 0.857472 | O41: 0.86655 | P41: 0.875432 | Q41: 0.884114 | R41: 0.892552 | S41: 0.90077 | T41: 0.908739 | U41: 0.916582 | V41: 0.924255 | W41: 0.931727 | X41: 0.939129 | Y41: 0.946474 | Z41: 0.953687 | AA41: 0.960795 | AB41: 0.967847 | AC41: 0.974895 | AD41: 0.982086 | AE41: 0.989328 | AF41: 0.996426 | AG41: 1.003511 | AH41: 1.010638 | AI41: 0.009
A42: Water Heating
A43: Electricity | B43: Commercial: Stock Average Efficiency: Water Heating: Electricity: Reference case | C43: AEO.2023.REF2023.EFF_STKE_COMM_WTHT_ELC_NA_NA_BTUOTPBTUIN.A | D43: Btu Out/Btu In | F43: 1.15897 | G43: 1.184838 | H43: 1.210067 | I43: 1.234157 | J43: 1.255187 | K43: 1.261848 | L43: 1.268374 | M43: 1.274774 | N43: 1.281186 | O43: 1.287499 | P43: 1.294107 | Q43: 1.30059 | R43: 1.307019 | S43: 1.313241 | T43: 1.319371 | U43: 1.325511 | V43: 1.331667 | W43: 1.337692 | X43: 1.343575 | Y43: 1.349317 | Z43: 1.354969 | AA43: 1.360491 | AB43: 1.365959 | AC43: 1.37123 | AD43: 1.376657 | AE43: 1.381959 | AF43: 1.387086 | AG43: 1.392069 | AH43: 1.396927 | AI43: 0.007
A44: Natural Gas | B44: Commercial: Stock Average Efficiency: Water Heating: Natural Gas: Reference case | C44: AEO.2023.REF2023.EFF_STKE_COMM_WTHT_NG_NA_NA_BTUOTPBTUIN.A | D44: Btu Out/Btu In | F44: 0.895232 | G44: 0.900596 | H44: 0.904943 | I44: 0.90891 | J44: 0.912434 | K44: 0.915599 | L44: 0.918505 | M44: 0.921151 | N44: 0.92355 | O44: 0.925713 | P44: 0.927647 | Q44: 0.929368 | R44: 0.930898 | S44: 0.93226 | T44: 0.933472 | U44: 0.934553 | V44: 0.935518 | W44: 0.936378 | X44: 0.937148 | Y44: 0.937837 | Z44: 0.938454 | AA44: 0.939008 | AB44: 0.939504 | AC44: 0.940205 | AD44: 0.940838 | AE44: 0.941408 | AF44: 0.941921 | AG44: 0.942382 | AH44: 0.942795 | AI44: 0.002
A45: Distillate Fuel Oil | B45: Commercial: Stock Average Efficiency: Water Heating: Distillate Fuel Oil: Reference case | C45: AEO.2023.REF2023.EFF_STKE_COMM_WTHT_DFO_NA_NA_BTUOTPBTUIN.A | D45: Btu Out/Btu In | F45: 0.807966 | G45: 0.808998 | H45: 0.80996 | I45: 0.810849 | J45: 0.811653 | K45: 0.812385 | L45: 0.813056 | M45: 0.813672 | N45: 0.814237 | O45: 0.814752 | P45: 0.81522 | Q45: 0.815644 | R45: 0.816028 | S45: 0.816377 | T45: 0.816692 | U45: 0.816983 | V45: 0.817244 | W45: 0.817485 | X45: 0.817701 | Y45: 0.817901 | Z45: 0.818083 | AA45: 0.81825 | AB45: 0.818401 | AC45: 0.81854 | AD45: 0.818667 | AE45: 0.818783 | AF45: 0.818888 | AG45: 0.818984 | AH45: 0.819071 | AI45: 0
A46: Ventilation (cubic feet per minute per Btu)
A47: Electricity | B47: Commercial: Stock Average Efficiency: Ventilation: Electricity: Reference case | C47: AEO.2023.REF2023.EFF_STKE_COMM_VNTC_ELC_NA_NA_CUFTPMINPBTU.A | D47: cu ft/minute/Btu | F47: 0.335243 | G47: 0.335928 | H47: 0.336595 | I47: 0.337237 | J47: 0.337879 | K47: 0.338488 | L47: 0.339075 | M47: 0.339638 | N47: 0.340535 | O47: 0.341409 | P47: 0.342242 | Q47: 0.343031 | R47: 0.34378 | S47: 0.344489 | T47: 0.345159 | U47: 0.345794 | V47: 0.346395 | W47: 0.346964 | X47: 0.347501 | Y47: 0.348013 | Z47: 0.348498 | AA47: 0.348956 | AB47: 0.349388 | AC47: 0.349795 | AD47: 0.350177 | AE47: 0.350535 | AF47: 0.35087 | AG47: 0.351182 | AH47: 0.351464 | AI47: 0.002
A48: Cooking
A49: Electricity | B49: Commercial: Stock Average Efficiency: Cooking: Electricity: Reference case | C49: AEO.2023.REF2023.EFF_STKE_COMM_CGR_ELC_NA_NA_BTUOTPBTUIN.A | D49: Btu Out/Btu In | F49: 0.693479 | G49: 0.694064 | H49: 0.694607 | I49: 0.695107 | J49: 0.695557 | K49: 0.695964 | L49: 0.696337 | M49: 0.696677 | N49: 0.696987 | O49: 0.697269 | P49: 0.697524 | Q49: 0.697753 | R49: 0.697961 | S49: 0.698147 | T49: 0.698316 | U49: 0.698469 | V49: 0.698608 | W49: 0.698733 | X49: 0.698847 | Y49: 0.69895 | Z49: 0.699044 | AA49: 0.69913 | AB49: 0.699208 | AC49: 0.699279 | AD49: 0.699343 | AE49: 0.699402 | AF49: 0.699456 | AG49: 0.699505 | AH49: 0.69955 | AI49: 0
A50: Natural Gas | B50: Commercial: Stock Average Efficiency: Cooking: Natural Gas: Reference case | C50: AEO.2023.REF2023.EFF_STKE_COMM_CGR_NG_NA_NA_BTUOTPBTUIN.A | D50: Btu Out/Btu In | F50: 0.316667 | G50: 0.316667 | H50: 0.316667 | I50: 0.316667 | J50: 0.316667 | K50: 0.316667 | L50: 0.316667 | M50: 0.316667 | N50: 0.316667 | O50: 0.316667 | P50: 0.316667 | Q50: 0.316667 | R50: 0.316667 | S50: 0.316667 | T50: 0.316667 | U50: 0.316667 | V50: 0.316667 | W50: 0.316667 | X50: 0.316667 | Y50: 0.316667 | Z50: 0.316667 | AA50: 0.316667 | AB50: 0.316667 | AC50: 0.316667 | AD50: 0.316667 | AE50: 0.316667 | AF50: 0.316667 | AG50: 0.316667 | AH50: 0.316667 | AI50: 0
A51: Lighting Efficacy
A52: (efficacy in lumens per watt)
A53: Electricity | B53: Commercial: Stock Average Efficiency: Lighting Efficacy: Electricity: Reference case | C53: AEO.2023.REF2023.EFF_STKE_COMM_LGHTNG_ELC_NA_NA_LMNPWATT.A | D53: lumens/watt | F53: 75.352577 | G53: 77.416039 | H53: 79.081436 | I53: 80.421127 | J53: 81.551735 | K53: 82.538506 | L53: 83.405853 | M53: 84.158943 | N53: 85.745209 | O53: 87.334564 | P53: 88.855927 | Q53: 90.298164 | R53: 91.731659 | S53: 93.147095 | T53: 94.561653 | U53: 96.152641 | V53: 97.851868 | W53: 99.830597 | X53: 100.64256 | Y53: 101.38133 | Z53: 102.09468 | AA53: 102.73066 | AB53: 103.28683 | AC53: 103.77985 | AD53: 104.21254 | AE53: 104.52364 | AF53: 104.79678 | AG53: 105.03486 | AH53: 105.22745 | AI53: 0.012
A54: Refrigeration
A55: Electricity | B55: Commercial: Stock Average Efficiency: Refrigeration: Electricity: Reference case | C55: AEO.2023.REF2023.EFF_STKE_COMM_REFR_ELC_NA_NA_BTUOTPBTUIN.A | D55: Btu Out/Btu In | F55: 3.018806 | G55: 3.040998 | H55: 3.060953 | I55: 3.078654 | J55: 3.094166 | K55: 3.1078 | L55: 3.119896 | M55: 3.130624 | N55: 3.145846 | O55: 3.1594 | P55: 3.17135 | Q55: 3.181871 | R55: 3.191118 | S55: 3.199244 | T55: 3.206392 | U55: 3.212689 | V55: 3.218246 | W55: 3.223154 | X55: 3.227481 | Y55: 3.231346 | Z55: 3.234773 | AA55: 3.237805 | AB55: 3.240493 | AC55: 3.242883 | AD55: 3.245009 | AE55: 3.246881 | AF55: 3.24855 | AG55: 3.250033 | AH55: 3.251345 | AI55: 0.003
A56: Distributed Generation and
A57: Combined Heat and Power
A58: Generating Capacity (gigawatts)
A59: Petroleum | B59: Commercial: Combined Heat and Power: Generating Capacity: Petroleum: Reference case | C59: AEO.2023.REF2023.CAP_NA_COMM_CHP_PET_NA_NA_MW.A | D59: GW | F59: 0.01398 | G59: 0.01398 | H59: 0.01398 | I59: 0.01398 | J59: 0.01398 | K59: 0.01398 | L59: 0.01398 | M59: 0.01398 | N59: 0.01398 | O59: 0.01398 | P59: 0.01398 | Q59: 0.01398 | R59: 0.01398 | S59: 0.01398 | T59: 0.01398 | U59: 0.01398 | V59: 0.01398 | W59: 0.01398 | X59: 0.01398 | Y59: 0.01398 | Z59: 0.01398 | AA59: 0.01398 | AB59: 0.01398 | AC59: 0.01398 | AD59: 0.01398 | AE59: 0.01398 | AF59: 0.01398 | AG59: 0.01398 | AH59: 0.01398 | AI59: 0
A60: Natural Gas | B60: Commercial: Combined Heat and Power: Generating Capacity: Natural Gas: Reference case | C60: AEO.2023.REF2023.CAP_NA_COMM_CHP_NG_NA_NA_MW.A | D60: GW | F60: 1.368147 | G60: 1.394019 | H60: 1.422768 | I60: 1.443255 | J60: 1.461629 | K60: 1.480808 | L60: 1.500384 | M60: 1.520532 | N60: 1.543804 | O60: 1.567393 | P60: 1.592353 | Q60: 1.615242 | R60: 1.636618 | S60: 1.655876 | T60: 1.671951 | U60: 1.685844 | V60: 1.700482 | W60: 1.716259 | X60: 1.727784 | Y60: 1.738951 | Z60: 1.749921 | AA60: 1.761486 | AB60: 1.771808 | AC60: 1.781531 | AD60: 1.791808 | AE60: 1.802317 | AF60: 1.814158 | AG60: 1.825154 | AH60: 1.836513 | AI60: 0.011
A61: Solar Photovoltaic | B61: Commercial: Combined Heat and Power: Generating Capacity: Solar Photovoltaic: Reference case | C61: AEO.2023.REF2023.CAP_NA_COMM_CHP_SLR_PHTVL_NA_MW.A | D61: GW | F61: 22.491291 | G61: 26.815535 | H61: 30.254023 | I61: 33.178463 | J61: 34.785683 | K61: 36.654331 | L61: 38.291962 | M61: 40.837509 | N61: 42.625347 | O61: 44.444 | P61: 46.077877 | Q61: 48.43885 | R61: 51.029842 | S61: 52.509289 | T61: 55.255535 | U61: 56.865173 | V61: 59.174522 | W61: 61.338108 | X61: 63.244408 | Y61: 64.905724 | Z61: 66.276016 | AA61: 67.472404 | AB61: 68.55864 | AC61: 69.653053 | AD61: 71.534721 | AE61: 72.148804 | AF61: 73.245369 | AG61: 73.763748 | AH61: 74.117523 | AI61: 0.044
A62: Wind | B62: Commercial: Combined Heat and Power: Generating Capacity: Wind: Reference case | C62: AEO.2023.REF2023.CAP_NA_COMM_CHP_WND_NA_NA_MW.A | D62: GW | F62: 0.554881 | G62: 0.559737 | H62: 0.561073 | I62: 0.561073 | J62: 0.561073 | K62: 0.561073 | L62: 0.561113 | M62: 0.561113 | N62: 0.561222 | O62: 0.56146 | P62: 0.562333 | Q62: 0.564162 | R62: 0.566106 | S62: 0.566459 | T62: 0.568103 | U62: 0.568389 | V62: 0.569803 | W62: 0.571587 | X62: 0.571747 | Y62: 0.572253 | Z62: 0.572517 | AA62: 0.573033 | AB62: 0.573227 | AC62: 0.573335 | AD62: 0.573658 | AE62: 0.573658 | AF62: 0.573971 | AG62: 0.573971 | AH62: 0.573971 | AI62: 0.001
A63: Other | B63: Commercial: Combined Heat and Power: Generating Capacity: Other: Reference case | C63: AEO.2023.REF2023.CAP_NA_COMM_CHP_OTH_NA_NA_MW.A | D63: GW | F63: 0.117763 | G63: 0.117763 | H63: 0.117763 | I63: 0.117763 | J63: 0.117763 | K63: 0.117763 | L63: 0.117763 | M63: 0.117763 | N63: 0.117763 | O63: 0.117763 | P63: 0.117763 | Q63: 0.117763 | R63: 0.117763 | S63: 0.117763 | T63: 0.117763 | U63: 0.117763 | V63: 0.117763 | W63: 0.117763 | X63: 0.117763 | Y63: 0.117763 | Z63: 0.117763 | AA63: 0.117763 | AB63: 0.117763 | AC63: 0.117763 | AD63: 0.117763 | AE63: 0.117763 | AF63: 0.117763 | AG63: 0.117763 | AH63: 0.117763 | AI63: 0
A64: Total | B64: Commercial: Combined Heat and Power: Generating Capacity: Total: Reference case | C64: AEO.2023.REF2023.CAP_NA_COMM_CHP_TOT_NA_NA_MW.A | D64: GW | F64: 24.546064 | G64: 28.901033 | H64: 32.36961 | I64: 35.314533 | J64: 36.940128 | K64: 38.827957 | L64: 40.485203 | M64: 43.0509 | N64: 44.862118 | O64: 46.704597 | P64: 48.364307 | Q64: 50.75 | R64: 53.364307 | S64: 54.863369 | T64: 57.627335 | U64: 59.251152 | V64: 61.576553 | W64: 63.757698 | X64: 65.675674 | Y64: 67.348663 | Z64: 68.730194 | AA64: 69.938667 | AB64: 71.035416 | AC64: 72.139656 | AD64: 74.031921 | AE64: 74.656517 | AF64: 75.765236 | AG64: 76.294609 | AH64: 76.659744 | AI64: 0.042
A65: Net Generation (billion kilowatthours)
A66: Petroleum | B66: Commercial: Combined Heat and Power: Net Generation: Petroleum: Reference case | C66: AEO.2023.REF2023.GEN_NA_COMM_CHP_PET_NA_NA_MILLKWH.A | D66: billion kWh | F66: 0.097511 | G66: 0.097511 | H66: 0.097511 | I66: 0.097511 | J66: 0.097511 | K66: 0.097511 | L66: 0.097511 | M66: 0.097511 | N66: 0.097511 | O66: 0.097511 | P66: 0.097511 | Q66: 0.097511 | R66: 0.097511 | S66: 0.097511 | T66: 0.097511 | U66: 0.097511 | V66: 0.097511 | W66: 0.097511 | X66: 0.097511 | Y66: 0.097511 | Z66: 0.097511 | AA66: 0.097511 | AB66: 0.097511 | AC66: 0.097511 | AD66: 0.097511 | AE66: 0.097511 | AF66: 0.097511 | AG66: 0.097511 | AH66: 0.097511 | AI66: 0
A67: Natural Gas | B67: Commercial: Combined Heat and Power: Net Generation: Natural Gas: Reference case | C67: AEO.2023.REF2023.GEN_NA_COMM_CHP_NG_NA_NA_MILLKWH.A | D67: billion kWh | F67: 9.542824 | G67: 9.723283 | H67: 9.923806 | I67: 10.066701 | J67: 10.194861 | K67: 10.328632 | L67: 10.465176 | M67: 10.605714 | N67: 10.768033 | O67: 10.932568 | P67: 11.106659 | Q67: 11.266313 | R67: 11.415409 | S67: 11.549734 | T67: 11.66186 | U67: 11.758763 | V67: 11.860858 | W67: 11.970905 | X67: 12.051291 | Y67: 12.12918 | Z67: 12.205701 | AA67: 12.286364 | AB67: 12.358362 | AC67: 12.426178 | AD67: 12.497861 | AE67: 12.571158 | AF67: 12.653754 | AG67: 12.730446 | AH67: 12.809677 | AI67: 0.011
A68: Solar Photovoltaic | B68: Commercial: Combined Heat and Power: Net Generation: Solar Photovoltaic: Reference case | C68: AEO.2023.REF2023.GEN_NA_COMM_CHP_SLR_PHTVL_NA_MILLKWH.A | D68: billion kWh | F68: 31.884121 | G68: 37.878464 | H68: 42.628193 | I68: 46.505924 | J68: 48.667229 | K68: 51.194096 | L68: 53.380569 | M68: 56.781303 | N68: 59.208065 | O68: 61.63969 | P68: 63.799805 | Q68: 66.962448 | R68: 70.303558 | S68: 72.27066 | T68: 75.848862 | U68: 77.991562 | V68: 81.021461 | W68: 83.826828 | X68: 86.340187 | Y68: 88.522995 | Z68: 90.352364 | AA68: 91.947807 | AB68: 93.428085 | AC68: 94.886871 | AD68: 97.368355 | AE68: 98.220367 | AF68: 99.64415 | AG68: 100.37446 | AH68: 100.87702 | AI68: 0.042
A69: Wind | B69: Commercial: Combined Heat and Power: Net Generation: Wind: Reference case | C69: AEO.2023.REF2023.GEN_NA_COMM_CHP_WND_NA_NA_MILLKWH.A | D69: billion kWh | F69: 0.755308 | G69: 0.763439 | H69: 0.765689 | I69: 0.765689 | J69: 0.765689 | K69: 0.765689 | L69: 0.765756 | M69: 0.765756 | N69: 0.76589 | O69: 0.766243 | P69: 0.767636 | Q69: 0.770626 | R69: 0.773866 | S69: 0.7744 | T69: 0.777133 | U69: 0.777592 | V69: 0.779941 | W69: 0.782966 | X69: 0.783237 | Y69: 0.784071 | Z69: 0.784478 | AA69: 0.785244 | AB69: 0.785486 | AC69: 0.785621 | AD69: 0.786121 | AE69: 0.786121 | AF69: 0.786621 | AG69: 0.786621 | AH69: 0.786621 | AI69: 0.001
A70: Other | B70: Commercial: Combined Heat and Power: Net Generation: Other: Reference case | C70: AEO.2023.REF2023.GEN_NA_COMM_CHP_OTH_NA_NA_MILLKWH.A | D70: billion kWh | F70: 0.86205 | G70: 0.86205 | H70: 0.86205 | I70: 0.86205 | J70: 0.86205 | K70: 0.86205 | L70: 0.86205 | M70: 0.86205 | N70: 0.86205 | O70: 0.86205 | P70: 0.86205 | Q70: 0.86205 | R70: 0.86205 | S70: 0.86205 | T70: 0.86205 | U70: 0.86205 | V70: 0.86205 | W70: 0.86205 | X70: 0.86205 | Y70: 0.86205 | Z70: 0.86205 | AA70: 0.86205 | AB70: 0.86205 | AC70: 0.86205 | AD70: 0.86205 | AE70: 0.86205 | AF70: 0.86205 | AG70: 0.86205 | AH70: 0.86205 | AI70: 0
A71: Total | B71: Commercial: Combined Heat and Power: Net Generation: Total: Reference case | C71: AEO.2023.REF2023.GEN_NA_COMM_CHP_TOT_NA_NA_MILLKWH.A | D71: billion kWh | F71: 43.141811 | G71: 49.324745 | H71: 54.277248 | I71: 58.297874 | J71: 60.587341 | K71: 63.247978 | L71: 65.571068 | M71: 69.112335 | N71: 71.701553 | O71: 74.298065 | P71: 76.633667 | Q71: 79.958954 | R71: 83.4524 | S71: 85.554359 | T71: 89.247414 | U71: 91.487488 | V71: 94.621819 | W71: 97.540268 | X71: 100.13428 | Y71: 102.39581 | Z71: 104.30211 | AA71: 105.97898 | AB71: 107.53149 | AC71: 109.05823 | AD71: 111.6119 | AE71: 112.53721 | AF71: 114.04409 | AG71: 114.85109 | AH71: 115.43288 | AI71: 0.036
A72: Disposition
A73: Sales to the Grid | B73: Commercial: Combined Heat and Power: Net Generation: Sales to the Grid: Reference case | C73: AEO.2023.REF2023.GEN_NA_COMM_CHP_STG_NA_NA_MILLKWH.A | D73: billion kWh | F73: 7.796522 | G73: 7.914052 | H73: 8.030015 | I73: 8.16405 | J73: 8.279953 | K73: 8.387985 | L73: 8.506828 | M73: 8.640635 | N73: 8.786509 | O73: 8.938856 | P73: 9.087277 | Q73: 9.222068 | R73: 9.345303 | S73: 9.456551 | T73: 9.556719 | U73: 9.648196 | V73: 9.730404 | W73: 9.806884 | X73: 9.876718 | Y73: 9.942617 | Z73: 10.007074 | AA73: 10.071661 | AB73: 10.136639 | AC73: 10.202756 | AD73: 10.27134 | AE73: 10.342049 | AF73: 10.415814 | AG73: 10.491967 | AH73: 10.570431 | AI73: 0.011
A74: Generation for Own Use | B74: Commercial: Combined Heat and Power: Net Generation: Generation for Own Use: Reference case | C74: AEO.2023.REF2023.GEN_NA_COMM_CHP_GFO_NA_NA_MILLKWH.A | D74: billion kWh | F74: 35.345287 | G74: 41.410698 | H74: 46.247234 | I74: 50.133827 | J74: 52.307392 | K74: 54.859993 | L74: 57.064236 | M74: 60.471703 | N74: 62.915043 | O74: 65.359207 | P74: 67.546379 | Q74: 70.736885 | R74: 74.107094 | S74: 76.097801 | T74: 79.690697 | U74: 81.839279 | V74: 84.891411 | W74: 87.733383 | X74: 90.257553 | Y74: 92.453186 | Z74: 94.295036 | AA74: 95.907318 | AB74: 97.394859 | AC74: 98.855484 | AD74: 101.34055 | AE74: 102.19516 | AF74: 103.62827 | AG74: 104.35912 | AH74: 104.86245 | AI74: 0.04
A75: Energy Input (trillion Btu)
A76: Petroleum | B76: Commercial: Combined Heat and Power: Energy Input: Petroleum: Reference case | C76: AEO.2023.REF2023.CNSM_NA_COMM_CHP_PET_NA_NA_TRLBTU.A | D76: trillion Btu | F76: 1.016528 | G76: 1.016528 | H76: 1.016528 | I76: 1.016528 | J76: 1.016528 | K76: 1.016528 | L76: 1.016528 | M76: 1.016528 | N76: 1.016528 | O76: 1.016528 | P76: 1.016528 | Q76: 1.016528 | R76: 1.016528 | S76: 1.016528 | T76: 1.016528 | U76: 1.016528 | V76: 1.016528 | W76: 1.016528 | X76: 1.016528 | Y76: 1.016528 | Z76: 1.016528 | AA76: 1.016528 | AB76: 1.016528 | AC76: 1.016528 | AD76: 1.016528 | AE76: 1.016528 | AF76: 1.016528 | AG76: 1.016528 | AH76: 1.016528 | AI76: 0
A77: Natural Gas | B77: Commercial: Combined Heat and Power: Energy Input: Natural Gas: Reference case | C77: AEO.2023.REF2023.CNSM_NA_COMM_CHP_NG_NA_NA_TRLBTU.A | D77: trillion Btu | F77: 102.6951 | G77: 104.68872 | H77: 106.93667 | I77: 108.52356 | J77: 109.95264 | K77: 111.45418 | L77: 112.9885 | M77: 114.56694 | N77: 116.39472 | O77: 118.24171 | P77: 120.19518 | Q77: 121.98265 | R77: 123.64547 | S77: 125.14055 | T77: 126.38202 | U77: 127.45241 | V77: 128.58028 | W77: 129.79591 | X77: 130.67847 | Y77: 131.53282 | Z77: 132.37248 | AA77: 133.25745 | AB77: 134.0457 | AC77: 134.78711 | AD77: 135.57063 | AE77: 136.3717 | AF77: 137.27466 | AG77: 138.11217 | AH77: 138.97696 | AI77: 0.011
A78: Solar Photovoltaic | B78: Commercial: Combined Heat and Power: Energy Input: Solar Photovoltaic: Reference case | C78: AEO.2023.REF2023.CNSM_NA_COMM_CHP_SLR_PHTVL_NA_TRLBTU.A | D78: trillion Btu | F78: 261.81537 | G78: 308.04425 | H78: 349.12451 | I78: 378.46252 | J78: 393.90903 | K78: 414.62033 | L78: 431.87567 | M78: 460.3053 | N78: 480.62396 | O78: 501.82758 | P78: 519.75446 | Q78: 545.57996 | R78: 573.5802 | S78: 591.70874 | T78: 620.7381 | U78: 637.33618 | V78: 658.83991 | W78: 681.91437 | X78: 701.09399 | Y78: 720.85175 | Z78: 735.41528 | AA78: 748.40485 | AB78: 761.18207 | AC78: 772.83423 | AD78: 793.08624 | AE78: 800.96893 | AF78: 811.40137 | AG78: 818.58081 | AH78: 819.18097 | AI78: 0.042
A79: Wind | B79: Commercial: Combined Heat and Power: Energy Input: Wind: Reference case | C79: AEO.2023.REF2023.CNSM_NA_COMM_CHP_WND_NA_NA_TRLBTU.A | D79: trillion Btu | F79: 6.791775 | G79: 6.788934 | H79: 6.848722 | I79: 6.793999 | J79: 6.729903 | K79: 6.714339 | L79: 6.731504 | M79: 6.795619 | N79: 6.782379 | O79: 6.819679 | P79: 6.834842 | Q79: 6.836193 | R79: 6.85681 | S79: 6.902808 | T79: 6.913902 | U79: 6.882823 | V79: 6.800419 | W79: 6.808289 | X79: 6.780758 | Y79: 6.804255 | Z79: 6.802587 | AA79: 6.791727 | AB79: 6.7827 | AC79: 6.768836 | AD79: 6.764524 | AE79: 6.76651 | AF79: 6.760385 | AG79: 6.754371 | AH79: 6.743033 | AI79: 0
A80: Other | B80: Commercial: Combined Heat and Power: Energy Input: Other: Reference case | C80: AEO.2023.REF2023.CNSM_NA_COMM_CHP_OTH_NA_NA_TRLBTU.A | D80: trillion Btu | F80: 16.760143 | G80: 16.760143 | H80: 16.760143 | I80: 16.760143 | J80: 16.760143 | K80: 16.760143 | L80: 16.760143 | M80: 16.760143 | N80: 16.760143 | O80: 16.760143 | P80: 16.760143 | Q80: 16.760143 | R80: 16.760143 | S80: 16.760143 | T80: 16.760143 | U80: 16.760143 | V80: 16.760143 | W80: 16.760143 | X80: 16.760143 | Y80: 16.760143 | Z80: 16.760143 | AA80: 16.760143 | AB80: 16.760143 | AC80: 16.760143 | AD80: 16.760143 | AE80: 16.760143 | AF80: 16.760143 | AG80: 16.760143 | AH80: 16.760143 | AI80: 0
A81: Total | B81: Commercial: Combined Heat and Power: Energy Input: Total: Reference case | C81: AEO.2023.REF2023.CNSM_NA_COMM_CHP_TOT_NA_NA_TRLBTU.A | D81: trillion Btu | F81: 389.07889 | G81: 437.29858 | H81: 480.68655 | I81: 511.55676 | J81: 528.36823 | K81: 550.56555 | L81: 569.37231 | M81: 599.44452 | N81: 621.5777 | O81: 644.66565 | P81: 664.56116 | Q81: 692.17542 | R81: 721.85913 | S81: 741.52881 | T81: 771.81067 | U81: 789.44806 | V81: 811.99725 | W81: 836.29523 | X81: 856.32989 | Y81: 876.96551 | Z81: 892.36707 | AA81: 906.23071 | AB81: 919.78711 | AC81: 932.16687 | AD81: 953.19806 | AE81: 961.88385 | AF81: 973.21307 | AG81: 981.224 | AH81: 982.67761 | AI81: 0.034

Sheet AEO25_Table_22._Commercial
A1: Table 22. Commercial Sector Energy Consumption, Floorspace, Equipment Efficiency, and Distributed Generation
A2: https://www.eia.gov/outlooks/aeo/data/browser/#/?id=32-AEO2025&cases=highZTC&sourcekey=0
A3: Tue Dec 02 2025 13:21:51 GMT-0800 (Pacific Standard Time)
A4: Source: U.S. Energy Information Administration
B5: full name | C5: api key | D5: units | E5: 2023 | F5: 2024 | G5: 2025 | H5: 2026 | I5: 2027 | J5: 2028 | K5: 2029 | L5: 2030 | M5: 2031 | N5: 2032 | O5: 2033 | P5: 2034 | Q5: 2035 | R5: 2036 | S5: 2037 | T5: 2038 | U5: 2039 | V5: 2040 | W5: 2041 | X5: 2042 | Y5: 2043 | Z5: 2044 | AA5: 2045 | AB5: 2046 | AC5: 2047 | AD5: 2048 | AE5: 2049 | AF5: 2050 | AG5: Growth (2024-2050)
A6: Commercial Building Delivered
A7: Energy Consumption (quadrillion Btu)
A8: Assembly | B8: Commercial: Gross End-use: Assembly: High Zero-Carbon Technology Cost | C8: AEO.2025.HIGHZTC.CNSM_NA_COMM_ASB_GROSENUS_NA_NA_QBTU.A | D8: quads | F8: 0.84868 | G8: 0.884049 | H8: 0.894175 | I8: 0.90365 | J8: 0.910477 | K8: 0.914431 | L8: 0.915831 | M8: 0.918122 | N8: 0.920175 | O8: 0.921771 | P8: 0.924584 | Q8: 0.929381 | R8: 0.936031 | S8: 0.943531 | T8: 0.950729 | U8: 0.958429 | V8: 0.965966 | W8: 0.973333 | X8: 0.980492 | Y8: 0.987832 | Z8: 0.995496 | AA8: 1.003386 | AB8: 1.011123 | AC8: 1.019229 | AD8: 1.027779 | AE8: 1.036476 | AF8: 1.045322 | AG8: 0.008
A9: Education | B9: Commercial: Gross End-use: Education: High Zero-Carbon Technology Cost | C9: AEO.2025.HIGHZTC.CNSM_NA_COMM_EDD_GROSENUS_NA_NA_QBTU.A | D9: quads | F9: 1.017924 | G9: 1.051998 | H9: 1.063778 | I9: 1.073902 | J9: 1.081212 | K9: 1.085343 | L9: 1.085965 | M9: 1.08698 | N9: 1.087402 | O9: 1.086918 | P9: 1.087472 | Q9: 1.090411 | R9: 1.095282 | S9: 1.100983 | T9: 1.106382 | U9: 1.112345 | V9: 1.117577 | W9: 1.122382 | X9: 1.126814 | Y9: 1.131356 | Z9: 1.136234 | AA9: 1.141255 | AB9: 1.145905 | AC9: 1.150848 | AD9: 1.156103 | AE9: 1.161276 | AF9: 1.166354 | AG9: 0.005
A10: Food Sales | B10: Commercial: Gross End-use: Food Sales: High Zero-Carbon Technology Cost | C10: AEO.2025.HIGHZTC.CNSM_NA_COMM_FDSA_GROSENUS_NA_NA_QBTU.A | D10: quads | F10: 0.19708 | G10: 0.201363 | H10: 0.202731 | I10: 0.20441 | J10: 0.205563 | K10: 0.206057 | L10: 0.205717 | M10: 0.205627 | N10: 0.205519 | O10: 0.205291 | P10: 0.205241 | Q10: 0.205561 | R10: 0.206175 | S10: 0.206885 | T10: 0.207471 | U10: 0.208073 | V10: 0.208533 | W10: 0.209096 | X10: 0.209596 | Y10: 0.210064 | Z10: 0.210534 | AA10: 0.210984 | AB10: 0.211364 | AC10: 0.21175 | AD10: 0.21215 | AE10: 0.212497 | AF10: 0.212814 | AG10: 0.003
A11: Food Service | B11: Commercial: Gross End-use: Food Service: High Zero-Carbon Technology Cost | C11: AEO.2025.HIGHZTC.CNSM_NA_COMM_FSC_GROSENUS_NA_NA_QBTU.A | D11: quads | F11: 0.360019 | G11: 0.369677 | H11: 0.374469 | I11: 0.378784 | J11: 0.381703 | K11: 0.383299 | L11: 0.383695 | M11: 0.384391 | N11: 0.384866 | O11: 0.385096 | P11: 0.385783 | Q11: 0.387344 | R11: 0.389631 | S11: 0.392176 | T11: 0.394504 | U11: 0.39686 | V11: 0.398888 | W11: 0.400824 | X11: 0.402572 | Y11: 0.404259 | Z11: 0.405966 | AA11: 0.40763 | AB11: 0.409099 | AC11: 0.410654 | AD11: 0.412275 | AE11: 0.413793 | AF11: 0.415203 | AG11: 0.006
A12: Health Care | B12: Commercial: Gross End-use: Health Care: High Zero-Carbon Technology Cost | C12: AEO.2025.HIGHZTC.CNSM_NA_COMM_HLC_GROSENUS_NA_NA_QBTU.A | D12: quads | F12: 0.425994 | G12: 0.444568 | H12: 0.452412 | I12: 0.459559 | J12: 0.46517 | K12: 0.469295 | L12: 0.471855 | M12: 0.474514 | N12: 0.476774 | O12: 0.478704 | P12: 0.481302 | Q12: 0.485045 | R12: 0.489859 | S12: 0.49523 | T12: 0.500559 | U12: 0.506202 | V12: 0.511552 | W12: 0.516625 | X12: 0.521468 | Y12: 0.526264 | Z12: 0.531287 | AA12: 0.536426 | AB12: 0.541428 | AC12: 0.5467 | AD12: 0.552199 | AE12: 0.557664 | AF12: 0.563132 | AG12: 0.011
A13: Lodging | B13: Commercial: Gross End-use: Lodging: High Zero-Carbon Technology Cost | C13: AEO.2025.HIGHZTC.CNSM_NA_COMM_LGC_GROSENUS_NA_NA_QBTU.A | D13: quads | F13: 0.68129 | G13: 0.707055 | H13: 0.721615 | I13: 0.735892 | J13: 0.748136 | K13: 0.75818 | L13: 0.765746 | M13: 0.773568 | N13: 0.781026 | O13: 0.788196 | P13: 0.796334 | Q13: 0.806096 | R13: 0.817446 | S13: 0.829603 | T13: 0.841577 | U13: 0.85406 | V13: 0.866164 | W13: 0.877925 | X13: 0.889385 | Y13: 0.900871 | Z13: 0.912726 | AA13: 0.924783 | AB13: 0.936698 | AC13: 0.949113 | AD13: 0.961922 | AE13: 0.974742 | AF13: 0.987673 | AG13: 0.014
A14: Office - Large | B14: Commercial: Gross End-use: Office - Large: High Zero-Carbon Technology Cost | C14: AEO.2025.HIGHZTC.CNSM_NA_COMM_OFLC_GROSENUS_NA_NA_QBTU.A | D14: quads | F14: 0.845312 | G14: 0.864796 | H14: 0.873578 | I14: 0.884024 | J14: 0.892534 | K14: 0.898061 | L14: 0.899843 | M14: 0.90124 | N14: 0.902273 | O14: 0.903094 | P14: 0.905004 | Q14: 0.908248 | R14: 0.9131 | S14: 0.918801 | T14: 0.924095 | U14: 0.930005 | V14: 0.93599 | W14: 0.941652 | X14: 0.947015 | Y14: 0.952329 | Z14: 0.957935 | AA14: 0.963698 | AB14: 0.96929 | AC14: 0.974955 | AD14: 0.980929 | AE14: 0.986945 | AF14: 0.993056 | AG14: 0.006
A15: Office - Small | B15: Commercial: Gross End-use: Office - Small: High Zero-Carbon Technology Cost | C15: AEO.2025.HIGHZTC.CNSM_NA_COMM_OFSC_GROSENUS_NA_NA_QBTU.A | D15: quads | F15: 0.548384 | G15: 0.564639 | H15: 0.572958 | I15: 0.581934 | J15: 0.589428 | K15: 0.594742 | L15: 0.597739 | M15: 0.60076 | N15: 0.603719 | O15: 0.606241 | P15: 0.609658 | Q15: 0.614359 | R15: 0.620033 | S15: 0.626238 | T15: 0.632174 | U15: 0.638417 | V15: 0.644746 | W15: 0.651136 | X15: 0.657451 | Y15: 0.663849 | Z15: 0.67047 | AA15: 0.677194 | AB15: 0.683866 | AC15: 0.690883 | AD15: 0.698138 | AE15: 0.705463 | AF15: 0.712948 | AG15: 0.01
A16: Mercantile/Service | B16: Commercial: Gross End-use: Mercantile/Service: High Zero-Carbon Technology Cost | C16: AEO.2025.HIGHZTC.CNSM_NA_COMM_MCSC_GROSENUS_NA_NA_QBTU.A | D16: quads | F16: 1.29377 | G16: 1.331958 | H16: 1.345749 | I16: 1.359766 | J16: 1.37026 | K16: 1.375947 | L16: 1.375796 | M16: 1.376849 | N16: 1.377693 | O16: 1.377624 | P16: 1.378849 | Q16: 1.383336 | R16: 1.390393 | S16: 1.398474 | T16: 1.405899 | U16: 1.413833 | V16: 1.420698 | W16: 1.427323 | X16: 1.433609 | Y16: 1.440001 | Z16: 1.44664 | AA16: 1.453325 | AB16: 1.459537 | AC16: 1.466175 | AD16: 1.473084 | AE16: 1.479912 | AF16: 1.486415 | AG16: 0.005
A17: Warehouse | B17: Commercial: Gross End-use: Warehouse: High Zero-Carbon Technology Cost | C17: AEO.2025.HIGHZTC.CNSM_NA_COMM_WHRC_GROSENUS_NA_NA_QBTU.A | D17: quads | F17: 0.715772 | G17: 0.724481 | H17: 0.741376 | I17: 0.757238 | J17: 0.771718 | K17: 0.784203 | L17: 0.794121 | M17: 0.80473 | N17: 0.815535 | O17: 0.826279 | P17: 0.838182 | Q17: 0.851497 | R17: 0.865933 | S17: 0.881155 | T17: 0.896323 | U17: 0.91209 | V17: 0.928087 | W17: 0.944319 | X17: 0.960609 | Y17: 0.977187 | Z17: 0.994199 | AA17: 1.011541 | AB17: 1.028967 | AC17: 1.04695 | AD17: 1.065453 | AE17: 1.084217 | AF17: 1.103227 | AG17: 0.017
A18: Other | B18: Commercial: Gross End-use: Other: High Zero-Carbon Technology Cost | C18: AEO.2025.HIGHZTC.CNSM_NA_COMM_OTHU_GROSENUS_NA_NA_QBTU.A | D18: quads | F18: 0.577606 | G18: 0.603712 | H18: 0.623714 | I18: 0.644811 | J18: 0.665413 | K18: 0.684768 | L18: 0.702575 | M18: 0.720824 | N18: 0.739429 | O18: 0.758544 | P18: 0.779087 | Q18: 0.80137 | R18: 0.825628 | S18: 0.851498 | T18: 0.87791 | U18: 0.905669 | V18: 0.934441 | W18: 0.964082 | X18: 0.994491 | Y18: 1.025867 | Z18: 1.058732 | AA18: 1.092843 | AB18: 1.12794 | AC18: 1.164685 | AD18: 1.203002 | AE18: 1.242329 | AF18: 1.283367 | AG18: 0.031
A19: Total | B19: Commercial: Gross End-use: Total: High Zero-Carbon Technology Cost | C19: AEO.2025.HIGHZTC.CNSM_NA_COMM_NA_GROSENUS_NA_NA_QBTU.A | D19: quads | F19: 7.511831 | G19: 7.748293 | H19: 7.866556 | I19: 7.983969 | J19: 8.081614 | K19: 8.154325 | L19: 8.198884 | M19: 8.247604 | N19: 8.294411 | O19: 8.337759 | P19: 8.391497 | Q19: 8.462648 | R19: 8.54951 | S19: 8.644574 | T19: 8.737625 | U19: 8.835984 | V19: 8.932642 | W19: 9.028697 | X19: 9.123503 | Y19: 9.219877 | Z19: 9.32022 | AA19: 9.423064 | AB19: 9.525215 | AC19: 9.631941 | AD19: 9.743034 | AE19: 9.855313 | AF19: 9.969512 | AG19: 0.011
A20: Commercial Building Floorspace
A21: (billion square feet)
A22: Assembly | B22: Commercial: Floorspace: Assembly: High Zero-Carbon Technology Cost | C22: AEO.2025.HIGHZTC.KEI_FLR_COMM_ASB_NA_NA_NA_BLNSQFT.A | D22: billion sq ft | F22: 12.817468 | G22: 13.024555 | H22: 13.14502 | I22: 13.28536 | J22: 13.435477 | K22: 13.58338 | L22: 13.724409 | M22: 13.860394 | N22: 13.995576 | O22: 14.131165 | P22: 14.266127 | Q22: 14.398698 | R22: 14.526923 | S22: 14.649873 | T22: 14.767888 | U22: 14.881609 | V22: 14.991705 | W22: 15.098835 | X22: 15.203425 | Y22: 15.305864 | Z22: 15.406607 | AA22: 15.506073 | AB22: 15.60465 | AC22: 15.702631 | AD22: 15.800199 | AE22: 15.897416 | AF22: 15.994262 | AG22: 0.009
A23: Education | B23: Commercial: Floorspace: Education: High Zero-Carbon Technology Cost | C23: AEO.2025.HIGHZTC.KEI_FLR_COMM_EDD_NA_NA_NA_BLNSQFT.A | D23: billion sq ft | F23: 14.477227 | G23: 14.669399 | H23: 14.860004 | I23: 15.074451 | J23: 15.301549 | K23: 15.527782 | L23: 15.747817 | M23: 15.963676 | N23: 16.180206 | O23: 16.398798 | P23: 16.618282 | Q23: 16.836611 | R23: 17.051477 | S23: 17.261757 | T23: 17.467796 | U23: 17.670296 | V23: 17.870014 | W23: 18.067698 | X23: 18.263834 | Y23: 18.45887 | Z23: 18.653334 | AA23: 18.847738 | AB23: 19.042536 | AC23: 19.238104 | AD23: 19.434662 | AE23: 19.632298 | AF23: 19.831005 | AG23: 0.012
A24: Food Sales | B24: Commercial: Floorspace: Food Sales: High Zero-Carbon Technology Cost | C24: AEO.2025.HIGHZTC.KEI_FLR_COMM_FDSA_NA_NA_NA_BLNSQFT.A | D24: billion sq ft | F24: 1.013164 | G24: 1.031002 | H24: 1.040686 | I24: 1.051947 | J24: 1.063986 | K24: 1.075855 | L24: 1.087183 | M24: 1.098117 | N24: 1.108991 | O24: 1.119901 | P24: 1.130767 | Q24: 1.141447 | R24: 1.151787 | S24: 1.161713 | T24: 1.171252 | U24: 1.180455 | V24: 1.189374 | W24: 1.198062 | X24: 1.206553 | Y24: 1.214876 | Z24: 1.223069 | AA24: 1.231166 | AB24: 1.239195 | AC24: 1.247181 | AD24: 1.255138 | AE24: 1.263071 | AF24: 1.27098 | AG24: 0.009
A25: Food Service | B25: Commercial: Floorspace: Food Service: High Zero-Carbon Technology Cost | C25: AEO.2025.HIGHZTC.KEI_FLR_COMM_FSC_NA_NA_NA_BLNSQFT.A | D25: billion sq ft | F25: 1.401535 | G25: 1.427102 | H25: 1.441598 | I25: 1.458307 | J25: 1.476126 | K25: 1.493741 | L25: 1.510639 | M25: 1.527021 | N25: 1.543351 | O25: 1.559765 | P25: 1.576147 | Q25: 1.592303 | R25: 1.608018 | S25: 1.623186 | T25: 1.637846 | U25: 1.652065 | V25: 1.665918 | W25: 1.679477 | X25: 1.692789 | Y25: 1.705896 | Z25: 1.71885 | AA25: 1.731696 | AB25: 1.744478 | AC25: 1.757228 | AD25: 1.769968 | AE25: 1.782704 | AF25: 1.795436 | AG25: 0.01
A26: Health Care | B26: Commercial: Floorspace: Health Care: High Zero-Carbon Technology Cost | C26: AEO.2025.HIGHZTC.KEI_FLR_COMM_HLC_NA_NA_NA_BLNSQFT.A | D26: billion sq ft | F26: 2.483398 | G26: 2.529708 | H26: 2.571741 | I26: 2.618129 | J26: 2.66697 | K26: 2.715932 | L26: 2.764082 | M26: 2.811763 | N26: 2.859819 | O26: 2.908498 | P26: 2.957596 | Q26: 3.00675 | R26: 3.055545 | S26: 3.103773 | T26: 3.151489 | U26: 3.198809 | V26: 3.245865 | W26: 3.292787 | X26: 3.339661 | Y26: 3.386563 | Z26: 3.43359 | AA26: 3.480834 | AB26: 3.528378 | AC26: 3.576293 | AD26: 3.62462 | AE26: 3.673378 | AF26: 3.722567 | AG26: 0.016
A27: Lodging | B27: Commercial: Floorspace: Lodging: High Zero-Carbon Technology Cost | C27: AEO.2025.HIGHZTC.KEI_FLR_COMM_LGC_NA_NA_NA_BLNSQFT.A | D27: billion sq ft | F27: 7.418135 | G27: 7.584061 | H27: 7.708387 | I27: 7.845709 | J27: 7.990322 | K27: 8.135231 | L27: 8.277637 | M27: 8.418574 | N27: 8.560569 | O27: 8.704365 | P27: 8.849349 | Q27: 8.994432 | R27: 9.138377 | S27: 9.280561 | T27: 9.421147 | U27: 9.56049 | V27: 9.698977 | W27: 9.837005 | X27: 9.974822 | Y27: 10.112667 | Z27: 10.250821 | AA27: 10.389561 | AB27: 10.529137 | AC27: 10.669755 | AD27: 10.811544 | AE27: 10.954556 | AF27: 11.09879 | AG27: 0.016
A28: Office - Large | B28: Commercial: Floorspace: Office - Large: High Zero-Carbon Technology Cost | C28: AEO.2025.HIGHZTC.KEI_FLR_COMM_OFLC_NA_NA_NA_BLNSQFT.A | D28: billion sq ft | F28: 11.034375 | G28: 11.170792 | H28: 11.289731 | I28: 11.426096 | J28: 11.571279 | K28: 11.714989 | L28: 11.853201 | M28: 11.987477 | N28: 12.12147 | O28: 12.256226 | P28: 12.390857 | Q28: 12.523828 | R28: 12.653435 | S28: 12.778854 | T28: 12.900372 | U28: 13.018527 | V28: 13.133893 | W28: 13.247038 | X28: 13.358327 | Y28: 13.468096 | Z28: 13.576739 | AA28: 13.684623 | AB28: 13.792088 | AC28: 13.899397 | AD28: 14.006706 | AE28: 14.114076 | AF28: 14.221491 | AG28: 0.01
A29: Office - Small | B29: Commercial: Floorspace: Office - Small: High Zero-Carbon Technology Cost | C29: AEO.2025.HIGHZTC.KEI_FLR_COMM_OFSC_NA_NA_NA_BLNSQFT.A | D29: billion sq ft | F29: 8.095156 | G29: 8.19727 | H29: 8.287075 | I29: 8.389712 | J29: 8.498872 | K29: 8.607003 | L29: 8.711153 | M29: 8.812455 | N29: 8.913598 | O29: 9.015349 | P29: 9.117056 | Q29: 9.217589 | R29: 9.315692 | S29: 9.410757 | T29: 9.502988 | U29: 9.592783 | V29: 9.680561 | W29: 9.76674 | X29: 9.851584 | Y29: 9.935343 | Z29: 10.018303 | AA29: 10.100739 | AB29: 10.182895 | AC29: 10.264968 | AD29: 10.347072 | AE29: 10.429251 | AF29: 10.511497 | AG29: 0.01
A30: Mercantile/Service | B30: Commercial: Floorspace: Mercantile/Service: High Zero-Carbon Technology Cost | C30: AEO.2025.HIGHZTC.KEI_FLR_COMM_MCSC_NA_NA_NA_BLNSQFT.A | D30: billion sq ft | F30: 17.797789 | G30: 18.087166 | H30: 18.296322 | I30: 18.534037 | J30: 18.786425 | K30: 19.036812 | L30: 19.278666 | M30: 19.514486 | N30: 19.750214 | O30: 19.987541 | P30: 20.225027 | Q30: 20.460169 | R30: 20.690165 | S30: 20.913662 | T30: 21.131105 | U30: 21.343359 | V30: 21.551353 | W30: 21.756001 | X30: 21.957897 | Y30: 22.157579 | Z30: 22.355694 | AA30: 22.552841 | AB30: 22.749567 | AC30: 22.946316 | AD30: 23.143337 | AE30: 23.340731 | AF30: 23.538469 | AG30: 0.011
A31: Warehouse | B31: Commercial: Floorspace: Warehouse: High Zero-Carbon Technology Cost | C31: AEO.2025.HIGHZTC.KEI_FLR_COMM_WHRC_NA_NA_NA_BLNSQFT.A | D31: billion sq ft | F31: 20.811037 | G31: 20.688267 | H31: 21.090683 | I31: 21.530262 | J31: 21.991648 | K31: 22.455757 | L31: 22.914848 | M31: 23.371706 | N31: 23.833302 | O31: 24.301704 | P31: 24.775219 | Q31: 25.250818 | R31: 25.72501 | S31: 26.195992 | T31: 26.664169 | U31: 27.130501 | V31: 27.596041 | W31: 28.06188 | X31: 28.528696 | Y31: 28.997156 | Z31: 29.468058 | AA31: 29.942181 | AB31: 30.420248 | AC31: 30.902866 | AD31: 31.390402 | AE31: 31.883022 | AF31: 32.380737 | AG31: 0.017
A32: Other | B32: Commercial: Floorspace: Other: High Zero-Carbon Technology Cost | C32: AEO.2025.HIGHZTC.KEI_FLR_COMM_OTHU_NA_NA_NA_BLNSQFT.A | D32: billion sq ft | F32: 6.022579 | G32: 6.112623 | H32: 6.203774 | I32: 6.305171 | J32: 6.41219 | K32: 6.519195 | L32: 6.623943 | M32: 6.727274 | N32: 6.831217 | O32: 6.936363 | P32: 7.042219 | Q32: 7.147921 | R32: 7.252486 | S32: 7.355425 | T32: 7.456878 | U32: 7.557133 | V32: 7.656504 | W32: 7.755305 | X32: 7.853741 | Y32: 7.951998 | Z32: 8.050304 | AA32: 8.148876 | AB32: 8.24791 | AC32: 8.347569 | AD32: 8.44795 | AE32: 8.549094 | AF32: 8.650999 | AG32: 0.014
A33: Total | B33: Commercial: Floorspace: Total: High Zero-Carbon Technology Cost | C33: AEO.2025.HIGHZTC.KEI_FLR_COMM_NA_NA_NA_NA_BLNSQFT.A | D33: billion sq ft | F33: 103.37187 | G33: 104.52194 | H33: 105.93502 | I33: 107.51917 | J33: 109.19484 | K33: 110.86568 | L33: 112.49358 | M33: 114.09294 | N33: 115.69831 | O33: 117.31967 | P33: 118.94865 | Q33: 120.57056 | R33: 122.16891 | S33: 123.73556 | T33: 125.27293 | U33: 126.78603 | V33: 128.2802 | W33: 129.76083 | X33: 131.23132 | Y33: 132.6949 | Z33: 134.15536 | AA33: 135.61633 | AB33: 137.08107 | AC33: 138.55231 | AD33: 140.03159 | AE33: 141.51959 | AF33: 143.01623 | AG33: 0.013
A34: Stock Average Equipment Efficiency
A35: Space Heating
A36: Electricity | B36: Commercial: Stock Average Efficiency: Space Heating: Electricity: High Zero-Carbon Technology Cost | C36: AEO.2025.HIGHZTC.EFF_STKE_COMM_SPH_ELC_NA_NA_BTUOTPBTUIN.A | D36: Btu Out/Btu In | F36: 1.689959 | G36: 1.666259 | H36: 1.642267 | I36: 1.618919 | J36: 1.597009 | K36: 1.580247 | L36: 1.560718 | M36: 1.543037 | N36: 1.526859 | O36: 1.519951 | P36: 1.512956 | Q36: 1.496655 | R36: 1.481462 | S36: 1.46725 | T36: 1.45409 | U36: 1.441667 | V36: 1.430003 | W36: 1.419147 | X36: 1.409232 | Y36: 1.399963 | Z36: 1.391268 | AA36: 1.383183 | AB36: 1.37577 | AC36: 1.368958 | AD36: 1.36269 | AE36: 1.356863 | AF36: 1.351421 | AG36: -0.009
A37: Natural Gas | B37: Commercial: Stock Average Efficiency: Space Heating: Natural Gas: High Zero-Carbon Technology Cost | C37: AEO.2025.HIGHZTC.EFF_STKE_COMM_SPH_NG_NA_NA_BTUOTPBTUIN.A | D37: Btu Out/Btu In | F37: 0.820157 | G37: 0.819889 | H37: 0.819612 | I37: 0.81934 | J37: 0.819072 | K37: 0.818812 | L37: 0.818561 | M37: 0.818315 | N37: 0.818077 | O37: 0.817844 | P37: 0.817619 | Q37: 0.817395 | R37: 0.817178 | S37: 0.816968 | T37: 0.816762 | U37: 0.816564 | V37: 0.816371 | W37: 0.816181 | X37: 0.815999 | Y37: 0.81582 | Z37: 0.815648 | AA37: 0.81548 | AB37: 0.815317 | AC37: 0.815159 | AD37: 0.815004 | AE37: 0.814854 | AF37: 0.814708 | AG37: 0
A38: Distillate Fuel Oil | B38: Commercial: Stock Average Efficiency: Space Heating: Distillate Fuel Oil: High Zero-Carbon Technology Cost | C38: AEO.2025.HIGHZTC.EFF_STKE_COMM_SPH_DFO_NA_NA_BTUOTPBTUIN.A | D38: Btu Out/Btu In | F38: 0.840583 | G38: 0.840815 | H38: 0.840996 | I38: 0.841116 | J38: 0.841196 | K38: 0.841251 | L38: 0.841277 | M38: 0.841283 | N38: 0.841268 | O38: 0.84124 | P38: 0.841195 | Q38: 0.84113 | R38: 0.841037 | S38: 0.840934 | T38: 0.840822 | U38: 0.840697 | V38: 0.840566 | W38: 0.840428 | X38: 0.840283 | Y38: 0.840132 | Z38: 0.83998 | AA38: 0.839821 | AB38: 0.839657 | AC38: 0.839488 | AD38: 0.839316 | AE38: 0.839143 | AF38: 0.838965 | AG38: 0
A39: Space Cooling
A40: Electricity | B40: Commercial: Stock Average Efficiency: Space Cooling: Electricity: High Zero-Carbon Technology Cost | C40: AEO.2025.HIGHZTC.EFF_STKE_COMM_SPC_ELC_NA_NA_BTUOTPBTUIN.A | D40: Btu Out/Btu In | F40: 4.258709 | G40: 4.300516 | H40: 4.334456 | I40: 4.366873 | J40: 4.397727 | K40: 4.426824 | L40: 4.459006 | M40: 4.489103 | N40: 4.517692 | O40: 4.546163 | P40: 4.572696 | Q40: 4.596867 | R40: 4.61952 | S40: 4.640612 | T40: 4.660393 | U40: 4.678863 | V40: 4.696362 | W40: 4.712734 | X40: 4.72816 | Y40: 4.742669 | Z40: 4.756349 | AA40: 4.769273 | AB40: 4.781502 | AC40: 4.7931 | AD40: 4.804057 | AE40: 4.814439 | AF40: 4.824294 | AG40: 0.005
A41: Natural Gas | B41: Commercial: Stock Average Efficiency: Space Cooling: Natural Gas: High Zero-Carbon Technology Cost | C41: AEO.2025.HIGHZTC.EFF_STKE_COMM_SPC_NG_NA_NA_BTUOTPBTUIN.A | D41: Btu Out/Btu In | F41: 0.996114 | G41: 1.016301 | H41: 1.024943 | I41: 1.033631 | J41: 1.04149 | K41: 1.049375 | L41: 1.056732 | M41: 1.064031 | N41: 1.071201 | O41: 1.078513 | P41: 1.085678 | Q41: 1.092653 | R41: 1.099439 | S41: 1.106004 | T41: 1.112399 | U41: 1.118591 | V41: 1.124154 | W41: 1.129521 | X41: 1.134754 | Y41: 1.139782 | Z41: 1.14463 | AA41: 1.149363 | AB41: 1.153932 | AC41: 1.158361 | AD41: 1.162617 | AE41: 1.16674 | AF41: 1.170699 | AG41: 0.006
A42: Water Heating
A43: Electricity | B43: Commercial: Stock Average Efficiency: Water Heating: Electricity: High Zero-Carbon Technology Cost | C43: AEO.2025.HIGHZTC.EFF_STKE_COMM_WTHT_ELC_NA_NA_BTUOTPBTUIN.A | D43: Btu Out/Btu In | F43: 1.079736 | G43: 1.087494 | H43: 1.092399 | I43: 1.096764 | J43: 1.101024 | K43: 1.10532 | L43: 1.109727 | M43: 1.114732 | N43: 1.119938 | O43: 1.125932 | P43: 1.131828 | Q43: 1.137575 | R43: 1.143182 | S43: 1.148643 | T43: 1.154029 | U43: 1.159391 | V43: 1.164619 | W43: 1.170236 | X43: 1.175714 | Y43: 1.181066 | Z43: 1.186285 | AA43: 1.191437 | AB43: 1.196554 | AC43: 1.201647 | AD43: 1.206899 | AE43: 1.212083 | AF43: 1.217387 | AG43: 0.005
A44: Natural Gas | B44: Commercial: Stock Average Efficiency: Water Heating: Natural Gas: High Zero-Carbon Technology Cost | C44: AEO.2025.HIGHZTC.EFF_STKE_COMM_WTHT_NG_NA_NA_BTUOTPBTUIN.A | D44: Btu Out/Btu In | F44: 0.867971 | G44: 0.872665 | H44: 0.877094 | I44: 0.886201 | J44: 0.894356 | K44: 0.901592 | L44: 0.907975 | M44: 0.913614 | N44: 0.918603 | O44: 0.923024 | P44: 0.926931 | Q44: 0.930372 | R44: 0.933399 | S44: 0.936057 | T44: 0.938393 | U44: 0.940446 | V44: 0.942252 | W44: 0.943841 | X44: 0.945238 | Y44: 0.94647 | Z44: 0.947554 | AA44: 0.948508 | AB44: 0.949347 | AC44: 0.950085 | AD44: 0.950733 | AE44: 0.951304 | AF44: 0.951805 | AG44: 0.004
A45: Distillate Fuel Oil | B45: Commercial: Stock Average Efficiency: Water Heating: Distillate Fuel Oil: High Zero-Carbon Technology Cost | C45: AEO.2025.HIGHZTC.EFF_STKE_COMM_WTHT_DFO_NA_NA_BTUOTPBTUIN.A | D45: Btu Out/Btu In | F45: 0.811931 | G45: 0.81256 | H45: 0.813125 | I45: 0.81366 | J45: 0.814162 | K45: 0.814628 | L45: 0.815059 | M45: 0.815457 | N45: 0.815827 | O45: 0.816169 | P45: 0.816484 | Q45: 0.816775 | R45: 0.817043 | S45: 0.81729 | T45: 0.817516 | U45: 0.817724 | V45: 0.817915 | W45: 0.81809 | X45: 0.818251 | Y45: 0.818398 | Z45: 0.818534 | AA45: 0.818658 | AB45: 0.818772 | AC45: 0.818877 | AD45: 0.818973 | AE45: 0.819061 | AF45: 0.819141 | AG45: 0
A46: Ventilation (cubic feet per minute per Btu)
A47: Electricity | B47: Commercial: Stock Average Efficiency: Ventilation: Electricity: High Zero-Carbon Technology Cost | C47: AEO.2025.HIGHZTC.EFF_STKE_COMM_VNTC_ELC_NA_NA_CUFTPMINPBTU.A | D47: cu ft/minute/Btu | F47: 0.370193 | G47: 0.371766 | H47: 0.373235 | I47: 0.374681 | J47: 0.376089 | K47: 0.377442 | L47: 0.380059 | M47: 0.382554 | N47: 0.38493 | O47: 0.387196 | P47: 0.389352 | Q47: 0.391402 | R47: 0.393347 | S47: 0.395191 | T47: 0.39694 | U47: 0.398599 | V47: 0.400176 | W47: 0.40168 | X47: 0.403112 | Y47: 0.404477 | Z47: 0.405778 | AA47: 0.407018 | AB47: 0.408203 | AC47: 0.409334 | AD47: 0.410413 | AE47: 0.411446 | AF47: 0.412433 | AG47: 0.004
A48: Cooking
A49: Electricity | B49: Commercial: Stock Average Efficiency: Cooking: Electricity: High Zero-Carbon Technology Cost | C49: AEO.2025.HIGHZTC.EFF_STKE_COMM_CGR_ELC_NA_NA_BTUOTPBTUIN.A | D49: Btu Out/Btu In | F49: 0.708108 | G49: 0.708667 | H49: 0.709152 | I49: 0.709595 | J49: 0.709997 | K49: 0.71036 | L49: 0.710687 | M49: 0.710981 | N49: 0.711246 | O49: 0.711486 | P49: 0.711704 | Q49: 0.711899 | R49: 0.712076 | S49: 0.712235 | T49: 0.712379 | U49: 0.712509 | V49: 0.712626 | W49: 0.712732 | X49: 0.712828 | Y49: 0.712915 | Z49: 0.712993 | AA49: 0.713064 | AB49: 0.713129 | AC49: 0.713187 | AD49: 0.71324 | AE49: 0.713288 | AF49: 0.713331 | AG49: 0
A50: Natural Gas | B50: Commercial: Stock Average Efficiency: Cooking: Natural Gas: High Zero-Carbon Technology Cost | C50: AEO.2025.HIGHZTC.EFF_STKE_COMM_CGR_NG_NA_NA_BTUOTPBTUIN.A | D50: Btu Out/Btu In | F50: 0.32267 | G50: 0.325773 | H50: 0.328432 | I50: 0.330852 | J50: 0.333034 | K50: 0.334982 | L50: 0.336715 | M50: 0.338259 | N50: 0.339636 | O50: 0.340866 | P50: 0.341963 | Q50: 0.342939 | R50: 0.343807 | S50: 0.344578 | T50: 0.345264 | U50: 0.345873 | V50: 0.346415 | W50: 0.346898 | X50: 0.347328 | Y50: 0.347711 | Z50: 0.348052 | AA50: 0.348356 | AB50: 0.348627 | AC50: 0.348869 | AD50: 0.349084 | AE50: 0.349276 | AF50: 0.349448 | AG50: 0.003
A51: Lighting Efficacy
A52: (efficacy in lumens per watt)
A53: Electricity | B53: Commercial: Stock Average Efficiency: Lighting Efficacy: Electricity: High Zero-Carbon Technology Cost | C53: AEO.2025.HIGHZTC.EFF_STKE_COMM_LGHTNG_ELC_NA_NA_LMNPWATT.A | D53: lumens/watt | F53: 75.495743 | G53: 78.406456 | H53: 80.647705 | I53: 82.438683 | J53: 83.836082 | K53: 85.001984 | L53: 87.771721 | M53: 90.388016 | N53: 92.890007 | O53: 95.361961 | P53: 97.894905 | Q53: 100.43623 | R53: 102.85927 | S53: 105.05647 | T53: 107.06066 | U53: 108.87384 | V53: 110.9582 | W53: 112.86351 | X53: 114.57954 | Y53: 116.11516 | Z53: 117.51068 | AA53: 118.76211 | AB53: 119.895 | AC53: 121.15402 | AD53: 122.30565 | AE53: 123.35109 | AF53: 124.39072 | AG53: 0.019
A54: Refrigeration
A55: Electricity | B55: Commercial: Stock Average Efficiency: Refrigeration: Electricity: High Zero-Carbon Technology Cost | C55: AEO.2025.HIGHZTC.EFF_STKE_COMM_REFR_ELC_NA_NA_BTUOTPBTUIN.A | D55: Btu Out/Btu In | F55: 3.648687 | G55: 3.683043 | H55: 3.714184 | I55: 3.742016 | J55: 3.766798 | K55: 3.788743 | L55: 3.81943 | M55: 3.846573 | N55: 3.870695 | O55: 3.892154 | P55: 3.911194 | Q55: 3.928063 | R55: 3.942988 | S55: 3.956189 | T55: 3.967906 | U55: 3.978283 | V55: 3.987513 | W55: 3.995587 | X55: 4.002774 | Y55: 4.009179 | Z55: 4.01491 | AA55: 4.02003 | AB55: 4.024622 | AC55: 4.028744 | AD55: 4.032453 | AE55: 4.03581 | AF55: 4.038882 | AG55: 0.004
A56: Distributed Generation and
A57: Combined Heat and Power
A58: Generating Capacity (gigawatts)
A59: Petroleum | B59: Commercial: Combined Heat and Power: Generating Capacity: Petroleum: High Zero-Carbon Technology Cost | C59: AEO.2025.HIGHZTC.CAP_NA_COMM_CHP_PET_NA_NA_MW.A | D59: GW | F59: 0.020507 | G59: 0.020507 | H59: 0.020507 | I59: 0.020507 | J59: 0.020507 | K59: 0.020507 | L59: 0.020507 | M59: 0.020507 | N59: 0.020507 | O59: 0.020507 | P59: 0.020507 | Q59: 0.020507 | R59: 0.020507 | S59: 0.020507 | T59: 0.020507 | U59: 0.020507 | V59: 0.020507 | W59: 0.020507 | X59: 0.020507 | Y59: 0.020507 | Z59: 0.020507 | AA59: 0.020507 | AB59: 0.020507 | AC59: 0.020507 | AD59: 0.020507 | AE59: 0.020507 | AF59: 0.020507 | AG59: 0
A60: Natural Gas | B60: Commercial: Combined Heat and Power: Generating Capacity: Natural Gas: High Zero-Carbon Technology Cost | C60: AEO.2025.HIGHZTC.CAP_NA_COMM_CHP_NG_NA_NA_MW.A | D60: GW | F60: 1.468725 | G60: 1.491927 | H60: 1.51303 | I60: 1.537755 | J60: 1.566026 | K60: 1.595875 | L60: 1.62534 | M60: 1.656078 | N60: 1.684031 | O60: 1.715831 | P60: 1.743984 | Q60: 1.769621 | R60: 1.794761 | S60: 1.818971 | T60: 1.844858 | U60: 1.867743 | V60: 1.890473 | W60: 1.913854 | X60: 1.937492 | Y60: 1.960683 | Z60: 1.9845 | AA60: 2.00775 | AB60: 2.030395 | AC60: 2.054643 | AD60: 2.079596 | AE60: 2.104159 | AF60: 2.12886 | AG60: 0.014
A61: Solar Photovoltaic | B61: Commercial: Combined Heat and Power: Generating Capacity: Solar Photovoltaic: High Zero-Carbon Technology Cost | C61: AEO.2025.HIGHZTC.CAP_NA_COMM_CHP_SLR_PHTVL_NA_MW.A | D61: GW | F61: 29.4039 | G61: 33.142555 | H61: 36.800396 | I61: 38.358521 | J61: 39.891655 | K61: 42.091751 | L61: 44.706081 | M61: 48.084167 | N61: 51.117046 | O61: 54.807766 | P61: 57.239326 | Q61: 58.673073 | R61: 59.890533 | S61: 61.188202 | T61: 63.243031 | U61: 64.33918 | V61: 65.586029 | W61: 67.469231 | X61: 69.360336 | Y61: 71.423912 | Z61: 73.477112 | AA61: 75.590889 | AB61: 77.521835 | AC61: 79.788017 | AD61: 82.122704 | AE61: 84.37561 | AF61: 86.847687 | AG61: 0.043
A62: Wind | B62: Commercial: Combined Heat and Power: Generating Capacity: Wind: High Zero-Carbon Technology Cost | C62: AEO.2025.HIGHZTC.CAP_NA_COMM_CHP_WND_NA_NA_MW.A | D62: GW | F62: 0.58564 | G62: 0.58614 | H62: 0.585976 | I62: 0.585812 | J62: 0.585966 | K62: 0.587707 | L62: 0.589139 | M62: 0.591231 | N62: 0.594085 | O62: 0.598396 | P62: 0.599722 | Q62: 0.60002 | R62: 0.600294 | S62: 0.600514 | T62: 0.601311 | U62: 0.602011 | V62: 0.602796 | W62: 0.603841 | X62: 0.604634 | Y62: 0.605307 | Z62: 0.606434 | AA62: 0.607621 | AB62: 0.608561 | AC62: 0.609704 | AD62: 0.610887 | AE62: 0.611937 | AF62: 0.613521 | AG62: 0.002
A63: Other | B63: Commercial: Combined Heat and Power: Generating Capacity: Other: High Zero-Carbon Technology Cost | C63: AEO.2025.HIGHZTC.CAP_NA_COMM_CHP_OTH_NA_NA_MW.A | D63: GW | F63: 0.130753 | G63: 0.130753 | H63: 0.130753 | I63: 0.130753 | J63: 0.130753 | K63: 0.130753 | L63: 0.130753 | M63: 0.130753 | N63: 0.130753 | O63: 0.130753 | P63: 0.130753 | Q63: 0.130753 | R63: 0.130753 | S63: 0.130753 | T63: 0.130753 | U63: 0.130753 | V63: 0.130753 | W63: 0.130753 | X63: 0.130753 | Y63: 0.130753 | Z63: 0.130753 | AA63: 0.130753 | AB63: 0.130753 | AC63: 0.130753 | AD63: 0.130753 | AE63: 0.130753 | AF63: 0.130753 | AG63: 0
A64: Total | B64: Commercial: Combined Heat and Power: Generating Capacity: Total: High Zero-Carbon Technology Cost | C64: AEO.2025.HIGHZTC.CAP_NA_COMM_CHP_TOT_NA_NA_MW.A | D64: GW | F64: 31.609526 | G64: 35.371883 | H64: 39.050663 | I64: 40.633347 | J64: 42.194908 | K64: 44.426594 | L64: 47.071819 | M64: 50.482738 | N64: 53.546421 | O64: 57.273254 | P64: 59.734291 | Q64: 61.193974 | R64: 62.436848 | S64: 63.758945 | T64: 65.840462 | U64: 66.960197 | V64: 68.23056 | W64: 70.138191 | X64: 72.053726 | Y64: 74.141167 | Z64: 76.219299 | AA64: 78.357521 | AB64: 80.31205 | AC64: 82.603622 | AD64: 84.964447 | AE64: 87.242966 | AF64: 89.741325 | AG64: 0.041
A65: Net Generation (billion kilowatthours)
A66: Petroleum | B66: Commercial: Combined Heat and Power: Net Generation: Petroleum: High Zero-Carbon Technology Cost | C66: AEO.2025.HIGHZTC.GEN_NA_COMM_CHP_PET_NA_NA_MILLKWH.A | D66: billion kWh | F66: 0.081209 | G66: 0.081209 | H66: 0.081209 | I66: 0.081209 | J66: 0.081209 | K66: 0.081209 | L66: 0.081209 | M66: 0.081209 | N66: 0.081209 | O66: 0.081209 | P66: 0.081209 | Q66: 0.081209 | R66: 0.081209 | S66: 0.081209 | T66: 0.081209 | U66: 0.081209 | V66: 0.081209 | W66: 0.081209 | X66: 0.081209 | Y66: 0.081209 | Z66: 0.081209 | AA66: 0.081209 | AB66: 0.081209 | AC66: 0.081209 | AD66: 0.081209 | AE66: 0.081209 | AF66: 0.081209 | AG66: 0
A67: Natural Gas | B67: Commercial: Combined Heat and Power: Net Generation: Natural Gas: High Zero-Carbon Technology Cost | C67: AEO.2025.HIGHZTC.GEN_NA_COMM_CHP_NG_NA_NA_MILLKWH.A | D67: billion kWh | F67: 8.774793 | G67: 8.913601 | H67: 9.042305 | I67: 9.192992 | J67: 9.363314 | K67: 9.541547 | L67: 9.716731 | M67: 9.897564 | N67: 10.06468 | O67: 10.251438 | P67: 10.419797 | Q67: 10.57531 | R67: 10.727733 | S67: 10.874772 | T67: 11.029309 | U67: 11.168316 | V67: 11.306188 | W67: 11.446854 | X67: 11.588435 | Y67: 11.727713 | Z67: 11.869937 | AA67: 12.009144 | AB67: 12.145295 | AC67: 12.289522 | AD67: 12.437376 | AE67: 12.583395 | AF67: 12.730259 | AG67: 0.014
A68: Solar Photovoltaic | B68: Commercial: Combined Heat and Power: Net Generation: Solar Photovoltaic: High Zero-Carbon Technology Cost | C68: AEO.2025.HIGHZTC.GEN_NA_COMM_CHP_SLR_PHTVL_NA_MILLKWH.A | D68: billion kWh | F68: 40.940166 | G68: 45.887695 | H68: 50.716282 | I68: 52.765446 | J68: 54.753529 | K68: 57.639774 | L68: 61.06139 | M68: 65.40625 | N68: 69.372765 | O68: 74.072678 | P68: 77.172493 | Q68: 79.02594 | R68: 80.611717 | S68: 82.329025 | T68: 84.916397 | U68: 86.38636 | V68: 88.04847 | W68: 90.493286 | X68: 92.879173 | Y68: 95.495697 | Z68: 98.128258 | AA68: 100.85287 | AB68: 103.32527 | AC68: 106.20082 | AD68: 109.17127 | AE68: 112.04884 | AF68: 115.19003 | AG68: 0.041
A69: Wind | B69: Commercial: Combined Heat and Power: Net Generation: Wind: High Zero-Carbon Technology Cost | C69: AEO.2025.HIGHZTC.GEN_NA_COMM_CHP_WND_NA_NA_MILLKWH.A | D69: billion kWh | F69: 0.741164 | G69: 0.741862 | H69: 0.741634 | I69: 0.741405 | J69: 0.741585 | K69: 0.743387 | L69: 0.744916 | M69: 0.747153 | N69: 0.750224 | O69: 0.754975 | P69: 0.7566 | Q69: 0.756915 | R69: 0.757258 | S69: 0.757475 | T69: 0.758398 | U69: 0.759129 | V69: 0.759939 | W69: 0.761029 | X69: 0.761872 | Y69: 0.762598 | Z69: 0.763846 | AA69: 0.765101 | AB69: 0.766083 | AC69: 0.767297 | AD69: 0.768562 | AE69: 0.769681 | AF69: 0.771365 | AG69: 0.002
A70: Other | B70: Commercial: Combined Heat and Power: Net Generation: Other: High Zero-Carbon Technology Cost | C70: AEO.2025.HIGHZTC.GEN_NA_COMM_CHP_OTH_NA_NA_MILLKWH.A | D70: billion kWh | F70: 0.951386 | G70: 0.951386 | H70: 0.951386 | I70: 0.951386 | J70: 0.951386 | K70: 0.951386 | L70: 0.951386 | M70: 0.951386 | N70: 0.951386 | O70: 0.951386 | P70: 0.951386 | Q70: 0.951386 | R70: 0.951386 | S70: 0.951386 | T70: 0.951386 | U70: 0.951386 | V70: 0.951386 | W70: 0.951386 | X70: 0.951386 | Y70: 0.951386 | Z70: 0.951386 | AA70: 0.951386 | AB70: 0.951386 | AC70: 0.951386 | AD70: 0.951386 | AE70: 0.951386 | AF70: 0.951386 | AG70: 0
A71: Total | B71: Commercial: Combined Heat and Power: Net Generation: Total: High Zero-Carbon Technology Cost | C71: AEO.2025.HIGHZTC.GEN_NA_COMM_CHP_TOT_NA_NA_MILLKWH.A | D71: billion kWh | F71: 51.488716 | G71: 56.575752 | H71: 61.532814 | I71: 63.732437 | J71: 65.891022 | K71: 68.957298 | L71: 72.555634 | M71: 77.083565 | N71: 81.220261 | O71: 86.111687 | P71: 89.381485 | Q71: 91.390755 | R71: 93.129295 | S71: 94.993866 | T71: 97.736702 | U71: 99.346405 | V71: 101.14719 | W71: 103.73377 | X71: 106.26207 | Y71: 109.0186 | Z71: 111.79464 | AA71: 114.65971 | AB71: 117.26924 | AC71: 120.29023 | AD71: 123.4098 | AE71: 126.43451 | AF71: 129.72424 | AG71: 0.036
A72: Disposition
A73: Sales to the Grid | B73: Commercial: Combined Heat and Power: Net Generation: Sales to the Grid: High Zero-Carbon Technology Cost | C73: AEO.2025.HIGHZTC.GEN_NA_COMM_CHP_STG_NA_NA_MILLKWH.A | D73: billion kWh | F73: 9.946276 | G73: 10.073193 | H73: 10.197064 | I73: 10.341887 | J73: 10.500024 | K73: 10.665711 | L73: 10.825236 | M73: 10.987113 | N73: 11.14402 | O73: 11.313128 | P73: 11.467194 | Q73: 11.614271 | R73: 11.757989 | S73: 11.897467 | T73: 12.037536 | U73: 12.171236 | V73: 12.30372 | W73: 12.435464 | X73: 12.565181 | Y73: 12.693213 | Z73: 12.822459 | AA73: 12.951511 | AB73: 13.079132 | AC73: 13.211131 | AD73: 13.344397 | AE73: 13.477484 | AF73: 13.611878 | AG73: 0.012
A74: Generation for Own Use | B74: Commercial: Combined Heat and Power: Net Generation: Generation for Own Use: High Zero-Carbon Technology Cost | C74: AEO.2025.HIGHZTC.GEN_NA_COMM_CHP_GFO_NA_NA_MILLKWH.A | D74: billion kWh | F74: 41.54245 | G74: 46.502563 | H74: 51.335747 | I74: 53.390553 | J74: 55.390995 | K74: 58.291595 | L74: 61.7304 | M74: 66.096443 | N74: 70.076241 | O74: 74.798553 | P74: 77.914291 | Q74: 79.776482 | R74: 81.371323 | S74: 83.096397 | T74: 85.699165 | U74: 87.175163 | V74: 88.843468 | W74: 91.298294 | X74: 93.696892 | Y74: 96.325394 | Z74: 98.972176 | AA74: 101.7082 | AB74: 104.19012 | AC74: 107.07911 | AD74: 110.0654 | AE74: 112.95702 | AF74: 116.11237 | AG74: 0.04
A75: Energy Input (trillion Btu)
A76: Petroleum | B76: Commercial: Combined Heat and Power: Energy Input: Petroleum: High Zero-Carbon Technology Cost | C76: AEO.2025.HIGHZTC.CNSM_NA_COMM_CHP_PET_NA_NA_TRLBTU.A | D76: trillion Btu | F76: 0.824655 | G76: 0.824655 | H76: 0.824655 | I76: 0.824655 | J76: 0.824655 | K76: 0.824655 | L76: 0.824655 | M76: 0.824655 | N76: 0.824655 | O76: 0.824655 | P76: 0.824655 | Q76: 0.824655 | R76: 0.824655 | S76: 0.824655 | T76: 0.824655 | U76: 0.824655 | V76: 0.824655 | W76: 0.824655 | X76: 0.824655 | Y76: 0.824655 | Z76: 0.824655 | AA76: 0.824655 | AB76: 0.824655 | AC76: 0.824655 | AD76: 0.824655 | AE76: 0.824655 | AF76: 0.824655 | AG76: 0
A77: Natural Gas | B77: Commercial: Combined Heat and Power: Energy Input: Natural Gas: High Zero-Carbon Technology Cost | C77: AEO.2025.HIGHZTC.CNSM_NA_COMM_CHP_NG_NA_NA_TRLBTU.A | D77: trillion Btu | F77: 113.84644 | G77: 115.64671 | H77: 117.34186 | I77: 119.32573 | J77: 121.5502 | K77: 123.85913 | L77: 126.12149 | M77: 128.43654 | N77: 130.60405 | O77: 132.99071 | P77: 135.17598 | Q77: 137.21712 | R77: 139.21729 | S77: 141.14899 | T77: 143.15292 | U77: 144.97745 | V77: 146.78522 | W77: 148.61865 | X77: 150.45962 | Y77: 152.2746 | Z77: 154.12007 | AA77: 155.92902 | AB77: 157.70288 | AC77: 159.56619 | AD77: 161.47075 | AE77: 163.35565 | AF77: 165.25282 | AG77: 0.014
A78: Solar Photovoltaic | B78: Commercial: Combined Heat and Power: Energy Input: Solar Photovoltaic: High Zero-Carbon Technology Cost | C78: AEO.2025.HIGHZTC.CNSM_NA_COMM_CHP_SLR_PHTVL_NA_TRLBTU.A | D78: trillion Btu | F78: 139.68785 | G78: 156.56882 | H78: 173.04395 | I78: 180.03567 | J78: 186.81902 | K78: 196.6669 | L78: 208.34146 | M78: 223.16612 | N78: 236.69986 | O78: 252.73596 | P78: 263.3125 | Q78: 269.63648 | R78: 275.04718 | S78: 280.90659 | T78: 289.73474 | U78: 294.75024 | V78: 300.42133 | W78: 308.76306 | X78: 316.90372 | Y78: 325.83124 | Z78: 334.8136 | AA78: 344.10992 | AB78: 352.54584 | AC78: 362.35718 | AD78: 372.49234 | AE78: 382.31061 | AF78: 393.02838 | AG78: 0.041
A79: Wind | B79: Commercial: Combined Heat and Power: Energy Input: Wind: High Zero-Carbon Technology Cost | C79: AEO.2025.HIGHZTC.CNSM_NA_COMM_CHP_WND_NA_NA_TRLBTU.A | D79: trillion Btu | F79: 2.528852 | G79: 2.531234 | H79: 2.530454 | I79: 2.529673 | J79: 2.530288 | K79: 2.536436 | L79: 2.541655 | M79: 2.549285 | N79: 2.559764 | O79: 2.575974 | P79: 2.581518 | Q79: 2.582592 | R79: 2.583763 | S79: 2.584505 | T79: 2.587654 | U79: 2.590147 | V79: 2.592913 | W79: 2.596629 | X79: 2.599507 | Y79: 2.601985 | Z79: 2.606242 | AA79: 2.610524 | AB79: 2.613875 | AC79: 2.618018 | AD79: 2.622333 | AE79: 2.626152 | AF79: 2.631898 | AG79: 0.002
A80: Other | B80: Commercial: Combined Heat and Power: Energy Input: Other: High Zero-Carbon Technology Cost | C80: AEO.2025.HIGHZTC.CNSM_NA_COMM_CHP_OTH_NA_NA_TRLBTU.A | D80: trillion Btu | F80: 19.423716 | G80: 19.423716 | H80: 19.423716 | I80: 19.423716 | J80: 19.423716 | K80: 19.423716 | L80: 19.423716 | M80: 19.423716 | N80: 19.423716 | O80: 19.423716 | P80: 19.423716 | Q80: 19.423716 | R80: 19.423716 | S80: 19.423716 | T80: 19.423716 | U80: 19.423716 | V80: 19.423716 | W80: 19.423716 | X80: 19.423716 | Y80: 19.423716 | Z80: 19.423716 | AA80: 19.423716 | AB80: 19.423716 | AC80: 19.423716 | AD80: 19.423716 | AE80: 19.423716 | AF80: 19.423716 | AG80: 0
A81: Total | B81: Commercial: Combined Heat and Power: Energy Input: Total: High Zero-Carbon Technology Cost | C81: AEO.2025.HIGHZTC.CNSM_NA_COMM_CHP_TOT_NA_NA_TRLBTU.A | D81: trillion Btu | F81: 276.31149 | G81: 294.99512 | H81: 313.16461 | I81: 322.13943 | J81: 331.14786 | K81: 343.31082 | L81: 357.25296 | M81: 374.4003 | N81: 390.11203 | O81: 408.55102 | P81: 421.31836 | Q81: 429.68454 | R81: 437.09659 | S81: 444.88846 | T81: 455.72369 | U81: 462.56622 | V81: 470.04782 | W81: 480.22668 | X81: 490.21121 | Y81: 500.95618 | Z81: 511.78827 | AA81: 522.89783 | AB81: 533.11096 | AC81: 544.7898 | AD81: 556.83374 | AE81: 568.54077 | AF81: 581.16144 | AG81: 0.029

Sheet RECS HC2.1
A1: Preliminary data release date: March 2022
A2: Table HC2.1 Structural and geographic characteristics of U.S. homes, by housing unit type, 2020
B3: Number of housing units (million)
C4: Housing unit type
B5: Total U.S.a | C5: Single-family detached | D5: Single-family attached | E5: Apartments (2–4 unit building) | F5: Apartments (5 or more unit building) | G5: Mobile home
A6: All homes | B6: 123.53 | C6: 77.07 | D6: 7.45 | E6: 9.34 | F6: 22.84 | G6: 6.83
A7: Census region and division
A8: Northeast | B8: 21.92 | C8: 11.23 | D8: 1.95 | E8: 3.15 | F8: 5.1 | G8: 0.5
A9: New England | B9: 5.88 | C9: 3.34 | D9: 0.3 | E9: 0.99 | F9: 1.1 | G9: 0.14
A10: Middle Atlantic | B10: 16.04 | C10: 7.89 | D10: 1.65 | E10: 2.15 | F10: 3.99 | G10: 0.36
A11: Midwest | B11: 27.04 | C11: 18.58 | D11: 1.33 | E11: 1.95 | F11: 4.2 | G11: 0.97
A12: East North Central | B12: 18.55 | C12: 12.59 | D12: 0.91 | E12: 1.49 | F12: 2.94 | G12: 0.63
A13: West North Central | B13: 8.5 | C13: 5.99 | D13: 0.43 | E13: 0.47 | F13: 1.26 | G13: 0.35
A14: South | B14: 46.84 | C14: 30.29 | D14: 2.48 | E14: 2.36 | F14: 7.83 | G14: 3.89
A15: South Atlantic | B15: 24.84 | C15: 15.25 | D15: 1.92 | E15: 1.17 | F15: 4.51 | G15: 2
A16: East South Central | B16: 7.38 | C16: 5.17 | D16: 0.19 | E16: 0.41 | F16: 0.84 | G16: 0.77
A17: West South Central | B17: 14.62 | C17: 9.87 | D17: 0.36 | E17: 0.78 | F17: 2.48 | G17: 1.12
A18: West | B18: 27.72 | C18: 16.97 | D18: 1.69 | E18: 1.89 | F18: 5.7 | G18: 1.47
A19: Mountain | B19: 9.22 | C19: 6.06 | D19: 0.5 | E19: 0.52 | F19: 1.47 | G19: 0.67
... A22: Pacific | B22: 18.51 | C22: 10.91 | D22: 1.19 | E22: 1.36 | F22: 4.24 | G22: 0.8
A23: Census urban-rural classificationb
A24: Urban | B24: 100.44 | C24: 58.8 | D24: 7.04 | E24: 9.02 | F24: 22.27 | G24: 3.31
A25: Urbanized area | B25: 89.24 | C25: 50.99 | D25: 6.57 | E25: 7.95 | F25: 21.2 | G25: 2.53
A26: Urban cluster | B26: 11.2 | C26: 7.82 | D26: 0.47 | E26: 1.07 | F26: 1.07 | G26: 0.77
A27: Rural | B27: 23.09 | C27: 18.27 | D27: 0.41 | E27: 0.32 | F27: 0.57 | G27: 3.52
A28: Climate regionc
A29: Very cold/Cold | B29: 42.5 | C29: 28.04 | D29: 2.43 | E29: 3.78 | F29: 6.74 | G29: 1.52
A30: Mixed-humid | B30: 36.79 | C30: 21.89 | D30: 2.8 | E30: 2.72 | F30: 7.03 | G30: 2.35
A31: Mixed-dry/Hot-dry | B31: 15.06 | C31: 9.07 | D31: 0.9 | E31: 1.12 | F31: 3.12 | G31: 0.83
A32: Hot-humid | B32: 22.31 | C32: 13.98 | D32: 0.92 | E32: 1.25 | F32: 4.37 | G32: 1.8
A33: Marine | B33: 6.87 | C33: 4.09 | D33: 0.4 | E33: 0.48 | F33: 1.57 | G33: 0.34
A34: Year of construction
A35: Before 1950 | B35: 20.26 | C35: 13.58 | D35: 1.14 | E35: 2.36 | F35: 3.08 | G35: 0.09
A36: 1950 to 1959 | B36: 12.48 | C36: 9.9 | D36: 0.4 | E36: 0.77 | F36: 1.25 | G36: 0.16
A37: 1960 to 1969 | B37: 12.76 | C37: 8.23 | D37: 0.63 | E37: 1.12 | F37: 2.41 | G37: 0.37
A38: 1970 to 1979 | B38: 18.34 | C38: 10.46 | D38: 0.97 | E38: 1.56 | F38: 4.01 | G38: 1.34
A39: 1980 to 1989 | B39: 16.3 | C39: 8.67 | D39: 1.26 | E39: 1.43 | F39: 3.6 | G39: 1.33
A40: 1990 to 1999 | B40: 17.16 | C40: 10.65 | D40: 1.08 | E40: 0.95 | F40: 2.55 | G40: 1.92
A41: 2000 to 2009 | B41: 16.16 | C41: 9.98 | D41: 1.31 | E41: 0.72 | F41: 3.17 | G41: 0.98
A42: 2010 to 2015 | B42: 5.53 | C42: 3.05 | D42: 0.37 | E42: 0.26 | F42: 1.52 | G42: 0.32
A43: 2016 to 2020 | B43: 4.56 | C43: 2.53 | D43: 0.29 | E43: 0.18 | F43: 1.26 | G43: 0.31
A44: Number of stories
A45: 1 story | B45: 47.15 | C45: 44.59 | D45: 2.57 | E45: N | F45: N | G45: N
A46: 2 stories | B46: 32.47 | C46: 28.53 | D46: 3.94 | E46: N | F46: N | G46: N
A47: 3 or more stories | B47: 2.61 | C47: 1.76 | D47: 0.85 | E47: N | F47: N | G47: N
A48: Split-level | B48: 2.28 | C48: 2.19 | D48: 0.09 | E48: N | F48: N | G48: N
A49: Not asked (apartments and mobile homes) | B49: 39.01 | C49: N | D49: N | E49: 9.34 | F49: 22.84 | G49: 6.83
A50: Major outside wall construction
A51: Siding (aluminum, fiber cement, vinyl, or steel) | B51: 45.44 | C51: 31.14 | D51: 2.83 | E51: 2.23 | F51: 3.79 | G51: 5.45
A52: Brick | B52: 33.37 | C52: 17.52 | D52: 2.01 | E52: 3.79 | F52: 9.8 | G52: 0.24
A53: Wood | B53: 18.8 | C53: 12.63 | D53: 0.92 | E53: 1.55 | F53: 2.86 | G53: 0.84
A54: Stucco | B54: 15.65 | C54: 10.54 | D54: 1.07 | E54: 0.89 | F54: 3.08 | G54: 0.08
A55: Concrete block | B55: 6.42 | C55: 2.89 | D55: 0.41 | E55: 0.5 | F55: 2.56 | G55: Q
A56: Shingle (composition) | B56: 1.89 | C56: 1.16 | D56: 0.11 | E56: 0.21 | F56: 0.3 | G56: 0.11
A57: Stone | B57: 1.46 | C57: 0.94 | D57: 0.08 | E57: 0.14 | F57: 0.31 | G57: N
A58: Some other material | B58: 0.5 | C58: 0.26 | D58: Q | E58: Q | F58: 0.14 | G58: Q
A59: Major roofing material
A60: Shingles (composition or asphalt) | B60: 76.03 | C60: 61.56 | D60: 5.49 | E60: 5.89 | F60: N | G60: 3.09
A61: Metal | B61: 9.69 | C61: 5.87 | D61: 0.28 | E61: 0.46 | F61: N | G61: 3.08
A62: Wood shingles or shakes | B62: 5.19 | C62: 3.06 | D62: 0.55 | E62: 1.23 | F62: N | G62: 0.35
A63: Ceramic or clay tiles | B63: 4.89 | C63: 3.6 | D63: 0.59 | E63: 0.66 | F63: N | G63: Q
A64: Concrete tiles | B64: 2.14 | C64: 1.58 | D64: 0.11 | E64: 0.43 | F64: N | G64: Q
A65: Slate or synthetic slate | B65: 1.49 | C65: 0.73 | D65: 0.18 | E65: 0.51 | F65: N | G65: 0.08
A66: Some other material | B66: 1.26 | C66: 0.67 | D66: 0.27 | E66: 0.15 | F66: N | G66: 0.18
A67: Not asked (apartments in buildings with 5 or more units) | B67: 22.84 | C67: N | D67: N | E67: N | F67: 22.84 | G67: N
A68: Total number of rooms (excluding bathrooms)
A69: 1 or 2 | B69: 4.59 | C69: 0.09 | D69: 0.05 | E69: 0.77 | F69: 3.56 | G69: 0.11
A70: 3 | B70: 8.73 | C70: 0.65 | D70: 0.3 | E70: 1.71 | F70: 5.86 | G70: 0.21
A71: 4 | B71: 15.95 | C71: 3.3 | D71: 1.46 | E71: 3.04 | F71: 6.98 | G71: 1.17
A72: 5 | B72: 19.54 | C72: 9.77 | D72: 1.81 | E72: 2.17 | F72: 4.13 | G72: 1.65
A73: 6 | B73: 22.1 | C73: 15.86 | D73: 1.66 | E73: 0.97 | F73: 1.68 | G73: 1.94
A74: 7 | B74: 18.86 | C74: 16.23 | D74: 1.1 | E74: 0.27 | F74: 0.38 | G74: 0.87
A75: 8 | B75: 13.87 | C75: 12.42 | D75: 0.56 | E75: 0.16 | F75: 0.15 | G75: 0.58
A76: 9 or more | B76: 19.9 | C76: 18.73 | D76: 0.51 | E76: 0.25 | F76: 0.11 | G76: 0.3
A77: Number of bedrooms
A78: 0 | B78: 1.82 | C78: 0.1 | D78: Q | E78: 0.32 | F78: 1.36 | G78: Q
A79: 1 | B79: 14.52 | C79: 1.25 | D79: 0.49 | E79: 2.61 | F79: 9.78 | G79: 0.4
A80: 2 | B80: 30.67 | C80: 10.56 | D80: 3.19 | E80: 4.57 | F80: 9.99 | G80: 2.36
A81: 3 | B81: 48.27 | C81: 38.87 | D81: 2.94 | E81: 1.48 | F81: 1.51 | G81: 3.49
A82: 4 | B82: 22.08 | C82: 20.61 | D82: 0.58 | E82: 0.23 | F82: 0.15 | G82: 0.51
A83: 5 or more | B83: 6.16 | C83: 5.69 | D83: 0.21 | E83: 0.13 | F83: Q | G83: 0.07
A84: Number of other rooms (excluding bathrooms)
A85: 1 | B85: 8.41 | C85: 1.43 | D85: 0.31 | E85: 1.55 | F85: 4.84 | G85: 0.28
A86: 2 | B86: 27.88 | C86: 9.65 | D86: 2.13 | E86: 3.9 | F86: 10.07 | G86: 2.13
A87: 3 | B87: 32.82 | C87: 19.91 | D87: 2.39 | E87: 2.55 | F87: 5.6 | G87: 2.36
A88: 4 | B88: 26.77 | C88: 21.33 | D88: 1.5 | E88: 0.82 | F88: 1.86 | G88: 1.26
A89: 5 or more | B89: 27.64 | C89: 24.75 | D89: 1.11 | E89: 0.51 | F89: 0.47 | G89: 0.79
A90: Number of full bathrooms
A91: 0 | B91: 0.15 | C91: 0.07 | D91: Q | E91: Q | F91: Q | G91: Q
A92: 1 | B92: 50.32 | C92: 21.7 | D92: 3.03 | E92: 7.24 | F92: 16.26 | G92: 2.1
A93: 2 | B93: 56.85 | C93: 40.42 | D93: 3.7 | E93: 1.86 | F93: 6.36 | G93: 4.51
A94: 3 or more | B94: 16.21 | C94: 14.89 | D94: 0.72 | E94: 0.23 | F94: 0.15 | G94: 0.22
A95: Number of half bathrooms
A96: 0 | B96: 86.83 | C96: 47.8 | D96: 4.06 | E96: 8.21 | F96: 20.77 | G96: 5.98
A97: 1 | B97: 33.79 | C97: 26.87 | D97: 3.21 | E97: 1.03 | F97: 1.94 | G97: 0.75
A98: 2 or more | B98: 2.91 | C98: 2.39 | D98: 0.18 | E98: 0.11 | F98: 0.13 | G98: 0.1
A99: Basement
A100: Yes | B100: 36.83 | C100: 33.86 | D100: 2.98 | E100: N | F100: N | G100: N
A101: Finished basement | B101: 21.71 | C101: 19.85 | D101: 1.87 | E101: N | F101: N | G101: N
A102: Unfinished basement | B102: 15.12 | C102: 14.01 | D102: 1.11 | E102: N | F102: N | G102: N
...

Sheet Calcs>

Sheet Calculations
A1: Table 21 | B1: AEO CODES
C2: Net Generation (billion kilowatthours)
C3: BDEQ-BEOfDS-urban-residential
C4: MW*hour | D4: 2023 | E4: 2024 | F4: 2025 | G4: 2026 | H4: 2027 | I4: 2028 | J4: 2029 | K4: 2030 | L4: 2031 | M4: 2032 | N4: 2033 | O4: 2034 | P4: 2035 | Q4: 2036 | R4: 2037 | S4: 2038 | T4: 2039 | U4: 2040 | V4: 2041 | W4: 2042 | X4: 2043 | Y4: 2044 | Z4: 2045 | AA4: 2046 | AB4: 2047 | AC4: 2048 | AD4: 2049 | AE4: 2050
C5: hard coal | D5: 0 | E5: 0 | F5: 0 | G5: 0 | H5: 0 | I5: 0 | J5: 0 | K5: 0 | L5: 0 | M5: 0 | N5: 0 | O5: 0 | P5: 0 | Q5: 0 | R5: 0 | S5: 0 | T5: 0 | U5: 0 | V5: 0 | W5: 0 | X5: 0 | Y5: 0 | Z5: 0 | AA5: 0 | AB5: 0 | AC5: 0 | AD5: 0 | AE5: 0
A6: Residential: Combined Heat and Power: Net Generation: Fuel Cells: Alternative Electricity and Transportation | B6: Residential: Combined Heat and Power: Net Generation: Fuel Cells: High Zero-Carbon Technology Cost | C6: natural gas nonpeaker | D6: 0 | E6: =INDEX(AEO25_Table_21._Residential!$F$82:$AG$93,MATCH($B6,AEO25_Table_21._Residential!$B$82:$B$93,0),MATCH(E$4,AEO25_Table_21._Residential!$F$5:$AG$5,0))*About!$A$27*About!$B$30 -> 5555.7882 | F6: =INDEX(AEO26_Table_21._Residential!$E$6:$AD$92,MATCH($A6,AEO26_Table_21._Residential!$B$6:$B$92,0),MATCH(F$4,AEO26_Table_21._Residential!$E$5:$AD$5,0))*About!$A$27*About!$B$30 -> 1627.7898 | G6: =INDEX(AEO26_Table_21._Residential!$E$6:$AD$92,MATCH($A6,AEO26_Table_21._Residential!$B$6:$B$92,0),MATCH(G$4,AEO26_Table_21._Residential!$E$5:$AD$5,0))*About!$A$27*About!$B$30 -> 3557.2331 | H6: =INDEX(AEO26_Table_21._Residential!$E$6:$AD$92,MATCH($A6,AEO26_Table_21._Residential!$B$6:$B$92,0),MATCH(H$4,AEO26_Table_21._Residential!$E$5:$AD$5,0))*About!$A$27*About!$B$30 -> 5437.8914 | I6: =INDEX(AEO26_Table_21._Residential!$E$6:$AD$92,MATCH($A6,AEO26_Table_21._Residential!$B$6:$B$92,0),MATCH(I$4,AEO26_Table_21._Residential!$E$5:$AD$5,0))*About!$A$27*About!$B$30 -> 5479.3585 | J6: =INDEX(AEO26_Table_21._Residential!$E$6:$AD$92,MATCH($A6,AEO26_Table_21._Residential!$B$6:$B$92,0),MATCH(J$4,AEO26_Table_21._Residential!$E$5:$AD$5,0))*About!$A$27*About!$B$30 -> 5521.6388 | K6: =INDEX(AEO26_Table_21._Residential!$E$6:$AD$92,MATCH($A6,AEO26_Table_21._Residential!$B$6:$B$92,0),MATCH(K$4,AEO26_Table_21._Residential!$E$5:$AD$5,0))*About!$A$27*About!$B$30 -> 8143.0147 | L6: =INDEX(AEO26_Table_21._Residential!$E$6:$AD$92,MATCH($A6,AEO26_Table_21._Residential!$B$6:$B$92,0),MATCH(L$4,AEO26_Table_21._Residential!$E$5:$AD$5,0))*About!$A$27*About!$B$30 -> 11642.519 | M6: =INDEX(AEO26_Table_21._Residential!$E$6:$AD$92,MATCH($A6,AEO26_Table_21._Residential!$B$6:$B$92,0),MATCH(M$4,AEO26_Table_21._Residential!$E$5:$AD$5,0))*About!$A$27*About!$B$30 -> 15250.976 | ... AE6: =INDEX(AEO26_Table_21._Residential!$E$6:$AD$92,MATCH($A6,AEO26_Table_21._Residential!$B$6:$B$92,0),MATCH(AE$4,AEO26_Table_21._Residential!$E$5:$AD$5,0))*About!$A$27*About!$B$30 -> 24694.109
C7: nuclear | D7: 0 | E7: 0 | F7: 0 | G7: 0 | H7: 0 | I7: 0 | J7: 0 | K7: 0 | L7: 0 | M7: 0 | N7: 0 | O7: 0 | P7: 0 | Q7: 0 | R7: 0 | S7: 0 | T7: 0 | U7: 0 | V7: 0 | W7: 0 | X7: 0 | Y7: 0 | Z7: 0 | AA7: 0 | AB7: 0 | AC7: 0 | AD7: 0 | AE7: 0
C8: hydro | D8: 0 | E8: 0 | F8: 0 | G8: 0 | H8: 0 | I8: 0 | J8: 0 | K8: 0 | L8: 0 | M8: 0 | N8: 0 | O8: 0 | P8: 0 | Q8: 0 | R8: 0 | S8: 0 | T8: 0 | U8: 0 | V8: 0 | W8: 0 | X8: 0 | Y8: 0 | Z8: 0 | AA8: 0 | AB8: 0 | AC8: 0 | AD8: 0 | AE8: 0
A9: Residential: Combined Heat and Power: Net Generation: Wind: Alternative Electricity and Transportation | B9: Residential: Combined Heat and Power: Net Generation: Wind: High Zero-Carbon Technology Cost | C9: onshore wind | D9: =AEO23_Table_21._Residential!$G$84*About!$A$27*About!$B$30 -> 60829.092 | E9: =INDEX(AEO25_Table_21._Residential!$F$82:$AG$93,MATCH($B9,AEO25_Table_21._Residential!$B$82:$B$93,0),MATCH(E$4,AEO25_Table_21._Residential!$F$5:$AG$5,0))*About!$A$27*About!$B$30 -> 300368.69 | F9: =INDEX(AEO26_Table_21._Residential!$E$6:$AD$92,MATCH($A9,AEO26_Table_21._Residential!$B$6:$B$92,0),MATCH(F$4,AEO26_Table_21._Residential!$E$5:$AD$5,0))*About!$A$27*About!$B$30 -> 140072.86 | G9: =INDEX(AEO26_Table_21._Residential!$E$6:$AD$92,MATCH($A9,AEO26_Table_21._Residential!$B$6:$B$92,0),MATCH(G$4,AEO26_Table_21._Residential!$E$5:$AD$5,0))*About!$A$27*About!$B$30 -> 140198.08 | H9: =INDEX(AEO26_Table_21._Residential!$E$6:$AD$92,MATCH($A9,AEO26_Table_21._Residential!$B$6:$B$92,0),MATCH(H$4,AEO26_Table_21._Residential!$E$5:$AD$5,0))*About!$A$27*About!$B$30 -> 140350.94 | I9: =INDEX(AEO26_Table_21._Residential!$E$6:$AD$92,MATCH($A9,AEO26_Table_21._Residential!$B$6:$B$92,0),MATCH(I$4,AEO26_Table_21._Residential!$E$5:$AD$5,0))*About!$A$27*About!$B$30 -> 140502.17 | J9: =INDEX(AEO26_Table_21._Residential!$E$6:$AD$92,MATCH($A9,AEO26_Table_21._Residential!$B$6:$B$92,0),MATCH(J$4,AEO26_Table_21._Residential!$E$5:$AD$5,0))*About!$A$27*About!$B$30 -> 140746.91 | K9: =INDEX(AEO26_Table_21._Residential!$E$6:$AD$92,MATCH($A9,AEO26_Table_21._Residential!$B$6:$B$92,0),MATCH(K$4,AEO26_Table_21._Residential!$E$5:$AD$5,0))*About!$A$27*About!$B$30 -> 141171.33 | L9: =INDEX(AEO26_Table_21._Residential!$E$6:$AD$92,MATCH($A9,AEO26_Table_21._Residential!$B$6:$B$92,0),MATCH(L$4,AEO26_Table_21._Residential!$E$5:$AD$5,0))*About!$A$27*About!$B$30 -> 141941.32 | M9: =INDEX(AEO26_Table_21._Residential!$E$6:$AD$92,MATCH($A9,AEO26_Table_21._Residential!$B$6:$B$92,0),MATCH(M$4,AEO26_Table_21._Residential!$E$5:$AD$5,0))*About!$A$27*About!$B$30 -> 143138.99 | ... AE9: =INDEX(AEO26_Table_21._Residential!$E$6:$AD$92,MATCH($A9,AEO26_Table_21._Residential!$B$6:$B$92,0),MATCH(AE$4,AEO26_Table_21._Residential!$E$5:$AD$5,0))*About!$A$27*About!$B$30 -> 229521.62
A10: Residential: Combined Heat and Power: Net Generation: Solar Photovoltaic: Alternative Electricity and Transportation | B10: Residential: Combined Heat and Power: Net Generation: Solar Photovoltaic: High Zero-Carbon Technology Cost | C10: solar PV | D10: =AEO23_Table_21._Residential!$G$83*About!$A$27*About!$B$30 -> 35064946 | E10: =INDEX(AEO25_Table_21._Residential!$F$82:$AG$93,MATCH($B10,AEO25_Table_21._Residential!$B$82:$B$93,0),MATCH(E$4,AEO25_Table_21._Residential!$F$5:$AG$5,0))*About!$A$27*About!$B$30 -> 50978365 | F10: =INDEX(AEO26_Table_21._Residential!$E$6:$AD$92,MATCH($A10,AEO26_Table_21._Residential!$B$6:$B$92,0),MATCH(F$4,AEO26_Table_21._Residential!$E$5:$AD$5,0))*About!$A$27*About!$B$30 -> 53470950 | G10: =INDEX(AEO26_Table_21._Residential!$E$6:$AD$92,MATCH($A10,AEO26_Table_21._Residential!$B$6:$B$92,0),MATCH(G$4,AEO26_Table_21._Residential!$E$5:$AD$5,0))*About!$A$27*About!$B$30 -> 56521291 | H10: =INDEX(AEO26_Table_21._Residential!$E$6:$AD$92,MATCH($A10,AEO26_Table_21._Residential!$B$6:$B$92,0),MATCH(H$4,AEO26_Table_21._Residential!$E$5:$AD$5,0))*About!$A$27*About!$B$30 -> 59964463 | I10: =INDEX(AEO26_Table_21._Residential!$E$6:$AD$92,MATCH($A10,AEO26_Table_21._Residential!$B$6:$B$92,0),MATCH(I$4,AEO26_Table_21._Residential!$E$5:$AD$5,0))*About!$A$27*About!$B$30 -> 63515989 | J10: =INDEX(AEO26_Table_21._Residential!$E$6:$AD$92,MATCH($A10,AEO26_Table_21._Residential!$B$6:$B$92,0),MATCH(J$4,AEO26_Table_21._Residential!$E$5:$AD$5,0))*About!$A$27*About!$B$30 -> 66825909 | K10: =INDEX(AEO26_Table_21._Residential!$E$6:$AD$92,MATCH($A10,AEO26_Table_21._Residential!$B$6:$B$92,0),MATCH(K$4,AEO26_Table_21._Residential!$E$5:$AD$5,0))*About!$A$27*About!$B$30 -> 70302740 | L10: =INDEX(AEO26_Table_21._Residential!$E$6:$AD$92,MATCH($A10,AEO26_Table_21._Residential!$B$6:$B$92,0),MATCH(L$4,AEO26_Table_21._Residential!$E$5:$AD$5,0))*About!$A$27*About!$B$30 -> 74066153 | M10: =INDEX(AEO26_Table_21._Residential!$E$6:$AD$92,MATCH($A10,AEO26_Table_21._Residential!$B$6:$B$92,0),MATCH(M$4,AEO26_Table_21._Residential!$E$5:$AD$5,0))*About!$A$27*About!$B$30 -> 77813084 | ... AE10: =INDEX(AEO26_Table_21._Residential!$E$6:$AD$92,MATCH($A10,AEO26_Table_21._Residential!$B$6:$B$92,0),MATCH(AE$4,AEO26_Table_21._Residential!$E$5:$AD$5,0))*About!$A$27*About!$B$30 -> 1.8415719e+08
C11: solar thermal | D11: 0 | E11: 0 | F11: 0 | G11: 0 | H11: 0 | I11: 0 | J11: 0 | K11: 0 | L11: 0 | M11: 0 | N11: 0 | O11: 0 | P11: 0 | Q11: 0 | R11: 0 | S11: 0 | T11: 0 | U11: 0 | V11: 0 | W11: 0 | X11: 0 | Y11: 0 | Z11: 0 | AA11: 0 | AB11: 0 | AC11: 0 | AD11: 0 | AE11: 0
C12: biomass | D12: 0 | E12: 0 | F12: 0 | G12: 0 | H12: 0 | I12: 0 | J12: 0 | K12: 0 | L12: 0 | M12: 0 | N12: 0 | O12: 0 | P12: 0 | Q12: 0 | R12: 0 | S12: 0 | T12: 0 | U12: 0 | V12: 0 | W12: 0 | X12: 0 | Y12: 0 | Z12: 0 | AA12: 0 | AB12: 0 | AC12: 0 | AD12: 0 | AE12: 0
C13: geothermal | D13: 0 | E13: 0 | F13: 0 | G13: 0 | H13: 0 | I13: 0 | J13: 0 | K13: 0 | L13: 0 | M13: 0 | N13: 0 | O13: 0 | P13: 0 | Q13: 0 | R13: 0 | S13: 0 | T13: 0 | U13: 0 | V13: 0 | W13: 0 | X13: 0 | Y13: 0 | Z13: 0 | AA13: 0 | AB13: 0 | AC13: 0 | AD13: 0 | AE13: 0
C14: petroleum | D14: 0 | E14: 0 | F14: 0 | G14: 0 | H14: 0 | I14: 0 | J14: 0 | K14: 0 | L14: 0 | M14: 0 | N14: 0 | O14: 0 | P14: 0 | Q14: 0 | R14: 0 | S14: 0 | T14: 0 | U14: 0 | V14: 0 | W14: 0 | X14: 0 | Y14: 0 | Z14: 0 | AA14: 0 | AB14: 0 | AC14: 0 | AD14: 0 | AE14: 0
C15: natural gas peaker | D15: 0 | E15: 0 | F15: 0 | G15: 0 | H15: 0 | I15: 0 | J15: 0 | K15: 0 | L15: 0 | M15: 0 | N15: 0 | O15: 0 | P15: 0 | Q15: 0 | R15: 0 | S15: 0 | T15: 0 | U15: 0 | V15: 0 | W15: 0 | X15: 0 | Y15: 0 | Z15: 0 | AA15: 0 | AB15: 0 | AC15: 0 | AD15: 0 | AE15: 0
C16: lignite | D16: 0 | E16: 0 | F16: 0 | G16: 0 | H16: 0 | I16: 0 | J16: 0 | K16: 0 | L16: 0 | M16: 0 | N16: 0 | O16: 0 | P16: 0 | Q16: 0 | R16: 0 | S16: 0 | T16: 0 | U16: 0 | V16: 0 | W16: 0 | X16: 0 | Y16: 0 | Z16: 0 | AA16: 0 | AB16: 0 | AC16: 0 | AD16: 0 | AE16: 0
C17: offshore wind | D17: 0 | E17: 0 | F17: 0 | G17: 0 | H17: 0 | I17: 0 | J17: 0 | K17: 0 | L17: 0 | M17: 0 | N17: 0 | O17: 0 | P17: 0 | Q17: 0 | R17: 0 | S17: 0 | T17: 0 | U17: 0 | V17: 0 | W17: 0 | X17: 0 | Y17: 0 | Z17: 0 | AA17: 0 | AB17: 0 | AC17: 0 | AD17: 0 | AE17: 0
C18: crude oil | D18: 0 | E18: 0 | F18: 0 | G18: 0 | H18: 0 | I18: 0 | J18: 0 | K18: 0 | L18: 0 | M18: 0 | N18: 0 | O18: 0 | P18: 0 | Q18: 0 | R18: 0 | S18: 0 | T18: 0 | U18: 0 | V18: 0 | W18: 0 | X18: 0 | Y18: 0 | Z18: 0 | AA18: 0 | AB18: 0 | AC18: 0 | AD18: 0 | AE18: 0
C19: heavy or residual fuel oil | D19: 0 | E19: 0 | F19: 0 | G19: 0 | H19: 0 | I19: 0 | J19: 0 | K19: 0 | L19: 0 | M19: 0 | N19: 0 | O19: 0 | P19: 0 | Q19: 0 | R19: 0 | S19: 0 | T19: 0 | U19: 0 | V19: 0 | W19: 0 | X19: 0 | Y19: 0 | Z19: 0 | AA19: 0 | AB19: 0 | AC19: 0 | AD19: 0 | AE19: 0
C20: municipal solid waste | D20: 0 | E20: 0 | F20: 0 | G20: 0 | H20: 0 | I20: 0 | J20: 0 | K20: 0 | L20: 0 | M20: 0 | N20: 0 | O20: 0 | P20: 0 | Q20: 0 | R20: 0 | S20: 0 | T20: 0 | U20: 0 | V20: 0 | W20: 0 | X20: 0 | Y20: 0 | Z20: 0 | AA20: 0 | AB20: 0 | AC20: 0 | AD20: 0 | AE20: 0
C22: BDEQ-BEOfDS-rural-residential
C23: MW*hour | D23: 2023 | E23: 2024 | F23: 2025 | G23: 2026 | H23: 2027 | I23: 2028 | J23: 2029 | K23: 2030 | L23: 2031 | M23: 2032 | N23: 2033 | O23: 2034 | P23: 2035 | Q23: 2036 | R23: 2037 | S23: 2038 | T23: 2039 | U23: 2040 | V23: 2041 | W23: 2042 | X23: 2043 | Y23: 2044 | Z23: 2045 | AA23: 2046 | AB23: 2047 | AC23: 2048 | AD23: 2049 | AE23: 2050
C24: hard coal | D24: 0 | E24: 0 | F24: 0 | G24: 0 | H24: 0 | I24: 0 | J24: 0 | K24: 0 | L24: 0 | M24: 0 | N24: 0 | O24: 0 | P24: 0 | Q24: 0 | R24: 0 | S24: 0 | T24: 0 | U24: 0 | V24: 0 | W24: 0 | X24: 0 | Y24: 0 | Z24: 0 | AA24: 0 | AB24: 0 | AC24: 0 | AD24: 0 | AE24: 0
A25: Residential: Combined Heat and Power: Net Generation: Fuel Cells: Alternative Electricity and Transportation | B25: Residential: Combined Heat and Power: Net Generation: Fuel Cells: High Zero-Carbon Technology Cost | C25: natural gas nonpeaker | D25: 0 | E25: =INDEX(AEO25_Table_21._Residential!$F$82:$AG$93,MATCH($B25,AEO25_Table_21._Residential!$B$82:$B$93,0),MATCH(E$4,AEO25_Table_21._Residential!$F$5:$AG$5,0))*About!$A$28*About!$B$30 -> 1277.2118 | F25: =INDEX(AEO26_Table_21._Residential!$E$6:$AD$92,MATCH($A25,AEO26_Table_21._Residential!$B$6:$B$92,0),MATCH(F$4,AEO26_Table_21._Residential!$E$5:$AD$5,0))*About!$A$28*About!$B$30 -> 374.21015 | G25: =INDEX(AEO26_Table_21._Residential!$E$6:$AD$92,MATCH($A25,AEO26_Table_21._Residential!$B$6:$B$92,0),MATCH(G$4,AEO26_Table_21._Residential!$E$5:$AD$5,0))*About!$A$28*About!$B$30 -> 817.76694 | H25: =INDEX(AEO26_Table_21._Residential!$E$6:$AD$92,MATCH($A25,AEO26_Table_21._Residential!$B$6:$B$92,0),MATCH(H$4,AEO26_Table_21._Residential!$E$5:$AD$5,0))*About!$A$28*About!$B$30 -> 1250.1086 | I25: =INDEX(AEO26_Table_21._Residential!$E$6:$AD$92,MATCH($A25,AEO26_Table_21._Residential!$B$6:$B$92,0),MATCH(I$4,AEO26_Table_21._Residential!$E$5:$AD$5,0))*About!$A$28*About!$B$30 -> 1259.6415 | J25: =INDEX(AEO26_Table_21._Residential!$E$6:$AD$92,MATCH($A25,AEO26_Table_21._Residential!$B$6:$B$92,0),MATCH(J$4,AEO26_Table_21._Residential!$E$5:$AD$5,0))*About!$A$28*About!$B$30 -> 1269.3612 | K25: =INDEX(AEO26_Table_21._Residential!$E$6:$AD$92,MATCH($A25,AEO26_Table_21._Residential!$B$6:$B$92,0),MATCH(K$4,AEO26_Table_21._Residential!$E$5:$AD$5,0))*About!$A$28*About!$B$30 -> 1871.9853 | L25: =INDEX(AEO26_Table_21._Residential!$E$6:$AD$92,MATCH($A25,AEO26_Table_21._Residential!$B$6:$B$92,0),MATCH(L$4,AEO26_Table_21._Residential!$E$5:$AD$5,0))*About!$A$28*About!$B$30 -> 2676.4811 | M25: =INDEX(AEO26_Table_21._Residential!$E$6:$AD$92,MATCH($A25,AEO26_Table_21._Residential!$B$6:$B$92,0),MATCH(M$4,AEO26_Table_21._Residential!$E$5:$AD$5,0))*About!$A$28*About!$B$30 -> 3506.0239 | ... AE25: =INDEX(AEO26_Table_21._Residential!$E$6:$AD$92,MATCH($A25,AEO26_Table_21._Residential!$B$6:$B$92,0),MATCH(AE$4,AEO26_Table_21._Residential!$E$5:$AD$5,0))*About!$A$28*About!$B$30 -> 5676.8914
C26: nuclear | D26: 0 | E26: 0 | F26: 0 | G26: 0 | H26: 0 | I26: 0 | J26: 0 | K26: 0 | L26: 0 | M26: 0 | N26: 0 | O26: 0 | P26: 0 | Q26: 0 | R26: 0 | S26: 0 | T26: 0 | U26: 0 | V26: 0 | W26: 0 | X26: 0 | Y26: 0 | Z26: 0 | AA26: 0 | AB26: 0 | AC26: 0 | AD26: 0 | AE26: 0
C27: hydro | D27: 0 | E27: 0 | F27: 0 | G27: 0 | H27: 0 | I27: 0 | J27: 0 | K27: 0 | L27: 0 | M27: 0 | N27: 0 | O27: 0 | P27: 0 | Q27: 0 | R27: 0 | S27: 0 | T27: 0 | U27: 0 | V27: 0 | W27: 0 | X27: 0 | Y27: 0 | Z27: 0 | AA27: 0 | AB27: 0 | AC27: 0 | AD27: 0 | AE27: 0
A28: Residential: Combined Heat and Power: Net Generation: Wind: Alternative Electricity and Transportation | B28: Residential: Combined Heat and Power: Net Generation: Wind: High Zero-Carbon Technology Cost | C28: onshore wind | D28: =AEO23_Table_21._Residential!$G$84*About!$A$28*About!$B$30 -> 13983.908 | E28: =INDEX(AEO25_Table_21._Residential!$F$82:$AG$93,MATCH($B28,AEO25_Table_21._Residential!$B$82:$B$93,0),MATCH(E$4,AEO25_Table_21._Residential!$F$5:$AG$5,0))*About!$A$28*About!$B$30 -> 69051.306 | F28: =INDEX(AEO26_Table_21._Residential!$E$6:$AD$92,MATCH($A28,AEO26_Table_21._Residential!$B$6:$B$92,0),MATCH(F$4,AEO26_Table_21._Residential!$E$5:$AD$5,0))*About!$A$28*About!$B$30 -> 32201.139 | G28: =INDEX(AEO26_Table_21._Residential!$E$6:$AD$92,MATCH($A28,AEO26_Table_21._Residential!$B$6:$B$92,0),MATCH(G$4,AEO26_Table_21._Residential!$E$5:$AD$5,0))*About!$A$28*About!$B$30 -> 32229.924 | H28: =INDEX(AEO26_Table_21._Residential!$E$6:$AD$92,MATCH($A28,AEO26_Table_21._Residential!$B$6:$B$92,0),MATCH(H$4,AEO26_Table_21._Residential!$E$5:$AD$5,0))*About!$A$28*About!$B$30 -> 32265.065 | I28: =INDEX(AEO26_Table_21._Residential!$E$6:$AD$92,MATCH($A28,AEO26_Table_21._Residential!$B$6:$B$92,0),MATCH(I$4,AEO26_Table_21._Residential!$E$5:$AD$5,0))*About!$A$28*About!$B$30 -> 32299.831 | J28: =INDEX(AEO26_Table_21._Residential!$E$6:$AD$92,MATCH($A28,AEO26_Table_21._Residential!$B$6:$B$92,0),MATCH(J$4,AEO26_Table_21._Residential!$E$5:$AD$5,0))*About!$A$28*About!$B$30 -> 32356.094 | K28: =INDEX(AEO26_Table_21._Residential!$E$6:$AD$92,MATCH($A28,AEO26_Table_21._Residential!$B$6:$B$92,0),MATCH(K$4,AEO26_Table_21._Residential!$E$5:$AD$5,0))*About!$A$28*About!$B$30 -> 32453.665 | L28: =INDEX(AEO26_Table_21._Residential!$E$6:$AD$92,MATCH($A28,AEO26_Table_21._Residential!$B$6:$B$92,0),MATCH(L$4,AEO26_Table_21._Residential!$E$5:$AD$5,0))*About!$A$28*About!$B$30 -> 32630.677 | M28: =INDEX(AEO26_Table_21._Residential!$E$6:$AD$92,MATCH($A28,AEO26_Table_21._Residential!$B$6:$B$92,0),MATCH(M$4,AEO26_Table_21._Residential!$E$5:$AD$5,0))*About!$A$28*About!$B$30 -> 32906.007 | ... AE28: =INDEX(AEO26_Table_21._Residential!$E$6:$AD$92,MATCH($A28,AEO26_Table_21._Residential!$B$6:$B$92,0),MATCH(AE$4,AEO26_Table_21._Residential!$E$5:$AD$5,0))*About!$A$28*About!$B$30 -> 52764.379
A29: Residential: Combined Heat and Power: Net Generation: Solar Photovoltaic: Alternative Electricity and Transportation | B29: Residential: Combined Heat and Power: Net Generation: Solar Photovoltaic: High Zero-Carbon Technology Cost | C29: solar PV | D29: =AEO23_Table_21._Residential!$G$83*About!$A$28*About!$B$30 -> 8061027.4 | E29: =INDEX(AEO25_Table_21._Residential!$F$82:$AG$93,MATCH($B29,AEO25_Table_21._Residential!$B$82:$B$93,0),MATCH(E$4,AEO25_Table_21._Residential!$F$5:$AG$5,0))*About!$A$28*About!$B$30 -> 11719339 | F29: =INDEX(AEO26_Table_21._Residential!$E$6:$AD$92,MATCH($A29,AEO26_Table_21._Residential!$B$6:$B$92,0),MATCH(F$4,AEO26_Table_21._Residential!$E$5:$AD$5,0))*About!$A$28*About!$B$30 -> 12292356 | G29: =INDEX(AEO26_Table_21._Residential!$E$6:$AD$92,MATCH($A29,AEO26_Table_21._Residential!$B$6:$B$92,0),MATCH(G$4,AEO26_Table_21._Residential!$E$5:$AD$5,0))*About!$A$28*About!$B$30 -> 12993594 | H29: =INDEX(AEO26_Table_21._Residential!$E$6:$AD$92,MATCH($A29,AEO26_Table_21._Residential!$B$6:$B$92,0),MATCH(H$4,AEO26_Table_21._Residential!$E$5:$AD$5,0))*About!$A$28*About!$B$30 -> 13785140 | I29: =INDEX(AEO26_Table_21._Residential!$E$6:$AD$92,MATCH($A29,AEO26_Table_21._Residential!$B$6:$B$92,0),MATCH(I$4,AEO26_Table_21._Residential!$E$5:$AD$5,0))*About!$A$28*About!$B$30 -> 14601595 | J29: =INDEX(AEO26_Table_21._Residential!$E$6:$AD$92,MATCH($A29,AEO26_Table_21._Residential!$B$6:$B$92,0),MATCH(J$4,AEO26_Table_21._Residential!$E$5:$AD$5,0))*About!$A$28*About!$B$30 -> 15362507 | K29: =INDEX(AEO26_Table_21._Residential!$E$6:$AD$92,MATCH($A29,AEO26_Table_21._Residential!$B$6:$B$92,0),MATCH(K$4,AEO26_Table_21._Residential!$E$5:$AD$5,0))*About!$A$28*About!$B$30 -> 16161791 | L29: =INDEX(AEO26_Table_21._Residential!$E$6:$AD$92,MATCH($A29,AEO26_Table_21._Residential!$B$6:$B$92,0),MATCH(L$4,AEO26_Table_21._Residential!$E$5:$AD$5,0))*About!$A$28*About!$B$30 -> 17026956 | M29: =INDEX(AEO26_Table_21._Residential!$E$6:$AD$92,MATCH($A29,AEO26_Table_21._Residential!$B$6:$B$92,0),MATCH(M$4,AEO26_Table_21._Residential!$E$5:$AD$5,0))*About!$A$28*About!$B$30 -> 17888332 | ... AE29: =INDEX(AEO26_Table_21._Residential!$E$6:$AD$92,MATCH($A29,AEO26_Table_21._Residential!$B$6:$B$92,0),MATCH(AE$4,AEO26_Table_21._Residential!$E$5:$AD$5,0))*About!$A$28*About!$B$30 -> 42335619
C30: solar thermal | D30: 0 | E30: 0 | F30: 0 | G30: 0 | H30: 0 | I30: 0 | J30: 0 | K30: 0 | L30: 0 | M30: 0 | N30: 0 | O30: 0 | P30: 0 | Q30: 0 | R30: 0 | S30: 0 | T30: 0 | U30: 0 | V30: 0 | W30: 0 | X30: 0 | Y30: 0 | Z30: 0 | AA30: 0 | AB30: 0 | AC30: 0 | AD30: 0 | AE30: 0
C31: biomass | D31: 0 | E31: 0 | F31: 0 | G31: 0 | H31: 0 | I31: 0 | J31: 0 | K31: 0 | L31: 0 | M31: 0 | N31: 0 | O31: 0 | P31: 0 | Q31: 0 | R31: 0 | S31: 0 | T31: 0 | U31: 0 | V31: 0 | W31: 0 | X31: 0 | Y31: 0 | Z31: 0 | AA31: 0 | AB31: 0 | AC31: 0 | AD31: 0 | AE31: 0
C32: geothermal | D32: 0 | E32: 0 | F32: 0 | G32: 0 | H32: 0 | I32: 0 | J32: 0 | K32: 0 | L32: 0 | M32: 0 | N32: 0 | O32: 0 | P32: 0 | Q32: 0 | R32: 0 | S32: 0 | T32: 0 | U32: 0 | V32: 0 | W32: 0 | X32: 0 | Y32: 0 | Z32: 0 | AA32: 0 | AB32: 0 | AC32: 0 | AD32: 0 | AE32: 0
