Workbook
Name dollars_2018_to_2012: About!$A$140
Name dollars_2019_2012: About!$A$139
Name dollars_2020_2012: About!$A$138
Name dollars_2021_2012: About!$A$137
Name dollars_2022_2012: About!$A$136
Name dollars_2023_2012: About!$A$135
Name dollars_2024_to_2012: About!$A$134
Name dollars_2025_to_2012: About!$A$133
Name lignite_multiplier: 'Hard Coal and Lig Multipliers'!$N$15
Name nonlignite_multiplier: 'Hard Coal and Lig Multipliers'!$N$16

Sheet About
A1: BFPaT BAU Pretax Fuel Price by Sector
A2: BFPaT BAU Fuel Tax by Sector
A4: Sources: | B4: most fuels and growth rates | D4: Tax on Petroleum Gasoline, Petroleum Diesel, Jet Fuel
B5: Energy Information Administration | D5: Energy Information Administration
B6: 2026 | D6: 2026
B7: Annual Energy Outlook 2026, "Alternative Electricity and Transportation" scenario | D7: Annual Energy Outlook 2026, "Alternative Electricity and Transportation" scenario
B8: https://www.eia.gov/outlooks/aeo/tables_side.php | D8: https://www.eia.gov/outlooks/aeo/tables_side.php
B9: Table 3 (and Table 2 for industrial coal consumption fractions by coal type) | D9: Table 57
B11: 2025-2027 prices and start year tax | D11: Tax on Non-Liquid Fuels
B12: Energy Information Administration | D12: The Sales Tax Clearinghouse
B13: 2026 | D13: n/a
B14: Short Term Energy Outlook | D14: FAQ
B15: https://www.eia.gov/outlooks/steo/data/browser/#/?v=8 | D15: https://thestc.com/FAQ.stm
B16: Table 2 | D16: Question "What is the average sales tax nationally?"
B17: October release data
D18: green hydrogen
B19: biomass | D19: Department of Energy
B20: Energy Information Administraton | D20: 2024
B21: 2025 | D21: DOE Pathways to Commercial Liftoff: Clean Hydrogen
B22: State Energy Data System (SEDS): 1960-2023 (complete) | D22: https://climateprogramportal.org/wp-content/uploads/2025/02/Pathways-to-Commercial-Liftoff_Clean-Hydrogen_December-2024-Update.pdf
B23: https://www.eia.gov/state/seds/archive/seper2018.pdf | D23: Figure 10
B24: Tables ET3, ET4, ET5, and ET7
B26: biofuel diesel
B27: DOE Alternative Fuels Data Center
B28: 2025
B29: Clean Cities Alternative Fuel Price Report
B30: https://afdc.energy.gov/files/u/publication/alternative_fuel_price_report_july_2025.pdf
B31: Table 2
B33: heat
B34: Euroheat & Power
B35: n/a
B36: DHC & Statistics: United States
B37: http://www.euroheat.org/United-States-156.aspx
B38: "Average District Heating price in 2011" (using "Steam" rather than "Water" because most U.S. district heating systems use steam)
B40: Gas future prices
B41: CME Group
B42: 2026
B43: Henry Hub Natural Gas Futures - Quotes
B44: https://www.cmegroup.com/trading/energy/natural-gas/natural-gas_quotes_globex.html
B46: ICF
B47: 2026
B48: U.S. natural gas outlook through 2030: Growing demand, infrastructure challenges, and price volatility
B49: https://www.icf.com/insights/energy/future-forecast-price-of-natural-gas#q3forecast
B51: Historical Henry Hub Prices, Retail Prices, and Consumption by Sector
B52: EIA
B53: 2026
B54: Natural Gas: Data
B55: https://www.eia.gov/naturalgas/data.php; https://www.eia.gov/dnav/ng/ng_pri_sum_dcu_nus_a.htm
B56: Prices; Natural gas spot and futures prices; and Delivered to Consumers links
B58: lignite and non-lignite price multipliers
B59: Energy Information Administration
B60: 2019
B61: Form EIA-923 detailed data
B62: https://www.eia.gov/electricity/data/eia923/
B63: Year 2018, Tab 5
A65: Notes
A67: Years Covered
A68: This variable should include data only for modeled years, not including the model's Initial Time.
A69: For the U.S., this means including the years 2025-2100.
A70: 2025
A72: Pre-Tax Prices
A73: This variable contains PRE-TAX fuel prices per unit energy, disaggregated by sector.
A75: BAU Fuel Taxes
A76: Separately, it also specifies the amount of BAU fuel tax per unit energy that is levied on each fuel.
A77: BAU fuel taxes include sales taxes, value-added taxes (VAT), and excise taxes, not carbon taxes.
A78: If there is a BAU Carbon Tax in the modeled region, its effect on fuel prices must not be included here.
A79: (A BAU carbon tax is specified separately in fuels/BCTR BAU Carbon Tax Rate.)
A81: BAU Fuel Subsidies
A82: All pre-tax fuel prices in this variable should incorporate the contribution of any BAU subsidies.
A83: This is because BAU subsidies are often applied far upstream of retail sales, such as subsidies for oil
A84: and gas drilling companies. Similarly, subsidies paid for electricity generation
A85: (such as a subsidy per MWh of electricity generated from wind)
... A132: We adjust dollars of the following years to 2012 dollars using the following conversion factors:
A133: 0.713109 | B133: 2025 to 2012
A134: 0.73191601 | B134: 2024 to 2012
A135: 0.75350342 | B135: 2023 to 2012; used for EIA AEO 2026 Hydrogen Market Module
A136: 0.785 | B136: 2022 to 2012; used for DOE Pathways to Commercial Liftoff
A137: 0.84730413 | B137: 2021 to 2012
A138: 0.88711067 | B138: 2020 to 2012
A139: 0.89805482 | B139: 2019 to 2012
A140: 0.914 | B140: 2018 to 2012; used for EIA AEO 2018, DOE Clean Cities report, and the NETL hydrogen premium
A141: 0.96868157 | B141: 2015 to 2012; used for CEC/CARB hydrogen report
A142: 1.022 | B142: 2011 to 2012; used for Euroheat and Power statistics
A143: See "cpi.xlsx" in the InputData folder for source information.
A146: Crude Oil Heat Content
A147: 5.719 | B147: million BTU / barrel (U.S.-produced crude)
A148: 6.063 | B148: million BTU / barrel (imported crude)
A149: Source: EIA AEO 2019, Appendix G, Conversion Factors
A151: For the United States EPS, we use West Texas Intermediate as our crude benchmark, as this is typical in the U.S.
A152: When adapting the EPS to other countries, using Brent crude (also available in AEO table 12) is advised, and
A153: the heat content used should be switched to the value for "imported" crude above.
A155: Municipal Solid Waste Prices
A156: Rather than costing money, companies usually pay a "tipping fee" to the processor for accepting their
A157: municipal solid waste. This would imply a negative fuel price. However, there may be extra expenses
A158: associated with sorting the waste so that only suitable MSW is combusted, while other items (such as
A159: electronics and batteries, which should not have been part of the MSW stream) don't get combusted.
A160: For simplicity, we assume that the added processing costs of dealing with MSW offset the tipping fees,
A161: resulting in a fuel cost of zero. (This assumes MSW power plants get all their profit from selling power,
A162: and they break even on the tipping fees.)
... A184: Other Conversions
...

Sheet Gas Futures
A1: Month | B1: Options | C1: Chart | D1: Last | E1: Change | F1: Prior | G1: Open | H1: High | I1: Low | J1: Volume | K1: Updated | L1: Month.year
B2: Opt | D2: 4.036 | E2: -0.077 (-1.87%) | F2: - | G2: 4.171 | H2: 4.218 | I2: 3.993 | J2: 154446 | K2: 15:59:59 CT
A3: 46296 | B3: Opt | D3: 3.298 | E3: - | F3: 3.023 | G3: 3.037 | H3: 3.317 | I3: 2.979 | J3: 104473 | K3: 14:32 CT | L3: =CONCATENATE(MONTH(A3),".",YEAR(A3)) -> 10.2026
A4: NGV26 | K4: 46289.534
A5: 46327 | B5: Opt | D5: 3.382 | E5: - | F5: 3.153 | G5: 3.169 | H5: 3.395 | I5: 3.124 | J5: 369118 | K5: 14:32 CT | L5: =CONCATENATE(MONTH(A5),".",YEAR(A5)) -> 11.2026
A6: NGX26 | K6: 46289.534
A7: 46357 | B7: Opt | D7: 3.7 | E7: - | F7: 3.493 | G7: 3.504 | H7: 3.704 | I7: 3.486 | J7: 138989 | K7: 14:32 CT | L7: =CONCATENATE(MONTH(A7),".",YEAR(A7)) -> 12.2026
A8: NGZ26 | K8: 46289.534
A9: 46388 | B9: Opt | D9: 4.061 | E9: - | F9: 3.86 | G9: 3.877 | H9: 4.066 | I9: 3.865 | J9: 82351 | K9: 14:32 CT | L9: =CONCATENATE(MONTH(A9),".",YEAR(A9)) -> 1.2027
A10: NGF27 | K10: 46289.534
A11: 46419 | B11: Opt | D11: 3.702 | E11: - | F11: 3.528 | G11: 3.542 | H11: 3.707 | I11: 3.532 | J11: 49503 | K11: 14:32 CT | L11: =CONCATENATE(MONTH(A11),".",YEAR(A11)) -> 2.2027
A12: NGG27 | K12: 46289.534
A13: 46447 | B13: Opt | D13: 2.919 | E13: - | F13: 2.851 | G13: 2.857 | H13: 2.929 | I13: 2.841 | J13: 75569 | K13: 14:32 CT | L13: =CONCATENATE(MONTH(A13),".",YEAR(A13)) -> 3.2027
A14: NGH27 | K14: 46289.534
A15: 46478 | B15: Opt | D15: 2.782 | E15: - | F15: 2.731 | G15: 2.734 | H15: 2.791 | I15: 2.729 | J15: 48722 | K15: 14:32 CT | L15: =CONCATENATE(MONTH(A15),".",YEAR(A15)) -> 4.2027
A16: NGJ27 | K16: 46289.534
A17: 46508 | B17: Opt | D17: 2.799 | E17: - | F17: 2.756 | G17: 2.765 | H17: 2.81 | I17: 2.755 | J17: 26296 | K17: 14:32 CT | L17: =CONCATENATE(MONTH(A17),".",YEAR(A17)) -> 5.2027
A18: NGK27 | K18: 46289.534
A19: 46539 | B19: Opt | D19: 2.949 | E19: - | F19: 2.913 | G19: 2.922 | H19: 2.959 | I19: 2.913 | J19: 12975 | K19: 14:32 CT | L19: =CONCATENATE(MONTH(A19),".",YEAR(A19)) -> 6.2027
A20: NGM27 | K20: 46289.534
A21: 46569 | B21: Opt | D21: 3.168 | E21: - | F21: 3.138 | G21: 3.149 | H21: 3.181 | I21: 3.14 | J21: 13735 | K21: 14:32 CT | L21: =CONCATENATE(MONTH(A21),".",YEAR(A21)) -> 7.2027
A22: NGN27 | K22: 46289.534
A23: 46600 | B23: Opt | D23: 3.241 | E23: - | F23: 3.212 | G23: 3.223 | H23: 3.252 | I23: 3.216 | J23: 7099 | K23: 14:32 CT | L23: =CONCATENATE(MONTH(A23),".",YEAR(A23)) -> 8.2027
A24: NGQ27 | K24: 46289.534
A25: 46631 | B25: Opt | D25: 3.223 | E25: - | F25: 3.197 | G25: 3.209 | H25: 3.238 | I25: 3.2 | J25: 8204 | K25: 14:32 CT | L25: =CONCATENATE(MONTH(A25),".",YEAR(A25)) -> 9.2027
A26: NGU27 | K26: 46289.534
A27: 46661 | B27: Opt | D27: 3.308 | E27: - | F27: 3.284 | G27: 3.29 | H27: 3.324 | I27: 3.287 | J27: 14448 | K27: 14:32 CT | L27: =CONCATENATE(MONTH(A27),".",YEAR(A27)) -> 10.2027
A28: NGV27 | K28: 46289.534
A29: 46692 | B29: Opt | D29: 3.585 | E29: - | F29: 3.568 | G29: 3.576 | H29: 3.601 | I29: 3.571 | J29: 3284 | K29: 14:32 CT | L29: =CONCATENATE(MONTH(A29),".",YEAR(A29)) -> 11.2027
A30: NGX27 | K30: 46289.534
A31: 46722 | B31: Opt | D31: 4.193 | E31: - | F31: 4.18 | G31: 4.188 | H31: 4.204 | I31: 4.181 | J31: 2295 | K31: 14:32 CT | L31: =CONCATENATE(MONTH(A31),".",YEAR(A31)) -> 12.2027
A32: NGZ27 | K32: 46289.534
A33: 46753 | B33: Opt | D33: 4.622 | E33: - | F33: 4.609 | G33: 4.613 | H33: 4.632 | I33: 4.608 | J33: 3983 | K33: 14:32 CT | L33: =CONCATENATE(MONTH(A33),".",YEAR(A33)) -> 1.2028
A34: NGF28 | K34: 46289.534
A35: 46784 | B35: Opt | D35: 4.22 | E35: - | F35: 4.207 | G35: 4.212 | H35: 4.226 | I35: 4.208 | J35: 1952 | K35: 14:32 CT | L35: =CONCATENATE(MONTH(A35),".",YEAR(A35)) -> 2.2028
A36: NGG28 | K36: 46289.534
A37: 46813 | B37: Opt | D37: 3.492 | E37: - | F37: 3.477 | G37: 3.486 | H37: 3.498 | I37: 3.482 | J37: 2601 | K37: 14:32 CT | L37: =CONCATENATE(MONTH(A37),".",YEAR(A37)) -> 3.2028
A38: NGH28 | K38: 46289.534
A39: 46844 | B39: Opt | D39: 3.253 | E39: - | F39: 3.246 | G39: 3.255 | H39: 3.261 | I39: 3.243 | J39: 2043 | K39: 14:32 CT | L39: =CONCATENATE(MONTH(A39),".",YEAR(A39)) -> 4.2028
A40: NGJ28 | K40: 46289.534
A41: 46874 | B41: Opt | D41: 3.247 | E41: - | F41: 3.243 | G41: 3.252 | H41: 3.258 | I41: 3.239 | J41: 461 | K41: 14:32 CT | L41: =CONCATENATE(MONTH(A41),".",YEAR(A41)) -> 5.2028
A42: NGK28 | K42: 46289.534
A43: 46905 | B43: Opt | D43: 3.4 | E43: - | F43: 3.403 | G43: 3.412 | H43: 3.418 | I43: 3.396 | J43: 480 | K43: 14:32 CT | L43: =CONCATENATE(MONTH(A43),".",YEAR(A43)) -> 6.2028
A44: NGM28 | K44: 46289.534
A45: 46935 | B45: Opt | D45: 3.602 | E45: - | F45: 3.612 | G45: 3.622 | H45: 3.625 | I45: 3.602 | J45: 476 | K45: 14:32 CT | L45: =CONCATENATE(MONTH(A45),".",YEAR(A45)) -> 7.2028
A46: NGN28 | K46: 46289.534
A47: 46966 | B47: Opt | D47: 3.66 | E47: - | F47: 3.672 | G47: 3.68 | H47: 3.683 | I47: 3.66 | J47: 447 | K47: 14:32 CT | L47: =CONCATENATE(MONTH(A47),".",YEAR(A47)) -> 8.2028
A48: NGQ28 | K48: 46289.534
A49: 46997 | B49: Opt | D49: 3.626 | E49: - | F49: 3.641 | G49: 3.638 | H49: 3.642 | I49: 3.626 | J49: 331 | K49: 14:32 CT | L49: =CONCATENATE(MONTH(A49),".",YEAR(A49)) -> 9.2028
A50: NGU28 | K50: 46289.534
A51: 47027 | B51: Opt | D51: 3.679 | E51: - | F51: 3.696 | G51: 3.704 | H51: 3.705 | I51: 3.677 | J51: 720 | K51: 14:32 CT | L51: =CONCATENATE(MONTH(A51),".",YEAR(A51)) -> 10.2028
A52: NGV28 | K52: 46289.534
A53: 47058 | B53: Opt | D53: 3.855 | E53: - | F53: 3.871 | G53: 3.875 | H53: 3.879 | I53: 3.855 | J53: 400 | K53: 14:32 CT | L53: =CONCATENATE(MONTH(A53),".",YEAR(A53)) -> 11.2028
A54: NGX28 | K54: 46289.534
A55: 47088 | B55: Opt | D55: 4.388 | E55: - | F55: 4.41 | G55: 4.409 | H55: 4.409 | I55: 4.383 | J55: 319 | K55: 14:32 CT | L55: =CONCATENATE(MONTH(A55),".",YEAR(A55)) -> 12.2028
A56: NGZ28 | K56: 46289.534
A57: 47119 | B57: Opt | D57: 4.83 | E57: - | F57: 4.841 | G57: 4.838 | H57: 4.838 | I57: 4.83 | J57: 250 | K57: 14:32 CT | L57: =CONCATENATE(MONTH(A57),".",YEAR(A57)) -> 1.2029
A58: NGF29 | K58: 46289.534
A59: 47150 | B59: Opt | D59: 4.38 | E59: - | F59: 4.38 | G59: 4.38 | H59: 4.38 | I59: 4.38 | J59: 15 | K59: 14:32 CT | L59: =CONCATENATE(MONTH(A59),".",YEAR(A59)) -> 2.2029
A60: NGG29 | K60: 46289.534
A61: 47178 | B61: Opt | D61: 3.45 | E61: - | F61: 3.457 | G61: 3.45 | H61: 3.45 | I61: 3.45 | J61: 9 | K61: 14:32 CT | L61: =CONCATENATE(MONTH(A61),".",YEAR(A61)) -> 3.2029
A62: NGH29 | K62: 46289.534
A63: 47209 | B63: Opt | D63: 3.178 | E63: - | F63: 3.178 | G63: 3.178 | H63: 3.178 | I63: 3.178 | J63: 2 | K63: 14:32 CT | L63: =CONCATENATE(MONTH(A63),".",YEAR(A63)) -> 4.2029
A64: NGJ29 | K64: 46289.534
A65: 47239 | B65: Opt | D65: 3.16 | E65: - | F65: 3.16 | G65: 3.16 | H65: 3.16 | I65: 3.16 | J65: 15 | K65: 14:32 CT | L65: =CONCATENATE(MONTH(A65),".",YEAR(A65)) -> 5.2029
A66: NGK29 | K66: 46289.534
A67: 47270 | B67: Opt | D67: 3.285 | E67: - | F67: 3.287 | G67: 3.285 | H67: 3.285 | I67: 3.285 | J67: 18 | K67: 14:32 CT | L67: =CONCATENATE(MONTH(A67),".",YEAR(A67)) -> 6.2029
A68: NGM29 | K68: 46289.534
A69: 47300 | B69: Opt | D69: 3.492 | E69: - | F69: 3.492 | G69: 3.492 | H69: 3.492 | I69: 3.492 | J69: 2 | K69: 14:32 CT | L69: =CONCATENATE(MONTH(A69),".",YEAR(A69)) -> 7.2029
A70: NGN29 | K70: 46289.534
A71: 47331 | B71: Opt | D71: - | E71: - | F71: 3.553 | G71: - | H71: - | I71: - | J71: 18 | K71: 14:32 CT | L71: =CONCATENATE(MONTH(A71),".",YEAR(A71)) -> 8.2029
A72: NGQ29 | K72: 46289.534
A73: 47362 | B73: Opt | D73: - | E73: - | F73: 3.533 | G73: - | H73: - | I73: - | J73: 63 | K73: 14:32 CT | L73: =CONCATENATE(MONTH(A73),".",YEAR(A73)) -> 9.2029
A74: NGU29 | K74: 46289.534
A75: 47392 | B75: Opt | D75: 3.59 | E75: - | F75: 3.589 | G75: 3.59 | H75: 3.59 | I75: 3.59 | J75: 56 | K75: 14:32 CT | L75: =CONCATENATE(MONTH(A75),".",YEAR(A75)) -> 10.2029
A76: NGV29 | K76: 46289.534
A77: 47423 | B77: Opt | D77: 3.722 | E77: - | F77: 3.726 | G77: 3.722 | H77: 3.722 | I77: 3.722 | J77: 8 | K77: 14:32 CT | L77: =CONCATENATE(MONTH(A77),".",YEAR(A77)) -> 11.2029
A78: NGX29 | K78: 46289.534
A79: 47453 | B79: Opt | D79: - | E79: - | F79: 4.281 | G79: - | H79: - | I79: - | J79: 1 | K79: 14:32 CT | L79: =CONCATENATE(MONTH(A79),".",YEAR(A79)) -> 12.2029
A80: NGZ29 | K80: 46289.534
A81: 47484 | B81: Opt | D81: - | E81: - | F81: 4.744 | G81: - | H81: - | I81: - | J81: 2 | K81: 14:32 CT | L81: =CONCATENATE(MONTH(A81),".",YEAR(A81)) -> 1.2030
A82: NGF30 | K82: 46289.534
A83: 47515 | B83: Opt | D83: 4.342 | E83: - | F83: 4.336 | G83: 4.342 | H83: 4.342 | I83: 4.342 | J83: 4 | K83: 14:32 CT | L83: =CONCATENATE(MONTH(A83),".",YEAR(A83)) -> 2.2030
A84: NGG30 | K84: 46289.534
A85: 47543 | B85: Opt | D85: - | E85: - | F85: 3.485 | G85: - | H85: - | I85: - | J85: 0 | K85: 14:32 CT | L85: =CONCATENATE(MONTH(A85),".",YEAR(A85)) -> 3.2030
A86: NGH30 | K86: 46289.534
A87: 47574 | B87: Opt | D87: - | E87: - | F87: 3.143 | G87: - | H87: - | I87: - | J87: 0 | K87: 14:32 CT | L87: =CONCATENATE(MONTH(A87),".",YEAR(A87)) -> 4.2030
A88: NGJ30 | K88: 46289.534
A89: 47604 | B89: Opt | D89: - | E89: - | F89: 3.106 | G89: - | H89: - | I89: - | J89: 0 | K89: 14:32 CT | L89: =CONCATENATE(MONTH(A89),".",YEAR(A89)) -> 5.2030
A90: NGK30 | K90: 46289.534
A91: 47635 | B91: Opt | D91: - | E91: - | F91: 3.222 | G91: - | H91: - | I91: - | J91: 0 | K91: 14:32 CT | L91: =CONCATENATE(MONTH(A91),".",YEAR(A91)) -> 6.2030
A92: NGM30 | K92: 46289.534
A93: 47665 | B93: Opt | D93: 3.46 | E93: - | F93: 3.459 | G93: 3.46 | H93: 3.46 | I93: 3.46 | J93: 1 | K93: 14:32 CT | L93: =CONCATENATE(MONTH(A93),".",YEAR(A93)) -> 7.2030
A94: NGN30 | K94: 46289.534
A95: 47696 | B95: Opt | D95: - | E95: - | F95: 3.498 | G95: - | H95: - | I95: - | J95: 0 | K95: 14:32 CT | L95: =CONCATENATE(MONTH(A95),".",YEAR(A95)) -> 8.2030
A96: NGQ30 | K96: 46289.534
A97: 47727 | B97: Opt | D97: - | E97: - | F97: 3.466 | G97: - | H97: - | I97: - | J97: 0 | K97: 14:32 CT | L97: =CONCATENATE(MONTH(A97),".",YEAR(A97)) -> 9.2030
A98: NGU30 | K98: 46289.534
A99: 47757 | B99: Opt | D99: - | E99: - | F99: 3.53 | G99: - | H99: - | I99: - | J99: 0 | K99: 14:32 CT | L99: =CONCATENATE(MONTH(A99),".",YEAR(A99)) -> 10.2030
A100: NGV30 | K100: 46289.534
...

Sheet Henry Hub Historicals
A1: Back to Contents | B1: Data 1: Spot Price
A2: Sourcekey | B2: RNGWHHD
A3: 35445 | B3: 3.45 | C3: Month.year
A4: 35476 | B4: 2.15 | C4: =CONCATENATE(MONTH(A4),".",YEAR(A4)) -> 2.1997
A5: 35504 | B5: 1.89 | C5: =CONCATENATE(MONTH(A5),".",YEAR(A5)) -> 3.1997
A6: 35535 | B6: 2.03 | C6: =CONCATENATE(MONTH(A6),".",YEAR(A6)) -> 4.1997
A7: 35565 | B7: 2.25 | C7: =CONCATENATE(MONTH(A7),".",YEAR(A7)) -> 5.1997
A8: 35596 | B8: 2.2 | C8: =CONCATENATE(MONTH(A8),".",YEAR(A8)) -> 6.1997
A9: 35626 | B9: 2.19 | C9: =CONCATENATE(MONTH(A9),".",YEAR(A9)) -> 7.1997
A10: 35657 | B10: 2.49 | C10: =CONCATENATE(MONTH(A10),".",YEAR(A10)) -> 8.1997
A11: 35688 | B11: 2.88 | C11: =CONCATENATE(MONTH(A11),".",YEAR(A11)) -> 9.1997
A12: 35718 | B12: 3.07 | C12: =CONCATENATE(MONTH(A12),".",YEAR(A12)) -> 10.1997
A13: 35749 | B13: 3.01 | C13: =CONCATENATE(MONTH(A13),".",YEAR(A13)) -> 11.1997
A14: 35779 | B14: 2.35 | C14: =CONCATENATE(MONTH(A14),".",YEAR(A14)) -> 12.1997
A15: 35810 | B15: 2.09 | C15: =CONCATENATE(MONTH(A15),".",YEAR(A15)) -> 1.1998
... A358: 46249.534 | B358: 2.78 | C358: =CONCATENATE(MONTH(A358),".",YEAR(A358)) -> 8.2026
A360: Back to Contents | B360: Data 1: Spot Price
A361: Sourcekey | B361: RNGWHHD
A362: Date | B362: Henry Hub Natural Gas Spot Price (Dollars per Million Btu)
A363: 35611 | B363: 2.49 | C363: 1997
A364: 35976 | B364: 2.09 | C364: 1998
A365: 36341 | B365: 2.27 | C365: 1999
A366: 36707 | B366: 4.31 | C366: 2000
A367: 37072 | B367: 3.96 | C367: 2001
A368: 37437 | B368: 3.38 | C368: 2002
A369: 37802 | B369: 5.47 | C369: 2003
A370: 38168 | B370: 5.89 | C370: 2004
A371: 38533 | B371: 8.69 | C371: 2005
A372: 38898 | B372: 6.73 | C372: 2006
A373: 39263 | B373: 6.97 | C373: 2007
A374: 39629 | B374: 8.86 | C374: 2008
... A391: 45838 | B391: 3.52 | C391: 2025

Sheet NG Sector Price Historicals
A1: Back to Contents | B1: Data 1: U.S. Natural Gas Prices
A2: Sourcekey | B2: N9190US3 | C2: N9100US3 | D2: N9102US3 | E2: N9103US3 | F2: N9130US3 | G2: N9132US3 | H2: N9133US3 | I2: NA1480_NUS_3 | J2: N3050US3 | K2: N3010US3 | L2: NA1504_NUS_4 | M2: N3020US3 | N2: N3020US4 | O2: N3035US3 | P2: N3035US4 | Q2: NA1570_NUS_3 | R2: N3045US3
A3: Date | B3: U.S. Natural Gas Wellhead Price (Dollars per Thousand Cubic Feet) | C3: Price of U.S. Natural Gas Imports (Dollars per Thousand Cubic Feet) | D3: U.S. Natural Gas Pipeline Imports Price (Dollars per Thousand Cubic Feet) | E3: Price of U.S. Natural Gas LNG Imports (Dollars per Thousand Cubic Feet) | F3: Price of U.S. Natural Gas Exports (Dollars per Thousand Cubic Feet) | G3: Price of U.S. Natural Gas Pipeline Exports (Dollars per Thousand Cubic Feet) | H3: Price of Liquefied U.S. Natural Gas Exports (Dollars per Thousand Cubic Feet) | I3: U.S. Natural Gas Pipeline and Distribution Use Price (Dollars per Thousand Cubic Feet) | J3: U.S. Natural Gas Citygate Price (Dollars per Thousand Cubic Feet) | K3: U.S. Price of Natural Gas Delivered to Residential Consumers (Dollars per Thousand Cubic Feet) | L3: U.S. Natural Gas % of Total Residential - Sales (%) | M3: U.S. Price of Natural Gas Sold to Commercial Consumers (Dollars per Thousand Cubic Feet) | N3: Percent of Commercial Natural Gas Deliveries in U.S. Total Represented by the Price (%) | O3: United States Natural Gas Industrial Price (Dollars per Thousand Cubic Feet) | P3: Percent of Industrial Natural Gas Deliveries in U.S. Total Represented by the Price (%) | Q3: U.S. Natural Gas Vehicle Fuel Price (Dollars per Thousand Cubic Feet) | R3: U.S. Natural Gas Electric Power Price (Dollars per Thousand Cubic Feet) | S3: Year
A4: 8217 | B4: 0.11 | S4: =YEAR(A4) -> 1922
A5: 8582 | B5: 0.1 | S5: =YEAR(A5) -> 1923
A6: 8948 | B6: 0.09 | S6: =YEAR(A6) -> 1924
A7: 9313 | B7: 0.09 | S7: =YEAR(A7) -> 1925
A8: 9678 | B8: 0.1 | S8: =YEAR(A8) -> 1926
A9: 10043 | B9: 0.09 | S9: =YEAR(A9) -> 1927
A10: 10409 | B10: 0.09 | S10: =YEAR(A10) -> 1928
A11: 10774 | B11: 0.08 | S11: =YEAR(A11) -> 1929
A12: 11139 | B12: 0.08 | S12: =YEAR(A12) -> 1930
A13: 11504 | B13: 0.07 | S13: =YEAR(A13) -> 1931
A14: 11870 | B14: 0.06 | S14: =YEAR(A14) -> 1932
A15: 12235 | B15: 0.06 | S15: =YEAR(A15) -> 1933
... A48: 24288 | B48: 0.16 | S48: =YEAR(A48) -> 1966
A49: 24653 | B49: 0.16 | I49: 0.2 | K49: 1.04 | M49: 0.74 | S49: =YEAR(A49) -> 1967
A50: 25019 | B50: 0.16 | I50: 0.2 | K50: 1.04 | M50: 0.73 | S50: =YEAR(A50) -> 1968
A51: 25384 | B51: 0.17 | I51: 0.21 | K51: 1.05 | M51: 0.74 | S51: =YEAR(A51) -> 1969
A52: 25749 | B52: 0.17 | I52: 0.21 | K52: 1.09 | M52: 0.77 | S52: =YEAR(A52) -> 1970
A53: 26114 | B53: 0.18 | I53: 0.22 | K53: 1.15 | M53: 0.82 | S53: =YEAR(A53) -> 1971
A54: 26480 | B54: 0.19 | I54: 0.23 | K54: 1.21 | M54: 0.88 | S54: =YEAR(A54) -> 1972
A55: 26845 | B55: 0.22 | I55: 0.25 | K55: 1.29 | M55: 0.94 | S55: =YEAR(A55) -> 1973
A56: 27210 | B56: 0.3 | I56: 0.3 | K56: 1.43 | M56: 1.07 | S56: =YEAR(A56) -> 1974
A57: 27575 | B57: 0.44 | I57: 0.4 | K57: 1.71 | M57: 1.35 | S57: =YEAR(A57) -> 1975
A58: 27941 | B58: 0.58 | I58: 0.51 | K58: 1.98 | M58: 1.64 | S58: =YEAR(A58) -> 1976
A59: 28306 | B59: 0.79 | I59: 0.77 | K59: 2.35 | M59: 2.04 | S59: =YEAR(A59) -> 1977
A60: 28671 | B60: 0.91 | I60: 0.9 | K60: 2.56 | M60: 2.23 | S60: =YEAR(A60) -> 1978
... A65: 30497 | B65: 2.59 | I65: 3.15 | K65: 6.06 | M65: 5.59 | S65: =YEAR(A65) -> 1983
A66: 30863 | B66: 2.66 | I66: 3.04 | J66: 3.95 | K66: 6.12 | M66: 5.55 | S66: =YEAR(A66) -> 1984
A67: 31228 | B67: 2.51 | C67: 3.21 | D67: 3.17 | E67: 4.6 | F67: 4.77 | G67: 3.92 | H67: 4.81 | I67: 2.92 | J67: 3.75 | K67: 6.12 | M67: 5.5 | S67: =YEAR(A67) -> 1985
A68: 31593 | B68: 1.94 | C68: 2.43 | D68: 2.42 | E68: 4.62 | F68: 2.81 | G68: 2.35 | H68: 2.91 | I68: 2.52 | J68: 3.22 | K68: 5.83 | M68: 5.08 | S68: =YEAR(A68) -> 1986
A69: 31958 | B69: 1.67 | C69: 1.95 | D69: 1.95 | F69: 3.07 | G69: 2.35 | H69: 3.15 | I69: 2.17 | J69: 2.87 | K69: 5.54 | M69: 4.77 | N69: 93.1 | S69: =YEAR(A69) -> 1987
A70: 32324 | B70: 1.69 | C70: 1.84 | D70: 1.83 | E70: 2.71 | F70: 2.74 | G70: 2.14 | H70: 2.98 | I70: 2.1 | J70: 2.92 | K70: 5.47 | M70: 4.63 | N70: 90.8 | S70: =YEAR(A70) -> 1988
A71: 32689 | B71: 1.69 | C71: 1.82 | D71: 1.81 | E71: 2.22 | F71: 2.51 | G71: 2.05 | H71: 3.01 | I71: 2.01 | J71: 3.01 | K71: 5.64 | L71: 99.9 | M71: 4.74 | N71: 89.1 | Q71: 4.17 | S71: =YEAR(A71) -> 1989
A72: 33054 | B72: 1.71 | C72: 1.94 | D72: 1.91 | E72: 2.47 | F72: 3.1 | G72: 2.31 | H72: 3.59 | I72: 1.95 | J72: 3.03 | K72: 5.8 | L72: 99.2 | M72: 4.83 | N72: 86.6 | Q72: 3.39 | S72: =YEAR(A72) -> 1990
A73: 33419 | B73: 1.64 | C73: 1.83 | D73: 1.81 | E73: 2.36 | F73: 2.59 | G73: 1.79 | H73: 3.71 | I73: 1.87 | J73: 2.9 | K73: 5.82 | L73: 99.2 | M73: 4.81 | N73: 85.1 | Q73: 3.96 | S73: =YEAR(A73) -> 1991
A74: 33785 | B74: 1.74 | C74: 1.85 | D74: 1.84 | E74: 2.54 | F74: 2.25 | G74: 1.88 | H74: 3.43 | I74: 2.07 | J74: 3.01 | K74: 5.89 | L74: 99.1 | M74: 4.88 | N74: 83.2 | Q74: 4.05 | S74: =YEAR(A74) -> 1992
A75: 34150 | B75: 2.04 | C75: 2.03 | D75: 2.02 | E75: 2.2 | F75: 2.59 | G75: 2.08 | H75: 3.34 | I75: 1.97 | J75: 3.21 | K75: 6.16 | L75: 99.1 | M75: 5.22 | N75: 83.9 | Q75: 4.27 | S75: =YEAR(A75) -> 1993
A76: 34515 | B76: 1.85 | C76: 1.87 | D76: 1.86 | E76: 2.28 | F76: 2.5 | G76: 2.08 | H76: 3.18 | I76: 1.7 | J76: 3.07 | K76: 6.41 | L76: 99.1 | M76: 5.44 | N76: 79.3 | Q76: 4.11 | S76: =YEAR(A76) -> 1994
A77: 34880 | B77: 1.55 | C77: 1.49 | D77: 1.48 | E77: 2.3 | F77: 2.39 | G77: 1.64 | H77: 3.41 | I77: 1.49 | J77: 2.78 | K77: 6.06 | L77: 99 | M77: 5.05 | N77: 76.7 | Q77: 3.98 | S77: =YEAR(A77) -> 1995
A78: 35246 | B78: 2.17 | C78: 1.97 | D78: 1.96 | E78: 2.8 | F78: 2.97 | G78: 2.45 | H78: 3.65 | I78: 2.27 | J78: 3.27 | K78: 6.34 | L78: 99 | M78: 5.4 | N78: 77.6 | Q78: 4.34 | S78: =YEAR(A78) -> 1996
A79: 35611 | B79: 2.32 | C79: 2.17 | D79: 2.15 | E79: 2.74 | F79: 3.02 | G79: 2.49 | H79: 3.83 | I79: 2.29 | J79: 3.66 | K79: 6.94 | L79: 98.8 | M79: 5.8 | N79: 70.8 | O79: 3.59 | P79: 18.1 | Q79: 4.44 | R79: 2.78 | S79: =YEAR(A79) -> 1997
A80: 35976 | B80: 1.96 | C80: 1.97 | D80: 1.95 | E80: 2.63 | F80: 2.45 | G80: 2.13 | H80: 2.91 | I80: 2.01 | J80: 3.07 | K80: 6.82 | L80: 97.7 | M80: 5.48 | N80: 67 | O80: 3.14 | P80: 16.1 | Q80: 4.59 | R80: 2.4 | S80: =YEAR(A80) -> 1998
A81: 36341 | B81: 2.19 | C81: 2.24 | D81: 2.23 | E81: 2.47 | F81: 2.61 | G81: 2.3 | H81: 3.1 | I81: 1.88 | J81: 3.1 | K81: 6.69 | L81: 95.2 | M81: 5.33 | N81: 66.1 | O81: 3.12 | P81: 18.8 | Q81: 4.34 | R81: 2.62 | S81: =YEAR(A81) -> 1999
A82: 36707 | B82: 3.68 | C82: 3.95 | D82: 3.98 | E82: 3.5 | F82: 4.1 | G82: 4.02 | H82: 4.32 | I82: 2.97 | J82: 4.62 | K82: 7.76 | L82: 92.6 | M82: 6.59 | N82: 63.9 | O82: 4.45 | P82: 19.8 | Q82: 5.54 | R82: 4.38 | S82: =YEAR(A82) -> 2000
A83: 37072 | B83: 4 | C83: 4.43 | D83: 4.44 | E83: 4.35 | F83: 4.19 | G83: 4.14 | H83: 4.4 | I83: 3.55 | J83: 5.72 | K83: 9.63 | L83: 92.4 | M83: 8.43 | N83: 66 | O83: 5.24 | P83: 20.8 | Q83: 6.6 | R83: 4.61 | S83: =YEAR(A83) -> 2001
A84: 37437 | B84: 2.95 | C84: 3.15 | D84: 3.13 | E84: 3.41 | F84: 3.41 | G84: 3.32 | H84: 4.08 | J84: 4.12 | K84: 7.89 | L84: 97.9 | M84: 6.63 | N84: 77.4 | O84: 4.02 | P84: 22.7 | Q84: 5.1 | R84: 3.68 | S84: =YEAR(A84) -> 2002
A85: 37802 | B85: 4.88 | C85: 5.17 | D85: 5.23 | E85: 4.79 | F85: 5.54 | G85: 5.66 | H85: 4.47 | J85: 5.85 | K85: 9.63 | L85: 97.5 | M85: 8.4 | N85: 78.2 | O85: 5.89 | P85: 22.1 | Q85: 6.19 | R85: 5.57 | S85: =YEAR(A85) -> 2003
A86: 38168 | B86: 5.46 | C86: 5.81 | D86: 5.8 | E86: 5.82 | F86: 6.09 | G86: 6.18 | H86: 4.96 | J86: 6.65 | K86: 10.75 | L86: 97.7 | M86: 9.43 | N86: 78 | O86: 6.53 | P86: 23.6 | Q86: 7.16 | R86: 6.11 | S86: =YEAR(A86) -> 2004
A87: 38533 | B87: 7.33 | C87: 8.12 | D87: 8.09 | E87: 8.26 | F87: 7.59 | G87: 7.77 | H87: 5.79 | J87: 8.67 | K87: 12.7 | L87: 98.1 | M87: 11.34 | N87: 82.1 | O87: 8.56 | P87: 24 | Q87: 9.14 | R87: 8.47 | S87: =YEAR(A87) -> 2005
A88: 38898 | B88: 6.39 | C88: 6.88 | D88: 6.83 | E88: 7.19 | F88: 6.83 | G88: 6.9 | H88: 6.02 | J88: 8.61 | K88: 13.73 | L88: 98.1 | M88: 12 | N88: 80.8 | O88: 7.87 | P88: 23.4 | Q88: 8.72 | R88: 7.11 | S88: =YEAR(A88) -> 2006
A89: 39263 | B89: 6.25 | C89: 6.87 | D89: 6.83 | E89: 7.07 | F89: 6.92 | G89: 6.96 | H89: 6.23 | J89: 8.16 | K89: 13.08 | L89: 98 | M89: 11.34 | N89: 80.4 | O89: 7.68 | P89: 22.2 | Q89: 8.5 | R89: 7.31 | S89: =YEAR(A89) -> 2007
A90: 39629 | B90: 7.97 | C90: 8.7 | D90: 8.57 | E90: 10.03 | F90: 8.58 | G90: 8.62 | H90: 7.69 | J90: 9.18 | K90: 13.89 | L90: 97.5 | M90: 12.23 | N90: 79.7 | O90: 9.65 | P90: 20.4 | Q90: 11.75 | R90: 9.26 | S90: =YEAR(A90) -> 2008
A91: 39994 | B91: 3.67 | C91: 4.19 | D91: 4.13 | E91: 4.59 | F91: 4.47 | G91: 4.34 | H91: 8.4 | J91: 6.48 | K91: 12.14 | L91: 97.4 | M91: 10.06 | N91: 77.8 | O91: 5.33 | P91: 18.8 | Q91: 8.13 | R91: 4.93 | S91: =YEAR(A91) -> 2009
A92: 40359 | B92: 4.48 | C92: 4.52 | D92: 4.46 | E92: 4.94 | F92: 5.02 | G92: 4.75 | H92: 9.53 | J92: 6.18 | K92: 11.39 | L92: 97.4 | M92: 9.47 | N92: 77.5 | O92: 5.49 | P92: 18 | Q92: 6.25 | R92: 5.27 | S92: =YEAR(A92) -> 2010
A93: 40724 | B93: 3.95 | C93: 4.24 | D93: 4.09 | E93: 5.63 | F93: 4.64 | G93: 4.35 | H93: 10.54 | J93: 5.63 | K93: 11.03 | L93: 96.3 | M93: 8.91 | N93: 67.3 | O93: 5.13 | P93: 16.3 | Q93: 7.48 | R93: 4.89 | S93: =YEAR(A93) -> 2011
A94: 41090 | B94: 2.66 | C94: 2.88 | D94: 2.79 | E94: 4.27 | F94: 3.25 | G94: 3.08 | H94: 12.82 | J94: 4.73 | K94: 10.65 | L94: 95.8 | M94: 8.1 | N94: 65.2 | O94: 3.88 | P94: 16.2 | Q94: 8.04 | R94: 3.54 | S94: =YEAR(A94) -> 2012
A95: 41455 | C95: 3.83 | D95: 3.73 | E95: 6.8 | F95: 4.08 | G95: 4.06 | H95: 13.36 | J95: 4.88 | K95: 10.32 | L95: 95.7 | M95: 8.08 | N95: 65.8 | O95: 4.64 | P95: 16.6 | R95: 4.49 | S95: =YEAR(A95) -> 2013
A96: 41820 | C96: 5.3 | D96: 5.21 | E96: 8.85 | F96: 5.51 | G96: 5.4 | H96: 15.66 | J96: 5.71 | K96: 10.97 | L96: 95.5 | M96: 8.9 | N96: 65.8 | O96: 5.62 | P96: 15.9 | R96: 5.19 | S96: =YEAR(A96) -> 2014
A97: 42185 | C97: 2.99 | D97: 2.84 | E97: 7.37 | F97: 3.07 | G97: 2.95 | H97: 10.92 | J97: 4.26 | K97: 10.38 | L97: 95.6 | M97: 7.91 | N97: 65.7 | O97: 3.93 | P97: 14.8 | R97: 3.38 | S97: =YEAR(A97) -> 2015
A98: 42551 | C98: 2.24 | D98: 2.18 | E98: 4.07 | F98: 2.79 | G98: 2.63 | H98: 4.71 | J98: 3.71 | K98: 10.05 | L98: 95.8 | M98: 7.28 | N98: 64.8 | O98: 3.51 | P98: 14.9 | R98: 2.99 | S98: =YEAR(A98) -> 2016
A99: 42916 | C99: 2.6 | D99: 2.55 | E99: 4.58 | F99: 3.54 | G99: 3.2 | H99: 4.69 | J99: 4.16 | K99: 10.91 | L99: 95.9 | M99: 7.88 | N99: 65.4 | O99: 4.08 | P99: 14.8 | R99: 3.51 | S99: =YEAR(A99) -> 2017
A100: 43281 | C100: 2.69 | D100: 2.58 | E100: 6.56 | F100: 3.89 | G100: 3.34 | H100: 5.2 | J100: 4.23 | K100: 10.5 | L100: 96 | M100: 7.79 | N100: 65.8 | O100: 4.19 | P100: 14.5 | R100: 3.68 | S100: =YEAR(A100) -> 2018
A101: 43646 | C101: 2.55 | D101: 2.46 | E101: 7.44 | F101: 3.64 | G101: 2.64 | H101: 5.21 | J101: 3.81 | K101: 10.51 | L101: 96.2 | M101: 7.61 | N101: 65.5 | O101: 3.9 | P101: 13 | R101: 2.99 | S101: =YEAR(A101) -> 2019
A102: 44012 | C102: 2.07 | D102: 2.02 | E102: 4.6 | F102: 3.7 | G102: 2.1 | H102: 5.64 | J102: 3.43 | K102: 10.78 | L102: 96.3 | M102: 7.48 | N102: 64.6 | O102: 3.32 | P102: 13.2 | R102: 2.49 | S102: =YEAR(A102) -> 2020
A103: 44377 | C103: 3.78 | D103: 3.72 | E103: 12.21 | F103: 6.38 | G103: 4.94 | H103: 7.62 | J103: 6.02 | K103: 12.18 | L103: 96.6 | M103: 8.79 | N103: 65.1 | O103: 5.44 | P103: 13.4 | R103: 5.43 | S103: =YEAR(A103) -> 2021
A104: 44742 | C104: 6.33 | D104: 6.15 | E104: 28.51 | F104: 9.64 | G104: 6.34 | H104: 12.24 | J104: 6.87 | K104: 14.75 | L104: 96.7 | M104: 11.32 | N104: 65.8 | O104: 7.69 | P104: 13.4 | R104: 7.51 | S104: =YEAR(A104) -> 2022
A105: 45107 | C105: 3.32 | D105: 3.23 | E105: 19.63 | F105: 5.41 | G105: 2.54 | H105: 7.57 | J105: 5.56 | K105: 15.39 | L105: 96.9 | M105: 11.07 | N105: 65.4 | O105: 4.53 | P105: 13.3 | R105: 3.5 | S105: =YEAR(A105) -> 2023
A106: 45473 | C106: 2.06 | D106: 2.01 | E106: 12.19 | F106: 4.48 | G106: 1.95 | H106: 6.41 | J106: 4.25 | K106: 14.5 | L106: 97 | M106: 10.07 | N106: 63.3 | O106: 4.07 | P106: 13.7 | R106: 2.87 | S106: =YEAR(A106) -> 2024
A107: 45838.534 | J107: 4.85 | K107: 15.34 | M107: 10.97 | O107: 5.23 | R107: 4.02 | S107: =YEAR(A107) -> 2025

Sheet Historical Monthly Gas Cons
A1: Back to Contents | B1: Data 1: Natural Gas Delivered to Consumers in the U.S. (MMcf)
A2: Sourcekey | B2: N3060US2
A3: Date | B3: Natural Gas Delivered to Consumers in the U.S. (MMcf)
A4: 36906 | B4: 2505011 | C4: =MONTH(A4) -> 1 | D4: =YEAR(A4) -> 2001
A5: 36937 | B5: 2156873 | C5: =MONTH(A5) -> 2 | D5: =YEAR(A5) -> 2001
A6: 36965 | B6: 2086568 | C6: =MONTH(A6) -> 3 | D6: =YEAR(A6) -> 2001
A7: 36996 | B7: 1663832 | C7: =MONTH(A7) -> 4 | D7: =YEAR(A7) -> 2001
A8: 37026 | B8: 1385163 | C8: =MONTH(A8) -> 5 | D8: =YEAR(A8) -> 2001
A9: 37057 | B9: 1313119 | C9: =MONTH(A9) -> 6 | D9: =YEAR(A9) -> 2001
A10: 37087 | B10: 1459919 | C10: =MONTH(A10) -> 7 | D10: =YEAR(A10) -> 2001
A11: 37118 | B11: 1528483 | C11: =MONTH(A11) -> 8 | D11: =YEAR(A11) -> 2001
A12: 37149 | B12: 1360871 | C12: =MONTH(A12) -> 9 | D12: =YEAR(A12) -> 2001
A13: 37179 | B13: 1507428 | C13: =MONTH(A13) -> 10 | D13: =YEAR(A13) -> 2001
A14: 37210 | B14: 1561970 | C14: =MONTH(A14) -> 11 | D14: =YEAR(A14) -> 2001
A15: 37240 | B15: 1965873 | C15: =MONTH(A15) -> 12 | D15: =YEAR(A15) -> 2001
... A300: 45915 | B300: 2162772 | C300: =MONTH(A300) -> 9 | D300: =YEAR(A300) -> 2025

Sheet NG Calcs
A1: Historical Monthly Consumption Average
A2: 1 | B2: {=SUMPRODUCT(IF('Historical Monthly Gas Cons'!$C:$C='NG Calcs'!A2,IF('Historical Monthly Gas Cons'!$D:$D>2021,'Historical Monthly Gas Cons'!$B:$B))/SUMPRODUCT(IF('Historical Monthly Gas Cons'!$D:$D>2021,'Historical Monthly Gas Cons'!$B:$B)))} -> 0.12049594
A3: 2 | B3: {=SUMPRODUCT(IF('Historical Monthly Gas Cons'!$C:$C='NG Calcs'!A3,IF('Historical Monthly Gas Cons'!$D:$D>2021,'Historical Monthly Gas Cons'!$B:$B))/SUMPRODUCT(IF('Historical Monthly Gas Cons'!$D:$D>2021,'Historical Monthly Gas Cons'!$B:$B)))} -> 0.10070617
A4: 3 | B4: {=SUMPRODUCT(IF('Historical Monthly Gas Cons'!$C:$C='NG Calcs'!A4,IF('Historical Monthly Gas Cons'!$D:$D>2021,'Historical Monthly Gas Cons'!$B:$B))/SUMPRODUCT(IF('Historical Monthly Gas Cons'!$D:$D>2021,'Historical Monthly Gas Cons'!$B:$B)))} -> 0.092746038
A5: 4 | B5: {=SUMPRODUCT(IF('Historical Monthly Gas Cons'!$C:$C='NG Calcs'!A5,IF('Historical Monthly Gas Cons'!$D:$D>2021,'Historical Monthly Gas Cons'!$B:$B))/SUMPRODUCT(IF('Historical Monthly Gas Cons'!$D:$D>2021,'Historical Monthly Gas Cons'!$B:$B)))} -> 0.07732915
A6: 5 | B6: {=SUMPRODUCT(IF('Historical Monthly Gas Cons'!$C:$C='NG Calcs'!A6,IF('Historical Monthly Gas Cons'!$D:$D>2021,'Historical Monthly Gas Cons'!$B:$B))/SUMPRODUCT(IF('Historical Monthly Gas Cons'!$D:$D>2021,'Historical Monthly Gas Cons'!$B:$B)))} -> 0.074025061
A7: 6 | B7: {=SUMPRODUCT(IF('Historical Monthly Gas Cons'!$C:$C='NG Calcs'!A7,IF('Historical Monthly Gas Cons'!$D:$D>2021,'Historical Monthly Gas Cons'!$B:$B))/SUMPRODUCT(IF('Historical Monthly Gas Cons'!$D:$D>2021,'Historical Monthly Gas Cons'!$B:$B)))} -> 0.076988667
A8: 7 | B8: {=SUMPRODUCT(IF('Historical Monthly Gas Cons'!$C:$C='NG Calcs'!A8,IF('Historical Monthly Gas Cons'!$D:$D>2021,'Historical Monthly Gas Cons'!$B:$B))/SUMPRODUCT(IF('Historical Monthly Gas Cons'!$D:$D>2021,'Historical Monthly Gas Cons'!$B:$B)))} -> 0.087090362
A9: 8 | B9: {=SUMPRODUCT(IF('Historical Monthly Gas Cons'!$C:$C='NG Calcs'!A9,IF('Historical Monthly Gas Cons'!$D:$D>2021,'Historical Monthly Gas Cons'!$B:$B))/SUMPRODUCT(IF('Historical Monthly Gas Cons'!$D:$D>2021,'Historical Monthly Gas Cons'!$B:$B)))} -> 0.086091328
A10: 9 | B10: {=SUMPRODUCT(IF('Historical Monthly Gas Cons'!$C:$C='NG Calcs'!A10,IF('Historical Monthly Gas Cons'!$D:$D>2021,'Historical Monthly Gas Cons'!$B:$B))/SUMPRODUCT(IF('Historical Monthly Gas Cons'!$D:$D>2021,'Historical Monthly Gas Cons'!$B:$B)))} -> 0.076769349
A11: 10 | B11: {=SUMPRODUCT(IF('Historical Monthly Gas Cons'!$C:$C='NG Calcs'!A11,IF('Historical Monthly Gas Cons'!$D:$D>2021,'Historical Monthly Gas Cons'!$B:$B))/SUMPRODUCT(IF('Historical Monthly Gas Cons'!$D:$D>2021,'Historical Monthly Gas Cons'!$B:$B)))} -> 0.058411579
A12: 11 | B12: {=SUMPRODUCT(IF('Historical Monthly Gas Cons'!$C:$C='NG Calcs'!A12,IF('Historical Monthly Gas Cons'!$D:$D>2021,'Historical Monthly Gas Cons'!$B:$B))/SUMPRODUCT(IF('Historical Monthly Gas Cons'!$D:$D>2021,'Historical Monthly Gas Cons'!$B:$B)))} -> 0.067770673
A13: 12 | B13: {=SUMPRODUCT(IF('Historical Monthly Gas Cons'!$C:$C='NG Calcs'!A13,IF('Historical Monthly Gas Cons'!$D:$D>2021,'Historical Monthly Gas Cons'!$B:$B))/SUMPRODUCT(IF('Historical Monthly Gas Cons'!$D:$D>2021,'Historical Monthly Gas Cons'!$B:$B)))} -> 0.081575676
A15: Future Prices | B15: 2021 | C15: 2022 | D15: 2023 | E15: 2024 | F15: 2025 | G15: 2026 | H15: 2027 | I15: 2028 | J15: 2029 | K15: 2030 | L15: 2031 | M15: 2032 | N15: 2033 | O15: 2034 | P15: 2035 | Q15: 2036
A16: 1 | B16: =INDEX('Henry Hub Historicals'!$B$4:$B$389,MATCH(CONCATENATE('NG Calcs'!$A16,".",'NG Calcs'!B$15),'Henry Hub Historicals'!$C$4:$C$389,0),1) -> 2.71 | C16: =INDEX('Henry Hub Historicals'!$B$4:$B$389,MATCH(CONCATENATE('NG Calcs'!$A16,".",'NG Calcs'!C$15),'Henry Hub Historicals'!$C$4:$C$389,0),1) -> 4.38 | D16: =INDEX('Henry Hub Historicals'!$B$4:$B$389,MATCH(CONCATENATE('NG Calcs'!$A16,".",'NG Calcs'!D$15),'Henry Hub Historicals'!$C$4:$C$389,0),1) -> 3.27 | E16: =INDEX('Henry Hub Historicals'!$B$4:$B$389,MATCH(CONCATENATE('NG Calcs'!$A16,".",'NG Calcs'!E$15),'Henry Hub Historicals'!$C$4:$C$389,0),1) -> 3.18 | F16: =INDEX('Henry Hub Historicals'!$B$4:$B$389,MATCH(CONCATENATE('NG Calcs'!$A16,".",'NG Calcs'!F$15),'Henry Hub Historicals'!$C$4:$C$389,0),1) -> 4.13 | G16: =INDEX('Henry Hub Historicals'!$B$4:$B$389,MATCH(CONCATENATE('NG Calcs'!$A16,".",'NG Calcs'!G$15),'Henry Hub Historicals'!$C$4:$C$389,0),1) -> 7.72 | H16: =INDEX('Gas Futures'!$G:$G,MATCH(CONCATENATE('NG Calcs'!$A16,".",'NG Calcs'!H$15),'Gas Futures'!$L:$L,0)) -> 3.877 | I16: =INDEX('Gas Futures'!$G:$G,MATCH(CONCATENATE('NG Calcs'!$A16,".",'NG Calcs'!I$15),'Gas Futures'!$L:$L,0)) -> 4.613 | J16: =INDEX('Gas Futures'!$G:$G,MATCH(CONCATENATE('NG Calcs'!$A16,".",'NG Calcs'!J$15),'Gas Futures'!$L:$L,0)) -> 4.838 | K16: =INDEX('Gas Futures'!$G:$G,MATCH(CONCATENATE('NG Calcs'!$A16,".",'NG Calcs'!K$15),'Gas Futures'!$L:$L,0)) -> - | L16: =INDEX('Gas Futures'!$G:$G,MATCH(CONCATENATE('NG Calcs'!$A16,".",'NG Calcs'!L$15),'Gas Futures'!$L:$L,0)) -> - | M16: =INDEX('Gas Futures'!$G:$G,MATCH(CONCATENATE('NG Calcs'!$A16,".",'NG Calcs'!M$15),'Gas Futures'!$L:$L,0)) -> - | N16: =INDEX('Gas Futures'!$G:$G,MATCH(CONCATENATE('NG Calcs'!$A16,".",'NG Calcs'!N$15),'Gas Futures'!$L:$L,0)) -> - | O16: =INDEX('Gas Futures'!$G:$G,MATCH(CONCATENATE('NG Calcs'!$A16,".",'NG Calcs'!O$15),'Gas Futures'!$L:$L,0)) -> - | ... Q16: =INDEX('Gas Futures'!$G:$G,MATCH(CONCATENATE('NG Calcs'!$A16,".",'NG Calcs'!Q$15),'Gas Futures'!$L:$L,0)) -> -
A17: 2 | B17: =INDEX('Henry Hub Historicals'!$B$4:$B$389,MATCH(CONCATENATE('NG Calcs'!$A17,".",'NG Calcs'!B$15),'Henry Hub Historicals'!$C$4:$C$389,0),1) -> 5.35 | C17: =INDEX('Henry Hub Historicals'!$B$4:$B$389,MATCH(CONCATENATE('NG Calcs'!$A17,".",'NG Calcs'!C$15),'Henry Hub Historicals'!$C$4:$C$389,0),1) -> 4.69 | D17: =INDEX('Henry Hub Historicals'!$B$4:$B$389,MATCH(CONCATENATE('NG Calcs'!$A17,".",'NG Calcs'!D$15),'Henry Hub Historicals'!$C$4:$C$389,0),1) -> 2.38 | E17: =INDEX('Henry Hub Historicals'!$B$4:$B$389,MATCH(CONCATENATE('NG Calcs'!$A17,".",'NG Calcs'!E$15),'Henry Hub Historicals'!$C$4:$C$389,0),1) -> 1.72 | F17: =INDEX('Henry Hub Historicals'!$B$4:$B$389,MATCH(CONCATENATE('NG Calcs'!$A17,".",'NG Calcs'!F$15),'Henry Hub Historicals'!$C$4:$C$389,0),1) -> 4.19 | G17: =INDEX('Henry Hub Historicals'!$B$4:$B$389,MATCH(CONCATENATE('NG Calcs'!$A17,".",'NG Calcs'!G$15),'Henry Hub Historicals'!$C$4:$C$389,0),1) -> 3.62 | H17: =INDEX('Gas Futures'!$G:$G,MATCH(CONCATENATE('NG Calcs'!$A17,".",'NG Calcs'!H$15),'Gas Futures'!$L:$L,0)) -> 3.542 | I17: =INDEX('Gas Futures'!$G:$G,MATCH(CONCATENATE('NG Calcs'!$A17,".",'NG Calcs'!I$15),'Gas Futures'!$L:$L,0)) -> 4.212 | J17: =INDEX('Gas Futures'!$G:$G,MATCH(CONCATENATE('NG Calcs'!$A17,".",'NG Calcs'!J$15),'Gas Futures'!$L:$L,0)) -> 4.38 | K17: =INDEX('Gas Futures'!$G:$G,MATCH(CONCATENATE('NG Calcs'!$A17,".",'NG Calcs'!K$15),'Gas Futures'!$L:$L,0)) -> 4.342 | L17: =INDEX('Gas Futures'!$G:$G,MATCH(CONCATENATE('NG Calcs'!$A17,".",'NG Calcs'!L$15),'Gas Futures'!$L:$L,0)) -> - | M17: =INDEX('Gas Futures'!$G:$G,MATCH(CONCATENATE('NG Calcs'!$A17,".",'NG Calcs'!M$15),'Gas Futures'!$L:$L,0)) -> - | N17: =INDEX('Gas Futures'!$G:$G,MATCH(CONCATENATE('NG Calcs'!$A17,".",'NG Calcs'!N$15),'Gas Futures'!$L:$L,0)) -> - | O17: =INDEX('Gas Futures'!$G:$G,MATCH(CONCATENATE('NG Calcs'!$A17,".",'NG Calcs'!O$15),'Gas Futures'!$L:$L,0)) -> - | ... Q17: =INDEX('Gas Futures'!$G:$G,MATCH(CONCATENATE('NG Calcs'!$A17,".",'NG Calcs'!Q$15),'Gas Futures'!$L:$L,0)) -> -
A18: 3 | B18: =INDEX('Henry Hub Historicals'!$B$4:$B$389,MATCH(CONCATENATE('NG Calcs'!$A18,".",'NG Calcs'!B$15),'Henry Hub Historicals'!$C$4:$C$389,0),1) -> 2.62 | C18: =INDEX('Henry Hub Historicals'!$B$4:$B$389,MATCH(CONCATENATE('NG Calcs'!$A18,".",'NG Calcs'!C$15),'Henry Hub Historicals'!$C$4:$C$389,0),1) -> 4.9 | D18: =INDEX('Henry Hub Historicals'!$B$4:$B$389,MATCH(CONCATENATE('NG Calcs'!$A18,".",'NG Calcs'!D$15),'Henry Hub Historicals'!$C$4:$C$389,0),1) -> 2.31 | E18: =INDEX('Henry Hub Historicals'!$B$4:$B$389,MATCH(CONCATENATE('NG Calcs'!$A18,".",'NG Calcs'!E$15),'Henry Hub Historicals'!$C$4:$C$389,0),1) -> 1.49 | F18: =INDEX('Henry Hub Historicals'!$B$4:$B$389,MATCH(CONCATENATE('NG Calcs'!$A18,".",'NG Calcs'!F$15),'Henry Hub Historicals'!$C$4:$C$389,0),1) -> 4.12 | G18: =INDEX('Henry Hub Historicals'!$B$4:$B$389,MATCH(CONCATENATE('NG Calcs'!$A18,".",'NG Calcs'!G$15),'Henry Hub Historicals'!$C$4:$C$389,0),1) -> 3.04 | H18: =INDEX('Gas Futures'!$G:$G,MATCH(CONCATENATE('NG Calcs'!$A18,".",'NG Calcs'!H$15),'Gas Futures'!$L:$L,0)) -> 2.857 | I18: =INDEX('Gas Futures'!$G:$G,MATCH(CONCATENATE('NG Calcs'!$A18,".",'NG Calcs'!I$15),'Gas Futures'!$L:$L,0)) -> 3.486 | J18: =INDEX('Gas Futures'!$G:$G,MATCH(CONCATENATE('NG Calcs'!$A18,".",'NG Calcs'!J$15),'Gas Futures'!$L:$L,0)) -> 3.45 | K18: =INDEX('Gas Futures'!$G:$G,MATCH(CONCATENATE('NG Calcs'!$A18,".",'NG Calcs'!K$15),'Gas Futures'!$L:$L,0)) -> - | L18: =INDEX('Gas Futures'!$G:$G,MATCH(CONCATENATE('NG Calcs'!$A18,".",'NG Calcs'!L$15),'Gas Futures'!$L:$L,0)) -> - | M18: =INDEX('Gas Futures'!$G:$G,MATCH(CONCATENATE('NG Calcs'!$A18,".",'NG Calcs'!M$15),'Gas Futures'!$L:$L,0)) -> - | N18: =INDEX('Gas Futures'!$G:$G,MATCH(CONCATENATE('NG Calcs'!$A18,".",'NG Calcs'!N$15),'Gas Futures'!$L:$L,0)) -> - | O18: =INDEX('Gas Futures'!$G:$G,MATCH(CONCATENATE('NG Calcs'!$A18,".",'NG Calcs'!O$15),'Gas Futures'!$L:$L,0)) -> - | ... Q18: =INDEX('Gas Futures'!$G:$G,MATCH(CONCATENATE('NG Calcs'!$A18,".",'NG Calcs'!Q$15),'Gas Futures'!$L:$L,0)) -> -
A19: 4 | B19: =INDEX('Henry Hub Historicals'!$B$4:$B$389,MATCH(CONCATENATE('NG Calcs'!$A19,".",'NG Calcs'!B$15),'Henry Hub Historicals'!$C$4:$C$389,0),1) -> 2.66 | C19: =INDEX('Henry Hub Historicals'!$B$4:$B$389,MATCH(CONCATENATE('NG Calcs'!$A19,".",'NG Calcs'!C$15),'Henry Hub Historicals'!$C$4:$C$389,0),1) -> 6.6 | D19: =INDEX('Henry Hub Historicals'!$B$4:$B$389,MATCH(CONCATENATE('NG Calcs'!$A19,".",'NG Calcs'!D$15),'Henry Hub Historicals'!$C$4:$C$389,0),1) -> 2.16 | E19: =INDEX('Henry Hub Historicals'!$B$4:$B$389,MATCH(CONCATENATE('NG Calcs'!$A19,".",'NG Calcs'!E$15),'Henry Hub Historicals'!$C$4:$C$389,0),1) -> 1.6 | F19: =INDEX('Henry Hub Historicals'!$B$4:$B$389,MATCH(CONCATENATE('NG Calcs'!$A19,".",'NG Calcs'!F$15),'Henry Hub Historicals'!$C$4:$C$389,0),1) -> 3.42 | G19: =INDEX('Henry Hub Historicals'!$B$4:$B$389,MATCH(CONCATENATE('NG Calcs'!$A19,".",'NG Calcs'!G$15),'Henry Hub Historicals'!$C$4:$C$389,0),1) -> 2.77 | H19: =INDEX('Gas Futures'!$G:$G,MATCH(CONCATENATE('NG Calcs'!$A19,".",'NG Calcs'!H$15),'Gas Futures'!$L:$L,0)) -> 2.734 | I19: =INDEX('Gas Futures'!$G:$G,MATCH(CONCATENATE('NG Calcs'!$A19,".",'NG Calcs'!I$15),'Gas Futures'!$L:$L,0)) -> 3.255 | J19: =INDEX('Gas Futures'!$G:$G,MATCH(CONCATENATE('NG Calcs'!$A19,".",'NG Calcs'!J$15),'Gas Futures'!$L:$L,0)) -> 3.178 | K19: =INDEX('Gas Futures'!$G:$G,MATCH(CONCATENATE('NG Calcs'!$A19,".",'NG Calcs'!K$15),'Gas Futures'!$L:$L,0)) -> - | L19: =INDEX('Gas Futures'!$G:$G,MATCH(CONCATENATE('NG Calcs'!$A19,".",'NG Calcs'!L$15),'Gas Futures'!$L:$L,0)) -> 3.05 | M19: =INDEX('Gas Futures'!$G:$G,MATCH(CONCATENATE('NG Calcs'!$A19,".",'NG Calcs'!M$15),'Gas Futures'!$L:$L,0)) -> 3.02 | N19: =INDEX('Gas Futures'!$G:$G,MATCH(CONCATENATE('NG Calcs'!$A19,".",'NG Calcs'!N$15),'Gas Futures'!$L:$L,0)) -> - | O19: =INDEX('Gas Futures'!$G:$G,MATCH(CONCATENATE('NG Calcs'!$A19,".",'NG Calcs'!O$15),'Gas Futures'!$L:$L,0)) -> - | ... Q19: =INDEX('Gas Futures'!$G:$G,MATCH(CONCATENATE('NG Calcs'!$A19,".",'NG Calcs'!Q$15),'Gas Futures'!$L:$L,0)) -> -
A20: 5 | B20: =INDEX('Henry Hub Historicals'!$B$4:$B$389,MATCH(CONCATENATE('NG Calcs'!$A20,".",'NG Calcs'!B$15),'Henry Hub Historicals'!$C$4:$C$389,0),1) -> 2.91 | C20: =INDEX('Henry Hub Historicals'!$B$4:$B$389,MATCH(CONCATENATE('NG Calcs'!$A20,".",'NG Calcs'!C$15),'Henry Hub Historicals'!$C$4:$C$389,0),1) -> 8.14 | D20: =INDEX('Henry Hub Historicals'!$B$4:$B$389,MATCH(CONCATENATE('NG Calcs'!$A20,".",'NG Calcs'!D$15),'Henry Hub Historicals'!$C$4:$C$389,0),1) -> 2.15 | E20: =INDEX('Henry Hub Historicals'!$B$4:$B$389,MATCH(CONCATENATE('NG Calcs'!$A20,".",'NG Calcs'!E$15),'Henry Hub Historicals'!$C$4:$C$389,0),1) -> 2.12 | F20: =INDEX('Henry Hub Historicals'!$B$4:$B$389,MATCH(CONCATENATE('NG Calcs'!$A20,".",'NG Calcs'!F$15),'Henry Hub Historicals'!$C$4:$C$389,0),1) -> 3.12 | G20: =INDEX('Henry Hub Historicals'!$B$4:$B$389,MATCH(CONCATENATE('NG Calcs'!$A20,".",'NG Calcs'!G$15),'Henry Hub Historicals'!$C$4:$C$389,0),1) -> 2.94 | H20: =INDEX('Gas Futures'!$G:$G,MATCH(CONCATENATE('NG Calcs'!$A20,".",'NG Calcs'!H$15),'Gas Futures'!$L:$L,0)) -> 2.765 | I20: =INDEX('Gas Futures'!$G:$G,MATCH(CONCATENATE('NG Calcs'!$A20,".",'NG Calcs'!I$15),'Gas Futures'!$L:$L,0)) -> 3.252 | J20: =INDEX('Gas Futures'!$G:$G,MATCH(CONCATENATE('NG Calcs'!$A20,".",'NG Calcs'!J$15),'Gas Futures'!$L:$L,0)) -> 3.16 | K20: =INDEX('Gas Futures'!$G:$G,MATCH(CONCATENATE('NG Calcs'!$A20,".",'NG Calcs'!K$15),'Gas Futures'!$L:$L,0)) -> - | L20: =INDEX('Gas Futures'!$G:$G,MATCH(CONCATENATE('NG Calcs'!$A20,".",'NG Calcs'!L$15),'Gas Futures'!$L:$L,0)) -> - | M20: =INDEX('Gas Futures'!$G:$G,MATCH(CONCATENATE('NG Calcs'!$A20,".",'NG Calcs'!M$15),'Gas Futures'!$L:$L,0)) -> - | N20: =INDEX('Gas Futures'!$G:$G,MATCH(CONCATENATE('NG Calcs'!$A20,".",'NG Calcs'!N$15),'Gas Futures'!$L:$L,0)) -> 2.9 | O20: =INDEX('Gas Futures'!$G:$G,MATCH(CONCATENATE('NG Calcs'!$A20,".",'NG Calcs'!O$15),'Gas Futures'!$L:$L,0)) -> - | ... Q20: =INDEX('Gas Futures'!$G:$G,MATCH(CONCATENATE('NG Calcs'!$A20,".",'NG Calcs'!Q$15),'Gas Futures'!$L:$L,0)) -> -
A21: 6 | B21: =INDEX('Henry Hub Historicals'!$B$4:$B$389,MATCH(CONCATENATE('NG Calcs'!$A21,".",'NG Calcs'!B$15),'Henry Hub Historicals'!$C$4:$C$389,0),1) -> 3.26 | C21: =INDEX('Henry Hub Historicals'!$B$4:$B$389,MATCH(CONCATENATE('NG Calcs'!$A21,".",'NG Calcs'!C$15),'Henry Hub Historicals'!$C$4:$C$389,0),1) -> 7.7 | D21: =INDEX('Henry Hub Historicals'!$B$4:$B$389,MATCH(CONCATENATE('NG Calcs'!$A21,".",'NG Calcs'!D$15),'Henry Hub Historicals'!$C$4:$C$389,0),1) -> 2.18 | E21: =INDEX('Henry Hub Historicals'!$B$4:$B$389,MATCH(CONCATENATE('NG Calcs'!$A21,".",'NG Calcs'!E$15),'Henry Hub Historicals'!$C$4:$C$389,0),1) -> 2.54 | F21: =INDEX('Henry Hub Historicals'!$B$4:$B$389,MATCH(CONCATENATE('NG Calcs'!$A21,".",'NG Calcs'!F$15),'Henry Hub Historicals'!$C$4:$C$389,0),1) -> 3.02 | G21: =INDEX('Henry Hub Historicals'!$B$4:$B$389,MATCH(CONCATENATE('NG Calcs'!$A21,".",'NG Calcs'!G$15),'Henry Hub Historicals'!$C$4:$C$389,0),1) -> 3.15 | H21: =INDEX('Gas Futures'!$G:$G,MATCH(CONCATENATE('NG Calcs'!$A21,".",'NG Calcs'!H$15),'Gas Futures'!$L:$L,0)) -> 2.922 | I21: =INDEX('Gas Futures'!$G:$G,MATCH(CONCATENATE('NG Calcs'!$A21,".",'NG Calcs'!I$15),'Gas Futures'!$L:$L,0)) -> 3.412 | J21: =INDEX('Gas Futures'!$G:$G,MATCH(CONCATENATE('NG Calcs'!$A21,".",'NG Calcs'!J$15),'Gas Futures'!$L:$L,0)) -> 3.285 | K21: =INDEX('Gas Futures'!$G:$G,MATCH(CONCATENATE('NG Calcs'!$A21,".",'NG Calcs'!K$15),'Gas Futures'!$L:$L,0)) -> - | L21: =INDEX('Gas Futures'!$G:$G,MATCH(CONCATENATE('NG Calcs'!$A21,".",'NG Calcs'!L$15),'Gas Futures'!$L:$L,0)) -> - | M21: =INDEX('Gas Futures'!$G:$G,MATCH(CONCATENATE('NG Calcs'!$A21,".",'NG Calcs'!M$15),'Gas Futures'!$L:$L,0)) -> - | N21: =INDEX('Gas Futures'!$G:$G,MATCH(CONCATENATE('NG Calcs'!$A21,".",'NG Calcs'!N$15),'Gas Futures'!$L:$L,0)) -> - | O21: =INDEX('Gas Futures'!$G:$G,MATCH(CONCATENATE('NG Calcs'!$A21,".",'NG Calcs'!O$15),'Gas Futures'!$L:$L,0)) -> - | ... Q21: =INDEX('Gas Futures'!$G:$G,MATCH(CONCATENATE('NG Calcs'!$A21,".",'NG Calcs'!Q$15),'Gas Futures'!$L:$L,0)) -> -
A22: 7 | B22: =INDEX('Henry Hub Historicals'!$B$4:$B$389,MATCH(CONCATENATE('NG Calcs'!$A22,".",'NG Calcs'!B$15),'Henry Hub Historicals'!$C$4:$C$389,0),1) -> 3.84 | C22: =INDEX('Henry Hub Historicals'!$B$4:$B$389,MATCH(CONCATENATE('NG Calcs'!$A22,".",'NG Calcs'!C$15),'Henry Hub Historicals'!$C$4:$C$389,0),1) -> 7.28 | D22: =INDEX('Henry Hub Historicals'!$B$4:$B$389,MATCH(CONCATENATE('NG Calcs'!$A22,".",'NG Calcs'!D$15),'Henry Hub Historicals'!$C$4:$C$389,0),1) -> 2.55 | E22: =INDEX('Henry Hub Historicals'!$B$4:$B$389,MATCH(CONCATENATE('NG Calcs'!$A22,".",'NG Calcs'!E$15),'Henry Hub Historicals'!$C$4:$C$389,0),1) -> 2.07 | F22: =INDEX('Henry Hub Historicals'!$B$4:$B$389,MATCH(CONCATENATE('NG Calcs'!$A22,".",'NG Calcs'!F$15),'Henry Hub Historicals'!$C$4:$C$389,0),1) -> 3.2 | G22: =INDEX('Henry Hub Historicals'!$B$4:$B$389,MATCH(CONCATENATE('NG Calcs'!$A22,".",'NG Calcs'!G$15),'Henry Hub Historicals'!$C$4:$C$389,0),1) -> 2.89 | H22: =INDEX('Gas Futures'!$G:$G,MATCH(CONCATENATE('NG Calcs'!$A22,".",'NG Calcs'!H$15),'Gas Futures'!$L:$L,0)) -> 3.149 | I22: =INDEX('Gas Futures'!$G:$G,MATCH(CONCATENATE('NG Calcs'!$A22,".",'NG Calcs'!I$15),'Gas Futures'!$L:$L,0)) -> 3.622 | J22: =INDEX('Gas Futures'!$G:$G,MATCH(CONCATENATE('NG Calcs'!$A22,".",'NG Calcs'!J$15),'Gas Futures'!$L:$L,0)) -> 3.492 | K22: =INDEX('Gas Futures'!$G:$G,MATCH(CONCATENATE('NG Calcs'!$A22,".",'NG Calcs'!K$15),'Gas Futures'!$L:$L,0)) -> 3.46 | L22: =INDEX('Gas Futures'!$G:$G,MATCH(CONCATENATE('NG Calcs'!$A22,".",'NG Calcs'!L$15),'Gas Futures'!$L:$L,0)) -> - | M22: =INDEX('Gas Futures'!$G:$G,MATCH(CONCATENATE('NG Calcs'!$A22,".",'NG Calcs'!M$15),'Gas Futures'!$L:$L,0)) -> - | N22: =INDEX('Gas Futures'!$G:$G,MATCH(CONCATENATE('NG Calcs'!$A22,".",'NG Calcs'!N$15),'Gas Futures'!$L:$L,0)) -> - | O22: =INDEX('Gas Futures'!$G:$G,MATCH(CONCATENATE('NG Calcs'!$A22,".",'NG Calcs'!O$15),'Gas Futures'!$L:$L,0)) -> - | ... Q22: =INDEX('Gas Futures'!$G:$G,MATCH(CONCATENATE('NG Calcs'!$A22,".",'NG Calcs'!Q$15),'Gas Futures'!$L:$L,0)) -> -
A23: 8 | B23: =INDEX('Henry Hub Historicals'!$B$4:$B$389,MATCH(CONCATENATE('NG Calcs'!$A23,".",'NG Calcs'!B$15),'Henry Hub Historicals'!$C$4:$C$389,0),1) -> 4.07 | C23: =INDEX('Henry Hub Historicals'!$B$4:$B$389,MATCH(CONCATENATE('NG Calcs'!$A23,".",'NG Calcs'!C$15),'Henry Hub Historicals'!$C$4:$C$389,0),1) -> 8.81 | D23: =INDEX('Henry Hub Historicals'!$B$4:$B$389,MATCH(CONCATENATE('NG Calcs'!$A23,".",'NG Calcs'!D$15),'Henry Hub Historicals'!$C$4:$C$389,0),1) -> 2.58 | E23: =INDEX('Henry Hub Historicals'!$B$4:$B$389,MATCH(CONCATENATE('NG Calcs'!$A23,".",'NG Calcs'!E$15),'Henry Hub Historicals'!$C$4:$C$389,0),1) -> 1.99 | F23: =INDEX('Henry Hub Historicals'!$B$4:$B$389,MATCH(CONCATENATE('NG Calcs'!$A23,".",'NG Calcs'!F$15),'Henry Hub Historicals'!$C$4:$C$389,0),1) -> 2.91 | G23: =INDEX('Henry Hub Historicals'!$B$4:$B$389,MATCH(CONCATENATE('NG Calcs'!$A23,".",'NG Calcs'!G$15),'Henry Hub Historicals'!$C$4:$C$389,0),1) -> 2.78 | H23: =INDEX('Gas Futures'!$G:$G,MATCH(CONCATENATE('NG Calcs'!$A23,".",'NG Calcs'!H$15),'Gas Futures'!$L:$L,0)) -> 3.223 | I23: =INDEX('Gas Futures'!$G:$G,MATCH(CONCATENATE('NG Calcs'!$A23,".",'NG Calcs'!I$15),'Gas Futures'!$L:$L,0)) -> 3.68 | J23: =INDEX('Gas Futures'!$G:$G,MATCH(CONCATENATE('NG Calcs'!$A23,".",'NG Calcs'!J$15),'Gas Futures'!$L:$L,0)) -> - | K23: =INDEX('Gas Futures'!$G:$G,MATCH(CONCATENATE('NG Calcs'!$A23,".",'NG Calcs'!K$15),'Gas Futures'!$L:$L,0)) -> - | L23: =INDEX('Gas Futures'!$G:$G,MATCH(CONCATENATE('NG Calcs'!$A23,".",'NG Calcs'!L$15),'Gas Futures'!$L:$L,0)) -> - | M23: =INDEX('Gas Futures'!$G:$G,MATCH(CONCATENATE('NG Calcs'!$A23,".",'NG Calcs'!M$15),'Gas Futures'!$L:$L,0)) -> - | N23: =INDEX('Gas Futures'!$G:$G,MATCH(CONCATENATE('NG Calcs'!$A23,".",'NG Calcs'!N$15),'Gas Futures'!$L:$L,0)) -> - | O23: =INDEX('Gas Futures'!$G:$G,MATCH(CONCATENATE('NG Calcs'!$A23,".",'NG Calcs'!O$15),'Gas Futures'!$L:$L,0)) -> - | ... Q23: =INDEX('Gas Futures'!$G:$G,MATCH(CONCATENATE('NG Calcs'!$A23,".",'NG Calcs'!Q$15),'Gas Futures'!$L:$L,0)) -> -
A24: 9 | B24: =INDEX('Henry Hub Historicals'!$B$4:$B$389,MATCH(CONCATENATE('NG Calcs'!$A24,".",'NG Calcs'!B$15),'Henry Hub Historicals'!$C$4:$C$389,0),1) -> 5.16 | C24: =INDEX('Henry Hub Historicals'!$B$4:$B$389,MATCH(CONCATENATE('NG Calcs'!$A24,".",'NG Calcs'!C$15),'Henry Hub Historicals'!$C$4:$C$389,0),1) -> 7.88 | D24: =INDEX('Henry Hub Historicals'!$B$4:$B$389,MATCH(CONCATENATE('NG Calcs'!$A24,".",'NG Calcs'!D$15),'Henry Hub Historicals'!$C$4:$C$389,0),1) -> 2.64 | E24: =INDEX('Henry Hub Historicals'!$B$4:$B$389,MATCH(CONCATENATE('NG Calcs'!$A24,".",'NG Calcs'!E$15),'Henry Hub Historicals'!$C$4:$C$389,0),1) -> 2.28 | F24: =INDEX('Henry Hub Historicals'!$B$4:$B$389,MATCH(CONCATENATE('NG Calcs'!$A24,".",'NG Calcs'!F$15),'Henry Hub Historicals'!$C$4:$C$389,0),1) -> 2.97 | G24: =AVERAGE(G23,G25) -> 2.9085 | H24: =INDEX('Gas Futures'!$G:$G,MATCH(CONCATENATE('NG Calcs'!$A24,".",'NG Calcs'!H$15),'Gas Futures'!$L:$L,0)) -> 3.209 | I24: =INDEX('Gas Futures'!$G:$G,MATCH(CONCATENATE('NG Calcs'!$A24,".",'NG Calcs'!I$15),'Gas Futures'!$L:$L,0)) -> 3.638 | J24: =INDEX('Gas Futures'!$G:$G,MATCH(CONCATENATE('NG Calcs'!$A24,".",'NG Calcs'!J$15),'Gas Futures'!$L:$L,0)) -> - | K24: =INDEX('Gas Futures'!$G:$G,MATCH(CONCATENATE('NG Calcs'!$A24,".",'NG Calcs'!K$15),'Gas Futures'!$L:$L,0)) -> - | L24: =INDEX('Gas Futures'!$G:$G,MATCH(CONCATENATE('NG Calcs'!$A24,".",'NG Calcs'!L$15),'Gas Futures'!$L:$L,0)) -> - | M24: =INDEX('Gas Futures'!$G:$G,MATCH(CONCATENATE('NG Calcs'!$A24,".",'NG Calcs'!M$15),'Gas Futures'!$L:$L,0)) -> - | N24: =INDEX('Gas Futures'!$G:$G,MATCH(CONCATENATE('NG Calcs'!$A24,".",'NG Calcs'!N$15),'Gas Futures'!$L:$L,0)) -> - | O24: =INDEX('Gas Futures'!$G:$G,MATCH(CONCATENATE('NG Calcs'!$A24,".",'NG Calcs'!O$15),'Gas Futures'!$L:$L,0)) -> - | ... Q24: =INDEX('Gas Futures'!$G:$G,MATCH(CONCATENATE('NG Calcs'!$A24,".",'NG Calcs'!Q$15),'Gas Futures'!$L:$L,0)) -> -
A25: 10 | B25: =INDEX('Henry Hub Historicals'!$B$4:$B$389,MATCH(CONCATENATE('NG Calcs'!$A25,".",'NG Calcs'!B$15),'Henry Hub Historicals'!$C$4:$C$389,0),1) -> 5.51 | C25: =INDEX('Henry Hub Historicals'!$B$4:$B$389,MATCH(CONCATENATE('NG Calcs'!$A25,".",'NG Calcs'!C$15),'Henry Hub Historicals'!$C$4:$C$389,0),1) -> 5.66 | D25: =INDEX('Henry Hub Historicals'!$B$4:$B$389,MATCH(CONCATENATE('NG Calcs'!$A25,".",'NG Calcs'!D$15),'Henry Hub Historicals'!$C$4:$C$389,0),1) -> 2.98 | E25: =INDEX('Henry Hub Historicals'!$B$4:$B$389,MATCH(CONCATENATE('NG Calcs'!$A25,".",'NG Calcs'!E$15),'Henry Hub Historicals'!$C$4:$C$389,0),1) -> 2.2 | F25: =INDEX('Henry Hub Historicals'!$B$4:$B$389,MATCH(CONCATENATE('NG Calcs'!$A25,".",'NG Calcs'!F$15),'Henry Hub Historicals'!$C$4:$C$389,0),1) -> 3.19 | G25: =INDEX('Gas Futures'!$G:$G,MATCH(CONCATENATE('NG Calcs'!$A25,".",'NG Calcs'!G$15),'Gas Futures'!$L:$L,0)) -> 3.037 | H25: =INDEX('Gas Futures'!$G:$G,MATCH(CONCATENATE('NG Calcs'!$A25,".",'NG Calcs'!H$15),'Gas Futures'!$L:$L,0)) -> 3.29 | I25: =INDEX('Gas Futures'!$G:$G,MATCH(CONCATENATE('NG Calcs'!$A25,".",'NG Calcs'!I$15),'Gas Futures'!$L:$L,0)) -> 3.704 | J25: =INDEX('Gas Futures'!$G:$G,MATCH(CONCATENATE('NG Calcs'!$A25,".",'NG Calcs'!J$15),'Gas Futures'!$L:$L,0)) -> 3.59 | K25: =INDEX('Gas Futures'!$G:$G,MATCH(CONCATENATE('NG Calcs'!$A25,".",'NG Calcs'!K$15),'Gas Futures'!$L:$L,0)) -> - | L25: =INDEX('Gas Futures'!$G:$G,MATCH(CONCATENATE('NG Calcs'!$A25,".",'NG Calcs'!L$15),'Gas Futures'!$L:$L,0)) -> - | M25: =INDEX('Gas Futures'!$G:$G,MATCH(CONCATENATE('NG Calcs'!$A25,".",'NG Calcs'!M$15),'Gas Futures'!$L:$L,0)) -> - | N25: =INDEX('Gas Futures'!$G:$G,MATCH(CONCATENATE('NG Calcs'!$A25,".",'NG Calcs'!N$15),'Gas Futures'!$L:$L,0)) -> - | ... Q25: =INDEX('Gas Futures'!$G:$G,MATCH(CONCATENATE('NG Calcs'!$A25,".",'NG Calcs'!Q$15),'Gas Futures'!$L:$L,0)) -> -
A26: 11 | B26: =INDEX('Henry Hub Historicals'!$B$4:$B$389,MATCH(CONCATENATE('NG Calcs'!$A26,".",'NG Calcs'!B$15),'Henry Hub Historicals'!$C$4:$C$389,0),1) -> 5.05 | C26: =INDEX('Henry Hub Historicals'!$B$4:$B$389,MATCH(CONCATENATE('NG Calcs'!$A26,".",'NG Calcs'!C$15),'Henry Hub Historicals'!$C$4:$C$389,0),1) -> 5.45 | D26: =INDEX('Henry Hub Historicals'!$B$4:$B$389,MATCH(CONCATENATE('NG Calcs'!$A26,".",'NG Calcs'!D$15),'Henry Hub Historicals'!$C$4:$C$389,0),1) -> 2.71 | E26: =INDEX('Henry Hub Historicals'!$B$4:$B$389,MATCH(CONCATENATE('NG Calcs'!$A26,".",'NG Calcs'!E$15),'Henry Hub Historicals'!$C$4:$C$389,0),1) -> 2.12 | F26: =INDEX('Henry Hub Historicals'!$B$4:$B$389,MATCH(CONCATENATE('NG Calcs'!$A26,".",'NG Calcs'!F$15),'Henry Hub Historicals'!$C$4:$C$389,0),1) -> 3.79 | G26: =INDEX('Gas Futures'!$G:$G,MATCH(CONCATENATE('NG Calcs'!$A26,".",'NG Calcs'!G$15),'Gas Futures'!$L:$L,0)) -> 3.169 | H26: =INDEX('Gas Futures'!$G:$G,MATCH(CONCATENATE('NG Calcs'!$A26,".",'NG Calcs'!H$15),'Gas Futures'!$L:$L,0)) -> 3.576 | I26: =INDEX('Gas Futures'!$G:$G,MATCH(CONCATENATE('NG Calcs'!$A26,".",'NG Calcs'!I$15),'Gas Futures'!$L:$L,0)) -> 3.875 | J26: =INDEX('Gas Futures'!$G:$G,MATCH(CONCATENATE('NG Calcs'!$A26,".",'NG Calcs'!J$15),'Gas Futures'!$L:$L,0)) -> 3.722 | K26: =INDEX('Gas Futures'!$G:$G,MATCH(CONCATENATE('NG Calcs'!$A26,".",'NG Calcs'!K$15),'Gas Futures'!$L:$L,0)) -> - | L26: =INDEX('Gas Futures'!$G:$G,MATCH(CONCATENATE('NG Calcs'!$A26,".",'NG Calcs'!L$15),'Gas Futures'!$L:$L,0)) -> - | M26: =INDEX('Gas Futures'!$G:$G,MATCH(CONCATENATE('NG Calcs'!$A26,".",'NG Calcs'!M$15),'Gas Futures'!$L:$L,0)) -> - | N26: =INDEX('Gas Futures'!$G:$G,MATCH(CONCATENATE('NG Calcs'!$A26,".",'NG Calcs'!N$15),'Gas Futures'!$L:$L,0)) -> - | ... Q26: =INDEX('Gas Futures'!$G:$G,MATCH(CONCATENATE('NG Calcs'!$A26,".",'NG Calcs'!Q$15),'Gas Futures'!$L:$L,0)) -> -
A27: 12 | B27: =INDEX('Henry Hub Historicals'!$B$4:$B$389,MATCH(CONCATENATE('NG Calcs'!$A27,".",'NG Calcs'!B$15),'Henry Hub Historicals'!$C$4:$C$389,0),1) -> 3.76 | C27: =INDEX('Henry Hub Historicals'!$B$4:$B$389,MATCH(CONCATENATE('NG Calcs'!$A27,".",'NG Calcs'!C$15),'Henry Hub Historicals'!$C$4:$C$389,0),1) -> 5.53 | D27: =INDEX('Henry Hub Historicals'!$B$4:$B$389,MATCH(CONCATENATE('NG Calcs'!$A27,".",'NG Calcs'!D$15),'Henry Hub Historicals'!$C$4:$C$389,0),1) -> 2.52 | E27: =INDEX('Henry Hub Historicals'!$B$4:$B$389,MATCH(CONCATENATE('NG Calcs'!$A27,".",'NG Calcs'!E$15),'Henry Hub Historicals'!$C$4:$C$389,0),1) -> 3.01 | F27: =INDEX('Henry Hub Historicals'!$B$4:$B$389,MATCH(CONCATENATE('NG Calcs'!$A27,".",'NG Calcs'!F$15),'Henry Hub Historicals'!$C$4:$C$389,0),1) -> 4.26 | G27: =INDEX('Gas Futures'!$G:$G,MATCH(CONCATENATE('NG Calcs'!$A27,".",'NG Calcs'!G$15),'Gas Futures'!$L:$L,0)) -> 3.504 | H27: =INDEX('Gas Futures'!$G:$G,MATCH(CONCATENATE('NG Calcs'!$A27,".",'NG Calcs'!H$15),'Gas Futures'!$L:$L,0)) -> 4.188 | I27: =INDEX('Gas Futures'!$G:$G,MATCH(CONCATENATE('NG Calcs'!$A27,".",'NG Calcs'!I$15),'Gas Futures'!$L:$L,0)) -> 4.409 | J27: =INDEX('Gas Futures'!$G:$G,MATCH(CONCATENATE('NG Calcs'!$A27,".",'NG Calcs'!J$15),'Gas Futures'!$L:$L,0)) -> - | K27: =INDEX('Gas Futures'!$G:$G,MATCH(CONCATENATE('NG Calcs'!$A27,".",'NG Calcs'!K$15),'Gas Futures'!$L:$L,0)) -> - | L27: =INDEX('Gas Futures'!$G:$G,MATCH(CONCATENATE('NG Calcs'!$A27,".",'NG Calcs'!L$15),'Gas Futures'!$L:$L,0)) -> - | M27: =INDEX('Gas Futures'!$G:$G,MATCH(CONCATENATE('NG Calcs'!$A27,".",'NG Calcs'!M$15),'Gas Futures'!$L:$L,0)) -> - | N27: =INDEX('Gas Futures'!$G:$G,MATCH(CONCATENATE('NG Calcs'!$A27,".",'NG Calcs'!N$15),'Gas Futures'!$L:$L,0)) -> - | ... Q27: =INDEX('Gas Futures'!$G:$G,MATCH(CONCATENATE('NG Calcs'!$A27,".",'NG Calcs'!Q$15),'Gas Futures'!$L:$L,0)) -> -
A29: key: | B29: henry hub historicals | C29: estim. | D29: futures
I30: uses ICF forecast (2030 base case Q4 2025: 3.97 real 2024$ = 4.07 in 2025$; entered in 2025$ to match the 2025-to-2012 deflator)
A31: Annual Average | B31: 2021 | C31: 2022 | D31: 2023 | E31: 2024 | F31: 2025 | G31: 2026 | H31: 2027 | I31: 2028 | J31: 2029 | K31: 2030 | L31: 2031 | M31: 2032 | N31: 2033 | O31: 2034 | P31: 2035 | Q31: 2036
B32: =SUMPRODUCT(B16:B27,$B$2:$B$13) -> 3.832171 | C32: =SUMPRODUCT(C16:C27,$B$2:$B$13) -> 6.308787 | D32: =SUMPRODUCT(D16:D27,$B$2:$B$13) -> 2.5521288 | E32: =SUMPRODUCT(E16:E27,$B$2:$B$13) -> 2.2151493 | F32: =SUMPRODUCT(F16:F27,$B$2:$B$13) -> 3.5775665 | G32: =SUMPRODUCT(G16:G27,$B$2:$B$13) -> 3.6433938 | H32: =SUMPRODUCT(H16:H27,$B$2:$B$13) -> 3.3041312 | I32: 4.07 | J32: 4.07 | K32: 4.07
A34: Henry Hub: Sector Price Ratio | B34: 2010 | C34: 2011 | D34: 2012 | E34: 2013 | F34: 2014 | G34: 2015 | H34: 2016 | I34: 2017 | J34: 2018 | K34: 2019 | L34: 2020 | M34: 2021 | N34: 2022 | O34: 2023 | P34: 2024 | Q34: 2025
A35: Residential | B35: =INDEX('NG Sector Price Historicals'!$K:$K,MATCH('NG Calcs'!B$34,'NG Sector Price Historicals'!$S:$S,0),1)/INDEX('Henry Hub Historicals'!$B$363:$B$390,MATCH('NG Calcs'!B$34,'Henry Hub Historicals'!$C$363:$C$390,0),1) -> 2.6064073 | C35: =INDEX('NG Sector Price Historicals'!$K:$K,MATCH('NG Calcs'!C$34,'NG Sector Price Historicals'!$S:$S,0),1)/INDEX('Henry Hub Historicals'!$B$363:$B$390,MATCH('NG Calcs'!C$34,'Henry Hub Historicals'!$C$363:$C$390,0),1) -> 2.7575 | D35: =INDEX('NG Sector Price Historicals'!$K:$K,MATCH('NG Calcs'!D$34,'NG Sector Price Historicals'!$S:$S,0),1)/INDEX('Henry Hub Historicals'!$B$363:$B$390,MATCH('NG Calcs'!D$34,'Henry Hub Historicals'!$C$363:$C$390,0),1) -> 3.8727273 | E35: =INDEX('NG Sector Price Historicals'!$K:$K,MATCH('NG Calcs'!E$34,'NG Sector Price Historicals'!$S:$S,0),1)/INDEX('Henry Hub Historicals'!$B$363:$B$390,MATCH('NG Calcs'!E$34,'Henry Hub Historicals'!$C$363:$C$390,0),1) -> 2.766756 | F35: =INDEX('NG Sector Price Historicals'!$K:$K,MATCH('NG Calcs'!F$34,'NG Sector Price Historicals'!$S:$S,0),1)/INDEX('Henry Hub Historicals'!$B$363:$B$390,MATCH('NG Calcs'!F$34,'Henry Hub Historicals'!$C$363:$C$390,0),1) -> 2.5102975 | G35: =INDEX('NG Sector Price Historicals'!$K:$K,MATCH('NG Calcs'!G$34,'NG Sector Price Historicals'!$S:$S,0),1)/INDEX('Henry Hub Historicals'!$B$363:$B$390,MATCH('NG Calcs'!G$34,'Henry Hub Historicals'!$C$363:$C$390,0),1) -> 3.9618321 | H35: =INDEX('NG Sector Price Historicals'!$K:$K,MATCH('NG Calcs'!H$34,'NG Sector Price Historicals'!$S:$S,0),1)/INDEX('Henry Hub Historicals'!$B$363:$B$390,MATCH('NG Calcs'!H$34,'Henry Hub Historicals'!$C$363:$C$390,0),1) -> 3.9880952 | I35: =INDEX('NG Sector Price Historicals'!$K:$K,MATCH('NG Calcs'!I$34,'NG Sector Price Historicals'!$S:$S,0),1)/INDEX('Henry Hub Historicals'!$B$363:$B$390,MATCH('NG Calcs'!I$34,'Henry Hub Historicals'!$C$363:$C$390,0),1) -> 3.6488294 | ... K35: =INDEX('NG Sector Price Historicals'!$K:$K,MATCH('NG Calcs'!K$34,'NG Sector Price Historicals'!$S:$S,0),1)/INDEX('Henry Hub Historicals'!$B$363:$B$390,MATCH('NG Calcs'!K$34,'Henry Hub Historicals'!$C$363:$C$390,0),1) -> 4.1054688 | L35: =INDEX('NG Sector Price Historicals'!$K:$K,MATCH('NG Calcs'!L$34,'NG Sector Price Historicals'!$S:$S,0),1)/INDEX('Henry Hub Historicals'!$B$363:$B$391,MATCH('NG Calcs'!L$34,'Henry Hub Historicals'!$C$363:$C$391,0),1) -> 5.3103448 | M35: =INDEX('NG Sector Price Historicals'!$K:$K,MATCH('NG Calcs'!M$34,'NG Sector Price Historicals'!$S:$S,0),1)/INDEX('Henry Hub Historicals'!$B$363:$B$391,MATCH('NG Calcs'!M$34,'Henry Hub Historicals'!$C$363:$C$391,0),1) -> 3.1311054 | N35: =INDEX('NG Sector Price Historicals'!$K:$K,MATCH('NG Calcs'!N$34,'NG Sector Price Historicals'!$S:$S,0),1)/INDEX('Henry Hub Historicals'!$B$363:$B$391,MATCH('NG Calcs'!N$34,'Henry Hub Historicals'!$C$363:$C$391,0),1) -> 2.2868217 | O35: =INDEX('NG Sector Price Historicals'!$K:$K,MATCH('NG Calcs'!O$34,'NG Sector Price Historicals'!$S:$S,0),1)/INDEX('Henry Hub Historicals'!$B$363:$B$391,MATCH('NG Calcs'!O$34,'Henry Hub Historicals'!$C$363:$C$391,0),1) -> 6.083004 | P35: =INDEX('NG Sector Price Historicals'!$K:$K,MATCH('NG Calcs'!P$34,'NG Sector Price Historicals'!$S:$S,0),1)/INDEX('Henry Hub Historicals'!$B$363:$B$391,MATCH('NG Calcs'!P$34,'Henry Hub Historicals'!$C$363:$C$391,0),1) -> 6.6210046 | Q35: =INDEX('NG Sector Price Historicals'!$K:$K,MATCH('NG Calcs'!Q$34,'NG Sector Price Historicals'!$S:$S,0),1)/INDEX('Henry Hub Historicals'!$B$363:$B$391,MATCH('NG Calcs'!Q$34,'Henry Hub Historicals'!$C$363:$C$391,0),1) -> 4.3579545
A36: Commercial | B36: =INDEX('NG Sector Price Historicals'!$M:$M,MATCH('NG Calcs'!B$34,'NG Sector Price Historicals'!$S:$S,0),1)/INDEX('Henry Hub Historicals'!$B363:$B$390,MATCH('NG Calcs'!B$34,'Henry Hub Historicals'!$C$363:$C$390,0),1) -> 2.1670481 | C36: =INDEX('NG Sector Price Historicals'!$M:$M,MATCH('NG Calcs'!C$34,'NG Sector Price Historicals'!$S:$S,0),1)/INDEX('Henry Hub Historicals'!$B363:$B$390,MATCH('NG Calcs'!C$34,'Henry Hub Historicals'!$C$363:$C$390,0),1) -> 2.2275 | D36: =INDEX('NG Sector Price Historicals'!$M:$M,MATCH('NG Calcs'!D$34,'NG Sector Price Historicals'!$S:$S,0),1)/INDEX('Henry Hub Historicals'!$B363:$B$390,MATCH('NG Calcs'!D$34,'Henry Hub Historicals'!$C$363:$C$390,0),1) -> 2.9454545 | E36: =INDEX('NG Sector Price Historicals'!$M:$M,MATCH('NG Calcs'!E$34,'NG Sector Price Historicals'!$S:$S,0),1)/INDEX('Henry Hub Historicals'!$B363:$B$390,MATCH('NG Calcs'!E$34,'Henry Hub Historicals'!$C$363:$C$390,0),1) -> 2.1662198 | F36: =INDEX('NG Sector Price Historicals'!$M:$M,MATCH('NG Calcs'!F$34,'NG Sector Price Historicals'!$S:$S,0),1)/INDEX('Henry Hub Historicals'!$B363:$B$390,MATCH('NG Calcs'!F$34,'Henry Hub Historicals'!$C$363:$C$390,0),1) -> 2.0366133 | G36: =INDEX('NG Sector Price Historicals'!$M:$M,MATCH('NG Calcs'!G$34,'NG Sector Price Historicals'!$S:$S,0),1)/INDEX('Henry Hub Historicals'!$B363:$B$390,MATCH('NG Calcs'!G$34,'Henry Hub Historicals'!$C$363:$C$390,0),1) -> 3.019084 | H36: =INDEX('NG Sector Price Historicals'!$M:$M,MATCH('NG Calcs'!H$34,'NG Sector Price Historicals'!$S:$S,0),1)/INDEX('Henry Hub Historicals'!$B363:$B$390,MATCH('NG Calcs'!H$34,'Henry Hub Historicals'!$C$363:$C$390,0),1) -> 2.8888889 | I36: =INDEX('NG Sector Price Historicals'!$M:$M,MATCH('NG Calcs'!I$34,'NG Sector Price Historicals'!$S:$S,0),1)/INDEX('Henry Hub Historicals'!$B363:$B$390,MATCH('NG Calcs'!I$34,'Henry Hub Historicals'!$C$363:$C$390,0),1) -> 2.6354515 | ... K36: =INDEX('NG Sector Price Historicals'!$M:$M,MATCH('NG Calcs'!K$34,'NG Sector Price Historicals'!$S:$S,0),1)/INDEX('Henry Hub Historicals'!$B363:$B$390,MATCH('NG Calcs'!K$34,'Henry Hub Historicals'!$C$363:$C$390,0),1) -> 2.9726562 | L36: =INDEX('NG Sector Price Historicals'!$M:$M,MATCH('NG Calcs'!L$34,'NG Sector Price Historicals'!$S:$S,0),1)/INDEX('Henry Hub Historicals'!$B$363:$B$391,MATCH('NG Calcs'!L$34,'Henry Hub Historicals'!$C$363:$C$391,0),1) -> 3.6847291 | M36: =INDEX('NG Sector Price Historicals'!$M:$M,MATCH('NG Calcs'!M$34,'NG Sector Price Historicals'!$S:$S,0),1)/INDEX('Henry Hub Historicals'!$B$363:$B$391,MATCH('NG Calcs'!M$34,'Henry Hub Historicals'!$C$363:$C$391,0),1) -> 2.2596401 | N36: =INDEX('NG Sector Price Historicals'!$M:$M,MATCH('NG Calcs'!N$34,'NG Sector Price Historicals'!$S:$S,0),1)/INDEX('Henry Hub Historicals'!$B$363:$B$391,MATCH('NG Calcs'!N$34,'Henry Hub Historicals'!$C$363:$C$391,0),1) -> 1.7550388 | O36: =INDEX('NG Sector Price Historicals'!$M:$M,MATCH('NG Calcs'!O$34,'NG Sector Price Historicals'!$S:$S,0),1)/INDEX('Henry Hub Historicals'!$B$363:$B$391,MATCH('NG Calcs'!O$34,'Henry Hub Historicals'!$C$363:$C$391,0),1) -> 4.3754941 | P36: =INDEX('NG Sector Price Historicals'!$M:$M,MATCH('NG Calcs'!P$34,'NG Sector Price Historicals'!$S:$S,0),1)/INDEX('Henry Hub Historicals'!$B$363:$B$391,MATCH('NG Calcs'!P$34,'Henry Hub Historicals'!$C$363:$C$391,0),1) -> 4.5981735 | Q36: =INDEX('NG Sector Price Historicals'!$M:$M,MATCH('NG Calcs'!Q$34,'NG Sector Price Historicals'!$S:$S,0),1)/INDEX('Henry Hub Historicals'!$B$363:$B$391,MATCH('NG Calcs'!Q$34,'Henry Hub Historicals'!$C$363:$C$391,0),1) -> 3.1164773
A37: Industry | B37: =INDEX('NG Sector Price Historicals'!$O:$O,MATCH('NG Calcs'!B$34,'NG Sector Price Historicals'!$S:$S,0),1)/INDEX('Henry Hub Historicals'!$B$363:$B$390,MATCH('NG Calcs'!B$34,'Henry Hub Historicals'!$C$363:$C$390,0),1) -> 1.2562929 | C37: =INDEX('NG Sector Price Historicals'!$O:$O,MATCH('NG Calcs'!C$34,'NG Sector Price Historicals'!$S:$S,0),1)/INDEX('Henry Hub Historicals'!$B$363:$B$390,MATCH('NG Calcs'!C$34,'Henry Hub Historicals'!$C$363:$C$390,0),1) -> 1.2825 | D37: =INDEX('NG Sector Price Historicals'!$O:$O,MATCH('NG Calcs'!D$34,'NG Sector Price Historicals'!$S:$S,0),1)/INDEX('Henry Hub Historicals'!$B$363:$B$390,MATCH('NG Calcs'!D$34,'Henry Hub Historicals'!$C$363:$C$390,0),1) -> 1.4109091 | E37: =INDEX('NG Sector Price Historicals'!$O:$O,MATCH('NG Calcs'!E$34,'NG Sector Price Historicals'!$S:$S,0),1)/INDEX('Henry Hub Historicals'!$B$363:$B$390,MATCH('NG Calcs'!E$34,'Henry Hub Historicals'!$C$363:$C$390,0),1) -> 1.2439678 | F37: =INDEX('NG Sector Price Historicals'!$O:$O,MATCH('NG Calcs'!F$34,'NG Sector Price Historicals'!$S:$S,0),1)/INDEX('Henry Hub Historicals'!$B$363:$B$390,MATCH('NG Calcs'!F$34,'Henry Hub Historicals'!$C$363:$C$390,0),1) -> 1.2860412 | G37: =INDEX('NG Sector Price Historicals'!$O:$O,MATCH('NG Calcs'!G$34,'NG Sector Price Historicals'!$S:$S,0),1)/INDEX('Henry Hub Historicals'!$B$363:$B$390,MATCH('NG Calcs'!G$34,'Henry Hub Historicals'!$C$363:$C$390,0),1) -> 1.5 | H37: =INDEX('NG Sector Price Historicals'!$O:$O,MATCH('NG Calcs'!H$34,'NG Sector Price Historicals'!$S:$S,0),1)/INDEX('Henry Hub Historicals'!$B$363:$B$390,MATCH('NG Calcs'!H$34,'Henry Hub Historicals'!$C$363:$C$390,0),1) -> 1.3928571 | I37: =INDEX('NG Sector Price Historicals'!$O:$O,MATCH('NG Calcs'!I$34,'NG Sector Price Historicals'!$S:$S,0),1)/INDEX('Henry Hub Historicals'!$B$363:$B$390,MATCH('NG Calcs'!I$34,'Henry Hub Historicals'!$C$363:$C$390,0),1) -> 1.3645485 | ... K37: =INDEX('NG Sector Price Historicals'!$O:$O,MATCH('NG Calcs'!K$34,'NG Sector Price Historicals'!$S:$S,0),1)/INDEX('Henry Hub Historicals'!$B$363:$B$390,MATCH('NG Calcs'!K$34,'Henry Hub Historicals'!$C$363:$C$390,0),1) -> 1.5234375 | L37: =INDEX('NG Sector Price Historicals'!$O:$O,MATCH('NG Calcs'!L$34,'NG Sector Price Historicals'!$S:$S,0),1)/INDEX('Henry Hub Historicals'!$B$363:$B$391,MATCH('NG Calcs'!L$34,'Henry Hub Historicals'!$C$363:$C$391,0),1) -> 1.635468 | M37: =INDEX('NG Sector Price Historicals'!$O:$O,MATCH('NG Calcs'!M$34,'NG Sector Price Historicals'!$S:$S,0),1)/INDEX('Henry Hub Historicals'!$B$363:$B$391,MATCH('NG Calcs'!M$34,'Henry Hub Historicals'!$C$363:$C$391,0),1) -> 1.3984576 | N37: =INDEX('NG Sector Price Historicals'!$O:$O,MATCH('NG Calcs'!N$34,'NG Sector Price Historicals'!$S:$S,0),1)/INDEX('Henry Hub Historicals'!$B$363:$B$391,MATCH('NG Calcs'!N$34,'Henry Hub Historicals'!$C$363:$C$391,0),1) -> 1.1922481 | O37: =INDEX('NG Sector Price Historicals'!$O:$O,MATCH('NG Calcs'!O$34,'NG Sector Price Historicals'!$S:$S,0),1)/INDEX('Henry Hub Historicals'!$B$363:$B$391,MATCH('NG Calcs'!O$34,'Henry Hub Historicals'!$C$363:$C$391,0),1) -> 1.7905138 | P37: =INDEX('NG Sector Price Historicals'!$O:$O,MATCH('NG Calcs'!P$34,'NG Sector Price Historicals'!$S:$S,0),1)/INDEX('Henry Hub Historicals'!$B$363:$B$391,MATCH('NG Calcs'!P$34,'Henry Hub Historicals'!$C$363:$C$391,0),1) -> 1.8584475 | Q37: =INDEX('NG Sector Price Historicals'!$O:$O,MATCH('NG Calcs'!Q$34,'NG Sector Price Historicals'!$S:$S,0),1)/INDEX('Henry Hub Historicals'!$B$363:$B$391,MATCH('NG Calcs'!Q$34,'Henry Hub Historicals'!$C$363:$C$391,0),1) -> 1.4857955
A38: Electricity | B38: =INDEX('NG Sector Price Historicals'!$R:$R,MATCH('NG Calcs'!B$34,'NG Sector Price Historicals'!$S:$S,0),1)/INDEX('Henry Hub Historicals'!$B$363:$B$390,MATCH('NG Calcs'!B$34,'Henry Hub Historicals'!$C$363:$C$390,0),1) -> 1.2059497 | C38: =INDEX('NG Sector Price Historicals'!$R:$R,MATCH('NG Calcs'!C$34,'NG Sector Price Historicals'!$S:$S,0),1)/INDEX('Henry Hub Historicals'!$B$363:$B$390,MATCH('NG Calcs'!C$34,'Henry Hub Historicals'!$C$363:$C$390,0),1) -> 1.2225 | D38: =INDEX('NG Sector Price Historicals'!$R:$R,MATCH('NG Calcs'!D$34,'NG Sector Price Historicals'!$S:$S,0),1)/INDEX('Henry Hub Historicals'!$B$363:$B$390,MATCH('NG Calcs'!D$34,'Henry Hub Historicals'!$C$363:$C$390,0),1) -> 1.2872727 | E38: =INDEX('NG Sector Price Historicals'!$R:$R,MATCH('NG Calcs'!E$34,'NG Sector Price Historicals'!$S:$S,0),1)/INDEX('Henry Hub Historicals'!$B$363:$B$390,MATCH('NG Calcs'!E$34,'Henry Hub Historicals'!$C$363:$C$390,0),1) -> 1.2037534 | F38: =INDEX('NG Sector Price Historicals'!$R:$R,MATCH('NG Calcs'!F$34,'NG Sector Price Historicals'!$S:$S,0),1)/INDEX('Henry Hub Historicals'!$B$363:$B$390,MATCH('NG Calcs'!F$34,'Henry Hub Historicals'!$C$363:$C$390,0),1) -> 1.187643 | G38: =INDEX('NG Sector Price Historicals'!$R:$R,MATCH('NG Calcs'!G$34,'NG Sector Price Historicals'!$S:$S,0),1)/INDEX('Henry Hub Historicals'!$B$363:$B$390,MATCH('NG Calcs'!G$34,'Henry Hub Historicals'!$C$363:$C$390,0),1) -> 1.2900763 | H38: =INDEX('NG Sector Price Historicals'!$R:$R,MATCH('NG Calcs'!H$34,'NG Sector Price Historicals'!$S:$S,0),1)/INDEX('Henry Hub Historicals'!$B$363:$B$390,MATCH('NG Calcs'!H$34,'Henry Hub Historicals'!$C$363:$C$390,0),1) -> 1.1865079 | I38: =INDEX('NG Sector Price Historicals'!$R:$R,MATCH('NG Calcs'!I$34,'NG Sector Price Historicals'!$S:$S,0),1)/INDEX('Henry Hub Historicals'!$B$363:$B$390,MATCH('NG Calcs'!I$34,'Henry Hub Historicals'!$C$363:$C$390,0),1) -> 1.173913 | ... K38: =INDEX('NG Sector Price Historicals'!$R:$R,MATCH('NG Calcs'!K$34,'NG Sector Price Historicals'!$S:$S,0),1)/INDEX('Henry Hub Historicals'!$B$363:$B$390,MATCH('NG Calcs'!K$34,'Henry Hub Historicals'!$C$363:$C$390,0),1) -> 1.1679688 | L38: =INDEX('NG Sector Price Historicals'!$R:$R,MATCH('NG Calcs'!L$34,'NG Sector Price Historicals'!$S:$S,0),1)/INDEX('Henry Hub Historicals'!$B$363:$B$391,MATCH('NG Calcs'!L$34,'Henry Hub Historicals'!$C$363:$C$391,0),1) -> 1.226601 | M38: =INDEX('NG Sector Price Historicals'!$R:$R,MATCH('NG Calcs'!M$34,'NG Sector Price Historicals'!$S:$S,0),1)/INDEX('Henry Hub Historicals'!$B$363:$B$391,MATCH('NG Calcs'!M$34,'Henry Hub Historicals'!$C$363:$C$391,0),1) -> 1.3958869 | N38: =INDEX('NG Sector Price Historicals'!$R:$R,MATCH('NG Calcs'!N$34,'NG Sector Price Historicals'!$S:$S,0),1)/INDEX('Henry Hub Historicals'!$B$363:$B$391,MATCH('NG Calcs'!N$34,'Henry Hub Historicals'!$C$363:$C$391,0),1) -> 1.1643411 | O38: =INDEX('NG Sector Price Historicals'!$R:$R,MATCH('NG Calcs'!O$34,'NG Sector Price Historicals'!$S:$S,0),1)/INDEX('Henry Hub Historicals'!$B$363:$B$391,MATCH('NG Calcs'!O$34,'Henry Hub Historicals'!$C$363:$C$391,0),1) -> 1.3833992 | P38: =INDEX('NG Sector Price Historicals'!$R:$R,MATCH('NG Calcs'!P$34,'NG Sector Price Historicals'!$S:$S,0),1)/INDEX('Henry Hub Historicals'!$B$363:$B$391,MATCH('NG Calcs'!P$34,'Henry Hub Historicals'!$C$363:$C$391,0),1) -> 1.3105023 | Q38: =INDEX('NG Sector Price Historicals'!$R:$R,MATCH('NG Calcs'!Q$34,'NG Sector Price Historicals'!$S:$S,0),1)/INDEX('Henry Hub Historicals'!$B$363:$B$391,MATCH('NG Calcs'!Q$34,'Henry Hub Historicals'!$C$363:$C$391,0),1) -> 1.1420455
A39: Transportation | B39: =INDEX('NG Sector Price Historicals'!$K:$K,MATCH('NG Calcs'!B$34,'NG Sector Price Historicals'!$S:$S,0),1)/INDEX('Henry Hub Historicals'!$B$363:$B$390,MATCH('NG Calcs'!B$34,'Henry Hub Historicals'!$C$363:$C$390,0),1) -> 2.6064073 | C39: =INDEX('NG Sector Price Historicals'!$K:$K,MATCH('NG Calcs'!C$34,'NG Sector Price Historicals'!$S:$S,0),1)/INDEX('Henry Hub Historicals'!$B$363:$B$390,MATCH('NG Calcs'!C$34,'Henry Hub Historicals'!$C$363:$C$390,0),1) -> 2.7575 | D39: =INDEX('NG Sector Price Historicals'!$K:$K,MATCH('NG Calcs'!D$34,'NG Sector Price Historicals'!$S:$S,0),1)/INDEX('Henry Hub Historicals'!$B$363:$B$390,MATCH('NG Calcs'!D$34,'Henry Hub Historicals'!$C$363:$C$390,0),1) -> 3.8727273 | E39: =INDEX('NG Sector Price Historicals'!$K:$K,MATCH('NG Calcs'!E$34,'NG Sector Price Historicals'!$S:$S,0),1)/INDEX('Henry Hub Historicals'!$B$363:$B$390,MATCH('NG Calcs'!E$34,'Henry Hub Historicals'!$C$363:$C$390,0),1) -> 2.766756 | F39: =INDEX('NG Sector Price Historicals'!$K:$K,MATCH('NG Calcs'!F$34,'NG Sector Price Historicals'!$S:$S,0),1)/INDEX('Henry Hub Historicals'!$B$363:$B$390,MATCH('NG Calcs'!F$34,'Henry Hub Historicals'!$C$363:$C$390,0),1) -> 2.5102975 | G39: =INDEX('NG Sector Price Historicals'!$K:$K,MATCH('NG Calcs'!G$34,'NG Sector Price Historicals'!$S:$S,0),1)/INDEX('Henry Hub Historicals'!$B$363:$B$390,MATCH('NG Calcs'!G$34,'Henry Hub Historicals'!$C$363:$C$390,0),1) -> 3.9618321 | H39: =INDEX('NG Sector Price Historicals'!$K:$K,MATCH('NG Calcs'!H$34,'NG Sector Price Historicals'!$S:$S,0),1)/INDEX('Henry Hub Historicals'!$B$363:$B$390,MATCH('NG Calcs'!H$34,'Henry Hub Historicals'!$C$363:$C$390,0),1) -> 3.9880952 | I39: =INDEX('NG Sector Price Historicals'!$K:$K,MATCH('NG Calcs'!I$34,'NG Sector Price Historicals'!$S:$S,0),1)/INDEX('Henry Hub Historicals'!$B$363:$B$390,MATCH('NG Calcs'!I$34,'Henry Hub Historicals'!$C$363:$C$390,0),1) -> 3.6488294 | ... K39: =INDEX('NG Sector Price Historicals'!$K:$K,MATCH('NG Calcs'!K$34,'NG Sector Price Historicals'!$S:$S,0),1)/INDEX('Henry Hub Historicals'!$B$363:$B$390,MATCH('NG Calcs'!K$34,'Henry Hub Historicals'!$C$363:$C$390,0),1) -> 4.1054688 | L39: =INDEX('NG Sector Price Historicals'!$K:$K,MATCH('NG Calcs'!L$34,'NG Sector Price Historicals'!$S:$S,0),1)/INDEX('Henry Hub Historicals'!$B$363:$B$391,MATCH('NG Calcs'!L$34,'Henry Hub Historicals'!$C$363:$C$391,0),1) -> 5.3103448 | M39: =INDEX('NG Sector Price Historicals'!$K:$K,MATCH('NG Calcs'!M$34,'NG Sector Price Historicals'!$S:$S,0),1)/INDEX('Henry Hub Historicals'!$B$363:$B$391,MATCH('NG Calcs'!M$34,'Henry Hub Historicals'!$C$363:$C$391,0),1) -> 3.1311054 | N39: =INDEX('NG Sector Price Historicals'!$K:$K,MATCH('NG Calcs'!N$34,'NG Sector Price Historicals'!$S:$S,0),1)/INDEX('Henry Hub Historicals'!$B$363:$B$391,MATCH('NG Calcs'!N$34,'Henry Hub Historicals'!$C$363:$C$391,0),1) -> 2.2868217 | O39: =INDEX('NG Sector Price Historicals'!$K:$K,MATCH('NG Calcs'!O$34,'NG Sector Price Historicals'!$S:$S,0),1)/INDEX('Henry Hub Historicals'!$B$363:$B$391,MATCH('NG Calcs'!O$34,'Henry Hub Historicals'!$C$363:$C$391,0),1) -> 6.083004 | P39: =INDEX('NG Sector Price Historicals'!$K:$K,MATCH('NG Calcs'!P$34,'NG Sector Price Historicals'!$S:$S,0),1)/INDEX('Henry Hub Historicals'!$B$363:$B$391,MATCH('NG Calcs'!P$34,'Henry Hub Historicals'!$C$363:$C$391,0),1) -> 6.6210046 | Q39: =INDEX('NG Sector Price Historicals'!$K:$K,MATCH('NG Calcs'!Q$34,'NG Sector Price Historicals'!$S:$S,0),1)/INDEX('Henry Hub Historicals'!$B$363:$B$391,MATCH('NG Calcs'!Q$34,'Henry Hub Historicals'!$C$363:$C$391,0),1) -> 4.3579545
A41: Historical and Future Prices by Sector | B41: 2021 | C41: 2022 | D41: 2023 | E41: 2024 | F41: 2025 | G41: 2026 | H41: 2027 | I41: 2028 | J41: 2029 | K41: 2030
A42: Residential | B42: =INDEX('NG Sector Price Historicals'!$K:$K,MATCH(B$41,'NG Sector Price Historicals'!$S:$S,0),1)*About!$A$134 -> 8.914737 | C42: =INDEX('NG Sector Price Historicals'!$K:$K,MATCH(C$41,'NG Sector Price Historicals'!$S:$S,0),1)*About!$A$134 -> 10.795761 | D42: =INDEX('NG Sector Price Historicals'!$K:$K,MATCH(D$41,'NG Sector Price Historicals'!$S:$S,0),1)*About!$A$134 -> 11.264187 | E42: =INDEX('NG Sector Price Historicals'!$K:$K,MATCH(E$41,'NG Sector Price Historicals'!$S:$S,0),1)*About!$A$134 -> 10.612782 | F42: =AVERAGE($M35:$Q35)*F$32*About!$A$133 -> 11.470116 | G42: =AVERAGE($M35:$Q35)*G$32*About!$A$133 -> 11.681166 | H42: =AVERAGE($M35:$Q35)*H$32*About!$A$133 -> 10.593449 | I42: =AVERAGE($M35:$Q35)*I$32*About!$A$133 -> 13.048918 | J42: =AVERAGE($M35:$Q35)*J$32*About!$A$133 -> 13.048918 | K42: =AVERAGE($M35:$Q35)*K$32*About!$A$133 -> 13.048918
A43: Commercial | B43: =INDEX('NG Sector Price Historicals'!$M:$M,MATCH(B$41,'NG Sector Price Historicals'!$S:$S,0),1)*About!$A$134 -> 6.4335417 | C43: =INDEX('NG Sector Price Historicals'!$M:$M,MATCH(C$41,'NG Sector Price Historicals'!$S:$S,0),1)*About!$A$134 -> 8.2852892 | D43: =INDEX('NG Sector Price Historicals'!$M:$M,MATCH(D$41,'NG Sector Price Historicals'!$S:$S,0),1)*About!$A$134 -> 8.1023102 | E43: =INDEX('NG Sector Price Historicals'!$M:$M,MATCH(E$41,'NG Sector Price Historicals'!$S:$S,0),1)*About!$A$134 -> 7.3703942 | F43: =AVERAGE($M36:$Q36)*F$32*About!$A$133 -> 8.2173087 | G43: =AVERAGE($M36:$Q36)*G$32*About!$A$133 -> 8.3685074 | H43: =AVERAGE($M36:$Q36)*H$32*About!$A$133 -> 7.5892556 | I43: =AVERAGE($M36:$Q36)*I$32*About!$A$133 -> 9.3483787 | J43: =AVERAGE($M36:$Q36)*J$32*About!$A$133 -> 9.3483787 | K43: =AVERAGE($M36:$Q36)*K$32*About!$A$133 -> 9.3483787
A44: Industry | B44: =INDEX('NG Sector Price Historicals'!$O:$O,MATCH(B$41,'NG Sector Price Historicals'!$S:$S,0),1)*About!$A$134 -> 3.9816231 | C44: =INDEX('NG Sector Price Historicals'!$O:$O,MATCH(C$41,'NG Sector Price Historicals'!$S:$S,0),1)*About!$A$134 -> 5.6284341 | D44: =INDEX('NG Sector Price Historicals'!$O:$O,MATCH(D$41,'NG Sector Price Historicals'!$S:$S,0),1)*About!$A$134 -> 3.3155795 | E44: =INDEX('NG Sector Price Historicals'!$O:$O,MATCH(E$41,'NG Sector Price Historicals'!$S:$S,0),1)*About!$A$134 -> 2.9788981 | F44: =AVERAGE($M37:$Q37)*F$32*About!$A$133 -> 3.941832 | G44: =AVERAGE($M37:$Q37)*G$32*About!$A$133 -> 4.0143618 | H44: =AVERAGE($M37:$Q37)*H$32*About!$A$133 -> 3.6405558 | I44: =AVERAGE($M37:$Q37)*I$32*About!$A$133 -> 4.4844048 | J44: =AVERAGE($M37:$Q37)*J$32*About!$A$133 -> 4.4844048 | K44: =AVERAGE($M37:$Q37)*K$32*About!$A$133 -> 4.4844048
A45: Electricity | B45: =INDEX('NG Sector Price Historicals'!$R:$R,MATCH(B$41,'NG Sector Price Historicals'!$S:$S,0),1)*About!$A$134 -> 3.9743039 | C45: =INDEX('NG Sector Price Historicals'!$R:$R,MATCH(C$41,'NG Sector Price Historicals'!$S:$S,0),1)*About!$A$134 -> 5.4966892 | D45: =INDEX('NG Sector Price Historicals'!$R:$R,MATCH(D$41,'NG Sector Price Historicals'!$S:$S,0),1)*About!$A$134 -> 2.561706 | E45: =INDEX('NG Sector Price Historicals'!$R:$R,MATCH(E$41,'NG Sector Price Historicals'!$S:$S,0),1)*About!$A$134 -> 2.1005989 | F45: =AVERAGE($M38:$Q38)*F$32*About!$A$133 -> 3.2635777 | G45: =AVERAGE($M38:$Q38)*G$32*About!$A$133 -> 3.3236276 | H45: =AVERAGE($M38:$Q38)*H$32*About!$A$133 -> 3.0141408 | I45: =AVERAGE($M38:$Q38)*I$32*About!$A$133 -> 3.7127923 | J45: =AVERAGE($M38:$Q38)*J$32*About!$A$133 -> 3.7127923 | K45: =AVERAGE($M38:$Q38)*K$32*About!$A$133 -> 3.7127923
A46: Transportation | B46: =B42 -> 8.914737 | C46: =C42 -> 10.795761 | D46: =D42 -> 11.264187 | E46: =E42 -> 10.612782 | F46: =AVERAGE($M39:$Q39)*F$32*About!$A$133 -> 11.470116 | G46: =AVERAGE($M39:$Q39)*G$32*About!$A$133 -> 11.681166 | H46: =AVERAGE($M39:$Q39)*H$32*About!$A$133 -> 10.593449 | I46: =AVERAGE($M39:$Q39)*I$32*About!$A$133 -> 13.048918 | J46: =AVERAGE($M39:$Q39)*J$32*About!$A$133 -> 13.048918 | K46: =AVERAGE($M39:$Q39)*K$32*About!$A$133 -> 13.048918

Sheet AEO 2025 Table 2 - High Cost
B1: Sector and Source | C1: 2024 | D1: 2025 | E1: 2026 | F1: 2027 | G1: 2028 | H1: 2029 | I1: 2030 | J1: 2031 | K1: 2032 | L1: 2033 | M1: 2034 | N1: 2035 | O1: 2036 | P1: 2037 | Q1: 2038 | R1: 2039 | S1: 2040 | T1: 2041 | U1: 2042 | V1: 2043 | W1: 2044 | X1: 2045 | Y1: 2046 | Z1: 2047 | AA1: 2048 | AB1: 2049 | AC1: 2050 | AD1: 2024-2050
B5: highztc.d032125b
C7: Report | D7: Annual Energy Outlook 2025
C8: Scenario | D8: highztc | F8: High Zero-Carbon Technology Cost
C9: Datekey | D9: d032125b
C10: Release Date | E10: April 2025
B11: 2. Energy Consumption by Sector and Source
B12: (quadrillion Btu, unless otherwise noted)
AD13: Avg Annual Change
B14: Sector and Source | C14: 2024 | D14: 2025 | E14: 2026 | F14: 2027 | G14: 2028 | H14: 2029 | I14: 2030 | J14: 2031 | K14: 2032 | L14: 2033 | M14: 2034 | N14: 2035 | O14: 2036 | P14: 2037 | Q14: 2038 | R14: 2039 | S14: 2040 | T14: 2041 | U14: 2042 | V14: 2043 | W14: 2044 | X14: 2045 | Y14: 2046 | Z14: 2047 | AA14: 2048 | AB14: 2049 | AC14: 2050 | AD14: 2024-2050
B16: Residential
A17: QUA000:ca_LiquefiedPetr | B17: Propane | C17: 0.44558504 | D17: 0.4807111 | E17: 0.47766578 | F17: 0.47374311 | G17: 0.46951377 | H17: 0.46448603 | I17: 0.4588486 | J17: 0.45316347 | K17: 0.44746599 | L17: 0.44225794 | M17: 0.43704322 | N17: 0.43268678 | O17: 0.42906451 | P17: 0.42608413 | Q17: 0.42352915 | R17: 0.42134741 | S17: 0.41947559 | T17: 0.41770104 | U17: 0.41602927 | V17: 0.41437557 | W17: 0.4128958 | X17: 0.4115926 | Y17: 0.41062033 | Z17: 0.40981495 | AA17: 0.40911356 | AB17: 0.4083488 | AC17: 0.40728819 | AD17: -0.0034504601
A18: QUA000:ca_DistillateFue | B18: Distillate Fuel Oil 1/ | C18: 0.44587705 | D18: 0.47523534 | E18: 0.46847582 | F18: 0.45941919 | G18: 0.44931555 | H18: 0.4391039 | I18: 0.42929116 | J18: 0.42082229 | K18: 0.41354707 | L18: 0.40717539 | M18: 0.40077126 | N18: 0.39471599 | O18: 0.38887388 | P18: 0.3830736 | Q18: 0.37743908 | R18: 0.37194869 | S18: 0.36648339 | T18: 0.36104238 | U18: 0.35572892 | V18: 0.35056219 | W18: 0.34526661 | X18: 0.34054413 | Y18: 0.33597279 | Z18: 0.33159229 | AA18: 0.32734603 | AB18: 0.32318777 | AC18: 0.31897494 | AD18: -0.012799332
A19: QUA000:ca_PetroleumSubt | B19: Petroleum and Other Liquids Subtotal | C19: 0.89146209 | D19: 0.95594645 | E19: 0.94614166 | F19: 0.93316227 | G19: 0.91882932 | H19: 0.90358996 | I19: 0.88813972 | J19: 0.87398577 | K19: 0.86101311 | L19: 0.84943336 | M19: 0.83781451 | N19: 0.82740277 | O19: 0.81793839 | P19: 0.80915773 | Q19: 0.80096817 | R19: 0.79329604 | S19: 0.78595895 | T19: 0.77874345 | U19: 0.7717582 | V19: 0.76493776 | W19: 0.75816238 | X19: 0.75213677 | Y19: 0.74659312 | Z19: 0.74140728 | AA19: 0.73645955 | AB19: 0.73153651 | AC19: 0.72626323 | AD19: -0.0078517203
A20: QUA000:ca_NaturalGas | B20: Natural Gas | C20: 4.6034398 | D20: 4.9662085 | E20: 4.9995217 | F20: 5.0195174 | G20: 5.0296082 | H20: 5.016108 | I20: 4.9945207 | J20: 4.9609523 | K20: 4.9130726 | L20: 4.8717971 | M20: 4.830965 | N20: 4.8000855 | O20: 4.776269 | P20: 4.7566199 | Q20: 4.7380295 | R20: 4.720499 | S20: 4.700645 | T20: 4.6752086 | U20: 4.6475148 | V20: 4.6186996 | W20: 4.5911007 | X20: 4.5650725 | Y20: 4.5387297 | Z20: 4.5131388 | AA20: 4.4889293 | AB20: 4.4652133 | AC20: 4.4413047 | AD20: -0.0013781121
A21: QUA000:ca_RenewableEner | B21: Renewable Energy 2/ | C21: 0.35758355 | D21: 0.36509404 | E21: 0.35265353 | F21: 0.34729543 | G21: 0.34571755 | H21: 0.34550309 | I21: 0.34529042 | J21: 0.34249941 | K21: 0.33729544 | L21: 0.33283803 | M21: 0.32823426 | N21: 0.32396501 | O21: 0.31938115 | P21: 0.31522074 | Q21: 0.3110182 | R21: 0.30656409 | S21: 0.30218205 | T21: 0.29810008 | U21: 0.29437715 | V21: 0.29094973 | W21: 0.28853625 | X21: 0.28493458 | Y21: 0.2813772 | Z21: 0.27769217 | AA21: 0.27387229 | AB21: 0.27057177 | AC21: 0.26805013 | AD21: -0.011023218
A22: QUA000:ca_Electricity | B22: Purchased Electricity for Residential Use 3/ | C22: 5.0973949 | D22: 5.0153503 | E22: 5.0563092 | F22: 5.1038275 | G22: 5.1289206 | H22: 5.1203732 | I22: 5.0907845 | J22: 5.0511241 | K22: 5.0159101 | L22: 4.9880023 | M22: 4.9690661 | N22: 4.9705262 | O22: 4.9866858 | P22: 5.0111814 | Q22: 5.0332589 | R22: 5.06003 | S22: 5.0864983 | T22: 5.1130481 | U22: 5.1415405 | V22: 5.1727648 | W22: 5.2034469 | X22: 5.2331009 | Y22: 5.2620907 | Z22: 5.2905922 | AA22: 5.3189726 | AB22: 5.3488092 | AC22: 5.3785472 | AD22: 0.0020670829
A23: QUA000:ca_DeliveredEner | B23: Delivered Energy | C23: 10.949879 | D23: 11.302598 | E23: 11.354626 | F23: 11.403802 | G23: 11.423075 | H23: 11.385574 | I23: 11.318736 | J23: 11.22856 | K23: 11.127291 | L23: 11.04207 | M23: 10.96608 | N23: 10.921979 | O23: 10.900274 | P23: 10.892181 | Q23: 10.883274 | R23: 10.880389 | S23: 10.875284 | T23: 10.865099 | U23: 10.855191 | V23: 10.847352 | W23: 10.841247 | X23: 10.835244 | Y23: 10.828792 | Z23: 10.82283 | AA23: 10.818233 | AB23: 10.81613 | AC23: 10.814168 | AD23: -0.00047954859
A24: QUA000:ca_ElectricityRe | B24: Electricity-Related Losses 4/ | C24: 7.2451472 | D24: 6.9122014 | E24: 6.553731 | F24: 6.3626113 | G24: 6.2520647 | H24: 6.1319804 | I24: 5.8515506 | J24: 5.6203084 | K24: 5.2200708 | L24: 5.0221 | M24: 4.822125 | N24: 4.611793 | O24: 4.4298358 | P24: 4.219049 | Q24: 4.1036115 | R24: 3.8784831 | S24: 3.8286736 | T24: 3.840003 | U24: 3.8532758 | V24: 3.8497481 | W24: 3.8522744 | X24: 3.8311646 | Y24: 3.808954 | Z24: 3.7996809 | AA24: 3.8008647 | AB24: 3.8104854 | AC24: 3.7907338 | AD24: -0.024606518
A25: QUA000:ca_Total | B25: Total | C25: 18.195026 | D25: 18.2148 | E25: 17.908356 | F25: 17.766413 | G25: 17.67514 | H25: 17.517555 | I25: 17.170286 | J25: 16.848869 | K25: 16.347363 | L25: 16.064171 | M25: 15.788204 | N25: 15.533772 | O25: 15.330111 | P25: 15.111231 | Q25: 14.986885 | R25: 14.758872 | S25: 14.703958 | T25: 14.705102 | U25: 14.708467 | V25: 14.6971 | W25: 14.693521 | X25: 14.666409 | Y25: 14.637746 | Z25: 14.622511 | AA25: 14.619099 | AB25: 14.626616 | AC25: 14.604902 | AD25: -0.0084178711
B27: Commercial
A28: QUA000:da_LiquefiedPetr | B28: Propane | C28: 0.2035272 | D28: 0.20703572 | E28: 0.21118894 | F28: 0.21576019 | G28: 0.22055462 | H28: 0.22461802 | I28: 0.22857586 | J28: 0.23246326 | K28: 0.23636471 | L28: 0.24030466 | M28: 0.24426264 | N28: 0.24820276 | O28: 0.25208464 | P28: 0.25588843 | Q28: 0.2596201 | R28: 0.26329187 | S28: 0.26691687 | T28: 0.2705082 | U28: 0.27407426 | V28: 0.27762291 | W28: 0.28116336 | X28: 0.2847046 | Y28: 0.2882545 | Z28: 0.29181975 | AA28: 0.29540417 | AB28: 0.29900929 | AC28: 0.30263504 | AD28: 0.015375777
A29: QUA000:da_MotorGasoline | B29: Motor Gasoline 5/ | C29: 0.4331153 | D29: 0.43885848 | E29: 0.445824 | F29: 0.45365909 | G29: 0.46195975 | H29: 0.47047722 | I29: 0.47877753 | J29: 0.48693374 | K29: 0.4951213 | L29: 0.50339103 | M29: 0.51170015 | N29: 0.51997435 | O29: 0.52812964 | P29: 0.53612465 | Q29: 0.54397178 | R29: 0.55169612 | S29: 0.55932534 | T29: 0.56688637 | U29: 0.57439673 | V29: 0.58187264 | W29: 0.58933347 | X29: 0.59679765 | Y29: 0.60428178 | Z29: 0.6117996 | AA29: 0.61935914 | AB29: 0.62696373 | AC29: 0.6346131 | AD29: 0.01480122
A30: QUA000:da_Kerosene | B30: Kerosene | C30: 0.0021011999 | D30: 0.0016626001 | E30: 0.0030831252 | F30: 0.0030999552 | G30: 0.0029596949 | H30: 0.0024966884 | I30: 0.0021045038 | J30: 0.0020330893 | K30: 0.0020650488 | L30: 0.0018904903 | M30: 0.0018184644 | N30: 0.0017056094 | O30: 0.001672694 | P30: 0.0015356261 | Q30: 0.0014303378 | R30: 0.0013767034 | S30: 0.0012748687 | T30: 0.0011420497 | U30: 0.0010247794 | V30: 0.00088782085 | W30: 0.00068789633 | X30: 0.00070742279 | Y30: 0.00067288999 | Z30: 0.00066217227 | AA30: 0.00066973234 | AB30: 0.00064883055 | AC30: 0.00060963305 | AD30: -0.046477792
A31: QUA000:da_DistillateFue | B31: Distillate Fuel Oil | C31: 0.30828425 | D31: 0.31653073 | E31: 0.32009089 | F31: 0.32202315 | G31: 0.32281336 | H31: 0.32287106 | I31: 0.32285032 | J31: 0.32228237 | K31: 0.32165998 | L31: 0.32047915 | M31: 0.3191781 | N31: 0.31771559 | O31: 0.31651142 | P31: 0.3150748 | Q31: 0.31380537 | R31: 0.31265193 | S31: 0.3113957 | T31: 0.31006923 | U31: 0.3086105 | V31: 0.30712631 | W31: 0.30511072 | X31: 0.30393124 | Y31: 0.30281207 | Z31: 0.30214378 | AA31: 0.30171916 | AB31: 0.30106044 | AC31: 0.30012986 | AD31: -0.0010305074
A32: QUA000:da_ResidualFuel | B32: Residual Fuel Oil | C32: 0.0025500001 | D32: 0.00098608341 | E32: 0.00098587933 | F32: 0.0010556977 | G32: 0.0011317286 | H32: 0.0011565251 | I32: 0.0011804914 | J32: 0.0012038745 | K32: 0.0012272617 | L32: 0.0012508213 | M32: 0.0012744097 | N32: 0.0012977807 | O32: 0.0013206588 | P32: 0.0013429098 | Q32: 0.0013645777 | R32: 0.0013857484 | S32: 0.0014065141 | T32: 0.0014269652 | U32: 0.0014471601 | V32: 0.0014671535 | W32: 0.0014870083 | X32: 0.0015067848 | Y32: 0.0015265369 | Z32: 0.0015463087 | AA32: 0.0015661255 | AB32: 0.0015859975 | AC32: 0.0016059229 | AD32: -0.017627205
A33: QUA000:da_PetroleumSubt | B33: Petroleum and Other Liquids Subtotal | C33: 0.94957799 | D33: 0.96507359 | E33: 0.98117286 | F33: 0.99559814 | G33: 1.0094192 | H33: 1.0216196 | I33: 1.0334888 | J33: 1.0449163 | K33: 1.0564384 | L33: 1.0673162 | M33: 1.0782337 | N33: 1.088896 | O33: 1.099719 | P33: 1.1099665 | Q33: 1.1201922 | R33: 1.1304024 | S33: 1.1403192 | T33: 1.1500328 | U33: 1.1595534 | V33: 1.1689769 | W33: 1.1777825 | X33: 1.1876478 | Y33: 1.1975477 | Z33: 1.2079716 | AA33: 1.2187183 | AB33: 1.2292681 | AC33: 1.2395935 | AD33: 0.010303532
A34: QUA000:da_NaturalGas | B34: Natural Gas | C34: 3.4267042 | D34: 3.6111779 | E34: 3.6454482 | F34: 3.6524363 | G34: 3.6438868 | H34: 3.6439722 | I34: 3.6367579 | J34: 3.632056 | K34: 3.6185274 | L34: 3.6024525 | M34: 3.5903449 | N34: 3.5876603 | O34: 3.5944943 | P34: 3.6066058 | Q34: 3.6202919 | R34: 3.6363382 | S34: 3.6494699 | T34: 3.6574109 | U34: 3.6625066 | V34: 3.666111 | W34: 3.6724765 | X34: 3.6793599 | Y34: 3.6838069 | Z34: 3.6905289 | AA34: 3.6991925 | AB34: 3.7067688 | AC34: 3.7131815 | AD34: 0.0030928553
A35: QUA000:da_Coal | B35: Coal | C35: 0.012117596 | D35: 0.012670438 | E35: 0.016739044 | F35: 0.017261488 | G35: 0.018486682 | H35: 0.017757935 | I35: 0.018492531 | J35: 0.019201657 | K35: 0.020130698 | L35: 0.020423077 | M35: 0.021233587 | N35: 0.021900656 | O35: 0.022011163 | P35: 0.022176119 | Q35: 0.021844823 | R35: 0.02226104 | S35: 0.022491174 | T35: 0.022289122 | U35: 0.022297949 | V35: 0.02214068 | W35: 0.021983474 | X35: 0.021867977 | Y35: 0.021567658 | Z35: 0.021553779 | AA35: 0.021544712 | AB35: 0.021556655 | AC35: 0.021255117 | AD35: 0.021848293
A36: QUA000:da_RenewableEner | B36: Renewable Energy 6/ | C36: 0.158104 | D36: 0.15810402 | E36: 0.15810402 | F36: 0.15810402 | G36: 0.158104 | H36: 0.15810402 | I36: 0.15810405 | J36: 0.158104 | K36: 0.15810402 | L36: 0.15810402 | M36: 0.15810402 | N36: 0.15810402 | O36: 0.15810402 | P36: 0.15810405 | Q36: 0.15810402 | R36: 0.15810402 | S36: 0.15810402 | T36: 0.15810405 | U36: 0.15810399 | V36: 0.15810405 | W36: 0.15810402 | X36: 0.15810399 | Y36: 0.15810405 | Z36: 0.15810402 | AA36: 0.15810399 | AB36: 0.15810402 | AC36: 0.15810396 | AD36: -1.0874899e-08
A37: QUA000:da_Electricity | B37: Purchased Electricity for Commercial Use 3/ | C37: 4.7493382 | D37: 4.8217502 | E37: 4.7823405 | F37: 4.8266182 | G37: 4.8610983 | H37: 4.9273343 | I37: 4.9671345 | J37: 5.0036864 | K37: 5.0454721 | L37: 5.0842228 | M37: 5.1357765 | N37: 5.2029762 | O37: 5.2810092 | P37: 5.3637099 | Q37: 5.4409227 | R37: 5.5250654 | S37: 5.6098452 | T37: 5.6957569 | U37: 5.78301 | V37: 5.8726916 | W37: 5.9649363 | X37: 6.0587931 | Y37: 6.1554279 | Z37: 6.2532177 | AA37: 6.3540168 | AB37: 6.4577465 | AC37: 6.5644989 | AD37: 0.012526691
A38: QUA000:da_DeliveredEner | B38: Delivered Energy | C38: 9.2958422 | D38: 9.568778 | E38: 9.5838041 | F38: 9.6500168 | G38: 9.6909933 | H38: 9.7687874 | I38: 9.8139772 | J38: 9.8579636 | K38: 9.8986721 | L38: 9.932518 | M38: 9.9836922 | N38: 10.059537 | O38: 10.155337 | P38: 10.260563 | Q38: 10.361356 | R38: 10.472172 | S38: 10.58023 | T38: 10.683596 | U38: 10.785473 | V38: 10.888024 | W38: 10.995282 | X38: 11.105772 | Y38: 11.216454 | Z38: 11.331375 | AA38: 11.451575 | AB38: 11.573444 | AC38: 11.696633 | AD38: 0.0088750685
A39: QUA000:da_ElectricityRe | B39: Electricity-Related Losses 4/ | C39: 6.7504392 | D39: 6.6453795 | E39: 6.198627 | F39: 6.0170331 | G39: 5.9255939 | H39: 5.9008031 | I39: 5.7094221 | J39: 5.5675249 | K39: 5.2508364 | L39: 5.1189775 | M39: 4.9839048 | N39: 4.8274674 | O39: 4.6912923 | P39: 4.515852 | Q39: 4.4359798 | R39: 4.2349305 | S39: 4.2226033 | T39: 4.2776289 | U39: 4.3340192 | V39: 4.3706579 | W39: 4.416029 | X39: 4.4356556 | Y39: 4.455595 | Z39: 4.4910345 | AA39: 4.540494 | AB39: 4.6004906 | AC39: 4.6265779 | AD39: -0.014425332
A40: QUA000:da_Total | B40: Total | C40: 16.046282 | D40: 16.214157 | E40: 15.782431 | F40: 15.667049 | G40: 15.616587 | H40: 15.66959 | I40: 15.523399 | J40: 15.425488 | K40: 15.149508 | L40: 15.051496 | M40: 14.967597 | N40: 14.887005 | O40: 14.84663 | P40: 14.776415 | Q40: 14.797336 | R40: 14.707102 | S40: 14.802834 | T40: 14.961225 | U40: 15.119492 | V40: 15.258682 | W40: 15.411311 | X40: 15.541428 | Y40: 15.672049 | Z40: 15.82241 | AA40: 15.992069 | AB40: 16.173935 | AC40: 16.323212 | AD40: 0.00065833059
B42: Industrial 7/
A43: QUA000:ea_LiquefiedPetr | B43: Hydrocarbon Gas Liquids 8/ | C43: 3.549334 | D43: 3.6120908 | E43: 3.608268 | F43: 3.6132569 | G43: 3.6198926 | H43: 3.6259682 | I43: 3.6304524 | J43: 3.6325908 | K43: 3.6348026 | L43: 3.6363418 | M43: 3.6331077 | N43: 3.6297038 | O43: 3.62797 | P43: 3.6233563 | Q43: 3.6534243 | R43: 3.7222829 | S43: 3.7976925 | T43: 3.8583491 | U43: 3.9214847 | V43: 3.9662054 | W43: 3.9386899 | X43: 3.8998945 | Y43: 3.9388001 | Z43: 4.0122061 | AA43: 4.0656796 | AB43: 4.0390134 | AC43: 4.0112762 | AD43: 0.004716838
A44: QUA000:ea_MotorGasoline | B44: Motor Gasoline 5/ | C44: 0.28129116 | D44: 0.28524733 | E44: 0.28838739 | F44: 0.29223931 | G44: 0.29710907 | H44: 0.30265772 | I44: 0.30711547 | J44: 0.31040412 | K44: 0.31344408 | L44: 0.31531975 | M44: 0.31691885 | N44: 0.31935063 | O44: 0.3222349 | P44: 0.32399002 | Q44: 0.32589963 | R44: 0.32769111 | S44: 0.32958576 | T44: 0.33104026 | U44: 0.3330465 | V44: 0.33460608 | W44: 0.33634329 | X44: 0.33907914 | Y44: 0.3421981 | Z44: 0.34522736 | AA44: 0.3482638 | AB44: 0.35161096 | AC44: 0.35469961 | AD44: 0.0089583879
A45: QUA000:ea_DistillateFue | B45: Distillate Fuel Oil | C45: 1.140013 | D45: 1.1517704 | E45: 1.163439 | F45: 1.1770879 | G45: 1.1952047 | H45: 1.2161039 | I45: 1.2327404 | J45: 1.2469035 | K45: 1.2609564 | L45: 1.2692895 | M45: 1.2779593 | N45: 1.2885053 | O45: 1.2995133 | P45: 1.3081962 | Q45: 1.3171865 | R45: 1.3246379 | S45: 1.3324291 | T45: 1.3377509 | U45: 1.3440975 | V45: 1.3499229 | W45: 1.3560994 | X45: 1.3644851 | Y45: 1.3749679 | Z45: 1.3852943 | AA45: 1.3944283 | AB45: 1.4056869 | AC45: 1.4157501 | AD45: 0.0083663377
A46: QUA000:ea_ResidualFuel | B46: Residual Fuel Oil | C46: 0.041173782 | D46: 0.041980214 | E46: 0.041255284 | F46: 0.040061377 | G46: 0.038840663 | H46: 0.03755071 | I46: 0.036368787 | J46: 0.035531987 | K46: 0.035132185 | L46: 0.034659758 | M46: 0.03427862 | N46: 0.033785958 | O46: 0.033265438 | P46: 0.032701276 | Q46: 0.032198168 | R46: 0.031758849 | S46: 0.031438194 | T46: 0.031171702 | U46: 0.030895893 | V46: 0.030628925 | W46: 0.030439584 | X46: 0.030239962 | Y46: 0.029949037 | Z46: 0.029728098 | AA46: 0.029473307 | AB46: 0.029252237 | AC46: 0.028856551 | AD46: -0.013578684
A47: QUA000:ea_Petrochemical | B47: Petrochemical Feedstocks | C47: 0.39052528 | D47: 0.35500002 | E47: 0.55000001 | F47: 0.55000001 | G47: 0.55000001 | H47: 0.55000001 | I47: 0.55000001 | J47: 0.55000001 | K47: 0.55000001 | L47: 0.55000001 | M47: 0.55000001 | N47: 0.55000001 | O47: 0.55000001 | P47: 0.55000001 | Q47: 0.55000001 | R47: 0.55000001 | S47: 0.55000001 | T47: 0.55000001 | U47: 0.55000001 | V47: 0.55000001 | W47: 0.69558024 | X47: 0.84116042 | Y47: 0.84116042 | Z47: 0.84116042 | AA47: 0.84116042 | AB47: 0.96409488 | AC47: 1.0870293 | AD47: 0.040158917
A48: QUA000:ea_OtherPetroleu | B48: Other Petroleum 9/ | C48: 3.0740016 | D48: 3.1140246 | E48: 3.0742402 | F48: 3.1022868 | G48: 3.1480894 | H48: 3.1397483 | I48: 3.1741762 | J48: 3.191782 | K48: 3.1912818 | L48: 3.1779342 | M48: 3.190891 | N48: 3.1891558 | O48: 3.2032456 | P48: 3.2078876 | Q48: 3.2083092 | R48: 3.2187264 | S48: 3.2361729 | T48: 3.2442126 | U48: 3.2330201 | V48: 3.2493777 | W48: 3.2495708 | X48: 3.2487731 | Y48: 3.2612281 | Z48: 3.279748 | AA48: 3.2799067 | AB48: 3.2766674 | AC48: 3.2632678 | AD48: 0.002300678
A49: QUA000:ea_PetroleumSubt | B49: Petroleum and Other Liquids Subtotal | C49: 8.4763393 | D49: 8.560113 | E49: 8.7255898 | F49: 8.7749329 | G49: 8.8491364 | H49: 8.8720293 | I49: 8.9308529 | J49: 8.9672136 | K49: 8.9856176 | L49: 8.9835443 | M49: 9.0031557 | N49: 9.0105028 | O49: 9.0362291 | P49: 9.0461311 | Q49: 9.087018 | R49: 9.1750984 | S49: 9.277319 | T49: 9.3525248 | U49: 9.4125452 | V49: 9.4807415 | W49: 9.6067228 | X49: 9.7236319 | Y49: 9.7883043 | Z49: 9.8933649 | AA49: 9.9589119 | AB49: 10.066326 | AC49: 10.16088 | AD49: 0.0069961436
A50: QUA000:ea_NaturalGas | B50: Natural Gas | C50: 7.8032799 | D50: 7.9154544 | E50: 7.6861334 | F50: 7.688715 | G50: 7.6922107 | H50: 7.7114305 | I50: 7.7261925 | J50: 7.7616153 | K50: 7.7715883 | L50: 7.7398701 | M50: 7.7059951 | N50: 7.6781607 | O50: 7.6657152 | P50: 7.666882 | Q50: 7.6988811 | R50: 7.741982 | S50: 7.7851615 | T50: 7.7981253 | U50: 7.8150301 | V50: 7.8523693 | W50: 7.8725629 | X50: 7.8945756 | Y50: 7.9203486 | Z50: 7.9723215 | AA50: 8.0101976 | AB50: 8.0410099 | AC50: 8.0624018 | AD50: 0.0012572264
A51: QUA000:ea_LeaseandPlant | B51: Lease and Plant Fuel 10/ | C51: 2.0452955 | D51: 2.0521982 | E51: 2.1515582 | F51: 2.160423 | G51: 2.2060053 | H51: 2.2267821 | I51: 2.2380469 | J51: 2.2325897 | K51: 2.2855608 | L51: 2.298938 | M51: 2.3135834 | N51: 2.3050079 | O51: 2.2963171 | P51: 2.271652 | Q51: 2.2656469 | R51: 2.24652 | S51: 2.2501502 | T51: 2.2605298 | U51: 2.2711818 | V51: 2.2756584 | W51: 2.2786613 | X51: 2.28227 | Y51: 2.2915204 | Z51: 2.3010576 | AA51: 2.3056939 | AB51: 2.3112719 | AC51: 2.318181 | AD51: 0.0048285654
A52: QUA000:ea_NaturalGasSub | B52: Natural Gas Subtotal | C52: 9.8485746 | D52: 9.9676533 | E52: 9.8376913 | F52: 9.8491383 | G52: 9.8982153 | H52: 9.9382124 | I52: 9.9642391 | J52: 9.9942055 | K52: 10.057149 | L52: 10.038807 | M52: 10.019579 | N52: 9.9831686 | O52: 9.9620323 | P52: 9.9385338 | Q52: 9.9645281 | R52: 9.9885025 | S52: 10.035312 | T52: 10.058655 | U52: 10.086212 | V52: 10.128028 | W52: 10.151224 | X52: 10.176846 | Y52: 10.211869 | Z52: 10.273379 | AA52: 10.315892 | AB52: 10.352282 | AC52: 10.380583 | AD52: 0.0020255211
A53: QUA000:ea_Metallurgical | B53: Metallurgical Coal | C53: 0.43991837 | D53: 0.43567309 | E53: 0.43846086 | F53: 0.42828897 | G53: 0.41177323 | H53: 0.39733613 | I53: 0.38921678 | J53: 0.38336113 | K53: 0.37771872 | L53: 0.36561811 | M53: 0.35786009 | N53: 0.34966362 | O53: 0.3411434 | P53: 0.33612818 | Q53: 0.32967824 | R53: 0.32287195 | S53: 0.31849402 | T53: 0.31237662 | U53: 0.30536726 | V53: 0.30014977 | W53: 0.29406098 | X53: 0.2868973 | Y53: 0.27923691 | Z53: 0.27291861 | AA53: 0.26561075 | AB53: 0.25784329 | AC53: 0.24997748 | AD53: -0.021504574
A54: QUA000:ea_SteamCoal | B54: Other Industrial Coal | C54: 0.34671885 | D54: 0.35904637 | E54: 0.36619395 | F54: 0.37179869 | G54: 0.37727422 | H54: 0.37957576 | I54: 0.38246772 | J54: 0.38462999 | K54: 0.38840577 | L54: 0.38864446 | M54: 0.38737294 | N54: 0.38355026 | O54: 0.37776071 | P54: 0.3718915 | Q54: 0.36603522 | R54: 0.36093733 | S54: 0.35692361 | T54: 0.35333821 | U54: 0.34936124 | V54: 0.34515244 | W54: 0.34085384 | X54: 0.33666408 | Y54: 0.33275953 | Z54: 0.32897627 | AA54: 0.32534856 | AB54: 0.32200006 | AC54: 0.31792194 | AD54: -0.0033293816
... A64: QUA000:ea_Total | B64: Total | C64: 31.18813 | D64: 31.434951 | E64: 31.323631 | F64: 31.263987 | G64: 31.322799 | H64: 31.378703 | I64: 31.417871 | J64: 31.491981 | K64: 31.493468 | L64: 31.508798 | M64: 31.602716 | N64: 31.624946 | O64: 31.669591 | P64: 31.610552 | Q64: 31.6734 | R64: 31.68539 | S64: 31.911348 | T64: 32.099259 | U64: 32.27078 | V64: 32.434256 | W64: 32.646597 | X64: 32.838162 | Y64: 32.990003 | Z64: 33.240052 | AA64: 33.419795 | AB64: 33.647184 | AC64: 33.819919 | AD64: 0.0031207202
B67: Transportation
A68: QUA000:fa_LiquefiedPetr | B68: Propane | C68: 0.011194721 | D68: 0.01132582 | E68: 0.011342343 | F68: 0.011296511 | G68: 0.011204666 | H68: 0.011043284 | I68: 0.010857326 | J68: 0.010561488 | K68: 0.010183936 | L68: 0.0098048383 | M68: 0.009443529 | N68: 0.0090809111 | O68: 0.0087324986 | P68: 0.0084068151 | Q68: 0.0080750557 | R68: 0.0077653914 | S68: 0.0074714478 | T68: 0.0071925912 | U68: 0.0069328435 | V68: 0.006679432 | W68: 0.0064509157 | X68: 0.0062675513 | Y68: 0.0061269314 | Z68: 0.0060079629 | AA68: 0.0058876802 | AB68: 0.0057717394 | AC68: 0.0056684841 | AD68: -0.025834302
A69: QUA000:fa_MotorGasoline | B69: Motor Gasoline 5/ | C69: 16.210775 | D69: 16.221838 | E69: 16.069057 | F69: 15.822627 | G69: 15.572903 | H69: 15.260414 | I69: 14.868507 | J69: 14.476609 | K69: 14.007551 | L69: 13.530052 | M69: 13.070603 | N69: 12.609262 | O69: 12.128078 | P69: 11.655457 | Q69: 11.219964 | R69: 10.806561 | S69: 10.438981 | T69: 10.102791 | U69: 9.7716827 | V69: 9.5066671 | W69: 9.2428837 | X69: 9.0307226 | Y69: 8.8326979 | Z69: 8.6771469 | AA69: 8.4899454 | AB69: 8.3657703 | AC69: 8.2689962 | AD69: -0.025558591
A70: QUA000:fa_RenewableEner | B70: of which: E85 14/ | C70: 0.0037425878 | D70: 0.0034678115 | E70: 0.0030934263 | F70: 0.0028972824 | G70: 0.0028112771 | H70: 0.0029138643 | I70: 0.0027621684 | J70: 0.0025515468 | K70: 0.0023751268 | L70: 0.0022268316 | M70: 0.002109227 | N70: 0.001984346 | O70: 0.0018585057 | P70: 0.0017643637 | Q70: 0.001666074 | R70: 0.0015909038 | S70: 0.0015549371 | T70: 0.0015218979 | U70: 0.0014945467 | V70: 0.0014800344 | W70: 0.0015016593 | X70: 0.0014627939 | Y70: 0.0014593391 | Z70: 0.0014924099 | AA70: 0.0014877509 | AB70: 0.0014884961 | AC70: 0.0014804708 | AD70: -0.035041218
A71: QUA000:fa_JetFuel | B71: Jet Fuel 15/ | C71: 3.5818703 | D71: 3.5793664 | E71: 3.5865006 | F71: 3.6006465 | G71: 3.6285143 | H71: 3.6628873 | I71: 3.6928756 | J71: 3.7134352 | K71: 3.7377982 | L71: 3.7617288 | M71: 3.7858496 | N71: 3.8191397 | O71: 3.8512988 | P71: 3.8876221 | Q71: 3.926214 | R71: 3.9663866 | S71: 4.0093832 | T71: 4.0481305 | U71: 4.0892224 | V71: 4.1273794 | W71: 4.1659346 | X71: 4.203361 | Y71: 4.241859 | Z71: 4.2803555 | AA71: 4.3183918 | AB71: 4.3574553 | AC71: 4.3961654 | AD71: 0.0079098712
A72: QUA000:fa_DistillateFue | B72: Distillate Fuel Oil 16/ | C72: 6.9979105 | D72: 7.0585365 | E72: 6.9956489 | F72: 6.8897605 | G72: 6.8189445 | H72: 6.7366619 | I72: 6.6246767 | J72: 6.4870749 | K72: 6.2792459 | L72: 6.086525 | M72: 5.9186425 | N72: 5.7605071 | O72: 5.620604 | P72: 5.4945588 | Q72: 5.3805766 | R72: 5.2683234 | S72: 5.179173 | T72: 5.0906634 | U72: 5.0174117 | V72: 4.9504118 | W72: 4.8920422 | X72: 4.8463073 | Y72: 4.8132887 | Z72: 4.788403 | AA72: 4.7639828 | AB72: 4.7489305 | AC72: 4.7323179 | AD72: -0.014933392
A73: QUA000:fa_ResidualFuel | B73: Residual Fuel Oil | C73: 0.55169058 | D73: 0.51529694 | E73: 0.51195145 | F73: 0.52094501 | G73: 0.5271576 | H73: 0.53540123 | I73: 0.54370654 | J73: 0.55016416 | K73: 0.55513942 | L73: 0.55919713 | M73: 0.56572789 | N73: 0.57143688 | O73: 0.57599622 | P73: 0.58207506 | Q73: 0.58621544 | R73: 0.59176618 | S73: 0.59672421 | T73: 0.60092074 | U73: 0.60536748 | V73: 0.60950303 | W73: 0.61703724 | X73: 0.62063181 | Y73: 0.62381786 | Z73: 0.62882209 | AA73: 0.63301003 | AB73: 0.63659424 | AC73: 0.63859546 | AD73: 0.0056421586
A74: QUA000:fa_OtherPetroleu | B74: Other Petroleum 17/ | C74: 0.15666306 | D74: 0.15705305 | E74: 0.15772593 | F74: 0.15820067 | G74: 0.15842745 | H74: 0.15855163 | I74: 0.15861559 | J74: 0.15853654 | K74: 0.15841712 | L74: 0.15837345 | M74: 0.15839437 | N74: 0.15840103 | O74: 0.15839081 | P74: 0.15838932 | Q74: 0.15841417 | R74: 0.15847965 | S74: 0.15854374 | T74: 0.15854563 | U74: 0.15853849 | V74: 0.15851457 | W74: 0.15847962 | X74: 0.1584473 | Y74: 0.15841375 | Z74: 0.15835039 | AA74: 0.1582725 | AB74: 0.15818226 | AC74: 0.15806621 | AD74: 0.00034300612
A75: QUA000:fa_PetroleumSubt | B75: Petroleum and Other Liquids Subtotal | C75: 27.510107 | D75: 27.543419 | E75: 27.332226 | F75: 27.003475 | G75: 26.71715 | H75: 26.364956 | I75: 25.899239 | J75: 25.396381 | K75: 24.748335 | L75: 24.10568 | M75: 23.508663 | N75: 22.927826 | O75: 22.343102 | P75: 21.786507 | Q75: 21.279457 | R75: 20.799284 | S75: 20.390274 | T75: 20.008244 | U75: 19.649155 | V75: 19.359158 | W75: 19.082829 | X75: 18.865738 | Y75: 18.676207 | Z75: 18.539085 | AA75: 18.36949 | AB75: 18.272703 | AC75: 18.199812 | AD75: -0.015764503
A76: QUA000:fa_PipelineFuelN | B76: Pipeline and Distribution Fuel Natural Gas | C76: 0.92418796 | D76: 0.87045646 | E76: 0.8644231 | F76: 0.8360585 | G76: 0.79698032 | H76: 0.7659651 | I76: 0.72879106 | J76: 0.71577013 | K76: 0.72421408 | L76: 0.71766335 | M76: 0.71669465 | N76: 0.71806842 | O76: 0.71989661 | P76: 0.71830803 | Q76: 0.71970445 | R76: 0.72253788 | S76: 0.73092747 | T76: 0.74004358 | U76: 0.75118923 | V76: 0.76455861 | W76: 0.7802605 | X76: 0.79553533 | Y76: 0.80706799 | Z76: 0.81946605 | AA76: 0.83334386 | AB76: 0.8486467 | AC76: 0.86641687 | AD76: -0.0024795861
A77: QUA000:ea_liquefactexp | B77: Natural Gas to Liquefy Gas for Export 18/ | C77: 0.36799014 | D77: 0.42041078 | E77: 0.44769335 | F77: 0.44849336 | G77: 0.53499717 | H77: 0.59558821 | I77: 0.65857673 | J77: 0.67561275 | K77: 0.6939941 | L77: 0.70917916 | M77: 0.72592348 | N77: 0.73431474 | O77: 0.74434364 | P77: 0.7511372 | Q77: 0.7511372 | R77: 0.7511372 | S77: 0.75273526 | T77: 0.7511372 | U77: 0.75105321 | V77: 0.74779612 | W77: 0.74588698 | X77: 0.74406099 | Y77: 0.74129367 | Z77: 0.74168199 | AA77: 0.74083316 | AB77: 0.73885125 | AC77: 0.74192649 | AD77: 0.027335956
A78: QUA000:fa_CompressedNat | B78: Compressed / Liquefied Natural Gas | C78: 0.088659957 | D78: 0.096424915 | E78: 0.1025497 | F78: 0.10725749 | G78: 0.11093071 | H78: 0.11405666 | I78: 0.11627778 | J78: 0.11767957 | K78: 0.11748469 | L78: 0.1169368 | M78: 0.11696292 | N78: 0.11752955 | O78: 0.11868542 | P78: 0.12059151 | Q78: 0.12354393 | R78: 0.1277284 | S78: 0.13412692 | T78: 0.14142573 | U78: 0.14980228 | V78: 0.159253 | W78: 0.16910984 | X78: 0.17960507 | Y78: 0.19103318 | Z78: 0.20267299 | AA78: 0.21461548 | AB78: 0.22708997 | AC78: 0.23996493 | AD78: 0.039038281
A79: QUA000:fa_LiquidHydroge | B79: Hydrogen | C79: 0.00081358542 | D79: 0.0029666617 | E79: 0.0065186247 | F79: 0.01192539 | G79: 0.020096527 | H79: 0.029843606 | I79: 0.041044701 | J79: 0.066349745 | K79: 0.12415636 | L79: 0.17742926 | M79: 0.22674634 | N79: 0.27223855 | O79: 0.31554592 | P79: 0.35688075 | Q79: 0.39580354 | R79: 0.43265939 | S79: 0.46864074 | T79: 0.5018543 | U79: 0.5328238 | V79: 0.56065708 | W79: 0.58648348 | X79: 0.61015189 | Y79: 0.63182551 | Z79: 0.6514588 | AA79: 0.66846031 | AB79: 0.68415236 | AC79: 0.69732517 | AD79: 0.2966087
... A87: QUA000:fa_Total | B87: Total | C87: 29.100668 | D87: 29.216925 | E87: 29.136339 | F87: 28.924061 | G87: 28.865067 | H87: 28.758085 | I87: 28.57081 | J87: 28.364347 | K87: 28.093412 | L87: 27.828226 | M87: 27.598871 | N87: 27.34617 | O87: 27.070158 | P87: 26.779694 | Q87: 26.539318 | R87: 26.2621 | S87: 26.106363 | T87: 25.978071 | U87: 25.855669 | V87: 25.770792 | W87: 25.685043 | X87: 25.629858 | Y87: 25.582588 | Z87: 25.58367 | AA87: 25.541851 | AB87: 25.563349 | AC87: 25.592537 | AD87: -0.0049285969
B89: Unspecified Sector 20/
A90: QUA000:un_Total | B90: Total | C90: -0.74169135 | D90: -0.53466761 | E90: -0.40727526 | F90: -0.2805714 | G90: -0.27667746 | H90: -0.2718659 | I90: -0.26572257 | J90: -0.25930393 | K90: -0.25118327 | L90: -0.24310534 | M90: -0.2355123 | N90: -0.22800976 | O90: -0.22043386 | P90: -0.21311578 | Q90: -0.2064046 | R90: -0.19999737 | S90: -0.1944221 | T90: -0.18925035 | U90: -0.18430342 | V90: -0.18026796 | W90: -0.17633638 | X90: -0.17319945 | Y90: -0.17037416 | Z90: -0.16817954 | AA90: -0.16558111 | AB90: -0.1638936 | AC90: -0.16254333 | AD90: -0.056712511
B92: Delivered Energy Consumption, All Sectors
A93: QUA000:ga_LiquefiedPetr | B93: Liquefied Petroleum Gases and Other 7/ | C93: 4.209641 | D93: 4.3111634 | E93: 4.308465 | F93: 4.3140569 | G93: 4.3211656 | H93: 4.3261156 | I93: 4.3287339 | J93: 4.3287792 | K93: 4.3288174 | L93: 4.3287091 | M93: 4.3238573 | N93: 4.319674 | O93: 4.3178515 | P93: 4.3137355 | Q93: 4.3446488 | R93: 4.4146876 | S93: 4.4915562 | T93: 4.5537505 | U93: 4.6185212 | V93: 4.6648831 | W93: 4.6391997 | X93: 4.6024594 | Y93: 4.6438022 | Z93: 4.7198486 | AA93: 4.7760854 | AB93: 4.7521434 | AC93: 4.7268677 | AD93: 0.0044670782
A94: QUA000:ga_MotorGasoline | B94: Motor Gasoline 5/ | C94: 16.513548 | D94: 16.489157 | E94: 16.473249 | F94: 16.364161 | G94: 16.130833 | H94: 15.836448 | I94: 15.462359 | J94: 15.086967 | K94: 14.635193 | L94: 14.174006 | M94: 13.730399 | N94: 13.285722 | O94: 12.821792 | P94: 12.365026 | Q94: 11.944914 | R94: 11.546367 | S94: 11.193057 | T94: 10.870225 | U94: 10.552912 | V94: 10.300356 | W94: 10.049176 | X94: 9.8499565 | Y94: 9.6650934 | Z94: 9.5220995 | AA94: 9.3479118 | AB94: 9.2362928 | AC94: 9.1515055 | AD94: -0.022446652
A95: QUA000:ga_E85 | B95: of which: E85 14/ | C95: 0.0037425878 | D95: 0.0034678115 | E95: 0.0030934263 | F95: 0.0028972824 | G95: 0.0028112771 | H95: 0.0029138643 | I95: 0.0027621684 | J95: 0.0025515468 | K95: 0.0023751268 | L95: 0.0022268316 | M95: 0.002109227 | N95: 0.001984346 | O95: 0.0018585057 | P95: 0.0017643637 | Q95: 0.001666074 | R95: 0.0015909038 | S95: 0.0015549371 | T95: 0.0015218979 | U95: 0.0014945467 | V95: 0.0014800344 | W95: 0.0015016593 | X95: 0.0014627939 | Y95: 0.0014593391 | Z95: 0.0014924099 | AA95: 0.0014877509 | AB95: 0.0014884961 | AC95: 0.0014804708 | AD95: -0.035041218
A96: QUA000:ga_JetFuel | B96: Jet Fuel 15/ | C96: 3.520226 | D96: 3.5730426 | E96: 3.5801642 | F96: 3.5942848 | G96: 3.6221037 | H96: 3.6564162 | I96: 3.6863513 | J96: 3.7068746 | K96: 3.7311945 | L96: 3.7550826 | M96: 3.7791607 | N96: 3.8123922 | O96: 3.8444946 | P96: 3.8807535 | Q96: 3.9192774 | R96: 3.9593792 | S96: 4.0022993 | T96: 4.0409784 | U96: 4.0819979 | V96: 4.1200876 | W96: 4.1585751 | X96: 4.1959348 | Y96: 4.234365 | Z96: 4.2727933 | AA96: 4.3107624 | AB96: 4.3497567 | AC96: 4.3883986 | AD96: 0.0085144743
A97: QUA000:ga_Kerosene | B97: Kerosene 21/ | C97: 0.0031892001 | D97: 0.0027506 | E97: 0.0041711251 | F97: 0.0041879551 | G97: 0.0040476951 | H97: 0.0035846883 | I97: 0.0031925037 | J97: 0.0031210892 | K97: 0.0031530487 | L97: 0.0029784902 | M97: 0.0029064643 | N97: 0.0027936092 | O97: 0.0027606941 | P97: 0.002623626 | Q97: 0.0025183379 | R97: 0.0024647033 | S97: 0.002362869 | T97: 0.0022300498 | U97: 0.0021127793 | V97: 0.0019758209 | W97: 0.0017758964 | X97: 0.0017954228 | Y97: 0.00176089 | Z97: 0.0017501722 | AA97: 0.0017577324 | AB97: 0.0017368306 | AC97: 0.0016976331 | AD97: -0.023959651
A98: QUA000:ga_DistillateFue | B98: Distillate Fuel Oil 1/ | C98: 8.6236725 | D98: 8.9305172 | E98: 8.8767366 | F98: 8.7784462 | G98: 8.7171507 | H98: 8.6464491 | I98: 8.5424004 | J98: 8.4113207 | K98: 8.2117529 | L98: 8.0217676 | M98: 7.8565512 | N98: 7.7030473 | O98: 7.5685244 | P98: 7.4452024 | Q98: 7.3344612 | R98: 7.224154 | S98: 7.1369767 | T98: 7.0479193 | U98: 6.9749846 | V98: 6.9078383 | W98: 6.8489256 | X98: 6.806139 | Y98: 6.7782464 | Z98: 6.7588916 | AA98: 6.7391815 | AB98: 6.7307229 | AC98: 6.7191992 | AD98: -0.0095518599
A99: QUA000:ga_ResidualFuel | B99: Residual Fuel Oil | C99: 0.59541434 | D99: 0.55826324 | E99: 0.55419266 | F99: 0.56206214 | G99: 0.56712997 | H99: 0.57410848 | I99: 0.58125579 | J99: 0.5869 | K99: 0.59149885 | L99: 0.59510761 | M99: 0.60128093 | N99: 0.60652059 | O99: 0.61058235 | P99: 0.61611921 | Q99: 0.61977816 | R99: 0.62491077 | S99: 0.62956887 | T99: 0.63351935 | U99: 0.63771045 | V99: 0.64159906 | W99: 0.64896381 | X99: 0.65237856 | Y99: 0.65529346 | Z99: 0.66009653 | AA99: 0.66404945 | AB99: 0.66743249 | AC99: 0.66905802 | AD99: 0.0044951985
A100: QUA000:ga_Petrochemical | B100: Petrochemical Feedstocks | C100: 0.39052528 | D100: 0.35500002 | E100: 0.55000001 | F100: 0.55000001 | G100: 0.55000001 | H100: 0.55000001 | I100: 0.55000001 | J100: 0.55000001 | K100: 0.55000001 | L100: 0.55000001 | M100: 0.55000001 | N100: 0.55000001 | O100: 0.55000001 | P100: 0.55000001 | Q100: 0.55000001 | R100: 0.55000001 | S100: 0.55000001 | T100: 0.55000001 | U100: 0.55000001 | V100: 0.55000001 | W100: 0.69558024 | X100: 0.84116042 | Y100: 0.84116042 | Z100: 0.84116042 | AA100: 0.84116042 | AB100: 0.96409488 | AC100: 1.0870293 | AD100: 0.040158917
A101: QUA000:ga_OtherPetroleu | B101: Other Petroleum 17/ | C101: 3.2295768 | D101: 3.2699895 | E101: 3.2308781 | F101: 3.2593997 | G101: 3.3054292 | H101: 3.2972121 | I101: 3.3317034 | J101: 3.3492303 | K101: 3.3486114 | L101: 3.3352199 | M101: 3.3481975 | N101: 3.3464687 | O101: 3.3605485 | P101: 3.3651891 | Q101: 3.3656352 | R101: 3.3761182 | S101: 3.3936288 | T101: 3.40167 | U101: 3.390471 | V101: 3.4068043 | W101: 3.4069626 | X101: 3.4061322 | Y101: 3.4185538 | Z101: 3.4370105 | AA101: 3.4370911 | AB101: 3.4337616 | AC101: 3.4202461 | AD101: 0.0022086431
A102: QUA000:ga_PetroleumSubt | B102: Petroleum and Other Liquids Subtotal | C102: 37.085793 | D102: 37.489883 | E102: 37.577854 | F102: 37.426598 | G102: 37.217857 | H102: 36.890331 | I102: 36.485996 | J102: 36.023193 | K102: 35.400219 | L102: 34.762871 | M102: 34.192352 | N102: 33.626617 | O102: 33.076553 | P102: 32.538647 | Q102: 32.081234 | R102: 31.69808 | S102: 31.399448 | T102: 31.100292 | U102: 30.808708 | V102: 30.593544 | W102: 30.449158 | X102: 30.355955 | Y102: 30.238276 | Z102: 30.21365 | AA102: 30.118 | AB102: 30.135941 | AC102: 30.164 | AD102: -0.0079140866
A103: QUA000:ga_NaturalGas | B103: Natural Gas | C103: 15.922085 | D103: 16.589268 | E103: 16.433655 | F103: 16.467926 | G103: 16.476635 | H103: 16.485569 | I103: 16.473749 | J103: 16.472303 | K103: 16.420673 | L103: 16.331055 | M103: 16.244268 | N103: 16.183437 | O103: 16.155165 | P103: 16.150698 | Q103: 16.180746 | R103: 16.226549 | S103: 16.269405 | T103: 16.272173 | U103: 16.274857 | V103: 16.296432 | W103: 16.30525 | X103: 16.318613 | Y103: 16.333918 | Z103: 16.378664 | AA103: 16.412935 | AB103: 16.440083 | AC103: 16.456854 | AD103: 0.001271381
A104: QUA000:ga_LeaseandPlant | B104: Lease and Plant Fuel 10/ | C104: 2.0452955 | D104: 2.0521982 | E104: 2.1515582 | F104: 2.160423 | G104: 2.2060053 | H104: 2.2267821 | I104: 2.2380469 | J104: 2.2325897 | K104: 2.2855608 | L104: 2.298938 | M104: 2.3135834 | N104: 2.3050079 | O104: 2.2963171 | P104: 2.271652 | Q104: 2.2656469 | R104: 2.24652 | S104: 2.2501502 | T104: 2.2605298 | U104: 2.2711818 | V104: 2.2756584 | W104: 2.2786613 | X104: 2.28227 | Y104: 2.2915204 | Z104: 2.3010576 | AA104: 2.3056939 | AB104: 2.3112719 | AC104: 2.318181 | AD104: 0.0048285654
... A119: QUA000:ga_Total | B119: Total | C119: 93.788419 | D119: 94.546169 | E119: 93.743479 | F119: 93.340944 | G119: 93.20291 | H119: 93.052064 | I119: 92.416649 | J119: 91.871381 | K119: 90.832564 | L119: 90.209591 | M119: 89.721876 | N119: 89.163886 | O119: 88.696052 | P119: 88.064775 | Q119: 87.79054 | R119: 87.213465 | S119: 87.330084 | T119: 87.554408 | U119: 87.770105 | V119: 87.98056 | W119: 88.260143 | X119: 88.502663 | Y119: 88.712009 | Z119: 89.100469 | AA119: 89.407232 | AB119: 89.847187 | AC119: 90.178018 | AD119: -0.0015086948
B121: Electric Power 23/
A122: QUA000:ha_DistillateFue | B122: Distillate Fuel Oil | C122: 0.066403143 | D122: 0.065482274 | E122: 0.059721522 | F122: 0.051562436 | G122: 0.047603745 | H122: 0.045218822 | I122: 0.040859323 | J122: 0.037158124 | K122: 0.026274355 | L122: 0.025522899 | M122: 0.025486546 | N122: 0.024426321 | O122: 0.024423892 | P122: 0.023857307 | Q122: 0.023148708 | R122: 0.02307808 | S122: 0.02301812 | T122: 0.022388805 | U122: 0.021225702 | V122: 0.020516135 | W122: 0.019153791 | X122: 0.018159341 | Y122: 0.017684897 | Z122: 0.017484162 | AA122: 0.017670512 | AB122: 0.017884392 | AC122: 0.018141914 | AD122: -0.048679818
A123: QUA000:ha_ResidualFuel | B123: Residual Fuel Oil | C123: 0.044082917 | D123: 0.042744439 | E123: 0.042098805 | F123: 0.041531701 | G123: 0.039579418 | H123: 0.039203979 | I123: 0.038851511 | J123: 0.038796071 | K123: 0.039023455 | L123: 0.039286334 | M123: 0.039635129 | N123: 0.040089402 | O123: 0.039733384 | P123: 0.039332956 | Q123: 0.038802154 | R123: 0.038284332 | S123: 0.037613764 | T123: 0.034838066 | U123: 0.03187814 | V123: 0.028754732 | W123: 0.02548375 | X123: 0.0221058 | Y123: 0.022298004 | Z123: 0.022472559 | AA123: 0.022656109 | AB123: 0.022861086 | AC123: 0.023051737 | AD123: -0.024627487
A124: QUA000:ha_PetroleumSubt | B124: Petroleum and Other Liquids Subtotal | C124: 0.11048606 | D124: 0.10822672 | E124: 0.10182033 | F124: 0.09309414 | G124: 0.087183163 | H124: 0.084422797 | I124: 0.079710834 | J124: 0.075954199 | K124: 0.065297812 | L124: 0.064809233 | M124: 0.065121673 | N124: 0.064515725 | O124: 0.064157277 | P124: 0.063190266 | Q124: 0.061950862 | R124: 0.061362412 | S124: 0.060631886 | T124: 0.05722687 | U124: 0.053103842 | V124: 0.049270868 | W124: 0.044637538 | X124: 0.040265143 | Y124: 0.0399829 | Z124: 0.039956719 | AA124: 0.040326621 | AB124: 0.040745478 | AC124: 0.041193649 | AD124: -0.037235414
A125: QUA000:ha_NaturalGas | B125: Natural Gas | C125: 13.928752 | D125: 12.961791 | E125: 12.332006 | F125: 12.814469 | G125: 12.775032 | H125: 12.874219 | I125: 13.066365 | J125: 12.920246 | K125: 14.43693 | L125: 13.99907 | M125: 13.549019 | N125: 12.973681 | O125: 12.49203 | P125: 11.657304 | Q125: 11.344967 | R125: 10.781556 | S125: 10.757802 | T125: 11.080935 | U125: 11.368726 | V125: 11.544607 | W125: 11.729016 | X125: 11.844905 | Y125: 12.052026 | Z125: 12.196947 | AA125: 12.346659 | AB125: 12.542368 | AC125: 12.544281 | AD125: -0.0040184552
A126: QUA000:ha_SteamCoal | B126: Steam Coal | C126: 6.7714281 | D126: 6.7575512 | E126: 5.8142242 | F126: 4.703229 | G126: 4.5218911 | H126: 4.2834682 | I126: 3.5192912 | J126: 3.2391207 | K126: 0.7612527 | L126: 0.76565677 | M126: 0.74390846 | N126: 0.70231581 | O126: 0.67731613 | P126: 0.63364023 | Q126: 0.58205354 | R126: 0.21281935 | S126: 0.21332814 | T126: 0.21385521 | U126: 0.21418442 | V126: 0.21473019 | W126: 0.21060497 | X126: 0.19238602 | Y126: 0.047468394 | Z126: 0.047543135 | AA126: 0.04759784 | AB126: 0.044522885 | AC126: 0.044709716 | AD126: -0.17559021
A127: QUA000:ha_NuclearPower | B127: Nuclear / Uranium 24/ | C127: 8.1225662 | D127: 8.2810526 | E127: 8.3596506 | F127: 8.3406391 | G127: 8.3405018 | H127: 8.3403893 | I127: 8.247139 | J127: 8.160346 | K127: 8.1603022 | L127: 8.1604614 | M127: 8.1604614 | N127: 8.1391783 | O127: 8.0871992 | P127: 8.127986 | Q127: 8.1249504 | R127: 8.1106997 | S127: 8.1093731 | T127: 8.1100388 | U127: 8.110383 | V127: 8.1107826 | W127: 8.108737 | X127: 8.1102085 | Y127: 8.1065235 | Z127: 8.1099443 | AA127: 8.1090002 | AB127: 8.1071606 | AC127: 8.1079435 | AD127: -6.9300566e-05
A128: QUA000:ha_RenewableEner | B128: Renewable Energy 25/ | C128: 3.4094412 | D128: 3.8024855 | E128: 4.3689404 | F128: 4.6928029 | G128: 4.8440752 | H128: 5.0673985 | I128: 5.4154825 | J128: 5.7938361 | K128: 6.2255588 | L128: 6.6744337 | M128: 7.2109437 | N128: 7.8499446 | O128: 8.4510164 | P128: 9.1673594 | Q128: 9.648984 | R128: 10.328339 | S128: 10.649783 | T128: 10.803039 | U128: 10.975296 | V128: 11.190047 | W128: 11.380852 | X128: 11.55542 | Y128: 11.771945 | Z128: 11.940047 | AA128: 12.114095 | AB128: 12.275303 | AC128: 12.507335 | AD128: 0.051261669
A129: QUA000:ha_Hydrogen | B129: Hydrogen | C129: 0 | D129: 0 | E129: 0 | F129: 0 | G129: 0 | H129: 0 | I129: 0 | J129: 0 | K129: 0.091394141 | L129: 0.10555667 | M129: 0.11796803 | N129: 0 | O129: 0 | P129: 0 | Q129: 0 | R129: 0 | S129: 0 | T129: 0 | U129: 0 | V129: 0 | W129: 0 | X129: 0 | Y129: 0 | Z129: 0 | AA129: 0 | AB129: 0 | AC129: 0 | AD129: --
A130: QUA000:ha_non-bio_mun | B130: Non-biogenic Municipal Waste | C130: 0.087990433 | D130: 0.087990433 | E130: 0.087990433 | F130: 0.087990433 | G130: 0.087990433 | H130: 0.087990433 | I130: 0.087990433 | J130: 0.087990433 | K130: 0.087990433 | L130: 0.087990433 | M130: 0.087990433 | N130: 0.087990433 | O130: 0.087990433 | P130: 0.087990433 | Q130: 0.087990433 | R130: 0.087990433 | S130: 0.087990433 | T130: 0.087990433 | U130: 0.087990433 | V130: 0.087990433 | W130: 0.087990433 | X130: 0.087990433 | Y130: 0.087990433 | Z130: 0.087990433 | AA130: 0.087990433 | AB130: 0.087990433 | AC130: 0.087990433 | AD130: 0
A131: QUA000:ha_ElectricityIm | B131: Electricity Imports | C131: 0.1003412 | D131: 0.11839326 | E131: 0.14245847 | F131: 0.20290294 | G131: 0.24338387 | H131: 0.26112166 | I131: 0.28683487 | J131: 0.29337007 | K131: 0.29980782 | L131: 0.30806202 | M131: 0.30971265 | N131: 0.31395516 | O131: 0.30632564 | P131: 0.30275732 | Q131: 0.30115148 | R131: 0.29325011 | S131: 0.29788169 | T131: 0.29930353 | U131: 0.29689026 | V131: 0.27686998 | W131: 0.27546498 | X131: 0.27317014 | Y131: 0.25714964 | Z131: 0.24611509 | AA131: 0.23954612 | AB131: 0.22953501 | AC131: 0.22034964 | AD131: 0.030717697
A132: QUA000:ha_TotalEnergy | B132: Total Energy | C132: 32.531006 | D132: 32.117489 | E132: 31.207094 | F132: 30.935127 | G132: 30.900059 | H132: 30.99901 | I132: 30.702814 | J132: 30.57086 | K132: 30.037231 | L132: 30.060589 | M132: 30.127275 | N132: 30.131582 | O132: 30.166039 | P132: 30.04023 | Q132: 30.15205 | R132: 29.876017 | S132: 30.17679 | T132: 30.652388 | U132: 31.106575 | V132: 31.474298 | W132: 31.837303 | X132: 32.104343 | Y132: 32.363087 | Z132: 32.668545 | AA132: 32.985218 | AB132: 33.327621 | AC132: 33.553802 | AD132: 0.001191345
A133: QUA000:ha_H2RelatLosses | B133: Hydrogen-Related Losses 13/ | C133: 0 | D133: 0 | E133: 0 | F133: 0 | G133: 0 | H133: 0 | I133: 0 | J133: 0 | K133: 3.6402285e-05 | L133: 4.2043226e-05 | M133: 4.6986668e-05 | N133: 0 | O133: 0 | P133: 0 | Q133: 0 | R133: 0 | S133: 0 | T133: 0 | U133: 0 | V133: 0 | W133: 0 | X133: 0 | Y133: 0 | Z133: 0 | AA133: 0 | AB133: 0 | AC133: 0 | AD133: --
A134: QUA000:ha_Total | B134: Total | C134: 32.531006 | D134: 32.117489 | E134: 31.207094 | F134: 30.935127 | G134: 30.900059 | H134: 30.99901 | I134: 30.702814 | J134: 30.57086 | K134: 30.037268 | L134: 30.060631 | M134: 30.127323 | N134: 30.131582 | O134: 30.166039 | P134: 30.04023 | Q134: 30.15205 | R134: 29.876017 | S134: 30.17679 | T134: 30.652388 | U134: 31.106575 | V134: 31.474298 | W134: 31.837303 | X134: 32.104343 | Y134: 32.363087 | Z134: 32.668545 | AA134: 32.985218 | AB134: 33.327621 | AC134: 33.553802 | AD134: 0.001191345
B136: Industrial: Hydrogen Production 26/
A137: QUA000:la_NaturalGas | B137: Natural Gas | C137: 1.0604824 | D137: 1.078702 | E137: 1.1099755 | F137: 1.1256274 | G137: 1.1349019 | H137: 1.1484714 | I137: 1.1765769 | J137: 1.222061 | K137: 1.309051 | L137: 1.3920895 | M137: 1.4700611 | N137: 1.5432655 | O137: 1.6124504 | P137: 1.6730843 | Q137: 1.7300197 | R137: 1.7820098 | S137: 1.831471 | T137: 1.8790311 | U137: 1.9213089 | V137: 1.9635477 | W137: 2.0080576 | X137: 2.04883 | Y137: 2.0800366 | Z137: 2.1036174 | AA137: 2.1276574 | AB137: 2.1479189 | AC137: 2.1715064 | AD137: 0.027948716
A138: QUA000:la_PurchasedElec | B138: Purchased Electricity | C138: 0.0036486231 | D138: 0.0036928754 | E138: 0.0046056723 | F138: 0.0047401022 | G138: 0.0048241555 | H138: 0.0049446798 | I138: 0.0051398696 | J138: 0.0054459423 | K138: 0.0064866995 | L138: 0.0080552408 | M138: 0.0095777046 | N138: 0.011226226 | O138: 0.011394272 | P138: 0.010608704 | Q138: 0.0098964293 | R138: 0.0099007199 | S138: 0.0099761346 | T138: 0.010060698 | U138: 0.0099067213 | V138: 0.0097962115 | W138: 0.0093012499 | X138: 0.0085842563 | Y138: 0.0080011869 | Z138: 0.007289385 | AA138: 0.007355751 | AB138: 0.0052315197 | AC138: 0.0052898368 | AD138: 0.014388592
A139: QUA000:la_ByproductH2 | B139: Byproduct Hydrogen | C139: 0.2812978 | D139: 0.28379169 | E139: 0.28559867 | F139: 0.28582275 | G139: 0.28619227 | H139: 0.28640378 | I139: 0.28644398 | J139: 0.28641137 | K139: 0.28726324 | L139: 0.28825971 | M139: 0.29222989 | N139: 0.29441708 | O139: 0.29534853 | P139: 0.29821536 | Q139: 0.3015438 | R139: 0.30737531 | S139: 0.31435218 | T139: 0.31943759 | U139: 0.32552114 | V139: 0.32820833 | W139: 0.32749715 | X139: 0.32506591 | Y139: 0.32816547 | Z139: 0.33494848 | AA139: 0.3396492 | AB139: 0.34065247 | AC139: 0.34046417 | AD139: 0.0073691736
A140: QUA000:la_TotalEnergy | B140: Total Energy | C140: 1.3454288 | D140: 1.3661865 | E140: 1.4001797 | F140: 1.4161903 | G140: 1.4259183 | H140: 1.4398198 | I140: 1.4681606 | J140: 1.5139184 | K140: 1.602801 | L140: 1.6884044 | M140: 1.7718687 | N140: 1.8489087 | O140: 1.9191931 | P140: 1.9819083 | Q140: 2.0414598 | R140: 2.0992858 | S140: 2.1557994 | T140: 2.2085292 | U140: 2.2567368 | V140: 2.3015523 | W140: 2.344856 | X140: 2.3824801 | Y140: 2.4162033 | Z140: 2.4458554 | AA140: 2.4746623 | AB140: 2.493803 | AC140: 2.5172603 | AD140: 0.024387171
A141: QUA000:la_ElectricityRe | B141: Electricity-Related Losses 4/ | C141: 0.0051859459 | D141: 0.005089554 | E141: 0.005969638 | F141: 0.0059091784 | G141: 0.0058805617 | H141: 0.0059215752 | I141: 0.0059079705 | J141: 0.0060596159 | K141: 0.0067507257 | L141: 0.0081103053 | M141: 0.009294481 | N141: 0.010416008 | O141: 0.010121902 | P141: 0.0089317532 | Q141: 0.0080685513 | R141: 0.0075888443 | S141: 0.0075091664 | T141: 0.0075557884 | U141: 0.0074244938 | V141: 0.0072906753 | W141: 0.0068860063 | X141: 0.0062845526 | Y141: 0.0057916436 | Z141: 0.0052352054 | AA141: 0.005256319 | AB141: 0.0037269283 | AC141: 0.0037282119 | AD141: -0.012612994
A142: QUA000:la_Total | B142: Total | C142: 1.3506148 | D142: 1.371276 | E142: 1.4061494 | F142: 1.4220995 | G142: 1.4317989 | H142: 1.4457414 | I142: 1.4740686 | J142: 1.519978 | K142: 1.6095517 | L142: 1.6965147 | M142: 1.7811632 | N142: 1.8593247 | O142: 1.9293151 | P142: 1.9908401 | Q142: 2.0495284 | R142: 2.1068747 | S142: 2.1633086 | T142: 2.216085 | U142: 2.2641613 | V142: 2.3088429 | W142: 2.351742 | X142: 2.3887646 | Y142: 2.4219949 | Z142: 2.4510906 | AA142: 2.4799187 | AB142: 2.49753 | AC142: 2.5209885 | AD142: 0.02429391
B144: Total Energy Consumption
...

Sheet AEO 2026 Table 2
A1: Table 2. Energy Consumption by Sector and Source
A2: https://www.eia.gov/outlooks/aeo/data/browser/#/?id=2-AEO2026&cases=electrnp&sourcekey=0
A3: Wed May 06 2026 12:02:09 GMT-0400 (Eastern Daylight Time)
A4: Source: U.S. Energy Information Administration
B5: full name | C5: api key | D5: units | E5: 2025 | F5: 2026 | G5: 2027 | H5: 2028 | I5: 2029 | J5: 2030 | K5: 2031 | L5: 2032 | M5: 2033 | N5: 2034 | O5: 2035 | P5: 2036 | Q5: 2037 | R5: 2038 | S5: 2039 | T5: 2040 | U5: 2041 | V5: 2042 | W5: 2043 | X5: 2044 | Y5: 2045 | Z5: 2046 | AA5: 2047 | AB5: 2048 | AC5: 2049 | AD5: 2050 | AE5: Growth (2025-2050)
A6: Residential
A7: Propane | B7: Energy Use: Residential: Propane: Alternative Electricity and Transportation | C7: AEO.2026.ELECTRNP.CNSM_ENU_RESD_NA_PROP_NA_NA_QBTU.A | D7: quads | E7: 0.5245 | F7: 0.51372 | G7: 0.495541 | H7: 0.496211 | I7: 0.493311 | J7: 0.488928 | K7: 0.483486 | L7: 0.478163 | M7: 0.473203 | N7: 0.469062 | O7: 0.465621 | P7: 0.462483 | Q7: 0.459429 | R7: 0.456475 | S7: 0.453566 | T7: 0.450898 | U7: 0.448539 | V7: 0.446738 | W7: 0.445416 | X7: 0.444479 | Y7: 0.443746 | Z7: 0.442976 | AA7: 0.442012 | AB7: 0.440991 | AC7: 0.44002 | AD7: 0.439191 | AE7: -0.007
A8: Distillate Fuel Oil | B8: Energy Use: Residential: Distillate Fuel Oil: Alternative Electricity and Transportation | C8: AEO.2026.ELECTRNP.CNSM_ENU_RESD_NA_DFO_NA_NA_QBTU.A | D8: quads | E8: 0.48928 | F8: 0.47136 | G8: 0.464952 | H8: 0.4565 | I8: 0.447624 | J8: 0.439746 | K8: 0.431983 | L8: 0.424812 | M8: 0.417945 | N8: 0.411851 | O8: 0.406073 | P8: 0.400473 | Q8: 0.395019 | R8: 0.389742 | S8: 0.38464 | T8: 0.379595 | U8: 0.374572 | V8: 0.369741 | W8: 0.364969 | X8: 0.360335 | Y8: 0.35574 | Z8: 0.351238 | AA8: 0.346724 | AB8: 0.342244 | AC8: 0.337805 | AD8: 0.333547 | AE8: -0.015
A9: Petroleum and Other Liquids Subtotal | B9: Energy Use: Residential: Liquid Fuels Subtotal: Alternative Electricity and Transportation | C9: AEO.2026.ELECTRNP.CNSM_ENU_RESD_NA_LFL_NA_NA_QBTU.A | D9: quads | E9: 1.01378 | F9: 0.98508 | G9: 0.960492 | H9: 0.952711 | I9: 0.940935 | J9: 0.928674 | K9: 0.915469 | L9: 0.902975 | M9: 0.891148 | N9: 0.880914 | O9: 0.871694 | P9: 0.862955 | Q9: 0.854449 | R9: 0.846217 | S9: 0.838206 | T9: 0.830493 | U9: 0.82311 | V9: 0.816479 | W9: 0.810385 | X9: 0.804814 | Y9: 0.799486 | Z9: 0.794214 | AA9: 0.788736 | AB9: 0.783235 | AC9: 0.777824 | AD9: 0.772738 | AE9: -0.011
A10: Natural Gas | B10: Energy Use: Residential: Natural Gas: Alternative Electricity and Transportation | C10: AEO.2026.ELECTRNP.CNSM_ENU_RESD_NA_NG_NA_NA_QBTU.A | D10: quads | E10: 4.92608 | F10: 4.756272 | G10: 4.887193 | H10: 4.880057 | I10: 4.841941 | J10: 4.792875 | K10: 4.741629 | L10: 4.695206 | M10: 4.647789 | N10: 4.605699 | O10: 4.566593 | P10: 4.529979 | Q10: 4.491732 | R10: 4.45528 | S10: 4.419171 | T10: 4.384261 | U10: 4.349348 | V10: 4.318778 | W10: 4.290055 | X10: 4.262946 | Y10: 4.23648 | Z10: 4.207667 | AA10: 4.176517 | AB10: 4.145389 | AC10: 4.115045 | AD10: 4.086372 | AE10: -0.007
A11: Renewable Energy | B11: Energy Use: Residential: Renewable Energy: Alternative Electricity and Transportation | C11: AEO.2026.ELECTRNP.CNSM_ENU_RESD_NA_REN_NA_NA_QBTU.A | D11: quads | E11: 0.371387 | F11: 0.342901 | G11: 0.33499 | H11: 0.331205 | I11: 0.328954 | J11: 0.323627 | K11: 0.319369 | L11: 0.315643 | M11: 0.312812 | N11: 0.309126 | O11: 0.305829 | P11: 0.302008 | Q11: 0.298094 | R11: 0.294199 | S11: 0.289954 | T11: 0.285538 | U11: 0.28127 | V11: 0.277378 | W11: 0.273631 | X11: 0.270078 | Y11: 0.266974 | Z11: 0.263978 | AA11: 0.26129 | AB11: 0.258824 | AC11: 0.256576 | AD11: 0.254137 | AE11: -0.015
A12: Purchased Electricity for Residential Use | B12: Energy Use: Residential: Electricity: Alternative Electricity and Transportation | C12: AEO.2026.ELECTRNP.CNSM_ENU_RESD_NA_ELC_NA_NA_QBTU.A | D12: quads | E12: 5.146283 | F12: 5.165968 | G12: 5.063568 | H12: 5.097425 | I12: 5.110842 | J12: 5.101124 | K12: 5.084683 | L12: 5.071815 | M12: 5.063284 | N12: 5.061672 | O12: 5.064488 | P12: 5.071559 | Q12: 5.081708 | R12: 5.095572 | S12: 5.111459 | T12: 5.122882 | U12: 5.139645 | V12: 5.162683 | W12: 5.191554 | X12: 5.221573 | Y12: 5.249293 | Z12: 5.279313 | AA12: 5.307253 | AB12: 5.334354 | AC12: 5.364092 | AD12: 5.394052 | AE12: 0.002
A13: Delivered Energy | B13: Energy Use: Residential: Delivered Energy: Alternative Electricity and Transportation | C13: AEO.2026.ELECTRNP.CNSM_ENU_RESD_NA_DELE_NA_NA_QBTU.A | D13: quads | E13: 11.457531 | F13: 11.25022 | G13: 11.246243 | H13: 11.2614 | I13: 11.222671 | J13: 11.146299 | K13: 11.06115 | L13: 10.98564 | M13: 10.915031 | N13: 10.85741 | O13: 10.808603 | P13: 10.7665 | Q13: 10.725982 | R13: 10.691268 | S13: 10.658791 | T13: 10.623175 | U13: 10.593373 | V13: 10.57532 | W13: 10.565623 | X13: 10.559411 | Y13: 10.552234 | Z13: 10.545171 | AA13: 10.533794 | AB13: 10.5218 | AC13: 10.513536 | AD13: 10.5073 | AE13: -0.003
A14: Electricity-Related Losses | B14: Energy Use: Residential: Electricity Related Losses: Alternative Electricity and Transportation | C14: AEO.2026.ELECTRNP.CNSM_ENU_RESD_NA_ERL_NA_NA_QBTU.A | D14: quads | E14: 7.071282 | F14: 7.030098 | G14: 6.364577 | H14: 6.131857 | I14: 6.008963 | J14: 5.890632 | K14: 5.684556 | L14: 5.5596 | M14: 5.483474 | N14: 5.37458 | O14: 5.297432 | P14: 5.223444 | Q14: 5.182245 | R14: 5.157815 | S14: 5.1249 | T14: 5.075423 | U14: 5.032132 | V14: 5.019648 | W14: 5.019057 | X14: 5.021711 | Y14: 5.022737 | Z14: 5.028126 | AA14: 5.036541 | AB14: 5.04317 | AC14: 5.033889 | AD14: 5.040434 | AE14: -0.013
A15: Total | B15: Energy Use: Residential: Total: Alternative Electricity and Transportation | C15: AEO.2026.ELECTRNP.CNSM_ENU_RESD_NA_TOT_NA_NA_QBTU.A | D15: quads | E15: 18.528812 | F15: 18.280319 | G15: 17.610821 | H15: 17.393257 | I15: 17.231632 | J15: 17.03693 | K15: 16.745705 | L15: 16.54524 | M15: 16.398506 | N15: 16.231991 | O15: 16.106035 | P15: 15.989944 | Q15: 15.908227 | R15: 15.849083 | S15: 15.783691 | T15: 15.698598 | U15: 15.625505 | V15: 15.594969 | W15: 15.584681 | X15: 15.581122 | Y15: 15.57497 | Z15: 15.573297 | AA15: 15.570335 | AB15: 15.56497 | AC15: 15.547426 | AD15: 15.547734 | AE15: -0.007
A16: Commercial
A17: Propane | B17: Energy Use: Commercial: Propane: Alternative Electricity and Transportation | C17: AEO.2026.ELECTRNP.CNSM_ENU_COMM_NA_PROP_NA_NA_QBTU.A | D17: quads | E17: 0.215225 | F17: 0.219131 | G17: 0.221612 | H17: 0.224037 | I17: 0.226424 | J17: 0.228837 | K17: 0.231314 | L17: 0.233862 | M17: 0.236496 | N17: 0.239221 | O17: 0.242036 | P17: 0.244938 | Q17: 0.247903 | R17: 0.250787 | S17: 0.253585 | T17: 0.256302 | U17: 0.258878 | V17: 0.261334 | W17: 0.263708 | X17: 0.266017 | Y17: 0.268283 | Z17: 0.270516 | AA17: 0.27272 | AB17: 0.274898 | AC17: 0.277053 | AD17: 0.279188 | AE17: 0.01
A18: Motor Gasoline | B18: Energy Use: Commercial: Motor Gasoline: Alternative Electricity and Transportation | C18: AEO.2026.ELECTRNP.CNSM_ENU_COMM_NA_MGS_NA_NA_QBTU.A | D18: quads | E18: 0.414315 | F18: 0.420968 | G18: 0.426488 | H18: 0.431913 | I18: 0.437276 | J18: 0.442694 | K18: 0.448233 | L18: 0.453909 | M18: 0.459748 | N18: 0.465758 | O18: 0.47194 | P18: 0.478287 | Q18: 0.484756 | R18: 0.491087 | S18: 0.497269 | T18: 0.503313 | U18: 0.509108 | V18: 0.514691 | W18: 0.520132 | X18: 0.525461 | Y18: 0.530719 | Z18: 0.535923 | AA18: 0.541079 | AB18: 0.546196 | AC18: 0.551277 | AD18: 0.556329 | AE18: 0.012
A19: Kerosene | B19: Energy Use: Commercial: Kerosene: Alternative Electricity and Transportation | C19: AEO.2026.ELECTRNP.CNSM_ENU_COMM_NA_KRS_NA_NA_QBTU.A | D19: quads | E19: 0.002501 | F19: 0.003571 | G19: 0.003598 | H19: 0.003246 | I19: 0.002967 | J19: 0.003276 | K19: 0.002843 | L19: 0.002643 | M19: 0.002231 | N19: 0.002149 | O19: 0.001869 | P19: 0.001809 | Q19: 0.001646 | R19: 0.001508 | S19: 0.001467 | T19: 0.001392 | U19: 0.001254 | V19: 0.00117 | W19: 0.001074 | X19: 0.000983 | Y19: 0.00085 | Z19: 0.000766 | AA19: 0.000661 | AB19: 0.000597 | AC19: 0.000554 | AD19: 0.000531 | AE19: -0.06
A20: Distillate Fuel Oil | B20: Energy Use: Commercial: Distillate Fuel Oil: Alternative Electricity and Transportation | C20: AEO.2026.ELECTRNP.CNSM_ENU_COMM_NA_DFO_NA_NA_QBTU.A | D20: quads | E20: 0.31542 | F20: 0.318988 | G20: 0.326446 | H20: 0.327495 | I20: 0.327918 | J20: 0.329482 | K20: 0.330749 | L20: 0.330317 | M20: 0.327748 | N20: 0.325246 | O20: 0.322803 | P20: 0.32087 | Q20: 0.318856 | R20: 0.316839 | S20: 0.315024 | T20: 0.313302 | U20: 0.31156 | V20: 0.309885 | W20: 0.308174 | X20: 0.306455 | Y20: 0.304637 | Z20: 0.302802 | AA20: 0.300869 | AB20: 0.299047 | AC20: 0.297122 | AD20: 0.295435 | AE20: -0.003
A21: Residual Fuel Oil | B21: Energy Use: Commercial: Residual Fuel Oil: Alternative Electricity and Transportation | C21: AEO.2026.ELECTRNP.CNSM_ENU_COMM_NA_RFO_NA_NA_QBTU.A | D21: quads | E21: 0.003996 | F21: 0.004127 | G21: 0.003166 | H21: 0.002817 | I21: 0.002552 | J21: 0.002484 | K21: 0.002231 | L21: 0.002243 | M21: 0.002201 | N21: 0.002234 | O21: 0.002188 | P21: 0.002206 | Q21: 0.002223 | R21: 0.002225 | S21: 0.002245 | T21: 0.002228 | U21: 0.002181 | V21: 0.002182 | W21: 0.002184 | X21: 0.002182 | Y21: 0.002165 | Z21: 0.002166 | AA21: 0.002148 | AB21: 0.002125 | AC21: 0.002114 | AD21: 0.002166 | AE21: -0.024
A22: Petroleum and Other Liquids Subtotal | B22: Energy Use: Commercial: Liquid Fuels Subtotal: Alternative Electricity and Transportation | C22: AEO.2026.ELECTRNP.CNSM_ENU_COMM_NA_LFL_NA_NA_QBTU.A | D22: quads | E22: 0.951457 | F22: 0.966786 | G22: 0.98131 | H22: 0.989507 | I22: 0.997137 | J22: 1.006773 | K22: 1.01537 | L22: 1.022974 | M22: 1.028423 | N22: 1.034608 | O22: 1.040836 | P22: 1.04811 | Q22: 1.055384 | R22: 1.062446 | S22: 1.06959 | T22: 1.076537 | U22: 1.082981 | V22: 1.089262 | W22: 1.095272 | X22: 1.101097 | Y22: 1.106654 | Z22: 1.112174 | AA22: 1.117477 | AB22: 1.122862 | AC22: 1.128121 | AD22: 1.133648 | AE22: 0.007
A23: Natural Gas | B23: Energy Use: Commercial: Natural Gas: Alternative Electricity and Transportation | C23: AEO.2026.ELECTRNP.CNSM_ENU_COMM_NA_NG_NA_NA_QBTU.A | D23: quads | E23: 3.639804 | F23: 3.563961 | G23: 3.57154 | H23: 3.555938 | I23: 3.519203 | J23: 3.474857 | K23: 3.433453 | L23: 3.41069 | M23: 3.395886 | N23: 3.389492 | O23: 3.383103 | P23: 3.380279 | Q23: 3.376655 | R23: 3.373224 | S23: 3.368847 | T23: 3.365051 | U23: 3.362263 | V23: 3.363703 | W23: 3.366547 | X23: 3.371504 | Y23: 3.37535 | Z23: 3.374094 | AA23: 3.369559 | AB23: 3.364201 | AC23: 3.358932 | AD23: 3.354442 | AE23: -0.003
A24: Coal | B24: Energy Use: Commercial: Coal: Alternative Electricity and Transportation | C24: AEO.2026.ELECTRNP.CNSM_ENU_COMM_NA_CL_NA_NA_QBTU.A | D24: quads | E24: 0.012012 | F24: 0.013296 | G24: 0.013296 | H24: 0.013296 | I24: 0.013296 | J24: 0.013296 | K24: 0.013296 | L24: 0.013296 | M24: 0.013296 | N24: 0.013296 | O24: 0.013296 | P24: 0.013296 | Q24: 0.013296 | R24: 0.013296 | S24: 0.013296 | T24: 0.013296 | U24: 0.013296 | V24: 0.013296 | W24: 0.013296 | X24: 0.013296 | Y24: 0.013296 | Z24: 0.013296 | AA24: 0.013296 | AB24: 0.013296 | AC24: 0.013296 | AD24: 0.013296 | AE24: 0.004
A25: Renewable Energy | B25: Energy Use: Commercial: Renewable Energy: Alternative Electricity and Transportation | C25: AEO.2026.ELECTRNP.CNSM_ENU_COMM_NA_REN_NA_NA_QBTU.A | D25: quads | E25: 0.143682 | F25: 0.143682 | G25: 0.143682 | H25: 0.143682 | I25: 0.143682 | J25: 0.143682 | K25: 0.143682 | L25: 0.143682 | M25: 0.143682 | N25: 0.143682 | O25: 0.143682 | P25: 0.143682 | Q25: 0.143682 | R25: 0.143682 | S25: 0.143682 | T25: 0.143682 | U25: 0.143682 | V25: 0.143682 | W25: 0.143682 | X25: 0.143682 | Y25: 0.143682 | Z25: 0.143682 | AA25: 0.143682 | AB25: 0.143682 | AC25: 0.143682 | AD25: 0.143682 | AE25: 0
A26: Purchased Electricity for Commercial Use | B26: Energy Use: Commercial: Electricity: Alternative Electricity and Transportation | C26: AEO.2026.ELECTRNP.CNSM_ENU_COMM_NA_ELC_NA_NA_QBTU.A | D26: quads | E26: 4.993747 | F26: 5.212289 | G26: 5.253817 | H26: 5.309168 | I26: 5.363724 | J26: 5.397077 | K26: 5.435783 | L26: 5.480072 | M26: 5.530184 | N26: 5.582539 | O26: 5.639092 | P26: 5.702602 | Q26: 5.765342 | R26: 5.829359 | S26: 5.892108 | T26: 5.953129 | U26: 6.017625 | V26: 6.079961 | W26: 6.143983 | X26: 6.205702 | Y26: 6.266315 | Z26: 6.32024 | AA26: 6.366059 | AB26: 6.406569 | AC26: 6.44475 | AD26: 6.479488 | AE26: 0.01
A27: Delivered Energy | B27: Energy Use: Commercial: Delivered Energy: Alternative Electricity and Transportation | C27: AEO.2026.ELECTRNP.CNSM_ENU_COMM_NA_DELE_NA_NA_QBTU.A | D27: quads | E27: 9.740702 | F27: 9.900015 | G27: 9.963643 | H27: 10.011592 | I27: 10.037043 | J27: 10.035685 | K27: 10.041583 | L27: 10.070711 | M27: 10.111471 | N27: 10.163616 | O27: 10.22001 | P27: 10.287968 | Q27: 10.35436 | R27: 10.422008 | S27: 10.487522 | T27: 10.551696 | U27: 10.619847 | V27: 10.689905 | W27: 10.762778 | X27: 10.835279 | Y27: 10.905296 | Z27: 10.963486 | AA27: 11.010074 | AB27: 11.050611 | AC27: 11.088779 | AD27: 11.124557 | AE27: 0.005
A28: Electricity-Related Losses | B28: Energy Use: Commercial: Electricity Related Losses: Alternative Electricity and Transportation | C28: AEO.2026.ELECTRNP.CNSM_ENU_COMM_NA_ERL_NA_NA_QBTU.A | D28: quads | E28: 6.861689 | F28: 7.093133 | G28: 6.603709 | H28: 6.386568 | I28: 6.306284 | J28: 6.232388 | K28: 6.077077 | L28: 6.007123 | M28: 5.989121 | N28: 5.927646 | O28: 5.898466 | P28: 5.873386 | Q28: 5.879405 | R28: 5.900565 | S28: 5.907603 | T28: 5.897978 | U28: 5.891747 | V28: 5.911511 | W28: 5.939841 | X28: 5.968172 | Y28: 5.995864 | Z28: 6.019526 | AA28: 6.04134 | AB28: 6.056858 | AC28: 6.048024 | AD28: 6.054713 | AE28: -0.005
A29: Total | B29: Energy Use: Commercial: Total: Alternative Electricity and Transportation | C29: AEO.2026.ELECTRNP.CNSM_ENU_COMM_NA_TOT_NA_NA_QBTU.A | D29: quads | E29: 16.60239 | F29: 16.993149 | G29: 16.567352 | H29: 16.398159 | I29: 16.343327 | J29: 16.268074 | K29: 16.11866 | L29: 16.077835 | M29: 16.100592 | N29: 16.091263 | O29: 16.118477 | P29: 16.161354 | Q29: 16.233765 | R29: 16.322573 | S29: 16.395124 | T29: 16.449675 | U29: 16.511595 | V29: 16.601418 | W29: 16.70262 | X29: 16.803452 | Y29: 16.901161 | Z29: 16.983013 | AA29: 17.051414 | AB29: 17.107468 | AC29: 17.136803 | AD29: 17.17927 | AE29: 0.001
A30: Industrial
A31: Hydrocarbon Gas Liquids | B31: Energy Use: Industrial: Hydrocarbon Gas Liquids: Alternative Electricity and Transportation | C31: AEO.2026.ELECTRNP.CNSM_ENU_IDAL_NA_LPG_NA_NA_QBTU.A | D31: quads | E31: 3.662158 | F31: 3.619826 | G31: 3.814983 | H31: 3.703949 | I31: 3.628261 | J31: 3.619809 | K31: 3.650235 | L31: 3.675397 | M31: 3.710558 | N31: 3.75121 | O31: 3.798428 | P31: 3.856649 | Q31: 3.902375 | R31: 3.949627 | S31: 4.027802 | T31: 4.09741 | U31: 4.173698 | V31: 4.262658 | W31: 4.345017 | X31: 4.428278 | Y31: 4.518957 | Z31: 4.61057 | AA31: 4.711479 | AB31: 4.800843 | AC31: 4.864139 | AD31: 4.951746 | AE31: 0.012
A32: Motor Gasoline | B32: Energy Use: Industrial: Motor Gasoline: Alternative Electricity and Transportation | C32: AEO.2026.ELECTRNP.CNSM_ENU_IDAL_NA_MGS_NA_NA_QBTU.A | D32: quads | E32: 0.274134 | F32: 0.272877 | G32: 0.274898 | H32: 0.278423 | I32: 0.281926 | J32: 0.286878 | K32: 0.291053 | L32: 0.295224 | M32: 0.298205 | N32: 0.30178 | O32: 0.304799 | P32: 0.307633 | Q32: 0.310316 | R32: 0.312839 | S32: 0.315401 | T32: 0.317999 | U32: 0.320688 | V32: 0.323215 | W32: 0.325655 | X32: 0.327945 | Y32: 0.330613 | Z32: 0.333403 | AA32: 0.336337 | AB32: 0.338948 | AC32: 0.341414 | AD32: 0.34381 | AE32: 0.009
A33: Distillate Fuel Oil | B33: Energy Use: Industrial: Distillate Fuel Oil: Alternative Electricity and Transportation | C33: AEO.2026.ELECTRNP.CNSM_ENU_IDAL_NA_DFO_NA_NA_QBTU.A | D33: quads | E33: 1.161135 | F33: 1.161444 | G33: 1.162011 | H33: 1.168513 | I33: 1.179822 | J33: 1.196678 | K33: 1.2089 | L33: 1.228125 | M33: 1.237822 | N33: 1.249308 | O33: 1.260567 | P33: 1.270628 | Q33: 1.281835 | R33: 1.292388 | S33: 1.302165 | T33: 1.31047 | U33: 1.317658 | V33: 1.325369 | W33: 1.332637 | X33: 1.339916 | Y33: 1.349524 | Z33: 1.359533 | AA33: 1.369825 | AB33: 1.378923 | AC33: 1.387899 | AD33: 1.396855 | AE33: 0.007
A34: Residual Fuel Oil | B34: Energy Use: Industrial: Residual Fuel Oil: Alternative Electricity and Transportation | C34: AEO.2026.ELECTRNP.CNSM_ENU_IDAL_NA_RFO_NA_NA_QBTU.A | D34: quads | E34: 0.040876 | F34: 0.039529 | G34: 0.035322 | H34: 0.034547 | I34: 0.033736 | J34: 0.034748 | K34: 0.0339 | L34: 0.034136 | M34: 0.033707 | N34: 0.033753 | O34: 0.033499 | P34: 0.033284 | Q34: 0.033025 | R34: 0.032672 | S34: 0.03256 | T34: 0.032231 | U34: 0.031566 | V34: 0.030664 | W34: 0.029574 | X34: 0.028497 | Y34: 0.027718 | Z34: 0.027413 | AA34: 0.027218 | AB34: 0.026843 | AC34: 0.026572 | AD34: 0.026396 | AE34: -0.017
A35: Petrochemical Feedstocks | B35: Energy Use: Industrial: Petrochemical Feedstocks: Alternative Electricity and Transportation | C35: AEO.2026.ELECTRNP.CNSM_ENU_IDAL_NA_PCF_NA_NA_QBTU.A | D35: quads | E35: 0.412934 | F35: 0.338138 | G35: 0.3482 | H35: 0.55 | I35: 0.55 | J35: 0.55 | K35: 0.55 | L35: 0.55 | M35: 0.55 | N35: 0.55 | O35: 0.55 | P35: 0.55 | Q35: 0.55 | R35: 0.55 | S35: 0.55 | T35: 0.55 | U35: 0.55 | V35: 0.55 | W35: 0.55 | X35: 0.55 | Y35: 0.55 | Z35: 0.55 | AA35: 0.55 | AB35: 0.55 | AC35: 0.55 | AD35: 0.55 | AE35: 0.012
A36: Other Petroleum | B36: Energy Use: Industrial: Other Petroleum: Alternative Electricity and Transportation | C36: AEO.2026.ELECTRNP.CNSM_ENU_IDAL_NA_ONP_NA_NA_QBTU.A | D36: quads | E36: 3.072672 | F36: 3.083884 | G36: 3.060251 | H36: 3.159648 | I36: 3.179748 | J36: 3.208421 | K36: 3.199021 | L36: 3.227253 | M36: 3.243433 | N36: 3.259159 | O36: 3.264192 | P36: 3.274461 | Q36: 3.294827 | R36: 3.301581 | S36: 3.308971 | T36: 3.328164 | U36: 3.338817 | V36: 3.347526 | W36: 3.356701 | X36: 3.359478 | Y36: 3.366012 | Z36: 3.350904 | AA36: 3.371716 | AB36: 3.361616 | AC36: 3.371541 | AD36: 3.357753 | AE36: 0.004
A37: Petroleum and Other Liquids Subtotal | B37: Energy Use: Industrial: Liquid Fuels Subtotal: Alternative Electricity and Transportation | C37: AEO.2026.ELECTRNP.CNSM_ENU_IDAL_NA_LFL_NA_NA_QBTU.A | D37: quads | E37: 8.623908 | F37: 8.515697 | G37: 8.695666 | H37: 8.895081 | I37: 8.853493 | J37: 8.896534 | K37: 8.93311 | L37: 9.010138 | M37: 9.073725 | N37: 9.145209 | O37: 9.211484 | P37: 9.292656 | Q37: 9.372376 | R37: 9.439108 | S37: 9.536899 | T37: 9.636274 | U37: 9.732427 | V37: 9.839432 | W37: 9.939585 | X37: 10.034114 | Y37: 10.142825 | Z37: 10.231822 | AA37: 10.366573 | AB37: 10.457173 | AC37: 10.541565 | AD37: 10.62656 | AE37: 0.008
A38: Natural Gas | B38: Energy Use: Industrial: Natural Gas: Alternative Electricity and Transportation | C38: AEO.2026.ELECTRNP.CNSM_ENU_IDAL_NA_NG_NA_NA_QBTU.A | D38: quads | E38: 7.890323 | F38: 7.801679 | G38: 7.691007 | H38: 7.694491 | I38: 7.686046 | J38: 7.689239 | K38: 7.731081 | L38: 7.760675 | M38: 7.764179 | N38: 7.788864 | O38: 7.813654 | P38: 7.827874 | Q38: 7.822379 | R38: 7.836251 | S38: 7.857157 | T38: 7.899248 | U38: 7.945885 | V38: 8.020393 | W38: 8.099469 | X38: 8.172278 | Y38: 8.254452 | Z38: 8.324203 | AA38: 8.409905 | AB38: 8.477641 | AC38: 8.531862 | AD38: 8.615801 | AE38: 0.004
A39: Lease and Plant Fuel | B39: Energy Use: Industrial: Lease and Plant Fuel: Alternative Electricity and Transportation | C39: AEO.2026.ELECTRNP.CNSM_ENU_IDAL_NA_LSAPFL_NA_NA_QBTU.A | D39: quads | E39: 2.136239 | F39: 2.128485 | G39: 2.16034 | H39: 2.165232 | I39: 2.162156 | J39: 2.203182 | K39: 2.264353 | L39: 2.334959 | M39: 2.395234 | N39: 2.452581 | O39: 2.473735 | P39: 2.482664 | Q39: 2.492755 | R39: 2.506868 | S39: 2.524662 | T39: 2.567465 | U39: 2.601775 | V39: 2.630552 | W39: 2.644943 | X39: 2.647805 | Y39: 2.645955 | Z39: 2.656424 | AA39: 2.673549 | AB39: 2.689496 | AC39: 2.689622 | AD39: 2.684877 | AE39: 0.009
A40: Natural Gas Subtotal | B40: Energy Use: Industrial: Natural Gas Subtotal: Alternative Electricity and Transportation | C40: AEO.2026.ELECTRNP.CNSM_ENU_IDAL_NA_NGS_NA_NA_QBTU.A | D40: quads | E40: 10.026562 | F40: 9.930164 | G40: 9.851347 | H40: 9.859723 | I40: 9.848203 | J40: 9.892421 | K40: 9.995433 | L40: 10.095635 | M40: 10.159411 | N40: 10.241446 | O40: 10.287389 | P40: 10.310538 | Q40: 10.315134 | R40: 10.34312 | S40: 10.38182 | T40: 10.466712 | U40: 10.54766 | V40: 10.650945 | W40: 10.744411 | X40: 10.820083 | Y40: 10.900406 | Z40: 10.980626 | AA40: 11.083455 | AB40: 11.167137 | AC40: 11.221485 | AD40: 11.300678 | AE40: 0.005
A41: Metallurgical Coal | B41: Energy Use: Industrial: Metallurgical Coal: Alternative Electricity and Transportation | C41: AEO.2026.ELECTRNP.CNSM_ENU_IDAL_NA_MTC_NA_NA_QBTU.A | D41: quads | E41: 0.418161 | F41: 0.437662 | G41: 0.44603 | H41: 0.430685 | I41: 0.419412 | J41: 0.41326 | K41: 0.405478 | L41: 0.399905 | M41: 0.39375 | N41: 0.38365 | O41: 0.375297 | P41: 0.36476 | Q41: 0.355506 | R41: 0.345369 | S41: 0.33481 | T41: 0.326546 | U41: 0.319121 | V41: 0.311913 | W41: 0.304025 | X41: 0.296245 | Y41: 0.290391 | Z41: 0.283607 | AA41: 0.277604 | AB41: 0.271253 | AC41: 0.263581 | AD41: 0.257168 | AE41: -0.019
A42: Other Industrial Coal | B42: Energy Use: Industrial: Other Industrial Coal: Alternative Electricity and Transportation | C42: AEO.2026.ELECTRNP.CNSM_ENU_IDAL_NA_OIC_NA_NA_QBTU.A | D42: quads | E42: 0.400357 | F42: 0.368676 | G42: 0.367838 | H42: 0.364646 | I42: 0.361133 | J42: 0.358318 | K42: 0.354281 | L42: 0.355666 | M42: 0.355927 | N42: 0.354811 | O42: 0.353166 | P42: 0.350292 | Q42: 0.346605 | R42: 0.342346 | S42: 0.337837 | T42: 0.333433 | U42: 0.329175 | V42: 0.324752 | W42: 0.32024 | X42: 0.315859 | Y42: 0.312079 | Z42: 0.30854 | AA42: 0.305125 | AB42: 0.301662 | AC42: 0.298052 | AD42: 0.294661 | AE42: -0.012
... A52: Total | B52: Energy Use: Industrial: Total: Alternative Electricity and Transportation | C52: AEO.2026.ELECTRNP.CNSM_ENU_IDAL_NA_TOT_NA_NA_QBTU.A | D52: quads | E52: 31.753458 | F52: 31.811975 | G52: 31.433118 | H52: 31.367507 | I52: 31.162773 | J52: 31.14043 | K52: 31.085595 | L52: 31.179845 | M52: 31.300316 | N52: 31.459044 | O52: 31.606235 | P52: 31.756123 | Q52: 31.941276 | R52: 32.1416 | S52: 32.368946 | T52: 32.614842 | U52: 32.828484 | V52: 33.089382 | W52: 33.313216 | X52: 33.532971 | Y52: 33.802793 | Z52: 34.042952 | AA52: 34.372683 | AB52: 34.630666 | AC52: 34.825866 | AD52: 35.059573 | AE52: 0.004
A53: Transportation
A54: Propane | B54: Energy Use: Transportation: Propane: Alternative Electricity and Transportation | C54: AEO.2026.ELECTRNP.CNSM_ENU_TRN_NA_PROP_NA_NA_QBTU.A | D54: quads | E54: 0.010834 | F54: 0.010579 | G54: 0.010311 | H54: 0.010076 | I54: 0.009849 | J54: 0.009642 | K54: 0.009427 | L54: 0.009225 | M54: 0.009048 | N54: 0.008873 | O54: 0.008713 | P54: 0.008567 | Q54: 0.008432 | R54: 0.008301 | S54: 0.008184 | T54: 0.008076 | U54: 0.007963 | V54: 0.007853 | W54: 0.007741 | X54: 0.007632 | Y54: 0.007526 | Z54: 0.00742 | AA54: 0.007319 | AB54: 0.00721 | AC54: 0.007098 | AD54: 0.006987 | AE54: -0.017
A55: Motor Gasoline | B55: Energy Use: Transportation: Motor Gasoline: Alternative Electricity and Transportation | C55: AEO.2026.ELECTRNP.CNSM_ENU_TRN_NA_MGS_NA_NA_QBTU.A | D55: quads | E55: 15.952119 | F55: 15.816211 | G55: 15.670795 | H55: 15.465606 | I55: 15.225313 | J55: 14.975726 | K55: 14.736685 | L55: 14.53596 | M55: 14.326003 | N55: 14.190125 | O55: 14.043919 | P55: 13.868751 | Q55: 13.694697 | R55: 13.547844 | S55: 13.405708 | T55: 13.291874 | U55: 13.186517 | V55: 13.058501 | W55: 12.968844 | X55: 12.866261 | Y55: 12.776155 | Z55: 12.674413 | AA55: 12.588914 | AB55: 12.471676 | AC55: 12.352423 | AD55: 12.263251 | AE55: -0.01
A56: of which: E85 | B56: Energy Use: Transportation: E85: Alternative Electricity and Transportation | C56: AEO.2026.ELECTRNP.CNSM_ENU_TRN_NA_E85_NA_NA_QBTU.A | D56: quads | E56: 0.039571 | F56: 0.031597 | G56: 0.029975 | H56: 0.028061 | I56: 0.025794 | J56: 0.026779 | K56: 0.022985 | L56: 0.021014 | M56: 0.019146 | N56: 0.017756 | O56: 0.015966 | P56: 0.01446 | Q56: 0.012975 | R56: 0.011777 | S56: 0.010739 | T56: 0.009934 | U56: 0.009025 | V56: 0.008495 | W56: 0.007977 | X56: 0.007621 | Y56: 0.0069 | Z56: 0.00664 | AA56: 0.00658 | AB56: 0.006774 | AC56: 0.006276 | AD56: 0.005978 | AE56: -0.073
A57: Jet Fuel | B57: Energy Use: Transportation: Jet Fuel: Alternative Electricity and Transportation | C57: AEO.2026.ELECTRNP.CNSM_ENU_TRN_NA_JFL_NA_NA_QBTU.A | D57: quads | E57: 3.559663 | F57: 3.614651 | G57: 3.641734 | H57: 3.639242 | I57: 3.653039 | J57: 3.677609 | K57: 3.700235 | L57: 3.732728 | M57: 3.767778 | N57: 3.810222 | O57: 3.861075 | P57: 3.897079 | Q57: 3.936533 | R57: 3.974361 | S57: 4.01077 | T57: 4.047615 | U57: 4.079945 | V57: 4.11531 | W57: 4.152023 | X57: 4.187668 | Y57: 4.223193 | Z57: 4.254883 | AA57: 4.281673 | AB57: 4.30826 | AC57: 4.330516 | AD57: 4.354498 | AE57: 0.008
A58: Distillate Fuel Oil | B58: Energy Use: Transportation: Distillate Fuel Oil: Alternative Electricity and Transportation | C58: AEO.2026.ELECTRNP.CNSM_ENU_TRN_NA_DFO_NA_NA_QBTU.A | D58: quads | E58: 6.60237 | F58: 6.581657 | G58: 6.579469 | H58: 6.540533 | I58: 6.512479 | J58: 6.503887 | K58: 6.465642 | L58: 6.431713 | M58: 6.386379 | N58: 6.349166 | O58: 6.320048 | P58: 6.289291 | Q58: 6.261694 | R58: 6.233672 | S58: 6.207705 | T58: 6.186847 | U58: 6.16387 | V58: 6.139411 | W58: 6.113602 | X58: 6.091432 | Y58: 6.077926 | Z58: 6.068889 | AA58: 6.063625 | AB58: 6.048604 | AC58: 6.031284 | AD58: 6.012776 | AE58: -0.004
A59: Residual Fuel Oil | B59: Energy Use: Transportation: Residual Fuel Oil: Alternative Electricity and Transportation | C59: AEO.2026.ELECTRNP.CNSM_ENU_TRN_NA_RFO_NA_NA_QBTU.A | D59: quads | E59: 0.553285 | F59: 0.53506 | G59: 0.549447 | H59: 0.570977 | I59: 0.576154 | J59: 0.582145 | K59: 0.584488 | L59: 0.592035 | M59: 0.601279 | N59: 0.61074 | O59: 0.618854 | P59: 0.626732 | Q59: 0.632527 | R59: 0.63838 | S59: 0.643494 | T59: 0.647669 | U59: 0.651536 | V59: 0.658491 | W59: 0.66569 | X59: 0.672429 | Y59: 0.679744 | Z59: 0.686508 | AA59: 0.692768 | AB59: 0.698817 | AC59: 0.70527 | AD59: 0.712213 | AE59: 0.01
A60: Other Petroleum | B60: Energy Use: Transportation: Other Petroleum: Alternative Electricity and Transportation | C60: AEO.2026.ELECTRNP.CNSM_ENU_TRN_NA_ONP_NA_NA_QBTU.A | D60: quads | E60: 0.111631 | F60: 0.111692 | G60: 0.111819 | H60: 0.111999 | I60: 0.11221 | J60: 0.1125 | K60: 0.112759 | L60: 0.113014 | M60: 0.11324 | N60: 0.11347 | O60: 0.113689 | P60: 0.113866 | Q60: 0.114039 | R60: 0.114207 | S60: 0.114367 | T60: 0.114523 | U60: 0.114658 | V60: 0.114773 | W60: 0.114866 | X60: 0.114952 | Y60: 0.115056 | Z60: 0.115158 | AA60: 0.115264 | AB60: 0.115343 | AC60: 0.115416 | AD60: 0.115464 | AE60: 0.001
A61: Petroleum and Other Liquids Subtotal | B61: Energy Use: Transportation: Liquid Fuels Subtotal: Alternative Electricity and Transportation | C61: AEO.2026.ELECTRNP.CNSM_ENU_TRN_NA_LFL_NA_NA_QBTU.A | D61: quads | E61: 26.7899 | F61: 26.669855 | G61: 26.563574 | H61: 26.338432 | I61: 26.089041 | J61: 25.861509 | K61: 25.609236 | L61: 25.414675 | M61: 25.203728 | N61: 25.082594 | O61: 24.966297 | P61: 24.804285 | Q61: 24.647921 | R61: 24.516766 | S61: 24.390228 | T61: 24.296602 | U61: 24.204489 | V61: 24.094343 | W61: 24.022764 | X61: 23.940372 | Y61: 23.879602 | Z61: 23.80727 | AA61: 23.749561 | AB61: 23.64991 | AC61: 23.542006 | AD61: 23.465187 | AE61: -0.005
A62: Pipeline and Distribution Fuel Natural Gas | B62: Energy Use: Transportation: Pipeline Fuel Natural Gas: Alternative Electricity and Transportation | C62: AEO.2026.ELECTRNP.CNSM_ENU_TRN_NA_PFN_NA_NA_QBTU.A | D62: quads | E62: 0.734602 | F62: 0.681256 | G62: 0.684287 | H62: 0.67399 | I62: 0.683417 | J62: 0.712555 | K62: 0.732711 | L62: 0.744844 | M62: 0.749815 | N62: 0.757921 | O62: 0.770471 | P62: 0.793589 | Q62: 0.821209 | R62: 0.845468 | S62: 0.872154 | T62: 0.890661 | U62: 0.906708 | V62: 0.924745 | W62: 0.943757 | X62: 0.957821 | Y62: 0.965948 | Z62: 0.975113 | AA62: 0.984192 | AB62: 0.9928 | AC62: 0.996047 | AD62: 1.001548 | AE62: 0.012
A63: Natural Gas to Liquefy Gas for Export | B63: Energy Use: Transportation: Liquefaction: Alternative Electricity and Transportation | C63: AEO.2026.ELECTRNP.CNSM_ENU_IDAL_NA_LQFCT_NA_NA_QBTU.A | D63: quads | E63: 0.59071 | F63: 0.589921 | G63: 0.673663 | H63: 0.72236 | I63: 0.770132 | J63: 0.911097 | K63: 0.97537 | L63: 1.036748 | M63: 1.082817 | N63: 1.159013 | O63: 1.212579 | P63: 1.254067 | Q63: 1.275981 | R63: 1.297406 | S63: 1.319519 | T63: 1.3404 | U63: 1.363284 | V63: 1.38506 | W63: 1.406836 | X63: 1.431363 | Y63: 1.450388 | Z63: 1.472164 | AA63: 1.49394 | AB63: 1.507578 | AC63: 1.504828 | AD63: 1.504828 | AE63: 0.038
A64: Compressed / Liquefied Natural Gas | B64: Energy Use: Transportation: Natural Gas: Alternative Electricity and Transportation | C64: AEO.2026.ELECTRNP.CNSM_ENU_TRN_NA_NG_NA_NA_QBTU.A | D64: quads | E64: 0.087022 | F64: 0.090491 | G64: 0.092753 | H64: 0.094261 | I64: 0.096067 | J64: 0.097447 | K64: 0.098788 | L64: 0.100023 | M64: 0.10119 | N64: 0.102386 | O64: 0.10376 | P64: 0.105181 | Q64: 0.106978 | R64: 0.109014 | S64: 0.111247 | T64: 0.114164 | U64: 0.117464 | V64: 0.121207 | W64: 0.125408 | X64: 0.130361 | Y64: 0.137252 | Z64: 0.144946 | AA64: 0.154619 | AB64: 0.165035 | AC64: 0.176932 | AD64: 0.190801 | AE64: 0.032
A65: Hydrogen | B65: Energy Use: Transportation: Hydrogen: Alternative Electricity and Transportation | C65: AEO.2026.ELECTRNP.CNSM_ENU_TRN_NA_HDG_NA_NA_QBTU.A | D65: quads | E65: 0.000416 | F65: 0.0004 | G65: 0.000382 | H65: 0.000363 | I65: 0.000344 | J65: 0.000324 | K65: 0.000305 | L65: 0.000284 | M65: 0.000264 | N65: 0.000244 | O65: 0.000224 | P65: 0.000205 | Q65: 0.000186 | R65: 0.000168 | S65: 0.000151 | T65: 0.000135 | U65: 0.000119 | V65: 0.000107 | W65: 9.6e-05 | X65: 8.8e-05 | Y65: 7.9e-05 | Z65: 7.3e-05 | AA65: 6.8e-05 | AB65: 6.3e-05 | AC65: 6e-05 | AD65: 5.7e-05 | AE65: -0.076
... A73: Total | B73: Energy Use: Transportation: Total: Alternative Electricity and Transportation | C73: AEO.2026.ELECTRNP.CNSM_ENU_TRN_NA_TOT_NA_NA_QBTU.A | D73: quads | E73: 28.502672 | F73: 28.405464 | G73: 28.462259 | H73: 28.364357 | I73: 28.263159 | J73: 28.290478 | K73: 28.189186 | L73: 28.131687 | M73: 28.037228 | N73: 28.06254 | O73: 28.077501 | P73: 28.044451 | Q73: 28.005249 | R73: 27.988297 | S73: 27.975931 | T73: 27.985262 | U73: 27.994024 | V73: 27.989136 | W73: 28.02499 | X73: 28.049982 | Y73: 28.088264 | Z73: 28.119028 | AA73: 28.166027 | AB73: 28.162708 | AC73: 28.126539 | AD73: 28.130478 | AE73: -0.001
A74: Unspecified Sector
A75: Total | B75: Energy Use: Unspecified: Total: Alternative Electricity and Transportation | C75: AEO.2026.ELECTRNP.CNSM_ENU_OTH_NA_TOT_NA_NA_QBTU.A | D75: quads | E75: -0.101399 | F75: 0.12702 | G75: 0.104695 | H75: 0.10269 | I75: 0.101522 | J75: 0.101295 | K75: 0.099786 | L75: 0.098207 | M75: 0.096267 | N75: 0.093977 | O75: 0.092024 | P75: 0.090323 | Q75: 0.088786 | R75: 0.08709 | S75: 0.085487 | T75: 0.083846 | U75: 0.082102 | V75: 0.080542 | W75: 0.078273 | X75: 0.076693 | Y75: 0.075351 | Z75: 0.074421 | AA75: 0.073583 | AB75: 0.072678 | AC75: 0.071827 | AD75: 0.07079 | AE75: - -
A76: Delivered Energy Consumption | B76: All Sectors
A77: Liquefied Petroleum Gases and Other | B77: Energy Use: Delivered: All Sectors: Liquefied Petroleum Gases: Alternative Electricity and Transportation | C77: AEO.2026.ELECTRNP.CNSM_ENU_ALLS_NA_LPG_DELV_NA_QBTU.A | D77: quads | E77: 4.412717 | F77: 4.363256 | G77: 4.542447 | H77: 4.434274 | I77: 4.357844 | J77: 4.347216 | K77: 4.374463 | L77: 4.396647 | M77: 4.429306 | N77: 4.468367 | O77: 4.514799 | P77: 4.572637 | Q77: 4.618139 | R77: 4.66519 | S77: 4.743137 | T77: 4.812687 | U77: 4.889078 | V77: 4.978583 | W77: 5.061882 | X77: 5.146407 | Y77: 5.238511 | Z77: 5.331482 | AA77: 5.433529 | AB77: 5.523942 | AC77: 5.588309 | AD77: 5.677113 | AE77: 0.01
A78: Motor Gasoline | B78: Energy Use: Delivered: All Sectors: Motor Gasoline: Alternative Electricity and Transportation | C78: AEO.2026.ELECTRNP.CNSM_ENU_ALLS_NA_MGS_DELV_NA_QBTU.A | D78: quads | E78: 16.463058 | F78: 16.388361 | G78: 16.24544 | H78: 16.049076 | I78: 15.818044 | J78: 15.579481 | K78: 15.350713 | L78: 15.160145 | M78: 14.95941 | N78: 14.832905 | O78: 14.69575 | P78: 14.529889 | Q78: 14.365158 | R78: 14.227191 | S78: 14.093845 | T78: 13.988489 | U78: 13.891426 | V78: 13.771574 | W78: 13.689218 | X78: 13.594233 | Y78: 13.511969 | Z78: 13.418295 | AA78: 13.340791 | AB78: 13.231429 | AC78: 13.119942 | AD78: 13.038264 | AE78: -0.009
A79: of which: E85 | B79: Energy Use: Delivered: All Sectors: E85: Alternative Electricity and Transportation | C79: AEO.2026.ELECTRNP.CNSM_ENU_ALLS_NA_E85_DELV_NA_QBTU.A | D79: quads | E79: 0.039571 | F79: 0.031597 | G79: 0.029975 | H79: 0.028061 | I79: 0.025794 | J79: 0.026779 | K79: 0.022985 | L79: 0.021014 | M79: 0.019146 | N79: 0.017756 | O79: 0.015966 | P79: 0.01446 | Q79: 0.012975 | R79: 0.011777 | S79: 0.010739 | T79: 0.009934 | U79: 0.009025 | V79: 0.008495 | W79: 0.007977 | X79: 0.007621 | Y79: 0.0069 | Z79: 0.00664 | AA79: 0.00658 | AB79: 0.006774 | AC79: 0.006276 | AD79: 0.005978 | AE79: -0.073
A80: Jet Fuel | B80: Energy Use: Delivered: All Sectors: Jet Fuel: Alternative Electricity and Transportation | C80: AEO.2026.ELECTRNP.CNSM_ENU_ALLS_NA_JFL_DELV_NA_QBTU.A | D80: quads | E80: 3.557093 | F80: 3.608027 | G80: 3.627769 | H80: 3.624877 | I80: 3.638196 | J80: 3.662257 | K80: 3.684337 | L80: 3.716255 | M80: 3.750722 | N80: 3.792531 | O80: 3.842687 | P80: 3.878021 | Q80: 3.916799 | R80: 3.953958 | S80: 3.989694 | T80: 4.025865 | U80: 4.057531 | V80: 4.092217 | W80: 4.128225 | X80: 4.163147 | Y80: 4.197931 | Z80: 4.228963 | AA80: 4.25522 | AB80: 4.281323 | AC80: 4.303166 | AD80: 4.326766 | AE80: 0.008
A81: Kerosene | B81: Energy Use: Delivered: All Sectors: Kerosene: Alternative Electricity and Transportation | C81: AEO.2026.ELECTRNP.CNSM_ENU_ALLS_NA_KRS_DELV_NA_QBTU.A | D81: quads | E81: 0.006868 | F81: 0.007938 | G81: 0.007965 | H81: 0.007613 | I81: 0.007334 | J81: 0.007643 | K81: 0.00721 | L81: 0.00701 | M81: 0.006598 | N81: 0.006516 | O81: 0.006236 | P81: 0.006176 | Q81: 0.006013 | R81: 0.005875 | S81: 0.005834 | T81: 0.005759 | U81: 0.005621 | V81: 0.005537 | W81: 0.005441 | X81: 0.00535 | Y81: 0.005217 | Z81: 0.005133 | AA81: 0.005028 | AB81: 0.004964 | AC81: 0.004921 | AD81: 0.004898 | AE81: -0.013
A82: Distillate Fuel Oil | B82: Energy Use: Delivered: All Sectors: Distillate Fuel Oil: Alternative Electricity and Transportation | C82: AEO.2026.ELECTRNP.CNSM_ENU_ALLS_NA_DFO_DELV_NA_QBTU.A | D82: quads | E82: 8.646882 | F82: 8.788788 | G82: 8.778279 | H82: 8.736961 | I82: 8.710678 | J82: 8.712256 | K82: 8.678218 | L82: 8.654596 | M82: 8.607762 | N82: 8.571997 | O82: 8.54481 | P82: 8.515424 | Q82: 8.490535 | R82: 8.464714 | S82: 8.440629 | T82: 8.420507 | U82: 8.397062 | V82: 8.372875 | W82: 8.346867 | X82: 8.324783 | Y82: 8.313959 | Z82: 8.308246 | AA82: 8.306618 | AB82: 8.293822 | AC82: 8.278459 | AD82: 8.262262 | AE82: -0.002
A83: Residual Fuel Oil | B83: Energy Use: Delivered: All Sectors: Residual Fuel Oil: Alternative Electricity and Transportation | C83: AEO.2026.ELECTRNP.CNSM_ENU_ALLS_NA_RFO_DELV_NA_QBTU.A | D83: quads | E83: 0.598157 | F83: 0.578717 | G83: 0.587935 | H83: 0.608342 | I83: 0.612441 | J83: 0.619377 | K83: 0.620618 | L83: 0.628415 | M83: 0.637186 | N83: 0.646728 | O83: 0.654541 | P83: 0.662221 | Q83: 0.667774 | R83: 0.673277 | S83: 0.678298 | T83: 0.682127 | U83: 0.685283 | V83: 0.691338 | W83: 0.697448 | X83: 0.703108 | Y83: 0.709627 | Z83: 0.716088 | AA83: 0.722134 | AB83: 0.727785 | AC83: 0.733957 | AD83: 0.740775 | AE83: 0.009
A84: Petrochemical Feedstocks | B84: Energy Use: Delivered: All Sectors: Petrochemical Feedstocks: Alternative Electricity and Transportation | C84: AEO.2026.ELECTRNP.CNSM_ENU_ALLS_NA_PCF_DELV_NA_QBTU.A | D84: quads | E84: 0.412934 | F84: 0.338138 | G84: 0.3482 | H84: 0.55 | I84: 0.55 | J84: 0.55 | K84: 0.55 | L84: 0.55 | M84: 0.55 | N84: 0.55 | O84: 0.55 | P84: 0.55 | Q84: 0.55 | R84: 0.55 | S84: 0.55 | T84: 0.55 | U84: 0.55 | V84: 0.55 | W84: 0.55 | X84: 0.55 | Y84: 0.55 | Z84: 0.55 | AA84: 0.55 | AB84: 0.55 | AC84: 0.55 | AD84: 0.55 | AE84: 0.012
A85: Other Petroleum | B85: Energy Use: Delivered: All Sectors: Other Petroleum: Alternative Electricity and Transportation | C85: AEO.2026.ELECTRNP.CNSM_ENU_ALLS_NA_ONP_DELV_NA_QBTU.A | D85: quads | E85: 3.179936 | F85: 3.19121 | G85: 3.167704 | H85: 3.26728 | I85: 3.287591 | J85: 3.316553 | K85: 3.307412 | L85: 3.3359 | M85: 3.352306 | N85: 3.368262 | O85: 3.373514 | P85: 3.38396 | Q85: 3.404499 | R85: 3.411421 | S85: 3.418971 | T85: 3.43832 | U85: 3.449108 | V85: 3.457932 | W85: 3.4672 | X85: 3.470064 | Y85: 3.476701 | Z85: 3.461695 | AA85: 3.482613 | AB85: 3.472592 | AC85: 3.48259 | AD85: 3.46885 | AE85: 0.003
A86: Petroleum and Other Liquids Subtotal | B86: Energy Use: Delivered: All Sectors: Liquid Fuels Subtotal: Alternative Electricity and Transportation | C86: AEO.2026.ELECTRNP.CNSM_ENU_ALLS_NA_LFL_DELV_NA_QBTU.A | D86: quads | E86: 37.277641 | F86: 37.264435 | G86: 37.30574 | H86: 37.278423 | I86: 36.982128 | J86: 36.794785 | K86: 36.572968 | L86: 36.448967 | M86: 36.293293 | N86: 36.237305 | O86: 36.182335 | P86: 36.098324 | Q86: 36.018917 | R86: 35.951622 | S86: 35.92041 | T86: 35.923752 | U86: 35.92511 | V86: 35.920055 | W86: 35.946281 | X86: 35.957088 | Y86: 36.003914 | Z86: 36.019905 | AA86: 36.095932 | AB86: 36.085854 | AC86: 36.06134 | AD86: 36.068928 | AE86: -0.001
A87: Natural Gas | B87: Energy Use: Delivered: All Sectors: Natural Gas: Alternative Electricity and Transportation | C87: AEO.2026.ELECTRNP.CNSM_ENU_ALLS_NA_NG_DELV_NA_QBTU.A | D87: quads | E87: 16.543232 | F87: 16.212402 | G87: 16.242493 | H87: 16.224749 | I87: 16.143257 | J87: 16.054417 | K87: 16.00495 | L87: 15.966595 | M87: 15.909042 | N87: 15.88644 | O87: 15.867111 | P87: 15.843314 | Q87: 15.797744 | R87: 15.773771 | S87: 15.756421 | T87: 15.762726 | U87: 15.77496 | V87: 15.824083 | W87: 15.881479 | X87: 15.93709 | Y87: 16.003534 | Z87: 16.050909 | AA87: 16.110601 | AB87: 16.152266 | AC87: 16.182772 | AD87: 16.247417 | AE87: -0.001
A88: Lease and Plant Fuel | B88: Energy Use: Delivered: All Sectors: Lease and Plant Fuel: Alternative Electricity and Transportation | C88: AEO.2026.ELECTRNP.CNSM_ENU_ALLS_NA_LSAPFL_DELV_NA_QBTU.A | D88: quads | E88: 2.136239 | F88: 2.128485 | G88: 2.16034 | H88: 2.165232 | I88: 2.162156 | J88: 2.203182 | K88: 2.264353 | L88: 2.334959 | M88: 2.395234 | N88: 2.452581 | O88: 2.473735 | P88: 2.482664 | Q88: 2.492755 | R88: 2.506868 | S88: 2.524662 | T88: 2.567465 | U88: 2.601775 | V88: 2.630552 | W88: 2.644943 | X88: 2.647805 | Y88: 2.645955 | Z88: 2.656424 | AA88: 2.673549 | AB88: 2.689496 | AC88: 2.689622 | AD88: 2.684877 | AE88: 0.009
... A103: Total | B103: Energy Use: Delivered: All Sectors: Total: Alternative Electricity and Transportation | C103: AEO.2026.ELECTRNP.CNSM_ENU_ALLS_NA_TOT_NA_NA_QBTU.A | D103: quads | E103: 95.285934 | F103: 95.617922 | G103: 94.178246 | H103: 93.62597 | I103: 93.102413 | J103: 92.837203 | K103: 92.238933 | L103: 92.032809 | M103: 91.932909 | N103: 91.938824 | O103: 92.000271 | P103: 92.042186 | Q103: 92.177298 | R103: 92.388636 | S103: 92.609177 | T103: 92.83222 | U103: 93.041712 | V103: 93.355441 | W103: 93.703781 | X103: 94.044222 | Y103: 94.442532 | Z103: 94.792711 | AA103: 95.234041 | AB103: 95.538493 | AC103: 95.708452 | AD103: 95.987854 | AE103: 0
A104: Electric Power
A105: Distillate Fuel Oil | B105: Energy Use: Electric Power: Distillate Fuel Oil: Alternative Electricity and Transportation | C105: AEO.2026.ELECTRNP.CNSM_ENU_ELEP_NA_DFO_NA_NA_QBTU.A | D105: quads | E105: 0.073607 | F105: 0.069322 | G105: 0.062622 | H105: 0.057161 | I105: 0.05441 | J105: 0.053268 | K105: 0.046351 | L105: 0.044252 | M105: 0.042729 | N105: 0.041557 | O105: 0.039856 | P105: 0.039032 | Q105: 0.037986 | R105: 0.036325 | S105: 0.035567 | T105: 0.034393 | U105: 0.033044 | V105: 0.030996 | W105: 0.029543 | X105: 0.027529 | Y105: 0.026179 | Z105: 0.026082 | AA105: 0.025358 | AB105: 0.025328 | AC105: 0.024867 | AD105: 0.025062 | AE105: -0.042
A106: Residual Fuel Oil | B106: Energy Use: Electric Power: Residual Fuel Oil: Alternative Electricity and Transportation | C106: AEO.2026.ELECTRNP.CNSM_ENU_ELEP_NA_RFO_NA_NA_QBTU.A | D106: quads | E106: 0.064062 | F106: 0.063801 | G106: 0.061447 | H106: 0.057519 | I106: 0.056238 | J106: 0.055711 | K106: 0.053856 | L106: 0.052138 | M106: 0.050618 | N106: 0.048918 | O106: 0.047375 | P106: 0.045979 | Q106: 0.04426 | R106: 0.042675 | S106: 0.041058 | T106: 0.039361 | U106: 0.035798 | V106: 0.03202 | W106: 0.028277 | X106: 0.024463 | Y106: 0.020596 | Z106: 0.020458 | AA106: 0.020431 | AB106: 0.020438 | AC106: 0.020433 | AD106: 0.020424 | AE106: -0.045
A107: Petroleum and Other Liquids Subtotal | B107: Energy Use: Electric Power: Liquid Fuels Subtotal: Alternative Electricity and Transportation | C107: AEO.2026.ELECTRNP.CNSM_ENU_ELEP_NA_LFL_NA_NA_QBTU.A | D107: quads | E107: 0.137669 | F107: 0.133122 | G107: 0.124069 | H107: 0.11468 | I107: 0.110648 | J107: 0.108979 | K107: 0.100208 | L107: 0.09639 | M107: 0.093347 | N107: 0.090475 | O107: 0.087231 | P107: 0.08501 | Q107: 0.082245 | R107: 0.079 | S107: 0.076625 | T107: 0.073754 | U107: 0.068841 | V107: 0.063016 | W107: 0.057821 | X107: 0.051992 | Y107: 0.046775 | Z107: 0.04654 | AA107: 0.045788 | AB107: 0.045766 | AC107: 0.0453 | AD107: 0.045486 | AE107: -0.043
A108: Natural Gas | B108: Energy Use: Electric Power: Natural Gas: Alternative Electricity and Transportation | C108: AEO.2026.ELECTRNP.CNSM_ENU_ELEP_NA_NG_NA_NA_QBTU.A | D108: quads | E108: 13.254009 | F108: 13.760337 | G108: 12.098905 | H108: 11.831322 | I108: 11.51959 | J108: 11.194534 | K108: 11.589209 | L108: 11.727729 | M108: 11.778518 | N108: 11.781666 | O108: 11.647706 | P108: 11.591108 | Q108: 11.70478 | R108: 11.819704 | S108: 11.911785 | T108: 12.08897 | U108: 12.209418 | V108: 12.438971 | W108: 12.751798 | X108: 13.023241 | Y108: 13.301497 | Z108: 13.585675 | AA108: 13.776622 | AB108: 13.974996 | AC108: 14.206823 | AD108: 14.350322 | AE108: 0.003
A109: Steam Coal | B109: Energy Use: Electric Power: Steam Coal: Alternative Electricity and Transportation | C109: AEO.2026.ELECTRNP.CNSM_ENU_ELEP_NA_STC_NA_NA_QBTU.A | D109: quads | E109: 7.51277 | F109: 7.194314 | G109: 6.610365 | H109: 5.897705 | I109: 5.780149 | J109: 5.756329 | K109: 4.801369 | L109: 4.407804 | M109: 4.241562 | N109: 3.987547 | O109: 3.963866 | P109: 3.898126 | Q109: 3.829367 | R109: 3.826789 | S109: 3.800425 | T109: 3.634791 | U109: 3.544769 | V109: 3.467078 | W109: 3.360476 | X109: 3.281324 | Y109: 3.226048 | Z109: 3.168838 | AA109: 3.191427 | AB109: 3.194729 | AC109: 3.086876 | AD109: 2.921594 | AE109: -0.037
A110: Nuclear / Uranium | B110: Energy Use: Electric Power: Nuclear: Alternative Electricity and Transportation | C110: AEO.2026.ELECTRNP.CNSM_ENU_ELEP_NA_NUC_NA_NA_QBTU.A | D110: quads | E110: 8.187651 | F110: 8.372738 | G110: 8.321443 | H110: 8.357332 | I110: 8.366615 | J110: 8.373707 | K110: 8.373858 | L110: 8.373865 | M110: 8.373583 | N110: 8.373583 | O110: 8.373577 | P110: 8.373578 | Q110: 8.370988 | R110: 8.366815 | S110: 8.368925 | T110: 8.36346 | U110: 8.357713 | V110: 8.371456 | W110: 8.365458 | X110: 8.373578 | Y110: 8.373578 | Z110: 8.373578 | AA110: 8.373579 | AB110: 8.373578 | AC110: 8.373578 | AD110: 8.373294 | AE110: 0.001
A111: Renewable Energy | B111: Energy Use: Electric Power: Renewable Energy: Alternative Electricity and Transportation | C111: AEO.2026.ELECTRNP.CNSM_ENU_ELEP_NA_REN_NA_NA_QBTU.A | D111: quads | E111: 3.717869 | F111: 4.061838 | G111: 4.668332 | H111: 5.063529 | I111: 5.282516 | J111: 5.446818 | K111: 5.604444 | L111: 5.702966 | M111: 5.829032 | N111: 6.005538 | O111: 6.205722 | P111: 6.411592 | Q111: 6.558394 | R111: 6.678237 | S111: 6.802344 | T111: 6.919462 | U111: 7.019967 | V111: 7.063256 | W111: 7.081019 | X111: 7.095361 | Y111: 7.107094 | Z111: 7.122409 | AA111: 7.144881 | AB111: 7.160776 | AC111: 7.185832 | AD111: 7.39609 | AE111: 0.028
A112: Hydrogen | B112: Energy Use: Electric Power: Hydrogen: Alternative Electricity and Transportation | C112: AEO.2026.ELECTRNP.CNSM_ENU_ELEP_NA_HDG_NA_NA_QBTU.A | D112: quads | E112: 0 | F112: 0 | G112: 0 | H112: 0 | I112: 0 | J112: 0 | K112: 0 | L112: 0 | M112: 0 | N112: 0 | O112: 0 | P112: 0 | Q112: 0 | R112: 0 | S112: 0 | T112: 0 | U112: 0 | V112: 0 | W112: 0 | X112: 0 | Y112: 0 | Z112: 0 | AA112: 0 | AB112: 0 | AC112: 0.004984 | AD112: 0.005515 | AE112: - -
A113: Non-biogenic Municipal Waste | B113: Energy Use: Electric Power: Non-biogenic Municipal Waste: Alternative Electricity and Transportation | C113: AEO.2026.ELECTRNP.CNSM_ENU_ELEP_NA_NBMSW_NA_NA_QBTU.A | D113: quads | E113: 0.069292 | F113: 0.069292 | G113: 0.069292 | H113: 0.069292 | I113: 0.069292 | J113: 0.069292 | K113: 0.069292 | L113: 0.069292 | M113: 0.069292 | N113: 0.069292 | O113: 0.069292 | P113: 0.069292 | Q113: 0.069292 | R113: 0.069292 | S113: 0.069292 | T113: 0.069292 | U113: 0.069292 | V113: 0.069292 | W113: 0.069292 | X113: 0.069292 | Y113: 0.069292 | Z113: 0.069292 | AA113: 0.069292 | AB113: 0.069292 | AC113: 0.069292 | AD113: 0.069292 | AE113: 0
A114: Electricity Imports | B114: Energy Use: Electric Power: Electricity Imports: Alternative Electricity and Transportation | C114: AEO.2026.ELECTRNP.CNSM_ENU_ELEP_NA_ELI_NA_NA_QBTU.A | D114: quads | E114: 0.08228 | F114: 0.106062 | G114: 0.19597 | H114: 0.235466 | I114: 0.255448 | J114: 0.279835 | K114: 0.285335 | L114: 0.290467 | M114: 0.300253 | N114: 0.304316 | O114: 0.309149 | P114: 0.300601 | Q114: 0.298927 | R114: 0.297556 | S114: 0.294068 | T114: 0.297165 | U114: 0.296862 | V114: 0.283909 | W114: 0.272758 | X114: 0.268169 | Y114: 0.266944 | Z114: 0.251526 | AA114: 0.242033 | AB114: 0.232839 | AC114: 0.222683 | AD114: 0.213269 | AE114: 0.039
A115: Total Energy | B115: Energy Use: Electric Power: Total Energy: Alternative Electricity and Transportation | C115: AEO.2026.ELECTRNP.CNSM_ENU_ELEP_NA_TEN_NA_NA_QBTU.A | D115: quads | E115: 32.96154 | F115: 33.697704 | G115: 32.088379 | H115: 31.569326 | I115: 31.384258 | J115: 31.229492 | K115: 30.823715 | L115: 30.66851 | M115: 30.685587 | N115: 30.612415 | O115: 30.656542 | P115: 30.729305 | Q115: 30.913994 | R115: 31.137394 | S115: 31.323463 | T115: 31.446892 | U115: 31.566862 | V115: 31.756975 | W115: 31.95862 | X115: 32.162956 | Y115: 32.391228 | Z115: 32.617863 | AA115: 32.84362 | AB115: 33.051979 | AC115: 33.190388 | AD115: 33.36935 | AE115: 0
A116: Hydrogen-Related Losses | B116: Energy Use: Electric Power: Hydrogen Related Losses: Alternative Electricity and Transportation | C116: AEO.2026.ELECTRNP.CNSM_ENU_ELEP_NA_H2RELLOS_NA_NA_QBTU.A | D116: quads | E116: 0 | F116: 0 | G116: 0 | H116: 0 | I116: 0 | J116: 0 | K116: 0 | L116: 0 | M116: 0 | N116: 0 | O116: 0 | P116: 0 | Q116: 0 | R116: 0 | S116: 0 | T116: 0 | U116: 0 | V116: 0 | W116: 0 | X116: 0 | Y116: 0 | Z116: 0 | AA116: 0 | AB116: 0 | AC116: 2e-06 | AD116: 2e-06 | AE116: - -
A117: Total | B117: Energy Use: Electric Power: Total: Alternative Electricity and Transportation | C117: AEO.2026.ELECTRNP.CNSM_ENU_ELEP_NA_TOT_NA_NA_QBTU.A | D117: quads | E117: 32.96154 | F117: 33.697704 | G117: 32.088379 | H117: 31.569326 | I117: 31.384258 | J117: 31.229492 | K117: 30.823715 | L117: 30.66851 | M117: 30.685587 | N117: 30.612415 | O117: 30.656542 | P117: 30.729305 | Q117: 30.913994 | R117: 31.137394 | S117: 31.323463 | T117: 31.446892 | U117: 31.566862 | V117: 31.756975 | W117: 31.95862 | X117: 32.162956 | Y117: 32.391228 | Z117: 32.617863 | AA117: 32.84362 | AB117: 33.051979 | AC117: 33.190392 | AD117: 33.369354 | AE117: 0
A118: Industrial: Hydrogen Production
A119: Natural Gas | B119: Energy Use: Industrial: Hydrogen Production: Natural Gas: Alternative Electricity and Transportation | C119: AEO.2026.ELECTRNP.INDH2_ENU_TEN_NA_NGAS_NA_NA_QBTU.A | D119: quads | E119: 1.052703 | F119: 0.972878 | G119: 0.965849 | H119: 0.970576 | I119: 0.989773 | J119: 0.986377 | K119: 0.970586 | L119: 0.967189 | M119: 0.970868 | N119: 0.996409 | O119: 1.004413 | P119: 1.004673 | Q119: 1.024941 | R119: 1.033659 | S119: 1.040166 | T119: 1.03831 | U119: 1.041728 | V119: 1.043187 | W119: 1.051639 | X119: 1.077071 | Y119: 1.092677 | Z119: 1.097955 | AA119: 1.107665 | AB119: 1.112769 | AC119: 1.117026 | AD119: 1.121287 | AE119: 0.003
A120: Purchased Electricity | B120: Energy Use: Industrial: Hydrogen Production: Purchased Electricity: Alternative Electricity and Transportation | C120: AEO.2026.ELECTRNP.INDH2_ENU_TEN_NA_PURCHELEC_NA_NA_QBTU.A | D120: quads | E120: 0.004232 | F120: 0.008701 | G120: 0.009063 | H120: 0.007734 | I120: 0.010198 | J120: 0.01061 | K120: 0.009538 | L120: 0.008913 | M120: 0.008893 | N120: 0.009014 | O120: 0.009089 | P120: 0.008562 | Q120: 0.007197 | R120: 0.005265 | S120: 0.005281 | T120: 0.005276 | U120: 0.00264 | V120: 0.002644 | W120: 0.002666 | X120: 0.00273 | Y120: 0.00277 | Z120: 0.002783 | AA120: 0.002808 | AB120: 0.00282 | AC120: 0.002831 | AD120: 0.002842 | AE120: -0.016
A121: Byproduct Hydrogen | B121: Energy Use: Alternative Electricity and Transportation | C121: AEO.2026.ELECTRNP.INDH2_ENU_TEN_NA_NA_NA_NA_NA.A | D121: quads | E121: 0.271885 | F121: 0.277033 | G121: 0.280171 | H121: 0.278806 | I121: 0.274321 | J121: 0.274384 | K121: 0.27545 | L121: 0.275836 | M121: 0.27796 | N121: 0.279312 | O121: 0.283083 | P121: 0.285696 | Q121: 0.286439 | R121: 0.289535 | S121: 0.292548 | T121: 0.295295 | U121: 0.299385 | V121: 0.303157 | W121: 0.306922 | X121: 0.30974 | Y121: 0.312859 | Z121: 0.31681 | AA121: 0.320986 | AB121: 0.32468 | AC121: 0.327309 | AD121: 0.330866 | AE121: 0.008
A122: Total Energy | B122: Energy Use: Industrial: Hydrogen Production: Total Energy: Alternative Electricity and Transportation | C122: AEO.2026.ELECTRNP.INDH2_ENU_TEN_NA_TEN_NA_NA_QBTU.A | D122: quads | E122: 1.328821 | F122: 1.258612 | G122: 1.255083 | H122: 1.257116 | I122: 1.274292 | J122: 1.271371 | K122: 1.255574 | L122: 1.251938 | M122: 1.257721 | N122: 1.284734 | O122: 1.296585 | P122: 1.298931 | Q122: 1.318577 | R122: 1.328459 | S122: 1.337996 | T122: 1.338882 | U122: 1.343754 | V122: 1.348988 | W122: 1.361227 | X122: 1.389541 | Y122: 1.408305 | Z122: 1.417548 | AA122: 1.431458 | AB122: 1.44027 | AC122: 1.447167 | AD122: 1.454996 | AE122: 0.004
A123: Electricity-Related Losses | B123: Energy Use: Industrial: Hydrogen Production: Electricity Related Losses: Alternative Electricity and Transportation | C123: AEO.2026.ELECTRNP.INDH2_ENU_TEN_NA_ELC_NA_NA_QBTU.A | D123: quads | E123: 0.005815 | F123: 0.011841 | G123: 0.011391 | H123: 0.009303 | I123: 0.01199 | J123: 0.012252 | K123: 0.010663 | L123: 0.00977 | M123: 0.009631 | N123: 0.009571 | O123: 0.009507 | P123: 0.008819 | Q123: 0.00734 | R123: 0.005329 | S123: 0.005295 | T123: 0.005228 | U123: 0.002585 | V123: 0.002571 | W123: 0.002577 | X123: 0.002625 | Y123: 0.00265 | Z123: 0.00265 | AA123: 0.002664 | AB123: 0.002666 | AC123: 0.002657 | AD123: 0.002656 | AE123: -0.031
A124: Total | B124: Energy Use: Industrial: Hydrogen Production: Total: Alternative Electricity and Transportation | C124: AEO.2026.ELECTRNP.INDH2_ENU_TEN_NA_TOT_NA_NA_QBTU.A | D124: quads | E124: 1.334636 | F124: 1.270453 | G124: 1.266474 | H124: 1.26642 | I124: 1.286282 | J124: 1.283624 | K124: 1.266236 | L124: 1.261708 | M124: 1.267351 | N124: 1.294306 | O124: 1.306092 | P124: 1.307749 | Q124: 1.325917 | R124: 1.333788 | S124: 1.343291 | T124: 1.344109 | U124: 1.346339 | V124: 1.351559 | W124: 1.363804 | X124: 1.392166 | Y124: 1.410955 | Z124: 1.420199 | AA124: 1.434122 | AB124: 1.442936 | AC124: 1.449823 | AD124: 1.457651 | AE124: 0.004
A125: Total Energy Consumption
A126: Liquefied Petroleum Gases and Other | B126: Energy Use: Total: Liquefied Petroleum Gases: Alternative Electricity and Transportation | C126: AEO.2026.ELECTRNP.CNSM_ENU_TEN_NA_LPG_NA_NA_QBTU.A | D126: quads | E126: 4.412717 | F126: 4.363256 | G126: 4.542447 | H126: 4.434274 | I126: 4.357844 | J126: 4.347216 | K126: 4.374463 | L126: 4.396647 | M126: 4.429306 | N126: 4.468367 | O126: 4.514799 | P126: 4.572637 | Q126: 4.618139 | R126: 4.66519 | S126: 4.743137 | T126: 4.812687 | U126: 4.889078 | V126: 4.978583 | W126: 5.061882 | X126: 5.146407 | Y126: 5.238511 | Z126: 5.331482 | AA126: 5.433529 | AB126: 5.523942 | AC126: 5.588309 | AD126: 5.677113 | AE126: 0.01
A127: Motor Gasoline | B127: Energy Use: Total: Motor Gasoline: Alternative Electricity and Transportation | C127: AEO.2026.ELECTRNP.CNSM_ENU_TEN_NA_MGS_NA_NA_QBTU.A | D127: quads | E127: 16.463058 | F127: 16.388361 | G127: 16.24544 | H127: 16.049076 | I127: 15.818044 | J127: 15.579481 | K127: 15.350713 | L127: 15.160145 | M127: 14.95941 | N127: 14.832905 | O127: 14.69575 | P127: 14.529889 | Q127: 14.365158 | R127: 14.227191 | S127: 14.093845 | T127: 13.988489 | U127: 13.891426 | V127: 13.771574 | W127: 13.689218 | X127: 13.594233 | Y127: 13.511969 | Z127: 13.418295 | AA127: 13.340791 | AB127: 13.231429 | AC127: 13.119942 | AD127: 13.038264 | AE127: -0.009
A128: of which: E85 | B128: Energy Use: Total: E85: Alternative Electricity and Transportation | C128: AEO.2026.ELECTRNP.CNSM_ENU_TEN_NA_E85_NA_NA_QBTU.A | D128: quads | E128: 0.039571 | F128: 0.031597 | G128: 0.029975 | H128: 0.028061 | I128: 0.025794 | J128: 0.026779 | K128: 0.022985 | L128: 0.021014 | M128: 0.019146 | N128: 0.017756 | O128: 0.015966 | P128: 0.01446 | Q128: 0.012975 | R128: 0.011777 | S128: 0.010739 | T128: 0.009934 | U128: 0.009025 | V128: 0.008495 | W128: 0.007977 | X128: 0.007621 | Y128: 0.0069 | Z128: 0.00664 | AA128: 0.00658 | AB128: 0.006774 | AC128: 0.006276 | AD128: 0.005978 | AE128: -0.073
A129: Jet Fuel | B129: Energy Use: Total: Jet Fuel: Alternative Electricity and Transportation | C129: AEO.2026.ELECTRNP.CNSM_ENU_TEN_NA_JFL_NA_NA_QBTU.A | D129: quads | E129: 3.557093 | F129: 3.608027 | G129: 3.627769 | H129: 3.624877 | I129: 3.638196 | J129: 3.662257 | K129: 3.684337 | L129: 3.716255 | M129: 3.750722 | N129: 3.792531 | O129: 3.842687 | P129: 3.878021 | Q129: 3.916799 | R129: 3.953958 | S129: 3.989694 | T129: 4.025865 | U129: 4.057531 | V129: 4.092217 | W129: 4.128225 | X129: 4.163147 | Y129: 4.197931 | Z129: 4.228963 | AA129: 4.25522 | AB129: 4.281323 | AC129: 4.303166 | AD129: 4.326766 | AE129: 0.008
A130: Kerosene | B130: Energy Use: Total: Kerosene: Alternative Electricity and Transportation | C130: AEO.2026.ELECTRNP.CNSM_ENU_TEN_NA_KRS_NA_NA_QBTU.A | D130: quads | E130: 0.006868 | F130: 0.007938 | G130: 0.007965 | H130: 0.007613 | I130: 0.007334 | J130: 0.007643 | K130: 0.00721 | L130: 0.00701 | M130: 0.006598 | N130: 0.006516 | O130: 0.006236 | P130: 0.006176 | Q130: 0.006013 | R130: 0.005875 | S130: 0.005834 | T130: 0.005759 | U130: 0.005621 | V130: 0.005537 | W130: 0.005441 | X130: 0.00535 | Y130: 0.005217 | Z130: 0.005133 | AA130: 0.005028 | AB130: 0.004964 | AC130: 0.004921 | AD130: 0.004898 | AE130: -0.013
...

Sheet AEO 2025 Table 3 - High Cost
C1: 2024 | D1: 2025 | E1: 2026 | F1: 2027 | G1: 2028 | H1: 2029 | I1: 2030 | J1: 2031 | K1: 2032 | L1: 2033 | M1: 2034 | N1: 2035 | O1: 2036 | P1: 2037 | Q1: 2038 | R1: 2039 | S1: 2040 | T1: 2041 | U1: 2042 | V1: 2043 | W1: 2044 | X1: 2045 | Y1: 2046 | Z1: 2047 | AA1: 2048 | AB1: 2049 | AC1: 2050 | AD1: 2024-2050
B4: highztc.d032125b
C6: Report | D6: Annual Energy Outlook 2025
C7: Scenario | D7: highztc | F7: High Zero-Carbon Technology Cost
C8: Datekey | D8: d032125b
C9: Release Date | E9: April 2025
B10: 3. Energy Prices by Sector and Source
B11: (2024 dollars per MMBtu, unless otherwise noted)
AD12: Avg Annual Change
B13: Sector and Source | C13: 2024 | D13: 2025 | E13: 2026 | F13: 2027 | G13: 2028 | H13: 2029 | I13: 2030 | J13: 2031 | K13: 2032 | L13: 2033 | M13: 2034 | N13: 2035 | O13: 2036 | P13: 2037 | Q13: 2038 | R13: 2039 | S13: 2040 | T13: 2041 | U13: 2042 | V13: 2043 | W13: 2044 | X13: 2045 | Y13: 2046 | Z13: 2047 | AA13: 2048 | AB13: 2049 | AC13: 2050 | AD13: 2024-2050
B15: Residential
A16: PRC000:ba_LiquefiedPetr | B16: Propane | C16: 26.593981 | D16: 25.690693 | E16: 25.882023 | F16: 25.734011 | G16: 25.761881 | H16: 25.984186 | I16: 26.494528 | J16: 27.035074 | K16: 27.848438 | L16: 28.895929 | M16: 29.836832 | N16: 30.497536 | O16: 30.975727 | P16: 31.295523 | Q16: 31.443632 | R16: 31.521713 | S16: 31.634783 | T16: 31.863678 | U16: 32.095478 | V16: 32.443432 | W16: 32.908676 | X16: 33.216011 | Y16: 33.459888 | Z16: 33.58733 | AA16: 33.707253 | AB16: 33.953312 | AC16: 34.455376 | AD16: 0.010010548
A17: PRC000:ba_DistillateFue | B17: Distillate Fuel Oil | C17: 26.158379 | D17: 24.617764 | E17: 24.643763 | F17: 25.310112 | G17: 26.17977 | H17: 27.100401 | I17: 28.068832 | J17: 28.11725 | K17: 28.0326 | L17: 28.357315 | M17: 28.466999 | N17: 28.689667 | O17: 28.809559 | P17: 29.071898 | Q17: 29.171333 | R17: 29.291199 | S17: 29.469152 | T17: 29.758438 | U17: 29.994083 | V17: 30.294477 | W17: 30.955036 | X17: 30.868721 | Y17: 30.956972 | Z17: 30.914091 | AA17: 30.902479 | AB17: 30.934729 | AC17: 31.279491 | AD17: 0.0069003567
A18: PRC000:ba_NaturalGas | B18: Natural Gas | C18: 13.932205 | D18: 12.694278 | E18: 12.476946 | F18: 12.0713 | G18: 11.825522 | H18: 11.708606 | I18: 11.628035 | J18: 11.829365 | K18: 12.259671 | L18: 12.641685 | M18: 12.901601 | N18: 13.046376 | O18: 13.061166 | P18: 13.048336 | Q18: 13.026576 | R18: 12.968637 | S18: 13.000326 | T18: 13.125381 | U18: 13.234643 | V18: 13.327177 | W18: 13.385166 | X18: 13.471466 | Y18: 13.568365 | Z18: 13.612545 | AA18: 13.641063 | AB18: 13.722773 | AC18: 13.794634 | AD18: -0.00038159698
A19: PRC000:ba_Electricity | B19: Electricity | C19: 45.553139 | D19: 45.024025 | E19: 42.541679 | F19: 40.45982 | G19: 40.182793 | H19: 40.569782 | I19: 41.046375 | J19: 41.716888 | K19: 42.268425 | L19: 43.117485 | M19: 43.465755 | N19: 43.342434 | O19: 43.037926 | P19: 42.73064 | Q19: 42.891632 | R19: 42.628983 | S19: 42.525494 | T19: 42.545128 | U19: 42.731728 | V19: 42.921192 | W19: 43.168861 | X19: 43.377872 | Y19: 43.621025 | Z19: 43.79406 | AA19: 44.126114 | AB19: 44.423275 | AC19: 44.787258 | AD19: -0.00065193533
B21: Commercial
A22: PRC000:ca_LiquefiedGas | B22: Propane | C22: 19.0868 | D22: 19.071598 | E22: 19.969246 | F22: 19.804914 | G22: 19.920181 | H22: 20.219919 | I22: 20.798326 | J22: 21.250935 | K22: 22.027008 | L22: 22.973885 | M22: 23.6208 | N22: 23.91017 | O22: 24.102671 | P22: 24.204554 | Q22: 24.180492 | R22: 24.168512 | S22: 24.257711 | T22: 24.494383 | U22: 24.6768 | V22: 25.001261 | W22: 25.422537 | X22: 25.562656 | Y22: 25.683006 | Z22: 25.692684 | AA22: 25.758125 | AB22: 26.007099 | AC22: 26.538202 | AD22: 0.012757161
A23: PRC000:ca_DistillateFue | B23: Distillate Fuel Oil | C23: 26.207932 | D23: 24.707527 | E23: 23.565269 | F23: 23.058794 | G23: 22.754671 | H23: 22.501291 | I23: 22.297827 | J23: 22.340889 | K23: 22.216309 | L23: 22.527172 | M23: 22.633039 | N23: 22.83795 | O23: 22.942883 | P23: 23.194223 | Q23: 23.297205 | R23: 23.403837 | S23: 23.570314 | T23: 23.852497 | U23: 24.078636 | V23: 24.381926 | W23: 25.030125 | X23: 24.942905 | Y23: 25.028816 | Z23: 24.984297 | AA23: 24.964209 | AB23: 25.003876 | AC23: 25.3452 | AD23: -0.001286585
A24: PRC000:ca_ResidualFuel | B24: Residual Fuel Oil | C24: 6.7460785 | D24: 7.4716978 | E24: 7.8411932 | F24: 8.8315973 | G24: 9.9149084 | H24: 11.015342 | I24: 12.183045 | J24: 12.244162 | K24: 12.208694 | L24: 12.446174 | M24: 12.544676 | N24: 12.678741 | O24: 12.753716 | P24: 12.87225 | Q24: 12.979047 | R24: 12.997785 | S24: 13.118733 | T24: 13.235469 | U24: 13.365701 | V24: 13.416109 | W24: 13.347304 | X24: 13.387928 | Y24: 13.678938 | Z24: 13.632569 | AA24: 13.671235 | AB24: 13.775191 | AC24: 14.322314 | AD24: 0.029379356
A25: PRC000:ca_NaturalGas | B25: Natural Gas | C25: 9.5558577 | D25: 8.473628 | E25: 8.571372 | F25: 8.5130539 | G25: 8.5931063 | H25: 8.7674656 | I25: 8.9761992 | J25: 9.1212845 | K25: 9.4725027 | L25: 9.7878332 | M25: 9.9884748 | N25: 10.085086 | O25: 10.067373 | P25: 10.026683 | Q25: 9.9779053 | R25: 9.894558 | S25: 9.8948059 | T25: 9.9813385 | U25: 10.052937 | V25: 10.11166 | W25: 10.137436 | X25: 10.191541 | Y25: 10.258538 | Z25: 10.274831 | AA25: 10.279621 | AB25: 10.336456 | AC25: 10.384078 | AD25: 0.0032020132
A26: PRC000:ca_Electricity | B26: Electricity | C26: 38.551605 | D26: 37.602798 | E26: 35.105431 | F26: 33.124508 | G26: 32.965439 | H26: 33.32024 | I26: 33.809681 | J26: 34.413387 | K26: 34.929173 | L26: 35.701324 | M26: 35.979614 | N26: 35.811676 | O26: 35.482807 | P26: 35.191898 | Q26: 35.411739 | R26: 35.115093 | S26: 34.986004 | T26: 34.99255 | U26: 35.154461 | V26: 35.305714 | W26: 35.501835 | X26: 35.64677 | Y26: 35.79763 | Z26: 35.841282 | AA26: 36.080368 | AB26: 36.286304 | AC26: 36.524944 | AD26: -0.0020748563
B28: Industrial 1/
A29: PRC000:da_LiquefiedPetr | B29: Propane | C29: 12.66026 | D29: 12.605674 | E29: 13.465074 | F29: 13.314802 | G29: 13.427592 | H29: 13.72262 | I29: 14.298682 | J29: 14.759735 | K29: 15.554036 | L29: 16.543209 | M29: 17.23724 | N29: 17.555822 | O29: 17.767212 | P29: 17.880009 | Q29: 17.856604 | R29: 17.844084 | S29: 17.93939 | T29: 18.19438 | U29: 18.394274 | V29: 18.748419 | W29: 19.21232 | X29: 19.372681 | Y29: 19.508192 | Z29: 19.52129 | AA29: 19.593958 | AB29: 19.869528 | AC29: 20.462763 | AD29: 0.018638445
A30: PRC000:da_DistillateFue | B30: Distillate Fuel Oil | C30: 26.091763 | D30: 24.600626 | E30: 23.425852 | F30: 22.88941 | G30: 22.557371 | H30: 22.274755 | I30: 22.032902 | J30: 22.079994 | K30: 21.943752 | L30: 22.273958 | M30: 22.39349 | N30: 22.623447 | O30: 22.746523 | P30: 23.008989 | Q30: 23.10652 | R30: 23.218241 | S30: 23.399351 | T30: 23.679426 | U30: 23.916767 | V30: 24.223963 | W30: 24.880014 | X30: 24.792429 | Y30: 24.880751 | Z30: 24.838329 | AA30: 24.82336 | AB30: 24.858402 | AC30: 25.202454 | AD30: -0.0013328916
A31: PRC000:da_ResidualFuel | B31: Residual Fuel Oil | C31: 7.8346596 | D31: 8.848094 | E31: 9.4351606 | F31: 10.629246 | G31: 11.88067 | H31: 13.214781 | I31: 14.622335 | J31: 14.725853 | K31: 14.700524 | L31: 14.992572 | M31: 15.113938 | N31: 15.285793 | O31: 15.383565 | P31: 15.518867 | Q31: 15.634306 | R31: 15.663942 | S31: 15.779115 | T31: 15.889836 | U31: 16.038828 | V31: 16.101131 | W31: 16.053886 | X31: 16.051018 | Y31: 16.34535 | Z31: 16.306047 | AA31: 16.344069 | AB31: 16.451635 | AC31: 16.998318 | AD31: 0.030238833
A32: PRC000:da_NaturalGas | B32: Natural Gas 2/ | C32: 3.3370697 | D32: 4.0105987 | E32: 3.9114852 | F32: 3.7915206 | G32: 3.869612 | H32: 4.0202494 | I32: 4.2306581 | J32: 4.3900928 | K32: 4.8307548 | L32: 5.1790876 | M32: 5.4123416 | N32: 5.4940538 | O32: 5.4814124 | P32: 5.4307976 | Q32: 5.3706851 | R32: 5.2902527 | S32: 5.3106718 | T32: 5.4036393 | U32: 5.4864745 | V32: 5.5612407 | W32: 5.6156774 | X32: 5.6656322 | Y32: 5.7171302 | Z32: 5.7226496 | AA32: 5.7369003 | AB32: 5.7977052 | AC32: 5.8629346 | AD32: 0.021911891
A33: PRC000:da_Metallurgical | B33: Metallurgical Coal | C33: 7.7677546 | D33: 7.6397476 | E33: 7.5851479 | F33: 7.5552115 | G33: 7.5209308 | H33: 7.512826 | I33: 7.5104437 | J33: 7.5159492 | K33: 7.537591 | L33: 7.5371671 | M33: 7.4998899 | N33: 7.5180893 | O33: 7.5179672 | P33: 7.5155568 | Q33: 7.5172701 | R33: 7.4982648 | S33: 7.496222 | T33: 7.4669147 | U33: 7.461041 | V33: 7.4532318 | W33: 7.4581027 | X33: 7.4715109 | Y33: 7.4675255 | Z33: 7.4625101 | AA33: 7.4612651 | AB33: 7.4693666 | AC33: 7.4669428 | AD33: -0.0015179039
A34: PRC000:da_SteamCoal | B34: Other Industrial Coal | C34: 3.5721552 | D34: 3.6240985 | E34: 3.6188056 | F34: 3.6017685 | G34: 3.5713363 | H34: 3.5591495 | I34: 3.5335374 | J34: 3.4978511 | K34: 3.4641423 | L34: 3.4595869 | M34: 3.4414332 | N34: 3.4154491 | O34: 3.4216378 | P34: 3.4235449 | Q34: 3.4324207 | R34: 3.4286089 | S34: 3.4309132 | T34: 3.4251916 | U34: 3.418891 | V34: 3.4220879 | W34: 3.4260631 | X34: 3.4342356 | Y34: 3.4441748 | Z34: 3.4487486 | AA34: 3.4481359 | AB34: 3.4493465 | AC34: 3.4545162 | AD34: -0.0012871214
A35: PRC000:da_Hydrogen | B35: Hydrogen | C35: 9.5338745 | D35: 10.619709 | E35: 10.514131 | F35: 10.426125 | G35: 10.55792 | H35: 10.787679 | I35: 11.065716 | J35: 11.319676 | K35: 11.63994 | L35: 12.155972 | M35: 12.524699 | N35: 12.666781 | O35: 12.616203 | P35: 12.533028 | Q35: 12.742199 | R35: 12.81229 | S35: 12.800771 | T35: 12.675635 | U35: 12.587033 | V35: 12.651853 | W35: 12.824852 | X35: 12.7927 | Y35: 12.813029 | Z35: 12.789708 | AA35: 12.823941 | AB35: 12.685263 | AC35: 12.783066 | AD35: 0.011343475
A36: PRC000:da_Electricity | B36: Electricity | C36: 26.507746 | D36: 25.922054 | E36: 23.537739 | F36: 22.156487 | G36: 22.004316 | H36: 22.322678 | I36: 22.749052 | J36: 23.346399 | K36: 23.998974 | L36: 24.751463 | M36: 24.95269 | N36: 24.768763 | O36: 24.45256 | P36: 24.243956 | Q36: 24.34145 | R36: 24.228069 | S36: 24.145441 | T36: 24.157953 | U36: 24.287434 | V36: 24.39603 | W36: 24.534168 | X36: 24.641457 | Y36: 24.755726 | Z36: 24.854349 | AA36: 25.022724 | AB36: 25.199516 | AC36: 25.411121 | AD36: -0.0016236825
B38: Transportation
A39: PRC000:ea_LiquefiedPetr | B39: Propane | C39: 17.589245 | D39: 17.749908 | E39: 18.586613 | F39: 18.389212 | G39: 18.496126 | H39: 18.760077 | I39: 19.2631 | J39: 19.634487 | K39: 20.300226 | L39: 21.098251 | M39: 21.613922 | N39: 21.826738 | O39: 21.975828 | P39: 22.052736 | Q39: 22.024448 | R39: 22.014761 | S39: 22.09473 | T39: 22.299959 | U39: 22.448139 | V39: 22.723597 | W39: 23.076363 | X39: 23.174244 | Y39: 23.269659 | Z39: 23.270405 | AA39: 23.326803 | AB39: 23.542395 | AC39: 23.995331 | AD39: 0.01201669
A40: PRC000:ea_Ethanol(E85) | B40: E85 3/ | C40: 28.823729 | D40: 28.93619 | E40: 30.221819 | F40: 29.874352 | G40: 29.356659 | H40: 28.412943 | I40: 28.414833 | J40: 28.528875 | K40: 28.297775 | L40: 28.022879 | M40: 27.970562 | N40: 27.737436 | O40: 27.879841 | P40: 27.706806 | Q40: 27.335274 | R40: 27.221582 | S40: 26.936087 | T40: 26.624407 | U40: 26.243464 | V40: 26.249161 | W40: 24.929926 | X40: 24.592495 | Y40: 24.79623 | Z40: 24.925064 | AA40: 24.988291 | AB40: 25.141323 | AC40: 25.433138 | AD40: -0.0048017419
A41: PRC000:ea_MotorGasoline | B41: Motor Gasoline 4/ | C41: 28.679842 | D41: 27.094545 | E41: 25.485424 | F41: 24.986969 | G41: 24.719851 | H41: 24.436867 | I41: 24.474363 | J41: 24.48147 | K41: 24.300167 | L41: 24.154732 | M41: 24.09795 | N41: 23.894083 | O41: 24.019566 | P41: 23.870735 | Q41: 23.556276 | R41: 23.430714 | S41: 23.173237 | T41: 22.909204 | U41: 22.57633 | V41: 22.596951 | W41: 21.468903 | X41: 21.182211 | Y41: 21.356647 | Z41: 21.464962 | AA41: 21.509295 | AB41: 21.631233 | AC41: 21.869665 | AD41: -0.010372522
A42: PRC000:ea_JetFuel | B42: Jet Fuel 5/ | C42: 17.638924 | D42: 16.395 | E42: 16.197346 | F42: 16.576864 | G42: 17.167725 | H42: 17.774681 | I42: 18.432444 | J42: 18.550699 | K42: 18.432102 | L42: 18.750156 | M42: 18.878136 | N42: 19.088032 | O42: 19.162302 | P42: 19.413189 | Q42: 19.636925 | R42: 19.743242 | S42: 19.910463 | T42: 20.238554 | U42: 20.505775 | V42: 20.876812 | W42: 21.614872 | X42: 21.580616 | Y42: 21.698483 | Z42: 21.705061 | AA42: 21.706541 | AB42: 21.788584 | AC42: 22.195864 | AD42: 0.0088775554
A43: PRC000:ea_DistillateFue | B43: Diesel Fuel (distillate fuel oil) 6/ | C43: 27.283649 | D43: 25.591213 | E43: 25.016569 | F43: 25.029736 | G43: 25.250086 | H43: 25.481937 | I43: 25.837044 | J43: 25.879503 | K43: 25.733622 | L43: 26.102192 | M43: 26.219612 | N43: 26.457941 | O43: 26.618042 | P43: 26.882929 | Q43: 26.978115 | R43: 27.113096 | S43: 27.266804 | T43: 27.578503 | U43: 27.813025 | V43: 28.145802 | W43: 28.854143 | X43: 28.858868 | Y43: 28.825182 | Z43: 28.706501 | AA43: 28.759977 | AB43: 28.70521 | AC43: 29.126087 | AD43: 0.0025164933
A44: PRC000:ea_ResidualFuel | B44: Residual Fuel Oil | C44: 13.401297 | D44: 11.843807 | E44: 12.665238 | F44: 12.576532 | G44: 12.510175 | H44: 12.503057 | I44: 12.525302 | J44: 12.597067 | K44: 12.550599 | L44: 12.745926 | M44: 12.831242 | N44: 12.954171 | O44: 13.008114 | P44: 13.096881 | Q44: 13.191089 | R44: 13.218472 | S44: 13.301097 | T44: 13.406687 | U44: 13.509968 | V44: 13.614932 | W44: 13.650314 | X44: 13.473039 | Y44: 13.708124 | Z44: 13.688977 | AA44: 13.7072 | AB44: 13.794828 | AC44: 14.231298 | AD44: 0.0023139111
A45: PRC000:ea_NaturalGas | B45: Natural Gas 7/ | C45: 14.514303 | D45: 15.045484 | E45: 14.977668 | F45: 14.858115 | G45: 14.908598 | H45: 15.040533 | I45: 15.186421 | J45: 15.299401 | K45: 15.666859 | L45: 15.903211 | M45: 16.017698 | N45: 16.016142 | O45: 15.907859 | P45: 15.77169 | Q45: 15.650945 | R45: 15.47576 | S45: 15.403385 | T45: 15.417639 | U45: 15.41606 | V45: 15.414666 | W45: 15.384685 | X45: 15.361653 | Y45: 15.353804 | Z45: 15.281762 | AA45: 15.215751 | AB45: 15.207031 | AC45: 15.19101 | AD45: 0.0017541977
A46: PRC000:ea_Hydrogen | B46: Hydrogen | C46: 60.468231 | D46: 60.745255 | E46: 60.549759 | F46: 60.44437 | G46: 60.531708 | H46: 60.737736 | I46: 60.991833 | J46: 61.818279 | K46: 62.04599 | L46: 62.676136 | M46: 63.049198 | N46: 63.198536 | O46: 63.044495 | P46: 62.949413 | Q46: 63.204426 | R46: 63.33548 | S46: 63.306995 | T46: 63.132828 | U46: 62.969875 | V46: 63.022812 | W46: 63.25135 | X46: 63.215389 | Y46: 63.382431 | Z46: 63.355698 | AA46: 63.409069 | AB46: 63.016552 | AC46: 63.101322 | AD46: 0.0016407137
A47: PRC000:ea_Electricity | B47: Electricity 8/ | C47: 42.609589 | D47: 42.26667 | E47: 39.670399 | F47: 36.717178 | G47: 36.535248 | H47: 36.81496 | I47: 37.285934 | J47: 38.057724 | K47: 38.70388 | L47: 39.740459 | M47: 40.09803 | N47: 40.153744 | O47: 40.057587 | P47: 39.782898 | Q47: 40.15593 | R47: 39.589664 | S47: 39.300087 | T47: 39.269657 | U47: 39.614471 | V47: 39.822304 | W47: 40.184521 | X47: 40.37289 | Y47: 40.537704 | Z47: 40.4916 | AA47: 41.027618 | AB47: 41.285618 | AC47: 41.592472 | AD47: -0.00092880385
B49: Electric Power 9/
A50: PRC000:ga_DistillateFue | B50: Distillate Fuel Oil | C50: 26.137505 | D50: 24.653458 | E50: 23.463963 | F50: 22.977613 | G50: 22.593882 | H50: 22.342915 | I50: 22.213257 | J50: 22.156206 | K50: 22.726322 | L50: 23.003592 | M50: 23.077461 | N50: 23.249807 | O50: 23.28072 | P50: 23.52141 | Q50: 23.668085 | R50: 23.751266 | S50: 23.886726 | T50: 24.176956 | U50: 24.404095 | V50: 24.709991 | W50: 25.257483 | X50: 25.158951 | Y50: 25.341908 | Z50: 25.316826 | AA50: 25.294249 | AB50: 25.372868 | AC50: 25.729799 | AD50: -0.00060448703
A51: PRC000:ga_ResidualFuel | B51: Residual Fuel Oil | C51: 17.394409 | D51: 13.672506 | E51: 13.615168 | F51: 14.296899 | G51: 15.031581 | H51: 15.753065 | I51: 16.474405 | J51: 16.627272 | K51: 16.536289 | L51: 16.771885 | M51: 16.909727 | N51: 17.088612 | O51: 17.157686 | P51: 17.269447 | Q51: 17.398418 | R51: 17.408293 | S51: 17.490879 | T51: 17.551632 | U51: 17.536398 | V51: 17.589537 | W51: 17.510019 | X51: 16.884666 | Y51: 17.201757 | Z51: 17.213936 | AA51: 17.253027 | AB51: 17.380194 | AC51: 17.916069 | AD51: 0.0011371529
