Workbook

Sheet About
A1: CC Capital Cost of Industrial Energy CCS Equipment
A2: CC Capital Cost of Industrial Process CCS Equipment
A3: CC Capital Cost of Industrial Hydrogen Sector CCS Equipment
A4: CC CCS Total O&M Cost per Ton Industrial Energy CO2 Sequestered
A5: CC CCS Total O&M Cost per Ton Industrial Process CO2 Sequestered
A6: CC CCS Total O&M Cost per Ton Hydrogen Sector CO2 Sequestered
A7: CC Energy Use per Ton Industrial Energy CO2 Sequestered
A8: CC Energy Use per Ton Industrial Process CO2 Sequestered
A9: CC Energy Use per Ton Hydrogen Sector CO2 Sequestered
A11: Source: | B11: Gaffney Cline
B12: National Petroleum Council (NPC) Capture Facility Reference Costs
B13: https://www.gaffneycline.com/calculator/npc-scenarios-table
A15: Notes:
A16: This variable captures the capital and O&M costs and energy use of
A17: carbon capture and sequestration, for both the industry and hydrogen sectors.
A18: It also includes data on energy use per ton CO2 sequestered.
A20: The energy use value here should exclude any energy that is not additional
A21: to the energy already accounted for in indst/BIFUbC.
A22: For example, if a steel mill has excess process heat that
A23: isn't being used, and they use it to power CCS, that heat should be excluded
A24: from here, since it does not increase the overall energy demand of the steel
A25: mill.
A28: 0.88711067 | B28: 2020 to 2012 USD
A30: 3412141 | B30: BTU per MWh
A32: 2026-10-02: the three CC-EUpT* tabs converted BTU per tonne CO2 to BTU per gram
A33: by dividing by 10^12 (and the process tab also applied the 2020->2012 USD deflator
A34: to energy). Corrected to /10^6 with no deflator; values rose ~1e6x, restoring the
A35: capture energy penalty (cement: 8.70 BTU/g gas + 0.546 BTU/g electricity).
A37: 2026-10-23: CC Energy Use per Ton Hydrogen Sector CO2 Sequestered (CC-EUpTHSCS) now comes from NETL 2022
A38: (Data rows 32-46): 1.16 BTU/g natural gas + 0.50 BTU/g electricity, replacing the NPC hydrogen-plant column
A39: (8.70 + 0.61 BTU/g). The industry tabs are unchanged. EPS now also charges this energy at fuel prices in
A40: CCS Cost per Ton Blue Hydrogen Produced (it was used physically but never costed).
A42: 2026-10-23: CapEx per annual tonne (Data row 24) no longer multiplies by (1 + tax rate). The gross-up came in
A43: with the NPC data (e87c7c8a, 2023) without a stated rationale; NPC uses the tax rate inside its levelized
A44: cost, and no other EPS sector marks up capital by an income-tax rate. CapEx and the O&M derived from it
A45: (Data row 27, a % of CapEx) fall by 1/1.21 for every industry and for the hydrogen sector.

Sheet Data
A1: Low Estimates
A3: Facility Type | B3: Natural Gas Processing | C3: Ethanol Production | D3: Ammonia Production | E3: Hydrogen Production | F3: Cement Plant | G3: Refinery Fluidized Catalytic Converter | H3: Iron and Steel Plant | I3: Industrial Furnace
A4: Capacity (tonne / year) | B4: 276216 | C4: 401775 | D4: 458000 | E4: 400000 | F4: 990000 | G4: 440000 | H4: 3910384 | I4: 259016
A5: Total CapEx (US $ / annual tonne) | B5: 16.5 | C5: 21.48 | D5: 24.48 | E5: 58.91 | F5: 148.05 | G5: 135.91 | H5: 805.15 | I5: 91.77
A6: Electricity usage (MWh / tonne) | B6: 0.1 | C6: 0.12 | D6: 0.1 | E6: 0.18 | F6: 0.16 | G6: 0.14 | H6: 0.16 | I6: 0.16
A7: Gas usage (MWh / tonne) | B7: 0 | C7: 0 | D7: 0 | E7: 2.55 | F7: 2.55 | G7: 2.55 | H7: 2.55 | I7: 2.6
A8: OpEx, Non-energy, annual (% CapEx) | B8: 0.06 | C8: 0.07 | D8: 0.05 | E8: 0.05 | F8: 0.07 | G8: 0.04 | H8: 0.05 | I8: 0.04
A9: Tax rate (%) | B9: 0.21 | C9: 0.21 | D9: 0.21 | E9: 0.21 | F9: 0.21 | G9: 0.21 | H9: 0.21 | I9: 0.21
A11: High Estimates
A13: Facility Type | B13: =B3 -> Natural Gas Processing | C13: =C3 -> Ethanol Production | D13: =D3 -> Ammonia Production | E13: =E3 -> Hydrogen Production | F13: =F3 -> Cement Plant | G13: =G3 -> Refinery Fluidized Catalytic Converter | H13: =H3 -> Iron and Steel Plant | I13: =I3 -> Industrial Furnace
A14: Capacity (tonne / year) | B14: =B4 -> 276216 | C14: =C4 -> 401775 | D14: =D4 -> 458000 | E14: =E4 -> 400000 | F14: =F4 -> 990000 | G14: =G4 -> 440000 | H14: =H4 -> 3910384 | I14: =I4 -> 259016
A15: Total CapEx (US $ / annual tonne) | B15: 27.5 | C15: 38.5 | D15: 40.81 | E15: 98.18 | F15: 246.75 | G15: 226.52 | H15: 343.17 | I15: 152.94
A16: Electricity usage (MWh / tonne) | B16: =B6 -> 0.1 | C16: =C6 -> 0.12 | D16: =D6 -> 0.1 | E16: =E6 -> 0.18 | F16: =F6 -> 0.16 | G16: =G6 -> 0.14 | H16: =H6 -> 0.16 | I16: =I6 -> 0.16
A17: Gas usage (MWh / tonne) | B17: =B7 -> 0 | C17: =C7 -> 0 | D17: =D7 -> 0 | E17: =E7 -> 2.55 | F17: =F7 -> 2.55 | G17: =G7 -> 2.55 | H17: =H7 -> 2.55 | I17: =I7 -> 2.6
A18: OpEx, Non-energy, annual (% CapEx) | B18: =B8 -> 0.06 | C18: =C8 -> 0.07 | D18: =D8 -> 0.05 | E18: =E8 -> 0.05 | F18: =F8 -> 0.07 | G18: =G8 -> 0.04 | H18: =H8 -> 0.05 | I18: =I8 -> 0.04
A19: Tax rate (%) | B19: =B9 -> 0.21 | C19: =C9 -> 0.21 | D19: =D9 -> 0.21 | E19: =E9 -> 0.21 | F19: =F9 -> 0.21 | G19: =G9 -> 0.21 | H19: =H9 -> 0.21 | I19: =I9 -> 0.21
A21: Averages
B22: energy pipelines and gas processing 352T353 | C22: chemicals 20 | F22: cement and other nonmetallic minerals 239 | G22: refined petroleum and coke 19 | H22: iron and steel 241
B23: =B3 -> Natural Gas Processing | C23: =C3 -> Ethanol Production | D23: =D3 -> Ammonia Production | E23: =E3 -> Hydrogen Production | F23: =F3 -> Cement Plant | G23: =G3 -> Refinery Fluidized Catalytic Converter | H23: =H3 -> Iron and Steel Plant | I23: =I3 -> Industrial Furnace
A24: CapEx ($ / annual tonne) | B24: =AVERAGE(B5,B15)*10^6/B14 -> 79.647812 | C24: =AVERAGE(C5,C15)*10^6/C14 -> 74.643768 | D24: =AVERAGE(D5,D15)*10^6/D14 -> 71.277293 | E24: =AVERAGE(E5,E15)*10^6/E14 -> 196.3625 | F24: =AVERAGE(F5,F15)*10^6/F14 -> 199.39394 | G24: =AVERAGE(G5,G15)*10^6/G14 -> 411.85227 | H24: =AVERAGE(H5,H15)*10^6/H14 -> 146.82957 | I24: =AVERAGE(I5,I15)*10^6/I14 -> 472.38395 | J24: 2026-10-23: the (1 + tax rate) multiplier was removed. NPC's tax rate is an input to its levelized-cost calculation, not a markup on capital; rows 9 and 19 are kept for reference only.
A25: Electricity usage (BTU / tonne) | B25: =AVERAGE(B6,B16)*About!$A$30 -> 341214.1 | C25: =AVERAGE(C6,C16)*About!$A$30 -> 409456.92 | D25: =AVERAGE(D6,D16)*About!$A$30 -> 341214.1 | E25: =AVERAGE(E6,E16)*About!$A$30 -> 614185.38 | F25: =AVERAGE(F6,F16)*About!$A$30 -> 545942.56 | G25: =AVERAGE(G6,G16)*About!$A$30 -> 477699.74 | H25: =AVERAGE(H6,H16)*About!$A$30 -> 545942.56 | I25: =AVERAGE(I6,I16)*About!$A$30 -> 545942.56
A26: Gas usage (BTU / tonne) | B26: =AVERAGE(B7,B17)*About!$A$30 -> 0 | C26: =AVERAGE(C7,C17)*About!$A$30 -> 0 | D26: =AVERAGE(D7,D17)*About!$A$30 -> 0 | E26: =AVERAGE(E7,E17)*About!$A$30 -> 8700959.5 | F26: =AVERAGE(F7,F17)*About!$A$30 -> 8700959.5 | G26: =AVERAGE(G7,G17)*About!$A$30 -> 8700959.5 | H26: =AVERAGE(H7,H17)*About!$A$30 -> 8700959.5 | I26: =AVERAGE(I7,I17)*About!$A$30 -> 8871566.6
A27: OpEx, Non-energy | B27: =AVERAGE(B8,B18)*B24 -> 4.7788687 | C27: =AVERAGE(C8,C18)*C24 -> 5.2250638 | D27: =AVERAGE(D8,D18)*D24 -> 3.5638646 | E27: =AVERAGE(E8,E18)*E24 -> 9.818125 | F27: =AVERAGE(F8,F18)*F24 -> 13.957576 | G27: =AVERAGE(G8,G18)*G24 -> 16.474091 | H27: =AVERAGE(H8,H18)*H24 -> 7.3414785 | I27: =AVERAGE(I8,I18)*I24 -> 18.895358
A29: *We use ethanol production as a proxy for the chemicals industry, as we expect ammonia production to be decarbonized via
A30: hydrogen electrolysis in our BAU case.
A32: Hydrogen sector capture energy: NETL 2022 SMR with and without CCS (added 2026-10-23)
A33: NETL, Comparison of Commercial, State-of-the-Art, Fossil-Based Hydrogen Production Technologies, DOE/NETL-2022/3241, April 2022, https://www.osti.gov/servlets/purl/1862910
B35: Case 1 SMR, no capture | C35: Case 2 SMR with CCS | D35: Source / formula
A36: Hydrogen production (kg/hr) | B36: 20126 | C36: 20125 | D36: Exhibits 3-5 and 3-23
A37: HHV thermal input, natural gas (kWt) | B37: 1031068 | C37: 1096328 | D37: Exhibits 3-5 and 3-23
A38: Auxiliary electricity load (kWe) | B38: 12650 | C38: =6710+16460+17500 -> 40670 | D38: Exhibits 3-5 and 3-23: balance of plant (+ CO2 capture/removal auxiliaries + CO2 compression in Case 2)
A39: CO2 product (kg carbon/hr) | B39: 0 | C39: 52502 | D39: Exhibit 3-26 carbon balance (overall capture 96.2%)
A40: CO2 captured (tonne CO2/hr) | C40: =C39*44.01/12.011/1000 -> 192.37474 | D40: carbon x 44.01/12.011
A41: Incremental natural gas for capture (BTU/hr) | C41: =(C37-B37)*About!$A$30/1000 -> 2.2267632e+08 | D41: (Case 2 - Case 1 thermal input) x BTU per kWh
A42: Incremental electricity for capture (BTU/hr) | C42: =(C38-B38)*About!$A$30/1000 -> 95608191 | D42: (Case 2 - Case 1 auxiliary load) x BTU per kWh
A43: Natural gas per tonne CO2 captured (BTU/tonne) | C43: =C41/C40 -> 1157513.3
A44: Electricity per tonne CO2 captured (BTU/tonne) | C44: =C42/C40 -> 496989.31
A45: Same hydrogen output in both cases, so the differences are the capture energy. NETL captures 96.2% of plant carbon (syngas and reformer flue gas); EPS captures CCP (0.85) of the production-gas CO2 and applies this per-tonne energy to it.
A46: The NPC/Gaffney Cline hydrogen column above (2.55 MWh gas + 0.18 MWh electricity per tonne) is no longer used for the hydrogen sector: it implied ~+39% gas on an SMR, against ~+6% in NETL.

Sheet CC-CCoIECE
B1: Capital cost ($/(metric ton CO2e*yr))
A2: agriculture and forestry 01T03 | B2: =Data!$I$24*About!$A$28 -> 419.05684
A3: coal mining 05 | B3: =Data!$I$24*About!$A$28 -> 419.05684
A4: oil and gas extraction 06 | B4: =Data!$I$24*About!$A$28 -> 419.05684
A5: other mining and quarrying 07T08 | B5: =Data!$I$24*About!$A$28 -> 419.05684
A6: food beverage and tobacco 10T12 | B6: =Data!$I$24*About!$A$28 -> 419.05684
A7: textiles apparel and leather 13T15 | B7: =Data!$I$24*About!$A$28 -> 419.05684
A8: wood products 16 | B8: =Data!$I$24*About!$A$28 -> 419.05684
A9: pulp paper and printing 17T18 | B9: =Data!$I$24*About!$A$28 -> 419.05684
A10: refined petroleum and coke 19 | B10: =IFERROR(INDEX(Data!$24:$24,MATCH('CC-CCoIPCE'!A10,Data!$22:$22,0)),Data!$I$24)*About!$A$28 -> 365.35855
A11: chemicals 20 | B11: =Data!$I$24*About!$A$28 -> 419.05684
A12: rubber and plastic products 22 | B12: =Data!$I$24*About!$A$28 -> 419.05684
A13: glass and glass products 231 | B13: =Data!$I$24*About!$A$28 -> 419.05684
A14: cement and other nonmetallic minerals 239 | B14: =Data!$I$24*About!$A$28 -> 419.05684
A15: iron and steel 241 | B15: =Data!$I$24*About!$A$28 -> 419.05684
A16: other metals 242 | B16: =Data!$I$24*About!$A$28 -> 419.05684
A17: metal products except machinery and vehicles 25 | B17: =Data!$I$24*About!$A$28 -> 419.05684
A18: computers and electronics 26 | B18: =Data!$I$24*About!$A$28 -> 419.05684
A19: appliances and electrical equipment 27 | B19: =Data!$I$24*About!$A$28 -> 419.05684
A20: other machinery 28 | B20: =Data!$I$24*About!$A$28 -> 419.05684
A21: road vehicles 29 | B21: =Data!$I$24*About!$A$28 -> 419.05684
A22: nonroad vehicles 30 | B22: =Data!$I$24*About!$A$28 -> 419.05684
... A26: construction 41T43 | B26: =Data!$I$24*About!$A$28 -> 419.05684

Sheet CC-CCoIPCE
B1: Capital cost ($/(metric ton CO2e*yr))
A2: agriculture and forestry 01T03 | B2: =IFERROR(INDEX(Data!$24:$24,MATCH('CC-CCoIPCE'!A2,Data!$22:$22,0)),Data!$I$24)*About!$A$28 -> 419.05684
A3: coal mining 05 | B3: =IFERROR(INDEX(Data!$24:$24,MATCH('CC-CCoIPCE'!A3,Data!$22:$22,0)),Data!$I$24)*About!$A$28 -> 419.05684
A4: oil and gas extraction 06 | B4: =IFERROR(INDEX(Data!$24:$24,MATCH('CC-CCoIPCE'!A4,Data!$22:$22,0)),Data!$I$24)*About!$A$28 -> 419.05684
A5: other mining and quarrying 07T08 | B5: =IFERROR(INDEX(Data!$24:$24,MATCH('CC-CCoIPCE'!A5,Data!$22:$22,0)),Data!$I$24)*About!$A$28 -> 419.05684
A6: food beverage and tobacco 10T12 | B6: =IFERROR(INDEX(Data!$24:$24,MATCH('CC-CCoIPCE'!A6,Data!$22:$22,0)),Data!$I$24)*About!$A$28 -> 419.05684
A7: textiles apparel and leather 13T15 | B7: =IFERROR(INDEX(Data!$24:$24,MATCH('CC-CCoIPCE'!A7,Data!$22:$22,0)),Data!$I$24)*About!$A$28 -> 419.05684
A8: wood products 16 | B8: =IFERROR(INDEX(Data!$24:$24,MATCH('CC-CCoIPCE'!A8,Data!$22:$22,0)),Data!$I$24)*About!$A$28 -> 419.05684
A9: pulp paper and printing 17T18 | B9: =IFERROR(INDEX(Data!$24:$24,MATCH('CC-CCoIPCE'!A9,Data!$22:$22,0)),Data!$I$24)*About!$A$28 -> 419.05684
A10: refined petroleum and coke 19 | B10: =Data!$I$24*About!$A$28 -> 419.05684
A11: chemicals 20 | B11: =IFERROR(INDEX(Data!$24:$24,MATCH('CC-CCoIPCE'!A11,Data!$22:$22,0)),Data!$I$24)*About!$A$28 -> 66.217283
A12: rubber and plastic products 22 | B12: =IFERROR(INDEX(Data!$24:$24,MATCH('CC-CCoIPCE'!A12,Data!$22:$22,0)),Data!$I$24)*About!$A$28 -> 419.05684
A13: glass and glass products 231 | B13: =IFERROR(INDEX(Data!$24:$24,MATCH('CC-CCoIPCE'!A13,Data!$22:$22,0)),Data!$I$24)*About!$A$28 -> 419.05684
A14: cement and other nonmetallic minerals 239 | B14: =IFERROR(INDEX(Data!$24:$24,MATCH('CC-CCoIPCE'!A14,Data!$22:$22,0)),Data!$I$24)*About!$A$28 -> 176.88449
A15: iron and steel 241 | B15: =IFERROR(INDEX(Data!$24:$24,MATCH('CC-CCoIPCE'!A15,Data!$22:$22,0)),Data!$I$24)*About!$A$28 -> 130.25408
A16: other metals 242 | B16: =IFERROR(INDEX(Data!$24:$24,MATCH('CC-CCoIPCE'!A16,Data!$22:$22,0)),Data!$I$24)*About!$A$28 -> 419.05684
A17: metal products except machinery and vehicles 25 | B17: =IFERROR(INDEX(Data!$24:$24,MATCH('CC-CCoIPCE'!A17,Data!$22:$22,0)),Data!$I$24)*About!$A$28 -> 419.05684
A18: computers and electronics 26 | B18: =IFERROR(INDEX(Data!$24:$24,MATCH('CC-CCoIPCE'!A18,Data!$22:$22,0)),Data!$I$24)*About!$A$28 -> 419.05684
A19: appliances and electrical equipment 27 | B19: =IFERROR(INDEX(Data!$24:$24,MATCH('CC-CCoIPCE'!A19,Data!$22:$22,0)),Data!$I$24)*About!$A$28 -> 419.05684
A20: other machinery 28 | B20: =IFERROR(INDEX(Data!$24:$24,MATCH('CC-CCoIPCE'!A20,Data!$22:$22,0)),Data!$I$24)*About!$A$28 -> 419.05684
A21: road vehicles 29 | B21: =IFERROR(INDEX(Data!$24:$24,MATCH('CC-CCoIPCE'!A21,Data!$22:$22,0)),Data!$I$24)*About!$A$28 -> 419.05684
A22: nonroad vehicles 30 | B22: =IFERROR(INDEX(Data!$24:$24,MATCH('CC-CCoIPCE'!A22,Data!$22:$22,0)),Data!$I$24)*About!$A$28 -> 419.05684
... A26: construction 41T43 | B26: =IFERROR(INDEX(Data!$24:$24,MATCH('CC-CCoIPCE'!A26,Data!$22:$22,0)),Data!$I$24)*About!$A$28 -> 419.05684

Sheet CC-CCoHSCE
B1: Capital cost ($/(metric ton CO2e*yr))
A2: Hydrogen Sector | B2: =Data!E24*About!$A$28 -> 174.19527

Sheet CC-TOMCpTIECS
B1: O&M Cost per Ton ($/metric ton CO2e)
A2: agriculture and forestry 01T03 | B2: =Data!$I$27*About!$A$28 -> 16.762274
A3: coal mining 05 | B3: =Data!$I$27*About!$A$28 -> 16.762274
A4: oil and gas extraction 06 | B4: =Data!$I$27*About!$A$28 -> 16.762274
A5: other mining and quarrying 07T08 | B5: =Data!$I$27*About!$A$28 -> 16.762274
A6: food beverage and tobacco 10T12 | B6: =Data!$I$27*About!$A$28 -> 16.762274
A7: textiles apparel and leather 13T15 | B7: =Data!$I$27*About!$A$28 -> 16.762274
A8: wood products 16 | B8: =Data!$I$27*About!$A$28 -> 16.762274
A9: pulp paper and printing 17T18 | B9: =Data!$I$27*About!$A$28 -> 16.762274
A10: refined petroleum and coke 19 | B10: =IFERROR(INDEX(Data!$27:$27,MATCH('CC-CCoIPCE'!A10,Data!$22:$22,0)),Data!$I$27)*About!$A$28 -> 14.614342
A11: chemicals 20 | B11: =Data!$I$27*About!$A$28 -> 16.762274
A12: rubber and plastic products 22 | B12: =Data!$I$27*About!$A$28 -> 16.762274
A13: glass and glass products 231 | B13: =Data!$I$27*About!$A$28 -> 16.762274
A14: cement and other nonmetallic minerals 239 | B14: =Data!$I$27*About!$A$28 -> 16.762274
A15: iron and steel 241 | B15: =Data!$I$27*About!$A$28 -> 16.762274
A16: other metals 242 | B16: =Data!$I$27*About!$A$28 -> 16.762274
A17: metal products except machinery and vehicles 25 | B17: =Data!$I$27*About!$A$28 -> 16.762274
A18: computers and electronics 26 | B18: =Data!$I$27*About!$A$28 -> 16.762274
A19: appliances and electrical equipment 27 | B19: =Data!$I$27*About!$A$28 -> 16.762274
A20: other machinery 28 | B20: =Data!$I$27*About!$A$28 -> 16.762274
A21: road vehicles 29 | B21: =Data!$I$27*About!$A$28 -> 16.762274
A22: nonroad vehicles 30 | B22: =Data!$I$27*About!$A$28 -> 16.762274
... A26: construction 41T43 | B26: =Data!$I$27*About!$A$28 -> 16.762274

Sheet CC-TOMCpTIPCS
B1: O&M Cost per Ton ($/metric ton CO2e)
A2: agriculture and forestry 01T03 | B2: =IFERROR(INDEX(Data!$27:$27,MATCH('CC-CCoIPCE'!A2,Data!$22:$22,0)),Data!$I$27)*About!$A$28 -> 16.762274
A3: coal mining 05 | B3: =IFERROR(INDEX(Data!$27:$27,MATCH('CC-CCoIPCE'!A3,Data!$22:$22,0)),Data!$I$27)*About!$A$28 -> 16.762274
A4: oil and gas extraction 06 | B4: =IFERROR(INDEX(Data!$27:$27,MATCH('CC-CCoIPCE'!A4,Data!$22:$22,0)),Data!$I$27)*About!$A$28 -> 16.762274
A5: other mining and quarrying 07T08 | B5: =IFERROR(INDEX(Data!$27:$27,MATCH('CC-CCoIPCE'!A5,Data!$22:$22,0)),Data!$I$27)*About!$A$28 -> 16.762274
A6: food beverage and tobacco 10T12 | B6: =IFERROR(INDEX(Data!$27:$27,MATCH('CC-CCoIPCE'!A6,Data!$22:$22,0)),Data!$I$27)*About!$A$28 -> 16.762274
A7: textiles apparel and leather 13T15 | B7: =IFERROR(INDEX(Data!$27:$27,MATCH('CC-CCoIPCE'!A7,Data!$22:$22,0)),Data!$I$27)*About!$A$28 -> 16.762274
A8: wood products 16 | B8: =IFERROR(INDEX(Data!$27:$27,MATCH('CC-CCoIPCE'!A8,Data!$22:$22,0)),Data!$I$27)*About!$A$28 -> 16.762274
A9: pulp paper and printing 17T18 | B9: =IFERROR(INDEX(Data!$27:$27,MATCH('CC-CCoIPCE'!A9,Data!$22:$22,0)),Data!$I$27)*About!$A$28 -> 16.762274
A10: refined petroleum and coke 19 | B10: =Data!$I$27*About!$A$28 -> 16.762274
A11: chemicals 20 | B11: =IFERROR(INDEX(Data!$27:$27,MATCH('CC-CCoIPCE'!A11,Data!$22:$22,0)),Data!$I$27)*About!$A$28 -> 4.6352098
A12: rubber and plastic products 22 | B12: =IFERROR(INDEX(Data!$27:$27,MATCH('CC-CCoIPCE'!A12,Data!$22:$22,0)),Data!$I$27)*About!$A$28 -> 16.762274
A13: glass and glass products 231 | B13: =IFERROR(INDEX(Data!$27:$27,MATCH('CC-CCoIPCE'!A13,Data!$22:$22,0)),Data!$I$27)*About!$A$28 -> 16.762274
A14: cement and other nonmetallic minerals 239 | B14: =IFERROR(INDEX(Data!$27:$27,MATCH('CC-CCoIPCE'!A14,Data!$22:$22,0)),Data!$I$27)*About!$A$28 -> 12.381914
A15: iron and steel 241 | B15: =IFERROR(INDEX(Data!$27:$27,MATCH('CC-CCoIPCE'!A15,Data!$22:$22,0)),Data!$I$27)*About!$A$28 -> 6.5127039
A16: other metals 242 | B16: =IFERROR(INDEX(Data!$27:$27,MATCH('CC-CCoIPCE'!A16,Data!$22:$22,0)),Data!$I$27)*About!$A$28 -> 16.762274
A17: metal products except machinery and vehicles 25 | B17: =IFERROR(INDEX(Data!$27:$27,MATCH('CC-CCoIPCE'!A17,Data!$22:$22,0)),Data!$I$27)*About!$A$28 -> 16.762274
A18: computers and electronics 26 | B18: =IFERROR(INDEX(Data!$27:$27,MATCH('CC-CCoIPCE'!A18,Data!$22:$22,0)),Data!$I$27)*About!$A$28 -> 16.762274
A19: appliances and electrical equipment 27 | B19: =IFERROR(INDEX(Data!$27:$27,MATCH('CC-CCoIPCE'!A19,Data!$22:$22,0)),Data!$I$27)*About!$A$28 -> 16.762274
A20: other machinery 28 | B20: =IFERROR(INDEX(Data!$27:$27,MATCH('CC-CCoIPCE'!A20,Data!$22:$22,0)),Data!$I$27)*About!$A$28 -> 16.762274
A21: road vehicles 29 | B21: =IFERROR(INDEX(Data!$27:$27,MATCH('CC-CCoIPCE'!A21,Data!$22:$22,0)),Data!$I$27)*About!$A$28 -> 16.762274
A22: nonroad vehicles 30 | B22: =IFERROR(INDEX(Data!$27:$27,MATCH('CC-CCoIPCE'!A22,Data!$22:$22,0)),Data!$I$27)*About!$A$28 -> 16.762274
... A26: construction 41T43 | B26: =IFERROR(INDEX(Data!$27:$27,MATCH('CC-CCoIPCE'!A26,Data!$22:$22,0)),Data!$I$27)*About!$A$28 -> 16.762274

Sheet CC-TOMCpTHSCS
B1: O&M Cost per Ton ($/metric ton CO2e)
A2: Hydrogen Sector | B2: =Data!E27*About!$A$28 -> 8.7097635

Sheet CC-EUpTIECS
A1: Energy Use per Ton Sequestered (BTU/gram CO2e) | B1: electricity | C1: coal | D1: natural gas | E1: biomass | F1: petroleum diesel | G1: heat | H1: crude oil | I1: heavy or residual oil | J1: LPG propane or butane | K1: hydrogen
A2: agriculture and forestry 01T03 | B2: =Data!$I$25/10^6 -> 0.54594256 | C2: 0 | D2: =Data!$I$26/10^6 -> 8.8715666 | E2: 0 | F2: 0 | G2: 0 | H2: 0 | I2: 0 | J2: 0 | K2: 0
A3: coal mining 05 | B3: =Data!$I$25/10^6 -> 0.54594256 | C3: 0 | D3: =Data!$I$26/10^6 -> 8.8715666 | E3: 0 | F3: 0 | G3: 0 | H3: 0 | I3: 0 | J3: 0 | K3: 0
A4: oil and gas extraction 06 | B4: =Data!$I$25/10^6 -> 0.54594256 | C4: 0 | D4: =Data!$I$26/10^6 -> 8.8715666 | E4: 0 | F4: 0 | G4: 0 | H4: 0 | I4: 0 | J4: 0 | K4: 0
A5: other mining and quarrying 07T08 | B5: =Data!$I$25/10^6 -> 0.54594256 | C5: 0 | D5: =Data!$I$26/10^6 -> 8.8715666 | E5: 0 | F5: 0 | G5: 0 | H5: 0 | I5: 0 | J5: 0 | K5: 0
A6: food beverage and tobacco 10T12 | B6: =Data!$I$25/10^6 -> 0.54594256 | C6: 0 | D6: =Data!$I$26/10^6 -> 8.8715666 | E6: 0 | F6: 0 | G6: 0 | H6: 0 | I6: 0 | J6: 0 | K6: 0
A7: textiles apparel and leather 13T15 | B7: =Data!$I$25/10^6 -> 0.54594256 | C7: 0 | D7: =Data!$I$26/10^6 -> 8.8715666 | E7: 0 | F7: 0 | G7: 0 | H7: 0 | I7: 0 | J7: 0 | K7: 0
A8: wood products 16 | B8: =Data!$I$25/10^6 -> 0.54594256 | C8: 0 | D8: =Data!$I$26/10^6 -> 8.8715666 | E8: 0 | F8: 0 | G8: 0 | H8: 0 | I8: 0 | J8: 0 | K8: 0
A9: pulp paper and printing 17T18 | B9: =Data!$I$25/10^6 -> 0.54594256 | C9: 0 | D9: =Data!$I$26/10^6 -> 8.8715666 | E9: 0 | F9: 0 | G9: 0 | H9: 0 | I9: 0 | J9: 0 | K9: 0
A10: refined petroleum and coke 19 | B10: =IFERROR(INDEX(Data!$25:$25,MATCH('CC-CCoIPCE'!A10,Data!$22:$22,0)),Data!$I$25)/10^6 -> 0.47769974 | C10: 0 | D10: =IFERROR(INDEX(Data!$26:$26,MATCH('CC-CCoIPCE'!A10,Data!$22:$22,0)),Data!$I$26)/10^6 -> 8.7009595 | E10: 0 | F10: 0 | G10: 0 | H10: 0 | I10: 0 | J10: 0 | K10: 0
A11: chemicals 20 | B11: =Data!$I$25/10^6 -> 0.54594256 | C11: 0 | D11: =Data!$I$26/10^6 -> 8.8715666 | E11: 0 | F11: 0 | G11: 0 | H11: 0 | I11: 0 | J11: 0 | K11: 0
A12: rubber and plastic products 22 | B12: =Data!$I$25/10^6 -> 0.54594256 | C12: 0 | D12: =Data!$I$26/10^6 -> 8.8715666 | E12: 0 | F12: 0 | G12: 0 | H12: 0 | I12: 0 | J12: 0 | K12: 0
A13: glass and glass products 231 | B13: =Data!$I$25/10^6 -> 0.54594256 | C13: 0 | D13: =Data!$I$26/10^6 -> 8.8715666 | E13: 0 | F13: 0 | G13: 0 | H13: 0 | I13: 0 | J13: 0 | K13: 0
A14: cement and other nonmetallic minerals 239 | B14: =Data!$I$25/10^6 -> 0.54594256 | C14: 0 | D14: =Data!$I$26/10^6 -> 8.8715666 | E14: 0 | F14: 0 | G14: 0 | H14: 0 | I14: 0 | J14: 0 | K14: 0
A15: iron and steel 241 | B15: =Data!$I$25/10^6 -> 0.54594256 | C15: 0 | D15: =Data!$I$26/10^6 -> 8.8715666 | E15: 0 | F15: 0 | G15: 0 | H15: 0 | I15: 0 | J15: 0 | K15: 0
A16: other metals 242 | B16: =Data!$I$25/10^6 -> 0.54594256 | C16: 0 | D16: =Data!$I$26/10^6 -> 8.8715666 | E16: 0 | F16: 0 | G16: 0 | H16: 0 | I16: 0 | J16: 0 | K16: 0
A17: metal products except machinery and vehicles 25 | B17: =Data!$I$25/10^6 -> 0.54594256 | C17: 0 | D17: =Data!$I$26/10^6 -> 8.8715666 | E17: 0 | F17: 0 | G17: 0 | H17: 0 | I17: 0 | J17: 0 | K17: 0
A18: computers and electronics 26 | B18: =Data!$I$25/10^6 -> 0.54594256 | C18: 0 | D18: =Data!$I$26/10^6 -> 8.8715666 | E18: 0 | F18: 0 | G18: 0 | H18: 0 | I18: 0 | J18: 0 | K18: 0
A19: appliances and electrical equipment 27 | B19: =Data!$I$25/10^6 -> 0.54594256 | C19: 0 | D19: =Data!$I$26/10^6 -> 8.8715666 | E19: 0 | F19: 0 | G19: 0 | H19: 0 | I19: 0 | J19: 0 | K19: 0
A20: other machinery 28 | B20: =Data!$I$25/10^6 -> 0.54594256 | C20: 0 | D20: =Data!$I$26/10^6 -> 8.8715666 | E20: 0 | F20: 0 | G20: 0 | H20: 0 | I20: 0 | J20: 0 | K20: 0
A21: road vehicles 29 | B21: =Data!$I$25/10^6 -> 0.54594256 | C21: 0 | D21: =Data!$I$26/10^6 -> 8.8715666 | E21: 0 | F21: 0 | G21: 0 | H21: 0 | I21: 0 | J21: 0 | K21: 0
A22: nonroad vehicles 30 | B22: =Data!$I$25/10^6 -> 0.54594256 | C22: 0 | D22: =Data!$I$26/10^6 -> 8.8715666 | E22: 0 | F22: 0 | G22: 0 | H22: 0 | I22: 0 | J22: 0 | K22: 0
... A26: construction 41T43 | B26: =Data!$I$25/10^6 -> 0.54594256 | C26: 0 | D26: =Data!$I$26/10^6 -> 8.8715666 | E26: 0 | F26: 0 | G26: 0 | H26: 0 | I26: 0 | J26: 0 | K26: 0

Sheet CC-EUpTIPCS
A1: Energy Use per Ton Sequestered (BTU/gram CO2e) | B1: electricity | C1: coal | D1: natural gas | E1: biomass | F1: petroleum diesel | G1: heat | H1: crude oil | I1: heavy or residual oil | J1: LPG propane or butane | K1: hydrogen
A2: agriculture and forestry 01T03 | B2: =IFERROR(INDEX(Data!$25:$25,MATCH('CC-CCoIPCE'!A2,Data!$22:$22,0)),Data!$I$25)/10^6 -> 0.54594256 | C2: 0 | D2: =IFERROR(INDEX(Data!$26:$26,MATCH('CC-CCoIPCE'!A2,Data!$22:$22,0)),Data!$I$26)/10^6 -> 8.8715666 | E2: 0 | F2: 0 | G2: 0 | H2: 0 | I2: 0 | J2: 0 | K2: 0
A3: coal mining 05 | B3: =IFERROR(INDEX(Data!$25:$25,MATCH('CC-CCoIPCE'!A3,Data!$22:$22,0)),Data!$I$25)/10^6 -> 0.54594256 | C3: 0 | D3: =IFERROR(INDEX(Data!$26:$26,MATCH('CC-CCoIPCE'!A3,Data!$22:$22,0)),Data!$I$26)/10^6 -> 8.8715666 | E3: 0 | F3: 0 | G3: 0 | H3: 0 | I3: 0 | J3: 0 | K3: 0
A4: oil and gas extraction 06 | B4: =IFERROR(INDEX(Data!$25:$25,MATCH('CC-CCoIPCE'!A4,Data!$22:$22,0)),Data!$I$25)/10^6 -> 0.54594256 | C4: 0 | D4: =IFERROR(INDEX(Data!$26:$26,MATCH('CC-CCoIPCE'!A4,Data!$22:$22,0)),Data!$I$26)/10^6 -> 8.8715666 | E4: 0 | F4: 0 | G4: 0 | H4: 0 | I4: 0 | J4: 0 | K4: 0
A5: other mining and quarrying 07T08 | B5: =IFERROR(INDEX(Data!$25:$25,MATCH('CC-CCoIPCE'!A5,Data!$22:$22,0)),Data!$I$25)/10^6 -> 0.54594256 | C5: 0 | D5: =IFERROR(INDEX(Data!$26:$26,MATCH('CC-CCoIPCE'!A5,Data!$22:$22,0)),Data!$I$26)/10^6 -> 8.8715666 | E5: 0 | F5: 0 | G5: 0 | H5: 0 | I5: 0 | J5: 0 | K5: 0
A6: food beverage and tobacco 10T12 | B6: =IFERROR(INDEX(Data!$25:$25,MATCH('CC-CCoIPCE'!A6,Data!$22:$22,0)),Data!$I$25)/10^6 -> 0.54594256 | C6: 0 | D6: =IFERROR(INDEX(Data!$26:$26,MATCH('CC-CCoIPCE'!A6,Data!$22:$22,0)),Data!$I$26)/10^6 -> 8.8715666 | E6: 0 | F6: 0 | G6: 0 | H6: 0 | I6: 0 | J6: 0 | K6: 0
A7: textiles apparel and leather 13T15 | B7: =IFERROR(INDEX(Data!$25:$25,MATCH('CC-CCoIPCE'!A7,Data!$22:$22,0)),Data!$I$25)/10^6 -> 0.54594256 | C7: 0 | D7: =IFERROR(INDEX(Data!$26:$26,MATCH('CC-CCoIPCE'!A7,Data!$22:$22,0)),Data!$I$26)/10^6 -> 8.8715666 | E7: 0 | F7: 0 | G7: 0 | H7: 0 | I7: 0 | J7: 0 | K7: 0
A8: wood products 16 | B8: =IFERROR(INDEX(Data!$25:$25,MATCH('CC-CCoIPCE'!A8,Data!$22:$22,0)),Data!$I$25)/10^6 -> 0.54594256 | C8: 0 | D8: =IFERROR(INDEX(Data!$26:$26,MATCH('CC-CCoIPCE'!A8,Data!$22:$22,0)),Data!$I$26)/10^6 -> 8.8715666 | E8: 0 | F8: 0 | G8: 0 | H8: 0 | I8: 0 | J8: 0 | K8: 0
A9: pulp paper and printing 17T18 | B9: =IFERROR(INDEX(Data!$25:$25,MATCH('CC-CCoIPCE'!A9,Data!$22:$22,0)),Data!$I$25)/10^6 -> 0.54594256 | C9: 0 | D9: =IFERROR(INDEX(Data!$26:$26,MATCH('CC-CCoIPCE'!A9,Data!$22:$22,0)),Data!$I$26)/10^6 -> 8.8715666 | E9: 0 | F9: 0 | G9: 0 | H9: 0 | I9: 0 | J9: 0 | K9: 0
A10: refined petroleum and coke 19 | B10: =B9 -> 0.54594256 | C10: =C9 -> 0 | D10: =D9 -> 8.8715666 | E10: 0 | F10: 0 | G10: 0 | H10: 0 | I10: 0 | J10: 0 | K10: 0
A11: chemicals 20 | B11: =IFERROR(INDEX(Data!$25:$25,MATCH('CC-CCoIPCE'!A11,Data!$22:$22,0)),Data!$I$25)/10^6 -> 0.40945692 | C11: 0 | D11: =IFERROR(INDEX(Data!$26:$26,MATCH('CC-CCoIPCE'!A11,Data!$22:$22,0)),Data!$I$26)/10^6 -> 0 | E11: 0 | F11: 0 | G11: 0 | H11: 0 | I11: 0 | J11: 0 | K11: 0
A12: rubber and plastic products 22 | B12: =IFERROR(INDEX(Data!$25:$25,MATCH('CC-CCoIPCE'!A12,Data!$22:$22,0)),Data!$I$25)/10^6 -> 0.54594256 | C12: 0 | D12: =IFERROR(INDEX(Data!$26:$26,MATCH('CC-CCoIPCE'!A12,Data!$22:$22,0)),Data!$I$26)/10^6 -> 8.8715666 | E12: 0 | F12: 0 | G12: 0 | H12: 0 | I12: 0 | J12: 0 | K12: 0
A13: glass and glass products 231 | B13: =IFERROR(INDEX(Data!$25:$25,MATCH('CC-CCoIPCE'!A13,Data!$22:$22,0)),Data!$I$25)/10^6 -> 0.54594256 | C13: 0 | D13: =IFERROR(INDEX(Data!$26:$26,MATCH('CC-CCoIPCE'!A13,Data!$22:$22,0)),Data!$I$26)/10^6 -> 8.8715666 | E13: 0 | F13: 0 | G13: 0 | H13: 0 | I13: 0 | J13: 0 | K13: 0
A14: cement and other nonmetallic minerals 239 | B14: =IFERROR(INDEX(Data!$25:$25,MATCH('CC-CCoIPCE'!A14,Data!$22:$22,0)),Data!$I$25)/10^6 -> 0.54594256 | C14: 0 | D14: =IFERROR(INDEX(Data!$26:$26,MATCH('CC-CCoIPCE'!A14,Data!$22:$22,0)),Data!$I$26)/10^6 -> 8.7009595 | E14: 0 | F14: 0 | G14: 0 | H14: 0 | I14: 0 | J14: 0 | K14: 0
A15: iron and steel 241 | B15: =IFERROR(INDEX(Data!$25:$25,MATCH('CC-CCoIPCE'!A15,Data!$22:$22,0)),Data!$I$25)/10^6 -> 0.54594256 | C15: 0 | D15: =IFERROR(INDEX(Data!$26:$26,MATCH('CC-CCoIPCE'!A15,Data!$22:$22,0)),Data!$I$26)/10^6 -> 8.7009595 | E15: 0 | F15: 0 | G15: 0 | H15: 0 | I15: 0 | J15: 0 | K15: 0
A16: other metals 242 | B16: =IFERROR(INDEX(Data!$25:$25,MATCH('CC-CCoIPCE'!A16,Data!$22:$22,0)),Data!$I$25)/10^6 -> 0.54594256 | C16: 0 | D16: =IFERROR(INDEX(Data!$26:$26,MATCH('CC-CCoIPCE'!A16,Data!$22:$22,0)),Data!$I$26)/10^6 -> 8.8715666 | E16: 0 | F16: 0 | G16: 0 | H16: 0 | I16: 0 | J16: 0 | K16: 0
A17: metal products except machinery and vehicles 25 | B17: =IFERROR(INDEX(Data!$25:$25,MATCH('CC-CCoIPCE'!A17,Data!$22:$22,0)),Data!$I$25)/10^6 -> 0.54594256 | C17: 0 | D17: =IFERROR(INDEX(Data!$26:$26,MATCH('CC-CCoIPCE'!A17,Data!$22:$22,0)),Data!$I$26)/10^6 -> 8.8715666 | E17: 0 | F17: 0 | G17: 0 | H17: 0 | I17: 0 | J17: 0 | K17: 0
A18: computers and electronics 26 | B18: =IFERROR(INDEX(Data!$25:$25,MATCH('CC-CCoIPCE'!A18,Data!$22:$22,0)),Data!$I$25)/10^6 -> 0.54594256 | C18: 0 | D18: =IFERROR(INDEX(Data!$26:$26,MATCH('CC-CCoIPCE'!A18,Data!$22:$22,0)),Data!$I$26)/10^6 -> 8.8715666 | E18: 0 | F18: 0 | G18: 0 | H18: 0 | I18: 0 | J18: 0 | K18: 0
A19: appliances and electrical equipment 27 | B19: =IFERROR(INDEX(Data!$25:$25,MATCH('CC-CCoIPCE'!A19,Data!$22:$22,0)),Data!$I$25)/10^6 -> 0.54594256 | C19: 0 | D19: =IFERROR(INDEX(Data!$26:$26,MATCH('CC-CCoIPCE'!A19,Data!$22:$22,0)),Data!$I$26)/10^6 -> 8.8715666 | E19: 0 | F19: 0 | G19: 0 | H19: 0 | I19: 0 | J19: 0 | K19: 0
A20: other machinery 28 | B20: =IFERROR(INDEX(Data!$25:$25,MATCH('CC-CCoIPCE'!A20,Data!$22:$22,0)),Data!$I$25)/10^6 -> 0.54594256 | C20: 0 | D20: =IFERROR(INDEX(Data!$26:$26,MATCH('CC-CCoIPCE'!A20,Data!$22:$22,0)),Data!$I$26)/10^6 -> 8.8715666 | E20: 0 | F20: 0 | G20: 0 | H20: 0 | I20: 0 | J20: 0 | K20: 0
A21: road vehicles 29 | B21: =IFERROR(INDEX(Data!$25:$25,MATCH('CC-CCoIPCE'!A21,Data!$22:$22,0)),Data!$I$25)/10^6 -> 0.54594256 | C21: 0 | D21: =IFERROR(INDEX(Data!$26:$26,MATCH('CC-CCoIPCE'!A21,Data!$22:$22,0)),Data!$I$26)/10^6 -> 8.8715666 | E21: 0 | F21: 0 | G21: 0 | H21: 0 | I21: 0 | J21: 0 | K21: 0
A22: nonroad vehicles 30 | B22: =IFERROR(INDEX(Data!$25:$25,MATCH('CC-CCoIPCE'!A22,Data!$22:$22,0)),Data!$I$25)/10^6 -> 0.54594256 | C22: 0 | D22: =IFERROR(INDEX(Data!$26:$26,MATCH('CC-CCoIPCE'!A22,Data!$22:$22,0)),Data!$I$26)/10^6 -> 8.8715666 | E22: 0 | F22: 0 | G22: 0 | H22: 0 | I22: 0 | J22: 0 | K22: 0
... A26: construction 41T43 | B26: =IFERROR(INDEX(Data!$25:$25,MATCH('CC-CCoIPCE'!A26,Data!$22:$22,0)),Data!$I$25)/10^6 -> 0.54594256 | C26: 0 | D26: =IFERROR(INDEX(Data!$26:$26,MATCH('CC-CCoIPCE'!A26,Data!$22:$22,0)),Data!$I$26)/10^6 -> 8.8715666 | E26: 0 | F26: 0 | G26: 0 | H26: 0 | I26: 0 | J26: 0 | K26: 0

Sheet CC-EUpTHSCS
B1: Energy Use per Ton Sequestered (BTU/gram CO2e)
A2: electricity if | B2: =Data!C44/10^6 -> 0.49698931
A3: coal if | B3: 0
A4: natural gas if | B4: =Data!C43/10^6 -> 1.1575133
A5: biomass if | B5: 0
A6: petroleum diesel if | B6: 0
A7: heat if | B7: 0
A8: crude oil if | B8: 0
A9: heavy or residual oil if | B9: 0
A10: LPG propane or butane if | B10: 0
A11: hydrogen if | B11: 0
