Workbook

Sheet About
A1: DoEbIC Demographics of Employees by ISIC Code
A3: Sources: | B3: Base-year demographics of employees by industry
B4: U.S. Bureau of Labor Statistics
B5: CPS Table 18/18b (employed persons by industry, sex, race, ethnicity, age) — tabs pasted with the stock projection machinery intact
B6: 2024
B7: https://www.bls.gov/cps/tables.htm
B8: Projected to 2050 with BLS labor-force projection ratios and S-curve trends (stock methodology, all calculation tabs preserved).
B10: Projections
B11: U.S. Bureau of Labor Statistics
B12: Labor force projections (see 'BLS LF projections' tab)
B13: 2024
B14: https://www.bls.gov/emp/
B15: S-curve convergence per demographic group.
A18: Notes:
A19: 52-code treatment | B19: The ten new child codes reference their PARENT's projected trajectory — the CPS industry tables carry no finer granularity at these splits. Refinement path: IPUMS ACS detailed-industry crosstabs per child.
A20: Export | B20: Each DoEbIC-<group>.csv = its output tab (52 rows x 2020-2050).

Sheet ISIC Code Key
A1: ISIC Code | B1: ISIC Code Meaning
A2: ISIC 01T03 | B2: Agriculture, forestry and fishing
A3: ISIC 05 | B3: Coal mining
A4: ISIC 06 | B4: Oil and gas extraction
A5: ISIC 07T08 | B5: Mining and quarrying of non-energy producing products (and uranium)
A6: ISIC 09 | B6: Mining support service activities
A7: ISIC 10T12 | B7: Food products, beverages and tobacco
A8: ISIC 13T15 | B8: Textiles, wearing apparel, leather and related products
A9: ISIC 16 | B9: Wood and products of wood and cork
A10: ISIC 17T18 | B10: Paper products and printing
A11: ISIC 19 | B11: Coke and refined petroleum products
A12: ISIC 20 | B12: Chemicals
... A43: ISIC 97T98 | B43: Private households with employed persons

Sheet BLS CPS T18
A1: HOUSEHOLD DATA ANNUAL AVERAGES 18. Employed persons by detailed industry, sex, race, and Hispanic or Latino ethnicity
A2: [Numbers in thousands]
A4: Industry | B4: 2020
B5: Total employed | C5: Percent of total employed
C6: Women | D6: White | E6: Black or African American | F6: Asian | G6: Hispanic or Latino | H6: Matching ISIC Code | I6: Other Race or 2+ Races
A8: Total, 16 years and over | B8: 147795 | C8: 46.8 | D8: 78 | E8: 12.1 | F8: 6.4 | G8: 17.6 | I8: =IF(OR(ISBLANK(D8),NOT(ISNUMBER(D8))),"",MAX(0,100-SUM(D8:F8))) -> 3.5
I9: =IF(OR(ISBLANK(D9),NOT(ISNUMBER(D9))),"",MAX(0,100-SUM(D9:F9)))
A10: Agriculture, forestry, fishing, and hunting | B10: 2349 | C10: 27.7 | D10: 92.4 | E10: 2.8 | F10: 1.2 | G10: 24.2 | H10: ISIC 01T03 | I10: =IF(OR(ISBLANK(D10),NOT(ISNUMBER(D10))),"",MAX(0,100-SUM(D10:F10))) -> 3.6
A11: Crop production | B11: 1186 | C11: 28.9 | D11: 92.7 | E11: 2.2 | F11: 1.7 | G11: 30.3 | I11: =IF(OR(ISBLANK(D11),NOT(ISNUMBER(D11))),"",MAX(0,100-SUM(D11:F11))) -> 3.4
A12: Animal production and aquaculture | B12: 832 | C12: 28.1 | D12: 92.9 | E12: 3.3 | F12: 0.4 | G12: 17.9 | I12: =IF(OR(ISBLANK(D12),NOT(ISNUMBER(D12))),"",MAX(0,100-SUM(D12:F12))) -> 3.4
A13: Support activities for agriculture and forestry | B13: 145 | C13: 33.9 | D13: 90.4 | E13: 5.7 | F13: 0.4 | G13: 26 | I13: =IF(OR(ISBLANK(D13),NOT(ISNUMBER(D13))),"",MAX(0,100-SUM(D13:F13))) -> 3.5
A14: Forestry, except logging | B14: 53 | C14: 25.5 | D14: 97.8 | E14: 0 | F14: 0.5 | G14: 9.9 | I14: =IF(OR(ISBLANK(D14),NOT(ISNUMBER(D14))),"",MAX(0,100-SUM(D14:F14))) -> 1.7
A15: Logging | B15: 88 | C15: 7.3 | D15: 89.9 | E15: 3.8 | F15: 2 | G15: 13.1 | I15: =IF(OR(ISBLANK(D15),NOT(ISNUMBER(D15))),"",MAX(0,100-SUM(D15:F15))) -> 4.3
A16: Fishing, hunting, and trapping | B16: 45 | C16: – | D16: – | E16: – | F16: – | G16: – | I16: =IF(OR(ISBLANK(D16),NOT(ISNUMBER(D16))),"",MAX(0,100-SUM(D16:F16)))
I17: =IF(OR(ISBLANK(D17),NOT(ISNUMBER(D17))),"",MAX(0,100-SUM(D17:F17)))
A18: Mining, quarrying, and oil and gas extraction | B18: 684 | C18: 14.5 | D18: 87.2 | E18: 4.6 | F18: 4.2 | G18: 17 | I18: =IF(OR(ISBLANK(D18),NOT(ISNUMBER(D18))),"",MAX(0,100-SUM(D18:F18))) -> 4
A19: Oil and gas extraction | B19: 97 | C19: 14.9 | D19: 80.6 | E19: 4.1 | F19: 10.5 | G19: 13 | H19: ISIC 06 | I19: =IF(OR(ISBLANK(D19),NOT(ISNUMBER(D19))),"",MAX(0,100-SUM(D19:F19))) -> 4.8
A20: Coal mining | B20: 51 | C20: 10.1 | D20: 93.1 | E20: 3.1 | F20: 0 | G20: 4.2 | H20: ISIC 05 | I20: =IF(OR(ISBLANK(D20),NOT(ISNUMBER(D20))),"",MAX(0,100-SUM(D20:F20))) -> 3.8
A21: Metal ore mining | B21: 36 | C21: – | D21: – | E21: – | F21: – | G21: – | I21: =IF(OR(ISBLANK(D21),NOT(ISNUMBER(D21))),"",MAX(0,100-SUM(D21:F21)))
A22: Nonmetallic mineral mining and quarrying | B22: 83 | C22: 10.7 | D22: 90.4 | E22: 0.8 | F22: 2.5 | G22: 12.7 | H22: ISIC 07T08 | I22: =IF(OR(ISBLANK(D22),NOT(ISNUMBER(D22))),"",MAX(0,100-SUM(D22:F22))) -> 6.3
A23: Not specified type of mining | B23: 0 | C23: – | D23: – | E23: – | F23: – | G23: – | I23: =IF(OR(ISBLANK(D23),NOT(ISNUMBER(D23))),"",MAX(0,100-SUM(D23:F23)))
A24: Support activities for mining | B24: 417 | C24: 15.2 | D24: 86.5 | E24: 6 | F24: 3.9 | G24: 20.7 | H24: ISIC 09 | I24: =IF(OR(ISBLANK(D24),NOT(ISNUMBER(D24))),"",MAX(0,100-SUM(D24:F24))) -> 3.6
I25: =IF(OR(ISBLANK(D25),NOT(ISNUMBER(D25))),"",MAX(0,100-SUM(D25:F25)))
A26: Construction | B26: 10786 | C26: 10.9 | D26: 88.6 | E26: 6 | F26: 2 | G26: 30 | H26: ISIC 41T43 | I26: =IF(OR(ISBLANK(D26),NOT(ISNUMBER(D26))),"",MAX(0,100-SUM(D26:F26))) -> 3.4
I27: =IF(OR(ISBLANK(D27),NOT(ISNUMBER(D27))),"",MAX(0,100-SUM(D27:F27)))
A28: Manufacturing | B28: 14550 | C28: 29.5 | D28: 79.7 | E28: 10.3 | F28: 7 | G28: 17.3 | I28: =IF(OR(ISBLANK(D28),NOT(ISNUMBER(D28))),"",MAX(0,100-SUM(D28:F28))) -> 3
A29: Durable goods manufacturing | B29: 9129 | C29: 25.4 | D29: 80.3 | E29: 9.5 | F29: 7.4 | G29: 15.5 | I29: =IF(OR(ISBLANK(D29),NOT(ISNUMBER(D29))),"",MAX(0,100-SUM(D29:F29))) -> 2.8
A30: Nonmetallic mineral products manufacturing | B30: 410 | C30: 21.3 | D30: 84 | E30: 8.8 | F30: 2.4 | G30: 24.4 | H30: see at bottom | I30: =IF(OR(ISBLANK(D30),NOT(ISNUMBER(D30))),"",MAX(0,100-SUM(D30:F30))) -> 4.8
A31: Pottery, ceramics, and plumbing fixture manufacturing | B31: 17 | C31: – | D31: – | E31: – | F31: – | G31: – | I31: =IF(OR(ISBLANK(D31),NOT(ISNUMBER(D31))),"",MAX(0,100-SUM(D31:F31)))
A32: Clay building material and refractories manufacturing | B32: 38 | C32: – | D32: – | E32: – | F32: – | G32: – | I32: =IF(OR(ISBLANK(D32),NOT(ISNUMBER(D32))),"",MAX(0,100-SUM(D32:F32)))
A33: Glass and glass product manufacturing | B33: 123 | C33: 22.9 | D33: 78.9 | E33: 10.6 | F33: 4.3 | G33: 21.8 | H33: ISIC 231 | I33: =IF(OR(ISBLANK(D33),NOT(ISNUMBER(D33))),"",MAX(0,100-SUM(D33:F33))) -> 6.2
A34: Cement, concrete, lime, and gypsum product manufacturing | B34: 157 | C34: 12.9 | D34: 89.3 | E34: 7.1 | F34: 2.1 | G34: 29.8 | I34: =IF(OR(ISBLANK(D34),NOT(ISNUMBER(D34))),"",MAX(0,100-SUM(D34:F34))) -> 1.5
A35: Miscellaneous nonmetallic mineral product manufacturing | B35: 75 | C35: 29.6 | D35: 84.5 | E35: 7.9 | F35: 1.6 | G35: 23.1 | I35: =IF(OR(ISBLANK(D35),NOT(ISNUMBER(D35))),"",MAX(0,100-SUM(D35:F35))) -> 6
A36: Primary metals and fabricated metal products manufacturing | B36: 1534 | C36: 16.4 | D36: 89.3 | E36: 5.7 | F36: 2.4 | G36: 14.9 | I36: =IF(OR(ISBLANK(D36),NOT(ISNUMBER(D36))),"",MAX(0,100-SUM(D36:F36))) -> 2.6
A37: Iron and steel mills and steel product manufacturing | B37: 256 | C37: 12.1 | D37: 87.4 | E37: 8.2 | F37: 1 | G37: 13.5 | H37: ISIC 241 | I37: =IF(OR(ISBLANK(D37),NOT(ISNUMBER(D37))),"",MAX(0,100-SUM(D37:F37))) -> 3.4
A38: Aluminum production and processing | B38: 71 | C38: 26.9 | D38: 92.2 | E38: 6.1 | F38: 0.8 | G38: 23.4 | H38: ISIC 242 | I38: =IF(OR(ISBLANK(D38),NOT(ISNUMBER(D38))),"",MAX(0,100-SUM(D38:F38))) -> 0.9
A39: Nonferrous metal (except aluminum) production and processing | B39: 31 | C39: – | D39: – | E39: – | F39: – | G39: – | I39: =IF(OR(ISBLANK(D39),NOT(ISNUMBER(D39))),"",MAX(0,100-SUM(D39:F39)))
A40: Foundries | B40: 59 | C40: 18.5 | D40: 94.6 | E40: 4.7 | F40: 0.4 | G40: 8 | H40: see at bottom | I40: =IF(OR(ISBLANK(D40),NOT(ISNUMBER(D40))),"",MAX(0,100-SUM(D40:F40))) -> 0.3
A41: Metal forgings and stampings | B41: 45 | C41: – | D41: – | E41: – | F41: – | G41: – | I41: =IF(OR(ISBLANK(D41),NOT(ISNUMBER(D41))),"",MAX(0,100-SUM(D41:F41)))
A42: Cutlery and hand tool manufacturing | B42: 46 | C42: – | D42: – | E42: – | F42: – | G42: – | I42: =IF(OR(ISBLANK(D42),NOT(ISNUMBER(D42))),"",MAX(0,100-SUM(D42:F42)))
A43: Structural metals, and boiler, tank, and shipping container manufacturing | B43: 304 | C43: 16.1 | D43: 86.4 | E43: 6.9 | F43: 2.6 | G43: 15.6 | H43: see at bottom | I43: =IF(OR(ISBLANK(D43),NOT(ISNUMBER(D43))),"",MAX(0,100-SUM(D43:F43))) -> 4.1
A44: Machine shops; turned product; screw, nut, and bolt manufacturing | B44: 287 | C44: 14 | D44: 90.9 | E44: 3.9 | F44: 4.6 | G44: 13.8 | H44: see at bottom | I44: =IF(OR(ISBLANK(D44),NOT(ISNUMBER(D44))),"",MAX(0,100-SUM(D44:F44))) -> 0.6
A45: Coating, engraving, heat treating, and allied activities | B45: 61 | C45: 18.5 | D45: 91.8 | E45: 1 | F45: 2.3 | G45: 20.9 | H45: see at bottom | I45: =IF(OR(ISBLANK(D45),NOT(ISNUMBER(D45))),"",MAX(0,100-SUM(D45:F45))) -> 4.9
A46: Ordnance | B46: 46 | C46: – | D46: – | E46: – | F46: – | G46: – | I46: =IF(OR(ISBLANK(D46),NOT(ISNUMBER(D46))),"",MAX(0,100-SUM(D46:F46)))
A47: Miscellaneous fabricated metal products manufacturing | B47: 310 | C47: 18.6 | D47: 89.8 | E47: 5.7 | F47: 1.9 | G47: 15.3 | H47: see at bottom | I47: =IF(OR(ISBLANK(D47),NOT(ISNUMBER(D47))),"",MAX(0,100-SUM(D47:F47))) -> 2.6
A48: Not specified metal industries | B48: 18 | C48: – | D48: – | E48: – | F48: – | G48: – | I48: =IF(OR(ISBLANK(D48),NOT(ISNUMBER(D48))),"",MAX(0,100-SUM(D48:F48)))
A49: Machinery manufacturing | B49: 1119 | C49: 23.3 | D49: 85.4 | E49: 7.7 | F49: 4.6 | G49: 11.2 | H49: ISIC 28 | I49: =IF(OR(ISBLANK(D49),NOT(ISNUMBER(D49))),"",MAX(0,100-SUM(D49:F49))) -> 2.3
A50: Agricultural implement manufacturing | B50: 93 | C50: 18.3 | D50: 84.7 | E50: 9.4 | F50: 3.8 | G50: 4.3 | I50: =IF(OR(ISBLANK(D50),NOT(ISNUMBER(D50))),"",MAX(0,100-SUM(D50:F50))) -> 2.1
A51: Construction, and mining and oil and gas field machinery manufacturing | B51: 129 | C51: 21.5 | D51: 89.7 | E51: 4.8 | F51: 3.9 | G51: 10 | I51: =IF(OR(ISBLANK(D51),NOT(ISNUMBER(D51))),"",MAX(0,100-SUM(D51:F51))) -> 1.6
A52: Commercial and service industry machinery manufacturing | B52: 81 | C52: 26.1 | D52: 84 | E52: 4 | F52: 6.1 | G52: 16.5 | I52: =IF(OR(ISBLANK(D52),NOT(ISNUMBER(D52))),"",MAX(0,100-SUM(D52:F52))) -> 5.9
A53: Metalworking machinery manufacturing | B53: 91 | C53: 13.5 | D53: 91.1 | E53: 1.2 | F53: 4.5 | G53: 6.7 | I53: =IF(OR(ISBLANK(D53),NOT(ISNUMBER(D53))),"",MAX(0,100-SUM(D53:F53))) -> 3.2
A54: Engine, turbine, and power transmission equipment manufacturing | B54: 41 | C54: – | D54: – | E54: – | F54: – | G54: – | I54: =IF(OR(ISBLANK(D54),NOT(ISNUMBER(D54))),"",MAX(0,100-SUM(D54:F54)))
A55: Machinery manufacturing, n.e.c. or not specified | B55: 684 | C55: 25 | D55: 84.5 | E55: 9 | F55: 4.5 | G55: 12.1 | I55: =IF(OR(ISBLANK(D55),NOT(ISNUMBER(D55))),"",MAX(0,100-SUM(D55:F55))) -> 2
A56: Computers and electronic products manufacturing | B56: 1039 | C56: 30.5 | D56: 68.1 | E56: 5.9 | F56: 22.8 | G56: 11.6 | H56: ISIC 26 | I56: =IF(OR(ISBLANK(D56),NOT(ISNUMBER(D56))),"",MAX(0,100-SUM(D56:F56))) -> 3.2
A57: Computer and peripheral equipment manufacturing | B57: 155 | C57: 27.3 | D57: 58.7 | E57: 7.4 | F57: 31.4 | G57: 12.7 | I57: =IF(OR(ISBLANK(D57),NOT(ISNUMBER(D57))),"",MAX(0,100-SUM(D57:F57))) -> 2.5
A58: Communications, audio, and video equipment manufacturing | B58: 103 | C58: 21.5 | D58: 73.3 | E58: 8.6 | F58: 18.1 | G58: 10 | I58: =IF(OR(ISBLANK(D58),NOT(ISNUMBER(D58))),"",MAX(0,100-SUM(D58:F58))) -> 0
A59: Navigational, measuring, electromedical, and control instruments manufacturing | B59: 175 | C59: 28.7 | D59: 82.3 | E59: 7.2 | F59: 9 | G59: 12.6 | I59: =IF(OR(ISBLANK(D59),NOT(ISNUMBER(D59))),"",MAX(0,100-SUM(D59:F59))) -> 1.5
A60: Electronic component and product manufacturing, n.e.c. | B60: 606 | C60: 33.4 | D60: 65.6 | E60: 4.7 | F60: 25.4 | G60: 11.2 | I60: =IF(OR(ISBLANK(D60),NOT(ISNUMBER(D60))),"",MAX(0,100-SUM(D60:F60))) -> 4.3
A61: Electrical equipment and appliances manufacturing | B61: 376 | C61: 28.9 | D61: 81.6 | E61: 9.4 | F61: 5.5 | G61: 15.3 | H61: ISIC 27 | I61: =IF(OR(ISBLANK(D61),NOT(ISNUMBER(D61))),"",MAX(0,100-SUM(D61:F61))) -> 3.5
A62: Household appliance manufacturing | B62: 68 | C62: 33 | D62: 70.6 | E62: 17.7 | F62: 3.6 | G62: 13.2 | I62: =IF(OR(ISBLANK(D62),NOT(ISNUMBER(D62))),"",MAX(0,100-SUM(D62:F62))) -> 8.1
A63: Electrical lighting and electrical equipment manufacturing, and other electrical component manufacturing, n.e.c. | B63: 307 | C63: 28 | D63: 84 | E63: 7.5 | F63: 6 | G63: 15.8 | I63: =IF(OR(ISBLANK(D63),NOT(ISNUMBER(D63))),"",MAX(0,100-SUM(D63:F63))) -> 2.5
A64: Transportation equipment manufacturing | B64: 2304 | C64: 24 | D64: 76.5 | E64: 14.3 | F64: 6.9 | G64: 12.9 | H64: see at bottom | I64: =IF(OR(ISBLANK(D64),NOT(ISNUMBER(D64))),"",MAX(0,100-SUM(D64:F64))) -> 2.3
A65: Motor vehicles and motor vehicle equipment manufacturing | B65: 1266 | C65: 26.1 | D65: 73.1 | E65: 18.2 | F65: 6.5 | G65: 9.9 | H65: ISIC 29 | I65: =IF(OR(ISBLANK(D65),NOT(ISNUMBER(D65))),"",MAX(0,100-SUM(D65:F65))) -> 2.2
A66: Aircraft and parts manufacturing | B66: 772 | C66: 22.7 | D66: 81.1 | E66: 7.6 | F66: 8.6 | G66: 16.7 | I66: =IF(OR(ISBLANK(D66),NOT(ISNUMBER(D66))),"",MAX(0,100-SUM(D66:F66))) -> 2.7
A67: Aerospace products and parts manufacturing | B67: 44 | C67: – | D67: – | E67: – | F67: – | G67: – | I67: =IF(OR(ISBLANK(D67),NOT(ISNUMBER(D67))),"",MAX(0,100-SUM(D67:F67)))
A68: Railroad rolling stock manufacturing | B68: 27 | C68: – | D68: – | E68: – | F68: – | G68: – | I68: =IF(OR(ISBLANK(D68),NOT(ISNUMBER(D68))),"",MAX(0,100-SUM(D68:F68)))
A69: Ship and boat building | B69: 176 | C69: 16 | D69: 76.9 | E69: 16.1 | F69: 4.9 | G69: 19.2 | I69: =IF(OR(ISBLANK(D69),NOT(ISNUMBER(D69))),"",MAX(0,100-SUM(D69:F69))) -> 2.1
A70: Other transportation equipment manufacturing | B70: 20 | C70: – | D70: – | E70: – | F70: – | G70: – | I70: =IF(OR(ISBLANK(D70),NOT(ISNUMBER(D70))),"",MAX(0,100-SUM(D70:F70)))
A71: Wood products manufacturing | B71: 430 | C71: 16.6 | D71: 85.1 | E71: 9.1 | F71: 1.7 | G71: 23.6 | H71: ISIC 16 | I71: =IF(OR(ISBLANK(D71),NOT(ISNUMBER(D71))),"",MAX(0,100-SUM(D71:F71))) -> 4.1
A72: Sawmills and wood preservation | B72: 141 | C72: 13.5 | D72: 86.5 | E72: 7.5 | F72: 0.5 | G72: 21.9 | I72: =IF(OR(ISBLANK(D72),NOT(ISNUMBER(D72))),"",MAX(0,100-SUM(D72:F72))) -> 5.5
A73: Veneer, plywood, and engineered wood products | B73: 30 | C73: – | D73: – | E73: – | F73: – | G73: – | I73: =IF(OR(ISBLANK(D73),NOT(ISNUMBER(D73))),"",MAX(0,100-SUM(D73:F73)))
A74: Prefabricated wood buildings and mobile homes manufacturing | B74: 29 | C74: – | D74: – | E74: – | F74: – | G74: – | I74: =IF(OR(ISBLANK(D74),NOT(ISNUMBER(D74))),"",MAX(0,100-SUM(D74:F74)))
A75: Miscellaneous wood products | B75: 230 | C75: 19.7 | D75: 86.3 | E75: 8 | F75: 2.4 | G75: 28.1 | I75: =IF(OR(ISBLANK(D75),NOT(ISNUMBER(D75))),"",MAX(0,100-SUM(D75:F75))) -> 3.3
A76: Furniture and related product manufacturing | B76: 395 | C76: 27.9 | D76: 86.7 | E76: 8.6 | F76: 3.6 | G76: 24.2 | I76: =IF(OR(ISBLANK(D76),NOT(ISNUMBER(D76))),"",MAX(0,100-SUM(D76:F76))) -> 1.1
A77: Miscellaneous manufacturing | B77: 1522 | C77: 36.4 | D77: 77.3 | E77: 10.4 | F77: 9.1 | G77: 18.7 | H77: ISIC 31T33 | I77: =IF(OR(ISBLANK(D77),NOT(ISNUMBER(D77))),"",MAX(0,100-SUM(D77:F77))) -> 3.2
A78: Medical equipment and supplies manufacturing | B78: 660 | C78: 39.7 | D78: 76.9 | E78: 8.4 | F78: 11.5 | G78: 13.9 | I78: =IF(OR(ISBLANK(D78),NOT(ISNUMBER(D78))),"",MAX(0,100-SUM(D78:F78))) -> 3.2
A79: Sporting and athletic goods, and doll, toy and game manufacturing | B79: 97 | C79: 33.1 | D79: 85 | E79: 8 | F79: 6.2 | G79: 13.6 | I79: =IF(OR(ISBLANK(D79),NOT(ISNUMBER(D79))),"",MAX(0,100-SUM(D79:F79))) -> 0.8
A80: Miscellaneous manufacturing, n.e.c. | B80: 455 | C80: 36.4 | D80: 79.3 | E80: 10.4 | F80: 6.6 | G80: 19 | I80: =IF(OR(ISBLANK(D80),NOT(ISNUMBER(D80))),"",MAX(0,100-SUM(D80:F80))) -> 3.7
A81: Not specified manufacturing industries | B81: 310 | C81: 30.4 | D81: 72.5 | E81: 15.7 | F81: 8.6 | G81: 30.3 | I81: =IF(OR(ISBLANK(D81),NOT(ISNUMBER(D81))),"",MAX(0,100-SUM(D81:F81))) -> 3.2
A82: Nondurable goods manufacturing | B82: 5421 | C82: 36.5 | D82: 78.7 | E82: 11.5 | F82: 6.4 | G82: 20.5 | I82: =IF(OR(ISBLANK(D82),NOT(ISNUMBER(D82))),"",MAX(0,100-SUM(D82:F82))) -> 3.4
A83: Food manufacturing | B83: 1672 | C83: 42.2 | D83: 77.4 | E83: 13.2 | F83: 5.3 | G83: 31 | H83: see at bottom | I83: =IF(OR(ISBLANK(D83),NOT(ISNUMBER(D83))),"",MAX(0,100-SUM(D83:F83))) -> 4.1
A84: Animal food, grain, and oilseed milling | B84: 149 | C84: 33.5 | D84: 85 | E84: 10.1 | F84: 2.7 | G84: 12.6 | I84: =IF(OR(ISBLANK(D84),NOT(ISNUMBER(D84))),"",MAX(0,100-SUM(D84:F84))) -> 2.2
A85: Sugar and confectionery products | B85: 60 | C85: 41.7 | D85: 74.7 | E85: 17.2 | F85: 5.6 | G85: 27.1 | I85: =IF(OR(ISBLANK(D85),NOT(ISNUMBER(D85))),"",MAX(0,100-SUM(D85:F85))) -> 2.5
A86: Fruit and vegetable preserving and specialty food manufacturing | B86: 138 | C86: 38.5 | D86: 81.4 | E86: 8.8 | F86: 5.7 | G86: 35.5 | I86: =IF(OR(ISBLANK(D86),NOT(ISNUMBER(D86))),"",MAX(0,100-SUM(D86:F86))) -> 4.1
A87: Dairy product manufacturing | B87: 136 | C87: 24.4 | D87: 88.4 | E87: 5.2 | F87: 2.5 | G87: 23.7 | I87: =IF(OR(ISBLANK(D87),NOT(ISNUMBER(D87))),"",MAX(0,100-SUM(D87:F87))) -> 3.9
A88: Animal slaughtering and processing | B88: 485 | C88: 43 | D88: 69.5 | E88: 20 | F88: 6.5 | G88: 36.9 | I88: =IF(OR(ISBLANK(D88),NOT(ISNUMBER(D88))),"",MAX(0,100-SUM(D88:F88))) -> 4
A89: Retail bakeries | B89: 236 | C89: 68.1 | D89: 83.4 | E89: 9 | F89: 4.3 | G89: 22.5 | I89: =IF(OR(ISBLANK(D89),NOT(ISNUMBER(D89))),"",MAX(0,100-SUM(D89:F89))) -> 3.3
A90: Bakeries and tortilla manufacturing, except retail bakeries | B90: 193 | C90: 41.1 | D90: 77.7 | E90: 10.2 | F90: 5.5 | G90: 40.5 | I90: =IF(OR(ISBLANK(D90),NOT(ISNUMBER(D90))),"",MAX(0,100-SUM(D90:F90))) -> 6.6
A91: Seafood and other miscellaneous foods, n.e.c. | B91: 188 | C91: 32.6 | D91: 75.1 | E91: 14.4 | F91: 6.3 | G91: 30.8 | I91: =IF(OR(ISBLANK(D91),NOT(ISNUMBER(D91))),"",MAX(0,100-SUM(D91:F91))) -> 4.2
A92: Not specified food industries | B92: 87 | C92: 39.3 | D92: 73.8 | E92: 12.5 | F92: 6.9 | G92: 38.5 | I92: =IF(OR(ISBLANK(D92),NOT(ISNUMBER(D92))),"",MAX(0,100-SUM(D92:F92))) -> 6.8
A93: Beverages and tobacco products manufacturing | B93: 285 | C93: 24.9 | D93: 83.3 | E93: 10.8 | F93: 2.4 | G93: 15 | H93: see at bottom | I93: =IF(OR(ISBLANK(D93),NOT(ISNUMBER(D93))),"",MAX(0,100-SUM(D93:F93))) -> 3.5
A94: Beverage manufacturing | B94: 263 | C94: 24 | D94: 85.5 | E94: 10.5 | F94: 1.9 | G94: 16 | I94: =IF(OR(ISBLANK(D94),NOT(ISNUMBER(D94))),"",MAX(0,100-SUM(D94:F94))) -> 2.1
A95: Tobacco manufacturing | B95: 22 | C95: – | D95: – | E95: – | F95: – | G95: – | I95: =IF(OR(ISBLANK(D95),NOT(ISNUMBER(D95))),"",MAX(0,100-SUM(D95:F95)))
A96: Textiles, apparel, and leather manufacturing | B96: 444 | C96: 52.2 | D96: 75.9 | E96: 11.9 | F96: 8.5 | G96: 22.6 | H96: ISIC 13T15 | I96: =IF(OR(ISBLANK(D96),NOT(ISNUMBER(D96))),"",MAX(0,100-SUM(D96:F96))) -> 3.7
A97: Fiber, yarn, and thread mills | B97: 5 | C97: – | D97: – | E97: – | F97: – | G97: – | I97: =IF(OR(ISBLANK(D97),NOT(ISNUMBER(D97))),"",MAX(0,100-SUM(D97:F97)))
A98: Fabric mills, except knitting mills | B98: 84 | C98: 45.1 | D98: 70 | E98: 16 | F98: 3.8 | G98: 19.6 | I98: =IF(OR(ISBLANK(D98),NOT(ISNUMBER(D98))),"",MAX(0,100-SUM(D98:F98))) -> 10.2
A99: Textile and fabric finishing and coating mills | B99: 7 | C99: – | D99: – | E99: – | F99: – | G99: – | I99: =IF(OR(ISBLANK(D99),NOT(ISNUMBER(D99))),"",MAX(0,100-SUM(D99:F99)))
A100: Carpet and rug mills | B100: 52 | C100: 41.1 | D100: 86.9 | E100: 8 | F100: 0.8 | G100: 26.1 | I100: =IF(OR(ISBLANK(D100),NOT(ISNUMBER(D100))),"",MAX(0,100-SUM(D100:F100))) -> 4.3
A101: Textile product mills, except carpet and rug | B101: 63 | C101: 48.1 | D101: 78.8 | E101: 11.6 | F101: 8.7 | G101: 6.8 | I101: =IF(OR(ISBLANK(D101),NOT(ISNUMBER(D101))),"",MAX(0,100-SUM(D101:F101))) -> 0.9
A102: Knitting fabric mills, and apparel knitting mills | B102: 6 | C102: – | D102: – | E102: – | F102: – | G102: – | I102: =IF(OR(ISBLANK(D102),NOT(ISNUMBER(D102))),"",MAX(0,100-SUM(D102:F102)))
...

Sheet BLS CPS T18b
A1: HOUSEHOLD DATA ANNUAL AVERAGES 18b. Employed persons by detailed industry and age
A2: [Numbers in thousands]
A4: Industry | B4: 2020
B5: Total, 16 years and over | C5: 16 to 19 years | D5: 20 to 24 years | E5: 25 to 34 years | F5: 35 to 44 years | G5: 45 to 54 years | H5: 55 to 64 years | I5: 65 years and over | J5: Median age | K5: Matching ISIC Code
A7: Total, 16 years and over | B7: 147795 | C7: 4695 | D7: 12497 | E7: 33426 | F7: 31807 | G7: 30099 | H7: 25454 | I7: 9818 | J7: 42.5
A9: Agriculture, forestry, fishing, and hunting | B9: 2349 | C9: 93 | D9: 161 | E9: 386 | F9: 403 | G9: 409 | H9: 462 | I9: 435 | J9: 48.5 | K9: ISIC 01T03
A10: Crop production | B10: 1186 | C10: 41 | D10: 74 | E10: 208 | F10: 199 | G10: 205 | H10: 243 | I10: 216 | J10: 48.6
A11: Animal production and aquaculture | B11: 832 | C11: 40 | D11: 63 | E11: 114 | F11: 143 | G11: 144 | H11: 148 | I11: 180 | J11: 49.2
A12: Support activities for agriculture and forestry | B12: 145 | C12: 9 | D12: 13 | E12: 28 | F12: 27 | G12: 26 | H12: 32 | I12: 11 | J12: 44.3
A13: Forestry, except logging | B13: 53 | C13: 1 | D13: 2 | E13: 9 | F13: 12 | G13: 10 | H13: 12 | I13: 5 | J13: 46.6
A14: Logging | B14: 88 | C14: 2 | D14: 7 | E14: 16 | F14: 15 | G14: 18 | H14: 18 | I14: 12 | J14: 48.7
A15: Fishing, hunting, and trapping | B15: 45 | C15: 1 | D15: 2 | E15: 11 | F15: 7 | G15: 6 | H15: 8 | I15: 11 | J15: –
A17: Mining, quarrying, and oil and gas extraction | B17: 684 | C17: 5 | D17: 41 | E17: 147 | F17: 198 | G17: 153 | H17: 107 | I17: 33 | J17: 42.8
A18: Oil and gas extraction | B18: 97 | C18: 0 | D18: 3 | E18: 23 | F18: 29 | G18: 23 | H18: 13 | I18: 7 | J18: 43.3 | K18: ISIC 06
A19: Coal mining | B19: 51 | C19: 0 | D19: 2 | E19: 10 | F19: 16 | G19: 12 | H19: 10 | I19: 1 | J19: 44.1 | K19: ISIC 05
A20: Metal ore mining | B20: 36 | C20: 0 | D20: 0 | E20: 10 | F20: 5 | G20: 12 | H20: 6 | I20: 2 | J20: –
A21: Nonmetallic mineral mining and quarrying | B21: 83 | C21: 0 | D21: 9 | E21: 12 | F21: 19 | G21: 14 | H21: 21 | I21: 7 | J21: 48 | K21: ISIC 07T08
A22: Not specified type of mining | B22: 0 | C22: 0 | D22: 0 | E22: 0 | F22: 0 | G22: 0 | H22: 0 | I22: 0 | J22: –
A23: Support activities for mining | B23: 417 | C23: 4 | D23: 27 | E23: 92 | F23: 130 | G23: 92 | H23: 57 | I23: 16 | J23: 41.8 | K23: ISIC 09
A25: Construction | B25: 10786 | C25: 199 | D25: 817 | E25: 2321 | F25: 2650 | G25: 2352 | H25: 1850 | I25: 598 | J25: 42.9 | K25: ISIC 41T43
A27: Manufacturing | B27: 14550 | C27: 169 | D27: 940 | E27: 3200 | F27: 3145 | G27: 3388 | H27: 2929 | I27: 780 | J27: 44.4
A28: Durable goods manufacturing | B28: 9129 | C28: 100 | D28: 593 | E28: 1980 | F28: 1947 | G28: 2118 | H28: 1900 | I28: 491 | J28: 44.6
A29: Nonmetallic mineral products manufacturing | B29: 410 | C29: 6 | D29: 28 | E29: 70 | F29: 96 | G29: 91 | H29: 95 | I29: 24 | J29: 45.8 | K29: see at bottom
A30: Pottery, ceramics, and plumbing fixture manufacturing | B30: 17 | C30: 0 | D30: 0 | E30: 2 | F30: 5 | G30: 4 | H30: 3 | I30: 3 | J30: –
A31: Clay building material and refractories manufacturing | B31: 38 | C31: 1 | D31: 4 | E31: 8 | F31: 6 | G31: 6 | H31: 10 | I31: 5 | J31: –
A32: Glass and glass product manufacturing | B32: 123 | C32: 2 | D32: 9 | E32: 20 | F32: 25 | G32: 31 | H32: 27 | I32: 9 | J32: 46.8 | K32: ISIC 231
A33: Cement, concrete, lime, and gypsum product manufacturing | B33: 157 | C33: 1 | D33: 11 | E33: 29 | F33: 32 | G33: 34 | H33: 44 | I33: 6 | J33: 46
A34: Miscellaneous nonmetallic mineral product manufacturing | B34: 75 | C34: 2 | D34: 4 | E34: 11 | F34: 28 | G34: 16 | H34: 12 | I34: 1 | J34: 43
A35: Primary metals and fabricated metal products manufacturing | B35: 1534 | C35: 20 | D35: 100 | E35: 320 | F35: 314 | G35: 328 | H35: 366 | I35: 85 | J35: 45.4
A36: Iron and steel mills and steel product manufacturing | B36: 256 | C36: 2 | D36: 19 | E36: 53 | F36: 55 | G36: 51 | H36: 65 | I36: 11 | J36: 45.2 | K36: ISIC 241
A37: Aluminum production and processing | B37: 71 | C37: 1 | D37: 3 | E37: 14 | F37: 13 | G37: 20 | H37: 17 | I37: 2 | J37: 47.3 | K37: ISIC 242
A38: Nonferrous metal (except aluminum) production and processing | B38: 31 | C38: 1 | D38: 0 | E38: 4 | F38: 8 | G38: 6 | H38: 8 | I38: 4 | J38: –
A39: Foundries | B39: 59 | C39: 1 | D39: 5 | E39: 14 | F39: 13 | G39: 12 | H39: 12 | I39: 3 | J39: 42.6 | K39: see at bottom
A40: Metal forgings and stampings | B40: 45 | C40: 0 | D40: 3 | E40: 9 | F40: 11 | G40: 10 | H40: 9 | I40: 3 | J40: –
A41: Cutlery and hand tool manufacturing | B41: 46 | C41: 1 | D41: 4 | E41: 11 | F41: 9 | G41: 5 | H41: 13 | I41: 4 | J41: –
A42: Structural metals, and boiler, tank, and shipping container manufacturing | B42: 304 | C42: 5 | D42: 17 | E42: 73 | F42: 66 | G42: 74 | H42: 52 | I42: 17 | J42: 43.3 | K42: see at bottom
A43: Machine shops; turned product; screw, nut, and bolt manufacturing | B43: 287 | C43: 1 | D43: 19 | E43: 51 | F43: 57 | G43: 54 | H43: 85 | I43: 20 | J43: 48.4 | K43: see at bottom
A44: Coating, engraving, heat treating, and allied activities | B44: 61 | C44: 1 | D44: 3 | E44: 17 | F44: 10 | G44: 11 | H44: 17 | I44: 1 | J44: 45 | K44: see at bottom
A45: Ordnance | B45: 46 | C45: 1 | D45: 7 | E45: 7 | F45: 10 | G45: 13 | H45: 7 | I45: 3 | J45: –
A46: Miscellaneous fabricated metal products manufacturing | B46: 310 | C46: 7 | D46: 16 | E46: 65 | F46: 58 | G46: 72 | H46: 74 | I46: 17 | J46: 45.4 | K46: see at bottom
A47: Not specified metal industries | B47: 18 | C47: 0 | D47: 3 | E47: 2 | F47: 5 | G47: 2 | H47: 7 | I47: 0 | J47: –
A48: Machinery manufacturing | B48: 1119 | C48: 9 | D48: 84 | E48: 219 | F48: 224 | G48: 261 | H48: 248 | I48: 74 | J48: 45.9 | K48: ISIC 28
A49: Agricultural implement manufacturing | B49: 93 | C49: 0 | D49: 9 | E49: 20 | F49: 21 | G49: 25 | H49: 13 | I49: 5 | J49: 42.5
A50: Construction, and mining and oil and gas field machinery manufacturing | B50: 129 | C50: 1 | D50: 12 | E50: 26 | F50: 30 | G50: 30 | H50: 24 | I50: 6 | J50: 43.1
A51: Commercial and service industry machinery manufacturing | B51: 81 | C51: 0 | D51: 9 | E51: 12 | F51: 17 | G51: 18 | H51: 21 | I51: 4 | J51: 47.1
A52: Metalworking machinery manufacturing | B52: 91 | C52: 2 | D52: 7 | E52: 17 | F52: 13 | G52: 15 | H52: 23 | I52: 13 | J52: 48.1
A53: Engine, turbine, and power transmission equipment manufacturing | B53: 41 | C53: 0 | D53: 4 | E53: 8 | F53: 10 | G53: 10 | H53: 6 | I53: 3 | J53: –
A54: Machinery manufacturing, n.e.c. or not specified | B54: 684 | C54: 6 | D54: 42 | E54: 137 | F54: 133 | G54: 163 | H54: 160 | I54: 43 | J54: 46.9
A55: Computers and electronic products manufacturing | B55: 1039 | C55: 10 | D55: 49 | E55: 219 | F55: 225 | G55: 250 | H55: 225 | I55: 61 | J55: 45.9 | K55: ISIC 26
A56: Computer and peripheral equipment manufacturing | B56: 155 | C56: 0 | D56: 9 | E56: 43 | F56: 43 | G56: 24 | H56: 30 | I56: 6 | J56: 42.3
A57: Communications, audio, and video equipment manufacturing | B57: 103 | C57: 3 | D57: 4 | E57: 19 | F57: 23 | G57: 27 | H57: 21 | I57: 7 | J57: 45.1
A58: Navigational, measuring, electromedical, and control instruments manufacturing | B58: 175 | C58: 1 | D58: 10 | E58: 24 | F58: 37 | G58: 39 | H58: 53 | I58: 10 | J58: 49.3
A59: Electronic component and product manufacturing, n.e.c. | B59: 606 | C59: 6 | D59: 26 | E59: 133 | F59: 121 | G59: 160 | H59: 121 | I59: 38 | J59: 46.2
A60: Electrical equipment and appliances manufacturing | B60: 376 | C60: 4 | D60: 25 | E60: 88 | F60: 83 | G60: 84 | H60: 70 | I60: 21 | J60: 43.3 | K60: ISIC 27
A61: Household appliance manufacturing | B61: 68 | C61: 1 | D61: 8 | E61: 16 | F61: 10 | G61: 23 | H61: 7 | I61: 2 | J61: 40.6
A62: Electrical lighting and electrical equipment manufacturing, and other electrical component manufacturing, n.e.c. | B62: 307 | C62: 2 | D62: 17 | E62: 72 | F62: 73 | G62: 60 | H62: 63 | I62: 20 | J62: 43.9
A63: Transportation equipment manufacturing | B63: 2304 | C63: 15 | D63: 139 | E63: 570 | F63: 499 | G63: 550 | H63: 448 | I63: 83 | J63: 43.6 | K63: see at bottom
A64: Motor vehicles and motor vehicle equipment manufacturing | B64: 1266 | C64: 12 | D64: 82 | E64: 316 | F64: 273 | G64: 320 | H64: 224 | I64: 37 | J64: 43.2 | K64: ISIC 29
A65: Aircraft and parts manufacturing | B65: 772 | C65: 1 | D65: 41 | E65: 186 | F65: 165 | G65: 167 | H65: 179 | I65: 33 | J65: 44.5
A66: Aerospace products and parts manufacturing | B66: 44 | C66: 0 | D66: 2 | E66: 16 | F66: 10 | G66: 6 | H66: 9 | I66: 1 | J66: –
A67: Railroad rolling stock manufacturing | B67: 27 | C67: 0 | D67: 3 | E67: 7 | F67: 6 | G67: 9 | H67: 1 | I67: 2 | J67: –
A68: Ship and boat building | B68: 176 | C68: 1 | D68: 10 | E68: 40 | F68: 41 | G68: 42 | H68: 33 | I68: 9 | J68: 43.4
A69: Other transportation equipment manufacturing | B69: 20 | C69: 0 | D69: 1 | E69: 5 | F69: 5 | G69: 5 | H69: 3 | I69: 1 | J69: –
A70: Wood products manufacturing | B70: 430 | C70: 8 | D70: 35 | E70: 97 | F70: 97 | G70: 94 | H70: 73 | I70: 26 | J70: 42.6 | K70: ISIC 16
A71: Sawmills and wood preservation | B71: 141 | C71: 2 | D71: 11 | E71: 37 | F71: 31 | G71: 26 | H71: 26 | I71: 7 | J71: 42.2
A72: Veneer, plywood, and engineered wood products | B72: 30 | C72: 0 | D72: 3 | E72: 4 | F72: 10 | G72: 7 | H72: 6 | I72: 0 | J72: –
A73: Prefabricated wood buildings and mobile homes manufacturing | B73: 29 | C73: 2 | D73: 3 | E73: 6 | F73: 9 | G73: 6 | H73: 2 | I73: 1 | J73: –
A74: Miscellaneous wood products | B74: 230 | C74: 3 | D74: 18 | E74: 50 | F74: 47 | G74: 55 | H74: 40 | I74: 17 | J74: 43.6
A75: Furniture and related product manufacturing | B75: 395 | C75: 12 | D75: 33 | E75: 79 | F75: 88 | G75: 96 | H75: 67 | I75: 21 | J75: 43.1
A76: Miscellaneous manufacturing | B76: 1522 | C76: 18 | D76: 99 | E76: 319 | F76: 321 | G76: 363 | H76: 308 | I76: 95 | J76: 44.6 | K76: ISIC 31T33
A77: Medical equipment and supplies manufacturing | B77: 660 | C77: 5 | D77: 35 | E77: 157 | F77: 134 | G77: 164 | H77: 132 | I77: 34 | J77: 44.7
A78: Sporting and athletic goods, and doll, toy and game manufacturing | B78: 97 | C78: 2 | D78: 11 | E78: 19 | F78: 19 | G78: 19 | H78: 16 | I78: 11 | J78: 43
A79: Miscellaneous manufacturing, n.e.c. | B79: 455 | C79: 8 | D79: 29 | E79: 79 | F79: 98 | G79: 111 | H79: 104 | I79: 27 | J79: 45.4
A80: Not specified manufacturing industries | B80: 310 | C80: 2 | D80: 24 | E80: 64 | F80: 70 | G80: 70 | H80: 57 | I80: 24 | J80: 43.9
A81: Nondurable goods manufacturing | B81: 5421 | C81: 68 | D81: 348 | E81: 1220 | F81: 1198 | G81: 1270 | H81: 1029 | I81: 289 | J81: 44
A82: Food manufacturing | B82: 1672 | C82: 41 | D82: 138 | E82: 393 | F82: 378 | G82: 364 | H82: 278 | I82: 80 | J82: 42.1 | K82: see at bottom
A83: Animal food, grain, and oilseed milling | B83: 149 | C83: 2 | D83: 5 | E83: 34 | F83: 32 | G83: 43 | H83: 22 | I83: 11 | J83: 45
A84: Sugar and confectionery products | B84: 60 | C84: 2 | D84: 1 | E84: 9 | F84: 13 | G84: 12 | H84: 18 | I84: 5 | J84: 49.4
A85: Fruit and vegetable preserving and specialty food manufacturing | B85: 138 | C85: 1 | D85: 11 | E85: 31 | F85: 29 | G85: 34 | H85: 24 | I85: 8 | J85: 43.7
A86: Dairy product manufacturing | B86: 136 | C86: 0 | D86: 11 | E86: 32 | F86: 29 | G86: 28 | H86: 30 | I86: 6 | J86: 44.1
A87: Animal slaughtering and processing | B87: 485 | C87: 9 | D87: 43 | E87: 129 | F87: 122 | G87: 98 | H87: 68 | I87: 16 | J87: 40.4
A88: Retail bakeries | B88: 236 | C88: 21 | D88: 29 | E88: 54 | F88: 44 | G88: 46 | H88: 33 | I88: 10 | J88: 37.8
A89: Bakeries and tortilla manufacturing, except retail bakeries | B89: 193 | C89: 3 | D89: 16 | E89: 49 | F89: 42 | G89: 39 | H89: 35 | I89: 10 | J89: 42.4
A90: Seafood and other miscellaneous foods, n.e.c. | B90: 188 | C90: 3 | D90: 18 | E90: 40 | F90: 37 | G90: 47 | H90: 34 | I90: 9 | J90: 43.2
A91: Not specified food industries | B91: 87 | C91: 1 | D91: 5 | E91: 16 | F91: 30 | G91: 15 | H91: 14 | I91: 6 | J91: 43.9
A92: Beverages and tobacco products manufacturing | B92: 285 | C92: 4 | D92: 22 | E92: 91 | F92: 65 | G92: 52 | H92: 36 | I92: 14 | J92: 39.3 | K92: see at bottom
A93: Beverage manufacturing | B93: 263 | C93: 4 | D93: 20 | E93: 90 | F93: 57 | G93: 44 | H93: 34 | I93: 14 | J93: 38.8
A94: Tobacco manufacturing | B94: 22 | C94: 0 | D94: 2 | E94: 1 | F94: 9 | G94: 8 | H94: 3 | I94: 0 | J94: –
A95: Textiles, apparel, and leather manufacturing | B95: 444 | C95: 6 | D95: 32 | E95: 97 | F95: 93 | G95: 91 | H95: 87 | I95: 37 | J95: 44.7 | K95: ISIC 13T15
A96: Fiber, yarn, and thread mills | B96: 5 | C96: 0 | D96: 0 | E96: 1 | F96: 2 | G96: 2 | H96: 0 | I96: 0 | J96: –
A97: Fabric mills, except knitting mills | B97: 84 | C97: 0 | D97: 7 | E97: 13 | F97: 18 | G97: 21 | H97: 18 | I97: 6 | J97: 47.4
A98: Textile and fabric finishing and coating mills | B98: 7 | C98: 0 | D98: 0 | E98: 1 | F98: 3 | G98: 1 | H98: 1 | I98: 0 | J98: –
A99: Carpet and rug mills | B99: 52 | C99: 1 | D99: 4 | E99: 13 | F99: 7 | G99: 12 | H99: 10 | I99: 5 | J99: 45.2
A100: Textile product mills, except carpet and rug | B100: 63 | C100: 2 | D100: 7 | E100: 10 | F100: 13 | G100: 10 | H100: 11 | I100: 9 | J100: 45.6
A101: Knitting fabric mills, and apparel knitting mills | B101: 6 | C101: 0 | D101: 0 | E101: 0 | F101: 0 | G101: 1 | H101: 3 | I101: 1 | J101: –
A102: Cut and sew, and apparel accessories and other apparel manufacturing | B102: 186 | C102: 2 | D102: 12 | E102: 44 | F102: 38 | G102: 40 | H102: 39 | I102: 12 | J102: 44.3
A103: Footwear manufacturing | B103: 18 | C103: 0 | D103: 0 | E103: 8 | F103: 4 | G103: 2 | H103: 3 | I103: 0 | J103: –
A104: Leather and hide tanning and finishing, and other leather and allied product manufacturing | B104: 25 | C104: 0 | D104: 1 | E104: 7 | F104: 7 | G104: 4 | H104: 2 | I104: 3 | J104: –
A105: Paper manufacturing and printing | B105: 801 | C105: 5 | D105: 39 | E105: 163 | F105: 160 | G105: 202 | H105: 178 | I105: 54 | J105: 47.1 | K105: ISIC 17T18
A106: Pulp, paper, and paperboard mills | B106: 193 | C106: 1 | D106: 6 | E106: 42 | F106: 42 | G106: 50 | H106: 43 | I106: 9 | J106: 46.8
...

Sheet BLS LF projections 2019-2029
A1: Civilian Labor Force (LF) Projections 2019-29 (numbers in thousands)
A2: This file was updated on February 24, 2021, to correct data for "all other" men.
B3: 2019 | C3: 2020 | D3: 2021 | E3: 2022 | F3: 2023 | G3: 2024 | H3: 2025 | I3: 2026 | J3: 2027 | K3: 2028 | L3: 2029 | M3: 2030 | N3: 2031 | O3: 2032 | P3: 2033 | Q3: 2034 | R3: 2035 | S3: 2036 | T3: 2037 | U3: 2038 | V3: 2039 | W3: 2040 | X3: 2041 | Y3: 2042 | Z3: 2043 | AA3: 2044 | AB3: 2045 | AC3: 2046 | AD3: 2047 | AE3: 2048 | AF3: 2049 | AG3: 2050
A4: Total Labor Force | B4: 163537 | C4: 164337 | D4: 165161 | E4: 165897 | F4: 166681 | G4: 167488 | H4: 168248 | I4: 169069 | J4: 169894 | K4: 170725 | L4: 171531 | M4: {=TREND($B4:$L4,$B$3:$L$3,M$3)} -> 172286.11 | N4: {=TREND($B4:$L4,$B$3:$L$3,N$3)} -> 173082.76 | O4: {=TREND($B4:$L4,$B$3:$L$3,O$3)} -> 173879.42 | P4: {=TREND($B4:$L4,$B$3:$L$3,P$3)} -> 174676.07 | Q4: {=TREND($B4:$L4,$B$3:$L$3,Q$3)} -> 175472.73 | R4: {=TREND($B4:$L4,$B$3:$L$3,R$3)} -> 176269.38 | S4: {=TREND($B4:$L4,$B$3:$L$3,S$3)} -> 177066.04 | T4: {=TREND($B4:$L4,$B$3:$L$3,T$3)} -> 177862.69 | ... AG4: {=TREND($B4:$L4,$B$3:$L$3,AG$3)} -> 188219.2
A5: 16 and 17 | B5: 2081 | C5: 2033 | D5: 1978 | E5: 1920 | F5: 1873 | G5: 1819 | H5: 1733 | I5: 1655 | J5: 1606 | K5: 1548 | L5: 1490 | M5: {=TREND($B5:$L5,$B$3:$L$3,M$3)} -> 1429.7636 | N5: {=TREND($B5:$L5,$B$3:$L$3,N$3)} -> 1369.0273 | O5: {=TREND($B5:$L5,$B$3:$L$3,O$3)} -> 1308.2909 | P5: {=TREND($B5:$L5,$B$3:$L$3,P$3)} -> 1247.5545 | Q5: {=TREND($B5:$L5,$B$3:$L$3,Q$3)} -> 1186.8182 | R5: {=TREND($B5:$L5,$B$3:$L$3,R$3)} -> 1126.0818 | S5: {=TREND($B5:$L5,$B$3:$L$3,S$3)} -> 1065.3455 | T5: {=TREND($B5:$L5,$B$3:$L$3,T$3)} -> 1004.6091 | ... AG5: {=TREND($B5:$L5,$B$3:$L$3,AG$3)} -> 215.03636
A6: 18 and 19 | B6: 3815 | C6: 3701 | D6: 3623 | E6: 3601 | F6: 3567 | G6: 3525 | H6: 3500 | I6: 3463 | J6: 3360 | K6: 3267 | L6: 3227 | M6: {=TREND($B6:$L6,$B$3:$L$3,M$3)} -> 3196.7455 | N6: {=TREND($B6:$L6,$B$3:$L$3,N$3)} -> 3143.9455 | O6: {=TREND($B6:$L6,$B$3:$L$3,O$3)} -> 3091.1455 | P6: {=TREND($B6:$L6,$B$3:$L$3,P$3)} -> 3038.3455 | Q6: {=TREND($B6:$L6,$B$3:$L$3,Q$3)} -> 2985.5455 | R6: {=TREND($B6:$L6,$B$3:$L$3,R$3)} -> 2932.7455 | S6: {=TREND($B6:$L6,$B$3:$L$3,S$3)} -> 2879.9455 | T6: {=TREND($B6:$L6,$B$3:$L$3,T$3)} -> 2827.1455 | ... AG6: {=TREND($B6:$L6,$B$3:$L$3,AG$3)} -> 2140.7455
A7: 20 to 24 | B7: 15195 | C7: 15159 | D7: 15134 | E7: 15054 | F7: 14989 | G7: 14943 | H7: 14843 | I7: 14794 | J7: 14835 | K7: 14849 | L7: 14755 | M7: {=TREND($B7:$L7,$B$3:$L$3,M$3)} -> 14686.2 | N7: {=TREND($B7:$L7,$B$3:$L$3,N$3)} -> 14640.718 | O7: {=TREND($B7:$L7,$B$3:$L$3,O$3)} -> 14595.236 | P7: {=TREND($B7:$L7,$B$3:$L$3,P$3)} -> 14549.755 | Q7: {=TREND($B7:$L7,$B$3:$L$3,Q$3)} -> 14504.273 | R7: {=TREND($B7:$L7,$B$3:$L$3,R$3)} -> 14458.791 | S7: {=TREND($B7:$L7,$B$3:$L$3,S$3)} -> 14413.309 | T7: {=TREND($B7:$L7,$B$3:$L$3,T$3)} -> 14367.827 | ... AG7: {=TREND($B7:$L7,$B$3:$L$3,AG$3)} -> 13776.564
A8: 25 to 29 | B8: 18991 | C8: 18817 | D8: 18555 | E8: 18329 | F8: 18183 | G8: 18083 | H8: 18097 | I8: 18123 | J8: 18086 | K8: 18064 | L8: 18067 | M8: {=TREND($B8:$L8,$B$3:$L$3,M$3)} -> 17788.436 | N8: {=TREND($B8:$L8,$B$3:$L$3,N$3)} -> 17701.736 | O8: {=TREND($B8:$L8,$B$3:$L$3,O$3)} -> 17615.036 | P8: {=TREND($B8:$L8,$B$3:$L$3,P$3)} -> 17528.336 | Q8: {=TREND($B8:$L8,$B$3:$L$3,Q$3)} -> 17441.636 | R8: {=TREND($B8:$L8,$B$3:$L$3,R$3)} -> 17354.936 | S8: {=TREND($B8:$L8,$B$3:$L$3,S$3)} -> 17268.236 | T8: {=TREND($B8:$L8,$B$3:$L$3,T$3)} -> 17181.536 | ... AG8: {=TREND($B8:$L8,$B$3:$L$3,AG$3)} -> 16054.436
A9: 30 to 34 | B9: 18200 | C9: 18565 | D9: 18972 | E9: 19333 | F9: 19542 | G9: 19611 | H9: 19455 | I9: 19209 | J9: 19000 | K9: 18868 | L9: 18779 | M9: {=TREND($B9:$L9,$B$3:$L$3,M$3)} -> 19258.873 | N9: {=TREND($B9:$L9,$B$3:$L$3,N$3)} -> 19293.927 | O9: {=TREND($B9:$L9,$B$3:$L$3,O$3)} -> 19328.982 | P9: {=TREND($B9:$L9,$B$3:$L$3,P$3)} -> 19364.036 | Q9: {=TREND($B9:$L9,$B$3:$L$3,Q$3)} -> 19399.091 | R9: {=TREND($B9:$L9,$B$3:$L$3,R$3)} -> 19434.145 | S9: {=TREND($B9:$L9,$B$3:$L$3,S$3)} -> 19469.2 | T9: {=TREND($B9:$L9,$B$3:$L$3,T$3)} -> 19504.255 | ... AG9: {=TREND($B9:$L9,$B$3:$L$3,AG$3)} -> 19959.964
A10: 35 to 39 | B10: 17736 | C10: 17821 | D10: 17959 | E10: 18053 | F10: 18218 | G10: 18533 | H10: 18895 | I10: 19301 | J10: 19660 | K10: 19868 | L10: 19936 | M10: {=TREND($B10:$L10,$B$3:$L$3,M$3)} -> 20223.491 | N10: {=TREND($B10:$L10,$B$3:$L$3,N$3)} -> 20473.164 | O10: {=TREND($B10:$L10,$B$3:$L$3,O$3)} -> 20722.836 | P10: {=TREND($B10:$L10,$B$3:$L$3,P$3)} -> 20972.509 | Q10: {=TREND($B10:$L10,$B$3:$L$3,Q$3)} -> 21222.182 | R10: {=TREND($B10:$L10,$B$3:$L$3,R$3)} -> 21471.855 | S10: {=TREND($B10:$L10,$B$3:$L$3,S$3)} -> 21721.527 | T10: {=TREND($B10:$L10,$B$3:$L$3,T$3)} -> 21971.2 | ... AG10: {=TREND($B10:$L10,$B$3:$L$3,AG$3)} -> 25216.945
A11: 40 to 44 | B11: 16321 | C11: 16652 | D11: 17016 | E11: 17329 | F11: 17619 | G11: 17801 | H11: 17887 | I11: 18024 | J11: 18116 | K11: 18275 | L11: 18584 | M11: {=TREND($B11:$L11,$B$3:$L$3,M$3)} -> 18843.909 | N11: {=TREND($B11:$L11,$B$3:$L$3,N$3)} -> 19050.864 | O11: {=TREND($B11:$L11,$B$3:$L$3,O$3)} -> 19257.818 | P11: {=TREND($B11:$L11,$B$3:$L$3,P$3)} -> 19464.773 | Q11: {=TREND($B11:$L11,$B$3:$L$3,Q$3)} -> 19671.727 | R11: {=TREND($B11:$L11,$B$3:$L$3,R$3)} -> 19878.682 | S11: {=TREND($B11:$L11,$B$3:$L$3,S$3)} -> 20085.636 | T11: {=TREND($B11:$L11,$B$3:$L$3,T$3)} -> 20292.591 | ... AG11: {=TREND($B11:$L11,$B$3:$L$3,AG$3)} -> 22983
A12: 45 to 49 | B12: 16707 | C12: 16374 | D12: 15995 | E12: 15909 | F12: 16006 | G12: 16223 | H12: 16561 | I12: 16933 | J12: 17255 | K12: 17553 | L12: 17743 | M12: {=TREND($B12:$L12,$B$3:$L$3,M$3)} -> 17547.855 | N12: {=TREND($B12:$L12,$B$3:$L$3,N$3)} -> 17695.845 | O12: {=TREND($B12:$L12,$B$3:$L$3,O$3)} -> 17843.836 | P12: {=TREND($B12:$L12,$B$3:$L$3,P$3)} -> 17991.827 | Q12: {=TREND($B12:$L12,$B$3:$L$3,Q$3)} -> 18139.818 | R12: {=TREND($B12:$L12,$B$3:$L$3,R$3)} -> 18287.809 | S12: {=TREND($B12:$L12,$B$3:$L$3,S$3)} -> 18435.8 | T12: {=TREND($B12:$L12,$B$3:$L$3,T$3)} -> 18583.791 | ... AG12: {=TREND($B12:$L12,$B$3:$L$3,AG$3)} -> 20507.673
A13: 50 to 54 | B13: 16224 | C13: 16194 | D13: 16323 | E13: 16333 | F13: 16216 | G13: 15995 | H13: 15704 | I13: 15371 | J13: 15314 | K13: 15432 | L13: 15663 | M13: {=TREND($B13:$L13,$B$3:$L$3,M$3)} -> 15270.855 | N13: {=TREND($B13:$L13,$B$3:$L$3,N$3)} -> 15167.982 | O13: {=TREND($B13:$L13,$B$3:$L$3,O$3)} -> 15065.109 | P13: {=TREND($B13:$L13,$B$3:$L$3,P$3)} -> 14962.236 | Q13: {=TREND($B13:$L13,$B$3:$L$3,Q$3)} -> 14859.364 | R13: {=TREND($B13:$L13,$B$3:$L$3,R$3)} -> 14756.491 | S13: {=TREND($B13:$L13,$B$3:$L$3,S$3)} -> 14653.618 | T13: {=TREND($B13:$L13,$B$3:$L$3,T$3)} -> 14550.745 | ... AG13: {=TREND($B13:$L13,$B$3:$L$3,AG$3)} -> 13213.4
A14: 55 to 59 | B14: 15756 | C14: 15638 | D14: 15376 | E14: 15106 | F14: 14833 | G14: 14628 | H14: 14645 | I14: 14803 | J14: 14852 | K14: 14786 | L14: 14624 | M14: {=TREND($B14:$L14,$B$3:$L$3,M$3)} -> 14380.6 | N14: {=TREND($B14:$L14,$B$3:$L$3,N$3)} -> 14276.655 | O14: {=TREND($B14:$L14,$B$3:$L$3,O$3)} -> 14172.709 | P14: {=TREND($B14:$L14,$B$3:$L$3,P$3)} -> 14068.764 | Q14: {=TREND($B14:$L14,$B$3:$L$3,Q$3)} -> 13964.818 | R14: {=TREND($B14:$L14,$B$3:$L$3,R$3)} -> 13860.873 | S14: {=TREND($B14:$L14,$B$3:$L$3,S$3)} -> 13756.927 | T14: {=TREND($B14:$L14,$B$3:$L$3,T$3)} -> 13652.982 | ... AG14: {=TREND($B14:$L14,$B$3:$L$3,AG$3)} -> 12301.691
A15: 60 to 64 | B15: 11847 | C15: 12124 | D15: 12367 | E15: 12500 | F15: 12615 | G15: 12723 | H15: 12702 | I15: 12563 | J15: 12415 | K15: 12262 | L15: 12163 | M15: {=TREND($B15:$L15,$B$3:$L$3,M$3)} -> 12524.945 | N15: {=TREND($B15:$L15,$B$3:$L$3,N$3)} -> 12547.573 | O15: {=TREND($B15:$L15,$B$3:$L$3,O$3)} -> 12570.2 | P15: {=TREND($B15:$L15,$B$3:$L$3,P$3)} -> 12592.827 | Q15: {=TREND($B15:$L15,$B$3:$L$3,Q$3)} -> 12615.455 | R15: {=TREND($B15:$L15,$B$3:$L$3,R$3)} -> 12638.082 | S15: {=TREND($B15:$L15,$B$3:$L$3,S$3)} -> 12660.709 | T15: {=TREND($B15:$L15,$B$3:$L$3,T$3)} -> 12683.336 | ... AG15: {=TREND($B15:$L15,$B$3:$L$3,AG$3)} -> 12977.491
... A20: LF Men | B20: 86685 | C20: 87014 | D20: 87352 | E20: 87638 | F20: 87951 | G20: 88277 | H20: 88574 | I20: 88898 | J20: 89217 | K20: 89533 | L20: 89838 | M20: {=TREND($B20:$L20,$B$3:$L$3,M$3)} -> 90156.764 | N20: {=TREND($B20:$L20,$B$3:$L$3,N$3)} -> 90471.118 | O20: {=TREND($B20:$L20,$B$3:$L$3,O$3)} -> 90785.473 | P20: {=TREND($B20:$L20,$B$3:$L$3,P$3)} -> 91099.827 | Q20: {=TREND($B20:$L20,$B$3:$L$3,Q$3)} -> 91414.182 | R20: {=TREND($B20:$L20,$B$3:$L$3,R$3)} -> 91728.536 | S20: {=TREND($B20:$L20,$B$3:$L$3,S$3)} -> 92042.891 | T20: {=TREND($B20:$L20,$B$3:$L$3,T$3)} -> 92357.245 | ... AG20: {=TREND($B20:$L20,$B$3:$L$3,AG$3)} -> 96443.855
A21: 16 and 17 | B21: 1027 | C21: 1001 | D21: 972 | E21: 941 | F21: 915 | G21: 886 | H21: 841 | I21: 801 | J21: 776 | K21: 746 | L21: 715
A22: 18 and 19 | B22: 1923 | C22: 1858 | D22: 1813 | E22: 1798 | F22: 1778 | G22: 1753 | H22: 1736 | I22: 1712 | J22: 1655 | K22: 1605 | L22: 1582
A23: 20 to 24 | B23: 7789 | C23: 7746 | D23: 7708 | E23: 7645 | F23: 7589 | G23: 7543 | H23: 7470 | I23: 7428 | J23: 7430 | K23: 7418 | L23: 7350
A24: 25 to 29 | B24: 10079 | C24: 9981 | D24: 9828 | E24: 9679 | F24: 9572 | G24: 9492 | H24: 9475 | I24: 9462 | J24: 9418 | K24: 9381 | L24: 9358
A25: 30 to 34 | B25: 9869 | C25: 10067 | D25: 10286 | E25: 10488 | F25: 10612 | G25: 10653 | H25: 10571 | I25: 10431 | J25: 10298 | K25: 10203 | L25: 10134
A26: 35 to 39 | B26: 9588 | C26: 9640 | D26: 9733 | E26: 9801 | F26: 9905 | G26: 10089 | H26: 10293 | I26: 10520 | J26: 10728 | K26: 10857 | L26: 10906
A27: 40 to 44 | B27: 8708 | C27: 8891 | D27: 9088 | E27: 9262 | F27: 9424 | G27: 9530 | H27: 9584 | I27: 9677 | J27: 9744 | K27: 9844 | L27: 10023
A28: 45 to 49 | B28: 8752 | C28: 8566 | D28: 8360 | E28: 8306 | F28: 8356 | G28: 8465 | H28: 8640 | I28: 8828 | J28: 8994 | K28: 9145 | L28: 9243
A29: 50 to 54 | B29: 8535 | C29: 8505 | D29: 8551 | E29: 8536 | F29: 8449 | G29: 8311 | H29: 8140 | I29: 7952 | J29: 7906 | K29: 7957 | L29: 8063
A30: 55 to 59 | B30: 8283 | C30: 8194 | D30: 8035 | E30: 7870 | F30: 7709 | G30: 7584 | H30: 7574 | I30: 7630 | J30: 7631 | K30: 7567 | L30: 7457
A31: 60 to 64 | B31: 6264 | C31: 6391 | D31: 6496 | E31: 6542 | F31: 6578 | G31: 6611 | H31: 6577 | I31: 6486 | J31: 6389 | K31: 6293 | L31: 6226
A32: 65 to 69 | B32: 3199 | C32: 3339 | D32: 3476 | E32: 3624 | F32: 3760 | G32: 3879 | H32: 4000 | I32: 4108 | J32: 4181 | K32: 4248 | L32: 4313
... A34: 75 and over | B34: 1113 | C34: 1174 | D34: 1235 | E34: 1341 | F34: 1436 | G34: 1531 | H34: 1629 | I34: 1729 | J34: 1832 | K34: 1942 | L34: 2057
A36: LF Women | B36: 76852 | C36: 77323 | D36: 77809 | E36: 78259 | F36: 78730 | G36: 79211 | H36: 79674 | I36: 80171 | J36: 80677 | K36: 81192 | L36: 81693 | M36: {=TREND($B36:$L36,$B$3:$L$3,M$3)} -> 82129.345 | N36: {=TREND($B36:$L36,$B$3:$L$3,N$3)} -> 82611.645 | O36: {=TREND($B36:$L36,$B$3:$L$3,O$3)} -> 83093.945 | P36: {=TREND($B36:$L36,$B$3:$L$3,P$3)} -> 83576.245 | Q36: {=TREND($B36:$L36,$B$3:$L$3,Q$3)} -> 84058.545 | R36: {=TREND($B36:$L36,$B$3:$L$3,R$3)} -> 84540.845 | S36: {=TREND($B36:$L36,$B$3:$L$3,S$3)} -> 85023.145 | T36: {=TREND($B36:$L36,$B$3:$L$3,T$3)} -> 85505.445 | ... AG36: {=TREND($B36:$L36,$B$3:$L$3,AG$3)} -> 91775.345
A37: 16 and 17 | B37: 1054 | C37: 1032 | D37: 1006 | E37: 979 | F37: 957 | G37: 933 | H37: 892 | I37: 854 | J37: 830 | K37: 802 | L37: 775
A38: 18 and 19 | B38: 1892 | C38: 1843 | D38: 1810 | E38: 1803 | F38: 1789 | G38: 1772 | H38: 1764 | I38: 1751 | J38: 1705 | K38: 1663 | L38: 1645
A39: 20 to 24 | B39: 7406 | C39: 7413 | D39: 7426 | E39: 7409 | F39: 7401 | G39: 7400 | H39: 7373 | I39: 7367 | J39: 7404 | K39: 7431 | L39: 7405
A40: 25 to 29 | B40: 8912 | C40: 8836 | D40: 8728 | E40: 8649 | F40: 8611 | G40: 8591 | H40: 8622 | I40: 8661 | J40: 8667 | K40: 8683 | L40: 8708
A41: 30 to 34 | B41: 8331 | C41: 8497 | D41: 8685 | E41: 8845 | F41: 8931 | G41: 8958 | H41: 8884 | I41: 8778 | J41: 8702 | K41: 8665 | L41: 8645
A42: 35 to 39 | B42: 8148 | C42: 8181 | D42: 8226 | E42: 8252 | F42: 8313 | G42: 8444 | H42: 8602 | I42: 8781 | J42: 8932 | K42: 9010 | L42: 9030
A43: 40 to 44 | B43: 7613 | C43: 7761 | D43: 7928 | E43: 8067 | F43: 8195 | G43: 8271 | H43: 8303 | I43: 8347 | J43: 8372 | K43: 8432 | L43: 8560
A44: 45 to 49 | B44: 7955 | C44: 7808 | D44: 7635 | E44: 7603 | F44: 7651 | G44: 7758 | H44: 7922 | I44: 8105 | J44: 8262 | K44: 8407 | L44: 8500
A45: 50 to 54 | B45: 7689 | C45: 7689 | D45: 7772 | E45: 7797 | F45: 7767 | G45: 7684 | H45: 7564 | I45: 7419 | J45: 7408 | K45: 7476 | L45: 7600
A46: 55 to 59 | B46: 7473 | C46: 7444 | D46: 7341 | E46: 7236 | F46: 7125 | G46: 7044 | H46: 7072 | I46: 7173 | J46: 7221 | K46: 7219 | L46: 7167
A47: 60 to 64 | B47: 5583 | C47: 5733 | D47: 5872 | E47: 5958 | F47: 6037 | G47: 6112 | H47: 6125 | I47: 6077 | J47: 6026 | K47: 5969 | L47: 5937
A48: 65 to 69 | B48: 2735 | C48: 2874 | D48: 3009 | E48: 3156 | F48: 3291 | G48: 3411 | H48: 3533 | I48: 3649 | J48: 3734 | K48: 3816 | L48: 3895
... A50: 75 and over | B50: 851 | C50: 905 | D50: 960 | E50: 1048 | F50: 1132 | G50: 1220 | H50: 1313 | I50: 1411 | J50: 1516 | K50: 1628 | L50: 1748
A52: LF White men | B52: 68367 | C52: 68433 | D52: 68502 | E52: 68523 | F52: 68566 | G52: 68617 | H52: 68644 | I52: 68688 | J52: 68725 | K52: 68759 | L52: 68784 | M52: {=TREND($B52:$L52,$B$3:$L$3,M$3)} -> 68844.327 | N52: {=TREND($B52:$L52,$B$3:$L$3,N$3)} -> 68884.927 | O52: {=TREND($B52:$L52,$B$3:$L$3,O$3)} -> 68925.527 | P52: {=TREND($B52:$L52,$B$3:$L$3,P$3)} -> 68966.127 | Q52: {=TREND($B52:$L52,$B$3:$L$3,Q$3)} -> 69006.727 | R52: {=TREND($B52:$L52,$B$3:$L$3,R$3)} -> 69047.327 | S52: {=TREND($B52:$L52,$B$3:$L$3,S$3)} -> 69087.927 | T52: {=TREND($B52:$L52,$B$3:$L$3,T$3)} -> 69128.527 | ... AG52: {=TREND($B52:$L52,$B$3:$L$3,AG$3)} -> 69656.327
A53: 16 and 17 | B53: 828 | C53: 805 | D53: 778 | E53: 750 | F53: 725 | G53: 698 | H53: 660 | I53: 626 | J53: 606 | K53: 581 | L53: 553
A54: 18 and 19 | B54: 1501 | C54: 1449 | D54: 1412 | E54: 1397 | F54: 1375 | G54: 1348 | H54: 1327 | I54: 1299 | J54: 1250 | K54: 1208 | L54: 1189
A55: 20 to 24 | B55: 5930 | C55: 5891 | D55: 5852 | E55: 5796 | F55: 5746 | G55: 5702 | H55: 5635 | I55: 5588 | J55: 5566 | K55: 5528 | L55: 5449
A56: 25 to 29 | B56: 7526 | C56: 7440 | D56: 7325 | E56: 7215 | F56: 7136 | G56: 7078 | H56: 7056 | I56: 7032 | J56: 6989 | K56: 6949 | L56: 6917
A57: 30 to 34 | B57: 7477 | C57: 7568 | D57: 7671 | E57: 7767 | F57: 7813 | G57: 7814 | H57: 7738 | I57: 7633 | J57: 7532 | K57: 7461 | L57: 7409
A58: 35 to 39 | B58: 7404 | C58: 7426 | D58: 7469 | E58: 7490 | F58: 7530 | G58: 7620 | H58: 7717 | I58: 7826 | J58: 7928 | K58: 7978 | L58: 7986
A59: 40 to 44 | B59: 6785 | C59: 6912 | D59: 7056 | E59: 7176 | F59: 7282 | G59: 7346 | H59: 7369 | I59: 7413 | J59: 7435 | K59: 7473 | L59: 7560
A60: 45 to 49 | B60: 6854 | C60: 6675 | D60: 6481 | E60: 6421 | F60: 6452 | G60: 6521 | H60: 6639 | I60: 6775 | J60: 6885 | K60: 6982 | L60: 7038
A61: 50 to 54 | B61: 6875 | C61: 6830 | D61: 6850 | E61: 6805 | F61: 6703 | G61: 6559 | H61: 6394 | I61: 6214 | J61: 6163 | K61: 6195 | L61: 6265
A62: 55 to 59 | B62: 6862 | C62: 6768 | D62: 6607 | E62: 6449 | F62: 6295 | G62: 6174 | H62: 6148 | I62: 6179 | J62: 6151 | K62: 6071 | L62: 5955
A63: 60 to 64 | B63: 5268 | C63: 5362 | D63: 5444 | E63: 5473 | F63: 5487 | G63: 5500 | H63: 5458 | I63: 5360 | J63: 5263 | K63: 5167 | L63: 5098
A64: 65 to 69 | B64: 2731 | C64: 2844 | D64: 2950 | E64: 3065 | F64: 3171 | G64: 3261 | H64: 3352 | I64: 3437 | J64: 3489 | K64: 3531 | L64: 3573
... A66: 75 and over | B66: 971 | C66: 1022 | D66: 1073 | E66: 1164 | F66: 1245 | G66: 1323 | H66: 1403 | I66: 1485 | J66: 1571 | K66: 1660 | L66: 1753
A68: LF White Women | B68: 58233 | C68: 58415 | D68: 58606 | E68: 58761 | F68: 58933 | G68: 59109 | H68: 59273 | I68: 59458 | J68: 59648 | K68: 59844 | L68: 60030 | M68: {=TREND($B68:$L68,$B$3:$L$3,M$3)} -> 60186.055 | N68: {=TREND($B68:$L68,$B$3:$L$3,N$3)} -> 60363.882 | O68: {=TREND($B68:$L68,$B$3:$L$3,O$3)} -> 60541.709 | P68: {=TREND($B68:$L68,$B$3:$L$3,P$3)} -> 60719.536 | Q68: {=TREND($B68:$L68,$B$3:$L$3,Q$3)} -> 60897.364 | R68: {=TREND($B68:$L68,$B$3:$L$3,R$3)} -> 61075.191 | S68: {=TREND($B68:$L68,$B$3:$L$3,S$3)} -> 61253.018 | T68: {=TREND($B68:$L68,$B$3:$L$3,T$3)} -> 61430.845 | ... AG68: {=TREND($B68:$L68,$B$3:$L$3,AG$3)} -> 63742.6
A69: 16 and 17 | B69: 816 | C69: 797 | D69: 773 | E69: 748 | F69: 727 | G69: 704 | H69: 670 | I69: 639 | J69: 620 | K69: 598 | L69: 573
A70: 18 and 19 | B70: 1449 | C70: 1410 | D70: 1382 | E70: 1373 | F70: 1357 | G70: 1337 | H70: 1324 | I70: 1305 | J70: 1264 | K70: 1230 | L70: 1216
A71: 20 to 24 | B71: 5465 | C71: 5460 | D71: 5455 | E71: 5431 | F71: 5414 | G71: 5400 | H71: 5365 | I71: 5342 | J71: 5346 | K71: 5337 | L71: 5290
A72: 25 to 29 | B72: 6453 | C72: 6389 | D72: 6308 | E72: 6248 | F72: 6218 | G72: 6201 | H72: 6214 | I72: 6227 | J72: 6220 | K72: 6220 | L72: 6223
A73: 30 to 34 | B73: 6078 | C73: 6160 | D73: 6257 | E73: 6339 | F73: 6371 | G73: 6373 | H73: 6312 | I73: 6234 | J73: 6176 | K73: 6148 | L73: 6132
A74: 35 to 39 | B74: 6004 | C74: 6018 | D74: 6034 | E74: 6032 | F74: 6049 | G74: 6107 | H74: 6181 | I74: 6269 | J74: 6342 | K74: 6365 | L74: 6360
A75: 40 to 44 | B75: 5613 | C75: 5704 | D75: 5817 | E75: 5908 | F75: 5989 | G75: 6035 | H75: 6048 | I75: 6064 | J75: 6061 | K75: 6078 | L75: 6134
A76: 45 to 49 | B76: 5972 | C76: 5827 | D76: 5665 | E76: 5621 | F76: 5646 | G76: 5709 | H76: 5813 | I76: 5939 | J76: 6043 | K76: 6138 | L76: 6197
A77: 50 to 54 | B77: 5986 | C77: 5964 | D77: 6008 | E77: 5994 | F77: 5939 | G77: 5840 | H77: 5718 | I77: 5579 | J77: 5553 | K77: 5596 | L77: 5676
A78: 55 to 59 | B78: 5984 | C78: 5940 | D78: 5826 | E78: 5716 | F78: 5602 | G78: 5517 | H78: 5517 | I78: 5578 | J78: 5584 | K78: 5551 | L78: 5478
A79: 60 to 64 | B79: 4485 | C79: 4592 | D79: 4697 | E79: 4755 | F79: 4801 | G79: 4843 | H79: 4836 | I79: 4771 | J79: 4708 | K79: 4640 | L79: 4596
A80: 65 to 69 | B80: 2218 | C80: 2326 | D80: 2428 | E80: 2538 | F80: 2639 | G80: 2727 | H80: 2816 | I80: 2904 | J80: 2964 | K80: 3018 | L80: 3069
... A82: 75 and over | B82: 711 | C82: 754 | D82: 798 | E82: 871 | F82: 939 | G82: 1009 | H82: 1083 | I82: 1160 | J82: 1243 | K82: 1332 | L82: 1427
A84: LF Black Men | B84: 9788 | C84: 9859 | D84: 9929 | E84: 9997 | F84: 10067 | G84: 10139 | H84: 10207 | I84: 10278 | J84: 10349 | K84: 10421 | L84: 10491 | M84: {=TREND($B84:$L84,$B$3:$L$3,M$3)} -> 10560 | N84: {=TREND($B84:$L84,$B$3:$L$3,N$3)} -> 10630.227 | O84: {=TREND($B84:$L84,$B$3:$L$3,O$3)} -> 10700.455 | P84: {=TREND($B84:$L84,$B$3:$L$3,P$3)} -> 10770.682 | Q84: {=TREND($B84:$L84,$B$3:$L$3,Q$3)} -> 10840.909 | R84: {=TREND($B84:$L84,$B$3:$L$3,R$3)} -> 10911.136 | S84: {=TREND($B84:$L84,$B$3:$L$3,S$3)} -> 10981.364 | T84: {=TREND($B84:$L84,$B$3:$L$3,T$3)} -> 11051.591 | ... AG84: {=TREND($B84:$L84,$B$3:$L$3,AG$3)} -> 11964.545
A85: 16 and 17 | B85: 98 | C85: 94 | D85: 92 | E85: 89 | F85: 88 | G85: 86 | H85: 82 | I85: 78 | J85: 75 | K85: 72 | L85: 70
A86: 18 and 19 | B86: 237 | C86: 226 | D86: 217 | E86: 213 | F86: 212 | G86: 211 | H86: 213 | I86: 213 | J86: 206 | K86: 200 | L86: 197
A87: 20 to 24 | B87: 1062 | C87: 1051 | D87: 1045 | E87: 1032 | F87: 1015 | G87: 1001 | H87: 982 | I87: 973 | J87: 978 | K87: 986 | L87: 987
A88: 25 to 29 | B88: 1396 | C88: 1374 | D88: 1331 | E88: 1288 | F88: 1251 | G88: 1222 | H88: 1212 | I88: 1208 | J88: 1195 | K88: 1178 | L88: 1163
A89: 30 to 34 | B89: 1235 | C89: 1299 | D89: 1367 | E89: 1430 | F89: 1475 | G89: 1491 | H89: 1473 | I89: 1431 | J89: 1390 | K89: 1354 | L89: 1326
A90: 35 to 39 | B90: 1097 | C90: 1103 | D90: 1121 | E90: 1143 | F90: 1176 | G90: 1230 | H90: 1294 | I90: 1362 | J90: 1424 | K90: 1469 | L90: 1486
A91: 40 to 44 | B91: 981 | C91: 1013 | D91: 1039 | E91: 1061 | F91: 1082 | G91: 1094 | H91: 1101 | I91: 1121 | J91: 1143 | K91: 1176 | L91: 1229
A92: 45 to 49 | B92: 998 | C92: 980 | D92: 960 | E92: 955 | F92: 963 | G92: 985 | H92: 1017 | I92: 1043 | J92: 1065 | K92: 1085 | L92: 1096
A93: 50 to 54 | B93: 927 | C93: 920 | D93: 922 | E93: 925 | F93: 919 | G93: 911 | H93: 896 | I93: 879 | J93: 876 | K93: 883 | L93: 903
A94: 55 to 59 | B94: 785 | C94: 782 | D94: 775 | E94: 763 | F94: 751 | G94: 736 | H94: 733 | I94: 735 | J94: 738 | K94: 735 | L94: 729
A95: 60 to 64 | B95: 551 | C95: 568 | D95: 579 | E95: 585 | F95: 591 | G95: 596 | H95: 597 | I95: 595 | J95: 588 | K95: 582 | L95: 574
A96: 65 to 69 | B96: 245 | C96: 260 | D96: 275 | E96: 292 | F96: 309 | G96: 324 | H96: 339 | I96: 351 | J96: 360 | K96: 369 | L96: 378
... A98: 75 and over | B98: 71 | C98: 76 | D98: 81 | E98: 88 | F98: 96 | G98: 104 | H98: 113 | I98: 123 | J98: 133 | K98: 143 | L98: 155
A100: LF Black Women | B100: 10843 | C100: 10943 | D100: 11043 | E100: 11141 | F100: 11242 | G100: 11343 | H100: 11440 | I100: 11542 | J100: 11646 | K100: 11751 | L100: 11853 | M100: {=TREND($B100:$L100,$B$3:$L$3,M$3)} -> 11949.236 | N100: {=TREND($B100:$L100,$B$3:$L$3,N$3)} -> 12050.064 | O100: {=TREND($B100:$L100,$B$3:$L$3,O$3)} -> 12150.891 | P100: {=TREND($B100:$L100,$B$3:$L$3,P$3)} -> 12251.718 | Q100: {=TREND($B100:$L100,$B$3:$L$3,Q$3)} -> 12352.545 | R100: {=TREND($B100:$L100,$B$3:$L$3,R$3)} -> 12453.373 | S100: {=TREND($B100:$L100,$B$3:$L$3,S$3)} -> 12554.2 | T100: {=TREND($B100:$L100,$B$3:$L$3,T$3)} -> 12655.027 | ... AG100: {=TREND($B100:$L100,$B$3:$L$3,AG$3)} -> 13965.782
A101: 16 and 17 | B101: 135 | C101: 132 | D101: 130 | E101: 129 | F101: 129 | G101: 128 | H101: 123 | I101: 118 | J101: 116 | K101: 113 | L101: 110
A102: 18 and 19 | B102: 270 | C102: 261 | D102: 254 | E102: 251 | F102: 251 | G102: 253 | H102: 257 | I102: 259 | J102: 254 | K102: 248 | L102: 246
A103: 20 to 24 | B103: 1124 | C103: 1122 | D103: 1125 | E103: 1121 | F103: 1113 | G103: 1108 | H103: 1098 | I103: 1099 | J103: 1111 | K103: 1127 | L103: 1136
A104: 25 to 29 | B104: 1422 | C104: 1402 | D104: 1367 | E104: 1338 | F104: 1315 | G104: 1297 | H104: 1298 | I104: 1302 | J104: 1300 | K104: 1293 | L104: 1289
A105: 30 to 34 | B105: 1292 | C105: 1345 | D105: 1402 | E105: 1451 | F105: 1483 | G105: 1493 | H105: 1472 | I105: 1437 | J105: 1406 | K105: 1384 | L105: 1366
A106: 35 to 39 | B106: 1235 | C106: 1237 | D106: 1248 | E106: 1262 | F106: 1286 | G106: 1331 | H106: 1385 | I106: 1442 | J106: 1491 | K106: 1523 | L106: 1532
A107: 40 to 44 | B107: 1118 | C107: 1149 | D107: 1176 | E107: 1197 | F107: 1216 | G107: 1222 | H107: 1224 | I107: 1235 | J107: 1247 | K107: 1270 | L107: 1313
A108: 45 to 49 | B108: 1136 | C108: 1122 | D108: 1101 | E108: 1100 | F108: 1109 | G108: 1132 | H108: 1165 | I108: 1194 | J108: 1217 | K108: 1237 | L108: 1246
A109: 50 to 54 | B109: 1024 | C109: 1022 | D109: 1033 | E109: 1042 | F109: 1044 | G109: 1042 | H109: 1032 | I109: 1015 | J109: 1016 | K109: 1026 | L109: 1049
A110: 55 to 59 | B110: 906 | C110: 909 | D110: 908 | E110: 903 | F110: 896 | G110: 886 | H110: 888 | I110: 901 | J110: 911 | K110: 917 | L110: 919
A111: 60 to 64 | B111: 663 | C111: 687 | D111: 705 | E111: 718 | F111: 731 | G111: 743 | H111: 750 | I111: 754 | J111: 753 | K111: 751 | L111: 747
A112: 65 to 69 | B112: 308 | C112: 326 | D112: 344 | E112: 366 | F112: 385 | G112: 403 | H112: 421 | I112: 436 | J112: 448 | K112: 461 | L112: 472
... A114: 75 and over | B114: 81 | C114: 87 | D114: 92 | E114: 100 | F114: 109 | G114: 118 | H114: 129 | I114: 140 | J114: 152 | K114: 164 | L114: 178
A116: LF "All Other" Men | B116: 8530 | C116: 8723 | D116: 8920 | E116: 9117 | F116: 9320 | G116: 9521 | H116: 9721 | I116: 9934 | J116: 10142 | K116: 10354 | L116: 10562 | M116: {=TREND($B116:$L116,$B$3:$L$3,M$3)} -> 10752.273 | N116: {=TREND($B116:$L116,$B$3:$L$3,N$3)} -> 10955.773 | O116: {=TREND($B116:$L116,$B$3:$L$3,O$3)} -> 11159.273 | P116: {=TREND($B116:$L116,$B$3:$L$3,P$3)} -> 11362.773 | Q116: {=TREND($B116:$L116,$B$3:$L$3,Q$3)} -> 11566.273 | R116: {=TREND($B116:$L116,$B$3:$L$3,R$3)} -> 11769.773 | S116: {=TREND($B116:$L116,$B$3:$L$3,S$3)} -> 11973.273 | T116: {=TREND($B116:$L116,$B$3:$L$3,T$3)} -> 12176.773 | ... AG116: {=TREND($B116:$L116,$B$3:$L$3,AG$3)} -> 14822.273
...

Sheet LF Projected Ratios
A1: Ratios of Labor Force Participants with Particular Demographic Traits
A2: Sex
B3: 2019 | C3: 2020 | D3: 2021 | E3: 2022 | F3: 2023 | G3: 2024 | H3: 2025 | I3: 2026 | J3: 2027 | K3: 2028 | L3: 2029 | M3: 2030 | N3: 2031 | O3: 2032 | P3: 2033 | Q3: 2034 | R3: 2035 | S3: 2036 | T3: 2037 | U3: 2038 | V3: 2039 | W3: 2040 | X3: 2041 | Y3: 2042 | Z3: 2043 | AA3: 2044 | AB3: 2045 | AC3: 2046 | AD3: 2047 | AE3: 2048 | AF3: 2049 | AG3: 2050
A4: Men | B4: ='BLS LF projections 2019-2029'!B20/SUM('BLS LF projections 2019-2029'!B$20,'BLS LF projections 2019-2029'!B$36) -> 0.53006353 | C4: ='BLS LF projections 2019-2029'!C20/SUM('BLS LF projections 2019-2029'!C$20,'BLS LF projections 2019-2029'!C$36) -> 0.52948514 | D4: ='BLS LF projections 2019-2029'!D20/SUM('BLS LF projections 2019-2029'!D$20,'BLS LF projections 2019-2029'!D$36) -> 0.52888999 | E4: ='BLS LF projections 2019-2029'!E20/SUM('BLS LF projections 2019-2029'!E$20,'BLS LF projections 2019-2029'!E$36) -> 0.52826754 | F4: ='BLS LF projections 2019-2029'!F20/SUM('BLS LF projections 2019-2029'!F$20,'BLS LF projections 2019-2029'!F$36) -> 0.52766062 | G4: ='BLS LF projections 2019-2029'!G20/SUM('BLS LF projections 2019-2029'!G$20,'BLS LF projections 2019-2029'!G$36) -> 0.52706463 | H4: ='BLS LF projections 2019-2029'!H20/SUM('BLS LF projections 2019-2029'!H$20,'BLS LF projections 2019-2029'!H$36) -> 0.52644905 | I4: ='BLS LF projections 2019-2029'!I20/SUM('BLS LF projections 2019-2029'!I$20,'BLS LF projections 2019-2029'!I$36) -> 0.52580899 | ... AG4: ='BLS LF projections 2019-2029'!AG20/SUM('BLS LF projections 2019-2029'!AG$20,'BLS LF projections 2019-2029'!AG$36) -> 0.51240179
A5: Women | B5: ='BLS LF projections 2019-2029'!B36/SUM('BLS LF projections 2019-2029'!B$20,'BLS LF projections 2019-2029'!B$36) -> 0.46993647 | C5: ='BLS LF projections 2019-2029'!C36/SUM('BLS LF projections 2019-2029'!C$20,'BLS LF projections 2019-2029'!C$36) -> 0.47051486 | D5: ='BLS LF projections 2019-2029'!D36/SUM('BLS LF projections 2019-2029'!D$20,'BLS LF projections 2019-2029'!D$36) -> 0.47111001 | E5: ='BLS LF projections 2019-2029'!E36/SUM('BLS LF projections 2019-2029'!E$20,'BLS LF projections 2019-2029'!E$36) -> 0.47173246 | F5: ='BLS LF projections 2019-2029'!F36/SUM('BLS LF projections 2019-2029'!F$20,'BLS LF projections 2019-2029'!F$36) -> 0.47233938 | G5: ='BLS LF projections 2019-2029'!G36/SUM('BLS LF projections 2019-2029'!G$20,'BLS LF projections 2019-2029'!G$36) -> 0.47293537 | H5: ='BLS LF projections 2019-2029'!H36/SUM('BLS LF projections 2019-2029'!H$20,'BLS LF projections 2019-2029'!H$36) -> 0.47355095 | I5: ='BLS LF projections 2019-2029'!I36/SUM('BLS LF projections 2019-2029'!I$20,'BLS LF projections 2019-2029'!I$36) -> 0.47419101 | ... AG5: ='BLS LF projections 2019-2029'!AG36/SUM('BLS LF projections 2019-2029'!AG$20,'BLS LF projections 2019-2029'!AG$36) -> 0.48759821
A7: Race
B8: 2019 | C8: 2020 | D8: 2021 | E8: 2022 | F8: 2023 | G8: 2024 | H8: 2025 | I8: 2026 | J8: 2027 | K8: 2028 | L8: 2029 | M8: 2030 | N8: 2031 | O8: 2032 | P8: 2033 | Q8: 2034 | R8: 2035 | S8: 2036 | T8: 2037 | U8: 2038 | V8: 2039 | W8: 2040 | X8: 2041 | Y8: 2042 | Z8: 2043 | AA8: 2044 | AB8: 2045 | AC8: 2046 | AD8: 2047 | AE8: 2048 | AF8: 2049 | AG8: 2050
A9: White | B9: =SUM('BLS LF projections 2019-2029'!B52,'BLS LF projections 2019-2029'!B68)/SUM('BLS LF projections 2019-2029'!B$52,'BLS LF projections 2019-2029'!B$68,'BLS LF projections 2019-2029'!B$84,'BLS LF projections 2019-2029'!B$100,'BLS LF projections 2019-2029'!B$116,'BLS LF projections 2019-2029'!B$132) -> 0.77413674 | C9: =SUM('BLS LF projections 2019-2029'!C52,'BLS LF projections 2019-2029'!C68)/SUM('BLS LF projections 2019-2029'!C$52,'BLS LF projections 2019-2029'!C$68,'BLS LF projections 2019-2029'!C$84,'BLS LF projections 2019-2029'!C$100,'BLS LF projections 2019-2029'!C$116,'BLS LF projections 2019-2029'!C$132) -> 0.7718726 | D9: =SUM('BLS LF projections 2019-2029'!D52,'BLS LF projections 2019-2029'!D68)/SUM('BLS LF projections 2019-2029'!D$52,'BLS LF projections 2019-2029'!D$68,'BLS LF projections 2019-2029'!D$84,'BLS LF projections 2019-2029'!D$100,'BLS LF projections 2019-2029'!D$116,'BLS LF projections 2019-2029'!D$132) -> 0.76960523 | E9: =SUM('BLS LF projections 2019-2029'!E52,'BLS LF projections 2019-2029'!E68)/SUM('BLS LF projections 2019-2029'!E$52,'BLS LF projections 2019-2029'!E$68,'BLS LF projections 2019-2029'!E$84,'BLS LF projections 2019-2029'!E$100,'BLS LF projections 2019-2029'!E$116,'BLS LF projections 2019-2029'!E$132) -> 0.76725177 | F9: =SUM('BLS LF projections 2019-2029'!F52,'BLS LF projections 2019-2029'!F68)/SUM('BLS LF projections 2019-2029'!F$52,'BLS LF projections 2019-2029'!F$68,'BLS LF projections 2019-2029'!F$84,'BLS LF projections 2019-2029'!F$100,'BLS LF projections 2019-2029'!F$116,'BLS LF projections 2019-2029'!F$132) -> 0.76491445 | G9: =SUM('BLS LF projections 2019-2029'!G52,'BLS LF projections 2019-2029'!G68)/SUM('BLS LF projections 2019-2029'!G$52,'BLS LF projections 2019-2029'!G$68,'BLS LF projections 2019-2029'!G$84,'BLS LF projections 2019-2029'!G$100,'BLS LF projections 2019-2029'!G$116,'BLS LF projections 2019-2029'!G$132) -> 0.76259792 | H9: =SUM('BLS LF projections 2019-2029'!H52,'BLS LF projections 2019-2029'!H68)/SUM('BLS LF projections 2019-2029'!H$52,'BLS LF projections 2019-2029'!H$68,'BLS LF projections 2019-2029'!H$84,'BLS LF projections 2019-2029'!H$100,'BLS LF projections 2019-2029'!H$116,'BLS LF projections 2019-2029'!H$132) -> 0.7602929 | I9: =SUM('BLS LF projections 2019-2029'!I52,'BLS LF projections 2019-2029'!I68)/SUM('BLS LF projections 2019-2029'!I$52,'BLS LF projections 2019-2029'!I$68,'BLS LF projections 2019-2029'!I$84,'BLS LF projections 2019-2029'!I$100,'BLS LF projections 2019-2029'!I$116,'BLS LF projections 2019-2029'!I$132) -> 0.75794193 | ... AG9: =SUM('BLS LF projections 2019-2029'!AG52,'BLS LF projections 2019-2029'!AG68)/SUM('BLS LF projections 2019-2029'!AG$52,'BLS LF projections 2019-2029'!AG$68,'BLS LF projections 2019-2029'!AG$84,'BLS LF projections 2019-2029'!AG$100,'BLS LF projections 2019-2029'!AG$116,'BLS LF projections 2019-2029'!AG$132) -> 0.70874829
A10: Black | B10: =SUM('BLS LF projections 2019-2029'!B84,'BLS LF projections 2019-2029'!B100)/SUM('BLS LF projections 2019-2029'!B$52,'BLS LF projections 2019-2029'!B$68,'BLS LF projections 2019-2029'!B$84,'BLS LF projections 2019-2029'!B$100,'BLS LF projections 2019-2029'!B$116,'BLS LF projections 2019-2029'!B$132) -> 0.12615494 | C10: =SUM('BLS LF projections 2019-2029'!C84,'BLS LF projections 2019-2029'!C100)/SUM('BLS LF projections 2019-2029'!C$52,'BLS LF projections 2019-2029'!C$68,'BLS LF projections 2019-2029'!C$84,'BLS LF projections 2019-2029'!C$100,'BLS LF projections 2019-2029'!C$116,'BLS LF projections 2019-2029'!C$132) -> 0.12658058 | D10: =SUM('BLS LF projections 2019-2029'!D84,'BLS LF projections 2019-2029'!D100)/SUM('BLS LF projections 2019-2029'!D$52,'BLS LF projections 2019-2029'!D$68,'BLS LF projections 2019-2029'!D$84,'BLS LF projections 2019-2029'!D$100,'BLS LF projections 2019-2029'!D$116,'BLS LF projections 2019-2029'!D$132) -> 0.1269799 | E10: =SUM('BLS LF projections 2019-2029'!E84,'BLS LF projections 2019-2029'!E100)/SUM('BLS LF projections 2019-2029'!E$52,'BLS LF projections 2019-2029'!E$68,'BLS LF projections 2019-2029'!E$84,'BLS LF projections 2019-2029'!E$100,'BLS LF projections 2019-2029'!E$116,'BLS LF projections 2019-2029'!E$132) -> 0.12741718 | F10: =SUM('BLS LF projections 2019-2029'!F84,'BLS LF projections 2019-2029'!F100)/SUM('BLS LF projections 2019-2029'!F$52,'BLS LF projections 2019-2029'!F$68,'BLS LF projections 2019-2029'!F$84,'BLS LF projections 2019-2029'!F$100,'BLS LF projections 2019-2029'!F$116,'BLS LF projections 2019-2029'!F$132) -> 0.1278407 | G10: =SUM('BLS LF projections 2019-2029'!G84,'BLS LF projections 2019-2029'!G100)/SUM('BLS LF projections 2019-2029'!G$52,'BLS LF projections 2019-2029'!G$68,'BLS LF projections 2019-2029'!G$84,'BLS LF projections 2019-2029'!G$100,'BLS LF projections 2019-2029'!G$116,'BLS LF projections 2019-2029'!G$132) -> 0.12825994 | H10: =SUM('BLS LF projections 2019-2029'!H84,'BLS LF projections 2019-2029'!H100)/SUM('BLS LF projections 2019-2029'!H$52,'BLS LF projections 2019-2029'!H$68,'BLS LF projections 2019-2029'!H$84,'BLS LF projections 2019-2029'!H$100,'BLS LF projections 2019-2029'!H$116,'BLS LF projections 2019-2029'!H$132) -> 0.12866203 | I10: =SUM('BLS LF projections 2019-2029'!I84,'BLS LF projections 2019-2029'!I100)/SUM('BLS LF projections 2019-2029'!I$52,'BLS LF projections 2019-2029'!I$68,'BLS LF projections 2019-2029'!I$84,'BLS LF projections 2019-2029'!I$100,'BLS LF projections 2019-2029'!I$116,'BLS LF projections 2019-2029'!I$132) -> 0.12905821 | ... AG10: =SUM('BLS LF projections 2019-2029'!AG84,'BLS LF projections 2019-2029'!AG100)/SUM('BLS LF projections 2019-2029'!AG$52,'BLS LF projections 2019-2029'!AG$68,'BLS LF projections 2019-2029'!AG$84,'BLS LF projections 2019-2029'!AG$100,'BLS LF projections 2019-2029'!AG$116,'BLS LF projections 2019-2029'!AG$132) -> 0.13776779
A11: Other (inc. Asian) | B11: =SUM('BLS LF projections 2019-2029'!B116,'BLS LF projections 2019-2029'!B132)/SUM('BLS LF projections 2019-2029'!B$52,'BLS LF projections 2019-2029'!B$68,'BLS LF projections 2019-2029'!B$84,'BLS LF projections 2019-2029'!B$100,'BLS LF projections 2019-2029'!B$116,'BLS LF projections 2019-2029'!B$132) -> 0.099708323 | C11: =SUM('BLS LF projections 2019-2029'!C116,'BLS LF projections 2019-2029'!C132)/SUM('BLS LF projections 2019-2029'!C$52,'BLS LF projections 2019-2029'!C$68,'BLS LF projections 2019-2029'!C$84,'BLS LF projections 2019-2029'!C$100,'BLS LF projections 2019-2029'!C$116,'BLS LF projections 2019-2029'!C$132) -> 0.10154681 | D11: =SUM('BLS LF projections 2019-2029'!D116,'BLS LF projections 2019-2029'!D132)/SUM('BLS LF projections 2019-2029'!D$52,'BLS LF projections 2019-2029'!D$68,'BLS LF projections 2019-2029'!D$84,'BLS LF projections 2019-2029'!D$100,'BLS LF projections 2019-2029'!D$116,'BLS LF projections 2019-2029'!D$132) -> 0.10341487 | E11: =SUM('BLS LF projections 2019-2029'!E116,'BLS LF projections 2019-2029'!E132)/SUM('BLS LF projections 2019-2029'!E$52,'BLS LF projections 2019-2029'!E$68,'BLS LF projections 2019-2029'!E$84,'BLS LF projections 2019-2029'!E$100,'BLS LF projections 2019-2029'!E$116,'BLS LF projections 2019-2029'!E$132) -> 0.10533105 | F11: =SUM('BLS LF projections 2019-2029'!F116,'BLS LF projections 2019-2029'!F132)/SUM('BLS LF projections 2019-2029'!F$52,'BLS LF projections 2019-2029'!F$68,'BLS LF projections 2019-2029'!F$84,'BLS LF projections 2019-2029'!F$100,'BLS LF projections 2019-2029'!F$116,'BLS LF projections 2019-2029'!F$132) -> 0.10724485 | G11: =SUM('BLS LF projections 2019-2029'!G116,'BLS LF projections 2019-2029'!G132)/SUM('BLS LF projections 2019-2029'!G$52,'BLS LF projections 2019-2029'!G$68,'BLS LF projections 2019-2029'!G$84,'BLS LF projections 2019-2029'!G$100,'BLS LF projections 2019-2029'!G$116,'BLS LF projections 2019-2029'!G$132) -> 0.10914215 | H11: =SUM('BLS LF projections 2019-2029'!H116,'BLS LF projections 2019-2029'!H132)/SUM('BLS LF projections 2019-2029'!H$52,'BLS LF projections 2019-2029'!H$68,'BLS LF projections 2019-2029'!H$84,'BLS LF projections 2019-2029'!H$100,'BLS LF projections 2019-2029'!H$116,'BLS LF projections 2019-2029'!H$132) -> 0.11104507 | I11: =SUM('BLS LF projections 2019-2029'!I116,'BLS LF projections 2019-2029'!I132)/SUM('BLS LF projections 2019-2029'!I$52,'BLS LF projections 2019-2029'!I$68,'BLS LF projections 2019-2029'!I$84,'BLS LF projections 2019-2029'!I$100,'BLS LF projections 2019-2029'!I$116,'BLS LF projections 2019-2029'!I$132) -> 0.11299986 | ... AG11: =SUM('BLS LF projections 2019-2029'!AG116,'BLS LF projections 2019-2029'!AG132)/SUM('BLS LF projections 2019-2029'!AG$52,'BLS LF projections 2019-2029'!AG$68,'BLS LF projections 2019-2029'!AG$84,'BLS LF projections 2019-2029'!AG$100,'BLS LF projections 2019-2029'!AG$116,'BLS LF projections 2019-2029'!AG$132) -> 0.15348393
A13: Hispanic Status
B14: 2019 | C14: 2020 | D14: 2021 | E14: 2022 | F14: 2023 | G14: 2024 | H14: 2025 | I14: 2026 | J14: 2027 | K14: 2028 | L14: 2029 | M14: 2030 | N14: 2031 | O14: 2032 | P14: 2033 | Q14: 2034 | R14: 2035 | S14: 2036 | T14: 2037 | U14: 2038 | V14: 2039 | W14: 2040 | X14: 2041 | Y14: 2042 | Z14: 2043 | AA14: 2044 | AB14: 2045 | AC14: 2046 | AD14: 2047 | AE14: 2048 | AF14: 2049 | AG14: 2050
A15: Hispanic | B15: =SUM('BLS LF projections 2019-2029'!B148,'BLS LF projections 2019-2029'!B164)/SUM('BLS LF projections 2019-2029'!B148,'BLS LF projections 2019-2029'!B164,'BLS LF projections 2019-2029'!B180,'BLS LF projections 2019-2029'!B196) -> 0.1776601 | C15: =SUM('BLS LF projections 2019-2029'!C148,'BLS LF projections 2019-2029'!C164)/SUM('BLS LF projections 2019-2029'!C148,'BLS LF projections 2019-2029'!C164,'BLS LF projections 2019-2029'!C180,'BLS LF projections 2019-2029'!C196) -> 0.18085288 | D15: =SUM('BLS LF projections 2019-2029'!D148,'BLS LF projections 2019-2029'!D164)/SUM('BLS LF projections 2019-2029'!D148,'BLS LF projections 2019-2029'!D164,'BLS LF projections 2019-2029'!D180,'BLS LF projections 2019-2029'!D196) -> 0.18404466 | E15: =SUM('BLS LF projections 2019-2029'!E148,'BLS LF projections 2019-2029'!E164)/SUM('BLS LF projections 2019-2029'!E148,'BLS LF projections 2019-2029'!E164,'BLS LF projections 2019-2029'!E180,'BLS LF projections 2019-2029'!E196) -> 0.18732218 | F15: =SUM('BLS LF projections 2019-2029'!F148,'BLS LF projections 2019-2029'!F164)/SUM('BLS LF projections 2019-2029'!F148,'BLS LF projections 2019-2029'!F164,'BLS LF projections 2019-2029'!F180,'BLS LF projections 2019-2029'!F196) -> 0.19057961 | G15: =SUM('BLS LF projections 2019-2029'!G148,'BLS LF projections 2019-2029'!G164)/SUM('BLS LF projections 2019-2029'!G148,'BLS LF projections 2019-2029'!G164,'BLS LF projections 2019-2029'!G180,'BLS LF projections 2019-2029'!G196) -> 0.19380493 | H15: =SUM('BLS LF projections 2019-2029'!H148,'BLS LF projections 2019-2029'!H164)/SUM('BLS LF projections 2019-2029'!H148,'BLS LF projections 2019-2029'!H164,'BLS LF projections 2019-2029'!H180,'BLS LF projections 2019-2029'!H196) -> 0.19702463 | I15: =SUM('BLS LF projections 2019-2029'!I148,'BLS LF projections 2019-2029'!I164)/SUM('BLS LF projections 2019-2029'!I148,'BLS LF projections 2019-2029'!I164,'BLS LF projections 2019-2029'!I180,'BLS LF projections 2019-2029'!I196) -> 0.20024369 | ... AG15: =SUM('BLS LF projections 2019-2029'!AG148,'BLS LF projections 2019-2029'!AG164)/SUM('BLS LF projections 2019-2029'!AG148,'BLS LF projections 2019-2029'!AG164,'BLS LF projections 2019-2029'!AG180,'BLS LF projections 2019-2029'!AG196) -> 0.26822829
A16: Non-Hispanic | B16: =SUM('BLS LF projections 2019-2029'!B180,'BLS LF projections 2019-2029'!B196)/SUM('BLS LF projections 2019-2029'!B148,'BLS LF projections 2019-2029'!B164,'BLS LF projections 2019-2029'!B180,'BLS LF projections 2019-2029'!B196) -> 0.8223399 | C16: =SUM('BLS LF projections 2019-2029'!C180,'BLS LF projections 2019-2029'!C196)/SUM('BLS LF projections 2019-2029'!C148,'BLS LF projections 2019-2029'!C164,'BLS LF projections 2019-2029'!C180,'BLS LF projections 2019-2029'!C196) -> 0.81914712 | D16: =SUM('BLS LF projections 2019-2029'!D180,'BLS LF projections 2019-2029'!D196)/SUM('BLS LF projections 2019-2029'!D148,'BLS LF projections 2019-2029'!D164,'BLS LF projections 2019-2029'!D180,'BLS LF projections 2019-2029'!D196) -> 0.81595534 | E16: =SUM('BLS LF projections 2019-2029'!E180,'BLS LF projections 2019-2029'!E196)/SUM('BLS LF projections 2019-2029'!E148,'BLS LF projections 2019-2029'!E164,'BLS LF projections 2019-2029'!E180,'BLS LF projections 2019-2029'!E196) -> 0.81267782 | F16: =SUM('BLS LF projections 2019-2029'!F180,'BLS LF projections 2019-2029'!F196)/SUM('BLS LF projections 2019-2029'!F148,'BLS LF projections 2019-2029'!F164,'BLS LF projections 2019-2029'!F180,'BLS LF projections 2019-2029'!F196) -> 0.80942039 | G16: =SUM('BLS LF projections 2019-2029'!G180,'BLS LF projections 2019-2029'!G196)/SUM('BLS LF projections 2019-2029'!G148,'BLS LF projections 2019-2029'!G164,'BLS LF projections 2019-2029'!G180,'BLS LF projections 2019-2029'!G196) -> 0.80619507 | H16: =SUM('BLS LF projections 2019-2029'!H180,'BLS LF projections 2019-2029'!H196)/SUM('BLS LF projections 2019-2029'!H148,'BLS LF projections 2019-2029'!H164,'BLS LF projections 2019-2029'!H180,'BLS LF projections 2019-2029'!H196) -> 0.80297537 | I16: =SUM('BLS LF projections 2019-2029'!I180,'BLS LF projections 2019-2029'!I196)/SUM('BLS LF projections 2019-2029'!I148,'BLS LF projections 2019-2029'!I164,'BLS LF projections 2019-2029'!I180,'BLS LF projections 2019-2029'!I196) -> 0.79975631 | ... AG16: =SUM('BLS LF projections 2019-2029'!AG180,'BLS LF projections 2019-2029'!AG196)/SUM('BLS LF projections 2019-2029'!AG148,'BLS LF projections 2019-2029'!AG164,'BLS LF projections 2019-2029'!AG180,'BLS LF projections 2019-2029'!AG196) -> 0.73177171
A18: Age Bracket
B19: 2019 | C19: 2020 | D19: 2021 | E19: 2022 | F19: 2023 | G19: 2024 | H19: 2025 | I19: 2026 | J19: 2027 | K19: 2028 | L19: 2029 | M19: 2030 | N19: 2031 | O19: 2032 | P19: 2033 | Q19: 2034 | R19: 2035 | S19: 2036 | T19: 2037 | U19: 2038 | V19: 2039 | W19: 2040 | X19: 2041 | Y19: 2042 | Z19: 2043 | AA19: 2044 | AB19: 2045 | AC19: 2046 | AD19: 2047 | AE19: 2048 | AF19: 2049 | AG19: 2050
A20: 16 to 19 years | B20: =SUM('BLS LF projections 2019-2029'!B5:B6)/SUM('BLS LF projections 2019-2029'!B5:B18) -> 0.036053003 | C20: =SUM('BLS LF projections 2019-2029'!C5:C6)/SUM('BLS LF projections 2019-2029'!C5:C18) -> 0.034891504 | D20: =SUM('BLS LF projections 2019-2029'!D5:D6)/SUM('BLS LF projections 2019-2029'!D5:D18) -> 0.033912159 | E20: =SUM('BLS LF projections 2019-2029'!E5:E6)/SUM('BLS LF projections 2019-2029'!E5:E18) -> 0.033279886 | F20: =SUM('BLS LF projections 2019-2029'!F5:F6)/SUM('BLS LF projections 2019-2029'!F5:F18) -> 0.032637585 | G20: =SUM('BLS LF projections 2019-2029'!G5:G6)/SUM('BLS LF projections 2019-2029'!G5:G18) -> 0.031906763 | H20: =SUM('BLS LF projections 2019-2029'!H5:H6)/SUM('BLS LF projections 2019-2029'!H5:H18) -> 0.03110345 | I20: =SUM('BLS LF projections 2019-2029'!I5:I6)/SUM('BLS LF projections 2019-2029'!I5:I18) -> 0.030271664 | ... AG20: =SUM('BLS LF projections 2019-2029'!AG5:AG6)/SUM('BLS LF projections 2019-2029'!AG5:AG18) -> 0.012516333
A21: 20 to 24 years | B21: ='BLS LF projections 2019-2029'!B7/SUM('BLS LF projections 2019-2029'!B5:B18) -> 0.092914753 | C21: ='BLS LF projections 2019-2029'!C7/SUM('BLS LF projections 2019-2029'!C5:C18) -> 0.092242817 | D21: ='BLS LF projections 2019-2029'!D7/SUM('BLS LF projections 2019-2029'!D5:D18) -> 0.091631247 | E21: ='BLS LF projections 2019-2029'!E7/SUM('BLS LF projections 2019-2029'!E5:E18) -> 0.090743598 | F21: ='BLS LF projections 2019-2029'!F7/SUM('BLS LF projections 2019-2029'!F5:F18) -> 0.089927345 | G21: ='BLS LF projections 2019-2029'!G7/SUM('BLS LF projections 2019-2029'!G5:G18) -> 0.089218332 | H21: ='BLS LF projections 2019-2029'!H7/SUM('BLS LF projections 2019-2029'!H5:H18) -> 0.088222533 | I21: ='BLS LF projections 2019-2029'!I7/SUM('BLS LF projections 2019-2029'!I5:I18) -> 0.087502736 | ... AG21: ='BLS LF projections 2019-2029'!AG7/SUM('BLS LF projections 2019-2029'!AG5:AG18) -> 0.073195256
A22: 25 to 34 years | B22: =SUM('BLS LF projections 2019-2029'!B8:B9)/SUM('BLS LF projections 2019-2029'!B5:B18) -> 0.22741643 | C22: =SUM('BLS LF projections 2019-2029'!C8:C9)/SUM('BLS LF projections 2019-2029'!C5:C18) -> 0.22747021 | D22: =SUM('BLS LF projections 2019-2029'!D8:D9)/SUM('BLS LF projections 2019-2029'!D5:D18) -> 0.22721328 | E22: =SUM('BLS LF projections 2019-2029'!E8:E9)/SUM('BLS LF projections 2019-2029'!E5:E18) -> 0.22702175 | F22: =SUM('BLS LF projections 2019-2029'!F8:F9)/SUM('BLS LF projections 2019-2029'!F5:F18) -> 0.22633325 | G22: =SUM('BLS LF projections 2019-2029'!G8:G9)/SUM('BLS LF projections 2019-2029'!G5:G18) -> 0.22505493 | H22: =SUM('BLS LF projections 2019-2029'!H8:H9)/SUM('BLS LF projections 2019-2029'!H5:H18) -> 0.22319831 | I22: =SUM('BLS LF projections 2019-2029'!I8:I9)/SUM('BLS LF projections 2019-2029'!I5:I18) -> 0.22080926 | ... AG22: =SUM('BLS LF projections 2019-2029'!AG8:AG9)/SUM('BLS LF projections 2019-2029'!AG5:AG18) -> 0.19134548
A23: 35 to 44 years | B23: =SUM('BLS LF projections 2019-2029'!B10:B11)/SUM('BLS LF projections 2019-2029'!B5:B18) -> 0.20825257 | C23: =SUM('BLS LF projections 2019-2029'!C10:C11)/SUM('BLS LF projections 2019-2029'!C5:C18) -> 0.20976889 | D23: =SUM('BLS LF projections 2019-2029'!D10:D11)/SUM('BLS LF projections 2019-2029'!D5:D18) -> 0.21176179 | E23: =SUM('BLS LF projections 2019-2029'!E10:E11)/SUM('BLS LF projections 2019-2029'!E5:E18) -> 0.2132782 | F23: =SUM('BLS LF projections 2019-2029'!F10:F11)/SUM('BLS LF projections 2019-2029'!F5:F18) -> 0.21500609 | G23: =SUM('BLS LF projections 2019-2029'!G10:G11)/SUM('BLS LF projections 2019-2029'!G5:G18) -> 0.21693494 | H23: =SUM('BLS LF projections 2019-2029'!H10:H11)/SUM('BLS LF projections 2019-2029'!H5:H18) -> 0.21862165 | I23: =SUM('BLS LF projections 2019-2029'!I10:I11)/SUM('BLS LF projections 2019-2029'!I5:I18) -> 0.22076785 | ... AG23: =SUM('BLS LF projections 2019-2029'!AG10:AG11)/SUM('BLS LF projections 2019-2029'!AG5:AG18) -> 0.25608762
A24: 45 to 54 years | B24: =SUM('BLS LF projections 2019-2029'!B12:B13)/SUM('BLS LF projections 2019-2029'!B5:B18) -> 0.20136727 | C24: =SUM('BLS LF projections 2019-2029'!C12:C13)/SUM('BLS LF projections 2019-2029'!C5:C18) -> 0.19817693 | D24: =SUM('BLS LF projections 2019-2029'!D12:D13)/SUM('BLS LF projections 2019-2029'!D5:D18) -> 0.19567455 | E24: =SUM('BLS LF projections 2019-2029'!E12:E13)/SUM('BLS LF projections 2019-2029'!E5:E18) -> 0.19435068 | F24: =SUM('BLS LF projections 2019-2029'!F12:F13)/SUM('BLS LF projections 2019-2029'!F5:F18) -> 0.19331769 | G24: =SUM('BLS LF projections 2019-2029'!G12:G13)/SUM('BLS LF projections 2019-2029'!G5:G18) -> 0.19236005 | H24: =SUM('BLS LF projections 2019-2029'!H12:H13)/SUM('BLS LF projections 2019-2029'!H5:H18) -> 0.1917739 | I24: =SUM('BLS LF projections 2019-2029'!I12:I13)/SUM('BLS LF projections 2019-2029'!I5:I18) -> 0.19106992 | ... AG24: =SUM('BLS LF projections 2019-2029'!AG12:AG13)/SUM('BLS LF projections 2019-2029'!AG5:AG18) -> 0.17916097
A25: 55 to 64 years | B25: =SUM('BLS LF projections 2019-2029'!B14:B15)/SUM('BLS LF projections 2019-2029'!B5:B18) -> 0.16878749 | C25: =SUM('BLS LF projections 2019-2029'!C14:C15)/SUM('BLS LF projections 2019-2029'!C5:C18) -> 0.16893232 | D25: =SUM('BLS LF projections 2019-2029'!D14:D15)/SUM('BLS LF projections 2019-2029'!D5:D18) -> 0.16797447 | E25: =SUM('BLS LF projections 2019-2029'!E14:E15)/SUM('BLS LF projections 2019-2029'!E5:E18) -> 0.16640546 | F25: =SUM('BLS LF projections 2019-2029'!F14:F15)/SUM('BLS LF projections 2019-2029'!F5:F18) -> 0.16467581 | G25: =SUM('BLS LF projections 2019-2029'!G14:G15)/SUM('BLS LF projections 2019-2029'!G5:G18) -> 0.16330125 | H25: =SUM('BLS LF projections 2019-2029'!H14:H15)/SUM('BLS LF projections 2019-2029'!H5:H18) -> 0.16254272 | I25: =SUM('BLS LF projections 2019-2029'!I14:I15)/SUM('BLS LF projections 2019-2029'!I5:I18) -> 0.16186291 | ... AG25: =SUM('BLS LF projections 2019-2029'!AG14:AG15)/SUM('BLS LF projections 2019-2029'!AG5:AG18) -> 0.13430898
A26: 65 years and over | B26: =SUM('BLS LF projections 2019-2029'!B16:B18)/SUM('BLS LF projections 2019-2029'!B5:B18) -> 0.065208485 | C26: =SUM('BLS LF projections 2019-2029'!C16:C18)/SUM('BLS LF projections 2019-2029'!C5:C18) -> 0.068517324 | D26: =SUM('BLS LF projections 2019-2029'!D16:D18)/SUM('BLS LF projections 2019-2029'!D5:D18) -> 0.071832504 | E26: =SUM('BLS LF projections 2019-2029'!E16:E18)/SUM('BLS LF projections 2019-2029'!E5:E18) -> 0.074920432 | F26: =SUM('BLS LF projections 2019-2029'!F16:F18)/SUM('BLS LF projections 2019-2029'!F5:F18) -> 0.07810222 | G26: =SUM('BLS LF projections 2019-2029'!G16:G18)/SUM('BLS LF projections 2019-2029'!G5:G18) -> 0.081223729 | H26: =SUM('BLS LF projections 2019-2029'!H16:H18)/SUM('BLS LF projections 2019-2029'!H5:H18) -> 0.084537431 | I26: =SUM('BLS LF projections 2019-2029'!I16:I18)/SUM('BLS LF projections 2019-2029'!I5:I18) -> 0.087715666 | ... AG26: =SUM('BLS LF projections 2019-2029'!AG16:AG18)/SUM('BLS LF projections 2019-2029'!AG5:AG18) -> 0.15338535
A29: If Positive: Fraction of Jobs Not Held by People with This Trait in 2020 Held by People with This Trait in Each Year
A30: If Negative: Fraction of Jobs Held by People with This Trait in 2020 No Longer Held by People with This Trait in Each Year
A31: Sex
C32: 2020 | D32: 2021 | E32: 2022 | F32: 2023 | G32: 2024 | H32: 2025 | I32: 2026 | J32: 2027 | K32: 2028 | L32: 2029 | M32: 2030 | N32: 2031 | O32: 2032 | P32: 2033 | Q32: 2034 | R32: 2035 | S32: 2036 | T32: 2037 | U32: 2038 | V32: 2039 | W32: 2040 | X32: 2041 | Y32: 2042 | Z32: 2043 | AA32: 2044 | AB32: 2045 | AC32: 2046 | AD32: 2047 | AE32: 2048 | AF32: 2049 | AG32: 2050
A33: Men | C33: =IF(C4>=$C4,(C4-$C4)/(1-$C4),(C4-$C4)/$C4) -> 0 | D33: =IF(D4>=$C4,(D4-$C4)/(1-$C4),(D4-$C4)/$C4) -> -0.0011240186 | E33: =IF(E4>=$C4,(E4-$C4)/(1-$C4),(E4-$C4)/$C4) -> -0.0022995996 | F33: =IF(F4>=$C4,(F4-$C4)/(1-$C4),(F4-$C4)/$C4) -> -0.003445842 | G33: =IF(G4>=$C4,(G4-$C4)/(1-$C4),(G4-$C4)/$C4) -> -0.0045714556 | H33: =IF(H4>=$C4,(H4-$C4)/(1-$C4),(H4-$C4)/$C4) -> -0.0057340456 | I33: =IF(I4>=$C4,(I4-$C4)/(1-$C4),(I4-$C4)/$C4) -> -0.0069428843 | J33: =IF(J4>=$C4,(J4-$C4)/(1-$C4),(J4-$C4)/$C4) -> -0.0082189745 | ... AG33: =IF(AG4>=$C4,(AG4-$C4)/(1-$C4),(AG4-$C4)/$C4) -> -0.032264089
A34: Women | C34: =IF(C5>=$C5,(C5-$C5)/(1-$C5),(C5-$C5)/$C5) -> 0 | D34: =IF(D5>=$C5,(D5-$C5)/(1-$C5),(D5-$C5)/$C5) -> 0.0011240186 | E34: =IF(E5>=$C5,(E5-$C5)/(1-$C5),(E5-$C5)/$C5) -> 0.0022995996 | F34: =IF(F5>=$C5,(F5-$C5)/(1-$C5),(F5-$C5)/$C5) -> 0.003445842 | G34: =IF(G5>=$C5,(G5-$C5)/(1-$C5),(G5-$C5)/$C5) -> 0.0045714556 | H34: =IF(H5>=$C5,(H5-$C5)/(1-$C5),(H5-$C5)/$C5) -> 0.0057340456 | I34: =IF(I5>=$C5,(I5-$C5)/(1-$C5),(I5-$C5)/$C5) -> 0.0069428843 | J34: =IF(J5>=$C5,(J5-$C5)/(1-$C5),(J5-$C5)/$C5) -> 0.0082189745 | ... AG34: =IF(AG5>=$C5,(AG5-$C5)/(1-$C5),(AG5-$C5)/$C5) -> 0.032264089
A36: Race
C37: 2020 | D37: 2021 | E37: 2022 | F37: 2023 | G37: 2024 | H37: 2025 | I37: 2026 | J37: 2027 | K37: 2028 | L37: 2029 | M37: 2030 | N37: 2031 | O37: 2032 | P37: 2033 | Q37: 2034 | R37: 2035 | S37: 2036 | T37: 2037 | U37: 2038 | V37: 2039 | W37: 2040 | X37: 2041 | Y37: 2042 | Z37: 2043 | AA37: 2044 | AB37: 2045 | AC37: 2046 | AD37: 2047 | AE37: 2048 | AF37: 2049 | AG37: 2050
A38: White | C38: =IF(C9>=$C9,(C9-$C9)/(1-$C9),(C9-$C9)/$C9) -> 0 | D38: =IF(D9>=$C9,(D9-$C9)/(1-$C9),(D9-$C9)/$C9) -> -0.0029374961 | E38: =IF(E9>=$C9,(E9-$C9)/(1-$C9),(E9-$C9)/$C9) -> -0.0059865214 | F38: =IF(F9>=$C9,(F9-$C9)/(1-$C9),(F9-$C9)/$C9) -> -0.0090146419 | G38: =IF(G9>=$C9,(G9-$C9)/(1-$C9),(G9-$C9)/$C9) -> -0.012015826 | H38: =IF(H9>=$C9,(H9-$C9)/(1-$C9),(H9-$C9)/$C9) -> -0.015002089 | I38: =IF(I9>=$C9,(I9-$C9)/(1-$C9),(I9-$C9)/$C9) -> -0.018047893 | J38: =IF(J9>=$C9,(J9-$C9)/(1-$C9),(J9-$C9)/$C9) -> -0.02106788 | ... AG38: =IF(AG9>=$C9,(AG9-$C9)/(1-$C9),(AG9-$C9)/$C9) -> -0.081780746
A39: Black | C39: =IF(C10>=$C10,(C10-$C10)/(1-$C10),(C10-$C10)/$C10) -> 0 | D39: =IF(D10>=$C10,(D10-$C10)/(1-$C10),(D10-$C10)/$C10) -> 0.00045718512 | E39: =IF(E10>=$C10,(E10-$C10)/(1-$C10),(E10-$C10)/$C10) -> 0.00095783663 | F39: =IF(F10>=$C10,(F10-$C10)/(1-$C10),(F10-$C10)/$C10) -> 0.001442744 | G39: =IF(G10>=$C10,(G10-$C10)/(1-$C10),(G10-$C10)/$C10) -> 0.0019227316 | H39: =IF(H10>=$C10,(H10-$C10)/(1-$C10),(H10-$C10)/$C10) -> 0.0023830965 | I39: =IF(I10>=$C10,(I10-$C10)/(1-$C10),(I10-$C10)/$C10) -> 0.0028366926 | J39: =IF(J10>=$C10,(J10-$C10)/(1-$C10),(J10-$C10)/$C10) -> 0.0033011117 | ... AG39: =IF(AG10>=$C10,(AG10-$C10)/(1-$C10),(AG10-$C10)/$C10) -> 0.012808512
A40: Other (inc. Asian) | C40: =IF(C11>=$C11,(C11-$C11)/(1-$C11),(C11-$C11)/$C11) -> 0 | D40: =IF(D11>=$C11,(D11-$C11)/(1-$C11),(D11-$C11)/$C11) -> 0.0020791939 | E40: =IF(E11>=$C11,(E11-$C11)/(1-$C11),(E11-$C11)/$C11) -> 0.0042119487 | F40: =IF(F11>=$C11,(F11-$C11)/(1-$C11),(F11-$C11)/$C11) -> 0.0063420494 | G40: =IF(G11>=$C11,(G11-$C11)/(1-$C11),(G11-$C11)/$C11) -> 0.008453791 | H40: =IF(H11>=$C11,(H11-$C11)/(1-$C11),(H11-$C11)/$C11) -> 0.01057179 | I40: =IF(I11>=$C11,(I11-$C11)/(1-$C11),(I11-$C11)/$C11) -> 0.012747522 | J40: =IF(J11>=$C11,(J11-$C11)/(1-$C11),(J11-$C11)/$C11) -> 0.014890553 | ... AG40: =IF(AG11>=$C11,(AG11-$C11)/(1-$C11),(AG11-$C11)/$C11) -> 0.057807257
A42: Hispanic Status
C43: 2020 | D43: 2021 | E43: 2022 | F43: 2023 | G43: 2024 | H43: 2025 | I43: 2026 | J43: 2027 | K43: 2028 | L43: 2029 | M43: 2030 | N43: 2031 | O43: 2032 | P43: 2033 | Q43: 2034 | R43: 2035 | S43: 2036 | T43: 2037 | U43: 2038 | V43: 2039 | W43: 2040 | X43: 2041 | Y43: 2042 | Z43: 2043 | AA43: 2044 | AB43: 2045 | AC43: 2046 | AD43: 2047 | AE43: 2048 | AF43: 2049 | AG43: 2050
A44: Hispanic | C44: =IF(C15>=$C15,(C15-$C15)/(1-$C15),(C15-$C15)/$C15) -> 0 | D44: =IF(D15>=$C15,(D15-$C15)/(1-$C15),(D15-$C15)/$C15) -> 0.0038964711 | E44: =IF(E15>=$C15,(E15-$C15)/(1-$C15),(E15-$C15)/$C15) -> 0.0078976061 | F44: =IF(F15>=$C15,(F15-$C15)/(1-$C15),(F15-$C15)/$C15) -> 0.011874221 | G44: =IF(G15>=$C15,(G15-$C15)/(1-$C15),(G15-$C15)/$C15) -> 0.015811632 | H44: =IF(H15>=$C15,(H15-$C15)/(1-$C15),(H15-$C15)/$C15) -> 0.019742185 | I44: =IF(I15>=$C15,(I15-$C15)/(1-$C15),(I15-$C15)/$C15) -> 0.023671952 | J44: =IF(J15>=$C15,(J15-$C15)/(1-$C15),(J15-$C15)/$C15) -> 0.027565075 | ... AG44: =IF(AG15>=$C15,(AG15-$C15)/(1-$C15),(AG15-$C15)/$C15) -> 0.10666632
A45: Non-Hispanic | C45: =IF(C16>=$C16,(C16-$C16)/(1-$C16),(C16-$C16)/$C16) -> 0 | D45: =IF(D16>=$C16,(D16-$C16)/(1-$C16),(D16-$C16)/$C16) -> -0.0038964711 | E45: =IF(E16>=$C16,(E16-$C16)/(1-$C16),(E16-$C16)/$C16) -> -0.0078976061 | F45: =IF(F16>=$C16,(F16-$C16)/(1-$C16),(F16-$C16)/$C16) -> -0.011874221 | G45: =IF(G16>=$C16,(G16-$C16)/(1-$C16),(G16-$C16)/$C16) -> -0.015811632 | H45: =IF(H16>=$C16,(H16-$C16)/(1-$C16),(H16-$C16)/$C16) -> -0.019742185 | I45: =IF(I16>=$C16,(I16-$C16)/(1-$C16),(I16-$C16)/$C16) -> -0.023671952 | J45: =IF(J16>=$C16,(J16-$C16)/(1-$C16),(J16-$C16)/$C16) -> -0.027565075 | ... AG45: =IF(AG16>=$C16,(AG16-$C16)/(1-$C16),(AG16-$C16)/$C16) -> -0.10666632
A47: Age Bracket
C48: 2020 | D48: 2021 | E48: 2022 | F48: 2023 | G48: 2024 | H48: 2025 | I48: 2026 | J48: 2027 | K48: 2028 | L48: 2029 | M48: 2030 | N48: 2031 | O48: 2032 | P48: 2033 | Q48: 2034 | R48: 2035 | S48: 2036 | T48: 2037 | U48: 2038 | V48: 2039 | W48: 2040 | X48: 2041 | Y48: 2042 | Z48: 2043 | AA48: 2044 | AB48: 2045 | AC48: 2046 | AD48: 2047 | AE48: 2048 | AF48: 2049 | AG48: 2050
A49: 16 to 19 years | C49: =IF(C20>=$C20,(C20-$C20)/(1-$C20),(C20-$C20)/$C20) -> 0 | D49: =IF(D20>=$C20,(D20-$C20)/(1-$C20),(D20-$C20)/$C20) -> -0.028068298 | E49: =IF(E20>=$C20,(E20-$C20)/(1-$C20),(E20-$C20)/$C20) -> -0.046189408 | F49: =IF(F20>=$C20,(F20-$C20)/(1-$C20),(F20-$C20)/$C20) -> -0.06459794 | G49: =IF(G20>=$C20,(G20-$C20)/(1-$C20),(G20-$C20)/$C20) -> -0.085543478 | H49: =IF(H20>=$C20,(H20-$C20)/(1-$C20),(H20-$C20)/$C20) -> -0.10856665 | I49: =IF(I20>=$C20,(I20-$C20)/(1-$C20),(I20-$C20)/$C20) -> -0.13240587 | J49: =IF(J20>=$C20,(J20-$C20)/(1-$C20),(J20-$C20)/$C20) -> -0.16226052 | ... AG49: =IF(AG20>=$C20,(AG20-$C20)/(1-$C20),(AG20-$C20)/$C20) -> -0.6412785
A50: 20 to 24 years | C50: =IF(C21>=$C21,(C21-$C21)/(1-$C21),(C21-$C21)/$C21) -> 0 | D50: =IF(D21>=$C21,(D21-$C21)/(1-$C21),(D21-$C21)/$C21) -> -0.0066299985 | E50: =IF(E21>=$C21,(E21-$C21)/(1-$C21),(E21-$C21)/$C21) -> -0.016252954 | F50: =IF(F21>=$C21,(F21-$C21)/(1-$C21),(F21-$C21)/$C21) -> -0.025101914 | G50: =IF(G21>=$C21,(G21-$C21)/(1-$C21),(G21-$C21)/$C21) -> -0.032788294 | H50: =IF(H21>=$C21,(H21-$C21)/(1-$C21),(H21-$C21)/$C21) -> -0.043583708 | I50: =IF(I21>=$C21,(I21-$C21)/(1-$C21),(I21-$C21)/$C21) -> -0.051386994 | J50: =IF(J21>=$C21,(J21-$C21)/(1-$C21),(J21-$C21)/$C21) -> -0.053377215 | ... AG50: =IF(AG21>=$C21,(AG21-$C21)/(1-$C21),(AG21-$C21)/$C21) -> -0.2064937
A51: 25 to 34 years | C51: =IF(C22>=$C22,(C22-$C22)/(1-$C22),(C22-$C22)/$C22) -> 0 | D51: =IF(D22>=$C22,(D22-$C22)/(1-$C22),(D22-$C22)/$C22) -> -0.0011295207 | E51: =IF(E22>=$C22,(E22-$C22)/(1-$C22),(E22-$C22)/$C22) -> -0.001971534 | F51: =IF(F22>=$C22,(F22-$C22)/(1-$C22),(F22-$C22)/$C22) -> -0.0049982917 | G51: =IF(G22>=$C22,(G22-$C22)/(1-$C22),(G22-$C22)/$C22) -> -0.010618025 | H51: =IF(H22>=$C22,(H22-$C22)/(1-$C22),(H22-$C22)/$C22) -> -0.018780049 | I51: =IF(I22>=$C22,(I22-$C22)/(1-$C22),(I22-$C22)/$C22) -> -0.029282772 | J51: =IF(J22>=$C22,(J22-$C22)/(1-$C22),(J22-$C22)/$C22) -> -0.040362045 | ... AG51: =IF(AG22>=$C22,(AG22-$C22)/(1-$C22),(AG22-$C22)/$C22) -> -0.15881081
A52: 35 to 44 years | C52: =IF(C23>=$C23,(C23-$C23)/(1-$C23),(C23-$C23)/$C23) -> 0 | D52: =IF(D23>=$C23,(D23-$C23)/(1-$C23),(D23-$C23)/$C23) -> 0.0025219134 | E52: =IF(E23>=$C23,(E23-$C23)/(1-$C23),(E23-$C23)/$C23) -> 0.0044408622 | F52: =IF(F23>=$C23,(F23-$C23)/(1-$C23),(F23-$C23)/$C23) -> 0.0066274265 | G52: =IF(G23>=$C23,(G23-$C23)/(1-$C23),(G23-$C23)/$C23) -> 0.0090683011 | H52: =IF(H23>=$C23,(H23-$C23)/(1-$C23),(H23-$C23)/$C23) -> 0.011202751 | I52: =IF(I23>=$C23,(I23-$C23)/(1-$C23),(I23-$C23)/$C23) -> 0.013918664 | J52: =IF(J23>=$C23,(J23-$C23)/(1-$C23),(J23-$C23)/$C23) -> 0.015921312 | ... AG52: =IF(AG23>=$C23,(AG23-$C23)/(1-$C23),(AG23-$C23)/$C23) -> 0.058614153
A53: 45 to 54 years | C53: =IF(C24>=$C24,(C24-$C24)/(1-$C24),(C24-$C24)/$C24) -> 0 | D53: =IF(D24>=$C24,(D24-$C24)/(1-$C24),(D24-$C24)/$C24) -> -0.012626991 | E53: =IF(E24>=$C24,(E24-$C24)/(1-$C24),(E24-$C24)/$C24) -> -0.019307245 | F53: =IF(F24>=$C24,(F24-$C24)/(1-$C24),(F24-$C24)/$C24) -> -0.024519673 | G53: =IF(G24>=$C24,(G24-$C24)/(1-$C24),(G24-$C24)/$C24) -> -0.029351945 | H53: =IF(H24>=$C24,(H24-$C24)/(1-$C24),(H24-$C24)/$C24) -> -0.032309648 | I53: =IF(I24>=$C24,(I24-$C24)/(1-$C24),(I24-$C24)/$C24) -> -0.035861944 | J53: =IF(J24>=$C24,(J24-$C24)/(1-$C24),(J24-$C24)/$C24) -> -0.032673043 | ... AG53: =IF(AG24>=$C24,(AG24-$C24)/(1-$C24),(AG24-$C24)/$C24) -> -0.095954427
A54: 55 to 64 years | C54: =IF(C25>=$C25,(C25-$C25)/(1-$C25),(C25-$C25)/$C25) -> 0 | D54: =IF(D25>=$C25,(D25-$C25)/(1-$C25),(D25-$C25)/$C25) -> -0.0056700154 | E54: =IF(E25>=$C25,(E25-$C25)/(1-$C25),(E25-$C25)/$C25) -> -0.014957845 | F54: =IF(F25>=$C25,(F25-$C25)/(1-$C25),(F25-$C25)/$C25) -> -0.025196531 | G54: =IF(G25>=$C25,(G25-$C25)/(1-$C25),(G25-$C25)/$C25) -> -0.033333295 | H54: =IF(H25>=$C25,(H25-$C25)/(1-$C25),(H25-$C25)/$C25) -> -0.037823442 | I54: =IF(I25>=$C25,(I25-$C25)/(1-$C25),(I25-$C25)/$C25) -> -0.041847612 | J54: =IF(J25>=$C25,(J25-$C25)/(1-$C25),(J25-$C25)/$C25) -> -0.049949777 | ... AG54: =IF(AG25>=$C25,(AG25-$C25)/(1-$C25),(AG25-$C25)/$C25) -> -0.20495393
A55: 65 years and over | C55: =IF(C26>=$C26,(C26-$C26)/(1-$C26),(C26-$C26)/$C26) -> 0 | D55: =IF(D26>=$C26,(D26-$C26)/(1-$C26),(D26-$C26)/$C26) -> 0.0035590354 | E55: =IF(E26>=$C26,(E26-$C26)/(1-$C26),(E26-$C26)/$C26) -> 0.0068741032 | F55: =IF(F26>=$C26,(F26-$C26)/(1-$C26),(F26-$C26)/$C26) -> 0.010289935 | G55: =IF(G26>=$C26,(G26-$C26)/(1-$C26),(G26-$C26)/$C26) -> 0.013641054 | H55: =IF(H26>=$C26,(H26-$C26)/(1-$C26),(H26-$C26)/$C26) -> 0.017198502 | I55: =IF(I26>=$C26,(I26-$C26)/(1-$C26),(I26-$C26)/$C26) -> 0.02061052 | J55: =IF(J26>=$C26,(J26-$C26)/(1-$C26),(J26-$C26)/$C26) -> 0.023723469 | ... AG55: =IF(AG26>=$C26,(AG26-$C26)/(1-$C26),(AG26-$C26)/$C26) -> 0.091110691

Sheet S Curve Equation
A1: We model growth or shrinkage in the percentage of jobs held by people with a given demographic
A2: characteristic along an S-curve, which more realistically represents the change near the extremes.
A3: For example, suppose people with a certain characteristic are 10% of the labor force but only hold
A4: 0.1% of the jobs in a given industry. If they increase to be 15% of the labor force, a linear estimate
A5: would suggest they become around 5% of the jobs in that industry, but this growth is too rapid for
A6: starting from such a small base. An S-curve slows down the changes as they approach 0% or 100%,
A7: making for more realistic behavior that approaches asymptotes.
A9: Sigmoid Property | B9: Value | C9: Note
A10: Steepness | B10: 4.5 | C10: Only this value may be edited
A11: Horizontal Shift | B11: 1 | C11: positive is rightward
A12: Horizontal Compression | B12: 2 | C12: positive is more compressed
A13: Y-shift | B13: =-1/(1+EXP(($B$11-A17*$B$12)*$B$10)) -> -0.010986943 | C13: Calculated to align 0% X and 0% Y
A14: Y-stretch | B14: =1/(1/(1+EXP(($B$11-A67*$B$12)*$B$10))+$B$13) -> 1.0224676 | C14: Calculated to align 100% X and 100% Y
A16: % w Factor (Avg) | C16: % w Factor (This Industry)
A17: 0 | C17: =(1/(1+EXP(($B$11-A17*$B$12)*$B$10))+$B$13)*$B$14 -> 0
A18: 0.02 | C18: =(1/(1+EXP(($B$11-A18*$B$12)*$B$10))+$B$13)*$B$14 -> 0.0021864198
A19: 0.04 | C19: =(1/(1+EXP(($B$11-A19*$B$12)*$B$10))+$B$13)*$B$14 -> 0.0047916363
A20: 0.06 | C20: =(1/(1+EXP(($B$11-A20*$B$12)*$B$10))+$B$13)*$B$14 -> 0.0078930074
A21: 0.08 | C21: =(1/(1+EXP(($B$11-A21*$B$12)*$B$10))+$B$13)*$B$14 -> 0.011580975
A22: 0.1 | C22: =(1/(1+EXP(($B$11-A22*$B$12)*$B$10))+$B$13)*$B$14 -> 0.015960771
A23: 0.12 | C23: =(1/(1+EXP(($B$11-A23*$B$12)*$B$10))+$B$13)*$B$14 -> 0.021154124
A24: 0.14 | C24: =(1/(1+EXP(($B$11-A24*$B$12)*$B$10))+$B$13)*$B$14 -> 0.027300854
A25: 0.16 | C25: =(1/(1+EXP(($B$11-A25*$B$12)*$B$10))+$B$13)*$B$14 -> 0.034560182
A26: 0.18 | C26: =(1/(1+EXP(($B$11-A26*$B$12)*$B$10))+$B$13)*$B$14 -> 0.043111521
A27: 0.2 | C27: =(1/(1+EXP(($B$11-A27*$B$12)*$B$10))+$B$13)*$B$14 -> 0.053154423
A28: 0.22 | C28: =(1/(1+EXP(($B$11-A28*$B$12)*$B$10))+$B$13)*$B$14 -> 0.064907267
... A67: 1 | C67: =(1/(1+EXP(($B$11-A67*$B$12)*$B$10))+$B$13)*$B$14 -> 1

Sheet S

Sheet Calculations male
A1: Fraction of Workers with This Demographic Trait in the Year for Which We Have Present-Day Data Disaggregated by ISIC Code
B2: 2020
A3: ISIC 01T03 | B3: =1-'Calculations female'!B3 -> 0.723
A4: ISIC 05 | B4: =1-'Calculations female'!B4 -> 0.899
A5: ISIC 06 | B5: =1-'Calculations female'!B5 -> 0.851
A6: ISIC 07T08 | B6: =1-'Calculations female'!B6 -> 0.893
A7: ISIC 09 | B7: =1-'Calculations female'!B7 -> 0.848
A8: ISIC 10T12 | B8: =1-'Calculations female'!B8 -> 0.60319417
A9: ISIC 13T15 | B9: =1-'Calculations female'!B9 -> 0.478
A10: ISIC 16 | B10: =1-'Calculations female'!B10 -> 0.834
A11: ISIC 17T18 | B11: =1-'Calculations female'!B11 -> 0.719
A12: ISIC 19 | B12: =1-'Calculations female'!B12 -> 0.822
A13: ISIC 20 | B13: =1-'Calculations female'!B13 -> 0.69398889
A14: ISIC 21 | B14: =1-'Calculations female'!B14 -> 0.568
... A44: ISIC 97T98 | B44: =1-'Calculations female'!B44 -> 0.111
A46: Reverse sigmoid (i.e. convert from Y value to X value)
B47: 2020
A48: ISIC 01T03 | B48: =('S Curve Equation'!$B$11-(LN(1/((B3/'S Curve Equation'!$B$14)-'S Curve Equation'!$B$13)-1)/'S Curve Equation'!$B$10))/'S Curve Equation'!$B$12 -> 0.60389506
A49: ISIC 05 | B49: =('S Curve Equation'!$B$11-(LN(1/((B4/'S Curve Equation'!$B$14)-'S Curve Equation'!$B$13)-1)/'S Curve Equation'!$B$10))/'S Curve Equation'!$B$12 -> 0.73256859
A50: ISIC 06 | B50: =('S Curve Equation'!$B$11-(LN(1/((B5/'S Curve Equation'!$B$14)-'S Curve Equation'!$B$13)-1)/'S Curve Equation'!$B$10))/'S Curve Equation'!$B$12 -> 0.68698806
A51: ISIC 07T08 | B51: =('S Curve Equation'!$B$11-(LN(1/((B6/'S Curve Equation'!$B$14)-'S Curve Equation'!$B$13)-1)/'S Curve Equation'!$B$10))/'S Curve Equation'!$B$12 -> 0.72604711
A52: ISIC 09 | B52: =('S Curve Equation'!$B$11-(LN(1/((B7/'S Curve Equation'!$B$14)-'S Curve Equation'!$B$13)-1)/'S Curve Equation'!$B$10))/'S Curve Equation'!$B$12 -> 0.68453973
A53: ISIC 10T12 | B53: =('S Curve Equation'!$B$11-(LN(1/((B8/'S Curve Equation'!$B$14)-'S Curve Equation'!$B$13)-1)/'S Curve Equation'!$B$10))/'S Curve Equation'!$B$12 -> 0.54548083
A54: ISIC 13T15 | B54: =('S Curve Equation'!$B$11-(LN(1/((B9/'S Curve Equation'!$B$14)-'S Curve Equation'!$B$13)-1)/'S Curve Equation'!$B$10))/'S Curve Equation'!$B$12 -> 0.49043117
A55: ISIC 16 | B55: =('S Curve Equation'!$B$11-(LN(1/((B10/'S Curve Equation'!$B$14)-'S Curve Equation'!$B$13)-1)/'S Curve Equation'!$B$10))/'S Curve Equation'!$B$12 -> 0.6735715
A56: ISIC 17T18 | B56: =('S Curve Equation'!$B$11-(LN(1/((B11/'S Curve Equation'!$B$14)-'S Curve Equation'!$B$13)-1)/'S Curve Equation'!$B$10))/'S Curve Equation'!$B$12 -> 0.60175673
A57: ISIC 19 | B57: =('S Curve Equation'!$B$11-(LN(1/((B12/'S Curve Equation'!$B$14)-'S Curve Equation'!$B$13)-1)/'S Curve Equation'!$B$10))/'S Curve Equation'!$B$12 -> 0.66470345
A58: ISIC 20 | B58: =('S Curve Equation'!$B$11-(LN(1/((B13/'S Curve Equation'!$B$14)-'S Curve Equation'!$B$13)-1)/'S Curve Equation'!$B$10))/'S Curve Equation'!$B$12 -> 0.58875995
A59: ISIC 21 | B59: =('S Curve Equation'!$B$11-(LN(1/((B14/'S Curve Equation'!$B$14)-'S Curve Equation'!$B$13)-1)/'S Curve Equation'!$B$10))/'S Curve Equation'!$B$12 -> 0.52973431
... A89: ISIC 97T98 | B89: =('S Curve Equation'!$B$11-(LN(1/((B44/'S Curve Equation'!$B$14)-'S Curve Equation'!$B$13)-1)/'S Curve Equation'!$B$10))/'S Curve Equation'!$B$12 -> 0.27814234
A91: Add or subtract linear segment (along X axis) - i.e. moving a percentage of the distance from 2020 value to 100% or to 0%
B92: 2020 | C92: 2021 | D92: 2022 | E92: 2023 | F92: 2024 | G92: 2025 | H92: 2026 | I92: 2027 | J92: 2028 | K92: 2029 | L92: 2030 | M92: 2031 | N92: 2032 | O92: 2033 | P92: 2034 | Q92: 2035 | R92: 2036 | S92: 2037 | T92: 2038 | U92: 2039 | V92: 2040 | W92: 2041 | X92: 2042 | Y92: 2043 | Z92: 2044 | AA92: 2045 | AB92: 2046 | AC92: 2047 | AD92: 2048 | AE92: 2049 | AF92: 2050
A93: ISIC 01T03 | B93: =B48 -> 0.60389506 | C93: =IF('LF Projected Ratios'!D$33>=0,$B93+(1-$B93)*'LF Projected Ratios'!D$33,$B93*(1+'LF Projected Ratios'!D$33)) -> 0.60321627 | D93: =IF('LF Projected Ratios'!E$33>=0,$B93+(1-$B93)*'LF Projected Ratios'!E$33,$B93*(1+'LF Projected Ratios'!E$33)) -> 0.60250635 | E93: =IF('LF Projected Ratios'!F$33>=0,$B93+(1-$B93)*'LF Projected Ratios'!F$33,$B93*(1+'LF Projected Ratios'!F$33)) -> 0.60181414 | F93: =IF('LF Projected Ratios'!G$33>=0,$B93+(1-$B93)*'LF Projected Ratios'!G$33,$B93*(1+'LF Projected Ratios'!G$33)) -> 0.60113438 | G93: =IF('LF Projected Ratios'!H$33>=0,$B93+(1-$B93)*'LF Projected Ratios'!H$33,$B93*(1+'LF Projected Ratios'!H$33)) -> 0.6004323 | H93: =IF('LF Projected Ratios'!I$33>=0,$B93+(1-$B93)*'LF Projected Ratios'!I$33,$B93*(1+'LF Projected Ratios'!I$33)) -> 0.59970229 | I93: =IF('LF Projected Ratios'!J$33>=0,$B93+(1-$B93)*'LF Projected Ratios'!J$33,$B93*(1+'LF Projected Ratios'!J$33)) -> 0.59893166 | J93: =IF('LF Projected Ratios'!K$33>=0,$B93+(1-$B93)*'LF Projected Ratios'!K$33,$B93*(1+'LF Projected Ratios'!K$33)) -> 0.59812742 | ... AF93: =IF('LF Projected Ratios'!AG$33>=0,$B93+(1-$B93)*'LF Projected Ratios'!AG$33,$B93*(1+'LF Projected Ratios'!AG$33)) -> 0.58441094
A94: ISIC 05 | B94: =B49 -> 0.73256859 | C94: =IF('LF Projected Ratios'!D$33>=0,$B94+(1-$B94)*'LF Projected Ratios'!D$33,$B94*(1+'LF Projected Ratios'!D$33)) -> 0.73174517 | D94: =IF('LF Projected Ratios'!E$33>=0,$B94+(1-$B94)*'LF Projected Ratios'!E$33,$B94*(1+'LF Projected Ratios'!E$33)) -> 0.73088398 | E94: =IF('LF Projected Ratios'!F$33>=0,$B94+(1-$B94)*'LF Projected Ratios'!F$33,$B94*(1+'LF Projected Ratios'!F$33)) -> 0.73004428 | F94: =IF('LF Projected Ratios'!G$33>=0,$B94+(1-$B94)*'LF Projected Ratios'!G$33,$B94*(1+'LF Projected Ratios'!G$33)) -> 0.72921969 | G94: =IF('LF Projected Ratios'!H$33>=0,$B94+(1-$B94)*'LF Projected Ratios'!H$33,$B94*(1+'LF Projected Ratios'!H$33)) -> 0.72836801 | H94: =IF('LF Projected Ratios'!I$33>=0,$B94+(1-$B94)*'LF Projected Ratios'!I$33,$B94*(1+'LF Projected Ratios'!I$33)) -> 0.72748246 | I94: =IF('LF Projected Ratios'!J$33>=0,$B94+(1-$B94)*'LF Projected Ratios'!J$33,$B94*(1+'LF Projected Ratios'!J$33)) -> 0.72654763 | J94: =IF('LF Projected Ratios'!K$33>=0,$B94+(1-$B94)*'LF Projected Ratios'!K$33,$B94*(1+'LF Projected Ratios'!K$33)) -> 0.72557203 | ... AF94: =IF('LF Projected Ratios'!AG$33>=0,$B94+(1-$B94)*'LF Projected Ratios'!AG$33,$B94*(1+'LF Projected Ratios'!AG$33)) -> 0.70893294
A95: ISIC 06 | B95: =B50 -> 0.68698806 | C95: =IF('LF Projected Ratios'!D$33>=0,$B95+(1-$B95)*'LF Projected Ratios'!D$33,$B95*(1+'LF Projected Ratios'!D$33)) -> 0.68621587 | D95: =IF('LF Projected Ratios'!E$33>=0,$B95+(1-$B95)*'LF Projected Ratios'!E$33,$B95*(1+'LF Projected Ratios'!E$33)) -> 0.68540826 | E95: =IF('LF Projected Ratios'!F$33>=0,$B95+(1-$B95)*'LF Projected Ratios'!F$33,$B95*(1+'LF Projected Ratios'!F$33)) -> 0.6846208 | F95: =IF('LF Projected Ratios'!G$33>=0,$B95+(1-$B95)*'LF Projected Ratios'!G$33,$B95*(1+'LF Projected Ratios'!G$33)) -> 0.68384752 | G95: =IF('LF Projected Ratios'!H$33>=0,$B95+(1-$B95)*'LF Projected Ratios'!H$33,$B95*(1+'LF Projected Ratios'!H$33)) -> 0.68304883 | H95: =IF('LF Projected Ratios'!I$33>=0,$B95+(1-$B95)*'LF Projected Ratios'!I$33,$B95*(1+'LF Projected Ratios'!I$33)) -> 0.68221838 | I95: =IF('LF Projected Ratios'!J$33>=0,$B95+(1-$B95)*'LF Projected Ratios'!J$33,$B95*(1+'LF Projected Ratios'!J$33)) -> 0.68134172 | J95: =IF('LF Projected Ratios'!K$33>=0,$B95+(1-$B95)*'LF Projected Ratios'!K$33,$B95*(1+'LF Projected Ratios'!K$33)) -> 0.68042682 | ... AF95: =IF('LF Projected Ratios'!AG$33>=0,$B95+(1-$B95)*'LF Projected Ratios'!AG$33,$B95*(1+'LF Projected Ratios'!AG$33)) -> 0.66482301
A96: ISIC 07T08 | B96: =B51 -> 0.72604711 | C96: =IF('LF Projected Ratios'!D$33>=0,$B96+(1-$B96)*'LF Projected Ratios'!D$33,$B96*(1+'LF Projected Ratios'!D$33)) -> 0.72523102 | D96: =IF('LF Projected Ratios'!E$33>=0,$B96+(1-$B96)*'LF Projected Ratios'!E$33,$B96*(1+'LF Projected Ratios'!E$33)) -> 0.72437749 | E96: =IF('LF Projected Ratios'!F$33>=0,$B96+(1-$B96)*'LF Projected Ratios'!F$33,$B96*(1+'LF Projected Ratios'!F$33)) -> 0.72354527 | F96: =IF('LF Projected Ratios'!G$33>=0,$B96+(1-$B96)*'LF Projected Ratios'!G$33,$B96*(1+'LF Projected Ratios'!G$33)) -> 0.72272802 | G96: =IF('LF Projected Ratios'!H$33>=0,$B96+(1-$B96)*'LF Projected Ratios'!H$33,$B96*(1+'LF Projected Ratios'!H$33)) -> 0.72188392 | H96: =IF('LF Projected Ratios'!I$33>=0,$B96+(1-$B96)*'LF Projected Ratios'!I$33,$B96*(1+'LF Projected Ratios'!I$33)) -> 0.72100625 | I96: =IF('LF Projected Ratios'!J$33>=0,$B96+(1-$B96)*'LF Projected Ratios'!J$33,$B96*(1+'LF Projected Ratios'!J$33)) -> 0.72007975 | J96: =IF('LF Projected Ratios'!K$33>=0,$B96+(1-$B96)*'LF Projected Ratios'!K$33,$B96*(1+'LF Projected Ratios'!K$33)) -> 0.71911283 | ... AF96: =IF('LF Projected Ratios'!AG$33>=0,$B96+(1-$B96)*'LF Projected Ratios'!AG$33,$B96*(1+'LF Projected Ratios'!AG$33)) -> 0.70262186
A97: ISIC 09 | B97: =B52 -> 0.68453973 | C97: =IF('LF Projected Ratios'!D$33>=0,$B97+(1-$B97)*'LF Projected Ratios'!D$33,$B97*(1+'LF Projected Ratios'!D$33)) -> 0.68377029 | D97: =IF('LF Projected Ratios'!E$33>=0,$B97+(1-$B97)*'LF Projected Ratios'!E$33,$B97*(1+'LF Projected Ratios'!E$33)) -> 0.68296556 | E97: =IF('LF Projected Ratios'!F$33>=0,$B97+(1-$B97)*'LF Projected Ratios'!F$33,$B97*(1+'LF Projected Ratios'!F$33)) -> 0.68218091 | F97: =IF('LF Projected Ratios'!G$33>=0,$B97+(1-$B97)*'LF Projected Ratios'!G$33,$B97*(1+'LF Projected Ratios'!G$33)) -> 0.68141039 | G97: =IF('LF Projected Ratios'!H$33>=0,$B97+(1-$B97)*'LF Projected Ratios'!H$33,$B97*(1+'LF Projected Ratios'!H$33)) -> 0.68061455 | H97: =IF('LF Projected Ratios'!I$33>=0,$B97+(1-$B97)*'LF Projected Ratios'!I$33,$B97*(1+'LF Projected Ratios'!I$33)) -> 0.67978705 | I97: =IF('LF Projected Ratios'!J$33>=0,$B97+(1-$B97)*'LF Projected Ratios'!J$33,$B97*(1+'LF Projected Ratios'!J$33)) -> 0.67891352 | J97: =IF('LF Projected Ratios'!K$33>=0,$B97+(1-$B97)*'LF Projected Ratios'!K$33,$B97*(1+'LF Projected Ratios'!K$33)) -> 0.67800188 | ... AF97: =IF('LF Projected Ratios'!AG$33>=0,$B97+(1-$B97)*'LF Projected Ratios'!AG$33,$B97*(1+'LF Projected Ratios'!AG$33)) -> 0.66245368
A98: ISIC 10T12 | B98: =B53 -> 0.54548083 | C98: =IF('LF Projected Ratios'!D$33>=0,$B98+(1-$B98)*'LF Projected Ratios'!D$33,$B98*(1+'LF Projected Ratios'!D$33)) -> 0.54486769 | D98: =IF('LF Projected Ratios'!E$33>=0,$B98+(1-$B98)*'LF Projected Ratios'!E$33,$B98*(1+'LF Projected Ratios'!E$33)) -> 0.54422644 | E98: =IF('LF Projected Ratios'!F$33>=0,$B98+(1-$B98)*'LF Projected Ratios'!F$33,$B98*(1+'LF Projected Ratios'!F$33)) -> 0.54360118 | F98: =IF('LF Projected Ratios'!G$33>=0,$B98+(1-$B98)*'LF Projected Ratios'!G$33,$B98*(1+'LF Projected Ratios'!G$33)) -> 0.54298718 | G98: =IF('LF Projected Ratios'!H$33>=0,$B98+(1-$B98)*'LF Projected Ratios'!H$33,$B98*(1+'LF Projected Ratios'!H$33)) -> 0.54235301 | H98: =IF('LF Projected Ratios'!I$33>=0,$B98+(1-$B98)*'LF Projected Ratios'!I$33,$B98*(1+'LF Projected Ratios'!I$33)) -> 0.54169362 | I98: =IF('LF Projected Ratios'!J$33>=0,$B98+(1-$B98)*'LF Projected Ratios'!J$33,$B98*(1+'LF Projected Ratios'!J$33)) -> 0.54099753 | J98: =IF('LF Projected Ratios'!K$33>=0,$B98+(1-$B98)*'LF Projected Ratios'!K$33,$B98*(1+'LF Projected Ratios'!K$33)) -> 0.54027109 | ... AF98: =IF('LF Projected Ratios'!AG$33>=0,$B98+(1-$B98)*'LF Projected Ratios'!AG$33,$B98*(1+'LF Projected Ratios'!AG$33)) -> 0.52788138
A99: ISIC 13T15 | B99: =B54 -> 0.49043117 | C99: =IF('LF Projected Ratios'!D$33>=0,$B99+(1-$B99)*'LF Projected Ratios'!D$33,$B99*(1+'LF Projected Ratios'!D$33)) -> 0.48987991 | D99: =IF('LF Projected Ratios'!E$33>=0,$B99+(1-$B99)*'LF Projected Ratios'!E$33,$B99*(1+'LF Projected Ratios'!E$33)) -> 0.48930337 | E99: =IF('LF Projected Ratios'!F$33>=0,$B99+(1-$B99)*'LF Projected Ratios'!F$33,$B99*(1+'LF Projected Ratios'!F$33)) -> 0.48874122 | F99: =IF('LF Projected Ratios'!G$33>=0,$B99+(1-$B99)*'LF Projected Ratios'!G$33,$B99*(1+'LF Projected Ratios'!G$33)) -> 0.48818918 | G99: =IF('LF Projected Ratios'!H$33>=0,$B99+(1-$B99)*'LF Projected Ratios'!H$33,$B99*(1+'LF Projected Ratios'!H$33)) -> 0.48761901 | H99: =IF('LF Projected Ratios'!I$33>=0,$B99+(1-$B99)*'LF Projected Ratios'!I$33,$B99*(1+'LF Projected Ratios'!I$33)) -> 0.48702616 | I99: =IF('LF Projected Ratios'!J$33>=0,$B99+(1-$B99)*'LF Projected Ratios'!J$33,$B99*(1+'LF Projected Ratios'!J$33)) -> 0.48640033 | J99: =IF('LF Projected Ratios'!K$33>=0,$B99+(1-$B99)*'LF Projected Ratios'!K$33,$B99*(1+'LF Projected Ratios'!K$33)) -> 0.48574719 | ... AF99: =IF('LF Projected Ratios'!AG$33>=0,$B99+(1-$B99)*'LF Projected Ratios'!AG$33,$B99*(1+'LF Projected Ratios'!AG$33)) -> 0.47460785
A100: ISIC 16 | B100: =B55 -> 0.6735715 | C100: =IF('LF Projected Ratios'!D$33>=0,$B100+(1-$B100)*'LF Projected Ratios'!D$33,$B100*(1+'LF Projected Ratios'!D$33)) -> 0.6728144 | D100: =IF('LF Projected Ratios'!E$33>=0,$B100+(1-$B100)*'LF Projected Ratios'!E$33,$B100*(1+'LF Projected Ratios'!E$33)) -> 0.67202256 | E100: =IF('LF Projected Ratios'!F$33>=0,$B100+(1-$B100)*'LF Projected Ratios'!F$33,$B100*(1+'LF Projected Ratios'!F$33)) -> 0.67125048 | F100: =IF('LF Projected Ratios'!G$33>=0,$B100+(1-$B100)*'LF Projected Ratios'!G$33,$B100*(1+'LF Projected Ratios'!G$33)) -> 0.6704923 | G100: =IF('LF Projected Ratios'!H$33>=0,$B100+(1-$B100)*'LF Projected Ratios'!H$33,$B100*(1+'LF Projected Ratios'!H$33)) -> 0.66970922 | H100: =IF('LF Projected Ratios'!I$33>=0,$B100+(1-$B100)*'LF Projected Ratios'!I$33,$B100*(1+'LF Projected Ratios'!I$33)) -> 0.66889498 | I100: =IF('LF Projected Ratios'!J$33>=0,$B100+(1-$B100)*'LF Projected Ratios'!J$33,$B100*(1+'LF Projected Ratios'!J$33)) -> 0.66803544 | J100: =IF('LF Projected Ratios'!K$33>=0,$B100+(1-$B100)*'LF Projected Ratios'!K$33,$B100*(1+'LF Projected Ratios'!K$33)) -> 0.66713841 | ... AF100: =IF('LF Projected Ratios'!AG$33>=0,$B100+(1-$B100)*'LF Projected Ratios'!AG$33,$B100*(1+'LF Projected Ratios'!AG$33)) -> 0.65183933
A101: ISIC 17T18 | B101: =B56 -> 0.60175673 | C101: =IF('LF Projected Ratios'!D$33>=0,$B101+(1-$B101)*'LF Projected Ratios'!D$33,$B101*(1+'LF Projected Ratios'!D$33)) -> 0.60108035 | D101: =IF('LF Projected Ratios'!E$33>=0,$B101+(1-$B101)*'LF Projected Ratios'!E$33,$B101*(1+'LF Projected Ratios'!E$33)) -> 0.60037293 | E101: =IF('LF Projected Ratios'!F$33>=0,$B101+(1-$B101)*'LF Projected Ratios'!F$33,$B101*(1+'LF Projected Ratios'!F$33)) -> 0.59968318 | F101: =IF('LF Projected Ratios'!G$33>=0,$B101+(1-$B101)*'LF Projected Ratios'!G$33,$B101*(1+'LF Projected Ratios'!G$33)) -> 0.59900583 | G101: =IF('LF Projected Ratios'!H$33>=0,$B101+(1-$B101)*'LF Projected Ratios'!H$33,$B101*(1+'LF Projected Ratios'!H$33)) -> 0.59830623 | H101: =IF('LF Projected Ratios'!I$33>=0,$B101+(1-$B101)*'LF Projected Ratios'!I$33,$B101*(1+'LF Projected Ratios'!I$33)) -> 0.59757881 | I101: =IF('LF Projected Ratios'!J$33>=0,$B101+(1-$B101)*'LF Projected Ratios'!J$33,$B101*(1+'LF Projected Ratios'!J$33)) -> 0.59681091 | J101: =IF('LF Projected Ratios'!K$33>=0,$B101+(1-$B101)*'LF Projected Ratios'!K$33,$B101*(1+'LF Projected Ratios'!K$33)) -> 0.59600952 | ... AF101: =IF('LF Projected Ratios'!AG$33>=0,$B101+(1-$B101)*'LF Projected Ratios'!AG$33,$B101*(1+'LF Projected Ratios'!AG$33)) -> 0.5823416
A102: ISIC 19 | B102: =B57 -> 0.66470345 | C102: =IF('LF Projected Ratios'!D$33>=0,$B102+(1-$B102)*'LF Projected Ratios'!D$33,$B102*(1+'LF Projected Ratios'!D$33)) -> 0.66395631 | D102: =IF('LF Projected Ratios'!E$33>=0,$B102+(1-$B102)*'LF Projected Ratios'!E$33,$B102*(1+'LF Projected Ratios'!E$33)) -> 0.66317489 | E102: =IF('LF Projected Ratios'!F$33>=0,$B102+(1-$B102)*'LF Projected Ratios'!F$33,$B102*(1+'LF Projected Ratios'!F$33)) -> 0.66241298 | F102: =IF('LF Projected Ratios'!G$33>=0,$B102+(1-$B102)*'LF Projected Ratios'!G$33,$B102*(1+'LF Projected Ratios'!G$33)) -> 0.66166478 | G102: =IF('LF Projected Ratios'!H$33>=0,$B102+(1-$B102)*'LF Projected Ratios'!H$33,$B102*(1+'LF Projected Ratios'!H$33)) -> 0.66089201 | H102: =IF('LF Projected Ratios'!I$33>=0,$B102+(1-$B102)*'LF Projected Ratios'!I$33,$B102*(1+'LF Projected Ratios'!I$33)) -> 0.66008849 | I102: =IF('LF Projected Ratios'!J$33>=0,$B102+(1-$B102)*'LF Projected Ratios'!J$33,$B102*(1+'LF Projected Ratios'!J$33)) -> 0.65924027 | J102: =IF('LF Projected Ratios'!K$33>=0,$B102+(1-$B102)*'LF Projected Ratios'!K$33,$B102*(1+'LF Projected Ratios'!K$33)) -> 0.65835504 | ... AF102: =IF('LF Projected Ratios'!AG$33>=0,$B102+(1-$B102)*'LF Projected Ratios'!AG$33,$B102*(1+'LF Projected Ratios'!AG$33)) -> 0.6432574
A103: ISIC 20 | B103: =B58 -> 0.58875995 | C103: =IF('LF Projected Ratios'!D$33>=0,$B103+(1-$B103)*'LF Projected Ratios'!D$33,$B103*(1+'LF Projected Ratios'!D$33)) -> 0.58809818 | D103: =IF('LF Projected Ratios'!E$33>=0,$B103+(1-$B103)*'LF Projected Ratios'!E$33,$B103*(1+'LF Projected Ratios'!E$33)) -> 0.58740604 | E103: =IF('LF Projected Ratios'!F$33>=0,$B103+(1-$B103)*'LF Projected Ratios'!F$33,$B103*(1+'LF Projected Ratios'!F$33)) -> 0.58673118 | F103: =IF('LF Projected Ratios'!G$33>=0,$B103+(1-$B103)*'LF Projected Ratios'!G$33,$B103*(1+'LF Projected Ratios'!G$33)) -> 0.58606846 | G103: =IF('LF Projected Ratios'!H$33>=0,$B103+(1-$B103)*'LF Projected Ratios'!H$33,$B103*(1+'LF Projected Ratios'!H$33)) -> 0.58538398 | H103: =IF('LF Projected Ratios'!I$33>=0,$B103+(1-$B103)*'LF Projected Ratios'!I$33,$B103*(1+'LF Projected Ratios'!I$33)) -> 0.58467226 | I103: =IF('LF Projected Ratios'!J$33>=0,$B103+(1-$B103)*'LF Projected Ratios'!J$33,$B103*(1+'LF Projected Ratios'!J$33)) -> 0.58392095 | J103: =IF('LF Projected Ratios'!K$33>=0,$B103+(1-$B103)*'LF Projected Ratios'!K$33,$B103*(1+'LF Projected Ratios'!K$33)) -> 0.58313687 | ... AF103: =IF('LF Projected Ratios'!AG$33>=0,$B103+(1-$B103)*'LF Projected Ratios'!AG$33,$B103*(1+'LF Projected Ratios'!AG$33)) -> 0.56976415
A104: ISIC 21 | B104: =B59 -> 0.52973431 | C104: =IF('LF Projected Ratios'!D$33>=0,$B104+(1-$B104)*'LF Projected Ratios'!D$33,$B104*(1+'LF Projected Ratios'!D$33)) -> 0.52913888 | D104: =IF('LF Projected Ratios'!E$33>=0,$B104+(1-$B104)*'LF Projected Ratios'!E$33,$B104*(1+'LF Projected Ratios'!E$33)) -> 0.52851613 | E104: =IF('LF Projected Ratios'!F$33>=0,$B104+(1-$B104)*'LF Projected Ratios'!F$33,$B104*(1+'LF Projected Ratios'!F$33)) -> 0.52790893 | F104: =IF('LF Projected Ratios'!G$33>=0,$B104+(1-$B104)*'LF Projected Ratios'!G$33,$B104*(1+'LF Projected Ratios'!G$33)) -> 0.52731265 | G104: =IF('LF Projected Ratios'!H$33>=0,$B104+(1-$B104)*'LF Projected Ratios'!H$33,$B104*(1+'LF Projected Ratios'!H$33)) -> 0.52669679 | H104: =IF('LF Projected Ratios'!I$33>=0,$B104+(1-$B104)*'LF Projected Ratios'!I$33,$B104*(1+'LF Projected Ratios'!I$33)) -> 0.52605643 | I104: =IF('LF Projected Ratios'!J$33>=0,$B104+(1-$B104)*'LF Projected Ratios'!J$33,$B104*(1+'LF Projected Ratios'!J$33)) -> 0.52538044 | J104: =IF('LF Projected Ratios'!K$33>=0,$B104+(1-$B104)*'LF Projected Ratios'!K$33,$B104*(1+'LF Projected Ratios'!K$33)) -> 0.52467496 | ... AF104: =IF('LF Projected Ratios'!AG$33>=0,$B104+(1-$B104)*'LF Projected Ratios'!AG$33,$B104*(1+'LF Projected Ratios'!AG$33)) -> 0.51264292
... A134: ISIC 97T98 | B134: =B89 -> 0.27814234 | C134: =IF('LF Projected Ratios'!D$33>=0,$B134+(1-$B134)*'LF Projected Ratios'!D$33,$B134*(1+'LF Projected Ratios'!D$33)) -> 0.2778297 | D134: =IF('LF Projected Ratios'!E$33>=0,$B134+(1-$B134)*'LF Projected Ratios'!E$33,$B134*(1+'LF Projected Ratios'!E$33)) -> 0.27750272 | E134: =IF('LF Projected Ratios'!F$33>=0,$B134+(1-$B134)*'LF Projected Ratios'!F$33,$B134*(1+'LF Projected Ratios'!F$33)) -> 0.2771839 | F134: =IF('LF Projected Ratios'!G$33>=0,$B134+(1-$B134)*'LF Projected Ratios'!G$33,$B134*(1+'LF Projected Ratios'!G$33)) -> 0.27687082 | G134: =IF('LF Projected Ratios'!H$33>=0,$B134+(1-$B134)*'LF Projected Ratios'!H$33,$B134*(1+'LF Projected Ratios'!H$33)) -> 0.27654746 | H134: =IF('LF Projected Ratios'!I$33>=0,$B134+(1-$B134)*'LF Projected Ratios'!I$33,$B134*(1+'LF Projected Ratios'!I$33)) -> 0.27621123 | I134: =IF('LF Projected Ratios'!J$33>=0,$B134+(1-$B134)*'LF Projected Ratios'!J$33,$B134*(1+'LF Projected Ratios'!J$33)) -> 0.27585629 | J134: =IF('LF Projected Ratios'!K$33>=0,$B134+(1-$B134)*'LF Projected Ratios'!K$33,$B134*(1+'LF Projected Ratios'!K$33)) -> 0.27548588 | ... AF134: =IF('LF Projected Ratios'!AG$33>=0,$B134+(1-$B134)*'LF Projected Ratios'!AG$33,$B134*(1+'LF Projected Ratios'!AG$33)) -> 0.26916833
A136: Reapply sigmoid (i.e. convert from X value to Y value)
B137: 2020 | C137: 2021 | D137: 2022 | E137: 2023 | F137: 2024 | G137: 2025 | H137: 2026 | I137: 2027 | J137: 2028 | K137: 2029 | L137: 2030 | M137: 2031 | N137: 2032 | O137: 2033 | P137: 2034 | Q137: 2035 | R137: 2036 | S137: 2037 | T137: 2038 | U137: 2039 | V137: 2040 | W137: 2041 | X137: 2042 | Y137: 2043 | Z137: 2044 | AA137: 2045 | AB137: 2046 | AC137: 2047 | AD137: 2048 | AE137: 2049 | AF137: 2050
A138: ISIC 01T03 | B138: =(1/(1+EXP(('S Curve Equation'!$B$11-B93*'S Curve Equation'!$B$12)*'S Curve Equation'!$B$10))+'S Curve Equation'!$B$13)*'S Curve Equation'!$B$14 -> 0.723 | C138: =(1/(1+EXP(('S Curve Equation'!$B$11-C93*'S Curve Equation'!$B$12)*'S Curve Equation'!$B$10))+'S Curve Equation'!$B$13)*'S Curve Equation'!$B$14 -> 0.72173385 | D138: =(1/(1+EXP(('S Curve Equation'!$B$11-D93*'S Curve Equation'!$B$12)*'S Curve Equation'!$B$10))+'S Curve Equation'!$B$13)*'S Curve Equation'!$B$14 -> 0.72040603 | E138: =(1/(1+EXP(('S Curve Equation'!$B$11-E93*'S Curve Equation'!$B$12)*'S Curve Equation'!$B$10))+'S Curve Equation'!$B$13)*'S Curve Equation'!$B$14 -> 0.71910781 | F138: =(1/(1+EXP(('S Curve Equation'!$B$11-F93*'S Curve Equation'!$B$12)*'S Curve Equation'!$B$10))+'S Curve Equation'!$B$13)*'S Curve Equation'!$B$14 -> 0.71782958 | G138: =(1/(1+EXP(('S Curve Equation'!$B$11-G93*'S Curve Equation'!$B$12)*'S Curve Equation'!$B$10))+'S Curve Equation'!$B$13)*'S Curve Equation'!$B$14 -> 0.71650586 | H138: =(1/(1+EXP(('S Curve Equation'!$B$11-H93*'S Curve Equation'!$B$12)*'S Curve Equation'!$B$10))+'S Curve Equation'!$B$13)*'S Curve Equation'!$B$14 -> 0.71512572 | I138: =(1/(1+EXP(('S Curve Equation'!$B$11-I93*'S Curve Equation'!$B$12)*'S Curve Equation'!$B$10))+'S Curve Equation'!$B$13)*'S Curve Equation'!$B$14 -> 0.71366466 | ... AF138: =(1/(1+EXP(('S Curve Equation'!$B$11-AF93*'S Curve Equation'!$B$12)*'S Curve Equation'!$B$10))+'S Curve Equation'!$B$13)*'S Curve Equation'!$B$14 -> 0.68536137
A139: ISIC 05 | B139: =(1/(1+EXP(('S Curve Equation'!$B$11-B94*'S Curve Equation'!$B$12)*'S Curve Equation'!$B$10))+'S Curve Equation'!$B$13)*'S Curve Equation'!$B$14 -> 0.899 | C139: =(1/(1+EXP(('S Curve Equation'!$B$11-C94*'S Curve Equation'!$B$12)*'S Curve Equation'!$B$10))+'S Curve Equation'!$B$13)*'S Curve Equation'!$B$14 -> 0.89825741 | D139: =(1/(1+EXP(('S Curve Equation'!$B$11-D94*'S Curve Equation'!$B$12)*'S Curve Equation'!$B$10))+'S Curve Equation'!$B$13)*'S Curve Equation'!$B$14 -> 0.89747616 | E139: =(1/(1+EXP(('S Curve Equation'!$B$11-E94*'S Curve Equation'!$B$12)*'S Curve Equation'!$B$10))+'S Curve Equation'!$B$13)*'S Curve Equation'!$B$14 -> 0.89670986 | F139: =(1/(1+EXP(('S Curve Equation'!$B$11-F94*'S Curve Equation'!$B$12)*'S Curve Equation'!$B$10))+'S Curve Equation'!$B$13)*'S Curve Equation'!$B$14 -> 0.89595297 | G139: =(1/(1+EXP(('S Curve Equation'!$B$11-G94*'S Curve Equation'!$B$12)*'S Curve Equation'!$B$10))+'S Curve Equation'!$B$13)*'S Curve Equation'!$B$14 -> 0.89516663 | H139: =(1/(1+EXP(('S Curve Equation'!$B$11-H94*'S Curve Equation'!$B$12)*'S Curve Equation'!$B$10))+'S Curve Equation'!$B$13)*'S Curve Equation'!$B$14 -> 0.89434405 | I139: =(1/(1+EXP(('S Curve Equation'!$B$11-I94*'S Curve Equation'!$B$12)*'S Curve Equation'!$B$10))+'S Curve Equation'!$B$13)*'S Curve Equation'!$B$14 -> 0.8934702 | ... AF139: =(1/(1+EXP(('S Curve Equation'!$B$11-AF94*'S Curve Equation'!$B$12)*'S Curve Equation'!$B$10))+'S Curve Equation'!$B$13)*'S Curve Equation'!$B$14 -> 0.87591701
A140: ISIC 06 | B140: =(1/(1+EXP(('S Curve Equation'!$B$11-B95*'S Curve Equation'!$B$12)*'S Curve Equation'!$B$10))+'S Curve Equation'!$B$13)*'S Curve Equation'!$B$14 -> 0.851 | C140: =(1/(1+EXP(('S Curve Equation'!$B$11-C95*'S Curve Equation'!$B$12)*'S Curve Equation'!$B$10))+'S Curve Equation'!$B$13)*'S Curve Equation'!$B$14 -> 0.85005869 | D140: =(1/(1+EXP(('S Curve Equation'!$B$11-D95*'S Curve Equation'!$B$12)*'S Curve Equation'!$B$10))+'S Curve Equation'!$B$13)*'S Curve Equation'!$B$14 -> 0.84906941 | E140: =(1/(1+EXP(('S Curve Equation'!$B$11-E95*'S Curve Equation'!$B$12)*'S Curve Equation'!$B$10))+'S Curve Equation'!$B$13)*'S Curve Equation'!$B$14 -> 0.84810007 | F140: =(1/(1+EXP(('S Curve Equation'!$B$11-F95*'S Curve Equation'!$B$12)*'S Curve Equation'!$B$10))+'S Curve Equation'!$B$13)*'S Curve Equation'!$B$14 -> 0.84714361 | G140: =(1/(1+EXP(('S Curve Equation'!$B$11-G95*'S Curve Equation'!$B$12)*'S Curve Equation'!$B$10))+'S Curve Equation'!$B$13)*'S Curve Equation'!$B$14 -> 0.84615097 | H140: =(1/(1+EXP(('S Curve Equation'!$B$11-H95*'S Curve Equation'!$B$12)*'S Curve Equation'!$B$10))+'S Curve Equation'!$B$13)*'S Curve Equation'!$B$14 -> 0.84511372 | I140: =(1/(1+EXP(('S Curve Equation'!$B$11-I95*'S Curve Equation'!$B$12)*'S Curve Equation'!$B$10))+'S Curve Equation'!$B$13)*'S Curve Equation'!$B$14 -> 0.84401306 | ... AF140: =(1/(1+EXP(('S Curve Equation'!$B$11-AF95*'S Curve Equation'!$B$12)*'S Curve Equation'!$B$10))+'S Curve Equation'!$B$13)*'S Curve Equation'!$B$14 -> 0.82216589
A141: ISIC 07T08 | B141: =(1/(1+EXP(('S Curve Equation'!$B$11-B96*'S Curve Equation'!$B$12)*'S Curve Equation'!$B$10))+'S Curve Equation'!$B$13)*'S Curve Equation'!$B$14 -> 0.893 | C141: =(1/(1+EXP(('S Curve Equation'!$B$11-C96*'S Curve Equation'!$B$12)*'S Curve Equation'!$B$10))+'S Curve Equation'!$B$13)*'S Curve Equation'!$B$14 -> 0.89222984 | D141: =(1/(1+EXP(('S Curve Equation'!$B$11-D96*'S Curve Equation'!$B$12)*'S Curve Equation'!$B$10))+'S Curve Equation'!$B$13)*'S Curve Equation'!$B$14 -> 0.8914197 | E141: =(1/(1+EXP(('S Curve Equation'!$B$11-E96*'S Curve Equation'!$B$12)*'S Curve Equation'!$B$10))+'S Curve Equation'!$B$13)*'S Curve Equation'!$B$14 -> 0.89062517 | F141: =(1/(1+EXP(('S Curve Equation'!$B$11-F96*'S Curve Equation'!$B$12)*'S Curve Equation'!$B$10))+'S Curve Equation'!$B$13)*'S Curve Equation'!$B$14 -> 0.88984051 | G141: =(1/(1+EXP(('S Curve Equation'!$B$11-G96*'S Curve Equation'!$B$12)*'S Curve Equation'!$B$10))+'S Curve Equation'!$B$13)*'S Curve Equation'!$B$14 -> 0.88902543 | H141: =(1/(1+EXP(('S Curve Equation'!$B$11-H96*'S Curve Equation'!$B$12)*'S Curve Equation'!$B$10))+'S Curve Equation'!$B$13)*'S Curve Equation'!$B$14 -> 0.88817292 | I141: =(1/(1+EXP(('S Curve Equation'!$B$11-I96*'S Curve Equation'!$B$12)*'S Curve Equation'!$B$10))+'S Curve Equation'!$B$13)*'S Curve Equation'!$B$14 -> 0.88726742 | ... AF141: =(1/(1+EXP(('S Curve Equation'!$B$11-AF96*'S Curve Equation'!$B$12)*'S Curve Equation'!$B$10))+'S Curve Equation'!$B$13)*'S Curve Equation'!$B$14 -> 0.86910788
A142: ISIC 09 | B142: =(1/(1+EXP(('S Curve Equation'!$B$11-B97*'S Curve Equation'!$B$12)*'S Curve Equation'!$B$10))+'S Curve Equation'!$B$13)*'S Curve Equation'!$B$14 -> 0.848 | C142: =(1/(1+EXP(('S Curve Equation'!$B$11-C97*'S Curve Equation'!$B$12)*'S Curve Equation'!$B$10))+'S Curve Equation'!$B$13)*'S Curve Equation'!$B$14 -> 0.84704784 | D142: =(1/(1+EXP(('S Curve Equation'!$B$11-D97*'S Curve Equation'!$B$12)*'S Curve Equation'!$B$10))+'S Curve Equation'!$B$13)*'S Curve Equation'!$B$14 -> 0.8460472 | E142: =(1/(1+EXP(('S Curve Equation'!$B$11-E97*'S Curve Equation'!$B$12)*'S Curve Equation'!$B$10))+'S Curve Equation'!$B$13)*'S Curve Equation'!$B$14 -> 0.8450668 | F142: =(1/(1+EXP(('S Curve Equation'!$B$11-F97*'S Curve Equation'!$B$12)*'S Curve Equation'!$B$10))+'S Curve Equation'!$B$13)*'S Curve Equation'!$B$14 -> 0.84409949 | G142: =(1/(1+EXP(('S Curve Equation'!$B$11-G97*'S Curve Equation'!$B$12)*'S Curve Equation'!$B$10))+'S Curve Equation'!$B$13)*'S Curve Equation'!$B$14 -> 0.84309565 | H142: =(1/(1+EXP(('S Curve Equation'!$B$11-H97*'S Curve Equation'!$B$12)*'S Curve Equation'!$B$10))+'S Curve Equation'!$B$13)*'S Curve Equation'!$B$14 -> 0.84204674 | I142: =(1/(1+EXP(('S Curve Equation'!$B$11-I97*'S Curve Equation'!$B$12)*'S Curve Equation'!$B$10))+'S Curve Equation'!$B$13)*'S Curve Equation'!$B$14 -> 0.8409338 | ... AF142: =(1/(1+EXP(('S Curve Equation'!$B$11-AF97*'S Curve Equation'!$B$12)*'S Curve Equation'!$B$10))+'S Curve Equation'!$B$13)*'S Curve Equation'!$B$14 -> 0.81885762
A143: ISIC 10T12 | B143: =(1/(1+EXP(('S Curve Equation'!$B$11-B98*'S Curve Equation'!$B$12)*'S Curve Equation'!$B$10))+'S Curve Equation'!$B$13)*'S Curve Equation'!$B$14 -> 0.60319417 | C143: =(1/(1+EXP(('S Curve Equation'!$B$11-C98*'S Curve Equation'!$B$12)*'S Curve Equation'!$B$10))+'S Curve Equation'!$B$13)*'S Curve Equation'!$B$14 -> 0.60184036 | D143: =(1/(1+EXP(('S Curve Equation'!$B$11-D98*'S Curve Equation'!$B$12)*'S Curve Equation'!$B$10))+'S Curve Equation'!$B$13)*'S Curve Equation'!$B$14 -> 0.60042284 | E143: =(1/(1+EXP(('S Curve Equation'!$B$11-E98*'S Curve Equation'!$B$12)*'S Curve Equation'!$B$10))+'S Curve Equation'!$B$13)*'S Curve Equation'!$B$14 -> 0.59903916 | F143: =(1/(1+EXP(('S Curve Equation'!$B$11-F98*'S Curve Equation'!$B$12)*'S Curve Equation'!$B$10))+'S Curve Equation'!$B$13)*'S Curve Equation'!$B$14 -> 0.5976789 | G143: =(1/(1+EXP(('S Curve Equation'!$B$11-G98*'S Curve Equation'!$B$12)*'S Curve Equation'!$B$10))+'S Curve Equation'!$B$13)*'S Curve Equation'!$B$14 -> 0.59627246 | H143: =(1/(1+EXP(('S Curve Equation'!$B$11-H98*'S Curve Equation'!$B$12)*'S Curve Equation'!$B$10))+'S Curve Equation'!$B$13)*'S Curve Equation'!$B$14 -> 0.59480846 | I143: =(1/(1+EXP(('S Curve Equation'!$B$11-I98*'S Curve Equation'!$B$12)*'S Curve Equation'!$B$10))+'S Curve Equation'!$B$13)*'S Curve Equation'!$B$14 -> 0.59326127 | ... AF143: =(1/(1+EXP(('S Curve Equation'!$B$11-AF98*'S Curve Equation'!$B$12)*'S Curve Equation'!$B$10))+'S Curve Equation'!$B$13)*'S Curve Equation'!$B$14 -> 0.56380811
A144: ISIC 13T15 | B144: =(1/(1+EXP(('S Curve Equation'!$B$11-B99*'S Curve Equation'!$B$12)*'S Curve Equation'!$B$10))+'S Curve Equation'!$B$13)*'S Curve Equation'!$B$14 -> 0.478 | C144: =(1/(1+EXP(('S Curve Equation'!$B$11-C99*'S Curve Equation'!$B$12)*'S Curve Equation'!$B$10))+'S Curve Equation'!$B$13)*'S Curve Equation'!$B$14 -> 0.4767343 | D144: =(1/(1+EXP(('S Curve Equation'!$B$11-D99*'S Curve Equation'!$B$12)*'S Curve Equation'!$B$10))+'S Curve Equation'!$B$13)*'S Curve Equation'!$B$14 -> 0.47541084 | E144: =(1/(1+EXP(('S Curve Equation'!$B$11-E99*'S Curve Equation'!$B$12)*'S Curve Equation'!$B$10))+'S Curve Equation'!$B$13)*'S Curve Equation'!$B$14 -> 0.47412073 | F144: =(1/(1+EXP(('S Curve Equation'!$B$11-F99*'S Curve Equation'!$B$12)*'S Curve Equation'!$B$10))+'S Curve Equation'!$B$13)*'S Curve Equation'!$B$14 -> 0.47285416 | G144: =(1/(1+EXP(('S Curve Equation'!$B$11-G99*'S Curve Equation'!$B$12)*'S Curve Equation'!$B$10))+'S Curve Equation'!$B$13)*'S Curve Equation'!$B$14 -> 0.47154633 | H144: =(1/(1+EXP(('S Curve Equation'!$B$11-H99*'S Curve Equation'!$B$12)*'S Curve Equation'!$B$10))+'S Curve Equation'!$B$13)*'S Curve Equation'!$B$14 -> 0.47018687 | I144: =(1/(1+EXP(('S Curve Equation'!$B$11-I99*'S Curve Equation'!$B$12)*'S Curve Equation'!$B$10))+'S Curve Equation'!$B$13)*'S Curve Equation'!$B$14 -> 0.46875224 | ... AF144: =(1/(1+EXP(('S Curve Equation'!$B$11-AF99*'S Curve Equation'!$B$12)*'S Curve Equation'!$B$10))+'S Curve Equation'!$B$13)*'S Curve Equation'!$B$14 -> 0.44183696
A145: ISIC 16 | B145: =(1/(1+EXP(('S Curve Equation'!$B$11-B100*'S Curve Equation'!$B$12)*'S Curve Equation'!$B$10))+'S Curve Equation'!$B$13)*'S Curve Equation'!$B$14 -> 0.834 | C145: =(1/(1+EXP(('S Curve Equation'!$B$11-C100*'S Curve Equation'!$B$12)*'S Curve Equation'!$B$10))+'S Curve Equation'!$B$13)*'S Curve Equation'!$B$14 -> 0.83299945 | D145: =(1/(1+EXP(('S Curve Equation'!$B$11-D100*'S Curve Equation'!$B$12)*'S Curve Equation'!$B$10))+'S Curve Equation'!$B$13)*'S Curve Equation'!$B$14 -> 0.83194824 | E145: =(1/(1+EXP(('S Curve Equation'!$B$11-E100*'S Curve Equation'!$B$12)*'S Curve Equation'!$B$10))+'S Curve Equation'!$B$13)*'S Curve Equation'!$B$14 -> 0.83091856 | F145: =(1/(1+EXP(('S Curve Equation'!$B$11-F100*'S Curve Equation'!$B$12)*'S Curve Equation'!$B$10))+'S Curve Equation'!$B$13)*'S Curve Equation'!$B$14 -> 0.82990291 | G145: =(1/(1+EXP(('S Curve Equation'!$B$11-G100*'S Curve Equation'!$B$12)*'S Curve Equation'!$B$10))+'S Curve Equation'!$B$13)*'S Curve Equation'!$B$14 -> 0.82884918 | H145: =(1/(1+EXP(('S Curve Equation'!$B$11-H100*'S Curve Equation'!$B$12)*'S Curve Equation'!$B$10))+'S Curve Equation'!$B$13)*'S Curve Equation'!$B$14 -> 0.82774845 | I145: =(1/(1+EXP(('S Curve Equation'!$B$11-I100*'S Curve Equation'!$B$12)*'S Curve Equation'!$B$10))+'S Curve Equation'!$B$13)*'S Curve Equation'!$B$14 -> 0.82658087 | ... AF145: =(1/(1+EXP(('S Curve Equation'!$B$11-AF100*'S Curve Equation'!$B$12)*'S Curve Equation'!$B$10))+'S Curve Equation'!$B$13)*'S Curve Equation'!$B$14 -> 0.80349172
A146: ISIC 17T18 | B146: =(1/(1+EXP(('S Curve Equation'!$B$11-B101*'S Curve Equation'!$B$12)*'S Curve Equation'!$B$10))+'S Curve Equation'!$B$13)*'S Curve Equation'!$B$14 -> 0.719 | C146: =(1/(1+EXP(('S Curve Equation'!$B$11-C101*'S Curve Equation'!$B$12)*'S Curve Equation'!$B$10))+'S Curve Equation'!$B$13)*'S Curve Equation'!$B$14 -> 0.71772783 | D146: =(1/(1+EXP(('S Curve Equation'!$B$11-D101*'S Curve Equation'!$B$12)*'S Curve Equation'!$B$10))+'S Curve Equation'!$B$13)*'S Curve Equation'!$B$14 -> 0.71639377 | E146: =(1/(1+EXP(('S Curve Equation'!$B$11-E101*'S Curve Equation'!$B$12)*'S Curve Equation'!$B$10))+'S Curve Equation'!$B$13)*'S Curve Equation'!$B$14 -> 0.71508953 | F146: =(1/(1+EXP(('S Curve Equation'!$B$11-F101*'S Curve Equation'!$B$12)*'S Curve Equation'!$B$10))+'S Curve Equation'!$B$13)*'S Curve Equation'!$B$14 -> 0.71380545 | G146: =(1/(1+EXP(('S Curve Equation'!$B$11-G101*'S Curve Equation'!$B$12)*'S Curve Equation'!$B$10))+'S Curve Equation'!$B$13)*'S Curve Equation'!$B$14 -> 0.71247575 | H146: =(1/(1+EXP(('S Curve Equation'!$B$11-H101*'S Curve Equation'!$B$12)*'S Curve Equation'!$B$10))+'S Curve Equation'!$B$13)*'S Curve Equation'!$B$14 -> 0.71108945 | I146: =(1/(1+EXP(('S Curve Equation'!$B$11-I101*'S Curve Equation'!$B$12)*'S Curve Equation'!$B$10))+'S Curve Equation'!$B$13)*'S Curve Equation'!$B$14 -> 0.70962196 | ... AF146: =(1/(1+EXP(('S Curve Equation'!$B$11-AF101*'S Curve Equation'!$B$12)*'S Curve Equation'!$B$10))+'S Curve Equation'!$B$13)*'S Curve Equation'!$B$14 -> 0.6812127
A147: ISIC 19 | B147: =(1/(1+EXP(('S Curve Equation'!$B$11-B102*'S Curve Equation'!$B$12)*'S Curve Equation'!$B$10))+'S Curve Equation'!$B$13)*'S Curve Equation'!$B$14 -> 0.822 | C147: =(1/(1+EXP(('S Curve Equation'!$B$11-C102*'S Curve Equation'!$B$12)*'S Curve Equation'!$B$10))+'S Curve Equation'!$B$13)*'S Curve Equation'!$B$14 -> 0.82096085 | D147: =(1/(1+EXP(('S Curve Equation'!$B$11-D102*'S Curve Equation'!$B$12)*'S Curve Equation'!$B$10))+'S Curve Equation'!$B$13)*'S Curve Equation'!$B$14 -> 0.81986932 | E147: =(1/(1+EXP(('S Curve Equation'!$B$11-E102*'S Curve Equation'!$B$12)*'S Curve Equation'!$B$10))+'S Curve Equation'!$B$13)*'S Curve Equation'!$B$14 -> 0.81880041 | F147: =(1/(1+EXP(('S Curve Equation'!$B$11-F102*'S Curve Equation'!$B$12)*'S Curve Equation'!$B$10))+'S Curve Equation'!$B$13)*'S Curve Equation'!$B$14 -> 0.81774627 | G147: =(1/(1+EXP(('S Curve Equation'!$B$11-G102*'S Curve Equation'!$B$12)*'S Curve Equation'!$B$10))+'S Curve Equation'!$B$13)*'S Curve Equation'!$B$14 -> 0.81665286 | H147: =(1/(1+EXP(('S Curve Equation'!$B$11-H102*'S Curve Equation'!$B$12)*'S Curve Equation'!$B$10))+'S Curve Equation'!$B$13)*'S Curve Equation'!$B$14 -> 0.81551095 | I147: =(1/(1+EXP(('S Curve Equation'!$B$11-I102*'S Curve Equation'!$B$12)*'S Curve Equation'!$B$10))+'S Curve Equation'!$B$13)*'S Curve Equation'!$B$14 -> 0.81429997 | ... AF147: =(1/(1+EXP(('S Curve Equation'!$B$11-AF102*'S Curve Equation'!$B$12)*'S Curve Equation'!$B$10))+'S Curve Equation'!$B$13)*'S Curve Equation'!$B$14 -> 0.79041299
A148: ISIC 20 | B148: =(1/(1+EXP(('S Curve Equation'!$B$11-B103*'S Curve Equation'!$B$12)*'S Curve Equation'!$B$10))+'S Curve Equation'!$B$13)*'S Curve Equation'!$B$14 -> 0.69398889 | C148: =(1/(1+EXP(('S Curve Equation'!$B$11-C103*'S Curve Equation'!$B$12)*'S Curve Equation'!$B$10))+'S Curve Equation'!$B$13)*'S Curve Equation'!$B$14 -> 0.69268417 | D148: =(1/(1+EXP(('S Curve Equation'!$B$11-D103*'S Curve Equation'!$B$12)*'S Curve Equation'!$B$10))+'S Curve Equation'!$B$13)*'S Curve Equation'!$B$14 -> 0.69131647 | E148: =(1/(1+EXP(('S Curve Equation'!$B$11-E103*'S Curve Equation'!$B$12)*'S Curve Equation'!$B$10))+'S Curve Equation'!$B$13)*'S Curve Equation'!$B$14 -> 0.68997983 | F148: =(1/(1+EXP(('S Curve Equation'!$B$11-F103*'S Curve Equation'!$B$12)*'S Curve Equation'!$B$10))+'S Curve Equation'!$B$13)*'S Curve Equation'!$B$14 -> 0.6886643 | G148: =(1/(1+EXP(('S Curve Equation'!$B$11-G103*'S Curve Equation'!$B$12)*'S Curve Equation'!$B$10))+'S Curve Equation'!$B$13)*'S Curve Equation'!$B$14 -> 0.68730252 | H148: =(1/(1+EXP(('S Curve Equation'!$B$11-H103*'S Curve Equation'!$B$12)*'S Curve Equation'!$B$10))+'S Curve Equation'!$B$13)*'S Curve Equation'!$B$14 -> 0.6858833 | I148: =(1/(1+EXP(('S Curve Equation'!$B$11-I103*'S Curve Equation'!$B$12)*'S Curve Equation'!$B$10))+'S Curve Equation'!$B$13)*'S Curve Equation'!$B$14 -> 0.68438153 | ... AF148: =(1/(1+EXP(('S Curve Equation'!$B$11-AF103*'S Curve Equation'!$B$12)*'S Curve Equation'!$B$10))+'S Curve Equation'!$B$13)*'S Curve Equation'!$B$14 -> 0.65542325
A149: ISIC 21 | B149: =(1/(1+EXP(('S Curve Equation'!$B$11-B104*'S Curve Equation'!$B$12)*'S Curve Equation'!$B$10))+'S Curve Equation'!$B$13)*'S Curve Equation'!$B$14 -> 0.568 | C149: =(1/(1+EXP(('S Curve Equation'!$B$11-C104*'S Curve Equation'!$B$12)*'S Curve Equation'!$B$10))+'S Curve Equation'!$B$13)*'S Curve Equation'!$B$14 -> 0.56665394 | D149: =(1/(1+EXP(('S Curve Equation'!$B$11-D104*'S Curve Equation'!$B$12)*'S Curve Equation'!$B$10))+'S Curve Equation'!$B$13)*'S Curve Equation'!$B$14 -> 0.56524512 | E149: =(1/(1+EXP(('S Curve Equation'!$B$11-E104*'S Curve Equation'!$B$12)*'S Curve Equation'!$B$10))+'S Curve Equation'!$B$13)*'S Curve Equation'!$B$14 -> 0.56387049 | F149: =(1/(1+EXP(('S Curve Equation'!$B$11-F104*'S Curve Equation'!$B$12)*'S Curve Equation'!$B$10))+'S Curve Equation'!$B$13)*'S Curve Equation'!$B$14 -> 0.56251969 | G149: =(1/(1+EXP(('S Curve Equation'!$B$11-G104*'S Curve Equation'!$B$12)*'S Curve Equation'!$B$10))+'S Curve Equation'!$B$13)*'S Curve Equation'!$B$14 -> 0.56112358 | H149: =(1/(1+EXP(('S Curve Equation'!$B$11-H104*'S Curve Equation'!$B$12)*'S Curve Equation'!$B$10))+'S Curve Equation'!$B$13)*'S Curve Equation'!$B$14 -> 0.55967096 | I149: =(1/(1+EXP(('S Curve Equation'!$B$11-I104*'S Curve Equation'!$B$12)*'S Curve Equation'!$B$10))+'S Curve Equation'!$B$13)*'S Curve Equation'!$B$14 -> 0.55813646 | ... AF149: =(1/(1+EXP(('S Curve Equation'!$B$11-AF104*'S Curve Equation'!$B$12)*'S Curve Equation'!$B$10))+'S Curve Equation'!$B$13)*'S Curve Equation'!$B$14 -> 0.52905435
... A179: ISIC 97T98 | B179: =(1/(1+EXP(('S Curve Equation'!$B$11-B134*'S Curve Equation'!$B$12)*'S Curve Equation'!$B$10))+'S Curve Equation'!$B$13)*'S Curve Equation'!$B$14 -> 0.111 | C179: =(1/(1+EXP(('S Curve Equation'!$B$11-C134*'S Curve Equation'!$B$12)*'S Curve Equation'!$B$10))+'S Curve Equation'!$B$13)*'S Curve Equation'!$B$14 -> 0.11069751 | D179: =(1/(1+EXP(('S Curve Equation'!$B$11-D134*'S Curve Equation'!$B$12)*'S Curve Equation'!$B$10))+'S Curve Equation'!$B$13)*'S Curve Equation'!$B$14 -> 0.11038183 | E179: =(1/(1+EXP(('S Curve Equation'!$B$11-E134*'S Curve Equation'!$B$12)*'S Curve Equation'!$B$10))+'S Curve Equation'!$B$13)*'S Curve Equation'!$B$14 -> 0.11007471 | F179: =(1/(1+EXP(('S Curve Equation'!$B$11-F134*'S Curve Equation'!$B$12)*'S Curve Equation'!$B$10))+'S Curve Equation'!$B$13)*'S Curve Equation'!$B$14 -> 0.10977378 | G179: =(1/(1+EXP(('S Curve Equation'!$B$11-G134*'S Curve Equation'!$B$12)*'S Curve Equation'!$B$10))+'S Curve Equation'!$B$13)*'S Curve Equation'!$B$14 -> 0.10946363 | H179: =(1/(1+EXP(('S Curve Equation'!$B$11-H134*'S Curve Equation'!$B$12)*'S Curve Equation'!$B$10))+'S Curve Equation'!$B$13)*'S Curve Equation'!$B$14 -> 0.10914188 | I179: =(1/(1+EXP(('S Curve Equation'!$B$11-I134*'S Curve Equation'!$B$12)*'S Curve Equation'!$B$10))+'S Curve Equation'!$B$13)*'S Curve Equation'!$B$14 -> 0.10880304 | ... AF179: =(1/(1+EXP(('S Curve Equation'!$B$11-AF134*'S Curve Equation'!$B$12)*'S Curve Equation'!$B$10))+'S Curve Equation'!$B$13)*'S Curve Equation'!$B$14 -> 0.10257144
A181: Rescale to Sum to 1 Across Traits
B182: 2020 | C182: 2021 | D182: 2022 | E182: 2023 | F182: 2024 | G182: 2025 | H182: 2026 | I182: 2027 | J182: 2028 | K182: 2029 | L182: 2030 | M182: 2031 | N182: 2032 | O182: 2033 | P182: 2034 | Q182: 2035 | R182: 2036 | S182: 2037 | T182: 2038 | U182: 2039 | V182: 2040 | W182: 2041 | X182: 2042 | Y182: 2043 | Z182: 2044 | AA182: 2045 | AB182: 2046 | AC182: 2047 | AD182: 2048 | AE182: 2049 | AF182: 2050
A183: ISIC 01T03 | B183: =B138/SUM(B138,'Calculations female'!B138) -> 0.723 | C183: =C138/SUM(C138,'Calculations female'!C138) -> 0.72173385 | D183: =D138/SUM(D138,'Calculations female'!D138) -> 0.72040603 | E183: =E138/SUM(E138,'Calculations female'!E138) -> 0.71910781 | F183: =F138/SUM(F138,'Calculations female'!F138) -> 0.71782958 | G183: =G138/SUM(G138,'Calculations female'!G138) -> 0.71650586 | H183: =H138/SUM(H138,'Calculations female'!H138) -> 0.71512572 | I183: =I138/SUM(I138,'Calculations female'!I138) -> 0.71366466 | ... AF183: =AF138/SUM(AF138,'Calculations female'!AF138) -> 0.68536137
A184: ISIC 05 | B184: =B139/SUM(B139,'Calculations female'!B139) -> 0.899 | C184: =C139/SUM(C139,'Calculations female'!C139) -> 0.89825741 | D184: =D139/SUM(D139,'Calculations female'!D139) -> 0.89747616 | E184: =E139/SUM(E139,'Calculations female'!E139) -> 0.89670986 | F184: =F139/SUM(F139,'Calculations female'!F139) -> 0.89595297 | G184: =G139/SUM(G139,'Calculations female'!G139) -> 0.89516663 | H184: =H139/SUM(H139,'Calculations female'!H139) -> 0.89434405 | I184: =I139/SUM(I139,'Calculations female'!I139) -> 0.8934702 | ... AF184: =AF139/SUM(AF139,'Calculations female'!AF139) -> 0.87591701
A185: ISIC 06 | B185: =B140/SUM(B140,'Calculations female'!B140) -> 0.851 | C185: =C140/SUM(C140,'Calculations female'!C140) -> 0.85005869 | D185: =D140/SUM(D140,'Calculations female'!D140) -> 0.84906941 | E185: =E140/SUM(E140,'Calculations female'!E140) -> 0.84810007 | F185: =F140/SUM(F140,'Calculations female'!F140) -> 0.84714361 | G185: =G140/SUM(G140,'Calculations female'!G140) -> 0.84615097 | H185: =H140/SUM(H140,'Calculations female'!H140) -> 0.84511372 | I185: =I140/SUM(I140,'Calculations female'!I140) -> 0.84401306 | ... AF185: =AF140/SUM(AF140,'Calculations female'!AF140) -> 0.82216589
A186: ISIC 07T08 | B186: =B141/SUM(B141,'Calculations female'!B141) -> 0.893 | C186: =C141/SUM(C141,'Calculations female'!C141) -> 0.89222984 | D186: =D141/SUM(D141,'Calculations female'!D141) -> 0.8914197 | E186: =E141/SUM(E141,'Calculations female'!E141) -> 0.89062517 | F186: =F141/SUM(F141,'Calculations female'!F141) -> 0.88984051 | G186: =G141/SUM(G141,'Calculations female'!G141) -> 0.88902543 | H186: =H141/SUM(H141,'Calculations female'!H141) -> 0.88817292 | I186: =I141/SUM(I141,'Calculations female'!I141) -> 0.88726742 | ... AF186: =AF141/SUM(AF141,'Calculations female'!AF141) -> 0.86910788
A187: ISIC 09 | B187: =B142/SUM(B142,'Calculations female'!B142) -> 0.848 | C187: =C142/SUM(C142,'Calculations female'!C142) -> 0.84704784 | D187: =D142/SUM(D142,'Calculations female'!D142) -> 0.8460472 | E187: =E142/SUM(E142,'Calculations female'!E142) -> 0.8450668 | F187: =F142/SUM(F142,'Calculations female'!F142) -> 0.84409949 | G187: =G142/SUM(G142,'Calculations female'!G142) -> 0.84309565 | H187: =H142/SUM(H142,'Calculations female'!H142) -> 0.84204674 | I187: =I142/SUM(I142,'Calculations female'!I142) -> 0.8409338 | ... AF187: =AF142/SUM(AF142,'Calculations female'!AF142) -> 0.81885762
A188: ISIC 10T12 | B188: =B143/SUM(B143,'Calculations female'!B143) -> 0.60319417 | C188: =C143/SUM(C143,'Calculations female'!C143) -> 0.60184036 | D188: =D143/SUM(D143,'Calculations female'!D143) -> 0.60042284 | E188: =E143/SUM(E143,'Calculations female'!E143) -> 0.59903916 | F188: =F143/SUM(F143,'Calculations female'!F143) -> 0.5976789 | G188: =G143/SUM(G143,'Calculations female'!G143) -> 0.59627246 | H188: =H143/SUM(H143,'Calculations female'!H143) -> 0.59480846 | I188: =I143/SUM(I143,'Calculations female'!I143) -> 0.59326127 | ... AF188: =AF143/SUM(AF143,'Calculations female'!AF143) -> 0.56380811
A189: ISIC 13T15 | B189: =B144/SUM(B144,'Calculations female'!B144) -> 0.478 | C189: =C144/SUM(C144,'Calculations female'!C144) -> 0.4767343 | D189: =D144/SUM(D144,'Calculations female'!D144) -> 0.47541084 | E189: =E144/SUM(E144,'Calculations female'!E144) -> 0.47412073 | F189: =F144/SUM(F144,'Calculations female'!F144) -> 0.47285416 | G189: =G144/SUM(G144,'Calculations female'!G144) -> 0.47154633 | H189: =H144/SUM(H144,'Calculations female'!H144) -> 0.47018687 | I189: =I144/SUM(I144,'Calculations female'!I144) -> 0.46875224 | ... AF189: =AF144/SUM(AF144,'Calculations female'!AF144) -> 0.44183696
A190: ISIC 16 | B190: =B145/SUM(B145,'Calculations female'!B145) -> 0.834 | C190: =C145/SUM(C145,'Calculations female'!C145) -> 0.83299945 | D190: =D145/SUM(D145,'Calculations female'!D145) -> 0.83194824 | E190: =E145/SUM(E145,'Calculations female'!E145) -> 0.83091856 | F190: =F145/SUM(F145,'Calculations female'!F145) -> 0.82990291 | G190: =G145/SUM(G145,'Calculations female'!G145) -> 0.82884918 | H190: =H145/SUM(H145,'Calculations female'!H145) -> 0.82774845 | I190: =I145/SUM(I145,'Calculations female'!I145) -> 0.82658087 | ... AF190: =AF145/SUM(AF145,'Calculations female'!AF145) -> 0.80349172
A191: ISIC 17T18 | B191: =B146/SUM(B146,'Calculations female'!B146) -> 0.719 | C191: =C146/SUM(C146,'Calculations female'!C146) -> 0.71772783 | D191: =D146/SUM(D146,'Calculations female'!D146) -> 0.71639377 | E191: =E146/SUM(E146,'Calculations female'!E146) -> 0.71508953 | F191: =F146/SUM(F146,'Calculations female'!F146) -> 0.71380545 | G191: =G146/SUM(G146,'Calculations female'!G146) -> 0.71247575 | H191: =H146/SUM(H146,'Calculations female'!H146) -> 0.71108945 | I191: =I146/SUM(I146,'Calculations female'!I146) -> 0.70962196 | ... AF191: =AF146/SUM(AF146,'Calculations female'!AF146) -> 0.6812127
A192: ISIC 19 | B192: =B147/SUM(B147,'Calculations female'!B147) -> 0.822 | C192: =C147/SUM(C147,'Calculations female'!C147) -> 0.82096085 | D192: =D147/SUM(D147,'Calculations female'!D147) -> 0.81986932 | E192: =E147/SUM(E147,'Calculations female'!E147) -> 0.81880041 | F192: =F147/SUM(F147,'Calculations female'!F147) -> 0.81774627 | G192: =G147/SUM(G147,'Calculations female'!G147) -> 0.81665286 | H192: =H147/SUM(H147,'Calculations female'!H147) -> 0.81551095 | I192: =I147/SUM(I147,'Calculations female'!I147) -> 0.81429997 | ... AF192: =AF147/SUM(AF147,'Calculations female'!AF147) -> 0.79041299
A193: ISIC 20 | B193: =B148/SUM(B148,'Calculations female'!B148) -> 0.69398889 | C193: =C148/SUM(C148,'Calculations female'!C148) -> 0.69268417 | D193: =D148/SUM(D148,'Calculations female'!D148) -> 0.69131647 | E193: =E148/SUM(E148,'Calculations female'!E148) -> 0.68997983 | F193: =F148/SUM(F148,'Calculations female'!F148) -> 0.6886643 | G193: =G148/SUM(G148,'Calculations female'!G148) -> 0.68730252 | H193: =H148/SUM(H148,'Calculations female'!H148) -> 0.6858833 | I193: =I148/SUM(I148,'Calculations female'!I148) -> 0.68438153 | ... AF193: =AF148/SUM(AF148,'Calculations female'!AF148) -> 0.65542325
A194: ISIC 21 | B194: =B149/SUM(B149,'Calculations female'!B149) -> 0.568 | C194: =C149/SUM(C149,'Calculations female'!C149) -> 0.56665394 | D194: =D149/SUM(D149,'Calculations female'!D149) -> 0.56524512 | E194: =E149/SUM(E149,'Calculations female'!E149) -> 0.56387049 | F194: =F149/SUM(F149,'Calculations female'!F149) -> 0.56251969 | G194: =G149/SUM(G149,'Calculations female'!G149) -> 0.56112358 | H194: =H149/SUM(H149,'Calculations female'!H149) -> 0.55967096 | I194: =I149/SUM(I149,'Calculations female'!I149) -> 0.55813646 | ... AF194: =AF149/SUM(AF149,'Calculations female'!AF149) -> 0.52905435
... A224: ISIC 97T98 | B224: =B179/SUM(B179,'Calculations female'!B179) -> 0.111 | C224: =C179/SUM(C179,'Calculations female'!C179) -> 0.11069751 | D224: =D179/SUM(D179,'Calculations female'!D179) -> 0.11038183 | E224: =E179/SUM(E179,'Calculations female'!E179) -> 0.11007471 | F224: =F179/SUM(F179,'Calculations female'!F179) -> 0.10977378 | G224: =G179/SUM(G179,'Calculations female'!G179) -> 0.10946363 | H224: =H179/SUM(H179,'Calculations female'!H179) -> 0.10914188 | I224: =I179/SUM(I179,'Calculations female'!I179) -> 0.10880304 | ... AF224: =AF179/SUM(AF179,'Calculations female'!AF179) -> 0.10257144

Sheet Calculations female
A1: Fraction of Workers with This Demographic Trait in the Year for Which We Have Present-Day Data Disaggregated by ISIC Code
B2: 2020
A3: ISIC 01T03 | B3: =INDEX('BLS CPS T18'!C:C,MATCH($A3,'BLS CPS T18'!H:H,0))/100 -> 0.277
A4: ISIC 05 | B4: =INDEX('BLS CPS T18'!C:C,MATCH($A4,'BLS CPS T18'!H:H,0))/100 -> 0.101
A5: ISIC 06 | B5: =INDEX('BLS CPS T18'!C:C,MATCH($A5,'BLS CPS T18'!H:H,0))/100 -> 0.149
A6: ISIC 07T08 | B6: =INDEX('BLS CPS T18'!C:C,MATCH($A6,'BLS CPS T18'!H:H,0))/100 -> 0.107
A7: ISIC 09 | B7: =INDEX('BLS CPS T18'!C:C,MATCH($A7,'BLS CPS T18'!H:H,0))/100 -> 0.152
A8: ISIC 10T12 | B8: =INDEX('BLS CPS T18'!C:C,MATCH($A8,'BLS CPS T18'!H:H,0))/100 -> 0.39680583
A9: ISIC 13T15 | B9: =INDEX('BLS CPS T18'!C:C,MATCH($A9,'BLS CPS T18'!H:H,0))/100 -> 0.522
A10: ISIC 16 | B10: =INDEX('BLS CPS T18'!C:C,MATCH($A10,'BLS CPS T18'!H:H,0))/100 -> 0.166
A11: ISIC 17T18 | B11: =INDEX('BLS CPS T18'!C:C,MATCH($A11,'BLS CPS T18'!H:H,0))/100 -> 0.281
A12: ISIC 19 | B12: =INDEX('BLS CPS T18'!C:C,MATCH($A12,'BLS CPS T18'!H:H,0))/100 -> 0.178
A13: ISIC 20 | B13: =INDEX('BLS CPS T18'!C:C,MATCH($A13,'BLS CPS T18'!H:H,0))/100 -> 0.30601111
A14: ISIC 21 | B14: =INDEX('BLS CPS T18'!C:C,MATCH($A14,'BLS CPS T18'!H:H,0))/100 -> 0.432
... A44: ISIC 97T98 | B44: =INDEX('BLS CPS T18'!C:C,MATCH($A44,'BLS CPS T18'!H:H,0))/100 -> 0.889
A46: Reverse sigmoid (i.e. convert from Y value to X value)
B47: 2020
A48: ISIC 01T03 | B48: =('S Curve Equation'!$B$11-(LN(1/((B3/'S Curve Equation'!$B$14)-'S Curve Equation'!$B$13)-1)/'S Curve Equation'!$B$10))/'S Curve Equation'!$B$12 -> 0.39610494
A49: ISIC 05 | B49: =('S Curve Equation'!$B$11-(LN(1/((B4/'S Curve Equation'!$B$14)-'S Curve Equation'!$B$13)-1)/'S Curve Equation'!$B$10))/'S Curve Equation'!$B$12 -> 0.26743141
A50: ISIC 06 | B50: =('S Curve Equation'!$B$11-(LN(1/((B5/'S Curve Equation'!$B$14)-'S Curve Equation'!$B$13)-1)/'S Curve Equation'!$B$10))/'S Curve Equation'!$B$12 -> 0.31301194
A51: ISIC 07T08 | B51: =('S Curve Equation'!$B$11-(LN(1/((B6/'S Curve Equation'!$B$14)-'S Curve Equation'!$B$13)-1)/'S Curve Equation'!$B$10))/'S Curve Equation'!$B$12 -> 0.27395289
A52: ISIC 09 | B52: =('S Curve Equation'!$B$11-(LN(1/((B7/'S Curve Equation'!$B$14)-'S Curve Equation'!$B$13)-1)/'S Curve Equation'!$B$10))/'S Curve Equation'!$B$12 -> 0.31546027
A53: ISIC 10T12 | B53: =('S Curve Equation'!$B$11-(LN(1/((B8/'S Curve Equation'!$B$14)-'S Curve Equation'!$B$13)-1)/'S Curve Equation'!$B$10))/'S Curve Equation'!$B$12 -> 0.45451917
A54: ISIC 13T15 | B54: =('S Curve Equation'!$B$11-(LN(1/((B9/'S Curve Equation'!$B$14)-'S Curve Equation'!$B$13)-1)/'S Curve Equation'!$B$10))/'S Curve Equation'!$B$12 -> 0.50956883
A55: ISIC 16 | B55: =('S Curve Equation'!$B$11-(LN(1/((B10/'S Curve Equation'!$B$14)-'S Curve Equation'!$B$13)-1)/'S Curve Equation'!$B$10))/'S Curve Equation'!$B$12 -> 0.3264285
A56: ISIC 17T18 | B56: =('S Curve Equation'!$B$11-(LN(1/((B11/'S Curve Equation'!$B$14)-'S Curve Equation'!$B$13)-1)/'S Curve Equation'!$B$10))/'S Curve Equation'!$B$12 -> 0.39824327
A57: ISIC 19 | B57: =('S Curve Equation'!$B$11-(LN(1/((B12/'S Curve Equation'!$B$14)-'S Curve Equation'!$B$13)-1)/'S Curve Equation'!$B$10))/'S Curve Equation'!$B$12 -> 0.33529655
A58: ISIC 20 | B58: =('S Curve Equation'!$B$11-(LN(1/((B13/'S Curve Equation'!$B$14)-'S Curve Equation'!$B$13)-1)/'S Curve Equation'!$B$10))/'S Curve Equation'!$B$12 -> 0.41124005
A59: ISIC 21 | B59: =('S Curve Equation'!$B$11-(LN(1/((B14/'S Curve Equation'!$B$14)-'S Curve Equation'!$B$13)-1)/'S Curve Equation'!$B$10))/'S Curve Equation'!$B$12 -> 0.47026569
... A89: ISIC 97T98 | B89: =('S Curve Equation'!$B$11-(LN(1/((B44/'S Curve Equation'!$B$14)-'S Curve Equation'!$B$13)-1)/'S Curve Equation'!$B$10))/'S Curve Equation'!$B$12 -> 0.72185766
A91: Add or subtract linear segment (along X axis) - i.e. moving a percentage of the distance from 2020 value to 100% or to 0%
B92: 2020 | C92: 2021 | D92: 2022 | E92: 2023 | F92: 2024 | G92: 2025 | H92: 2026 | I92: 2027 | J92: 2028 | K92: 2029 | L92: 2030 | M92: 2031 | N92: 2032 | O92: 2033 | P92: 2034 | Q92: 2035 | R92: 2036 | S92: 2037 | T92: 2038 | U92: 2039 | V92: 2040 | W92: 2041 | X92: 2042 | Y92: 2043 | Z92: 2044 | AA92: 2045 | AB92: 2046 | AC92: 2047 | AD92: 2048 | AE92: 2049 | AF92: 2050
A93: ISIC 01T03 | B93: =B48 -> 0.39610494 | C93: =IF('LF Projected Ratios'!D$34>=0,$B93+(1-$B93)*'LF Projected Ratios'!D$34,$B93*(1+'LF Projected Ratios'!D$34)) -> 0.39678373 | D93: =IF('LF Projected Ratios'!E$34>=0,$B93+(1-$B93)*'LF Projected Ratios'!E$34,$B93*(1+'LF Projected Ratios'!E$34)) -> 0.39749365 | E93: =IF('LF Projected Ratios'!F$34>=0,$B93+(1-$B93)*'LF Projected Ratios'!F$34,$B93*(1+'LF Projected Ratios'!F$34)) -> 0.39818586 | F93: =IF('LF Projected Ratios'!G$34>=0,$B93+(1-$B93)*'LF Projected Ratios'!G$34,$B93*(1+'LF Projected Ratios'!G$34)) -> 0.39886562 | G93: =IF('LF Projected Ratios'!H$34>=0,$B93+(1-$B93)*'LF Projected Ratios'!H$34,$B93*(1+'LF Projected Ratios'!H$34)) -> 0.3995677 | H93: =IF('LF Projected Ratios'!I$34>=0,$B93+(1-$B93)*'LF Projected Ratios'!I$34,$B93*(1+'LF Projected Ratios'!I$34)) -> 0.40029771 | I93: =IF('LF Projected Ratios'!J$34>=0,$B93+(1-$B93)*'LF Projected Ratios'!J$34,$B93*(1+'LF Projected Ratios'!J$34)) -> 0.40106834 | J93: =IF('LF Projected Ratios'!K$34>=0,$B93+(1-$B93)*'LF Projected Ratios'!K$34,$B93*(1+'LF Projected Ratios'!K$34)) -> 0.40187258 | ... AF93: =IF('LF Projected Ratios'!AG$34>=0,$B93+(1-$B93)*'LF Projected Ratios'!AG$34,$B93*(1+'LF Projected Ratios'!AG$34)) -> 0.41558906
A94: ISIC 05 | B94: =B49 -> 0.26743141 | C94: =IF('LF Projected Ratios'!D$34>=0,$B94+(1-$B94)*'LF Projected Ratios'!D$34,$B94*(1+'LF Projected Ratios'!D$34)) -> 0.26825483 | D94: =IF('LF Projected Ratios'!E$34>=0,$B94+(1-$B94)*'LF Projected Ratios'!E$34,$B94*(1+'LF Projected Ratios'!E$34)) -> 0.26911602 | E94: =IF('LF Projected Ratios'!F$34>=0,$B94+(1-$B94)*'LF Projected Ratios'!F$34,$B94*(1+'LF Projected Ratios'!F$34)) -> 0.26995572 | F94: =IF('LF Projected Ratios'!G$34>=0,$B94+(1-$B94)*'LF Projected Ratios'!G$34,$B94*(1+'LF Projected Ratios'!G$34)) -> 0.27078031 | G94: =IF('LF Projected Ratios'!H$34>=0,$B94+(1-$B94)*'LF Projected Ratios'!H$34,$B94*(1+'LF Projected Ratios'!H$34)) -> 0.27163199 | H94: =IF('LF Projected Ratios'!I$34>=0,$B94+(1-$B94)*'LF Projected Ratios'!I$34,$B94*(1+'LF Projected Ratios'!I$34)) -> 0.27251754 | I94: =IF('LF Projected Ratios'!J$34>=0,$B94+(1-$B94)*'LF Projected Ratios'!J$34,$B94*(1+'LF Projected Ratios'!J$34)) -> 0.27345237 | J94: =IF('LF Projected Ratios'!K$34>=0,$B94+(1-$B94)*'LF Projected Ratios'!K$34,$B94*(1+'LF Projected Ratios'!K$34)) -> 0.27442797 | ... AF94: =IF('LF Projected Ratios'!AG$34>=0,$B94+(1-$B94)*'LF Projected Ratios'!AG$34,$B94*(1+'LF Projected Ratios'!AG$34)) -> 0.29106706
A95: ISIC 06 | B95: =B50 -> 0.31301194 | C95: =IF('LF Projected Ratios'!D$34>=0,$B95+(1-$B95)*'LF Projected Ratios'!D$34,$B95*(1+'LF Projected Ratios'!D$34)) -> 0.31378413 | D95: =IF('LF Projected Ratios'!E$34>=0,$B95+(1-$B95)*'LF Projected Ratios'!E$34,$B95*(1+'LF Projected Ratios'!E$34)) -> 0.31459174 | E95: =IF('LF Projected Ratios'!F$34>=0,$B95+(1-$B95)*'LF Projected Ratios'!F$34,$B95*(1+'LF Projected Ratios'!F$34)) -> 0.3153792 | F95: =IF('LF Projected Ratios'!G$34>=0,$B95+(1-$B95)*'LF Projected Ratios'!G$34,$B95*(1+'LF Projected Ratios'!G$34)) -> 0.31615248 | G95: =IF('LF Projected Ratios'!H$34>=0,$B95+(1-$B95)*'LF Projected Ratios'!H$34,$B95*(1+'LF Projected Ratios'!H$34)) -> 0.31695117 | H95: =IF('LF Projected Ratios'!I$34>=0,$B95+(1-$B95)*'LF Projected Ratios'!I$34,$B95*(1+'LF Projected Ratios'!I$34)) -> 0.31778162 | I95: =IF('LF Projected Ratios'!J$34>=0,$B95+(1-$B95)*'LF Projected Ratios'!J$34,$B95*(1+'LF Projected Ratios'!J$34)) -> 0.31865828 | J95: =IF('LF Projected Ratios'!K$34>=0,$B95+(1-$B95)*'LF Projected Ratios'!K$34,$B95*(1+'LF Projected Ratios'!K$34)) -> 0.31957318 | ... AF95: =IF('LF Projected Ratios'!AG$34>=0,$B95+(1-$B95)*'LF Projected Ratios'!AG$34,$B95*(1+'LF Projected Ratios'!AG$34)) -> 0.33517699
A96: ISIC 07T08 | B96: =B51 -> 0.27395289 | C96: =IF('LF Projected Ratios'!D$34>=0,$B96+(1-$B96)*'LF Projected Ratios'!D$34,$B96*(1+'LF Projected Ratios'!D$34)) -> 0.27476898 | D96: =IF('LF Projected Ratios'!E$34>=0,$B96+(1-$B96)*'LF Projected Ratios'!E$34,$B96*(1+'LF Projected Ratios'!E$34)) -> 0.27562251 | E96: =IF('LF Projected Ratios'!F$34>=0,$B96+(1-$B96)*'LF Projected Ratios'!F$34,$B96*(1+'LF Projected Ratios'!F$34)) -> 0.27645473 | F96: =IF('LF Projected Ratios'!G$34>=0,$B96+(1-$B96)*'LF Projected Ratios'!G$34,$B96*(1+'LF Projected Ratios'!G$34)) -> 0.27727198 | G96: =IF('LF Projected Ratios'!H$34>=0,$B96+(1-$B96)*'LF Projected Ratios'!H$34,$B96*(1+'LF Projected Ratios'!H$34)) -> 0.27811608 | H96: =IF('LF Projected Ratios'!I$34>=0,$B96+(1-$B96)*'LF Projected Ratios'!I$34,$B96*(1+'LF Projected Ratios'!I$34)) -> 0.27899375 | I96: =IF('LF Projected Ratios'!J$34>=0,$B96+(1-$B96)*'LF Projected Ratios'!J$34,$B96*(1+'LF Projected Ratios'!J$34)) -> 0.27992025 | J96: =IF('LF Projected Ratios'!K$34>=0,$B96+(1-$B96)*'LF Projected Ratios'!K$34,$B96*(1+'LF Projected Ratios'!K$34)) -> 0.28088717 | ... AF96: =IF('LF Projected Ratios'!AG$34>=0,$B96+(1-$B96)*'LF Projected Ratios'!AG$34,$B96*(1+'LF Projected Ratios'!AG$34)) -> 0.29737814
A97: ISIC 09 | B97: =B52 -> 0.31546027 | C97: =IF('LF Projected Ratios'!D$34>=0,$B97+(1-$B97)*'LF Projected Ratios'!D$34,$B97*(1+'LF Projected Ratios'!D$34)) -> 0.31622971 | D97: =IF('LF Projected Ratios'!E$34>=0,$B97+(1-$B97)*'LF Projected Ratios'!E$34,$B97*(1+'LF Projected Ratios'!E$34)) -> 0.31703444 | E97: =IF('LF Projected Ratios'!F$34>=0,$B97+(1-$B97)*'LF Projected Ratios'!F$34,$B97*(1+'LF Projected Ratios'!F$34)) -> 0.31781909 | F97: =IF('LF Projected Ratios'!G$34>=0,$B97+(1-$B97)*'LF Projected Ratios'!G$34,$B97*(1+'LF Projected Ratios'!G$34)) -> 0.31858961 | G97: =IF('LF Projected Ratios'!H$34>=0,$B97+(1-$B97)*'LF Projected Ratios'!H$34,$B97*(1+'LF Projected Ratios'!H$34)) -> 0.31938545 | H97: =IF('LF Projected Ratios'!I$34>=0,$B97+(1-$B97)*'LF Projected Ratios'!I$34,$B97*(1+'LF Projected Ratios'!I$34)) -> 0.32021295 | I97: =IF('LF Projected Ratios'!J$34>=0,$B97+(1-$B97)*'LF Projected Ratios'!J$34,$B97*(1+'LF Projected Ratios'!J$34)) -> 0.32108648 | J97: =IF('LF Projected Ratios'!K$34>=0,$B97+(1-$B97)*'LF Projected Ratios'!K$34,$B97*(1+'LF Projected Ratios'!K$34)) -> 0.32199812 | ... AF97: =IF('LF Projected Ratios'!AG$34>=0,$B97+(1-$B97)*'LF Projected Ratios'!AG$34,$B97*(1+'LF Projected Ratios'!AG$34)) -> 0.33754632
A98: ISIC 10T12 | B98: =B53 -> 0.45451917 | C98: =IF('LF Projected Ratios'!D$34>=0,$B98+(1-$B98)*'LF Projected Ratios'!D$34,$B98*(1+'LF Projected Ratios'!D$34)) -> 0.45513231 | D98: =IF('LF Projected Ratios'!E$34>=0,$B98+(1-$B98)*'LF Projected Ratios'!E$34,$B98*(1+'LF Projected Ratios'!E$34)) -> 0.45577356 | E98: =IF('LF Projected Ratios'!F$34>=0,$B98+(1-$B98)*'LF Projected Ratios'!F$34,$B98*(1+'LF Projected Ratios'!F$34)) -> 0.45639882 | F98: =IF('LF Projected Ratios'!G$34>=0,$B98+(1-$B98)*'LF Projected Ratios'!G$34,$B98*(1+'LF Projected Ratios'!G$34)) -> 0.45701282 | G98: =IF('LF Projected Ratios'!H$34>=0,$B98+(1-$B98)*'LF Projected Ratios'!H$34,$B98*(1+'LF Projected Ratios'!H$34)) -> 0.45764699 | H98: =IF('LF Projected Ratios'!I$34>=0,$B98+(1-$B98)*'LF Projected Ratios'!I$34,$B98*(1+'LF Projected Ratios'!I$34)) -> 0.45830638 | I98: =IF('LF Projected Ratios'!J$34>=0,$B98+(1-$B98)*'LF Projected Ratios'!J$34,$B98*(1+'LF Projected Ratios'!J$34)) -> 0.45900247 | J98: =IF('LF Projected Ratios'!K$34>=0,$B98+(1-$B98)*'LF Projected Ratios'!K$34,$B98*(1+'LF Projected Ratios'!K$34)) -> 0.45972891 | ... AF98: =IF('LF Projected Ratios'!AG$34>=0,$B98+(1-$B98)*'LF Projected Ratios'!AG$34,$B98*(1+'LF Projected Ratios'!AG$34)) -> 0.47211862
A99: ISIC 13T15 | B99: =B54 -> 0.50956883 | C99: =IF('LF Projected Ratios'!D$34>=0,$B99+(1-$B99)*'LF Projected Ratios'!D$34,$B99*(1+'LF Projected Ratios'!D$34)) -> 0.51012009 | D99: =IF('LF Projected Ratios'!E$34>=0,$B99+(1-$B99)*'LF Projected Ratios'!E$34,$B99*(1+'LF Projected Ratios'!E$34)) -> 0.51069663 | E99: =IF('LF Projected Ratios'!F$34>=0,$B99+(1-$B99)*'LF Projected Ratios'!F$34,$B99*(1+'LF Projected Ratios'!F$34)) -> 0.51125878 | F99: =IF('LF Projected Ratios'!G$34>=0,$B99+(1-$B99)*'LF Projected Ratios'!G$34,$B99*(1+'LF Projected Ratios'!G$34)) -> 0.51181082 | G99: =IF('LF Projected Ratios'!H$34>=0,$B99+(1-$B99)*'LF Projected Ratios'!H$34,$B99*(1+'LF Projected Ratios'!H$34)) -> 0.51238099 | H99: =IF('LF Projected Ratios'!I$34>=0,$B99+(1-$B99)*'LF Projected Ratios'!I$34,$B99*(1+'LF Projected Ratios'!I$34)) -> 0.51297384 | I99: =IF('LF Projected Ratios'!J$34>=0,$B99+(1-$B99)*'LF Projected Ratios'!J$34,$B99*(1+'LF Projected Ratios'!J$34)) -> 0.51359967 | J99: =IF('LF Projected Ratios'!K$34>=0,$B99+(1-$B99)*'LF Projected Ratios'!K$34,$B99*(1+'LF Projected Ratios'!K$34)) -> 0.51425281 | ... AF99: =IF('LF Projected Ratios'!AG$34>=0,$B99+(1-$B99)*'LF Projected Ratios'!AG$34,$B99*(1+'LF Projected Ratios'!AG$34)) -> 0.52539215
A100: ISIC 16 | B100: =B55 -> 0.3264285 | C100: =IF('LF Projected Ratios'!D$34>=0,$B100+(1-$B100)*'LF Projected Ratios'!D$34,$B100*(1+'LF Projected Ratios'!D$34)) -> 0.3271856 | D100: =IF('LF Projected Ratios'!E$34>=0,$B100+(1-$B100)*'LF Projected Ratios'!E$34,$B100*(1+'LF Projected Ratios'!E$34)) -> 0.32797744 | E100: =IF('LF Projected Ratios'!F$34>=0,$B100+(1-$B100)*'LF Projected Ratios'!F$34,$B100*(1+'LF Projected Ratios'!F$34)) -> 0.32874952 | F100: =IF('LF Projected Ratios'!G$34>=0,$B100+(1-$B100)*'LF Projected Ratios'!G$34,$B100*(1+'LF Projected Ratios'!G$34)) -> 0.3295077 | G100: =IF('LF Projected Ratios'!H$34>=0,$B100+(1-$B100)*'LF Projected Ratios'!H$34,$B100*(1+'LF Projected Ratios'!H$34)) -> 0.33029078 | H100: =IF('LF Projected Ratios'!I$34>=0,$B100+(1-$B100)*'LF Projected Ratios'!I$34,$B100*(1+'LF Projected Ratios'!I$34)) -> 0.33110502 | I100: =IF('LF Projected Ratios'!J$34>=0,$B100+(1-$B100)*'LF Projected Ratios'!J$34,$B100*(1+'LF Projected Ratios'!J$34)) -> 0.33196456 | J100: =IF('LF Projected Ratios'!K$34>=0,$B100+(1-$B100)*'LF Projected Ratios'!K$34,$B100*(1+'LF Projected Ratios'!K$34)) -> 0.33286159 | ... AF100: =IF('LF Projected Ratios'!AG$34>=0,$B100+(1-$B100)*'LF Projected Ratios'!AG$34,$B100*(1+'LF Projected Ratios'!AG$34)) -> 0.34816067
A101: ISIC 17T18 | B101: =B56 -> 0.39824327 | C101: =IF('LF Projected Ratios'!D$34>=0,$B101+(1-$B101)*'LF Projected Ratios'!D$34,$B101*(1+'LF Projected Ratios'!D$34)) -> 0.39891965 | D101: =IF('LF Projected Ratios'!E$34>=0,$B101+(1-$B101)*'LF Projected Ratios'!E$34,$B101*(1+'LF Projected Ratios'!E$34)) -> 0.39962707 | E101: =IF('LF Projected Ratios'!F$34>=0,$B101+(1-$B101)*'LF Projected Ratios'!F$34,$B101*(1+'LF Projected Ratios'!F$34)) -> 0.40031682 | F101: =IF('LF Projected Ratios'!G$34>=0,$B101+(1-$B101)*'LF Projected Ratios'!G$34,$B101*(1+'LF Projected Ratios'!G$34)) -> 0.40099417 | G101: =IF('LF Projected Ratios'!H$34>=0,$B101+(1-$B101)*'LF Projected Ratios'!H$34,$B101*(1+'LF Projected Ratios'!H$34)) -> 0.40169377 | H101: =IF('LF Projected Ratios'!I$34>=0,$B101+(1-$B101)*'LF Projected Ratios'!I$34,$B101*(1+'LF Projected Ratios'!I$34)) -> 0.40242119 | I101: =IF('LF Projected Ratios'!J$34>=0,$B101+(1-$B101)*'LF Projected Ratios'!J$34,$B101*(1+'LF Projected Ratios'!J$34)) -> 0.40318909 | J101: =IF('LF Projected Ratios'!K$34>=0,$B101+(1-$B101)*'LF Projected Ratios'!K$34,$B101*(1+'LF Projected Ratios'!K$34)) -> 0.40399048 | ... AF101: =IF('LF Projected Ratios'!AG$34>=0,$B101+(1-$B101)*'LF Projected Ratios'!AG$34,$B101*(1+'LF Projected Ratios'!AG$34)) -> 0.4176584
A102: ISIC 19 | B102: =B57 -> 0.33529655 | C102: =IF('LF Projected Ratios'!D$34>=0,$B102+(1-$B102)*'LF Projected Ratios'!D$34,$B102*(1+'LF Projected Ratios'!D$34)) -> 0.33604369 | D102: =IF('LF Projected Ratios'!E$34>=0,$B102+(1-$B102)*'LF Projected Ratios'!E$34,$B102*(1+'LF Projected Ratios'!E$34)) -> 0.33682511 | E102: =IF('LF Projected Ratios'!F$34>=0,$B102+(1-$B102)*'LF Projected Ratios'!F$34,$B102*(1+'LF Projected Ratios'!F$34)) -> 0.33758702 | F102: =IF('LF Projected Ratios'!G$34>=0,$B102+(1-$B102)*'LF Projected Ratios'!G$34,$B102*(1+'LF Projected Ratios'!G$34)) -> 0.33833522 | G102: =IF('LF Projected Ratios'!H$34>=0,$B102+(1-$B102)*'LF Projected Ratios'!H$34,$B102*(1+'LF Projected Ratios'!H$34)) -> 0.33910799 | H102: =IF('LF Projected Ratios'!I$34>=0,$B102+(1-$B102)*'LF Projected Ratios'!I$34,$B102*(1+'LF Projected Ratios'!I$34)) -> 0.33991151 | I102: =IF('LF Projected Ratios'!J$34>=0,$B102+(1-$B102)*'LF Projected Ratios'!J$34,$B102*(1+'LF Projected Ratios'!J$34)) -> 0.34075973 | J102: =IF('LF Projected Ratios'!K$34>=0,$B102+(1-$B102)*'LF Projected Ratios'!K$34,$B102*(1+'LF Projected Ratios'!K$34)) -> 0.34164496 | ... AF102: =IF('LF Projected Ratios'!AG$34>=0,$B102+(1-$B102)*'LF Projected Ratios'!AG$34,$B102*(1+'LF Projected Ratios'!AG$34)) -> 0.3567426
A103: ISIC 20 | B103: =B58 -> 0.41124005 | C103: =IF('LF Projected Ratios'!D$34>=0,$B103+(1-$B103)*'LF Projected Ratios'!D$34,$B103*(1+'LF Projected Ratios'!D$34)) -> 0.41190182 | D103: =IF('LF Projected Ratios'!E$34>=0,$B103+(1-$B103)*'LF Projected Ratios'!E$34,$B103*(1+'LF Projected Ratios'!E$34)) -> 0.41259396 | E103: =IF('LF Projected Ratios'!F$34>=0,$B103+(1-$B103)*'LF Projected Ratios'!F$34,$B103*(1+'LF Projected Ratios'!F$34)) -> 0.41326882 | F103: =IF('LF Projected Ratios'!G$34>=0,$B103+(1-$B103)*'LF Projected Ratios'!G$34,$B103*(1+'LF Projected Ratios'!G$34)) -> 0.41393154 | G103: =IF('LF Projected Ratios'!H$34>=0,$B103+(1-$B103)*'LF Projected Ratios'!H$34,$B103*(1+'LF Projected Ratios'!H$34)) -> 0.41461602 | H103: =IF('LF Projected Ratios'!I$34>=0,$B103+(1-$B103)*'LF Projected Ratios'!I$34,$B103*(1+'LF Projected Ratios'!I$34)) -> 0.41532774 | I103: =IF('LF Projected Ratios'!J$34>=0,$B103+(1-$B103)*'LF Projected Ratios'!J$34,$B103*(1+'LF Projected Ratios'!J$34)) -> 0.41607905 | J103: =IF('LF Projected Ratios'!K$34>=0,$B103+(1-$B103)*'LF Projected Ratios'!K$34,$B103*(1+'LF Projected Ratios'!K$34)) -> 0.41686313 | ... AF103: =IF('LF Projected Ratios'!AG$34>=0,$B103+(1-$B103)*'LF Projected Ratios'!AG$34,$B103*(1+'LF Projected Ratios'!AG$34)) -> 0.43023585
A104: ISIC 21 | B104: =B59 -> 0.47026569 | C104: =IF('LF Projected Ratios'!D$34>=0,$B104+(1-$B104)*'LF Projected Ratios'!D$34,$B104*(1+'LF Projected Ratios'!D$34)) -> 0.47086112 | D104: =IF('LF Projected Ratios'!E$34>=0,$B104+(1-$B104)*'LF Projected Ratios'!E$34,$B104*(1+'LF Projected Ratios'!E$34)) -> 0.47148387 | E104: =IF('LF Projected Ratios'!F$34>=0,$B104+(1-$B104)*'LF Projected Ratios'!F$34,$B104*(1+'LF Projected Ratios'!F$34)) -> 0.47209107 | F104: =IF('LF Projected Ratios'!G$34>=0,$B104+(1-$B104)*'LF Projected Ratios'!G$34,$B104*(1+'LF Projected Ratios'!G$34)) -> 0.47268735 | G104: =IF('LF Projected Ratios'!H$34>=0,$B104+(1-$B104)*'LF Projected Ratios'!H$34,$B104*(1+'LF Projected Ratios'!H$34)) -> 0.47330321 | H104: =IF('LF Projected Ratios'!I$34>=0,$B104+(1-$B104)*'LF Projected Ratios'!I$34,$B104*(1+'LF Projected Ratios'!I$34)) -> 0.47394357 | I104: =IF('LF Projected Ratios'!J$34>=0,$B104+(1-$B104)*'LF Projected Ratios'!J$34,$B104*(1+'LF Projected Ratios'!J$34)) -> 0.47461956 | J104: =IF('LF Projected Ratios'!K$34>=0,$B104+(1-$B104)*'LF Projected Ratios'!K$34,$B104*(1+'LF Projected Ratios'!K$34)) -> 0.47532504 | ... AF104: =IF('LF Projected Ratios'!AG$34>=0,$B104+(1-$B104)*'LF Projected Ratios'!AG$34,$B104*(1+'LF Projected Ratios'!AG$34)) -> 0.48735708
... A134: ISIC 97T98 | B134: =B89 -> 0.72185766 | C134: =IF('LF Projected Ratios'!D$34>=0,$B134+(1-$B134)*'LF Projected Ratios'!D$34,$B134*(1+'LF Projected Ratios'!D$34)) -> 0.7221703 | D134: =IF('LF Projected Ratios'!E$34>=0,$B134+(1-$B134)*'LF Projected Ratios'!E$34,$B134*(1+'LF Projected Ratios'!E$34)) -> 0.72249728 | E134: =IF('LF Projected Ratios'!F$34>=0,$B134+(1-$B134)*'LF Projected Ratios'!F$34,$B134*(1+'LF Projected Ratios'!F$34)) -> 0.7228161 | F134: =IF('LF Projected Ratios'!G$34>=0,$B134+(1-$B134)*'LF Projected Ratios'!G$34,$B134*(1+'LF Projected Ratios'!G$34)) -> 0.72312918 | G134: =IF('LF Projected Ratios'!H$34>=0,$B134+(1-$B134)*'LF Projected Ratios'!H$34,$B134*(1+'LF Projected Ratios'!H$34)) -> 0.72345254 | H134: =IF('LF Projected Ratios'!I$34>=0,$B134+(1-$B134)*'LF Projected Ratios'!I$34,$B134*(1+'LF Projected Ratios'!I$34)) -> 0.72378877 | I134: =IF('LF Projected Ratios'!J$34>=0,$B134+(1-$B134)*'LF Projected Ratios'!J$34,$B134*(1+'LF Projected Ratios'!J$34)) -> 0.72414371 | J134: =IF('LF Projected Ratios'!K$34>=0,$B134+(1-$B134)*'LF Projected Ratios'!K$34,$B134*(1+'LF Projected Ratios'!K$34)) -> 0.72451412 | ... AF134: =IF('LF Projected Ratios'!AG$34>=0,$B134+(1-$B134)*'LF Projected Ratios'!AG$34,$B134*(1+'LF Projected Ratios'!AG$34)) -> 0.73083167
A136: Reapply sigmoid (i.e. convert from X value to Y value)
B137: 2020 | C137: 2021 | D137: 2022 | E137: 2023 | F137: 2024 | G137: 2025 | H137: 2026 | I137: 2027 | J137: 2028 | K137: 2029 | L137: 2030 | M137: 2031 | N137: 2032 | O137: 2033 | P137: 2034 | Q137: 2035 | R137: 2036 | S137: 2037 | T137: 2038 | U137: 2039 | V137: 2040 | W137: 2041 | X137: 2042 | Y137: 2043 | Z137: 2044 | AA137: 2045 | AB137: 2046 | AC137: 2047 | AD137: 2048 | AE137: 2049 | AF137: 2050
A138: ISIC 01T03 | B138: =(1/(1+EXP(('S Curve Equation'!$B$11-B93*'S Curve Equation'!$B$12)*'S Curve Equation'!$B$10))+'S Curve Equation'!$B$13)*'S Curve Equation'!$B$14 -> 0.277 | C138: =(1/(1+EXP(('S Curve Equation'!$B$11-C93*'S Curve Equation'!$B$12)*'S Curve Equation'!$B$10))+'S Curve Equation'!$B$13)*'S Curve Equation'!$B$14 -> 0.27826615 | D138: =(1/(1+EXP(('S Curve Equation'!$B$11-D93*'S Curve Equation'!$B$12)*'S Curve Equation'!$B$10))+'S Curve Equation'!$B$13)*'S Curve Equation'!$B$14 -> 0.27959397 | E138: =(1/(1+EXP(('S Curve Equation'!$B$11-E93*'S Curve Equation'!$B$12)*'S Curve Equation'!$B$10))+'S Curve Equation'!$B$13)*'S Curve Equation'!$B$14 -> 0.28089219 | F138: =(1/(1+EXP(('S Curve Equation'!$B$11-F93*'S Curve Equation'!$B$12)*'S Curve Equation'!$B$10))+'S Curve Equation'!$B$13)*'S Curve Equation'!$B$14 -> 0.28217042 | G138: =(1/(1+EXP(('S Curve Equation'!$B$11-G93*'S Curve Equation'!$B$12)*'S Curve Equation'!$B$10))+'S Curve Equation'!$B$13)*'S Curve Equation'!$B$14 -> 0.28349414 | H138: =(1/(1+EXP(('S Curve Equation'!$B$11-H93*'S Curve Equation'!$B$12)*'S Curve Equation'!$B$10))+'S Curve Equation'!$B$13)*'S Curve Equation'!$B$14 -> 0.28487428 | I138: =(1/(1+EXP(('S Curve Equation'!$B$11-I93*'S Curve Equation'!$B$12)*'S Curve Equation'!$B$10))+'S Curve Equation'!$B$13)*'S Curve Equation'!$B$14 -> 0.28633534 | ... AF138: =(1/(1+EXP(('S Curve Equation'!$B$11-AF93*'S Curve Equation'!$B$12)*'S Curve Equation'!$B$10))+'S Curve Equation'!$B$13)*'S Curve Equation'!$B$14 -> 0.31463863
A139: ISIC 05 | B139: =(1/(1+EXP(('S Curve Equation'!$B$11-B94*'S Curve Equation'!$B$12)*'S Curve Equation'!$B$10))+'S Curve Equation'!$B$13)*'S Curve Equation'!$B$14 -> 0.101 | C139: =(1/(1+EXP(('S Curve Equation'!$B$11-C94*'S Curve Equation'!$B$12)*'S Curve Equation'!$B$10))+'S Curve Equation'!$B$13)*'S Curve Equation'!$B$14 -> 0.10174259 | D139: =(1/(1+EXP(('S Curve Equation'!$B$11-D94*'S Curve Equation'!$B$12)*'S Curve Equation'!$B$10))+'S Curve Equation'!$B$13)*'S Curve Equation'!$B$14 -> 0.10252384 | E139: =(1/(1+EXP(('S Curve Equation'!$B$11-E94*'S Curve Equation'!$B$12)*'S Curve Equation'!$B$10))+'S Curve Equation'!$B$13)*'S Curve Equation'!$B$14 -> 0.10329014 | F139: =(1/(1+EXP(('S Curve Equation'!$B$11-F94*'S Curve Equation'!$B$12)*'S Curve Equation'!$B$10))+'S Curve Equation'!$B$13)*'S Curve Equation'!$B$14 -> 0.10404703 | G139: =(1/(1+EXP(('S Curve Equation'!$B$11-G94*'S Curve Equation'!$B$12)*'S Curve Equation'!$B$10))+'S Curve Equation'!$B$13)*'S Curve Equation'!$B$14 -> 0.10483337 | H139: =(1/(1+EXP(('S Curve Equation'!$B$11-H94*'S Curve Equation'!$B$12)*'S Curve Equation'!$B$10))+'S Curve Equation'!$B$13)*'S Curve Equation'!$B$14 -> 0.10565595 | I139: =(1/(1+EXP(('S Curve Equation'!$B$11-I94*'S Curve Equation'!$B$12)*'S Curve Equation'!$B$10))+'S Curve Equation'!$B$13)*'S Curve Equation'!$B$14 -> 0.1065298 | ... AF139: =(1/(1+EXP(('S Curve Equation'!$B$11-AF94*'S Curve Equation'!$B$12)*'S Curve Equation'!$B$10))+'S Curve Equation'!$B$13)*'S Curve Equation'!$B$14 -> 0.12408299
A140: ISIC 06 | B140: =(1/(1+EXP(('S Curve Equation'!$B$11-B95*'S Curve Equation'!$B$12)*'S Curve Equation'!$B$10))+'S Curve Equation'!$B$13)*'S Curve Equation'!$B$14 -> 0.149 | C140: =(1/(1+EXP(('S Curve Equation'!$B$11-C95*'S Curve Equation'!$B$12)*'S Curve Equation'!$B$10))+'S Curve Equation'!$B$13)*'S Curve Equation'!$B$14 -> 0.14994131 | D140: =(1/(1+EXP(('S Curve Equation'!$B$11-D95*'S Curve Equation'!$B$12)*'S Curve Equation'!$B$10))+'S Curve Equation'!$B$13)*'S Curve Equation'!$B$14 -> 0.15093059 | E140: =(1/(1+EXP(('S Curve Equation'!$B$11-E95*'S Curve Equation'!$B$12)*'S Curve Equation'!$B$10))+'S Curve Equation'!$B$13)*'S Curve Equation'!$B$14 -> 0.15189993 | F140: =(1/(1+EXP(('S Curve Equation'!$B$11-F95*'S Curve Equation'!$B$12)*'S Curve Equation'!$B$10))+'S Curve Equation'!$B$13)*'S Curve Equation'!$B$14 -> 0.15285639 | G140: =(1/(1+EXP(('S Curve Equation'!$B$11-G95*'S Curve Equation'!$B$12)*'S Curve Equation'!$B$10))+'S Curve Equation'!$B$13)*'S Curve Equation'!$B$14 -> 0.15384903 | H140: =(1/(1+EXP(('S Curve Equation'!$B$11-H95*'S Curve Equation'!$B$12)*'S Curve Equation'!$B$10))+'S Curve Equation'!$B$13)*'S Curve Equation'!$B$14 -> 0.15488628 | I140: =(1/(1+EXP(('S Curve Equation'!$B$11-I95*'S Curve Equation'!$B$12)*'S Curve Equation'!$B$10))+'S Curve Equation'!$B$13)*'S Curve Equation'!$B$14 -> 0.15598694 | ... AF140: =(1/(1+EXP(('S Curve Equation'!$B$11-AF95*'S Curve Equation'!$B$12)*'S Curve Equation'!$B$10))+'S Curve Equation'!$B$13)*'S Curve Equation'!$B$14 -> 0.17783411
A141: ISIC 07T08 | B141: =(1/(1+EXP(('S Curve Equation'!$B$11-B96*'S Curve Equation'!$B$12)*'S Curve Equation'!$B$10))+'S Curve Equation'!$B$13)*'S Curve Equation'!$B$14 -> 0.107 | C141: =(1/(1+EXP(('S Curve Equation'!$B$11-C96*'S Curve Equation'!$B$12)*'S Curve Equation'!$B$10))+'S Curve Equation'!$B$13)*'S Curve Equation'!$B$14 -> 0.10777016 | D141: =(1/(1+EXP(('S Curve Equation'!$B$11-D96*'S Curve Equation'!$B$12)*'S Curve Equation'!$B$10))+'S Curve Equation'!$B$13)*'S Curve Equation'!$B$14 -> 0.1085803 | E141: =(1/(1+EXP(('S Curve Equation'!$B$11-E96*'S Curve Equation'!$B$12)*'S Curve Equation'!$B$10))+'S Curve Equation'!$B$13)*'S Curve Equation'!$B$14 -> 0.10937483 | F141: =(1/(1+EXP(('S Curve Equation'!$B$11-F96*'S Curve Equation'!$B$12)*'S Curve Equation'!$B$10))+'S Curve Equation'!$B$13)*'S Curve Equation'!$B$14 -> 0.11015949 | G141: =(1/(1+EXP(('S Curve Equation'!$B$11-G96*'S Curve Equation'!$B$12)*'S Curve Equation'!$B$10))+'S Curve Equation'!$B$13)*'S Curve Equation'!$B$14 -> 0.11097457 | H141: =(1/(1+EXP(('S Curve Equation'!$B$11-H96*'S Curve Equation'!$B$12)*'S Curve Equation'!$B$10))+'S Curve Equation'!$B$13)*'S Curve Equation'!$B$14 -> 0.11182708 | I141: =(1/(1+EXP(('S Curve Equation'!$B$11-I96*'S Curve Equation'!$B$12)*'S Curve Equation'!$B$10))+'S Curve Equation'!$B$13)*'S Curve Equation'!$B$14 -> 0.11273258 | ... AF141: =(1/(1+EXP(('S Curve Equation'!$B$11-AF96*'S Curve Equation'!$B$12)*'S Curve Equation'!$B$10))+'S Curve Equation'!$B$13)*'S Curve Equation'!$B$14 -> 0.13089212
A142: ISIC 09 | B142: =(1/(1+EXP(('S Curve Equation'!$B$11-B97*'S Curve Equation'!$B$12)*'S Curve Equation'!$B$10))+'S Curve Equation'!$B$13)*'S Curve Equation'!$B$14 -> 0.152 | C142: =(1/(1+EXP(('S Curve Equation'!$B$11-C97*'S Curve Equation'!$B$12)*'S Curve Equation'!$B$10))+'S Curve Equation'!$B$13)*'S Curve Equation'!$B$14 -> 0.15295216 | D142: =(1/(1+EXP(('S Curve Equation'!$B$11-D97*'S Curve Equation'!$B$12)*'S Curve Equation'!$B$10))+'S Curve Equation'!$B$13)*'S Curve Equation'!$B$14 -> 0.1539528 | E142: =(1/(1+EXP(('S Curve Equation'!$B$11-E97*'S Curve Equation'!$B$12)*'S Curve Equation'!$B$10))+'S Curve Equation'!$B$13)*'S Curve Equation'!$B$14 -> 0.1549332 | F142: =(1/(1+EXP(('S Curve Equation'!$B$11-F97*'S Curve Equation'!$B$12)*'S Curve Equation'!$B$10))+'S Curve Equation'!$B$13)*'S Curve Equation'!$B$14 -> 0.15590051 | G142: =(1/(1+EXP(('S Curve Equation'!$B$11-G97*'S Curve Equation'!$B$12)*'S Curve Equation'!$B$10))+'S Curve Equation'!$B$13)*'S Curve Equation'!$B$14 -> 0.15690435 | H142: =(1/(1+EXP(('S Curve Equation'!$B$11-H97*'S Curve Equation'!$B$12)*'S Curve Equation'!$B$10))+'S Curve Equation'!$B$13)*'S Curve Equation'!$B$14 -> 0.15795326 | I142: =(1/(1+EXP(('S Curve Equation'!$B$11-I97*'S Curve Equation'!$B$12)*'S Curve Equation'!$B$10))+'S Curve Equation'!$B$13)*'S Curve Equation'!$B$14 -> 0.1590662 | ... AF142: =(1/(1+EXP(('S Curve Equation'!$B$11-AF97*'S Curve Equation'!$B$12)*'S Curve Equation'!$B$10))+'S Curve Equation'!$B$13)*'S Curve Equation'!$B$14 -> 0.18114238
A143: ISIC 10T12 | B143: =(1/(1+EXP(('S Curve Equation'!$B$11-B98*'S Curve Equation'!$B$12)*'S Curve Equation'!$B$10))+'S Curve Equation'!$B$13)*'S Curve Equation'!$B$14 -> 0.39680583 | C143: =(1/(1+EXP(('S Curve Equation'!$B$11-C98*'S Curve Equation'!$B$12)*'S Curve Equation'!$B$10))+'S Curve Equation'!$B$13)*'S Curve Equation'!$B$14 -> 0.39815964 | D143: =(1/(1+EXP(('S Curve Equation'!$B$11-D98*'S Curve Equation'!$B$12)*'S Curve Equation'!$B$10))+'S Curve Equation'!$B$13)*'S Curve Equation'!$B$14 -> 0.39957716 | E143: =(1/(1+EXP(('S Curve Equation'!$B$11-E98*'S Curve Equation'!$B$12)*'S Curve Equation'!$B$10))+'S Curve Equation'!$B$13)*'S Curve Equation'!$B$14 -> 0.40096084 | F143: =(1/(1+EXP(('S Curve Equation'!$B$11-F98*'S Curve Equation'!$B$12)*'S Curve Equation'!$B$10))+'S Curve Equation'!$B$13)*'S Curve Equation'!$B$14 -> 0.4023211 | G143: =(1/(1+EXP(('S Curve Equation'!$B$11-G98*'S Curve Equation'!$B$12)*'S Curve Equation'!$B$10))+'S Curve Equation'!$B$13)*'S Curve Equation'!$B$14 -> 0.40372754 | H143: =(1/(1+EXP(('S Curve Equation'!$B$11-H98*'S Curve Equation'!$B$12)*'S Curve Equation'!$B$10))+'S Curve Equation'!$B$13)*'S Curve Equation'!$B$14 -> 0.40519154 | I143: =(1/(1+EXP(('S Curve Equation'!$B$11-I98*'S Curve Equation'!$B$12)*'S Curve Equation'!$B$10))+'S Curve Equation'!$B$13)*'S Curve Equation'!$B$14 -> 0.40673873 | ... AF143: =(1/(1+EXP(('S Curve Equation'!$B$11-AF98*'S Curve Equation'!$B$12)*'S Curve Equation'!$B$10))+'S Curve Equation'!$B$13)*'S Curve Equation'!$B$14 -> 0.43619189
A144: ISIC 13T15 | B144: =(1/(1+EXP(('S Curve Equation'!$B$11-B99*'S Curve Equation'!$B$12)*'S Curve Equation'!$B$10))+'S Curve Equation'!$B$13)*'S Curve Equation'!$B$14 -> 0.522 | C144: =(1/(1+EXP(('S Curve Equation'!$B$11-C99*'S Curve Equation'!$B$12)*'S Curve Equation'!$B$10))+'S Curve Equation'!$B$13)*'S Curve Equation'!$B$14 -> 0.5232657 | D144: =(1/(1+EXP(('S Curve Equation'!$B$11-D99*'S Curve Equation'!$B$12)*'S Curve Equation'!$B$10))+'S Curve Equation'!$B$13)*'S Curve Equation'!$B$14 -> 0.52458916 | E144: =(1/(1+EXP(('S Curve Equation'!$B$11-E99*'S Curve Equation'!$B$12)*'S Curve Equation'!$B$10))+'S Curve Equation'!$B$13)*'S Curve Equation'!$B$14 -> 0.52587927 | F144: =(1/(1+EXP(('S Curve Equation'!$B$11-F99*'S Curve Equation'!$B$12)*'S Curve Equation'!$B$10))+'S Curve Equation'!$B$13)*'S Curve Equation'!$B$14 -> 0.52714584 | G144: =(1/(1+EXP(('S Curve Equation'!$B$11-G99*'S Curve Equation'!$B$12)*'S Curve Equation'!$B$10))+'S Curve Equation'!$B$13)*'S Curve Equation'!$B$14 -> 0.52845367 | H144: =(1/(1+EXP(('S Curve Equation'!$B$11-H99*'S Curve Equation'!$B$12)*'S Curve Equation'!$B$10))+'S Curve Equation'!$B$13)*'S Curve Equation'!$B$14 -> 0.52981313 | I144: =(1/(1+EXP(('S Curve Equation'!$B$11-I99*'S Curve Equation'!$B$12)*'S Curve Equation'!$B$10))+'S Curve Equation'!$B$13)*'S Curve Equation'!$B$14 -> 0.53124776 | ... AF144: =(1/(1+EXP(('S Curve Equation'!$B$11-AF99*'S Curve Equation'!$B$12)*'S Curve Equation'!$B$10))+'S Curve Equation'!$B$13)*'S Curve Equation'!$B$14 -> 0.55816304
A145: ISIC 16 | B145: =(1/(1+EXP(('S Curve Equation'!$B$11-B100*'S Curve Equation'!$B$12)*'S Curve Equation'!$B$10))+'S Curve Equation'!$B$13)*'S Curve Equation'!$B$14 -> 0.166 | C145: =(1/(1+EXP(('S Curve Equation'!$B$11-C100*'S Curve Equation'!$B$12)*'S Curve Equation'!$B$10))+'S Curve Equation'!$B$13)*'S Curve Equation'!$B$14 -> 0.16700055 | D145: =(1/(1+EXP(('S Curve Equation'!$B$11-D100*'S Curve Equation'!$B$12)*'S Curve Equation'!$B$10))+'S Curve Equation'!$B$13)*'S Curve Equation'!$B$14 -> 0.16805176 | E145: =(1/(1+EXP(('S Curve Equation'!$B$11-E100*'S Curve Equation'!$B$12)*'S Curve Equation'!$B$10))+'S Curve Equation'!$B$13)*'S Curve Equation'!$B$14 -> 0.16908144 | F145: =(1/(1+EXP(('S Curve Equation'!$B$11-F100*'S Curve Equation'!$B$12)*'S Curve Equation'!$B$10))+'S Curve Equation'!$B$13)*'S Curve Equation'!$B$14 -> 0.17009709 | G145: =(1/(1+EXP(('S Curve Equation'!$B$11-G100*'S Curve Equation'!$B$12)*'S Curve Equation'!$B$10))+'S Curve Equation'!$B$13)*'S Curve Equation'!$B$14 -> 0.17115082 | H145: =(1/(1+EXP(('S Curve Equation'!$B$11-H100*'S Curve Equation'!$B$12)*'S Curve Equation'!$B$10))+'S Curve Equation'!$B$13)*'S Curve Equation'!$B$14 -> 0.17225155 | I145: =(1/(1+EXP(('S Curve Equation'!$B$11-I100*'S Curve Equation'!$B$12)*'S Curve Equation'!$B$10))+'S Curve Equation'!$B$13)*'S Curve Equation'!$B$14 -> 0.17341913 | ... AF145: =(1/(1+EXP(('S Curve Equation'!$B$11-AF100*'S Curve Equation'!$B$12)*'S Curve Equation'!$B$10))+'S Curve Equation'!$B$13)*'S Curve Equation'!$B$14 -> 0.19650828
A146: ISIC 17T18 | B146: =(1/(1+EXP(('S Curve Equation'!$B$11-B101*'S Curve Equation'!$B$12)*'S Curve Equation'!$B$10))+'S Curve Equation'!$B$13)*'S Curve Equation'!$B$14 -> 0.281 | C146: =(1/(1+EXP(('S Curve Equation'!$B$11-C101*'S Curve Equation'!$B$12)*'S Curve Equation'!$B$10))+'S Curve Equation'!$B$13)*'S Curve Equation'!$B$14 -> 0.28227217 | D146: =(1/(1+EXP(('S Curve Equation'!$B$11-D101*'S Curve Equation'!$B$12)*'S Curve Equation'!$B$10))+'S Curve Equation'!$B$13)*'S Curve Equation'!$B$14 -> 0.28360623 | E146: =(1/(1+EXP(('S Curve Equation'!$B$11-E101*'S Curve Equation'!$B$12)*'S Curve Equation'!$B$10))+'S Curve Equation'!$B$13)*'S Curve Equation'!$B$14 -> 0.28491047 | F146: =(1/(1+EXP(('S Curve Equation'!$B$11-F101*'S Curve Equation'!$B$12)*'S Curve Equation'!$B$10))+'S Curve Equation'!$B$13)*'S Curve Equation'!$B$14 -> 0.28619455 | G146: =(1/(1+EXP(('S Curve Equation'!$B$11-G101*'S Curve Equation'!$B$12)*'S Curve Equation'!$B$10))+'S Curve Equation'!$B$13)*'S Curve Equation'!$B$14 -> 0.28752425 | H146: =(1/(1+EXP(('S Curve Equation'!$B$11-H101*'S Curve Equation'!$B$12)*'S Curve Equation'!$B$10))+'S Curve Equation'!$B$13)*'S Curve Equation'!$B$14 -> 0.28891055 | I146: =(1/(1+EXP(('S Curve Equation'!$B$11-I101*'S Curve Equation'!$B$12)*'S Curve Equation'!$B$10))+'S Curve Equation'!$B$13)*'S Curve Equation'!$B$14 -> 0.29037804 | ... AF146: =(1/(1+EXP(('S Curve Equation'!$B$11-AF101*'S Curve Equation'!$B$12)*'S Curve Equation'!$B$10))+'S Curve Equation'!$B$13)*'S Curve Equation'!$B$14 -> 0.3187873
A147: ISIC 19 | B147: =(1/(1+EXP(('S Curve Equation'!$B$11-B102*'S Curve Equation'!$B$12)*'S Curve Equation'!$B$10))+'S Curve Equation'!$B$13)*'S Curve Equation'!$B$14 -> 0.178 | C147: =(1/(1+EXP(('S Curve Equation'!$B$11-C102*'S Curve Equation'!$B$12)*'S Curve Equation'!$B$10))+'S Curve Equation'!$B$13)*'S Curve Equation'!$B$14 -> 0.17903915 | D147: =(1/(1+EXP(('S Curve Equation'!$B$11-D102*'S Curve Equation'!$B$12)*'S Curve Equation'!$B$10))+'S Curve Equation'!$B$13)*'S Curve Equation'!$B$14 -> 0.18013068 | E147: =(1/(1+EXP(('S Curve Equation'!$B$11-E102*'S Curve Equation'!$B$12)*'S Curve Equation'!$B$10))+'S Curve Equation'!$B$13)*'S Curve Equation'!$B$14 -> 0.18119959 | F147: =(1/(1+EXP(('S Curve Equation'!$B$11-F102*'S Curve Equation'!$B$12)*'S Curve Equation'!$B$10))+'S Curve Equation'!$B$13)*'S Curve Equation'!$B$14 -> 0.18225373 | G147: =(1/(1+EXP(('S Curve Equation'!$B$11-G102*'S Curve Equation'!$B$12)*'S Curve Equation'!$B$10))+'S Curve Equation'!$B$13)*'S Curve Equation'!$B$14 -> 0.18334714 | H147: =(1/(1+EXP(('S Curve Equation'!$B$11-H102*'S Curve Equation'!$B$12)*'S Curve Equation'!$B$10))+'S Curve Equation'!$B$13)*'S Curve Equation'!$B$14 -> 0.18448905 | I147: =(1/(1+EXP(('S Curve Equation'!$B$11-I102*'S Curve Equation'!$B$12)*'S Curve Equation'!$B$10))+'S Curve Equation'!$B$13)*'S Curve Equation'!$B$14 -> 0.18570003 | ... AF147: =(1/(1+EXP(('S Curve Equation'!$B$11-AF102*'S Curve Equation'!$B$12)*'S Curve Equation'!$B$10))+'S Curve Equation'!$B$13)*'S Curve Equation'!$B$14 -> 0.20958701
A148: ISIC 20 | B148: =(1/(1+EXP(('S Curve Equation'!$B$11-B103*'S Curve Equation'!$B$12)*'S Curve Equation'!$B$10))+'S Curve Equation'!$B$13)*'S Curve Equation'!$B$14 -> 0.30601111 | C148: =(1/(1+EXP(('S Curve Equation'!$B$11-C103*'S Curve Equation'!$B$12)*'S Curve Equation'!$B$10))+'S Curve Equation'!$B$13)*'S Curve Equation'!$B$14 -> 0.30731583 | D148: =(1/(1+EXP(('S Curve Equation'!$B$11-D103*'S Curve Equation'!$B$12)*'S Curve Equation'!$B$10))+'S Curve Equation'!$B$13)*'S Curve Equation'!$B$14 -> 0.30868353 | E148: =(1/(1+EXP(('S Curve Equation'!$B$11-E103*'S Curve Equation'!$B$12)*'S Curve Equation'!$B$10))+'S Curve Equation'!$B$13)*'S Curve Equation'!$B$14 -> 0.31002017 | F148: =(1/(1+EXP(('S Curve Equation'!$B$11-F103*'S Curve Equation'!$B$12)*'S Curve Equation'!$B$10))+'S Curve Equation'!$B$13)*'S Curve Equation'!$B$14 -> 0.3113357 | G148: =(1/(1+EXP(('S Curve Equation'!$B$11-G103*'S Curve Equation'!$B$12)*'S Curve Equation'!$B$10))+'S Curve Equation'!$B$13)*'S Curve Equation'!$B$14 -> 0.31269748 | H148: =(1/(1+EXP(('S Curve Equation'!$B$11-H103*'S Curve Equation'!$B$12)*'S Curve Equation'!$B$10))+'S Curve Equation'!$B$13)*'S Curve Equation'!$B$14 -> 0.3141167 | I148: =(1/(1+EXP(('S Curve Equation'!$B$11-I103*'S Curve Equation'!$B$12)*'S Curve Equation'!$B$10))+'S Curve Equation'!$B$13)*'S Curve Equation'!$B$14 -> 0.31561847 | ... AF148: =(1/(1+EXP(('S Curve Equation'!$B$11-AF103*'S Curve Equation'!$B$12)*'S Curve Equation'!$B$10))+'S Curve Equation'!$B$13)*'S Curve Equation'!$B$14 -> 0.34457675
A149: ISIC 21 | B149: =(1/(1+EXP(('S Curve Equation'!$B$11-B104*'S Curve Equation'!$B$12)*'S Curve Equation'!$B$10))+'S Curve Equation'!$B$13)*'S Curve Equation'!$B$14 -> 0.432 | C149: =(1/(1+EXP(('S Curve Equation'!$B$11-C104*'S Curve Equation'!$B$12)*'S Curve Equation'!$B$10))+'S Curve Equation'!$B$13)*'S Curve Equation'!$B$14 -> 0.43334606 | D149: =(1/(1+EXP(('S Curve Equation'!$B$11-D104*'S Curve Equation'!$B$12)*'S Curve Equation'!$B$10))+'S Curve Equation'!$B$13)*'S Curve Equation'!$B$14 -> 0.43475488 | E149: =(1/(1+EXP(('S Curve Equation'!$B$11-E104*'S Curve Equation'!$B$12)*'S Curve Equation'!$B$10))+'S Curve Equation'!$B$13)*'S Curve Equation'!$B$14 -> 0.43612951 | F149: =(1/(1+EXP(('S Curve Equation'!$B$11-F104*'S Curve Equation'!$B$12)*'S Curve Equation'!$B$10))+'S Curve Equation'!$B$13)*'S Curve Equation'!$B$14 -> 0.43748031 | G149: =(1/(1+EXP(('S Curve Equation'!$B$11-G104*'S Curve Equation'!$B$12)*'S Curve Equation'!$B$10))+'S Curve Equation'!$B$13)*'S Curve Equation'!$B$14 -> 0.43887642 | H149: =(1/(1+EXP(('S Curve Equation'!$B$11-H104*'S Curve Equation'!$B$12)*'S Curve Equation'!$B$10))+'S Curve Equation'!$B$13)*'S Curve Equation'!$B$14 -> 0.44032904 | I149: =(1/(1+EXP(('S Curve Equation'!$B$11-I104*'S Curve Equation'!$B$12)*'S Curve Equation'!$B$10))+'S Curve Equation'!$B$13)*'S Curve Equation'!$B$14 -> 0.44186354 | ... AF149: =(1/(1+EXP(('S Curve Equation'!$B$11-AF104*'S Curve Equation'!$B$12)*'S Curve Equation'!$B$10))+'S Curve Equation'!$B$13)*'S Curve Equation'!$B$14 -> 0.47094565
... A179: ISIC 97T98 | B179: =(1/(1+EXP(('S Curve Equation'!$B$11-B134*'S Curve Equation'!$B$12)*'S Curve Equation'!$B$10))+'S Curve Equation'!$B$13)*'S Curve Equation'!$B$14 -> 0.889 | C179: =(1/(1+EXP(('S Curve Equation'!$B$11-C134*'S Curve Equation'!$B$12)*'S Curve Equation'!$B$10))+'S Curve Equation'!$B$13)*'S Curve Equation'!$B$14 -> 0.88930249 | D179: =(1/(1+EXP(('S Curve Equation'!$B$11-D134*'S Curve Equation'!$B$12)*'S Curve Equation'!$B$10))+'S Curve Equation'!$B$13)*'S Curve Equation'!$B$14 -> 0.88961817 | E179: =(1/(1+EXP(('S Curve Equation'!$B$11-E134*'S Curve Equation'!$B$12)*'S Curve Equation'!$B$10))+'S Curve Equation'!$B$13)*'S Curve Equation'!$B$14 -> 0.88992529 | F179: =(1/(1+EXP(('S Curve Equation'!$B$11-F134*'S Curve Equation'!$B$12)*'S Curve Equation'!$B$10))+'S Curve Equation'!$B$13)*'S Curve Equation'!$B$14 -> 0.89022622 | G179: =(1/(1+EXP(('S Curve Equation'!$B$11-G134*'S Curve Equation'!$B$12)*'S Curve Equation'!$B$10))+'S Curve Equation'!$B$13)*'S Curve Equation'!$B$14 -> 0.89053637 | H179: =(1/(1+EXP(('S Curve Equation'!$B$11-H134*'S Curve Equation'!$B$12)*'S Curve Equation'!$B$10))+'S Curve Equation'!$B$13)*'S Curve Equation'!$B$14 -> 0.89085812 | I179: =(1/(1+EXP(('S Curve Equation'!$B$11-I134*'S Curve Equation'!$B$12)*'S Curve Equation'!$B$10))+'S Curve Equation'!$B$13)*'S Curve Equation'!$B$14 -> 0.89119696 | ... AF179: =(1/(1+EXP(('S Curve Equation'!$B$11-AF134*'S Curve Equation'!$B$12)*'S Curve Equation'!$B$10))+'S Curve Equation'!$B$13)*'S Curve Equation'!$B$14 -> 0.89742856
A181: Rescale to Sum to 1 Across Traits
B182: 2020 | C182: 2021 | D182: 2022 | E182: 2023 | F182: 2024 | G182: 2025 | H182: 2026 | I182: 2027 | J182: 2028 | K182: 2029 | L182: 2030 | M182: 2031 | N182: 2032 | O182: 2033 | P182: 2034 | Q182: 2035 | R182: 2036 | S182: 2037 | T182: 2038 | U182: 2039 | V182: 2040 | W182: 2041 | X182: 2042 | Y182: 2043 | Z182: 2044 | AA182: 2045 | AB182: 2046 | AC182: 2047 | AD182: 2048 | AE182: 2049 | AF182: 2050
A183: ISIC 01T03 | B183: =B138/SUM(B138,'Calculations male'!B138) -> 0.277 | C183: =C138/SUM(C138,'Calculations male'!C138) -> 0.27826615 | D183: =D138/SUM(D138,'Calculations male'!D138) -> 0.27959397 | E183: =E138/SUM(E138,'Calculations male'!E138) -> 0.28089219 | F183: =F138/SUM(F138,'Calculations male'!F138) -> 0.28217042 | G183: =G138/SUM(G138,'Calculations male'!G138) -> 0.28349414 | H183: =H138/SUM(H138,'Calculations male'!H138) -> 0.28487428 | I183: =I138/SUM(I138,'Calculations male'!I138) -> 0.28633534 | ... AF183: =AF138/SUM(AF138,'Calculations male'!AF138) -> 0.31463863
A184: ISIC 05 | B184: =B139/SUM(B139,'Calculations male'!B139) -> 0.101 | C184: =C139/SUM(C139,'Calculations male'!C139) -> 0.10174259 | D184: =D139/SUM(D139,'Calculations male'!D139) -> 0.10252384 | E184: =E139/SUM(E139,'Calculations male'!E139) -> 0.10329014 | F184: =F139/SUM(F139,'Calculations male'!F139) -> 0.10404703 | G184: =G139/SUM(G139,'Calculations male'!G139) -> 0.10483337 | H184: =H139/SUM(H139,'Calculations male'!H139) -> 0.10565595 | I184: =I139/SUM(I139,'Calculations male'!I139) -> 0.1065298 | ... AF184: =AF139/SUM(AF139,'Calculations male'!AF139) -> 0.12408299
A185: ISIC 06 | B185: =B140/SUM(B140,'Calculations male'!B140) -> 0.149 | C185: =C140/SUM(C140,'Calculations male'!C140) -> 0.14994131 | D185: =D140/SUM(D140,'Calculations male'!D140) -> 0.15093059 | E185: =E140/SUM(E140,'Calculations male'!E140) -> 0.15189993 | F185: =F140/SUM(F140,'Calculations male'!F140) -> 0.15285639 | G185: =G140/SUM(G140,'Calculations male'!G140) -> 0.15384903 | H185: =H140/SUM(H140,'Calculations male'!H140) -> 0.15488628 | I185: =I140/SUM(I140,'Calculations male'!I140) -> 0.15598694 | ... AF185: =AF140/SUM(AF140,'Calculations male'!AF140) -> 0.17783411
A186: ISIC 07T08 | B186: =B141/SUM(B141,'Calculations male'!B141) -> 0.107 | C186: =C141/SUM(C141,'Calculations male'!C141) -> 0.10777016 | D186: =D141/SUM(D141,'Calculations male'!D141) -> 0.1085803 | E186: =E141/SUM(E141,'Calculations male'!E141) -> 0.10937483 | F186: =F141/SUM(F141,'Calculations male'!F141) -> 0.11015949 | G186: =G141/SUM(G141,'Calculations male'!G141) -> 0.11097457 | H186: =H141/SUM(H141,'Calculations male'!H141) -> 0.11182708 | I186: =I141/SUM(I141,'Calculations male'!I141) -> 0.11273258 | ... AF186: =AF141/SUM(AF141,'Calculations male'!AF141) -> 0.13089212
A187: ISIC 09 | B187: =B142/SUM(B142,'Calculations male'!B142) -> 0.152 | C187: =C142/SUM(C142,'Calculations male'!C142) -> 0.15295216 | D187: =D142/SUM(D142,'Calculations male'!D142) -> 0.1539528 | E187: =E142/SUM(E142,'Calculations male'!E142) -> 0.1549332 | F187: =F142/SUM(F142,'Calculations male'!F142) -> 0.15590051 | G187: =G142/SUM(G142,'Calculations male'!G142) -> 0.15690435 | H187: =H142/SUM(H142,'Calculations male'!H142) -> 0.15795326 | I187: =I142/SUM(I142,'Calculations male'!I142) -> 0.1590662 | ... AF187: =AF142/SUM(AF142,'Calculations male'!AF142) -> 0.18114238
A188: ISIC 10T12 | B188: =B143/SUM(B143,'Calculations male'!B143) -> 0.39680583 | C188: =C143/SUM(C143,'Calculations male'!C143) -> 0.39815964 | D188: =D143/SUM(D143,'Calculations male'!D143) -> 0.39957716 | E188: =E143/SUM(E143,'Calculations male'!E143) -> 0.40096084 | F188: =F143/SUM(F143,'Calculations male'!F143) -> 0.4023211 | G188: =G143/SUM(G143,'Calculations male'!G143) -> 0.40372754 | H188: =H143/SUM(H143,'Calculations male'!H143) -> 0.40519154 | I188: =I143/SUM(I143,'Calculations male'!I143) -> 0.40673873 | ... AF188: =AF143/SUM(AF143,'Calculations male'!AF143) -> 0.43619189
A189: ISIC 13T15 | B189: =B144/SUM(B144,'Calculations male'!B144) -> 0.522 | C189: =C144/SUM(C144,'Calculations male'!C144) -> 0.5232657 | D189: =D144/SUM(D144,'Calculations male'!D144) -> 0.52458916 | E189: =E144/SUM(E144,'Calculations male'!E144) -> 0.52587927 | F189: =F144/SUM(F144,'Calculations male'!F144) -> 0.52714584 | G189: =G144/SUM(G144,'Calculations male'!G144) -> 0.52845367 | H189: =H144/SUM(H144,'Calculations male'!H144) -> 0.52981313 | I189: =I144/SUM(I144,'Calculations male'!I144) -> 0.53124776 | ... AF189: =AF144/SUM(AF144,'Calculations male'!AF144) -> 0.55816304
A190: ISIC 16 | B190: =B145/SUM(B145,'Calculations male'!B145) -> 0.166 | C190: =C145/SUM(C145,'Calculations male'!C145) -> 0.16700055 | D190: =D145/SUM(D145,'Calculations male'!D145) -> 0.16805176 | E190: =E145/SUM(E145,'Calculations male'!E145) -> 0.16908144 | F190: =F145/SUM(F145,'Calculations male'!F145) -> 0.17009709 | G190: =G145/SUM(G145,'Calculations male'!G145) -> 0.17115082 | H190: =H145/SUM(H145,'Calculations male'!H145) -> 0.17225155 | I190: =I145/SUM(I145,'Calculations male'!I145) -> 0.17341913 | ... AF190: =AF145/SUM(AF145,'Calculations male'!AF145) -> 0.19650828
A191: ISIC 17T18 | B191: =B146/SUM(B146,'Calculations male'!B146) -> 0.281 | C191: =C146/SUM(C146,'Calculations male'!C146) -> 0.28227217 | D191: =D146/SUM(D146,'Calculations male'!D146) -> 0.28360623 | E191: =E146/SUM(E146,'Calculations male'!E146) -> 0.28491047 | F191: =F146/SUM(F146,'Calculations male'!F146) -> 0.28619455 | G191: =G146/SUM(G146,'Calculations male'!G146) -> 0.28752425 | H191: =H146/SUM(H146,'Calculations male'!H146) -> 0.28891055 | I191: =I146/SUM(I146,'Calculations male'!I146) -> 0.29037804 | ... AF191: =AF146/SUM(AF146,'Calculations male'!AF146) -> 0.3187873
A192: ISIC 19 | B192: =B147/SUM(B147,'Calculations male'!B147) -> 0.178 | C192: =C147/SUM(C147,'Calculations male'!C147) -> 0.17903915 | D192: =D147/SUM(D147,'Calculations male'!D147) -> 0.18013068 | E192: =E147/SUM(E147,'Calculations male'!E147) -> 0.18119959 | F192: =F147/SUM(F147,'Calculations male'!F147) -> 0.18225373 | G192: =G147/SUM(G147,'Calculations male'!G147) -> 0.18334714 | H192: =H147/SUM(H147,'Calculations male'!H147) -> 0.18448905 | I192: =I147/SUM(I147,'Calculations male'!I147) -> 0.18570003 | ... AF192: =AF147/SUM(AF147,'Calculations male'!AF147) -> 0.20958701
A193: ISIC 20 | B193: =B148/SUM(B148,'Calculations male'!B148) -> 0.30601111 | C193: =C148/SUM(C148,'Calculations male'!C148) -> 0.30731583 | D193: =D148/SUM(D148,'Calculations male'!D148) -> 0.30868353 | E193: =E148/SUM(E148,'Calculations male'!E148) -> 0.31002017 | F193: =F148/SUM(F148,'Calculations male'!F148) -> 0.3113357 | G193: =G148/SUM(G148,'Calculations male'!G148) -> 0.31269748 | H193: =H148/SUM(H148,'Calculations male'!H148) -> 0.3141167 | I193: =I148/SUM(I148,'Calculations male'!I148) -> 0.31561847 | ... AF193: =AF148/SUM(AF148,'Calculations male'!AF148) -> 0.34457675
A194: ISIC 21 | B194: =B149/SUM(B149,'Calculations male'!B149) -> 0.432 | C194: =C149/SUM(C149,'Calculations male'!C149) -> 0.43334606 | D194: =D149/SUM(D149,'Calculations male'!D149) -> 0.43475488 | E194: =E149/SUM(E149,'Calculations male'!E149) -> 0.43612951 | F194: =F149/SUM(F149,'Calculations male'!F149) -> 0.43748031 | G194: =G149/SUM(G149,'Calculations male'!G149) -> 0.43887642 | H194: =H149/SUM(H149,'Calculations male'!H149) -> 0.44032904 | I194: =I149/SUM(I149,'Calculations male'!I149) -> 0.44186354 | ... AF194: =AF149/SUM(AF149,'Calculations male'!AF149) -> 0.47094565
... A224: ISIC 97T98 | B224: =B179/SUM(B179,'Calculations male'!B179) -> 0.889 | C224: =C179/SUM(C179,'Calculations male'!C179) -> 0.88930249 | D224: =D179/SUM(D179,'Calculations male'!D179) -> 0.88961817 | E224: =E179/SUM(E179,'Calculations male'!E179) -> 0.88992529 | F224: =F179/SUM(F179,'Calculations male'!F179) -> 0.89022622 | G224: =G179/SUM(G179,'Calculations male'!G179) -> 0.89053637 | H224: =H179/SUM(H179,'Calculations male'!H179) -> 0.89085812 | I224: =I179/SUM(I179,'Calculations male'!I179) -> 0.89119696 | ... AF224: =AF179/SUM(AF179,'Calculations male'!AF179) -> 0.89742856

Sheet R

Sheet Calculations white
A1: Fraction of Workers with This Demographic Trait in the Year for Which We Have Present-Day Data Disaggregated by ISIC Code
B2: 2020
A3: ISIC 01T03 | B3: =INDEX('BLS CPS T18'!D:D,MATCH($A3,'BLS CPS T18'!H:H,0))/100 -> 0.924
A4: ISIC 05 | B4: =INDEX('BLS CPS T18'!D:D,MATCH($A4,'BLS CPS T18'!H:H,0))/100 -> 0.931
A5: ISIC 06 | B5: =INDEX('BLS CPS T18'!D:D,MATCH($A5,'BLS CPS T18'!H:H,0))/100 -> 0.806
A6: ISIC 07T08 | B6: =INDEX('BLS CPS T18'!D:D,MATCH($A6,'BLS CPS T18'!H:H,0))/100 -> 0.904
A7: ISIC 09 | B7: =INDEX('BLS CPS T18'!D:D,MATCH($A7,'BLS CPS T18'!H:H,0))/100 -> 0.865
A8: ISIC 10T12 | B8: =INDEX('BLS CPS T18'!D:D,MATCH($A8,'BLS CPS T18'!H:H,0))/100 -> 0.78259223
A9: ISIC 13T15 | B9: =INDEX('BLS CPS T18'!D:D,MATCH($A9,'BLS CPS T18'!H:H,0))/100 -> 0.759
A10: ISIC 16 | B10: =INDEX('BLS CPS T18'!D:D,MATCH($A10,'BLS CPS T18'!H:H,0))/100 -> 0.851
A11: ISIC 17T18 | B11: =INDEX('BLS CPS T18'!D:D,MATCH($A11,'BLS CPS T18'!H:H,0))/100 -> 0.834
A12: ISIC 19 | B12: =INDEX('BLS CPS T18'!D:D,MATCH($A12,'BLS CPS T18'!H:H,0))/100 -> 0.781
A13: ISIC 20 | B13: =INDEX('BLS CPS T18'!D:D,MATCH($A13,'BLS CPS T18'!H:H,0))/100 -> 0.80499259
A14: ISIC 21 | B14: =INDEX('BLS CPS T18'!D:D,MATCH($A14,'BLS CPS T18'!H:H,0))/100 -> 0.721
... A44: ISIC 97T98 | B44: =INDEX('BLS CPS T18'!D:D,MATCH($A44,'BLS CPS T18'!H:H,0))/100 -> 0.8
A46: Reverse sigmoid (i.e. convert from Y value to X value)
B47: 2020
A48: ISIC 01T03 | B48: =('S Curve Equation'!$B$11-(LN(1/((B3/'S Curve Equation'!$B$14)-'S Curve Equation'!$B$13)-1)/'S Curve Equation'!$B$10))/'S Curve Equation'!$B$12 -> 0.76357831
A49: ISIC 05 | B49: =('S Curve Equation'!$B$11-(LN(1/((B4/'S Curve Equation'!$B$14)-'S Curve Equation'!$B$13)-1)/'S Curve Equation'!$B$10))/'S Curve Equation'!$B$12 -> 0.77370096
A50: ISIC 06 | B50: =('S Curve Equation'!$B$11-(LN(1/((B5/'S Curve Equation'!$B$14)-'S Curve Equation'!$B$13)-1)/'S Curve Equation'!$B$10))/'S Curve Equation'!$B$12 -> 0.6535306
A51: ISIC 07T08 | B51: =('S Curve Equation'!$B$11-(LN(1/((B6/'S Curve Equation'!$B$14)-'S Curve Equation'!$B$13)-1)/'S Curve Equation'!$B$10))/'S Curve Equation'!$B$12 -> 0.7382409
A52: ISIC 09 | B52: =('S Curve Equation'!$B$11-(LN(1/((B7/'S Curve Equation'!$B$14)-'S Curve Equation'!$B$13)-1)/'S Curve Equation'!$B$10))/'S Curve Equation'!$B$12 -> 0.69893625
A53: ISIC 10T12 | B53: =('S Curve Equation'!$B$11-(LN(1/((B8/'S Curve Equation'!$B$14)-'S Curve Equation'!$B$13)-1)/'S Curve Equation'!$B$10))/'S Curve Equation'!$B$12 -> 0.63830098
A54: ISIC 13T15 | B54: =('S Curve Equation'!$B$11-(LN(1/((B9/'S Curve Equation'!$B$14)-'S Curve Equation'!$B$13)-1)/'S Curve Equation'!$B$10))/'S Curve Equation'!$B$12 -> 0.62403752
A55: ISIC 16 | B55: =('S Curve Equation'!$B$11-(LN(1/((B10/'S Curve Equation'!$B$14)-'S Curve Equation'!$B$13)-1)/'S Curve Equation'!$B$10))/'S Curve Equation'!$B$12 -> 0.68698806
A56: ISIC 17T18 | B56: =('S Curve Equation'!$B$11-(LN(1/((B11/'S Curve Equation'!$B$14)-'S Curve Equation'!$B$13)-1)/'S Curve Equation'!$B$10))/'S Curve Equation'!$B$12 -> 0.6735715
A57: ISIC 19 | B57: =('S Curve Equation'!$B$11-(LN(1/((B12/'S Curve Equation'!$B$14)-'S Curve Equation'!$B$13)-1)/'S Curve Equation'!$B$10))/'S Curve Equation'!$B$12 -> 0.63730681
A58: ISIC 20 | B58: =('S Curve Equation'!$B$11-(LN(1/((B13/'S Curve Equation'!$B$14)-'S Curve Equation'!$B$13)-1)/'S Curve Equation'!$B$10))/'S Curve Equation'!$B$12 -> 0.65284949
A59: ISIC 21 | B59: =('S Curve Equation'!$B$11-(LN(1/((B14/'S Curve Equation'!$B$14)-'S Curve Equation'!$B$13)-1)/'S Curve Equation'!$B$10))/'S Curve Equation'!$B$12 -> 0.60282367
... A89: ISIC 97T98 | B89: =('S Curve Equation'!$B$11-(LN(1/((B44/'S Curve Equation'!$B$14)-'S Curve Equation'!$B$13)-1)/'S Curve Equation'!$B$10))/'S Curve Equation'!$B$12 -> 0.64951008
A91: Add or subtract linear segment (along X axis) - i.e. moving a percentage of the distance from 2020 value to 100% or to 0%
B92: 2020 | C92: 2021 | D92: 2022 | E92: 2023 | F92: 2024 | G92: 2025 | H92: 2026 | I92: 2027 | J92: 2028 | K92: 2029 | L92: 2030 | M92: 2031 | N92: 2032 | O92: 2033 | P92: 2034 | Q92: 2035 | R92: 2036 | S92: 2037 | T92: 2038 | U92: 2039 | V92: 2040 | W92: 2041 | X92: 2042 | Y92: 2043 | Z92: 2044 | AA92: 2045 | AB92: 2046 | AC92: 2047 | AD92: 2048 | AE92: 2049 | AF92: 2050
A93: ISIC 01T03 | B93: =B48 -> 0.76357831 | C93: =IF('LF Projected Ratios'!D$38>=0,$B93+(1-$B93)*'LF Projected Ratios'!D$38,$B93*(1+'LF Projected Ratios'!D$38)) -> 0.7613353 | D93: =IF('LF Projected Ratios'!E$38>=0,$B93+(1-$B93)*'LF Projected Ratios'!E$38,$B93*(1+'LF Projected Ratios'!E$38)) -> 0.75900713 | E93: =IF('LF Projected Ratios'!F$38>=0,$B93+(1-$B93)*'LF Projected Ratios'!F$38,$B93*(1+'LF Projected Ratios'!F$38)) -> 0.75669492 | F93: =IF('LF Projected Ratios'!G$38>=0,$B93+(1-$B93)*'LF Projected Ratios'!G$38,$B93*(1+'LF Projected Ratios'!G$38)) -> 0.75440328 | G93: =IF('LF Projected Ratios'!H$38>=0,$B93+(1-$B93)*'LF Projected Ratios'!H$38,$B93*(1+'LF Projected Ratios'!H$38)) -> 0.75212304 | H93: =IF('LF Projected Ratios'!I$38>=0,$B93+(1-$B93)*'LF Projected Ratios'!I$38,$B93*(1+'LF Projected Ratios'!I$38)) -> 0.74979733 | I93: =IF('LF Projected Ratios'!J$38>=0,$B93+(1-$B93)*'LF Projected Ratios'!J$38,$B93*(1+'LF Projected Ratios'!J$38)) -> 0.74749133 | J93: =IF('LF Projected Ratios'!K$38>=0,$B93+(1-$B93)*'LF Projected Ratios'!K$38,$B93*(1+'LF Projected Ratios'!K$38)) -> 0.74518127 | ... AF93: =IF('LF Projected Ratios'!AG$38>=0,$B93+(1-$B93)*'LF Projected Ratios'!AG$38,$B93*(1+'LF Projected Ratios'!AG$38)) -> 0.7011323
