Workbook
Name dollars_2020_2012: [1]About!$A$104
Name dollars_2021_2012: [1]About!$A$103
Name lignite_multiplier: '[1]Hard Coal and Lig Multipliers'!$N$15
Name nonlignite_multiplier: '[1]Hard Coal and Lig Multipliers'!$N$16
Name nonlignite_multiplier: '[1]Hard Coal and Lig Multipliers'!$N$16
Name nonlignite_multiplier: '[1]Hard Coal and Lig Multipliers'!$N$16
Name nonlignite_multiplier: '[2]Hard Coal and Lig Multipliers'!$N$15

Sheet About
A1: IMFPbFT International Market Fuel Price by Fuel Type
A3: Source: | B3: see fuels/BFPaT and EPS outputs referenced in BAU Fuel Use by Sector tab
A4: Natural Gas Price Source:
B5: AEO Table 60 | C5: https://www.eia.gov/outlooks/aeo/data/browser/#/?id=76-AEO2021&region=0-0&cases=highogs&start=2019&end=2050&f=A&sourcekey=0
B6: AEO Table 13 | C6: https://www.eia.gov/outlooks/aeo/data/browser/#/?id=13-AEO2021&cases=ref2021&sourcekey=0
B7: EIA Natural Gas Prices | C7: https://www.eia.gov/dnav/ng/ng_pri_sum_dcu_nus_m.htm
B8: Henry Hub Prices | C8: https://www.eia.gov/dnav/ng/hist/rngwhhdA.htm
A9: Notes
A10: The prices in this variable should include export taxes, if any. In other words, they should be
A11: the prices paid on the global market. For more details on export taxes, see variable fuels/ETRbF.
A13: Electricity exports are handled separately (in the power sector), not in this variable.
A15: Nuclear here refers to nuclear fuel, i.e. uranium oxide, not electricity from nuclear plants.
A17: We estimate this value based on the prices seen within the United States.
A18: For fuels that vary by sector, we take a weighted average based on the first year consumption in the model.
A20: Natural gas prices
A21: Estimated by creating an average multiplier for pipeline and lng gas compared to henry hub prices.
A22: Use futures prices forecast of henry hub prices multiplied by pipeline and lng multiplier to get forecasted natural gas export prices for 2022-2025.
A23: Linearly interpolated between 2025 and 2030.
A24: Use AEO forecast of henry hub prices multiplied by pipeline and lng multiplier to get forecasted natural gas export prices for 2030-2050.
A25: Created weighted total natural gas export price based on forecasted export volumes of pipeline and lng (AEO 60).
A27: mmbtu per thousand cubic feet | B27: 1.037
A28: 2020 to 2012 $ | B28: 0.887
A29: 2021 to 2012 $ | B29: =0.847 -> 0.847
A30: 2022 to 2012 $ | B30: 0.785
A31: 2024 to 2012 $ | B31: 0.73191601

Sheet AEO 2022 Table 13
A1: Table 13. Natural Gas Supply, Disposition, and Prices
A2: https://www.eia.gov/outlooks/aeo/data/browser/#/?id=13-AEO2022&region=0-0&cases=ref2022&start=2020&end=2050&f=A&sourcekey=0
A3: Fri Jun 03 2022 14:36:16 GMT-0700 (Pacific Daylight Time)
A4: Source: U.S. Energy Information Administration
B5: full name | C5: api key | D5: units | E5: 2020 | F5: 2021 | G5: 2022 | H5: 2023 | I5: 2024 | J5: 2025 | K5: 2026 | L5: 2027 | M5: 2028 | N5: 2029 | O5: 2030 | P5: 2031 | Q5: 2032 | R5: 2033 | S5: 2034 | T5: 2035 | U5: 2036 | V5: 2037 | W5: 2038 | X5: 2039 | Y5: 2040 | Z5: 2041 | AA5: 2042 | AB5: 2043 | AC5: 2044 | AD5: 2045 | AE5: 2046 | AF5: 2047 | AG5: 2048 | AH5: 2049 | AI5: 2050 | AJ5: Growth (2021-2050)
A6: Production | C6: 13-AEO2022.2.
A7: Dry Gas Production | B7: Natural Gas: Production: Dry Gas Production: Low economic growth | C7: 13-AEO2022.3.lowmacro-d011222a | D7: Tcf | F7: 34.409626 | G7: 35.322708 | H7: 35.604687 | I7: 35.806705 | J7: 35.905468 | K7: 35.882885 | L7: 35.810017 | M7: 36.400112 | N7: 36.655968 | O7: 36.721214 | P7: 36.966469 | Q7: 37.231819 | R7: 37.474743 | S7: 37.30827 | T7: 37.172085 | U7: 37.122219 | V7: 37.233501 | W7: 37.447079 | X7: 37.700321 | Y7: 37.972595 | Z7: 38.092804 | AA7: 38.278564 | AB7: 38.60881 | AC7: 38.921223 | AD7: 39.147614 | AE7: 39.39146 | AF7: 39.666965 | AG7: 39.861118 | AH7: 40.032658 | AI7: 40.400124 | AJ7: 0.006
A8: Supplemental Natural Gas | B8: Natural Gas: Production: Supplemental Natural Gas: Low economic growth | C8: 13-AEO2022.4.lowmacro-d011222a | D8: Tcf | F8: 0.05953 | G8: 0.06312 | H8: 0.062993 | I8: 0.062865 | J8: 0.062738 | K8: 0.062611 | L8: 0.062483 | M8: 0.062483 | N8: 0.062483 | O8: 0.062483 | P8: 0.062483 | Q8: 0.062483 | R8: 0.062483 | S8: 0.062483 | T8: 0.062483 | U8: 0.062483 | V8: 0.062483 | W8: 0.062483 | X8: 0.062483 | Y8: 0.062483 | Z8: 0.062483 | AA8: 0.062483 | AB8: 0.062483 | AC8: 0.062483 | AD8: 0.062483 | AE8: 0.062483 | AF8: 0.062483 | AG8: 0.062483 | AH8: 0.062483 | AI8: 0.062483 | AJ8: 0.002
A9: Net Imports | B9: Natural Gas: Net Imports: Low economic growth | C9: 13-AEO2022.6.lowmacro-d011222a | D9: Tcf | F9: -4.018888 | G9: -5.032922 | H9: -5.319394 | I9: -5.505922 | J9: -5.795665 | K9: -5.835703 | L9: -6.007035 | M9: -6.346346 | N9: -6.726242 | O9: -7.007736 | P9: -7.372563 | Q9: -7.634319 | R9: -7.706789 | S9: -7.787818 | T9: -7.890796 | U9: -7.918286 | V9: -7.883421 | W9: -7.908661 | X9: -7.962761 | Y9: -8.031993 | Z9: -8.043514 | AA9: -8.068309 | AB9: -8.137873 | AC9: -8.294017 | AD9: -8.36681 | AE9: -8.370378 | AF9: -8.386253 | AG9: -8.38794 | AH9: -8.39177 | AI9: -8.429087 | AJ9: 0.026
A10: Pipeline | B10: Natural Gas: Net Imports: Pipeline: Low economic growth | C10: 13-AEO2022.7.lowmacro-d011222a | D10: Tcf | F10: -0.476819 | G10: -0.916066 | H10: -0.959442 | I10: -1.099447 | J10: -1.217244 | K10: -1.243205 | L10: -1.312514 | M10: -1.43905 | N10: -1.631721 | O10: -1.713215 | P10: -1.878042 | Q10: -1.927022 | R10: -1.912268 | S10: -1.993297 | T10: -2.096275 | U10: -2.11099 | V10: -2.088901 | W10: -2.11414 | X10: -2.16824 | Y10: -2.224696 | Z10: -2.248994 | AA10: -2.273788 | AB10: -2.343352 | AC10: -2.486721 | AD10: -2.572289 | AE10: -2.575856 | AF10: -2.591733 | AG10: -2.580644 | AH10: -2.59725 | AI10: -2.634566 | AJ10: 0.061
A11: Liquefied Natural Gas | B11: Natural Gas: Net Imports: Liquefied Natural Gas: Low economic growth | C11: 13-AEO2022.8.lowmacro-d011222a | D11: Tcf | F11: -3.542069 | G11: -4.116855 | H11: -4.359952 | I11: -4.406474 | J11: -4.578421 | K11: -4.592499 | L11: -4.694521 | M11: -4.907297 | N11: -5.094521 | O11: -5.294521 | P11: -5.494521 | Q11: -5.707297 | R11: -5.794521 | S11: -5.794521 | T11: -5.794521 | U11: -5.807297 | V11: -5.794521 | W11: -5.794521 | X11: -5.794521 | Y11: -5.807297 | Z11: -5.794521 | AA11: -5.794521 | AB11: -5.794521 | AC11: -5.807297 | AD11: -5.794521 | AE11: -5.794521 | AF11: -5.794521 | AG11: -5.807297 | AH11: -5.794521 | AI11: -5.794521 | AJ11: 0.017
A12: Total Supply | B12: Natural Gas: Total Supply: Low economic growth | C12: 13-AEO2022.10.lowmacro-d011222a | D12: Tcf | F12: 30.450266 | G12: 30.352909 | H12: 30.348286 | I12: 30.363649 | J12: 30.172539 | K12: 30.109793 | L12: 29.865467 | M12: 30.116251 | N12: 29.99221 | O12: 29.775963 | P12: 29.656391 | Q12: 29.659985 | R12: 29.830439 | S12: 29.582935 | T12: 29.343773 | U12: 29.266418 | V12: 29.412565 | W12: 29.600903 | X12: 29.800045 | Y12: 30.003086 | Z12: 30.111774 | AA12: 30.272739 | AB12: 30.533422 | AC12: 30.68969 | AD12: 30.843288 | AE12: 31.083569 | AF12: 31.343197 | AG12: 31.535664 | AH12: 31.703373 | AI12: 32.033524 | AJ12: 0.002
A13: Consumption by Sector | B13: Natural Gas: Use by Sector: Total: Low economic growth | C13: 13-AEO2022.12.lowmacro-d011222a | D13: Tcf | F13: 30.242594 | G13: 30.085173 | H13: 30.064831 | I13: 30.056604 | J13: 29.859272 | K13: 29.777143 | L13: 29.518978 | M13: 29.768036 | N13: 29.655115 | O13: 29.44602 | P13: 29.328667 | Q13: 29.327215 | R13: 29.514547 | S13: 29.269196 | T13: 29.029827 | U13: 28.959255 | V13: 29.105549 | W13: 29.295654 | X13: 29.500248 | Y13: 29.703928 | Z13: 29.806578 | AA13: 29.968973 | AB13: 30.229542 | AC13: 30.386457 | AD13: 30.550423 | AE13: 30.797487 | AF13: 31.028425 | AG13: 31.22183 | AH13: 31.388659 | AI13: 31.717159 | AJ13: 0.002
A14: Residential | B14: Natural Gas: Use by Sector: Residential: Low economic growth | C14: 13-AEO2022.13.lowmacro-d011222a | D14: Tcf | F14: 4.819419 | G14: 4.87988 | H14: 4.803436 | I14: 4.816045 | J14: 4.830301 | K14: 4.835493 | L14: 4.835128 | M14: 4.826184 | N14: 4.811259 | O14: 4.796466 | P14: 4.782578 | Q14: 4.765706 | R14: 4.748952 | S14: 4.735481 | T14: 4.726693 | U14: 4.720163 | V14: 4.712776 | W14: 4.704755 | X14: 4.69628 | Y14: 4.689078 | Z14: 4.680464 | AA14: 4.673137 | AB14: 4.667832 | AC14: 4.663457 | AD14: 4.659014 | AE14: 4.653883 | AF14: 4.647811 | AG14: 4.64085 | AH14: 4.632444 | AI14: 4.623201 | AJ14: -0.001
A15: Commercial | B15: Natural Gas: Use by Sector: Commercial: Low economic growth | C15: 13-AEO2022.14.lowmacro-d011222a | D15: Tcf | F15: 3.350484 | G15: 3.482587 | H15: 3.428924 | I15: 3.434704 | J15: 3.444488 | K15: 3.443654 | L15: 3.458211 | M15: 3.461361 | N15: 3.456904 | O15: 3.452962 | P15: 3.453952 | Q15: 3.451528 | R15: 3.448314 | S15: 3.448515 | T15: 3.454259 | U15: 3.462657 | V15: 3.468118 | W15: 3.470585 | X15: 3.471409 | Y15: 3.472769 | Z15: 3.472588 | AA15: 3.475296 | AB15: 3.481176 | AC15: 3.487429 | AD15: 3.493799 | AE15: 3.499022 | AF15: 3.502862 | AG15: 3.505532 | AH15: 3.505991 | AI15: 3.505614 | AJ15: 0.002
A16: Industrial | B16: Natural Gas: Use by Sector: Industrial: Low economic growth | C16: 13-AEO2022.15.lowmacro-d011222a | D16: Tcf | F16: 10.38806 | G16: 10.575246 | H16: 10.486811 | I16: 10.540606 | J16: 10.645499 | K16: 10.709901 | L16: 10.719416 | M16: 10.767504 | N16: 10.779654 | O16: 10.815272 | P16: 10.848524 | Q16: 10.876146 | R16: 10.905524 | S16: 10.913145 | T16: 10.922623 | U16: 10.966375 | V16: 10.982613 | W16: 11.020459 | X16: 11.064152 | Y16: 11.106756 | Z16: 11.119011 | AA16: 11.164563 | AB16: 11.248596 | AC16: 11.29722 | AD16: 11.350711 | AE16: 11.430659 | AF16: 11.498 | AG16: 11.531771 | AH16: 11.566927 | AI16: 11.694829 | AJ16: 0.004
A17: Other Industrial | B17: Natural Gas: Use by Sector: Industrial: Other: Low economic growth | C17: 13-AEO2022.16.lowmacro-d011222a | D17: Tcf | F17: 8.25777 | G17: 8.328052 | H17: 8.209694 | I17: 8.235285 | J17: 8.295445 | K17: 8.354473 | L17: 8.355721 | M17: 8.349208 | N17: 8.332207 | O17: 8.328288 | P17: 8.329494 | Q17: 8.313449 | R17: 8.315689 | S17: 8.332453 | T17: 8.340832 | U17: 8.390054 | V17: 8.412317 | W17: 8.446038 | X17: 8.472146 | Y17: 8.496502 | Z17: 8.513413 | AA17: 8.551575 | AB17: 8.608138 | AC17: 8.642073 | AD17: 8.672221 | AE17: 8.737638 | AF17: 8.794087 | AG17: 8.814433 | AH17: 8.846367 | AI17: 8.932115 | AJ17: 0.003
A18: Lease and Plant Fuel | B18: Natural Gas: Use by Sector: Industrial: Lease and Plant Fuel: Low economic growth | C18: 13-AEO2022.17.lowmacro-d011222a | D18: Tcf | F18: 1.840362 | G18: 1.90736 | H18: 1.917754 | I18: 1.942354 | J18: 1.973323 | K18: 1.97772 | L18: 1.977887 | M18: 2.015253 | N18: 2.029239 | O18: 2.052577 | P18: 2.068422 | Q18: 2.094856 | R18: 2.114927 | S18: 2.105785 | T18: 2.106883 | U18: 2.100379 | V18: 2.095387 | W18: 2.099513 | X18: 2.117098 | Y18: 2.134312 | Z18: 2.130689 | AA18: 2.138081 | AB18: 2.16555 | AC18: 2.179204 | AD18: 2.203582 | AE18: 2.218113 | AF18: 2.229005 | AG18: 2.241395 | AH18: 2.245652 | AI18: 2.287807 | AJ18: 0.008
A19: Fuel Used to Liquefy Gas for Export | B19: Natural Gas: Use by Sector: Industrial: Liquefaction for Export: Low economic growth | C19: 13-AEO2022.18.lowmacro-d011222a | D19: Tcf | F19: 0.289928 | G19: 0.339835 | H19: 0.359363 | I19: 0.362967 | J19: 0.376731 | K19: 0.377708 | L19: 0.385808 | M19: 0.403042 | N19: 0.418208 | O19: 0.434408 | P19: 0.450608 | Q19: 0.467842 | R19: 0.474908 | S19: 0.474908 | T19: 0.474908 | U19: 0.475942 | V19: 0.474908 | W19: 0.474908 | X19: 0.474908 | Y19: 0.475942 | Z19: 0.474908 | AA19: 0.474908 | AB19: 0.474908 | AC19: 0.475942 | AD19: 0.474908 | AE19: 0.474908 | AF19: 0.474908 | AG19: 0.475942 | AH19: 0.474908 | AI19: 0.474908 | AJ19: 0.017
A20: Natural Gas-to-Liquids Heat and Power | B20: Natural Gas: Use by Sector: Industrial: GTL Heat and Power: Low economic growth | C20: 13-AEO2022.19.lowmacro-d011222a | D20: Tcf | F20: 0 | G20: 0 | H20: 0 | I20: 0 | J20: 0 | K20: 0 | L20: 0 | M20: 0 | N20: 0 | O20: 0 | P20: 0 | Q20: 0 | R20: 0 | S20: 0 | T20: 0 | U20: 0 | V20: 0 | W20: 0 | X20: 0 | Y20: 0 | Z20: 0 | AA20: 0 | AB20: 0 | AC20: 0 | AD20: 0 | AE20: 0 | AF20: 0 | AG20: 0 | AH20: 0 | AI20: 0 | AJ20: - -
A21: Natural Gas to Liquids Production | B21: Natural Gas: Use by Sector: Industrial: GTL Liquids: Low economic growth | C21: 13-AEO2022.20.lowmacro-d011222a | D21: Tcf | F21: 0 | G21: 0 | H21: 0 | I21: 0 | J21: 0 | K21: 0 | L21: 0 | M21: 0 | N21: 0 | O21: 0 | P21: 0 | Q21: 0 | R21: 0 | S21: 0 | T21: 0 | U21: 0 | V21: 0 | W21: 0 | X21: 0 | Y21: 0 | Z21: 0 | AA21: 0 | AB21: 0 | AC21: 0 | AD21: 0 | AE21: 0 | AF21: 0 | AG21: 0 | AH21: 0 | AI21: 0 | AJ21: - -
A22: Transportation | B22: Natural Gas: Use by Sector: Transportation: Low economic growth | C22: 13-AEO2022.21.lowmacro-d011222a | D22: Tcf | F22: 0.82787 | G22: 0.770456 | H22: 0.769016 | I22: 0.759091 | J22: 0.754646 | K22: 0.751995 | L22: 0.746852 | M22: 0.759835 | N22: 0.761848 | O22: 0.761588 | P22: 0.766947 | Q22: 0.773339 | R22: 0.783053 | S22: 0.781493 | T22: 0.786302 | U22: 0.794828 | V22: 0.808952 | W22: 0.8245 | X22: 0.837743 | Y22: 0.857536 | Z22: 0.870359 | AA22: 0.884783 | AB22: 0.901461 | AC22: 0.921563 | AD22: 0.930299 | AE22: 0.946389 | AF22: 0.964842 | AG22: 0.981295 | AH22: 0.998166 | AI22: 1.012687 | AJ22: 0.007
A23: Motor Vehicles | B23: Trains | C23: and Ships | D23: Natural Gas: Use by Sector: Transportation: Vehicles: Low economic growth | E23: 13-AEO2022.22.lowmacro-d011222a | F23: Tcf | H23: 0.10664 | I23: 0.096182 | J23: 0.113294 | K23: 0.119665 | L23: 0.126026 | M23: 0.135944 | N23: 0.146969 | O23: 0.154949 | P23: 0.162695 | Q23: 0.171487 | R23: 0.180423 | S23: 0.184107 | T23: 0.191779 | U23: 0.199366 | V23: 0.206543 | W23: 0.214237 | X23: 0.222566 | Y23: 0.231628 | Z23: 0.239112 | AA23: 0.253512 | AB23: 0.263027 | AC23: 0.272002 | AD23: 0.284502 | AE23: 0.297652 | AF23: 0.308227 | AG23: 0.321112 | AH23: 0.331511 | AI23: 0.340022 | AJ23: 0.349799 | AK23: 0.405344 | AL23: 0.047
A24: Pipeline and Distribution Fuel | B24: Natural Gas: Use by Sector: Transportation: Pipeline Fuel: Low economic growth | C24: 13-AEO2022.23.lowmacro-d011222a | D24: Tcf | F24: 0.72123 | G24: 0.674274 | H24: 0.655722 | I24: 0.639426 | J24: 0.62862 | K24: 0.616051 | L24: 0.599883 | M24: 0.604886 | N24: 0.599153 | O24: 0.590101 | P24: 0.586524 | Q24: 0.589232 | R24: 0.591273 | S24: 0.582127 | T24: 0.57976 | U24: 0.580591 | V24: 0.586386 | W24: 0.592872 | X24: 0.598631 | Y24: 0.604024 | Z24: 0.607332 | AA24: 0.61278 | AB24: 0.616958 | AC24: 0.623911 | AD24: 0.622073 | AE24: 0.625277 | AF24: 0.633331 | AG24: 0.641273 | AH24: 0.648367 | AI24: 0.653551 | AJ24: -0.003
A25: Electric Power | B25: Natural Gas: Use by Sector: Electric Power: Low economic growth | C25: 13-AEO2022.24.lowmacro-d011222a | D25: Tcf | F25: 10.85676 | G25: 10.377003 | H25: 10.576644 | I25: 10.506159 | J25: 10.184333 | K25: 10.036098 | L25: 9.759375 | M25: 9.953151 | N25: 9.845448 | O25: 9.61973 | P25: 9.476666 | Q25: 9.460497 | R25: 9.628703 | S25: 9.390562 | T25: 9.139952 | U25: 9.015231 | V25: 9.13309 | W25: 9.275352 | X25: 9.430664 | Y25: 9.577788 | Z25: 9.664156 | AA25: 9.771195 | AB25: 9.930477 | AC25: 10.016788 | AD25: 10.116599 | AE25: 10.267536 | AF25: 10.414912 | AG25: 10.56238 | AH25: 10.685132 | AI25: 10.88083 | AJ25: 0
A26: Discrepancy | B26: Natural Gas: Discrepancy: Low economic growth | C26: 13-AEO2022.26.lowmacro-d011222a | D26: Tcf | F26: 0.207672 | G26: 0.267736 | H26: 0.283455 | I26: 0.307045 | J26: 0.313267 | K26: 0.332649 | L26: 0.346489 | M26: 0.348215 | N26: 0.337095 | O26: 0.329943 | P26: 0.327724 | Q26: 0.332769 | R26: 0.315891 | S26: 0.31374 | T26: 0.313946 | U26: 0.307163 | V26: 0.307016 | W26: 0.305248 | X26: 0.299797 | Y26: 0.299158 | Z26: 0.305197 | AA26: 0.303766 | AB26: 0.303881 | AC26: 0.303232 | AD26: 0.292866 | AE26: 0.286081 | AF26: 0.314772 | AG26: 0.313833 | AH26: 0.314714 | AI26: 0.316364 | AJ26: - -
A27: Natural Gas Prices | C27: 13-AEO2022.28.
A28: Natural Gas Spot Price at Henry Hub | C28: 13-AEO2022.30.
A29: (2021 dollars per million Btu) | B29: Natural Gas: Henry Hub Spot Price: Low economic growth | C29: 13-AEO2022.31.lowmacro-d011222a | D29: 2021 $/MMBtu | F29: 4.115437 | G29: 3.837557 | H29: 3.471147 | I29: 3.126585 | J29: 2.953741 | K29: 2.906966 | L29: 2.954549 | M29: 3.136157 | N29: 3.292231 | O29: 3.388971 | P29: 3.454448 | Q29: 3.491858 | R29: 3.59329 | S29: 3.594153 | T29: 3.524364 | U29: 3.485305 | V29: 3.48693 | W29: 3.51827 | X29: 3.545613 | Y29: 3.577658 | Z29: 3.63465 | AA29: 3.652029 | AB29: 3.589562 | AC29: 3.561126 | AD29: 3.469676 | AE29: 3.425366 | AF29: 3.400315 | AG29: 3.392432 | AH29: 3.403568 | AI29: 3.409512 | AJ29: -0.006
A30: Delivered Prices | C30: 13-AEO2022.33.
A31: (2021 dollars per thousand cubic feet) | C31: 13-AEO2022.34.
A32: Residential | B32: Natural Gas: Delivered Prices: Residential: Low economic growth | C32: 13-AEO2022.35.lowmacro-d011222a | D32: 2021 $/Mcf | F32: 12.171644 | G32: 12.625865 | H32: 11.979866 | I32: 11.480213 | J32: 11.157559 | K32: 10.968821 | L32: 10.837678 | M32: 10.981541 | N32: 11.152151 | O32: 11.246775 | P32: 11.342472 | Q32: 11.68836 | R32: 11.833169 | S32: 11.888336 | T32: 11.88853 | U32: 11.856069 | V32: 11.895705 | W32: 11.930015 | X32: 11.970271 | Y32: 12.000363 | Z32: 12.084126 | AA32: 12.079756 | AB32: 12.043774 | AC32: 12.028834 | AD32: 11.998742 | AE32: 11.996384 | AF32: 12.001075 | AG32: 12.006783 | AH32: 12.045881 | AI32: 12.069625 | AJ32: 0
A33: Commercial | B33: Natural Gas: Delivered Prices: Commercial: Low economic growth | C33: 13-AEO2022.36.lowmacro-d011222a | D33: 2021 $/Mcf | F33: 8.771839 | G33: 9.162567 | H33: 8.828384 | I33: 8.499667 | J33: 8.33059 | K33: 8.281426 | L33: 8.273354 | M33: 8.399084 | N33: 8.544633 | O33: 8.616765 | P33: 8.690123 | Q33: 8.905362 | R33: 9.008744 | S33: 9.037756 | T33: 9.009416 | U33: 8.96355 | V33: 8.989129 | W33: 9.011681 | X33: 9.040559 | Y33: 9.060416 | Z33: 9.132076 | AA33: 9.116379 | AB33: 9.069324 | AC33: 9.045333 | AD33: 9.007052 | AE33: 8.995634 | AF33: 8.99243 | AG33: 8.990973 | AH33: 9.022299 | AI33: 9.039542 | AJ33: 0.001
A34: Industrial | B34: Natural Gas: Delivered Prices: Industrial: Low economic growth | C34: 13-AEO2022.37.lowmacro-d011222a | D34: 2021 $/Mcf | F34: 5.269056 | G34: 5.03236 | H34: 4.688 | I34: 4.317468 | J34: 4.135796 | K34: 4.079431 | L34: 4.111363 | M34: 4.275023 | N34: 4.428134 | O34: 4.517744 | P34: 4.577354 | Q34: 4.57688 | R34: 4.677366 | S34: 4.682547 | T34: 4.609011 | U34: 4.556269 | V34: 4.554906 | W34: 4.577663 | X34: 4.599112 | Y34: 4.622378 | Z34: 4.678865 | AA34: 4.686431 | AB34: 4.620964 | AC34: 4.584721 | AD34: 4.508954 | AE34: 4.477705 | AF34: 4.458506 | AG34: 4.452824 | AH34: 4.463304 | AI34: 4.471565 | AJ34: -0.006
A35: Transportation | B35: Natural Gas: Delivered Prices: Transportation: Low economic growth | C35: 13-AEO2022.38.lowmacro-d011222a | D35: 2021 $/Mcf | F35: 15.22551 | G35: 15.189867 | H35: 14.413707 | I35: 13.82573 | J35: 13.402384 | K35: 13.030856 | L35: 12.741631 | M35: 12.603173 | N35: 12.474068 | O35: 12.308931 | P35: 12.141323 | Q35: 12.813327 | R35: 12.722208 | S35: 12.575328 | T35: 12.46647 | U35: 12.278451 | V35: 12.158415 | W35: 12.07103 | X35: 11.987044 | Y35: 11.964777 | Z35: 11.952209 | AA35: 11.886301 | AB35: 11.783961 | AC35: 11.709952 | AD35: 11.603604 | AE35: 11.546721 | AF35: 11.496274 | AG35: 11.448224 | AH35: 11.422692 | AI35: 11.379571 | AJ35: -0.01
A36: Electric Power | B36: Natural Gas: Delivered Prices: Electric Power: Low economic growth | C36: 13-AEO2022.39.lowmacro-d011222a | D36: 2021 $/Mcf | F36: 5.332857 | G36: 4.178648 | H36: 3.885905 | I36: 3.547021 | J36: 3.377793 | K36: 3.342421 | L36: 3.381722 | M36: 3.556563 | N36: 3.688859 | O36: 3.763834 | P36: 3.807873 | Q36: 3.82572 | R36: 3.921008 | S36: 3.904177 | T36: 3.798467 | U36: 3.750271 | V36: 3.744769 | W36: 3.767939 | X36: 3.793509 | Y36: 3.829679 | Z36: 3.882215 | AA36: 3.881239 | AB36: 3.803053 | AC36: 3.765003 | AD36: 3.692361 | AE36: 3.66632 | AF36: 3.650438 | AG36: 3.654424 | AH36: 3.66035 | AI36: 3.687017 | AJ36: -0.013
A37: Average | B37: Natural Gas: Delivered Prices: Average: Low economic growth | C37: 13-AEO2022.40.lowmacro-d011222a | D37: 2021 $/Mcf | F37: 6.975946 | G37: 6.635291 | H37: 6.229839 | I37: 5.862714 | J37: 5.690771 | K37: 5.630795 | L37: 5.656798 | M37: 5.799069 | N37: 5.953547 | O37: 6.053108 | P37: 6.125708 | Q37: 6.227705 | R37: 6.316007 | S37: 6.343978 | T37: 6.301665 | U37: 6.264091 | V37: 6.259395 | W37: 6.268137 | X37: 6.278011 | Y37: 6.292707 | Z37: 6.344999 | AA37: 6.332001 | AB37: 6.253158 | AC37: 6.213667 | AD37: 6.142462 | AE37: 6.105012 | AF37: 6.077645 | AG37: 6.06405 | AH37: 6.067497 | AI37: 6.06418 | AJ37: -0.005
A38: Natural Gas Spot Price at Henry Hub | C38: 13-AEO2022.59.
A39: (nominal dollars per million Btu) | B39: Natural Gas: Henry Hub Spot Price: Low economic growth | C39: 13-AEO2022.60.lowmacro-d011222a | D39: nom $/MMBtu | F39: 4.115437 | G39: 3.961129 | H39: 3.67353 | I39: 3.407579 | J39: 3.321223 | K39: 3.380046 | L39: 3.55681 | M39: 3.909547 | N39: 4.247153 | O39: 4.519075 | P39: 4.759894 | Q39: 4.967306 | R39: 5.278396 | S39: 5.456114 | T39: 5.532805 | U39: 5.659725 | V39: 5.858712 | W39: 6.116162 | X39: 6.373682 | Y39: 6.653007 | Z39: 6.991181 | AA39: 7.266311 | AB39: 7.385303 | AC39: 7.573573 | AD39: 7.62625 | AE39: 7.781052 | AF39: 7.982764 | AG39: 8.228611 | AH39: 8.525277 | AI39: 8.814068 | AJ39: 0.027
A40: Delivered Prices | C40: 13-AEO2022.66.
A41: (nominal dollars per thousand cubic feet) | C41: 13-AEO2022.67.
A42: Residential | B42: Natural Gas: Delivered Prices: Residential: Low economic growth | C42: 13-AEO2022.68.lowmacro-d011222a | D42: nom $/Mcf | F42: 12.171644 | G42: 13.032427 | H42: 12.678345 | I42: 12.511969 | J42: 12.5457 | K42: 12.753887 | L42: 13.046851 | M42: 13.689635 | N42: 14.386866 | O42: 14.997186 | P42: 15.628823 | Q42: 16.627151 | R42: 17.382442 | S42: 18.047121 | T42: 18.663486 | U42: 19.252861 | V42: 19.98707 | W42: 20.73914 | X42: 21.518059 | Y42: 22.315857 | Z42: 23.243591 | AA42: 24.034658 | AB42: 24.779325 | AC42: 25.582144 | AD42: 26.372894 | AE42: 27.250956 | AF42: 28.174376 | AG42: 29.1234 | AH42: 30.172592 | AI42: 31.201681 | AJ42: 0.033
A43: Commercial | B43: Natural Gas: Delivered Prices: Commercial: Low economic growth | C43: 13-AEO2022.69.lowmacro-d011222a | D43: nom $/Mcf | F43: 8.771839 | G43: 9.457608 | H43: 9.343118 | I43: 9.263554 | J43: 9.367021 | K43: 9.629147 | L43: 9.95981 | M43: 10.470333 | N43: 11.023029 | O43: 11.490159 | P43: 11.974144 | Q43: 12.668225 | R43: 13.233478 | S43: 13.71979 | T43: 14.143641 | U43: 14.555749 | V43: 15.103463 | W43: 15.665908 | X43: 16.251535 | Y43: 16.848736 | Z43: 17.56538 | AA43: 18.138533 | AB43: 18.659576 | AC43: 19.237028 | AD43: 19.797245 | AE43: 20.43446 | AF43: 21.111115 | AG43: 21.808311 | AH43: 22.599108 | AI43: 23.36849 | AJ43: 0.034
A44: Industrial | B44: Natural Gas: Delivered Prices: Industrial: Low economic growth | C44: 13-AEO2022.70.lowmacro-d011222a | D44: nom $/Mcf | F44: 5.269056 | G44: 5.194405 | H44: 4.961331 | I44: 4.70549 | J44: 4.650341 | K44: 4.743318 | L44: 4.949431 | M44: 5.329262 | N44: 5.712528 | O44: 6.024255 | P44: 6.307149 | Q44: 6.510792 | R44: 6.87086 | S44: 7.108353 | T44: 7.235563 | U44: 7.398845 | V44: 7.653116 | W44: 7.95781 | X44: 8.267478 | Y44: 8.595767 | Z44: 8.999711 | AA44: 9.324426 | AB44: 9.50735 | AC44: 9.750486 | AD44: 9.910552 | AE44: 10.171543 | AF44: 10.46703 | AG44: 10.800675 | AH44: 11.179709 | AI44: 11.559625 | AJ44: 0.027
A45: Transportation | B45: Natural Gas: Delivered Prices: Transportation: Low economic growth | C45: 13-AEO2022.71.lowmacro-d011222a | D45: nom $/Mcf | F45: 15.22551 | G45: 15.678991 | H45: 15.254088 | I45: 15.068284 | J45: 15.06981 | K45: 15.151498 | L45: 15.33891 | M45: 15.711169 | N45: 16.092209 | O45: 16.413536 | P45: 16.729563 | Q45: 18.227459 | R45: 18.688402 | S45: 19.090012 | T45: 19.570778 | U45: 19.938759 | V45: 20.428473 | W45: 20.984282 | X45: 21.54821 | Y45: 22.24968 | Z45: 22.989855 | AA45: 23.649748 | AB45: 24.244778 | AC45: 24.903967 | AD45: 25.504393 | AE45: 26.229502 | AF45: 26.989277 | AG45: 27.76857 | AH45: 28.611628 | AI45: 29.417795 | AJ45: 0.023
A46: Electric Power | B46: Natural Gas: Delivered Prices: Electric Power: Low economic growth | C46: 13-AEO2022.72.lowmacro-d011222a | D46: nom $/Mcf | F46: 5.332857 | G46: 4.313203 | H46: 4.112471 | I46: 3.865801 | J46: 3.798033 | K46: 3.886366 | L46: 4.071059 | M46: 4.433627 | N46: 4.758823 | O46: 5.018943 | P46: 5.24688 | Q46: 5.442236 | R46: 5.7598 | S46: 5.926747 | T46: 5.963112 | U46: 6.089999 | V46: 6.291931 | W46: 6.550187 | X46: 6.819307 | Y46: 7.121665 | Z46: 7.46737 | AA46: 7.722362 | AB46: 7.824549 | AC46: 8.007165 | AD46: 8.115704 | AE46: 8.328403 | AF46: 8.569965 | AG46: 8.864093 | AH46: 9.168466 | AI46: 9.531458 | AJ46: 0.02
A47: Average | B47: Natural Gas: Delivered Prices: Average: Low economic growth | C47: 13-AEO2022.73.lowmacro-d011222a | D47: nom $/Mcf | F47: 6.975946 | G47: 6.848952 | H47: 6.593066 | I47: 6.389611 | J47: 6.398775 | K47: 6.547151 | L47: 6.809891 | M47: 7.229145 | N47: 7.680391 | O47: 8.071611 | P47: 8.44063 | Q47: 8.859155 | R47: 9.277956 | S47: 9.630492 | T47: 9.892816 | U47: 10.172147 | V47: 10.516985 | W47: 10.89653 | X47: 11.28551 | Y47: 11.701908 | Z47: 12.204488 | AA47: 12.598556 | AB47: 12.865489 | AC47: 13.214825 | AD47: 13.500958 | AE47: 13.868131 | AF47: 14.268209 | AG47: 14.708831 | AH47: 15.197902 | AI47: 15.67676 | AJ47: 0.028

Sheet AEO 2023 Table 13
A1: Table 13. Natural Gas Supply, Disposition, and Prices
A2: https://www.eia.gov/outlooks/aeo/data/browser/#/?id=13-AEO2023&cases=ref2023&sourcekey=0
A3: Thu Apr 13 2023 09:58:18 GMT-0400 (Eastern Daylight Time)
A4: Source: U.S. Energy Information Administration
B5: full name | C5: api key | D5: units | E5: 2021 | F5: 2022 | G5: 2023 | H5: 2024 | I5: 2025 | J5: 2026 | K5: 2027 | L5: 2028 | M5: 2029 | N5: 2030 | O5: 2031 | P5: 2032 | Q5: 2033 | R5: 2034 | S5: 2035 | T5: 2036 | U5: 2037 | V5: 2038 | W5: 2039 | X5: 2040 | Y5: 2041 | Z5: 2042 | AA5: 2043 | AB5: 2044 | AC5: 2045 | AD5: 2046 | AE5: 2047 | AF5: 2048 | AG5: 2049 | AH5: 2050 | AI5: Growth (2022-2050)
A6: Production
A7: Dry Gas Production | B7: Natural Gas: Production: Dry Gas Production: Reference case | C7: AEO.2023.REF2023.SUP_PRD_NA_NA_NG_DNG_USA_TRLCF.A | D7: Tcf | F7: 36.465069 | G7: 36.485851 | H7: 35.567017 | I7: 35.725479 | J7: 36.183468 | K7: 36.13615 | L7: 36.43782 | M7: 36.679688 | N7: 37.035736 | O7: 37.466896 | P7: 37.973099 | Q7: 38.551033 | R7: 39.045914 | S7: 39.497391 | T7: 39.857361 | U7: 40.219318 | V7: 40.491047 | W7: 40.733463 | X7: 40.870892 | Y7: 40.98983 | Z7: 41.16486 | AA7: 41.277199 | AB7: 41.354496 | AC7: 41.505783 | AD7: 41.340649 | AE7: 41.544994 | AF7: 41.613247 | AG7: 41.692951 | AH7: 42.065376 | AI7: 0.005
A8: Supplemental Natural Gas | B8: Natural Gas: Production: Supplemental Natural Gas: Reference case | C8: AEO.2023.REF2023.SUP_PRD_NA_NA_NG_SPNG_USA_TRLCF.A | D8: Tcf | F8: 0.066783 | G8: 0.068295 | H8: 0.067215 | I8: 0.066134 | J8: 0.065053 | K8: 0.063973 | L8: 0.062892 | M8: 0.062892 | N8: 0.062892 | O8: 0.062892 | P8: 0.062892 | Q8: 0.062892 | R8: 0.062892 | S8: 0.062892 | T8: 0.062892 | U8: 0.062892 | V8: 0.062892 | W8: 0.062892 | X8: 0.062892 | Y8: 0.062892 | Z8: 0.062892 | AA8: 0.062892 | AB8: 0.062892 | AC8: 0.062892 | AD8: 0.062892 | AE8: 0.062892 | AF8: 0.062892 | AG8: 0.062892 | AH8: 0.062892 | AI8: -0.002
A9: Net Imports | B9: Natural Gas: Net Imports: Reference case | C9: AEO.2023.REF2023.TRAD_NETIMP_NA_NA_NG_NA_USA_TRLCF.A | D9: Tcf | F9: -4.184249 | G9: -5.135025 | H9: -5.471915 | I9: -5.969136 | J9: -6.566689 | K9: -7.050437 | L9: -7.555391 | M9: -7.942295 | N9: -8.553591 | O9: -9.253424 | P9: -9.895041 | Q9: -10.548451 | R9: -11.116964 | S9: -11.524033 | T9: -11.819523 | U9: -12.03135 | V9: -12.089127 | W9: -12.149171 | X9: -12.05528 | Y9: -12.019996 | Z9: -12.016218 | AA9: -11.976196 | AB9: -11.936414 | AC9: -11.84736 | AD9: -11.800188 | AE9: -11.753365 | AF9: -11.711053 | AG9: -11.659772 | AH9: -11.61386 | AI9: 0.037
A10: Pipeline | B10: Natural Gas: Net Imports: Pipeline: Reference case | C10: AEO.2023.REF2023.TRAD_NETIMP_NA_NA_NG_PIPL_USA_TRLCF.A | D10: Tcf | F10: -0.251181 | G10: -0.656535 | H10: -0.92837 | I10: -1.137381 | J10: -1.295535 | K10: -1.418052 | L10: -1.615046 | M10: -1.716692 | N10: -1.727988 | O10: -1.82782 | P10: -1.854696 | Q10: -1.922849 | R10: -1.991361 | S10: -2.098429 | T10: -2.179178 | U10: -2.205747 | V10: -2.163523 | W10: -2.223567 | X10: -2.114935 | Y10: -2.094392 | Z10: -2.090615 | AA10: -2.050593 | AB10: -1.996069 | AC10: -1.921756 | AD10: -1.874585 | AE10: -1.827761 | AF10: -1.770708 | AG10: -1.734168 | AH10: -1.688256 | AI10: 0.07
A11: Liquefied Natural Gas | B11: Natural Gas: Net Imports: Liquefied Natural Gas: Reference case | C11: AEO.2023.REF2023.TRAD_NETIMP_NA_NA_NG_LNG_USA_TRLCF.A | D11: Tcf | F11: -3.933068 | G11: -4.47849 | H11: -4.543546 | I11: -4.831755 | J11: -5.271153 | K11: -5.632385 | L11: -5.940345 | M11: -6.225603 | N11: -6.825603 | O11: -7.425603 | P11: -8.040345 | Q11: -8.625603 | R11: -9.125603 | S11: -9.425603 | T11: -9.640346 | U11: -9.825603 | V11: -9.925603 | W11: -9.925603 | X11: -9.940345 | Y11: -9.925603 | Z11: -9.925603 | AA11: -9.925603 | AB11: -9.940345 | AC11: -9.925603 | AD11: -9.925603 | AE11: -9.925603 | AF11: -9.940345 | AG11: -9.925603 | AH11: -9.925603 | AI11: 0.034
A12: Total Supply | B12: Natural Gas: Total Supply: Reference case | C12: AEO.2023.REF2023.SUP_NA_TOT_NA_NG_NA_USA_TRLCF.A | D12: Tcf | F12: 32.347603 | G12: 31.419121 | H12: 30.162315 | I12: 29.822479 | J12: 29.681831 | K12: 29.149685 | L12: 28.945322 | M12: 28.800285 | N12: 28.545038 | O12: 28.276365 | P12: 28.140951 | Q12: 28.065475 | R12: 27.991842 | S12: 28.036251 | T12: 28.100731 | U12: 28.250862 | V12: 28.464813 | W12: 28.647186 | X12: 28.878506 | Y12: 29.032726 | Z12: 29.211535 | AA12: 29.363895 | AB12: 29.480976 | AC12: 29.721317 | AD12: 29.603354 | AE12: 29.854523 | AF12: 29.965088 | AG12: 30.096073 | AH12: 30.514408 | AI12: -0.002
A13: Consumption by Sector | B13: Natural Gas: Use by Sector: Total: Reference case | C13: AEO.2023.REF2023.CNSM_NA_ALLS_NA_NG_TOT_USA_TRLCF.A | D13: Tcf | F13: 32.0019 | G13: 30.83448 | H13: 29.646107 | I13: 29.365435 | J13: 29.27512 | K13: 28.788441 | L13: 28.623919 | M13: 28.478455 | N13: 28.230896 | O13: 27.957972 | P13: 27.826681 | Q13: 27.740482 | R13: 27.671423 | S13: 27.676506 | T13: 27.779486 | U13: 27.932875 | V13: 28.156765 | W13: 28.337158 | X13: 28.564293 | Y13: 28.715166 | Z13: 28.903845 | AA13: 29.067936 | AB13: 29.189127 | AC13: 29.33363 | AD13: 29.315384 | AE13: 29.439484 | AF13: 29.640429 | AG13: 29.790031 | AH13: 30.00979 | AI13: -0.002
A14: Residential | B14: Natural Gas: Use by Sector: Residential: Reference case | C14: AEO.2023.REF2023.CNSM_NA_RESD_NA_NG_NA_USA_TRLCF.A | D14: Tcf | F14: 4.956103 | G14: 4.991772 | H14: 4.758877 | I14: 4.787258 | J14: 4.812247 | K14: 4.827975 | L14: 4.836563 | M14: 4.83274 | N14: 4.822402 | O14: 4.807221 | P14: 4.791358 | Q14: 4.783406 | R14: 4.772306 | S14: 4.761995 | T14: 4.754158 | U14: 4.747469 | V14: 4.739067 | W14: 4.733147 | X14: 4.728353 | Y14: 4.723671 | Z14: 4.719968 | AA14: 4.718853 | AB14: 4.720119 | AC14: 4.719804 | AD14: 4.71269 | AE14: 4.708236 | AF14: 4.70734 | AG14: 4.707267 | AH14: 4.705333 | AI14: -0.002
A15: Commercial | B15: Natural Gas: Use by Sector: Commercial: Reference case | C15: AEO.2023.REF2023.CNSM_NA_COMM_NA_NG_NA_USA_TRLCF.A | D15: Tcf | F15: 3.467453 | G15: 3.474621 | H15: 3.371255 | I15: 3.408176 | J15: 3.444571 | K15: 3.463666 | L15: 3.492099 | M15: 3.507773 | N15: 3.518465 | O15: 3.527853 | P15: 3.534745 | Q15: 3.535379 | R15: 3.533345 | S15: 3.529708 | T15: 3.527303 | U15: 3.523382 | V15: 3.514469 | W15: 3.507703 | X15: 3.499254 | Y15: 3.490335 | Z15: 3.482872 | AA15: 3.47906 | AB15: 3.478466 | AC15: 3.474299 | AD15: 3.463223 | AE15: 3.456198 | AF15: 3.454088 | AG15: 3.4524 | AH15: 3.44776 | AI15: 0
A16: Industrial | B16: Natural Gas: Use by Sector: Industrial: Reference case | C16: AEO.2023.REF2023.CNSM_NA_IDAL_NA_NG_NA_USA_TRLCF.A | D16: Tcf | F16: 10.480146 | G16: 10.226862 | H16: 10.131637 | I16: 10.278058 | J16: 10.51756 | K16: 10.654901 | L16: 10.790815 | M16: 10.848591 | N16: 10.895127 | O16: 10.918686 | P16: 10.984386 | Q16: 11.023491 | R16: 11.092604 | S16: 11.149645 | T16: 11.237076 | U16: 11.30991 | V16: 11.372004 | W16: 11.465014 | X16: 11.521564 | Y16: 11.596119 | Z16: 11.678681 | AA16: 11.764809 | AB16: 11.847437 | AC16: 11.907819 | AD16: 11.919591 | AE16: 12.003326 | AF16: 12.115173 | AG16: 12.20997 | AH16: 12.331114 | AI16: 0.006
A17: Other Industrial | B17: Natural Gas: Use by Sector: Industrial: Other: Reference case | C17: AEO.2023.REF2023.CNSM_NA_IDAL_OTH_NG_NA_USA_TRLCF.A | D17: Tcf | F17: 8.49547 | G17: 8.208763 | H17: 8.124475 | I17: 8.262086 | J17: 8.473062 | K17: 8.609991 | L17: 8.714933 | M17: 8.767846 | N17: 8.803032 | O17: 8.814925 | P17: 8.852177 | Q17: 8.873966 | R17: 8.926038 | S17: 8.972638 | T17: 9.032281 | U17: 9.087664 | V17: 9.140488 | W17: 9.213684 | X17: 9.271225 | Y17: 9.343618 | Z17: 9.409446 | AA17: 9.478456 | AB17: 9.536632 | AC17: 9.58894 | AD17: 9.591058 | AE17: 9.673329 | AF17: 9.757198 | AG17: 9.837563 | AH17: 9.950478 | AI17: 0.006
A18: Lease and Plant Fuel | B18: Natural Gas: Use by Sector: Industrial: Lease and Plant Fuel: Reference case | C18: AEO.2023.REF2023.CNSM_NA_LAP_NA_NG_LSAPFL_USA_TRLCF.A | D18: Tcf | F18: 1.984676 | G18: 2.018099 | H18: 2.007162 | I18: 2.015972 | J18: 2.044499 | K18: 2.044909 | L18: 2.075882 | M18: 2.080745 | N18: 2.092096 | O18: 2.10376 | P18: 2.132209 | Q18: 2.149524 | R18: 2.166565 | S18: 2.177007 | T18: 2.204795 | U18: 2.222246 | V18: 2.231516 | W18: 2.251329 | X18: 2.25034 | Y18: 2.2525 | Z18: 2.269236 | AA18: 2.286354 | AB18: 2.310805 | AC18: 2.318879 | AD18: 2.328533 | AE18: 2.329997 | AF18: 2.357975 | AG18: 2.372407 | AH18: 2.380637 | AI18: 0.007
A19: Natural Gas-to-Liquids Heat and Power | B19: Natural Gas: Use by Sector: Industrial: GTL Heat and Power: Reference case | C19: AEO.2023.REF2023.CNSM_NA_IDAL_HAP_NG_FT_USA_TRLCF.A | D19: Tcf | F19: 0 | G19: 0 | H19: 0 | I19: 0 | J19: 0 | K19: 0 | L19: 0 | M19: 0 | N19: 0 | O19: 0 | P19: 0 | Q19: 0 | R19: 0 | S19: 0 | T19: 0 | U19: 0 | V19: 0 | W19: 0 | X19: 0 | Y19: 0 | Z19: 0 | AA19: 0 | AB19: 0 | AC19: 0 | AD19: 0 | AE19: 0 | AF19: 0 | AG19: 0 | AH19: 0 | AI19: - -
A20: Natural Gas to Liquids Production | B20: Natural Gas: Use by Sector: Industrial: GTL Liquids: Reference case | C20: AEO.2023.REF2023.CNSM_NA_IDAL_FSK_NG_FT_USA_TRLCF.A | D20: Tcf | F20: 0 | G20: 0 | H20: 0 | I20: 0 | J20: 0 | K20: 0 | L20: 0 | M20: 0 | N20: 0 | O20: 0 | P20: 0 | Q20: 0 | R20: 0 | S20: 0 | T20: 0 | U20: 0 | V20: 0 | W20: 0 | X20: 0 | Y20: 0 | Z20: 0 | AA20: 0 | AB20: 0 | AC20: 0 | AD20: 0 | AE20: 0 | AF20: 0 | AG20: 0 | AH20: 0 | AI20: - -
A21: Transportation | B21: Natural Gas: Use by Sector: Transportation: Reference case | C21: AEO.2023.REF2023.CNSM_NA_TRN_NA_NG_NA_USA_TRLCF.A | D21: Tcf | F21: 1.298378 | G21: 1.266994 | H21: 1.225015 | I21: 1.213742 | J21: 1.23106 | K21: 1.222495 | L21: 1.214443 | M21: 1.239322 | N21: 1.28755 | O21: 1.338387 | P21: 1.394878 | Q21: 1.451291 | R21: 1.498329 | S21: 1.52884 | T21: 1.552042 | U21: 1.571726 | V21: 1.589475 | W21: 1.596188 | X21: 1.612993 | Y21: 1.626597 | Z21: 1.640996 | AA21: 1.654405 | AB21: 1.669935 | AC21: 1.683864 | AD21: 1.697575 | AE21: 1.718812 | AF21: 1.742685 | AG21: 1.759869 | AH21: 1.780975 | AI21: 0.011
A22: Motor Vehicles | B22: Trains | C22: and Ships | D22: Natural Gas: Use by Sector: Transportation: Vehicles: Reference case | E22: AEO.2023.REF2023.CNSM_NA_MVF_NA_NG_NA_USA_TRLCF.A | F22: Tcf | H22: 0.104304 | I22: 0.111244 | J22: 0.120881 | K22: 0.118723 | L22: 0.1297 | M22: 0.131696 | N22: 0.136779 | O22: 0.140379 | P22: 0.141662 | Q22: 0.142376 | R22: 0.143415 | S22: 0.144205 | T22: 0.146421 | U22: 0.150018 | V22: 0.155319 | W22: 0.160994 | X22: 0.165954 | Y22: 0.173789 | Z22: 0.180587 | AA22: 0.189002 | AB22: 0.197866 | AC22: 0.208548 | AD22: 0.218929 | AE22: 0.230091 | AF22: 0.238662 | AG22: 0.252568 | AH22: 0.268154 | AI22: 0.284226 | AJ22: 0.300612 | AK22: 0.039
A23: Pipeline and Distribution Fuel | B23: Natural Gas: Use by Sector: Transportation: Pipeline Fuel: Reference case | C23: AEO.2023.REF2023.CNSM_NA_PIPL_NA_NG_PFT_USA_TRLCF.A | D23: Tcf | F23: 0.873416 | G23: 0.791266 | H23: 0.733831 | I23: 0.700822 | J23: 0.671022 | K23: 0.630651 | L23: 0.592023 | M23: 0.590196 | N23: 0.58854 | O23: 0.590064 | P23: 0.595722 | Q23: 0.603939 | R23: 0.608261 | S23: 0.610875 | T23: 0.611382 | U23: 0.610384 | V23: 0.615074 | W23: 0.613952 | X23: 0.622765 | Y23: 0.629148 | Z23: 0.634683 | AA23: 0.63741 | AB23: 0.641364 | AC23: 0.645326 | AD23: 0.650466 | AE23: 0.657796 | AF23: 0.66489 | AG23: 0.667196 | AH23: 0.671916 | AI23: -0.009
A24: Fuel Used to Liquefy Gas for Export | B24: Natural Gas: Use by Sector: Transportation: Liquefaction for Export: Reference case | C24: AEO.2023.REF2023.CNSM_NA_LQFCT_NA_NG_LQFCT_USA_TRLCF.A | D24: Tcf | F24: 0.320659 | G24: 0.364485 | H24: 0.370303 | I24: 0.394198 | J24: 0.430338 | K24: 0.460147 | L24: 0.485641 | M24: 0.508747 | N24: 0.557347 | O24: 0.605947 | P24: 0.655741 | Q24: 0.703147 | R24: 0.743647 | S24: 0.767947 | T24: 0.785341 | U24: 0.800347 | V24: 0.808447 | W24: 0.808447 | X24: 0.809641 | Y24: 0.808447 | Z24: 0.808447 | AA24: 0.808447 | AB24: 0.809641 | AC24: 0.808447 | AD24: 0.808447 | AE24: 0.808447 | AF24: 0.809641 | AG24: 0.808447 | AH24: 0.808447 | AI24: 0.034
A25: Electric Power | B25: Natural Gas: Use by Sector: Electric Power: Reference case | C25: AEO.2023.REF2023.CNSM_NA_ELEP_NA_NG_NA_USA_TRLCF.A | D25: Tcf | F25: 11.799821 | G25: 10.874231 | H25: 10.15932 | I25: 9.678199 | J25: 9.269681 | K25: 8.619404 | L25: 8.289996 | M25: 8.050027 | N25: 7.707353 | O25: 7.365824 | P25: 7.121314 | Q25: 6.946913 | R25: 6.77484 | S25: 6.706319 | T25: 6.708906 | U25: 6.78039 | V25: 6.941749 | W25: 7.035107 | X25: 7.202128 | Y25: 7.278445 | Z25: 7.381327 | AA25: 7.45081 | AB25: 7.473168 | AC25: 7.547843 | AD25: 7.522304 | AE25: 7.552913 | AF25: 7.621141 | AG25: 7.660525 | AH25: 7.744609 | AI25: -0.015
A26: Discrepancy | B26: Natural Gas: Discrepancy: Reference case | C26: AEO.2023.REF2023.UNC_DESCR_NA_NA_NG_NA_USA_TRLCF.A | D26: Tcf | F26: 0.345703 | G26: 0.584641 | H26: 0.516209 | I26: 0.457045 | J26: 0.406712 | K26: 0.361244 | L26: 0.321404 | M26: 0.321831 | N26: 0.314142 | O26: 0.318394 | P26: 0.31427 | Q26: 0.324993 | R26: 0.320419 | S26: 0.359745 | T26: 0.321245 | U26: 0.317987 | V26: 0.308048 | W26: 0.310028 | X26: 0.314213 | Y26: 0.31756 | Z26: 0.30769 | AA26: 0.295959 | AB26: 0.291849 | AC26: 0.387688 | AD26: 0.28797 | AE26: 0.415039 | AF26: 0.324659 | AG26: 0.306042 | AH26: 0.504618 | AI26: - -
A27: Natural Gas Prices
A28: Natural Gas Spot Price at Henry Hub
A29: (2022 dollars per million Btu) | B29: Natural Gas: Henry Hub Spot Price: Reference case | C29: AEO.2023.REF2023.PRCE_HHP_NA_NA_NG_NA_USA_Y13DLRPMMBTU.A | D29: 2022 $/MMBtu | F29: 6.523997 | G29: 5.266376 | H29: 4.072381 | I29: 3.489514 | J29: 3.065508 | K29: 2.853001 | L29: 2.799904 | M29: 2.825097 | N29: 2.91248 | O29: 3.043758 | P29: 3.208004 | Q29: 3.416918 | R29: 3.56943 | S29: 3.681824 | T29: 3.694155 | U29: 3.737596 | V29: 3.866561 | W29: 3.78878 | X29: 3.938065 | Y29: 4.022155 | Z29: 4.014737 | AA29: 3.950616 | AB29: 3.913768 | AC29: 3.910706 | AD29: 3.907083 | AE29: 3.870706 | AF29: 3.849094 | AG29: 3.783895 | AH29: 3.771015 | AI29: -0.019
A30: Delivered Prices
A31: (2022 dollars per thousand cubic feet)
A32: Residential | B32: Natural Gas: Delivered Prices: Residential: Reference case | C32: AEO.2023.REF2023.PRCE_NA_RESD_NA_NG_NA_USA_Y13DLRPMCF.A | D32: 2022 $/Mcf | F32: 14.851385 | G32: 14.613103 | H32: 13.320674 | I32: 12.568542 | J32: 11.938526 | K32: 11.516709 | L32: 11.244637 | M32: 11.297374 | N32: 11.341838 | O32: 11.448148 | P32: 11.542928 | Q32: 11.695349 | R32: 11.820528 | S32: 11.932122 | T32: 11.985453 | U32: 12.072364 | V32: 12.21761 | W32: 12.224497 | X32: 12.320653 | Y32: 12.420988 | Z32: 12.447018 | AA32: 12.433571 | AB32: 12.389417 | AC32: 12.451289 | AD32: 12.773996 | AE32: 12.757806 | AF32: 12.723811 | AG32: 12.728624 | AH32: 12.764476 | AI32: -0.005
A33: Commercial | B33: Natural Gas: Delivered Prices: Commercial: Reference case | C33: AEO.2023.REF2023.PRCE_NA_COMM_NA_NG_NA_USA_Y13DLRPMCF.A | D33: 2022 $/Mcf | F33: 11.415294 | G33: 10.728111 | H33: 9.689114 | I33: 9.191208 | J33: 8.786163 | K33: 8.566701 | L33: 8.471746 | M33: 8.510685 | N33: 8.536977 | O33: 8.619786 | P33: 8.694034 | Q33: 8.831333 | R33: 8.936175 | S33: 9.027164 | T33: 9.064223 | U33: 9.135649 | V33: 9.26419 | W33: 9.26075 | X33: 9.346378 | Y33: 9.434954 | Z33: 9.451041 | AA33: 9.430367 | AB33: 9.382954 | AC33: 9.433675 | AD33: 9.638147 | AE33: 9.596008 | AF33: 9.551413 | AG33: 9.551454 | AH33: 9.584112 | AI33: -0.006
A34: Industrial | B34: Natural Gas: Delivered Prices: Industrial: Reference case | C34: AEO.2023.REF2023.PRCE_NA_IDAL_NA_NG_NA_USA_Y13DLRPMCF.A | D34: 2022 $/Mcf | F34: 7.616823 | G34: 6.514565 | H34: 5.361677 | I34: 4.771115 | J34: 4.321446 | K34: 4.073116 | L34: 3.986617 | M34: 4.002231 | N34: 4.062998 | O34: 4.172425 | P34: 4.287567 | Q34: 4.451732 | R34: 4.582922 | S34: 4.698439 | T34: 4.718104 | U34: 4.7644 | V34: 4.893519 | W34: 4.836315 | X34: 4.960828 | Y34: 5.040644 | Z34: 5.034396 | AA34: 4.981189 | AB34: 4.929628 | AC34: 4.927132 | AD34: 4.889997 | AE34: 4.854081 | AF34: 4.818973 | AG34: 4.775721 | AH34: 4.771768 | AI34: -0.017
A35: Transportation | B35: Natural Gas: Delivered Prices: Transportation: Reference case | C35: AEO.2023.REF2023.PRCE_NA_TRN_NA_NG_NA_USA_Y13DLRPMCF.A | D35: 2022 $/Mcf | F35: 18.233704 | G35: 16.934088 | H35: 15.467999 | I35: 14.862036 | J35: 14.140349 | K35: 13.775438 | L35: 13.516741 | M35: 13.379853 | N35: 13.303586 | O35: 13.292125 | P35: 13.270398 | Q35: 13.314075 | R35: 13.310819 | S35: 13.281555 | T35: 13.144871 | U35: 13.03176 | V35: 13.025172 | W35: 12.814609 | X35: 12.791951 | Y35: 12.729706 | Z35: 12.588048 | AA35: 12.407153 | AB35: 12.225408 | AC35: 12.150856 | AD35: 12.777818 | AE35: 12.609349 | AF35: 12.449089 | AG35: 12.321486 | AH35: 12.23544 | AI35: -0.014
A36: Electric Power | B36: Natural Gas: Delivered Prices: Electric Power: Reference case | C36: AEO.2023.REF2023.PRCE_NA_ELEP_NA_NG_NA_USA_Y13DLRPMCF.A | D36: 2022 $/Mcf | F36: 7.258743 | G36: 5.812993 | H36: 4.63491 | I36: 3.999119 | J36: 3.50011 | K36: 3.19096 | L36: 3.068681 | M36: 3.063734 | N36: 3.101904 | O36: 3.175818 | P36: 3.259538 | Q36: 3.393531 | R36: 3.506565 | S36: 3.630531 | T36: 3.666931 | U36: 3.715862 | V36: 3.860356 | W36: 3.830414 | X36: 3.974774 | Y36: 4.050839 | Z36: 4.031197 | AA36: 3.977907 | AB36: 3.906839 | AC36: 3.898304 | AD36: 3.873679 | AE36: 3.840307 | AF36: 3.823201 | AG36: 3.766449 | AH36: 3.764557 | AI36: -0.023
A37: Average | B37: Natural Gas: Delivered Prices: Average: Reference case | C37: AEO.2023.REF2023.PRCE_NA_NA_NA_NG_NA_USA_Y13DLRPMCF.A | D37: 2022 $/Mcf | F37: 9.209998 | G37: 8.271177 | H37: 7.106081 | I37: 6.526754 | J37: 6.0689 | K37: 5.83237 | L37: 5.730124 | M37: 5.772043 | N37: 5.850703 | O37: 5.979175 | P37: 6.097002 | Q37: 6.262642 | R37: 6.397126 | S37: 6.512626 | T37: 6.539738 | U37: 6.584328 | V37: 6.695644 | W37: 6.649044 | X37: 6.744039 | Y37: 6.813235 | Z37: 6.795757 | AA37: 6.742805 | AB37: 6.682416 | AC37: 6.686844 | AD37: 6.760439 | AE37: 6.718736 | AF37: 6.676045 | AG37: 6.635656 | AH37: 6.628702 | AI37: -0.012
A38: Natural Gas Spot Price at Henry Hub
A39: (nominal dollars per million Btu) | B39: Natural Gas: Henry Hub Spot Price: Reference case | C39: AEO.2023.REF2023.PRCE_HHP_NA_NA_NG_NA_USA_NDLRPMBTU.A | D39: nom $/MMBtu | F39: 6.523997 | G39: 5.48408 | H39: 4.344237 | I39: 3.803406 | J39: 3.4125 | K39: 3.244545 | L39: 3.252955 | M39: 3.354208 | N39: 3.535144 | O39: 3.779019 | P39: 4.074234 | Q39: 4.442329 | R39: 4.751782 | S39: 5.016179 | T39: 5.148898 | U39: 5.326049 | V39: 5.631648 | W39: 5.639552 | X39: 5.992483 | Y39: 6.257671 | Z39: 6.387211 | AA39: 6.429273 | AB39: 6.516381 | AC39: 6.663004 | AD39: 6.813882 | AE39: 6.910819 | AF39: 7.036972 | AG39: 7.083812 | AH39: 7.230118 | AI39: 0.004
A40: Delivered Prices
A41: (nominal dollars per thousand cubic feet)
A42: Residential | B42: Natural Gas: Delivered Prices: Residential: Reference case | C42: AEO.2023.REF2023.PRCE_DELV_RESD_NA_NG_NA_USA_NDLRPMCF.A | D42: nom $/Mcf | F42: 14.851385 | G42: 15.217185 | H42: 14.209907 | I42: 13.699121 | J42: 13.289873 | K42: 13.097257 | L42: 13.064121 | M42: 13.413251 | N42: 13.766628 | O42: 14.213603 | P42: 14.659766 | Q42: 15.205101 | R42: 15.736008 | S42: 16.256527 | T42: 16.705276 | U42: 17.203039 | V42: 17.794956 | W42: 18.196011 | X42: 18.748116 | Y42: 19.324581 | Z42: 19.802475 | AA42: 20.23452 | AB42: 20.628242 | AC42: 21.214325 | AD42: 22.27762 | AE42: 22.777987 | AF42: 23.261866 | AG42: 23.829199 | AH42: 24.473167 | AI42: 0.018
A43: Commercial | B43: Natural Gas: Delivered Prices: Commercial: Reference case | C43: AEO.2023.REF2023.PRCE_DELV_COMM_NA_NG_NA_USA_NDLRPMCF.A | D43: nom $/Mcf | F43: 11.415294 | G43: 11.171594 | H43: 10.335918 | I43: 10.017985 | J43: 9.780688 | K43: 9.74239 | L43: 9.842553 | M43: 10.104645 | N43: 10.362112 | O43: 10.702013 | P43: 11.041609 | Q43: 11.4816 | R43: 11.89623 | S43: 12.29876 | T43: 12.633677 | U43: 13.018239 | V43: 13.493298 | W43: 13.784511 | X43: 14.222216 | Y43: 14.678907 | Z43: 15.036051 | AA43: 15.347076 | AB43: 15.622515 | AC43: 16.072956 | AD43: 16.808756 | AE43: 17.132866 | AF43: 17.462038 | AG43: 17.881231 | AH43: 18.375498 | AI43: 0.017
A44: Industrial | B44: Natural Gas: Delivered Prices: Industrial: Reference case | C44: AEO.2023.REF2023.PRCE_DELV_IDAL_NA_NG_NA_USA_NDLRPMCF.A | D44: nom $/Mcf | F44: 7.616823 | G44: 6.783866 | H44: 5.719601 | I44: 5.200292 | J44: 4.8106 | K44: 4.632108 | L44: 4.631688 | M44: 4.751806 | N44: 4.931633 | O44: 5.180331 | P44: 5.445302 | Q44: 5.787689 | R44: 6.100988 | S44: 6.401233 | T44: 6.576075 | U44: 6.789239 | V44: 7.127412 | W44: 7.198794 | X44: 7.548803 | Y44: 7.842237 | Z44: 8.009428 | AA44: 8.106438 | AB44: 8.207777 | AC44: 8.394775 | AD44: 8.528066 | AE44: 8.666553 | AF44: 8.81012 | AG44: 8.940605 | AH44: 9.148849 | AI44: 0.007
A45: Transportation | B45: Natural Gas: Delivered Prices: Transportation: Reference case | C45: AEO.2023.REF2023.PRCE_DELV_TRN_NA_NG_NA_USA_NDLRPMCF.A | D45: nom $/Mcf | F45: 18.233704 | G45: 17.634115 | H45: 16.500578 | I45: 16.198921 | J45: 15.740927 | K45: 15.665972 | L45: 15.703874 | M45: 15.885756 | N45: 16.147781 | O45: 16.503017 | P45: 16.853691 | Q45: 17.309605 | R45: 17.719948 | S45: 18.095016 | T45: 18.321268 | U45: 18.570173 | V45: 18.97117 | W45: 19.074385 | X45: 19.465282 | Y45: 19.804884 | Z45: 20.026846 | AA45: 20.191528 | AB45: 20.355171 | AC45: 20.702452 | AD45: 22.284286 | AE45: 22.512932 | AF45: 22.759615 | AG45: 23.066996 | AH45: 23.458855 | AI45: 0.009
A46: Electric Power | B46: Natural Gas: Delivered Prices: Electric Power: Reference case | C46: AEO.2023.REF2023.PRCE_DELV_ELEP_NA_NG_NA_USA_NDLRPMCF.A | D46: nom $/Mcf | F46: 7.258743 | G46: 6.053293 | H46: 4.944318 | I46: 4.358852 | J46: 3.896295 | K46: 3.628886 | L46: 3.565222 | M46: 3.637538 | N46: 3.765066 | O46: 3.94298 | P46: 4.139684 | Q46: 4.411922 | R46: 4.668094 | S46: 4.946298 | T46: 5.110954 | U46: 5.295079 | V46: 5.622611 | W46: 5.701523 | X46: 6.048342 | Y46: 6.302299 | Z46: 6.413398 | AA46: 6.473688 | AB46: 6.504844 | AC46: 6.641873 | AD46: 6.755627 | AE46: 6.856544 | AF46: 6.989635 | AG46: 7.051152 | AH46: 7.217737 | AI46: 0
A47: Average | B47: Natural Gas: Delivered Prices: Average: Reference case | C47: AEO.2023.REF2023.PRCE_DELV_AVG_NA_NG_NA_USA_NDLRPMCF.A | D47: nom $/Mcf | F47: 9.209998 | G47: 8.613094 | H47: 7.580453 | I47: 7.113855 | J47: 6.755852 | K47: 6.632801 | L47: 6.65731 | M47: 6.853085 | N47: 7.101535 | O47: 7.423525 | P47: 7.743322 | Q47: 8.142049 | R47: 8.516135 | S47: 8.872911 | T47: 9.115061 | U47: 9.382624 | V47: 9.752209 | W47: 9.897018 | X47: 10.262282 | Y47: 10.600035 | Z47: 10.81165 | AA47: 10.97331 | AB47: 11.12615 | AC47: 11.392948 | AD47: 11.790085 | AE47: 11.995737 | AF47: 12.205248 | AG47: 12.422582 | AH47: 12.709126 | AI47: 0.012

Sheet AEO 2025 Table 13
A1: Table 13. Natural Gas Supply, Disposition, and Prices
A2: https://www.eia.gov/outlooks/aeo/data/browser/#/?id=13-AEO2025&cases=highZTC&sourcekey=0
A3: Tue Dec 02 2025 13:20:31 GMT-0800 (Pacific Standard Time)
A4: Source: U.S. Energy Information Administration
B5: full name | C5: api key | D5: units | E5: 2023 | F5: 2024 | G5: 2025 | H5: 2026 | I5: 2027 | J5: 2028 | K5: 2029 | L5: 2030 | M5: 2031 | N5: 2032 | O5: 2033 | P5: 2034 | Q5: 2035 | R5: 2036 | S5: 2037 | T5: 2038 | U5: 2039 | V5: 2040 | W5: 2041 | X5: 2042 | Y5: 2043 | Z5: 2044 | AA5: 2045 | AB5: 2046 | AC5: 2047 | AD5: 2048 | AE5: 2049 | AF5: 2050 | AG5: Growth (2024-2050)
A6: Production
A7: Dry Gas Production | B7: Natural Gas: Production: Dry Gas Production: High Zero-Carbon Technology Cost | C7: AEO.2025.HIGHZTC.SUP_PRD_NA_NA_NG_DNG_USA_TRLCF.A | D7: Tcf | F7: 38.395714 | G7: 38.575592 | H7: 38.973137 | I7: 39.201183 | J7: 40.363079 | K7: 41.169594 | L7: 42.049503 | M7: 42.139233 | N7: 43.939369 | O7: 43.920151 | P7: 43.910572 | Q7: 43.515194 | R7: 43.168228 | S7: 42.547188 | T7: 42.325035 | U7: 41.954548 | V7: 42.21479 | W7: 42.761806 | X7: 42.998825 | Y7: 43.180714 | Z7: 43.340855 | AA7: 43.59359 | AB7: 43.969772 | AC7: 44.232101 | AD7: 44.389687 | AE7: 44.596985 | AF7: 44.749317 | AG7: 0.006
A8: Supplemental Natural Gas | B8: Natural Gas: Production: Supplemental Natural Gas: High Zero-Carbon Technology Cost | C8: AEO.2025.HIGHZTC.SUP_PRD_NA_NA_NG_SPNG_USA_TRLCF.A | D8: Tcf | F8: 0.1159 | G8: 0.1038 | H8: 0.098233 | I8: 0.092666 | J8: 0.087099 | K8: 0.081532 | L8: 0.075964 | M8: 0.075964 | N8: 0.075964 | O8: 0.075964 | P8: 0.075964 | Q8: 0.075964 | R8: 0.075964 | S8: 0.075964 | T8: 0.075964 | U8: 0.075964 | V8: 0.075964 | W8: 0.075964 | X8: 0.075964 | Y8: 0.075964 | Z8: 0.075964 | AA8: 0.075964 | AB8: 0.075964 | AC8: 0.075964 | AD8: 0.075964 | AE8: 0.075964 | AF8: 0.075964 | AG8: -0.016
A9: Renewable Natural Gas | B9: Natural Gas: Production: Renewable Natural Gas: High Zero-Carbon Technology Cost | C9: AEO.2025.HIGHZTC.SUP_PRD_NA_NA_NG_RNG_USA_TRLCF.A | D9: Tcf | F9: 0.09652 | G9: 0.104645 | H9: 0.104645 | I9: 0.11496 | J9: 0.11496 | K9: 0.11496 | L9: 0.11496 | M9: 0.11496 | N9: 0.11496 | O9: 0.11496 | P9: 0.11496 | Q9: 0.11496 | R9: 0.11496 | S9: 0.11496 | T9: 0.11496 | U9: 0.11496 | V9: 0.11496 | W9: 0.11496 | X9: 0.11496 | Y9: 0.11496 | Z9: 0.11496 | AA9: 0.11496 | AB9: 0.11496 | AC9: 0.11496 | AD9: 0.11496 | AE9: 0.11496 | AF9: 0.115501 | AG9: 0.007
A10: Net Imports | B10: Natural Gas: Net Imports: High Zero-Carbon Technology Cost | C10: AEO.2025.HIGHZTC.TRAD_NETIMP_NA_NA_NG_NA_USA_TRLCF.A | D10: Tcf | F10: -4.73696 | G10: -5.657986 | H10: -6.638683 | I10: -6.303125 | J10: -7.369331 | K10: -7.94297 | L10: -8.510733 | M10: -8.761023 | N10: -9.030772 | O10: -9.428055 | P10: -9.84154 | Q10: -9.98183 | R10: -10.124131 | S10: -10.227389 | T10: -10.250424 | U10: -10.291261 | V10: -10.438177 | W10: -10.616791 | X10: -10.646292 | Y10: -10.566377 | Z10: -10.494195 | AA10: -10.52496 | AB10: -10.717752 | AC10: -10.773986 | AD10: -10.725961 | AE10: -10.625355 | AF10: -10.590052 | AG10: 0.031
A11: Pipeline | B11: Natural Gas: Net Imports: Pipeline: High Zero-Carbon Technology Cost | C11: AEO.2025.HIGHZTC.TRAD_NETIMP_NA_NA_NG_PIPL_USA_TRLCF.A | D11: Tcf | F11: -0.371399 | G11: -0.669318 | H11: -1.327138 | I11: -0.984286 | J11: -1.021896 | K11: -0.87573 | L11: -0.695118 | M11: -0.742396 | N11: -0.7931 | O11: -1.009427 | P11: -1.223377 | Q11: -1.26367 | R11: -1.28646 | S11: -1.308762 | T11: -1.331797 | U11: -1.372633 | V11: -1.500507 | W11: -1.698164 | X11: -1.728665 | Y11: -1.687564 | Z11: -1.638133 | AA11: -1.690658 | AB11: -1.916426 | AC11: -1.968033 | AD11: -1.930123 | AE11: -1.853135 | AF11: -1.781184 | AG11: 0.062
A12: Liquefied Natural Gas | B12: Natural Gas: Net Imports: Liquefied Natural Gas: High Zero-Carbon Technology Cost | C12: AEO.2025.HIGHZTC.TRAD_NETIMP_NA_NA_NG_LNG_USA_TRLCF.A | D12: Tcf | F12: -4.36556 | G12: -4.988667 | H12: -5.311545 | I12: -5.318838 | J12: -6.347436 | K12: -7.06724 | L12: -7.815614 | M12: -8.018627 | N12: -8.23767 | O12: -8.418627 | P12: -8.618162 | Q12: -8.718159 | R12: -8.83767 | S12: -8.918627 | T12: -8.918627 | U12: -8.918627 | V12: -8.937671 | W12: -8.918627 | X12: -8.917626 | Y12: -8.878812 | Z12: -8.856062 | AA12: -8.834302 | AB12: -8.801325 | AC12: -8.805953 | AD12: -8.795837 | AE12: -8.772219 | AF12: -8.808866 | AG12: 0.027
A13: Total Supply | B13: Natural Gas: Total Supply: High Zero-Carbon Technology Cost | C13: AEO.2025.HIGHZTC.SUP_NA_TOT_NA_NG_NA_USA_TRLCF.A | D13: Tcf | F13: 33.774651 | G13: 33.021408 | H13: 32.432686 | I13: 32.990723 | J13: 33.080845 | K13: 33.308155 | L13: 33.614738 | M13: 33.454178 | N13: 34.984562 | O13: 34.568062 | P13: 34.144997 | Q13: 33.609329 | R13: 33.120064 | S13: 32.395763 | T13: 32.150578 | U13: 31.739254 | V13: 31.852579 | W13: 32.220982 | X13: 32.428497 | Y13: 32.690304 | Z13: 32.922626 | AA13: 33.144596 | AB13: 33.327988 | AC13: 33.534081 | AD13: 33.739693 | AE13: 34.047596 | AF13: 34.235229 | AG13: 0.001
A14: Consumption by Sector | B14: Natural Gas: Use by Sector: Total: High Zero-Carbon Technology Cost | C14: AEO.2025.HIGHZTC.CNSM_NA_ALLS_NA_NG_TOT_USA_TRLCF.A | D14: Tcf | F14: 33.066139 | G14: 32.79578 | H14: 32.182739 | I14: 32.67984 | J14: 32.748764 | K14: 32.915066 | L14: 33.15255 | M14: 33.052132 | N14: 34.631451 | O14: 34.222492 | P14: 33.80769 | Q14: 33.263802 | R14: 32.840008 | S14: 32.067276 | T14: 31.844267 | U14: 31.377337 | V14: 31.456423 | W14: 31.834995 | X14: 32.177868 | Y14: 32.423691 | Z14: 32.669796 | AA14: 32.850601 | AB14: 33.113304 | AC14: 33.340969 | AD14: 33.559128 | AE14: 33.8125 | AF14: 33.88002 | AG14: 0.001
A15: Residential | B15: Natural Gas: Use by Sector: Residential: High Zero-Carbon Technology Cost | C15: AEO.2025.HIGHZTC.CNSM_NA_RESD_NA_NG_NA_USA_TRLCF.A | D15: Tcf | F15: 4.434913 | G15: 4.784401 | H15: 4.816495 | I15: 4.835759 | J15: 4.84548 | K15: 4.832474 | L15: 4.811677 | M15: 4.779337 | N15: 4.733211 | O15: 4.693446 | P15: 4.654109 | Q15: 4.62436 | R15: 4.601415 | S15: 4.582486 | T15: 4.564576 | U15: 4.547687 | V15: 4.52856 | W15: 4.504055 | X15: 4.477375 | Y15: 4.449614 | Z15: 4.423026 | AA15: 4.39795 | AB15: 4.372572 | AC15: 4.347918 | AD15: 4.324595 | AE15: 4.301747 | AF15: 4.278714 | AG15: -0.001
A16: Commercial | B16: Natural Gas: Use by Sector: Commercial: High Zero-Carbon Technology Cost | C16: AEO.2025.HIGHZTC.CNSM_NA_COMM_NA_NG_NA_USA_TRLCF.A | D16: Tcf | F16: 3.301256 | G16: 3.478977 | H16: 3.511993 | I16: 3.518725 | J16: 3.510489 | K16: 3.510571 | L16: 3.50362 | M16: 3.499091 | N16: 3.486057 | O16: 3.470571 | P16: 3.458906 | Q16: 3.45632 | R16: 3.462904 | S16: 3.474572 | T16: 3.487757 | U16: 3.503216 | V16: 3.515867 | W16: 3.523517 | X16: 3.528426 | Y16: 3.531899 | Z16: 3.538031 | AA16: 3.544663 | AB16: 3.548947 | AC16: 3.555423 | AD16: 3.563769 | AE16: 3.571068 | AF16: 3.577246 | AG16: 0.003
A17: Industrial | B17: Natural Gas: Use by Sector: Industrial: High Zero-Carbon Technology Cost | C17: AEO.2025.HIGHZTC.CNSM_NA_IDAL_NA_NG_NA_USA_TRLCF.A | D17: Tcf | F17: 10.513494 | G17: 10.645778 | H17: 10.550887 | I17: 10.57701 | J17: 10.633311 | K17: 10.684954 | L17: 10.737125 | M17: 10.809804 | N17: 10.954347 | O17: 11.016701 | P17: 11.073318 | Q17: 11.108751 | R17: 11.155025 | S17: 11.190754 | T17: 11.270637 | U17: 11.343785 | V17: 11.436538 | W17: 11.504867 | X17: 11.572164 | Y17: 11.65315 | Z17: 11.718382 | AA17: 11.782353 | AB17: 11.846175 | AC17: 11.928168 | AD17: 11.992293 | AE17: 12.046882 | AF17: 12.096884 | AG17: 0.005
A18: Other Industrial | B18: Natural Gas: Use by Sector: Industrial: Other: High Zero-Carbon Technology Cost | C18: AEO.2025.HIGHZTC.CNSM_NA_IDAL_OTH_NG_NA_USA_TRLCF.A | D18: Tcf | F18: 7.667322 | G18: 7.777962 | H18: 7.561479 | I18: 7.566178 | J18: 7.570857 | K18: 7.591291 | L18: 7.609484 | M18: 7.650037 | N18: 7.67195 | O18: 7.653161 | P18: 7.631577 | Q18: 7.615146 | R18: 7.61292 | S18: 7.622569 | T18: 7.661403 | U18: 7.710259 | V18: 7.758837 | W18: 7.778039 | X18: 7.800282 | Y18: 7.842208 | Z18: 7.867923 | AA18: 7.894856 | AB18: 7.924067 | AC18: 7.977438 | AD18: 8.017321 | AE18: 8.049789 | AF18: 8.073728 | AG18: 0.002
... A21: Transportation | B21: Natural Gas: Use by Sector: Transportation: High Zero-Carbon Technology Cost | C21: AEO.2025.HIGHZTC.CNSM_NA_TRN_NA_NG_NA_USA_TRLCF.A | D21: Tcf | F21: 1.33269 | G21: 1.338906 | H21: 1.365317 | I21: 1.343246 | J21: 1.392562 | K21: 1.424122 | L21: 1.451179 | M21: 1.456405 | N21: 1.482111 | O21: 1.489917 | P21: 1.50517 | Q21: 1.515141 | R21: 1.5277 | S21: 1.53456 | T21: 1.538752 | U21: 1.545519 | V21: 1.561324 | W21: 1.575612 | X21: 1.594359 | Y21: 1.613225 | Z21: 1.636034 | AA21: 1.659127 | AB21: 1.678597 | AC21: 1.702153 | AD21: 1.726235 | AE21: 1.75111 | AF21: 1.783635 | AG21: 0.011
A22: Motor Vehicles | B22: Trains | C22: and Ships | D22: Natural Gas: Use by Sector: Transportation: Vehicles: High Zero-Carbon Technology Cost | E22: AEO.2025.HIGHZTC.CNSM_NA_MVF_NA_NG_NA_USA_TRLCF.A | F22: Tcf | H22: 0.085414 | I22: 0.092895 | J22: 0.098795 | K22: 0.103331 | L22: 0.10687 | M22: 0.109881 | N22: 0.112021 | O22: 0.113371 | P22: 0.113184 | Q22: 0.112656 | R22: 0.112681 | S22: 0.113227 | T22: 0.11434 | U22: 0.116177 | V22: 0.119021 | W22: 0.123052 | X22: 0.129217 | Y22: 0.136248 | Z22: 0.144318 | AA22: 0.153423 | AB22: 0.162919 | AC22: 0.17303 | AD22: 0.18404 | AE22: 0.195253 | AF22: 0.206759 | AG22: 0.218776 | AH22: 0.23118 | AI22: 0.039
A23: Pipeline and Distribution Fuel | B23: Natural Gas: Use by Sector: Transportation: Pipeline Fuel: High Zero-Carbon Technology Cost | C23: AEO.2025.HIGHZTC.CNSM_NA_PIPL_NA_NG_PFT_USA_TRLCF.A | D23: Tcf | F23: 0.892073 | G23: 0.840209 | H23: 0.834385 | I23: 0.807006 | J23: 0.769286 | K23: 0.739349 | L23: 0.703466 | M23: 0.690898 | N23: 0.699048 | O23: 0.692725 | P23: 0.69179 | Q23: 0.693116 | R23: 0.694881 | S23: 0.693348 | T23: 0.694695 | U23: 0.69743 | V23: 0.705528 | W23: 0.714328 | X23: 0.725086 | Y23: 0.737991 | Z23: 0.753147 | AA23: 0.767891 | AB23: 0.779023 | AC23: 0.79099 | AD23: 0.804386 | AE23: 0.819157 | AF23: 0.83631 | AG23: -0.002
A24: Fuel Used to Liquefy Gas for Export | B24: Natural Gas: Use by Sector: Transportation: Liquefaction for Export: High Zero-Carbon Technology Cost | C24: AEO.2025.HIGHZTC.CNSM_NA_LQFCT_NA_NG_LQFCT_USA_TRLCF.A | D24: Tcf | F24: 0.355203 | G24: 0.405802 | H24: 0.432136 | I24: 0.432909 | J24: 0.516407 | K24: 0.574892 | L24: 0.635692 | M24: 0.652136 | N24: 0.669878 | O24: 0.684536 | P24: 0.700698 | Q24: 0.708798 | R24: 0.718478 | S24: 0.725036 | T24: 0.725036 | U24: 0.725036 | V24: 0.726578 | W24: 0.725036 | X24: 0.724955 | Y24: 0.721811 | Z24: 0.719968 | AA24: 0.718206 | AB24: 0.715534 | AC24: 0.715909 | AD24: 0.71509 | AE24: 0.713177 | AF24: 0.716145 | AG24: 0.027
A25: Electric Power | B25: Natural Gas: Use by Sector: Electric Power: High Zero-Carbon Technology Cost | C25: AEO.2025.HIGHZTC.CNSM_NA_ELEP_NA_NG_NA_USA_TRLCF.A | D25: Tcf | F25: 13.483787 | G25: 12.547716 | H25: 11.93805 | I25: 12.405101 | J25: 12.366923 | K25: 12.462942 | L25: 12.64895 | M25: 12.507499 | N25: 13.97573 | O25: 13.551859 | P25: 13.116185 | Q25: 12.559227 | R25: 12.092962 | S25: 11.284903 | T25: 10.982544 | U25: 10.437131 | V25: 10.414136 | W25: 10.726946 | X25: 11.005544 | Y25: 11.175805 | Z25: 11.354323 | AA25: 11.466511 | AB25: 11.667014 | AC25: 11.807306 | AD25: 11.952235 | AE25: 12.141692 | AF25: 12.143543 | AG25: -0.004
A26: Discrepancy | B26: Natural Gas: Discrepancy: High Zero-Carbon Technology Cost | C26: AEO.2025.HIGHZTC.UNC_DESCR_NA_NA_NG_NA_USA_TRLCF.A | D26: Tcf | F26: 0.708511 | G26: 0.225628 | H26: 0.249947 | I26: 0.310883 | J26: 0.332081 | K26: 0.393089 | L26: 0.462189 | M26: 0.402046 | N26: 0.353111 | O26: 0.34557 | P26: 0.337307 | Q26: 0.345528 | R26: 0.280056 | S26: 0.328487 | T26: 0.306311 | U26: 0.361917 | V26: 0.396156 | W26: 0.385986 | X26: 0.250629 | Y26: 0.266613 | Z26: 0.252831 | AA26: 0.293995 | AB26: 0.214684 | AC26: 0.193111 | AD26: 0.180565 | AE26: 0.235096 | AF26: 0.355209 | AG26: -0.026
A27: Natural Gas Prices
A28: Natural Gas Spot Price at Henry Hub
A29: (2024 dollars per MMBtu) | B29: Natural Gas: Henry Hub Spot Price: High Zero-Carbon Technology Cost | C29: AEO.2025.HIGHZTC.PRCE_HHP_NA_NA_NG_NA_USA_Y13DLRPMMBTU.A | D29: 2024 $/MMBtu | F29: 2.191582 | G29: 2.883112 | H29: 2.74762 | I29: 2.637806 | J29: 2.748927 | K29: 2.919188 | L29: 3.159309 | M29: 3.320045 | N29: 3.767092 | O29: 4.157829 | P29: 4.435957 | Q29: 4.524341 | R29: 4.54022 | S29: 4.508521 | T29: 4.457513 | U29: 4.400403 | V29: 4.435027 | W29: 4.522207 | X29: 4.606845 | Y29: 4.711344 | Z29: 4.796789 | AA29: 4.847375 | AB29: 4.8777 | AC29: 4.887398 | AD29: 4.920235 | AE29: 5.013657 | AF29: 5.126889 | AG29: 0.033
A30: Delivered Prices
A31: (2024 dollars per thousand cubic feet)
A32: Residential | B32: Natural Gas: Delivered Prices: Residential: High Zero-Carbon Technology Cost | C32: AEO.2025.HIGHZTC.PRCE_NA_RESD_NA_NG_NA_USA_Y13DLRPMCF.A | D32: 2024 $/Mcf | F32: 14.461629 | G32: 13.17666 | H32: 12.95107 | I32: 12.530008 | J32: 12.274893 | K32: 12.153533 | L32: 12.0699 | M32: 12.278881 | N32: 12.725538 | O32: 13.122069 | P32: 13.391861 | Q32: 13.542139 | R32: 13.557489 | S32: 13.544172 | T32: 13.521586 | U32: 13.461446 | V32: 13.494338 | W32: 13.624146 | X32: 13.737558 | Y32: 13.83361 | Z32: 13.893803 | AA32: 13.983382 | AB32: 14.083962 | AC32: 14.129821 | AD32: 14.159422 | AE32: 14.244238 | AF32: 14.31883 | AG32: 0
A33: Commercial | B33: Natural Gas: Delivered Prices: Commercial: High Zero-Carbon Technology Cost | C33: AEO.2025.HIGHZTC.PRCE_NA_COMM_NA_NG_NA_USA_Y13DLRPMCF.A | D33: 2024 $/Mcf | F33: 9.91898 | G33: 8.795626 | H33: 8.897083 | I33: 8.83655 | J33: 8.919644 | K33: 9.100629 | L33: 9.317294 | M33: 9.467894 | N33: 9.832458 | O33: 10.159771 | P33: 10.368036 | Q33: 10.468319 | R33: 10.449934 | S33: 10.407696 | T33: 10.357066 | U33: 10.270552 | V33: 10.270808 | W33: 10.360629 | X33: 10.434948 | Y33: 10.495902 | Z33: 10.522658 | AA33: 10.578819 | AB33: 10.648362 | AC33: 10.665274 | AD33: 10.670247 | AE33: 10.729241 | AF33: 10.778672 | AG33: 0.003
A34: Industrial | B34: Natural Gas: Delivered Prices: Industrial: High Zero-Carbon Technology Cost | C34: AEO.2025.HIGHZTC.PRCE_NA_IDAL_NA_NG_NA_USA_Y13DLRPMCF.A | D34: 2024 $/Mcf | F34: 3.463878 | G34: 4.163002 | H34: 4.060122 | I34: 3.935598 | J34: 4.016657 | K34: 4.173019 | L34: 4.391423 | M34: 4.556916 | N34: 5.014323 | O34: 5.375893 | P34: 5.618011 | Q34: 5.702828 | R34: 5.689706 | S34: 5.637167 | T34: 5.574771 | U34: 5.491282 | V34: 5.512477 | W34: 5.608978 | X34: 5.69496 | Y34: 5.772568 | Z34: 5.829073 | AA34: 5.880927 | AB34: 5.934381 | AC34: 5.94011 | AD34: 5.954903 | AE34: 6.018018 | AF34: 6.085726 | AG34: 0.022
A35: Transportation | B35: Natural Gas: Delivered Prices: Transportation: High Zero-Carbon Technology Cost | C35: AEO.2025.HIGHZTC.PRCE_NA_TRN_NA_NG_NA_USA_Y13DLRPMCF.A | D35: 2024 $/Mcf | F35: 15.065847 | G35: 15.617211 | H35: 15.54682 | I35: 15.422724 | J35: 15.475124 | K35: 15.612073 | L35: 15.763506 | M35: 15.880778 | N35: 16.262199 | O35: 16.507532 | P35: 16.626369 | Q35: 16.624754 | R35: 16.512358 | S35: 16.371016 | T35: 16.24568 | U35: 16.063837 | V35: 15.988713 | W35: 16.00351 | X35: 16.001871 | Y35: 16.000423 | Z35: 15.969303 | AA35: 15.945396 | AB35: 15.937248 | AC35: 15.86247 | AD35: 15.79395 | AE35: 15.784898 | AF35: 15.768268 | AG35: 0.002
A36: Electric Power | B36: Natural Gas: Delivered Prices: Electric Power: High Zero-Carbon Technology Cost | C36: AEO.2025.HIGHZTC.PRCE_NA_ELEP_NA_NG_NA_USA_Y13DLRPMCF.A | D36: 2024 $/Mcf | F36: 2.809139 | G36: 3.234845 | H36: 3.169723 | I36: 3.095491 | J36: 3.2292 | K36: 3.437231 | L36: 3.72268 | M36: 3.817652 | N36: 4.33585 | O36: 4.656738 | P36: 4.873566 | Q36: 4.94741 | R36: 4.942368 | S36: 4.906366 | T36: 4.871217 | U36: 4.813748 | V36: 4.845653 | W36: 4.926926 | X36: 5.002026 | Y36: 5.092052 | Z36: 5.180276 | AA36: 5.226538 | AB36: 5.285358 | AC36: 5.293941 | AD36: 5.317598 | AE36: 5.389843 | AF36: 5.472437 | AG36: 0.026
A37: Average | B37: Natural Gas: Delivered Prices: Average: High Zero-Carbon Technology Cost | C37: AEO.2025.HIGHZTC.PRCE_NA_NA_NA_NG_NA_USA_Y13DLRPMCF.A | D37: 2024 $/Mcf | F37: 5.550955 | G37: 5.809318 | H37: 5.8052 | I37: 5.624908 | J37: 5.677902 | K37: 5.801815 | L37: 5.977849 | M37: 6.118377 | N37: 6.46763 | O37: 6.829228 | P37: 7.079875 | Q37: 7.204213 | R37: 7.226892 | S37: 7.246867 | T37: 7.221004 | U37: 7.189759 | V37: 7.209283 | W37: 7.272129 | X37: 7.327355 | Y37: 7.389088 | Z37: 7.43451 | AA37: 7.47609 | AB37: 7.520052 | AC37: 7.517616 | AD37: 7.521401 | AE37: 7.57298 | AF37: 7.641388 | AG37: 0.012
A38: Natural Gas Spot Price at Henry Hub
A39: (nominal dollars per MMBtu) | B39: Natural Gas: Henry Hub Spot Price: High Zero-Carbon Technology Cost | C39: AEO.2025.HIGHZTC.PRCE_HHP_NA_NA_NG_NA_USA_NDLRPMBTU.A | D39: nom $/MMBtu | F39: 2.191582 | G39: 2.942171 | H39: 2.851325 | I39: 2.783173 | J39: 2.955328 | K39: 3.194383 | L39: 3.522112 | M39: 3.777838 | N39: 4.378026 | O39: 4.938162 | P39: 5.38605 | Q39: 5.612916 | R39: 5.749376 | S39: 5.828076 | T39: 5.882189 | U39: 5.926426 | V39: 6.098291 | W39: 6.350842 | X39: 6.609289 | Y39: 6.907372 | Z39: 7.188035 | AA39: 7.425647 | AB39: 7.638891 | AC39: 7.827547 | AD39: 8.059517 | AE39: 8.400294 | AF39: 8.787301 | AG39: 0.055
A40: Delivered Prices
A41: (nominal dollars per thousand cubic feet)
A42: Residential | B42: Natural Gas: Delivered Prices: Residential: High Zero-Carbon Technology Cost | C42: AEO.2025.HIGHZTC.PRCE_DELV_RESD_NA_NG_NA_USA_NDLRPMCF.A | D42: nom $/Mcf | F42: 14.461629 | G42: 13.446575 | H42: 13.439891 | I42: 13.220521 | J42: 13.196542 | K42: 13.29926 | L42: 13.45596 | M42: 13.971986 | N42: 14.78932 | O42: 15.584794 | P42: 16.26013 | Q42: 16.800436 | R42: 17.168133 | S42: 17.508286 | T42: 17.84325 | U42: 18.129765 | V42: 18.555111 | W42: 19.133314 | X42: 19.708822 | Y42: 20.281662 | Z42: 20.82 | AA42: 21.421007 | AB42: 22.056677 | AC42: 22.630005 | AD42: 23.193628 | AE42: 23.865969 | AF42: 24.541954 | AG42: 0.021
A43: Commercial | B43: Natural Gas: Delivered Prices: Commercial: High Zero-Carbon Technology Cost | C43: AEO.2025.HIGHZTC.PRCE_DELV_COMM_NA_NG_NA_USA_NDLRPMCF.A | D43: nom $/Mcf | F43: 9.91898 | G43: 8.975799 | H43: 9.232892 | I43: 9.323521 | J43: 9.589368 | K43: 9.958555 | L43: 10.387256 | M43: 10.773398 | N43: 11.42705 | O43: 12.066538 | P43: 12.588662 | Q43: 12.987041 | R43: 13.23297 | S43: 13.453823 | T43: 13.667311 | U43: 13.832294 | V43: 14.122663 | W43: 14.550138 | X43: 14.970676 | Y43: 15.3882 | Z43: 15.768307 | AA43: 16.205591 | AB43: 16.676235 | AC43: 17.081264 | AD43: 17.478237 | AE43: 17.976654 | AF43: 18.474251 | AG43: 0.024
A44: Industrial | B44: Natural Gas: Delivered Prices: Industrial: High Zero-Carbon Technology Cost | C44: AEO.2025.HIGHZTC.PRCE_DELV_IDAL_NA_NG_NA_USA_NDLRPMCF.A | D44: nom $/Mcf | F44: 3.463878 | G44: 4.248278 | H44: 4.213366 | I44: 4.152484 | J44: 4.318244 | K44: 4.566414 | L44: 4.895717 | M44: 5.185258 | N44: 5.827528 | O44: 6.38483 | P44: 6.821276 | Q44: 7.074953 | R44: 7.204993 | S44: 7.287055 | T44: 7.356536 | U44: 7.395614 | V44: 7.579817 | W44: 7.877069 | X44: 8.170372 | Y44: 8.463248 | Z44: 8.734923 | AA44: 9.008934 | AB44: 9.293743 | AC44: 9.513547 | AD44: 9.754338 | AE44: 10.083083 | AF44: 10.430713 | AG44: 0.043
A45: Transportation | B45: Natural Gas: Delivered Prices: Transportation: High Zero-Carbon Technology Cost | C45: AEO.2025.HIGHZTC.PRCE_DELV_TRN_NA_NG_NA_USA_NDLRPMCF.A | D45: nom $/Mcf | F45: 15.065847 | G45: 15.93712 | H45: 16.133614 | I45: 16.27265 | J45: 16.63706 | K45: 17.083841 | L45: 17.573725 | M45: 18.070541 | N45: 18.899544 | O45: 19.605635 | P45: 20.187405 | Q45: 20.624743 | R45: 20.909943 | S45: 21.162491 | T45: 21.437998 | U45: 21.634644 | V45: 21.984949 | W45: 22.474817 | X45: 22.957357 | Y45: 23.45846 | Z45: 23.930157 | AA45: 24.426598 | AB45: 24.959078 | AC45: 25.404976 | AD45: 25.871042 | AE45: 26.447317 | AF45: 27.026236 | AG45: 0.023
A46: Electric Power | B46: Natural Gas: Delivered Prices: Electric Power: High Zero-Carbon Technology Cost | C46: AEO.2025.HIGHZTC.PRCE_DELV_ELEP_NA_NG_NA_USA_NDLRPMCF.A | D46: nom $/Mcf | F46: 2.809139 | G46: 3.301109 | H46: 3.28936 | I46: 3.266079 | J46: 3.471662 | K46: 3.761263 | L46: 4.150178 | M46: 4.344059 | N46: 5.039022 | O46: 5.530705 | P46: 5.917387 | Q46: 6.137778 | R46: 6.258624 | S46: 6.342363 | T46: 6.428118 | U46: 6.483116 | V46: 6.662915 | W46: 6.919217 | X46: 7.176242 | Y46: 7.465534 | Z46: 7.762695 | AA46: 8.006482 | AB46: 8.277317 | AC46: 8.478658 | AD46: 8.710411 | AE46: 9.030587 | AF46: 9.379557 | AG46: 0.047
A47: Average | B47: Natural Gas: Delivered Prices: Average: High Zero-Carbon Technology Cost | C47: AEO.2025.HIGHZTC.PRCE_DELV_AVG_NA_NG_NA_USA_NDLRPMCF.A | D47: nom $/Mcf | F47: 5.550955 | G47: 5.928319 | H47: 6.02431 | I47: 5.93489 | J47: 6.104222 | K47: 6.348759 | L47: 6.664321 | M47: 6.962025 | N47: 7.516527 | O47: 8.110924 | P47: 8.596243 | Q47: 8.937578 | R47: 9.151564 | S47: 9.367882 | T47: 9.528926 | U47: 9.683108 | V47: 9.912974 | W47: 10.212746 | X47: 10.512316 | Y47: 10.833253 | Z47: 11.140686 | AA47: 11.452549 | AB47: 11.777038 | AC47: 12.040045 | AD47: 12.320317 | AE47: 12.688394 | AF47: 13.097061 | AG47: 0.034

Sheet AEO 2022 Table 60
A1: Table 60. Natural Gas Imports and Exports
A2: https://www.eia.gov/outlooks/aeo/data/browser/#/?id=76-AEO2022&region=0-0&cases=ref2022&start=2020&end=2050&f=A&linechart=&ctype=linechart&sourcekey=0
A3: Fri Jun 03 2022 14:37:41 GMT-0700 (Pacific Daylight Time)
A4: Source: U.S. Energy Information Administration
B5: full name | C5: api key | D5: units | E5: 2020 | F5: 2021 | G5: 2022 | H5: 2023 | I5: 2024 | J5: 2025 | K5: 2026 | L5: 2027 | M5: 2028 | N5: 2029 | O5: 2030 | P5: 2031 | Q5: 2032 | R5: 2033 | S5: 2034 | T5: 2035 | U5: 2036 | V5: 2037 | W5: 2038 | X5: 2039 | Y5: 2040 | Z5: 2041 | AA5: 2042 | AB5: 2043 | AC5: 2044 | AD5: 2045 | AE5: 2046 | AF5: 2047 | AG5: 2048 | AH5: 2049 | AI5: 2050 | AJ5: Growth (2021-2050)
A6: Volumes (trillion cubic feet) | C6: 76-AEO2022.2.
A7: Imports | B7: Natural Gas: Volumes: Imports: Low economic growth | C7: 76-AEO2022.3.lowmacro-d011222a | D7: Tcf | F7: 2.730044 | G7: 2.478948 | H7: 2.399872 | I7: 2.299369 | J7: 2.227211 | K7: 2.201699 | L7: 2.167048 | M7: 2.117685 | N7: 1.987127 | O7: 1.935035 | P7: 1.844631 | Q7: 1.832976 | R7: 1.877825 | S7: 1.8405 | T7: 1.799475 | U7: 1.794174 | V7: 1.827648 | W7: 1.824522 | X7: 1.795108 | Y7: 1.761056 | Z7: 1.736678 | AA7: 1.728937 | AB7: 1.669057 | AC7: 1.548609 | AD7: 1.472641 | AE7: 1.452845 | AF7: 1.425173 | AG7: 1.428671 | AH7: 1.39673 | AI7: 1.353371 | AJ7: -0.024
A8: Pipeline Imports from Canada | B8: Natural Gas: Volumes: Imports: Pipeline Imports from Canada: Low economic growth | C8: 76-AEO2022.4.lowmacro-d011222a | D8: Tcf | F8: 2.692753 | G8: 2.400303 | H8: 2.323249 | I8: 2.224767 | J8: 2.154631 | K8: 2.13114 | L8: 2.098511 | M8: 2.049148 | N8: 1.91859 | O8: 1.866498 | P8: 1.776095 | Q8: 1.76444 | R8: 1.809288 | S8: 1.771963 | T8: 1.730938 | U8: 1.725637 | V8: 1.759111 | W8: 1.755986 | X8: 1.726571 | Y8: 1.69252 | Z8: 1.668141 | AA8: 1.6604 | AB8: 1.60052 | AC8: 1.480073 | AD8: 1.404104 | AE8: 1.384308 | AF8: 1.356636 | AG8: 1.360134 | AH8: 1.328193 | AI8: 1.284834 | AJ8: -0.025
A9: Pipeline Imports from Mexico | B9: Natural Gas: Volumes: Imports: Pipeline Imports from Mexico: Low economic growth | C9: 76-AEO2022.5.lowmacro-d011222a | D9: Tcf | F9: 0 | G9: 0 | H9: 0 | I9: 0 | J9: 0 | K9: 0 | L9: 0 | M9: 0 | N9: 0 | O9: 0 | P9: 0 | Q9: 0 | R9: 0 | S9: 0 | T9: 0 | U9: 0 | V9: 0 | W9: 0 | X9: 0 | Y9: 0 | Z9: 0 | AA9: 0 | AB9: 0 | AC9: 0 | AD9: 0 | AE9: 0 | AF9: 0 | AG9: 0 | AH9: 0 | AI9: 0 | AJ9: - -
A10: Liquefied Natural Gas Imports | B10: Natural Gas: Volumes: Imports: Liquefied Natural Gas Imports: Low economic growth | C10: 76-AEO2022.6.lowmacro-d011222a | D10: Tcf | F10: 0.037291 | G10: 0.078645 | H10: 0.076623 | I10: 0.074602 | J10: 0.07258 | K10: 0.070558 | L10: 0.068537 | M10: 0.068537 | N10: 0.068537 | O10: 0.068537 | P10: 0.068537 | Q10: 0.068537 | R10: 0.068537 | S10: 0.068537 | T10: 0.068537 | U10: 0.068537 | V10: 0.068537 | W10: 0.068537 | X10: 0.068537 | Y10: 0.068537 | Z10: 0.068537 | AA10: 0.068537 | AB10: 0.068537 | AC10: 0.068537 | AD10: 0.068537 | AE10: 0.068537 | AF10: 0.068537 | AG10: 0.068537 | AH10: 0.068537 | AI10: 0.068537 | AJ10: 0.021
A11: Exports | B11: Natural Gas: Volumes: Exports: Low economic growth | C11: 76-AEO2022.7.lowmacro-d011222a | D11: Tcf | F11: 6.748932 | G11: 7.511869 | H11: 7.719266 | I11: 7.80529 | J11: 8.022876 | K11: 8.037402 | L11: 8.174084 | M11: 8.464031 | N11: 8.713368 | O11: 8.942771 | P11: 9.217195 | Q11: 9.467295 | R11: 9.584615 | S11: 9.628318 | T11: 9.690271 | U11: 9.712461 | V11: 9.711069 | W11: 9.733184 | X11: 9.75787 | Y11: 9.793049 | Z11: 9.780193 | AA11: 9.797247 | AB11: 9.80693 | AC11: 9.842627 | AD11: 9.839452 | AE11: 9.823222 | AF11: 9.811426 | AG11: 9.816612 | AH11: 9.788502 | AI11: 9.782457 | AJ11: 0.013
A12: Pipeline Exports to Canada | B12: Natural Gas: Volumes: Exports: Pipeline Exports to Canada: Low economic growth | C12: 76-AEO2022.8.lowmacro-d011222a | D12: Tcf | F12: 0.950934 | G12: 0.994317 | H12: 0.966944 | I12: 0.984799 | J12: 0.99467 | K12: 0.984524 | L12: 0.989653 | M12: 0.998102 | N12: 1.021865 | O12: 1.021977 | P12: 1.059877 | Q12: 1.06349 | R12: 1.063998 | S12: 1.071854 | T12: 1.096582 | U12: 1.10407 | V12: 1.110207 | W12: 1.121564 | X12: 1.137337 | Y12: 1.150079 | Z12: 1.158589 | AA12: 1.182333 | AB12: 1.198976 | AC12: 1.231174 | AD12: 1.24635 | AE12: 1.254089 | AF12: 1.263327 | AG12: 1.274598 | AH12: 1.27874 | AI12: 1.289769 | AJ12: 0.011
A13: Pipeline Exports to Mexico | B13: Natural Gas: Volumes: Exports: Pipeline Exports to Mexico: Low economic growth | C13: 76-AEO2022.9.lowmacro-d011222a | D13: Tcf | F13: 2.218637 | G13: 2.322052 | H13: 2.315747 | I13: 2.339416 | J13: 2.377205 | K13: 2.389821 | L13: 2.421372 | M13: 2.490095 | N13: 2.528445 | O13: 2.557736 | P13: 2.59426 | Q13: 2.627972 | R13: 2.657558 | S13: 2.693406 | T13: 2.730632 | U13: 2.732557 | V13: 2.737805 | W13: 2.748562 | X13: 2.757474 | Y13: 2.767137 | Z13: 2.758546 | AA13: 2.751855 | AB13: 2.744895 | AC13: 2.735619 | AD13: 2.730044 | AE13: 2.706074 | AF13: 2.685041 | AG13: 2.666181 | AH13: 2.646703 | AI13: 2.62963 | AJ13: 0.006
A14: Liquefied Natural Gas Exports | B14: Natural Gas: Volumes: Exports: Liquefied Natural Gas Exports: Low economic growth | C14: 76-AEO2022.10.lowmacro-d011222a | D14: Tcf | F14: 3.57936 | G14: 4.1955 | H14: 4.436575 | I14: 4.481076 | J14: 4.651001 | K14: 4.663058 | L14: 4.763058 | M14: 4.975833 | N14: 5.163058 | O14: 5.363058 | P14: 5.563058 | Q14: 5.775833 | R14: 5.863058 | S14: 5.863058 | T14: 5.863058 | U14: 5.875834 | V14: 5.863058 | W14: 5.863058 | X14: 5.863058 | Y14: 5.875834 | Z14: 5.863058 | AA14: 5.863058 | AB14: 5.863058 | AC14: 5.875834 | AD14: 5.863058 | AE14: 5.863058 | AF14: 5.863058 | AG14: 5.875834 | AH14: 5.863058 | AI14: 5.863058 | AJ14: 0.017
A15: Net Imports | B15: Natural Gas: Volumes: Net Imports: Low economic growth | C15: 76-AEO2022.11.lowmacro-d011222a | D15: Tcf | F15: -4.018888 | G15: -5.032922 | H15: -5.319394 | I15: -5.505921 | J15: -5.795666 | K15: -5.835704 | L15: -6.007035 | M15: -6.346347 | N15: -6.726242 | O15: -7.007736 | P15: -7.372563 | Q15: -7.634318 | R15: -7.706789 | S15: -7.787818 | T15: -7.890796 | U15: -7.918287 | V15: -7.883422 | W15: -7.908662 | X15: -7.962761 | Y15: -8.031993 | Z15: -8.043514 | AA15: -8.06831 | AB15: -8.137873 | AC15: -8.294018 | AD15: -8.366811 | AE15: -8.370377 | AF15: -8.386254 | AG15: -8.387941 | AH15: -8.391771 | AI15: -8.429087 | AJ15: 0.026
A16: Canada | B16: Natural Gas: Volumes: Net Imports: Canada: Low economic growth | C16: 76-AEO2022.12.lowmacro-d011222a | D16: Tcf | F16: 1.741819 | G16: 1.405986 | H16: 1.356305 | I16: 1.239969 | J16: 1.159961 | K16: 1.146616 | L16: 1.108858 | M16: 1.051045 | N16: 0.896725 | O16: 0.844522 | P16: 0.716218 | Q16: 0.70095 | R16: 0.74529 | S16: 0.700109 | T16: 0.634357 | U16: 0.621567 | V16: 0.648904 | W16: 0.634422 | X16: 0.589234 | Y16: 0.54244 | Z16: 0.509553 | AA16: 0.478067 | AB16: 0.401543 | AC16: 0.248898 | AD16: 0.157755 | AE16: 0.130219 | AF16: 0.093309 | AG16: 0.085537 | AH16: 0.049454 | AI16: -0.004935 | AJ16: - -
A17: Mexico | B17: Natural Gas: Volumes: Net Imports: Mexico: Low economic growth | C17: 76-AEO2022.13.lowmacro-d011222a | D17: Tcf | F17: -2.218637 | G17: -2.322052 | H17: -2.315747 | I17: -2.339416 | J17: -2.377205 | K17: -2.389821 | L17: -2.421372 | M17: -2.490095 | N17: -2.528445 | O17: -2.557736 | P17: -2.59426 | Q17: -2.627972 | R17: -2.657558 | S17: -2.693406 | T17: -2.730632 | U17: -2.732557 | V17: -2.737805 | W17: -2.748562 | X17: -2.757474 | Y17: -2.767137 | Z17: -2.758546 | AA17: -2.751855 | AB17: -2.744895 | AC17: -2.735619 | AD17: -2.730044 | AE17: -2.706074 | AF17: -2.685041 | AG17: -2.666181 | AH17: -2.646703 | AI17: -2.62963 | AJ17: 0.006
A18: Liquefied Natural Gas | B18: Natural Gas: Volumes: Net Imports: Liquefied Natural Gas: Low economic growth | C18: 76-AEO2022.14.lowmacro-d011222a | D18: Tcf | F18: -3.542069 | G18: -4.116856 | H18: -4.359952 | I18: -4.406474 | J18: -4.578421 | K18: -4.592499 | L18: -4.694521 | M18: -4.907297 | N18: -5.094521 | O18: -5.294521 | P18: -5.494521 | Q18: -5.707296 | R18: -5.794521 | S18: -5.794521 | T18: -5.794521 | U18: -5.807297 | V18: -5.794521 | W18: -5.794521 | X18: -5.794521 | Y18: -5.807297 | Z18: -5.794521 | AA18: -5.794521 | AB18: -5.794521 | AC18: -5.807297 | AD18: -5.794521 | AE18: -5.794521 | AF18: -5.794521 | AG18: -5.807297 | AH18: -5.794521 | AI18: -5.794521 | AJ18: 0.017
B21: Transposed
C22: Pipeline Exports to Canada | D22: Pipeline Exports to Mexico | E22: Liquefied Natural Gas Exports
B23: 2021 | C23: 0.950934 | D23: 2.218661 | E23: 3.57936
B24: 2022 | C24: 0.993488 | D24: 2.321824 | E24: 4.1955
B25: 2023 | C25: 0.962994 | D25: 2.313414 | E25: 4.436575
B26: 2024 | C26: 0.979468 | D26: 2.334801 | E26: 4.481076
B27: 2025 | C27: 0.994414 | D27: 2.372 | E27: 4.651001
B28: 2026 | C28: 0.984083 | D28: 2.381717 | E28: 4.663058
B29: 2027 | C29: 0.982755 | D29: 2.409727 | E29: 4.763058
B30: 2028 | C30: 0.994677 | D30: 2.477914 | E30: 4.975833
B31: 2029 | C31: 1.026718 | D31: 2.513206 | E31: 5.163058
B32: 2030 | C32: 1.024433 | D32: 2.539065 | E32: 5.363058
B33: 2031 | C33: 1.059514 | D33: 2.574106 | E33: 5.563058
B34: 2032 | C34: 1.065948 | D34: 2.607545 | E34: 5.775833
... B52: 2050 | C52: 1.307339 | D52: 2.577559 | E52: 5.863058
B53: Growth (2021-2050) | C53: 0.011 | D53: 0.005 | E53: 0.017

Sheet AEO 2023 Table 60
A1: Table 60. Natural Gas Imports and Exports
A2: https://www.eia.gov/outlooks/aeo/data/browser/#/?id=76-AEO2022&region=0-0&cases=lowmacro&start=2020&end=2050&f=A&sid=lowmacro-d011222a.10-114-AEO2022&sourcekey=0
A3: Mon Apr 03 2023 13:21:21 GMT-0400 (Eastern Daylight Time)
A4: Source: U.S. Energy Information Administration
B5: full name | C5: api key | D5: units | E5: 2021 | F5: 2022 | G5: 2023 | H5: 2024 | I5: 2025 | J5: 2026 | K5: 2027 | L5: 2028 | M5: 2029 | N5: 2030 | O5: 2031 | P5: 2032 | Q5: 2033 | R5: 2034 | S5: 2035 | T5: 2036 | U5: 2037 | V5: 2038 | W5: 2039 | X5: 2040 | Y5: 2041 | Z5: 2042 | AA5: 2043 | AB5: 2044 | AC5: 2045 | AD5: 2046 | AE5: 2047 | AF5: 2048 | AG5: 2049 | AH5: 2050 | AI5: Growth (2021-2050)
A6: Volumes (trillion cubic feet)
A7: Imports | B7: Natural Gas: Volumes: Imports: Reference case | C7: AEO.2023.REF2023.SUP_IMP_NA_NA_NG_NA_NA_TRLCF.A | D7: Tcf | F7: 2.908926 | G7: 2.739982 | H7: 2.401043 | I7: 2.293532 | J7: 2.19718 | K7: 2.130779 | L7: 2.02316 | M7: 1.990783 | N7: 2.022308 | O7: 2.017502 | P7: 2.067005 | Q7: 2.085759 | R7: 2.089465 | S7: 2.07385 | T7: 2.029643 | U7: 2.028635 | V7: 2.084848 | W7: 2.058595 | X7: 2.176973 | Y7: 2.201737 | Z7: 2.214351 | AA7: 2.261465 | AB7: 2.343375 | AC7: 2.416977 | AD7: 2.446887 | AE7: 2.473611 | AF7: 2.519592 | AG7: 2.535872 | AH7: 2.563126 | AI7: -0.005
A8: Pipeline Imports from Canada | B8: Natural Gas: Volumes: Imports: Pipeline Imports from Canada: Reference case | C8: AEO.2023.REF2023.SUP_IMP_PIPL_CAN_NG_NA_NA_TRLCF.A | D8: Tcf | F8: 2.883244 | G8: 2.718662 | H8: 2.372942 | I8: 2.258649 | J8: 2.155516 | K8: 2.082333 | L8: 1.967933 | M8: 1.935556 | N8: 1.967081 | O8: 1.962275 | P8: 2.011777 | Q8: 2.030531 | R8: 2.034238 | S8: 2.018623 | T8: 1.974416 | U8: 1.973408 | V8: 2.029621 | W8: 2.003368 | X8: 2.121746 | Y8: 2.14651 | Z8: 2.159123 | AA8: 2.206238 | AB8: 2.288148 | AC8: 2.36175 | AD8: 2.391659 | AE8: 2.418383 | AF8: 2.464365 | AG8: 2.480645 | AH8: 2.507899 | AI8: -0.005
A9: Pipeline Imports from Mexico | B9: Natural Gas: Volumes: Imports: Pipeline Imports from Mexico: Reference case | C9: AEO.2023.REF2023.SUP_IMP_PIPL_MEX_NG_NA_NA_TRLCF.A | D9: Tcf | F9: 0 | G9: 0 | H9: 0 | I9: 0 | J9: 0 | K9: 0 | L9: 0 | M9: 0 | N9: 0 | O9: 0 | P9: 0 | Q9: 0 | R9: 0 | S9: 0 | T9: 0 | U9: 0 | V9: 0 | W9: 0 | X9: 0 | Y9: 0 | Z9: 0 | AA9: 0 | AB9: 0 | AC9: 0 | AD9: 0 | AE9: 0 | AF9: 0 | AG9: 0 | AH9: 0 | AI9: - -
A10: Liquefied Natural Gas Imports | B10: Natural Gas: Volumes: Imports: Liquefied Natural Gas Imports: Reference case | C10: AEO.2023.REF2023.SUP_IMP_LIQ_NA_NG_NA_NA_TRLCF.A | D10: Tcf | F10: 0.025682 | G10: 0.02132 | H10: 0.028101 | I10: 0.034883 | J10: 0.041664 | K10: 0.048446 | L10: 0.055227 | M10: 0.055227 | N10: 0.055227 | O10: 0.055227 | P10: 0.055227 | Q10: 0.055227 | R10: 0.055227 | S10: 0.055227 | T10: 0.055227 | U10: 0.055227 | V10: 0.055227 | W10: 0.055227 | X10: 0.055227 | Y10: 0.055227 | Z10: 0.055227 | AA10: 0.055227 | AB10: 0.055227 | AC10: 0.055227 | AD10: 0.055227 | AE10: 0.055227 | AF10: 0.055227 | AG10: 0.055227 | AH10: 0.055227 | AI10: 0.028
A11: Exports | B11: Natural Gas: Volumes: Exports: Reference case | C11: AEO.2023.REF2023.SUP_EXPT_NA_NA_NG_NA_NA_TRLCF.A | D11: Tcf | F11: 7.093175 | G11: 7.875007 | H11: 7.872959 | I11: 8.262668 | J11: 8.763868 | K11: 9.181215 | L11: 9.578551 | M11: 9.933079 | N11: 10.575899 | O11: 11.270926 | P11: 11.962046 | Q11: 12.634211 | R11: 13.20643 | S11: 13.597881 | T11: 13.849167 | U11: 14.059985 | V11: 14.173973 | W11: 14.207765 | X11: 14.232254 | Y11: 14.221733 | Z11: 14.230569 | AA11: 14.237661 | AB11: 14.27979 | AC11: 14.264336 | AD11: 14.247074 | AE11: 14.226974 | AF11: 14.230646 | AG11: 14.195643 | AH11: 14.176985 | AI11: 0.025
A12: Pipeline Exports to Canada | B12: Natural Gas: Volumes: Exports: Pipeline Exports to Canada: Reference case | C12: AEO.2023.REF2023.SUP_EXPT_PIPL_TCAN_NG_NA_NA_TRLCF.A | D12: Tcf | F12: 0.950255 | G12: 1.026193 | H12: 0.909472 | I12: 0.942763 | J12: 0.959821 | K12: 0.975364 | L12: 0.991567 | M12: 1.010723 | N12: 1.006537 | O12: 1.030218 | P12: 1.038245 | Q12: 1.045705 | R12: 1.050724 | S12: 1.069249 | T12: 1.080646 | U12: 1.084818 | V12: 1.084996 | W12: 1.09773 | X12: 1.09712 | Y12: 1.096224 | Z12: 1.102869 | AA12: 1.108019 | AB12: 1.109189 | AC12: 1.108968 | AD12: 1.108895 | AE12: 1.116778 | AF12: 1.124629 | AG12: 1.131158 | AH12: 1.12003 | AI12: 0.006
A13: Pipeline Exports to Mexico | B13: Natural Gas: Volumes: Exports: Pipeline Exports to Mexico: Reference case | C13: AEO.2023.REF2023.SUP_EXPT_PIPL_TMEX_NG_NA_NA_TRLCF.A | D13: Tcf | F13: 2.18417 | G13: 2.349004 | H13: 2.39184 | I13: 2.453267 | J13: 2.49123 | K13: 2.525021 | L13: 2.591412 | M13: 2.641525 | N13: 2.688531 | O13: 2.759877 | P13: 2.828228 | Q13: 2.907675 | R13: 2.974875 | S13: 3.047803 | T13: 3.072947 | U13: 3.094337 | V13: 3.108147 | W13: 3.129205 | X13: 3.139561 | Y13: 3.144678 | Z13: 3.146869 | AA13: 3.148812 | AB13: 3.175028 | AC13: 3.174538 | AD13: 3.157349 | AE13: 3.129367 | AF13: 3.110444 | AG13: 3.083656 | AH13: 3.076124 | AI13: 0.012
A14: Liquefied Natural Gas Exports | B14: Natural Gas: Volumes: Exports: Liquefied Natural Gas Exports: Reference case | C14: AEO.2023.REF2023.SUP_EXPT_LIQ_NA_NG_NA_NA_TRLCF.A | D14: Tcf | F14: 3.95875 | G14: 4.49981 | H14: 4.571647 | I14: 4.866638 | J14: 5.312817 | K14: 5.68083 | L14: 5.995572 | M14: 6.28083 | N14: 6.88083 | O14: 7.480831 | P14: 8.095572 | Q14: 8.680831 | R14: 9.180831 | S14: 9.48083 | T14: 9.695573 | U14: 9.880831 | V14: 9.98083 | W14: 9.98083 | X14: 9.995573 | Y14: 9.98083 | Z14: 9.98083 | AA14: 9.98083 | AB14: 9.995573 | AC14: 9.98083 | AD14: 9.98083 | AE14: 9.98083 | AF14: 9.995573 | AG14: 9.98083 | AH14: 9.98083 | AI14: 0.034
A15: Net Imports | B15: Natural Gas: Volumes: Net Imports: Reference case | C15: AEO.2023.REF2023.SUP_NEI_NA_NA_NG_NA_NA_TRLCF.A | D15: Tcf | F15: -4.184249 | G15: -5.135025 | H15: -5.471915 | I15: -5.969136 | J15: -6.566688 | K15: -7.050436 | L15: -7.555391 | M15: -7.942296 | N15: -8.553591 | O15: -9.253424 | P15: -9.895041 | Q15: -10.548452 | R15: -11.116964 | S15: -11.524033 | T15: -11.819523 | U15: -12.03135 | V15: -12.089126 | W15: -12.14917 | X15: -12.055281 | Y15: -12.019995 | Z15: -12.016218 | AA15: -11.976196 | AB15: -11.936415 | AC15: -11.847359 | AD15: -11.800187 | AE15: -11.753365 | AF15: -11.711054 | AG15: -11.659771 | AH15: -11.613858 | AI15: 0.037
A16: Canada | B16: Natural Gas: Volumes: Net Imports: Canada: Reference case | C16: AEO.2023.REF2023.SUP_NEI_NA_CAN_NG_NA_NA_TRLCF.A | D16: Tcf | F16: 1.932989 | G16: 1.692469 | H16: 1.46347 | I16: 1.315886 | J16: 1.195694 | K16: 1.106969 | L16: 0.976365 | M16: 0.924833 | N16: 0.960544 | O16: 0.932057 | P16: 0.973532 | Q16: 0.984827 | R16: 0.983514 | S16: 0.949374 | T16: 0.89377 | U16: 0.88859 | V16: 0.944624 | W16: 0.905638 | X16: 1.024626 | Y16: 1.050286 | Z16: 1.056254 | AA16: 1.098219 | AB16: 1.178959 | AC16: 1.252782 | AD16: 1.282764 | AE16: 1.301606 | AF16: 1.339736 | AG16: 1.349488 | AH16: 1.387868 | AI16: -0.012
A17: Mexico | B17: Natural Gas: Volumes: Net Imports: Mexico: Reference case | C17: AEO.2023.REF2023.SUP_NEI_NA_MEX_NG_NA_NA_TRLCF.A | D17: Tcf | F17: -2.18417 | G17: -2.349004 | H17: -2.39184 | I17: -2.453267 | J17: -2.49123 | K17: -2.525021 | L17: -2.591412 | M17: -2.641525 | N17: -2.688531 | O17: -2.759877 | P17: -2.828228 | Q17: -2.907675 | R17: -2.974875 | S17: -3.047803 | T17: -3.072947 | U17: -3.094337 | V17: -3.108147 | W17: -3.129205 | X17: -3.139561 | Y17: -3.144678 | Z17: -3.146869 | AA17: -3.148812 | AB17: -3.175028 | AC17: -3.174538 | AD17: -3.157349 | AE17: -3.129367 | AF17: -3.110444 | AG17: -3.083656 | AH17: -3.076124 | AI17: 0.012
A18: Liquefied Natural Gas | B18: Natural Gas: Volumes: Net Imports: Liquefied Natural Gas: Reference case | C18: AEO.2023.REF2023.SUP_NEI_LIQ_NA_NG_NA_NA_TRLCF.A | D18: Tcf | F18: -3.933068 | G18: -4.47849 | H18: -4.543546 | I18: -4.831755 | J18: -5.271153 | K18: -5.632385 | L18: -5.940345 | M18: -6.225603 | N18: -6.825603 | O18: -7.425603 | P18: -8.040345 | Q18: -8.625604 | R18: -9.125604 | S18: -9.425603 | T18: -9.640346 | U18: -9.825603 | V18: -9.925603 | W18: -9.925603 | X18: -9.940346 | Y18: -9.925603 | Z18: -9.925603 | AA18: -9.925603 | AB18: -9.940346 | AC18: -9.925603 | AD18: -9.925603 | AE18: -9.925603 | AF18: -9.940346 | AG18: -9.925603 | AH18: -9.925603 | AI18: 0.034
B21: Transposed
C22: Pipeline Exports to Canada | D22: Pipeline Exports to Mexico | E22: Liquefied Natural Gas Exports
B23: 2022 | C23: 0.950255 | D23: 2.18417 | E23: 3.95875
B24: 2023 | C24: 1.026193 | D24: 2.349004 | E24: 4.49981
B25: 2024 | C25: 0.909472 | D25: 2.39184 | E25: 4.571647
B26: 2025 | C26: 0.942763 | D26: 2.453267 | E26: 4.866638
B27: 2026 | C27: 0.959821 | D27: 2.49123 | E27: 5.312817
B28: 2027 | C28: 0.975364 | D28: 2.525021 | E28: 5.68083
B29: 2028 | C29: 0.991567 | D29: 2.591412 | E29: 5.995572
B30: 2029 | C30: 1.010723 | D30: 2.641525 | E30: 6.28083
B31: 2030 | C31: 1.006537 | D31: 2.688531 | E31: 6.88083
B32: 2031 | C32: 1.030218 | D32: 2.759877 | E32: 7.480831
B33: 2032 | C33: 1.038245 | D33: 2.828228 | E33: 8.095572
B34: 2033 | C34: 1.045705 | D34: 2.907675 | E34: 8.680831
... B51: 2050 | C51: 1.12003 | D51: 3.076124 | E51: 9.98083
B52: Growth (2021-2050) | C52: 0.006 | D52: 0.012 | E52: 0.034

Sheet AEO 2025 Table 61
A1: Table 61. Natural Gas Imports and Exports
A2: https://www.eia.gov/outlooks/aeo/data/browser/#/?id=76-AEO2025&cases=highZTC&sourcekey=0
A3: Tue Dec 02 2025 13:30:08 GMT-0800 (Pacific Standard Time)
A4: Source: U.S. Energy Information Administration
B5: full name | C5: api key | D5: units | E5: 2023 | F5: 2024 | G5: 2025 | H5: 2026 | I5: 2027 | J5: 2028 | K5: 2029 | L5: 2030 | M5: 2031 | N5: 2032 | O5: 2033 | P5: 2034 | Q5: 2035 | R5: 2036 | S5: 2037 | T5: 2038 | U5: 2039 | V5: 2040 | W5: 2041 | X5: 2042 | Y5: 2043 | Z5: 2044 | AA5: 2045 | AB5: 2046 | AC5: 2047 | AD5: 2048 | AE5: 2049 | AF5: 2050 | AG5: Growth (2024-2050)
A6: Volumes (trillion cubic feet)
A7: Imports | B7: Natural Gas: Volumes: Imports: High Zero-Carbon Technology Cost | C7: AEO.2025.HIGHZTC.SUP_IMP_NA_NA_NG_NA_NA_TRLCF.A | D7: Tcf | F7: 3.012052 | G7: 2.857089 | H7: 2.388888 | I7: 2.626017 | J7: 2.570984 | K7: 2.620331 | L7: 2.68814 | M7: 2.698177 | N7: 2.693758 | O7: 2.561996 | P7: 2.417445 | Q7: 2.416046 | R7: 2.450658 | S7: 2.479497 | T7: 2.512113 | U7: 2.534436 | V7: 2.492806 | W7: 2.3657 | X7: 2.369418 | Y7: 2.434206 | Z7: 2.499149 | AA7: 2.486878 | AB7: 2.323115 | AC7: 2.306185 | AD7: 2.368421 | AE7: 2.456457 | AF7: 2.543923 | AG7: -0.006
A8: Pipeline Imports from Canada | B8: Natural Gas: Volumes: Imports: Pipeline Imports from Canada: High Zero-Carbon Technology Cost | C8: AEO.2025.HIGHZTC.SUP_IMP_PIPL_CAN_NG_NA_NA_TRLCF.A | D8: Tcf | F8: 2.992392 | G8: 2.835856 | H8: 2.365415 | I8: 2.600304 | J8: 2.543031 | K8: 2.590138 | L8: 2.655707 | M8: 2.665743 | N8: 2.661324 | O8: 2.529563 | P8: 2.385012 | Q8: 2.383613 | R8: 2.418224 | S8: 2.447064 | T8: 2.47968 | U8: 2.502003 | V8: 2.460373 | W8: 2.333267 | X8: 2.336984 | Y8: 2.401773 | Z8: 2.466716 | AA8: 2.454444 | AB8: 2.290682 | AC8: 2.273751 | AD8: 2.335987 | AE8: 2.424024 | AF8: 2.51149 | AG8: -0.007
A9: Pipeline Imports from Mexico | B9: Natural Gas: Volumes: Imports: Pipeline Imports from Mexico: High Zero-Carbon Technology Cost | C9: AEO.2025.HIGHZTC.SUP_IMP_PIPL_MEX_NG_NA_NA_TRLCF.A | D9: Tcf | F9: 0 | G9: 0 | H9: 0 | I9: 0 | J9: 0 | K9: 0 | L9: 0 | M9: 0 | N9: 0 | O9: 0 | P9: 0 | Q9: 0 | R9: 0 | S9: 0 | T9: 0 | U9: 0 | V9: 0 | W9: 0 | X9: 0 | Y9: 0 | Z9: 0 | AA9: 0 | AB9: 0 | AC9: 0 | AD9: 0 | AE9: 0 | AF9: 0 | AG9: - -
A10: Liquefied Natural Gas Imports | B10: Natural Gas: Volumes: Imports: Liquefied Natural Gas Imports: High Zero-Carbon Technology Cost | C10: AEO.2025.HIGHZTC.SUP_IMP_LIQ_NA_NG_NA_NA_TRLCF.A | D10: Tcf | F10: 0.01966 | G10: 0.021233 | H10: 0.023473 | I10: 0.025713 | J10: 0.027953 | K10: 0.030193 | L10: 0.032433 | M10: 0.032433 | N10: 0.032433 | O10: 0.032433 | P10: 0.032433 | Q10: 0.032433 | R10: 0.032433 | S10: 0.032433 | T10: 0.032433 | U10: 0.032433 | V10: 0.032433 | W10: 0.032433 | X10: 0.032433 | Y10: 0.032433 | Z10: 0.032433 | AA10: 0.032433 | AB10: 0.032433 | AC10: 0.032433 | AD10: 0.032433 | AE10: 0.032433 | AF10: 0.032433 | AG10: 0.019
A11: Exports | B11: Natural Gas: Volumes: Exports: High Zero-Carbon Technology Cost | C11: AEO.2025.HIGHZTC.SUP_EXPT_NA_NA_NG_NA_NA_TRLCF.A | D11: Tcf | F11: 7.749012 | G11: 8.515074 | H11: 9.027571 | I11: 8.929142 | J11: 9.940316 | K11: 10.563301 | L11: 11.198873 | M11: 11.4592 | N11: 11.724527 | O11: 11.990051 | P11: 12.258986 | Q11: 12.397875 | R11: 12.574788 | S11: 12.706885 | T11: 12.762537 | U11: 12.825695 | V11: 12.930984 | W11: 12.982491 | X11: 13.015709 | Y11: 13.000582 | Z11: 12.993344 | AA11: 13.011837 | AB11: 13.040867 | AC11: 13.080172 | AD11: 13.094381 | AE11: 13.081812 | AF11: 13.133973 | AG11: 0.021
A12: Pipeline Exports to Canada | B12: Natural Gas: Volumes: Exports: Pipeline Exports to Canada: High Zero-Carbon Technology Cost | C12: AEO.2025.HIGHZTC.SUP_EXPT_PIPL_TCAN_NG_NA_NA_TRLCF.A | D12: Tcf | F12: 0.972127 | G12: 0.998821 | H12: 1.114752 | I12: 1.022621 | J12: 1.002377 | K12: 0.927389 | L12: 0.838999 | M12: 0.866082 | N12: 0.888778 | O12: 0.948026 | P12: 0.992346 | Q12: 1.00906 | R12: 1.019033 | S12: 1.023679 | T12: 1.032078 | U12: 1.04553 | V12: 1.084344 | W12: 1.135717 | X12: 1.14923 | Y12: 1.151601 | Z12: 1.147211 | AA12: 1.169935 | AB12: 1.221693 | AC12: 1.244047 | AD12: 1.254553 | AE12: 1.253523 | AF12: 1.254808 | AG12: 0.01
A13: Pipeline Exports to Mexico | B13: Natural Gas: Volumes: Exports: Pipeline Exports to Mexico: High Zero-Carbon Technology Cost | C13: AEO.2025.HIGHZTC.SUP_EXPT_PIPL_TMEX_NG_NA_NA_TRLCF.A | D13: Tcf | F13: 2.391665 | G13: 2.506353 | H13: 2.577801 | I13: 2.56197 | J13: 2.56255 | K13: 2.53848 | L13: 2.511826 | M13: 2.542057 | N13: 2.565646 | O13: 2.590965 | P13: 2.616043 | Q13: 2.638223 | R13: 2.685651 | S13: 2.732147 | T13: 2.779398 | U13: 2.829105 | V13: 2.876536 | W13: 2.895714 | X13: 2.916419 | Y13: 2.937736 | Z13: 2.957637 | AA13: 2.975167 | AB13: 2.985415 | AC13: 2.997738 | AD13: 3.011558 | AE13: 3.023636 | AF13: 3.037866 | AG13: 0.009
A14: Liquefied Natural Gas Exports | B14: Natural Gas: Volumes: Exports: Liquefied Natural Gas Exports: High Zero-Carbon Technology Cost | C14: AEO.2025.HIGHZTC.SUP_EXPT_LIQ_NA_NG_NA_NA_TRLCF.A | D14: Tcf | F14: 4.385221 | G14: 5.0099 | H14: 5.335018 | I14: 5.344551 | J14: 6.375389 | K14: 7.097433 | L14: 7.848047 | M14: 8.051061 | N14: 8.270103 | O14: 8.45106 | P14: 8.650596 | Q14: 8.750592 | R14: 8.870104 | S14: 8.95106 | T14: 8.95106 | U14: 8.95106 | V14: 8.970104 | W14: 8.95106 | X14: 8.95006 | Y14: 8.911245 | Z14: 8.888495 | AA14: 8.866735 | AB14: 8.833758 | AC14: 8.838387 | AD14: 8.828271 | AE14: 8.804653 | AF14: 8.841299 | AG14: 0.027
A15: Net Imports | B15: Natural Gas: Volumes: Net Imports: High Zero-Carbon Technology Cost | C15: AEO.2025.HIGHZTC.SUP_NEI_NA_NA_NG_NA_NA_TRLCF.A | D15: Tcf | F15: -4.73696 | G15: -5.657985 | H15: -6.638683 | I15: -6.303124 | J15: -7.369332 | K15: -7.94297 | L15: -8.510733 | M15: -8.761024 | N15: -9.03077 | O15: -9.428054 | P15: -9.841539 | Q15: -9.981829 | R15: -10.12413 | S15: -10.227388 | T15: -10.250423 | U15: -10.29126 | V15: -10.438177 | W15: -10.61679 | X15: -10.646292 | Y15: -10.566376 | Z15: -10.494195 | AA15: -10.52496 | AB15: -10.717751 | AC15: -10.773987 | AD15: -10.725961 | AE15: -10.625355 | AF15: -10.59005 | AG15: 0.031
A16: Canada | B16: Natural Gas: Volumes: Net Imports: Canada: High Zero-Carbon Technology Cost | C16: AEO.2025.HIGHZTC.SUP_NEI_NA_CAN_NG_NA_NA_TRLCF.A | D16: Tcf | F16: 2.020265 | G16: 1.837036 | H16: 1.250663 | I16: 1.577684 | J16: 1.540654 | K16: 1.662749 | L16: 1.816708 | M16: 1.799661 | N16: 1.772546 | O16: 1.581537 | P16: 1.392666 | Q16: 1.374553 | R16: 1.399191 | S16: 1.423385 | T16: 1.447601 | U16: 1.456473 | V16: 1.376029 | W16: 1.19755 | X16: 1.187754 | Y16: 1.250172 | Z16: 1.319505 | AA16: 1.284509 | AB16: 1.068989 | AC16: 1.029705 | AD16: 1.081435 | AE16: 1.170501 | AF16: 1.256682 | AG16: -0.018
A17: Mexico | B17: Natural Gas: Volumes: Net Imports: Mexico: High Zero-Carbon Technology Cost | C17: AEO.2025.HIGHZTC.SUP_NEI_NA_MEX_NG_NA_NA_TRLCF.A | D17: Tcf | F17: -2.391665 | G17: -2.506353 | H17: -2.577801 | I17: -2.56197 | J17: -2.56255 | K17: -2.53848 | L17: -2.511826 | M17: -2.542057 | N17: -2.565646 | O17: -2.590965 | P17: -2.616043 | Q17: -2.638223 | R17: -2.685651 | S17: -2.732147 | T17: -2.779398 | U17: -2.829105 | V17: -2.876536 | W17: -2.895714 | X17: -2.916419 | Y17: -2.937736 | Z17: -2.957637 | AA17: -2.975167 | AB17: -2.985415 | AC17: -2.997738 | AD17: -3.011558 | AE17: -3.023636 | AF17: -3.037866 | AG17: 0.009
A18: Liquefied Natural Gas | B18: Natural Gas: Volumes: Net Imports: Liquefied Natural Gas: High Zero-Carbon Technology Cost | C18: AEO.2025.HIGHZTC.SUP_NEI_LIQ_NA_NG_NA_NA_TRLCF.A | D18: Tcf | F18: -4.365561 | G18: -4.988667 | H18: -5.311545 | I18: -5.318838 | J18: -6.347436 | K18: -7.06724 | L18: -7.815614 | M18: -8.018627 | N18: -8.23767 | O18: -8.418627 | P18: -8.618162 | Q18: -8.718159 | R18: -8.83767 | S18: -8.918627 | T18: -8.918627 | U18: -8.918627 | V18: -8.937671 | W18: -8.918627 | X18: -8.917626 | Y18: -8.878812 | Z18: -8.856062 | AA18: -8.834302 | AB18: -8.801325 | AC18: -8.805953 | AD18: -8.795837 | AE18: -8.77222 | AF18: -8.808866 | AG18: 0.027
C22: Pipeline Exports to Canada | D22: Pipeline Exports to Mexico | E22: Liquefied Natural Gas Exports
B23: 2024 | C23: 0.972127 | D23: 2.391665 | E23: 4.385221
B24: 2025 | C24: 0.998821 | D24: 2.506353 | E24: 5.0099
B25: 2026 | C25: 1.114752 | D25: 2.577801 | E25: 5.335018
B26: 2027 | C26: 1.022621 | D26: 2.56197 | E26: 5.344551
B27: 2028 | C27: 1.002377 | D27: 2.56255 | E27: 6.375389
B28: 2029 | C28: 0.927389 | D28: 2.53848 | E28: 7.097433
B29: 2030 | C29: 0.838999 | D29: 2.511826 | E29: 7.848047
B30: 2031 | C30: 0.866082 | D30: 2.542057 | E30: 8.051061
B31: 2032 | C31: 0.888778 | D31: 2.565646 | E31: 8.270103
B32: 2033 | C32: 0.948026 | D32: 2.590965 | E32: 8.45106
B33: 2034 | C33: 0.992346 | D33: 2.616043 | E33: 8.650596
B34: 2035 | C34: 1.00906 | D34: 2.638223 | E34: 8.750592
... B49: 2050 | C49: 1.254808 | D49: 3.037866 | E49: 8.841299
B50: Growth (2024-2050) | C50: 0.01 | D50: 0.009 | E50: 0.027

Sheet Historical Monthly Gas Cons
A1: Back to Contents | B1: Data 1: Natural Gas Delivered to Consumers in the U.S. (MMcf)
A2: Sourcekey | B2: N3060US2
A3: Date | B3: Natural Gas Delivered to Consumers in the U.S. (MMcf)
A4: 36906 | B4: 2505011 | C4: =MONTH(A4) -> 1 | D4: =YEAR(A4) -> 2001
A5: 36937 | B5: 2156873 | C5: =MONTH(A5) -> 2 | D5: =YEAR(A5) -> 2001
A6: 36965 | B6: 2086568 | C6: =MONTH(A6) -> 3 | D6: =YEAR(A6) -> 2001
A7: 36996 | B7: 1663832 | C7: =MONTH(A7) -> 4 | D7: =YEAR(A7) -> 2001
A8: 37026 | B8: 1385163 | C8: =MONTH(A8) -> 5 | D8: =YEAR(A8) -> 2001
A9: 37057 | B9: 1313119 | C9: =MONTH(A9) -> 6 | D9: =YEAR(A9) -> 2001
A10: 37087 | B10: 1459919 | C10: =MONTH(A10) -> 7 | D10: =YEAR(A10) -> 2001
A11: 37118 | B11: 1528483 | C11: =MONTH(A11) -> 8 | D11: =YEAR(A11) -> 2001
A12: 37149 | B12: 1360871 | C12: =MONTH(A12) -> 9 | D12: =YEAR(A12) -> 2001
A13: 37179 | B13: 1507428 | C13: =MONTH(A13) -> 10 | D13: =YEAR(A13) -> 2001
A14: 37210 | B14: 1561970 | C14: =MONTH(A14) -> 11 | D14: =YEAR(A14) -> 2001
A15: 37240 | B15: 1965873 | C15: =MONTH(A15) -> 12 | D15: =YEAR(A15) -> 2001
... A269: 44972 | B269: 2693317 | C269: =MONTH(A269) -> 2 | D269: =YEAR(A269) -> 2023

Sheet EIA Henry Hub Nat Gas Spot
A1: Back to Contents | B1: Data 1: Henry Hub Natural Gas Spot Price (Dollars per Million Btu)
A2: Sourcekey | B2: RNGWHHD
A3: Date | B3: Henry Hub Natural Gas Spot Price (Dollars per Million Btu)
A4: 35611 | B4: 2.49 | C4: 1997
A5: 35976 | B5: 2.09 | C5: 1998
A6: 36341 | B6: 2.27 | C6: 1999
A7: 36707 | B7: 4.31 | C7: 2000
A8: 37072 | B8: 3.96 | C8: 2001
A9: 37437 | B9: 3.38 | C9: 2002
A10: 37802 | B10: 5.47 | C10: 2003
A11: 38168 | B11: 5.89 | C11: 2004
A12: 38533 | B12: 8.69 | C12: 2005
A13: 38898 | B13: 6.73 | C13: 2006
A14: 39263 | B14: 6.97 | C14: 2007
A15: 39629 | B15: 8.86 | C15: 2008
... A29: 44742 | B29: 6.45 | C29: 2022

Sheet NG Sector Price Historicals
A1: Back to Contents | B1: Data 1: U.S. Natural Gas Prices | U1: Converted to mmbtu
A2: Sourcekey | B2: N9190US3 | C2: N9100US3 | D2: N9102US3 | E2: N9103US3 | F2: N9130US3 | G2: N9132US3 | H2: N9133US3 | I2: NA1480_NUS_3 | J2: N3050US3 | K2: N3010US3 | L2: NA1504_NUS_4 | M2: N3020US3 | N2: N3020US4 | O2: N3035US3 | P2: N3035US4 | Q2: NA1570_NUS_3 | R2: N3045US3 | U2: Pipeline | V2: lng
A3: Date | B3: U.S. Natural Gas Wellhead Price (Dollars per Thousand Cubic Feet) | C3: Price of U.S. Natural Gas Imports (Dollars per Thousand Cubic Feet) | D3: U.S. Natural Gas Pipeline Imports Price (Dollars per Thousand Cubic Feet) | E3: Price of U.S. Natural Gas LNG Imports (Dollars per Thousand Cubic Feet) | F3: Price of U.S. Natural Gas Exports (Dollars per Thousand Cubic Feet) | G3: Price of U.S. Natural Gas Pipeline Exports (Dollars per Thousand Cubic Feet) | H3: Price of Liquefied U.S. Natural Gas Exports (Dollars per Thousand Cubic Feet) | I3: U.S. Natural Gas Pipeline and Distribution Use Price (Dollars per Thousand Cubic Feet) | J3: U.S. Natural Gas Citygate Price (Dollars per Thousand Cubic Feet) | K3: U.S. Price of Natural Gas Delivered to Residential Consumers (Dollars per Thousand Cubic Feet) | L3: U.S. Natural Gas % of Total Residential - Sales (%) | M3: U.S. Price of Natural Gas Sold to Commercial Consumers (Dollars per Thousand Cubic Feet) | N3: Percent of Commercial Natural Gas Deliveries in U.S. Total Represented by the Price (%) | O3: United States Natural Gas Industrial Price (Dollars per Thousand Cubic Feet) | P3: Percent of Industrial Natural Gas Deliveries in U.S. Total Represented by the Price (%) | Q3: U.S. Natural Gas Vehicle Fuel Price (Dollars per Thousand Cubic Feet) | R3: U.S. Natural Gas Electric Power Price (Dollars per Thousand Cubic Feet) | S3: Year | U3: dollars per million btu | V3: dollars per million btu
A4: 8217 | B4: 0.11 | S4: =YEAR(A4) -> 1922
A5: 8582 | B5: 0.1 | S5: =YEAR(A5) -> 1923
A6: 8948 | B6: 0.09 | S6: =YEAR(A6) -> 1924
A7: 9313 | B7: 0.09 | S7: =YEAR(A7) -> 1925
A8: 9678 | B8: 0.1 | S8: =YEAR(A8) -> 1926
A9: 10043 | B9: 0.09 | S9: =YEAR(A9) -> 1927
A10: 10409 | B10: 0.09 | S10: =YEAR(A10) -> 1928
A11: 10774 | B11: 0.08 | S11: =YEAR(A11) -> 1929
A12: 11139 | B12: 0.08 | S12: =YEAR(A12) -> 1930
A13: 11504 | B13: 0.07 | S13: =YEAR(A13) -> 1931
A14: 11870 | B14: 0.06 | S14: =YEAR(A14) -> 1932
A15: 12235 | B15: 0.06 | S15: =YEAR(A15) -> 1933
... A48: 24288 | B48: 0.16 | S48: =YEAR(A48) -> 1966
A49: 24653 | B49: 0.16 | I49: 0.2 | K49: 1.04 | M49: 0.74 | S49: =YEAR(A49) -> 1967
A50: 25019 | B50: 0.16 | I50: 0.2 | K50: 1.04 | M50: 0.73 | S50: =YEAR(A50) -> 1968
A51: 25384 | B51: 0.17 | I51: 0.21 | K51: 1.05 | M51: 0.74 | S51: =YEAR(A51) -> 1969
A52: 25749 | B52: 0.17 | I52: 0.21 | K52: 1.09 | M52: 0.77 | S52: =YEAR(A52) -> 1970
A53: 26114 | B53: 0.18 | I53: 0.22 | K53: 1.15 | M53: 0.82 | S53: =YEAR(A53) -> 1971
A54: 26480 | B54: 0.19 | I54: 0.23 | K54: 1.21 | M54: 0.88 | S54: =YEAR(A54) -> 1972
A55: 26845 | B55: 0.22 | I55: 0.25 | K55: 1.29 | M55: 0.94 | S55: =YEAR(A55) -> 1973
A56: 27210 | B56: 0.3 | I56: 0.3 | K56: 1.43 | M56: 1.07 | S56: =YEAR(A56) -> 1974
A57: 27575 | B57: 0.44 | I57: 0.4 | K57: 1.71 | M57: 1.35 | S57: =YEAR(A57) -> 1975
A58: 27941 | B58: 0.58 | I58: 0.51 | K58: 1.98 | M58: 1.64 | S58: =YEAR(A58) -> 1976
A59: 28306 | B59: 0.79 | I59: 0.77 | K59: 2.35 | M59: 2.04 | S59: =YEAR(A59) -> 1977
A60: 28671 | B60: 0.91 | I60: 0.9 | K60: 2.56 | M60: 2.23 | S60: =YEAR(A60) -> 1978
... A65: 30497 | B65: 2.59 | I65: 3.15 | K65: 6.06 | M65: 5.59 | S65: =YEAR(A65) -> 1983
A66: 30863 | B66: 2.66 | I66: 3.04 | J66: 3.95 | K66: 6.12 | M66: 5.55 | S66: =YEAR(A66) -> 1984
A67: 31228 | B67: 2.51 | C67: 3.21 | D67: 3.17 | E67: 4.6 | F67: 4.77 | G67: 3.92 | H67: 4.81 | I67: 2.92 | J67: 3.75 | K67: 6.12 | M67: 5.5 | S67: =YEAR(A67) -> 1985
A68: 31593 | B68: 1.94 | C68: 2.43 | D68: 2.42 | E68: 4.62 | F68: 2.81 | G68: 2.35 | H68: 2.91 | I68: 2.52 | J68: 3.22 | K68: 5.83 | M68: 5.08 | S68: =YEAR(A68) -> 1986
A69: 31958 | B69: 1.67 | C69: 1.95 | D69: 1.95 | F69: 3.07 | G69: 2.35 | H69: 3.15 | I69: 2.17 | J69: 2.87 | K69: 5.54 | M69: 4.77 | N69: 93.1 | S69: =YEAR(A69) -> 1987
A70: 32324 | B70: 1.69 | C70: 1.84 | D70: 1.83 | E70: 2.71 | F70: 2.74 | G70: 2.14 | H70: 2.98 | I70: 2.1 | J70: 2.92 | K70: 5.47 | M70: 4.63 | N70: 90.8 | S70: =YEAR(A70) -> 1988
A71: 32689 | B71: 1.69 | C71: 1.82 | D71: 1.81 | E71: 2.22 | F71: 2.51 | G71: 2.05 | H71: 3.01 | I71: 2.01 | J71: 3.01 | K71: 5.64 | L71: 99.9 | M71: 4.74 | N71: 89.1 | Q71: 4.17 | S71: =YEAR(A71) -> 1989
A72: 33054 | B72: 1.71 | C72: 1.94 | D72: 1.91 | E72: 2.47 | F72: 3.1 | G72: 2.31 | H72: 3.59 | I72: 1.95 | J72: 3.03 | K72: 5.8 | L72: 99.2 | M72: 4.83 | N72: 86.6 | Q72: 3.39 | S72: =YEAR(A72) -> 1990
A73: 33419 | B73: 1.64 | C73: 1.83 | D73: 1.81 | E73: 2.36 | F73: 2.59 | G73: 1.79 | H73: 3.71 | I73: 1.87 | J73: 2.9 | K73: 5.82 | L73: 99.2 | M73: 4.81 | N73: 85.1 | Q73: 3.96 | S73: =YEAR(A73) -> 1991
A74: 33785 | B74: 1.74 | C74: 1.85 | D74: 1.84 | E74: 2.54 | F74: 2.25 | G74: 1.88 | H74: 3.43 | I74: 2.07 | J74: 3.01 | K74: 5.89 | L74: 99.1 | M74: 4.88 | N74: 83.2 | Q74: 4.05 | S74: =YEAR(A74) -> 1992
A75: 34150 | B75: 2.04 | C75: 2.03 | D75: 2.02 | E75: 2.2 | F75: 2.59 | G75: 2.08 | H75: 3.34 | I75: 1.97 | J75: 3.21 | K75: 6.16 | L75: 99.1 | M75: 5.22 | N75: 83.9 | Q75: 4.27 | S75: =YEAR(A75) -> 1993
A76: 34515 | B76: 1.85 | C76: 1.87 | D76: 1.86 | E76: 2.28 | F76: 2.5 | G76: 2.08 | H76: 3.18 | I76: 1.7 | J76: 3.07 | K76: 6.41 | L76: 99.1 | M76: 5.44 | N76: 79.3 | Q76: 4.11 | S76: =YEAR(A76) -> 1994
A77: 34880 | B77: 1.55 | C77: 1.49 | D77: 1.48 | E77: 2.3 | F77: 2.39 | G77: 1.64 | H77: 3.41 | I77: 1.49 | J77: 2.78 | K77: 6.06 | L77: 99 | M77: 5.05 | N77: 76.7 | Q77: 3.98 | S77: =YEAR(A77) -> 1995
A78: 35246 | B78: 2.17 | C78: 1.97 | D78: 1.96 | E78: 2.8 | F78: 2.97 | G78: 2.45 | H78: 3.65 | I78: 2.27 | J78: 3.27 | K78: 6.34 | L78: 99 | M78: 5.4 | N78: 77.6 | Q78: 4.34 | S78: =YEAR(A78) -> 1996
A79: 35611 | B79: 2.32 | C79: 2.17 | D79: 2.15 | E79: 2.74 | F79: 3.02 | G79: 2.49 | H79: 3.83 | I79: 2.29 | J79: 3.66 | K79: 6.94 | L79: 98.8 | M79: 5.8 | N79: 70.8 | O79: 3.59 | P79: 18.1 | Q79: 4.44 | R79: 2.78 | S79: =YEAR(A79) -> 1997
A80: 35976 | B80: 1.96 | C80: 1.97 | D80: 1.95 | E80: 2.63 | F80: 2.45 | G80: 2.13 | H80: 2.91 | I80: 2.01 | J80: 3.07 | K80: 6.82 | L80: 97.7 | M80: 5.48 | N80: 67 | O80: 3.14 | P80: 16.1 | Q80: 4.59 | R80: 2.4 | S80: =YEAR(A80) -> 1998
A81: 36341 | B81: 2.19 | C81: 2.24 | D81: 2.23 | E81: 2.47 | F81: 2.61 | G81: 2.3 | H81: 3.1 | I81: 1.88 | J81: 3.1 | K81: 6.69 | L81: 95.2 | M81: 5.33 | N81: 66.1 | O81: 3.12 | P81: 18.8 | Q81: 4.34 | R81: 2.62 | S81: =YEAR(A81) -> 1999
A82: 36707 | B82: 3.68 | C82: 3.95 | D82: 3.98 | E82: 3.5 | F82: 4.1 | G82: 4.02 | H82: 4.32 | I82: 2.97 | J82: 4.62 | K82: 7.76 | L82: 92.6 | M82: 6.59 | N82: 63.9 | O82: 4.45 | P82: 19.8 | Q82: 5.54 | R82: 4.38 | S82: =YEAR(A82) -> 2000
A83: 37072 | B83: 4 | C83: 4.43 | D83: 4.44 | E83: 4.35 | F83: 4.19 | G83: 4.14 | H83: 4.4 | I83: 3.55 | J83: 5.72 | K83: 9.63 | L83: 92.4 | M83: 8.43 | N83: 66 | O83: 5.24 | P83: 20.8 | Q83: 6.6 | R83: 4.61 | S83: =YEAR(A83) -> 2001 | U83: =G83*About!$B$27 -> 4.29318 | V83: =H83*About!$B$27 -> 4.5628
A84: 37437 | B84: 2.95 | C84: 3.15 | D84: 3.13 | E84: 3.41 | F84: 3.41 | G84: 3.32 | H84: 4.08 | J84: 4.12 | K84: 7.89 | L84: 97.9 | M84: 6.63 | N84: 77.4 | O84: 4.02 | P84: 22.7 | Q84: 5.1 | R84: 3.68 | S84: =YEAR(A84) -> 2002 | U84: =G84*About!$B$27 -> 3.44284 | V84: =H84*About!$B$27 -> 4.23096
A85: 37802 | B85: 4.88 | C85: 5.17 | D85: 5.23 | E85: 4.79 | F85: 5.54 | G85: 5.66 | H85: 4.47 | J85: 5.85 | K85: 9.63 | L85: 97.5 | M85: 8.4 | N85: 78.2 | O85: 5.89 | P85: 22.1 | Q85: 6.19 | R85: 5.57 | S85: =YEAR(A85) -> 2003 | U85: =G85*About!$B$27 -> 5.86942 | V85: =H85*About!$B$27 -> 4.63539
A86: 38168 | B86: 5.46 | C86: 5.81 | D86: 5.8 | E86: 5.82 | F86: 6.09 | G86: 6.18 | H86: 4.96 | J86: 6.65 | K86: 10.75 | L86: 97.7 | M86: 9.43 | N86: 78 | O86: 6.53 | P86: 23.6 | Q86: 7.16 | R86: 6.11 | S86: =YEAR(A86) -> 2004 | U86: =G86*About!$B$27 -> 6.40866 | V86: =H86*About!$B$27 -> 5.14352
A87: 38533 | B87: 7.33 | C87: 8.12 | D87: 8.09 | E87: 8.26 | F87: 7.59 | G87: 7.77 | H87: 5.79 | J87: 8.67 | K87: 12.7 | L87: 98.1 | M87: 11.34 | N87: 82.1 | O87: 8.56 | P87: 24 | Q87: 9.14 | R87: 8.47 | S87: =YEAR(A87) -> 2005 | U87: =G87*About!$B$27 -> 8.05749 | V87: =H87*About!$B$27 -> 6.00423
A88: 38898 | B88: 6.39 | C88: 6.88 | D88: 6.83 | E88: 7.19 | F88: 6.83 | G88: 6.9 | H88: 6.02 | J88: 8.61 | K88: 13.73 | L88: 98.1 | M88: 12 | N88: 80.8 | O88: 7.87 | P88: 23.4 | Q88: 8.72 | R88: 7.11 | S88: =YEAR(A88) -> 2006 | U88: =G88*About!$B$27 -> 7.1553 | V88: =H88*About!$B$27 -> 6.24274
A89: 39263 | B89: 6.25 | C89: 6.87 | D89: 6.83 | E89: 7.07 | F89: 6.92 | G89: 6.96 | H89: 6.23 | J89: 8.16 | K89: 13.08 | L89: 98 | M89: 11.34 | N89: 80.4 | O89: 7.68 | P89: 22.2 | Q89: 8.5 | R89: 7.31 | S89: =YEAR(A89) -> 2007 | U89: =G89*About!$B$27 -> 7.21752 | V89: =H89*About!$B$27 -> 6.46051
A90: 39629 | B90: 7.97 | C90: 8.7 | D90: 8.57 | E90: 10.03 | F90: 8.58 | G90: 8.62 | H90: 7.69 | J90: 9.18 | K90: 13.89 | L90: 97.5 | M90: 12.23 | N90: 79.7 | O90: 9.65 | P90: 20.4 | Q90: 11.75 | R90: 9.26 | S90: =YEAR(A90) -> 2008 | U90: =G90*About!$B$27 -> 8.93894 | V90: =H90*About!$B$27 -> 7.97453
A91: 39994 | B91: 3.67 | C91: 4.19 | D91: 4.13 | E91: 4.59 | F91: 4.47 | G91: 4.34 | H91: 8.4 | J91: 6.48 | K91: 12.14 | L91: 97.4 | M91: 10.06 | N91: 77.8 | O91: 5.33 | P91: 18.8 | Q91: 8.13 | R91: 4.93 | S91: =YEAR(A91) -> 2009 | U91: =G91*About!$B$27 -> 4.50058 | V91: =H91*About!$B$27 -> 8.7108
A92: 40359 | B92: 4.48 | C92: 4.52 | D92: 4.46 | E92: 4.94 | F92: 5.02 | G92: 4.75 | H92: 9.53 | J92: 6.18 | K92: 11.39 | L92: 97.4 | M92: 9.47 | N92: 77.5 | O92: 5.49 | P92: 18 | Q92: 6.25 | R92: 5.27 | S92: =YEAR(A92) -> 2010 | U92: =G92*About!$B$27 -> 4.92575 | V92: =H92*About!$B$27 -> 9.88261
A93: 40724 | B93: 3.95 | C93: 4.24 | D93: 4.09 | E93: 5.63 | F93: 4.64 | G93: 4.35 | H93: 10.54 | J93: 5.63 | K93: 11.03 | L93: 96.3 | M93: 8.91 | N93: 67.3 | O93: 5.13 | P93: 16.3 | Q93: 7.48 | R93: 4.89 | S93: =YEAR(A93) -> 2011 | U93: =G93*About!$B$27 -> 4.51095 | V93: =H93*About!$B$27 -> 10.92998
A94: 41090 | B94: 2.66 | C94: 2.88 | D94: 2.79 | E94: 4.27 | F94: 3.25 | G94: 3.08 | H94: 12.82 | J94: 4.73 | K94: 10.65 | L94: 95.8 | M94: 8.1 | N94: 65.2 | O94: 3.88 | P94: 16.2 | Q94: 8.04 | R94: 3.54 | S94: =YEAR(A94) -> 2012 | U94: =G94*About!$B$27 -> 3.19396 | V94: =H94*About!$B$27 -> 13.29434
A95: 41455 | C95: 3.83 | D95: 3.73 | E95: 6.8 | F95: 4.08 | G95: 4.06 | H95: 13.36 | J95: 4.88 | K95: 10.32 | L95: 95.7 | M95: 8.08 | N95: 65.8 | O95: 4.64 | P95: 16.6 | R95: 4.49 | S95: =YEAR(A95) -> 2013 | U95: =G95*About!$B$27 -> 4.21022 | V95: =H95*About!$B$27 -> 13.85432
A96: 41820 | C96: 5.3 | D96: 5.21 | E96: 8.85 | F96: 5.51 | G96: 5.4 | H96: 15.66 | J96: 5.71 | K96: 10.97 | L96: 95.5 | M96: 8.9 | N96: 65.8 | O96: 5.62 | P96: 15.9 | R96: 5.19 | S96: =YEAR(A96) -> 2014 | U96: =G96*About!$B$27 -> 5.5998 | V96: =H96*About!$B$27 -> 16.23942
A97: 42185 | C97: 2.99 | D97: 2.84 | E97: 7.37 | F97: 3.07 | G97: 2.95 | H97: 10.92 | J97: 4.26 | K97: 10.38 | L97: 95.6 | M97: 7.91 | N97: 65.7 | O97: 3.93 | P97: 14.8 | R97: 3.38 | S97: =YEAR(A97) -> 2015 | U97: =G97*About!$B$27 -> 3.05915 | V97: =H97*About!$B$27 -> 11.32404
A98: 42551 | C98: 2.24 | D98: 2.18 | E98: 4.07 | F98: 2.79 | G98: 2.63 | H98: 4.71 | J98: 3.71 | K98: 10.05 | L98: 95.8 | M98: 7.28 | N98: 64.8 | O98: 3.51 | P98: 14.9 | R98: 2.99 | S98: =YEAR(A98) -> 2016 | U98: =G98*About!$B$27 -> 2.72731 | V98: =H98*About!$B$27 -> 4.88427
A99: 42916 | C99: 2.6 | D99: 2.55 | E99: 4.58 | F99: 3.54 | G99: 3.2 | H99: 4.69 | J99: 4.16 | K99: 10.91 | L99: 95.9 | M99: 7.88 | N99: 65.4 | O99: 4.08 | P99: 14.8 | R99: 3.51 | S99: =YEAR(A99) -> 2017 | U99: =G99*About!$B$27 -> 3.3184 | V99: =H99*About!$B$27 -> 4.86353
A100: 43281 | C100: 2.69 | D100: 2.58 | E100: 6.56 | F100: 3.89 | G100: 3.34 | H100: 5.2 | J100: 4.23 | K100: 10.5 | L100: 96 | M100: 7.79 | N100: 65.8 | O100: 4.19 | P100: 14.5 | R100: 3.68 | S100: =YEAR(A100) -> 2018 | U100: =G100*About!$B$27 -> 3.46358 | V100: =H100*About!$B$27 -> 5.3924
A101: 43646 | C101: 2.55 | D101: 2.46 | E101: 7.44 | F101: 3.64 | G101: 2.64 | H101: 5.21 | J101: 3.81 | K101: 10.51 | L101: 96.2 | M101: 7.61 | N101: 65.5 | O101: 3.9 | P101: 13 | R101: 2.99 | S101: =YEAR(A101) -> 2019 | U101: =G101*About!$B$27 -> 2.73768 | V101: =H101*About!$B$27 -> 5.40277
A102: 44012 | C102: 2.07 | D102: 2.02 | E102: 4.6 | F102: 3.7 | G102: 2.1 | H102: 5.64 | J102: 3.43 | K102: 10.78 | L102: 96.3 | M102: 7.49 | N102: 64.6 | O102: 3.32 | P102: 13.2 | R102: 2.49 | S102: =YEAR(A102) -> 2020 | U102: =G102*About!$B$27 -> 2.1777 | V102: =H102*About!$B$27 -> 5.84868
A103: 44377 | C103: 3.78 | D103: 3.72 | E103: 12.21 | F103: 6.38 | G103: 4.94 | H103: 7.62 | J103: 6.02 | K103: 12.18 | L103: 96.6 | M103: 8.79 | N103: 65.1 | O103: 5.5 | P103: 13.4 | R103: 5.17 | S103: =YEAR(A103) -> 2021 | U103: =G103*About!$B$27 -> 5.12278 | V103: =H103*About!$B$27 -> 7.90194
A104: 44742 | C104: 6.33 | D104: 6.15 | E104: 28.51 | F104: 9.65 | G104: 6.33 | H104: 12.24 | J104: 6.83 | K104: 14.8 | L104: 96.8 | M104: 11.34 | N104: 66.1 | O104: 7.9 | P104: 13.6 | R104: 7.52 | S104: =YEAR(A104) -> 2022 | U104: =G104*About!$B$27 -> 6.56421 | V104: =H104*About!$B$27 -> 12.69288

Sheet NG Calcs
A1: Historical Monthly Consumption Average
A2: 1 | B2: {=SUMPRODUCT(IF('Historical Monthly Gas Cons'!$C$4:$C$269='NG Calcs'!A2,IF('Historical Monthly Gas Cons'!$D$4:$D$269>2015,'Historical Monthly Gas Cons'!$B$4:$B$269))/SUMPRODUCT(IF('Historical Monthly Gas Cons'!$D$4:$D$269>2015,'Historical Monthly Gas Cons'!$B$4:$B$269)))} -> 0.12382705
A3: 2 | B3: {=SUMPRODUCT(IF('Historical Monthly Gas Cons'!$C$4:$C$269='NG Calcs'!A3,IF('Historical Monthly Gas Cons'!$D$4:$D$269>2015,'Historical Monthly Gas Cons'!$B$4:$B$269))/SUMPRODUCT(IF('Historical Monthly Gas Cons'!$D$4:$D$269>2015,'Historical Monthly Gas Cons'!$B$4:$B$269)))} -> 0.10742266
A4: 3 | B4: {=SUMPRODUCT(IF('Historical Monthly Gas Cons'!$C$4:$C$269='NG Calcs'!A4,IF('Historical Monthly Gas Cons'!$D$4:$D$269>2015,'Historical Monthly Gas Cons'!$B$4:$B$269))/SUMPRODUCT(IF('Historical Monthly Gas Cons'!$D$4:$D$269>2015,'Historical Monthly Gas Cons'!$B$4:$B$269)))} -> 0.087329299
A5: 4 | B5: {=SUMPRODUCT(IF('Historical Monthly Gas Cons'!$C$4:$C$269='NG Calcs'!A5,IF('Historical Monthly Gas Cons'!$D$4:$D$269>2015,'Historical Monthly Gas Cons'!$B$4:$B$269))/SUMPRODUCT(IF('Historical Monthly Gas Cons'!$D$4:$D$269>2015,'Historical Monthly Gas Cons'!$B$4:$B$269)))} -> 0.071282727
A6: 5 | B6: {=SUMPRODUCT(IF('Historical Monthly Gas Cons'!$C$4:$C$269='NG Calcs'!A6,IF('Historical Monthly Gas Cons'!$D$4:$D$269>2015,'Historical Monthly Gas Cons'!$B$4:$B$269))/SUMPRODUCT(IF('Historical Monthly Gas Cons'!$D$4:$D$269>2015,'Historical Monthly Gas Cons'!$B$4:$B$269)))} -> 0.0662691
A7: 6 | B7: {=SUMPRODUCT(IF('Historical Monthly Gas Cons'!$C$4:$C$269='NG Calcs'!A7,IF('Historical Monthly Gas Cons'!$D$4:$D$269>2015,'Historical Monthly Gas Cons'!$B$4:$B$269))/SUMPRODUCT(IF('Historical Monthly Gas Cons'!$D$4:$D$269>2015,'Historical Monthly Gas Cons'!$B$4:$B$269)))} -> 0.067885393
A8: 7 | B8: {=SUMPRODUCT(IF('Historical Monthly Gas Cons'!$C$4:$C$269='NG Calcs'!A8,IF('Historical Monthly Gas Cons'!$D$4:$D$269>2015,'Historical Monthly Gas Cons'!$B$4:$B$269))/SUMPRODUCT(IF('Historical Monthly Gas Cons'!$D$4:$D$269>2015,'Historical Monthly Gas Cons'!$B$4:$B$269)))} -> 0.076317396
A9: 8 | B9: {=SUMPRODUCT(IF('Historical Monthly Gas Cons'!$C$4:$C$269='NG Calcs'!A9,IF('Historical Monthly Gas Cons'!$D$4:$D$269>2015,'Historical Monthly Gas Cons'!$B$4:$B$269))/SUMPRODUCT(IF('Historical Monthly Gas Cons'!$D$4:$D$269>2015,'Historical Monthly Gas Cons'!$B$4:$B$269)))} -> 0.075843105
A10: 9 | B10: {=SUMPRODUCT(IF('Historical Monthly Gas Cons'!$C$4:$C$269='NG Calcs'!A10,IF('Historical Monthly Gas Cons'!$D$4:$D$269>2015,'Historical Monthly Gas Cons'!$B$4:$B$269))/SUMPRODUCT(IF('Historical Monthly Gas Cons'!$D$4:$D$269>2015,'Historical Monthly Gas Cons'!$B$4:$B$269)))} -> 0.06794589
A11: 10 | B11: {=SUMPRODUCT(IF('Historical Monthly Gas Cons'!$C$4:$C$269='NG Calcs'!A11,IF('Historical Monthly Gas Cons'!$D$4:$D$269>2015,'Historical Monthly Gas Cons'!$B$4:$B$269))/SUMPRODUCT(IF('Historical Monthly Gas Cons'!$D$4:$D$269>2015,'Historical Monthly Gas Cons'!$B$4:$B$269)))} -> 0.071095411
A12: 11 | B12: {=SUMPRODUCT(IF('Historical Monthly Gas Cons'!$C$4:$C$269='NG Calcs'!A12,IF('Historical Monthly Gas Cons'!$D$4:$D$269>2015,'Historical Monthly Gas Cons'!$B$4:$B$269))/SUMPRODUCT(IF('Historical Monthly Gas Cons'!$D$4:$D$269>2015,'Historical Monthly Gas Cons'!$B$4:$B$269)))} -> 0.083164349
A13: 12 | B13: {=SUMPRODUCT(IF('Historical Monthly Gas Cons'!$C$4:$C$269='NG Calcs'!A13,IF('Historical Monthly Gas Cons'!$D$4:$D$269>2015,'Historical Monthly Gas Cons'!$B$4:$B$269))/SUMPRODUCT(IF('Historical Monthly Gas Cons'!$D$4:$D$269>2015,'Historical Monthly Gas Cons'!$B$4:$B$269)))} -> 0.10161762
A15: from variable fuels/BFPaT:
A16: Future Prices | B16: 2021 | C16: 2022 | D16: 2023 | E16: 2024 | F16: 2025 | G16: 2026 | H16: 2027 | I16: 2028 | J16: 2029 | K16: 2030 | L16: 2031 | M16: 2032 | N16: 2033 | O16: 2034 | P16: 2035
A17: 1 | B17: 2.71 | C17: 4.38 | D17: 3.27 | E17: 3.922 | F17: 4.649 | G17: 4.95 | H17: 4.933 | I17: 4.936 | J17: 4.952 | K17: 4.988 | L17: 4.927 | M17: 4.952 | N17: 4.931 | O17: 5.045 | P17: 5.034
A18: 2 | B18: 5.35 | C18: 4.69 | D18: 2.38 | E18: 3.843 | F18: 4.546 | G18: 4.741 | H18: 4.745 | I18: 4.748 | J18: 4.762 | K18: 4.788 | L18: 4.757 | M18: 4.782 | N18: 4.771 | O18: 4.885 | P18: 4.969
A19: 3 | B19: 2.62 | C19: 4.9 | D19: 2.31 | E19: 3.511 | F19: 4.176 | G19: 4.305 | H19: 4.295 | I19: 4.301 | J19: 4.312 | K19: 4.328 | L19: 4.357 | M19: 4.382 | N19: 4.421 | O19: 4.61 | P19: 4.869
A20: 4 | B20: 2.66 | C20: 6.6 | D20: 2.16 | E20: 3.148 | F20: 3.752 | G20: 3.79 | H20: 3.785 | I20: 3.774 | J20: 3.757 | K20: 3.778 | L20: 3.858 | M20: 3.937 | N20: 4.091 | O20: 4.28 | P20: 4.539
A21: 5 | B21: 2.91 | C21: 8.14 | D21: 2.2873333 | E21: 3.129 | F21: 3.724 | G21: 3.775 | H21: 3.76 | I21: 3.732 | J21: 3.712 | K21: 3.756 | L21: 3.836 | M21: 3.915 | N21: 4.069 | O21: 4.258 | P21: 4.517
A22: 6 | B22: 3.26 | C22: 7.7 | D22: 2.4146667 | E22: 3.26 | F22: 3.854 | G22: 3.872 | H22: 3.83 | I22: 3.807 | J22: 3.789 | K22: 3.816 | L22: 3.871 | M22: 3.95 | N22: 4.104 | O22: 4.293 | P22: 4.552
A23: 7 | B23: 3.84 | C23: 7.28 | D23: 2.542 | E23: 3.379 | F23: 3.982 | G23: 3.981 | H23: 3.911 | I23: 3.887 | J23: 3.874 | K23: 3.886 | L23: 3.911 | M23: 3.99 | N23: 4.144 | O23: 4.333 | P23: 4.592
A24: 8 | B24: 4.07 | C24: 8.81 | D24: 2.624 | E24: 3.419 | F24: 4.02 | G24: 3.992 | H24: 3.945 | I24: 3.914 | J24: 3.9 | K24: 3.926 | L24: 3.951 | M24: 4.03 | N24: 4.184 | O24: 4.373 | P24: 4.632
A25: 9 | B25: 5.16 | C25: 7.88 | D25: 2.62 | E25: 3.385 | F25: 3.971 | G25: 3.945 | H25: 3.928 | I25: 3.914 | J25: 3.904 | K25: 3.941 | L25: 3.966 | M25: 4.045 | N25: 4.199 | O25: 4.388 | P25: 4.647
A26: 10 | B26: 5.51 | C26: 5.66 | D26: 2.721 | E26: 3.47 | F26: 4.035 | G26: 4.011 | H26: 4.03 | I26: 4.017 | J26: 3.984 | K26: 3.987 | L26: 4.036 | M26: 4.091 | N26: 4.245 | O26: 4.434 | P26: 4.693
A27: 11 | B27: 5.05 | C27: 5.45 | D27: 3.157 | E27: 3.85 | F27: 4.355 | G27: 4.326 | H27: 4.366 | I27: 4.333 | J27: 4.339 | K27: 4.307 | L27: 4.356 | M27: 4.296 | N27: 4.42 | O27: 4.584 | P27: 4.765
A28: 12 | B28: 3.76 | C28: 5.53 | D28: 3.654 | E28: 4.323 | F28: 4.71 | G28: 4.716 | H28: 4.756 | I28: 4.722 | J28: 4.758 | K28: 4.717 | L28: 4.736 | M28: 4.696 | N28: 4.82 | O28: 4.834 | P28: 4.92
A31: Annual Average | B31: 2021 | C31: 2022 | D31: 2023 | E31: 2024 | F31: 2025 | G31: 2026
B32: =SUMPRODUCT(B17:B28,$B$2:$B$13) -> 3.8889858 | C32: =SUMPRODUCT(C17:C28,$B$2:$B$13) -> 6.1834755 | D32: =SUMPRODUCT(D17:D28,$B$2:$B$13) -> 2.7301225 | E32: =SUMPRODUCT(E17:E28,$B$2:$B$13) -> 3.6115062 | F32: =SUMPRODUCT(F17:F28,$B$2:$B$13) -> 4.2108397 | G32: =SUMPRODUCT(G17:G28,$B$2:$B$13) -> 4.2801601

Sheet Natural Gas Prices
A1: Historical Data
B2: Historical | C2: Pipeline | D2: LNG | E2: Henry Hub Prices ($/mmbtu) | F2: Pipeline multiplier | G2: LNG multiplier
B3: 2001 | C3: ='NG Sector Price Historicals'!U83 -> 4.29318 | D3: ='NG Sector Price Historicals'!V83 -> 4.5628 | E3: ='EIA Henry Hub Nat Gas Spot'!B8 -> 3.96 | F3: =C3/E3 -> 1.0841364 | G3: =D3/E3 -> 1.1522222
B4: 2002 | C4: ='NG Sector Price Historicals'!U84 -> 3.44284 | D4: ='NG Sector Price Historicals'!V84 -> 4.23096 | E4: ='EIA Henry Hub Nat Gas Spot'!B9 -> 3.38 | F4: =C4/E4 -> 1.0185917 | G4: =D4/E4 -> 1.2517633
B5: 2003 | C5: ='NG Sector Price Historicals'!U85 -> 5.86942 | D5: ='NG Sector Price Historicals'!V85 -> 4.63539 | E5: ='EIA Henry Hub Nat Gas Spot'!B10 -> 5.47 | F5: =C5/E5 -> 1.0730201 | G5: =D5/E5 -> 0.84742048
B6: 2004 | C6: ='NG Sector Price Historicals'!U86 -> 6.40866 | D6: ='NG Sector Price Historicals'!V86 -> 5.14352 | E6: ='EIA Henry Hub Nat Gas Spot'!B11 -> 5.89 | F6: =C6/E6 -> 1.0880577 | G6: =D6/E6 -> 0.87326316
B7: 2005 | C7: ='NG Sector Price Historicals'!U87 -> 8.05749 | D7: ='NG Sector Price Historicals'!V87 -> 6.00423 | E7: ='EIA Henry Hub Nat Gas Spot'!B12 -> 8.69 | F7: =C7/E7 -> 0.92721404 | G7: =D7/E7 -> 0.69093556
B8: 2006 | C8: ='NG Sector Price Historicals'!U88 -> 7.1553 | D8: ='NG Sector Price Historicals'!V88 -> 6.24274 | E8: ='EIA Henry Hub Nat Gas Spot'!B13 -> 6.73 | F8: =C8/E8 -> 1.0631947 | G8: =D8/E8 -> 0.92759881
B9: 2007 | C9: ='NG Sector Price Historicals'!U89 -> 7.21752 | D9: ='NG Sector Price Historicals'!V89 -> 6.46051 | E9: ='EIA Henry Hub Nat Gas Spot'!B14 -> 6.97 | F9: =C9/E9 -> 1.0355122 | G9: =D9/E9 -> 0.92690244
B10: 2008 | C10: ='NG Sector Price Historicals'!U90 -> 8.93894 | D10: ='NG Sector Price Historicals'!V90 -> 7.97453 | E10: ='EIA Henry Hub Nat Gas Spot'!B15 -> 8.86 | F10: =C10/E10 -> 1.0089097 | G10: =D10/E10 -> 0.90005982
B11: 2009 | C11: ='NG Sector Price Historicals'!U91 -> 4.50058 | D11: ='NG Sector Price Historicals'!V91 -> 8.7108 | E11: ='EIA Henry Hub Nat Gas Spot'!B16 -> 3.94 | F11: =C11/E11 -> 1.1422792 | G11: =D11/E11 -> 2.2108629
B12: 2010 | C12: ='NG Sector Price Historicals'!U92 -> 4.92575 | D12: ='NG Sector Price Historicals'!V92 -> 9.88261 | E12: ='EIA Henry Hub Nat Gas Spot'!B17 -> 4.37 | F12: =C12/E12 -> 1.1271739 | G12: =D12/E12 -> 2.2614668
B13: 2011 | C13: ='NG Sector Price Historicals'!U93 -> 4.51095 | D13: ='NG Sector Price Historicals'!V93 -> 10.92998 | E13: ='EIA Henry Hub Nat Gas Spot'!B18 -> 4 | F13: =C13/E13 -> 1.1277375 | G13: =D13/E13 -> 2.732495
B14: 2012 | C14: ='NG Sector Price Historicals'!U94 -> 3.19396 | D14: ='NG Sector Price Historicals'!V94 -> 13.29434 | E14: ='EIA Henry Hub Nat Gas Spot'!B19 -> 2.75 | F14: =C14/E14 -> 1.16144 | G14: =D14/E14 -> 4.8343055
... B24: 2022 | C24: ='NG Sector Price Historicals'!U104 -> 6.56421 | D24: ='NG Sector Price Historicals'!V104 -> 12.69288 | E24: ='EIA Henry Hub Nat Gas Spot'!B29 -> 6.45 | F24: =C24/E24 -> 1.017707 | G24: =D24/E24 -> 1.9678884
A25: Average | E25: =AVERAGE(E3:E24) -> 4.5145455 | F25: =AVERAGE(F3:F24) -> 1.100158 | G25: =AVERAGE(G3:G24) -> 2.0740613
A27: Forecast ($) | C27: Pipeline | D27: LNG
B28: 2023 | C28: =$E28*F$25 -> 3.003566 | D28: =$E28*G$25 -> 5.6624413 | E28: ='NG Calcs'!D32 -> 2.7301225 | G28: futures prices
B29: 2024 | C29: =$E29*F$25 -> 3.9732274 | D29: =$E29*G$25 -> 7.4904852 | E29: ='NG Calcs'!E32 -> 3.6115062 | G29: transition back to AEO22 ref
B30: 2025 | C30: =$E30*F$25 -> 4.6325889 | D30: =$E30*G$25 -> 8.7335396 | E30: ='NG Calcs'!F32 -> 4.2108397 | G30: AEO23 ref
B31: 2026 | C31: =$E31*F$25 -> 4.7088523 | D31: =$E31*G$25 -> 8.8773143 | E31: ='NG Calcs'!G32 -> 4.2801601 | G31: AEO 2025 High Zero-Carbon Technology Cost
B32: 2027 | C32: =$E32*F$25 -> 4.400574 | D32: =$E32*G$25 -> 8.2961358 | E32: =E31-(($E$31-$E$35)/4) -> 3.9999473
B33: 2028 | C33: =$E33*F$25 -> 4.0922956 | D33: =$E33*G$25 -> 7.7149573 | E33: =E32-(($E$31-$E$35)/4) -> 3.7197346
B34: 2029 | C34: =$E34*F$25 -> 3.7840173 | D34: =$E34*G$25 -> 7.1337789 | E34: =E33-(($E$31-$E$35)/4) -> 3.4395218
B35: 2030 | C35: =$E35*F$25 -> 3.475739 | D35: =$E35*G$25 -> 6.5526004 | E35: {=TRANSPOSE('AEO 2025 Table 13'!L29:AF29)} -> 3.159309
B36: 2031 | C36: =$E36*F$25 -> 3.652574 | D36: =$E36*G$25 -> 6.8859767 | E36: 3.320045
B37: 2032 | C37: =$E37*F$25 -> 4.1443963 | D37: =$E37*G$25 -> 7.8131796 | E37: 3.767092
B38: 2033 | C38: =$E38*F$25 -> 4.5742687 | D38: =$E38*G$25 -> 8.623592 | E38: 4.157829
B39: 2034 | C39: =$E39*F$25 -> 4.8802535 | D39: =$E39*G$25 -> 9.2004466 | E39: 4.435957
B40: 2035 | C40: =$E40*F$25 -> 4.9774898 | D40: =$E40*G$25 -> 9.3837604 | E40: 4.524341
B41: 2036 | C41: =$E41*F$25 -> 4.9949592 | D41: =$E41*G$25 -> 9.4166944 | E41: 4.54022
B42: 2037 | C42: =$E42*F$25 -> 4.9600853 | D42: =$E42*G$25 -> 9.3509487 | E42: 4.508521
B43: 2038 | C43: =$E43*F$25 -> 4.9039685 | D43: =$E43*G$25 -> 9.245155 | E43: 4.457513
B44: 2039 | C44: =$E44*F$25 -> 4.8411384 | D44: =$E44*G$25 -> 9.1267054 | E44: 4.400403
B45: 2040 | C45: =$E45*F$25 -> 4.8792303 | D45: =$E45*G$25 -> 9.1985177 | E45: 4.435027
B46: 2041 | C46: =$E46*F$25 -> 4.9751421 | D46: =$E46*G$25 -> 9.3793343 | E46: 4.522207
B47: 2042 | C47: =$E47*F$25 -> 5.0682573 | D47: =$E47*G$25 -> 9.5548787 | E47: 4.606845
... B55: 2050 | C55: =$E55*F$25 -> 5.6403878 | D55: =$E55*G$25 -> 10.633482 | E55: 5.126889
A57: Forecasted Volume (Tcf) | C57: Pipeline | D57: LNG | E57: % pipeline | F57: % lng
B58: 2021 | C58: =SUM('AEO 2022 Table 60'!C23:D23) -> 3.169595 | D58: ='AEO 2022 Table 60'!E23 -> 3.57936 | E58: =C58/SUM(C58:D58) -> 0.46964234 | F58: =D58/SUM(C58:D58) -> 0.53035766 | G58: =SUM(E58:F58) -> 1
B59: 2022 | C59: =SUM('AEO 2023 Table 60'!C23:D23) -> 3.134425 | D59: ='AEO 2023 Table 60'!E23 -> 3.95875 | E59: =C59/SUM(C59:D59) -> 0.44189309 | F59: =D59/SUM(C59:D59) -> 0.55810691 | G59: =SUM(E59:F59) -> 1
B60: 2023 | C60: =SUM('AEO 2023 Table 60'!C24:D24) -> 3.375197 | D60: ='AEO 2023 Table 60'!E24 -> 4.49981 | E60: =C60/SUM(C60:D60) -> 0.42859606 | F60: =D60/SUM(C60:D60) -> 0.57140394 | G60: =SUM(E60:F60) -> 1
B61: 2024 | C61: =SUM('AEO 2025 Table 61'!C23:D23) -> 3.363792 | D61: ='AEO 2025 Table 61'!E23 -> 4.385221 | E61: =C61/SUM(C61:D61) -> 0.43409296 | F61: =D61/SUM(C61:D61) -> 0.56590704 | G61: =SUM(E61:F61) -> 1
B62: 2025 | C62: =SUM('AEO 2025 Table 61'!C24:D24) -> 3.505174 | D62: ='AEO 2025 Table 61'!E24 -> 5.0099 | E62: =C62/SUM(C62:D62) -> 0.4116434 | F62: =D62/SUM(C62:D62) -> 0.5883566 | G62: =SUM(E62:F62) -> 1
B63: 2026 | C63: =SUM('AEO 2025 Table 61'!C25:D25) -> 3.692553 | D63: ='AEO 2025 Table 61'!E25 -> 5.335018 | E63: =C63/SUM(C63:D63) -> 0.40903062 | F63: =D63/SUM(C63:D63) -> 0.59096938 | G63: =SUM(E63:F63) -> 1
B64: 2027 | C64: =SUM('AEO 2025 Table 61'!C26:D26) -> 3.584591 | D64: ='AEO 2025 Table 61'!E26 -> 5.344551 | E64: =C64/SUM(C64:D64) -> 0.40144854 | F64: =D64/SUM(C64:D64) -> 0.59855146 | G64: =SUM(E64:F64) -> 1
B65: 2028 | C65: =SUM('AEO 2025 Table 61'!C27:D27) -> 3.564927 | D65: ='AEO 2025 Table 61'!E27 -> 6.375389 | E65: =C65/SUM(C65:D65) -> 0.35863317 | F65: =D65/SUM(C65:D65) -> 0.64136683 | G65: =SUM(E65:F65) -> 1
B66: 2029 | C66: =SUM('AEO 2025 Table 61'!C28:D28) -> 3.465869 | D66: ='AEO 2025 Table 61'!E28 -> 7.097433 | E66: =C66/SUM(C66:D66) -> 0.3281047 | F66: =D66/SUM(C66:D66) -> 0.6718953 | G66: =SUM(E66:F66) -> 1
B67: 2030 | C67: =SUM('AEO 2025 Table 61'!C29:D29) -> 3.350825 | D67: ='AEO 2025 Table 61'!E29 -> 7.848047 | E67: =C67/SUM(C67:D67) -> 0.29921094 | F67: =D67/SUM(C67:D67) -> 0.70078906 | G67: =SUM(E67:F67) -> 1
B68: 2031 | C68: =SUM('AEO 2025 Table 61'!C30:D30) -> 3.408139 | D68: ='AEO 2025 Table 61'!E30 -> 8.051061 | E68: =C68/SUM(C68:D68) -> 0.29741509 | F68: =D68/SUM(C68:D68) -> 0.70258491 | G68: =SUM(E68:F68) -> 1
B69: 2032 | C69: =SUM('AEO 2025 Table 61'!C31:D31) -> 3.454424 | D69: ='AEO 2025 Table 61'!E31 -> 8.270103 | E69: =C69/SUM(C69:D69) -> 0.29463227 | F69: =D69/SUM(C69:D69) -> 0.70536773 | G69: =SUM(E69:F69) -> 1
B70: 2033 | C70: =SUM('AEO 2025 Table 61'!C32:D32) -> 3.538991 | D70: ='AEO 2025 Table 61'!E32 -> 8.45106 | E70: =C70/SUM(C70:D70) -> 0.29516063 | F70: =D70/SUM(C70:D70) -> 0.70483937 | G70: =SUM(E70:F70) -> 1
B71: 2034 | C71: =SUM('AEO 2025 Table 61'!C33:D33) -> 3.608389 | D71: ='AEO 2025 Table 61'!E33 -> 8.650596 | E71: =C71/SUM(C71:D71) -> 0.29434647 | F71: =D71/SUM(C71:D71) -> 0.70565353 | G71: =SUM(E71:F71) -> 1
B72: 2035 | C72: =SUM('AEO 2025 Table 61'!C34:D34) -> 3.647283 | D72: ='AEO 2025 Table 61'!E34 -> 8.750592 | E72: =C72/SUM(C72:D72) -> 0.29418614 | F72: =D72/SUM(C72:D72) -> 0.70581386 | G72: =SUM(E72:F72) -> 1
... B87: 2050 | C87: =SUM('AEO 2025 Table 61'!C49:D49) -> 4.292674 | D87: ='AEO 2025 Table 61'!E49 -> 8.841299 | E87: =C87/SUM(C87:D87) -> 0.32683743 | F87: =D87/SUM(C87:D87) -> 0.67316257 | G87: =SUM(E87:F87) -> 1
A89: Prices ( | B89: Total Gas Prices ($2021/mmbtu for 2021, then $2022/mmbtu) | D89: $2012/btu
B90: 2021 | C90: =E58*C23+F58*D23 -> 6.5967288 | D90: =C90*About!$B$29/10^6 -> 5.5874293e-06
B91: 2022 | C91: =E59*C24+F59*D24 -> 9.9846631 | D91: =C91*About!$B$30/10^6 -> 7.8379605e-06
B92: 2023 | C92: =E60*C28+D28*F60 -> 4.5228578 | D92: =C92*About!$B$30/10^6 -> 3.5504434e-06
B93: 2024 | C93: =E61*C29+D29*F61 -> 5.9636683 | D93: =C93*About!$B$30/10^6 -> 4.6814796e-06
B94: 2025 | C94: =E62*C30+D30*F62 -> 7.0454103 | D94: =C94*About!$B$30/10^6 -> 5.5306471e-06
B95: 2026 | C95: =E63*C31+D31*F63 -> 7.1722857 | D95: =C95*About!$B$30/10^6 -> 5.6302442e-06
B96: 2027 | C96: =E64*C32+D32*F64 -> 6.7322682 | D96: =C96*About!$B$30/10^6 -> 5.2848305e-06
B97: 2028 | C97: =E65*C33+D33*F65 -> 6.4157507 | D97: =C97*About!$B$30/10^6 -> 5.0363643e-06
B98: 2029 | C98: =E66*C34+D34*F66 -> 6.0347064 | D98: =C98*About!$B$30/10^6 -> 4.7372445e-06
B99: 2030 | C99: =E67*C35+D35*F67 -> 5.6319698 | D99: =C99*About!$B$31/10^6 -> 4.1221288e-06
B100: 2031 | C100: =E68*C36+D36*F68 -> 5.9243139 | D100: =C100*About!$B$31/10^6 -> 4.3361002e-06
B101: 2032 | C101: =E69*C37+D37*F69 -> 6.7322376 | D101: =C101*About!$B$31/10^6 -> 4.9274325e-06
B102: 2033 | C102: =E70*C38+D38*F70 -> 7.4283912 | D102: =C102*About!$B$31/10^6 -> 5.4369584e-06
B103: 2034 | C103: =E71*C39+D39*F71 -> 7.928813 | D103: =C103*About!$B$31/10^6 -> 5.8032251e-06
B104: 2035 | C104: =E72*C40+D40*F72 -> 8.0874967 | D104: =C104*About!$B$31/10^6 -> 5.9193682e-06
B105: 2036 | C105: =E73*C41+D41*F73 -> 8.113998 | D105: =C105*About!$B$31/10^6 -> 5.938765e-06
B106: 2037 | C106: =E74*C42+D42*F74 -> 8.0531234 | D106: =C106*About!$B$31/10^6 -> 5.8942099e-06
B107: 2038 | C107: =E75*C43+D43*F75 -> 7.9486785 | D107: =C107*About!$B$31/10^6 -> 5.817765e-06
B108: 2039 | C108: =E76*C44+D44*F76 -> 7.8320381 | D108: =C108*About!$B$31/10^6 -> 5.732394e-06
B109: 2040 | C109: =E77*C45+D45*F77 -> 7.87548 | D109: =C109*About!$B$31/10^6 -> 5.7641899e-06
B110: 2041 | C110: =E78*C46+D46*F78 -> 8.011708 | D110: =C110*About!$B$31/10^6 -> 5.8638973e-06
... B119: 2050 | C119: =E87*C55+D55*F87 -> 9.0015518 | D119: =C119*About!$B$31/10^6 -> 6.5883799e-06

Sheet Pretax Fuel Prices
B1: 2021 | C1: 2022 | D1: 2023 | E1: 2024 | F1: 2025 | G1: 2026 | H1: 2027 | I1: 2028 | J1: 2029 | K1: 2030 | L1: 2031 | M1: 2032 | N1: 2033 | O1: 2034 | P1: 2035 | Q1: 2036 | R1: 2037 | S1: 2038 | T1: 2039 | U1: 2040 | V1: 2041 | W1: 2042 | X1: 2043 | Y1: 2044 | Z1: 2045 | AA1: 2046 | AB1: 2047 | AC1: 2048 | AD1: 2049 | AE1: 2050
A2: Hard Coal
A3: Year | B3: 2021 | C3: 2022 | D3: 2023 | E3: 2024 | F3: 2025 | G3: 2026 | H3: 2027 | I3: 2028 | J3: 2029 | K3: 2030 | L3: 2031 | M3: 2032 | N3: 2033 | O3: 2034 | P3: 2035 | Q3: 2036 | R3: 2037 | S3: 2038 | T3: 2039 | U3: 2040 | V3: 2041 | W3: 2042 | X3: 2043 | Y3: 2044 | Z3: 2045 | AA3: 2046 | AB3: 2047 | AC3: 2048 | AD3: 2049 | AE3: 2050
A4: Transportation Sector | B4: 0 | C4: 0 | D4: 0 | E4: 0 | F4: 0 | G4: 0 | H4: 0 | I4: 0 | J4: 0 | K4: 0 | L4: 0 | M4: 0 | N4: 0 | O4: 0 | P4: 0 | Q4: 0 | R4: 0 | S4: 0 | T4: 0 | U4: 0 | V4: 0 | W4: 0 | X4: 0 | Y4: 0 | Z4: 0 | AA4: 0 | AB4: 0 | AC4: 0 | AD4: 0 | AE4: 0 | AF4: 0 | AG4: 0 | AH4: 0 | AI4: 0 | AJ4: 0 | AK4: 0 | AL4: 0 | AM4: 0 | AN4: 0 | AO4: 0 | AP4: 0 | AQ4: 0 | AR4: 0 | AS4: 0 | AT4: 0 | AU4: 0 | AV4: 0 | AW4: 0 | AX4: 0 | AY4: 0 | AZ4: 0 | BA4: 0 | BB4: 0 | BC4: 0 | BD4: 0 | BE4: 0 | BF4: 0 | BG4: 0 | BH4: 0 | BI4: 0 | BJ4: 0 | BK4: 0 | BL4: 0 | BM4: 0 | BN4: 0 | BO4: 0 | BP4: 0 | BQ4: 0 | BR4: 0 | BS4: 0 | BT4: 0 | BU4: 0 | BV4: 0 | BW4: 0 | BX4: 0 | BY4: 0 | BZ4: 0 | CA4: 0 | CB4: 0 | CC4: 0
A5: Electricity Sector | B5: 1.6429965e-06 | C5: 1.74025e-06 | D5: 1.8797637e-06 | E5: 1.7043115e-06 | F5: 1.6618773e-06 | G5: 1.6263232e-06 | H5: 1.5925409e-06 | I5: 1.5243217e-06 | J5: 1.5244769e-06 | K5: 1.5389526e-06 | L5: 1.5184534e-06 | M5: 1.4713367e-06 | N5: 1.4739782e-06 | O5: 1.4644835e-06 | P5: 1.4552376e-06 | Q5: 1.4552551e-06 | R5: 1.476415e-06 | S5: 1.4735283e-06 | T5: 1.5156258e-06 | U5: 1.5135963e-06 | V5: 1.511719e-06 | W5: 1.5107166e-06 | X5: 1.5112678e-06 | Y5: 1.5110861e-06 | Z5: 1.5035086e-06 | AA5: 1.2925599e-06 | AB5: 1.4913563e-06 | AC5: 1.4912254e-06 | AD5: 1.5030987e-06 | AE5: 1.5007824e-06 | AF5: 1.5007824e-06 | AG5: 1.5007824e-06 | AH5: 1.5007824e-06 | AI5: 1.5007824e-06 | AJ5: 1.5007824e-06 | AK5: 1.5007824e-06 | AL5: 1.5007824e-06 | AM5: 1.5007824e-06 | AN5: 1.5007824e-06 | AO5: 1.5007824e-06 | AP5: 1.5007824e-06 | AQ5: 1.5007824e-06 | AR5: 1.5007824e-06 | AS5: 1.5007824e-06 | AT5: 1.5007824e-06 | AU5: 1.5007824e-06 | AV5: 1.5007824e-06 | AW5: 1.5007824e-06 | AX5: 1.5007824e-06 | AY5: 1.5007824e-06 | AZ5: 1.5007824e-06 | BA5: 1.5007824e-06 | BB5: 1.5007824e-06 | BC5: 1.5007824e-06 | BD5: 1.5007824e-06 | BE5: 1.5007824e-06 | BF5: 1.5007824e-06 | BG5: 1.5007824e-06 | BH5: 1.5007824e-06 | BI5: 1.5007824e-06 | BJ5: 1.5007824e-06 | BK5: 1.5007824e-06 | BL5: 1.5007824e-06 | BM5: 1.5007824e-06 | BN5: 1.5007824e-06 | BO5: 1.5007824e-06 | BP5: 1.5007824e-06 | BQ5: 1.5007824e-06 | BR5: 1.5007824e-06 | BS5: 1.5007824e-06 | BT5: 1.5007824e-06 | BU5: 1.5007824e-06 | BV5: 1.5007824e-06 | BW5: 1.5007824e-06 | BX5: 1.5007824e-06 | BY5: 1.5007824e-06 | BZ5: 1.5007824e-06 | CA5: 1.5007824e-06 | CB5: 1.5007824e-06 | CC5: 1.5007824e-06
A6: Residential Buildings Sector | B6: 0 | C6: 0 | D6: 0 | E6: 0 | F6: 0 | G6: 0 | H6: 0 | I6: 0 | J6: 0 | K6: 0 | L6: 0 | M6: 0 | N6: 0 | O6: 0 | P6: 0 | Q6: 0 | R6: 0 | S6: 0 | T6: 0 | U6: 0 | V6: 0 | W6: 0 | X6: 0 | Y6: 0 | Z6: 0 | AA6: 0 | AB6: 0 | AC6: 0 | AD6: 0 | AE6: 0 | AF6: 0 | AG6: 0 | AH6: 0 | AI6: 0 | AJ6: 0 | AK6: 0 | AL6: 0 | AM6: 0 | AN6: 0 | AO6: 0 | AP6: 0 | AQ6: 0 | AR6: 0 | AS6: 0 | AT6: 0 | AU6: 0 | AV6: 0 | AW6: 0 | AX6: 0 | AY6: 0 | AZ6: 0 | BA6: 0 | BB6: 0 | BC6: 0 | BD6: 0 | BE6: 0 | BF6: 0 | BG6: 0 | BH6: 0 | BI6: 0 | BJ6: 0 | BK6: 0 | BL6: 0 | BM6: 0 | BN6: 0 | BO6: 0 | BP6: 0 | BQ6: 0 | BR6: 0 | BS6: 0 | BT6: 0 | BU6: 0 | BV6: 0 | BW6: 0 | BX6: 0 | BY6: 0 | BZ6: 0 | CA6: 0 | CB6: 0 | CC6: 0
A7: Commercial Buildings Sector | B7: 0 | C7: 0 | D7: 0 | E7: 0 | F7: 0 | G7: 0 | H7: 0 | I7: 0 | J7: 0 | K7: 0 | L7: 0 | M7: 0 | N7: 0 | O7: 0 | P7: 0 | Q7: 0 | R7: 0 | S7: 0 | T7: 0 | U7: 0 | V7: 0 | W7: 0 | X7: 0 | Y7: 0 | Z7: 0 | AA7: 0 | AB7: 0 | AC7: 0 | AD7: 0 | AE7: 0 | AF7: 0 | AG7: 0 | AH7: 0 | AI7: 0 | AJ7: 0 | AK7: 0 | AL7: 0 | AM7: 0 | AN7: 0 | AO7: 0 | AP7: 0 | AQ7: 0 | AR7: 0 | AS7: 0 | AT7: 0 | AU7: 0 | AV7: 0 | AW7: 0 | AX7: 0 | AY7: 0 | AZ7: 0 | BA7: 0 | BB7: 0 | BC7: 0 | BD7: 0 | BE7: 0 | BF7: 0 | BG7: 0 | BH7: 0 | BI7: 0 | BJ7: 0 | BK7: 0 | BL7: 0 | BM7: 0 | BN7: 0 | BO7: 0 | BP7: 0 | BQ7: 0 | BR7: 0 | BS7: 0 | BT7: 0 | BU7: 0 | BV7: 0 | BW7: 0 | BX7: 0 | BY7: 0 | BZ7: 0 | CA7: 0 | CB7: 0 | CC7: 0
A8: Industry Sector | B8: 4.9035848e-06 | C8: 5.1938415e-06 | D8: 5.6102255e-06 | E8: 5.6816941e-06 | F8: 5.4263596e-06 | G8: 5.3751648e-06 | H8: 5.3521878e-06 | I8: 5.323103e-06 | J8: 5.3107545e-06 | K8: 5.3057241e-06 | L8: 5.3077499e-06 | M8: 5.3206938e-06 | N8: 5.3161073e-06 | O8: 5.2872988e-06 | P8: 5.2997515e-06 | Q8: 5.2983656e-06 | R8: 5.2961757e-06 | S8: 5.2965499e-06 | T8: 5.28197e-06 | U8: 5.2776098e-06 | V8: 5.2556025e-06 | W8: 5.2506546e-06 | X8: 5.2425424e-06 | Y8: 5.2449123e-06 | Z8: 5.2535837e-06 | AA8: 5.2500852e-06 | AB8: 5.2444837e-06 | AC8: 5.2437148e-06 | AD8: 5.2492193e-06 | AE8: 5.2450892e-06 | AF8: 5.2450892e-06 | AG8: 5.2450892e-06 | AH8: 5.2450892e-06 | AI8: 5.2450892e-06 | AJ8: 5.2450892e-06 | AK8: 5.2450892e-06 | AL8: 5.2450892e-06 | AM8: 5.2450892e-06 | AN8: 5.2450892e-06 | AO8: 5.2450892e-06 | AP8: 5.2450892e-06 | AQ8: 5.2450892e-06 | AR8: 5.2450892e-06 | AS8: 5.2450892e-06 | AT8: 5.2450892e-06 | AU8: 5.2450892e-06 | AV8: 5.2450892e-06 | AW8: 5.2450892e-06 | AX8: 5.2450892e-06 | AY8: 5.2450892e-06 | AZ8: 5.2450892e-06 | BA8: 5.2450892e-06 | BB8: 5.2450892e-06 | BC8: 5.2450892e-06 | BD8: 5.2450892e-06 | BE8: 5.2450892e-06 | BF8: 5.2450892e-06 | BG8: 5.2450892e-06 | BH8: 5.2450892e-06 | BI8: 5.2450892e-06 | BJ8: 5.2450892e-06 | BK8: 5.2450892e-06 | BL8: 5.2450892e-06 | BM8: 5.2450892e-06 | BN8: 5.2450892e-06 | BO8: 5.2450892e-06 | BP8: 5.2450892e-06 | BQ8: 5.2450892e-06 | BR8: 5.2450892e-06 | BS8: 5.2450892e-06 | BT8: 5.2450892e-06 | BU8: 5.2450892e-06 | BV8: 5.2450892e-06 | BW8: 5.2450892e-06 | BX8: 5.2450892e-06 | BY8: 5.2450892e-06 | BZ8: 5.2450892e-06 | CA8: 5.2450892e-06 | CB8: 5.2450892e-06 | CC8: 5.2450892e-06
A9: District Heating Sector | B9: 1.6429965e-06 | C9: 1.74025e-06 | D9: 1.8797637e-06 | E9: 1.7043115e-06 | F9: 1.6618773e-06 | G9: 1.6263232e-06 | H9: 1.5925409e-06 | I9: 1.5243217e-06 | J9: 1.5244769e-06 | K9: 1.5389526e-06 | L9: 1.5184534e-06 | M9: 1.4713367e-06 | N9: 1.4739782e-06 | O9: 1.4644835e-06 | P9: 1.4552376e-06 | Q9: 1.4552551e-06 | R9: 1.476415e-06 | S9: 1.4735283e-06 | T9: 1.5156258e-06 | U9: 1.5135963e-06 | V9: 1.511719e-06 | W9: 1.5107166e-06 | X9: 1.5112678e-06 | Y9: 1.5110861e-06 | Z9: 1.5035086e-06 | AA9: 1.2925599e-06 | AB9: 1.4913563e-06 | AC9: 1.4912254e-06 | AD9: 1.5030987e-06 | AE9: 1.5007824e-06 | AF9: 1.5007824e-06 | AG9: 1.5007824e-06 | AH9: 1.5007824e-06 | AI9: 1.5007824e-06 | AJ9: 1.5007824e-06 | AK9: 1.5007824e-06 | AL9: 1.5007824e-06 | AM9: 1.5007824e-06 | AN9: 1.5007824e-06 | AO9: 1.5007824e-06 | AP9: 1.5007824e-06 | AQ9: 1.5007824e-06 | AR9: 1.5007824e-06 | AS9: 1.5007824e-06 | AT9: 1.5007824e-06 | AU9: 1.5007824e-06 | AV9: 1.5007824e-06 | AW9: 1.5007824e-06 | AX9: 1.5007824e-06 | AY9: 1.5007824e-06 | AZ9: 1.5007824e-06 | BA9: 1.5007824e-06 | BB9: 1.5007824e-06 | BC9: 1.5007824e-06 | BD9: 1.5007824e-06 | BE9: 1.5007824e-06 | BF9: 1.5007824e-06 | BG9: 1.5007824e-06 | BH9: 1.5007824e-06 | BI9: 1.5007824e-06 | BJ9: 1.5007824e-06 | BK9: 1.5007824e-06 | BL9: 1.5007824e-06 | BM9: 1.5007824e-06 | BN9: 1.5007824e-06 | BO9: 1.5007824e-06 | BP9: 1.5007824e-06 | BQ9: 1.5007824e-06 | BR9: 1.5007824e-06 | BS9: 1.5007824e-06 | BT9: 1.5007824e-06 | BU9: 1.5007824e-06 | BV9: 1.5007824e-06 | BW9: 1.5007824e-06 | BX9: 1.5007824e-06 | BY9: 1.5007824e-06 | BZ9: 1.5007824e-06 | CA9: 1.5007824e-06 | CB9: 1.5007824e-06 | CC9: 1.5007824e-06
A10: LULUCF Sector | B10: 0 | C10: 0 | D10: 0 | E10: 0 | F10: 0 | G10: 0 | H10: 0 | I10: 0 | J10: 0 | K10: 0 | L10: 0 | M10: 0 | N10: 0 | O10: 0 | P10: 0 | Q10: 0 | R10: 0 | S10: 0 | T10: 0 | U10: 0 | V10: 0 | W10: 0 | X10: 0 | Y10: 0 | Z10: 0 | AA10: 0 | AB10: 0 | AC10: 0 | AD10: 0 | AE10: 0 | AF10: 0 | AG10: 0 | AH10: 0 | AI10: 0 | AJ10: 0 | AK10: 0 | AL10: 0 | AM10: 0 | AN10: 0 | AO10: 0 | AP10: 0 | AQ10: 0 | AR10: 0 | AS10: 0 | AT10: 0 | AU10: 0 | AV10: 0 | AW10: 0 | AX10: 0 | AY10: 0 | AZ10: 0 | BA10: 0 | BB10: 0 | BC10: 0 | BD10: 0 | BE10: 0 | BF10: 0 | BG10: 0 | BH10: 0 | BI10: 0 | BJ10: 0 | BK10: 0 | BL10: 0 | BM10: 0 | BN10: 0 | BO10: 0 | BP10: 0 | BQ10: 0 | BR10: 0 | BS10: 0 | BT10: 0 | BU10: 0 | BV10: 0 | BW10: 0 | BX10: 0 | BY10: 0 | BZ10: 0 | CA10: 0 | CB10: 0 | CC10: 0
A11: Geoengineering Sector | B11: 4.9035848e-06 | C11: 5.1938415e-06 | D11: 5.6102255e-06 | E11: 5.6816941e-06 | F11: 5.4263596e-06 | G11: 5.3751648e-06 | H11: 5.3521878e-06 | I11: 5.323103e-06 | J11: 5.3107545e-06 | K11: 5.3057241e-06 | L11: 5.3077499e-06 | M11: 5.3206938e-06 | N11: 5.3161073e-06 | O11: 5.2872988e-06 | P11: 5.2997515e-06 | Q11: 5.2983656e-06 | R11: 5.2961757e-06 | S11: 5.2965499e-06 | T11: 5.28197e-06 | U11: 5.2776098e-06 | V11: 5.2556025e-06 | W11: 5.2506546e-06 | X11: 5.2425424e-06 | Y11: 5.2449123e-06 | Z11: 5.2535837e-06 | AA11: 5.2500852e-06 | AB11: 5.2444837e-06 | AC11: 5.2437148e-06 | AD11: 5.2492193e-06 | AE11: 5.2450892e-06 | AF11: 5.2450892e-06 | AG11: 5.2450892e-06 | AH11: 5.2450892e-06 | AI11: 5.2450892e-06 | AJ11: 5.2450892e-06 | AK11: 5.2450892e-06 | AL11: 5.2450892e-06 | AM11: 5.2450892e-06 | AN11: 5.2450892e-06 | AO11: 5.2450892e-06 | AP11: 5.2450892e-06 | AQ11: 5.2450892e-06 | AR11: 5.2450892e-06 | AS11: 5.2450892e-06 | AT11: 5.2450892e-06 | AU11: 5.2450892e-06 | AV11: 5.2450892e-06 | AW11: 5.2450892e-06 | AX11: 5.2450892e-06 | AY11: 5.2450892e-06 | AZ11: 5.2450892e-06 | BA11: 5.2450892e-06 | BB11: 5.2450892e-06 | BC11: 5.2450892e-06 | BD11: 5.2450892e-06 | BE11: 5.2450892e-06 | BF11: 5.2450892e-06 | BG11: 5.2450892e-06 | BH11: 5.2450892e-06 | BI11: 5.2450892e-06 | BJ11: 5.2450892e-06 | BK11: 5.2450892e-06 | BL11: 5.2450892e-06 | BM11: 5.2450892e-06 | BN11: 5.2450892e-06 | BO11: 5.2450892e-06 | BP11: 5.2450892e-06 | BQ11: 5.2450892e-06 | BR11: 5.2450892e-06 | BS11: 5.2450892e-06 | BT11: 5.2450892e-06 | BU11: 5.2450892e-06 | BV11: 5.2450892e-06 | BW11: 5.2450892e-06 | BX11: 5.2450892e-06 | BY11: 5.2450892e-06 | BZ11: 5.2450892e-06 | CA11: 5.2450892e-06 | CB11: 5.2450892e-06 | CC11: 5.2450892e-06
A12: Natural Gas
A13: Year | B13: 2021 | C13: 2022 | D13: 2023 | E13: 2024 | F13: 2025 | G13: 2026 | H13: 2027 | I13: 2028 | J13: 2029 | K13: 2030 | L13: 2031 | M13: 2032 | N13: 2033 | O13: 2034 | P13: 2035 | Q13: 2036 | R13: 2037 | S13: 2038 | T13: 2039 | U13: 2040 | V13: 2041 | W13: 2042 | X13: 2043 | Y13: 2044 | Z13: 2045 | AA13: 2046 | AB13: 2047 | AC13: 2048 | AD13: 2049 | AE13: 2050
A14: Transportation Sector | B14: 9.9734043e-06 | C14: 1.5857682e-05 | D14: 7.0014695e-06 | E14: 9.9729704e-06 | F14: 1.134805e-05 | G14: 1.2223687e-05 | H14: 1.2604259e-05 | I14: 1.1855957e-05 | J14: 1.1107654e-05 | K14: 1.0359352e-05 | L14: 1.0436421e-05 | M14: 1.0687081e-05 | N14: 1.0848307e-05 | O14: 1.0926404e-05 | P14: 1.0925343e-05 | Q14: 1.0851478e-05 | R14: 1.0758591e-05 | S14: 1.0676225e-05 | T14: 1.0556723e-05 | U14: 1.0507353e-05 | V14: 1.0517076e-05 | W14: 1.0516e-05 | X14: 1.0515049e-05 | Y14: 1.0494597e-05 | Z14: 1.0478886e-05 | AA14: 1.0473531e-05 | AB14: 1.0424389e-05 | AC14: 1.0379359e-05 | AD14: 1.0373411e-05 | AE14: 1.0362482e-05 | AF14: 1.0362482e-05 | AG14: 1.0362482e-05 | AH14: 1.0362482e-05 | AI14: 1.0362482e-05 | AJ14: 1.0362482e-05 | AK14: 1.0362482e-05 | AL14: 1.0362482e-05 | AM14: 1.0362482e-05 | AN14: 1.0362482e-05 | AO14: 1.0362482e-05 | AP14: 1.0362482e-05 | AQ14: 1.0362482e-05 | AR14: 1.0362482e-05 | AS14: 1.0362482e-05 | AT14: 1.0362482e-05 | AU14: 1.0362482e-05 | AV14: 1.0362482e-05 | AW14: 1.0362482e-05 | AX14: 1.0362482e-05 | AY14: 1.0362482e-05 | AZ14: 1.0362482e-05 | BA14: 1.0362482e-05 | BB14: 1.0362482e-05 | BC14: 1.0362482e-05 | BD14: 1.0362482e-05 | BE14: 1.0362482e-05 | BF14: 1.0362482e-05 | BG14: 1.0362482e-05 | BH14: 1.0362482e-05 | BI14: 1.0362482e-05 | BJ14: 1.0362482e-05 | BK14: 1.0362482e-05 | BL14: 1.0362482e-05 | BM14: 1.0362482e-05 | BN14: 1.0362482e-05 | BO14: 1.0362482e-05 | BP14: 1.0362482e-05 | BQ14: 1.0362482e-05 | BR14: 1.0362482e-05 | BS14: 1.0362482e-05 | BT14: 1.0362482e-05 | BU14: 1.0362482e-05 | BV14: 1.0362482e-05 | BW14: 1.0362482e-05 | BX14: 1.0362482e-05 | BY14: 1.0362482e-05 | BZ14: 1.0362482e-05 | CA14: 1.0362482e-05 | CB14: 1.0362482e-05 | CC14: 1.0362482e-05
A15: Electricity Sector | B15: 3.3241875e-06 | C15: 5.285448e-06 | D15: 2.3336262e-06 | E15: 1.9509368e-06 | F15: 3.1290331e-06 | G15: 3.3704752e-06 | H15: 3.4754115e-06 | I15: 3.13637e-06 | J15: 2.7973285e-06 | K15: 2.458287e-06 | L15: 2.5210021e-06 | M15: 2.8631959e-06 | N15: 3.0750956e-06 | O15: 3.2182789e-06 | P15: 3.2670421e-06 | Q15: 3.2637126e-06 | R15: 3.2399388e-06 | S15: 3.216728e-06 | T15: 3.1787778e-06 | U15: 3.1998467e-06 | V15: 3.2535153e-06 | W15: 3.3031077e-06 | X15: 3.362557e-06 | Y15: 3.4208166e-06 | Z15: 3.4513655e-06 | AA15: 3.4902076e-06 | AB15: 3.4958755e-06 | AC15: 3.5114973e-06 | AD15: 3.5592047e-06 | AE15: 3.6137457e-06 | AF15: 3.6137457e-06 | AG15: 3.6137457e-06 | AH15: 3.6137457e-06 | AI15: 3.6137457e-06 | AJ15: 3.6137457e-06 | AK15: 3.6137457e-06 | AL15: 3.6137457e-06 | AM15: 3.6137457e-06 | AN15: 3.6137457e-06 | AO15: 3.6137457e-06 | AP15: 3.6137457e-06 | AQ15: 3.6137457e-06 | AR15: 3.6137457e-06 | AS15: 3.6137457e-06 | AT15: 3.6137457e-06 | AU15: 3.6137457e-06 | AV15: 3.6137457e-06 | AW15: 3.6137457e-06 | AX15: 3.6137457e-06 | AY15: 3.6137457e-06 | AZ15: 3.6137457e-06 | BA15: 3.6137457e-06 | BB15: 3.6137457e-06 | BC15: 3.6137457e-06 | BD15: 3.6137457e-06 | BE15: 3.6137457e-06 | BF15: 3.6137457e-06 | BG15: 3.6137457e-06 | BH15: 3.6137457e-06 | BI15: 3.6137457e-06 | BJ15: 3.6137457e-06 | BK15: 3.6137457e-06 | BL15: 3.6137457e-06 | BM15: 3.6137457e-06 | BN15: 3.6137457e-06 | BO15: 3.6137457e-06 | BP15: 3.6137457e-06 | BQ15: 3.6137457e-06 | BR15: 3.6137457e-06 | BS15: 3.6137457e-06 | BT15: 3.6137457e-06 | BU15: 3.6137457e-06 | BV15: 3.6137457e-06 | BW15: 3.6137457e-06 | BX15: 3.6137457e-06 | BY15: 3.6137457e-06 | BZ15: 3.6137457e-06 | CA15: 3.6137457e-06 | CB15: 3.6137457e-06 | CC15: 3.6137457e-06
A16: Residential Buildings Sector | B16: 9.9734043e-06 | C16: 1.5857682e-05 | D16: 7.0014695e-06 | E16: 9.9729704e-06 | F16: 1.134805e-05 | G16: 1.2223687e-05 | H16: 1.2604259e-05 | I16: 1.1046844e-05 | J16: 9.4894289e-06 | K16: 7.932014e-06 | L16: 8.0693505e-06 | M16: 8.3628822e-06 | N16: 8.6234716e-06 | O16: 8.8007718e-06 | P16: 8.8995297e-06 | Q16: 8.9096183e-06 | R16: 8.9008665e-06 | S16: 8.8860231e-06 | T16: 8.8465005e-06 | U16: 8.8681168e-06 | V16: 8.9534221e-06 | W16: 9.027955e-06 | X16: 9.0910768e-06 | Y16: 9.1306338e-06 | Z16: 9.1895029e-06 | AA16: 9.2556021e-06 | AB16: 9.2857393e-06 | AC16: 9.3051925e-06 | AD16: 9.3609306e-06 | AE16: 9.4099504e-06 | AF16: 9.4099504e-06 | AG16: 9.4099504e-06 | AH16: 9.4099504e-06 | AI16: 9.4099504e-06 | AJ16: 9.4099504e-06 | AK16: 9.4099504e-06 | AL16: 9.4099504e-06 | AM16: 9.4099504e-06 | AN16: 9.4099504e-06 | AO16: 9.4099504e-06 | AP16: 9.4099504e-06 | AQ16: 9.4099504e-06 | AR16: 9.4099504e-06 | AS16: 9.4099504e-06 | AT16: 9.4099504e-06 | AU16: 9.4099504e-06 | AV16: 9.4099504e-06 | AW16: 9.4099504e-06 | AX16: 9.4099504e-06 | AY16: 9.4099504e-06 | AZ16: 9.4099504e-06 | BA16: 9.4099504e-06 | BB16: 9.4099504e-06 | BC16: 9.4099504e-06 | BD16: 9.4099504e-06 | BE16: 9.4099504e-06 | BF16: 9.4099504e-06 | BG16: 9.4099504e-06 | BH16: 9.4099504e-06 | BI16: 9.4099504e-06 | BJ16: 9.4099504e-06 | BK16: 9.4099504e-06 | BL16: 9.4099504e-06 | BM16: 9.4099504e-06 | BN16: 9.4099504e-06 | BO16: 9.4099504e-06 | BP16: 9.4099504e-06 | BQ16: 9.4099504e-06 | BR16: 9.4099504e-06 | BS16: 9.4099504e-06 | BT16: 9.4099504e-06 | BU16: 9.4099504e-06 | BV16: 9.4099504e-06 | BW16: 9.4099504e-06 | BX16: 9.4099504e-06 | BY16: 9.4099504e-06 | BZ16: 9.4099504e-06 | CA16: 9.4099504e-06 | CB16: 9.4099504e-06 | CC16: 9.4099504e-06
A17: Commercial Buildings Sector | B17: 7.2177447e-06 | C17: 1.1476192e-05 | D17: 5.0669578e-06 | E17: 6.9033147e-06 | F17: 8.0668188e-06 | G17: 8.68927e-06 | H17: 8.9598014e-06 | I17: 8.0142262e-06 | J17: 7.068651e-06 | K17: 6.1230758e-06 | L17: 6.2220452e-06 | M17: 6.4616272e-06 | N17: 6.6767285e-06 | O17: 6.8135953e-06 | P17: 6.8794981e-06 | Q17: 6.8674156e-06 | R17: 6.8396588e-06 | S17: 6.8063854e-06 | T17: 6.7495303e-06 | U17: 6.7496995e-06 | V17: 6.8087273e-06 | W17: 6.8575676e-06 | X17: 6.8976256e-06 | Y17: 6.9152085e-06 | Z17: 6.9521159e-06 | AA17: 6.9978179e-06 | AB17: 7.0089318e-06 | AC17: 7.0121995e-06 | AD17: 7.0509694e-06 | AE17: 7.0834544e-06 | AF17: 7.0834544e-06 | AG17: 7.0834544e-06 | AH17: 7.0834544e-06 | AI17: 7.0834544e-06 | AJ17: 7.0834544e-06 | AK17: 7.0834544e-06 | AL17: 7.0834544e-06 | AM17: 7.0834544e-06 | AN17: 7.0834544e-06 | AO17: 7.0834544e-06 | AP17: 7.0834544e-06 | AQ17: 7.0834544e-06 | AR17: 7.0834544e-06 | AS17: 7.0834544e-06 | AT17: 7.0834544e-06 | AU17: 7.0834544e-06 | AV17: 7.0834544e-06 | AW17: 7.0834544e-06 | AX17: 7.0834544e-06 | AY17: 7.0834544e-06 | AZ17: 7.0834544e-06 | BA17: 7.0834544e-06 | BB17: 7.0834544e-06 | BC17: 7.0834544e-06 | BD17: 7.0834544e-06 | BE17: 7.0834544e-06 | BF17: 7.0834544e-06 | BG17: 7.0834544e-06 | BH17: 7.0834544e-06 | BI17: 7.0834544e-06 | BJ17: 7.0834544e-06 | BK17: 7.0834544e-06 | BL17: 7.0834544e-06 | BM17: 7.0834544e-06 | BN17: 7.0834544e-06 | BO17: 7.0834544e-06 | BP17: 7.0834544e-06 | BQ17: 7.0834544e-06 | BR17: 7.0834544e-06 | BS17: 7.0834544e-06 | BT17: 7.0834544e-06 | BU17: 7.0834544e-06 | BV17: 7.0834544e-06 | BW17: 7.0834544e-06 | BX17: 7.0834544e-06 | BY17: 7.0834544e-06 | BZ17: 7.0834544e-06 | CA17: 7.0834544e-06 | CB17: 7.0834544e-06 | CC17: 7.0834544e-06
A18: Industry Sector | B18: 3.9113417e-06 | C18: 6.2190213e-06 | D18: 2.7458166e-06 | E18: 2.6603683e-06 | F18: 3.7674561e-06 | G18: 4.0581603e-06 | H18: 4.1845068e-06 | I18: 3.7516463e-06 | J18: 3.3187858e-06 | K18: 2.8859253e-06 | L18: 2.994683e-06 | M18: 3.2952787e-06 | N18: 3.5328925e-06 | O18: 3.6920056e-06 | P18: 3.7477453e-06 | Q18: 3.739122e-06 | R18: 3.7045953e-06 | S18: 3.6635898e-06 | T18: 3.6087232e-06 | U18: 3.622652e-06 | V18: 3.6860694e-06 | W18: 3.7425751e-06 | X18: 3.7935765e-06 | Y18: 3.8307103e-06 | Z18: 3.8647868e-06 | AA18: 3.8999159e-06 | AB18: 3.9036809e-06 | AC18: 3.913402e-06 | AD18: 3.9548798e-06 | AE18: 3.9993757e-06 | AF18: 3.9993757e-06 | AG18: 3.9993757e-06 | AH18: 3.9993757e-06 | AI18: 3.9993757e-06 | AJ18: 3.9993757e-06 | AK18: 3.9993757e-06 | AL18: 3.9993757e-06 | AM18: 3.9993757e-06 | AN18: 3.9993757e-06 | AO18: 3.9993757e-06 | AP18: 3.9993757e-06 | AQ18: 3.9993757e-06 | AR18: 3.9993757e-06 | AS18: 3.9993757e-06 | AT18: 3.9993757e-06 | AU18: 3.9993757e-06 | AV18: 3.9993757e-06 | AW18: 3.9993757e-06 | AX18: 3.9993757e-06 | AY18: 3.9993757e-06 | AZ18: 3.9993757e-06 | BA18: 3.9993757e-06 | BB18: 3.9993757e-06 | BC18: 3.9993757e-06 | BD18: 3.9993757e-06 | BE18: 3.9993757e-06 | BF18: 3.9993757e-06 | BG18: 3.9993757e-06 | BH18: 3.9993757e-06 | BI18: 3.9993757e-06 | BJ18: 3.9993757e-06 | BK18: 3.9993757e-06 | BL18: 3.9993757e-06 | BM18: 3.9993757e-06 | BN18: 3.9993757e-06 | BO18: 3.9993757e-06 | BP18: 3.9993757e-06 | BQ18: 3.9993757e-06 | BR18: 3.9993757e-06 | BS18: 3.9993757e-06 | BT18: 3.9993757e-06 | BU18: 3.9993757e-06 | BV18: 3.9993757e-06 | BW18: 3.9993757e-06 | BX18: 3.9993757e-06 | BY18: 3.9993757e-06 | BZ18: 3.9993757e-06 | CA18: 3.9993757e-06 | CB18: 3.9993757e-06 | CC18: 3.9993757e-06
A19: District Heating Sector | B19: 3.3241875e-06 | C19: 5.285448e-06 | D19: 2.3336262e-06 | E19: 1.9509368e-06 | F19: 3.1290331e-06 | G19: 3.3704752e-06 | H19: 3.4754115e-06 | I19: 3.13637e-06 | J19: 2.7973285e-06 | K19: 2.458287e-06 | L19: 2.5210021e-06 | M19: 2.8631959e-06 | N19: 3.0750956e-06 | O19: 3.2182789e-06 | P19: 3.2670421e-06 | Q19: 3.2637126e-06 | R19: 3.2399388e-06 | S19: 3.216728e-06 | T19: 3.1787778e-06 | U19: 3.1998467e-06 | V19: 3.2535153e-06 | W19: 3.3031077e-06 | X19: 3.362557e-06 | Y19: 3.4208166e-06 | Z19: 3.4513655e-06 | AA19: 3.4902076e-06 | AB19: 3.4958755e-06 | AC19: 3.5114973e-06 | AD19: 3.5592047e-06 | AE19: 3.6137457e-06 | AF19: 3.6137457e-06 | AG19: 3.6137457e-06 | AH19: 3.6137457e-06 | AI19: 3.6137457e-06 | AJ19: 3.6137457e-06 | AK19: 3.6137457e-06 | AL19: 3.6137457e-06 | AM19: 3.6137457e-06 | AN19: 3.6137457e-06 | AO19: 3.6137457e-06 | AP19: 3.6137457e-06 | AQ19: 3.6137457e-06 | AR19: 3.6137457e-06 | AS19: 3.6137457e-06 | AT19: 3.6137457e-06 | AU19: 3.6137457e-06 | AV19: 3.6137457e-06 | AW19: 3.6137457e-06 | AX19: 3.6137457e-06 | AY19: 3.6137457e-06 | AZ19: 3.6137457e-06 | BA19: 3.6137457e-06 | BB19: 3.6137457e-06 | BC19: 3.6137457e-06 | BD19: 3.6137457e-06 | BE19: 3.6137457e-06 | BF19: 3.6137457e-06 | BG19: 3.6137457e-06 | BH19: 3.6137457e-06 | BI19: 3.6137457e-06 | BJ19: 3.6137457e-06 | BK19: 3.6137457e-06 | BL19: 3.6137457e-06 | BM19: 3.6137457e-06 | BN19: 3.6137457e-06 | BO19: 3.6137457e-06 | BP19: 3.6137457e-06 | BQ19: 3.6137457e-06 | BR19: 3.6137457e-06 | BS19: 3.6137457e-06 | BT19: 3.6137457e-06 | BU19: 3.6137457e-06 | BV19: 3.6137457e-06 | BW19: 3.6137457e-06 | BX19: 3.6137457e-06 | BY19: 3.6137457e-06 | BZ19: 3.6137457e-06 | CA19: 3.6137457e-06 | CB19: 3.6137457e-06 | CC19: 3.6137457e-06
A20: LULUCF Sector | B20: 0 | C20: 0 | D20: 0 | E20: 0 | F20: 0 | G20: 0 | H20: 0 | I20: 0 | J20: 0 | K20: 0 | L20: 0 | M20: 0 | N20: 0 | O20: 0 | P20: 0 | Q20: 0 | R20: 0 | S20: 0 | T20: 0 | U20: 0 | V20: 0 | W20: 0 | X20: 0 | Y20: 0 | Z20: 0 | AA20: 0 | AB20: 0 | AC20: 0 | AD20: 0 | AE20: 0 | AF20: 0 | AG20: 0 | AH20: 0 | AI20: 0 | AJ20: 0 | AK20: 0 | AL20: 0 | AM20: 0 | AN20: 0 | AO20: 0 | AP20: 0 | AQ20: 0 | AR20: 0 | AS20: 0 | AT20: 0 | AU20: 0 | AV20: 0 | AW20: 0 | AX20: 0 | AY20: 0 | AZ20: 0 | BA20: 0 | BB20: 0 | BC20: 0 | BD20: 0 | BE20: 0 | BF20: 0 | BG20: 0 | BH20: 0 | BI20: 0 | BJ20: 0 | BK20: 0 | BL20: 0 | BM20: 0 | BN20: 0 | BO20: 0 | BP20: 0 | BQ20: 0 | BR20: 0 | BS20: 0 | BT20: 0 | BU20: 0 | BV20: 0 | BW20: 0 | BX20: 0 | BY20: 0 | BZ20: 0 | CA20: 0 | CB20: 0 | CC20: 0
A21: Geoengineering Sector | B21: 3.9113417e-06 | C21: 6.2190213e-06 | D21: 2.7458166e-06 | E21: 2.6603683e-06 | F21: 3.7674561e-06 | G21: 4.0581603e-06 | H21: 4.1845068e-06 | I21: 3.7516463e-06 | J21: 3.3187858e-06 | K21: 2.8859253e-06 | L21: 2.994683e-06 | M21: 3.2952787e-06 | N21: 3.5328925e-06 | O21: 3.6920056e-06 | P21: 3.7477453e-06 | Q21: 3.739122e-06 | R21: 3.7045953e-06 | S21: 3.6635898e-06 | T21: 3.6087232e-06 | U21: 3.622652e-06 | V21: 3.6860694e-06 | W21: 3.7425751e-06 | X21: 3.7935765e-06 | Y21: 3.8307103e-06 | Z21: 3.8647868e-06 | AA21: 3.8999159e-06 | AB21: 3.9036809e-06 | AC21: 3.913402e-06 | AD21: 3.9548798e-06 | AE21: 3.9993757e-06 | AF21: 3.9993757e-06 | AG21: 3.9993757e-06 | AH21: 3.9993757e-06 | AI21: 3.9993757e-06 | AJ21: 3.9993757e-06 | AK21: 3.9993757e-06 | AL21: 3.9993757e-06 | AM21: 3.9993757e-06 | AN21: 3.9993757e-06 | AO21: 3.9993757e-06 | AP21: 3.9993757e-06 | AQ21: 3.9993757e-06 | AR21: 3.9993757e-06 | AS21: 3.9993757e-06 | AT21: 3.9993757e-06 | AU21: 3.9993757e-06 | AV21: 3.9993757e-06 | AW21: 3.9993757e-06 | AX21: 3.9993757e-06 | AY21: 3.9993757e-06 | AZ21: 3.9993757e-06 | BA21: 3.9993757e-06 | BB21: 3.9993757e-06 | BC21: 3.9993757e-06 | BD21: 3.9993757e-06 | BE21: 3.9993757e-06 | BF21: 3.9993757e-06 | BG21: 3.9993757e-06 | BH21: 3.9993757e-06 | BI21: 3.9993757e-06 | BJ21: 3.9993757e-06 | BK21: 3.9993757e-06 | BL21: 3.9993757e-06 | BM21: 3.9993757e-06 | BN21: 3.9993757e-06 | BO21: 3.9993757e-06 | BP21: 3.9993757e-06 | BQ21: 3.9993757e-06 | BR21: 3.9993757e-06 | BS21: 3.9993757e-06 | BT21: 3.9993757e-06 | BU21: 3.9993757e-06 | BV21: 3.9993757e-06 | BW21: 3.9993757e-06 | BX21: 3.9993757e-06 | BY21: 3.9993757e-06 | BZ21: 3.9993757e-06 | CA21: 3.9993757e-06 | CB21: 3.9993757e-06 | CC21: 3.9993757e-06
A22: Nuclear
A23: Year | B23: 2021 | C23: 2022 | D23: 2023 | E23: 2024 | F23: 2025 | G23: 2026 | H23: 2027 | I23: 2028 | J23: 2029 | K23: 2030 | L23: 2031 | M23: 2032 | N23: 2033 | O23: 2034 | P23: 2035 | Q23: 2036 | R23: 2037 | S23: 2038 | T23: 2039 | U23: 2040 | V23: 2041 | W23: 2042 | X23: 2043 | Y23: 2044 | Z23: 2045 | AA23: 2046 | AB23: 2047 | AC23: 2048 | AD23: 2049 | AE23: 2050
A24: Transportation Sector | B24: 0 | C24: 0 | D24: 0 | E24: 0 | F24: 0 | G24: 0 | H24: 0 | I24: 0 | J24: 0 | K24: 0 | L24: 0 | M24: 0 | N24: 0 | O24: 0 | P24: 0 | Q24: 0 | R24: 0 | S24: 0 | T24: 0 | U24: 0 | V24: 0 | W24: 0 | X24: 0 | Y24: 0 | Z24: 0 | AA24: 0 | AB24: 0 | AC24: 0 | AD24: 0 | AE24: 0 | AF24: 0 | AG24: 0 | AH24: 0 | AI24: 0 | AJ24: 0 | AK24: 0 | AL24: 0 | AM24: 0 | AN24: 0 | AO24: 0 | AP24: 0 | AQ24: 0 | AR24: 0 | AS24: 0 | AT24: 0 | AU24: 0 | AV24: 0 | AW24: 0 | AX24: 0 | AY24: 0 | AZ24: 0 | BA24: 0 | BB24: 0 | BC24: 0 | BD24: 0 | BE24: 0 | BF24: 0 | BG24: 0 | BH24: 0 | BI24: 0 | BJ24: 0 | BK24: 0 | BL24: 0 | BM24: 0 | BN24: 0 | BO24: 0 | BP24: 0 | BQ24: 0 | BR24: 0 | BS24: 0 | BT24: 0 | BU24: 0 | BV24: 0 | BW24: 0 | BX24: 0 | BY24: 0 | BZ24: 0 | CA24: 0 | CB24: 0 | CC24: 0
A25: Electricity Sector | B25: 5.9347691e-07 | C25: 5.2008817e-07 | D25: 5.200355e-07 | E25: 5.1387916e-07 | F25: 5.138346e-07 | G25: 5.1378268e-07 | H25: 5.1373832e-07 | I25: 5.1369384e-07 | J25: 5.1364196e-07 | K25: 5.1359743e-07 | L25: 5.1354555e-07 | M25: 5.1350099e-07 | N25: 5.1345655e-07 | O25: 5.1340463e-07 | P25: 5.1336015e-07 | Q25: 5.1330827e-07 | R25: 5.1326379e-07 | S25: 5.1321926e-07 | T25: 5.1316738e-07 | U25: 5.1312286e-07 | V25: 5.130785e-07 | W25: 5.1302654e-07 | X25: 5.1298202e-07 | Y25: 5.1293014e-07 | Z25: 5.1288566e-07 | AA25: 5.1284114e-07 | AB25: 5.1278925e-07 | AC25: 5.1274485e-07 | AD25: 5.1270037e-07 | AE25: 5.1264841e-07 | AF25: 5.1264841e-07 | AG25: 5.1264841e-07 | AH25: 5.1264841e-07 | AI25: 5.1264841e-07 | AJ25: 5.1264841e-07 | AK25: 5.1264841e-07 | AL25: 5.1264841e-07 | AM25: 5.1264841e-07 | AN25: 5.1264841e-07 | AO25: 5.1264841e-07 | AP25: 5.1264841e-07 | AQ25: 5.1264841e-07 | AR25: 5.1264841e-07 | AS25: 5.1264841e-07 | AT25: 5.1264841e-07 | AU25: 5.1264841e-07 | AV25: 5.1264841e-07 | AW25: 5.1264841e-07 | AX25: 5.1264841e-07 | AY25: 5.1264841e-07 | AZ25: 5.1264841e-07 | BA25: 5.1264841e-07 | BB25: 5.1264841e-07 | BC25: 5.1264841e-07 | BD25: 5.1264841e-07 | BE25: 5.1264841e-07 | BF25: 5.1264841e-07 | BG25: 5.1264841e-07 | BH25: 5.1264841e-07 | BI25: 5.1264841e-07 | BJ25: 5.1264841e-07 | BK25: 5.1264841e-07 | BL25: 5.1264841e-07 | BM25: 5.1264841e-07 | BN25: 5.1264841e-07 | BO25: 5.1264841e-07 | BP25: 5.1264841e-07 | BQ25: 5.1264841e-07 | BR25: 5.1264841e-07 | BS25: 5.1264841e-07 | BT25: 5.1264841e-07 | BU25: 5.1264841e-07 | BV25: 5.1264841e-07 | BW25: 5.1264841e-07 | BX25: 5.1264841e-07 | BY25: 5.1264841e-07 | BZ25: 5.1264841e-07 | CA25: 5.1264841e-07 | CB25: 5.1264841e-07 | CC25: 5.1264841e-07
A26: Residential Buildings Sector | B26: 0 | C26: 0 | D26: 0 | E26: 0 | F26: 0 | G26: 0 | H26: 0 | I26: 0 | J26: 0 | K26: 0 | L26: 0 | M26: 0 | N26: 0 | O26: 0 | P26: 0 | Q26: 0 | R26: 0 | S26: 0 | T26: 0 | U26: 0 | V26: 0 | W26: 0 | X26: 0 | Y26: 0 | Z26: 0 | AA26: 0 | AB26: 0 | AC26: 0 | AD26: 0 | AE26: 0 | AF26: 0 | AG26: 0 | AH26: 0 | AI26: 0 | AJ26: 0 | AK26: 0 | AL26: 0 | AM26: 0 | AN26: 0 | AO26: 0 | AP26: 0 | AQ26: 0 | AR26: 0 | AS26: 0 | AT26: 0 | AU26: 0 | AV26: 0 | AW26: 0 | AX26: 0 | AY26: 0 | AZ26: 0 | BA26: 0 | BB26: 0 | BC26: 0 | BD26: 0 | BE26: 0 | BF26: 0 | BG26: 0 | BH26: 0 | BI26: 0 | BJ26: 0 | BK26: 0 | BL26: 0 | BM26: 0 | BN26: 0 | BO26: 0 | BP26: 0 | BQ26: 0 | BR26: 0 | BS26: 0 | BT26: 0 | BU26: 0 | BV26: 0 | BW26: 0 | BX26: 0 | BY26: 0 | BZ26: 0 | CA26: 0 | CB26: 0 | CC26: 0
A27: Commercial Buildings Sector | B27: 0 | C27: 0 | D27: 0 | E27: 0 | F27: 0 | G27: 0 | H27: 0 | I27: 0 | J27: 0 | K27: 0 | L27: 0 | M27: 0 | N27: 0 | O27: 0 | P27: 0 | Q27: 0 | R27: 0 | S27: 0 | T27: 0 | U27: 0 | V27: 0 | W27: 0 | X27: 0 | Y27: 0 | Z27: 0 | AA27: 0 | AB27: 0 | AC27: 0 | AD27: 0 | AE27: 0 | AF27: 0 | AG27: 0 | AH27: 0 | AI27: 0 | AJ27: 0 | AK27: 0 | AL27: 0 | AM27: 0 | AN27: 0 | AO27: 0 | AP27: 0 | AQ27: 0 | AR27: 0 | AS27: 0 | AT27: 0 | AU27: 0 | AV27: 0 | AW27: 0 | AX27: 0 | AY27: 0 | AZ27: 0 | BA27: 0 | BB27: 0 | BC27: 0 | BD27: 0 | BE27: 0 | BF27: 0 | BG27: 0 | BH27: 0 | BI27: 0 | BJ27: 0 | BK27: 0 | BL27: 0 | BM27: 0 | BN27: 0 | BO27: 0 | BP27: 0 | BQ27: 0 | BR27: 0 | BS27: 0 | BT27: 0 | BU27: 0 | BV27: 0 | BW27: 0 | BX27: 0 | BY27: 0 | BZ27: 0 | CA27: 0 | CB27: 0 | CC27: 0
A28: Industry Sector | B28: 0 | C28: 0 | D28: 0 | E28: 0 | F28: 0 | G28: 0 | H28: 0 | I28: 0 | J28: 0 | K28: 0 | L28: 0 | M28: 0 | N28: 0 | O28: 0 | P28: 0 | Q28: 0 | R28: 0 | S28: 0 | T28: 0 | U28: 0 | V28: 0 | W28: 0 | X28: 0 | Y28: 0 | Z28: 0 | AA28: 0 | AB28: 0 | AC28: 0 | AD28: 0 | AE28: 0 | AF28: 0 | AG28: 0 | AH28: 0 | AI28: 0 | AJ28: 0 | AK28: 0 | AL28: 0 | AM28: 0 | AN28: 0 | AO28: 0 | AP28: 0 | AQ28: 0 | AR28: 0 | AS28: 0 | AT28: 0 | AU28: 0 | AV28: 0 | AW28: 0 | AX28: 0 | AY28: 0 | AZ28: 0 | BA28: 0 | BB28: 0 | BC28: 0 | BD28: 0 | BE28: 0 | BF28: 0 | BG28: 0 | BH28: 0 | BI28: 0 | BJ28: 0 | BK28: 0 | BL28: 0 | BM28: 0 | BN28: 0 | BO28: 0 | BP28: 0 | BQ28: 0 | BR28: 0 | BS28: 0 | BT28: 0 | BU28: 0 | BV28: 0 | BW28: 0 | BX28: 0 | BY28: 0 | BZ28: 0 | CA28: 0 | CB28: 0 | CC28: 0
A29: District Heating Sector | B29: 0 | C29: 0 | D29: 0 | E29: 0 | F29: 0 | G29: 0 | H29: 0 | I29: 0 | J29: 0 | K29: 0 | L29: 0 | M29: 0 | N29: 0 | O29: 0 | P29: 0 | Q29: 0 | R29: 0 | S29: 0 | T29: 0 | U29: 0 | V29: 0 | W29: 0 | X29: 0 | Y29: 0 | Z29: 0 | AA29: 0 | AB29: 0 | AC29: 0 | AD29: 0 | AE29: 0 | AF29: 0 | AG29: 0 | AH29: 0 | AI29: 0 | AJ29: 0 | AK29: 0 | AL29: 0 | AM29: 0 | AN29: 0 | AO29: 0 | AP29: 0 | AQ29: 0 | AR29: 0 | AS29: 0 | AT29: 0 | AU29: 0 | AV29: 0 | AW29: 0 | AX29: 0 | AY29: 0 | AZ29: 0 | BA29: 0 | BB29: 0 | BC29: 0 | BD29: 0 | BE29: 0 | BF29: 0 | BG29: 0 | BH29: 0 | BI29: 0 | BJ29: 0 | BK29: 0 | BL29: 0 | BM29: 0 | BN29: 0 | BO29: 0 | BP29: 0 | BQ29: 0 | BR29: 0 | BS29: 0 | BT29: 0 | BU29: 0 | BV29: 0 | BW29: 0 | BX29: 0 | BY29: 0 | BZ29: 0 | CA29: 0 | CB29: 0 | CC29: 0
A30: LULUCF Sector | B30: 0 | C30: 0 | D30: 0 | E30: 0 | F30: 0 | G30: 0 | H30: 0 | I30: 0 | J30: 0 | K30: 0 | L30: 0 | M30: 0 | N30: 0 | O30: 0 | P30: 0 | Q30: 0 | R30: 0 | S30: 0 | T30: 0 | U30: 0 | V30: 0 | W30: 0 | X30: 0 | Y30: 0 | Z30: 0 | AA30: 0 | AB30: 0 | AC30: 0 | AD30: 0 | AE30: 0 | AF30: 0 | AG30: 0 | AH30: 0 | AI30: 0 | AJ30: 0 | AK30: 0 | AL30: 0 | AM30: 0 | AN30: 0 | AO30: 0 | AP30: 0 | AQ30: 0 | AR30: 0 | AS30: 0 | AT30: 0 | AU30: 0 | AV30: 0 | AW30: 0 | AX30: 0 | AY30: 0 | AZ30: 0 | BA30: 0 | BB30: 0 | BC30: 0 | BD30: 0 | BE30: 0 | BF30: 0 | BG30: 0 | BH30: 0 | BI30: 0 | BJ30: 0 | BK30: 0 | BL30: 0 | BM30: 0 | BN30: 0 | BO30: 0 | BP30: 0 | BQ30: 0 | BR30: 0 | BS30: 0 | BT30: 0 | BU30: 0 | BV30: 0 | BW30: 0 | BX30: 0 | BY30: 0 | BZ30: 0 | CA30: 0 | CB30: 0 | CC30: 0
A31: Geoengineering Sector | B31: 0 | C31: 0 | D31: 0 | E31: 0 | F31: 0 | G31: 0 | H31: 0 | I31: 0 | J31: 0 | K31: 0 | L31: 0 | M31: 0 | N31: 0 | O31: 0 | P31: 0 | Q31: 0 | R31: 0 | S31: 0 | T31: 0 | U31: 0 | V31: 0 | W31: 0 | X31: 0 | Y31: 0 | Z31: 0 | AA31: 0 | AB31: 0 | AC31: 0 | AD31: 0 | AE31: 0 | AF31: 0 | AG31: 0 | AH31: 0 | AI31: 0 | AJ31: 0 | AK31: 0 | AL31: 0 | AM31: 0 | AN31: 0 | AO31: 0 | AP31: 0 | AQ31: 0 | AR31: 0 | AS31: 0 | AT31: 0 | AU31: 0 | AV31: 0 | AW31: 0 | AX31: 0 | AY31: 0 | AZ31: 0 | BA31: 0 | BB31: 0 | BC31: 0 | BD31: 0 | BE31: 0 | BF31: 0 | BG31: 0 | BH31: 0 | BI31: 0 | BJ31: 0 | BK31: 0 | BL31: 0 | BM31: 0 | BN31: 0 | BO31: 0 | BP31: 0 | BQ31: 0 | BR31: 0 | BS31: 0 | BT31: 0 | BU31: 0 | BV31: 0 | BW31: 0 | BX31: 0 | BY31: 0 | BZ31: 0 | CA31: 0 | CB31: 0 | CC31: 0
A32: Biomass
A33: Year | B33: 2021 | C33: 2022 | D33: 2023 | E33: 2024 | F33: 2025 | G33: 2026 | H33: 2027 | I33: 2028 | J33: 2029 | K33: 2030 | L33: 2031 | M33: 2032 | N33: 2033 | O33: 2034 | P33: 2035 | Q33: 2036 | R33: 2037 | S33: 2038 | T33: 2039 | U33: 2040 | V33: 2041 | W33: 2042 | X33: 2043 | Y33: 2044 | Z33: 2045 | AA33: 2046 | AB33: 2047 | AC33: 2048 | AD33: 2049 | AE33: 2050
A34: Transportation Sector | B34: 0 | C34: 0 | D34: 0 | E34: 0 | F34: 0 | G34: 0 | H34: 0 | I34: 0 | J34: 0 | K34: 0 | L34: 0 | M34: 0 | N34: 0 | O34: 0 | P34: 0 | Q34: 0 | R34: 0 | S34: 0 | T34: 0 | U34: 0 | V34: 0 | W34: 0 | X34: 0 | Y34: 0 | Z34: 0 | AA34: 0 | AB34: 0 | AC34: 0 | AD34: 0 | AE34: 0 | AF34: 0 | AG34: 0 | AH34: 0 | AI34: 0 | AJ34: 0 | AK34: 0 | AL34: 0 | AM34: 0 | AN34: 0 | AO34: 0 | AP34: 0 | AQ34: 0 | AR34: 0 | AS34: 0 | AT34: 0 | AU34: 0 | AV34: 0 | AW34: 0 | AX34: 0 | AY34: 0 | AZ34: 0 | BA34: 0 | BB34: 0 | BC34: 0 | BD34: 0 | BE34: 0 | BF34: 0 | BG34: 0 | BH34: 0 | BI34: 0 | BJ34: 0 | BK34: 0 | BL34: 0 | BM34: 0 | BN34: 0 | BO34: 0 | BP34: 0 | BQ34: 0 | BR34: 0 | BS34: 0 | BT34: 0 | BU34: 0 | BV34: 0 | BW34: 0 | BX34: 0 | BY34: 0 | BZ34: 0 | CA34: 0 | CB34: 0 | CC34: 0
A35: Electricity Sector | B35: 1.8911026e-06 | C35: 1.8911026e-06 | D35: 1.8911026e-06 | E35: 1.9522972e-06 | F35: 1.9522972e-06 | G35: 1.9522972e-06 | H35: 1.9522972e-06 | I35: 1.9522972e-06 | J35: 1.9522972e-06 | K35: 1.9522972e-06 | L35: 1.9522972e-06 | M35: 1.9522972e-06 | N35: 1.9522972e-06 | O35: 1.9522972e-06 | P35: 1.9522972e-06 | Q35: 1.9522972e-06 | R35: 1.9522972e-06 | S35: 1.9522972e-06 | T35: 1.9522972e-06 | U35: 1.9522972e-06 | V35: 1.9522972e-06 | W35: 1.9522972e-06 | X35: 1.9522972e-06 | Y35: 1.9522972e-06 | Z35: 1.9522972e-06 | AA35: 1.9522972e-06 | AB35: 1.9522972e-06 | AC35: 1.9522972e-06 | AD35: 1.9522972e-06 | AE35: 1.9522972e-06 | AF35: 1.9522972e-06 | AG35: 1.9522972e-06 | AH35: 1.9522972e-06 | AI35: 1.9522972e-06 | AJ35: 1.9522972e-06 | AK35: 1.9522972e-06 | AL35: 1.9522972e-06 | AM35: 1.9522972e-06 | AN35: 1.9522972e-06 | AO35: 1.9522972e-06 | AP35: 1.9522972e-06 | AQ35: 1.9522972e-06 | AR35: 1.9522972e-06 | AS35: 1.9522972e-06 | AT35: 1.9522972e-06 | AU35: 1.9522972e-06 | AV35: 1.9522972e-06 | AW35: 1.9522972e-06 | AX35: 1.9522972e-06 | AY35: 1.9522972e-06 | AZ35: 1.9522972e-06 | BA35: 1.9522972e-06 | BB35: 1.9522972e-06 | BC35: 1.9522972e-06 | BD35: 1.9522972e-06 | BE35: 1.9522972e-06 | BF35: 1.9522972e-06 | BG35: 1.9522972e-06 | BH35: 1.9522972e-06 | BI35: 1.9522972e-06 | BJ35: 1.9522972e-06 | BK35: 1.9522972e-06 | BL35: 1.9522972e-06 | BM35: 1.9522972e-06 | BN35: 1.9522972e-06 | BO35: 1.9522972e-06 | BP35: 1.9522972e-06 | BQ35: 1.9522972e-06 | BR35: 1.9522972e-06 | BS35: 1.9522972e-06 | BT35: 1.9522972e-06 | BU35: 1.9522972e-06 | BV35: 1.9522972e-06 | BW35: 1.9522972e-06 | BX35: 1.9522972e-06 | BY35: 1.9522972e-06 | BZ35: 1.9522972e-06 | CA35: 1.9522972e-06 | CB35: 1.9522972e-06 | CC35: 1.9522972e-06
A36: Residential Buildings Sector | B36: 7.5388548e-06 | C36: 7.5388548e-06 | D36: 7.5388548e-06 | E36: 8.3780237e-06 | F36: 8.3780237e-06 | G36: 8.3780237e-06 | H36: 8.3780237e-06 | I36: 8.3780237e-06 | J36: 8.3780237e-06 | K36: 8.3780237e-06 | L36: 8.3780237e-06 | M36: 8.3780237e-06 | N36: 8.3780237e-06 | O36: 8.3780237e-06 | P36: 8.3780237e-06 | Q36: 8.3780237e-06 | R36: 8.3780237e-06 | S36: 8.3780237e-06 | T36: 8.3780237e-06 | U36: 8.3780237e-06 | V36: 8.3780237e-06 | W36: 8.3780237e-06 | X36: 8.3780237e-06 | Y36: 8.3780237e-06 | Z36: 8.3780237e-06 | AA36: 8.3780237e-06 | AB36: 8.3780237e-06 | AC36: 8.3780237e-06 | AD36: 8.3780237e-06 | AE36: 8.3780237e-06 | AF36: 8.3780237e-06 | AG36: 8.3780237e-06 | AH36: 8.3780237e-06 | AI36: 8.3780237e-06 | AJ36: 8.3780237e-06 | AK36: 8.3780237e-06 | AL36: 8.3780237e-06 | AM36: 8.3780237e-06 | AN36: 8.3780237e-06 | AO36: 8.3780237e-06 | AP36: 8.3780237e-06 | AQ36: 8.3780237e-06 | AR36: 8.3780237e-06 | AS36: 8.3780237e-06 | AT36: 8.3780237e-06 | AU36: 8.3780237e-06 | AV36: 8.3780237e-06 | AW36: 8.3780237e-06 | AX36: 8.3780237e-06 | AY36: 8.3780237e-06 | AZ36: 8.3780237e-06 | BA36: 8.3780237e-06 | BB36: 8.3780237e-06 | BC36: 8.3780237e-06 | BD36: 8.3780237e-06 | BE36: 8.3780237e-06 | BF36: 8.3780237e-06 | BG36: 8.3780237e-06 | BH36: 8.3780237e-06 | BI36: 8.3780237e-06 | BJ36: 8.3780237e-06 | BK36: 8.3780237e-06 | BL36: 8.3780237e-06 | BM36: 8.3780237e-06 | BN36: 8.3780237e-06 | BO36: 8.3780237e-06 | BP36: 8.3780237e-06 | BQ36: 8.3780237e-06 | BR36: 8.3780237e-06 | BS36: 8.3780237e-06 | BT36: 8.3780237e-06 | BU36: 8.3780237e-06 | BV36: 8.3780237e-06 | BW36: 8.3780237e-06 | BX36: 8.3780237e-06 | BY36: 8.3780237e-06 | BZ36: 8.3780237e-06 | CA36: 8.3780237e-06 | CB36: 8.3780237e-06 | CC36: 8.3780237e-06
A37: Commercial Buildings Sector | B37: 3.5010953e-06 | C37: 3.5010953e-06 | D37: 3.5010953e-06 | E37: 2.9144005e-06 | F37: 2.9144005e-06 | G37: 2.9144005e-06 | H37: 2.9144005e-06 | I37: 2.9144005e-06 | J37: 2.9144005e-06 | K37: 2.9144005e-06 | L37: 2.9144005e-06 | M37: 2.9144005e-06 | N37: 2.9144005e-06 | O37: 2.9144005e-06 | P37: 2.9144005e-06 | Q37: 2.9144005e-06 | R37: 2.9144005e-06 | S37: 2.9144005e-06 | T37: 2.9144005e-06 | U37: 2.9144005e-06 | V37: 2.9144005e-06 | W37: 2.9144005e-06 | X37: 2.9144005e-06 | Y37: 2.9144005e-06 | Z37: 2.9144005e-06 | AA37: 2.9144005e-06 | AB37: 2.9144005e-06 | AC37: 2.9144005e-06 | AD37: 2.9144005e-06 | AE37: 2.9144005e-06 | AF37: 2.9144005e-06 | AG37: 2.9144005e-06 | AH37: 2.9144005e-06 | AI37: 2.9144005e-06 | AJ37: 2.9144005e-06 | AK37: 2.9144005e-06 | AL37: 2.9144005e-06 | AM37: 2.9144005e-06 | AN37: 2.9144005e-06 | AO37: 2.9144005e-06 | AP37: 2.9144005e-06 | AQ37: 2.9144005e-06 | AR37: 2.9144005e-06 | AS37: 2.9144005e-06 | AT37: 2.9144005e-06 | AU37: 2.9144005e-06 | AV37: 2.9144005e-06 | AW37: 2.9144005e-06 | AX37: 2.9144005e-06 | AY37: 2.9144005e-06 | AZ37: 2.9144005e-06 | BA37: 2.9144005e-06 | BB37: 2.9144005e-06 | BC37: 2.9144005e-06 | BD37: 2.9144005e-06 | BE37: 2.9144005e-06 | BF37: 2.9144005e-06 | BG37: 2.9144005e-06 | BH37: 2.9144005e-06 | BI37: 2.9144005e-06 | BJ37: 2.9144005e-06 | BK37: 2.9144005e-06 | BL37: 2.9144005e-06 | BM37: 2.9144005e-06 | BN37: 2.9144005e-06 | BO37: 2.9144005e-06 | BP37: 2.9144005e-06 | BQ37: 2.9144005e-06 | BR37: 2.9144005e-06 | BS37: 2.9144005e-06 | BT37: 2.9144005e-06 | BU37: 2.9144005e-06 | BV37: 2.9144005e-06 | BW37: 2.9144005e-06 | BX37: 2.9144005e-06 | BY37: 2.9144005e-06 | BZ37: 2.9144005e-06 | CA37: 2.9144005e-06 | CB37: 2.9144005e-06 | CC37: 2.9144005e-06
A38: Industry Sector | B38: 2.2403602e-06 | C38: 2.2403602e-06 | D38: 2.2403602e-06 | E38: 2.1770221e-06 | F38: 2.1770221e-06 | G38: 2.1770221e-06 | H38: 2.1770221e-06 | I38: 2.1770221e-06 | J38: 2.1770221e-06 | K38: 2.1770221e-06 | L38: 2.1770221e-06 | M38: 2.1770221e-06 | N38: 2.1770221e-06 | O38: 2.1770221e-06 | P38: 2.1770221e-06 | Q38: 2.1770221e-06 | R38: 2.1770221e-06 | S38: 2.1770221e-06 | T38: 2.1770221e-06 | U38: 2.1770221e-06 | V38: 2.1770221e-06 | W38: 2.1770221e-06 | X38: 2.1770221e-06 | Y38: 2.1770221e-06 | Z38: 2.1770221e-06 | AA38: 2.1770221e-06 | AB38: 2.1770221e-06 | AC38: 2.1770221e-06 | AD38: 2.1770221e-06 | AE38: 2.1770221e-06 | AF38: 2.1770221e-06 | AG38: 2.1770221e-06 | AH38: 2.1770221e-06 | AI38: 2.1770221e-06 | AJ38: 2.1770221e-06 | AK38: 2.1770221e-06 | AL38: 2.1770221e-06 | AM38: 2.1770221e-06 | AN38: 2.1770221e-06 | AO38: 2.1770221e-06 | AP38: 2.1770221e-06 | AQ38: 2.1770221e-06 | AR38: 2.1770221e-06 | AS38: 2.1770221e-06 | AT38: 2.1770221e-06 | AU38: 2.1770221e-06 | AV38: 2.1770221e-06 | AW38: 2.1770221e-06 | AX38: 2.1770221e-06 | AY38: 2.1770221e-06 | AZ38: 2.1770221e-06 | BA38: 2.1770221e-06 | BB38: 2.1770221e-06 | BC38: 2.1770221e-06 | BD38: 2.1770221e-06 | BE38: 2.1770221e-06 | BF38: 2.1770221e-06 | BG38: 2.1770221e-06 | BH38: 2.1770221e-06 | BI38: 2.1770221e-06 | BJ38: 2.1770221e-06 | BK38: 2.1770221e-06 | BL38: 2.1770221e-06 | BM38: 2.1770221e-06 | BN38: 2.1770221e-06 | BO38: 2.1770221e-06 | BP38: 2.1770221e-06 | BQ38: 2.1770221e-06 | BR38: 2.1770221e-06 | BS38: 2.1770221e-06 | BT38: 2.1770221e-06 | BU38: 2.1770221e-06 | BV38: 2.1770221e-06 | BW38: 2.1770221e-06 | BX38: 2.1770221e-06 | BY38: 2.1770221e-06 | BZ38: 2.1770221e-06 | CA38: 2.1770221e-06 | CB38: 2.1770221e-06 | CC38: 2.1770221e-06
A39: District Heating Sector | B39: 1.8911026e-06 | C39: 1.8911026e-06 | D39: 1.8911026e-06 | E39: 1.9522972e-06 | F39: 1.9522972e-06 | G39: 1.9522972e-06 | H39: 1.9522972e-06 | I39: 1.9522972e-06 | J39: 1.9522972e-06 | K39: 1.9522972e-06 | L39: 1.9522972e-06 | M39: 1.9522972e-06 | N39: 1.9522972e-06 | O39: 1.9522972e-06 | P39: 1.9522972e-06 | Q39: 1.9522972e-06 | R39: 1.9522972e-06 | S39: 1.9522972e-06 | T39: 1.9522972e-06 | U39: 1.9522972e-06 | V39: 1.9522972e-06 | W39: 1.9522972e-06 | X39: 1.9522972e-06 | Y39: 1.9522972e-06 | Z39: 1.9522972e-06 | AA39: 1.9522972e-06 | AB39: 1.9522972e-06 | AC39: 1.9522972e-06 | AD39: 1.9522972e-06 | AE39: 1.9522972e-06 | AF39: 1.9522972e-06 | AG39: 1.9522972e-06 | AH39: 1.9522972e-06 | AI39: 1.9522972e-06 | AJ39: 1.9522972e-06 | AK39: 1.9522972e-06 | AL39: 1.9522972e-06 | AM39: 1.9522972e-06 | AN39: 1.9522972e-06 | AO39: 1.9522972e-06 | AP39: 1.9522972e-06 | AQ39: 1.9522972e-06 | AR39: 1.9522972e-06 | AS39: 1.9522972e-06 | AT39: 1.9522972e-06 | AU39: 1.9522972e-06 | AV39: 1.9522972e-06 | AW39: 1.9522972e-06 | AX39: 1.9522972e-06 | AY39: 1.9522972e-06 | AZ39: 1.9522972e-06 | BA39: 1.9522972e-06 | BB39: 1.9522972e-06 | BC39: 1.9522972e-06 | BD39: 1.9522972e-06 | BE39: 1.9522972e-06 | BF39: 1.9522972e-06 | BG39: 1.9522972e-06 | BH39: 1.9522972e-06 | BI39: 1.9522972e-06 | BJ39: 1.9522972e-06 | BK39: 1.9522972e-06 | BL39: 1.9522972e-06 | BM39: 1.9522972e-06 | BN39: 1.9522972e-06 | BO39: 1.9522972e-06 | BP39: 1.9522972e-06 | BQ39: 1.9522972e-06 | BR39: 1.9522972e-06 | BS39: 1.9522972e-06 | BT39: 1.9522972e-06 | BU39: 1.9522972e-06 | BV39: 1.9522972e-06 | BW39: 1.9522972e-06 | BX39: 1.9522972e-06 | BY39: 1.9522972e-06 | BZ39: 1.9522972e-06 | CA39: 1.9522972e-06 | CB39: 1.9522972e-06 | CC39: 1.9522972e-06
A40: LULUCF Sector | B40: 0 | C40: 0 | D40: 0 | E40: 0 | F40: 0 | G40: 0 | H40: 0 | I40: 0 | J40: 0 | K40: 0 | L40: 0 | M40: 0 | N40: 0 | O40: 0 | P40: 0 | Q40: 0 | R40: 0 | S40: 0 | T40: 0 | U40: 0 | V40: 0 | W40: 0 | X40: 0 | Y40: 0 | Z40: 0 | AA40: 0 | AB40: 0 | AC40: 0 | AD40: 0 | AE40: 0 | AF40: 0 | AG40: 0 | AH40: 0 | AI40: 0 | AJ40: 0 | AK40: 0 | AL40: 0 | AM40: 0 | AN40: 0 | AO40: 0 | AP40: 0 | AQ40: 0 | AR40: 0 | AS40: 0 | AT40: 0 | AU40: 0 | AV40: 0 | AW40: 0 | AX40: 0 | AY40: 0 | AZ40: 0 | BA40: 0 | BB40: 0 | BC40: 0 | BD40: 0 | BE40: 0 | BF40: 0 | BG40: 0 | BH40: 0 | BI40: 0 | BJ40: 0 | BK40: 0 | BL40: 0 | BM40: 0 | BN40: 0 | BO40: 0 | BP40: 0 | BQ40: 0 | BR40: 0 | BS40: 0 | BT40: 0 | BU40: 0 | BV40: 0 | BW40: 0 | BX40: 0 | BY40: 0 | BZ40: 0 | CA40: 0 | CB40: 0 | CC40: 0
A41: Geoengineering Sector | B41: 2.2403602e-06 | C41: 2.2403602e-06 | D41: 2.2403602e-06 | E41: 2.1770221e-06 | F41: 2.1770221e-06 | G41: 2.1770221e-06 | H41: 2.1770221e-06 | I41: 2.1770221e-06 | J41: 2.1770221e-06 | K41: 2.1770221e-06 | L41: 2.1770221e-06 | M41: 2.1770221e-06 | N41: 2.1770221e-06 | O41: 2.1770221e-06 | P41: 2.1770221e-06 | Q41: 2.1770221e-06 | R41: 2.1770221e-06 | S41: 2.1770221e-06 | T41: 2.1770221e-06 | U41: 2.1770221e-06 | V41: 2.1770221e-06 | W41: 2.1770221e-06 | X41: 2.1770221e-06 | Y41: 2.1770221e-06 | Z41: 2.1770221e-06 | AA41: 2.1770221e-06 | AB41: 2.1770221e-06 | AC41: 2.1770221e-06 | AD41: 2.1770221e-06 | AE41: 2.1770221e-06 | AF41: 2.1770221e-06 | AG41: 2.1770221e-06 | AH41: 2.1770221e-06 | AI41: 2.1770221e-06 | AJ41: 2.1770221e-06 | AK41: 2.1770221e-06 | AL41: 2.1770221e-06 | AM41: 2.1770221e-06 | AN41: 2.1770221e-06 | AO41: 2.1770221e-06 | AP41: 2.1770221e-06 | AQ41: 2.1770221e-06 | AR41: 2.1770221e-06 | AS41: 2.1770221e-06 | AT41: 2.1770221e-06 | AU41: 2.1770221e-06 | AV41: 2.1770221e-06 | AW41: 2.1770221e-06 | AX41: 2.1770221e-06 | AY41: 2.1770221e-06 | AZ41: 2.1770221e-06 | BA41: 2.1770221e-06 | BB41: 2.1770221e-06 | BC41: 2.1770221e-06 | BD41: 2.1770221e-06 | BE41: 2.1770221e-06 | BF41: 2.1770221e-06 | BG41: 2.1770221e-06 | BH41: 2.1770221e-06 | BI41: 2.1770221e-06 | BJ41: 2.1770221e-06 | BK41: 2.1770221e-06 | BL41: 2.1770221e-06 | BM41: 2.1770221e-06 | BN41: 2.1770221e-06 | BO41: 2.1770221e-06 | BP41: 2.1770221e-06 | BQ41: 2.1770221e-06 | BR41: 2.1770221e-06 | BS41: 2.1770221e-06 | BT41: 2.1770221e-06 | BU41: 2.1770221e-06 | BV41: 2.1770221e-06 | BW41: 2.1770221e-06 | BX41: 2.1770221e-06 | BY41: 2.1770221e-06 | BZ41: 2.1770221e-06 | CA41: 2.1770221e-06 | CB41: 2.1770221e-06 | CC41: 2.1770221e-06
A42: Petroleum Gasoline
A43: Year | B43: 2021 | C43: 2022 | D43: 2023 | E43: 2024 | F43: 2025 | G43: 2026 | H43: 2027 | I43: 2028 | J43: 2029 | K43: 2030 | L43: 2031 | M43: 2032 | N43: 2033 | O43: 2034 | P43: 2035 | Q43: 2036 | R43: 2037 | S43: 2038 | T43: 2039 | U43: 2040 | V43: 2041 | W43: 2042 | X43: 2043 | Y43: 2044 | Z43: 2045 | AA43: 2046 | AB43: 2047 | AC43: 2048 | AD43: 2049 | AE43: 2050
A44: Transportation Sector | B44: 1.6334341e-05 | C44: 2.1468663e-05 | D44: 1.8166409e-05 | E44: 1.8189628e-05 | F44: 1.7917979e-05 | G44: 1.7193707e-05 | H44: 1.5712003e-05 | I44: 1.4230299e-05 | J44: 1.4317581e-05 | K44: 1.4353328e-05 | L44: 1.457428e-05 | M44: 1.4494561e-05 | N44: 1.4586278e-05 | O44: 1.5090217e-05 | P44: 1.5407762e-05 | Q44: 1.5631121e-05 | R44: 1.5743546e-05 | S44: 1.5939684e-05 | T44: 1.6165216e-05 | U44: 1.6206163e-05 | V44: 1.6214429e-05 | W44: 1.6126639e-05 | X44: 1.629814e-05 | Y44: 1.6345616e-05 | Z44: 1.6506083e-05 | AA44: 1.6633543e-05 | AB44: 1.6598531e-05 | AC44: 1.6694431e-05 | AD44: 1.6855372e-05 | AE44: 1.7388398e-05 | AF44: 1.7388398e-05 | AG44: 1.7388398e-05 | AH44: 1.7388398e-05 | AI44: 1.7388398e-05 | AJ44: 1.7388398e-05 | AK44: 1.7388398e-05 | AL44: 1.7388398e-05 | AM44: 1.7388398e-05 | AN44: 1.7388398e-05 | AO44: 1.7388398e-05 | AP44: 1.7388398e-05 | AQ44: 1.7388398e-05 | AR44: 1.7388398e-05 | AS44: 1.7388398e-05 | AT44: 1.7388398e-05 | AU44: 1.7388398e-05 | AV44: 1.7388398e-05 | AW44: 1.7388398e-05 | AX44: 1.7388398e-05 | AY44: 1.7388398e-05 | AZ44: 1.7388398e-05 | BA44: 1.7388398e-05 | BB44: 1.7388398e-05 | BC44: 1.7388398e-05 | BD44: 1.7388398e-05 | BE44: 1.7388398e-05 | BF44: 1.7388398e-05 | BG44: 1.7388398e-05 | BH44: 1.7388398e-05 | BI44: 1.7388398e-05 | BJ44: 1.7388398e-05 | BK44: 1.7388398e-05 | BL44: 1.7388398e-05 | BM44: 1.7388398e-05 | BN44: 1.7388398e-05 | BO44: 1.7388398e-05 | BP44: 1.7388398e-05 | BQ44: 1.7388398e-05 | BR44: 1.7388398e-05 | BS44: 1.7388398e-05 | BT44: 1.7388398e-05 | BU44: 1.7388398e-05 | BV44: 1.7388398e-05 | BW44: 1.7388398e-05 | BX44: 1.7388398e-05 | BY44: 1.7388398e-05 | BZ44: 1.7388398e-05 | CA44: 1.7388398e-05 | CB44: 1.7388398e-05 | CC44: 1.7388398e-05
A45: Electricity Sector | B45: 0 | C45: 0 | D45: 0 | E45: 0 | F45: 0 | G45: 0 | H45: 0 | I45: 0 | J45: 0 | K45: 0 | L45: 0 | M45: 0 | N45: 0 | O45: 0 | P45: 0 | Q45: 0 | R45: 0 | S45: 0 | T45: 0 | U45: 0 | V45: 0 | W45: 0 | X45: 0 | Y45: 0 | Z45: 0 | AA45: 0 | AB45: 0 | AC45: 0 | AD45: 0 | AE45: 0 | AF45: 0 | AG45: 0 | AH45: 0 | AI45: 0 | AJ45: 0 | AK45: 0 | AL45: 0 | AM45: 0 | AN45: 0 | AO45: 0 | AP45: 0 | AQ45: 0 | AR45: 0 | AS45: 0 | AT45: 0 | AU45: 0 | AV45: 0 | AW45: 0 | AX45: 0 | AY45: 0 | AZ45: 0 | BA45: 0 | BB45: 0 | BC45: 0 | BD45: 0 | BE45: 0 | BF45: 0 | BG45: 0 | BH45: 0 | BI45: 0 | BJ45: 0 | BK45: 0 | BL45: 0 | BM45: 0 | BN45: 0 | BO45: 0 | BP45: 0 | BQ45: 0 | BR45: 0 | BS45: 0 | BT45: 0 | BU45: 0 | BV45: 0 | BW45: 0 | BX45: 0 | BY45: 0 | BZ45: 0 | CA45: 0 | CB45: 0 | CC45: 0
A46: Residential Buildings Sector | B46: 0 | C46: 0 | D46: 0 | E46: 0 | F46: 0 | G46: 0 | H46: 0 | I46: 0 | J46: 0 | K46: 0 | L46: 0 | M46: 0 | N46: 0 | O46: 0 | P46: 0 | Q46: 0 | R46: 0 | S46: 0 | T46: 0 | U46: 0 | V46: 0 | W46: 0 | X46: 0 | Y46: 0 | Z46: 0 | AA46: 0 | AB46: 0 | AC46: 0 | AD46: 0 | AE46: 0 | AF46: 0 | AG46: 0 | AH46: 0 | AI46: 0 | AJ46: 0 | AK46: 0 | AL46: 0 | AM46: 0 | AN46: 0 | AO46: 0 | AP46: 0 | AQ46: 0 | AR46: 0 | AS46: 0 | AT46: 0 | AU46: 0 | AV46: 0 | AW46: 0 | AX46: 0 | AY46: 0 | AZ46: 0 | BA46: 0 | BB46: 0 | BC46: 0 | BD46: 0 | BE46: 0 | BF46: 0 | BG46: 0 | BH46: 0 | BI46: 0 | BJ46: 0 | BK46: 0 | BL46: 0 | BM46: 0 | BN46: 0 | BO46: 0 | BP46: 0 | BQ46: 0 | BR46: 0 | BS46: 0 | BT46: 0 | BU46: 0 | BV46: 0 | BW46: 0 | BX46: 0 | BY46: 0 | BZ46: 0 | CA46: 0 | CB46: 0 | CC46: 0
A47: Commercial Buildings Sector | B47: 0 | C47: 0 | D47: 0 | E47: 0 | F47: 0 | G47: 0 | H47: 0 | I47: 0 | J47: 0 | K47: 0 | L47: 0 | M47: 0 | N47: 0 | O47: 0 | P47: 0 | Q47: 0 | R47: 0 | S47: 0 | T47: 0 | U47: 0 | V47: 0 | W47: 0 | X47: 0 | Y47: 0 | Z47: 0 | AA47: 0 | AB47: 0 | AC47: 0 | AD47: 0 | AE47: 0 | AF47: 0 | AG47: 0 | AH47: 0 | AI47: 0 | AJ47: 0 | AK47: 0 | AL47: 0 | AM47: 0 | AN47: 0 | AO47: 0 | AP47: 0 | AQ47: 0 | AR47: 0 | AS47: 0 | AT47: 0 | AU47: 0 | AV47: 0 | AW47: 0 | AX47: 0 | AY47: 0 | AZ47: 0 | BA47: 0 | BB47: 0 | BC47: 0 | BD47: 0 | BE47: 0 | BF47: 0 | BG47: 0 | BH47: 0 | BI47: 0 | BJ47: 0 | BK47: 0 | BL47: 0 | BM47: 0 | BN47: 0 | BO47: 0 | BP47: 0 | BQ47: 0 | BR47: 0 | BS47: 0 | BT47: 0 | BU47: 0 | BV47: 0 | BW47: 0 | BX47: 0 | BY47: 0 | BZ47: 0 | CA47: 0 | CB47: 0 | CC47: 0
A48: Industry Sector | B48: 0 | C48: 0 | D48: 0 | E48: 0 | F48: 0 | G48: 0 | H48: 0 | I48: 0 | J48: 0 | K48: 0 | L48: 0 | M48: 0 | N48: 0 | O48: 0 | P48: 0 | Q48: 0 | R48: 0 | S48: 0 | T48: 0 | U48: 0 | V48: 0 | W48: 0 | X48: 0 | Y48: 0 | Z48: 0 | AA48: 0 | AB48: 0 | AC48: 0 | AD48: 0 | AE48: 0 | AF48: 0 | AG48: 0 | AH48: 0 | AI48: 0 | AJ48: 0 | AK48: 0 | AL48: 0 | AM48: 0 | AN48: 0 | AO48: 0 | AP48: 0 | AQ48: 0 | AR48: 0 | AS48: 0 | AT48: 0 | AU48: 0 | AV48: 0 | AW48: 0 | AX48: 0 | AY48: 0 | AZ48: 0 | BA48: 0 | BB48: 0 | BC48: 0 | BD48: 0 | BE48: 0 | BF48: 0 | BG48: 0 | BH48: 0 | BI48: 0 | BJ48: 0 | BK48: 0 | BL48: 0 | BM48: 0 | BN48: 0 | BO48: 0 | BP48: 0 | BQ48: 0 | BR48: 0 | BS48: 0 | BT48: 0 | BU48: 0 | BV48: 0 | BW48: 0 | BX48: 0 | BY48: 0 | BZ48: 0 | CA48: 0 | CB48: 0 | CC48: 0
A49: District Heating Sector | B49: 0 | C49: 0 | D49: 0 | E49: 0 | F49: 0 | G49: 0 | H49: 0 | I49: 0 | J49: 0 | K49: 0 | L49: 0 | M49: 0 | N49: 0 | O49: 0 | P49: 0 | Q49: 0 | R49: 0 | S49: 0 | T49: 0 | U49: 0 | V49: 0 | W49: 0 | X49: 0 | Y49: 0 | Z49: 0 | AA49: 0 | AB49: 0 | AC49: 0 | AD49: 0 | AE49: 0 | AF49: 0 | AG49: 0 | AH49: 0 | AI49: 0 | AJ49: 0 | AK49: 0 | AL49: 0 | AM49: 0 | AN49: 0 | AO49: 0 | AP49: 0 | AQ49: 0 | AR49: 0 | AS49: 0 | AT49: 0 | AU49: 0 | AV49: 0 | AW49: 0 | AX49: 0 | AY49: 0 | AZ49: 0 | BA49: 0 | BB49: 0 | BC49: 0 | BD49: 0 | BE49: 0 | BF49: 0 | BG49: 0 | BH49: 0 | BI49: 0 | BJ49: 0 | BK49: 0 | BL49: 0 | BM49: 0 | BN49: 0 | BO49: 0 | BP49: 0 | BQ49: 0 | BR49: 0 | BS49: 0 | BT49: 0 | BU49: 0 | BV49: 0 | BW49: 0 | BX49: 0 | BY49: 0 | BZ49: 0 | CA49: 0 | CB49: 0 | CC49: 0
A50: LULUCF Sector | B50: 0 | C50: 0 | D50: 0 | E50: 0 | F50: 0 | G50: 0 | H50: 0 | I50: 0 | J50: 0 | K50: 0 | L50: 0 | M50: 0 | N50: 0 | O50: 0 | P50: 0 | Q50: 0 | R50: 0 | S50: 0 | T50: 0 | U50: 0 | V50: 0 | W50: 0 | X50: 0 | Y50: 0 | Z50: 0 | AA50: 0 | AB50: 0 | AC50: 0 | AD50: 0 | AE50: 0 | AF50: 0 | AG50: 0 | AH50: 0 | AI50: 0 | AJ50: 0 | AK50: 0 | AL50: 0 | AM50: 0 | AN50: 0 | AO50: 0 | AP50: 0 | AQ50: 0 | AR50: 0 | AS50: 0 | AT50: 0 | AU50: 0 | AV50: 0 | AW50: 0 | AX50: 0 | AY50: 0 | AZ50: 0 | BA50: 0 | BB50: 0 | BC50: 0 | BD50: 0 | BE50: 0 | BF50: 0 | BG50: 0 | BH50: 0 | BI50: 0 | BJ50: 0 | BK50: 0 | BL50: 0 | BM50: 0 | BN50: 0 | BO50: 0 | BP50: 0 | BQ50: 0 | BR50: 0 | BS50: 0 | BT50: 0 | BU50: 0 | BV50: 0 | BW50: 0 | BX50: 0 | BY50: 0 | BZ50: 0 | CA50: 0 | CB50: 0 | CC50: 0
A51: Geoengineering Sector | B51: 0 | C51: 0 | D51: 0 | E51: 0 | F51: 0 | G51: 0 | H51: 0 | I51: 0 | J51: 0 | K51: 0 | L51: 0 | M51: 0 | N51: 0 | O51: 0 | P51: 0 | Q51: 0 | R51: 0 | S51: 0 | T51: 0 | U51: 0 | V51: 0 | W51: 0 | X51: 0 | Y51: 0 | Z51: 0 | AA51: 0 | AB51: 0 | AC51: 0 | AD51: 0 | AE51: 0 | AF51: 0 | AG51: 0 | AH51: 0 | AI51: 0 | AJ51: 0 | AK51: 0 | AL51: 0 | AM51: 0 | AN51: 0 | AO51: 0 | AP51: 0 | AQ51: 0 | AR51: 0 | AS51: 0 | AT51: 0 | AU51: 0 | AV51: 0 | AW51: 0 | AX51: 0 | AY51: 0 | AZ51: 0 | BA51: 0 | BB51: 0 | BC51: 0 | BD51: 0 | BE51: 0 | BF51: 0 | BG51: 0 | BH51: 0 | BI51: 0 | BJ51: 0 | BK51: 0 | BL51: 0 | BM51: 0 | BN51: 0 | BO51: 0 | BP51: 0 | BQ51: 0 | BR51: 0 | BS51: 0 | BT51: 0 | BU51: 0 | BV51: 0 | BW51: 0 | BX51: 0 | BY51: 0 | BZ51: 0 | CA51: 0 | CB51: 0 | CC51: 0
A52: Petroleum Diesel
A53: Year | B53: 2021 | C53: 2022 | D53: 2023 | E53: 2024 | F53: 2025 | G53: 2026 | H53: 2027 | I53: 2028 | J53: 2029 | K53: 2030 | L53: 2031 | M53: 2032 | N53: 2033 | O53: 2034 | P53: 2035 | Q53: 2036 | R53: 2037 | S53: 2038 | T53: 2039 | U53: 2040 | V53: 2041 | W53: 2042 | X53: 2043 | Y53: 2044 | Z53: 2045 | AA53: 2046 | AB53: 2047 | AC53: 2048 | AD53: 2049 | AE53: 2050
A54: Transportation Sector | B54: 1.566221e-05 | C54: 2.3950846e-05 | D54: 1.8669079e-05 | E54: 1.5773075e-05 | F54: 1.5826995e-05 | G54: 1.4679646e-05 | H54: 1.4833827e-05 | I54: 1.4988008e-05 | J54: 1.533623e-05 | K54: 1.5587861e-05 | L54: 1.5851265e-05 | M54: 1.5666746e-05 | N54: 1.5805941e-05 | O54: 1.6141378e-05 | P54: 1.6543254e-05 | Q54: 1.6587629e-05 | R54: 1.6790455e-05 | S54: 1.6911281e-05 | T54: 1.706662e-05 | U54: 1.7216672e-05 | V54: 1.7283041e-05 | W54: 1.7231608e-05 | X54: 1.7410239e-05 | Y54: 1.7527719e-05 | Z54: 1.7697361e-05 | AA54: 1.8075202e-05 | AB54: 1.8077015e-05 | AC54: 1.8167462e-05 | AD54: 1.8375618e-05 | AE54: 1.8606078e-05 | AF54: 1.8606078e-05 | AG54: 1.8606078e-05 | AH54: 1.8606078e-05 | AI54: 1.8606078e-05 | AJ54: 1.8606078e-05 | AK54: 1.8606078e-05 | AL54: 1.8606078e-05 | AM54: 1.8606078e-05 | AN54: 1.8606078e-05 | AO54: 1.8606078e-05 | AP54: 1.8606078e-05 | AQ54: 1.8606078e-05 | AR54: 1.8606078e-05 | AS54: 1.8606078e-05 | AT54: 1.8606078e-05 | AU54: 1.8606078e-05 | AV54: 1.8606078e-05 | AW54: 1.8606078e-05 | AX54: 1.8606078e-05 | AY54: 1.8606078e-05 | AZ54: 1.8606078e-05 | BA54: 1.8606078e-05 | BB54: 1.8606078e-05 | BC54: 1.8606078e-05 | BD54: 1.8606078e-05 | BE54: 1.8606078e-05 | BF54: 1.8606078e-05 | BG54: 1.8606078e-05 | BH54: 1.8606078e-05 | BI54: 1.8606078e-05 | BJ54: 1.8606078e-05 | BK54: 1.8606078e-05 | BL54: 1.8606078e-05 | BM54: 1.8606078e-05 | BN54: 1.8606078e-05 | BO54: 1.8606078e-05 | BP54: 1.8606078e-05 | BQ54: 1.8606078e-05 | BR54: 1.8606078e-05 | BS54: 1.8606078e-05 | BT54: 1.8606078e-05 | BU54: 1.8606078e-05 | BV54: 1.8606078e-05 | BW54: 1.8606078e-05 | BX54: 1.8606078e-05 | BY54: 1.8606078e-05 | BZ54: 1.8606078e-05 | CA54: 1.8606078e-05 | CB54: 1.8606078e-05 | CC54: 1.8606078e-05
A55: Electricity Sector | B55: 1.4875678e-05 | C55: 2.2748071e-05 | D55: 1.8698125e-05 | E55: 1.5687286e-05 | F55: 1.4565285e-05 | G55: 1.3830876e-05 | H55: 1.3546132e-05 | I55: 1.3419286e-05 | J55: 1.3469744e-05 | K55: 1.3466771e-05 | L55: 1.363524e-05 | M55: 1.3976404e-05 | N55: 1.4105303e-05 | O55: 1.4408978e-05 | P55: 1.4503749e-05 | Q55: 1.4449691e-05 | R55: 1.4635375e-05 | S55: 1.4746672e-05 | T55: 1.4874438e-05 | U55: 1.5036074e-05 | V55: 1.5068043e-05 | W55: 1.5052366e-05 | X55: 1.5206804e-05 | Y55: 1.5280465e-05 | Z55: 1.5498403e-05 | AA55: 1.5858768e-05 | AB55: 1.5824443e-05 | AC55: 1.5912211e-05 | AD55: 1.6052666e-05 | AE55: 1.6255147e-05 | AF55: 1.6255147e-05 | AG55: 1.6255147e-05 | AH55: 1.6255147e-05 | AI55: 1.6255147e-05 | AJ55: 1.6255147e-05 | AK55: 1.6255147e-05 | AL55: 1.6255147e-05 | AM55: 1.6255147e-05 | AN55: 1.6255147e-05 | AO55: 1.6255147e-05 | AP55: 1.6255147e-05 | AQ55: 1.6255147e-05 | AR55: 1.6255147e-05 | AS55: 1.6255147e-05 | AT55: 1.6255147e-05 | AU55: 1.6255147e-05 | AV55: 1.6255147e-05 | AW55: 1.6255147e-05 | AX55: 1.6255147e-05 | AY55: 1.6255147e-05 | AZ55: 1.6255147e-05 | BA55: 1.6255147e-05 | BB55: 1.6255147e-05 | BC55: 1.6255147e-05 | BD55: 1.6255147e-05 | BE55: 1.6255147e-05 | BF55: 1.6255147e-05 | BG55: 1.6255147e-05 | BH55: 1.6255147e-05 | BI55: 1.6255147e-05 | BJ55: 1.6255147e-05 | BK55: 1.6255147e-05 | BL55: 1.6255147e-05 | BM55: 1.6255147e-05 | BN55: 1.6255147e-05 | BO55: 1.6255147e-05 | BP55: 1.6255147e-05 | BQ55: 1.6255147e-05 | BR55: 1.6255147e-05 | BS55: 1.6255147e-05 | BT55: 1.6255147e-05 | BU55: 1.6255147e-05 | BV55: 1.6255147e-05 | BW55: 1.6255147e-05 | BX55: 1.6255147e-05 | BY55: 1.6255147e-05 | BZ55: 1.6255147e-05 | CA55: 1.6255147e-05 | CB55: 1.6255147e-05 | CC55: 1.6255147e-05
A56: Residential Buildings Sector | B56: 1.4868543e-05 | C56: 2.273716e-05 | D56: 1.8651004e-05 | E56: 1.5700335e-05 | F56: 1.4554993e-05 | G56: 1.4515316e-05 | H56: 1.4918282e-05 | I56: 1.5530822e-05 | J56: 1.6244892e-05 | K56: 1.6913379e-05 | L56: 1.7174979e-05 | M56: 1.7033848e-05 | N56: 1.7173341e-05 | O56: 1.7503156e-05 | P56: 1.7657067e-05 | Q56: 1.7641795e-05 | R56: 1.7839297e-05 | S56: 1.7976658e-05 | T56: 1.8141981e-05 | U56: 1.8288439e-05 | V56: 1.8361559e-05 | W56: 1.8333501e-05 | X56: 1.8500086e-05 | Y56: 1.8607858e-05 | Z56: 1.8818158e-05 | AA56: 1.9117883e-05 | AB56: 1.9132115e-05 | AC56: 1.9222512e-05 | AD56: 1.9377499e-05 | AE56: 1.9599805e-05 | AF56: 1.9599805e-05 | AG56: 1.9599805e-05 | AH56: 1.9599805e-05 | AI56: 1.9599805e-05 | AJ56: 1.9599805e-05 | AK56: 1.9599805e-05 | AL56: 1.9599805e-05 | AM56: 1.9599805e-05 | AN56: 1.9599805e-05 | AO56: 1.9599805e-05 | AP56: 1.9599805e-05 | AQ56: 1.9599805e-05 | AR56: 1.9599805e-05 | AS56: 1.9599805e-05 | AT56: 1.9599805e-05 | AU56: 1.9599805e-05 | AV56: 1.9599805e-05 | AW56: 1.9599805e-05 | AX56: 1.9599805e-05 | AY56: 1.9599805e-05 | AZ56: 1.9599805e-05 | BA56: 1.9599805e-05 | BB56: 1.9599805e-05 | BC56: 1.9599805e-05 | BD56: 1.9599805e-05 | BE56: 1.9599805e-05 | BF56: 1.9599805e-05 | BG56: 1.9599805e-05 | BH56: 1.9599805e-05 | BI56: 1.9599805e-05 | BJ56: 1.9599805e-05 | BK56: 1.9599805e-05 | BL56: 1.9599805e-05 | BM56: 1.9599805e-05 | BN56: 1.9599805e-05 | BO56: 1.9599805e-05 | BP56: 1.9599805e-05 | BQ56: 1.9599805e-05 | BR56: 1.9599805e-05 | BS56: 1.9599805e-05 | BT56: 1.9599805e-05 | BU56: 1.9599805e-05 | BV56: 1.9599805e-05 | BW56: 1.9599805e-05 | BX56: 1.9599805e-05 | BY56: 1.9599805e-05 | BZ56: 1.9599805e-05 | CA56: 1.9599805e-05 | CB56: 1.9599805e-05 | CC56: 1.9599805e-05
A57: Commercial Buildings Sector | B57: 1.4877487e-05 | C57: 2.2750837e-05 | D57: 1.873933e-05 | E57: 1.5730076e-05 | F57: 1.4608064e-05 | G57: 1.388497e-05 | H57: 1.3594642e-05 | I57: 1.3503895e-05 | J57: 1.3505739e-05 | K57: 1.3457338e-05 | L57: 1.3702312e-05 | M57: 1.3558335e-05 | N57: 1.3680311e-05 | O57: 1.3986113e-05 | P57: 1.4263723e-05 | Q57: 1.4266388e-05 | R57: 1.4450289e-05 | S57: 1.4571117e-05 | T57: 1.4713864e-05 | U57: 1.4850433e-05 | V57: 1.4911283e-05 | W57: 1.4880948e-05 | X57: 1.5041256e-05 | Y57: 1.5149396e-05 | Z57: 1.5346136e-05 | AA57: 1.5626748e-05 | AB57: 1.5629941e-05 | AC57: 1.571193e-05 | AD57: 1.5882644e-05 | AE57: 1.609025e-05 | AF57: 1.609025e-05 | AG57: 1.609025e-05 | AH57: 1.609025e-05 | AI57: 1.609025e-05 | AJ57: 1.609025e-05 | AK57: 1.609025e-05 | AL57: 1.609025e-05 | AM57: 1.609025e-05 | AN57: 1.609025e-05 | AO57: 1.609025e-05 | AP57: 1.609025e-05 | AQ57: 1.609025e-05 | AR57: 1.609025e-05 | AS57: 1.609025e-05 | AT57: 1.609025e-05 | AU57: 1.609025e-05 | AV57: 1.609025e-05 | AW57: 1.609025e-05 | AX57: 1.609025e-05 | AY57: 1.609025e-05 | AZ57: 1.609025e-05 | BA57: 1.609025e-05 | BB57: 1.609025e-05 | BC57: 1.609025e-05 | BD57: 1.609025e-05 | BE57: 1.609025e-05 | BF57: 1.609025e-05 | BG57: 1.609025e-05 | BH57: 1.609025e-05 | BI57: 1.609025e-05 | BJ57: 1.609025e-05 | BK57: 1.609025e-05 | BL57: 1.609025e-05 | BM57: 1.609025e-05 | BN57: 1.609025e-05 | BO57: 1.609025e-05 | BP57: 1.609025e-05 | BQ57: 1.609025e-05 | BR57: 1.609025e-05 | BS57: 1.609025e-05 | BT57: 1.609025e-05 | BU57: 1.609025e-05 | BV57: 1.609025e-05 | BW57: 1.609025e-05 | BX57: 1.609025e-05 | BY57: 1.609025e-05 | BZ57: 1.609025e-05 | CA57: 1.609025e-05 | CB57: 1.609025e-05 | CC57: 1.609025e-05
A58: Industry Sector | B58: 1.4845257e-05 | C58: 2.2701551e-05 | D58: 1.8639038e-05 | E58: 1.5660341e-05 | F58: 1.4544991e-05 | G58: 1.380203e-05 | H58: 1.3493824e-05 | I58: 1.3386155e-05 | J58: 1.3367414e-05 | K58: 1.3296103e-05 | L58: 1.3543005e-05 | M58: 1.3388443e-05 | N58: 1.3517676e-05 | O58: 1.382576e-05 | P58: 1.394264e-05 | Q58: 1.3922394e-05 | R58: 1.4111088e-05 | S58: 1.4230056e-05 | T58: 1.436865e-05 | U58: 1.4505657e-05 | V58: 1.4568833e-05 | W58: 1.4541835e-05 | X58: 1.4706445e-05 | Y58: 1.482522e-05 | Z58: 1.5022896e-05 | AA58: 1.5301327e-05 | AB58: 1.5303948e-05 | AC58: 1.5388639e-05 | AD58: 1.5534916e-05 | AE58: 1.5747601e-05 | AF58: 1.5747601e-05 | AG58: 1.5747601e-05 | AH58: 1.5747601e-05 | AI58: 1.5747601e-05 | AJ58: 1.5747601e-05 | AK58: 1.5747601e-05 | AL58: 1.5747601e-05 | AM58: 1.5747601e-05 | AN58: 1.5747601e-05 | AO58: 1.5747601e-05 | AP58: 1.5747601e-05 | AQ58: 1.5747601e-05 | AR58: 1.5747601e-05 | AS58: 1.5747601e-05 | AT58: 1.5747601e-05 | AU58: 1.5747601e-05 | AV58: 1.5747601e-05 | AW58: 1.5747601e-05 | AX58: 1.5747601e-05 | AY58: 1.5747601e-05 | AZ58: 1.5747601e-05 | BA58: 1.5747601e-05 | BB58: 1.5747601e-05 | BC58: 1.5747601e-05 | BD58: 1.5747601e-05 | BE58: 1.5747601e-05 | BF58: 1.5747601e-05 | BG58: 1.5747601e-05 | BH58: 1.5747601e-05 | BI58: 1.5747601e-05 | BJ58: 1.5747601e-05 | BK58: 1.5747601e-05 | BL58: 1.5747601e-05 | BM58: 1.5747601e-05 | BN58: 1.5747601e-05 | BO58: 1.5747601e-05 | BP58: 1.5747601e-05 | BQ58: 1.5747601e-05 | BR58: 1.5747601e-05 | BS58: 1.5747601e-05 | BT58: 1.5747601e-05 | BU58: 1.5747601e-05 | BV58: 1.5747601e-05 | BW58: 1.5747601e-05 | BX58: 1.5747601e-05 | BY58: 1.5747601e-05 | BZ58: 1.5747601e-05 | CA58: 1.5747601e-05 | CB58: 1.5747601e-05 | CC58: 1.5747601e-05
A59: District Heating Sector | B59: 1.4875678e-05 | C59: 2.2748071e-05 | D59: 1.8698125e-05 | E59: 1.6572253e-05 | F59: 1.5784012e-05 | G59: 1.499577e-05 | H59: 1.4207528e-05 | I59: 1.3419286e-05 | J59: 1.3469744e-05 | K59: 1.3466771e-05 | L59: 1.363524e-05 | M59: 1.3976404e-05 | N59: 1.4105303e-05 | O59: 1.4408978e-05 | P59: 1.4503749e-05 | Q59: 1.4449691e-05 | R59: 1.4635375e-05 | S59: 1.4746672e-05 | T59: 1.4874438e-05 | U59: 1.5036074e-05 | V59: 1.5068043e-05 | W59: 1.5052366e-05 | X59: 1.5206804e-05 | Y59: 1.5280465e-05 | Z59: 1.5498403e-05 | AA59: 1.5858768e-05 | AB59: 1.5824443e-05 | AC59: 1.5912211e-05 | AD59: 1.6052666e-05 | AE59: 1.6255147e-05 | AF59: 1.6255147e-05 | AG59: 1.6255147e-05 | AH59: 1.6255147e-05 | AI59: 1.6255147e-05 | AJ59: 1.6255147e-05 | AK59: 1.6255147e-05 | AL59: 1.6255147e-05 | AM59: 1.6255147e-05 | AN59: 1.6255147e-05 | AO59: 1.6255147e-05 | AP59: 1.6255147e-05 | AQ59: 1.6255147e-05 | AR59: 1.6255147e-05 | AS59: 1.6255147e-05 | AT59: 1.6255147e-05 | AU59: 1.6255147e-05 | AV59: 1.6255147e-05 | AW59: 1.6255147e-05 | AX59: 1.6255147e-05 | AY59: 1.6255147e-05 | AZ59: 1.6255147e-05 | BA59: 1.6255147e-05 | BB59: 1.6255147e-05 | BC59: 1.6255147e-05 | BD59: 1.6255147e-05 | BE59: 1.6255147e-05 | BF59: 1.6255147e-05 | BG59: 1.6255147e-05 | BH59: 1.6255147e-05 | BI59: 1.6255147e-05 | BJ59: 1.6255147e-05 | BK59: 1.6255147e-05 | BL59: 1.6255147e-05 | BM59: 1.6255147e-05 | BN59: 1.6255147e-05 | BO59: 1.6255147e-05 | BP59: 1.6255147e-05 | BQ59: 1.6255147e-05 | BR59: 1.6255147e-05 | BS59: 1.6255147e-05 | BT59: 1.6255147e-05 | BU59: 1.6255147e-05 | BV59: 1.6255147e-05 | BW59: 1.6255147e-05 | BX59: 1.6255147e-05 | BY59: 1.6255147e-05 | BZ59: 1.6255147e-05 | CA59: 1.6255147e-05 | CB59: 1.6255147e-05 | CC59: 1.6255147e-05
A60: LULUCF Sector | B60: 0 | C60: 0 | D60: 0 | E60: 0 | F60: 0 | G60: 0 | H60: 0 | I60: 0 | J60: 0 | K60: 0 | L60: 0 | M60: 0 | N60: 0 | O60: 0 | P60: 0 | Q60: 0 | R60: 0 | S60: 0 | T60: 0 | U60: 0 | V60: 0 | W60: 0 | X60: 0 | Y60: 0 | Z60: 0 | AA60: 0 | AB60: 0 | AC60: 0 | AD60: 0 | AE60: 0 | AF60: 0 | AG60: 0 | AH60: 0 | AI60: 0 | AJ60: 0 | AK60: 0 | AL60: 0 | AM60: 0 | AN60: 0 | AO60: 0 | AP60: 0 | AQ60: 0 | AR60: 0 | AS60: 0 | AT60: 0 | AU60: 0 | AV60: 0 | AW60: 0 | AX60: 0 | AY60: 0 | AZ60: 0 | BA60: 0 | BB60: 0 | BC60: 0 | BD60: 0 | BE60: 0 | BF60: 0 | BG60: 0 | BH60: 0 | BI60: 0 | BJ60: 0 | BK60: 0 | BL60: 0 | BM60: 0 | BN60: 0 | BO60: 0 | BP60: 0 | BQ60: 0 | BR60: 0 | BS60: 0 | BT60: 0 | BU60: 0 | BV60: 0 | BW60: 0 | BX60: 0 | BY60: 0 | BZ60: 0 | CA60: 0 | CB60: 0 | CC60: 0
A61: Geoengineering Sector | B61: 1.4845257e-05 | C61: 2.2701551e-05 | D61: 1.8639038e-05 | E61: 1.5660341e-05 | F61: 1.4544991e-05 | G61: 1.380203e-05 | H61: 1.3493824e-05 | I61: 1.3386155e-05 | J61: 1.3367414e-05 | K61: 1.3296103e-05 | L61: 1.3543005e-05 | M61: 1.3388443e-05 | N61: 1.3517676e-05 | O61: 1.382576e-05 | P61: 1.394264e-05 | Q61: 1.3922394e-05 | R61: 1.4111088e-05 | S61: 1.4230056e-05 | T61: 1.436865e-05 | U61: 1.4505657e-05 | V61: 1.4568833e-05 | W61: 1.4541835e-05 | X61: 1.4706445e-05 | Y61: 1.482522e-05 | Z61: 1.5022896e-05 | AA61: 1.5301327e-05 | AB61: 1.5303948e-05 | AC61: 1.5388639e-05 | AD61: 1.5534916e-05 | AE61: 1.5747601e-05 | AF61: 1.5747601e-05 | AG61: 1.5747601e-05 | AH61: 1.5747601e-05 | AI61: 1.5747601e-05 | AJ61: 1.5747601e-05 | AK61: 1.5747601e-05 | AL61: 1.5747601e-05 | AM61: 1.5747601e-05 | AN61: 1.5747601e-05 | AO61: 1.5747601e-05 | AP61: 1.5747601e-05 | AQ61: 1.5747601e-05 | AR61: 1.5747601e-05 | AS61: 1.5747601e-05 | AT61: 1.5747601e-05 | AU61: 1.5747601e-05 | AV61: 1.5747601e-05 | AW61: 1.5747601e-05 | AX61: 1.5747601e-05 | AY61: 1.5747601e-05 | AZ61: 1.5747601e-05 | BA61: 1.5747601e-05 | BB61: 1.5747601e-05 | BC61: 1.5747601e-05 | BD61: 1.5747601e-05 | BE61: 1.5747601e-05 | BF61: 1.5747601e-05 | BG61: 1.5747601e-05 | BH61: 1.5747601e-05 | BI61: 1.5747601e-05 | BJ61: 1.5747601e-05 | BK61: 1.5747601e-05 | BL61: 1.5747601e-05 | BM61: 1.5747601e-05 | BN61: 1.5747601e-05 | BO61: 1.5747601e-05 | BP61: 1.5747601e-05 | BQ61: 1.5747601e-05 | BR61: 1.5747601e-05 | BS61: 1.5747601e-05 | BT61: 1.5747601e-05 | BU61: 1.5747601e-05 | BV61: 1.5747601e-05 | BW61: 1.5747601e-05 | BX61: 1.5747601e-05 | BY61: 1.5747601e-05 | BZ61: 1.5747601e-05 | CA61: 1.5747601e-05 | CB61: 1.5747601e-05 | CC61: 1.5747601e-05
A62: Biofuel Gasoline
A63: Year | B63: 2021 | C63: 2022 | D63: 2023 | E63: 2024 | F63: 2025 | G63: 2026 | H63: 2027 | I63: 2028 | J63: 2029 | K63: 2030 | L63: 2031 | M63: 2032 | N63: 2033 | O63: 2034 | P63: 2035 | Q63: 2036 | R63: 2037 | S63: 2038 | T63: 2039 | U63: 2040 | V63: 2041 | W63: 2042 | X63: 2043 | Y63: 2044 | Z63: 2045 | AA63: 2046 | AB63: 2047 | AC63: 2048 | AD63: 2049 | AE63: 2050
A64: Transportation Sector | B64: 1.7185281e-05 | C64: 2.5512359e-05 | D64: 2.2003046e-05 | E64: 1.7138133e-05 | F64: 1.6970862e-05 | G64: 1.7251742e-05 | H64: 1.7151595e-05 | I64: 1.6884259e-05 | J64: 1.684295e-05 | K64: 1.6833793e-05 | L64: 1.7097343e-05 | M64: 1.7036347e-05 | N64: 1.7107416e-05 | O64: 1.7713868e-05 | P64: 1.79625e-05 | Q64: 1.8196313e-05 | R64: 1.8252278e-05 | S64: 1.8568123e-05 | T64: 1.8724999e-05 | U64: 1.8724993e-05 | V64: 1.8706347e-05 | W64: 1.8597772e-05 | X64: 1.8792265e-05 | Y64: 1.8840507e-05 | Z64: 1.9016108e-05 | AA64: 1.9144365e-05 | AB64: 1.9104894e-05 | AC64: 1.9215775e-05 | AD64: 1.9373373e-05 | AE64: 2.0036011e-05 | AF64: 2.0036011e-05 | AG64: 2.0036011e-05 | AH64: 2.0036011e-05 | AI64: 2.0036011e-05 | AJ64: 2.0036011e-05 | AK64: 2.0036011e-05 | AL64: 2.0036011e-05 | AM64: 2.0036011e-05 | AN64: 2.0036011e-05 | AO64: 2.0036011e-05 | AP64: 2.0036011e-05 | AQ64: 2.0036011e-05 | AR64: 2.0036011e-05 | AS64: 2.0036011e-05 | AT64: 2.0036011e-05 | AU64: 2.0036011e-05 | AV64: 2.0036011e-05 | AW64: 2.0036011e-05 | AX64: 2.0036011e-05 | AY64: 2.0036011e-05 | AZ64: 2.0036011e-05 | BA64: 2.0036011e-05 | BB64: 2.0036011e-05 | BC64: 2.0036011e-05 | BD64: 2.0036011e-05 | BE64: 2.0036011e-05 | BF64: 2.0036011e-05 | BG64: 2.0036011e-05 | BH64: 2.0036011e-05 | BI64: 2.0036011e-05 | BJ64: 2.0036011e-05 | BK64: 2.0036011e-05 | BL64: 2.0036011e-05 | BM64: 2.0036011e-05 | BN64: 2.0036011e-05 | BO64: 2.0036011e-05 | BP64: 2.0036011e-05 | BQ64: 2.0036011e-05 | BR64: 2.0036011e-05 | BS64: 2.0036011e-05 | BT64: 2.0036011e-05 | BU64: 2.0036011e-05 | BV64: 2.0036011e-05 | BW64: 2.0036011e-05 | BX64: 2.0036011e-05 | BY64: 2.0036011e-05 | BZ64: 2.0036011e-05 | CA64: 2.0036011e-05 | CB64: 2.0036011e-05 | CC64: 2.0036011e-05
A65: Electricity Sector | B65: 0 | C65: 0 | D65: 0 | E65: 0 | F65: 0 | G65: 0 | H65: 0 | I65: 0 | J65: 0 | K65: 0 | L65: 0 | M65: 0 | N65: 0 | O65: 0 | P65: 0 | Q65: 0 | R65: 0 | S65: 0 | T65: 0 | U65: 0 | V65: 0 | W65: 0 | X65: 0 | Y65: 0 | Z65: 0 | AA65: 0 | AB65: 0 | AC65: 0 | AD65: 0 | AE65: 0 | AF65: 0 | AG65: 0 | AH65: 0 | AI65: 0 | AJ65: 0 | AK65: 0 | AL65: 0 | AM65: 0 | AN65: 0 | AO65: 0 | AP65: 0 | AQ65: 0 | AR65: 0 | AS65: 0 | AT65: 0 | AU65: 0 | AV65: 0 | AW65: 0 | AX65: 0 | AY65: 0 | AZ65: 0 | BA65: 0 | BB65: 0 | BC65: 0 | BD65: 0 | BE65: 0 | BF65: 0 | BG65: 0 | BH65: 0 | BI65: 0 | BJ65: 0 | BK65: 0 | BL65: 0 | BM65: 0 | BN65: 0 | BO65: 0 | BP65: 0 | BQ65: 0 | BR65: 0 | BS65: 0 | BT65: 0 | BU65: 0 | BV65: 0 | BW65: 0 | BX65: 0 | BY65: 0 | BZ65: 0 | CA65: 0 | CB65: 0 | CC65: 0
A66: Residential Buildings Sector | B66: 0 | C66: 0 | D66: 0 | E66: 0 | F66: 0 | G66: 0 | H66: 0 | I66: 0 | J66: 0 | K66: 0 | L66: 0 | M66: 0 | N66: 0 | O66: 0 | P66: 0 | Q66: 0 | R66: 0 | S66: 0 | T66: 0 | U66: 0 | V66: 0 | W66: 0 | X66: 0 | Y66: 0 | Z66: 0 | AA66: 0 | AB66: 0 | AC66: 0 | AD66: 0 | AE66: 0 | AF66: 0 | AG66: 0 | AH66: 0 | AI66: 0 | AJ66: 0 | AK66: 0 | AL66: 0 | AM66: 0 | AN66: 0 | AO66: 0 | AP66: 0 | AQ66: 0 | AR66: 0 | AS66: 0 | AT66: 0 | AU66: 0 | AV66: 0 | AW66: 0 | AX66: 0 | AY66: 0 | AZ66: 0 | BA66: 0 | BB66: 0 | BC66: 0 | BD66: 0 | BE66: 0 | BF66: 0 | BG66: 0 | BH66: 0 | BI66: 0 | BJ66: 0 | BK66: 0 | BL66: 0 | BM66: 0 | BN66: 0 | BO66: 0 | BP66: 0 | BQ66: 0 | BR66: 0 | BS66: 0 | BT66: 0 | BU66: 0 | BV66: 0 | BW66: 0 | BX66: 0 | BY66: 0 | BZ66: 0 | CA66: 0 | CB66: 0 | CC66: 0
