Workbook

Sheet About
A1: BCtCR BAU Clinker to Cement Ratio
A3: Sources: | B3: U.S. clinker and cement production, 2021-2025 | D3: India ratio, disagreeing estimate
B4: U.S. Geological Survey | D4: Global Cement and Concrete Association (GCCA), with TERI
B5: Mineral Commodity Summaries 2026: Cement | D5: Indian roadmap aims for net zero by 2070
B6: 2026
B7: https://pubs.usgs.gov/periodicals/mcs2026/mcs2026-cement.pdf | D7: https://www.cemnet.com/News/story/178891/indian-roadmap-aims-for-net-zero-by-2070.html
B8: Cement production (84.0 million metric tons in 2025, an estimate), clinker production (69.0) and clinker imports (0.66), pasted as published on the 'USGS MCS 2026 Cement' tab. Blend ratio = (clinker production + clinker imports) / cement production, which gives 0.8921, 0.8828, 0.8663, 0.8551, and 0.8293 for 2021-2025. The report also says blended cement was 63% of 2025 shipments and 95% of that was Type IL (portland-limestone) cement; that sentence is in the report text, not on the pasted tab. | D8: The GCCA India / TERI roadmap puts the ratio at 0.75 in 2020 (SNIPPET). We did not open the CemNet page itself; the figure comes from a search summary.
B10: Cross-check on the U.S. ratio | D10: EU-27 ratio
B11: World Resources Institute | D11: CEMBUREAU (now Cement Europe)
B12: How Blended Cements Can Reduce Emissions and Improve Resilience | D12: Net Zero Roadmap: From Ambition to Deployment
B13: 2023
B14: https://www.wri.org/insights/lower-carbon-blended-cement | D14: https://www.cementeurope.eu/media/g44cvp5a/cembureau-net-zero-roadmap.pdf
B15: Cites a U.S. ratio of about 0.88, consistent with our 2021-2022 values. We use it only as a check, not as an input. | D15: The roadmap text gives a clinker-to-cement ratio of 77% for Europe in 2021 (DIRECT). The scope is Europe, not strictly EU-27. Cement Europe also says the ratio fell by about 2% over the last three years.
B17: U.S. cement product mix, 2019-2025 | D17: Brazil ratio
B18: U.S. Geological Survey | D18: Sindicato Nacional da Industria do Cimento (SNIC)
B19: Mineral Industry Surveys: Cement (monthly; December issues 2019-2025 and May 2026) | D19: SNIC Annual Report 2023
B20: 2026 | D20: 2024
B21: https://www.usgs.gov/centers/national-minerals-information-center/cement-statistics-and-information | D21: http://snic.org.br/assets/pdf/relatorio_anual/1732731328.pdf
B22: Shipments of portland cement (ASTM C150) and blended cement (ASTM C595), including imports, on the 'US Product Mix' tab. Blended cement rose from 2.4% of shipments in 2019 and 5.6% in 2021 to 24.2% (2022), 49.8% (2023), 59.5% (2024) and 64.6% (2025); about 96% of blended cement is Type IL. January-May 2026 was 63.1%, only 0.9 points above the same months of 2025, so the switch to Type IL has largely run its course. All 50 states had accepted Type IL by April 2024 (USGS Mineral Commodity Summaries 2025). | D22: A GCCA figure printed in the report: 71% in 2022, down from 84% in 1990. A search summary elsewhere gave 2024 clinker production of 77.5 million tons, which is more than Brazil's cement output, so we treated it as unreliable and did not use it.
B24: Clinker content of each cement type | D24: Mexico ratio
B25: Portland Cement Association (PCA) | D25: FICEM / CANACEM (Mexican cement chamber)
B26: Industry-average environmental product declarations for portland cement and portland-limestone cement (2019 data, revised July 2026) | D26: Hoja de Ruta: Industria del Cemento Mexico
B27: 2026
B28: https://www.cement.org/wp-content/uploads/2026/07/PCA_EPD_PLC_Athena_Final_revised_Jul2026.pdf | D28: https://canacem.org.mx/site/wp-content/uploads/2023/03/Hoja-de-Ruta-Mexico-FICEM.pdf
B29: Type IL averages 82.7% clinker and 10.8% limestone; Type I/II averages 91.4% clinker. PCA's 2024 limestone cement report confirms the 10.8% average and the 15% limestone cap. | D29: A clinker factor of 75% for 2016, from GNR data verified by PwC (DIRECT). It is an old anchor year; a newer CANACEM or GNR figure would be better.
B31: Official projections for comparison | D31: Canada ratio
B32: U.S. Energy Information Administration | D32: Cement Association of Canada
B33: Industrial Demand Module of NEMS, AEO2025 documentation | D33: Concrete Zero: Action Plan
B34: 2025 | D34: 2023
B35: https://www.eia.gov/outlooks/aeo/nems/documentation/industrial/pdf/IDM_AEO2025.pdf | D35: https://cement.ca/wp-content/uploads/ConcreteZero-Report-FINAL-reduced.pdf
B36: AEO2025 holds cement additives constant (an implied clinker ratio of about 0.90), already above the recent data. DOE's Liftoff report (2023, updated 2025) uses a 0.89 baseline and treats 0.65 by the early 2030s as an aggressive scenario; PCA's roadmap aims for 0.85 by 2030, 0.80 by 2040 and 0.75 by 2050 as industry goals, not business as usual. | D36: A 2020 baseline of 89% (DIRECT). Clinker of 11.4 million tons over cement of 12.7 million tons gives 0.90, a little higher. These are production figures for the association's member companies, and Canada is a net exporter of cement.
B38: India ratio, and Indonesia cross-check | D38: Indonesia ratio
B39: American Council for an Energy-Efficient Economy (ACEEE) | D39: Asosiasi Pengusaha Semen Indonesia (Asperssi)
B40: Decarbonisation in the Indian Cement Industry | D40: Asperssi ungkap volume produksi & penjualan semen di 2025 dan proyeksi untuk 2026
B41: 2026 | D41: 2026
B42: https://www.aceee.org/wp-content/uploads/2026/07/ACEEE_Decarbonisation_in_Cement_Industry.pdf | D42: https://asperssi.id/asperssi-ungkap-volume-produksi-penjualan-semen-di-2025-dan-proyeksi-untuk-2026/
B43: India: a clinker-to-cement ratio of 0.73 for fiscal year 2024-25, which ACEEE attributes to Indian Cement Review (SNIPPET). It is a production-basis figure, close to the consumption-blend basis because India's net trade is near zero. Indonesia: the same report gives about 0.68 for 2026, which we use only as a cross-check (SNIPPET). | D43: 2025 clinker production of 57.301 million tons, clinker exports of 12.34 million tons, and domestic cement sales of 63.912 million tons (DIRECT). Our ratio is domestic clinker use over domestic sales: (57.301 - 12.34) / 63.912 = 0.70. Do not use 57.3 / 64.7 = 0.89, which counts exported clinker.
B45: India ratio, disagreeing estimate
B46: Indian Cement Review
B47: NITI Aayog unveils decarbonisation roadmaps
B48: 2026
B49: https://indiancementreview.com/2026/01/28/niti-aayog-unveils-decarbonisation-roadmaps/
B50: NITI Aayog's roadmap baseline is 0.675 (SNIPPET, from a search summary of the article). It disagrees with ACEEE's 0.73, and we have not resolved the difference.
A53: Notes:
A54: Purpose and layout | B54: This file gives the business-as-usual clinker-to-cement ratio: the metric tons of clinker in each metric ton of cement the region consumes. Clinker is the kiln product that causes nearly all of the cement industry's fuel use and process emissions, so this ratio is what turns cement demand (the BCD file) into clinker demand. It is a blend ratio: clinker used in the cement the region consumes, including clinker that is imported, divided by cement produced, with imported finished cement assumed to carry the same ratio. How much of that clinker is made inside the region is handled separately (BFoCDMbNI). In the policy case, the clinker-substitution lever lowers the ratio below this path, down toward the floor in MACtCR. The tabs run from inputs to output. 'Regions' holds the region selector and each region's starting ratio and optional target. 'USGS MCS 2026 Cement' holds the U.S. production data as published. 'US Product Mix' projects the U.S. ratio from the mix of cement types and their clinker content. 'Derivation' builds the 2021-2050 series, and the last tab, 'BCtCR', reads it directly. That 'BCtCR' tab is what gets exported to BCtCR.csv.
A55: Using it for other regions | B55: We set this file up to be adaptable to each of the main EPS regions. If you are working on a non-US region, use the drop-down selector at the top of the 'Regions' tab to choose a different country. The Derivation then holds that country's starting ratio flat across 2021-2050, unless the Regions tab also gives a target ratio and target year, in which case the ratio moves in a straight line to the target and stays there. The 'BCtCR' tab updates on its own; just re-export the CSV. If your region is blank, or not listed, you will have to build the ratio on your own.
A56: U.S. values | B56: For 2021-2025 (2025 estimated) the ratio comes from USGS production and import data: 0.892, 0.883, 0.866, 0.855 and 0.829. The decline is the shift to portland-limestone (Type IL) cement, which went from about 5% to 65% of shipments over those years. From 2026 the 'US Product Mix' tab projects the ratio from the share of each cement type times its clinker content (PCA's product declarations), scaled so 2025 matches USGS. That shift is now mostly complete, so the remaining business-as-usual decline is slow: a little more blended cement (68% of shipments by 2030, 72% by 2050), a little more slag and pozzolan cement (2.8% of all cement now, 5% by 2050), and Type IL limestone content drifting from 11% to 12.5% by 2035. The result is 0.820 in 2030, 0.813 in 2035, 0.811 in 2040 and 0.809 in 2050. The milestone shares are our judgment from the shipment trend; a reasonable range is 0.80-0.83 in 2035 and 0.79-0.83 in 2050. Deeper cuts are the job of the clinker-substitution lever and the MACtCR floor.
A57: Other regions' values | B57: Starting values for the other regions come from national cement associations, roadmaps, and press, listed under Sources. Each non-US value on the 'Regions' tab carries a tag showing how far to trust it: DIRECT means we read the number in the original document; SNIPPET means it came from a secondary summary, such as a trade-press article, and should be checked against the original; JUDGMENT means it is our own estimate or arithmetic, shown as a formula where possible. A blank means we have not found a good value yet. None of the non-US rows has a business-as-usual trend, so those ratios are held flat; the roadmap targets we found are policy goals and live in MACtCR instead. China is blank because the published figures conflict (roughly 0.66 against 0.74, with the China Cement Association disputing the rise), and Japan and Australia are blank because we have not found a value. The GCCA's GNR database holds regional detail but sits behind a login, so most values here come from association reports and trade press instead. Several rows are on a production basis rather than the consumption-blend basis used for the U.S.; that is close where net trade is small. The Mexico value is from 2016 and the EU value is for Europe in 2021, so both are due for updates.

Sheet Regions
A1: Selected region (drop-down): | B1: United States
A2: Pick a region from the drop-down in B1. The Derivation and the export tab update on their own; re-export the CSV afterward. A blank cell means no sourced value yet.
A4: Region | B4: Anchor year | C4: Anchor blend ratio | D4: Flag | E4: BAU target ratio (blank = flat) | F4: Target year | G4: Flag | H4: Source / note
A5: United States | B5: 2025 | C5: 0.8293 | D5: DIRECT | H5: USGS MCS 2026 history; 2026-2050 from the 'US Product Mix' tab (product shares x PCA clinker contents)
A6: China | H6: TO FILL - conflicting snippets (0.657 vs 0.735, CCA disputes the rise); 53% utilization x 1.81 Bt capacity implies ~0.52, which also conflicts. Next: NBS clinker output + CCA annual report.
A7: India | B7: 2025 | C7: 0.73 | D7: SNIPPET | H7: ACEEE Jul-2026 citing Indian Cement Review (SNIPPET). NITI Aayog baseline 0.675 (SNIPPET); GCCA India/TERI 0.75 in 2020 (SNIPPET) - sources disagree. Production basis, not consumption blend basis (trade ~0, so close). | BAU target blank = flat at anchor (no BAU trajectory sourced; roadmap targets are policy, see MACtCR).
A8: EU-27 | B8: 2021 | C8: 0.77 | D8: DIRECT | H8: CEMBUREAU Net Zero Roadmap text: 77% for 'Europe' in 2021 (DIRECT); Cement Europe says the ratio fell ~2% over the last 3 years. Scope is Europe, not strictly EU-27. | BAU target blank = flat at anchor (no BAU trajectory sourced; roadmap targets are policy, see MACtCR).
A9: Japan | H9: TO FILL
A10: Brazil | B10: 2022 | C10: 0.71 | D10: DIRECT | H10: GCCA figure in SNIC Annual Report 2023 (DIRECT); 0.84 in 1990. A snippet clinker figure (77.5 Mt 2024) exceeds cement output - unreliable. | BAU target blank = flat at anchor (no BAU trajectory sourced; roadmap targets are policy, see MACtCR).
A11: Mexico | B11: 2016 | C11: 0.75 | D11: DIRECT | H11: FICEM/CANACEM roadmap, PwC-verified GNR data, 2016 (DIRECT). Stale anchor year - newer CANACEM/GNR figure needed. | BAU target blank = flat at anchor (no BAU trajectory sourced; roadmap targets are policy, see MACtCR).
A12: Canada | B12: 2020 | C12: 0.89 | D12: DIRECT | H12: CAC Concrete Zero 2020 baseline 89% (DIRECT; 11.4 clinker / 12.7 cement = 0.90). Production basis; Canada is a net exporter. | BAU target blank = flat at anchor (no BAU trajectory sourced; roadmap targets are policy, see MACtCR).
A13: Indonesia | B13: 2025 | C13: =((57.301-12.34)/63.912) -> 0.70348291 | D13: JUDGMENT | H13: Domestic clinker use (ASI clinker production 57.301 - clinker exports 12.34, DIRECT) / domestic sales 63.912 (DIRECT) - domestic basis. Do not use 57.3/64.7 = 0.89 (includes exported clinker). ACEEE: 0.68 in 2026 (SNIPPET). | BAU target blank = flat at anchor (no BAU trajectory sourced; roadmap targets are policy, see MACtCR).
A14: Australia | H14: TO FILL

Sheet USGS MCS 2026 Cement
A1: USGS Mineral Commodity Summaries 2026 - Cement (Ashley K. Hatfield). Pasted from the PDF text; 'e' = estimated. Data in thousand metric tons unless otherwise specified.
A3: Salient Statistics - United States (thousand metric tons unless noted) | B3: 2021 | C3: 2022 | D3: 2023 | E3: 2024 | F3: 2025e
A4: Production: Portland, blended, and masonry cement (includes cement made from imported clinker) | B4: 91000 | C4: 91200 | D4: 89700 | E4: 85000 | F4: 84000
A5: Production: Clinker | B5: 79616 | C5: 79489 | D5: 76789 | E5: 72000 | F5: 69000
A6: Shipments to final customers, includes exports | B6: 108969 | C6: 111092 | D6: 110290 | E6: 100000 | F6: 100000
A7: Imports for consumption: Hydraulic cement | B7: 19937 | C7: 24985 | D7: 24986 | E7: 23675 | F7: 23000
A8: Imports for consumption: Clinker | B8: 1563 | C8: 1021 | D8: 921 | E8: 685 | F8: 660
A9: Exports, hydraulic cement and clinker | B9: 939 | C9: 904 | D9: 889 | E9: 932 | F9: 1000
A10: Consumption, apparent (production incl. from imported clinker + imports excl. clinker - exports - stock changes) | B10: 111000 | C10: 114000 | D10: 113000 | E10: 110000 | F10: 110000
A11: Price, average mill unit value, dollars per metric ton | B11: 127 | C11: 139 | D11: 152 | E11: 160 | F11: 160
A12: Stocks, cement, yearend | B12: 6280 | C12: 8010 | D12: 8830 | E12: 9700 | F12: 8200
A13: Net import reliance as a percentage of apparent consumption | B13: 19 | C13: 22 | D13: 22 | E13: 22 | F13: 21
A15: World Production and Capacity (thousand metric tons) | B15: Cement production 2024 | C15: Cement production 2025e | D15: Clinker capacity 2024 | E15: Clinker capacity 2025e
A16: United States (includes Puerto Rico) | B16: 85000 | C16: 84000 | D16: 100000 | E16: 100000
A17: Brazil | B17: 65000 | C17: 67000 | D17: 60000 | E17: 61000
A18: China | B18: 1800000 | C18: 1700000 | D18: 1900000 | E18: 1800000
A19: Egypt | B19: 53000 | C19: 64000 | D19: 60000 | E19: 75000
A20: India | B20: 440000 | C20: 470000 | D20: 380000 | E20: 400000
A21: Indonesia | B21: 68000 | C21: 64000 | D21: 79000 | E21: 83000
A22: Iran | B22: 71000 | C22: 68000 | D22: 85000 | E22: 85000
A23: Japan | B23: 46000 | C23: 44000 | D23: 50000 | E23: 50000
A24: Korea, Republic of | B24: 44000 | C24: 37000 | D24: 62000 | E24: 62000
A25: Mexico | B25: 44000 | C25: 42000 | D25: 42000 | E25: 42000
A26: Russia | B26: 67000 | C26: 59000 | D26: 80000 | E26: 80000
A27: Saudi Arabia | B27: 51000 | C27: 54000 | D27: 75000 | E27: 75000
... A31: World total (rounded) | B31: 3900000 | C31: 3800000 | D31: 3800000 | E31: 3800000

Sheet US Product Mix
A1: U.S. business-as-usual clinker ratio from the cement product mix
A3: USGS Mineral Industry Surveys, Cement (December issues): shipments including imports, million metric tons
A4: Year | B4: 2019 | C4: 2020 | D4: 2021 | E4: 2022 | F4: 2023 | G4: 2024 | H4: 2025
A5: Portland cement (ASTM C150) | B5: 98.59 | C5: 99.55 | D5: 101.21 | E5: 82.87 | F5: 54.66 | G5: 41.78 | H5: 36.02
A6: Blended cement (ASTM C595) | B6: 2.43 | C6: 3.28 | D6: 6.04 | E6: 26.39 | F6: 54.21 | G6: 61.41 | H6: 65.6
A7: Blended share of shipments | B7: =B6/(B5+B6) -> 0.024054643 | C7: =C6/(C5+C6) -> 0.031897306 | D7: =D6/(D5+D6) -> 0.056317016 | E7: =E6/(E5+E6) -> 0.24153396 | F7: =F6/(F5+F6) -> 0.49793331 | G7: =G6/(G5+G6) -> 0.59511581 | H7: =H6/(H5+H6) -> 0.64554222
A8: Type IL share of blended | G8: 0.966 | H8: 0.956
A10: Clinker content per metric ton of cement (PCA industry-average EPDs, 2019 data)
A11: Portland cement, Type I/II | B11: 0.914
A12: Type IL: clinker plus limestone (the rest is gypsum and minor additions) | B12: 0.935
A13: Other blended cements (slag, pozzolan, ternary; EI estimate) | B13: 0.65
A15: Business-as-usual assumptions at milestone years (EI judgment from the shipment trend; 2025 from data)
A16: Year | B16: 2025 | C16: 2030 | D16: 2035 | E16: 2040 | F16: 2050
A17: Blended share of shipments | B17: =H7 -> 0.64554222 | C17: 0.68 | D17: 0.7 | E17: 0.71 | F17: 0.72
A18: Other blended share of all cement | B18: =H7*(1-H8) -> 0.028403858 | C18: 0.034 | D18: 0.04 | E18: 0.043 | F18: 0.05
A19: Limestone fraction of Type IL | B19: 0.11 | C19: 0.118 | D19: 0.125 | E19: 0.125 | F19: 0.125
A21: Annual path (straight lines between milestone years)
A22: Year | B22: 2025 | C22: 2026 | D22: 2027 | E22: 2028 | F22: 2029 | G22: 2030 | H22: 2031 | I22: 2032 | J22: 2033 | K22: 2034 | L22: 2035 | M22: 2036 | N22: 2037 | O22: 2038 | P22: 2039 | Q22: 2040 | R22: 2041 | S22: 2042 | T22: 2043 | U22: 2044 | V22: 2045 | W22: 2046 | X22: 2047 | Y22: 2048 | Z22: 2049 | AA22: 2050
A23: Blended share | B23: =IF(B$22<=2030,$B$17+($C$17-$B$17)*(B$22-2025)/5,IF(B$22<=2035,$C$17+($D$17-$C$17)*(B$22-2030)/5,IF(B$22<=2040,$D$17+($E$17-$D$17)*(B$22-2035)/5,$E$17+($F$17-$E$17)*(B$22-2040)/10))) -> 0.64554222 | C23: =IF(C$22<=2030,$B$17+($C$17-$B$17)*(C$22-2025)/5,IF(C$22<=2035,$C$17+($D$17-$C$17)*(C$22-2030)/5,IF(C$22<=2040,$D$17+($E$17-$D$17)*(C$22-2035)/5,$E$17+($F$17-$E$17)*(C$22-2040)/10))) -> 0.65243377 | D23: =IF(D$22<=2030,$B$17+($C$17-$B$17)*(D$22-2025)/5,IF(D$22<=2035,$C$17+($D$17-$C$17)*(D$22-2030)/5,IF(D$22<=2040,$D$17+($E$17-$D$17)*(D$22-2035)/5,$E$17+($F$17-$E$17)*(D$22-2040)/10))) -> 0.65932533 | E23: =IF(E$22<=2030,$B$17+($C$17-$B$17)*(E$22-2025)/5,IF(E$22<=2035,$C$17+($D$17-$C$17)*(E$22-2030)/5,IF(E$22<=2040,$D$17+($E$17-$D$17)*(E$22-2035)/5,$E$17+($F$17-$E$17)*(E$22-2040)/10))) -> 0.66621689 | F23: =IF(F$22<=2030,$B$17+($C$17-$B$17)*(F$22-2025)/5,IF(F$22<=2035,$C$17+($D$17-$C$17)*(F$22-2030)/5,IF(F$22<=2040,$D$17+($E$17-$D$17)*(F$22-2035)/5,$E$17+($F$17-$E$17)*(F$22-2040)/10))) -> 0.67310844 | G23: =IF(G$22<=2030,$B$17+($C$17-$B$17)*(G$22-2025)/5,IF(G$22<=2035,$C$17+($D$17-$C$17)*(G$22-2030)/5,IF(G$22<=2040,$D$17+($E$17-$D$17)*(G$22-2035)/5,$E$17+($F$17-$E$17)*(G$22-2040)/10))) -> 0.68 | H23: =IF(H$22<=2030,$B$17+($C$17-$B$17)*(H$22-2025)/5,IF(H$22<=2035,$C$17+($D$17-$C$17)*(H$22-2030)/5,IF(H$22<=2040,$D$17+($E$17-$D$17)*(H$22-2035)/5,$E$17+($F$17-$E$17)*(H$22-2040)/10))) -> 0.684 | I23: =IF(I$22<=2030,$B$17+($C$17-$B$17)*(I$22-2025)/5,IF(I$22<=2035,$C$17+($D$17-$C$17)*(I$22-2030)/5,IF(I$22<=2040,$D$17+($E$17-$D$17)*(I$22-2035)/5,$E$17+($F$17-$E$17)*(I$22-2040)/10))) -> 0.688 | ... AA23: =IF(AA$22<=2030,$B$17+($C$17-$B$17)*(AA$22-2025)/5,IF(AA$22<=2035,$C$17+($D$17-$C$17)*(AA$22-2030)/5,IF(AA$22<=2040,$D$17+($E$17-$D$17)*(AA$22-2035)/5,$E$17+($F$17-$E$17)*(AA$22-2040)/10))) -> 0.72
A24: Other blended share | B24: =IF(B$22<=2030,$B$18+($C$18-$B$18)*(B$22-2025)/5,IF(B$22<=2035,$C$18+($D$18-$C$18)*(B$22-2030)/5,IF(B$22<=2040,$D$18+($E$18-$D$18)*(B$22-2035)/5,$E$18+($F$18-$E$18)*(B$22-2040)/10))) -> 0.028403858 | C24: =IF(C$22<=2030,$B$18+($C$18-$B$18)*(C$22-2025)/5,IF(C$22<=2035,$C$18+($D$18-$C$18)*(C$22-2030)/5,IF(C$22<=2040,$D$18+($E$18-$D$18)*(C$22-2035)/5,$E$18+($F$18-$E$18)*(C$22-2040)/10))) -> 0.029523086 | D24: =IF(D$22<=2030,$B$18+($C$18-$B$18)*(D$22-2025)/5,IF(D$22<=2035,$C$18+($D$18-$C$18)*(D$22-2030)/5,IF(D$22<=2040,$D$18+($E$18-$D$18)*(D$22-2035)/5,$E$18+($F$18-$E$18)*(D$22-2040)/10))) -> 0.030642315 | E24: =IF(E$22<=2030,$B$18+($C$18-$B$18)*(E$22-2025)/5,IF(E$22<=2035,$C$18+($D$18-$C$18)*(E$22-2030)/5,IF(E$22<=2040,$D$18+($E$18-$D$18)*(E$22-2035)/5,$E$18+($F$18-$E$18)*(E$22-2040)/10))) -> 0.031761543 | F24: =IF(F$22<=2030,$B$18+($C$18-$B$18)*(F$22-2025)/5,IF(F$22<=2035,$C$18+($D$18-$C$18)*(F$22-2030)/5,IF(F$22<=2040,$D$18+($E$18-$D$18)*(F$22-2035)/5,$E$18+($F$18-$E$18)*(F$22-2040)/10))) -> 0.032880772 | G24: =IF(G$22<=2030,$B$18+($C$18-$B$18)*(G$22-2025)/5,IF(G$22<=2035,$C$18+($D$18-$C$18)*(G$22-2030)/5,IF(G$22<=2040,$D$18+($E$18-$D$18)*(G$22-2035)/5,$E$18+($F$18-$E$18)*(G$22-2040)/10))) -> 0.034 | H24: =IF(H$22<=2030,$B$18+($C$18-$B$18)*(H$22-2025)/5,IF(H$22<=2035,$C$18+($D$18-$C$18)*(H$22-2030)/5,IF(H$22<=2040,$D$18+($E$18-$D$18)*(H$22-2035)/5,$E$18+($F$18-$E$18)*(H$22-2040)/10))) -> 0.0352 | I24: =IF(I$22<=2030,$B$18+($C$18-$B$18)*(I$22-2025)/5,IF(I$22<=2035,$C$18+($D$18-$C$18)*(I$22-2030)/5,IF(I$22<=2040,$D$18+($E$18-$D$18)*(I$22-2035)/5,$E$18+($F$18-$E$18)*(I$22-2040)/10))) -> 0.0364 | ... AA24: =IF(AA$22<=2030,$B$18+($C$18-$B$18)*(AA$22-2025)/5,IF(AA$22<=2035,$C$18+($D$18-$C$18)*(AA$22-2030)/5,IF(AA$22<=2040,$D$18+($E$18-$D$18)*(AA$22-2035)/5,$E$18+($F$18-$E$18)*(AA$22-2040)/10))) -> 0.05
A25: Type IL share of all cement | B25: =B23-B24 -> 0.61713836 | C25: =C23-C24 -> 0.62291069 | D25: =D23-D24 -> 0.62868302 | E25: =E23-E24 -> 0.63445534 | F25: =F23-F24 -> 0.64022767 | G25: =G23-G24 -> 0.646 | H25: =H23-H24 -> 0.6488 | I25: =I23-I24 -> 0.6516 | ... AA25: =AA23-AA24 -> 0.67
A26: Portland (Type I/II) share | B26: =1-B23 -> 0.35445778 | C26: =1-C23 -> 0.34756623 | D26: =1-D23 -> 0.34067467 | E26: =1-E23 -> 0.33378311 | F26: =1-F23 -> 0.32689156 | G26: =1-G23 -> 0.32 | H26: =1-H23 -> 0.316 | I26: =1-I23 -> 0.312 | ... AA26: =1-AA23 -> 0.28
A27: Limestone fraction of Type IL | B27: =IF(B$22<=2030,$B$19+($C$19-$B$19)*(B$22-2025)/5,IF(B$22<=2035,$C$19+($D$19-$C$19)*(B$22-2030)/5,IF(B$22<=2040,$D$19+($E$19-$D$19)*(B$22-2035)/5,$E$19+($F$19-$E$19)*(B$22-2040)/10))) -> 0.11 | C27: =IF(C$22<=2030,$B$19+($C$19-$B$19)*(C$22-2025)/5,IF(C$22<=2035,$C$19+($D$19-$C$19)*(C$22-2030)/5,IF(C$22<=2040,$D$19+($E$19-$D$19)*(C$22-2035)/5,$E$19+($F$19-$E$19)*(C$22-2040)/10))) -> 0.1116 | D27: =IF(D$22<=2030,$B$19+($C$19-$B$19)*(D$22-2025)/5,IF(D$22<=2035,$C$19+($D$19-$C$19)*(D$22-2030)/5,IF(D$22<=2040,$D$19+($E$19-$D$19)*(D$22-2035)/5,$E$19+($F$19-$E$19)*(D$22-2040)/10))) -> 0.1132 | E27: =IF(E$22<=2030,$B$19+($C$19-$B$19)*(E$22-2025)/5,IF(E$22<=2035,$C$19+($D$19-$C$19)*(E$22-2030)/5,IF(E$22<=2040,$D$19+($E$19-$D$19)*(E$22-2035)/5,$E$19+($F$19-$E$19)*(E$22-2040)/10))) -> 0.1148 | F27: =IF(F$22<=2030,$B$19+($C$19-$B$19)*(F$22-2025)/5,IF(F$22<=2035,$C$19+($D$19-$C$19)*(F$22-2030)/5,IF(F$22<=2040,$D$19+($E$19-$D$19)*(F$22-2035)/5,$E$19+($F$19-$E$19)*(F$22-2040)/10))) -> 0.1164 | G27: =IF(G$22<=2030,$B$19+($C$19-$B$19)*(G$22-2025)/5,IF(G$22<=2035,$C$19+($D$19-$C$19)*(G$22-2030)/5,IF(G$22<=2040,$D$19+($E$19-$D$19)*(G$22-2035)/5,$E$19+($F$19-$E$19)*(G$22-2040)/10))) -> 0.118 | H27: =IF(H$22<=2030,$B$19+($C$19-$B$19)*(H$22-2025)/5,IF(H$22<=2035,$C$19+($D$19-$C$19)*(H$22-2030)/5,IF(H$22<=2040,$D$19+($E$19-$D$19)*(H$22-2035)/5,$E$19+($F$19-$E$19)*(H$22-2040)/10))) -> 0.1194 | I27: =IF(I$22<=2030,$B$19+($C$19-$B$19)*(I$22-2025)/5,IF(I$22<=2035,$C$19+($D$19-$C$19)*(I$22-2030)/5,IF(I$22<=2040,$D$19+($E$19-$D$19)*(I$22-2035)/5,$E$19+($F$19-$E$19)*(I$22-2040)/10))) -> 0.1208 | ... AA27: =IF(AA$22<=2030,$B$19+($C$19-$B$19)*(AA$22-2025)/5,IF(AA$22<=2035,$C$19+($D$19-$C$19)*(AA$22-2030)/5,IF(AA$22<=2040,$D$19+($E$19-$D$19)*(AA$22-2035)/5,$E$19+($F$19-$E$19)*(AA$22-2040)/10))) -> 0.125
A28: Unscaled clinker ratio | B28: =B26*$B$11+B25*($B$12-B27)+B24*$B$13 -> 0.85157607 | C28: =C26*$B$11+C25*($B$12-C27)+C24*$B$13 -> 0.8497702 | D28: =D26*$B$11+D25*($B$12-D27)+D24*$B$13 -> 0.84794585 | E28: =E26*$B$11+E25*($B$12-E27)+E24*$B$13 -> 0.84610304 | F28: =F26*$B$11+F25*($B$12-F27)+F24*$B$13 -> 0.84424176 | G28: =G26*$B$11+G25*($B$12-G27)+G24*$B$13 -> 0.842362 | H28: =H26*$B$11+H25*($B$12-H27)+H24*$B$13 -> 0.84086528 | I28: =I26*$B$11+I25*($B$12-I27)+I24*$B$13 -> 0.83936072 | ... AA28: =AA26*$B$11+AA25*($B$12-AA27)+AA24*$B$13 -> 0.83112
A29: Clinker ratio (scaled to the 2025 USGS value) | B29: =B28*$B$31 -> 0.82928571 | C29: =C28*$B$31 -> 0.82752711 | D29: =D28*$B$31 -> 0.82575052 | E29: =E28*$B$31 -> 0.82395595 | F29: =F28*$B$31 -> 0.82214338 | G29: =G28*$B$31 -> 0.82031283 | H29: =H28*$B$31 -> 0.81885529 | I29: =I28*$B$31 -> 0.81739011 | ... AA29: =AA28*$B$31 -> 0.80936509
A31: Scale factor = 2025 USGS blend ratio / 2025 unscaled ratio (covers masonry cement, stock changes, and USGS estimation) | B31: =Derivation!F10/B28 -> 0.97382459

Sheet Derivation
A1: Selected region | B1: =Regions!B1 -> United States
A2: Anchor year | B2: =INDEX(Regions!$B$5:$B$14,MATCH(Regions!$B$1,Regions!$A$5:$A$14,0)) -> 2025
A3: Anchor blend ratio | B3: =INDEX(Regions!$C$5:$C$14,MATCH(Regions!$B$1,Regions!$A$5:$A$14,0)) -> 0.8293
A4: Target ratio (blank = anchor) | B4: =IF(ISNUMBER(INDEX(Regions!$E$5:$E$14,MATCH(Regions!$B$1,Regions!$A$5:$A$14,0))),INDEX(Regions!$E$5:$E$14,MATCH(Regions!$B$1,Regions!$A$5:$A$14,0)),B3) -> 0.8293
A5: Target year (blank = anchor year) | B5: =IF(ISNUMBER(INDEX(Regions!$F$5:$F$14,MATCH(Regions!$B$1,Regions!$A$5:$A$14,0))),INDEX(Regions!$F$5:$F$14,MATCH(Regions!$B$1,Regions!$A$5:$A$14,0)),B2) -> 2025
A6: Is US? (history from USGS tab) | B6: =IF(B1="United States",1,0) -> 1
A8: US historical blend ratio = (clinker production + clinker imports) / cement production
A9: Year | B9: 2021 | C9: 2022 | D9: 2023 | E9: 2024 | F9: 2025
A10: Blend ratio | B10: =(('USGS MCS 2026 Cement'!B5+'USGS MCS 2026 Cement'!B8)/'USGS MCS 2026 Cement'!B4) -> 0.89207692 | C10: =(('USGS MCS 2026 Cement'!C5+'USGS MCS 2026 Cement'!C8)/'USGS MCS 2026 Cement'!C4) -> 0.88278509 | D10: =(('USGS MCS 2026 Cement'!D5+'USGS MCS 2026 Cement'!D8)/'USGS MCS 2026 Cement'!D4) -> 0.86633222 | E10: =(('USGS MCS 2026 Cement'!E5+'USGS MCS 2026 Cement'!E8)/'USGS MCS 2026 Cement'!E4) -> 0.85511765 | F10: =(('USGS MCS 2026 Cement'!F5+'USGS MCS 2026 Cement'!F8)/'USGS MCS 2026 Cement'!F4) -> 0.82928571
A12: Year | B12: 2021 | C12: 2022 | D12: 2023 | E12: 2024 | F12: 2025 | G12: 2026 | H12: 2027 | I12: 2028 | J12: 2029 | K12: 2030 | L12: 2031 | M12: 2032 | N12: 2033 | O12: 2034 | P12: 2035 | Q12: 2036 | R12: 2037 | S12: 2038 | T12: 2039 | U12: 2040 | V12: 2041 | W12: 2042 | X12: 2043 | Y12: 2044 | Z12: 2045 | AA12: 2046 | AB12: 2047 | AC12: 2048 | AD12: 2049 | AE12: 2050
A13: BAU Clinker to Cement Ratio | B13: =IF(AND($B$6=1,B12>2025),INDEX('US Product Mix'!$B$29:$AA$29,MATCH(B12,'US Product Mix'!$B$22:$AA$22,0)),IF(AND($B$6=1,B12<=2025),B10,($B$3+($B$4-$B$3)*MAX(0,MIN(1,IF($B$5=$B$2,1,(B12-$B$2)/($B$5-$B$2))))))) -> 0.89207692 | C13: =IF(AND($B$6=1,C12>2025),INDEX('US Product Mix'!$B$29:$AA$29,MATCH(C12,'US Product Mix'!$B$22:$AA$22,0)),IF(AND($B$6=1,C12<=2025),C10,($B$3+($B$4-$B$3)*MAX(0,MIN(1,IF($B$5=$B$2,1,(C12-$B$2)/($B$5-$B$2))))))) -> 0.88278509 | D13: =IF(AND($B$6=1,D12>2025),INDEX('US Product Mix'!$B$29:$AA$29,MATCH(D12,'US Product Mix'!$B$22:$AA$22,0)),IF(AND($B$6=1,D12<=2025),D10,($B$3+($B$4-$B$3)*MAX(0,MIN(1,IF($B$5=$B$2,1,(D12-$B$2)/($B$5-$B$2))))))) -> 0.86633222 | E13: =IF(AND($B$6=1,E12>2025),INDEX('US Product Mix'!$B$29:$AA$29,MATCH(E12,'US Product Mix'!$B$22:$AA$22,0)),IF(AND($B$6=1,E12<=2025),E10,($B$3+($B$4-$B$3)*MAX(0,MIN(1,IF($B$5=$B$2,1,(E12-$B$2)/($B$5-$B$2))))))) -> 0.85511765 | F13: =IF(AND($B$6=1,F12>2025),INDEX('US Product Mix'!$B$29:$AA$29,MATCH(F12,'US Product Mix'!$B$22:$AA$22,0)),IF(AND($B$6=1,F12<=2025),F10,($B$3+($B$4-$B$3)*MAX(0,MIN(1,IF($B$5=$B$2,1,(F12-$B$2)/($B$5-$B$2))))))) -> 0.82928571 | G13: =IF(AND($B$6=1,G12>2025),INDEX('US Product Mix'!$B$29:$AA$29,MATCH(G12,'US Product Mix'!$B$22:$AA$22,0)),($B$3+($B$4-$B$3)*MAX(0,MIN(1,IF($B$5=$B$2,1,(G12-$B$2)/($B$5-$B$2)))))) -> 0.82752711 | H13: =IF(AND($B$6=1,H12>2025),INDEX('US Product Mix'!$B$29:$AA$29,MATCH(H12,'US Product Mix'!$B$22:$AA$22,0)),($B$3+($B$4-$B$3)*MAX(0,MIN(1,IF($B$5=$B$2,1,(H12-$B$2)/($B$5-$B$2)))))) -> 0.82575052 | I13: =IF(AND($B$6=1,I12>2025),INDEX('US Product Mix'!$B$29:$AA$29,MATCH(I12,'US Product Mix'!$B$22:$AA$22,0)),($B$3+($B$4-$B$3)*MAX(0,MIN(1,IF($B$5=$B$2,1,(I12-$B$2)/($B$5-$B$2)))))) -> 0.82395595 | J13: =IF(AND($B$6=1,J12>2025),INDEX('US Product Mix'!$B$29:$AA$29,MATCH(J12,'US Product Mix'!$B$22:$AA$22,0)),($B$3+($B$4-$B$3)*MAX(0,MIN(1,IF($B$5=$B$2,1,(J12-$B$2)/($B$5-$B$2)))))) -> 0.82214338 | K13: =IF(AND($B$6=1,K12>2025),INDEX('US Product Mix'!$B$29:$AA$29,MATCH(K12,'US Product Mix'!$B$22:$AA$22,0)),($B$3+($B$4-$B$3)*MAX(0,MIN(1,IF($B$5=$B$2,1,(K12-$B$2)/($B$5-$B$2)))))) -> 0.82031283 | L13: =IF(AND($B$6=1,L12>2025),INDEX('US Product Mix'!$B$29:$AA$29,MATCH(L12,'US Product Mix'!$B$22:$AA$22,0)),($B$3+($B$4-$B$3)*MAX(0,MIN(1,IF($B$5=$B$2,1,(L12-$B$2)/($B$5-$B$2)))))) -> 0.81885529 | M13: =IF(AND($B$6=1,M12>2025),INDEX('US Product Mix'!$B$29:$AA$29,MATCH(M12,'US Product Mix'!$B$22:$AA$22,0)),($B$3+($B$4-$B$3)*MAX(0,MIN(1,IF($B$5=$B$2,1,(M12-$B$2)/($B$5-$B$2)))))) -> 0.81739011 | N13: =IF(AND($B$6=1,N12>2025),INDEX('US Product Mix'!$B$29:$AA$29,MATCH(N12,'US Product Mix'!$B$22:$AA$22,0)),($B$3+($B$4-$B$3)*MAX(0,MIN(1,IF($B$5=$B$2,1,(N12-$B$2)/($B$5-$B$2)))))) -> 0.8159173 | ... AE13: =IF(AND($B$6=1,AE12>2025),INDEX('US Product Mix'!$B$29:$AA$29,MATCH(AE12,'US Product Mix'!$B$22:$AA$22,0)),($B$3+($B$4-$B$3)*MAX(0,MIN(1,IF($B$5=$B$2,1,(AE12-$B$2)/($B$5-$B$2)))))) -> 0.80936509

Sheet BCtCR
A1: Unit: dimensionless | B1: 2021 | C1: 2022 | D1: 2023 | E1: 2024 | F1: 2025 | G1: 2026 | H1: 2027 | I1: 2028 | J1: 2029 | K1: 2030 | L1: 2031 | M1: 2032 | N1: 2033 | O1: 2034 | P1: 2035 | Q1: 2036 | R1: 2037 | S1: 2038 | T1: 2039 | U1: 2040 | V1: 2041 | W1: 2042 | X1: 2043 | Y1: 2044 | Z1: 2045 | AA1: 2046 | AB1: 2047 | AC1: 2048 | AD1: 2049 | AE1: 2050
A2: BAU Clinker to Cement Ratio | B2: =Derivation!B13 -> 0.89207692 | C2: =Derivation!C13 -> 0.88278509 | D2: =Derivation!D13 -> 0.86633222 | E2: =Derivation!E13 -> 0.85511765 | F2: =Derivation!F13 -> 0.82928571 | G2: =Derivation!G13 -> 0.82752711 | H2: =Derivation!H13 -> 0.82575052 | I2: =Derivation!I13 -> 0.82395595 | ... AE2: =Derivation!AE13 -> 0.80936509
