Workbook

Sheet About
A1: BVS BAU Vehicle Subsidy
A3: Sources: | B3: Federal IRA Incentives
B4: ICCT and Energy Innovation
B5: 2023
B6: https://energyinnovation.org/publication/analyzing-the-impact-of-the-inflation-reduction-act-on-electric-vehicle-uptake-in-the-united-states/
B8: Foreign Entities of Concern Multiplier
B9: BloombergNEF, MarkLines, Department of Energy

Sheet Passenger Vehicle Calculations
A1: Federal EV Subsidy Amount (2012$)
A2: These values come from our internal analysis of weighted 30D and 45W purchase and leasing credits. (ICCT spreadsheet)
A3: Updated 2/11/25
B4: 2021 | C4: 2022 | D4: 2023 | E4: 2024 | F4: 2025 | G4: 2026 | H4: 2027 | I4: 2028 | J4: 2029 | K4: 2030 | L4: 2031 | M4: 2032 | N4: 2033 | O4: 2034 | P4: 2035 | Q4: 2036 | R4: 2037 | S4: 2038 | T4: 2039 | U4: 2040 | V4: 2041 | W4: 2042 | X4: 2043 | Y4: 2044 | Z4: 2045 | AA4: 2046 | AB4: 2047 | AC4: 2048 | AD4: 2049 | AE4: 2050
A5: battery electric vehicles | B5: 1646.4981 | C5: 1368.5858 | D5: 4795.9637 | E5: 3555.4877 | F5: 3365.6877 | G5: 3118.2247 | H5: 2391.1776 | I5: 2424.5099 | J5: 2459.8873 | K5: 2497.1121 | L5: 2525.3972 | M5: 2552.5013 | N5: 0 | O5: 0 | P5: 0 | Q5: 0 | R5: 0 | S5: 0 | T5: 0 | U5: 0 | V5: 0 | W5: 0 | X5: 0 | Y5: 0 | Z5: 0 | AA5: 0 | AB5: 0 | AC5: 0 | AD5: 0 | AE5: 0
A6: plugin hybrid vehicles | B6: 6652.7185 | C6: 3617.0507 | D6: 3481.1983 | E6: 2846.5223 | F6: 2396.2167 | G6: 2262.2796 | H6: 2133.3804 | I6: 2079.448 | J6: 2027.139 | K6: 1976.3953 | L6: 1926.1485 | M6: 1877.1377 | N6: 0 | O6: 0 | P6: 0 | Q6: 0 | R6: 0 | S6: 0 | T6: 0 | U6: 0 | V6: 0 | W6: 0 | X6: 0 | Y6: 0 | Z6: 0 | AA6: 0 | AB6: 0 | AC6: 0 | AD6: 0 | AE6: 0
A9: State EV Subsidy Amounts
A10: This list only includes rebates on the EV itself, not on charging equipment.
A11: It also omits states that do not offer a rebate but do exempt EVs from sales, use, or excise taxes.
A12: State Rebates + Tax Credits Updated 1/30/25
A13: TC | C13: https://www.energysage.com/electric-vehicles/costs-and-benefits-evs/ev-tax-credits/
A14: Rebates | C14: https://www.tesla.com/support/incentives
A15: Note: Could be an optimistic estimate
A16: State | B16: Population, millions (June 2022) | C16: Category | D16: 2020 | E16: =D16+1 -> 2021 | F16: =E16+1 -> 2022 | G16: =F16+1 -> 2023 | H16: =G16+1 -> 2024 | I16: =H16+1 -> 2025 | J16: =I16+1 -> 2026 | K16: data 1 | L16: data 2
A17: CO | B17: 5.685 | C17: LDV | D17: =2000*D76+4000*(1-D76) -> 3506.6 | E17: =1500*E76+2500*(1-E76) -> 2190.8 | F17: =1500*F76+2500*(1-F76) -> 2359 | G17: =0.5*(1500*G76+2500*(1-G76))+0.5*(5000) -> 3641.35 | H17: 5000 | I17: 3500 | J17: =I17 -> 3500 | K17: https://tax.colorado.gov/sites/tax/files/documents/ITT_Innovative_Motor_Vehicle_Credit_Feb_2024.pdf
A18: CT | B18: 3.571 | C18: LDV | D18: =613500/(7880-5480) -> 255.625 | E18: =1079750/(12513-7880) -> 233.05633 | F18: =1468250/(18509-12513) -> 244.87158 | G18: =7744000/(27709-18509) -> 841.73913 | H18: =11982750/(27146*27709/44313) -> 705.92889 | I18: =H18*1500/2250 -> 470.61926 | J18: =I18 -> 470.61926 | K18: https://portal.ct.gov/ceq/ar-23-gold/2023-ceq-annual-report-ebook/personal-impact---waste-diversion/transportation | L18: https://portal.ct.gov/ceq/ar-23-gold/2023-ceq-annual-report-ebook/personal-impact---waste-diversion/transportation | R18: https://afdc.energy.gov/laws/11609
A19: DE | B19: 0.968 | C19: LDV | D19: =852000/311 -> 2739.5498 | E19: =2500 -> 2500 | F19: =2500 -> 2500 | G19: =2500 -> 2500 | H19: =2500 -> 2500 | I19: =2500 -> 2500 | J19: =2500 -> 2500 | K19: https://data.delaware.gov/Energy-and-Environment/State-Rebates-for-Alternative-Fuel-Vehicles/8z8z-di7f/explore
A20: NY | B20: 8.38 | C20: LDV | D20: =17436700/10692 -> 1630.8174 | E20: =18953100/20836 -> 909.63237 | F20: =16215000/28241 -> 574.16522 | G20: =26945500/48746 -> 552.77356 | H20: =19221500/54664 -> 351.62996 | I20: =H20 -> 351.62996 | J20: =I20 -> 351.62996 | K20: https://www.nyserda.ny.gov/All-Programs/Drive-Clean-Rebate-For-Electric-Cars-Program/Rebate-Data/Rebate-Stats | L20: https://www.nyserda.ny.gov/All-Programs/Drive-Clean-Rebate-For-Electric-Cars-Program/Rebate-Data/Map-of-EV-Registrations
A21: TX | B21: 28.64 | C21: LDV | D21: 2500 | E21: 0 | F21: 0 | G21: 0 | H21: 0 | I21: 0 | J21: 0 | K21: Note: only 1 year program
A22: CA | B22: 39.35 | C22: LDV | D22: =80255483/(100377+5569) -> 757.5131 | E22: =103494583/(152400+7866) -> 645.76756 | F22: =88529166/(256315+5761) -> 337.79959 | G22: =310602850/(371002+3666) -> 829.00822 | H22: 0 | I22: 0 | J22: 0 | K22: https://cleanvehiclerebate.org/en/rebate-statistics | L22: https://www.energy.ca.gov/data-reports/energy-almanac/zero-emission-vehicle-and-infrastructure-statistics-collection/new-zev
A23: LA | B23: 4.665 | C23: LDV | D23: 0 | E23: 0 | F23: 0 | G23: 0 | H23: 0 | I23: 0 | J23: 0 | K23: Note: value was previously 1500 but after digging I don’t believe LA has ever had a state tax credit
A24: ME | B24: 1.341 | C24: LDV | D24: 2000 | E24: 2000 | F24: 2000 | G24: 2000 | H24: 2000 | I24: 0 | J24: 0 | K24: suspended all ev rebate programs starting in 2024
A25: MN | B25: 5.717 | C25: LDV | D25: 0 | E25: 0 | F25: 0 | G25: 2500 | H25: 2500 | I25: 0 | J25: 0 | K25: no longer funds program
A26: MD | B26: 6.038 | C26: LDV | D26: 2500 | E26: 2500 | F26: 2500 | G26: 3000 | H26: 3000 | I26: 3000 | J26: 3000
A27: MA | B27: 6.873 | C27: LDV | D27: 2500 | E27: 2500 | F27: 2500 | G27: 3500 | H27: 3500 | I27: 3500 | J27: 3500
A28: PA | B28: =500/10^6 -> 0.0005 | C28: LDV | D28: 0 | E28: 0 | F28: 0 | G28: 3000 | H28: 3000 | I28: 3000 | J28: 3000 | K28: Note; renewed on annual basis, only for first 500
A29: RI | B29: 1.094 | C29: LDV | D29: 0 | E29: 0 | F29: 1500 | G29: 1500 | H29: 1500 | I29: 1500 | J29: 1500
A30: NJ | B30: 8.885 | C30: LDV | D30: 2000 | E30: 2000 | F30: 2000 | G30: 2000 | H30: 2000 | I30: 2000 | J30: 2000 | K30: up to 4k if low income
A31: OR | B31: 4.176 | C31: LDV | D31: =9294500/3753 -> 2476.5521 | E31: =14303500/7764 -> 1842.2849 | F31: =19442500/12379 -> 1570.6034 | G31: =13295000/19790 -> 671.80394 | H31: =G31 -> 671.80394 | I31: =H31 -> 671.80394 | J31: =I31 -> 671.80394 | K31: https://evrebate.oregon.gov/rebate-statistics | L31: https://www.oregon.gov/energy/Data-and-Reports/Pages/Oregon-Electric-Vehicle-Dashboard.aspx
A32: VT | B32: 0.624 | C32: LDV | D32: 2200 | E32: 2200 | F32: 2200 | G32: 2200 | H32: 2200 | I32: 2200 | J32: 2200 | K32: up to 3.2k if low income
A33: Rest of country | B33: =B34-SUM(B17:B32) -> 203.4925 | D33: 0 | E33: 0 | F33: 0 | G33: 0 | H33: 0 | I33: 0 | J33: 0
A34: USA | B34: 329.5
A36: PHEV Subsidies | B36: Population, millions (June 2022) | C36: Category | D36: 2020 | E36: =D36+1 -> 2021 | F36: =E36+1 -> 2022 | G36: =F36+1 -> 2023 | H36: =G36+1 -> 2024 | I36: =H36+1 -> 2025 | J36: =I36+1 -> 2026
A37: CO | B37: 5.685 | C37: LDV | D37: =D17 -> 3506.6 | E37: =E17 -> 2190.8 | F37: =F17 -> 2359 | G37: =G17 -> 3641.35 | H37: =H17 -> 5000 | I37: =I17 -> 3500 | J37: =J17 -> 3500
A38: CT | B38: 3.571 | C38: LDV | D38: =128000/255 -> 501.96078 | E38: =537750/(8827-5893) -> 183.28221 | F38: =412000/(11615-8827) -> 147.77618 | G38: =512500/(16517-11615) -> 104.54916 | H38: =685000/(27146*16517/44313) -> 67.699383 | I38: =H38 -> 67.699383 | J38: =I38 -> 67.699383
A39: DE | B39: 0.968 | C39: LDV | D39: =104500/97 -> 1077.3196 | E39: 1000 | F39: 1000 | G39: 1000 | H39: 1000 | I39: 1000 | J39: 1000
A40: NY | B40: 8.38 | C40: LDV | D40: =4684500/6464 -> 724.70606 | E40: =9996000/14360 -> 696.10028 | F40: =5049700/14312 -> 352.82979 | G40: =8627000/30164 -> 286.00318 | H40: =7694000/35557 -> 216.38496 | I40: =H40 -> 216.38496 | J40: =I40 -> 216.38496
A41: TX | B41: 28.64 | C41: LDV | D41: 2500 | E41: 0 | F41: 0 | G41: 0 | H41: 0 | I41: 0 | J41: 0
A42: CA | B42: 39.35 | C42: LDV | D42: =12007419/38153 -> 314.71756 | E42: =10067604/53090 -> 189.63277 | F42: =3681500/(43689) -> 84.266062 | G42: =8757316/(63496) -> 137.91918 | H42: 0 | I42: 0 | J42: 0
A43: LA | B43: 4.665 | C43: LDV | D43: 0 | E43: 0 | F43: 0 | G43: 0 | H43: 0 | I43: 0 | J43: 0
A44: ME | B44: 1.341 | C44: LDV | D44: 1000 | E44: 1000 | F44: 1000 | G44: 1000 | H44: 1000 | I44: 0 | J44: 0
A45: MN | B45: 5.717 | C45: LDV | D45: 0 | E45: 0 | F45: 0 | G45: 2500 | H45: 2500 | I45: 0 | J45: 0
A46: MD | B46: 6.038 | C46: LDV | D46: 2500 | E46: 2500 | F46: 2500 | G46: 3000 | H46: 3000 | I46: 3000 | J46: 3000
A47: MA | B47: 6.873 | C47: LDV | D47: 2500 | E47: 2500 | F47: 2500 | G47: =G27*0.5 -> 1750 | H47: 0 | I47: 0 | J47: 0
A48: PA | B48: =500/10^6 -> 0.0005 | C48: LDV | D48: 0 | E48: 0 | F48: 0 | G48: 1500 | H48: 1500 | I48: 1500 | J48: 1500
A49: RI | B49: 1.094 | C49: LDV | D49: 0 | E49: 0 | F49: 1000 | G49: 1000 | H49: 1000 | I49: 1000 | J49: 1000
A50: NJ | B50: 8.885 | C50: LDV | D50: 2000 | E50: 2000 | F50: 2000 | G50: 0 | H50: 0 | I50: 0 | J50: 0
A51: OR | B51: 4.176 | C51: LDV | D51: =1843000/1494 -> 1233.6011 | E51: =4828500/4476 -> 1078.7534 | F51: =5495500/4897 -> 1122.2177 | G51: =2876000/6464 -> 444.92574 | H51: =G51 -> 444.92574 | I51: =H51 -> 444.92574 | J51: =I51 -> 444.92574
A52: VT | B52: 0.624 | C52: LDV | D52: 1000 | E52: 1000 | F52: 1000 | G52: 1000 | H52: 1000 | I52: 1000 | J52: 1000
A53: Rest of country | B53: =B54-SUM(B37:B52) -> 203.4925 | D53: 0 | E53: 0 | F53: 0 | G53: 0 | H53: 0 | I53: 0 | J53: 0
A54: USA | B54: 329.5
A59: 2022 to 2012 $ | B59: 0.785
A61: Pop-Weighted State Avg Tax Credit (2012$)
C62: 2021 | D62: 2022 | E62: 2023 | F62: 2024 | G62: 2025 | H62: 2026 | I62: 2027 | J62: 2028 | K62: 2029 | L62: 2030 | M62: 2031 | N62: 2032 | O62: 2033 | P62: 2034 | Q62: 2035 | R62: 2036 | S62: 2037 | T62: 2038 | U62: 2039 | V62: 2040 | W62: 2041 | X62: 2042 | Y62: 2043 | Z62: 2044 | AA62: 2045 | AB62: 2046 | AC62: 2047 | AD62: 2048 | AE62: 2049 | AF62: 2050
A63: battery electric vehicles | C63: =SUMPRODUCT(E17:E33,$B$17:$B$33)/SUM($B$17:$B$33)*L79 -> 284.24237 | D63: =SUMPRODUCT(F17:F33,$B$17:$B$33)/SUM($B$17:$B$33)*M79 -> 231.21682 | E63: =SUMPRODUCT(G17:G33,$B$17:$B$33)/SUM($B$17:$B$33)*N79 -> 334.13794 | F63: =SUMPRODUCT(H17:H33,$B$17:$B$33)/SUM($B$17:$B$33)*O79 -> 264.43889 | G63: =SUMPRODUCT(I17:I33,$B$17:$B$33)/SUM($B$17:$B$33)*P79 -> 199.92713 | H63: =SUMPRODUCT(J17:J33,$B$17:$B$33)/SUM($B$17:$B$33)*Q79 -> 194.10401 | I63: =H63*R79/Q79 -> 188.45049 | J63: =I63*S79/R79 -> 182.96164 | K63: =J63*T79/S79 -> 177.63266 | L63: =K63*U79/T79 -> 172.4589 | M63: =L63*V79/U79 -> 167.43582 | N63: =M63*W79/V79 -> 162.55905 | O63: =N63*X79/W79 -> 157.82432 | P63: =O63*Y79/X79 -> 153.2275 | Q63: =P63*Z79/Y79 -> 148.76456 | R63: 0 | S63: 0 | T63: 0 | U63: 0 | V63: 0 | W63: 0 | X63: 0 | Y63: 0 | Z63: 0 | AA63: 0 | AB63: 0 | AC63: 0 | AD63: 0 | AE63: 0 | AF63: 0
A64: plugin hybrid vehicles | C64: =SUMPRODUCT(E37:E53,$B$37:$B$53)/SUM($B$37:$B$53)*L79 -> 215.72168 | D64: =SUMPRODUCT(F37:F53,$B$37:$B$53)/SUM($B$37:$B$53)*M79 -> 188.02811 | E64: =SUMPRODUCT(G37:G53,$B$37:$B$53)/SUM($B$37:$B$53)*N79 -> 181.15699 | F64: =SUMPRODUCT(H37:H53,$B$37:$B$53)/SUM($B$37:$B$53)*O79 -> 152.76347 | G64: =SUMPRODUCT(I37:I53,$B$37:$B$53)/SUM($B$37:$B$53)*P79 -> 96.208552 | H64: =SUMPRODUCT(J37:J53,$B$37:$B$53)/SUM($B$37:$B$53)*Q79 -> 93.406361 | I64: =H64*R79/Q79 -> 90.685788 | J64: =I64*S79/R79 -> 88.044454 | K64: =J64*T79/S79 -> 85.480052 | L64: =K64*U79/T79 -> 82.990342 | M64: =L64*V79/U79 -> 80.573148 | N64: =M64*W79/V79 -> 78.226357 | O64: =N64*X79/W79 -> 75.947919 | P64: =O64*Y79/X79 -> 73.735844 | Q64: =P64*Z79/Y79 -> 71.588198 | R64: 0 | S64: 0 | T64: 0 | U64: 0 | V64: 0 | W64: 0 | X64: 0 | Y64: 0 | Z64: 0 | AA64: 0 | AB64: 0 | AC64: 0 | AD64: 0 | AE64: 0 | AF64: 0
A66: Total Tax Credit (2012$)
C67: 2021 | D67: 2022 | E67: 2023 | F67: 2024 | G67: 2025 | H67: 2026 | I67: 2027 | J67: 2028 | K67: 2029 | L67: 2030 | M67: 2031 | N67: 2032 | O67: 2033 | P67: 2034 | Q67: 2035 | R67: 2036 | S67: 2037 | T67: 2038 | U67: 2039 | V67: 2040 | W67: 2041 | X67: 2042 | Y67: 2043 | Z67: 2044 | AA67: 2045 | AB67: 2046 | AC67: 2047 | AD67: 2048 | AE67: 2049 | AF67: 2050
A68: battery electric vehicles | C68: =B5+C63 -> 1930.7405 | D68: =C5+D63 -> 1599.8026 | E68: =D5+E63 -> 5130.1016 | F68: =E5+F63 -> 3819.9266 | G68: =F5+G63 -> 3565.6148 | H68: =G5+H63 -> 3312.3287 | I68: =H5+I63 -> 2579.6281 | J68: =I5+J63 -> 2607.4716 | ... AF68: =AE5+AF63 -> 0
A69: plugin hybrid vehicles | C69: =B6+C64 -> 6868.4402 | D69: =C6+D64 -> 3805.0788 | E69: =D6+E64 -> 3662.3553 | F69: =E6+F64 -> 2999.2858 | G69: =F6+G64 -> 2492.4252 | H69: =G6+H64 -> 2355.686 | I69: =H6+I64 -> 2224.0662 | J69: =I6+J64 -> 2167.4924 | ... AF69: =AE6+AF64 -> 0
D73: US average share of EVs leased vs purchased
D74: https://www.experian.com/blogs/ask-experian/electric-vehicle-trends/
D75: 2020 | E75: 2021 | F75: 2022 | G75: 2023 | H75: 2024 | I75: 2025 | J75: 2026
D76: 0.2467 | E76: 0.3092 | F76: 0.141 | G76: 0.2173 | H76: 0.4656 | I76: =H76 -> 0.4656 | J76: =I76 -> 0.4656
C78: 2012 | D78: 2013 | E78: 2014 | F78: 2015 | G78: 2016 | H78: 2017 | I78: 2018 | J78: 2019 | K78: 2020 | L78: 2021 | M78: 2022 | N78: 2023 | O78: 2024 | P78: 2025 | Q78: 2026 | R78: 2027 | S78: 2028 | T78: 2029 | U78: 2030 | V78: 2031 | W78: 2032 | X78: 2033 | Y78: 2034 | Z78: 2035
B79: Inflation adjuster | C79: {=TRANSPOSE(G84:G107)} -> 1 | D79: 0.98556386 | E79: 0.96983137 | F79: 0.96868157 | G79: 0.95661377 | H79: 0.9366596 | I79: 0.91432736 | J79: 0.89805482 | K79: 0.88711067 | L79: 0.84730413 | M79: 0.78452102 | N79: 0.75350342 | O79: 0.73191601 | P79: 0.71059806 | Q79: 0.68990103 | R79: 0.66980683 | S79: 0.65029789 | T79: 0.63135718 | U79: 0.61296813 | V79: 0.59511469 | W79: 0.57778125 | X79: 0.56095267 | Y79: 0.54461425 | Z79: 0.5287517
A82: Inflation Historical Data and Assumptions | D82: Future inflation assumption: | G82: 0.03
A84: 2012............................................................................. . | B84: 228.85 | C84: 230.338 | D84: 229.594 | E84: 1.7 | F84: 2.1 | G84: 1
A85: 2013............................................................................. . | B85: 232.366 | C85: 233.548 | D85: 232.957 | E85: 1.5 | F85: 1.5 | G85: 0.98556386
A86: 2014............................................................................. . | B86: 236.384 | C86: 237.088 | D86: 236.736 | E86: 0.8 | F86: 1.6 | G86: 0.96983137
A87: 2015............................................................................. . | B87: 236.265 | C87: 237.769 | D87: 237.017 | E87: 0.7 | F87: 0.1 | G87: 0.96868157
A88: 2016............................................................................. . | B88: 238.778 | C88: 241.237 | D88: 240.007 | E88: 2.1 | F88: 1.3 | G88: 0.95661377
A89: 2017............................................................................. . | B89: 244.076 | C89: 246.163 | D89: 245.12 | E89: 2.1 | F89: 2.1 | G89: 0.9366596
A90: 2018............................................................................. . | B90: 250.089 | C90: 252.125 | D90: 251.107 | E90: 1.9 | F90: 2.4 | G90: 0.91432736
A91: 2019............................................................................. . | B91: 254.412 | C91: 256.903 | D91: 255.657 | E91: 2.3 | F91: 1.8 | G91: 0.89805482
A92: 2020............................................................................. . | B92: 257.557 | C92: 260.065 | D92: 258.811 | E92: 1.4 | F92: 1.2 | G92: 0.88711067
A93: 2021............................................................................. . | B93: 266.236 | C93: 275.703 | D93: 270.97 | E93: 7 | F93: 4.7 | G93: 0.84730413
A94: 2022............................................................................. . | B94: 288.347 | C94: 296.963 | D94: 292.655 | E94: 6.5 | F94: 8 | G94: 0.78452102
A95: 2023............................................................................. . | B95: 302.408 | C95: 306.996 | D95: 304.702 | G95: 0.75350342
A96: 2024............................................................................. . | B96: 312.145 | C96: 315.233 | D96: 313.689 | G96: 0.73191601
A97: 2025 | D97: =D96*(1+F97) -> 323.09967 | F97: =G$82 -> 0.03 | G97: =D$84/D97 -> 0.71059806
A98: 2026 | D98: =D97*(1+F98) -> 332.79266 | F98: =G$82 -> 0.03 | G98: =D$84/D98 -> 0.68990103
A99: 2027 | D99: =D98*(1+F99) -> 342.77644 | F99: =G$82 -> 0.03 | G99: =D$84/D99 -> 0.66980683
A100: 2028 | D100: =D99*(1+F100) -> 353.05973 | F100: =G$82 -> 0.03 | G100: =D$84/D100 -> 0.65029789
A101: 2029 | D101: =D100*(1+F101) -> 363.65153 | F101: =G$82 -> 0.03 | G101: =D$84/D101 -> 0.63135718
A102: 2030 | D102: =D101*(1+F102) -> 374.56107 | F102: =G$82 -> 0.03 | G102: =D$84/D102 -> 0.61296813
A103: 2031 | D103: =D102*(1+F103) -> 385.7979 | F103: =G$82 -> 0.03 | G103: =D$84/D103 -> 0.59511469
A104: 2032 | D104: =D103*(1+F104) -> 397.37184 | F104: =G$82 -> 0.03 | G104: =D$84/D104 -> 0.57778125
A105: 2033 | D105: =D104*(1+F105) -> 409.293 | F105: =G$82 -> 0.03 | G105: =D$84/D105 -> 0.56095267
A106: 2034 | D106: =D105*(1+F106) -> 421.57179 | F106: =G$82 -> 0.03 | G106: =D$84/D106 -> 0.54461425
A107: 2035 | D107: =D106*(1+F107) -> 434.21894 | F107: =G$82 -> 0.03 | G107: =D$84/D107 -> 0.5287517

Sheet Commercial Vehicles
A1: Methodology:
A2: For commercial vehicle credits, we find that the credit caps of $7,500 for vehicles under 14,000 pounds or $40,000 for vehicles over 14,000 pounds apply in all years. We apply the credit to all new sales of commercial trucks, using a weighted average credit value for our freight LDV category which covers both light and medium duty trucks. We also apply the credit to a fraction of buses, excluding buses purchased by the government. The credit runs from 2023-2032.
A4: Commercial Vehicle Credit (2022 $) | B4: 40000
A5: Passenger Vehicle Credit (2022 $) | B5: 7500
B7: 2023 | C7: 2024 | D7: 2025 | E7: 2026 | F7: 2027 | G7: 2028 | H7: 2029 | I7: 2030 | J7: 2031 | K7: 2032
A8: Psgr HDV (2012 $) | B8: =$B4*$B$16*C$14 -> 25920.518 | C8: =$B4*$B$16*D$14 -> 25177.911 | D8: =$B4*$B$16*E$14 -> 24444.573 | E8: =$B4*$B$16*F$14 -> 23732.596 | F8: =$B4*$B$16*G$14 -> 23041.355 | G8: =$B4*$B$16*H$14 -> 22370.247 | H8: =$B4*$B$16*I$14 -> 21718.687 | I8: =$B4*$B$16*J$14 -> 21086.104 | ... K8: =$B4*$B$16*L$14 -> 19875.675
A9: Freight HDV (2012 $) | B9: =$B$4*C14 -> 30140.137 | C9: =$B$4*D14 -> 29276.64 | D9: =$B$4*E14 -> 28423.923 | E9: =$B$4*F14 -> 27596.041 | F9: =$B$4*G14 -> 26792.273 | G9: =$B$4*H14 -> 26011.916 | H9: =$B$4*I14 -> 25254.287 | I9: =$B$4*J14 -> 24518.725 | ... K9: =$B$4*L14 -> 23111.25
A10: Frgt LDV (2012 $) | B10: =C36 -> 9715.071 | C10: =D36 -> 9379.5013 | D10: =E36 -> 9098.1571 | E10: =F36 -> 8900.5394 | F10: =G36 -> 8762.1956 | G10: =H36 -> 8574.6386 | H10: =I36 -> 8327.2184 | I10: =J36 -> 8038.2687 | ... K10: =L36 -> 7566.1942
A12: Calculations:
B13: 2022 | C13: 2023 | D13: 2024 | E13: 2025 | F13: 2026 | G13: 2027 | H13: 2028 | I13: 2029 | J13: 2030 | K13: 2031 | L13: 2032
A14: Conversion to 2012$ | B14: {=TRANSPOSE('Passenger Vehicle Calculations'!G94:G104)} -> 0.78452102 | C14: 0.75350342 | D14: 0.73191601 | E14: 0.71059806 | F14: 0.68990103 | G14: 0.66980683 | H14: 0.65029789 | I14: 0.63135718 | J14: 0.61296813 | K14: 0.59511469 | L14: 0.57778125
A16: Fraction of buses owned by private entities (see trans/FoVObE) | B16: 0.86
A19: The credit caps are $7,500 for vehicles under 14,000 lbs and $40,000 for vehicles over 14,000 lbs (class 4 and above). We need to calculate
A20: a weighted average credit for our freight LDV category, which includes vehicle classes 2b-6.
A22: AEO classifications (see AEO table footnotes) | B22: Class | C22: Weight | D22: Credit Amount (2012 $)
A23: Commercial light trucks | B23: 2b | C23: 8,501-10,000 lbs | D23: =B5*B14 -> 5883.9077
A24: Light Medium trucks | B24: 3 | C24: 10,001-14,000 lbs | D24: =D23 -> 5883.9077
A25: Medium trucks | B25: 44657 | C25: 14,001-26,000 lbs | D25: =B4*B14 -> 31380.841
A27: Weighted Average calculated relative to AEO sales
A28: Source: EIA AEO 2023, Tables 44 and 49
A30: Sales (thousands)
A31: AEO 2023 | B31: 2022 | C31: 2023 | D31: 2024 | E31: 2025 | F31: 2026 | G31: 2027 | H31: 2028 | I31: 2029 | J31: 2030 | K31: 2031 | L31: 2032
A32: Total Commercial Light Truck Sales | B32: 652.15881 | C32: 675.13666 | D32: 689.60468 | E32: 691.51691 | F32: 688.42426 | G32: 684.18414 | H32: 682.62189 | I32: 679.86218 | J32: 678.07776 | K32: 677.36639 | L32: 675.92621
A33: Light Medium Subtotal | B33: 252.12297 | C33: 262.19943 | D33: 276.18127 | E33: 286.01892 | F33: 290.46655 | G33: 292.4324 | H33: 293.63425 | I33: 296.17325 | J33: 298.1217 | K33: 300.39685 | L33: 303.25729
A34: Medium Subtotal | B34: 180.61983 | C34: 186.4935 | D34: 188.82283 | E34: 190.62694 | F34: 195.10698 | G34: 202.50728 | H34: 207.00558 | I34: 207.12138 | J34: 203.82384 | K34: 201.78429 | L34: 203.63635
A36: Weighted Average Credit | B36: =SUMPRODUCT(B32:B34,$D$23:$D$25)/SUM(B32:B34) -> 10128.764 | C36: =SUMPRODUCT(C32:C34,$D$23:$D$25)/SUM(C32:C34)*C14/$B$14 -> 9715.071 | D36: =SUMPRODUCT(D32:D34,$D$23:$D$25)/SUM(D32:D34)*D14/$B$14 -> 9379.5013 | E36: =SUMPRODUCT(E32:E34,$D$23:$D$25)/SUM(E32:E34)*E14/$B$14 -> 9098.1571 | F36: =SUMPRODUCT(F32:F34,$D$23:$D$25)/SUM(F32:F34)*F14/$B$14 -> 8900.5394 | G36: =SUMPRODUCT(G32:G34,$D$23:$D$25)/SUM(G32:G34)*G14/$B$14 -> 8762.1956 | H36: =SUMPRODUCT(H32:H34,$D$23:$D$25)/SUM(H32:H34)*H14/$B$14 -> 8574.6386 | I36: =SUMPRODUCT(I32:I34,$D$23:$D$25)/SUM(I32:I34)*I14/$B$14 -> 8327.2184 | J36: =SUMPRODUCT(J32:J34,$D$23:$D$25)/SUM(J32:J34)*J14/$B$14 -> 8038.2687 | ... L36: =SUMPRODUCT(L32:L34,$D$23:$D$25)/SUM(L32:L34)*L14/$B$14 -> 7566.1942

Sheet psgr

Sheet BVS-psgr-LDVs
A1: Subsidy (2012 USD) | B1: 2021 | C1: 2022 | D1: 2023 | E1: 2024 | F1: 2025 | G1: 2026 | H1: 2027 | I1: 2028 | J1: 2029 | K1: 2030 | L1: 2031 | M1: 2032 | N1: 2033 | O1: 2034 | P1: 2035 | Q1: 2036 | R1: 2037 | S1: 2038 | T1: 2039 | U1: 2040 | V1: 2041 | W1: 2042 | X1: 2043 | Y1: 2044 | Z1: 2045 | AA1: 2046 | AB1: 2047 | AC1: 2048 | AD1: 2049 | AE1: 2050
A2: battery electric vehicle | B2: ='Passenger Vehicle Calculations'!C68 -> 1930.7405 | C2: ='Passenger Vehicle Calculations'!D68 -> 1599.8026 | D2: ='Passenger Vehicle Calculations'!E68 -> 5130.1016 | E2: ='Passenger Vehicle Calculations'!F68 -> 3819.9266 | F2: ='Passenger Vehicle Calculations'!G68 -> 3565.6148 | G2: ='Passenger Vehicle Calculations'!H68 -> 3312.3287 | H2: ='Passenger Vehicle Calculations'!I68 -> 2579.6281 | I2: ='Passenger Vehicle Calculations'!J68 -> 2607.4716 | ... AE2: ='Passenger Vehicle Calculations'!AF68 -> 0
A3: natural gas vehicle | B3: 0 | C3: 0 | D3: 0 | E3: 0 | F3: 0 | G3: 0 | H3: 0 | I3: 0 | J3: 0 | K3: 0 | L3: 0 | M3: 0 | N3: 0 | O3: 0 | P3: 0 | Q3: 0 | R3: 0 | S3: 0 | T3: 0 | U3: 0 | V3: 0 | W3: 0 | X3: 0 | Y3: 0 | Z3: 0 | AA3: 0 | AB3: 0 | AC3: 0 | AD3: 0 | AE3: 0
A4: gasoline vehicle | B4: 0 | C4: 0 | D4: 0 | E4: 0 | F4: 0 | G4: 0 | H4: 0 | I4: 0 | J4: 0 | K4: 0 | L4: 0 | M4: 0 | N4: 0 | O4: 0 | P4: 0 | Q4: 0 | R4: 0 | S4: 0 | T4: 0 | U4: 0 | V4: 0 | W4: 0 | X4: 0 | Y4: 0 | Z4: 0 | AA4: 0 | AB4: 0 | AC4: 0 | AD4: 0 | AE4: 0
A5: diesel vehicle | B5: 0 | C5: 0 | D5: 0 | E5: 0 | F5: 0 | G5: 0 | H5: 0 | I5: 0 | J5: 0 | K5: 0 | L5: 0 | M5: 0 | N5: 0 | O5: 0 | P5: 0 | Q5: 0 | R5: 0 | S5: 0 | T5: 0 | U5: 0 | V5: 0 | W5: 0 | X5: 0 | Y5: 0 | Z5: 0 | AA5: 0 | AB5: 0 | AC5: 0 | AD5: 0 | AE5: 0
A6: plugin hybrid vehicle | B6: ='Passenger Vehicle Calculations'!C69 -> 6868.4402 | C6: ='Passenger Vehicle Calculations'!D69 -> 3805.0788 | D6: ='Passenger Vehicle Calculations'!E69 -> 3662.3553 | E6: ='Passenger Vehicle Calculations'!F69 -> 2999.2858 | F6: ='Passenger Vehicle Calculations'!G69 -> 2492.4252 | G6: ='Passenger Vehicle Calculations'!H69 -> 2355.686 | H6: ='Passenger Vehicle Calculations'!I69 -> 2224.0662 | I6: ='Passenger Vehicle Calculations'!J69 -> 2167.4924 | ... AE6: ='Passenger Vehicle Calculations'!AF69 -> 0
A7: LPG vehicle | B7: 0 | C7: 0 | D7: 0 | E7: 0 | F7: 0 | G7: 0 | H7: 0 | I7: 0 | J7: 0 | K7: 0 | L7: 0 | M7: 0 | N7: 0 | O7: 0 | P7: 0 | Q7: 0 | R7: 0 | S7: 0 | T7: 0 | U7: 0 | V7: 0 | W7: 0 | X7: 0 | Y7: 0 | Z7: 0 | AA7: 0 | AB7: 0 | AC7: 0 | AD7: 0 | AE7: 0
A8: hydrogen vehicle | B8: 0 | C8: 0 | D8: =D2 -> 5130.1016 | E8: =E2 -> 3819.9266 | F8: =F2 -> 3565.6148 | G8: =G2 -> 3312.3287 | H8: =H2 -> 2579.6281 | I8: =I2 -> 2607.4716 | J8: =J2 -> 2637.52 | K8: =K2 -> 2669.571 | ... AE8: =AE2 -> 0

Sheet BVS-psgr-HDVs
A1: Subsidy (2012 USD) | B1: 2021 | C1: 2022 | D1: 2023 | E1: 2024 | F1: 2025 | G1: 2026 | H1: 2027 | I1: 2028 | J1: 2029 | K1: 2030 | L1: 2031 | M1: 2032 | N1: 2033 | O1: 2034 | P1: 2035 | Q1: 2036 | R1: 2037 | S1: 2038 | T1: 2039 | U1: 2040 | V1: 2041 | W1: 2042 | X1: 2043 | Y1: 2044 | Z1: 2045 | AA1: 2046 | AB1: 2047 | AC1: 2048 | AD1: 2049 | AE1: 2050
A2: battery electric vehicle | B2: 0 | C2: 0 | D2: ='Commercial Vehicles'!$B4*'Commercial Vehicles'!C14*'Commercial Vehicles'!$B16 -> 25920.518 | E2: ='Commercial Vehicles'!$B4*'Commercial Vehicles'!D14*'Commercial Vehicles'!$B16 -> 25177.911 | F2: ='Commercial Vehicles'!$B4*'Commercial Vehicles'!E14*'Commercial Vehicles'!$B16 -> 24444.573 | G2: ='Commercial Vehicles'!$B4*'Commercial Vehicles'!F14*'Commercial Vehicles'!$B16 -> 23732.596 | H2: ='Commercial Vehicles'!$B4*'Commercial Vehicles'!G14*'Commercial Vehicles'!$B16 -> 23041.355 | I2: ='Commercial Vehicles'!$B4*'Commercial Vehicles'!H14*'Commercial Vehicles'!$B16 -> 22370.247 | J2: ='Commercial Vehicles'!$B4*'Commercial Vehicles'!I14*'Commercial Vehicles'!$B16 -> 21718.687 | K2: ='Commercial Vehicles'!$B4*'Commercial Vehicles'!J14*'Commercial Vehicles'!$B16 -> 21086.104 | ... M2: ='Commercial Vehicles'!$B4*'Commercial Vehicles'!L14*'Commercial Vehicles'!$B16 -> 19875.675 | N2: 0 | O2: 0 | P2: 0 | Q2: 0 | R2: 0 | S2: 0 | T2: 0 | U2: 0 | V2: 0 | W2: 0 | X2: 0 | Y2: 0 | Z2: 0 | AA2: 0 | AB2: 0 | AC2: 0 | AD2: 0 | AE2: 0
A3: natural gas vehicle | B3: 0 | C3: 0 | D3: 0 | E3: 0 | F3: 0 | G3: 0 | H3: 0 | I3: 0 | J3: 0 | K3: 0 | L3: 0 | M3: 0 | N3: 0 | O3: 0 | P3: 0 | Q3: 0 | R3: 0 | S3: 0 | T3: 0 | U3: 0 | V3: 0 | W3: 0 | X3: 0 | Y3: 0 | Z3: 0 | AA3: 0 | AB3: 0 | AC3: 0 | AD3: 0 | AE3: 0
A4: gasoline vehicle | B4: 0 | C4: 0 | D4: 0 | E4: 0 | F4: 0 | G4: 0 | H4: 0 | I4: 0 | J4: 0 | K4: 0 | L4: 0 | M4: 0 | N4: 0 | O4: 0 | P4: 0 | Q4: 0 | R4: 0 | S4: 0 | T4: 0 | U4: 0 | V4: 0 | W4: 0 | X4: 0 | Y4: 0 | Z4: 0 | AA4: 0 | AB4: 0 | AC4: 0 | AD4: 0 | AE4: 0
A5: diesel vehicle | B5: 0 | C5: 0 | D5: 0 | E5: 0 | F5: 0 | G5: 0 | H5: 0 | I5: 0 | J5: 0 | K5: 0 | L5: 0 | M5: 0 | N5: 0 | O5: 0 | P5: 0 | Q5: 0 | R5: 0 | S5: 0 | T5: 0 | U5: 0 | V5: 0 | W5: 0 | X5: 0 | Y5: 0 | Z5: 0 | AA5: 0 | AB5: 0 | AC5: 0 | AD5: 0 | AE5: 0
A6: plugin hybrid vehicle | B6: 0 | C6: 0 | D6: =D2 -> 25920.518 | E6: =E2 -> 25177.911 | F6: =F2 -> 24444.573 | G6: =G2 -> 23732.596 | H6: =H2 -> 23041.355 | I6: =I2 -> 22370.247 | J6: =J2 -> 21718.687 | K6: =K2 -> 21086.104 | ... M6: =M2 -> 19875.675 | N6: 0 | O6: 0 | P6: 0 | Q6: 0 | R6: 0 | S6: 0 | T6: 0 | U6: 0 | V6: 0 | W6: 0 | X6: 0 | Y6: 0 | Z6: 0 | AA6: 0 | AB6: 0 | AC6: 0 | AD6: 0 | AE6: 0
A7: LPG vehicle | B7: 0 | C7: 0 | D7: 0 | E7: 0 | F7: 0 | G7: 0 | H7: 0 | I7: 0 | J7: 0 | K7: 0 | L7: 0 | M7: 0 | N7: 0 | O7: 0 | P7: 0 | Q7: 0 | R7: 0 | S7: 0 | T7: 0 | U7: 0 | V7: 0 | W7: 0 | X7: 0 | Y7: 0 | Z7: 0 | AA7: 0 | AB7: 0 | AC7: 0 | AD7: 0 | AE7: 0
A8: hydrogen vehicle | B8: 0 | C8: 0 | D8: =D2 -> 25920.518 | E8: =E2 -> 25177.911 | F8: =F2 -> 24444.573 | G8: =G2 -> 23732.596 | H8: =H2 -> 23041.355 | I8: =I2 -> 22370.247 | J8: =J2 -> 21718.687 | K8: =K2 -> 21086.104 | ... M8: =M2 -> 19875.675 | N8: 0 | O8: 0 | P8: 0 | Q8: 0 | R8: 0 | S8: 0 | T8: 0 | U8: 0 | V8: 0 | W8: 0 | X8: 0 | Y8: 0 | Z8: 0 | AA8: 0 | AB8: 0 | AC8: 0 | AD8: 0 | AE8: 0

Sheet BVS-psgr-aircraft
A1: Subsidy (2012 USD) | B1: 2021 | C1: 2022 | D1: 2023 | E1: 2024 | F1: 2025 | G1: 2026 | H1: 2027 | I1: 2028 | J1: 2029 | K1: 2030 | L1: 2031 | M1: 2032 | N1: 2033 | O1: 2034 | P1: 2035 | Q1: 2036 | R1: 2037 | S1: 2038 | T1: 2039 | U1: 2040 | V1: 2041 | W1: 2042 | X1: 2043 | Y1: 2044 | Z1: 2045 | AA1: 2046 | AB1: 2047 | AC1: 2048 | AD1: 2049 | AE1: 2050
A2: battery electric vehicle | B2: 0 | C2: 0 | D2: 0 | E2: 0 | F2: 0 | G2: 0 | H2: 0 | I2: 0 | J2: 0 | K2: 0 | L2: 0 | M2: 0 | N2: 0 | O2: 0 | P2: 0 | Q2: 0 | R2: 0 | S2: 0 | T2: 0 | U2: 0 | V2: 0 | W2: 0 | X2: 0 | Y2: 0 | Z2: 0 | AA2: 0 | AB2: 0 | AC2: 0 | AD2: 0 | AE2: 0
A3: natural gas vehicle | B3: 0 | C3: 0 | D3: 0 | E3: 0 | F3: 0 | G3: 0 | H3: 0 | I3: 0 | J3: 0 | K3: 0 | L3: 0 | M3: 0 | N3: 0 | O3: 0 | P3: 0 | Q3: 0 | R3: 0 | S3: 0 | T3: 0 | U3: 0 | V3: 0 | W3: 0 | X3: 0 | Y3: 0 | Z3: 0 | AA3: 0 | AB3: 0 | AC3: 0 | AD3: 0 | AE3: 0
A4: gasoline vehicle | B4: 0 | C4: 0 | D4: 0 | E4: 0 | F4: 0 | G4: 0 | H4: 0 | I4: 0 | J4: 0 | K4: 0 | L4: 0 | M4: 0 | N4: 0 | O4: 0 | P4: 0 | Q4: 0 | R4: 0 | S4: 0 | T4: 0 | U4: 0 | V4: 0 | W4: 0 | X4: 0 | Y4: 0 | Z4: 0 | AA4: 0 | AB4: 0 | AC4: 0 | AD4: 0 | AE4: 0
A5: diesel vehicle | B5: 0 | C5: 0 | D5: 0 | E5: 0 | F5: 0 | G5: 0 | H5: 0 | I5: 0 | J5: 0 | K5: 0 | L5: 0 | M5: 0 | N5: 0 | O5: 0 | P5: 0 | Q5: 0 | R5: 0 | S5: 0 | T5: 0 | U5: 0 | V5: 0 | W5: 0 | X5: 0 | Y5: 0 | Z5: 0 | AA5: 0 | AB5: 0 | AC5: 0 | AD5: 0 | AE5: 0
A6: plugin hybrid vehicle | B6: 0 | C6: 0 | D6: 0 | E6: 0 | F6: 0 | G6: 0 | H6: 0 | I6: 0 | J6: 0 | K6: 0 | L6: 0 | M6: 0 | N6: 0 | O6: 0 | P6: 0 | Q6: 0 | R6: 0 | S6: 0 | T6: 0 | U6: 0 | V6: 0 | W6: 0 | X6: 0 | Y6: 0 | Z6: 0 | AA6: 0 | AB6: 0 | AC6: 0 | AD6: 0 | AE6: 0
A7: LPG vehicle | B7: 0 | C7: 0 | D7: 0 | E7: 0 | F7: 0 | G7: 0 | H7: 0 | I7: 0 | J7: 0 | K7: 0 | L7: 0 | M7: 0 | N7: 0 | O7: 0 | P7: 0 | Q7: 0 | R7: 0 | S7: 0 | T7: 0 | U7: 0 | V7: 0 | W7: 0 | X7: 0 | Y7: 0 | Z7: 0 | AA7: 0 | AB7: 0 | AC7: 0 | AD7: 0 | AE7: 0
A8: hydrogen vehicle | B8: 0 | C8: 0 | D8: 0 | E8: 0 | F8: 0 | G8: 0 | H8: 0 | I8: 0 | J8: 0 | K8: 0 | L8: 0 | M8: 0 | N8: 0 | O8: 0 | P8: 0 | Q8: 0 | R8: 0 | S8: 0 | T8: 0 | U8: 0 | V8: 0 | W8: 0 | X8: 0 | Y8: 0 | Z8: 0 | AA8: 0 | AB8: 0 | AC8: 0 | AD8: 0 | AE8: 0

Sheet BVP-psgr-rail
A1: Subsidy (2012 USD) | B1: 2021 | C1: 2022 | D1: 2023 | E1: 2024 | F1: 2025 | G1: 2026 | H1: 2027 | I1: 2028 | J1: 2029 | K1: 2030 | L1: 2031 | M1: 2032 | N1: 2033 | O1: 2034 | P1: 2035 | Q1: 2036 | R1: 2037 | S1: 2038 | T1: 2039 | U1: 2040 | V1: 2041 | W1: 2042 | X1: 2043 | Y1: 2044 | Z1: 2045 | AA1: 2046 | AB1: 2047 | AC1: 2048 | AD1: 2049 | AE1: 2050
A2: battery electric vehicle | B2: 0 | C2: 0 | D2: 0 | E2: 0 | F2: 0 | G2: 0 | H2: 0 | I2: 0 | J2: 0 | K2: 0 | L2: 0 | M2: 0 | N2: 0 | O2: 0 | P2: 0 | Q2: 0 | R2: 0 | S2: 0 | T2: 0 | U2: 0 | V2: 0 | W2: 0 | X2: 0 | Y2: 0 | Z2: 0 | AA2: 0 | AB2: 0 | AC2: 0 | AD2: 0 | AE2: 0
A3: natural gas vehicle | B3: 0 | C3: 0 | D3: 0 | E3: 0 | F3: 0 | G3: 0 | H3: 0 | I3: 0 | J3: 0 | K3: 0 | L3: 0 | M3: 0 | N3: 0 | O3: 0 | P3: 0 | Q3: 0 | R3: 0 | S3: 0 | T3: 0 | U3: 0 | V3: 0 | W3: 0 | X3: 0 | Y3: 0 | Z3: 0 | AA3: 0 | AB3: 0 | AC3: 0 | AD3: 0 | AE3: 0
A4: gasoline vehicle | B4: 0 | C4: 0 | D4: 0 | E4: 0 | F4: 0 | G4: 0 | H4: 0 | I4: 0 | J4: 0 | K4: 0 | L4: 0 | M4: 0 | N4: 0 | O4: 0 | P4: 0 | Q4: 0 | R4: 0 | S4: 0 | T4: 0 | U4: 0 | V4: 0 | W4: 0 | X4: 0 | Y4: 0 | Z4: 0 | AA4: 0 | AB4: 0 | AC4: 0 | AD4: 0 | AE4: 0
A5: diesel vehicle | B5: 0 | C5: 0 | D5: 0 | E5: 0 | F5: 0 | G5: 0 | H5: 0 | I5: 0 | J5: 0 | K5: 0 | L5: 0 | M5: 0 | N5: 0 | O5: 0 | P5: 0 | Q5: 0 | R5: 0 | S5: 0 | T5: 0 | U5: 0 | V5: 0 | W5: 0 | X5: 0 | Y5: 0 | Z5: 0 | AA5: 0 | AB5: 0 | AC5: 0 | AD5: 0 | AE5: 0
A6: plugin hybrid vehicle | B6: 0 | C6: 0 | D6: 0 | E6: 0 | F6: 0 | G6: 0 | H6: 0 | I6: 0 | J6: 0 | K6: 0 | L6: 0 | M6: 0 | N6: 0 | O6: 0 | P6: 0 | Q6: 0 | R6: 0 | S6: 0 | T6: 0 | U6: 0 | V6: 0 | W6: 0 | X6: 0 | Y6: 0 | Z6: 0 | AA6: 0 | AB6: 0 | AC6: 0 | AD6: 0 | AE6: 0
A7: LPG vehicle | B7: 0 | C7: 0 | D7: 0 | E7: 0 | F7: 0 | G7: 0 | H7: 0 | I7: 0 | J7: 0 | K7: 0 | L7: 0 | M7: 0 | N7: 0 | O7: 0 | P7: 0 | Q7: 0 | R7: 0 | S7: 0 | T7: 0 | U7: 0 | V7: 0 | W7: 0 | X7: 0 | Y7: 0 | Z7: 0 | AA7: 0 | AB7: 0 | AC7: 0 | AD7: 0 | AE7: 0
A8: hydrogen vehicle | B8: 0 | C8: 0 | D8: 0 | E8: 0 | F8: 0 | G8: 0 | H8: 0 | I8: 0 | J8: 0 | K8: 0 | L8: 0 | M8: 0 | N8: 0 | O8: 0 | P8: 0 | Q8: 0 | R8: 0 | S8: 0 | T8: 0 | U8: 0 | V8: 0 | W8: 0 | X8: 0 | Y8: 0 | Z8: 0 | AA8: 0 | AB8: 0 | AC8: 0 | AD8: 0 | AE8: 0

Sheet BVS-psgr-ships
A1: Subsidy (2012 USD) | B1: 2021 | C1: 2022 | D1: 2023 | E1: 2024 | F1: 2025 | G1: 2026 | H1: 2027 | I1: 2028 | J1: 2029 | K1: 2030 | L1: 2031 | M1: 2032 | N1: 2033 | O1: 2034 | P1: 2035 | Q1: 2036 | R1: 2037 | S1: 2038 | T1: 2039 | U1: 2040 | V1: 2041 | W1: 2042 | X1: 2043 | Y1: 2044 | Z1: 2045 | AA1: 2046 | AB1: 2047 | AC1: 2048 | AD1: 2049 | AE1: 2050
A2: battery electric vehicle | B2: 0 | C2: 0 | D2: 0 | E2: 0 | F2: 0 | G2: 0 | H2: 0 | I2: 0 | J2: 0 | K2: 0 | L2: 0 | M2: 0 | N2: 0 | O2: 0 | P2: 0 | Q2: 0 | R2: 0 | S2: 0 | T2: 0 | U2: 0 | V2: 0 | W2: 0 | X2: 0 | Y2: 0 | Z2: 0 | AA2: 0 | AB2: 0 | AC2: 0 | AD2: 0 | AE2: 0
A3: natural gas vehicle | B3: 0 | C3: 0 | D3: 0 | E3: 0 | F3: 0 | G3: 0 | H3: 0 | I3: 0 | J3: 0 | K3: 0 | L3: 0 | M3: 0 | N3: 0 | O3: 0 | P3: 0 | Q3: 0 | R3: 0 | S3: 0 | T3: 0 | U3: 0 | V3: 0 | W3: 0 | X3: 0 | Y3: 0 | Z3: 0 | AA3: 0 | AB3: 0 | AC3: 0 | AD3: 0 | AE3: 0
A4: gasoline vehicle | B4: 0 | C4: 0 | D4: 0 | E4: 0 | F4: 0 | G4: 0 | H4: 0 | I4: 0 | J4: 0 | K4: 0 | L4: 0 | M4: 0 | N4: 0 | O4: 0 | P4: 0 | Q4: 0 | R4: 0 | S4: 0 | T4: 0 | U4: 0 | V4: 0 | W4: 0 | X4: 0 | Y4: 0 | Z4: 0 | AA4: 0 | AB4: 0 | AC4: 0 | AD4: 0 | AE4: 0
A5: diesel vehicle | B5: 0 | C5: 0 | D5: 0 | E5: 0 | F5: 0 | G5: 0 | H5: 0 | I5: 0 | J5: 0 | K5: 0 | L5: 0 | M5: 0 | N5: 0 | O5: 0 | P5: 0 | Q5: 0 | R5: 0 | S5: 0 | T5: 0 | U5: 0 | V5: 0 | W5: 0 | X5: 0 | Y5: 0 | Z5: 0 | AA5: 0 | AB5: 0 | AC5: 0 | AD5: 0 | AE5: 0
A6: plugin hybrid vehicle | B6: 0 | C6: 0 | D6: 0 | E6: 0 | F6: 0 | G6: 0 | H6: 0 | I6: 0 | J6: 0 | K6: 0 | L6: 0 | M6: 0 | N6: 0 | O6: 0 | P6: 0 | Q6: 0 | R6: 0 | S6: 0 | T6: 0 | U6: 0 | V6: 0 | W6: 0 | X6: 0 | Y6: 0 | Z6: 0 | AA6: 0 | AB6: 0 | AC6: 0 | AD6: 0 | AE6: 0
A7: LPG vehicle | B7: 0 | C7: 0 | D7: 0 | E7: 0 | F7: 0 | G7: 0 | H7: 0 | I7: 0 | J7: 0 | K7: 0 | L7: 0 | M7: 0 | N7: 0 | O7: 0 | P7: 0 | Q7: 0 | R7: 0 | S7: 0 | T7: 0 | U7: 0 | V7: 0 | W7: 0 | X7: 0 | Y7: 0 | Z7: 0 | AA7: 0 | AB7: 0 | AC7: 0 | AD7: 0 | AE7: 0
A8: hydrogen vehicle | B8: 0 | C8: 0 | D8: 0 | E8: 0 | F8: 0 | G8: 0 | H8: 0 | I8: 0 | J8: 0 | K8: 0 | L8: 0 | M8: 0 | N8: 0 | O8: 0 | P8: 0 | Q8: 0 | R8: 0 | S8: 0 | T8: 0 | U8: 0 | V8: 0 | W8: 0 | X8: 0 | Y8: 0 | Z8: 0 | AA8: 0 | AB8: 0 | AC8: 0 | AD8: 0 | AE8: 0

Sheet BVS-psgr-motorbikes
A1: Subsidy (2012 USD) | B1: 2021 | C1: 2022 | D1: 2023 | E1: 2024 | F1: 2025 | G1: 2026 | H1: 2027 | I1: 2028 | J1: 2029 | K1: 2030 | L1: 2031 | M1: 2032 | N1: 2033 | O1: 2034 | P1: 2035 | Q1: 2036 | R1: 2037 | S1: 2038 | T1: 2039 | U1: 2040 | V1: 2041 | W1: 2042 | X1: 2043 | Y1: 2044 | Z1: 2045 | AA1: 2046 | AB1: 2047 | AC1: 2048 | AD1: 2049 | AE1: 2050
A2: battery electric vehicle | B2: 0 | C2: 0 | D2: 0 | E2: 0 | F2: 0 | G2: 0 | H2: 0 | I2: 0 | J2: 0 | K2: 0 | L2: 0 | M2: 0 | N2: 0 | O2: 0 | P2: 0 | Q2: 0 | R2: 0 | S2: 0 | T2: 0 | U2: 0 | V2: 0 | W2: 0 | X2: 0 | Y2: 0 | Z2: 0 | AA2: 0 | AB2: 0 | AC2: 0 | AD2: 0 | AE2: 0
A3: natural gas vehicle | B3: 0 | C3: 0 | D3: 0 | E3: 0 | F3: 0 | G3: 0 | H3: 0 | I3: 0 | J3: 0 | K3: 0 | L3: 0 | M3: 0 | N3: 0 | O3: 0 | P3: 0 | Q3: 0 | R3: 0 | S3: 0 | T3: 0 | U3: 0 | V3: 0 | W3: 0 | X3: 0 | Y3: 0 | Z3: 0 | AA3: 0 | AB3: 0 | AC3: 0 | AD3: 0 | AE3: 0
A4: gasoline vehicle | B4: 0 | C4: 0 | D4: 0 | E4: 0 | F4: 0 | G4: 0 | H4: 0 | I4: 0 | J4: 0 | K4: 0 | L4: 0 | M4: 0 | N4: 0 | O4: 0 | P4: 0 | Q4: 0 | R4: 0 | S4: 0 | T4: 0 | U4: 0 | V4: 0 | W4: 0 | X4: 0 | Y4: 0 | Z4: 0 | AA4: 0 | AB4: 0 | AC4: 0 | AD4: 0 | AE4: 0
A5: diesel vehicle | B5: 0 | C5: 0 | D5: 0 | E5: 0 | F5: 0 | G5: 0 | H5: 0 | I5: 0 | J5: 0 | K5: 0 | L5: 0 | M5: 0 | N5: 0 | O5: 0 | P5: 0 | Q5: 0 | R5: 0 | S5: 0 | T5: 0 | U5: 0 | V5: 0 | W5: 0 | X5: 0 | Y5: 0 | Z5: 0 | AA5: 0 | AB5: 0 | AC5: 0 | AD5: 0 | AE5: 0
A6: plugin hybrid vehicle | B6: 0 | C6: 0 | D6: 0 | E6: 0 | F6: 0 | G6: 0 | H6: 0 | I6: 0 | J6: 0 | K6: 0 | L6: 0 | M6: 0 | N6: 0 | O6: 0 | P6: 0 | Q6: 0 | R6: 0 | S6: 0 | T6: 0 | U6: 0 | V6: 0 | W6: 0 | X6: 0 | Y6: 0 | Z6: 0 | AA6: 0 | AB6: 0 | AC6: 0 | AD6: 0 | AE6: 0
A7: LPG vehicle | B7: 0 | C7: 0 | D7: 0 | E7: 0 | F7: 0 | G7: 0 | H7: 0 | I7: 0 | J7: 0 | K7: 0 | L7: 0 | M7: 0 | N7: 0 | O7: 0 | P7: 0 | Q7: 0 | R7: 0 | S7: 0 | T7: 0 | U7: 0 | V7: 0 | W7: 0 | X7: 0 | Y7: 0 | Z7: 0 | AA7: 0 | AB7: 0 | AC7: 0 | AD7: 0 | AE7: 0
A8: hydrogen vehicle | B8: 0 | C8: 0 | D8: 0 | E8: 0 | F8: 0 | G8: 0 | H8: 0 | I8: 0 | J8: 0 | K8: 0 | L8: 0 | M8: 0 | N8: 0 | O8: 0 | P8: 0 | Q8: 0 | R8: 0 | S8: 0 | T8: 0 | U8: 0 | V8: 0 | W8: 0 | X8: 0 | Y8: 0 | Z8: 0 | AA8: 0 | AB8: 0 | AC8: 0 | AD8: 0 | AE8: 0

Sheet frgt

Sheet BVS-frgt-LDVs
A1: Subsidy (2012 USD) | B1: 2021 | C1: 2022 | D1: 2023 | E1: 2024 | F1: 2025 | G1: 2026 | H1: 2027 | I1: 2028 | J1: 2029 | K1: 2030 | L1: 2031 | M1: 2032 | N1: 2033 | O1: 2034 | P1: 2035 | Q1: 2036 | R1: 2037 | S1: 2038 | T1: 2039 | U1: 2040 | V1: 2041 | W1: 2042 | X1: 2043 | Y1: 2044 | Z1: 2045 | AA1: 2046 | AB1: 2047 | AC1: 2048 | AD1: 2049 | AE1: 2050
A2: battery electric vehicle | B2: 0 | C2: 0 | D2: ='Commercial Vehicles'!B10 -> 9715.071 | E2: ='Commercial Vehicles'!C10 -> 9379.5013 | F2: ='Commercial Vehicles'!D10 -> 9098.1571 | G2: ='Commercial Vehicles'!E10 -> 8900.5394 | H2: ='Commercial Vehicles'!F10 -> 8762.1956 | I2: ='Commercial Vehicles'!G10 -> 8574.6386 | J2: ='Commercial Vehicles'!H10 -> 8327.2184 | K2: ='Commercial Vehicles'!I10 -> 8038.2687 | ... M2: ='Commercial Vehicles'!K10 -> 7566.1942 | N2: 0 | O2: 0 | P2: 0 | Q2: 0 | R2: 0 | S2: 0 | T2: 0 | U2: 0 | V2: 0 | W2: 0 | X2: 0 | Y2: 0 | Z2: 0 | AA2: 0 | AB2: 0 | AC2: 0 | AD2: 0 | AE2: 0
A3: natural gas vehicle | B3: 0 | C3: 0 | D3: 0 | E3: 0 | F3: 0 | G3: 0 | H3: 0 | I3: 0 | J3: 0 | K3: 0 | L3: 0 | M3: 0 | N3: 0 | O3: 0 | P3: 0 | Q3: 0 | R3: 0 | S3: 0 | T3: 0 | U3: 0 | V3: 0 | W3: 0 | X3: 0 | Y3: 0 | Z3: 0 | AA3: 0 | AB3: 0 | AC3: 0 | AD3: 0 | AE3: 0
A4: gasoline vehicle | B4: 0 | C4: 0 | D4: 0 | E4: 0 | F4: 0 | G4: 0 | H4: 0 | I4: 0 | J4: 0 | K4: 0 | L4: 0 | M4: 0 | N4: 0 | O4: 0 | P4: 0 | Q4: 0 | R4: 0 | S4: 0 | T4: 0 | U4: 0 | V4: 0 | W4: 0 | X4: 0 | Y4: 0 | Z4: 0 | AA4: 0 | AB4: 0 | AC4: 0 | AD4: 0 | AE4: 0
A5: diesel vehicle | B5: 0 | C5: 0 | D5: 0 | E5: 0 | F5: 0 | G5: 0 | H5: 0 | I5: 0 | J5: 0 | K5: 0 | L5: 0 | M5: 0 | N5: 0 | O5: 0 | P5: 0 | Q5: 0 | R5: 0 | S5: 0 | T5: 0 | U5: 0 | V5: 0 | W5: 0 | X5: 0 | Y5: 0 | Z5: 0 | AA5: 0 | AB5: 0 | AC5: 0 | AD5: 0 | AE5: 0
A6: plugin hybrid vehicle | B6: 0 | C6: 0 | D6: =D2 -> 9715.071 | E6: =E2 -> 9379.5013 | F6: =F2 -> 9098.1571 | G6: =G2 -> 8900.5394 | H6: =H2 -> 8762.1956 | I6: =I2 -> 8574.6386 | J6: =J2 -> 8327.2184 | K6: =K2 -> 8038.2687 | ... M6: =M2 -> 7566.1942 | N6: 0 | O6: 0 | P6: 0 | Q6: 0 | R6: 0 | S6: 0 | T6: 0 | U6: 0 | V6: 0 | W6: 0 | X6: 0 | Y6: 0 | Z6: 0 | AA6: 0 | AB6: 0 | AC6: 0 | AD6: 0 | AE6: 0
A7: LPG vehicle | B7: 0 | C7: 0 | D7: 0 | E7: 0 | F7: 0 | G7: 0 | H7: 0 | I7: 0 | J7: 0 | K7: 0 | L7: 0 | M7: 0 | N7: 0 | O7: 0 | P7: 0 | Q7: 0 | R7: 0 | S7: 0 | T7: 0 | U7: 0 | V7: 0 | W7: 0 | X7: 0 | Y7: 0 | Z7: 0 | AA7: 0 | AB7: 0 | AC7: 0 | AD7: 0 | AE7: 0
A8: hydrogen vehicle | B8: 0 | C8: 0 | D8: =D2 -> 9715.071 | E8: =E2 -> 9379.5013 | F8: =F2 -> 9098.1571 | G8: =G2 -> 8900.5394 | H8: =H2 -> 8762.1956 | I8: =I2 -> 8574.6386 | J8: =J2 -> 8327.2184 | K8: =K2 -> 8038.2687 | ... M8: =M2 -> 7566.1942 | N8: 0 | O8: 0 | P8: 0 | Q8: 0 | R8: 0 | S8: 0 | T8: 0 | U8: 0 | V8: 0 | W8: 0 | X8: 0 | Y8: 0 | Z8: 0 | AA8: 0 | AB8: 0 | AC8: 0 | AD8: 0 | AE8: 0

Sheet BVS-frgt-HDVs
A1: Subsidy (2012 USD) | B1: 2021 | C1: 2022 | D1: 2023 | E1: 2024 | F1: 2025 | G1: 2026 | H1: 2027 | I1: 2028 | J1: 2029 | K1: 2030 | L1: 2031 | M1: 2032 | N1: 2033 | O1: 2034 | P1: 2035 | Q1: 2036 | R1: 2037 | S1: 2038 | T1: 2039 | U1: 2040 | V1: 2041 | W1: 2042 | X1: 2043 | Y1: 2044 | Z1: 2045 | AA1: 2046 | AB1: 2047 | AC1: 2048 | AD1: 2049 | AE1: 2050
A2: battery electric vehicle | B2: 0 | C2: 0 | D2: ='Commercial Vehicles'!$B4*'Commercial Vehicles'!C14 -> 30140.137 | E2: ='Commercial Vehicles'!$B4*'Commercial Vehicles'!D14 -> 29276.64 | F2: ='Commercial Vehicles'!$B4*'Commercial Vehicles'!E14 -> 28423.923 | G2: ='Commercial Vehicles'!$B4*'Commercial Vehicles'!F14 -> 27596.041 | H2: ='Commercial Vehicles'!$B4*'Commercial Vehicles'!G14 -> 26792.273 | I2: ='Commercial Vehicles'!$B4*'Commercial Vehicles'!H14 -> 26011.916 | J2: ='Commercial Vehicles'!$B4*'Commercial Vehicles'!I14 -> 25254.287 | K2: ='Commercial Vehicles'!$B4*'Commercial Vehicles'!J14 -> 24518.725 | ... M2: ='Commercial Vehicles'!$B4*'Commercial Vehicles'!L14 -> 23111.25 | N2: 0 | O2: 0 | P2: 0 | Q2: 0 | R2: 0 | S2: 0 | T2: 0 | U2: 0 | V2: 0 | W2: 0 | X2: 0 | Y2: 0 | Z2: 0 | AA2: 0 | AB2: 0 | AC2: 0 | AD2: 0 | AE2: 0
A3: natural gas vehicle | B3: 0 | C3: 0 | D3: 0 | E3: 0 | F3: 0 | G3: 0 | H3: 0 | I3: 0 | J3: 0 | K3: 0 | L3: 0 | M3: 0 | N3: 0 | O3: 0 | P3: 0 | Q3: 0 | R3: 0 | S3: 0 | T3: 0 | U3: 0 | V3: 0 | W3: 0 | X3: 0 | Y3: 0 | Z3: 0 | AA3: 0 | AB3: 0 | AC3: 0 | AD3: 0 | AE3: 0
A4: gasoline vehicle | B4: 0 | C4: 0 | D4: 0 | E4: 0 | F4: 0 | G4: 0 | H4: 0 | I4: 0 | J4: 0 | K4: 0 | L4: 0 | M4: 0 | N4: 0 | O4: 0 | P4: 0 | Q4: 0 | R4: 0 | S4: 0 | T4: 0 | U4: 0 | V4: 0 | W4: 0 | X4: 0 | Y4: 0 | Z4: 0 | AA4: 0 | AB4: 0 | AC4: 0 | AD4: 0 | AE4: 0
A5: diesel vehicle | B5: 0 | C5: 0 | D5: 0 | E5: 0 | F5: 0 | G5: 0 | H5: 0 | I5: 0 | J5: 0 | K5: 0 | L5: 0 | M5: 0 | N5: 0 | O5: 0 | P5: 0 | Q5: 0 | R5: 0 | S5: 0 | T5: 0 | U5: 0 | V5: 0 | W5: 0 | X5: 0 | Y5: 0 | Z5: 0 | AA5: 0 | AB5: 0 | AC5: 0 | AD5: 0 | AE5: 0
A6: plugin hybrid vehicle | B6: 0 | C6: 0 | D6: =D2 -> 30140.137 | E6: =E2 -> 29276.64 | F6: =F2 -> 28423.923 | G6: =G2 -> 27596.041 | H6: =H2 -> 26792.273 | I6: =I2 -> 26011.916 | J6: =J2 -> 25254.287 | K6: =K2 -> 24518.725 | ... M6: =M2 -> 23111.25 | N6: 0 | O6: 0 | P6: 0 | Q6: 0 | R6: 0 | S6: 0 | T6: 0 | U6: 0 | V6: 0 | W6: 0 | X6: 0 | Y6: 0 | Z6: 0 | AA6: 0 | AB6: 0 | AC6: 0 | AD6: 0 | AE6: 0
A7: LPG vehicle | B7: 0 | C7: 0 | D7: 0 | E7: 0 | F7: 0 | G7: 0 | H7: 0 | I7: 0 | J7: 0 | K7: 0 | L7: 0 | M7: 0 | N7: 0 | O7: 0 | P7: 0 | Q7: 0 | R7: 0 | S7: 0 | T7: 0 | U7: 0 | V7: 0 | W7: 0 | X7: 0 | Y7: 0 | Z7: 0 | AA7: 0 | AB7: 0 | AC7: 0 | AD7: 0 | AE7: 0
A8: hydrogen vehicle | B8: 0 | C8: 0 | D8: =D2 -> 30140.137 | E8: =E2 -> 29276.64 | F8: =F2 -> 28423.923 | G8: =G2 -> 27596.041 | H8: =H2 -> 26792.273 | I8: =I2 -> 26011.916 | J8: =J2 -> 25254.287 | K8: =K2 -> 24518.725 | ... M8: =M2 -> 23111.25 | N8: 0 | O8: 0 | P8: 0 | Q8: 0 | R8: 0 | S8: 0 | T8: 0 | U8: 0 | V8: 0 | W8: 0 | X8: 0 | Y8: 0 | Z8: 0 | AA8: 0 | AB8: 0 | AC8: 0 | AD8: 0 | AE8: 0

Sheet BVS-frgt-aircraft
A1: Subsidy (2012 USD) | B1: 2021 | C1: 2022 | D1: 2023 | E1: 2024 | F1: 2025 | G1: 2026 | H1: 2027 | I1: 2028 | J1: 2029 | K1: 2030 | L1: 2031 | M1: 2032 | N1: 2033 | O1: 2034 | P1: 2035 | Q1: 2036 | R1: 2037 | S1: 2038 | T1: 2039 | U1: 2040 | V1: 2041 | W1: 2042 | X1: 2043 | Y1: 2044 | Z1: 2045 | AA1: 2046 | AB1: 2047 | AC1: 2048 | AD1: 2049 | AE1: 2050
A2: battery electric vehicle | B2: 0 | C2: 0 | D2: 0 | E2: 0 | F2: 0 | G2: 0 | H2: 0 | I2: 0 | J2: 0 | K2: 0 | L2: 0 | M2: 0 | N2: 0 | O2: 0 | P2: 0 | Q2: 0 | R2: 0 | S2: 0 | T2: 0 | U2: 0 | V2: 0 | W2: 0 | X2: 0 | Y2: 0 | Z2: 0 | AA2: 0 | AB2: 0 | AC2: 0 | AD2: 0 | AE2: 0
A3: natural gas vehicle | B3: 0 | C3: 0 | D3: 0 | E3: 0 | F3: 0 | G3: 0 | H3: 0 | I3: 0 | J3: 0 | K3: 0 | L3: 0 | M3: 0 | N3: 0 | O3: 0 | P3: 0 | Q3: 0 | R3: 0 | S3: 0 | T3: 0 | U3: 0 | V3: 0 | W3: 0 | X3: 0 | Y3: 0 | Z3: 0 | AA3: 0 | AB3: 0 | AC3: 0 | AD3: 0 | AE3: 0
A4: gasoline vehicle | B4: 0 | C4: 0 | D4: 0 | E4: 0 | F4: 0 | G4: 0 | H4: 0 | I4: 0 | J4: 0 | K4: 0 | L4: 0 | M4: 0 | N4: 0 | O4: 0 | P4: 0 | Q4: 0 | R4: 0 | S4: 0 | T4: 0 | U4: 0 | V4: 0 | W4: 0 | X4: 0 | Y4: 0 | Z4: 0 | AA4: 0 | AB4: 0 | AC4: 0 | AD4: 0 | AE4: 0
A5: diesel vehicle | B5: 0 | C5: 0 | D5: 0 | E5: 0 | F5: 0 | G5: 0 | H5: 0 | I5: 0 | J5: 0 | K5: 0 | L5: 0 | M5: 0 | N5: 0 | O5: 0 | P5: 0 | Q5: 0 | R5: 0 | S5: 0 | T5: 0 | U5: 0 | V5: 0 | W5: 0 | X5: 0 | Y5: 0 | Z5: 0 | AA5: 0 | AB5: 0 | AC5: 0 | AD5: 0 | AE5: 0
A6: plugin hybrid vehicle | B6: 0 | C6: 0 | D6: 0 | E6: 0 | F6: 0 | G6: 0 | H6: 0 | I6: 0 | J6: 0 | K6: 0 | L6: 0 | M6: 0 | N6: 0 | O6: 0 | P6: 0 | Q6: 0 | R6: 0 | S6: 0 | T6: 0 | U6: 0 | V6: 0 | W6: 0 | X6: 0 | Y6: 0 | Z6: 0 | AA6: 0 | AB6: 0 | AC6: 0 | AD6: 0 | AE6: 0
A7: LPG vehicle | B7: 0 | C7: 0 | D7: 0 | E7: 0 | F7: 0 | G7: 0 | H7: 0 | I7: 0 | J7: 0 | K7: 0 | L7: 0 | M7: 0 | N7: 0 | O7: 0 | P7: 0 | Q7: 0 | R7: 0 | S7: 0 | T7: 0 | U7: 0 | V7: 0 | W7: 0 | X7: 0 | Y7: 0 | Z7: 0 | AA7: 0 | AB7: 0 | AC7: 0 | AD7: 0 | AE7: 0
A8: hydrogen vehicle | B8: 0 | C8: 0 | D8: 0 | E8: 0 | F8: 0 | G8: 0 | H8: 0 | I8: 0 | J8: 0 | K8: 0 | L8: 0 | M8: 0 | N8: 0 | O8: 0 | P8: 0 | Q8: 0 | R8: 0 | S8: 0 | T8: 0 | U8: 0 | V8: 0 | W8: 0 | X8: 0 | Y8: 0 | Z8: 0 | AA8: 0 | AB8: 0 | AC8: 0 | AD8: 0 | AE8: 0

Sheet BVS-frgt-rail
A1: Subsidy (2012 USD) | B1: 2021 | C1: 2022 | D1: 2023 | E1: 2024 | F1: 2025 | G1: 2026 | H1: 2027 | I1: 2028 | J1: 2029 | K1: 2030 | L1: 2031 | M1: 2032 | N1: 2033 | O1: 2034 | P1: 2035 | Q1: 2036 | R1: 2037 | S1: 2038 | T1: 2039 | U1: 2040 | V1: 2041 | W1: 2042 | X1: 2043 | Y1: 2044 | Z1: 2045 | AA1: 2046 | AB1: 2047 | AC1: 2048 | AD1: 2049 | AE1: 2050
A2: battery electric vehicle | B2: 0 | C2: 0 | D2: 0 | E2: 0 | F2: 0 | G2: 0 | H2: 0 | I2: 0 | J2: 0 | K2: 0 | L2: 0 | M2: 0 | N2: 0 | O2: 0 | P2: 0 | Q2: 0 | R2: 0 | S2: 0 | T2: 0 | U2: 0 | V2: 0 | W2: 0 | X2: 0 | Y2: 0 | Z2: 0 | AA2: 0 | AB2: 0 | AC2: 0 | AD2: 0 | AE2: 0
A3: natural gas vehicle | B3: 0 | C3: 0 | D3: 0 | E3: 0 | F3: 0 | G3: 0 | H3: 0 | I3: 0 | J3: 0 | K3: 0 | L3: 0 | M3: 0 | N3: 0 | O3: 0 | P3: 0 | Q3: 0 | R3: 0 | S3: 0 | T3: 0 | U3: 0 | V3: 0 | W3: 0 | X3: 0 | Y3: 0 | Z3: 0 | AA3: 0 | AB3: 0 | AC3: 0 | AD3: 0 | AE3: 0
A4: gasoline vehicle | B4: 0 | C4: 0 | D4: 0 | E4: 0 | F4: 0 | G4: 0 | H4: 0 | I4: 0 | J4: 0 | K4: 0 | L4: 0 | M4: 0 | N4: 0 | O4: 0 | P4: 0 | Q4: 0 | R4: 0 | S4: 0 | T4: 0 | U4: 0 | V4: 0 | W4: 0 | X4: 0 | Y4: 0 | Z4: 0 | AA4: 0 | AB4: 0 | AC4: 0 | AD4: 0 | AE4: 0
A5: diesel vehicle | B5: 0 | C5: 0 | D5: 0 | E5: 0 | F5: 0 | G5: 0 | H5: 0 | I5: 0 | J5: 0 | K5: 0 | L5: 0 | M5: 0 | N5: 0 | O5: 0 | P5: 0 | Q5: 0 | R5: 0 | S5: 0 | T5: 0 | U5: 0 | V5: 0 | W5: 0 | X5: 0 | Y5: 0 | Z5: 0 | AA5: 0 | AB5: 0 | AC5: 0 | AD5: 0 | AE5: 0
A6: plugin hybrid vehicle | B6: 0 | C6: 0 | D6: 0 | E6: 0 | F6: 0 | G6: 0 | H6: 0 | I6: 0 | J6: 0 | K6: 0 | L6: 0 | M6: 0 | N6: 0 | O6: 0 | P6: 0 | Q6: 0 | R6: 0 | S6: 0 | T6: 0 | U6: 0 | V6: 0 | W6: 0 | X6: 0 | Y6: 0 | Z6: 0 | AA6: 0 | AB6: 0 | AC6: 0 | AD6: 0 | AE6: 0
A7: LPG vehicle | B7: 0 | C7: 0 | D7: 0 | E7: 0 | F7: 0 | G7: 0 | H7: 0 | I7: 0 | J7: 0 | K7: 0 | L7: 0 | M7: 0 | N7: 0 | O7: 0 | P7: 0 | Q7: 0 | R7: 0 | S7: 0 | T7: 0 | U7: 0 | V7: 0 | W7: 0 | X7: 0 | Y7: 0 | Z7: 0 | AA7: 0 | AB7: 0 | AC7: 0 | AD7: 0 | AE7: 0
A8: hydrogen vehicle | B8: 0 | C8: 0 | D8: 0 | E8: 0 | F8: 0 | G8: 0 | H8: 0 | I8: 0 | J8: 0 | K8: 0 | L8: 0 | M8: 0 | N8: 0 | O8: 0 | P8: 0 | Q8: 0 | R8: 0 | S8: 0 | T8: 0 | U8: 0 | V8: 0 | W8: 0 | X8: 0 | Y8: 0 | Z8: 0 | AA8: 0 | AB8: 0 | AC8: 0 | AD8: 0 | AE8: 0

Sheet BVS-frgt-ships
A1: Subsidy (2012 USD) | B1: 2021 | C1: 2022 | D1: 2023 | E1: 2024 | F1: 2025 | G1: 2026 | H1: 2027 | I1: 2028 | J1: 2029 | K1: 2030 | L1: 2031 | M1: 2032 | N1: 2033 | O1: 2034 | P1: 2035 | Q1: 2036 | R1: 2037 | S1: 2038 | T1: 2039 | U1: 2040 | V1: 2041 | W1: 2042 | X1: 2043 | Y1: 2044 | Z1: 2045 | AA1: 2046 | AB1: 2047 | AC1: 2048 | AD1: 2049 | AE1: 2050
A2: battery electric vehicle | B2: 0 | C2: 0 | D2: 0 | E2: 0 | F2: 0 | G2: 0 | H2: 0 | I2: 0 | J2: 0 | K2: 0 | L2: 0 | M2: 0 | N2: 0 | O2: 0 | P2: 0 | Q2: 0 | R2: 0 | S2: 0 | T2: 0 | U2: 0 | V2: 0 | W2: 0 | X2: 0 | Y2: 0 | Z2: 0 | AA2: 0 | AB2: 0 | AC2: 0 | AD2: 0 | AE2: 0
A3: natural gas vehicle | B3: 0 | C3: 0 | D3: 0 | E3: 0 | F3: 0 | G3: 0 | H3: 0 | I3: 0 | J3: 0 | K3: 0 | L3: 0 | M3: 0 | N3: 0 | O3: 0 | P3: 0 | Q3: 0 | R3: 0 | S3: 0 | T3: 0 | U3: 0 | V3: 0 | W3: 0 | X3: 0 | Y3: 0 | Z3: 0 | AA3: 0 | AB3: 0 | AC3: 0 | AD3: 0 | AE3: 0
A4: gasoline vehicle | B4: 0 | C4: 0 | D4: 0 | E4: 0 | F4: 0 | G4: 0 | H4: 0 | I4: 0 | J4: 0 | K4: 0 | L4: 0 | M4: 0 | N4: 0 | O4: 0 | P4: 0 | Q4: 0 | R4: 0 | S4: 0 | T4: 0 | U4: 0 | V4: 0 | W4: 0 | X4: 0 | Y4: 0 | Z4: 0 | AA4: 0 | AB4: 0 | AC4: 0 | AD4: 0 | AE4: 0
A5: diesel vehicle | B5: 0 | C5: 0 | D5: 0 | E5: 0 | F5: 0 | G5: 0 | H5: 0 | I5: 0 | J5: 0 | K5: 0 | L5: 0 | M5: 0 | N5: 0 | O5: 0 | P5: 0 | Q5: 0 | R5: 0 | S5: 0 | T5: 0 | U5: 0 | V5: 0 | W5: 0 | X5: 0 | Y5: 0 | Z5: 0 | AA5: 0 | AB5: 0 | AC5: 0 | AD5: 0 | AE5: 0
A6: plugin hybrid vehicle | B6: 0 | C6: 0 | D6: 0 | E6: 0 | F6: 0 | G6: 0 | H6: 0 | I6: 0 | J6: 0 | K6: 0 | L6: 0 | M6: 0 | N6: 0 | O6: 0 | P6: 0 | Q6: 0 | R6: 0 | S6: 0 | T6: 0 | U6: 0 | V6: 0 | W6: 0 | X6: 0 | Y6: 0 | Z6: 0 | AA6: 0 | AB6: 0 | AC6: 0 | AD6: 0 | AE6: 0
A7: LPG vehicle | B7: 0 | C7: 0 | D7: 0 | E7: 0 | F7: 0 | G7: 0 | H7: 0 | I7: 0 | J7: 0 | K7: 0 | L7: 0 | M7: 0 | N7: 0 | O7: 0 | P7: 0 | Q7: 0 | R7: 0 | S7: 0 | T7: 0 | U7: 0 | V7: 0 | W7: 0 | X7: 0 | Y7: 0 | Z7: 0 | AA7: 0 | AB7: 0 | AC7: 0 | AD7: 0 | AE7: 0
A8: hydrogen vehicle | B8: 0 | C8: 0 | D8: 0 | E8: 0 | F8: 0 | G8: 0 | H8: 0 | I8: 0 | J8: 0 | K8: 0 | L8: 0 | M8: 0 | N8: 0 | O8: 0 | P8: 0 | Q8: 0 | R8: 0 | S8: 0 | T8: 0 | U8: 0 | V8: 0 | W8: 0 | X8: 0 | Y8: 0 | Z8: 0 | AA8: 0 | AB8: 0 | AC8: 0 | AD8: 0 | AE8: 0

Sheet BVS-frgt-motorbikes
A1: Subsidy (2012 USD) | B1: 2021 | C1: 2022 | D1: 2023 | E1: 2024 | F1: 2025 | G1: 2026 | H1: 2027 | I1: 2028 | J1: 2029 | K1: 2030 | L1: 2031 | M1: 2032 | N1: 2033 | O1: 2034 | P1: 2035 | Q1: 2036 | R1: 2037 | S1: 2038 | T1: 2039 | U1: 2040 | V1: 2041 | W1: 2042 | X1: 2043 | Y1: 2044 | Z1: 2045 | AA1: 2046 | AB1: 2047 | AC1: 2048 | AD1: 2049 | AE1: 2050
A2: battery electric vehicle | B2: 0 | C2: 0 | D2: 0 | E2: 0 | F2: 0 | G2: 0 | H2: 0 | I2: 0 | J2: 0 | K2: 0 | L2: 0 | M2: 0 | N2: 0 | O2: 0 | P2: 0 | Q2: 0 | R2: 0 | S2: 0 | T2: 0 | U2: 0 | V2: 0 | W2: 0 | X2: 0 | Y2: 0 | Z2: 0 | AA2: 0 | AB2: 0 | AC2: 0 | AD2: 0 | AE2: 0
A3: natural gas vehicle | B3: 0 | C3: 0 | D3: 0 | E3: 0 | F3: 0 | G3: 0 | H3: 0 | I3: 0 | J3: 0 | K3: 0 | L3: 0 | M3: 0 | N3: 0 | O3: 0 | P3: 0 | Q3: 0 | R3: 0 | S3: 0 | T3: 0 | U3: 0 | V3: 0 | W3: 0 | X3: 0 | Y3: 0 | Z3: 0 | AA3: 0 | AB3: 0 | AC3: 0 | AD3: 0 | AE3: 0
A4: gasoline vehicle | B4: 0 | C4: 0 | D4: 0 | E4: 0 | F4: 0 | G4: 0 | H4: 0 | I4: 0 | J4: 0 | K4: 0 | L4: 0 | M4: 0 | N4: 0 | O4: 0 | P4: 0 | Q4: 0 | R4: 0 | S4: 0 | T4: 0 | U4: 0 | V4: 0 | W4: 0 | X4: 0 | Y4: 0 | Z4: 0 | AA4: 0 | AB4: 0 | AC4: 0 | AD4: 0 | AE4: 0
A5: diesel vehicle | B5: 0 | C5: 0 | D5: 0 | E5: 0 | F5: 0 | G5: 0 | H5: 0 | I5: 0 | J5: 0 | K5: 0 | L5: 0 | M5: 0 | N5: 0 | O5: 0 | P5: 0 | Q5: 0 | R5: 0 | S5: 0 | T5: 0 | U5: 0 | V5: 0 | W5: 0 | X5: 0 | Y5: 0 | Z5: 0 | AA5: 0 | AB5: 0 | AC5: 0 | AD5: 0 | AE5: 0
A6: plugin hybrid vehicle | B6: 0 | C6: 0 | D6: 0 | E6: 0 | F6: 0 | G6: 0 | H6: 0 | I6: 0 | J6: 0 | K6: 0 | L6: 0 | M6: 0 | N6: 0 | O6: 0 | P6: 0 | Q6: 0 | R6: 0 | S6: 0 | T6: 0 | U6: 0 | V6: 0 | W6: 0 | X6: 0 | Y6: 0 | Z6: 0 | AA6: 0 | AB6: 0 | AC6: 0 | AD6: 0 | AE6: 0
A7: LPG vehicle | B7: 0 | C7: 0 | D7: 0 | E7: 0 | F7: 0 | G7: 0 | H7: 0 | I7: 0 | J7: 0 | K7: 0 | L7: 0 | M7: 0 | N7: 0 | O7: 0 | P7: 0 | Q7: 0 | R7: 0 | S7: 0 | T7: 0 | U7: 0 | V7: 0 | W7: 0 | X7: 0 | Y7: 0 | Z7: 0 | AA7: 0 | AB7: 0 | AC7: 0 | AD7: 0 | AE7: 0
A8: hydrogen vehicle | B8: 0 | C8: 0 | D8: 0 | E8: 0 | F8: 0 | G8: 0 | H8: 0 | I8: 0 | J8: 0 | K8: 0 | L8: 0 | M8: 0 | N8: 0 | O8: 0 | P8: 0 | Q8: 0 | R8: 0 | S8: 0 | T8: 0 | U8: 0 | V8: 0 | W8: 0 | X8: 0 | Y8: 0 | Z8: 0 | AA8: 0 | AB8: 0 | AC8: 0 | AD8: 0 | AE8: 0
