Workbook

Sheet About
A1: SoFCtMbCtPRCoS Share of Forward Costs that Must Be Covered to Prevent Retirement for Cost of Service Plants | B1: United States | C1: 2026-08-25 | F1: Alabama | G1: AL
B2: =VLOOKUP($B$1,$F$1:$G$51,2,FALSE) -> US | F2: Alaska | G2: AK
A3: Sources: | B3: Primary anchor: regulated-vs-merchant exit-probability differential | F3: Arizona | G3: AZ
B4: Lucas W. Davis and Paige E. Weber | F4: Arkansas | G4: AR
B5: Does Regulation Distort Exit Decisions? Evidence from U.S. Power Plants - NBER Working Paper 34454 | F5: California | G5: CA
B6: 2025 | F6: Colorado | G6: CO
B7: https://www.nber.org/papers/w34454 | F7: Connecticut | G7: CT
B8: Generator-level data 2010-2023: regulated units are 45% less likely to exit than unregulated; merchant exits respond to wholesale prices and capital costs while regulated owners are largely insulated. The 0.55 here = 1 - 0.45, per the model developers mapping (2026-08-24). CAVEAT: a 45% lower exit PROBABILITY is not literally a 55% forward-cost-coverage share - this is an empirically anchored placeholder until the margin coefficients are pulled from the paper body or a PUDL survival model is run (FERC Form 1 costs + EIA-923 margins by Regulatory Status). Only the abstract was verified verbatim; see the literature section of NOTES-CoS-Retirement-Exposure-2026-08-24.md (EPS Structure Research folder) for the full verified/unverified citation ledger. | F8: Delaware | G8: DE
F9: Florida | G9: FL
B10: Complementary anchors (directional support) | F10: Georgia | G10: GA
B11: Gowrisankaran, Langer and Reguant | F11: Hawaii | G11: HI
B12: Energy Transitions in Regulated Markets - American Economic Review (2026); NBER WP 32088 | F12: Idaho | G12: ID
B13: 2026 | F13: Illinois | G13: IL
B14: https://www.nber.org/papers/w32088 | F14: Indiana | G14: IN
B15: Structural model of rate-of-return regulation: a regulated utility cuts short-run coal generation only ~48% as much as a cost-minimizer; a cost-minimizer retires substantially more coal capacity. Also RMI Utility Transition Hub economic-dispatch data and Sierra Club "Other Peoples Money" (2019) quantify regulated loss-tolerance in dollars (not independently verified - see NOTES doc). | F15: Iowa | G15: IA
F16: Kansas | G16: KS
A17: Notes: | F17: Kentucky | G17: KY
A18: What it does | B18: For plants under cost-of-service regulation, the share of forward-going costs (fuel, O&M, and capital recovery going forward) that operating revenue must cover for the plant to stay online. Below this share, the plant becomes a candidate for economic retirement. It enters the retirement bar as a capacity-weighted blend: SoFCtMbCtPR = SoCtICoS x SoFCtMbCtPRCoS + (1 - SoCtICoS) x SoFCtMbCtPRM, where SoCtICoS is the cost-of-service share of capacity (own workbook in its folder) and SoFCtMbCtPRM is the merchant twin (set to 1.0: merchant plants must fully cover forward costs). | F18: Louisiana | G18: LA
A19: Why below 1.0 | B19: Rate-regulated plants persist while covering only part of their forward costs because recovery flows through rates rather than market revenue: regulators retire plants slowly, undepreciated rate base creates inertia, and reliability/jobs considerations enter commission decisions. 0.55 encodes that a cost-of-service plant is tolerated while covering roughly half its forward costs, where a merchant plant covering less than all of them exits. | F19: Maine | G19: ME
A20: State configurability | B20: Cell B1 of this tab selects the region per the standard convention (B2 derives the abbreviation; calculations key on B2). The parameter is currently NOT state-differentiated - every state folder carries the identical 0.55 - so the selector is inert today. To differentiate a state, add a row to the override table on the Parameters tab; the output picks it up for that state automatically. | F20: Maryland | G20: MD
A21: How to revise | B21: Change the default on Parameters!B2 (all techs, all states) or add state/tech override rows. The output tab mirrors SoFCtMbCtPRCoS.csv exactly. Open and save in Excel before exporting so formula caches exist. | F21: Massachusetts | G21: MA
F22: Michigan | G22: MI
F23: Minnesota | G23: MN
F24: Mississippi | G24: MS
F25: Missouri | G25: MO
F26: Montana | G26: MT
F27: Nebraska | G27: NE
F28: Nevada | G28: NV
F29: New Hampshire | G29: NH
F30: New Jersey | G30: NJ
F31: New Mexico | G31: NM
F32: New York | G32: NY
F33: North Carolina | G33: NC
... F51: United States | G51: US

Sheet Parameters
A1: Editable parameters (region selector is on the About tab, cell B1)
A2: Default share of forward costs covered to prevent retirement (cost-of-service plants, all techs, all states) | B2: 0.55
D3: Optional state/tech overrides (empty = default everywhere)
D4: State | E4: EPS technology | F4: Value

Sheet Checks
A1: Validation checks
A2: All output values within [0,1]? | B2: =IF(AND(MIN(SoFCtMbCtPRCoS!$B$2:$B$25)>=0,MAX(SoFCtMbCtPRCoS!$B$2:$B$25)<=1),"PASS","FAIL") -> PASS
A3: CoS bar below merchant bar (should be <= 1.0)? | B3: =IF(MAX(SoFCtMbCtPRCoS!$B$2:$B$25)<=1,"PASS","FAIL") -> PASS
A4: Override rows active for selected region (count) | B4: =COUNTIFS(Parameters!$D$5:$D$54,About!$B$2) -> 0

Sheet SoFCtMbCtPRCoS
A1: Unit: dimensionless (% of costs) | B1: Share of costs covered to be deemed profitable for cost of service plants
A2: hard coal | B2: =IF(COUNTIFS(Parameters!$D$5:$D$54,About!$B$2,Parameters!$E$5:$E$54,$A2)>0,SUMIFS(Parameters!$F$5:$F$54,Parameters!$D$5:$D$54,About!$B$2,Parameters!$E$5:$E$54,$A2),Parameters!$B$2) -> 0.55
A3: natural gas steam turbine | B3: =IF(COUNTIFS(Parameters!$D$5:$D$54,About!$B$2,Parameters!$E$5:$E$54,$A3)>0,SUMIFS(Parameters!$F$5:$F$54,Parameters!$D$5:$D$54,About!$B$2,Parameters!$E$5:$E$54,$A3),Parameters!$B$2) -> 0.55
A4: natural gas combined cycle | B4: =IF(COUNTIFS(Parameters!$D$5:$D$54,About!$B$2,Parameters!$E$5:$E$54,$A4)>0,SUMIFS(Parameters!$F$5:$F$54,Parameters!$D$5:$D$54,About!$B$2,Parameters!$E$5:$E$54,$A4),Parameters!$B$2) -> 0.55
A5: nuclear | B5: =IF(COUNTIFS(Parameters!$D$5:$D$54,About!$B$2,Parameters!$E$5:$E$54,$A5)>0,SUMIFS(Parameters!$F$5:$F$54,Parameters!$D$5:$D$54,About!$B$2,Parameters!$E$5:$E$54,$A5),Parameters!$B$2) -> 0.55
A6: hydro | B6: =IF(COUNTIFS(Parameters!$D$5:$D$54,About!$B$2,Parameters!$E$5:$E$54,$A6)>0,SUMIFS(Parameters!$F$5:$F$54,Parameters!$D$5:$D$54,About!$B$2,Parameters!$E$5:$E$54,$A6),Parameters!$B$2) -> 0.55
A7: onshore wind | B7: =IF(COUNTIFS(Parameters!$D$5:$D$54,About!$B$2,Parameters!$E$5:$E$54,$A7)>0,SUMIFS(Parameters!$F$5:$F$54,Parameters!$D$5:$D$54,About!$B$2,Parameters!$E$5:$E$54,$A7),Parameters!$B$2) -> 0.55
A8: solar PV | B8: =IF(COUNTIFS(Parameters!$D$5:$D$54,About!$B$2,Parameters!$E$5:$E$54,$A8)>0,SUMIFS(Parameters!$F$5:$F$54,Parameters!$D$5:$D$54,About!$B$2,Parameters!$E$5:$E$54,$A8),Parameters!$B$2) -> 0.55
A9: solar thermal | B9: =IF(COUNTIFS(Parameters!$D$5:$D$54,About!$B$2,Parameters!$E$5:$E$54,$A9)>0,SUMIFS(Parameters!$F$5:$F$54,Parameters!$D$5:$D$54,About!$B$2,Parameters!$E$5:$E$54,$A9),Parameters!$B$2) -> 0.55
A10: biomass | B10: =IF(COUNTIFS(Parameters!$D$5:$D$54,About!$B$2,Parameters!$E$5:$E$54,$A10)>0,SUMIFS(Parameters!$F$5:$F$54,Parameters!$D$5:$D$54,About!$B$2,Parameters!$E$5:$E$54,$A10),Parameters!$B$2) -> 0.55
A11: geothermal | B11: =IF(COUNTIFS(Parameters!$D$5:$D$54,About!$B$2,Parameters!$E$5:$E$54,$A11)>0,SUMIFS(Parameters!$F$5:$F$54,Parameters!$D$5:$D$54,About!$B$2,Parameters!$E$5:$E$54,$A11),Parameters!$B$2) -> 0.55
A12: petroleum | B12: =IF(COUNTIFS(Parameters!$D$5:$D$54,About!$B$2,Parameters!$E$5:$E$54,$A12)>0,SUMIFS(Parameters!$F$5:$F$54,Parameters!$D$5:$D$54,About!$B$2,Parameters!$E$5:$E$54,$A12),Parameters!$B$2) -> 0.55
A13: natural gas peaker | B13: =IF(COUNTIFS(Parameters!$D$5:$D$54,About!$B$2,Parameters!$E$5:$E$54,$A13)>0,SUMIFS(Parameters!$F$5:$F$54,Parameters!$D$5:$D$54,About!$B$2,Parameters!$E$5:$E$54,$A13),Parameters!$B$2) -> 0.55
... A25: hydrogen combined cycle | B25: =IF(COUNTIFS(Parameters!$D$5:$D$54,About!$B$2,Parameters!$E$5:$E$54,$A25)>0,SUMIFS(Parameters!$F$5:$F$54,Parameters!$D$5:$D$54,About!$B$2,Parameters!$E$5:$E$54,$A25),Parameters!$B$2) -> 0.55
