Workbook

Sheet About
A1: EEpTSCA Electricity per Ton of Stack CO2 Abated
A3: Sources: | B3: US petrochemical and ammonia process CO2 (2023) | D3: Independent inventory of an electrified cracker (naphtha)
B4: U.S. Environmental Protection Agency | D4: Layritz, Dolganova, Finkbeiner, Luderer, Penteado, Ueckerdt and Repke (PIK / TU Berlin)
B5: Inventory of U.S. Greenhouse Gas Emissions and Sinks: 1990-2023 (EPA 430-R-25-003), Chapter 4 Industrial Processes and Product Use: Petrochemical Production (Tables 4-55 to 4-57) and Ammonia Production (Tables 4-23 and 4-24) | D5: The potential of direct steam cracker electrification and carbon capture & utilization via oxidative coupling of methane as decarbonization strategies for ethylene production, Applied Energy 296:117049 (preprint)
B6: 2025 | D6: 2021
B7: https://www.epa.gov/ghgemissions/inventory-us-greenhouse-gas-emissions-and-sinks | D7: https://publications.pik-potsdam.de/pubman/item/item_25669_4/component/file_25682/25669_preprint.pdf
B8: Tables 4-55/4-56 give 2023 petrochemical CO2 by product in MMT CO2 Eq. and kt (total 30,540 kt: carbon black 2,550; ethylene 22,600; ethylene dichloride 460; ethylene oxide 1,730; methanol 2,130; acrylonitrile 1,070). Table 4-57 gives production (ethylene 2023: 39,400 kt). The ethylene figure is the CO2 from burning ethylene process off-gas (the GHGRP optional combustion method), so it excludes CO2 from any natural gas make-up fuel. Ammonia (Table 4-24): 12,211 kt CO2 in 2023, net of CO2 recovered for urea. Held verbatim on the Source Data tab. Do not use these as a facility-level or non-US figure. | D8: Preprint read 2026-10-29 (the published version may differ). Appendix A.2 (conventional naphtha cracker, flows from Zimmermann and Walzl): furnace heat 6.78 MWh per tonne of ethylene supplied by 0.488 t of methane-rich fuel gas, with an emission factor of 2.6 t CO2 per t fuel (Appendix A.5), so 1.27 t CO2 per tonne of ethylene from the furnace. Appendix A.3 (electrified cracker): furnace electricity 6.78 MWh per tonne of ethylene, footnote 3: demand and furnace efficiency assumed identical to the conventional process. Section 3.2.1 states the same assumption: added electricity equals the lower heating value of the off-gas the furnace burned. Used as an independent check (Calcs rows 21-23) and as the equal-efficiency sensitivity case.
B10: Steam cracker energy use and its split by section (primary source) | D10: US ethane-cracker techno-economics with an electrically heated cracker case
B11: Ren, Patel and Blok (Utrecht University) | D11: Shin, Lin, Lai, Ibrahim and Zang (MIT Energy Initiative)
B12: Olefins from conventional and heavy feedstocks: Energy use in steam cracking and alternative processes, Energy 31(4):425-451 | D12: Decarbonization approaches for ethylene production: comparative techno-economic and life-cycle analysis, Green Chemistry 27:3655-3675 (open access, CC-BY-NC) and its Electronic Supplementary Information
B13: 2006 | D13: 2025
B14: https://dspace.library.uu.nl/handle/1874/21674 | D14: https://doi.org/10.1039/d4gc04538f
B15: Open-access PDF read 2026-10-29. Table 2 (p.433): ethane steam cracking 17-21 GJ per tonne of ethylene (typical; 15-25 maximum), naphtha 26-31; CO2 1.0-1.2 t per tonne ethylene for ethane. Footnote a: the figure is process energy in pyrolysis and separation; all figures are primary energy, with electricity (about 1 GJ/t) and steam converted at 40% and 85%. Table 3 (p.435): one ethane column gives pyrolysis 65%, fractionation and compression 15%, separation 20%; a second ethane column gives heat of reaction 23%, steam, heating and losses 24%, compression 22%, separation 31%. The 65% share is used centrally because it reproduces the inventory stack CO2 per tonne (Calcs row 17); the second split is noted as a caution. | D15: Paper and ESI read 2026-10-30 (PDFs supplied by Dan; the site refuses automated download). Aspen Plus models of a 1 million t/yr U.S. ethane cracker in four cases. Table 5 (p.3663): Baseline imports no electricity, burns 5,920 kg/h natural gas plus purge gas (combustion energy 1,173,780 MJ/h, on-site 50,505 kg CO2e/h); the Electrical heating case imports 353 MW, burns nothing, and exports 7,448 kg/h hydrogen and 13,659 kg/h other gas; ethylene 114,335 kg/h in all cases. Section 2.2.2 (p.3659): 100% efficiency assumed for the electrically heated cracker. ESI Tables S6 and S8: the cracker unit is the same $370,332,924 installed in the Baseline and Electrical heating cases (no capital premium for electric heating; scaling exponent 0.67); total plant cost $626,044,269 (Baseline) and $533,973,722 (Electrical heating, no boiler or turbine). ESI Table S10: reference year 2019, operating capacity factor 90%, design capacity 1.00 million t/yr. Table 1 (p.3658): combustion energy 17.2 GJ per tonne of ethylene, consistent with Ren et al.
B17: Steam cracker energy use and plant capital cost | D17: Demonstration furnace scale (context)
B18: Idaho National Laboratory (Hu, Ding, Knighton, Wendt and Boardman) | D18: BASF, SABIC and Linde
B19: Technoeconomic Analysis on an Electrochemical Nonoxidative Deprotonation Process for Ethylene Production from Ethane (INL/EXT-19-56936) | D19: Press release P-24-177: BASF, SABIC and Linde inaugurate the world's first large-scale electrically heated steam cracking furnace
B20: 2020 | D20: 2024
B21: https://inldigitallibrary.inl.gov/sites/sti/sti/Sort_21795.pdf | D21: https://www.basf.com/global/en/media/news-releases/2024/04/p-24-177
B22: Section 1.2 (p.iii) quotes 17-21 GJ of process energy per tonne of ethylene for ethane steam cracking, 65% of it in high-temperature pyrolysis (both from Ren et al. 2006), and 1-1.6 t CO2 per tonne of ethylene from external heating (Gartner et al. 2013). Table 5 (p.12): simulated fired duty, feedstock preheater 7.376 plus cracker 7.355 MMBtu per tonne ethylene (its full energy table sums to 37.5 MMBtu/t because it also counts cooling and refrigeration duties). Table 14 (p.28): steam cracker total capital investment $1,110 million for 830,132 t/yr ethylene, from PetroChemical Update 2018 cost data for the US Gulf Coast (treated here as 2018 dollars; the report states no cost year for this table). Table 15 (p.29): Lang factor 3.282 (Wain 2014). Table 27 (p.62): on-stream factor 91%, 8,000 operating hours per year (stated for the LDPE unit of the same complex; the cracking energy balance in Table 8 uses 8,760). All values read in the report text (2026-10-29). Not an electric-furnace cost. | D22: Two demonstration furnaces at Ludwigshafen consume about 6 MW of renewable electricity and process about 4 tonnes of hydrocarbon feed per hour combined (feed, not ethylene; feedstock type not stated), one heated by passing current through the coils and one by radiant elements. Claims at least 90% lower CO2 with renewable power. That is about 1.5 MWh per tonne of feed, or 5-6 MWh per tonne of ethylene if 25-30% of the feed becomes ethylene, which is the same order as the Layritz inventory (6.78 MWh/t). Context only; nothing is taken from it numerically.
B24: Efficiency of fired versus electrified cracking (reported as a pair) | D24: Electric cracking furnace status (context)
B25: Maporti et al., Energy Conversion and Management (Elsevier) | D25: ISPT (Shell, Dow, TNO)
B26: Flexible ethylene production: Electrified ethane cracking coupled with oxidative dehydrogenation, 296:117761 (ScienceDirect PII S019689042301107X) | D26: Public report: e-Missi0n electric steam cracker furnace development
B27: 2023 | D27: 2026
B28: https://doi.org/10.1016/j.enconman.2023.117761 | D28: https://ispt.eu/publications/public-report-e-missi0n/
B29: Paywalled; only the abstract was seen (search snippet, re-checked 2026-10-29): thermal efficiency 89.9% for fuel-fired cracking, 97.1% for electrified cracking, 98.1% for oxidative dehydrogenation. The paper's definition of thermal efficiency is not confirmed; for an ethane cracker it is most likely heat delivered to the process over fuel or electricity input. These two values are the central pair because they were reported together for the same unit. The Calcs tab shows the result with the alternative fired efficiency (95%, Amghizar) and with equal efficiencies (Layritz): the three differ by 8%. | D29: Reports that direct electric heating of cracker tubes gave performance comparable to gas-fired furnaces, that electric cracking competes at electricity below about 67 EUR/MWh or a CO2 price above about 235 EUR/t, and that silicon carbide heating elements are unlikely to meet the targeted four-year lifetime; gives no electricity per tonne, efficiency or capital cost, so nothing is taken from it numerically.
B31: Fired cracking furnace efficiency (state of the art) | D31: Fuel CO2 intensity (consistency check)
B32: Amghizar, Dedeyne, Brown, Marin and Van Geem (Ghent University) | D32: Energy Policy Simulator input files (this repository)
B33: Sustainable innovations in steam cracking: CO2 neutral olefin production, Reaction Chemistry & Engineering 5:239-257 (accepted manuscript) | D33: InputData/fuels/PEI/PEI-IFPEI.csv (natural gas CO2)
B34: 2020 | D34: 2026
B35: https://biblio.ugent.be/publication/8651201 | D35: https://github.com/EnergyInnovation/eps-us
B36: Accepted manuscript read 2026-10-29. Introduction: state-of-the-art furnaces reach efficiencies up to 95% (citing Zimmermann 2000); of the burner heat about 42% is absorbed by the reactor coil, 29% recovered in the transfer-line exchanger, 5% leaves through the stack, and up to 55% of the remaining flue-gas heat is recovered in the convection section. Abstract: more than 90% of a cracker's direct CO2 comes from furnace combustion. Gives no electricity per tonne for electric furnaces. The 95% figure is the alternative fired-efficiency case on the Calcs tab. | D36: Used only in the Calcs consistency rows (Source Data row 17); not in the exported value.
A39: Notes:
A40: Purpose and layout | B40: EEpTSCA is the electricity the chemicals module adds when cracker furnace heating (the "other stack" CO2 pool) is electrified: BTU of electricity per metric ton of stack CO2 abated. The Source Data tab holds the published inputs, Calcs works through furnace duty, efficiency and stack CO2 and then tests the result against an independent inventory and other efficiency assumptions, Checks tests it, and the last tab, EEpTSCA, is exactly what is written to EEpTSCA.csv (same layout as CGSCR.csv).
A41: Method in plain words | B41: A steam cracker heats its reaction tubes in furnaces fired mostly with its own off-gas. We take the fuel energy the furnaces burn per tonne of ethylene (65% of the 17-21 GJ/t total process energy in Ren et al.). Fired furnaces deliver about 90% of that fuel energy to the tubes and electric heating about 97% of the electricity, so the electricity needed is the fuel energy times 0.899/0.971. We then divide by the stack CO2 per tonne of ethylene from the U.S. greenhouse gas inventory (22.6 million tonnes of CO2 over 39.4 million tonnes of ethylene in 2023, about 0.574) to get electricity per tonne of CO2 abated.
A42: Confidence (research pass 2026-10-29/30) | B42: Every number except the efficiency pair was read in its primary source. The result is robust to the efficiency assumption: with the state-of-the-art fired efficiency of 95% (Amghizar et al.) or with equal efficiencies (Layritz et al.; Shin et al. assume 100% for electric heating) the value rises by 5% and 8% (Calcs rows 27-30). Two independent plant models bracket it: a European naphtha-cracker inventory (Layritz et al., 6.78 MWh of furnace heat against 1.27 t of furnace CO2 per tonne of ethylene) gives a value within 4% of the export (Calcs row 23), and a U.S. ethane-plant model that electrifies the whole plant (Shin et al., 353 MW for 114 t/h of ethylene against 50.5 t/h of on-site CO2e) gives a value 26% higher, which is an upper bound because that electricity also replaces the plant's own power generation (Calcs rows 33-37). The furnace-duty range (17-21 GJ/t) moves the result by +/-11% (columns C-D). Two cautions remain: the 89.9% / 97.1% pair comes from an abstract and its definition is unconfirmed, and Ren et al. give a second ethane energy split in which heating is 47% rather than 65% of process energy; that split would not reproduce the inventory stack CO2 (Calcs row 17), which is why 65% is used. Verify against the primary sources before relying on this in a work product.
A43: Sanity check | B43: The result (about 1.89e7 BTU of electricity per tonne of CO2) is close to the energy in the natural gas that would emit one tonne of CO2 (about 1.88e7 BTU), as it should be if the furnace duty is mostly burned fuel gas. The Checks tab tests this and the Layritz comparison.
A44: Things this value does not capture | B44: Electricity used on site for other cracker sections is unchanged. The off-gas no longer burned in the furnaces is not given a value here, so the model should treat it as a by-product (sold or used elsewhere) if it wants to credit it. Furnace efficiency varies with the definition used: Amghizar et al. report about 42% of burner heat absorbed by the coil and up to 95% overall with heat recovery, which are different boundaries; we use the pair that was reported together.
A45: Regional adaptation | B45: The method is feedstock-neutral: replace the furnace duty (naphtha crackers use 26-31 GJ/t ethylene in Ren et al. Table 2) and the stack CO2 per tonne of ethylene with the region's inventory figure. The Layritz inventory is a European naphtha plant and can serve directly where no national figure exists.
A46: Export format | B46: Unit line and label in the first row, one data row below, as in CGSCR.csv. CSV values computed in Python from the same formulas; recalc in Excel to verify.

Sheet Source Data
A1: SOURCE DATA: values pasted as published (confidence flag in column E: DIRECT = read in the source text; SNIPPET = read from an abstract or search snippet only)
A3: Item | B3: Value | C3: Unit | D3: Source and location | E3: Confidence
A4: Ethane steam cracking process energy, low end | B4: 17 | C4: GJ per t ethylene | D4: Ren, Patel and Blok (2006) Energy 31:425, Table 2 (p.433), ethane, typical range 17-21 GJ/t ethylene (open-access PDF, Utrecht repository) | E4: DIRECT
A5: Ethane steam cracking process energy, high end | B5: 21 | C5: GJ per t ethylene | D5: Same | E5: DIRECT
A6: Share of that process energy used in high-temperature pyrolysis (furnaces) | B6: 0.65 | C6: fraction | D6: Ren et al. (2006) Table 3 (p.435), ethane column from its ref. 68: pyrolysis 65%, fractionation and compression 15%, separation 20%. The other ethane column (ref. 20) gives heat of reaction 23% plus steam, heating and losses 24%. | E6: DIRECT
A7: Simulated fired duty: feedstock preheater | B7: 7.376 | C7: MMBtu per t ethylene | D7: INL/EXT-19-56936 Table 5 (p.12), CH4-fired | E7: DIRECT
A8: Simulated fired duty: cracker | B8: 7.355 | C8: MMBtu per t ethylene | D8: INL/EXT-19-56936 Table 5 (p.12), CH4-fired | E8: DIRECT
A9: GJ per MMBtu | B9: 1.055056 | C9: GJ/MMBtu | D9: Unit conversion (1 MMBtu = 1.055056 GJ) | E9: DIRECT
A10: BTU per GJ | B10: 947817.12 | C10: BTU/GJ | D10: Unit conversion (1 GJ = 947,817 BTU) | E10: DIRECT
A11: Thermal efficiency of fuel-fired cracking (central) | B11: 0.899 | C11: fraction | D11: Maporti et al. (2023), Energy Conversion and Management 296:117761, abstract text (89.9%); definition of thermal efficiency not confirmed in the full text | E11: SNIPPET
A12: Thermal efficiency of electrified cracking (central) | B12: 0.971 | C12: fraction | D12: Same abstract text (97.1%) | E12: SNIPPET
A13: CO2 from burning ethylene process off-gas, 2023 | B13: 22600 | C13: kt CO2 | D13: US GHGI 2025 (EPA 430-R-25-003) Section 4.4 text and Table 4-56 (p.4-74): 22,600,000 t CO2 from ethylene production, 2023 | E13: DIRECT
A14: Ethylene production, 2023 | B14: 39400 | C14: kt ethylene | D14: US GHGI 2025 Table 4-57 (p.4-78), ethylene, 2023 | E14: DIRECT
A15: Literature CO2 from external heating per t ethylene, low (context only) | B15: 1 | C15: t CO2 per t ethylene | D15: Gartner, van Veen and Lercher (2013) ChemCatChem 5:3196, as quoted in INL/EXT-19-56936 Section 1.2 (original not accessed); Ren et al. Table 2 gives 1.0-1.2 for ethane | E15: DIRECT (as quoted)
... A26: Shin et al.: combustion energy of the Baseline plant | B26: 1173780 | C26: MJ per h | D26: Same, Table 5, Baseline | E26: DIRECT

Sheet Calcs
A1: CALCULATIONS: electricity needed to replace the fuel burned for cracker furnace heat, per tonne of CO2 avoided
A2: Question this tab answers: if a steam cracker's furnaces are heated by electricity instead of burning off-gas, how much electricity does it take for each tonne of stack CO2 avoided? Steps: furnace fuel energy per tonne of ethylene (Ren et al.), converted to electricity using the efficiency of fired versus electric heating, then divided by the stack CO2 per tonne of ethylene (U.S. inventory). Columns B-D give the central, low and high furnace-duty estimates; the central column (B) is exported. The blocks below test the result against other efficiency assumptions and against an independent inventory.
A4: Quantity | B4: CENTRAL (exported) | C4: Low furnace duty | D4: High furnace duty | E4: Formula in words
A5: Process energy per tonne ethylene, GJ (17-21 range) | B5: =AVERAGE('Source Data'!$B$4,'Source Data'!$B$5) -> 19 | C5: ='Source Data'!$B$4 -> 17 | D5: ='Source Data'!$B$5 -> 21 | E5: Midpoint of the 17-21 GJ/t range; low and high end of the range
A6: Fired furnace duty per tonne ethylene, GJ (pyrolysis share of process energy) | B6: =B5*'Source Data'!$B$6 -> 12.35 | C6: =C5*'Source Data'!$B$6 -> 11.05 | D6: =D5*'Source Data'!$B$6 -> 13.65 | E6: Process energy x 65% used in furnaces
A7: Heat actually delivered to the cracking tubes, GJ per t ethylene | B7: =B6*'Source Data'!$B$11 -> 11.10265 | C7: =C6*'Source Data'!$B$11 -> 9.93395 | D7: =D6*'Source Data'!$B$11 -> 12.27135 | E7: Fired duty x efficiency of fuel-fired cracking
A8: Electricity needed to deliver the same heat, GJ per t ethylene | B8: =B7/'Source Data'!$B$12 -> 11.434243 | C8: =C7/'Source Data'!$B$12 -> 10.230639 | D8: =D7/'Source Data'!$B$12 -> 12.637848 | E8: Delivered heat / efficiency of electrified cracking
A9: Electricity needed, BTU per t ethylene | B9: =B8*'Source Data'!$B$10 -> 10837571 | C9: =C8*'Source Data'!$B$10 -> 9696774.3 | D9: =D8*'Source Data'!$B$10 -> 11978368 | E9: GJ x BTU per GJ
A10: Stack CO2 per tonne ethylene, t CO2 per t (2023 U.S. inventory) | B10: ='Source Data'!$B$13/'Source Data'!$B$14 -> 0.57360406 | C10: =B10 -> 0.57360406 | D10: =B10 -> 0.57360406 | E10: Off-gas combustion CO2 / ethylene production
A11: EEpTSCA: ELECTRICITY PER TON OF STACK CO2 ABATED, BTU per t CO2 | B11: =B9/B10 -> 18893819 | C11: =C9/C10 -> 16904996 | D11: =D9/D10 -> 20882642 | E11: BTU of electricity per t ethylene / t CO2 per t ethylene
A13: Consistency rows (not used in the export)
A14: Fired duty from the INL simulation (preheater + cracker), GJ per t ethylene | B14: =('Source Data'!$B$7+'Source Data'!$B$8)*'Source Data'!$B$9 -> 15.54203 | E14: A single Aspen model; higher than the literature range because of its lower ethylene yield
A15: CO2 intensity implied by the central furnace duty, kg CO2 per GJ of fired duty | B15: =B10*1000/B6 -> 46.445673
A16: CO2 intensity of natural gas in the EPS input, kg CO2 per GJ | B16: ='Source Data'!$B$17*'Source Data'!$B$10/1000 -> 50.291176
A17: Ratio: implied intensity / natural gas intensity | B17: =B15/B16 -> 0.92353523 | E17: Near 1 means the stack CO2 is consistent with the furnace duty being mostly burned fuel gas. Well below 1 would mean much of the duty is not CO2-emitting (hydrogen-rich off-gas) or that the inventory pool covers only part of the duty.
A18: Literature CO2 from external heating per t ethylene, range (Gartner et al. as quoted by INL) | B18: ='Source Data'!$B$15 -> 1 | C18: ='Source Data'!$B$16 -> 1.6 | E18: The inventory figure (B10) is lower than this range; it counts only the off-gas share of furnace CO2
A20: Independent check: Layritz et al. (2021) naphtha cracker inventory, equal furnace efficiencies
A21: Furnace CO2 per tonne ethylene, t CO2 per t (fuel gas burned x its emission factor) | B21: ='Source Data'!$B$20*'Source Data'!$B$21 -> 1.2688
A22: Electricity per tonne of furnace CO2 avoided, BTU per t CO2 (furnace electricity / furnace CO2) | B22: ='Source Data'!$B$19*'Source Data'!$B$22/B21 -> 18233220 | E22: Naphtha feed, European plant data, electricity assumed equal to the fuel heat it replaces
A23: Ratio: central result / Layritz estimate | B23: =B11/B22 -> 1.0362305 | E23: Two different feedstocks, data sets and efficiency assumptions; agreement within about 10% supports the order of magnitude
A25: Sensitivity to the efficiency assumption (central furnace duty)
A26: Case | B26: Fired efficiency | C26: Electric efficiency | D26: Result, BTU per t CO2 | E26: Source of the pair
A27: Central: pair reported together (Maporti et al. 2023 abstract) | B27: ='Source Data'!$B$11 -> 0.899 | C27: ='Source Data'!$B$12 -> 0.971 | D27: =$B$6*B27/C27*'Source Data'!$B$10/$B$10 -> 18893819 | E27: Exported
A28: Alternative fired efficiency: state of the art up to 95% (Amghizar et al. 2020) | B28: ='Source Data'!$B$18 -> 0.95 | C28: ='Source Data'!$B$12 -> 0.971 | D28: =$B$6*B28/C28*'Source Data'!$B$10/$B$10 -> 19965660 | E28: Fired 95% with the same electric efficiency
A29: Equal efficiencies (Layritz et al. 2021 assumption; Shin et al. 2025 assume 100% electric) | B29: 1 | C29: 1 | D29: =$B$6*B29/C29*'Source Data'!$B$10/$B$10 -> 20407006 | E29: Electricity equals the fuel heat it replaces
A30: Spread: highest / lowest of the three cases | B30: =MAX(D27:D29)/MIN(D27:D29) -> 1.080089
A32: Third check: Shin et al. (2025) U.S. ethane plant, whole-plant electrification (an upper bound)
A33: Electricity imported per tonne of ethylene, MWh per t | B33: ='Source Data'!$B$23*1000/'Source Data'!$B$24 -> 3.0874186 | E33: MW x 1000 kg/t / (kg ethylene per h)
A34: On-site CO2e avoided per tonne of ethylene, t per t | B34: ='Source Data'!$B$25/'Source Data'!$B$24 -> 0.44172825 | E34: Baseline on-site emissions (the electric case emits none on site)
A35: Electricity per tonne of on-site CO2 avoided, BTU per t CO2 | B35: =B33*'Source Data'!$B$22/B34 -> 23848835
A36: CO2 intensity of the Baseline fuel burned, kg CO2 per GJ | B36: ='Source Data'!$B$25/'Source Data'!$B$26*1000 -> 43.027654 | E36: Hydrogen-rich purge gas plus natural gas: well below natural gas alone (row 16)
A37: Ratio: central result / Shin estimate | B37: =B11/B35 -> 0.79223236 | E37: Shin's figure is higher by design: the imported electricity also replaces the plant's own steam-turbine power and the hydrogen-rich purge gas it stops burning is exported, so it is an upper bound for the furnace-only quantity EEpTSCA represents

Sheet Checks
A1: CHECKS: live tests on the calculation
A2: What is tested | B2: Value | C2: Result
A3: Electric efficiency is above fired efficiency (otherwise electricity use would exceed fuel use) | B3: ='Source Data'!$B$12-'Source Data'!$B$11 -> 0.072 | C3: =IF(B3>0,"PASS","FAIL") -> PASS
A4: Central result lies between the low-duty and high-duty results | B4: =Calcs!B11 -> 18893819 | C4: =IF(AND(B4>=Calcs!C11,B4<=Calcs!D11),"PASS","FAIL") -> PASS
A5: Implied furnace CO2 intensity is within 50-110% of natural gas | B5: =Calcs!B17 -> 0.92353523 | C5: =IF(AND(B5>0.5,B5<1.1),"PASS","FAIL") -> PASS
A6: Stack CO2 per tonne ethylene is positive and below 1 | B6: =Calcs!B10 -> 0.57360406 | C6: =IF(AND(B6>0,B6<1),"PASS","FAIL") -> PASS
A7: Result is within 25% of the simple physical estimate: 1 tonne CO2 of natural gas fuel = 1,000,000 / PEI BTU | B7: =Calcs!B11/(1000000/'Source Data'!$B$17)-1 -> 0.0025060372 | C7: =IF(ABS(B7)<0.25,"PASS","FAIL") -> PASS
A8: Result is within 25% of the independent Layritz et al. inventory estimate | B8: =Calcs!B23-1 -> 0.036230534 | C8: =IF(ABS(B8)<0.25,"PASS","FAIL") -> PASS
A9: Exported value equals the central case of the efficiency sensitivity block | B9: =Calcs!B11/Calcs!D27-1 -> 0 | C9: =IF(ABS(B9)<0.000000001,"PASS","FAIL") -> PASS
A10: Result lies below the Shin et al. whole-plant figure (an upper bound) and above 60% of it | B10: =Calcs!B37 -> 0.79223236 | C10: =IF(AND(B10>0.6,B10<=1),"PASS","FAIL") -> PASS

Sheet EEpTSCA
A1: Unit: BTU electricity per metric ton CO2 abated | B1: Electricity per Ton of Stack CO2 Abated
A2: electricity per ton of stack CO2 abated | B2: =Calcs!B11 -> 18893819
