Workbook

Sheet About
A1: ECCpTSCA Electrified Heat Capital Cost per Ton of Stack CO2 Abated
A3: Sources: | B3: US ethane-cracker techno-economics with an electrically heated cracker case | D3: Premium of an electrified cracker over a gas-fired cracker (cross-check only)
B4: Shin, Lin, Lai, Ibrahim and Zang (MIT Energy Initiative) | D4: Dataintelo (market research)
B5: Decarbonization approaches for ethylene production: comparative techno-economic and life-cycle analysis, Green Chemistry 27:3655-3675 (open access, CC-BY-NC) and its Electronic Supplementary Information | D5: Electrified Ethylene Cracking Furnace Market Size, Share and Forecast Report 2025 to 2034
B6: 2025 | D6: 2025
B7: https://doi.org/10.1039/d4gc04538f | D7: https://www.dataintelo.com/report/electrified-ethylene-cracking-furnace-market
B8: Paper and ESI read 2026-10-30 (PDFs supplied by Dan; the site refuses automated download). ESI Table S8 (Electrical heating case) and Table S6 (Baseline) list the cracker unit at the same $370,332,924 installed (2019 USD, installation factor 2.47, scaling exponent 0.67), so the study assumes no capital premium for electric heating; the Electrical heating plant totals $533,973,722 against $626,044,269 for the Baseline because the boiler and steam turbine disappear. ESI Table S10: reference year 2019, operating capacity factor 90%, design capacity 1.00 million t/yr, 40-year life, 8% after-tax real IRR. Section 3.3.1 (p.3667): the cracker is the largest cost item at $135 per kg-ethylene per day in every case. Capital costs are scaled from NREL, NETL and PNNL studies (Section 2.4). Held on the Source Data tab (rows 4-9). | D8: Page text read 2026-10-29: the capital cost premium for a fully electrified world-scale cracker is "estimated in the range of 15 to 30%", about $150 to $400 million of extra capital for a typical 1 Mt/yr ethylene unit, attributed only to "engineering studies completed through 2025" with no named study, baseline cost or dollar year. A commercial market-report estimate, not an engineering source. Used only on the Calcs cross-check rows 29-32; not in the exported value.
B10: Cost of resistive heating equipment | D10: Published study assuming no electric-furnace capital premium (context)
B11: Energy Innovation (Rissman and Gimon) | D11: Layritz, Dolganova, Finkbeiner, Luderer, Penteado, Ueckerdt and Repke (PIK / TU Berlin)
B12: Thermal Batteries: Decarbonizing U.S. Industry While Supporting a High-Renewables Grid, p.15 | D12: The potential of direct steam cracker electrification and carbon capture & utilization via oxidative coupling of methane as decarbonization strategies for ethylene production, Applied Energy 296:117049 (preprint)
B13: 2023 | D13: 2021
B14: https://energyinnovation.org/report/thermal-batteries-decarbonizing-u-s-industry-while-supporting-a-high-renewables-grid/ | D14: https://publications.pik-potsdam.de/pubman/item/item_25669_4/component/file_25682/25669_preprint.pdf
B15: Charging equipment $100 per kW of electrical input, 2023 USD. A thermal battery heater, not a cracker furnace: it is used as a lower-bound equipment price. Unclear whether equipment-only or installed. Held on the Source Data tab (row 11). | D15: Preprint read 2026-10-29. Table 2: steam cracking capital cost 1,488 EUR per tonne of ethylene per year (average of five reported values, currency year not stated), operating cost 76.42 EUR/t/yr, 30-year life. Appendix A.3 footnote 3 and Section 2: the electrified cracker uses the same capital cost and furnace efficiency as the conventional one, because no specific data exist. Held on the Source Data tab (row 28) and Calcs row 34 as context; not in the exported value.
B17: Lang factor, whole-plant cost comparison and on-stream hours (context) | D17: Electricity required per tonne of CO2 abated
B18: Idaho National Laboratory (Hu, Ding, Knighton, Wendt and Boardman) | D18: Energy Policy Simulator input files (this repository)
B19: Technoeconomic Analysis on an Electrochemical Nonoxidative Deprotonation Process for Ethylene Production from Ethane (INL/EXT-19-56936) | D19: InputData/indst/_chemicals/EEpTSCA/EEpTSCA.csv
B20: 2020 | D20: 2026
B21: https://inldigitallibrary.inl.gov/sites/sti/sti/Sort_21795.pdf | D21: https://github.com/EnergyInnovation/eps-us
B22: Table 15 (p.29): Lang factor 3.282 (Wain 2014), used in Method 1. Table 14 (p.28): steam cracker total capital investment $1,110 million for 830,132 t/yr ethylene (PetroChemical Update 2018 data, U.S. Gulf Coast), shown on Calcs row 33 as context only: it is about twice the Shin et al. total plant cost per tonne because TCI includes owner's costs, contingency and interest. Table 27 (p.62): on-stream factor 91% (8,000 operating hours per year), stated for the LDPE unit of the same complex; corroborates the 90% capacity factor used. | D22: The exported EEpTSCA value, pasted on the Source Data tab (row 17), sizes the electric furnace in Method 1. If EEpTSCA changes, paste the new value.
B24: Dollar-year conversion | D24: Demonstration furnace scale and funding (context)
B25: U.S. Bureau of Labor Statistics | D25: BASF, SABIC and Linde
B26: Consumer Price Index for All Urban Consumers (CPI-U), annual averages | D26: Press release P-24-177: BASF, SABIC and Linde inaugurate the world's first large-scale electrically heated steam cracking furnace
B27: 2024 | D27: 2024
B28: https://www.bls.gov/cpi/ | D28: https://www.basf.com/global/en/media/news-releases/2024/04/p-24-177
B29: Annual averages 2012 = 229.594, 2018 = 251.107, 2019 = 255.657, 2023 = 304.702 (2012 and 2023 as used in the TBCC workbook). Converts all costs to 2012 USD. | D29: Two demonstration furnaces at Ludwigshafen, about 6 MW electric and about 4 tonnes of feed per hour combined, inaugurated April 2024; the German Federal Ministry for Economic Affairs and Climate Action funded EUR 14.8 million under its Decarbonisation in Industry programme (trade-press summaries of the release). No total project cost is published, so nothing is taken from it numerically.
B31: US petrochemical and ammonia process CO2 (2023) | D31: Electric cracking furnace status (context)
B32: U.S. Environmental Protection Agency | D32: ISPT (Shell, Dow, TNO)
B33: Inventory of U.S. Greenhouse Gas Emissions and Sinks: 1990-2023 (EPA 430-R-25-003), Chapter 4 Industrial Processes and Product Use: Petrochemical Production (Tables 4-55 to 4-57) and Ammonia Production (Tables 4-23 and 4-24) | D33: Public report: e-Missi0n electric steam cracker furnace development
B34: 2025 | D34: 2026
B35: https://www.epa.gov/ghgemissions/inventory-us-greenhouse-gas-emissions-and-sinks | D35: https://ispt.eu/publications/public-report-e-missi0n/
B36: Tables 4-55/4-56 give 2023 petrochemical CO2 by product in MMT CO2 Eq. and kt (total 30,540 kt: carbon black 2,550; ethylene 22,600; ethylene dichloride 460; ethylene oxide 1,730; methanol 2,130; acrylonitrile 1,070). Table 4-57 gives production (ethylene 2023: 39,400 kt). The ethylene figure is the CO2 from burning ethylene process off-gas (the GHGRP optional combustion method), so it excludes CO2 from any natural gas make-up fuel. Ammonia (Table 4-24): 12,211 kt CO2 in 2023, net of CO2 recovered for urea. Held verbatim on the Source Data tab. Do not use these as a facility-level or non-US figure. | D36: Reports that direct electric heating of cracker tubes gave performance comparable to gas-fired furnaces, that electric cracking competes at electricity below about 67 EUR/MWh or a CO2 price above about 235 EUR/t, and that silicon carbide heating elements are unlikely to meet the targeted four-year lifetime; gives no electricity per tonne, efficiency or capital cost, so nothing is taken from it numerically.
A39: Notes:
A40: DRAFT, narrowed (research pass 2026-10-30) | B40: The exported value is still a judgment, but it now sits between two published anchors instead of resting on a market report. Shin et al. (2025), an open-access MIT techno-economic model of a 1 Mt/yr U.S. ethane cracker, give the electrically heated cracker the same installed cost as the fired one ($370 million, ESI Tables S6 and S8); Layritz et al. (2021) make the same parity assumption for Europe. So electrifying costs at least the electric heating equipment (Method 1, from thermal-battery heater prices) and at most a new cracker unit at parity cost (Method 2). The export is their simple average (the weight is the one JUDGMENT row on Source Data); the two differ by about a factor of three. The market report's 15-30% premium, applied to the Shin plant cost, lands between the two methods, which is reassuring but not independent evidence. No source gives the cost of electrifying an existing cracker directly; a technology-vendor or engineering-study retrofit cost would replace this. Verify against primary sources before relying on this in a work product.
A41: Purpose and layout | B41: ECCpTSCA is the up-front capital the chemicals module charges for electrified furnace heat in the "other stack" CO2 pool, per metric ton of CO2 per year abated, in 2012 U.S. dollars (the dollar year EPS uses for capital costs, as in the thermal battery capital cost input). The Source Data tab holds the published and assumed inputs, Calcs builds the two estimates, the exported value and the cross-checks, Checks tests it, and the last tab, ECCpTSCA, is exactly what is written to ECCpTSCA.csv (same layout as CGSCR.csv).
A42: Method in plain words | B42: Method 1 starts from the electricity the furnaces need (from the EEpTSCA input), turns it into kilowatts of heating equipment using the plant's operating hours (90% of the year, Shin et al.), prices that equipment at $100/kW (the figure used for thermal battery charging equipment in EPS) and multiplies by the Lang factor of 3.28 for installation and indirect costs. Method 2 takes the installed cost of the cracker unit in Shin et al. ($370 per tonne per year of ethylene capacity, 2019 dollars, the same for fired and electric heating) as the cost of replacing the furnaces outright. Both are divided by the stack CO2 per tonne of ethylene (0.574 t, U.S. inventory) to express them per tonne of CO2 per year, and converted to 2012 dollars with the consumer price index. The export averages the two.
A43: Why two methods | B43: Method 1 probably understates cost, because cracker tubes need much higher heat flux and special alloys than a thermal battery heater, and the pilot furnaces report short element lifetimes. Method 2 probably overstates it for a retrofit, because a plant that replaces furnaces at the end of their life would have paid for new fired furnaces anyway, and EPS does not credit that avoided spend. The truth is likely between them, so the file uses the average and reports the range.
A44: What this does not include | B44: Operating and maintenance cost is not part of this capital figure. The cost of any new power supply, grid connection or generation is not included. The cost of the furnaces that are replaced is not credited. Shin et al. show the electric plant's total cost is lower than the fired plant's because the boiler and steam turbine disappear; that saving is not credited either.
A45: Regional adaptation | B45: Method 1 depends only on EEpTSCA and equipment prices, so it carries over once EEpTSCA is rebuilt for the region. Method 2 needs a regional cracker capital cost in place of the U.S. Gulf Coast figure (Layritz et al. give 1,488 EUR per tonne per year for a whole European plant; the cracker unit is about 59% of plant cost in Shin et al.).
A46: Export format | B46: Unit line and label in the first row, one data row below, as in CGSCR.csv. CSV values computed in Python from the same formulas; recalc in Excel to verify.

Sheet Source Data
A1: SOURCE DATA: values pasted as published (confidence flag in column E: DIRECT = read in the source text; MARKET REPORT = read on a commercial market-report page that names no underlying study; JUDGMENT = assumption with no source in hand)
A3: Item | B3: Value | C3: Unit | D3: Source and location | E3: Confidence
A4: Shin et al.: installed cost of the cracker unit (furnaces, coils, quench-side heat recovery) | B4: 370332924 | C4: $ (2019 USD) | D4: Shin et al. (2025) Green Chemistry 27:3655, ESI Table S8 (Electrical heating case) and Table S6 (Baseline): the same $370,332,924 in both, i.e. no capital premium for electric heating; installation factor 2.47, scaling exponent 0.67 | E4: DIRECT
A5: Shin et al.: plant design capacity | B5: 1000000 | C5: t ethylene per yr | D5: Same, ESI Table S10 (Plant Design Capacity 1.00 million t/yr; output 0.90 at the capacity factor below) | E5: DIRECT
A6: Shin et al.: operating capacity factor | B6: 0.9 | C6: fraction | D6: Same, ESI Table S10 (Operating Capacity Factor 90.0%) | E6: DIRECT
A7: Hours per year | B7: 8760 | C7: hours/yr | D7: Calendar | E7: DIRECT
A8: Shin et al.: total plant cost, Baseline case (context) | B8: 626044269 | C8: $ (2019 USD) | D8: Same, ESI Table S6 total | E8: DIRECT
A9: Shin et al.: total plant cost, Electrical heating case (context) | B9: 533973722 | C9: $ (2019 USD) | D9: Same, ESI Table S8 total (no boiler or steam turbine; smaller cooling tower; adds PSA for hydrogen export) | E9: DIRECT
A10: Lang factor (total installed cost per unit of major equipment cost) | B10: 3.282 | C10: dimensionless | D10: INL/EXT-19-56936 Table 15 (p.29): updated Lang factor 3.28 (Wain 2014) | E10: DIRECT
A11: Resistive charging (heating) equipment cost | B11: 100 | C11: $ per kW-in (2023 USD) | D11: Rissman and Gimon (2023), Thermal Batteries, p.15 (the same value used in the EPS thermal battery capital cost input TBCC) | E11: DIRECT
A12: CPI-U annual average, 2012 | B12: 229.594 | C12: index | D12: U.S. Bureau of Labor Statistics (as used in the TBCC workbook) | E12: DIRECT
A13: CPI-U annual average, 2019 | B13: 255.657 | C13: index | D13: U.S. Bureau of Labor Statistics, CPI-U all items, annual average 2019 | E13: DIRECT
A14: CPI-U annual average, 2023 | B14: 304.702 | C14: index | D14: U.S. Bureau of Labor Statistics (as used in the TBCC workbook) | E14: DIRECT
A15: CO2 from burning ethylene process off-gas, 2023 | B15: 22600 | C15: kt CO2 | D15: US GHGI 2025 (EPA 430-R-25-003) Table 4-56 (p.4-74) | E15: DIRECT
... A28: Layritz et al.: steam cracker capital cost (context) | B28: 1488 | C28: EUR per (t ethylene/yr), year not stated | D28: Layritz et al. (2021) preprint Table 2, average of five reported values; the electrified cracker is given the same capital cost (no furnace premium), Appendix A.3 footnote 3 | E28: DIRECT

Sheet Calcs
A1: CALCULATIONS: capital cost of electrifying cracker furnace heat, per tonne per year of stack CO2 abated, in 2012 dollars
A2: Question this tab answers: what does it cost, as up-front capital, to electrify the furnace heat that now burns off-gas, for each tonne per year of CO2 that this stops? Published plant models (Shin et al. 2025; Layritz et al. 2021) give an electrically heated cracker the same capital cost as a fired one, so the cost of electrifying is bounded below by the electric heating equipment alone (Method 1) and above by replacing the whole cracker unit at that parity cost (Method 2). The export is a weighted average of the two; a market report's premium is shown as a cross-check. All figures are converted to 2012 dollars with the consumer price index, the way the EPS thermal battery capital cost is.
A4: Stack CO2 per tonne of ethylene, t CO2 per t ethylene | B4: ='Source Data'!$B$15/'Source Data'!$B$16 -> 0.57360406 | E4: GHGI 2023: off-gas combustion CO2 / production
A6: Method 1 (low): electric heating equipment sized to the electricity needed
A7: Electricity per tonne of CO2 abated, kWh | B7: ='Source Data'!$B$17/'Source Data'!$B$18 -> 5537.2344 | E7: EEpTSCA BTU / BTU per kWh
A8: Operating hours per year | B8: ='Source Data'!$B$6*'Source Data'!$B$7 -> 7884 | E8: Capacity factor x 8,760 (Shin et al. Table S10); INL quotes 8,000
A9: Furnace electric power per (t CO2 per yr), kW | B9: =B7/B8 -> 0.70233821 | E9: kWh per t / operating hours
A10: Heating equipment cost, 2023 USD per (t CO2/yr) | B10: =B9*'Source Data'!$B$11 -> 70.233821 | E10: kW x $100 per kW
A11: Installed cost (equipment x Lang factor), 2023 USD per (t CO2/yr) | B11: =B10*'Source Data'!$B$10 -> 230.5074 | E11: Adds installation, bulk materials and indirect costs
A12: Method 1 in 2012 USD per (t CO2/yr) | B12: =B11*'Source Data'!$B$12/'Source Data'!$B$14 -> 173.68811 | E12: x CPI 2012 / CPI 2023
A14: Method 2 (high): replace the whole cracker unit with an electric one at parity cost (Shin et al. 2025)
A15: Cracker unit installed cost per tonne per year of design capacity, 2019 USD | B15: ='Source Data'!$B$4/'Source Data'!$B$5 -> 370.33292 | E15: ESI Table S8 cracker / 1.00 Mt/yr (equals the paper's $135 per kg-ethylene per day)
A16: Same per (t CO2 per yr), 2019 USD | B16: =B15/B4 -> 645.62466 | E16: / stack CO2 per tonne of ethylene
A17: Method 2 in 2012 USD per (t CO2/yr) | B17: =B16*'Source Data'!$B$12/'Source Data'!$B$13 -> 579.80633 | E17: x CPI 2012 / CPI 2019
A18: Context: Shin et al. total plant cost per (t ethylene/yr), Baseline, 2019 USD | B18: ='Source Data'!$B$8/'Source Data'!$B$5 -> 626.04427 | E18: Whole plant; the cracker unit is 59% of it
A19: Context: Shin et al. total plant cost per (t ethylene/yr), Electrical heating, 2019 USD | B19: ='Source Data'!$B$9/'Source Data'!$B$5 -> 533.97372 | E19: Lower than Baseline: no boiler or turbine, smaller cooling tower
A21: Result: exported value and range (2012 USD per (t CO2 per yr))
A22: ECCpTSCA: ELECTRIFIED HEAT CAPITAL COST PER TON OF STACK CO2 ABATED (weighted average of Methods 1 and 2) | B22: ='Source Data'!$B$19*B12+(1-'Source Data'!$B$19)*B17 -> 376.74722
A23: Low end of the range (Method 1) | B23: =MIN(B12,B17) -> 173.68811
A24: High end of the range (Method 2) | B24: =MAX(B12,B17) -> 579.80633
A25: Ratio of the high end to the low end | B25: =B24/B23 -> 3.3382038
A27: Cross-checks (not used in the export)
B28: Low premium | C28: Mid premium | D28: High premium
A29: Market-report premium (15-30%) applied to Shin et al. Baseline total plant cost, USD per (t ethylene/yr), 2019 USD | B29: =$B$18*'Source Data'!$B$20 -> 93.90664 | C29: =$B$18*AVERAGE('Source Data'!$B$20,'Source Data'!$B$21) -> 140.85996 | D29: =$B$18*'Source Data'!$B$21 -> 187.81328
A30: Same per (t CO2/yr) in 2012 USD | B30: =B29/$B$4*'Source Data'!$B$12/'Source Data'!$B$13 -> 147.02356 | C30: =C29/$B$4*'Source Data'!$B$12/'Source Data'!$B$13 -> 220.53534 | D30: =D29/$B$4*'Source Data'!$B$12/'Source Data'!$B$13 -> 294.04712 | E30: Lies between Method 1 and Method 2 (Checks tab)
A31: Market-report premium as a share of the Shin et al. cracker unit cost | B31: =B29/$B$15 -> 0.25357357 | C31: =C29/$B$15 -> 0.38036035 | D31: =D29/$B$15 -> 0.50714713 | E31: A 15-30% whole-plant premium is 25-51% of the cracker unit, i.e. between heater-only and full replacement
A32: Market report's own dollar range, USD per (t CO2/yr), dollar year not stated | B32: ='Source Data'!$B$22/$B$4 -> 261.50442 | D32: ='Source Data'!$B$23/$B$4 -> 697.34513
A33: INL total capital investment per (t ethylene/yr), 2018 data (whole plant, different cost scope) | B33: ='Source Data'!$B$24*1000000/'Source Data'!$B$25 -> 1337.1367 | E33: About twice the Shin et al. total plant cost: TCI includes owner's costs, contingency and interest that TPC does not
A34: Layritz et al. whole-plant capital per (t ethylene/yr), EUR, no premium for the electric furnace | B34: ='Source Data'!$B$28 -> 1488
A35: Operating hours: Shin et al. capacity factor basis vs INL on-stream figure | B35: =B8 -> 7884 | C35: ='Source Data'!$B$27 -> 8000

Sheet Checks
A1: CHECKS: live tests on the calculation
A2: What is tested | B2: Value | C2: Result
A3: Exported value lies inside the range from the two methods | B3: =Calcs!B22 -> 376.74722 | C3: =IF(AND(B3>=Calcs!B23,B3<=Calcs!B24),"PASS","FAIL") -> PASS
A4: Weight on Method 1 is between 0 and 1 | B4: ='Source Data'!$B$19 -> 0.5 | C4: =IF(AND(B4>=0,B4<=1),"PASS","FAIL") -> PASS
A5: Market-report mid premium (cross-check) lies between Method 1 and Method 2 | B5: =Calcs!C30 -> 220.53534 | C5: =IF(AND(B5>=Calcs!B23,B5<=Calcs!B24),"PASS","FAIL") -> PASS
A6: Shin et al. electrical-heating plant costs less than the Baseline plant (parity cracker, no boiler) | B6: ='Source Data'!$B$9/'Source Data'!$B$8 -> 0.85293285 | C6: =IF(B6<1,"PASS","FAIL") -> PASS
A7: 2012 values are below the nominal-year values (deflation direction is right) | B7: =Calcs!B12/Calcs!B11 -> 0.75350342 | C7: =IF(B7<1,"PASS","FAIL") -> PASS
A8: Stack CO2 per tonne ethylene is positive and below 1 | B8: =Calcs!B4 -> 0.57360406 | C8: =IF(AND(B8>0,B8<1),"PASS","FAIL") -> PASS
A9: Operating hours are below 8,760 and within 5% of the INL figure | B9: =Calcs!B8 -> 7884 | C9: =IF(AND(B9<=8760,ABS(B9/'Source Data'!$B$27-1)<0.05),"PASS","FAIL") -> PASS

Sheet ECCpTSCA
A1: Unit: 2012 USD per (metric ton CO2 per year) of stack CO2 abated | B1: Electrified Heat Capital Cost
A2: electrified heat capital cost per ton of stack CO2 abated | B2: =Calcs!B22 -> 376.74722
