Workbook
Name acres_per_hectare: #REF!
Name acres_per_hectare: #REF!
Name acres_per_million_hectares: #REF!
Name acres_per_million_hectares: #REF!
Name acres_per_million_hectares: #REF!
Name C_to_CO2: #REF!
Name CH4_Ar4_to_AR5: #REF!
Name CH4_Ar4_to_AR5: #REF!
Name CH4_to_CO2e: #REF!
Name dollars_2009_2012: #REF!
Name gal_per_barrel: #REF!
Name grams_per_ton: #REF!
Name grams_per_ton: #REF!
Name HHV_Adjust: #REF!
Name IQ_CH: 110000
Name IQ_CQ: 5000
Name IQ_CY: 10000
Name IQ_DAILY: 500000
Name IQ_FH: 100000
Name IQ_FQ: 500
Name IQ_FY: 1000
Name IQ_LTM: 2000
Name IQ_MONTH: 15000
Name IQ_NTM: 6000
Name IQ_WEEK: 50000
Name IQ_YTD: 3000
Name metricton_to_shortton: #REF!
Name million: #REF!
Name N2O_to_CO2e: #REF!
Name unit_conv: #REF!

Sheet About
A1: PLANAbPiaSY Potential Land Area Newly Affected by Policy in a Single Year
A3: Sources: | B3: Forest management and afforestation/reforestation potential CO2 abatement
B4: EPA
B5: 2024
B6: Forestry and Agriculture Sector Mitigation Analysis
B7: https://www.epa.gov/climate-change/climate-economic-analysis#Forestry%20and%20Agriculture%20Mitigation
B8: Figure 3-8
B10: CO2 per land unit: reforestation and grasslands
B11: Nature4Climate
B12: US Carbon Mapper
B13: https://nature4climate.org/u-s-carbon-mapper/
B14: Data underlying the online mapper send by Joe Fargione upon request September 22, 2021
B16: Peatland Restoration
B17: ICF International
B18: 2016
B19: Managing Agricultural Land for Greenhouse Gas Mitigation within the United States
B20: https://www.usda.gov/sites/default/files/documents/White_Paper_WEB71816.pdf
B21: pages 36-37
B23: other: see file CApULAbIFM for forest management CO2 per acre and BLAPE for IRA impacts
A25: Notes
A26: Our main data source is EPA's 2024 report which compiles an integrated abatement potential
A27: across the agriculture and forestry sectors. We map their abatement activities to the forest
A28: management and afforestation/reforestation levers. We do not use the forest set aside or
A29: deforestation levers. The EPA does not cover grasslands or wetlands, so we use separate TNC
A30: and ICF data for those ecosystems.
A32: We also adjust this variable to remove the potential implemented as part of Inflation Reduction Act
A33: calculations (see file land/BLAPE for methodology).

Sheet EPA land and ag potential
A1: Average annual change in GHG flux in the land sector from the baseline across scenarios and models by GHG category. Results are presented in MtCO2e yr-1 from 2025 to 2050. Baseline GHG emissions from the land sector by GHG category are presented in Figure 31. GHG categories are described in Figure 23. FASOMGHG includes all GHG categories, while GLOBIOM does not include forest products, forest soils, or cropland CO2. As the results are presented in atmospheric accounting terms, negative values equal more mitigation than the Baseline. GTM is not included because it does not explicitly model emissions from agriculture. Initial values differ between models because they measure the change from baseline values and models respond differently to different GHG prices. See Box 2 for further discussion on movement of soil carbon across land use categories when LUC land use change occurs in FASOMGHG.
A2: Figure | B2: Position | C2: Year | D2: Model | E2: Group | F2: Growth.Rate | G2: Starting.Price | H2: Value | I2: Units | K2: EPS Map
A3: Fig_3.8 | B3: Bar | C3: 2025 | D3: FASOMGHG | E3: Ag Soils | F3: 3% Growth | G3: $50 | H3: 126.9 | I3: MtCO2e/yr | K3: =INDEX('EPA land and ag calcs'!$G$7:$G$14,MATCH('EPA land and ag potential'!E3,'EPA land and ag calcs'!$A$7:$A$15,0)) -> afforestation and reforestation
A4: Fig_3.8 | B4: Bar | C4: 2035 | D4: FASOMGHG | E4: Ag Soils | F4: 3% Growth | G4: $50 | H4: 116.2 | I4: MtCO2e/yr | K4: =INDEX('EPA land and ag calcs'!$G$7:$G$14,MATCH('EPA land and ag potential'!E4,'EPA land and ag calcs'!$A$7:$A$15,0)) -> afforestation and reforestation
A5: Fig_3.8 | B5: Bar | C5: 2045 | D5: FASOMGHG | E5: Ag Soils | F5: 3% Growth | G5: $50 | H5: 78.6 | I5: MtCO2e/yr | K5: =INDEX('EPA land and ag calcs'!$G$7:$G$14,MATCH('EPA land and ag potential'!E5,'EPA land and ag calcs'!$A$7:$A$15,0)) -> afforestation and reforestation
A6: Fig_3.8 | B6: Bar | C6: 2055 | D6: FASOMGHG | E6: Ag Soils | F6: 3% Growth | G6: $50 | H6: 49.6 | I6: MtCO2e/yr | K6: =INDEX('EPA land and ag calcs'!$G$7:$G$14,MATCH('EPA land and ag potential'!E6,'EPA land and ag calcs'!$A$7:$A$15,0)) -> afforestation and reforestation
A7: Fig_3.8 | B7: Bar | C7: 2025 | D7: FASOMGHG | E7: Ag Soils | F7: 1% Growth | G7: $50 | H7: 39.4 | I7: MtCO2e/yr
A8: Fig_3.8 | B8: Bar | C8: 2035 | D8: FASOMGHG | E8: Ag Soils | F8: 1% Growth | G8: $50 | H8: 17.1 | I8: MtCO2e/yr
A9: Fig_3.8 | B9: Bar | C9: 2045 | D9: FASOMGHG | E9: Ag Soils | F9: 1% Growth | G9: $50 | H9: 8.9 | I9: MtCO2e/yr
A10: Fig_3.8 | B10: Bar | C10: 2055 | D10: FASOMGHG | E10: Ag Soils | F10: 1% Growth | G10: $50 | H10: 4.2 | I10: MtCO2e/yr
A11: Fig_3.8 | B11: Bar | C11: 2025 | D11: FASOMGHG | E11: Ag Soils | F11: 3% Growth | G11: $5 | H11: 24 | I11: MtCO2e/yr | K11: =INDEX('EPA land and ag calcs'!$G$7:$G$14,MATCH('EPA land and ag potential'!E11,'EPA land and ag calcs'!$A$7:$A$15,0)) -> afforestation and reforestation
A12: Fig_3.8 | B12: Bar | C12: 2035 | D12: FASOMGHG | E12: Ag Soils | F12: 3% Growth | G12: $5 | H12: 38.8 | I12: MtCO2e/yr | K12: =INDEX('EPA land and ag calcs'!$G$7:$G$14,MATCH('EPA land and ag potential'!E12,'EPA land and ag calcs'!$A$7:$A$15,0)) -> afforestation and reforestation
A13: Fig_3.8 | B13: Bar | C13: 2025 | D13: FASOMGHG | E13: Cropland Non-CO2 | F13: 3% Growth | G13: $50 | H13: -2.9 | I13: MtCO2e/yr | K13: =INDEX('EPA land and ag calcs'!$G$7:$G$14,MATCH('EPA land and ag potential'!E13,'EPA land and ag calcs'!$A$7:$A$15,0)) -> *handled in agriculture files
A14: Fig_3.8 | B14: Bar | C14: 2035 | D14: FASOMGHG | E14: Cropland Non-CO2 | F14: 3% Growth | G14: $50 | H14: -6.6 | I14: MtCO2e/yr | K14: =INDEX('EPA land and ag calcs'!$G$7:$G$14,MATCH('EPA land and ag potential'!E14,'EPA land and ag calcs'!$A$7:$A$15,0)) -> *handled in agriculture files
A15: Fig_3.8 | B15: Bar | C15: 2045 | D15: FASOMGHG | E15: Cropland Non-CO2 | F15: 3% Growth | G15: $50 | H15: -9.2 | I15: MtCO2e/yr | K15: =INDEX('EPA land and ag calcs'!$G$7:$G$14,MATCH('EPA land and ag potential'!E15,'EPA land and ag calcs'!$A$7:$A$15,0)) -> *handled in agriculture files
A16: Fig_3.8 | B16: Bar | C16: 2055 | D16: FASOMGHG | E16: Cropland Non-CO2 | F16: 3% Growth | G16: $50 | H16: -11.1 | I16: MtCO2e/yr | K16: =INDEX('EPA land and ag calcs'!$G$7:$G$14,MATCH('EPA land and ag potential'!E16,'EPA land and ag calcs'!$A$7:$A$15,0)) -> *handled in agriculture files
A17: Fig_3.8 | B17: Bar | C17: 2025 | D17: FASOMGHG | E17: Cropland Non-CO2 | F17: 1% Growth | G17: $50 | H17: -4.5 | I17: MtCO2e/yr
A18: Fig_3.8 | B18: Bar | C18: 2035 | D18: FASOMGHG | E18: Cropland Non-CO2 | F18: 1% Growth | G18: $50 | H18: -7.4 | I18: MtCO2e/yr
A19: Fig_3.8 | B19: Bar | C19: 2045 | D19: FASOMGHG | E19: Cropland Non-CO2 | F19: 1% Growth | G19: $50 | H19: -9.7 | I19: MtCO2e/yr
A20: Fig_3.8 | B20: Bar | C20: 2055 | D20: FASOMGHG | E20: Cropland Non-CO2 | F20: 1% Growth | G20: $50 | H20: -11.2 | I20: MtCO2e/yr
A21: Fig_3.8 | B21: Bar | C21: 2025 | D21: FASOMGHG | E21: Cropland Non-CO2 | F21: 3% Growth | G21: $5 | H21: -0.2 | I21: MtCO2e/yr | K21: =INDEX('EPA land and ag calcs'!$G$7:$G$14,MATCH('EPA land and ag potential'!E21,'EPA land and ag calcs'!$A$7:$A$15,0)) -> *handled in agriculture files
A22: Fig_3.8 | B22: Bar | C22: 2035 | D22: FASOMGHG | E22: Cropland Non-CO2 | F22: 3% Growth | G22: $5 | H22: -0.9 | I22: MtCO2e/yr | K22: =INDEX('EPA land and ag calcs'!$G$7:$G$14,MATCH('EPA land and ag potential'!E22,'EPA land and ag calcs'!$A$7:$A$15,0)) -> *handled in agriculture files
A23: Fig_3.8 | B23: Bar | C23: 2025 | D23: FASOMGHG | E23: Cropland CO2 | F23: 3% Growth | G23: $50 | H23: -0.9 | I23: MtCO2e/yr | K23: =INDEX('EPA land and ag calcs'!$G$7:$G$14,MATCH('EPA land and ag potential'!E23,'EPA land and ag calcs'!$A$7:$A$15,0)) -> *handled in agriculture files
A24: Fig_3.8 | B24: Bar | C24: 2035 | D24: FASOMGHG | E24: Cropland CO2 | F24: 3% Growth | G24: $50 | H24: -4.8 | I24: MtCO2e/yr | K24: =INDEX('EPA land and ag calcs'!$G$7:$G$14,MATCH('EPA land and ag potential'!E24,'EPA land and ag calcs'!$A$7:$A$15,0)) -> *handled in agriculture files
A25: Fig_3.8 | B25: Bar | C25: 2045 | D25: FASOMGHG | E25: Cropland CO2 | F25: 3% Growth | G25: $50 | H25: -9.3 | I25: MtCO2e/yr | K25: =INDEX('EPA land and ag calcs'!$G$7:$G$14,MATCH('EPA land and ag potential'!E25,'EPA land and ag calcs'!$A$7:$A$15,0)) -> *handled in agriculture files
A26: Fig_3.8 | B26: Bar | C26: 2055 | D26: FASOMGHG | E26: Cropland CO2 | F26: 3% Growth | G26: $50 | H26: -12.5 | I26: MtCO2e/yr | K26: =INDEX('EPA land and ag calcs'!$G$7:$G$14,MATCH('EPA land and ag potential'!E26,'EPA land and ag calcs'!$A$7:$A$15,0)) -> *handled in agriculture files
A27: Fig_3.8 | B27: Bar | C27: 2025 | D27: FASOMGHG | E27: Cropland CO2 | F27: 1% Growth | G27: $50 | H27: -3.5 | I27: MtCO2e/yr
A28: Fig_3.8 | B28: Bar | C28: 2035 | D28: FASOMGHG | E28: Cropland CO2 | F28: 1% Growth | G28: $50 | H28: -6 | I28: MtCO2e/yr
A29: Fig_3.8 | B29: Bar | C29: 2045 | D29: FASOMGHG | E29: Cropland CO2 | F29: 1% Growth | G29: $50 | H29: -9.3 | I29: MtCO2e/yr
A30: Fig_3.8 | B30: Bar | C30: 2055 | D30: FASOMGHG | E30: Cropland CO2 | F30: 1% Growth | G30: $50 | H30: -11.9 | I30: MtCO2e/yr
A31: Fig_3.8 | B31: Bar | C31: 2025 | D31: FASOMGHG | E31: Cropland CO2 | F31: 3% Growth | G31: $5 | H31: -0.4 | I31: MtCO2e/yr | K31: =INDEX('EPA land and ag calcs'!$G$7:$G$14,MATCH('EPA land and ag potential'!E31,'EPA land and ag calcs'!$A$7:$A$15,0)) -> *handled in agriculture files
A32: Fig_3.8 | B32: Bar | C32: 2035 | D32: FASOMGHG | E32: Cropland CO2 | F32: 3% Growth | G32: $5 | H32: -0.6 | I32: MtCO2e/yr | K32: =INDEX('EPA land and ag calcs'!$G$7:$G$14,MATCH('EPA land and ag potential'!E32,'EPA land and ag calcs'!$A$7:$A$15,0)) -> *handled in agriculture files
A33: Fig_3.8 | B33: Bar | C33: 2025 | D33: FASOMGHG | E33: Forest (Existing forests) | F33: 3% Growth | G33: $50 | H33: -19 | I33: MtCO2e/yr | K33: =INDEX('EPA land and ag calcs'!$G$7:$G$14,MATCH('EPA land and ag potential'!E33,'EPA land and ag calcs'!$A$7:$A$15,0)) -> forest management
A34: Fig_3.8 | B34: Bar | C34: 2035 | D34: FASOMGHG | E34: Forest (Existing forests) | F34: 3% Growth | G34: $50 | H34: -54.9 | I34: MtCO2e/yr | K34: =INDEX('EPA land and ag calcs'!$G$7:$G$14,MATCH('EPA land and ag potential'!E34,'EPA land and ag calcs'!$A$7:$A$15,0)) -> forest management
A35: Fig_3.8 | B35: Bar | C35: 2045 | D35: FASOMGHG | E35: Forest (Existing forests) | F35: 3% Growth | G35: $50 | H35: -65.7 | I35: MtCO2e/yr | K35: =INDEX('EPA land and ag calcs'!$G$7:$G$14,MATCH('EPA land and ag potential'!E35,'EPA land and ag calcs'!$A$7:$A$15,0)) -> forest management
A36: Fig_3.8 | B36: Bar | C36: 2055 | D36: FASOMGHG | E36: Forest (Existing forests) | F36: 3% Growth | G36: $50 | H36: -78 | I36: MtCO2e/yr | K36: =INDEX('EPA land and ag calcs'!$G$7:$G$14,MATCH('EPA land and ag potential'!E36,'EPA land and ag calcs'!$A$7:$A$15,0)) -> forest management
A37: Fig_3.8 | B37: Bar | C37: 2025 | D37: FASOMGHG | E37: Forest (Existing forests) | F37: 1% Growth | G37: $50 | H37: -36.5 | I37: MtCO2e/yr
A38: Fig_3.8 | B38: Bar | C38: 2035 | D38: FASOMGHG | E38: Forest (Existing forests) | F38: 1% Growth | G38: $50 | H38: -61.2 | I38: MtCO2e/yr
A39: Fig_3.8 | B39: Bar | C39: 2045 | D39: FASOMGHG | E39: Forest (Existing forests) | F39: 1% Growth | G39: $50 | H39: -62.5 | I39: MtCO2e/yr
A40: Fig_3.8 | B40: Bar | C40: 2055 | D40: FASOMGHG | E40: Forest (Existing forests) | F40: 1% Growth | G40: $50 | H40: -61.3 | I40: MtCO2e/yr
A41: Fig_3.8 | B41: Bar | C41: 2025 | D41: FASOMGHG | E41: Forest (Existing forests) | F41: 3% Growth | G41: $5 | H41: -6.9 | I41: MtCO2e/yr | K41: =INDEX('EPA land and ag calcs'!$G$7:$G$14,MATCH('EPA land and ag potential'!E41,'EPA land and ag calcs'!$A$7:$A$15,0)) -> forest management
A42: Fig_3.8 | B42: Bar | C42: 2035 | D42: FASOMGHG | E42: Forest (Existing forests) | F42: 3% Growth | G42: $5 | H42: -16 | I42: MtCO2e/yr | K42: =INDEX('EPA land and ag calcs'!$G$7:$G$14,MATCH('EPA land and ag potential'!E42,'EPA land and ag calcs'!$A$7:$A$15,0)) -> forest management
A43: Fig_3.8 | B43: Bar | C43: 2025 | D43: FASOMGHG | E43: Forest (New forests) | F43: 3% Growth | G43: $50 | I43: MtCO2e/yr | K43: =INDEX('EPA land and ag calcs'!$G$7:$G$14,MATCH('EPA land and ag potential'!E43,'EPA land and ag calcs'!$A$7:$A$15,0)) -> afforestation and reforestation
A44: Fig_3.8 | B44: Bar | C44: 2035 | D44: FASOMGHG | E44: Forest (New forests) | F44: 3% Growth | G44: $50 | H44: -57.5 | I44: MtCO2e/yr | K44: =INDEX('EPA land and ag calcs'!$G$7:$G$14,MATCH('EPA land and ag potential'!E44,'EPA land and ag calcs'!$A$7:$A$15,0)) -> afforestation and reforestation
A45: Fig_3.8 | B45: Bar | C45: 2045 | D45: FASOMGHG | E45: Forest (New forests) | F45: 3% Growth | G45: $50 | H45: -75.7 | I45: MtCO2e/yr | K45: =INDEX('EPA land and ag calcs'!$G$7:$G$14,MATCH('EPA land and ag potential'!E45,'EPA land and ag calcs'!$A$7:$A$15,0)) -> afforestation and reforestation
A46: Fig_3.8 | B46: Bar | C46: 2055 | D46: FASOMGHG | E46: Forest (New forests) | F46: 3% Growth | G46: $50 | H46: -92.6 | I46: MtCO2e/yr | K46: =INDEX('EPA land and ag calcs'!$G$7:$G$14,MATCH('EPA land and ag potential'!E46,'EPA land and ag calcs'!$A$7:$A$15,0)) -> afforestation and reforestation
A47: Fig_3.8 | B47: Bar | C47: 2025 | D47: FASOMGHG | E47: Forest (New forests) | F47: 1% Growth | G47: $50 | I47: MtCO2e/yr
A48: Fig_3.8 | B48: Bar | C48: 2035 | D48: FASOMGHG | E48: Forest (New forests) | F48: 1% Growth | G48: $50 | H48: -60.2 | I48: MtCO2e/yr
A49: Fig_3.8 | B49: Bar | C49: 2045 | D49: FASOMGHG | E49: Forest (New forests) | F49: 1% Growth | G49: $50 | H49: -86.8 | I49: MtCO2e/yr
A50: Fig_3.8 | B50: Bar | C50: 2055 | D50: FASOMGHG | E50: Forest (New forests) | F50: 1% Growth | G50: $50 | H50: -111 | I50: MtCO2e/yr
A51: Fig_3.8 | B51: Bar | C51: 2025 | D51: FASOMGHG | E51: Forest (New forests) | F51: 3% Growth | G51: $5 | I51: MtCO2e/yr | K51: =INDEX('EPA land and ag calcs'!$G$7:$G$14,MATCH('EPA land and ag potential'!E51,'EPA land and ag calcs'!$A$7:$A$15,0)) -> afforestation and reforestation
A52: Fig_3.8 | B52: Bar | C52: 2035 | D52: FASOMGHG | E52: Forest (New forests) | F52: 3% Growth | G52: $5 | H52: -3.4 | I52: MtCO2e/yr | K52: =INDEX('EPA land and ag calcs'!$G$7:$G$14,MATCH('EPA land and ag potential'!E52,'EPA land and ag calcs'!$A$7:$A$15,0)) -> afforestation and reforestation
A53: Fig_3.8 | B53: Bar | C53: 2025 | D53: FASOMGHG | E53: Forest Products | F53: 3% Growth | G53: $50 | H53: 1.6 | I53: MtCO2e/yr | K53: =INDEX('EPA land and ag calcs'!$G$7:$G$14,MATCH('EPA land and ag potential'!E53,'EPA land and ag calcs'!$A$7:$A$15,0)) -> forest management
A54: Fig_3.8 | B54: Bar | C54: 2035 | D54: FASOMGHG | E54: Forest Products | F54: 3% Growth | G54: $50 | H54: 1.6 | I54: MtCO2e/yr | K54: =INDEX('EPA land and ag calcs'!$G$7:$G$14,MATCH('EPA land and ag potential'!E54,'EPA land and ag calcs'!$A$7:$A$15,0)) -> forest management
A55: Fig_3.8 | B55: Bar | C55: 2045 | D55: FASOMGHG | E55: Forest Products | F55: 3% Growth | G55: $50 | H55: 1.6 | I55: MtCO2e/yr | K55: =INDEX('EPA land and ag calcs'!$G$7:$G$14,MATCH('EPA land and ag potential'!E55,'EPA land and ag calcs'!$A$7:$A$15,0)) -> forest management
A56: Fig_3.8 | B56: Bar | C56: 2055 | D56: FASOMGHG | E56: Forest Products | F56: 3% Growth | G56: $50 | H56: 1.3 | I56: MtCO2e/yr | K56: =INDEX('EPA land and ag calcs'!$G$7:$G$14,MATCH('EPA land and ag potential'!E56,'EPA land and ag calcs'!$A$7:$A$15,0)) -> forest management
A57: Fig_3.8 | B57: Bar | C57: 2025 | D57: FASOMGHG | E57: Forest Products | F57: 1% Growth | G57: $50 | H57: 4.1 | I57: MtCO2e/yr
A58: Fig_3.8 | B58: Bar | C58: 2035 | D58: FASOMGHG | E58: Forest Products | F58: 1% Growth | G58: $50 | H58: 3.1 | I58: MtCO2e/yr
A59: Fig_3.8 | B59: Bar | C59: 2045 | D59: FASOMGHG | E59: Forest Products | F59: 1% Growth | G59: $50 | H59: 2.9 | I59: MtCO2e/yr
A60: Fig_3.8 | B60: Bar | C60: 2055 | D60: FASOMGHG | E60: Forest Products | F60: 1% Growth | G60: $50 | H60: 2.6 | I60: MtCO2e/yr
A61: Fig_3.8 | B61: Bar | C61: 2025 | D61: FASOMGHG | E61: Forest Products | F61: 3% Growth | G61: $5 | H61: 0.7 | I61: MtCO2e/yr | K61: =INDEX('EPA land and ag calcs'!$G$7:$G$14,MATCH('EPA land and ag potential'!E61,'EPA land and ag calcs'!$A$7:$A$15,0)) -> forest management
A62: Fig_3.8 | B62: Bar | C62: 2035 | D62: FASOMGHG | E62: Forest Products | F62: 3% Growth | G62: $5 | H62: 0.3 | I62: MtCO2e/yr | K62: =INDEX('EPA land and ag calcs'!$G$7:$G$14,MATCH('EPA land and ag potential'!E62,'EPA land and ag calcs'!$A$7:$A$15,0)) -> forest management
A63: Fig_3.8 | B63: Bar | C63: 2025 | D63: FASOMGHG | E63: Forest Soils | F63: 3% Growth | G63: $50 | H63: -153.4 | I63: MtCO2e/yr | K63: =INDEX('EPA land and ag calcs'!$G$7:$G$14,MATCH('EPA land and ag potential'!E63,'EPA land and ag calcs'!$A$7:$A$15,0)) -> afforestation and reforestation
A64: Fig_3.8 | B64: Bar | C64: 2035 | D64: FASOMGHG | E64: Forest Soils | F64: 3% Growth | G64: $50 | H64: -162.2 | I64: MtCO2e/yr | K64: =INDEX('EPA land and ag calcs'!$G$7:$G$14,MATCH('EPA land and ag potential'!E64,'EPA land and ag calcs'!$A$7:$A$15,0)) -> afforestation and reforestation
A65: Fig_3.8 | B65: Bar | C65: 2045 | D65: FASOMGHG | E65: Forest Soils | F65: 3% Growth | G65: $50 | H65: -144.8 | I65: MtCO2e/yr | K65: =INDEX('EPA land and ag calcs'!$G$7:$G$14,MATCH('EPA land and ag potential'!E65,'EPA land and ag calcs'!$A$7:$A$15,0)) -> afforestation and reforestation
A66: Fig_3.8 | B66: Bar | C66: 2055 | D66: FASOMGHG | E66: Forest Soils | F66: 3% Growth | G66: $50 | H66: -125.4 | I66: MtCO2e/yr | K66: =INDEX('EPA land and ag calcs'!$G$7:$G$14,MATCH('EPA land and ag potential'!E66,'EPA land and ag calcs'!$A$7:$A$15,0)) -> afforestation and reforestation
A67: Fig_3.8 | B67: Bar | C67: 2025 | D67: FASOMGHG | E67: Forest Soils | F67: 1% Growth | G67: $50 | H67: -153.3 | I67: MtCO2e/yr
A68: Fig_3.8 | B68: Bar | C68: 2035 | D68: FASOMGHG | E68: Forest Soils | F68: 1% Growth | G68: $50 | H68: -122.9 | I68: MtCO2e/yr
A69: Fig_3.8 | B69: Bar | C69: 2045 | D69: FASOMGHG | E69: Forest Soils | F69: 1% Growth | G69: $50 | H69: -100.8 | I69: MtCO2e/yr
A70: Fig_3.8 | B70: Bar | C70: 2055 | D70: FASOMGHG | E70: Forest Soils | F70: 1% Growth | G70: $50 | H70: -92.3 | I70: MtCO2e/yr
A71: Fig_3.8 | B71: Bar | C71: 2025 | D71: FASOMGHG | E71: Forest Soils | F71: 3% Growth | G71: $5 | H71: -8.4 | I71: MtCO2e/yr | K71: =INDEX('EPA land and ag calcs'!$G$7:$G$14,MATCH('EPA land and ag potential'!E71,'EPA land and ag calcs'!$A$7:$A$15,0)) -> afforestation and reforestation
A72: Fig_3.8 | B72: Bar | C72: 2035 | D72: FASOMGHG | E72: Forest Soils | F72: 3% Growth | G72: $5 | H72: -33.7 | I72: MtCO2e/yr | K72: =INDEX('EPA land and ag calcs'!$G$7:$G$14,MATCH('EPA land and ag potential'!E72,'EPA land and ag calcs'!$A$7:$A$15,0)) -> afforestation and reforestation
A73: Fig_3.8 | B73: Bar | C73: 2025 | D73: FASOMGHG | E73: Livestock Non-CO2 | F73: 3% Growth | G73: $50 | H73: -15.2 | I73: MtCO2e/yr | K73: =INDEX('EPA land and ag calcs'!$G$7:$G$14,MATCH('EPA land and ag potential'!E73,'EPA land and ag calcs'!$A$7:$A$15,0)) -> *handled in agriculture files
A74: Fig_3.8 | B74: Bar | C74: 2035 | D74: FASOMGHG | E74: Livestock Non-CO2 | F74: 3% Growth | G74: $50 | H74: -28.6 | I74: MtCO2e/yr | K74: =INDEX('EPA land and ag calcs'!$G$7:$G$14,MATCH('EPA land and ag potential'!E74,'EPA land and ag calcs'!$A$7:$A$15,0)) -> *handled in agriculture files
A75: Fig_3.8 | B75: Bar | C75: 2045 | D75: FASOMGHG | E75: Livestock Non-CO2 | F75: 3% Growth | G75: $50 | H75: -36.3 | I75: MtCO2e/yr | K75: =INDEX('EPA land and ag calcs'!$G$7:$G$14,MATCH('EPA land and ag potential'!E75,'EPA land and ag calcs'!$A$7:$A$15,0)) -> *handled in agriculture files
A76: Fig_3.8 | B76: Bar | C76: 2055 | D76: FASOMGHG | E76: Livestock Non-CO2 | F76: 3% Growth | G76: $50 | H76: -45.2 | I76: MtCO2e/yr | K76: =INDEX('EPA land and ag calcs'!$G$7:$G$14,MATCH('EPA land and ag potential'!E76,'EPA land and ag calcs'!$A$7:$A$15,0)) -> *handled in agriculture files
A77: Fig_3.8 | B77: Bar | C77: 2025 | D77: FASOMGHG | E77: Livestock Non-CO2 | F77: 1% Growth | G77: $50 | H77: -15.5 | I77: MtCO2e/yr
A78: Fig_3.8 | B78: Bar | C78: 2035 | D78: FASOMGHG | E78: Livestock Non-CO2 | F78: 1% Growth | G78: $50 | H78: -21.9 | I78: MtCO2e/yr
A79: Fig_3.8 | B79: Bar | C79: 2045 | D79: FASOMGHG | E79: Livestock Non-CO2 | F79: 1% Growth | G79: $50 | H79: -29.7 | I79: MtCO2e/yr
A80: Fig_3.8 | B80: Bar | C80: 2055 | D80: FASOMGHG | E80: Livestock Non-CO2 | F80: 1% Growth | G80: $50 | H80: -33.8 | I80: MtCO2e/yr
A81: Fig_3.8 | B81: Bar | C81: 2025 | D81: FASOMGHG | E81: Livestock Non-CO2 | F81: 3% Growth | G81: $5 | H81: -0.5 | I81: MtCO2e/yr | K81: =INDEX('EPA land and ag calcs'!$G$7:$G$14,MATCH('EPA land and ag potential'!E81,'EPA land and ag calcs'!$A$7:$A$15,0)) -> *handled in agriculture files
A82: Fig_3.8 | B82: Bar | C82: 2035 | D82: FASOMGHG | E82: Livestock Non-CO2 | F82: 3% Growth | G82: $5 | H82: -1 | I82: MtCO2e/yr | K82: =INDEX('EPA land and ag calcs'!$G$7:$G$14,MATCH('EPA land and ag potential'!E82,'EPA land and ag calcs'!$A$7:$A$15,0)) -> *handled in agriculture files
A83: Fig_3.8 | B83: Line | C83: 2025 | D83: FASOMGHG | E83: Total | F83: 1% Growth | G83: $100 | H83: -232.1 | I83: MtCO2e/yr
A84: Fig_3.8 | B84: Line | C84: 2025 | D84: FASOMGHG | E84: Total | F84: 1% Growth | G84: $20 | H84: -77.8 | I84: MtCO2e/yr
A85: Fig_3.8 | B85: Line | C85: 2025 | D85: FASOMGHG | E85: Total | F85: 1% Growth | G85: $35 | H85: -114.7 | I85: MtCO2e/yr
A86: Fig_3.8 | B86: Line | C86: 2025 | D86: FASOMGHG | E86: Total | F86: 1% Growth | G86: $5 | H86: -30.5 | I86: MtCO2e/yr
A87: Fig_3.8 | B87: Line | C87: 2025 | D87: FASOMGHG | E87: Total | F87: 1% Growth | G87: $50 | H87: -169.8 | I87: MtCO2e/yr
A88: Fig_3.8 | B88: Line | C88: 2025 | D88: FASOMGHG | E88: Total | F88: 3% Growth | G88: $100 | H88: -96.9 | I88: MtCO2e/yr | K88: =INDEX('EPA land and ag calcs'!$G$7:$G$14,MATCH('EPA land and ag potential'!E88,'EPA land and ag calcs'!$A$7:$A$15,0)) -> #REF!
A89: Fig_3.8 | B89: Line | C89: 2025 | D89: FASOMGHG | E89: Total | F89: 3% Growth | G89: $20 | H89: -5.7 | I89: MtCO2e/yr | K89: =INDEX('EPA land and ag calcs'!$G$7:$G$14,MATCH('EPA land and ag potential'!E89,'EPA land and ag calcs'!$A$7:$A$15,0)) -> #REF!
A90: Fig_3.8 | B90: Line | C90: 2025 | D90: FASOMGHG | E90: Total | F90: 3% Growth | G90: $35 | H90: -6.6 | I90: MtCO2e/yr | K90: =INDEX('EPA land and ag calcs'!$G$7:$G$14,MATCH('EPA land and ag potential'!E90,'EPA land and ag calcs'!$A$7:$A$15,0)) -> #REF!
A91: Fig_3.8 | B91: Line | C91: 2025 | D91: FASOMGHG | E91: Total | F91: 3% Growth | G91: $5 | H91: 8.3 | I91: MtCO2e/yr | K91: =INDEX('EPA land and ag calcs'!$G$7:$G$14,MATCH('EPA land and ag potential'!E91,'EPA land and ag calcs'!$A$7:$A$15,0)) -> #REF!
A92: Fig_3.8 | B92: Line | C92: 2025 | D92: FASOMGHG | E92: Total | F92: 3% Growth | G92: $50 | H92: -62.9 | I92: MtCO2e/yr | K92: =INDEX('EPA land and ag calcs'!$G$7:$G$14,MATCH('EPA land and ag potential'!E92,'EPA land and ag calcs'!$A$7:$A$15,0)) -> #REF!
A93: Fig_3.8 | B93: Bar | C93: 2025 | D93: GLOBIOM | E93: Ag Soils | F93: 3% Growth | G93: $50 | H93: -12.7 | I93: MtCO2e/yr
A94: Fig_3.8 | B94: Bar | C94: 2035 | D94: GLOBIOM | E94: Ag Soils | F94: 3% Growth | G94: $50 | H94: -8.8 | I94: MtCO2e/yr
A95: Fig_3.8 | B95: Bar | C95: 2045 | D95: GLOBIOM | E95: Ag Soils | F95: 3% Growth | G95: $50 | H95: -7.7 | I95: MtCO2e/yr
A96: Fig_3.8 | B96: Bar | C96: 2055 | D96: GLOBIOM | E96: Ag Soils | F96: 3% Growth | G96: $50 | H96: -7.2 | I96: MtCO2e/yr
A97: Fig_3.8 | B97: Bar | C97: 2025 | D97: GLOBIOM | E97: Ag Soils | F97: 1% Growth | G97: $50 | H97: -12.7 | I97: MtCO2e/yr
A98: Fig_3.8 | B98: Bar | C98: 2035 | D98: GLOBIOM | E98: Ag Soils | F98: 1% Growth | G98: $50 | H98: -8.7 | I98: MtCO2e/yr
A99: Fig_3.8 | B99: Bar | C99: 2045 | D99: GLOBIOM | E99: Ag Soils | F99: 1% Growth | G99: $50 | H99: -7.7 | I99: MtCO2e/yr
A100: Fig_3.8 | B100: Bar | C100: 2055 | D100: GLOBIOM | E100: Ag Soils | F100: 1% Growth | G100: $50 | H100: -7.1 | I100: MtCO2e/yr
...

Sheet EPA land and ag calcs
A1: Model | B1: FASOMGHG
A2: Growth.Rate | B2: 3% Growth
A3: Starting.Price | B3: $100
A5: Sum of Value | B5: Column Labels
A6: Row Labels | B6: 2025 | C6: 2035 | D6: 2045 | E6: 2055 | F6: Grand Total
A7: Ag Soils | B7: 124.1 | C7: 109.7 | D7: 73.5 | E7: 45.3 | F7: 352.6 | G7: afforestation and reforestation
A8: Cropland CO2 | B8: -4 | C8: -8.8 | D8: -13 | E8: -15.8 | F8: -41.6 | G8: *handled in agriculture files
A9: Cropland Non-CO2 | B9: -3.8 | C9: -7.6 | D9: -10.2 | E9: -12 | F9: -33.6 | G9: *handled in agriculture files
A10: Forest (Existing forests) | B10: -30.3 | C10: -67.1 | D10: -77.8 | E10: -91.9 | F10: -267.1 | G10: forest management
A11: Forest (New forests) | C11: -59 | D11: -77.6 | E11: -107 | F11: -243.6 | G11: afforestation and reforestation
A12: Forest Products | B12: 3.6 | C12: 3 | D12: 2.6 | E12: 2.4 | F12: 11.6 | G12: forest management
A13: Forest Soils | B13: -153.2 | C13: -173.5 | D13: -154.1 | E13: -130.2 | F13: -611 | G13: afforestation and reforestation
A14: Livestock Non-CO2 | B14: -33.3 | C14: -44.3 | D14: -51.2 | E14: -59.2 | F14: -188 | G14: *handled in agriculture files
A15: Total | B15: -96.9 | C15: -247.6 | D15: -307.8 | E15: -368.4 | F15: -1020.7
A16: Grand Total | B16: -193.8 | C16: -495.2 | D16: -615.6 | E16: -736.8 | F16: -2041.4
A18: Check on Total | B18: =SUM(B7:B14) -> -96.9 | C18: =SUM(C7:C14) -> -247.6 | D18: =SUM(D7:D14) -> -307.8 | E18: =SUM(E7:E14) -> -368.4
A20: forest management
B21: cumulative | H21: broken out | M21: amount spent | S21: cumulative amount spent | Y21: annual target | Z21: 1.0205e+08 | AB21: used in IRA scenario | AE21: potential remaining in IRA scenario
B22: 2025 | C22: 2035 | D22: 2045 | E22: 2055 | H22: 2025 | I22: 2035 | J22: 2045 | K22: 2055 | N22: 2025 | O22: 2035 | P22: 2045 | Q22: 2055 | T22: 2025 | U22: 2035 | V22: 2045 | W22: 2055 | Y22: 2025 | Z22: 2035 | AB22: 2025 | AC22: 2035 | AE22: 2025 | AF22: 2035
A23: 5 | B23: =SUMIFS('EPA land and ag potential'!$H:$H,'EPA land and ag potential'!$C:$C,'EPA land and ag calcs'!B$22,'EPA land and ag potential'!$G:$G,'EPA land and ag calcs'!$A23,'EPA land and ag potential'!$D:$D,"FASOMGHG",'EPA land and ag potential'!$F:$F,"3% Growth",'EPA land and ag potential'!$K:$K,'EPA land and ag calcs'!$A$20) -> -6.2 | C23: =SUMIFS('EPA land and ag potential'!$H:$H,'EPA land and ag potential'!$C:$C,'EPA land and ag calcs'!C$22,'EPA land and ag potential'!$G:$G,'EPA land and ag calcs'!$A23,'EPA land and ag potential'!$D:$D,"FASOMGHG",'EPA land and ag potential'!$F:$F,"3% Growth",'EPA land and ag potential'!$K:$K,'EPA land and ag calcs'!$A$20) -> -15.7 | D23: =SUMIFS('EPA land and ag potential'!$H:$H,'EPA land and ag potential'!$C:$C,'EPA land and ag calcs'!D$22,'EPA land and ag potential'!$G:$G,'EPA land and ag calcs'!$A23,'EPA land and ag potential'!$D:$D,"FASOMGHG",'EPA land and ag potential'!$F:$F,"3% Growth",'EPA land and ag potential'!$K:$K,'EPA land and ag calcs'!$A$20) -> -21.9 | E23: =SUMIFS('EPA land and ag potential'!$H:$H,'EPA land and ag potential'!$C:$C,'EPA land and ag calcs'!E$22,'EPA land and ag potential'!$G:$G,'EPA land and ag calcs'!$A23,'EPA land and ag potential'!$D:$D,"FASOMGHG",'EPA land and ag potential'!$F:$F,"3% Growth",'EPA land and ag potential'!$K:$K,'EPA land and ag calcs'!$A$20) -> -27.9 | G23: 5 | H23: =SUMIFS('EPA land and ag potential'!$H:$H,'EPA land and ag potential'!$C:$C,'EPA land and ag calcs'!B$22,'EPA land and ag potential'!$G:$G,'EPA land and ag calcs'!$A23,'EPA land and ag potential'!$K:$K,'EPA land and ag calcs'!$A$20,'EPA land and ag potential'!$D:$D,"FASOMGHG",'EPA land and ag potential'!$F:$F,"3% Growth") -> -6.2 | I23: =SUMIFS('EPA land and ag potential'!$H:$H,'EPA land and ag potential'!$C:$C,'EPA land and ag calcs'!C$22,'EPA land and ag potential'!$G:$G,'EPA land and ag calcs'!$A23,'EPA land and ag potential'!$K:$K,'EPA land and ag calcs'!$A$20,'EPA land and ag potential'!$D:$D,"FASOMGHG",'EPA land and ag potential'!$F:$F,"3% Growth") -> -15.7 | J23: =SUMIFS('EPA land and ag potential'!$H:$H,'EPA land and ag potential'!$C:$C,'EPA land and ag calcs'!D$22,'EPA land and ag potential'!$G:$G,'EPA land and ag calcs'!$A23,'EPA land and ag potential'!$K:$K,'EPA land and ag calcs'!$A$20,'EPA land and ag potential'!$D:$D,"FASOMGHG",'EPA land and ag potential'!$F:$F,"3% Growth") -> -21.9 | K23: =SUMIFS('EPA land and ag potential'!$H:$H,'EPA land and ag potential'!$C:$C,'EPA land and ag calcs'!E$22,'EPA land and ag potential'!$G:$G,'EPA land and ag calcs'!$A23,'EPA land and ag potential'!$K:$K,'EPA land and ag calcs'!$A$20,'EPA land and ag potential'!$D:$D,"FASOMGHG",'EPA land and ag potential'!$F:$F,"3% Growth") -> -27.9 | M23: 5 | N23: 27500431 | O23: 69638188 | P23: 97138619 | Q23: 1.2375194e+08 | S23: 5 | T23: =N23 -> 27500431 | U23: =O23 -> 69638188 | V23: =P23 -> 97138619 | W23: =Q23 -> 1.2375194e+08 | Y23: =T23/$Z$21 -> 0.26947997 | Z23: =U23/$Z$21 -> 0.68239282 | AB23: 1 | AC23: 1 | AE23: =AB23*H23*-1 -> 6.2 | AF23: =AC23*I23*-1 -> 15.7
A24: 20 | B24: =SUMIFS('EPA land and ag potential'!$H:$H,'EPA land and ag potential'!$C:$C,'EPA land and ag calcs'!B$22,'EPA land and ag potential'!$G:$G,'EPA land and ag calcs'!$A24,'EPA land and ag potential'!$D:$D,"FASOMGHG",'EPA land and ag potential'!$F:$F,"3% Growth",'EPA land and ag potential'!$K:$K,'EPA land and ag calcs'!$A$20) -> -12.3 | C24: =SUMIFS('EPA land and ag potential'!$H:$H,'EPA land and ag potential'!$C:$C,'EPA land and ag calcs'!C$22,'EPA land and ag potential'!$G:$G,'EPA land and ag calcs'!$A24,'EPA land and ag potential'!$D:$D,"FASOMGHG",'EPA land and ag potential'!$F:$F,"3% Growth",'EPA land and ag potential'!$K:$K,'EPA land and ag calcs'!$A$20) -> -39.1 | D24: =SUMIFS('EPA land and ag potential'!$H:$H,'EPA land and ag potential'!$C:$C,'EPA land and ag calcs'!D$22,'EPA land and ag potential'!$G:$G,'EPA land and ag calcs'!$A24,'EPA land and ag potential'!$D:$D,"FASOMGHG",'EPA land and ag potential'!$F:$F,"3% Growth",'EPA land and ag potential'!$K:$K,'EPA land and ag calcs'!$A$20) -> -48.1 | E24: =SUMIFS('EPA land and ag potential'!$H:$H,'EPA land and ag potential'!$C:$C,'EPA land and ag calcs'!E$22,'EPA land and ag potential'!$G:$G,'EPA land and ag calcs'!$A24,'EPA land and ag potential'!$D:$D,"FASOMGHG",'EPA land and ag potential'!$F:$F,"3% Growth",'EPA land and ag potential'!$K:$K,'EPA land and ag calcs'!$A$20) -> -58.3 | G24: 20 | H24: =B24-B23 -> -6.1 | I24: =C24-C23 -> -23.4 | J24: =D24-D23 -> -26.2 | K24: =E24-E23 -> -30.4 | M24: 20 | N24: 1.082275e+08 | O24: 4.1516779e+08 | P24: 4.6484599e+08 | Q24: 5.3936329e+08 | S24: 20 | T24: =T23+N24 -> 1.3572793e+08 | U24: =U23+O24 -> 4.8480598e+08 | V24: =V23+P24 -> 5.6198461e+08 | W24: =W23+Q24 -> 6.6311523e+08 | Y24: =T24/$Z$21 -> 1.330014 | Z24: =U24/$Z$21 -> 4.7506711 | AB24: =(Z21-N23)/N24 -> 0.68882278 | AC24: =1-(U24-U23)/U24 -> 0.14364135 | AE24: =AB24*H24*-1 -> 4.201819 | AF24: =AC24*I24*-1 -> 3.3612077
A25: 35 | B25: =SUMIFS('EPA land and ag potential'!$H:$H,'EPA land and ag potential'!$C:$C,'EPA land and ag calcs'!B$22,'EPA land and ag potential'!$G:$G,'EPA land and ag calcs'!$A25,'EPA land and ag potential'!$D:$D,"FASOMGHG",'EPA land and ag potential'!$F:$F,"3% Growth",'EPA land and ag potential'!$K:$K,'EPA land and ag calcs'!$A$20) -> -14.8 | C25: =SUMIFS('EPA land and ag potential'!$H:$H,'EPA land and ag potential'!$C:$C,'EPA land and ag calcs'!C$22,'EPA land and ag potential'!$G:$G,'EPA land and ag calcs'!$A25,'EPA land and ag potential'!$D:$D,"FASOMGHG",'EPA land and ag potential'!$F:$F,"3% Growth",'EPA land and ag potential'!$K:$K,'EPA land and ag calcs'!$A$20) -> -49.5 | D25: =SUMIFS('EPA land and ag potential'!$H:$H,'EPA land and ag potential'!$C:$C,'EPA land and ag calcs'!D$22,'EPA land and ag potential'!$G:$G,'EPA land and ag calcs'!$A25,'EPA land and ag potential'!$D:$D,"FASOMGHG",'EPA land and ag potential'!$F:$F,"3% Growth",'EPA land and ag potential'!$K:$K,'EPA land and ag calcs'!$A$20) -> -59.9 | E25: =SUMIFS('EPA land and ag potential'!$H:$H,'EPA land and ag potential'!$C:$C,'EPA land and ag calcs'!E$22,'EPA land and ag potential'!$G:$G,'EPA land and ag calcs'!$A25,'EPA land and ag potential'!$D:$D,"FASOMGHG",'EPA land and ag potential'!$F:$F,"3% Growth",'EPA land and ag potential'!$K:$K,'EPA land and ag calcs'!$A$20) -> -72 | G25: 35 | H25: =B25-B24 -> -2.5 | I25: =C25-C24 -> -10.4 | J25: =D25-D24 -> -11.8 | K25: =E25-E24 -> -13.7 | M25: 35 | N25: 77622184 | O25: 3.2290828e+08 | P25: 3.6637671e+08 | Q25: 4.2536957e+08 | S25: 35 | T25: =T24+N25 -> 2.1335012e+08 | U25: =U24+O25 -> 8.0771427e+08 | V25: =V24+P25 -> 9.2836132e+08 | W25: =W24+Q25 -> 1.0884848e+09 | AB25: 0 | AC25: 0
A26: 50 | B26: =SUMIFS('EPA land and ag potential'!$H:$H,'EPA land and ag potential'!$C:$C,'EPA land and ag calcs'!B$22,'EPA land and ag potential'!$G:$G,'EPA land and ag calcs'!$A26,'EPA land and ag potential'!$D:$D,"FASOMGHG",'EPA land and ag potential'!$F:$F,"3% Growth",'EPA land and ag potential'!$K:$K,'EPA land and ag calcs'!$A$20) -> -17.4 | C26: =SUMIFS('EPA land and ag potential'!$H:$H,'EPA land and ag potential'!$C:$C,'EPA land and ag calcs'!C$22,'EPA land and ag potential'!$G:$G,'EPA land and ag calcs'!$A26,'EPA land and ag potential'!$D:$D,"FASOMGHG",'EPA land and ag potential'!$F:$F,"3% Growth",'EPA land and ag potential'!$K:$K,'EPA land and ag calcs'!$A$20) -> -53.3 | D26: =SUMIFS('EPA land and ag potential'!$H:$H,'EPA land and ag potential'!$C:$C,'EPA land and ag calcs'!D$22,'EPA land and ag potential'!$G:$G,'EPA land and ag calcs'!$A26,'EPA land and ag potential'!$D:$D,"FASOMGHG",'EPA land and ag potential'!$F:$F,"3% Growth",'EPA land and ag potential'!$K:$K,'EPA land and ag calcs'!$A$20) -> -64.1 | E26: =SUMIFS('EPA land and ag potential'!$H:$H,'EPA land and ag potential'!$C:$C,'EPA land and ag calcs'!E$22,'EPA land and ag potential'!$G:$G,'EPA land and ag calcs'!$A26,'EPA land and ag potential'!$D:$D,"FASOMGHG",'EPA land and ag potential'!$F:$F,"3% Growth",'EPA land and ag potential'!$K:$K,'EPA land and ag calcs'!$A$20) -> -76.7 | G26: 50 | H26: =B26-B25 -> -2.6 | I26: =C26-C25 -> -3.8 | J26: =D26-D25 -> -4.2 | K26: =E26-E25 -> -4.7 | M26: 50 | N26: 1.1532439e+08 | O26: 1.6855103e+08 | P26: 1.8629324e+08 | Q26: 2.0847101e+08 | S26: 50 | T26: =T25+N26 -> 3.286745e+08 | U26: =U25+O26 -> 9.7626529e+08 | V26: =V25+P26 -> 1.1146546e+09 | W26: =W25+Q26 -> 1.2969558e+09 | AB26: 0 | AC26: 0
A27: 100 | B27: =SUMIFS('EPA land and ag potential'!$H:$H,'EPA land and ag potential'!$C:$C,'EPA land and ag calcs'!B$22,'EPA land and ag potential'!$G:$G,'EPA land and ag calcs'!$A27,'EPA land and ag potential'!$D:$D,"FASOMGHG",'EPA land and ag potential'!$F:$F,"3% Growth",'EPA land and ag potential'!$K:$K,'EPA land and ag calcs'!$A$20) -> -26.7 | C27: =SUMIFS('EPA land and ag potential'!$H:$H,'EPA land and ag potential'!$C:$C,'EPA land and ag calcs'!C$22,'EPA land and ag potential'!$G:$G,'EPA land and ag calcs'!$A27,'EPA land and ag potential'!$D:$D,"FASOMGHG",'EPA land and ag potential'!$F:$F,"3% Growth",'EPA land and ag potential'!$K:$K,'EPA land and ag calcs'!$A$20) -> -64.1 | D27: =SUMIFS('EPA land and ag potential'!$H:$H,'EPA land and ag potential'!$C:$C,'EPA land and ag calcs'!D$22,'EPA land and ag potential'!$G:$G,'EPA land and ag calcs'!$A27,'EPA land and ag potential'!$D:$D,"FASOMGHG",'EPA land and ag potential'!$F:$F,"3% Growth",'EPA land and ag potential'!$K:$K,'EPA land and ag calcs'!$A$20) -> -75.2 | E27: =SUMIFS('EPA land and ag potential'!$H:$H,'EPA land and ag potential'!$C:$C,'EPA land and ag calcs'!E$22,'EPA land and ag potential'!$G:$G,'EPA land and ag calcs'!$A27,'EPA land and ag potential'!$D:$D,"FASOMGHG",'EPA land and ag potential'!$F:$F,"3% Growth",'EPA land and ag potential'!$K:$K,'EPA land and ag calcs'!$A$20) -> -89.5 | G27: 100 | H27: =B27-B26 -> -9.3 | I27: =C27-C26 -> -10.8 | J27: =D27-D26 -> -11.1 | K27: =E27-E26 -> -12.8 | M27: 100 | N27: 8.2501292e+08 | O27: 9.5807953e+08 | P27: 9.8469285e+08 | Q27: 1.1355017e+09 | S27: 100 | T27: =T26+N27 -> 1.1536874e+09 | U27: =U26+O27 -> 1.9343448e+09 | V27: =V26+P27 -> 2.0993474e+09 | W27: =W26+Q27 -> 2.4324575e+09 | AB27: 0 | AC27: 0
AD28: total (g) | AE28: =SUM(AE23:AE27)*10^12 -> 1.0401819e+13 | AF28: =SUM(AF23:AF27)*10^12 -> 1.9061208e+13
A29: afforestation and reforestation
B30: cumulative | H30: broken out | M30: amount spent | S30: cumulative amount spent | Y30: annual target | Z30: 150000000 | AB30: used in IRA scenario | AE30: potential remaining in IRA scenario
B31: 2025 | C31: 2035 | D31: 2045 | E31: 2055 | H31: 2025 | I31: 2035 | J31: 2045 | K31: 2055 | N31: 2025 | O31: 2035 | P31: 2045 | Q31: 2055 | T31: 2025 | U31: 2035 | V31: 2045 | W31: 2055 | Y31: 2025 | Z31: 2035 | AB31: 2025 | AC31: 2035 | AE31: 2025 | AF31: 2035
A32: 5 | B32: =SUMIFS('EPA land and ag potential'!$H:$H,'EPA land and ag potential'!$C:$C,'EPA land and ag calcs'!B$22,'EPA land and ag potential'!$G:$G,'EPA land and ag calcs'!$A23,'EPA land and ag potential'!$D:$D,"FASOMGHG",'EPA land and ag potential'!$F:$F,"3% Growth",'EPA land and ag potential'!$K:$K,'EPA land and ag calcs'!$A$29) -> 15.6 | C32: =SUMIFS('EPA land and ag potential'!$H:$H,'EPA land and ag potential'!$C:$C,'EPA land and ag calcs'!C$22,'EPA land and ag potential'!$G:$G,'EPA land and ag calcs'!$A23,'EPA land and ag potential'!$D:$D,"FASOMGHG",'EPA land and ag potential'!$F:$F,"3% Growth",'EPA land and ag potential'!$K:$K,'EPA land and ag calcs'!$A$29) -> 1.7 | D32: =SUMIFS('EPA land and ag potential'!$H:$H,'EPA land and ag potential'!$C:$C,'EPA land and ag calcs'!D$22,'EPA land and ag potential'!$G:$G,'EPA land and ag calcs'!$A23,'EPA land and ag potential'!$D:$D,"FASOMGHG",'EPA land and ag potential'!$F:$F,"3% Growth",'EPA land and ag potential'!$K:$K,'EPA land and ag calcs'!$A$29) -> -1.5 | E32: =SUMIFS('EPA land and ag potential'!$H:$H,'EPA land and ag potential'!$C:$C,'EPA land and ag calcs'!E$22,'EPA land and ag potential'!$G:$G,'EPA land and ag calcs'!$A23,'EPA land and ag potential'!$D:$D,"FASOMGHG",'EPA land and ag potential'!$F:$F,"3% Growth",'EPA land and ag potential'!$K:$K,'EPA land and ag calcs'!$A$29) -> -0.6 | G32: 5 | H32: =SUMIFS('EPA land and ag potential'!$H:$H,'EPA land and ag potential'!$C:$C,'EPA land and ag calcs'!B$22,'EPA land and ag potential'!$G:$G,'EPA land and ag calcs'!$A32,'EPA land and ag potential'!$K:$K,'EPA land and ag calcs'!$A$29,'EPA land and ag potential'!$D:$D,"FASOMGHG",'EPA land and ag potential'!$F:$F,"3% Growth") -> 15.6 | I32: =SUMIFS('EPA land and ag potential'!$H:$H,'EPA land and ag potential'!$C:$C,'EPA land and ag calcs'!C$22,'EPA land and ag potential'!$G:$G,'EPA land and ag calcs'!$A32,'EPA land and ag potential'!$K:$K,'EPA land and ag calcs'!$A$29,'EPA land and ag potential'!$D:$D,"FASOMGHG",'EPA land and ag potential'!$F:$F,"3% Growth") -> 1.7 | J32: =SUMIFS('EPA land and ag potential'!$H:$H,'EPA land and ag potential'!$C:$C,'EPA land and ag calcs'!D$22,'EPA land and ag potential'!$G:$G,'EPA land and ag calcs'!$A32,'EPA land and ag potential'!$K:$K,'EPA land and ag calcs'!$A$29,'EPA land and ag potential'!$D:$D,"FASOMGHG",'EPA land and ag potential'!$F:$F,"3% Growth") -> -1.5 | K32: =SUMIFS('EPA land and ag potential'!$H:$H,'EPA land and ag potential'!$C:$C,'EPA land and ag calcs'!E$22,'EPA land and ag potential'!$G:$G,'EPA land and ag calcs'!$A32,'EPA land and ag potential'!$K:$K,'EPA land and ag calcs'!$A$29,'EPA land and ag potential'!$D:$D,"FASOMGHG",'EPA land and ag potential'!$F:$F,"3% Growth") -> -0.6 | M32: 5 | N32: 0 | O32: 0 | P32: 6653330 | Q32: 2661332 | S32: 5 | T32: =N32 -> 0 | U32: =O32 -> 0 | V32: =P32 -> 6653330 | W32: =Q32 -> 2661332 | Y32: =T32/$Z$21 -> 0 | Z32: =U32/$Z$21 -> 0 | AB32: 1 | AC32: 1 | AE32: =IF(AB32*H32*-1<0,0,AB32*H32*-1) -> 0 | AF32: =IF(AC32*I32*-1<0,0,AC32*I32*-1) -> 0
A33: 20 | B33: =SUMIFS('EPA land and ag potential'!$H:$H,'EPA land and ag potential'!$C:$C,'EPA land and ag calcs'!B$22,'EPA land and ag potential'!$G:$G,'EPA land and ag calcs'!$A24,'EPA land and ag potential'!$D:$D,"FASOMGHG",'EPA land and ag potential'!$F:$F,"3% Growth",'EPA land and ag potential'!$K:$K,'EPA land and ag calcs'!$A$29) -> 15.1 | C33: =SUMIFS('EPA land and ag potential'!$H:$H,'EPA land and ag potential'!$C:$C,'EPA land and ag calcs'!C$22,'EPA land and ag potential'!$G:$G,'EPA land and ag calcs'!$A24,'EPA land and ag potential'!$D:$D,"FASOMGHG",'EPA land and ag potential'!$F:$F,"3% Growth",'EPA land and ag potential'!$K:$K,'EPA land and ag calcs'!$A$29) -> -25.5 | D33: =SUMIFS('EPA land and ag potential'!$H:$H,'EPA land and ag potential'!$C:$C,'EPA land and ag calcs'!D$22,'EPA land and ag potential'!$G:$G,'EPA land and ag calcs'!$A24,'EPA land and ag potential'!$D:$D,"FASOMGHG",'EPA land and ag potential'!$F:$F,"3% Growth",'EPA land and ag potential'!$K:$K,'EPA land and ag calcs'!$A$29) -> -40.1 | E33: =SUMIFS('EPA land and ag potential'!$H:$H,'EPA land and ag potential'!$C:$C,'EPA land and ag calcs'!E$22,'EPA land and ag potential'!$G:$G,'EPA land and ag calcs'!$A24,'EPA land and ag potential'!$D:$D,"FASOMGHG",'EPA land and ag potential'!$F:$F,"3% Growth",'EPA land and ag potential'!$K:$K,'EPA land and ag calcs'!$A$29) -> -62.5 | G33: 20 | H33: =B33-B32 -> -0.5 | I33: =C33-C32 -> -27.2 | J33: =D33-D32 -> -38.6 | K33: =E33-E32 -> -61.9 | M33: 20 | N33: 8871106.7 | O33: 4.8258821e+08 | P33: 6.8484944e+08 | Q33: 1.098243e+09 | S33: 20 | T33: =T32+N33 -> 8871106.7 | U33: =U32+O33 -> 4.8258821e+08 | V33: =V32+P33 -> 6.9150277e+08 | W33: =W32+Q33 -> 1.1009043e+09 | Y33: =T33/$Z$21 -> 0.086929022 | Z33: =U33/$Z$21 -> 4.7289388 | AB33: 1 | AC33: =(Z30-U32)/O33 -> 0.31082401 | AE33: =IF(AB33*H33*-1<0,0,AB33*H33*-1) -> 0.5 | AF33: =IF(AC33*I33*-1<0,0,AC33*I33*-1) -> 8.454413
A34: 35 | B34: =SUMIFS('EPA land and ag potential'!$H:$H,'EPA land and ag potential'!$C:$C,'EPA land and ag calcs'!B$22,'EPA land and ag potential'!$G:$G,'EPA land and ag calcs'!$A25,'EPA land and ag potential'!$D:$D,"FASOMGHG",'EPA land and ag potential'!$F:$F,"3% Growth",'EPA land and ag potential'!$K:$K,'EPA land and ag calcs'!$A$29) -> 20.5 | C34: =SUMIFS('EPA land and ag potential'!$H:$H,'EPA land and ag potential'!$C:$C,'EPA land and ag calcs'!C$22,'EPA land and ag potential'!$G:$G,'EPA land and ag calcs'!$A25,'EPA land and ag potential'!$D:$D,"FASOMGHG",'EPA land and ag potential'!$F:$F,"3% Growth",'EPA land and ag potential'!$K:$K,'EPA land and ag calcs'!$A$29) -> -59.3 | D34: =SUMIFS('EPA land and ag potential'!$H:$H,'EPA land and ag potential'!$C:$C,'EPA land and ag calcs'!D$22,'EPA land and ag potential'!$G:$G,'EPA land and ag calcs'!$A25,'EPA land and ag potential'!$D:$D,"FASOMGHG",'EPA land and ag potential'!$F:$F,"3% Growth",'EPA land and ag potential'!$K:$K,'EPA land and ag calcs'!$A$29) -> -99.2 | E34: =SUMIFS('EPA land and ag potential'!$H:$H,'EPA land and ag potential'!$C:$C,'EPA land and ag calcs'!E$22,'EPA land and ag potential'!$G:$G,'EPA land and ag calcs'!$A25,'EPA land and ag potential'!$D:$D,"FASOMGHG",'EPA land and ag potential'!$F:$F,"3% Growth",'EPA land and ag potential'!$K:$K,'EPA land and ag calcs'!$A$29) -> -124.1 | G34: 35 | H34: =B34-B33 -> 5.4 | I34: =C34-C33 -> -33.8 | J34: =D34-D33 -> -59.1 | K34: =E34-E33 -> -61.6 | M34: 35 | N34: 0 | O34: 1.0494519e+09 | P34: 1.8349884e+09 | Q34: 1.9126106e+09 | S34: 35 | T34: =T33+N34 -> 8871106.7 | U34: =U33+O34 -> 1.5320401e+09 | V34: =V33+P34 -> 2.5264912e+09 | W34: =W33+Q34 -> 3.013515e+09 | Y34: =T34/$Z$21 -> 0.086929022 | Z34: =U34/$Z$21 -> 15.012642 | AB34: 1 | AC34: 0 | AE34: =IF(AB34*H34*-1<0,0,AB34*H34*-1) -> 0 | AF34: =IF(AC34*I34*-1<0,0,AC34*I34*-1) -> 0
A35: 50 | B35: =SUMIFS('EPA land and ag potential'!$H:$H,'EPA land and ag potential'!$C:$C,'EPA land and ag calcs'!B$22,'EPA land and ag potential'!$G:$G,'EPA land and ag calcs'!$A26,'EPA land and ag potential'!$D:$D,"FASOMGHG",'EPA land and ag potential'!$F:$F,"3% Growth",'EPA land and ag potential'!$K:$K,'EPA land and ag calcs'!$A$29) -> -26.5 | C35: =SUMIFS('EPA land and ag potential'!$H:$H,'EPA land and ag potential'!$C:$C,'EPA land and ag calcs'!C$22,'EPA land and ag potential'!$G:$G,'EPA land and ag calcs'!$A26,'EPA land and ag potential'!$D:$D,"FASOMGHG",'EPA land and ag potential'!$F:$F,"3% Growth",'EPA land and ag potential'!$K:$K,'EPA land and ag calcs'!$A$29) -> -103.5 | D35: =SUMIFS('EPA land and ag potential'!$H:$H,'EPA land and ag potential'!$C:$C,'EPA land and ag calcs'!D$22,'EPA land and ag potential'!$G:$G,'EPA land and ag calcs'!$A26,'EPA land and ag potential'!$D:$D,"FASOMGHG",'EPA land and ag potential'!$F:$F,"3% Growth",'EPA land and ag potential'!$K:$K,'EPA land and ag calcs'!$A$29) -> -141.9 | E35: =SUMIFS('EPA land and ag potential'!$H:$H,'EPA land and ag potential'!$C:$C,'EPA land and ag calcs'!E$22,'EPA land and ag potential'!$G:$G,'EPA land and ag calcs'!$A26,'EPA land and ag potential'!$D:$D,"FASOMGHG",'EPA land and ag potential'!$F:$F,"3% Growth",'EPA land and ag potential'!$K:$K,'EPA land and ag calcs'!$A$29) -> -168.4 | G35: 50 | H35: =B35-B34 -> -47 | I35: =C35-C34 -> -44.2 | J35: =D35-D34 -> -42.7 | K35: =E35-E34 -> -44.3 | M35: 50 | N35: 2.0847101e+09 | O35: 1.9605146e+09 | P35: 1.8939813e+09 | Q35: 1.9649501e+09 | S35: 50 | T35: =T34+N35 -> 2.0935812e+09 | U35: =U34+O35 -> 3.4925547e+09 | V35: =V34+P35 -> 4.4204725e+09 | W35: =W34+Q35 -> 4.9784651e+09 | Y35: =T35/$Z$21 -> 20.515249 | Z35: =U35/$Z$21 -> 34.223956 | AB35: =(Z30-T34)/N35 -> 0.067697132 | AC35: 0 | AE35: =IF(AB35*H35*-1<0,0,AB35*H35*-1) -> 3.1817652 | AF35: =IF(AC35*I35*-1<0,0,AC35*I35*-1) -> 0
A36: 100 | B36: =SUMIFS('EPA land and ag potential'!$H:$H,'EPA land and ag potential'!$C:$C,'EPA land and ag calcs'!B$22,'EPA land and ag potential'!$G:$G,'EPA land and ag calcs'!$A27,'EPA land and ag potential'!$D:$D,"FASOMGHG",'EPA land and ag potential'!$F:$F,"3% Growth",'EPA land and ag potential'!$K:$K,'EPA land and ag calcs'!$A$29) -> -29.1 | C36: =SUMIFS('EPA land and ag potential'!$H:$H,'EPA land and ag potential'!$C:$C,'EPA land and ag calcs'!C$22,'EPA land and ag potential'!$G:$G,'EPA land and ag calcs'!$A27,'EPA land and ag potential'!$D:$D,"FASOMGHG",'EPA land and ag potential'!$F:$F,"3% Growth",'EPA land and ag potential'!$K:$K,'EPA land and ag calcs'!$A$29) -> -122.8 | D36: =SUMIFS('EPA land and ag potential'!$H:$H,'EPA land and ag potential'!$C:$C,'EPA land and ag calcs'!D$22,'EPA land and ag potential'!$G:$G,'EPA land and ag calcs'!$A27,'EPA land and ag potential'!$D:$D,"FASOMGHG",'EPA land and ag potential'!$F:$F,"3% Growth",'EPA land and ag potential'!$K:$K,'EPA land and ag calcs'!$A$29) -> -158.2 | E36: =SUMIFS('EPA land and ag potential'!$H:$H,'EPA land and ag potential'!$C:$C,'EPA land and ag calcs'!E$22,'EPA land and ag potential'!$G:$G,'EPA land and ag calcs'!$A27,'EPA land and ag potential'!$D:$D,"FASOMGHG",'EPA land and ag potential'!$F:$F,"3% Growth",'EPA land and ag potential'!$K:$K,'EPA land and ag calcs'!$A$29) -> -191.9 | G36: 100 | H36: =B36-B35 -> -2.6 | I36: =C36-C35 -> -19.3 | J36: =D36-D35 -> -16.3 | K36: =E36-E35 -> -23.5 | M36: 100 | N36: 2.3064877e+08 | O36: 1.7121236e+09 | P36: 1.4459904e+09 | Q36: 2.0847101e+09 | S36: 100 | T36: =T35+N36 -> 2.32423e+09 | U36: =U35+O36 -> 5.2046783e+09 | V36: =V35+P36 -> 5.8664629e+09 | W36: =W35+Q36 -> 7.0631752e+09 | AB36: 0 | AC36: 0 | AE36: =IF(AB36*H36*-1<0,0,AB36*H36*-1) -> 0 | AF36: =IF(AC36*I36*-1<0,0,AC36*I36*-1) -> 0
AD37: total (g) | AE37: =SUM(AE32:AE36)*10^12 -> 3.6817652e+12 | AF37: =SUM(AF32:AF36)*10^12 -> 8.454413e+12
A38: interpolated potential achieved in IRA (see land/BLAPE)
B39: 2021 | C39: 2022 | D39: 2023 | E39: 2024 | F39: 2025 | G39: 2026 | H39: 2027 | I39: 2028 | J39: 2029 | K39: 2030 | L39: 2031 | M39: 2032 | N39: 2033 | O39: 2034 | P39: 2035 | Q39: 2036 | R39: 2037 | S39: 2038 | T39: 2039 | U39: 2040 | V39: 2041 | W39: 2042 | X39: 2043 | Y39: 2044 | Z39: 2045 | AA39: 2046 | AB39: 2047 | AC39: 2048 | AD39: 2049 | AE39: 2050
A40: forest management | B40: 0 | C40: 0 | D40: 4.9574094e+12 | E40: 8.926839e+12 | F40: 1.2203305e+13 | G40: 1.5384377e+13 | H40: 17578198294243 | I40: 1.7459142e+13 | J40: 1.5815565e+13 | K40: 1.4795656e+13 | L40: 1.2251226e+13 | M40: 9.978678e+12 | N40: 6.652452e+12 | O40: 3.326226e+12 | P40: 0 | Q40: 0 | R40: 0 | S40: 0 | T40: 0 | U40: 0 | V40: 0 | W40: 0 | X40: 0 | Y40: 0 | Z40: 0 | AA40: 0 | AB40: 0 | AC40: 0 | AD40: 0 | AE40: 0
A41: afforestation and reforestation | B41: 0 | C41: 0 | D41: 0 | E41: 0 | F41: 0 | G41: 0 | H41: 5.0829325e+11 | I41: 7.0535348e+12 | J41: 1.0179858e+13 | K41: 1.0179858e+13 | L41: 1.0179858e+13 | M41: 1.0179858e+13 | N41: 1.0179858e+13 | O41: 1.0179858e+13 | P41: 1.0179858e+13 | Q41: =P41 -> 1.0179858e+13 | R41: =Q41 -> 1.0179858e+13 | S41: =R41 -> 1.0179858e+13 | T41: =S41 -> 1.0179858e+13 | U41: =T41 -> 1.0179858e+13 | V41: =U41 -> 1.0179858e+13 | W41: =V41 -> 1.0179858e+13 | X41: =W41 -> 1.0179858e+13 | ... AE41: =AD41 -> 1.0179858e+13
A43: interpolated total potential before IRA
B44: 2021 | C44: 2022 | D44: 2023 | E44: 2024 | F44: 2025 | G44: 2026 | H44: 2027 | I44: 2028 | J44: 2029 | K44: 2030 | L44: 2031 | M44: 2032 | N44: 2033 | O44: 2034 | P44: 2035 | Q44: 2036 | R44: 2037 | S44: 2038 | T44: 2039 | U44: 2040 | V44: 2041 | W44: 2042 | X44: 2043 | Y44: 2044 | Z44: 2045 | AA44: 2046 | AB44: 2047 | AC44: 2048 | AD44: 2049 | AE44: 2050
A45: forest management | B45: {=-TREND($B$27:$C$27,$B$22:$C$22,B44)*10^12} -> 1.174e+13 | C45: {=-TREND($B$27:$C$27,$B$22:$C$22,C44)*10^12} -> 1.548e+13 | D45: {=-TREND($B$27:$C$27,$B$22:$C$22,D44)*10^12} -> 1.922e+13 | E45: {=-TREND($B$27:$C$27,$B$22:$C$22,E44)*10^12} -> 2.296e+13 | F45: {=-TREND($B$27:$C$27,$B$22:$C$22,F44)*10^12} -> 2.67e+13 | G45: {=-TREND($B$27:$C$27,$B$22:$C$22,G44)*10^12} -> 3.044e+13 | H45: {=-TREND($B$27:$C$27,$B$22:$C$22,H44)*10^12} -> 3.418e+13 | I45: {=-TREND($B$27:$C$27,$B$22:$C$22,I44)*10^12} -> 3.792e+13 | ... P45: {=-TREND($B$27:$C$27,$B$22:$C$22,P44)*10^12} -> 6.41e+13 | Q45: {=-TREND($C$27:$D$27,$C$22:$D$22,Q44)*10^12} -> 6.521e+13 | R45: {=-TREND($C$27:$D$27,$C$22:$D$22,R44)*10^12} -> 6.632e+13 | S45: {=-TREND($C$27:$D$27,$C$22:$D$22,S44)*10^12} -> 6.743e+13 | T45: {=-TREND($C$27:$D$27,$C$22:$D$22,T44)*10^12} -> 6.854e+13 | U45: {=-TREND($C$27:$D$27,$C$22:$D$22,U44)*10^12} -> 6.965e+13 | V45: {=-TREND($C$27:$D$27,$C$22:$D$22,V44)*10^12} -> 7.076e+13 | W45: {=-TREND($C$27:$D$27,$C$22:$D$22,W44)*10^12} -> 7.187e+13 | X45: {=-TREND($C$27:$D$27,$C$22:$D$22,X44)*10^12} -> 7.298e+13 | ... Z45: {=-TREND($C$27:$D$27,$C$22:$D$22,Z44)*10^12} -> 7.52e+13 | AA45: {=-TREND($D$27:$E$27,$D$22:$E$22,AA44)*10^12} -> 7.663e+13 | AB45: {=-TREND($D$27:$E$27,$D$22:$E$22,AB44)*10^12} -> 7.806e+13 | AC45: {=-TREND($D$27:$E$27,$D$22:$E$22,AC44)*10^12} -> 7.949e+13 | AD45: {=-TREND($D$27:$E$27,$D$22:$E$22,AD44)*10^12} -> 8.092e+13 | AE45: {=-TREND($D$27:$E$27,$D$22:$E$22,AE44)*10^12} -> 8.235e+13
A46: afforestation and reforestation | B46: {=MAX(-TREND($B$36:$C$36,$B$31:$C$31,B44)*10^12,0)} -> 0 | C46: {=MAX(-TREND($B$36:$C$36,$B$31:$C$31,C44)*10^12,0)} -> 9.9e+11 | D46: {=MAX(-TREND($B$36:$C$36,$B$31:$C$31,D44)*10^12,0)} -> 1.036e+13 | E46: {=MAX(-TREND($B$36:$C$36,$B$31:$C$31,E44)*10^12,0)} -> 1.973e+13 | F46: {=MAX(-TREND($B$36:$C$36,$B$31:$C$31,F44)*10^12,0)} -> 2.91e+13 | G46: {=MAX(-TREND($B$36:$C$36,$B$31:$C$31,G44)*10^12,0)} -> 3.847e+13 | H46: {=MAX(-TREND($B$36:$C$36,$B$31:$C$31,H44)*10^12,0)} -> 4.784e+13 | I46: {=MAX(-TREND($B$36:$C$36,$B$31:$C$31,I44)*10^12,0)} -> 5.721e+13 | ... P46: {=MAX(-TREND($B$36:$C$36,$B$31:$C$31,P44)*10^12,0)} -> 1.228e+14 | Q46: {=MAX(-TREND($C$36:$D$36,$C$31:$D$31,Q44)*10^12,0)} -> 1.2634e+14 | R46: {=MAX(-TREND($C$36:$D$36,$C$31:$D$31,R44)*10^12,0)} -> 1.2988e+14 | S46: {=MAX(-TREND($C$36:$D$36,$C$31:$D$31,S44)*10^12,0)} -> 1.3342e+14 | T46: {=MAX(-TREND($C$36:$D$36,$C$31:$D$31,T44)*10^12,0)} -> 1.3696e+14 | U46: {=MAX(-TREND($C$36:$D$36,$C$31:$D$31,U44)*10^12,0)} -> 140500000000000 | V46: {=MAX(-TREND($C$36:$D$36,$C$31:$D$31,V44)*10^12,0)} -> 1.4404e+14 | W46: {=MAX(-TREND($C$36:$D$36,$C$31:$D$31,W44)*10^12,0)} -> 1.4758e+14 | X46: {=MAX(-TREND($C$36:$D$36,$C$31:$D$31,X44)*10^12,0)} -> 1.5112e+14 | ... Z46: {=MAX(-TREND($C$36:$D$36,$C$31:$D$31,Z44)*10^12,0)} -> 1.582e+14 | AA46: {=MAX(-TREND($D$36:$E$36,$D$31:$E$31,AA44)*10^12,0)} -> 1.6157e+14 | AB46: {=MAX(-TREND($D$36:$E$36,$D$31:$E$31,AB44)*10^12,0)} -> 1.6494e+14 | AC46: {=MAX(-TREND($D$36:$E$36,$D$31:$E$31,AC44)*10^12,0)} -> 1.6831e+14 | AD46: {=MAX(-TREND($D$36:$E$36,$D$31:$E$31,AD44)*10^12,0)} -> 1.7168e+14 | AE46: {=MAX(-TREND($D$36:$E$36,$D$31:$E$31,AE44)*10^12,0)} -> 1.7505e+14
A48: interpolated potential after IRA
B49: 2021 | C49: 2022 | D49: 2023 | E49: 2024 | F49: 2025 | G49: 2026 | H49: 2027 | I49: 2028 | J49: 2029 | K49: 2030 | L49: 2031 | M49: 2032 | N49: 2033 | O49: 2034 | P49: 2035 | Q49: 2036 | R49: 2037 | S49: 2038 | T49: 2039 | U49: 2040 | V49: 2041 | W49: 2042 | X49: 2043 | Y49: 2044 | Z49: 2045 | AA49: 2046 | AB49: 2047 | AC49: 2048 | AD49: 2049 | AE49: 2050
A50: forest management | B50: =B45 -> 1.174e+13 | C50: =C45 -> 1.548e+13 | D50: =D45 -> 1.922e+13 | E50: =E45 -> 2.296e+13 | F50: =F45 -> 2.67e+13 | G50: =G45 -> 3.044e+13 | H50: =H45 -> 3.418e+13 | I50: =I45 -> 3.792e+13 | ... AE50: =AE45 -> 8.235e+13
A51: afforestation and reforestation | B51: =B46 -> 0 | C51: =C46 -> 9.9e+11 | D51: =D46 -> 1.036e+13 | E51: =E46 -> 1.973e+13 | F51: =F46 -> 2.91e+13 | G51: =G46 -> 3.847e+13 | H51: =H46 -> 4.784e+13 | I51: =I46 -> 5.721e+13 | ... AE51: =AE46 -> 1.7505e+14
A53: potential cumulative acreage
B54: 2021 | C54: 2022 | D54: 2023 | E54: 2024 | F54: 2025 | G54: 2026 | H54: 2027 | I54: 2028 | J54: 2029 | K54: 2030 | L54: 2031 | M54: 2032 | N54: 2033 | O54: 2034 | P54: 2035 | Q54: 2036 | R54: 2037 | S54: 2038 | T54: 2039 | U54: 2040 | V54: 2041 | W54: 2042 | X54: 2043 | Y54: 2044 | Z54: 2045 | AA54: 2046 | AB54: 2047 | AC54: 2048 | AD54: 2049 | AE54: 2050
A55: forest management | B55: =B50/CApULAbIFM!$B$2 -> 7826666.7 | C55: =C50/CApULAbIFM!$B$2 -> 10320000 | D55: =D50/CApULAbIFM!$B$2 -> 12813333 | E55: =E50/CApULAbIFM!$B$2 -> 15306667 | F55: =F50/CApULAbIFM!$B$2 -> 17800000 | G55: =G50/CApULAbIFM!$B$2 -> 20293333 | H55: =H50/CApULAbIFM!$B$2 -> 22786667 | I55: =I50/CApULAbIFM!$B$2 -> 25280000 | ... AE55: =AE50/CApULAbIFM!$B$2 -> 54900000
A56: afforestation and reforestation | B56: =B51/TNC_summary!$C$10 -> 0 | C56: =C51/TNC_summary!$C$10 -> 501757.7 | D56: =D51/TNC_summary!$C$10 -> 5250716.9 | E56: =E51/TNC_summary!$C$10 -> 9999676.1 | F56: =F51/TNC_summary!$C$10 -> 14748635 | G56: =G51/TNC_summary!$C$10 -> 19497595 | H56: =H51/TNC_summary!$C$10 -> 24246554 | I56: =I51/TNC_summary!$C$10 -> 28995513 | ... AE56: =AE51/TNC_summary!$C$10 -> 88719884
A58: potential annual acreage
B59: 2021 | C59: 2022 | D59: 2023 | E59: 2024 | F59: 2025 | G59: 2026 | H59: 2027 | I59: 2028 | J59: 2029 | K59: 2030 | L59: 2031 | M59: 2032 | N59: 2033 | O59: 2034 | P59: 2035 | Q59: 2036 | R59: 2037 | S59: 2038 | T59: 2039 | U59: 2040 | V59: 2041 | W59: 2042 | X59: 2043 | Y59: 2044 | Z59: 2045 | AA59: 2046 | AB59: 2047 | AC59: 2048 | AD59: 2049 | AE59: 2050
A60: forest management | B60: =B55 -> 7826666.7 | C60: =C55 -> 10320000 | D60: =D55 -> 12813333 | E60: =E55 -> 15306667 | F60: =F55 -> 17800000 | G60: =G55 -> 20293333 | H60: =H55 -> 22786667 | I60: =I55 -> 25280000 | ... AE60: =AE55 -> 54900000
A61: afforestation and reforestation | B61: =B56 -> 0 | C61: =C56-B56 -> 501757.7 | D61: =D56-C56 -> 4748959.2 | E61: =E56-D56 -> 4748959.2 | F61: =F56-E56 -> 4748959.2 | G61: =G56-F56 -> 4748959.2 | H61: =H56-G56 -> 4748959.2 | I61: =I56-H56 -> 4748959.2 | J61: =J56-I56 -> 4748959.2 | ... AE61: =AE56-AD56 -> 1708003.5

Sheet CApULAbIFM
B1: Per Acre
A2: CO2 Abated (g) | B2: =1.5*10^6 -> 1500000
A4: Source: | B4: consultation with American Forest Foundation
A5: see file land/CApULAbIFM

Sheet TNC Data
G1: 0-10 $/ton | H1: 0-50 $/ton | I1: 0-100 $/ton | J1: max $ton | K1: IGNORE - zero | O1: IGNORE-max | P1: REFORESTATION | Q1: Average CO2/Acre | R1: Total acres | AC1: Avoided forest conversion | AD1: Average CO2/Acre | AE1: Total acres | AP1: RICE | AQ1: Average CO2/Acre | AR1: Total acres | BC1: FIRE | BD1: Average CO2/Acre | BE1: Total acres | CT1: Avoided Grassland Conversion | CU1: Average CO2/Acre | CV1: Total acres | DG1: Grassland Restoration | DH1: Average CO2/Acre | DI1: Total acres
A3: state_name | B3: State_abv | C3: state_fips | D3: emis_tot | E3: emis_xlulc | F3: refor_0 | G3: refor_1 | H3: refor_2 | I3: refor_3 | J3: refor_4 | K3: refor_area_0 | L3: refor_area_1 | M3: refor_area_2 | N3: refor_area_3 | O3: refor_area_4 | P3: $/ton/yr | Q3: tons/acre | R3: acres (0-100) | S3: defor_0 | T3: defor_1 | U3: defor_2 | V3: defor_3 | W3: defor_4 | X3: defor_area_0 | Y3: defor_area_1 | Z3: defor_area_2 | AA3: defor_area_3 | AB3: defor_area_4 | AC3: average $/MTCO2/yr | AD3: MTCO2/million acres | AE3: acres (0-100) | AF3: rice_0 | AG3: rice_1 | AH3: rice_2 | AI3: rice_3 | AJ3: rice_4 | AK3: rice_area_0 | AL3: rice_area_1 | AM3: rice_area_2 | AN3: rice_area_3 | AO3: rice_area_4 | AP3: average $/MTCO2/yr | AQ3: MTCO2/million acres | AR3: acres (0-100) | AS3: fire_0 | AT3: fire_1 | AU3: fire_2 | AV3: fire_3 | AW3: fire_4 | AX3: fire_area_0 | AY3: fire_area_1 | AZ3: fire_area_2 | BA3: fire_area_3 | BB3: fire_area_4 | BC3: average $/MTCO2/yr | BD3: MTCO2/million acres | BE3: acres (0-100) | BF3: urban_0 | BG3: urban_1 | BH3: urban_2 | BI3: urban_3 | BJ3: urban_4 | BK3: urban_area_0 | BL3: urban_area_1 | BM3: urban_area_2 | BN3: urban_area_3 | BO3: urban_area_4 | BP3: cov_crop_0 | BQ3: cov_crop_1 | BR3: cov_crop_2 | BS3: cov_crop_3 | BT3: cov_crop_4 | BU3: cov_crop_area_0 | BV3: cov_crop_area_1 | BW3: cov_crop_area_2 | BX3: cov_crop_area_3 | BY3: cov_crop_area_4 | BZ3: aly_crop_0 | CA3: aly_crop_1 | CB3: aly_crop_2 | CC3: aly_crop_3 | CD3: aly_crop_4 | CE3: aly_crop_area_0 | CF3: aly_crop_area_1 | CG3: aly_crop_area_2 | CH3: aly_crop_area_3 | CI3: aly_crop_area_4 | CJ3: grass_con_0 | CK3: grass_con_1 | CL3: grass_con_2 | CM3: grass_con_3 | CN3: grass_con_4 | CO3: grass_con_area_0 | CP3: grass_con_area_1 | CQ3: grass_con_area_2 | CR3: grass_con_area_3 | CS3: grass_con_area_4 | CT3: average $/MTCO2/yr | CU3: MTCO2/million acres | CV3: acres (0-100) | CW3: grass_res_0 | CX3: grass_res_1 | CY3: grass_res_2 | CZ3: grass_res_3 | DA3: grass_res_4 | DB3: grass_res_area_0 | DC3: grass_res_area_1 | DD3: grass_res_area_2 | DE3: grass_res_area_3 | DF3: grass_res_area_4 | DG3: average $/MTCO2/yr | DH3: MTCO2/million acres | DI3: acres (0-100) | DJ3: nut_mgt_0 | DK3: nut_mgt_1 | DL3: nut_mgt_2 | DM3: nut_mgt_3 | DN3: nut_mgt_4 | DO3: nut_mgt_area_0 | DP3: nut_mgt_area_1 | DQ3: nut_mgt_area_2 | DR3: nut_mgt_area_3 | DS3: nut_mgt_area_4 | DT3: manure_0 | DU3: manure_1 | DV3: manure_2 | DW3: manure_3 | DX3: manure_4 | DY3: manure_area_0 | DZ3: manure_area_1 | EA3: manure_area_2 | EB3: manure_area_3 | EC3: manure_area_4
A4: Alabama | B4: AL | C4: 1 | D4: 1.5133086e+08 | E4: 98863107 | G4: 500021.36 | H4: 11757645 | I4: 11757645 | J4: 14286325 | L4: 155206.13 | M4: 3649561.2 | N4: 3649561.2 | O4: 4434460.7 | P4: =((G4*10+(H4-G4)*50+(I4-H4)*100)/I4) -> 48.298906 | Q4: =I4/N4 -> 3.22166 | R4: =N4 -> 3649561.2 | T4: 2113474 | U4: 2201535.5 | V4: 2201535.5 | W4: 2201535.5 | Y4: 415964.4 | Z4: 433296.25 | AA4: 433296.25 | AB4: 433296.25 | AC4: =((T4*10+(U4-T4)*50+(V4-U4)*100)/V4) -> 11.6 | AD4: =V4/AA4 -> 5.0809013 | AE4: =AA4 -> 433296.25 | AF4: -9999 | AG4: -9999 | AH4: -9999 | AI4: -9999 | AJ4: -9999 | AK4: -9999 | AL4: -9999 | AM4: -9999 | AN4: -9999 | AO4: 0 | AP4: =(IF(AK4=-9999,0,(AG4*10+(AH4-AG4)*50+(AI4-AH4)*100)/AI4)) -> 0 | AQ4: =IF(AK4=-9999,0,AI4/AN4) -> 0 | AR4: =IF(AK4=-9999,0,AN4) -> 0 | AS4: -9999 | AT4: -9999 | AU4: -9999 | AV4: -9999 | AW4: -9999 | AX4: -9999 | AY4: -9999 | AZ4: -9999 | BA4: -9999 | BB4: -9999 | BC4: =(IF(AY4=-9999,0,(AT4*10+(AU4-AT4)*50+(AV4-AU4)*100)/AV4)) -> 0 | BD4: =IF(AY4=-9999,0,AV4/BA4) -> 0 | BE4: =IF(AY4=-9999,0,BA4) -> 0 | BF4: 0 | BG4: 0 | BH4: 0 | BI4: 0 | BJ4: 521818.15 | BK4: 0 | BL4: 0 | BM4: 0 | BN4: 0 | BO4: 145838.12 | BQ4: 732209.45 | BR4: 732209.45 | BS4: 755634.11 | BT4: 755634.11 | BV4: 1542008.1 | BW4: 1542008.1 | BX4: 1591339.7 | BY4: 1591339.7 | CA4: 29891.776 | CB4: 478268.42 | CC4: 597835.52 | CD4: 597835.52 | CF4: 13892.648 | CG4: 222282.37 | CH4: 277852.96 | CI4: 277852.96 | CK4: 151246.23 | CL4: 1279373 | CM4: 1159706.4 | CN4: 1159706.4 | CP4: 699.26671 | CQ4: 19062.678 | CR4: 19062.678 | CS4: 19062.678 | CT4: =(IF(CP4=-9999,0,(CK4*10+(CL4-CK4)*50+(CM4-CL4)*100)/CM4)) -> 39.623941 | CU4: =IF(CP4=-9999,0,CM4/CR4) -> 60.836489 | CV4: =IF(CP4=-9999,0,CR4) -> 19062.678 | CX4: 1973.6581 | CY4: 94481.312 | CZ4: 119436.58 | DA4: 121083.32 | DC4: 1211.6188 | DD4: 45882.656 | DE4: 57212.783 | DF4: 58001.605 | DG4: =(IF(DC4=-9999,0,(CX4*10+(CY4-CX4)*50+(CZ4-CY4)*100)/CZ4)) -> 59.786091 | DH4: =IF(DC4=-9999,0,CZ4/DE4) -> 2.0875856 | DI4: =IF(DC4=-9999,0,DE4) -> 57212.783 | DK4: 163418.85 | DL4: 184504.92 | DM4: 197615.71 | DN4: 247552.05 | DO4: -9999 | DP4: -9999 | DQ4: -9999 | DR4: -9999 | DS4: -9999 | DU4: 7127 | DV4: 20108 | DW4: 25903 | DX4: 25903 | DY4: -9999 | DZ4: -9999 | EA4: -9999 | EB4: -9999 | EC4: -9999
A5: Arizona | B5: AR | C5: 4 | D5: 91536412 | E5: 55797032 | G5: 39172.044 | H5: 921102.63 | I5: 921102.63 | J5: 1119201.3 | L5: 87162.765 | M5: 2049570.2 | N5: 2049570.2 | O5: 2490364.7 | P5: =((G5*10+(H5-G5)*50+(I5-H5)*100)/I5) -> 48.298906 | Q5: =I5/N5 -> 0.44941259 | R5: =N5 -> 2049570.2 | T5: 85449.954 | U5: 89010.369 | V5: 89010.369 | W5: 89010.369 | Y5: 41397.659 | Z5: 43122.561 | AA5: 43122.561 | AB5: 43122.561 | AC5: =((T5*10+(U5-T5)*50+(V5-U5)*100)/V5) -> 11.6 | AD5: =V5/AA5 -> 2.0641253 | AE5: =AA5 -> 43122.561 | AF5: -9999 | AG5: -9999 | AH5: -9999 | AI5: -9999 | AJ5: -9999 | AK5: -9999 | AL5: -9999 | AM5: -9999 | AN5: -9999 | AO5: -9999 | AP5: =(IF(AK5=-9999,0,(AG5*10+(AH5-AG5)*50+(AI5-AH5)*100)/AI5)) -> 0 | AQ5: =IF(AK5=-9999,0,AI5/AN5) -> 0 | AR5: =IF(AK5=-9999,0,AN5) -> 0 | AS5: 0 | AT5: 0 | AU5: 1808984 | AV5: 1808984 | AW5: 1808984 | AX5: -9999 | AY5: 0 | AZ5: 2830272.6 | BA5: 2830272.6 | BB5: 2830272.6 | BC5: =(IF(AY5=-9999,0,(AT5*10+(AU5-AT5)*50+(AV5-AU5)*100)/AV5)) -> 50 | BD5: =IF(AY5=-9999,0,AV5/BA5) -> 0.63915537 | BE5: =IF(AY5=-9999,0,BA5) -> 2830272.6 | BF5: 0 | BG5: 0 | BH5: 0 | BI5: 0 | BJ5: 497483.95 | BK5: 0 | BL5: 0 | BM5: 0 | BN5: 0 | BO5: 134716.81 | BQ5: 220294.05 | BR5: 220294.05 | BS5: 227341.64 | BT5: 227341.64 | BV5: 463931.76 | BW5: 463931.76 | BX5: 478773.75 | BY5: 478773.75 | CA5: 8993.3016 | CB5: 143892.83 | CC5: 179866.03 | CD5: 179866.03 | CF5: 4179.7708 | CG5: 66876.333 | CH5: 83595.416 | CI5: 83595.416 | CK5: 87136.651 | CL5: 128053.36 | CM5: 116076.7 | CN5: 116076.7 | CP5: 10.346468 | CQ5: 3957.2497 | CR5: 4200.1309 | CS5: 4227.3038 | CT5: =(IF(CP5=-9999,0,(CK5*10+(CL5-CK5)*50+(CM5-CL5)*100)/CM5)) -> 14.813788 | CU5: =IF(CP5=-9999,0,CM5/CR5) -> 27.636448 | CV5: =IF(CP5=-9999,0,CR5) -> 4200.1309 | CX5: 106.96426 | CY5: 5120.504 | CZ5: 6472.9785 | DA5: 6562.2247 | DC5: 268.68632 | DD5: 10174.852 | DE5: 12687.4 | DF5: 12862.327 | DG5: =(IF(DC5=-9999,0,(CX5*10+(CY5-CX5)*50+(CZ5-CY5)*100)/CZ5)) -> 59.786091 | DH5: =IF(DC5=-9999,0,CZ5/DE5) -> 0.51018953 | DI5: =IF(DC5=-9999,0,DE5) -> 12687.4 | DK5: 173735.03 | DL5: 196142.32 | DM5: 213151.23 | DN5: 266173.04 | DO5: -9999 | DP5: -9999 | DQ5: -9999 | DR5: -9999 | DS5: -9999 | DU5: 11962 | DV5: 48324 | DW5: 61252 | DX5: 61252 | DY5: -9999 | DZ5: -9999 | EA5: -9999 | EB5: -9999 | EC5: -9999
A6: Arkansas | B6: AZ | C6: 5 | D6: 1.054362e+08 | E6: 1.0726192e+08 | G6: 427670.46 | H6: 10056365 | I6: 10056365 | J6: 12219156 | L6: 136499.75 | M6: 3209694.1 | N6: 3209694.1 | O6: 3899992.8 | P6: =((G6*10+(H6-G6)*50+(I6-H6)*100)/I6) -> 48.298906 | Q6: =I6/N6 -> 3.1331227 | R6: =N6 -> 3209694.1 | T6: 1467744.9 | U6: 1528901 | V6: 1528901 | W6: 1528901 | Y6: 280617.98 | Z6: 292310.39 | AA6: 292310.39 | AB6: 292310.39 | AC6: =((T6*10+(U6-T6)*50+(V6-U6)*100)/V6) -> 11.6 | AD6: =V6/AA6 -> 5.2304024 | AE6: =AA6 -> 292310.39 | AF6: 0 | AG6: 631622.97 | AH6: 1316897.3 | AI6: 1609541.2 | AJ6: 1804637 | AK6: 0 | AL6: 1339333.3 | AM6: 1339333.3 | AN6: 1339333.3 | AO6: 1339333.3 | AP6: =(IF(AK6=-9999,0,(AG6*10+(AH6-AG6)*50+(AI6-AH6)*100)/AI6)) -> 43.393939 | AQ6: =IF(AK6=-9999,0,AI6/AN6) -> 1.201748 | AR6: =IF(AK6=-9999,0,AN6) -> 1339333.3 | AS6: -9999 | AT6: -9999 | AU6: -9999 | AV6: -9999 | AW6: -9999 | AX6: -9999 | AY6: -9999 | AZ6: -9999 | BA6: -9999 | BB6: -9999 | BC6: =(IF(AY6=-9999,0,(AT6*10+(AU6-AT6)*50+(AV6-AU6)*100)/AV6)) -> 0 | BD6: =IF(AY6=-9999,0,AV6/BA6) -> 0 | BE6: =IF(AY6=-9999,0,BA6) -> 0 | BF6: 0 | BG6: 0 | BH6: 0 | BI6: 0 | BJ6: 249732.81 | BK6: 0 | BL6: 0 | BM6: 0 | BN6: 0 | BO6: 72325.86 | BQ6: 2270585.7 | BR6: 2270585.7 | BS6: 2343225.7 | BT6: 2343225.7 | BV6: 4781776.1 | BW6: 4781776.1 | BX6: 4934753.5 | BY6: 4934753.5 | CA6: 92694.569 | CB6: 1483113.1 | CC6: 1853891.4 | CD6: 1853891.4 | CF6: 43081.181 | CG6: 689298.9 | CH6: 861623.62 | CI6: 861623.62 | CK6: 242199.15 | CL6: 447446.3 | CM6: 405594.24 | CN6: 405594.24 | CP6: 30.363846 | CQ6: 6628.1551 | CR6: 6628.1551 | CS6: 6628.1551 | CT6: =(IF(CP6=-9999,0,(CK6*10+(CL6-CK6)*50+(CM6-CL6)*100)/CM6)) -> 20.954791 | CU6: =IF(CP6=-9999,0,CM6/CR6) -> 61.19263 | CV6: =IF(CP6=-9999,0,CR6) -> 6628.1551 | CX6: 607.60662 | CY6: 29086.837 | CZ6: 36769.52 | DA6: 37276.48 | DC6: 421.2838 | DD6: 15953.549 | DE6: 19893.071 | DF6: 20167.347 | DG6: =(IF(DC6=-9999,0,(CX6*10+(CY6-CX6)*50+(CZ6-CY6)*100)/CZ6)) -> 59.786091 | DH6: =IF(DC6=-9999,0,CZ6/DE6) -> 1.8483582 | DI6: =IF(DC6=-9999,0,DE6) -> 19893.071 | DK6: 705625.2 | DL6: 796694.32 | DM6: 846553.69 | DN6: 1062320.5 | DO6: -9999 | DP6: -9999 | DQ6: -9999 | DR6: -9999 | DS6: -9999 | DU6: 276204 | DV6: 523790 | DW6: 551481 | DX6: 551481 | DY6: -9999 | DZ6: -9999 | EA6: -9999 | EB6: -9999 | EC6: -9999
A7: California | B7: CA | C7: 6 | D7: 4.5452145e+08 | E7: 427693094 | F7: 0 | G7: 194039.57 | H7: 4562702 | I7: 4562702 | J7: 5543987.8 | K7: 0 | L7: 288428.71 | M7: 6782195.1 | N7: 6782195.1 | O7: 8240820.2 | P7: =((G7*10+(H7-G7)*50+(I7-H7)*100)/I7) -> 48.298906 | Q7: =I7/N7 -> 0.67274709 | R7: =N7 -> 6782195.1 | S7: 0 | T7: 1536798.8 | U7: 1600832.1 | V7: 1600832.1 | W7: 1600832.1 | X7: 0 | Y7: 208118.11 | Z7: 216789.7 | AA7: 216789.7 | AB7: 216789.7 | AC7: =((T7*10+(U7-T7)*50+(V7-U7)*100)/V7) -> 11.6 | AD7: =V7/AA7 -> 7.3842629 | AE7: =AA7 -> 216789.7 | AF7: 0 | AG7: 222435.66 | AH7: 463765.48 | AI7: 566824.47 | AJ7: 635530.47 | AK7: 0 | AL7: 471666.67 | AM7: 471666.67 | AN7: 471666.67 | AO7: 471666.67 | AP7: =(IF(AK7=-9999,0,(AG7*10+(AH7-AG7)*50+(AI7-AH7)*100)/AI7)) -> 43.393939 | AQ7: =IF(AK7=-9999,0,AI7/AN7) -> 1.201748 | AR7: =IF(AK7=-9999,0,AN7) -> 471666.67 | AS7: 0 | AT7: 0 | AU7: 3187496.4 | AV7: 5109342 | AW7: 5109342 | AX7: -9999 | AY7: 0 | AZ7: 16636427 | BA7: 20091506 | BB7: 20091506 | BC7: =(IF(AY7=-9999,0,(AT7*10+(AU7-AT7)*50+(AV7-AU7)*100)/AV7)) -> 68.807173 | BD7: =IF(AY7=-9999,0,AV7/BA7) -> 0.25430358 | BE7: =IF(AY7=-9999,0,BA7) -> 20091506 | BF7: 0 | BG7: 0 | BH7: 0 | BI7: 0 | BJ7: 1814651.1 | BK7: 0 | BL7: 0 | BM7: 0 | BN7: 0 | BO7: 447187.36 | BQ7: 984485.07 | BR7: 984485.07 | BS7: 1015980.5 | BT7: 1015980.5 | BV7: 2073292 | BW7: 2073292 | BX7: 2139620.2 | BY7: 2139620.2 | CA7: 40190.695 | CB7: 643051.13 | CC7: 803813.91 | CD7: 803813.91 | CF7: 18679.224 | CG7: 298867.59 | CH7: 373584.48 | CI7: 373584.48 | CJ7: 0 | CK7: 615968.76 | CL7: 2545068.7 | CM7: 2352081.1 | CN7: 2352081.1 | CO7: 0 | CP7: 3446.6088 | CQ7: 50091.674 | CR7: 50475.812 | CS7: 50481.032 | CT7: =(IF(CP7=-9999,0,(CK7*10+(CL7-CK7)*50+(CM7-CL7)*100)/CM7)) -> 35.422216 | CU7: =IF(CP7=-9999,0,CM7/CR7) -> 46.598183 | CV7: =IF(CP7=-9999,0,CR7) -> 50475.812 | CX7: 3109.9094 | CY7: 148874.99 | CZ7: 188197.22 | DA7: 190791.99 | DC7: 3208.5611 | DD7: 121504.64 | DE7: 151508.64 | DF7: 153597.56 | DG7: =(IF(DC7=-9999,0,(CX7*10+(CY7-CX7)*50+(CZ7-CY7)*100)/CZ7)) -> 59.786091 | DH7: =IF(DC7=-9999,0,CZ7/DE7) -> 1.242155 | DI7: =IF(DC7=-9999,0,DE7) -> 151508.64 | DJ7: 1232971.2 | DK7: 1274395.6 | DL7: 1437329.9 | DM7: 2006307 | DN7: 2385561.9 | DO7: -9999 | DP7: -9999 | DQ7: -9999 | DR7: -9999 | DS7: -9999 | DT7: 0 | DU7: 2327889 | DV7: 4475325 | DW7: 4766315 | DX7: 4766315 | DY7: -9999 | DZ7: -9999 | EA7: -9999 | EB7: -9999 | EC7: -9999
A8: Colorado | B8: CO | C8: 8 | D8: 1.2724922e+08 | E8: 1.1820659e+08 | F8: 0 | G8: 156714.81 | H8: 3685036.7 | I8: 3685036.7 | J8: 4477565.9 | K8: 0 | L8: 280035.75 | M8: 6584840.6 | N8: 6584840.6 | O8: 8001021.3 | P8: =((G8*10+(H8-G8)*50+(I8-H8)*100)/I8) -> 48.298906 | Q8: =I8/N8 -> 0.55962429 | R8: =N8 -> 6584840.6 | S8: 0 | T8: 165798.02 | U8: 172706.27 | V8: 172706.27 | W8: 172706.27 | X8: 0 | Y8: 52078.227 | Z8: 54248.153 | AA8: 54248.153 | AB8: 54248.153 | AC8: =((T8*10+(U8-T8)*50+(V8-U8)*100)/V8) -> 11.6 | AD8: =V8/AA8 -> 3.1836341 | AE8: =AA8 -> 54248.153 | AF8: -9999 | AG8: -9999 | AH8: -9999 | AI8: -9999 | AJ8: -9999 | AK8: -9999 | AL8: -9999 | AM8: -9999 | AN8: -9999 | AO8: -9999 | AP8: =(IF(AK8=-9999,0,(AG8*10+(AH8-AG8)*50+(AI8-AH8)*100)/AI8)) -> 0 | AQ8: =IF(AK8=-9999,0,AI8/AN8) -> 0 | AR8: =IF(AK8=-9999,0,AN8) -> 0 | AS8: 0 | AT8: 0 | AU8: 1098.3728 | AV8: 1098.3728 | AW8: 38947.483 | AX8: -9999 | AY8: 0 | AZ8: 1718.4754 | BA8: 1718.4754 | BB8: 2945355.4 | BC8: =(IF(AY8=-9999,0,(AT8*10+(AU8-AT8)*50+(AV8-AU8)*100)/AV8)) -> 50 | BD8: =IF(AY8=-9999,0,AV8/BA8) -> 0.63915537 | BE8: =IF(AY8=-9999,0,BA8) -> 1718.4754 | BF8: 0 | BG8: 0 | BH8: 0 | BI8: 0 | BJ8: 221528.89 | BK8: 0 | BL8: 0 | BM8: 0 | BN8: 0 | BO8: 107797.86 | BQ8: 1941301.9 | BR8: 1941301.9 | BS8: 2003407.5 | BT8: 2003407.5 | BV8: 4088315.6 | BW8: 4088315.6 | BX8: 4219107.9 | BY8: 4219107.9 | CA8: 79251.86 | CB8: 1268029.8 | CC8: 1585037.2 | CD8: 1585037.2 | CF8: 36833.482 | CG8: 589335.71 | CH8: 736669.64 | CI8: 736669.64 | CJ8: 0 | CK8: 1851913.1 | CL8: 4129008 | CM8: 3742799.7 | CN8: 3742799.7 | CO8: 0 | CP8: 5463.0051 | CQ8: 74410.31 | CR8: 74410.31 | CS8: 74410.31 | CT8: =(IF(CP8=-9999,0,(CK8*10+(CL8-CK8)*50+(CM8-CL8)*100)/CM8)) -> 25.048907 | CU8: =IF(CP8=-9999,0,CM8/CR8) -> 50.299477 | CV8: =IF(CP8=-9999,0,CR8) -> 74410.31 | CX8: 4701.8756 | CY8: 225084.27 | CZ8: 284535.59 | DA8: 288458.63 | DC8: 4729.4998 | DD8: 179100.9 | DE8: 223327.54 | DF8: 226406.67 | DG8: =(IF(DC8=-9999,0,(CX8*10+(CY8-CX8)*50+(CZ8-CY8)*100)/CZ8)) -> 59.786091 | DH8: =IF(DC8=-9999,0,CZ8/DE8) -> 1.274073 | DI8: =IF(DC8=-9999,0,DE8) -> 223327.54 | DJ8: 324336.54 | DK8: 335399.82 | DL8: 378502.41 | DM8: 459579.7 | DN8: 560888.92 | DO8: -9999 | DP8: -9999 | DQ8: -9999 | DR8: -9999 | DS8: -9999 | DT8: 0 | DU8: 193218 | DV8: 389298 | DW8: 455516 | DX8: 455516 | DY8: -9999 | DZ8: -9999 | EA8: -9999 | EB8: -9999 | EC8: -9999
A9: Connecticut | B9: CT | C9: 9 | D9: 40713158 | E9: 35152743 | F9: 0 | G9: 19744.635 | H9: 464280.98 | I9: 464280.98 | J9: 564132.42 | K9: 0 | L9: 4423.6865 | M9: 104019.83 | N9: 104019.83 | O9: 126391.04 | P9: =((G9*10+(H9-G9)*50+(I9-H9)*100)/I9) -> 48.298906 | Q9: =I9/N9 -> 4.4633893 | R9: =N9 -> 104019.83 | S9: 0 | T9: 172451.82 | U9: 179637.32 | V9: 179637.32 | W9: 179637.32 | X9: 0 | Y9: 17425.287 | Z9: 18151.34 | AA9: 18151.34 | AB9: 18151.34 | AC9: =((T9*10+(U9-T9)*50+(V9-U9)*100)/V9) -> 11.6 | AD9: =V9/AA9 -> 9.8966421 | AE9: =AA9 -> 18151.34 | AF9: -9999 | AG9: -9999 | AH9: -9999 | AI9: -9999 | AJ9: -9999 | AK9: -9999 | AL9: -9999 | AM9: -9999 | AN9: -9999 | AO9: -9999 | AP9: =(IF(AK9=-9999,0,(AG9*10+(AH9-AG9)*50+(AI9-AH9)*100)/AI9)) -> 0 | AQ9: =IF(AK9=-9999,0,AI9/AN9) -> 0 | AR9: =IF(AK9=-9999,0,AN9) -> 0 | AS9: -9999 | AT9: -9999 | AU9: -9999 | AV9: -9999 | AW9: -9999 | AX9: -9999 | AY9: -9999 | AZ9: -9999 | BA9: -9999 | BB9: -9999 | BC9: =(IF(AY9=-9999,0,(AT9*10+(AU9-AT9)*50+(AV9-AU9)*100)/AV9)) -> 0 | BD9: =IF(AY9=-9999,0,AV9/BA9) -> 0 | BE9: =IF(AY9=-9999,0,BA9) -> 0 | BF9: 0 | BG9: 0 | BH9: 0 | BI9: 0 | BJ9: 325993.86 | BK9: 0 | BL9: 0 | BM9: 0 | BN9: 0 | BO9: 130754.76 | BQ9: 23144.552 | BR9: 23144.552 | BS9: 23884.986 | BT9: 23884.986 | BV9: 48741.637 | BW9: 48741.637 | BX9: 50300.967 | BY9: 50300.967 | CA9: 944.85499 | CB9: 15117.68 | CC9: 18897.1 | CD9: 18897.1 | CF9: 439.13542 | CG9: 7026.1668 | CH9: 8782.7085 | CI9: 8782.7085 | CJ9: 0 | CK9: 0 | CL9: 2696.9799 | CM9: 2444.7168 | CN9: 2444.7168 | CO9: 0 | CP9: 0 | CQ9: 28.284054 | CR9: 28.284054 | CS9: 28.284054 | CT9: =(IF(CP9=-9999,0,(CK9*10+(CL9-CK9)*50+(CM9-CL9)*100)/CM9)) -> 44.840649 | CU9: =IF(CP9=-9999,0,CM9/CR9) -> 86.434455 | CV9: =IF(CP9=-9999,0,CR9) -> 28.284054 | CX9: 3.3966874 | CY9: 162.60339 | CZ9: 205.55168 | DA9: 208.38573 | DC9: 1.7977271 | DD9: 68.077925 | DE9: 84.888885 | DF9: 86.059291 | DG9: =(IF(DC9=-9999,0,(CX9*10+(CY9-CX9)*50+(CZ9-CY9)*100)/CZ9)) -> 59.786091 | DH9: =IF(DC9=-9999,0,CZ9/DE9) -> 2.4214205 | DI9: =IF(DC9=-9999,0,DE9) -> 84.888885 | DJ9: 13142.727 | DK9: 13596.588 | DL9: 15351.271 | DM9: 16347.452 | DN9: 20504.259 | DO9: -9999 | DP9: -9999 | DQ9: -9999 | DR9: -9999 | DS9: -9999 | DT9: 0 | DU9: 0 | DV9: 1776 | DW9: 1776 | DX9: 1776 | DY9: -9999 | DZ9: -9999 | EA9: -9999 | EB9: -9999 | EC9: -9999
A10: Delaware | B10: DE | C10: 10 | D10: 14913536 | E10: 13717565 | F10: 0 | G10: 15489.023 | H10: 364213.31 | I10: 364213.31 | J10: 442543.52 | K10: 0 | L10: 3838.283 | M10: 90254.482 | N10: 90254.482 | O10: 109665.23 | P10: =((G10*10+(H10-G10)*50+(I10-H10)*100)/I10) -> 48.298906 | Q10: =I10/N10 -> 4.0354042 | R10: =N10 -> 90254.482 | S10: 0 | T10: 56029.702 | U10: 58364.273 | V10: 58364.273 | W10: 58364.273 | X10: 0 | Y10: 6290.631 | Z10: 6552.7407 | AA10: 6552.7407 | AB10: 6552.7407 | AC10: =((T10*10+(U10-T10)*50+(V10-U10)*100)/V10) -> 11.6 | AD10: =V10/AA10 -> 8.9068492 | AE10: =AA10 -> 6552.7407 | AF10: -9999 | AG10: -9999 | AH10: -9999 | AI10: -9999 | AJ10: -9999 | AK10: -9999 | AL10: -9999 | AM10: -9999 | AN10: -9999 | AO10: -9999 | AP10: =(IF(AK10=-9999,0,(AG10*10+(AH10-AG10)*50+(AI10-AH10)*100)/AI10)) -> 0 | AQ10: =IF(AK10=-9999,0,AI10/AN10) -> 0 | AR10: =IF(AK10=-9999,0,AN10) -> 0 | AS10: -9999 | AT10: -9999 | AU10: -9999 | AV10: -9999 | AW10: -9999 | AX10: -9999 | AY10: -9999 | AZ10: -9999 | BA10: -9999 | BB10: -9999 | BC10: =(IF(AY10=-9999,0,(AT10*10+(AU10-AT10)*50+(AV10-AU10)*100)/AV10)) -> 0 | BD10: =IF(AY10=-9999,0,AV10/BA10) -> 0 | BE10: =IF(AY10=-9999,0,BA10) -> 0 | BF10: 0 | BG10: 0 | BH10: 0 | BI10: 0 | BJ10: 45662.07 | BK10: 0 | BL10: 0 | BM10: 0 | BN10: 0 | BO10: 13066.425 | BQ10: 145495.07 | BR10: 145495.07 | BS10: 150149.71 | BT10: 150149.71 | BV10: 306407.65 | BW10: 306407.65 | BX10: 316210.17 | BY10: 316210.17 | CA10: 5939.702 | CB10: 95035.233 | CC10: 118794.04 | CD10: 118794.04 | CF10: 2760.565 | CG10: 44169.039 | CH10: 55211.299 | CI10: 55211.299 | CJ10: 0 | CK10: 889.61154 | CL10: 11469.964 | CM10: 10397.116 | CN10: 10397.116 | CO10: 0 | CP10: 0 | CQ10: 142.3889 | CR10: 142.3889 | CS10: 142.3889 | CT10: =(IF(CP10=-9999,0,(CK10*10+(CL10-CK10)*50+(CM10-CL10)*100)/CM10)) -> 41.418117 | CU10: =IF(CP10=-9999,0,CM10/CR10) -> 73.019145 | CV10: =IF(CP10=-9999,0,CR10) -> 142.3889 | CX10: 13.264913 | CY10: 635.00686 | CZ10: 802.7307 | DA10: 813.79836 | DC10: 9.0502015 | DD10: 342.72106 | DE10: 427.35158 | DF10: 433.24369 | DG10: =(IF(DC10=-9999,0,(CX10*10+(CY10-CX10)*50+(CZ10-CY10)*100)/CZ10)) -> 59.786091 | DH10: =IF(DC10=-9999,0,CZ10/DE10) -> 1.8783848 | DI10: =IF(DC10=-9999,0,DE10) -> 427.35158 | DJ10: 44876.666 | DK10: 46426.81 | DL10: 52418.88 | DM10: 55652.179 | DN10: 69849.647 | DO10: -9999 | DP10: -9999 | DQ10: -9999 | DR10: -9999 | DS10: -9999 | DT10: 0 | DU10: 0 | DV10: 247 | DW10: 247 | DX10: 247 | DY10: -9999 | DZ10: -9999 | EA10: -9999 | EB10: -9999 | EC10: -9999
A11: Florida | B11: FL | C11: 12 | D11: 2.6823182e+08 | E11: 2.3344256e+08 | G11: 277530.89 | H11: 6525940.7 | I11: 6525940.7 | J11: 7929454 | L11: 126629.58 | M11: 2977604.1 | N11: 2977604.1 | O11: 3617988 | P11: =((G11*10+(H11-G11)*50+(I11-H11)*100)/I11) -> 48.298906 | Q11: =I11/N11 -> 2.191675 | R11: =N11 -> 2977604.1 | T11: 1019621 | U11: 1062105.2 | V11: 1062105.2 | W11: 1062105.2 | Y11: 263558.23 | Z11: 274539.82 | AA11: 274539.82 | AB11: 274539.82 | AC11: =((T11*10+(U11-T11)*50+(V11-U11)*100)/V11) -> 11.6 | AD11: =V11/AA11 -> 3.8686745 | AE11: =AA11 -> 274539.82 | AF11: -9999 | AG11: -9999 | AH11: -9999 | AI11: -9999 | AJ11: -9999 | AK11: -9999 | AL11: -9999 | AM11: -9999 | AN11: -9999 | AO11: -9999 | AP11: =(IF(AK11=-9999,0,(AG11*10+(AH11-AG11)*50+(AI11-AH11)*100)/AI11)) -> 0 | AQ11: =IF(AK11=-9999,0,AI11/AN11) -> 0 | AR11: =IF(AK11=-9999,0,AN11) -> 0 | AS11: -9999 | AT11: -9999 | AU11: -9999 | AV11: -9999 | AW11: -9999 | AX11: -9999 | AY11: -9999 | AZ11: -9999 | BA11: -9999 | BB11: -9999 | BC11: =(IF(AY11=-9999,0,(AT11*10+(AU11-AT11)*50+(AV11-AU11)*100)/AV11)) -> 0 | BD11: =IF(AY11=-9999,0,AV11/BA11) -> 0 | BE11: =IF(AY11=-9999,0,BA11) -> 0 | BF11: 0 | BG11: 0 | BH11: 0 | BI11: 0 | BJ11: 2333798.8 | BK11: 0 | BL11: 0 | BM11: 0 | BN11: 0 | BO11: 470994.45 | BQ11: 360423.79 | BR11: 360423.79 | BS11: 371954.38 | BT11: 371954.38 | BV11: 759040.22 | BW11: 759040.22 | BX11: 783323.24 | BY11: 783323.24 | CA11: 14713.969 | CB11: 235423.5 | CC11: 294279.38 | CD11: 294279.38 | CF11: 6838.5362 | CG11: 109416.58 | CH11: 136770.72 | CI11: 136770.72 | CK11: 724484.78 | CL11: 1346897 | CM11: 1220914.4 | CN11: 1220914.4 | CP11: 8889.5278 | CQ11: 12325.261 | CR11: 12325.261 | CS11: 12325.261 | CT11: =(IF(CP11=-9999,0,(CK11*10+(CL11-CK11)*50+(CM11-CL11)*100)/CM11)) -> 21.10484 | CU11: =IF(CP11=-9999,0,CM11/CR11) -> 99.057898 | CV11: =IF(CP11=-9999,0,CR11) -> 12325.261 | CX11: 4238.94 | CY11: 202923 | CZ11: 256520.88 | DA11: 260057.67 | DC11: 783.39036 | DD11: 29666.121 | DE11: 36991.785 | DF11: 37501.81 | DG11: =(IF(DC11=-9999,0,(CX11*10+(CY11-CX11)*50+(CZ11-CY11)*100)/CZ11)) -> 59.786091 | DH11: =IF(DC11=-9999,0,CZ11/DE11) -> 6.9345364 | DI11: =IF(DC11=-9999,0,DE11) -> 36991.785 | DK11: 322463.88 | DL11: 364064.22 | DM11: 392246.3 | DN11: 490732.11 | DO11: -9999 | DP11: -9999 | DQ11: -9999 | DR11: -9999 | DS11: -9999 | DU11: 17130 | DV11: 34271 | DW11: 34923 | DX11: 34923 | DY11: -9999 | DZ11: -9999 | EA11: -9999 | EB11: -9999 | EC11: -9999
A12: Georgia | B12: GA | C12: 13 | D12: 1.6078401e+08 | E12: 1.1430292e+08 | G12: 401662.48 | H12: 9444806.2 | I12: 9444806.2 | J12: 11476071 | L12: 155695.57 | M12: 3661070 | N12: 3661070 | O12: 4448444.7 | P12: =((G12*10+(H12-G12)*50+(I12-H12)*100)/I12) -> 48.298906 | Q12: =I12/N12 -> 2.5797939 | R12: =N12 -> 3661070 | T12: 3244602.4 | U12: 3379794.2 | V12: 3379794.2 | W12: 3379794.2 | Y12: 586892.38 | Z12: 611346.23 | AA12: 611346.23 | AB12: 611346.23 | AC12: =((T12*10+(U12-T12)*50+(V12-U12)*100)/V12) -> 11.6 | AD12: =V12/AA12 -> 5.5284453 | AE12: =AA12 -> 611346.23 | AF12: -9999 | AG12: -9999 | AH12: -9999 | AI12: -9999 | AJ12: -9999 | AK12: -9999 | AL12: -9999 | AM12: -9999 | AN12: -9999 | AO12: -9999 | AP12: =(IF(AK12=-9999,0,(AG12*10+(AH12-AG12)*50+(AI12-AH12)*100)/AI12)) -> 0 | AQ12: =IF(AK12=-9999,0,AI12/AN12) -> 0 | AR12: =IF(AK12=-9999,0,AN12) -> 0 | AS12: -9999 | AT12: -9999 | AU12: -9999 | AV12: -9999 | AW12: -9999 | AX12: -9999 | AY12: -9999 | AZ12: -9999 | BA12: -9999 | BB12: -9999 | BC12: =(IF(AY12=-9999,0,(AT12*10+(AU12-AT12)*50+(AV12-AU12)*100)/AV12)) -> 0 | BD12: =IF(AY12=-9999,0,AV12/BA12) -> 0 | BE12: =IF(AY12=-9999,0,BA12) -> 0 | BF12: 0 | BG12: 0 | BH12: 0 | BI12: 0 | BJ12: 1208091.9 | BK12: 0 | BL12: 0 | BM12: 0 | BN12: 0 | BO12: 328073.58 | BQ12: 1152598.7 | BR12: 1152598.7 | BS12: 1189472.3 | BT12: 1189472.3 | BV12: 2427333.5 | BW12: 2427333.5 | BX12: 2504988.1 | BY12: 2504988.1 | CA12: 47053.778 | CB12: 752860.45 | CC12: 941075.57 | CD12: 941075.57 | CF12: 21868.944 | CG12: 349903.11 | CH12: 437378.88 | CI12: 437378.88 | CK12: 54842.543 | CL12: 1071085.6 | CM12: 970901.19 | CN12: 970901.19 | CP12: 788.84311 | CQ12: 17069.621 | CR12: 17069.621 | CS12: 17069.621 | CT12: =(IF(CP12=-9999,0,(CK12*10+(CL12-CK12)*50+(CM12-CL12)*100)/CM12)) -> 42.5812 | CU12: =IF(CP12=-9999,0,CM12/CR12) -> 56.878897 | CV12: =IF(CP12=-9999,0,CR12) -> 17069.621 | CX12: 1528.8933 | CY12: 73189.904 | CZ12: 92521.493 | DA12: 93797.134 | DC12: 1084.9406 | DD12: 41085.494 | DE12: 51231.024 | DF12: 51937.372 | DG12: =(IF(DC12=-9999,0,(CX12*10+(CY12-CX12)*50+(CZ12-CY12)*100)/CZ12)) -> 59.786091 | DH12: =IF(DC12=-9999,0,CZ12/DE12) -> 1.8059661 | DI12: =IF(DC12=-9999,0,DE12) -> 51231.024 | DK12: 330987.01 | DL12: 373661.68 | DM12: 410426.3 | DN12: 511344.51 | DO12: -9999 | DP12: -9999 | DQ12: -9999 | DR12: -9999 | DS12: -9999 | DU12: 13908 | DV12: 37422 | DW12: 46360 | DX12: 46360 | DY12: -9999 | DZ12: -9999 | EA12: -9999 | EB12: -9999 | EC12: -9999
A13: Idaho | B13: ID | C13: 16 | D13: 30143100 | E13: 29457755 | G13: 148578.44 | H13: 3493715.9 | I13: 3493715.9 | J13: 4245098.2 | L13: 254788.62 | M13: 5991172.4 | N13: 5991172.4 | O13: 7279674.9 | P13: =((G13*10+(H13-G13)*50+(I13-H13)*100)/I13) -> 48.298906 | Q13: =I13/N13 -> 0.58314393 | R13: =N13 -> 5991172.4 | T13: 430075.4 | U13: 447995.21 | V13: 447995.21 | W13: 447995.21 | Y13: 110002.05 | Z13: 114585.47 | AA13: 114585.47 | AB13: 114585.47 | AC13: =((T13*10+(U13-T13)*50+(V13-U13)*100)/V13) -> 11.6 | AD13: =V13/AA13 -> 3.9097035 | AE13: =AA13 -> 114585.47 | AF13: -9999 | AG13: -9999 | AH13: -9999 | AI13: -9999 | AJ13: -9999 | AK13: -9999 | AL13: -9999 | AM13: -9999 | AN13: -9999 | AO13: -9999 | AP13: =(IF(AK13=-9999,0,(AG13*10+(AH13-AG13)*50+(AI13-AH13)*100)/AI13)) -> 0 | AQ13: =IF(AK13=-9999,0,AI13/AN13) -> 0 | AR13: =IF(AK13=-9999,0,AN13) -> 0 | AS13: 0 | AT13: 0 | AU13: 0 | AV13: 0 | AW13: 1023606.3 | AX13: -9999 | AY13: 0 | AZ13: 0 | BA13: 0 | BB13: 1389497.1 | BC13: =(IF(AY13=-9999,0,(AT13*10+(AU13-AT13)*50+(AV13-AU13)*100)/AV13)) -> #DIV/0! | BD13: =IF(AY13=-9999,0,AV13/BA13) -> #DIV/0! | BE13: =IF(AY13=-9999,0,BA13) -> 0 | BF13: 0 | BG13: 0 | BH13: 0 | BI13: 0 | BJ13: 55054.211 | BK13: 0 | BL13: 0 | BM13: 0 | BN13: 0 | BO13: 28682.613 | BQ13: 1317977 | BR13: 1317977 | BS13: 1360141.4 | BT13: 1360141.4 | BV13: 2775614.7 | BW13: 2775614.7 | BX13: 2864411.4 | BY13: 2864411.4 | CA13: 53805.197 | CB13: 860883.15 | CC13: 1076103.9 | CD13: 1076103.9 | CF13: 25006.766 | CG13: 400108.26 | CH13: 500135.33 | CI13: 500135.33 | CK13: 496010.08 | CL13: 1300427.3 | CM13: 1178791.3 | CN13: 1178791.3 | CP13: 2603.0746 | CQ13: 19140.314 | CR13: 19284.301 | CS13: 19284.301 | CT13: =(IF(CP13=-9999,0,(CK13*10+(CL13-CK13)*50+(CM13-CL13)*100)/CM13)) -> 28.009507 | CU13: =IF(CP13=-9999,0,CM13/CR13) -> 61.126994 | CV13: =IF(CP13=-9999,0,CR13) -> 19284.301 | CX13: 1690.7664 | CY13: 80938.957 | CZ13: 102317.3 | DA13: 103728 | DC13: 1225.7051 | DD13: 46416.089 | DE13: 57877.94 | DF13: 58675.932 | DG13: =(IF(DC13=-9999,0,(CX13*10+(CY13-CX13)*50+(CZ13-CY13)*100)/CZ13)) -> 59.786091 | DH13: =IF(DC13=-9999,0,CZ13/DE13) -> 1.7678117 | DI13: =IF(DC13=-9999,0,DE13) -> 57877.94 | DK13: 451123.55 | DL13: 509237.18 | DM13: 575015.34 | DN13: 712222 | DO13: -9999 | DP13: -9999 | DQ13: -9999 | DR13: -9999 | DS13: -9999 | DU13: 680363 | DV13: 1372296 | DW13: 1453924 | DX13: 1453924 | DY13: -9999 | DZ13: -9999 | EA13: -9999 | EB13: -9999 | EC13: -9999
A14: Illinois | B14: IL | C14: 17 | D14: 2.890508e+08 | E14: 2.6491582e+08 | G14: 199613.61 | H14: 4693771.4 | I14: 4693771.4 | J14: 5703245.9 | L14: 87613.933 | M14: 2060179 | N14: 2060179 | O14: 2503255.2 | P14: =((G14*10+(H14-G14)*50+(I14-H14)*100)/I14) -> 48.298906 | Q14: =I14/N14 -> 2.2783318 | R14: =N14 -> 2060179 | T14: 271812.66 | U14: 283138.18 | V14: 283138.18 | W14: 283138.18 | Y14: 41574.498 | Z14: 43306.769 | AA14: 43306.769 | AB14: 43306.769 | AC14: =((T14*10+(U14-T14)*50+(V14-U14)*100)/V14) -> 11.6 | AD14: =V14/AA14 -> 6.537966 | AE14: =AA14 -> 43306.769 | AF14: -9999 | AG14: -9999 | AH14: -9999 | AI14: -9999 | AJ14: -9999 | AK14: -9999 | AL14: -9999 | AM14: -9999 | AN14: -9999 | AO14: -9999 | AP14: =(IF(AK14=-9999,0,(AG14*10+(AH14-AG14)*50+(AI14-AH14)*100)/AI14)) -> 0 | AQ14: =IF(AK14=-9999,0,AI14/AN14) -> 0 | AR14: =IF(AK14=-9999,0,AN14) -> 0 | AS14: -9999 | AT14: -9999 | AU14: -9999 | AV14: -9999 | AW14: -9999 | AX14: -9999 | AY14: -9999 | AZ14: -9999 | BA14: -9999 | BB14: -9999 | BC14: =(IF(AY14=-9999,0,(AT14*10+(AU14-AT14)*50+(AV14-AU14)*100)/AV14)) -> 0 | BD14: =IF(AY14=-9999,0,AV14/BA14) -> 0 | BE14: =IF(AY14=-9999,0,BA14) -> 0 | BF14: 0 | BG14: 0 | BH14: 0 | BI14: 0 | BJ14: 770695.6 | BK14: 0 | BL14: 0 | BM14: 0 | BN14: 0 | BO14: 261061.26 | BQ14: 7178598.3 | BR14: 7178598.3 | BS14: 7408254.2 | BT14: 7408254.2 | BV14: 15117883 | BW14: 15117883 | BX14: 15601531 | BY14: 15601531 | CA14: 293059.66 | CB14: 4688954.5 | CC14: 5861193.2 | CD14: 5861193.2 | CF14: 136203.84 | CG14: 2179261.4 | CH14: 2724076.8 | CI14: 2724076.8 | CK14: 0 | CL14: 359788.63 | CM14: 1705976.4 | CN14: 1705976.4 | CP14: 0 | CQ14: 28918.574 | CR14: 31003.973 | CS14: 31003.973 | CT14: =(IF(CP14=-9999,0,(CK14*10+(CL14-CK14)*50+(CM14-CL14)*100)/CM14)) -> 89.455053 | CU14: =IF(CP14=-9999,0,CM14/CR14) -> 55.024446 | CV14: =IF(CP14=-9999,0,CR14) -> 31003.973 | CX14: 2725.4 | CY14: 130468.08 | CZ14: 164928.5 | DA14: 167202.45 | DC14: 1970.6044 | DD14: 74624.597 | DE14: 93052.172 | DF14: 94335.13 | DG14: =(IF(DC14=-9999,0,(CX14*10+(CY14-CX14)*50+(CZ14-CY14)*100)/CZ14)) -> 59.786091 | DH14: =IF(DC14=-9999,0,CZ14/DE14) -> 1.7724304 | DI14: =IF(DC14=-9999,0,DE14) -> 93052.172 | DK14: 2595411.8 | DL14: 2925357.3 | DM14: 4669426.5 | DN14: 5429062.5 | DO14: -9999 | DP14: -9999 | DQ14: -9999 | DR14: -9999 | DS14: -9999 | DU14: 596839 | DV14: 674807 | DW14: 849748 | DX14: 849748 | DY14: -9999 | DZ14: -9999 | EA14: -9999 | EB14: -9999 | EC14: -9999
A15: Indiana | B15: IN | C15: 18 | D15: 251501677 | E15: 2.3845416e+08 | G15: 330015.16 | H15: 7760070.8 | I15: 7760070.8 | J15: 9429004.6 | L15: 112247.9 | M15: 2639429.2 | N15: 2639429.2 | O15: 3207082.9 | P15: =((G15*10+(H15-G15)*50+(I15-H15)*100)/I15) -> 48.298906 | Q15: =I15/N15 -> 2.9400564 | R15: =N15 -> 2639429.2 | T15: 306677.86 | U15: 319456.1 | V15: 319456.1 | W15: 319456.1 | Y15: 36699.201 | Z15: 38228.334 | AA15: 38228.334 | AB15: 38228.334 | AC15: =((T15*10+(U15-T15)*50+(V15-U15)*100)/V15) -> 11.6 | AD15: =V15/AA15 -> 8.3565268 | AE15: =AA15 -> 38228.334 | AF15: -9999 | AG15: -9999 | AH15: -9999 | AI15: -9999 | AJ15: -9999 | AK15: -9999 | AL15: -9999 | AM15: -9999 | AN15: -9999 | AO15: -9999 | AP15: =(IF(AK15=-9999,0,(AG15*10+(AH15-AG15)*50+(AI15-AH15)*100)/AI15)) -> 0 | AQ15: =IF(AK15=-9999,0,AI15/AN15) -> 0 | AR15: =IF(AK15=-9999,0,AN15) -> 0 | AS15: -9999 | AT15: -9999 | AU15: -9999 | AV15: -9999 | AW15: -9999 | AX15: -9999 | AY15: -9999 | AZ15: -9999 | BA15: -9999 | BB15: -9999 | BC15: =(IF(AY15=-9999,0,(AT15*10+(AU15-AT15)*50+(AV15-AU15)*100)/AV15)) -> 0 | BD15: =IF(AY15=-9999,0,AV15/BA15) -> 0 | BE15: =IF(AY15=-9999,0,BA15) -> 0 | BF15: 0 | BG15: 0 | BH15: 0 | BI15: 0 | BJ15: 412730.95 | BK15: 0 | BL15: 0 | BM15: 0 | BN15: 0 | BO15: 158260.68 | BQ15: 3820429.1 | BR15: 3820429.1 | BS15: 3942651.3 | BT15: 3942651.3 | BV15: 8045693.4 | BW15: 8045693.4 | BX15: 8303089.1 | BY15: 8303089.1 | CA15: 155965.49 | CB15: 2495447.9 | CC15: 3119309.9 | CD15: 3119309.9 | CF15: 72487.286 | CG15: 1159796.6 | CH15: 1449745.7 | CI15: 1449745.7 | CK15: 0 | CL15: 514658.93 | CM15: 808318.09 | CN15: 808318.09 | CP15: 48.012577 | CQ15: 11229.65 | CR15: 11476.546 | CS15: 11476.546 | CT15: =(IF(CP15=-9999,0,(CK15*10+(CL15-CK15)*50+(CM15-CL15)*100)/CM15)) -> 68.164827 | CU15: =IF(CP15=-9999,0,CM15/CR15) -> 70.432177 | CV15: =IF(CP15=-9999,0,CR15) -> 11476.546 | CX15: 1094.3592 | CY15: 52388.251 | CZ15: 66225.517 | DA15: 67138.602 | DC15: 729.44624 | DD15: 27623.317 | DE15: 34444.537 | DF15: 34919.442 | DG15: =(IF(DC15=-9999,0,(CX15*10+(CY15-CX15)*50+(CZ15-CY15)*100)/CZ15)) -> 59.786091 | DH15: =IF(DC15=-9999,0,CZ15/DE15) -> 1.9226711 | DI15: =IF(DC15=-9999,0,DE15) -> 34444.537 | DK15: 1564992.8 | DL15: 1764800.5 | DM15: 2550554.8 | DN15: 3014394.7 | DO15: -9999 | DP15: -9999 | DQ15: -9999 | DR15: -9999 | DS15: -9999 | DU15: 498068 | DV15: 609062 | DW15: 778428 | DX15: 778428 | DY15: -9999 | DZ15: -9999 | EA15: -9999 | EB15: -9999 | EC15: -9999
A16: Iowa | B16: IA | C16: 19 | D16: 1.5336949e+08 | E16: 1.4851931e+08 | G16: 149308.01 | H16: 3510871.3 | I16: 3510871.3 | J16: 4265943.2 | L16: 82708.048 | M16: 1944820.7 | N16: 1944820.7 | O16: 2363087.1 | P16: =((G16*10+(H16-G16)*50+(I16-H16)*100)/I16) -> 48.298906 | Q16: =I16/N16 -> 1.8052417 | R16: =N16 -> 1944820.7 | T16: 82450.92 | U16: 85886.375 | V16: 85886.375 | W16: 85886.375 | Y16: 13813.021 | Z16: 14388.564 | AA16: 14388.564 | AB16: 14388.564 | AC16: =((T16*10+(U16-T16)*50+(V16-U16)*100)/V16) -> 11.6 | AD16: =V16/AA16 -> 5.9690721 | AE16: =AA16 -> 14388.564 | AF16: -9999 | AG16: -9999 | AH16: -9999 | AI16: -9999 | AJ16: -9999 | AK16: -9999 | AL16: -9999 | AM16: -9999 | AN16: -9999 | AO16: -9999 | AP16: =(IF(AK16=-9999,0,(AG16*10+(AH16-AG16)*50+(AI16-AH16)*100)/AI16)) -> 0 | AQ16: =IF(AK16=-9999,0,AI16/AN16) -> 0 | AR16: =IF(AK16=-9999,0,AN16) -> 0 | AS16: -9999 | AT16: -9999 | AU16: -9999 | AV16: -9999 | AW16: -9999 | AX16: -9999 | AY16: -9999 | AZ16: -9999 | BA16: -9999 | BB16: -9999 | BC16: =(IF(AY16=-9999,0,(AT16*10+(AU16-AT16)*50+(AV16-AU16)*100)/AV16)) -> 0 | BD16: =IF(AY16=-9999,0,AV16/BA16) -> 0 | BE16: =IF(AY16=-9999,0,BA16) -> 0 | BF16: 0 | BG16: 0 | BH16: 0 | BI16: 0 | BJ16: 135729.48 | BK16: 0 | BL16: 0 | BM16: 0 | BN16: 0 | BO16: 54213.685 | BQ16: 7745113.8 | BR16: 7745113.8 | BS16: 7992893.5 | BT16: 7992893.5 | BV16: 16310946 | BW16: 16310946 | BX16: 16832761 | BY16: 16832761 | CA16: 316187.13 | CB16: 5058994.1 | CC16: 6323742.6 | CD16: 6323742.6 | CF16: 146952.68 | CG16: 2351242.8 | CH16: 2939053.6 | CI16: 2939053.6 | CK16: 0 | CL16: 1621221.8 | CM16: 5668901.2 | CN16: 5668901.2 | CP16: 0 | CQ16: 86395.639 | CR16: 87376.806 | CS16: 87376.806 | CT16: =(IF(CP16=-9999,0,(CK16*10+(CL16-CK16)*50+(CM16-CL16)*100)/CM16)) -> 85.70074 | CU16: =IF(CP16=-9999,0,CM16/CR16) -> 64.878788 | CV16: =IF(CP16=-9999,0,CR16) -> 87376.806 | CX16: 8271.2555 | CY16: 395954.64 | CZ16: 500537.82 | DA16: 507438.99 | DC16: 5553.6469 | DD16: 210310.43 | DE16: 262243.86 | DF16: 265859.55 | DG16: =(IF(DC16=-9999,0,(CX16*10+(CY16-CX16)*50+(CZ16-CY16)*100)/CZ16)) -> 59.786091 | DH16: =IF(DC16=-9999,0,CZ16/DE16) -> 1.9086732 | DI16: =IF(DC16=-9999,0,DE16) -> 262243.86 | DK16: 3070372 | DL16: 3460929.7 | DM16: 5452045 | DN16: 6352265.1 | DO16: -9999 | DP16: -9999 | DQ16: -9999 | DR16: -9999 | DS16: -9999 | DU16: 2623710 | DV16: 3015268 | DW16: 3793206 | DX16: 3793206 | DY16: -9999 | DZ16: -9999 | EA16: -9999 | EB16: -9999 | EC16: -9999
A17: Kansas | B17: KS | C17: 20 | D17: 1.1038081e+08 | E17: 97814382 | G17: 150433.91 | H17: 3537345.9 | I17: 3537345.9 | J17: 4298111.7 | L17: 67623.83 | M17: 1590126.1 | N17: 1590126.1 | O17: 1932109.4 | P17: =((G17*10+(H17-G17)*50+(I17-H17)*100)/I17) -> 48.298906 | Q17: =I17/N17 -> 2.2245695 | R17: =N17 -> 1590126.1 | T17: 74597.681 | U17: 77705.918 | V17: 77705.918 | W17: 77705.918 | Y17: 14610.808 | Z17: 15219.592 | AA17: 15219.592 | AB17: 15219.592 | AC17: =((T17*10+(U17-T17)*50+(V17-U17)*100)/V17) -> 11.6 | AD17: =V17/AA17 -> 5.1056507 | AE17: =AA17 -> 15219.592 | AF17: -9999 | AG17: -9999 | AH17: -9999 | AI17: -9999 | AJ17: -9999 | AK17: -9999 | AL17: -9999 | AM17: -9999 | AN17: -9999 | AO17: -9999 | AP17: =(IF(AK17=-9999,0,(AG17*10+(AH17-AG17)*50+(AI17-AH17)*100)/AI17)) -> 0 | AQ17: =IF(AK17=-9999,0,AI17/AN17) -> 0 | AR17: =IF(AK17=-9999,0,AN17) -> 0 | AS17: -9999 | AT17: -9999 | AU17: -9999 | AV17: -9999 | AW17: -9999 | AX17: -9999 | AY17: -9999 | AZ17: -9999 | BA17: -9999 | BB17: -9999 | BC17: =(IF(AY17=-9999,0,(AT17*10+(AU17-AT17)*50+(AV17-AU17)*100)/AV17)) -> 0 | BD17: =IF(AY17=-9999,0,AV17/BA17) -> 0 | BE17: =IF(AY17=-9999,0,BA17) -> 0 | BF17: 0 | BG17: 0 | BH17: 0 | BI17: 0 | BJ17: 106731.72 | BK17: 0 | BL17: 0 | BM17: 0 | BN17: 0 | BO17: 36153.728 | BQ17: 7442761.8 | BR17: 7442761.8 | BS17: 7680868.7 | BT17: 7680868.7 | BV17: 15674203 | BW17: 15674203 | BX17: 16175648 | BY17: 16175648 | CA17: 303843.89 | CB17: 4861502.2 | CC17: 6076877.8 | CD17: 6076877.8 | CF17: 141215.97 | CG17: 2259455.6 | CH17: 2824319.4 | CI17: 2824319.4 | CK17: 10333.984 | CL17: 7720081.8 | CM17: 7029505.5 | CN17: 7029505.5 | CP17: 24.842994 | CQ17: 141601.21 | CR17: 141601.21 | CS17: 141601.21 | CT17: =(IF(CP17=-9999,0,(CK17*10+(CL17-CK17)*50+(CM17-CL17)*100)/CM17)) -> 45.029214 | CU17: =IF(CP17=-9999,0,CM17/CR17) -> 49.642975 | CV17: =IF(CP17=-9999,0,CR17) -> 141601.21 | CX17: 9440.6364 | CY17: 451934.27 | CZ17: 571303.3 | DA17: 579180.15 | DC17: 9000.136 | DD17: 340825.14 | DE17: 424987.48 | DF17: 430847 | DG17: =(IF(DC17=-9999,0,(CX17*10+(CY17-CX17)*50+(CZ17-CY17)*100)/CZ17)) -> 59.786091 | DH17: =IF(DC17=-9999,0,CZ17/DE17) -> 1.3442826 | DI17: =IF(DC17=-9999,0,DE17) -> 424987.48 | DK17: 1956947.3 | DL17: 2207197.2 | DM17: 3065407.2 | DN17: 3648124.4 | DO17: -9999 | DP17: -9999 | DQ17: -9999 | DR17: -9999 | DS17: -9999 | DU17: 287327 | DV17: 334152 | DW17: 357242 | DX17: 357242 | DY17: -9999 | DZ17: -9999 | EA17: -9999 | EB17: -9999 | EC17: -9999
A18: Kentucky | B18: KY | C18: 21 | D18: 1.6408595e+08 | E18: 1.4131988e+08 | G18: 427292.23 | H18: 10047472 | I18: 10047472 | J18: 12208349 | L18: 131750.1 | M18: 3098009.4 | N18: 3098009.4 | O18: 3764288.5 | P18: =((G18*10+(H18-G18)*50+(I18-H18)*100)/I18) -> 48.298906 | Q18: =I18/N18 -> 3.2432024 | R18: =N18 -> 3098009.4 | T18: 1189556.1 | U18: 1239120.9 | V18: 1239120.9 | W18: 1239120.9 | Y18: 141117.59 | Z18: 146997.49 | AA18: 146997.49 | AB18: 146997.49 | AC18: =((T18*10+(U18-T18)*50+(V18-U18)*100)/V18) -> 11.6 | AD18: =V18/AA18 -> 8.4295375 | AE18: =AA18 -> 146997.49 | AF18: -9999 | AG18: -9999 | AH18: -9999 | AI18: -9999 | AJ18: -9999 | AK18: -9999 | AL18: -9999 | AM18: -9999 | AN18: -9999 | AO18: -9999 | AP18: =(IF(AK18=-9999,0,(AG18*10+(AH18-AG18)*50+(AI18-AH18)*100)/AI18)) -> 0 | AQ18: =IF(AK18=-9999,0,AI18/AN18) -> 0 | AR18: =IF(AK18=-9999,0,AN18) -> 0 | AS18: -9999 | AT18: -9999 | AU18: -9999 | AV18: -9999 | AW18: -9999 | AX18: -9999 | AY18: -9999 | AZ18: -9999 | BA18: -9999 | BB18: -9999 | BC18: =(IF(AY18=-9999,0,(AT18*10+(AU18-AT18)*50+(AV18-AU18)*100)/AV18)) -> 0 | BD18: =IF(AY18=-9999,0,AV18/BA18) -> 0 | BE18: =IF(AY18=-9999,0,BA18) -> 0 | BF18: 0 | BG18: 0 | BH18: 0 | BI18: 0 | BJ18: 267515.25 | BK18: 0 | BL18: 0 | BM18: 0 | BN18: 0 | BO18: 89666.146 | BQ18: 1930360.8 | BR18: 1930360.8 | BS18: 1992116.4 | BT18: 1992116.4 | BV18: 4065274.1 | BW18: 4065274.1 | BX18: 4195329.3 | BY18: 4195329.3 | CA18: 78805.201 | CB18: 1260883.2 | CC18: 1576104 | CD18: 1576104 | CF18: 36625.891 | CG18: 586014.25 | CH18: 732517.81 | CI18: 732517.81 | CK18: 1529.8261 | CL18: 1318533 | CM18: 1901294.9 | CN18: 1901294.9 | CP18: 0 | CQ18: 28630.028 | CR18: 32602.797 | CS18: 32602.797 | CT18: =(IF(CP18=-9999,0,(CK18*10+(CL18-CK18)*50+(CM18-CL18)*100)/CM18)) -> 65.29321 | CU18: =IF(CP18=-9999,0,CM18/CR18) -> 58.316926 | CV18: =IF(CP18=-9999,0,CR18) -> 32602.797 | CX18: 2804.5637 | CY18: 134257.73 | CZ18: 169719.12 | DA18: 172059.12 | DC18: 2072.2252 | DD18: 78472.864 | DE18: 97850.72 | DF18: 99199.838 | DG18: =(IF(DC18=-9999,0,(CX18*10+(CY18-CX18)*50+(CZ18-CY18)*100)/CZ18)) -> 59.786091 | DH18: =IF(DC18=-9999,0,CZ18/DE18) -> 1.7344698 | DI18: =IF(DC18=-9999,0,DE18) -> 97850.72 | DK18: 578018.31 | DL18: 652129.09 | DM18: 844981.54 | DN18: 1018417.8 | DO18: -9999 | DP18: -9999 | DQ18: -9999 | DR18: -9999 | DS18: -9999 | DU18: 25863 | DV18: 78429 | DW18: 86640 | DX18: 86640 | DY18: -9999 | DZ18: -9999 | EA18: -9999 | EB18: -9999 | EC18: -9999
A19: Louisiana | B19: LA | C19: 22 | D19: 2.3358975e+08 | E19: 2.0929551e+08 | G19: 281322.81 | H19: 6615105 | I19: 6615105 | J19: 8037794.7 | L19: 93790.944 | M19: 2205427 | N19: 2205427 | O19: 2679741.2 | P19: =((G19*10+(H19-G19)*50+(I19-H19)*100)/I19) -> 48.298906 | Q19: =I19/N19 -> 2.9994667 | R19: =N19 -> 2205427 | T19: 1014135.5 | U19: 1056391.1 | V19: 1056391.1 | W19: 1056391.1 | Y19: 205378.97 | Z19: 213936.42 | AA19: 213936.42 | AB19: 213936.42 | AC19: =((T19*10+(U19-T19)*50+(V19-U19)*100)/V19) -> 11.6 | AD19: =V19/AA19 -> 4.9378741 | AE19: =AA19 -> 213936.42 | AF19: 0 | AG19: 197598.32 | AH19: 411981.06 | AI19: 503532.41 | AJ19: 564566.64 | AK19: 0 | AL19: 419000 | AM19: 419000 | AN19: 419000 | AO19: 419000 | AP19: =(IF(AK19=-9999,0,(AG19*10+(AH19-AG19)*50+(AI19-AH19)*100)/AI19)) -> 43.393939 | AQ19: =IF(AK19=-9999,0,AI19/AN19) -> 1.201748 | AR19: =IF(AK19=-9999,0,AN19) -> 419000 | AS19: -9999 | AT19: -9999 | AU19: -9999 | AV19: -9999 | AW19: -9999 | AX19: -9999 | AY19: -9999 | AZ19: -9999 | BA19: -9999 | BB19: -9999 | BC19: =(IF(AY19=-9999,0,(AT19*10+(AU19-AT19)*50+(AV19-AU19)*100)/AV19)) -> 0 | BD19: =IF(AY19=-9999,0,AV19/BA19) -> 0 | BE19: =IF(AY19=-9999,0,BA19) -> 0 | BF19: 0 | BG19: 0 | BH19: 0 | BI19: 0 | BJ19: 524443.27 | BK19: 0 | BL19: 0 | BM19: 0 | BN19: 0 | BO19: 126635.07 | BQ19: 1045923.3 | BR19: 1045923.3 | BS19: 1079384.2 | BT19: 1079384.2 | BV19: 2202678.9 | BW19: 2202678.9 | BX19: 2273146.4 | BY19: 2273146.4 | CA19: 42698.856 | CB19: 683181.69 | CC19: 853977.12 | CD19: 853977.12 | CF19: 19844.929 | CG19: 317518.86 | CH19: 396898.58 | CI19: 396898.58 | CK19: 391113.6 | CL19: 1002795.5 | CM19: 908998.62 | CN19: 908998.62 | CP19: 5836.5154 | CQ19: 11878.722 | CR19: 11878.722 | CS19: 11878.722 | CT19: =(IF(CP19=-9999,0,(CK19*10+(CL19-CK19)*50+(CM19-CL19)*100)/CM19)) -> 27.629903 | CU19: =IF(CP19=-9999,0,CM19/CR19) -> 76.52327 | CV19: =IF(CP19=-9999,0,CR19) -> 11878.722 | CX19: 1534.3998 | CY19: 73453.509 | CZ19: 92854.724 | DA19: 94134.96 | DC19: 755.00844 | DD19: 28591.33 | DE19: 35651.587 | DF19: 36143.134 | DG19: =(IF(DC19=-9999,0,(CX19*10+(CY19-CX19)*50+(CZ19-CY19)*100)/CZ19)) -> 59.786091 | DH19: =IF(DC19=-9999,0,CZ19/DE19) -> 2.6045046 | DI19: =IF(DC19=-9999,0,DE19) -> 35651.587 | DK19: 467514.54 | DL19: 527774.27 | DM19: 585185.26 | DN19: 727611.44 | DO19: -9999 | DP19: -9999 | DQ19: -9999 | DR19: -9999 | DS19: -9999 | DU19: 650 | DV19: 1836 | DW19: 2610 | DX19: 2610 | DY19: -9999 | DZ19: -9999 | EA19: -9999 | EB19: -9999 | EC19: -9999
A20: Maine | B20: ME | C20: 23 | D20: 19282638 | E20: 1877831.1 | G20: 112202.73 | H20: 2638367.1 | I20: 2638367.1 | J20: 3205792.3 | L20: 45637.505 | M20: 1073133.3 | N20: 1073133.3 | O20: 1303928.7 | P20: =((G20*10+(H20-G20)*50+(I20-H20)*100)/I20) -> 48.298906 | Q20: =I20/N20 -> 2.4585641 | R20: =N20 -> 1073133.3 | T20: 491795.19 | U20: 512286.66 | V20: 512286.66 | W20: 512286.66 | Y20: 77986.86 | Z20: 81236.312 | AA20: 81236.312 | AB20: 81236.312 | AC20: =((T20*10+(U20-T20)*50+(V20-U20)*100)/V20) -> 11.6 | AD20: =V20/AA20 -> 6.3061289 | AE20: =AA20 -> 81236.312 | AF20: -9999 | AG20: -9999 | AH20: -9999 | AI20: -9999 | AJ20: -9999 | AK20: -9999 | AL20: -9999 | AM20: -9999 | AN20: -9999 | AO20: -9999 | AP20: =(IF(AK20=-9999,0,(AG20*10+(AH20-AG20)*50+(AI20-AH20)*100)/AI20)) -> 0 | AQ20: =IF(AK20=-9999,0,AI20/AN20) -> 0 | AR20: =IF(AK20=-9999,0,AN20) -> 0 | AS20: -9999 | AT20: -9999 | AU20: -9999 | AV20: -9999 | AW20: -9999 | AX20: -9999 | AY20: -9999 | AZ20: -9999 | BA20: -9999 | BB20: -9999 | BC20: =(IF(AY20=-9999,0,(AT20*10+(AU20-AT20)*50+(AV20-AU20)*100)/AV20)) -> 0 | BD20: =IF(AY20=-9999,0,AV20/BA20) -> 0 | BE20: =IF(AY20=-9999,0,BA20) -> 0 | BF20: 0 | BG20: 0 | BH20: 0 | BI20: 0 | BJ20: 59187.66 | BK20: 0 | BL20: 0 | BM20: 0 | BN20: 0 | BO20: 25673.489 | BQ20: 77323.843 | BR20: 77323.843 | BS20: 79797.568 | BT20: 79797.568 | BV20: 162841.38 | BW20: 162841.38 | BX20: 168050.96 | BY20: 168050.96 | CA20: 3156.6746 | CB20: 50506.794 | CC20: 63133.492 | CD20: 63133.492 | CF20: 1467.1115 | CG20: 23473.785 | CH20: 29342.231 | CI20: 29342.231 | CK20: 34926.264 | CL20: 82996.227 | CM20: 75233.142 | CN20: 75233.142 | CP20: 269.67327 | CQ20: 754.17688 | CR20: 754.17688 | CS20: 754.17688 | CT20: =(IF(CP20=-9999,0,(CK20*10+(CL20-CK20)*50+(CM20-CL20)*100)/CM20)) -> 26.271033 | CU20: =IF(CP20=-9999,0,CM20/CR20) -> 99.755302 | CV20: =IF(CP20=-9999,0,CR20) -> 754.17688 | CX20: 88.971992 | CY20: 4259.193 | CZ20: 5384.1701 | DA20: 5458.4044 | DC20: 47.935285 | DD20: 1815.2559 | DE20: 2263.5098 | DF20: 2294.718 | DG20: =(IF(DC20=-9999,0,(CX20*10+(CY20-CX20)*50+(CZ20-CY20)*100)/CZ20)) -> 59.786091 | DH20: =IF(DC20=-9999,0,CZ20/DE20) -> 2.3786821 | DI20: =IF(DC20=-9999,0,DE20) -> 2263.5098 | DK20: 21679.858 | DL20: 24477.966 | DM20: 25987.815 | DN20: 32617.586 | DO20: -9999 | DP20: -9999 | DQ20: -9999 | DR20: -9999 | DS20: -9999 | DU20: 0 | DV20: 2157 | DW20: 2157 | DX20: 2157 | DY20: -9999 | DZ20: -9999 | EA20: -9999 | EB20: -9999 | EC20: -9999
A21: Maryland | B21: MD | C21: 24 | D21: 74057508 | E21: 67809371 | F21: 0 | G21: 114628.53 | H21: 2695407.9 | I21: 2695407.9 | J21: 3275100.7 | K21: 0 | L21: 24920.521 | M21: 585988.26 | N21: 585988.26 | O21: 712014.9 | P21: =((G21*10+(H21-G21)*50+(I21-H21)*100)/I21) -> 48.298906 | Q21: =I21/N21 -> 4.5997643 | R21: =N21 -> 585988.26 | S21: 0 | T21: 355075.48 | U21: 369870.3 | V21: 369870.3 | W21: 369870.3 | X21: 0 | Y21: 39472.706 | Z21: 41117.403 | AA21: 41117.403 | AB21: 41117.403 | AC21: =((T21*10+(U21-T21)*50+(V21-U21)*100)/V21) -> 11.6 | AD21: =V21/AA21 -> 8.9954684 | AE21: =AA21 -> 41117.403 | AF21: -9999 | AG21: -9999 | AH21: -9999 | AI21: -9999 | AJ21: -9999 | AK21: -9999 | AL21: -9999 | AM21: -9999 | AN21: -9999 | AO21: -9999 | AP21: =(IF(AK21=-9999,0,(AG21*10+(AH21-AG21)*50+(AI21-AH21)*100)/AI21)) -> 0 | AQ21: =IF(AK21=-9999,0,AI21/AN21) -> 0 | AR21: =IF(AK21=-9999,0,AN21) -> 0 | AS21: -9999 | AT21: -9999 | AU21: -9999 | AV21: -9999 | AW21: -9999 | AX21: -9999 | AY21: -9999 | AZ21: -9999 | BA21: -9999 | BB21: -9999 | BC21: =(IF(AY21=-9999,0,(AT21*10+(AU21-AT21)*50+(AV21-AU21)*100)/AV21)) -> 0 | BD21: =IF(AY21=-9999,0,AV21/BA21) -> 0 | BE21: =IF(AY21=-9999,0,BA21) -> 0 | BF21: 0 | BG21: 0 | BH21: 0 | BI21: 0 | BJ21: 348385.72 | BK21: 0 | BL21: 0 | BM21: 0 | BN21: 0 | BO21: 103396.02 | BQ21: 508654.12 | BR21: 508654.12 | BS21: 524926.86 | BT21: 524926.86 | BV21: 1071208.2 | BW21: 1071208.2 | BX21: 1105478.1 | BY21: 1105478.1 | CA21: 20765.336 | CB21: 332245.37 | CC21: 415306.72 | CD21: 415306.72 | CF21: 9650.999 | CG21: 154415.98 | CH21: 193019.98 | CI21: 193019.98 | CJ21: 0 | CK21: 11292.713 | CL21: 145539.09 | CM21: 132061.74 | CN21: 132061.74 | CO21: 0 | CP21: 0 | CQ21: 1924.4535 | CR21: 2038.7766 | CS21: 2038.7766 | CT21: =(IF(CP21=-9999,0,(CK21*10+(CL21-CK21)*50+(CM21-CL21)*100)/CM21)) -> 41.476898 | CU21: =IF(CP21=-9999,0,CM21/CR21) -> 64.774993 | CV21: =IF(CP21=-9999,0,CR21) -> 2038.7766 | CX21: 190.35834 | CY21: 9112.6754 | CZ21: 11519.599 | DA21: 11678.425 | DC21: 129.58411 | DD21: 4907.206 | DE21: 6118.9769 | DF21: 6203.3423 | DG21: =(IF(DC21=-9999,0,(CX21*10+(CY21-CX21)*50+(CZ21-CY21)*100)/CZ21)) -> 59.786091 | DH21: =IF(DC21=-9999,0,CZ21/DE21) -> 1.8826021 | DI21: =IF(DC21=-9999,0,DE21) -> 6118.9769 | DJ21: 84982.199 | DK21: 87910.233 | DL21: 99246.478 | DM21: 108438.17 | DN21: 135254.55 | DO21: -9999 | DP21: -9999 | DQ21: -9999 | DR21: -9999 | DS21: -9999 | DT21: 0 | DU21: 1000 | DV21: 3816 | DW21: 5130 | DX21: 5130 | DY21: -9999 | DZ21: -9999 | EA21: -9999 | EB21: -9999 | EC21: -9999
A22: Massachusetts | B22: MA | C22: 25 | D22: 73769871 | E22: 66922848 | F22: 0 | G22: 28980.062 | H22: 681445.46 | I22: 681445.46 | J22: 828001.77 | K22: 0 | L22: 6863.6452 | M22: 161393.71 | N22: 161393.71 | O22: 196104.15 | P22: =((G22*10+(H22-G22)*50+(I22-H22)*100)/I22) -> 48.298906 | Q22: =I22/N22 -> 4.2222553 | R22: =N22 -> 161393.71 | S22: 0 | T22: 350225.29 | U22: 364818.01 | V22: 364818.01 | W22: 364818.01 | X22: 0 | Y22: 40256.46 | Z22: 41933.813 | AA22: 41933.813 | AB22: 41933.813 | AC22: =((T22*10+(U22-T22)*50+(V22-U22)*100)/V22) -> 11.6 | AD22: =V22/AA22 -> 8.699853 | AE22: =AA22 -> 41933.813 | AF22: -9999 | AG22: -9999 | AH22: -9999 | AI22: -9999 | AJ22: -9999 | AK22: -9999 | AL22: -9999 | AM22: -9999 | AN22: -9999 | AO22: -9999 | AP22: =(IF(AK22=-9999,0,(AG22*10+(AH22-AG22)*50+(AI22-AH22)*100)/AI22)) -> 0 | AQ22: =IF(AK22=-9999,0,AI22/AN22) -> 0 | AR22: =IF(AK22=-9999,0,AN22) -> 0 | AS22: -9999 | AT22: -9999 | AU22: -9999 | AV22: -9999 | AW22: -9999 | AX22: -9999 | AY22: -9999 | AZ22: -9999 | BA22: -9999 | BB22: -9999 | BC22: =(IF(AY22=-9999,0,(AT22*10+(AU22-AT22)*50+(AV22-AU22)*100)/AV22)) -> 0 | BD22: =IF(AY22=-9999,0,AV22/BA22) -> 0 | BE22: =IF(AY22=-9999,0,BA22) -> 0 | BF22: 0 | BG22: 0 | BH22: 0 | BI22: 0 | BJ22: 592627.83 | BK22: 0 | BL22: 0 | BM22: 0 | BN22: 0 | BO22: 223663.09 | BQ22: 34822.03 | BR22: 34822.03 | BS22: 35936.048 | BT22: 35936.048 | BV22: 73334.008 | BW22: 73334.008 | BX22: 75680.091 | BY22: 75680.091 | CA22: 1421.5773 | CB22: 22745.236 | CC22: 28431.546 | CD22: 28431.546 | CF22: 660.69921 | CG22: 10571.187 | CH22: 13213.984 | CI22: 13213.984 | CJ22: 0 | CK22: 4262.2151 | CL22: 13205.896 | CM22: 11970.678 | CN22: 11970.678 | CO22: 0 | CP22: 0 | CQ22: 129.60296 | CR22: 129.60296 | CS22: 129.60296 | CT22: =(IF(CP22=-9999,0,(CK22*10+(CL22-CK22)*50+(CM22-CL22)*100)/CM22)) -> 30.598464 | CU22: =IF(CP22=-9999,0,CM22/CR22) -> 92.364229 | CV22: =IF(CP22=-9999,0,CR22) -> 129.60296 | CX22: 14.248792 | CY22: 682.10628 | CZ22: 862.27046 | DA22: 874.15902 | DC22: 8.2375303 | DD22: 311.94611 | DE22: 388.97715 | DF22: 394.34018 | DG22: =(IF(DC22=-9999,0,(CX22*10+(CY22-CX22)*50+(CZ22-CY22)*100)/CZ22)) -> 59.786091 | DH22: =IF(DC22=-9999,0,CZ22/DE22) -> 2.2167638 | DI22: =IF(DC22=-9999,0,DE22) -> 388.97715 | DJ22: 18378.286 | DK22: 19012.775 | DL22: 21466.206 | DM22: 22930.261 | DN22: 28741.381 | DO22: -9999 | DP22: -9999 | DQ22: -9999 | DR22: -9999 | DS22: -9999 | DT22: -9999 | DU22: 0 | DV22: 0 | DW22: 0 | DX22: 0 | DY22: -9999 | DZ22: -9999 | EA22: -9999 | EB22: -9999 | EC22: -9999
A23: Michigan | B23: MI | C23: 26 | D23: 1.9657353e+08 | E23: 1.3514183e+08 | G23: 376190.38 | H23: 8845848 | I23: 8845848 | J23: 10748296 | L23: 147068.52 | M23: 3458211.2 | N23: 3458211.2 | O23: 4201957.7 | P23: =((G23*10+(H23-G23)*50+(I23-H23)*100)/I23) -> 48.298906 | Q23: =I23/N23 -> 2.5579259 | R23: =N23 -> 3458211.2 | T23: 670937.87 | U23: 698893.62 | V23: 698893.62 | W23: 698893.62 | Y23: 114891.25 | Z23: 119678.39 | AA23: 119678.39 | AB23: 119678.39 | AC23: =((T23*10+(U23-T23)*50+(V23-U23)*100)/V23) -> 11.6 | AD23: =V23/AA23 -> 5.8397647 | AE23: =AA23 -> 119678.39 | AF23: -9999 | AG23: -9999 | AH23: -9999 | AI23: -9999 | AJ23: -9999 | AK23: -9999 | AL23: -9999 | AM23: -9999 | AN23: -9999 | AO23: -9999 | AP23: =(IF(AK23=-9999,0,(AG23*10+(AH23-AG23)*50+(AI23-AH23)*100)/AI23)) -> 0 | AQ23: =IF(AK23=-9999,0,AI23/AN23) -> 0 | AR23: =IF(AK23=-9999,0,AN23) -> 0 | AS23: -9999 | AT23: -9999 | AU23: -9999 | AV23: -9999 | AW23: -9999 | AX23: -9999 | AY23: -9999 | AZ23: -9999 | BA23: -9999 | BB23: -9999 | BC23: =(IF(AY23=-9999,0,(AT23*10+(AU23-AT23)*50+(AV23-AU23)*100)/AV23)) -> 0 | BD23: =IF(AY23=-9999,0,AV23/BA23) -> 0 | BE23: =IF(AY23=-9999,0,BA23) -> 0 | BF23: 0 | BG23: 0 | BH23: 0 | BI23: 0 | BJ23: 626681.68 | BK23: 0 | BL23: 0 | BM23: 0 | BN23: 0 | BO23: 273067.68 | BQ23: 2021676.6 | BR23: 2021676.6 | BS23: 2086353.6 | BT23: 2086353.6 | BV23: 4257582 | BW23: 4257582 | BX23: 4393789.5 | BY23: 4393789.5 | CA23: 82533.083 | CB23: 1320529.3 | CC23: 1650661.7 | CD23: 1650661.7 | CF23: 38358.479 | CG23: 613735.67 | CH23: 767169.59 | CI23: 767169.59 | CK23: 733979.37 | CL23: 2555603.7 | CM23: 2316988.4 | CN23: 2316988.4 | CP23: 8053.1618 | CQ23: 18463.095 | CR23: 18463.095 | CS23: 18463.095 | CT23: =(IF(CP23=-9999,0,(CK23*10+(CL23-CK23)*50+(CM23-CL23)*100)/CM23)) -> 32.17948 | CU23: =IF(CP23=-9999,0,CM23/CR23) -> 125.49296 | CV23: =IF(CP23=-9999,0,CR23) -> 18463.095 | CX23: 2921.2524 | CY23: 139843.76 | CZ23: 176780.57 | DA23: 179217.94 | DC23: 1173.5095 | DD23: 44439.497 | DE23: 55413.255 | DF23: 56177.266 | DG23: =(IF(DC23=-9999,0,(CX23*10+(CY23-CX23)*50+(CZ23-CY23)*100)/CZ23)) -> 59.786091 | DH23: =IF(DC23=-9999,0,CZ23/DE23) -> 3.1902218 | DI23: =IF(DC23=-9999,0,DE23) -> 55413.255 | DK23: 502467.46 | DL23: 567128.8 | DM23: 661023.55 | DN23: 813396.84 | DO23: -9999 | DP23: -9999 | DQ23: -9999 | DR23: -9999 | DS23: -9999 | DU23: 114391 | DV23: 190132 | DW23: 206526 | DX23: 206526 | DY23: -9999 | DZ23: -9999 | EA23: -9999 | EB23: -9999 | EC23: -9999
A24: Minnesota | B24: MN | C24: 27 | D24: 1.2934778e+08 | E24: 79665599 | F24: 0 | G24: 204608.05 | H24: 4811212.1 | I24: 4811212.1 | J24: 5845944.2 | K24: 0 | L24: 114861.08 | M24: 2700876.3 | N24: 2700876.3 | O24: 3281745.2 | P24: =((G24*10+(H24-G24)*50+(I24-H24)*100)/I24) -> 48.298906 | Q24: =I24/N24 -> 1.7813523 | R24: =N24 -> 2700876.3 | S24: 0 | T24: 237305.51 | U24: 247193.24 | V24: 247193.24 | W24: 247193.24 | X24: 0 | Y24: 51961.007 | Z24: 54126.049 | AA24: 54126.049 | AB24: 54126.049 | AC24: =((T24*10+(U24-T24)*50+(V24-U24)*100)/V24) -> 11.6 | AD24: =V24/AA24 -> 4.5669921 | AE24: =AA24 -> 54126.049 | AF24: -9999 | AG24: -9999 | AH24: -9999 | AI24: -9999 | AJ24: -9999 | AK24: -9999 | AL24: -9999 | AM24: -9999 | AN24: -9999 | AO24: -9999 | AP24: =(IF(AK24=-9999,0,(AG24*10+(AH24-AG24)*50+(AI24-AH24)*100)/AI24)) -> 0 | AQ24: =IF(AK24=-9999,0,AI24/AN24) -> 0 | AR24: =IF(AK24=-9999,0,AN24) -> 0 | AS24: -9999 | AT24: -9999 | AU24: -9999 | AV24: -9999 | AW24: -9999 | AX24: -9999 | AY24: -9999 | AZ24: -9999 | BA24: -9999 | BB24: -9999 | BC24: =(IF(AY24=-9999,0,(AT24*10+(AU24-AT24)*50+(AV24-AU24)*100)/AV24)) -> 0 | BD24: =IF(AY24=-9999,0,AV24/BA24) -> 0 | BE24: =IF(AY24=-9999,0,BA24) -> 0 | BF24: 0 | BG24: 0 | BH24: 0 | BI24: 0 | BJ24: 293642.02 | BK24: 0 | BL24: 0 | BM24: 0 | BN24: 0 | BO24: 122921.74 | BQ24: 6271752.7 | BR24: 6271752.7 | BS24: 6472397 | BT24: 6472397 | BV24: 13208097 | BW24: 13208097 | BX24: 13630647 | BY24: 13630647 | CA24: 256038.52 | CB24: 4096616.4 | CC24: 5120770.5 | CD24: 5120770.5 | CF24: 118997.72 | CG24: 1903963.5 | CH24: 2379954.3 | CI24: 2379954.3 | CJ24: 0 | CK24: 900660.57 | CL24: 4769681.1 | CM24: 4735746.5 | CN24: 4735746.5 | CO24: 0 | CP24: 11452.108 | CQ24: 55426.285 | CR24: 55426.285 | CS24: 55426.285 | CT24: =(IF(CP24=-9999,0,(CK24*10+(CL24-CK24)*50+(CM24-CL24)*100)/CM24)) -> 42.034382 | CU24: =IF(CP24=-9999,0,CM24/CR24) -> 85.44225 | CV24: =IF(CP24=-9999,0,CR24) -> 55426.285 | CX24: 6928.318 | CY24: 331666.66 | CZ24: 419269.5 | DA24: 425050.18 | DC24: 3522.8802 | DD24: 133407.55 | DE24: 166350.82 | DF24: 168644.38 | DG24: =(IF(DC24=-9999,0,(CX24*10+(CY24-CX24)*50+(CZ24-CY24)*100)/CZ24)) -> 59.786091 | DH24: =IF(DC24=-9999,0,CZ24/DE24) -> 2.5203934 | DI24: =IF(DC24=-9999,0,DE24) -> 166350.82 | DJ24: 1831711.1 | DK24: 1893486.9 | DL24: 2135885.8 | DM24: 2884207.8 | DN24: 3449815.7 | DO24: -9999 | DP24: -9999 | DQ24: -9999 | DR24: -9999 | DS24: -9999 | DT24: 0 | DU24: 641305 | DV24: 764470 | DW24: 879442 | DX24: 879442 | DY24: -9999 | DZ24: -9999 | EA24: -9999 | EB24: -9999 | EC24: -9999
A25: Mississippi | B25: MS | C25: 28 | D25: 78720487 | E25: 25831280 | G25: 460598.63 | H25: 10830648 | I25: 10830648 | J25: 13159961 | L25: 141732.81 | M25: 3332745.7 | N25: 3332745.7 | O25: 4049508.8 | P25: =((G25*10+(H25-G25)*50+(I25-H25)*100)/I25) -> 48.298906 | Q25: =I25/N25 -> 3.2497672 | R25: =N25 -> 3332745.7 | T25: 1573446.2 | U25: 1639006.5 | V25: 1639006.5 | W25: 1639006.5 | Y25: 322850.1 | Z25: 336302.18 | AA25: 336302.18 | AB25: 336302.18 | AC25: =((T25*10+(U25-T25)*50+(V25-U25)*100)/V25) -> 11.6 | AD25: =V25/AA25 -> 4.8736123 | AE25: =AA25 -> 336302.18 | AF25: 0 | AG25: 72311.241 | AH25: 150764.75 | AI25: 184268.03 | AJ25: 206603.54 | AK25: 0 | AL25: 153333.33 | AM25: 153333.33 | AN25: 153333.33 | AO25: 153333.33 | AP25: =(IF(AK25=-9999,0,(AG25*10+(AH25-AG25)*50+(AI25-AH25)*100)/AI25)) -> 43.393939 | AQ25: =IF(AK25=-9999,0,AI25/AN25) -> 1.201748 | AR25: =IF(AK25=-9999,0,AN25) -> 153333.33 | AS25: -9999 | AT25: -9999 | AU25: -9999 | AV25: -9999 | AW25: -9999 | AX25: -9999 | AY25: -9999 | AZ25: -9999 | BA25: -9999 | BB25: -9999 | BC25: =(IF(AY25=-9999,0,(AT25*10+(AU25-AT25)*50+(AV25-AU25)*100)/AV25)) -> 0 | BD25: =IF(AY25=-9999,0,AV25/BA25) -> 0 | BE25: =IF(AY25=-9999,0,BA25) -> 0 | BF25: 0 | BG25: 0 | BH25: 0 | BI25: 0 | BJ25: 247486.25 | BK25: 0 | BL25: 0 | BM25: 0 | BN25: 0 | BO25: 68966.57 | BQ25: 1326603.6 | BR25: 1326603.6 | BS25: 1369044 | BT25: 1369044 | BV25: 2793782 | BW25: 2793782 | BX25: 2883160 | BY25: 2883160 | CA25: 54157.37 | CB25: 866517.92 | CC25: 1083147.4 | CD25: 1083147.4 | CF25: 25170.444 | CG25: 402727.11 | CH25: 503408.88 | CI25: 503408.88 | CK25: 118163.71 | CL25: 723727.64 | CM25: 666727.87 | CN25: 666727.87 | CP25: 2003.6334 | CQ25: 10918.42 | CR25: 10918.42 | CS25: 10918.42 | CT25: =(IF(CP25=-9999,0,(CK25*10+(CL25-CK25)*50+(CM25-CL25)*100)/CM25)) -> 38.636238 | CU25: =IF(CP25=-9999,0,CM25/CR25) -> 61.064502 | CV25: =IF(CP25=-9999,0,CR25) -> 10918.42 | CX25: 1094.7929 | CY25: 52409.012 | CZ25: 66251.762 | DA25: 67165.209 | DC25: 693.97191 | DD25: 26279.944 | DE25: 32769.435 | DF25: 33221.244 | DG25: =(IF(DC25=-9999,0,(CX25*10+(CY25-CX25)*50+(CZ25-CY25)*100)/CZ25)) -> 59.786091 | DH25: =IF(DC25=-9999,0,CZ25/DE25) -> 2.0217548 | DI25: =IF(DC25=-9999,0,DE25) -> 32769.435 | DK25: 298855.35 | DL25: 337424.58 | DM25: 359014.28 | DN25: 450388.3 | DO25: -9999 | DP25: -9999 | DQ25: -9999 | DR25: -9999 | DS25: -9999 | DU25: 37086 | DV25: 107646 | DW25: 112198 | DX25: 112198 | DY25: -9999 | DZ25: -9999 | EA25: -9999 | EB25: -9999 | EC25: -9999
A26: Missouri | B26: MO | C26: 29 | D26: 1.6914889e+08 | E26: 1.4403519e+08 | G26: 389792.33 | H26: 9165688.1 | I26: 9165688.1 | J26: 11136924 | L26: 154399.04 | M26: 3630583.1 | N26: 3630583.1 | O26: 4411401.1 | P26: =((G26*10+(H26-G26)*50+(I26-H26)*100)/I26) -> 48.298906 | Q26: =I26/N26 -> 2.5245774 | R26: =N26 -> 3630583.1 | T26: 919562.26 | U26: 957877.36 | V26: 957877.36 | W26: 957877.36 | Y26: 158088.14 | Z26: 164675.14 | AA26: 164675.14 | AB26: 164675.14 | AC26: =((T26*10+(U26-T26)*50+(V26-U26)*100)/V26) -> 11.6 | AD26: =V26/AA26 -> 5.8167696 | AE26: =AA26 -> 164675.14 | AF26: 0 | AG26: 92275.431 | AH26: 192388.93 | AI26: 235142.02 | AJ26: 263644.09 | AK26: 0 | AL26: 195666.67 | AM26: 195666.67 | AN26: 195666.67 | AO26: 195666.67 | AP26: =(IF(AK26=-9999,0,(AG26*10+(AH26-AG26)*50+(AI26-AH26)*100)/AI26)) -> 43.393939 | AQ26: =IF(AK26=-9999,0,AI26/AN26) -> 1.201748 | AR26: =IF(AK26=-9999,0,AN26) -> 195666.67 | AS26: -9999 | AT26: -9999 | AU26: -9999 | AV26: -9999 | AW26: -9999 | AX26: -9999 | AY26: -9999 | AZ26: -9999 | BA26: -9999 | BB26: -9999 | BC26: =(IF(AY26=-9999,0,(AT26*10+(AU26-AT26)*50+(AV26-AU26)*100)/AV26)) -> 0 | BD26: =IF(AY26=-9999,0,AV26/BA26) -> 0 | BE26: =IF(AY26=-9999,0,BA26) -> 0 | BF26: 0 | BG26: 0 | BH26: 0 | BI26: 0 | BJ26: 482099.16 | BK26: 0 | BL26: 0 | BM26: 0 | BN26: 0 | BO26: 162157.67 | BQ26: 4104791.4 | BR26: 4104791.4 | BS26: 4236110.9 | BT26: 4236110.9 | BV26: 8644550.9 | BW26: 8644550.9 | BX26: 8921105.1 | BY26: 8921105.1 | CA26: 167574.33 | CB26: 2681189.2 | CC26: 3351486.5 | CD26: 3351486.5 | CF26: 77882.664 | CG26: 1246122.6 | CH26: 1557653.3 | CI26: 1557653.3 | CK26: 22302.325 | CL26: 5465712.9 | CM26: 5945018.1 | CN26: 5945018.1 | CP26: 0 | CQ26: 98132.495 | CR26: 98132.495 | CS26: 98132.495 | CT26: =(IF(CP26=-9999,0,(CK26*10+(CL26-CK26)*50+(CM26-CL26)*100)/CM26)) -> 53.881092 | CU26: =IF(CP26=-9999,0,CM26/CR26) -> 60.581544 | CV26: =IF(CP26=-9999,0,CR26) -> 98132.495 | CX26: 8377.9815 | CY26: 401063.74 | CZ26: 506996.38 | DA26: 513986.6 | DC26: 6237.2757 | DD26: 236198.69 | DE26: 294524.89 | DF26: 298585.66 | DG26: =(IF(DC26=-9999,0,(CX26*10+(CY26-CX26)*50+(CZ26-CY26)*100)/CZ26)) -> 59.786091 | DH26: =IF(DC26=-9999,0,CZ26/DE26) -> 1.7214042 | DI26: =IF(DC26=-9999,0,DE26) -> 294524.89 | DK26: 1158570.2 | DL26: 1306644.2 | DM26: 1839990.1 | DN26: 2184425.6 | DO26: -9999 | DP26: -9999 | DQ26: -9999 | DR26: -9999 | DS26: -9999 | DU26: 545850 | DV26: 585413 | DW26: 660404 | DX26: 660404 | DY26: -9999 | DZ26: -9999 | EA26: -9999 | EB26: -9999 | EC26: -9999
A27: Montana | B27: MT | C27: 30 | D27: 46143631 | E27: 2421011.6 | G27: 237557.29 | H27: 5585990 | I27: 5585990 | J27: 6787351.1 | L27: 345337.14 | M27: 8120356.2 | N27: 8120356.2 | O27: 9866775.5 | P27: =((G27*10+(H27-G27)*50+(I27-H27)*100)/I27) -> 48.298906 | Q27: =I27/N27 -> 0.68789962 | R27: =N27 -> 8120356.2 | T27: 504340 | U27: 525354.17 | V27: 525354.17 | W27: 525354.17 | Y27: 179816.88 | Z27: 187309.25 | AA27: 187309.25 | AB27: 187309.25 | AC27: =((T27*10+(U27-T27)*50+(V27-U27)*100)/V27) -> 11.6 | AD27: =V27/AA27 -> 2.8047423 | AE27: =AA27 -> 187309.25 | AF27: -9999 | AG27: -9999 | AH27: -9999 | AI27: -9999 | AJ27: -9999 | AK27: -9999 | AL27: -9999 | AM27: -9999 | AN27: -9999 | AO27: -9999 | AP27: =(IF(AK27=-9999,0,(AG27*10+(AH27-AG27)*50+(AI27-AH27)*100)/AI27)) -> 0 | AQ27: =IF(AK27=-9999,0,AI27/AN27) -> 0 | AR27: =IF(AK27=-9999,0,AN27) -> 0 | AS27: 0 | AT27: 0 | AU27: 42713.736 | AV27: 42713.736 | AW27: 1680835.4 | AX27: -9999 | AY27: 0 | AZ27: 63897.704 | BA27: 63897.704 | BB27: 1948661.3 | BC27: =(IF(AY27=-9999,0,(AT27*10+(AU27-AT27)*50+(AV27-AU27)*100)/AV27)) -> 50 | BD27: =IF(AY27=-9999,0,AV27/BA27) -> 0.66847059 | BE27: =IF(AY27=-9999,0,BA27) -> 63897.704 | BF27: 0 | BG27: 0 | BH27: 0 | BI27: 0 | BJ27: 32569.22 | BK27: 0 | BL27: 0 | BM27: 0 | BN27: 0 | BO27: 16968.19 | BQ27: 2919054 | BR27: 2919054 | BS27: 3012439.6 | BT27: 3012439.6 | BV27: 6147428.2 | BW27: 6147428.2 | BX27: 6344095.1 | BY27: 6344095.1 | CA27: 119167.69 | CB27: 1906683 | CC27: 2383353.8 | CD27: 2383353.8 | CF27: 55384.957 | CG27: 886159.32 | CH27: 1107699.1 | CI27: 1107699.1 | CK27: 2314607 | CL27: 3210942.8 | CM27: 2910606 | CN27: 2910606 | CP27: 12566.134 | CQ27: 46368.026 | CR27: 46368.026 | CS27: 46368.026 | CT27: =(IF(CP27=-9999,0,(CK27*10+(CL27-CK27)*50+(CM27-CL27)*100)/CM27)) -> 13.03137 | CU27: =IF(CP27=-9999,0,CM27/CR27) -> 62.771833 | CV27: =IF(CP27=-9999,0,CR27) -> 46368.026 | CX27: 4286.7127 | CY27: 205209.93 | CZ27: 259411.86 | DA27: 262988.51 | DC27: 2947.1396 | DD27: 111604.9 | DE27: 139164.28 | DF27: 141083.01 | DG27: =(IF(DC27=-9999,0,(CX27*10+(CY27-CX27)*50+(CZ27-CY27)*100)/CZ27)) -> 59.786091 | DH27: =IF(DC27=-9999,0,CZ27/DE27) -> 1.8640693 | DI27: =IF(DC27=-9999,0,DE27) -> 139164.28 | DK27: 494359.97 | DL27: 558100.4 | DM27: 612439.28 | DN27: 763182.5 | DO27: -9999 | DP27: -9999 | DQ27: -9999 | DR27: -9999 | DS27: -9999 | DU27: 8488 | DV27: 20067 | DW27: 29547 | DX27: 29547 | DY27: -9999 | DZ27: -9999 | EA27: -9999 | EB27: -9999 | EC27: -9999
A28: Nebraska | B28: NE | C28: 31 | D28: 88445638 | E28: 78151560 | G28: 98474.867 | H28: 2315566.1 | I28: 2315566.1 | J28: 2813567.6 | L28: 77221.745 | M28: 1815814.2 | N28: 1815814.2 | O28: 2206335.6 | P28: =((G28*10+(H28-G28)*50+(I28-H28)*100)/I28) -> 48.298906 | Q28: =I28/N28 -> 1.275222 | R28: =N28 -> 1815814.2 | T28: 28511.675 | U28: 29699.661 | V28: 29699.661 | W28: 29699.661 | Y28: 7100.527 | Z28: 7396.3823 | AA28: 7396.3823 | AB28: 7396.3823 | AC28: =((T28*10+(U28-T28)*50+(V28-U28)*100)/V28) -> 11.6 | AD28: =V28/AA28 -> 4.0154308 | AE28: =AA28 -> 7396.3823 | AF28: -9999 | AG28: -9999 | AH28: -9999 | AI28: -9999 | AJ28: -9999 | AK28: -9999 | AL28: -9999 | AM28: -9999 | AN28: -9999 | AO28: -9999 | AP28: =(IF(AK28=-9999,0,(AG28*10+(AH28-AG28)*50+(AI28-AH28)*100)/AI28)) -> 0 | AQ28: =IF(AK28=-9999,0,AI28/AN28) -> 0 | AR28: =IF(AK28=-9999,0,AN28) -> 0 | AS28: 0 | AT28: 0 | AU28: 96205.344 | AV28: 96205.344 | AW28: 96205.344 | AX28: -9999 | AY28: 0 | AZ28: 143918.59 | BA28: 143918.59 | BB28: 143918.59 | BC28: =(IF(AY28=-9999,0,(AT28*10+(AU28-AT28)*50+(AV28-AU28)*100)/AV28)) -> 50 | BD28: =IF(AY28=-9999,0,AV28/BA28) -> 0.66847059 | BE28: =IF(AY28=-9999,0,BA28) -> 143918.59 | BF28: 0 | BG28: 0 | BH28: 0 | BI28: 0 | BJ28: 71144.052 | BK28: 0 | BL28: 0 | BM28: 0 | BN28: 0 | BO28: 28655.476 | BQ28: 6194534.1 | BR28: 6194534.1 | BS28: 6392708 | BT28: 6392708 | BV28: 13045478 | BW28: 13045478 | BX28: 13462825 | BY28: 13462825 | CA28: 252886.14 | CB28: 4046178.3 | CC28: 5057722.9 | CD28: 5057722.9 | CF28: 117532.6 | CG28: 1880521.6 | CH28: 2350652 | CI28: 2350652 | CK28: 101002.84 | CL28: 3600340.7 | CM28: 4857297.6 | CN28: 4857297.6 | CP28: 742.06762 | CQ28: 77625.394 | CR28: 77625.394 | CS28: 77625.394 | CT28: =(IF(CP28=-9999,0,(CK28*10+(CL28-CK28)*50+(CM28-CL28)*100)/CM28)) -> 62.107089 | CU28: =IF(CP28=-9999,0,CM28/CR28) -> 62.573565 | CV28: =IF(CP28=-9999,0,CR28) -> 77625.394 | CX28: 6245.7958 | CY28: 298993.53 | CZ28: 377966.44 | DA28: 383177.66 | DC28: 4933.8497 | DD28: 186839.4 | DE28: 232976.96 | DF28: 236189.14 | DG28: =(IF(DC28=-9999,0,(CX28*10+(CY28-CX28)*50+(CZ28-CY28)*100)/CZ28)) -> 59.786091 | DH28: =IF(DC28=-9999,0,CZ28/DE28) -> 1.622334 | DI28: =IF(DC28=-9999,0,DE28) -> 232976.96 | DK28: 2505559.9 | DL28: 2826786.6 | DM28: 3670323.6 | DN28: 4421960.1 | DO28: -9999 | DP28: -9999 | DQ28: -9999 | DR28: -9999 | DS28: -9999 | DU28: 333419 | DV28: 360744 | DW28: 431377 | DX28: 431377 | DY28: -9999 | DZ28: -9999 | EA28: -9999 | EB28: -9999 | EC28: -9999
A29: Nevada | B29: NV | C29: 32 | D29: 42529626 | E29: 36131118 | G29: 33496.329 | H29: 787642.25 | I29: 787642.25 | J29: 957037.97 | L29: 60285.501 | M29: 1417570.5 | N29: 1417570.5 | O29: 1722442.9 | P29: =((G29*10+(H29-G29)*50+(I29-H29)*100)/I29) -> 48.298906 | Q29: =I29/N29 -> 0.55562827 | R29: =N29 -> 1417570.5 | T29: 30814.159 | U29: 32098.082 | V29: 32098.082 | W29: 32098.082 | Y29: 17525.668 | Z29: 18255.904 | AA29: 18255.904 | AB29: 18255.904 | AC29: =((T29*10+(U29-T29)*50+(V29-U29)*100)/V29) -> 11.6 | AD29: =V29/AA29 -> 1.7582302 | AE29: =AA29 -> 18255.904 | AF29: -9999 | AG29: -9999 | AH29: -9999 | AI29: -9999 | AJ29: -9999 | AK29: -9999 | AL29: -9999 | AM29: -9999 | AN29: -9999 | AO29: -9999 | AP29: =(IF(AK29=-9999,0,(AG29*10+(AH29-AG29)*50+(AI29-AH29)*100)/AI29)) -> 0 | AQ29: =IF(AK29=-9999,0,AI29/AN29) -> 0 | AR29: =IF(AK29=-9999,0,AN29) -> 0 | AS29: 0 | AT29: 0 | AU29: 37205.971 | AV29: 37403.578 | AW29: 38537.899 | AX29: -9999 | AY29: 0 | AZ29: 194148.93 | BA29: 194240.69 | BB29: 282460.22 | BC29: =(IF(AY29=-9999,0,(AT29*10+(AU29-AT29)*50+(AV29-AU29)*100)/AV29)) -> 50.264155 | BD29: =IF(AY29=-9999,0,AV29/BA29) -> 0.19256304 | BE29: =IF(AY29=-9999,0,BA29) -> 194240.69 | BF29: 0 | BG29: 0 | BH29: 0 | BI29: 0 | BJ29: 98838.064 | BK29: 0 | BL29: 0 | BM29: 0 | BN29: 0 | BO29: 45771.998 | BQ29: 114775.94 | BR29: 114775.94 | BS29: 118447.82 | BT29: 118447.82 | BV29: 241714.21 | BW29: 241714.21 | BX29: 249447.07 | BY29: 249447.07 | CA29: 4685.6218 | CB29: 74969.948 | CC29: 93712.436 | CD29: 93712.436 | CF29: 2177.7125 | CG29: 34843.4 | CH29: 43554.25 | CI29: 43554.25 | CK29: 179844.13 | CL29: 218158.82 | CM29: 197753.25 | CN29: 197753.25 | CP29: 311.34239 | CQ29: 4465.5872 | CR29: 4465.5872 | CS29: 4465.5872 | CT29: =(IF(CP29=-9999,0,(CK29*10+(CL29-CK29)*50+(CM29-CL29)*100)/CM29)) -> 8.4631671 | CU29: =IF(CP29=-9999,0,CM29/CR29) -> 44.283817 | CV29: =IF(CP29=-9999,0,CR29) -> 4465.5872 | CX29: 264.88991 | CY29: 12680.589 | CZ29: 16029.902 | DA29: 16250.914 | DC29: 283.83156 | DD29: 10748.385 | DE29: 13402.56 | DF29: 13587.347 | DG29: =(IF(DC29=-9999,0,(CX29*10+(CY29-CX29)*50+(CZ29-CY29)*100)/CZ29)) -> 59.786091 | DH29: =IF(DC29=-9999,0,CZ29/DE29) -> 1.1960329 | DI29: =IF(DC29=-9999,0,DE29) -> 13402.56 | DK29: 26166.792 | DL29: 29543.247 | DM29: 31601.332 | DN29: 39598.087 | DO29: -9999 | DP29: -9999 | DQ29: -9999 | DR29: -9999 | DS29: -9999 | DU29: 24710 | DV29: 65520 | DW29: 71807 | DX29: 71807 | DY29: -9999 | DZ29: -9999 | EA29: -9999 | EB29: -9999 | EC29: -9999
A30: New Hampshire | B30: NH | C30: 33 | D30: 16064006 | E30: 6640723.8 | G30: 41830.258 | H30: 983608.65 | I30: 983608.65 | J30: 1195150.2 | L30: 12141.06 | M30: 285488.36 | N30: 285488.36 | O30: 346887.43 | P30: =((G30*10+(H30-G30)*50+(I30-H30)*100)/I30) -> 48.298906 | Q30: =I30/N30 -> 3.4453547 | R30: =N30 -> 285488.36 | T30: 303717.21 | U30: 316372.1 | V30: 316372.1 | W30: 316372.1 | Y30: 36113.758 | Z30: 37618.498 | AA30: 37618.498 | AB30: 37618.498 | AC30: =((T30*10+(U30-T30)*50+(V30-U30)*100)/V30) -> 11.6 | AD30: =V30/AA30 -> 8.410014 | AE30: =AA30 -> 37618.498 | AF30: -9999 | AG30: -9999 | AH30: -9999 | AI30: -9999 | AJ30: -9999 | AK30: -9999 | AL30: -9999 | AM30: -9999 | AN30: -9999 | AO30: -9999 | AP30: =(IF(AK30=-9999,0,(AG30*10+(AH30-AG30)*50+(AI30-AH30)*100)/AI30)) -> 0 | AQ30: =IF(AK30=-9999,0,AI30/AN30) -> 0 | AR30: =IF(AK30=-9999,0,AN30) -> 0 | AS30: -9999 | AT30: -9999 | AU30: -9999 | AV30: -9999 | AW30: -9999 | AX30: -9999 | AY30: -9999 | AZ30: -9999 | BA30: -9999 | BB30: -9999 | BC30: =(IF(AY30=-9999,0,(AT30*10+(AU30-AT30)*50+(AV30-AU30)*100)/AV30)) -> 0 | BD30: =IF(AY30=-9999,0,AV30/BA30) -> 0 | BE30: =IF(AY30=-9999,0,BA30) -> 0 | BF30: 0 | BG30: 0 | BH30: 0 | BI30: 0 | BJ30: 96980.681 | BK30: 0 | BL30: 0 | BM30: 0 | BN30: 0 | BO30: 42842.172 | BQ30: 20198.881 | BR30: 20198.881 | BS30: 20845.079 | BT30: 20845.079 | BV30: 42538.156 | BW30: 42538.156 | BX30: 43899.026 | BY30: 43899.026 | CA30: 824.60072 | CB30: 13193.611 | CC30: 16492.014 | CD30: 16492.014 | CF30: 383.24546 | CG30: 6131.9274 | CH30: 7664.9092 | CI30: 7664.9092 | CK30: 5318.6273 | CL30: 10316.361 | CM30: 9351.4166 | CN30: 9351.4166 | CP30: 0 | CQ30: 86.983154 | CR30: 86.983154 | CS30: 86.983154 | CT30: =(IF(CP30=-9999,0,(CK30*10+(CL30-CK30)*50+(CM30-CL30)*100)/CM30)) -> 22.090609 | CU30: =IF(CP30=-9999,0,CM30/CR30) -> 107.50836 | CV30: =IF(CP30=-9999,0,CR30) -> 86.983154 | CX30: 12.875135 | CY30: 616.3477 | CZ30: 779.14311 | DA30: 789.88556 | DC30: 5.5286265 | DD30: 209.36293 | DE30: 261.06239 | DF30: 264.66179 | DG30: =(IF(DC30=-9999,0,(CX30*10+(CY30-CX30)*50+(CZ30-CY30)*100)/CZ30)) -> 59.786091 | DH30: =IF(DC30=-9999,0,CZ30/DE30) -> 2.9845092 | DI30: =IF(DC30=-9999,0,DE30) -> 261.06239 | DK30: 3725.706 | DL30: 4206.4343 | DM30: 4506.1207 | DN30: 5644.5776 | DO30: -9999 | DP30: -9999 | DQ30: -9999 | DR30: -9999 | DS30: -9999 | DU30: 0 | DV30: 504 | DW30: 504 | DX30: 504 | DY30: -9999 | DZ30: -9999 | EA30: -9999 | EB30: -9999 | EC30: -9999
A31: New Jersey | B31: NJ | C31: 34 | D31: 1.278764e+08 | E31: 1.2334907e+08 | F31: 0 | G31: 37499.239 | H31: 881767.82 | I31: 881767.82 | J31: 1071406.8 | K31: 0 | L31: 8700.0029 | M31: 204574.35 | N31: 204574.35 | O31: 248571.51 | P31: =((G31*10+(H31-G31)*50+(I31-H31)*100)/I31) -> 48.298906 | Q31: =I31/N31 -> 4.3102559 | R31: =N31 -> 204574.35 | S31: 0 | T31: 285108.23 | U31: 296987.74 | V31: 296987.74 | W31: 296987.74 | X31: 0 | Y31: 34652.587 | Z31: 36096.445 | AA31: 36096.445 | AB31: 36096.445 | AC31: =((T31*10+(U31-T31)*50+(V31-U31)*100)/V31) -> 11.6 | AD31: =V31/AA31 -> 8.2276174 | AE31: =AA31 -> 36096.445 | AF31: -9999 | AG31: -9999 | AH31: -9999 | AI31: -9999 | AJ31: -9999 | AK31: -9999 | AL31: -9999 | AM31: -9999 | AN31: -9999 | AO31: -9999 | AP31: =(IF(AK31=-9999,0,(AG31*10+(AH31-AG31)*50+(AI31-AH31)*100)/AI31)) -> 0 | AQ31: =IF(AK31=-9999,0,AI31/AN31) -> 0 | AR31: =IF(AK31=-9999,0,AN31) -> 0 | AS31: -9999 | AT31: -9999 | AU31: -9999 | AV31: -9999 | AW31: -9999 | AX31: -9999 | AY31: -9999 | AZ31: -9999 | BA31: -9999 | BB31: -9999 | BC31: =(IF(AY31=-9999,0,(AT31*10+(AU31-AT31)*50+(AV31-AU31)*100)/AV31)) -> 0 | BD31: =IF(AY31=-9999,0,AV31/BA31) -> 0 | BE31: =IF(AY31=-9999,0,BA31) -> 0 | BF31: 0 | BG31: 0 | BH31: 0 | BI31: 0 | BJ31: 110317.45 | BK31: 0 | BL31: 0 | BM31: 0 | BN31: 0 | BO31: 35970.201 | BQ31: 99942.382 | BR31: 99942.382 | BS31: 103139.71 | BT31: 103139.71 | BV31: 210475.25 | BW31: 210475.25 | BX31: 217208.72 | BY31: 217208.72 | CA31: 4080.0556 | CB31: 65280.89 | CC31: 81601.113 | CD31: 81601.113 | CF31: 1896.2666 | CG31: 30340.266 | CH31: 37925.332 | CI31: 37925.332 | CJ31: 0 | CK31: 559.79076 | CL31: 38814.692 | CM31: 35184.144 | CN31: 35184.144 | CO31: 0 | CP31: 0 | CQ31: 533.90996 | CR31: 533.90996 | CS31: 533.90996 | CT31: =(IF(CP31=-9999,0,(CK31*10+(CL31-CK31)*50+(CM31-CL31)*100)/CM31)) -> 44.204236 | CU31: =IF(CP31=-9999,0,CM31/CR31) -> 65.899022 | CV31: =IF(CP31=-9999,0,CR31) -> 533.90996 | CX31: 50.251542 | CY31: 2405.5999 | CZ31: 3040.989 | DA31: 3082.9167 | DC31: 33.935177 | DD31: 1285.0874 | DE31: 1602.4231 | DF31: 1624.5165 | DG31: =(IF(DC31=-9999,0,(CX31*10+(CY31-CX31)*50+(CZ31-CY31)*100)/CZ31)) -> 59.786091 | DH31: =IF(DC31=-9999,0,CZ31/DE31) -> 1.8977442 | DI31: =IF(DC31=-9999,0,DE31) -> 1602.4231 | DJ31: 40316.638 | DK31: 41709.251 | DL31: 47092.427 | DM31: 50004.368 | DN31: 62759.035 | DO31: -9999 | DP31: -9999 | DQ31: -9999 | DR31: -9999 | DS31: -9999 | DT31: 0 | DU31: 0 | DV31: 121 | DW31: 1115 | DX31: 1115 | DY31: -9999 | DZ31: -9999 | EA31: -9999 | EB31: -9999 | EC31: -9999
A32: New Mexico | B32: NM | C32: 35 | D32: 77689507 | E32: 76185697 | G32: 83725.335 | H32: 1968741.5 | I32: 1968741.5 | J32: 2392152.4 | L32: 168076.29 | M32: 3952193.8 | N32: 3952193.8 | O32: 4802179.6 | P32: =((G32*10+(H32-G32)*50+(I32-H32)*100)/I32) -> 48.298906 | Q32: =I32/N32 -> 0.4981389 | R32: =N32 -> 3952193.8 | T32: 107791.47 | U32: 112282.78 | V32: 112282.78 | W32: 112282.78 | Y32: 56001.974 | Z32: 58335.389 | AA32: 58335.389 | AB32: 58335.389 | AC32: =((T32*10+(U32-T32)*50+(V32-U32)*100)/V32) -> 11.6 | AD32: =V32/AA32 -> 1.9247798 | AE32: =AA32 -> 58335.389 | AF32: -9999 | AG32: -9999 | AH32: -9999 | AI32: -9999 | AJ32: -9999 | AK32: -9999 | AL32: -9999 | AM32: -9999 | AN32: -9999 | AO32: -9999 | AP32: =(IF(AK32=-9999,0,(AG32*10+(AH32-AG32)*50+(AI32-AH32)*100)/AI32)) -> 0 | AQ32: =IF(AK32=-9999,0,AI32/AN32) -> 0 | AR32: =IF(AK32=-9999,0,AN32) -> 0 | AS32: 0 | AT32: 0 | AU32: 1350725.9 | AV32: 1350725.9 | AW32: 1362218.4 | AX32: -9999 | AY32: 0 | AZ32: 2113298.3 | BA32: 2113298.3 | BB32: 3007104.6 | BC32: =(IF(AY32=-9999,0,(AT32*10+(AU32-AT32)*50+(AV32-AU32)*100)/AV32)) -> 50 | BD32: =IF(AY32=-9999,0,AV32/BA32) -> 0.63915537 | BE32: =IF(AY32=-9999,0,BA32) -> 2113298.3 | BF32: 0 | BG32: 0 | BH32: 0 | BI32: 0 | BJ32: 135689.45 | BK32: 0 | BL32: 0 | BM32: 0 | BN32: 0 | BO32: 49457.976 | BQ32: 293409.79 | BR32: 293409.79 | BS32: 302796.49 | BT32: 302796.49 | BV32: 617911.02 | BW32: 617911.02 | BX32: 637679.08 | BY32: 637679.08 | CA32: 11978.184 | CB32: 191650.95 | CC32: 239563.69 | CD32: 239563.69 | CF32: 5567.0395 | CG32: 89072.633 | CH32: 111340.79 | CI32: 111340.79 | CK32: 460947.38 | CL32: 906273.79 | CM32: 821505.12 | CN32: 821505.12 | CP32: 293.53304 | CQ32: 22223.737 | CR32: 22230.298 | CS32: 22230.298 | CT32: =(IF(CP32=-9999,0,(CK32*10+(CL32-CK32)*50+(CM32-CL32)*100)/CM32)) -> 22.396607 | CU32: =IF(CP32=-9999,0,CM32/CR32) -> 36.954301 | CV32: =IF(CP32=-9999,0,CR32) -> 22230.298 | CX32: 831.18751 | CY32: 39789.915 | CZ32: 50299.592 | DA32: 50993.099 | DC32: 1412.9519 | DD32: 53506.918 | DE32: 66719.756 | DF32: 67639.656 | DG32: =(IF(DC32=-9999,0,(CX32*10+(CY32-CX32)*50+(CZ32-CY32)*100)/CZ32)) -> 59.786091 | DH32: =IF(DC32=-9999,0,CZ32/DE32) -> 0.75389353 | DI32: =IF(DC32=-9999,0,DE32) -> 66719.756 | DK32: 42229.025 | DL32: 47666.658 | DM32: 54538.802 | DN32: 67366.953 | DO32: -9999 | DP32: -9999 | DQ32: -9999 | DR32: -9999 | DS32: -9999 | DU32: 473025 | DV32: 931726 | DW32: 982432 | DX32: 982432 | DY32: -9999 | DZ32: -9999 | EA32: -9999 | EB32: -9999 | EC32: -9999
A33: New York | B33: NY | C33: 36 | D33: 2.061448e+08 | E33: 1.8556267e+08 | F33: 0 | G33: 302569.03 | H33: 7114694.7 | I33: 7114694.7 | J33: 8644829.5 | K33: 0 | L33: 83106.439 | M33: 1954188.5 | N33: 1954188.5 | O33: 2374469.7 | P33: =((G33*10+(H33-G33)*50+(I33-H33)*100)/I33) -> 48.298906 | Q33: =I33/N33 -> 3.6407412 | R33: =N33 -> 1954188.5 | S33: 0 | T33: 559234.58 | U33: 582536.03 | V33: 582536.03 | W33: 582536.03 | X33: 0 | Y33: 65624.047 | Z33: 68358.383 | AA33: 68358.383 | AB33: 68358.383 | AC33: =((T33*10+(U33-T33)*50+(V33-U33)*100)/V33) -> 11.6 | AD33: =V33/AA33 -> 8.5217936 | AE33: =AA33 -> 68358.383 | AF33: -9999 | AG33: -9999 | AH33: -9999 | AI33: -9999 | AJ33: -9999 | AK33: -9999 | AL33: -9999 | AM33: -9999 | AN33: -9999 | AO33: -9999 | AP33: =(IF(AK33=-9999,0,(AG33*10+(AH33-AG33)*50+(AI33-AH33)*100)/AI33)) -> 0 | AQ33: =IF(AK33=-9999,0,AI33/AN33) -> 0 | AR33: =IF(AK33=-9999,0,AN33) -> 0 | AS33: -9999 | AT33: -9999 | AU33: -9999 | AV33: -9999 | AW33: -9999 | AX33: -9999 | AY33: -9999 | AZ33: -9999 | BA33: -9999 | BB33: -9999 | BC33: =(IF(AY33=-9999,0,(AT33*10+(AU33-AT33)*50+(AV33-AU33)*100)/AV33)) -> 0 | BD33: =IF(AY33=-9999,0,AV33/BA33) -> 0 | BE33: =IF(AY33=-9999,0,BA33) -> 0 | BF33: 0 | BG33: 0 | BH33: 0 | BI33: 0 | BJ33: 1114786.1 | BK33: 0 | BL33: 0 | BM33: 0 | BN33: 0 | BO33: 445272.95 | BQ33: 910422.5 | BR33: 910422.5 | BS33: 939548.51 | BT33: 939548.51 | BV33: 1917318.8 | BW33: 1917318.8 | BX33: 1978657.1 | BY33: 1978657.1 | CA33: 37167.159 | CB33: 594674.55 | CC33: 743343.19 | CD33: 743343.19 | CF33: 17273.991 | CG33: 276383.85 | CH33: 345479.82 | CI33: 345479.82 | CJ33: 0 | CK33: 830441.12 | CL33: 3538089.3 | CM33: 3207152.8 | CN33: 3207152.8 | CO33: 0 | CP33: 7484.3649 | CQ33: 36920.958 | CR33: 36954.21 | CS33: 36974.233 | CT33: =(IF(CP33=-9999,0,(CK33*10+(CL33-CK33)*50+(CM33-CL33)*100)/CM33)) -> 34.483286 | CU33: =IF(CP33=-9999,0,CM33/CR33) -> 86.787209 | CV33: =IF(CP33=-9999,0,CR33) -> 36954.21 | CX33: 4183.581 | CY33: 200272.9 | CZ33: 253170.82 | DA33: 256661.41 | DC33: 2350.0726 | DD33: 88994.634 | DE33: 110970.7 | DF33: 112500.71 | DG33: =(IF(DC33=-9999,0,(CX33*10+(CY33-CX33)*50+(CZ33-CY33)*100)/CZ33)) -> 59.786091 | DH33: =IF(DC33=-9999,0,CZ33/DE33) -> 2.2814203 | DI33: =IF(DC33=-9999,0,DE33) -> 110970.7 | DJ33: 161764.79 | DK33: 167329.12 | DL33: 188894.4 | DM33: 210190.43 | DN33: 261150.19 | DO33: -9999 | DP33: -9999 | DQ33: -9999 | DR33: -9999 | DS33: -9999 | DT33: 0 | DU33: 24437 | DV33: 82562 | DW33: 84140 | DX33: 84140 | DY33: -9999 | DZ33: -9999 | EA33: -9999 | EB33: -9999 | EC33: -9999
A34: North Carolina | B34: NC | C34: 37 | D34: 1.6634482e+08 | E34: 1.4017448e+08 | F34: 0 | G34: 296122.69 | H34: 6963113.6 | I34: 6963113.6 | J34: 8460648.4 | K34: 0 | L34: 101861.18 | M34: 2395193 | N34: 2395193 | O34: 2910319.6 | P34: =((G34*10+(H34-G34)*50+(I34-H34)*100)/I34) -> 48.298906 | Q34: =I34/N34 -> 2.9071201 | R34: =N34 -> 2395193 | S34: 0 | T34: 2603912 | U34: 2712408.3 | V34: 2712408.3 | W34: 2712408.3 | X34: 0 | Y34: 380506.98 | Z34: 396361.44 | AA34: 396361.44 | AB34: 396361.44 | AC34: =((T34*10+(U34-T34)*50+(V34-U34)*100)/V34) -> 11.6 | AD34: =V34/AA34 -> 6.84327 | AE34: =AA34 -> 396361.44 | AF34: -9999 | AG34: -9999 | AH34: -9999 | AI34: -9999 | AJ34: -9999 | AK34: -9999 | AL34: -9999 | AM34: -9999 | AN34: -9999 | AO34: -9999 | AP34: =(IF(AK34=-9999,0,(AG34*10+(AH34-AG34)*50+(AI34-AH34)*100)/AI34)) -> 0 | AQ34: =IF(AK34=-9999,0,AI34/AN34) -> 0 | AR34: =IF(AK34=-9999,0,AN34) -> 0 | AS34: -9999 | AT34: -9999 | AU34: -9999 | AV34: -9999 | AW34: -9999 | AX34: -9999 | AY34: -9999 | AZ34: -9999 | BA34: -9999 | BB34: -9999 | BC34: =(IF(AY34=-9999,0,(AT34*10+(AU34-AT34)*50+(AV34-AU34)*100)/AV34)) -> 0 | BD34: =IF(AY34=-9999,0,AV34/BA34) -> 0 | BE34: =IF(AY34=-9999,0,BA34) -> 0 | BF34: 0 | BG34: 0 | BH34: 0 | BI34: 0 | BJ34: 1046733.1 | BK34: 0 | BL34: 0 | BM34: 0 | BN34: 0 | BO34: 321608.38 | BQ34: 1432121.7 | BR34: 1432121.7 | BS34: 1477937.8 | BT34: 1477937.8 | BV34: 3015999.6 | BW34: 3015999.6 | BX34: 3112486.6 | BY34: 3112486.6 | CA34: 58465.05 | CB34: 935440.8 | CC34: 1169301 | CD34: 1169301 | CF34: 27172.502 | CG34: 434760.04 | CH34: 543450.05 | CI34: 543450.05 | CJ34: 0 | CK34: 1097.7692 | CL34: 585906.09 | CM34: 531244.29 | CN34: 531244.29 | CO34: 0 | CP34: 0 | CQ34: 9876.7531 | CR34: 9876.7531 | CS34: 9876.7531 | CT34: =(IF(CP34=-9999,0,(CK34*10+(CL34-CK34)*50+(CM34-CL34)*100)/CM34)) -> 44.772648 | CU34: =IF(CP34=-9999,0,CM34/CR34) -> 53.787341 | CV34: =IF(CP34=-9999,0,CR34) -> 9876.7531 | CX34: 1082.1837 | CY34: 51805.394 | CZ34: 65488.711 | DA34: 66391.637 | DC34: 627.76384 | DD34: 23772.718 | DE34: 29643.082 | DF34: 30051.787 | DG34: =(IF(DC34=-9999,0,(CX34*10+(CY34-CX34)*50+(CZ34-CY34)*100)/CZ34)) -> 59.786091 | DH34: =IF(DC34=-9999,0,CZ34/DE34) -> 2.2092409 | DI34: =IF(DC34=-9999,0,DE34) -> 29643.082 | DJ34: 371625.06 | DK34: 384436.08 | DL34: 434019.1 | DM34: 471413.6 | DN34: 588744.06 | DO34: -9999 | DP34: -9999 | DQ34: -9999 | DR34: -9999 | DS34: -9999 | DT34: 0 | DU34: 1039321 | DV34: 2978577 | DW34: 3154873 | DX34: 3154873 | DY34: -9999 | DZ34: -9999 | EA34: -9999 | EB34: -9999 | EC34: -9999
A35: North Dakota | B35: ND | C35: 38 | D35: 90041267 | E35: 89180168 | G35: 43003.192 | H35: 1011189.3 | I35: 1011189.3 | J35: 1228662.6 | L35: 36305.972 | M35: 853709 | N35: 853709 | O35: 1037313.5 | P35: =((G35*10+(H35-G35)*50+(I35-H35)*100)/I35) -> 48.298906 | Q35: =I35/N35 -> 1.1844661 | R35: =N35 -> 853709 | T35: 3202.1829 | U35: 3335.6072 | V35: 3335.6072 | W35: 3335.6072 | Y35: 809.72152 | Z35: 843.45992 | AA35: 843.45992 | AB35: 843.45992 | AC35: =((T35*10+(U35-T35)*50+(V35-U35)*100)/V35) -> 11.6 | AD35: =V35/AA35 -> 3.9546718 | AE35: =AA35 -> 843.45992 | AF35: -9999 | AG35: -9999 | AH35: -9999 | AI35: -9999 | AJ35: -9999 | AK35: -9999 | AL35: -9999 | AM35: -9999 | AN35: -9999 | AO35: -9999 | AP35: =(IF(AK35=-9999,0,(AG35*10+(AH35-AG35)*50+(AI35-AH35)*100)/AI35)) -> 0 | AQ35: =IF(AK35=-9999,0,AI35/AN35) -> 0 | AR35: =IF(AK35=-9999,0,AN35) -> 0 | AS35: -9999 | AT35: -9999 | AU35: -9999 | AV35: -9999 | AW35: -9999 | AX35: -9999 | AY35: -9999 | AZ35: -9999 | BA35: -9999 | BB35: -9999 | BC35: =(IF(AY35=-9999,0,(AT35*10+(AU35-AT35)*50+(AV35-AU35)*100)/AV35)) -> 0 | BD35: =IF(AY35=-9999,0,AV35/BA35) -> 0 | BE35: =IF(AY35=-9999,0,BA35) -> 0 | BF35: 0 | BG35: 0 | BH35: 0 | BI35: 0 | BJ35: 25259.659 | BK35: 0 | BL35: 0 | BM35: 0 | BN35: 0 | BO35: 10858.469 | BQ35: 7478109.9 | BR35: 7478109.9 | BS35: 7717347.6 | BT35: 7717347.6 | BV35: 15748644 | BW35: 15748644 | BX35: 16252471 | BY35: 16252471 | CA35: 305286.94 | CB35: 4884591.1 | CC35: 6105738.8 | CD35: 6105738.8 | CF35: 141886.65 | CG35: 2270186.4 | CH35: 2837733 | CI35: 2837733 | CK35: 1539192.4 | CL35: 10383055 | CM35: 9411871.9 | CN35: 9411871.9 | CP35: 97052.987 | CQ35: 124399.86 | CR35: 124399.86 | CS35: 124399.86 | CT35: =(IF(CP35=-9999,0,(CK35*10+(CL35-CK35)*50+(CM35-CL35)*100)/CM35)) -> 38.299156 | CU35: =IF(CP35=-9999,0,CM35/CR35) -> 75.658221 | CV35: =IF(CP35=-9999,0,CR35) -> 124399.86 | CX35: 14653.994 | CY35: 701503.77 | CZ35: 886791.38 | DA35: 899018.03 | DC35: 7906.8224 | DD35: 299422.57 | DE35: 373361.09 | DF35: 378508.8 | DG35: =(IF(DC35=-9999,0,(CX35*10+(CY35-CX35)*50+(CZ35-CY35)*100)/CZ35)) -> 59.786091 | DH35: =IF(DC35=-9999,0,CZ35/DE35) -> 2.3751575 | DI35: =IF(DC35=-9999,0,DE35) -> 373361.09 | DK35: 1769828.1 | DL35: 1996389.5 | DM35: 2698008 | DN35: 3226630.3 | DO35: -9999 | DP35: -9999 | DQ35: -9999 | DR35: -9999 | DS35: -9999 | DU35: 18996 | DV35: 21452 | DW35: 24426 | DX35: 24426 | DY35: -9999 | DZ35: -9999 | EA35: -9999 | EB35: -9999 | EC35: -9999
A36: Ohio | B36: OH | C36: 39 | D36: 2.7521835e+08 | E36: 2.5128019e+08 | G36: 492670.13 | H36: 11584786 | I36: 11584786 | J36: 14076290 | L36: 134191.07 | M36: 3155407.2 | N36: 3155407.2 | O36: 3834030.6 | P36: =((G36*10+(H36-G36)*50+(I36-H36)*100)/I36) -> 48.298906 | Q36: =I36/N36 -> 3.6714077 | R36: =N36 -> 3155407.2 | T36: 927811.21 | U36: 966470.01 | V36: 966470.01 | W36: 966470.01 | Y36: 101898.93 | Z36: 106144.71 | AA36: 106144.71 | AB36: 106144.71 | AC36: =((T36*10+(U36-T36)*50+(V36-U36)*100)/V36) -> 11.6 | AD36: =V36/AA36 -> 9.1052109 | AE36: =AA36 -> 106144.71 | AF36: -9999 | AG36: -9999 | AH36: -9999 | AI36: -9999 | AJ36: -9999 | AK36: -9999 | AL36: -9999 | AM36: -9999 | AN36: -9999 | AO36: -9999 | AP36: =(IF(AK36=-9999,0,(AG36*10+(AH36-AG36)*50+(AI36-AH36)*100)/AI36)) -> 0 | AQ36: =IF(AK36=-9999,0,AI36/AN36) -> 0 | AR36: =IF(AK36=-9999,0,AN36) -> 0 | AS36: -9999 | AT36: -9999 | AU36: -9999 | AV36: -9999 | AW36: -9999 | AX36: -9999 | AY36: -9999 | AZ36: -9999 | BA36: -9999 | BB36: -9999 | BC36: =(IF(AY36=-9999,0,(AT36*10+(AU36-AT36)*50+(AV36-AU36)*100)/AV36)) -> 0 | BD36: =IF(AY36=-9999,0,AV36/BA36) -> 0 | BE36: =IF(AY36=-9999,0,BA36) -> 0 | BF36: 0 | BG36: 0 | BH36: 0 | BI36: 0 | BJ36: 878377.75 | BK36: 0 | BL36: 0 | BM36: 0 | BN36: 0 | BO36: 339528.03 | BQ36: 3161651 | BR36: 3161651 | BS36: 3262797.7 | BT36: 3262797.7 | BV36: 6658329.1 | BW36: 6658329.1 | BX36: 6871340.7 | BY36: 6871340.7 | CA36: 129071.49 | CB36: 2065143.8 | CC36: 2581429.7 | CD36: 2581429.7 | CF36: 59987.895 | CG36: 959806.32 | CH36: 1199757.9 | CI36: 1199757.9 | CK36: 13090.2 | CL36: 1128028.2 | CM36: 1141693.5 | CN36: 1141693.5 | CP36: 288.80894 | CQ36: 15273.706 | CR36: 15997.732 | CS36: 15997.732 | CT36: =(IF(CP36=-9999,0,(CK36*10+(CL36-CK36)*50+(CM36-CL36)*100)/CM36)) -> 50.139846 | CU36: =IF(CP36=-9999,0,CM36/CR36) -> 71.365961 | CV36: =IF(CP36=-9999,0,CR36) -> 15997.732 | CX36: 1604.4573 | CY36: 76807.24 | CZ36: 97094.274 | DA36: 98432.962 | DC36: 1016.8117 | DD36: 38505.527 | DE36: 48013.967 | DF36: 48675.96 | DG36: =(IF(DC36=-9999,0,(CX36*10+(CY36-CX36)*50+(CZ36-CY36)*100)/CZ36)) -> 59.786091 | DH36: =IF(DC36=-9999,0,CZ36/DE36) -> 2.0222089 | DI36: =IF(DC36=-9999,0,DE36) -> 48013.967 | DK36: 754758.48 | DL36: 851528.2 | DM36: 1103927.2 | DN36: 1330382.3 | DO36: -9999 | DP36: -9999 | DQ36: -9999 | DR36: -9999 | DS36: -9999 | DU36: 164576 | DV36: 244165 | DW36: 360768 | DX36: 360768 | DY36: -9999 | DZ36: -9999 | EA36: -9999 | EB36: -9999 | EC36: -9999
A37: Oklahoma | B37: OK | C37: 40 | D37: 1.4513842e+08 | E37: 1.3595639e+08 | G37: 248463.54 | H37: 5842442.7 | I37: 5842442.7 | J37: 7098958.4 | L37: 87265.285 | M37: 2051980.8 | N37: 2051980.8 | O37: 2493293.9 | P37: =((G37*10+(H37-G37)*50+(I37-H37)*100)/I37) -> 48.298906 | Q37: =I37/N37 -> 2.8472209 | R37: =N37 -> 2051980.8 | T37: 766260.59 | U37: 798188.11 | V37: 798188.11 | W37: 798188.11 | Y37: 155398.42 | Z37: 161873.36 | AA37: 161873.36 | AB37: 161873.36 | AC37: =((T37*10+(U37-T37)*50+(V37-U37)*100)/V37) -> 11.6 | AD37: =V37/AA37 -> 4.9309418 | AE37: =AA37 -> 161873.36 | AF37: -9999 | AG37: -9999 | AH37: -9999 | AI37: -9999 | AJ37: -9999 | AK37: -9999 | AL37: -9999 | AM37: -9999 | AN37: -9999 | AO37: -9999 | AP37: =(IF(AK37=-9999,0,(AG37*10+(AH37-AG37)*50+(AI37-AH37)*100)/AI37)) -> 0 | AQ37: =IF(AK37=-9999,0,AI37/AN37) -> 0 | AR37: =IF(AK37=-9999,0,AN37) -> 0 | AS37: -9999 | AT37: -9999 | AU37: -9999 | AV37: -9999 | AW37: -9999 | AX37: -9999 | AY37: -9999 | AZ37: -9999 | BA37: -9999 | BB37: -9999 | BC37: =(IF(AY37=-9999,0,(AT37*10+(AU37-AT37)*50+(AV37-AU37)*100)/AV37)) -> 0 | BD37: =IF(AY37=-9999,0,AV37/BA37) -> 0 | BE37: =IF(AY37=-9999,0,BA37) -> 0 | BF37: 0 | BG37: 0 | BH37: 0 | BI37: 0 | BJ37: 238997.27 | BK37: 0 | BL37: 0 | BM37: 0 | BN37: 0 | BO37: 69008.225 | BQ37: 3157653.3 | BR37: 3157653.3 | BS37: 3258672.1 | BT37: 3258672.1 | BV37: 6649910.1 | BW37: 6649910.1 | BX37: 6862652.4 | BY37: 6862652.4 | CA37: 128908.28 | CB37: 2062532.5 | CC37: 2578165.7 | CD37: 2578165.7 | CF37: 59912.044 | CG37: 958592.71 | CH37: 1198240.9 | CI37: 1198240.9 | CK37: 1544880 | CL37: 4005499.5 | CM37: 3630843.6 | CN37: 3630843.6 | CP37: 995.60716 | CQ37: 71611.545 | CR37: 71611.545 | CS37: 71611.545 | CT37: =(IF(CP37=-9999,0,(CK37*10+(CL37-CK37)*50+(CM37-CL37)*100)/CM37)) -> 27.821132 | CU37: =IF(CP37=-9999,0,CM37/CR37) -> 50.70193 | CV37: =IF(CP37=-9999,0,CR37) -> 71611.545 | CX37: 4523.3021 | CY37: 216535.74 | CZ37: 273729.15 | DA37: 277503.19 | DC37: 4551.611 | DD37: 172364.45 | DE37: 214927.61 | DF37: 217890.93 | DG37: =(IF(DC37=-9999,0,(CX37*10+(CY37-CX37)*50+(CZ37-CY37)*100)/CZ37)) -> 59.786091 | DH37: =IF(DC37=-9999,0,CZ37/DE37) -> 1.2735877 | DI37: =IF(DC37=-9999,0,DE37) -> 214927.61 | DK37: 567390.23 | DL37: 640253.44 | DM37: 793789.61 | DN37: 964815.96 | DO37: -9999 | DP37: -9999 | DQ37: -9999 | DR37: -9999 | DS37: -9999 | DU37: 366452 | DV37: 821292 | DW37: 832590 | DX37: 832590 | DY37: -9999 | DZ37: -9999 | EA37: -9999 | EB37: -9999 | EC37: -9999
A38: Oregon | B38: OR | C38: 41 | D38: 50191238 | E38: 51946273 | F38: 0 | G38: 195225.08 | H38: 4590578.4 | I38: 4590578.4 | J38: 5577859.5 | K38: 0 | L38: 184429.44 | M38: 4336726.5 | N38: 4336726.5 | O38: 5269412.5 | P38: =((G38*10+(H38-G38)*50+(I38-H38)*100)/I38) -> 48.298906 | Q38: =I38/N38 -> 1.0585354 | R38: =N38 -> 4336726.5 | S38: 0 | T38: 1621819.1 | U38: 1689394.9 | V38: 1689394.9 | W38: 1689394.9 | X38: 0 | Y38: 313921.63 | Z38: 327001.7 | AA38: 327001.7 | AB38: 327001.7 | AC38: =((T38*10+(U38-T38)*50+(V38-U38)*100)/V38) -> 11.6 | AD38: =V38/AA38 -> 5.1663183 | AE38: =AA38 -> 327001.7 | AF38: -9999 | AG38: -9999 | AH38: -9999 | AI38: -9999 | AJ38: -9999 | AK38: -9999 | AL38: -9999 | AM38: -9999 | AN38: -9999 | AO38: -9999 | AP38: =(IF(AK38=-9999,0,(AG38*10+(AH38-AG38)*50+(AI38-AH38)*100)/AI38)) -> 0 | AQ38: =IF(AK38=-9999,0,AI38/AN38) -> 0 | AR38: =IF(AK38=-9999,0,AN38) -> 0 | AS38: 0 | AT38: 0 | AU38: 0 | AV38: 1818135.7 | AW38: 2701882.4 | AX38: -9999 | AY38: 0 | AZ38: 0 | BA38: 1444646.3 | BB38: 2461453.3 | BC38: =(IF(AY38=-9999,0,(AT38*10+(AU38-AT38)*50+(AV38-AU38)*100)/AV38)) -> 100 | BD38: =IF(AY38=-9999,0,AV38/BA38) -> 1.2585335 | BE38: =IF(AY38=-9999,0,BA38) -> 1444646.3 | BF38: 0 | BG38: 0 | BH38: 0 | BI38: 0 | BJ38: 228065.12 | BK38: 0 | BL38: 0 | BM38: 0 | BN38: 0 | BO38: 90341.958 | BQ38: 667089.1 | BR38: 667089.1 | BS38: 688430.45 | BT38: 688430.45 | BV38: 1404866.9 | BW38: 1404866.9 | BX38: 1449811 | BY38: 1449811 | CA38: 27233.298 | CB38: 435732.76 | CC38: 544665.95 | CD38: 544665.95 | CF38: 12657.081 | CG38: 202513.29 | CH38: 253141.61 | CI38: 253141.61 | CJ38: 0 | CK38: 38036.245 | CL38: 1184730.9 | CM38: 1073916.6 | CN38: 1073916.6 | CO38: 0 | CP38: 189.41404 | CQ38: 15748.514 | CR38: 15878.591 | CS38: 15878.591 | CT38: =(IF(CP38=-9999,0,(CK38*10+(CL38-CK38)*50+(CM38-CL38)*100)/CM38)) -> 43.423919 | CU38: =IF(CP38=-9999,0,CM38/CR38) -> 67.632993 | CV38: =IF(CP38=-9999,0,CR38) -> 15878.591 | CX38: 1297.8353 | CY38: 62128.888 | CZ38: 78538.941 | DA38: 79621.797 | DC38: 1009.2391 | DD38: 38218.76 | DE38: 47656.387 | DF38: 48313.45 | DG38: =(IF(DC38=-9999,0,(CX38*10+(CY38-CX38)*50+(CZ38-CY38)*100)/CZ38)) -> 59.786091 | DH38: =IF(DC38=-9999,0,CZ38/DE38) -> 1.6480255 | DI38: =IF(DC38=-9999,0,DE38) -> 47656.387 | DJ38: 435502.26 | DK38: 450307.14 | DL38: 508109.82 | DM38: 637713.34 | DN38: 773278.97 | DO38: -9999 | DP38: -9999 | DQ38: -9999 | DR38: -9999 | DS38: -9999 | DT38: 0 | DU38: 107060 | DV38: 206354 | DW38: 228818 | DX38: 228818 | DY38: -9999 | DZ38: -9999 | EA38: -9999 | EB38: -9999 | EC38: -9999
A39: Pennsylvania | B39: PA | C39: 42 | D39: 2.9501839e+08 | E39: 2.6046616e+08 | G39: 482574.45 | H39: 11347393 | I39: 11347393 | J39: 13787841 | L39: 110730.68 | M39: 2603752.8 | N39: 2603752.8 | O39: 3163733.7 | P39: =((G39*10+(H39-G39)*50+(I39-H39)*100)/I39) -> 48.298906 | Q39: =I39/N39 -> 4.3580917 | R39: =N39 -> 2603752.8 | T39: 1075981.9 | U39: 1120814.4 | V39: 1120814.4 | W39: 1120814.4 | Y39: 115015.21 | Z39: 119807.52 | AA39: 119807.52 | AB39: 119807.52 | AC39: =((T39*10+(U39-T39)*50+(V39-U39)*100)/V39) -> 11.6 | AD39: =V39/AA39 -> 9.3551264 | AE39: =AA39 -> 119807.52 | AF39: -9999 | AG39: -9999 | AH39: -9999 | AI39: -9999 | AJ39: -9999 | AK39: -9999 | AL39: -9999 | AM39: -9999 | AN39: -9999 | AO39: -9999 | AP39: =(IF(AK39=-9999,0,(AG39*10+(AH39-AG39)*50+(AI39-AH39)*100)/AI39)) -> 0 | AQ39: =IF(AK39=-9999,0,AI39/AN39) -> 0 | AR39: =IF(AK39=-9999,0,AN39) -> 0 | AS39: -9999 | AT39: -9999 | AU39: -9999 | AV39: -9999 | AW39: -9999 | AX39: -9999 | AY39: -9999 | AZ39: -9999 | BA39: -9999 | BB39: -9999 | BC39: =(IF(AY39=-9999,0,(AT39*10+(AU39-AT39)*50+(AV39-AU39)*100)/AV39)) -> 0 | BD39: =IF(AY39=-9999,0,AV39/BA39) -> 0 | BE39: =IF(AY39=-9999,0,BA39) -> 0 | BF39: 0 | BG39: 0 | BH39: 0 | BI39: 0 | BJ39: 1022273.1 | BK39: 0 | BL39: 0 | BM39: 0 | BN39: 0 | BO39: 401627.17 | BQ39: 1156596.4 | BR39: 1156596.4 | BS39: 1193597.9 | BT39: 1193597.9 | BV39: 2435752.5 | BW39: 2435752.5 | BX39: 2513676.5 | BY39: 2513676.5 | CA39: 47216.981 | CB39: 755471.69 | CC39: 944339.61 | CD39: 944339.61 | CF39: 21944.795 | CG39: 351116.72 | CH39: 438895.9 | CI39: 438895.9 | CK39: 323182.24 | CL39: 1305619.2 | CM39: 1208533.1 | CN39: 1208533.1 | CP39: 0 | CQ39: 17380.137 | CR39: 17948.945 | CS39: 17948.945 | CT39: =(IF(CP39=-9999,0,(CK39*10+(CL39-CK39)*50+(CM39-CL39)*100)/CM39)) -> 35.28663 | CU39: =IF(CP39=-9999,0,CM39/CR39) -> 67.331708 | CV39: =IF(CP39=-9999,0,CR39) -> 17948.945 | CX39: 1589.7411 | CY39: 76102.759 | CZ39: 96203.719 | DA39: 97530.129 | DC39: 1140.8302 | DD39: 43201.971 | DE39: 53870.138 | DF39: 54612.873 | DG39: =(IF(DC39=-9999,0,(CX39*10+(CY39-CX39)*50+(CZ39-CY39)*100)/CZ39)) -> 59.786091 | DH39: =IF(DC39=-9999,0,CZ39/DE39) -> 1.7858451 | DI39: =IF(DC39=-9999,0,DE39) -> 53870.138 | DK39: 224188.24 | DL39: 253117.67 | DM39: 270406.58 | DN39: 338927.57 | DO39: -9999 | DP39: -9999 | DQ39: -9999 | DR39: -9999 | DS39: -9999 | DU39: 33962 | DV39: 99454 | DW39: 152977 | DX39: 152977 | DY39: -9999 | DZ39: -9999 | EA39: -9999 | EB39: -9999 | EC39: -9999
A40: Rhode Island | B40: RI | C40: 44 | D40: 10848582 | E40: 9509835.2 | F40: 0 | G40: 5435.8242 | H40: 127819.52 | I40: 127819.52 | J40: 155309.26 | K40: 0 | L40: 1179.178 | M40: 27727.528 | N40: 27727.528 | O40: 33690.799 | P40: =((G40*10+(H40-G40)*50+(I40-H40)*100)/I40) -> 48.298906 | Q40: =I40/N40 -> 4.609842 | R40: =N40 -> 27727.528 | S40: 0 | T40: 0 | U40: 0 | V40: 0 | W40: 0 | X40: 0 | Y40: 0 | Z40: 0 | AA40: 0 | AB40: 0 | AC40: =((T40*10+(U40-T40)*50+(V40-U40)*100)/V40) -> #DIV/0! | AD40: =V40/AA40 -> #DIV/0! | AE40: =AA40 -> 0 | AF40: -9999 | AG40: -9999 | AH40: -9999 | AI40: -9999 | AJ40: -9999 | AK40: -9999 | AL40: -9999 | AM40: -9999 | AN40: -9999 | AO40: -9999 | AP40: =(IF(AK40=-9999,0,(AG40*10+(AH40-AG40)*50+(AI40-AH40)*100)/AI40)) -> 0 | AQ40: =IF(AK40=-9999,0,AI40/AN40) -> 0 | AR40: =IF(AK40=-9999,0,AN40) -> 0 | AS40: -9999 | AT40: -9999 | AU40: -9999 | AV40: -9999 | AW40: -9999 | AX40: -9999 | AY40: -9999 | AZ40: -9999 | BA40: -9999 | BB40: -9999 | BC40: =(IF(AY40=-9999,0,(AT40*10+(AU40-AT40)*50+(AV40-AU40)*100)/AV40)) -> 0 | BD40: =IF(AY40=-9999,0,AV40/BA40) -> 0 | BE40: =IF(AY40=-9999,0,BA40) -> 0 | BF40: 0 | BG40: 0 | BH40: 0 | BI40: 0 | BJ40: 107949.03 | BK40: 0 | BL40: 0 | BM40: 0 | BN40: 0 | BO40: 40109.293 | BQ40: 2735.2652 | BR40: 2735.2652 | BS40: 2822.7711 | BT40: 2822.7711 | BV40: 5760.3753 | BW40: 5760.3753 | BX40: 5944.6597 | BY40: 5944.6597 | CA40: 111.66468 | CB40: 1786.6349 | CC40: 2233.2936 | CD40: 2233.2936 | CF40: 51.897823 | CG40: 830.36517 | CH40: 1037.9565 | CI40: 1037.9565 | CJ40: -9999 | CK40: -9999 | CL40: -9999 | CM40: -9999 | CN40: -9999 | CO40: -9999 | CP40: -9999 | CQ40: -9999 | CR40: -9999 | CS40: -9999 | CT40: =(IF(CP40=-9999,0,(CK40*10+(CL40-CK40)*50+(CM40-CL40)*100)/CM40)) -> 0 | CU40: =IF(CP40=-9999,0,CM40/CR40) -> 0 | CV40: =IF(CP40=-9999,0,CR40) -> 0 | CX40: 0 | CY40: 0 | CZ40: 0 | DA40: 0 | DC40: 0 | DD40: 0 | DE40: 0 | DF40: 0 | DG40: =(IF(DC40=-9999,0,(CX40*10+(CY40-CX40)*50+(CZ40-CY40)*100)/CZ40)) -> #DIV/0! | DH40: =IF(DC40=-9999,0,CZ40/DE40) -> #DIV/0! | DI40: =IF(DC40=-9999,0,DE40) -> 0 | DJ40: 2603.2147 | DK40: 2693.1357 | DL40: 3040.7249 | DM40: 3228.2828 | DN40: 4051.8524 | DO40: -9999 | DP40: -9999 | DQ40: -9999 | DR40: -9999 | DS40: -9999 | DT40: -9999 | DU40: 0 | DV40: 0 | DW40: 0 | DX40: 0 | DY40: -9999 | DZ40: -9999 | EA40: -9999 | EB40: -9999 | EC40: -9999
A41: South Carolina | B41: SC | C41: 45 | D41: 85405016 | E41: 49244946 | G41: 215288.38 | H41: 5062352.4 | I41: 5062352.4 | J41: 6151096.5 | L41: 82448.309 | M41: 1938713.1 | N41: 1938713.1 | O41: 2355666 | P41: =((G41*10+(H41-G41)*50+(I41-H41)*100)/I41) -> 48.298906 | Q41: =I41/N41 -> 2.6111921 | R41: =N41 -> 1938713.1 | T41: 1456554.3 | U41: 1517244.1 | V41: 1517244.1 | W41: 1517244.1 | Y41: 280895.12 | Z41: 292599.09 | AA41: 292599.09 | AB41: 292599.09 | AC41: =((T41*10+(U41-T41)*50+(V41-U41)*100)/V41) -> 11.6 | AD41: =V41/AA41 -> 5.1854027 | AE41: =AA41 -> 292599.09 | AF41: -9999 | AG41: -9999 | AH41: -9999 | AI41: -9999 | AJ41: -9999 | AK41: -9999 | AL41: -9999 | AM41: -9999 | AN41: -9999 | AO41: -9999 | AP41: =(IF(AK41=-9999,0,(AG41*10+(AH41-AG41)*50+(AI41-AH41)*100)/AI41)) -> 0 | AQ41: =IF(AK41=-9999,0,AI41/AN41) -> 0 | AR41: =IF(AK41=-9999,0,AN41) -> 0 | AS41: -9999 | AT41: -9999 | AU41: -9999 | AV41: -9999 | AW41: -9999 | AX41: -9999 | AY41: -9999 | AZ41: -9999 | BA41: -9999 | BB41: -9999 | BC41: =(IF(AY41=-9999,0,(AT41*10+(AU41-AT41)*50+(AV41-AU41)*100)/AV41)) -> 0 | BD41: =IF(AY41=-9999,0,AV41/BA41) -> 0 | BE41: =IF(AY41=-9999,0,BA41) -> 0 | BF41: 0 | BG41: 0 | BH41: 0 | BI41: 0 | BJ41: 545382.82 | BK41: 0 | BL41: 0 | BM41: 0 | BN41: 0 | BO41: 154678.78 | BQ41: 487403.22 | BR41: 487403.22 | BS41: 502996.1 | BT41: 502996.1 | BV41: 1026454.6 | BW41: 1026454.6 | BX41: 1059292.6 | BY41: 1059292.6 | CA41: 19897.787 | CB41: 318364.59 | CC41: 397955.74 | CD41: 397955.74 | CF41: 9247.7928 | CG41: 147964.69 | CH41: 184955.86 | CI41: 184955.86 | CK41: 36131.413 | CL41: 125673.45 | CM41: 113918.54 | CN41: 113918.54 | CP41: 473.53612 | CQ41: 1894.063 | CR41: 1894.063 | CS41: 1894.063 | CT41: =(IF(CP41=-9999,0,(CK41*10+(CL41-CK41)*50+(CM41-CL41)*100)/CM41)) -> 32.153894 | CU41: =IF(CP41=-9999,0,CM41/CR41) -> 60.145061 | CV41: =IF(CP41=-9999,0,CR41) -> 1894.063 | CX41: 173.4279 | CY41: 8302.1959 | CZ41: 10495.048 | DA41: 10639.749 | DC41: 120.38615 | DD41: 4558.8895 | DE41: 5684.6481 | DF41: 5763.0253 | DG41: =(IF(DC41=-9999,0,(CX41*10+(CY41-CX41)*50+(CZ41-CY41)*100)/CZ41)) -> 59.786091 | DH41: =IF(DC41=-9999,0,CZ41/DE41) -> 1.8462089 | DI41: =IF(DC41=-9999,0,DE41) -> 5684.6481 | DK41: 111091.46 | DL41: 125427.06 | DM41: 133911.55 | DN41: 167867.39 | DO41: -9999 | DP41: -9999 | DQ41: -9999 | DR41: -9999 | DS41: -9999 | DU41: 13590 | DV41: 37686 | DW41: 46883 | DX41: 46883 | DY41: -9999 | DZ41: -9999 | EA41: -9999 | EB41: -9999 | EC41: -9999
A42: South Dakota | B42: SD | C42: 46 | D42: 36010909 | E42: 29424331 | G42: 150838.78 | H42: 3546866.1 | I42: 3546866.1 | J42: 4309679.3 | L42: 109331.73 | M42: 2570857.4 | N42: 2570857.4 | O42: 3123763.6 | P42: =((G42*10+(H42-G42)*50+(I42-H42)*100)/I42) -> 48.298906 | Q42: =I42/N42 -> 1.3796432 | R42: =N42 -> 2570857.4 | T42: 15531.156 | U42: 16178.288 | V42: 16178.288 | W42: 16178.288 | Y42: 5426.9251 | Z42: 5653.0469 | AA42: 5653.0469 | AB42: 5653.0469 | AC42: =((T42*10+(U42-T42)*50+(V42-U42)*100)/V42) -> 11.6 | AD42: =V42/AA42 -> 2.8618704 | AE42: =AA42 -> 5653.0469 | AF42: -9999 | AG42: -9999 | AH42: -9999 | AI42: -9999 | AJ42: -9999 | AK42: -9999 | AL42: -9999 | AM42: -9999 | AN42: -9999 | AO42: -9999 | AP42: =(IF(AK42=-9999,0,(AG42*10+(AH42-AG42)*50+(AI42-AH42)*100)/AI42)) -> 0 | AQ42: =IF(AK42=-9999,0,AI42/AN42) -> 0 | AR42: =IF(AK42=-9999,0,AN42) -> 0 | AS42: 0 | AT42: 0 | AU42: 1909849 | AV42: 1909849 | AW42: 1909849 | AX42: -9999 | AY42: 0 | AZ42: 2857042.7 | BA42: 2857042.7 | BB42: 2857042.7 | BC42: =(IF(AY42=-9999,0,(AT42*10+(AU42-AT42)*50+(AV42-AU42)*100)/AV42)) -> 50 | BD42: =IF(AY42=-9999,0,AV42/BA42) -> 0.66847059 | BE42: =IF(AY42=-9999,0,BA42) -> 2857042.7 | BF42: 0 | BG42: 0 | BH42: 0 | BI42: 0 | BJ42: 28891.663 | BK42: 0 | BL42: 0 | BM42: 0 | BN42: 0 | BO42: 11735.633 | BQ42: 5577100.5 | BR42: 5577100.5 | BS42: 5755521.7 | BT42: 5755521.7 | BV42: 11745184 | BW42: 11745184 | BX42: 12120933 | BY42: 12120933 | CA42: 227679.99 | CB42: 3642879.8 | CC42: 4553599.8 | CD42: 4553599.8 | CF42: 105817.66 | CG42: 1693082.6 | CH42: 2116353.3 | CI42: 2116353.3 | CK42: 1076948.5 | CL42: 13836186 | CM42: 12652912 | CN42: 12652912 | CP42: 61316.861 | CQ42: 175981.45 | CR42: 175981.45 | CS42: 175981.45 | CT42: =(IF(CP42=-9999,0,(CK42*10+(CL42-CK42)*50+(CM42-CL42)*100)/CM42)) -> 41.919519 | CU42: =IF(CP42=-9999,0,CM42/CR42) -> 71.899126 | CV42: =IF(CP42=-9999,0,CR42) -> 175981.45 | CX42: 18022.131 | CY42: 862740.41 | CZ42: 1090615.3 | DA42: 1105652.2 | DC42: 11185.335 | DD42: 423576.19 | DE42: 528172.83 | DF42: 535455.02 | DG42: =(IF(DC42=-9999,0,(CX42*10+(CY42-CX42)*50+(CZ42-CY42)*100)/CZ42)) -> 59.786091 | DH42: =IF(DC42=-9999,0,CZ42/DE42) -> 2.0648835 | DI42: =IF(DC42=-9999,0,DE42) -> 528172.83 | DK42: 1540203.1 | DL42: 1738679.4 | DM42: 1942200.1 | DN42: 2411102.7 | DO42: -9999 | DP42: -9999 | DQ42: -9999 | DR42: -9999 | DS42: -9999 | DU42: 181354 | DV42: 208199 | DW42: 235678 | DX42: 235678 | DY42: -9999 | DZ42: -9999 | EA42: -9999 | EB42: -9999 | EC42: -9999
A43: Tennessee | B43: TN | C43: 47 | D43: 1.2386943e+08 | E43: 96484928 | G43: 474085.66 | H43: 11147786 | I43: 11147786 | J43: 13545305 | L43: 136658.55 | M43: 3213428.2 | N43: 3213428.2 | O43: 3904530.1 | P43: =((G43*10+(H43-G43)*50+(I43-H43)*100)/I43) -> 48.298906 | Q43: =I43/N43 -> 3.4691254 | R43: =N43 -> 3213428.2 | T43: 1544738.1 | U43: 1609102.2 | V43: 1609102.2 | W43: 1609102.2 | Y43: 204767.3 | Z43: 213299.27 | AA43: 213299.27 | AB43: 213299.27 | AC43: =((T43*10+(U43-T43)*50+(V43-U43)*100)/V43) -> 11.6 | AD43: =V43/AA43 -> 7.5438708 | AE43: =AA43 -> 213299.27 | AF43: -9999 | AG43: -9999 | AH43: -9999 | AI43: -9999 | AJ43: -9999 | AK43: -9999 | AL43: -9999 | AM43: -9999 | AN43: -9999 | AO43: -9999 | AP43: =(IF(AK43=-9999,0,(AG43*10+(AH43-AG43)*50+(AI43-AH43)*100)/AI43)) -> 0 | AQ43: =IF(AK43=-9999,0,AI43/AN43) -> 0 | AR43: =IF(AK43=-9999,0,AN43) -> 0 | AS43: -9999 | AT43: -9999 | AU43: -9999 | AV43: -9999 | AW43: -9999 | AX43: -9999 | AY43: -9999 | AZ43: -9999 | BA43: -9999 | BB43: -9999 | BC43: =(IF(AY43=-9999,0,(AT43*10+(AU43-AT43)*50+(AV43-AU43)*100)/AV43)) -> 0 | BD43: =IF(AY43=-9999,0,AV43/BA43) -> 0 | BE43: =IF(AY43=-9999,0,BA43) -> 0 | BF43: 0 | BG43: 0 | BH43: 0 | BI43: 0 | BJ43: 695176.08 | BK43: 0 | BL43: 0 | BM43: 0 | BN43: 0 | BO43: 219936.94 | BQ43: 1561941.6 | BR43: 1561941.6 | BS43: 1611910.9 | BT43: 1611910.9 | BV43: 3289395.8 | BW43: 3289395.8 | BX43: 3394629.3 | BY43: 3394629.3 | CA43: 63764.827 | CB43: 1020237.2 | CC43: 1275296.5 | CD43: 1275296.5 | CF43: 29635.653 | CG43: 474170.45 | CH43: 592713.06 | CI43: 592713.06 | CK43: 3679.9509 | CL43: 973085.88 | CM43: 993017.1 | CN43: 993017.1 | CP43: 0 | CQ43: 18431.711 | CR43: 18431.711 | CS43: 18431.711 | CT43: =(IF(CP43=-9999,0,(CK43*10+(CL43-CK43)*50+(CM43-CL43)*100)/CM43)) -> 50.855336 | CU43: =IF(CP43=-9999,0,CM43/CR43) -> 53.875471 | CV43: =IF(CP43=-9999,0,CR43) -> 18431.711 | CX43: 1571.9949 | CY43: 75253.227 | CZ43: 95129.8 | DA43: 96441.403 | DC43: 1171.5147 | DD43: 44363.959 | DE43: 55319.063 | DF43: 56081.775 | DG43: =(IF(DC43=-9999,0,(CX43*10+(CY43-CX43)*50+(CZ43-CY43)*100)/CZ43)) -> 59.786091 | DH43: =IF(DC43=-9999,0,CZ43/DE43) -> 1.7196567 | DI43: =IF(DC43=-9999,0,DE43) -> 55319.063 | DK43: 381091.63 | DL43: 430222.54 | DM43: 473741.85 | DN43: 589911.1 | DO43: -9999 | DP43: -9999 | DQ43: -9999 | DR43: -9999 | DS43: -9999 | DU43: 5473 | DV43: 20020 | DW43: 24687 | DX43: 24687 | DY43: -9999 | DZ43: -9999 | EA43: -9999 | EB43: -9999 | EC43: -9999
A44: Texas | B44: TX | C44: 48 | D44: 8.7380363e+08 | E44: 8.558589e+08 | G44: 680154.52 | H44: 15993348 | I44: 15993348 | J44: 19432986 | L44: 227977.58 | M44: 5360730 | N44: 5360730 | O44: 6513645.2 | P44: =((G44*10+(H44-G44)*50+(I44-H44)*100)/I44) -> 48.298906 | Q44: =I44/N44 -> 2.9834272 | R44: =N44 -> 5360730 | T44: 2045309.6 | U44: 2130530.8 | V44: 2130530.8 | W44: 2130530.8 | Y44: 581881.51 | Z44: 606126.58 | AA44: 606126.58 | AB44: 606126.58 | AC44: =((T44*10+(U44-T44)*50+(V44-U44)*100)/V44) -> 11.6 | AD44: =V44/AA44 -> 3.5149932 | AE44: =AA44 -> 606126.58 | AF44: 0 | AG44: 78756.373 | AH44: 164202.48 | AI44: 200691.92 | AJ44: 225018.21 | AK44: 0 | AL44: 167000 | AM44: 167000 | AN44: 167000 | AO44: 167000 | AP44: =(IF(AK44=-9999,0,(AG44*10+(AH44-AG44)*50+(AI44-AH44)*100)/AI44)) -> 43.393939 | AQ44: =IF(AK44=-9999,0,AI44/AN44) -> 1.201748 | AR44: =IF(AK44=-9999,0,AN44) -> 167000 | AS44: -9999 | AT44: -9999 | AU44: -9999 | AV44: -9999 | AW44: -9999 | AX44: -9999 | AY44: -9999 | AZ44: -9999 | BA44: -9999 | BB44: -9999 | BC44: =(IF(AY44=-9999,0,(AT44*10+(AU44-AT44)*50+(AV44-AU44)*100)/AV44)) -> 0 | BD44: =IF(AY44=-9999,0,AV44/BA44) -> 0 | BE44: =IF(AY44=-9999,0,BA44) -> 0 | BF44: 0 | BG44: 0 | BH44: 0 | BI44: 0 | BJ44: 1930756.5 | BK44: 0 | BL44: 0 | BM44: 0 | BN44: 0 | BO44: 502950.99 | BQ44: 6840687.9 | BR44: 6840687.9 | BS44: 7059533.4 | BT44: 7059533.4 | BV44: 14406255 | BW44: 14406255 | BX44: 14867137 | BY44: 14867137 | CA44: 279264.78 | CB44: 4468236.4 | CC44: 5585295.5 | CD44: 5585295.5 | CF44: 129792.46 | CG44: 2076679.4 | CH44: 2595849.3 | CI44: 2595849.3 | CK44: 6440333.9 | CL44: 12823284 | CM44: 11624972 | CN44: 11624972 | CP44: 26046.096 | CQ44: 217349.04 | CR44: 217366.25 | CS44: 217366.25 | CT44: =(IF(CP44=-9999,0,(CK44*10+(CL44-CK44)*50+(CM44-CL44)*100)/CM44)) -> 22.685611 | CU44: =IF(CP44=-9999,0,CM44/CR44) -> 53.481033 | CV44: =IF(CP44=-9999,0,CR44) -> 217366.25 | CX44: 12587.408 | CY44: 602573.88 | CZ44: 761731.23 | DA44: 772233.6 | DC44: 13815.742 | DD44: 523186.78 | DE44: 652380.97 | DF44: 661375.68 | DG44: =(IF(DC44=-9999,0,(CX44*10+(CY44-CX44)*50+(CZ44-CY44)*100)/CZ44)) -> 59.786091 | DH44: =IF(DC44=-9999,0,CZ44/DE44) -> 1.1676172 | DI44: =IF(DC44=-9999,0,DE44) -> 652380.97 | DK44: 1405048.3 | DL44: 1585916.2 | DM44: 1831205 | DN44: 2257662 | DO44: -9999 | DP44: -9999 | DQ44: -9999 | DR44: -9999 | DS44: -9999 | DU44: 594482 | DV44: 1092948 | DW44: 1118112 | DX44: 1118112 | DY44: -9999 | DZ44: -9999 | EA44: -9999 | EB44: -9999 | EC44: -9999
A45: Utah | B45: UT | C45: 49 | D45: 77579592 | E45: 51947352 | G45: 98137.758 | H45: 2307639.3 | I45: 2307639.3 | J45: 2803936 | L45: 199845.95 | M45: 4699234.8 | N45: 4699234.8 | O45: 5709884.4 | P45: =((G45*10+(H45-G45)*50+(I45-H45)*100)/I45) -> 48.298906 | Q45: =I45/N45 -> 0.49106703 | R45: =N45 -> 4699234.8 | T45: 74973.488 | U45: 78097.383 | V45: 78097.383 | W45: 78097.383 | Y45: 32041.869 | Z45: 33376.947 | AA45: 33376.947 | AB45: 33376.947 | AC45: =((T45*10+(U45-T45)*50+(V45-U45)*100)/V45) -> 11.6 | AD45: =V45/AA45 -> 2.33986 | AE45: =AA45 -> 33376.947 | AF45: -9999 | AG45: -9999 | AH45: -9999 | AI45: -9999 | AJ45: -9999 | AK45: -9999 | AL45: -9999 | AM45: -9999 | AN45: -9999 | AO45: -9999 | AP45: =(IF(AK45=-9999,0,(AG45*10+(AH45-AG45)*50+(AI45-AH45)*100)/AI45)) -> 0 | AQ45: =IF(AK45=-9999,0,AI45/AN45) -> 0 | AR45: =IF(AK45=-9999,0,AN45) -> 0 | AS45: 0 | AT45: 0 | AU45: 1786.5557 | AV45: 1786.5557 | AW45: 22014.925 | AX45: -9999 | AY45: 0 | AZ45: 2795.1822 | BA45: 2795.1822 | BB45: 1576015.1 | BC45: =(IF(AY45=-9999,0,(AT45*10+(AU45-AT45)*50+(AV45-AU45)*100)/AV45)) -> 50 | BD45: =IF(AY45=-9999,0,AV45/BA45) -> 0.63915537 | BE45: =IF(AY45=-9999,0,BA45) -> 2795.1822 | BF45: 0 | BG45: 0 | BH45: 0 | BI45: 0 | BJ45: 146512.2 | BK45: 0 | BL45: 0 | BM45: 0 | BN45: 0 | BO45: 65325.287 | BQ45: 293935.81 | BR45: 293935.81 | BS45: 303339.33 | BT45: 303339.33 | BV45: 619018.79 | BW45: 619018.79 | BX45: 638822.28 | BY45: 638822.28 | CA45: 11999.658 | CB45: 191994.53 | CC45: 239993.17 | CD45: 239993.17 | CF45: 5577.0199 | CG45: 89232.318 | CH45: 111540.4 | CI45: 111540.4 | CK45: 684632.83 | CL45: 1437016.1 | CM45: 1302604.2 | CN45: 1302604.2 | CP45: 3363.2751 | CQ45: 25229.958 | CR45: 25229.958 | CS45: 25229.958 | CT45: =(IF(CP45=-9999,0,(CK45*10+(CL45-CK45)*50+(CM45-CL45)*100)/CM45)) -> 23.817138 | CU45: =IF(CP45=-9999,0,CM45/CR45) -> 51.629267 | CV45: =IF(CP45=-9999,0,CR45) -> 25229.958 | CX45: 1841.7082 | CY45: 88164.717 | CZ45: 111451.59 | DA45: 112988.23 | DC45: 1603.6095 | DD45: 60726.908 | DE45: 75722.63 | DF45: 76766.656 | DG45: =(IF(DC45=-9999,0,(CX45*10+(CY45-CX45)*50+(CZ45-CY45)*100)/CZ45)) -> 59.786091 | DH45: =IF(DC45=-9999,0,CZ45/DE45) -> 1.47184 | DI45: =IF(DC45=-9999,0,DE45) -> 75722.63 | DK45: 58974.12 | DL45: 66576.354 | DM45: 73558.934 | DN45: 91530.782 | DO45: -9999 | DP45: -9999 | DQ45: -9999 | DR45: -9999 | DS45: -9999 | DU45: 100720 | DV45: 211559 | DW45: 266721 | DX45: 266721 | DY45: -9999 | DZ45: -9999 | EA45: -9999 | EB45: -9999 | EC45: -9999
A46: Vermont | B46: VT | C46: 50 | D46: 7073996 | E46: -66651.494 | F46: 0 | G46: 43158.293 | H46: 1014836.4 | I46: 1014836.4 | J46: 1233094.1 | K46: 0 | L46: 13948.838 | M46: 327996.96 | N46: 327996.96 | O46: 398538.22 | P46: =((G46*10+(H46-G46)*50+(I46-H46)*100)/I46) -> 48.298906 | Q46: =I46/N46 -> 3.0940423 | R46: =N46 -> 327996.96 | S46: 0 | T46: 106779.84 | U46: 111229 | V46: 111229 | W46: 111229 | X46: 0 | Y46: 11435.266 | Z46: 11911.735 | AA46: 11911.735 | AB46: 11911.735 | AC46: =((T46*10+(U46-T46)*50+(V46-U46)*100)/V46) -> 11.6 | AD46: =V46/AA46 -> 9.3377664 | AE46: =AA46 -> 11911.735 | AF46: -9999 | AG46: -9999 | AH46: -9999 | AI46: -9999 | AJ46: -9999 | AK46: -9999 | AL46: -9999 | AM46: -9999 | AN46: -9999 | AO46: -9999 | AP46: =(IF(AK46=-9999,0,(AG46*10+(AH46-AG46)*50+(AI46-AH46)*100)/AI46)) -> 0 | AQ46: =IF(AK46=-9999,0,AI46/AN46) -> 0 | AR46: =IF(AK46=-9999,0,AN46) -> 0 | AS46: -9999 | AT46: -9999 | AU46: -9999 | AV46: -9999 | AW46: -9999 | AX46: -9999 | AY46: -9999 | AZ46: -9999 | BA46: -9999 | BB46: -9999 | BC46: =(IF(AY46=-9999,0,(AT46*10+(AU46-AT46)*50+(AV46-AU46)*100)/AV46)) -> 0 | BD46: =IF(AY46=-9999,0,AV46/BA46) -> 0 | BE46: =IF(AY46=-9999,0,BA46) -> 0 | BF46: 0 | BG46: 0 | BH46: 0 | BI46: 0 | BJ46: 26060.001 | BK46: 0 | BL46: 0 | BM46: 0 | BN46: 0 | BO46: 11728.455 | BQ46: 81952.754 | BR46: 81952.754 | BS46: 84574.565 | BT46: 84574.565 | BV46: 172589.71 | BW46: 172589.71 | BX46: 178111.15 | BY46: 178111.15 | CA46: 3345.6456 | CB46: 53530.33 | CC46: 66912.912 | CD46: 66912.912 | CF46: 1554.9386 | CG46: 24879.018 | CH46: 31098.772 | CI46: 31098.772 | CJ46: 0 | CK46: 60277.956 | CL46: 145504.52 | CM46: 131894.7 | CN46: 131894.7 | CO46: 0 | CP46: 0 | CQ46: 1380.4943 | CR46: 1380.4943 | CS46: 1380.4943 | CT46: =(IF(CP46=-9999,0,(CK46*10+(CL46-CK46)*50+(CM46-CL46)*100)/CM46)) -> 26.560018 | CU46: =IF(CP46=-9999,0,CM46/CR46) -> 95.541643 | CV46: =IF(CP46=-9999,0,CR46) -> 1380.4943 | CX46: 161.15084 | CY46: 7714.4786 | CZ46: 9752.0975 | DA46: 9886.5546 | DC46: 87.743858 | DD46: 3322.7623 | DE46: 4143.2753 | DF46: 4200.4008 | DG46: =(IF(DC46=-9999,0,(CX46*10+(CY46-CX46)*50+(CZ46-CY46)*100)/CZ46)) -> 59.786091 | DH46: =IF(DC46=-9999,0,CZ46/DE46) -> 2.353717 | DI46: =IF(DC46=-9999,0,DE46) -> 4143.2753 | DJ46: 197188.83 | DK46: 21076.001 | DL46: 23796.172 | DM46: 25263.967 | DN46: 31709.076 | DO46: -9999 | DP46: -9999 | DQ46: -9999 | DR46: -9999 | DS46: -9999 | DT46: 0 | DU46: 4319 | DV46: 17272 | DW46: 17272 | DX46: 17272 | DY46: -9999 | DZ46: -9999 | EA46: -9999 | EB46: -9999 | EC46: -9999
A47: Virginia | B47: VA | C47: 51 | D47: 1.3264499e+08 | E47: 1.0025329e+08 | F47: 0 | G47: 349794.17 | H47: 8225159.9 | I47: 8225159.9 | J47: 9994119 | K47: 0 | L47: 90349.033 | M47: 2124493 | N47: 2124493 | O47: 2581400.9 | P47: =((G47*10+(H47-G47)*50+(I47-H47)*100)/I47) -> 48.298906 | Q47: =I47/N47 -> 3.8715873 | R47: =N47 -> 2124493 | S47: 0 | T47: 1745553.3 | U47: 1818284.7 | V47: 1818284.7 | W47: 1818284.7 | X47: 0 | Y47: 214002.67 | Z47: 222919.45 | AA47: 222919.45 | AB47: 222919.45 | AC47: =((T47*10+(U47-T47)*50+(V47-U47)*100)/V47) -> 11.6 | AD47: =V47/AA47 -> 8.1566893 | AE47: =AA47 -> 222919.45 | AF47: -9999 | AG47: -9999 | AH47: -9999 | AI47: -9999 | AJ47: -9999 | AK47: -9999 | AL47: -9999 | AM47: -9999 | AN47: -9999 | AO47: -9999 | AP47: =(IF(AK47=-9999,0,(AG47*10+(AH47-AG47)*50+(AI47-AH47)*100)/AI47)) -> 0 | AQ47: =IF(AK47=-9999,0,AI47/AN47) -> 0 | AR47: =IF(AK47=-9999,0,AN47) -> 0 | AS47: -9999 | AT47: -9999 | AU47: -9999 | AV47: -9999 | AW47: -9999 | AX47: -9999 | AY47: -9999 | AZ47: -9999 | BA47: -9999 | BB47: -9999 | BC47: =(IF(AY47=-9999,0,(AT47*10+(AU47-AT47)*50+(AV47-AU47)*100)/AV47)) -> 0 | BD47: =IF(AY47=-9999,0,AV47/BA47) -> 0 | BE47: =IF(AY47=-9999,0,BA47) -> 0 | BF47: 0 | BG47: 0 | BH47: 0 | BI47: 0 | BJ47: 414676.23 | BK47: 0 | BL47: 0 | BM47: 0 | BN47: 0 | BO47: 135671.15 | BQ47: 848879.04 | BR47: 848879.04 | BS47: 876036.16 | BT47: 876036.16 | BV47: 1787710.3 | BW47: 1787710.3 | BX47: 1844902.3 | BY47: 1844902.3 | CA47: 34654.704 | CB47: 554475.27 | CC47: 693094.08 | CD47: 693094.08 | CF47: 16106.29 | CG47: 257700.64 | CH47: 322125.79 | CI47: 322125.79 | CJ47: 0 | CK47: 73092.839 | CL47: 713041.81 | CM47: 646347.17 | CN47: 646347.17 | CO47: 0 | CP47: 0.45525704 | CQ47: 11414.747 | CR47: 11414.747 | CS47: 11414.747 | CT47: =(IF(CP47=-9999,0,(CK47*10+(CL47-CK47)*50+(CM47-CL47)*100)/CM47)) -> 40.317207 | CU47: =IF(CP47=-9999,0,CM47/CR47) -> 56.623872 | CV47: =IF(CP47=-9999,0,CR47) -> 11414.747 | CX47: 1055.6517 | CY47: 50535.279 | CZ47: 63883.121 | DA47: 64763.91 | DC47: 725.51833 | DD47: 27474.572 | DE47: 34259.061 | DF47: 34731.408 | DG47: =(IF(DC47=-9999,0,(CX47*10+(CY47-CX47)*50+(CZ47-CY47)*100)/CZ47)) -> 59.786091 | DH47: =IF(DC47=-9999,0,CZ47/DE47) -> 1.8647073 | DI47: =IF(DC47=-9999,0,DE47) -> 34259.061 | DJ47: 20372.295 | DK47: 203999.84 | DL47: 230328.6 | DM47: 244678.82 | DN47: 307059.51 | DO47: -9999 | DP47: -9999 | DQ47: -9999 | DR47: -9999 | DS47: -9999 | DT47: 0 | DU47: 36429 | DV47: 104176 | DW47: 111232 | DX47: 111232 | DY47: -9999 | DZ47: -9999 | EA47: -9999 | EB47: -9999 | EC47: -9999
A48: Washington | B48: WA | C48: 53 | D48: 88245188 | E48: 49804266 | F48: 0 | G48: 168579.77 | H48: 3964032.9 | I48: 3964032.9 | J48: 4816564.9 | K48: 0 | L48: 147176.71 | M48: 3460755.2 | N48: 3460755.2 | O48: 4205048.9 | P48: =((G48*10+(H48-G48)*50+(I48-H48)*100)/I48) -> 48.298906 | Q48: =I48/N48 -> 1.1454242 | R48: =N48 -> 3460755.2 | S48: 0 | T48: 1811831.4 | U48: 1887324.4 | V48: 1887324.4 | W48: 1887324.4 | X48: 0 | Y48: 308087.33 | Z48: 320924.31 | AA48: 320924.31 | AB48: 320924.31 | AC48: =((T48*10+(U48-T48)*50+(V48-U48)*100)/V48) -> 11.6 | AD48: =V48/AA48 -> 5.8809019 | AE48: =AA48 -> 320924.31 | AF48: -9999 | AG48: -9999 | AH48: -9999 | AI48: -9999 | AJ48: -9999 | AK48: -9999 | AL48: -9999 | AM48: -9999 | AN48: -9999 | AO48: -9999 | AP48: =(IF(AK48=-9999,0,(AG48*10+(AH48-AG48)*50+(AI48-AH48)*100)/AI48)) -> 0 | AQ48: =IF(AK48=-9999,0,AI48/AN48) -> 0 | AR48: =IF(AK48=-9999,0,AN48) -> 0 | AS48: 0 | AT48: 0 | AU48: 0 | AV48: 850583.12 | AW48: 1481046.4 | AX48: -9999 | AY48: 0 | AZ48: 0 | BA48: 394979.64 | BB48: 1120368 | BC48: =(IF(AY48=-9999,0,(AT48*10+(AU48-AT48)*50+(AV48-AU48)*100)/AV48)) -> 100 | BD48: =IF(AY48=-9999,0,AV48/BA48) -> 2.153486 | BE48: =IF(AY48=-9999,0,BA48) -> 394979.64 | BF48: 0 | BG48: 0 | BH48: 0 | BI48: 0 | BJ48: 422331.28 | BK48: 0 | BL48: 0 | BM48: 0 | BN48: 0 | BO48: 156920.45 | BQ48: 1157964 | BR48: 1157964 | BS48: 1195009.3 | BT48: 1195009.3 | BV48: 2438632.7 | BW48: 2438632.7 | BX48: 2516648.8 | BY48: 2516648.8 | CA48: 47272.813 | CB48: 756365.01 | CC48: 945456.26 | CD48: 945456.26 | CF48: 21970.744 | CG48: 351531.9 | CH48: 439414.87 | CI48: 439414.87 | CJ48: 0 | CK48: 121792.61 | CL48: 1971962.4 | CM48: 1792552.1 | CN48: 1792552.1 | CO48: 0 | CP48: 453.87719 | CQ48: 31176.642 | CR48: 31742.071 | CS48: 31742.071 | CT48: =(IF(CP48=-9999,0,(CK48*10+(CL48-CK48)*50+(CM48-CL48)*100)/CM48)) -> 42.277927 | CU48: =IF(CP48=-9999,0,CM48/CR48) -> 56.472438 | CV48: =IF(CP48=-9999,0,CR48) -> 31742.071 | CX48: 2170.1342 | CY48: 103886.85 | CZ48: 131326.4 | DA48: 133137.07 | DC48: 2017.5177 | DD48: 76401.151 | DE48: 95267.423 | DF48: 96580.924 | DG48: =(IF(DC48=-9999,0,(CX48*10+(CY48-CX48)*50+(CZ48-CY48)*100)/CZ48)) -> 59.786091 | DH48: =IF(DC48=-9999,0,CZ48/DE48) -> 1.3785027 | DI48: =IF(DC48=-9999,0,DE48) -> 95267.423 | DJ48: 561341.29 | DK48: 580375.58 | DL48: 654809.84 | DM48: 841846.5 | DN48: 1016133.9 | DO48: -9999 | DP48: -9999 | DQ48: -9999 | DR48: -9999 | DS48: -9999 | DT48: 0 | DU48: 235148 | DV48: 485537 | DW48: 529328 | DX48: 529328 | DY48: -9999 | DZ48: -9999 | EA48: -9999 | EB48: -9999 | EC48: -9999
A49: West Virginia | B49: WV | C49: 54 | D49: 1.2985774e+08 | E49: 96989378 | G49: 206469.13 | H49: 4854974 | I49: 4854974 | J49: 5899117.9 | L49: 49684.975 | M49: 1168306.7 | N49: 1168306.7 | O49: 1419570.7 | P49: =((G49*10+(H49-G49)*50+(I49-H49)*100)/I49) -> 48.298906 | Q49: =I49/N49 -> 4.1555646 | R49: =N49 -> 1168306.7 | T49: 708003.01 | U49: 737503.13 | V49: 737503.13 | W49: 737503.13 | Y49: 71749.953 | Z49: 74739.534 | AA49: 74739.534 | AB49: 74739.534 | AC49: =((T49*10+(U49-T49)*50+(V49-U49)*100)/V49) -> 11.6 | AD49: =V49/AA49 -> 9.8676442 | AE49: =AA49 -> 74739.534 | AF49: -9999 | AG49: -9999 | AH49: -9999 | AI49: -9999 | AJ49: -9999 | AK49: -9999 | AL49: -9999 | AM49: -9999 | AN49: -9999 | AO49: -9999 | AP49: =(IF(AK49=-9999,0,(AG49*10+(AH49-AG49)*50+(AI49-AH49)*100)/AI49)) -> 0 | AQ49: =IF(AK49=-9999,0,AI49/AN49) -> 0 | AR49: =IF(AK49=-9999,0,AN49) -> 0 | AS49: -9999 | AT49: -9999 | AU49: -9999 | AV49: -9999 | AW49: -9999 | AX49: -9999 | AY49: -9999 | AZ49: -9999 | BA49: -9999 | BB49: -9999 | BC49: =(IF(AY49=-9999,0,(AT49*10+(AU49-AT49)*50+(AV49-AU49)*100)/AV49)) -> 0 | BD49: =IF(AY49=-9999,0,AV49/BA49) -> 0 | BE49: =IF(AY49=-9999,0,BA49) -> 0 | BF49: 0 | BG49: 0 | BH49: 0 | BI49: 0 | BJ49: 127815.13 | BK49: 0 | BL49: 0 | BM49: 0 | BN49: 0 | BO49: 50840.665 | BQ49: 212403.86 | BR49: 212403.86 | BS49: 219199.03 | BT49: 219199.03 | BV49: 447315.29 | BW49: 447315.29 | BX49: 461625.69 | BY49: 461625.69 | CA49: 8671.1919 | CB49: 138739.07 | CC49: 173423.84 | CD49: 173423.84 | CF49: 4030.0656 | CG49: 64481.049 | CH49: 80601.311 | CI49: 80601.311 | CK49: 17772.05 | CL49: 72940.656 | CM49: 66118.123 | CN49: 66118.123 | CP49: 69.815668 | CQ49: 1066.8513 | CR49: 1066.8513 | CS49: 1066.8513 | CT49: =(IF(CP49=-9999,0,(CK49*10+(CL49-CK49)*50+(CM49-CL49)*100)/CM49)) -> 34.088952 | CU49: =IF(CP49=-9999,0,CM49/CR49) -> 61.975014 | CV49: =IF(CP49=-9999,0,CR49) -> 1066.8513 | CX49: 84.735414 | CY49: 4056.383 | CZ49: 5127.7922 | DA49: 5198.4916 | DC49: 67.808788 | DD49: 2567.8434 | DE49: 3201.939 | DF49: 3246.0857 | DG49: =(IF(DC49=-9999,0,(CX49*10+(CY49-CX49)*50+(CZ49-CY49)*100)/CZ49)) -> 59.786091 | DH49: =IF(DC49=-9999,0,CZ49/DE49) -> 1.6014647 | DI49: =IF(DC49=-9999,0,DE49) -> 3201.939 | DK49: 14256.138 | DL49: 16096.104 | DM49: 17088.943 | DN49: 21448.516 | DO49: -9999 | DP49: -9999 | DQ49: -9999 | DR49: -9999 | DS49: -9999 | DU49: 76 | DV49: 152 | DW49: 304 | DX49: 304 | DY49: -9999 | DZ49: -9999 | EA49: -9999 | EB49: -9999 | EC49: -9999
A50: Wisconsin | B50: WI | C50: 55 | D50: 1.2345529e+08 | E50: 64365453 | G50: 237960.42 | H50: 5595469.2 | I50: 5595469.2 | J50: 6798869.1 | L50: 92283.456 | M50: 2169979.6 | N50: 2169979.6 | O50: 2636670.2 | P50: =((G50*10+(H50-G50)*50+(I50-H50)*100)/I50) -> 48.298906 | Q50: =I50/N50 -> 2.5785816 | R50: =N50 -> 2169979.6 | T50: 265754.81 | U50: 276827.92 | V50: 276827.92 | W50: 276827.92 | Y50: 52730.375 | Z50: 54927.474 | AA50: 54927.474 | AB50: 54927.474 | AC50: =((T50*10+(U50-T50)*50+(V50-U50)*100)/V50) -> 11.6 | AD50: =V50/AA50 -> 5.0398809 | AE50: =AA50 -> 54927.474 | AF50: -9999 | AG50: -9999 | AH50: -9999 | AI50: -9999 | AJ50: -9999 | AK50: -9999 | AL50: -9999 | AM50: -9999 | AN50: -9999 | AO50: -9999 | AP50: =(IF(AK50=-9999,0,(AG50*10+(AH50-AG50)*50+(AI50-AH50)*100)/AI50)) -> 0 | AQ50: =IF(AK50=-9999,0,AI50/AN50) -> 0 | AR50: =IF(AK50=-9999,0,AN50) -> 0 | AS50: -9999 | AT50: -9999 | AU50: -9999 | AV50: -9999 | AW50: -9999 | AX50: -9999 | AY50: -9999 | AZ50: -9999 | BA50: -9999 | BB50: -9999 | BC50: =(IF(AY50=-9999,0,(AT50*10+(AU50-AT50)*50+(AV50-AU50)*100)/AV50)) -> 0 | BD50: =IF(AY50=-9999,0,AV50/BA50) -> 0 | BE50: =IF(AY50=-9999,0,BA50) -> 0 | BF50: 0 | BG50: 0 | BH50: 0 | BI50: 0 | BJ50: 331683.6 | BK50: 0 | BL50: 0 | BM50: 0 | BN50: 0 | BO50: 141314.74 | BQ50: 2487197.7 | BR50: 2487197.7 | BS50: 2566767.5 | BT50: 2566767.5 | BV50: 5237953.5 | BW50: 5237953.5 | BX50: 5405524.8 | BY50: 5405524.8 | CA50: 101537.55 | CB50: 1624600.8 | CC50: 2030751.1 | CD50: 2030751.1 | CF50: 47191.09 | CG50: 755057.43 | CH50: 943821.79 | CI50: 943821.79 | CK50: 172679.29 | CL50: 4123457.4 | CM50: 4024927.8 | CN50: 4024927.8 | CP50: 5606.2873 | CQ50: 47484.084 | CR50: 47484.084 | CS50: 47484.084 | CT50: =(IF(CP50=-9999,0,(CK50*10+(CL50-CK50)*50+(CM50-CL50)*100)/CM50)) -> 47.059909 | CU50: =IF(CP50=-9999,0,CM50/CR50) -> 84.763724 | CV50: =IF(CP50=-9999,0,CR50) -> 47484.084 | CX50: 5350.2065 | CY50: 256120.62 | CZ50: 323769.55 | DA50: 328233.53 | DC50: 3018.076 | DD50: 114291.18 | DE50: 142513.9 | DF50: 144478.81 | DG50: =(IF(DC50=-9999,0,(CX50*10+(CY50-CX50)*50+(CZ50-CY50)*100)/CZ50)) -> 59.786091 | DH50: =IF(DC50=-9999,0,CZ50/DE50) -> 2.2718454 | DI50: =IF(DC50=-9999,0,DE50) -> 142513.9 | DK50: 852594.43 | DL50: 962376.64 | DM50: 1101854.7 | DN50: 1360836.3 | DO50: -9999 | DP50: -9999 | DQ50: -9999 | DR50: -9999 | DS50: -9999 | DU50: 58076 | DV50: 194806 | DW50: 209629 | DX50: 209629 | DY50: -9999 | DZ50: -9999 | EA50: -9999 | EB50: -9999 | EC50: -9999
A51: Wyoming | B51: WY | C51: 56 | D51: 92164273 | E51: 99551280 | G51: 107073.49 | H51: 2517756.6 | I51: 2517756.6 | J51: 3059242.5 | L51: 176718.14 | M51: 4155400.8 | N51: 4155400.8 | O51: 5049089.7 | P51: =((G51*10+(H51-G51)*50+(I51-H51)*100)/I51) -> 48.298906 | Q51: =I51/N51 -> 0.60589981 | R51: =N51 -> 4155400.8 | T51: 56842.155 | U51: 59210.578 | V51: 59210.578 | W51: 59210.578 | Y51: 25567.24 | Z51: 26632.541 | AA51: 26632.541 | AB51: 26632.541 | AC51: =((T51*10+(U51-T51)*50+(V51-U51)*100)/V51) -> 11.6 | AD51: =V51/AA51 -> 2.2232418 | AE51: =AA51 -> 26632.541 | AF51: -9999 | AG51: -9999 | AH51: -9999 | AI51: -9999 | AJ51: -9999 | AK51: -9999 | AL51: -9999 | AM51: -9999 | AN51: -9999 | AO51: -9999 | AP51: =(IF(AK51=-9999,0,(AG51*10+(AH51-AG51)*50+(AI51-AH51)*100)/AI51)) -> 0 | AQ51: =IF(AK51=-9999,0,AI51/AN51) -> 0 | AR51: =IF(AK51=-9999,0,AN51) -> 0 | AS51: 0 | AT51: 0 | AU51: 746358.48 | AV51: 746358.48 | AW51: 848003.69 | AX51: -9999 | AY51: 0 | AZ51: 1116516.5 | BA51: 1116516.5 | BB51: 1399420.7 | BC51: =(IF(AY51=-9999,0,(AT51*10+(AU51-AT51)*50+(AV51-AU51)*100)/AV51)) -> 50 | BD51: =IF(AY51=-9999,0,AV51/BA51) -> 0.66847059 | BE51: =IF(AY51=-9999,0,BA51) -> 1116516.5 | BF51: 0 | BG51: 0 | BH51: 0 | BI51: 0 | BJ51: 22636.386 | BK51: 0 | BL51: 0 | BM51: 0 | BN51: 0 | BO51: 11922.894 | BQ51: 464784.68 | BR51: 464784.68 | BS51: 479653.95 | BT51: 479653.95 | BV51: 978820.69 | BW51: 978820.69 | BX51: 1010134.9 | BY51: 1010134.9 | CA51: 18974.406 | CB51: 303590.5 | CC51: 379488.12 | CD51: 379488.12 | CF51: 8818.6378 | CG51: 141098.2 | CH51: 176372.76 | CI51: 176372.76 | CK51: 1407203.5 | CL51: 1706999.6 | CM51: 1547334.7 | CN51: 1547334.7 | CP51: 3560.6116 | CQ51: 23986.234 | CR51: 23986.234 | CS51: 23986.234 | CT51: =(IF(CP51=-9999,0,(CK51*10+(CL51-CK51)*50+(CM51-CL51)*100)/CM51)) -> 8.4631671 | CU51: =IF(CP51=-9999,0,CM51/CR51) -> 64.50928 | CV51: =IF(CP51=-9999,0,CR51) -> 23986.234 | CX51: 1998.7111 | CY51: 95680.631 | CZ51: 120952.68 | DA51: 122620.31 | DC51: 1524.5588 | DD51: 57733.344 | DE51: 71989.845 | DF51: 72982.405 | DG51: =(IF(DC51=-9999,0,(CX51*10+(CY51-CX51)*50+(CZ51-CY51)*100)/CZ51)) -> 59.786091 | DH51: =IF(DC51=-9999,0,CZ51/DE51) -> 1.6801353 | DI51: =IF(DC51=-9999,0,DE51) -> 71989.845 | DK51: 446015.14 | DL51: 503096 | DM51: 684565.27 | DN51: 817682.24 | DO51: -9999 | DP51: -9999 | DQ51: -9999 | DR51: -9999 | DS51: -9999 | DU51: 5957 | DV51: 9588 | DW51: 14969 | DX51: 14969 | DY51: -9999 | DZ51: -9999 | EA51: -9999 | EB51: -9999 | EC51: -9999
A52: TOTAL US | I52: =SUM(I4:I51) -> 2.5244462e+08 | J52: =SUM(J4:J51) -> 3.0673708e+08 | K52: =SUM(K4:K51) -> 0 | L52: =SUM(L4:L51) -> 5441181 | M52: =SUM(M4:M51) -> 1.2794548e+08 | N52: =SUM(N4:N51) -> 1.2794548e+08 | S52: =SUM(S4:S51) -> 0 | T52: =SUM(T4:T51) -> 36480000 | U52: =SUM(U4:U51) -> 38000000 | V52: =SUM(V4:V51) -> 38000000 | W52: =SUM(W4:W51) -> 38000000 | X52: =SUM(X4:X51) -> 0 | Y52: =SUM(Y4:Y51) -> 6494017.5 | Z52: =SUM(Z4:Z51) -> 6764601.5 | AA52: =SUM(AA4:AA51) -> 6764601.5 | CM52: =SUM(CM4:CM51) -> 1.0699e+08 | CR52: =SUM(CR4:CR51) -> 1695386.6 | CZ52: =SUM(CZ4:CZ51) -> 9023192.6 | DE52: =SUM(DE4:DE51) -> 5118528.2

Sheet TNC_summary
B2: TNC Data: based on guidance from TNC Staff at Nature4Climate, we are using bucket 3 which includes abatement potential that costs 0-100$ per ton. Bucket 4 includes abatement potential that could be infinitely expensive
B3: EPS calculations: To estimate average US gCO2/acre/year, we use total available abatement potential from reforestation and deforestation bucket 3 and total acreage bucket 3 to calculate tons/acre
B4: Note that values are in CO2e
A6: Units | B6: Reforestation
A7: tons/year | B7: Total abatement potential: 0-100 | C7: ='TNC Data'!I52 -> 2.5244462e+08
A8: acres | B8: Total acreage: 0-100 | C8: ='TNC Data'!N52 -> 1.2794548e+08
B9: Acres per year (potential spread over 36 years based on guidance from TNC) | C9: =C8/36 -> 3554041.2
B10: grams/acre/year | C10: =C7*10^6/C8 -> 1973063.9
A12: Units | B12: Avoided deforestation
A13: tons/year | B13: Total abatement potential: 0-100 | C13: ='TNC Data'!V52 -> 38000000
A14: acres | B14: Total acreage: 0-100 | C14: ='TNC Data'!AA52 -> 6764601.5
B15: Acres per year (potential spread over 36 years based on guidance from TNC) | C15: =C14/36 -> 187905.6
B16: grams/acre/year | C16: =C13*10^6/C14 -> 5617478
A18: Units | B18: Grasslands
A19: tons/year | B19: Total abatement potential: 0-100 | C19: =SUM('TNC Data'!CM52,'TNC Data'!CZ52) -> 1.1601319e+08
A20: acres | B20: Total acreage: 0-100 | C20: =SUM('TNC Data'!CR52,'TNC Data'!DE52) -> 6813914.8
B21: Acres per year (potential spread over 36 years based on guidance from TNC) | C21: =C20/36 -> 189275.41
B22: grams/acre/year | C22: =C19*10^6/C20 -> 17025924

Sheet Peatland
A1: ICF Report Summary
A3: Measure | B3: Acres Covered
A4: Restoring Wetlands | B4: =2.5*10^6 -> 2500000
A5: Restoring Riparian Forest Buffers | B5: 890909
A6: Total | B6: =SUM(B4:B5) -> 3390909
A8: Total Divided Over 29 Years | B8: =B6/29 -> 116927.9

Sheet Inflation Reduction Act
A1: Methodology:
A2: We sum IRA forestry funding that aligns with the scope of the Energy Policy Simulator's LULUCF sector, then assign it to either the model's 'forest management' or 'afforestation and reforestation' levers. We then find the policy setting that matches total government spend over the period of 2023-2031. For Section 23001, we only include the protection of old-growth forests funding and exclude hazardous fuels reduction and vegetation management, which are outside the scope of the model. The EPS assumes forest management practices need to be consistently implemented in every year in order to maintain emissions reductions. To be conservative, we phase out forest management practices incentivized by the IRA over a period of 4 years rather than assume permanent reductions.
A4: Calculations:
A5: 2022 to 2012 USD | B5: 0.785
A7: Forestry Funding in Inflation Reduction Act of 2022 (Billion USD)
A8: hazardous fuels reduction | B8: 1.8 | D8: N/A
A9: vegetation management | B9: 0.2 | D9: N/A
A10: environmental reviews | B10: 0.1 | D10: N/A
A11: protection of old-growth forests | B11: 0.05 | D11: forest management
A12: competitive grants for climate mitigation | B12: 0.15 | D12: forest management
A13: competitive grants for climate mitigation | B13: 0.15 | D13: forest management
A14: competitive grants for climate mitigation | B14: 0.1 | D14: forest management
A15: competitive grants for climate mitigation | B15: 0.05 | D15: forest management
A16: wood innovation grant program | B16: 0.1 | D16: forest management
A17: competitive grants for climate mitigation | B17: 0.7 | D17: forest management
A18: tree planting | B18: 1.5 | D18: afforestation and reforestation
A19: admin costs | B19: 0.1 | D19: N/A
A21: Total Target Spend by EPS Policy, by year
A22: forest management | B22: =SUM(B11:B17)*10^9/10*B5 -> 1.0205e+08
A23: afforestation and reforestation | B23: =B18*10^9/10*B5 -> 117750000
A25: see EPA land and ag calcs for further calculations using EPA data

Sheet PLANAbPiaSY
A1: Potential Land Area (acres/year) | B1: 2021 | C1: 2022 | D1: 2023 | E1: 2024 | F1: 2025 | G1: 2026 | H1: 2027 | I1: 2028 | J1: 2029 | K1: 2030 | L1: 2031 | M1: 2032 | N1: 2033 | O1: 2034 | P1: 2035 | Q1: 2036 | R1: 2037 | S1: 2038 | T1: 2039 | U1: 2040 | V1: 2041 | W1: 2042 | X1: 2043 | Y1: 2044 | Z1: 2045 | AA1: 2046 | AB1: 2047 | AC1: 2048 | AD1: 2049 | AE1: 2050
A2: forest set asides | B2: 0 | C2: 0 | D2: 0 | E2: 0 | F2: 0 | G2: 0 | H2: 0 | I2: 0 | J2: 0 | K2: 0 | L2: 0 | M2: 0 | N2: 0 | O2: 0 | P2: 0 | Q2: 0 | R2: 0 | S2: 0 | T2: 0 | U2: 0 | V2: 0 | W2: 0 | X2: 0 | Y2: 0 | Z2: 0 | AA2: 0 | AB2: 0 | AC2: 0 | AD2: 0 | AE2: 0
A3: afforestation and reforestation | B3: ='EPA land and ag calcs'!B61 -> 0 | C3: ='EPA land and ag calcs'!C61 -> 501757.7 | D3: ='EPA land and ag calcs'!D61 -> 4748959.2 | E3: ='EPA land and ag calcs'!E61 -> 4748959.2 | F3: ='EPA land and ag calcs'!F61 -> 4748959.2 | G3: ='EPA land and ag calcs'!G61 -> 4748959.2 | H3: ='EPA land and ag calcs'!H61 -> 4748959.2 | I3: ='EPA land and ag calcs'!I61 -> 4748959.2 | ... AE3: ='EPA land and ag calcs'!AE61 -> 1708003.5
A4: improved forest management | B4: ='EPA land and ag calcs'!B60 -> 7826666.7 | C4: ='EPA land and ag calcs'!C60 -> 10320000 | D4: ='EPA land and ag calcs'!D60 -> 12813333 | E4: ='EPA land and ag calcs'!E60 -> 15306667 | F4: ='EPA land and ag calcs'!F60 -> 17800000 | G4: ='EPA land and ag calcs'!G60 -> 20293333 | H4: ='EPA land and ag calcs'!H60 -> 22786667 | I4: ='EPA land and ag calcs'!I60 -> 25280000 | ... AE4: ='EPA land and ag calcs'!AE60 -> 54900000
A5: avoid deforestation | B5: 0 | C5: 0 | D5: 0 | E5: 0 | F5: 0 | G5: 0 | H5: 0 | I5: 0 | J5: 0 | K5: 0 | L5: 0 | M5: 0 | N5: 0 | O5: 0 | P5: 0 | Q5: 0 | R5: 0 | S5: 0 | T5: 0 | U5: 0 | V5: 0 | W5: 0 | X5: 0 | Y5: 0 | Z5: 0 | AA5: 0 | AB5: 0 | AC5: 0 | AD5: 0 | AE5: 0
A6: peatland restoration | B6: 0 | C6: =Peatland!$B$8 -> 116927.9 | D6: =Peatland!$B$8 -> 116927.9 | E6: =Peatland!$B$8 -> 116927.9 | F6: =Peatland!$B$8 -> 116927.9 | G6: =Peatland!$B$8 -> 116927.9 | H6: =Peatland!$B$8 -> 116927.9 | I6: =Peatland!$B$8 -> 116927.9 | J6: =Peatland!$B$8 -> 116927.9 | ... AE6: =Peatland!$B$8 -> 116927.9
A7: forest restoration | B7: =TNC_summary!$C$21 -> 189275.41 | C7: =TNC_summary!$C$21 -> 189275.41 | D7: =TNC_summary!$C$21 -> 189275.41 | E7: =TNC_summary!$C$21 -> 189275.41 | F7: =TNC_summary!$C$21 -> 189275.41 | G7: =TNC_summary!$C$21 -> 189275.41 | H7: =TNC_summary!$C$21 -> 189275.41 | I7: =TNC_summary!$C$21 -> 189275.41 | ... AE7: =TNC_summary!$C$21 -> 189275.41
