Workbook

Sheet About
A1: CABI Cement Allocation Benchmark Intensity
A3: Sources: | B3: U.S. clinker CO2 intensity distribution (the U.S. value) | D3: California cap-and-trade cement benchmark
B4: U.S. Environmental Protection Agency | D4: California Air Resources Board
B5: U.S. Cement Industry Carbon Intensities (2019), EPA 430-F-21-004 | D5: Cap-and-Invest Program, 2026 Final Regulation Order, Tables 8-1, 9-1 and 9-2
B6: 2021 | D6: 2026
B7: https://www.epa.gov/system/files/documents/2021-10/cement-carbon-intensities-fact-sheet.pdf | D7: https://ww2.arb.ca.gov/sites/default/files/barcu/regact/2026/cap_invest/Attachment%20A-1%20Final%20Regulation%20Order.pdf
B8: Kiln CO2 (fuel combustion plus calcination, excluding biogenic CO2, methane and nitrous oxide) per tonne of clinker at the 92 U.S. plants with continuous emissions monitors in 2019: 0.787 at the 75th percentile (cleaner plants), 0.838 at the median and 0.934 at the 25th percentile. The median is the shipped value; the other two are sensitivity cases on the Values tab. Per tonne of cement the same quartiles are 0.722, 0.776 and 0.886. | D8: 0.742 allowances per short ton (0.818 per metric tonne) with a 100 percent assistance factor and a cap adjustment factor of 0.824 in 2026 falling to 0.782 in 2030. The unit basis (adjusted clinker and additives versus finished cement) changed in the 2026 order and should be confirmed in the clean text before converting to a clinker basis.
B10: EU ETS grey clinker benchmark 2026-2030 | D10: China national ETS cement allocation rule (for the marginal price factor)
B11: European Commission | D11: Ministry of Ecology and Environment of China
B12: Commission Implementing Regulation (EU) 2026/1412 updating the product benchmark values, Annex, section 1 | D12: 2026 allowance total and allocation plan for the power, steel, cement and aluminium sectors, section 3(2)
B13: 2026 | D13: 2026
B14: https://eur-lex.europa.eu/eli/reg_impl/2026/1412/oj | D14: https://www.mee.gov.cn/xxgk2018/xxgk/xxgk03/202609/W020260903551498752549.pdf
B15: Grey cement clinker 0.656 allowances per tonne (the 10 percent most efficient installations averaged 0.689 in 2021-22); white clinker 0.890. The 2021-2025 value was 0.693 (Implementing Regulation (EU) 2021/447). Read from the EUR-Lex text; confirm against the Official Journal before use. The value an EU build would enter here. | D15: Allocation equals verified emissions times (1 + 0.15 times the intensity deviation from the sector balance value), capped at plus or minus 3 percent. The balance value itself is not published, so a China build should use its own start-year intensity here and set the Marginal Carbon Price Factor for Cement to 0.15.
B17: Canada federal output-based pricing standard for clinker
B18: Government of Canada
B19: Output-Based Pricing System Regulations SOR/2019-266, Schedule 1 item 7 and section 36
B20: 2025
B21: https://laws-lois.justice.gc.ca/eng/XML/SOR-2019-266.xml
B22: 0.799 tonnes CO2e per tonne of clinker (0.733 per tonne of grey cement), tightening 1 percent a year from 2022, so about 0.767 in 2026 and 0.735 in 2030. Primary regulation text.
A24: Notes:
A25: Purpose and layout | B25: CABI is the benchmark CO2 intensity, in tonnes of CO2 per tonne of clinker, that output-based allocation of the carbon price is measured against. When the allocation policy (or the BAU allocation fraction BCAF) is on, the cement industry is handed back the carbon price on this benchmark times the clinker it produces, capped at the carbon tax it actually pays. Edit the 'Values by Year' tab (the 'Sensitivities' tab holds the quartile values to copy in); the 'CABI' tab is exported to CABI.csv.
A26: U.S. values | B26: The United States has no cement carbon price, so there is no official benchmark. The shipped values follow the EU grey clinker benchmark, the strictest benchmark in force for cement: 0.693 tonnes of CO2 per tonne of clinker through 2025 and 0.656 from 2026 (the average of the 10 percent most efficient EU installations, tightened), held after 2030. It sits below the U.S. median plant (0.838, EPA 2019), so a full allocation refunds only the cleaner plants in full and the industry still pays carbon tax on emissions above the benchmark. The U.S. plant quartiles (0.787, 0.838, 0.934) are on the Sensitivities tab for a benchmark set on U.S. plants, as the Clean Competition Act proposals would.
A27: Other regions | B27: Enter the official benchmark: 0.656 for the EU from 2026 (0.693 before), Canada's 0.799 tightening 1 percent a year, California's 0.818 per metric tonne once converted to a clinker basis. Where the benchmark tightens over time, enter the path year by year.

Sheet Sensitivities
A1: U.S. clinker CO2 intensity quartiles, EPA 2019 (tonnes CO2 per tonne of clinker)
A3: Case | B3: Value | C3: Meaning
A4: Central (median plant) | B4: 0.838 | C4: Half of U.S. clinker capacity is cleaner than this
A5: Strict (75th percentile, cleaner plants) | B5: 0.787 | C5: Benchmark set at the cleaner quarter of plants, as the EU does with its top 10 percent
A6: Loose (25th percentile) | B6: 0.934 | C6: Only the dirtiest quarter of plants pays net carbon costs
A7: EU benchmark 2021-2025 (Implementing Regulation (EU) 2021/447) | B7: 0.693 | C7: Grey cement clinker benchmark, allowances per tonne of clinker
A8: EU benchmark 2026-2030 (Implementing Regulation (EU) 2026/1412) | B8: 0.656 | C8: Grey cement clinker benchmark, allowances per tonne of clinker; the shipped value from 2026
A10: To use a different case, point the Values by Year formulas at the row you want. The shipped values use the EU rows.

Sheet Values by Year
A1: Benchmark clinker CO2 intensity for output-based allocation (edit here)
A2: Tonnes of CO2 per tonne of clinker by year. The shipped U.S. values are the EU grey clinker benchmark: 0.693 through 2025 and 0.656 from 2026, held after 2030 until the EU sets its 2031-2035 value. The Sensitivities tab lists the U.S. plant quartiles as alternatives.
A3: Year | B3: metric tons CO2 per metric ton clinker | C3: Basis
A4: 2021 | B4: =Sensitivities!B7 -> 0.693 | C4: EU benchmark 2021-2025 (Sensitivities tab)
A5: 2022 | B5: =Sensitivities!B7 -> 0.693 | C5: EU benchmark 2021-2025 (Sensitivities tab)
A6: 2023 | B6: =Sensitivities!B7 -> 0.693 | C6: EU benchmark 2021-2025 (Sensitivities tab)
A7: 2024 | B7: =Sensitivities!B7 -> 0.693 | C7: EU benchmark 2021-2025 (Sensitivities tab)
A8: 2025 | B8: =Sensitivities!B7 -> 0.693 | C8: EU benchmark 2021-2025 (Sensitivities tab)
A9: 2026 | B9: =Sensitivities!B8 -> 0.656 | C9: EU benchmark 2026-2030, held after 2030 (Sensitivities tab)
A10: 2027 | B10: =Sensitivities!B8 -> 0.656 | C10: EU benchmark 2026-2030, held after 2030 (Sensitivities tab)
A11: 2028 | B11: =Sensitivities!B8 -> 0.656 | C11: EU benchmark 2026-2030, held after 2030 (Sensitivities tab)
A12: 2029 | B12: =Sensitivities!B8 -> 0.656 | C12: EU benchmark 2026-2030, held after 2030 (Sensitivities tab)
A13: 2030 | B13: =Sensitivities!B8 -> 0.656 | C13: EU benchmark 2026-2030, held after 2030 (Sensitivities tab)
A14: 2031 | B14: =Sensitivities!B8 -> 0.656 | C14: EU benchmark 2026-2030, held after 2030 (Sensitivities tab)
A15: 2032 | B15: =Sensitivities!B8 -> 0.656 | C15: EU benchmark 2026-2030, held after 2030 (Sensitivities tab)
A16: 2033 | B16: =Sensitivities!B8 -> 0.656 | C16: EU benchmark 2026-2030, held after 2030 (Sensitivities tab)
A17: 2034 | B17: =Sensitivities!B8 -> 0.656 | C17: EU benchmark 2026-2030, held after 2030 (Sensitivities tab)
A18: 2035 | B18: =Sensitivities!B8 -> 0.656 | C18: EU benchmark 2026-2030, held after 2030 (Sensitivities tab)
A19: 2036 | B19: =Sensitivities!B8 -> 0.656 | C19: EU benchmark 2026-2030, held after 2030 (Sensitivities tab)
A20: 2037 | B20: =Sensitivities!B8 -> 0.656 | C20: EU benchmark 2026-2030, held after 2030 (Sensitivities tab)
A21: 2038 | B21: =Sensitivities!B8 -> 0.656 | C21: EU benchmark 2026-2030, held after 2030 (Sensitivities tab)
A22: 2039 | B22: =Sensitivities!B8 -> 0.656 | C22: EU benchmark 2026-2030, held after 2030 (Sensitivities tab)
A23: 2040 | B23: =Sensitivities!B8 -> 0.656 | C23: EU benchmark 2026-2030, held after 2030 (Sensitivities tab)
A24: 2041 | B24: =Sensitivities!B8 -> 0.656 | C24: EU benchmark 2026-2030, held after 2030 (Sensitivities tab)
A25: 2042 | B25: =Sensitivities!B8 -> 0.656 | C25: EU benchmark 2026-2030, held after 2030 (Sensitivities tab)
A26: 2043 | B26: =Sensitivities!B8 -> 0.656 | C26: EU benchmark 2026-2030, held after 2030 (Sensitivities tab)
A27: 2044 | B27: =Sensitivities!B8 -> 0.656 | C27: EU benchmark 2026-2030, held after 2030 (Sensitivities tab)
A28: 2045 | B28: =Sensitivities!B8 -> 0.656 | C28: EU benchmark 2026-2030, held after 2030 (Sensitivities tab)
A29: 2046 | B29: =Sensitivities!B8 -> 0.656 | C29: EU benchmark 2026-2030, held after 2030 (Sensitivities tab)
A30: 2047 | B30: =Sensitivities!B8 -> 0.656 | C30: EU benchmark 2026-2030, held after 2030 (Sensitivities tab)
A31: 2048 | B31: =Sensitivities!B8 -> 0.656 | C31: EU benchmark 2026-2030, held after 2030 (Sensitivities tab)
A32: 2049 | B32: =Sensitivities!B8 -> 0.656 | C32: EU benchmark 2026-2030, held after 2030 (Sensitivities tab)
A33: 2050 | B33: =Sensitivities!B8 -> 0.656 | C33: EU benchmark 2026-2030, held after 2030 (Sensitivities tab)

Sheet Checks
A1: Live checks
A2: Check | B2: Value | C2: Result
A3: Values at or below 0 (count) | B3: =COUNTIF('Values by Year'!B4:B33,"<=0") -> 0 | C3: =IF(B3=0,"PASS","FAIL") -> PASS
A4: Values above 1.2 t/t, outside any observed kiln (count) | B4: =COUNTIF('Values by Year'!B4:B33,">1.2") -> 0 | C4: =IF(B4=0,"PASS","CHECK") -> PASS

Sheet CABI
A1: Unit: metric tons CO2 per metric ton clinker | B1: 2021 | C1: 2022 | D1: 2023 | E1: 2024 | F1: 2025 | G1: 2026 | H1: 2027 | I1: 2028 | J1: 2029 | K1: 2030 | L1: 2031 | M1: 2032 | N1: 2033 | O1: 2034 | P1: 2035 | Q1: 2036 | R1: 2037 | S1: 2038 | T1: 2039 | U1: 2040 | V1: 2041 | W1: 2042 | X1: 2043 | Y1: 2044 | Z1: 2045 | AA1: 2046 | AB1: 2047 | AC1: 2048 | AD1: 2049 | AE1: 2050
A2: Cement Allocation Benchmark Intensity | B2: ='Values by Year'!B4 -> 0.693 | C2: ='Values by Year'!B5 -> 0.693 | D2: ='Values by Year'!B6 -> 0.693 | E2: ='Values by Year'!B7 -> 0.693 | F2: ='Values by Year'!B8 -> 0.693 | G2: ='Values by Year'!B9 -> 0.656 | H2: ='Values by Year'!B10 -> 0.656 | I2: ='Values by Year'!B11 -> 0.656 | J2: ='Values by Year'!B12 -> 0.656 | K2: ='Values by Year'!B13 -> 0.656 | L2: ='Values by Year'!B14 -> 0.656 | M2: ='Values by Year'!B15 -> 0.656 | N2: ='Values by Year'!B16 -> 0.656 | O2: ='Values by Year'!B17 -> 0.656 | P2: ='Values by Year'!B18 -> 0.656 | Q2: ='Values by Year'!B19 -> 0.656 | R2: ='Values by Year'!B20 -> 0.656 | S2: ='Values by Year'!B21 -> 0.656 | T2: ='Values by Year'!B22 -> 0.656 | U2: ='Values by Year'!B23 -> 0.656 | V2: ='Values by Year'!B24 -> 0.656 | W2: ='Values by Year'!B25 -> 0.656 | X2: ='Values by Year'!B26 -> 0.656 | Y2: ='Values by Year'!B27 -> 0.656 | Z2: ='Values by Year'!B28 -> 0.656 | AA2: ='Values by Year'!B29 -> 0.656 | AB2: ='Values by Year'!B30 -> 0.656 | AC2: ='Values by Year'!B31 -> 0.656 | AD2: ='Values by Year'!B32 -> 0.656 | AE2: ='Values by Year'!B33 -> 0.656
